Workbook

Sheet Dashboard
A1: ADEL INCOME FUND I – DASHBOARD (SAR)
A2: Version | B2: Budget 2025
A4: Fund IRR (net, to unitholders) | B4: =IRR(Fund!$C$20:$J$20) -> 0.11501022
A5: Equity multiple | B5: =SUMIF(Fund!$C$20:$J$20,">0")/-SUMIF(Fund!$C$20:$J$20,"<0") -> 1.9729146
A6: Equity raised (SAR) | B6: =Fund!C7 -> 1043400000
A7: Net operating income 2025 (SAR) | B7: =Fund!D9 -> 125102640
A8: Distributions to unitholders 2025 (SAR) | B8: =Fund!D18 -> 43785504
A9: Distribution yield 2025 | B9: =Fund!D21 -> 0.041964255
A10: Net asset value 31 Dec 2025 (SAR) | B10: =Fund!D13 -> 1.1884801e+09
A11: NAV per unit 31 Dec 2025 (SAR) | B11: =Fund!D22 -> 11.390455
A12: Loan to value 31 Dec 2025 | B12: =Fund!D23 -> 0.30354882
A13: Interest cover 2025 | B13: =Fund!D24 -> 3.2201452

Sheet Inputs
A1: ADEL INCOME FUND I – BUDGET 2025
A2: Yellow cells are inputs. 2025 figures are the approved budget.
A4: Fund
A5: Acquisition year (assets bought on 31 December) | C5: 2024
A6: Unit price at launch (SAR) | C6: 10
A7: Debt as share of acquisition price | C7: 0.35
A8: Real estate transaction tax and acquisition costs | C8: 0.055
A9: SAIBOR | C9: 0.055
A10: Margin (bps) | C10: 200
A11: Management fee (share of NAV) | C11: 0.0085
A12: Fund administration and custody fees (SAR a year) | C12: 4500000
A13: Cost inflation a year | C13: 0.03
A14: Distribution policy (share of cash available) | C14: 0.9
A15: Exit year (assets sold on 31 December) | C15: 2031
A16: Disposal costs | C16: 0.015
A18: Assets | C18: Al Olaya Office Tower, Riyadh | D18: Corniche Retail Centre, Jeddah | E18: Dammam Logistics Park
A19: Purchase price (SAR) | C19: 620000000 | D19: 480000000 | E19: 380000000
A20: Leasable area (sqm) | C20: 48000 | D20: 36000 | E20: 140000
A21: Rent in 2025 (SAR per sqm a year) | C21: 1450 | D21: 1350 | E21: 330
A22: Occupancy in 2025 | C22: 0.9 | D22: 0.88 | E22: 0.95
A23: Stabilised occupancy (from 2026) | C23: 0.93 | D23: 0.92 | E23: 0.96
A24: Rent growth a year | C24: 0.03 | D24: 0.025 | E24: 0.03
A25: Operating costs (share of rent) | C25: 0.18 | D25: 0.22 | E25: 0.08
A26: Capital expenditure in 2025 (SAR) | C26: 12000000 | D26: 8000000 | E26: 3000000
A27: Maintenance capex from 2026 (share of purchase price) | C27: 0.005 | D27: 0.005 | E27: 0.003
A28: Valuation cap rate | C28: 0.075 | D28: 0.08 | E28: 0.0725

Sheet Assets
A1: ASSETS – ANNUAL (SAR)
A3: Year | C3: 2024 | D3: 2025 | E3: 2026 | F3: 2027 | G3: 2028 | H3: 2029 | I3: 2030 | J3: 2031
A4: Operating year (0 = acquisition) | C4: =C3-Inputs!$C$5 -> 0 | D4: =D3-Inputs!$C$5 -> 1 | E4: =E3-Inputs!$C$5 -> 2 | F4: =F3-Inputs!$C$5 -> 3 | G4: =G3-Inputs!$C$5 -> 4 | H4: =H3-Inputs!$C$5 -> 5 | I4: =I3-Inputs!$C$5 -> 6 | J4: =J3-Inputs!$C$5 -> 7
A5: Exit flag | C5: =IF(C3=Inputs!$C$15,1,0) -> 0 | D5: =IF(D3=Inputs!$C$15,1,0) -> 0 | E5: =IF(E3=Inputs!$C$15,1,0) -> 0 | F5: =IF(F3=Inputs!$C$15,1,0) -> 0 | G5: =IF(G3=Inputs!$C$15,1,0) -> 0 | H5: =IF(H3=Inputs!$C$15,1,0) -> 0 | I5: =IF(I3=Inputs!$C$15,1,0) -> 0 | J5: =IF(J3=Inputs!$C$15,1,0) -> 1
A7: Al Olaya Office Tower, Riyadh
A8: Occupancy | C8: =IF(C$4<1,0,IF(C$4=1,Inputs!$C$22,Inputs!$C$23)) -> 0 | D8: =IF(D$4<1,0,IF(D$4=1,Inputs!$C$22,Inputs!$C$23)) -> 0.9 | E8: =IF(E$4<1,0,IF(E$4=1,Inputs!$C$22,Inputs!$C$23)) -> 0.93 | F8: =IF(F$4<1,0,IF(F$4=1,Inputs!$C$22,Inputs!$C$23)) -> 0.93 | G8: =IF(G$4<1,0,IF(G$4=1,Inputs!$C$22,Inputs!$C$23)) -> 0.93 | H8: =IF(H$4<1,0,IF(H$4=1,Inputs!$C$22,Inputs!$C$23)) -> 0.93 | I8: =IF(I$4<1,0,IF(I$4=1,Inputs!$C$22,Inputs!$C$23)) -> 0.93 | J8: =IF(J$4<1,0,IF(J$4=1,Inputs!$C$22,Inputs!$C$23)) -> 0.93
A9: Rent (SAR per sqm a year) | C9: =IF(C$4<1,0,Inputs!$C$21*(1+Inputs!$C$24)^(C$4-1)) -> 0 | D9: =IF(D$4<1,0,Inputs!$C$21*(1+Inputs!$C$24)^(D$4-1)) -> 1450 | E9: =IF(E$4<1,0,Inputs!$C$21*(1+Inputs!$C$24)^(E$4-1)) -> 1493.5 | F9: =IF(F$4<1,0,Inputs!$C$21*(1+Inputs!$C$24)^(F$4-1)) -> 1538.305 | G9: =IF(G$4<1,0,Inputs!$C$21*(1+Inputs!$C$24)^(G$4-1)) -> 1584.4542 | H9: =IF(H$4<1,0,Inputs!$C$21*(1+Inputs!$C$24)^(H$4-1)) -> 1631.9878 | I9: =IF(I$4<1,0,Inputs!$C$21*(1+Inputs!$C$24)^(I$4-1)) -> 1680.9474 | J9: =IF(J$4<1,0,Inputs!$C$21*(1+Inputs!$C$24)^(J$4-1)) -> 1731.3758
A10: Gross rent | C10: =Inputs!$C$20*C9*C8 -> 0 | D10: =Inputs!$C$20*D9*D8 -> 62640000 | E10: =Inputs!$C$20*E9*E8 -> 66669840 | F10: =Inputs!$C$20*F9*F8 -> 68669935 | G10: =Inputs!$C$20*G9*G8 -> 70730033 | H10: =Inputs!$C$20*H9*H8 -> 72851934 | I10: =Inputs!$C$20*I9*I8 -> 75037492 | J10: =Inputs!$C$20*J9*J8 -> 77288617
A11: Operating costs | C11: =C10*Inputs!$C$25 -> 0 | D11: =D10*Inputs!$C$25 -> 11275200 | E11: =E10*Inputs!$C$25 -> 12000571 | F11: =F10*Inputs!$C$25 -> 12360588 | G11: =G10*Inputs!$C$25 -> 12731406 | H11: =H10*Inputs!$C$25 -> 13113348 | I11: =I10*Inputs!$C$25 -> 13506749 | J11: =J10*Inputs!$C$25 -> 13911951
A12: Net operating income | C12: =C10-C11 -> 0 | D12: =D10-D11 -> 51364800 | E12: =E10-E11 -> 54669269 | F12: =F10-F11 -> 56309347 | G12: =G10-G11 -> 57998627 | H12: =H10-H11 -> 59738586 | I12: =I10-I11 -> 61530744 | J12: =J10-J11 -> 63376666
A13: Capital expenditure | C13: =IF(C$4<1,0,IF(C$4=1,Inputs!$C$26,Inputs!$C$19*Inputs!$C$27)) -> 0 | D13: =IF(D$4<1,0,IF(D$4=1,Inputs!$C$26,Inputs!$C$19*Inputs!$C$27)) -> 12000000 | E13: =IF(E$4<1,0,IF(E$4=1,Inputs!$C$26,Inputs!$C$19*Inputs!$C$27)) -> 3100000 | F13: =IF(F$4<1,0,IF(F$4=1,Inputs!$C$26,Inputs!$C$19*Inputs!$C$27)) -> 3100000 | G13: =IF(G$4<1,0,IF(G$4=1,Inputs!$C$26,Inputs!$C$19*Inputs!$C$27)) -> 3100000 | H13: =IF(H$4<1,0,IF(H$4=1,Inputs!$C$26,Inputs!$C$19*Inputs!$C$27)) -> 3100000 | I13: =IF(I$4<1,0,IF(I$4=1,Inputs!$C$26,Inputs!$C$19*Inputs!$C$27)) -> 3100000 | J13: =IF(J$4<1,0,IF(J$4=1,Inputs!$C$26,Inputs!$C$19*Inputs!$C$27)) -> 3100000
A14: Valuation at year end | C14: =IF(C$4<1,Inputs!$C$19,C12*(1+Inputs!$C$24)/Inputs!$C$28) -> 620000000 | D14: =IF(D$4<1,Inputs!$C$19,D12*(1+Inputs!$C$24)/Inputs!$C$28) -> 705409920 | E14: =IF(E$4<1,Inputs!$C$19,E12*(1+Inputs!$C$24)/Inputs!$C$28) -> 7.5079129e+08 | F14: =IF(F$4<1,Inputs!$C$19,F12*(1+Inputs!$C$24)/Inputs!$C$28) -> 7.7331503e+08 | G14: =IF(G$4<1,Inputs!$C$19,G12*(1+Inputs!$C$24)/Inputs!$C$28) -> 7.9651448e+08 | H14: =IF(H$4<1,Inputs!$C$19,H12*(1+Inputs!$C$24)/Inputs!$C$28) -> 8.2040992e+08 | I14: =IF(I$4<1,Inputs!$C$19,I12*(1+Inputs!$C$24)/Inputs!$C$28) -> 8.4502221e+08 | J14: =IF(J$4<1,Inputs!$C$19,J12*(1+Inputs!$C$24)/Inputs!$C$28) -> 8.7037288e+08
A15: Exit value net of disposal costs | C15: =C$5*C14*(1-Inputs!$C$16) -> 0 | D15: =D$5*D14*(1-Inputs!$C$16) -> 0 | E15: =E$5*E14*(1-Inputs!$C$16) -> 0 | F15: =F$5*F14*(1-Inputs!$C$16) -> 0 | G15: =G$5*G14*(1-Inputs!$C$16) -> 0 | H15: =H$5*H14*(1-Inputs!$C$16) -> 0 | I15: =I$5*I14*(1-Inputs!$C$16) -> 0 | J15: =J$5*J14*(1-Inputs!$C$16) -> 8.5731729e+08
A17: Corniche Retail Centre, Jeddah
A18: Occupancy | C18: =IF(C$4<1,0,IF(C$4=1,Inputs!$D$22,Inputs!$D$23)) -> 0 | D18: =IF(D$4<1,0,IF(D$4=1,Inputs!$D$22,Inputs!$D$23)) -> 0.88 | E18: =IF(E$4<1,0,IF(E$4=1,Inputs!$D$22,Inputs!$D$23)) -> 0.92 | F18: =IF(F$4<1,0,IF(F$4=1,Inputs!$D$22,Inputs!$D$23)) -> 0.92 | G18: =IF(G$4<1,0,IF(G$4=1,Inputs!$D$22,Inputs!$D$23)) -> 0.92 | H18: =IF(H$4<1,0,IF(H$4=1,Inputs!$D$22,Inputs!$D$23)) -> 0.92 | I18: =IF(I$4<1,0,IF(I$4=1,Inputs!$D$22,Inputs!$D$23)) -> 0.92 | J18: =IF(J$4<1,0,IF(J$4=1,Inputs!$D$22,Inputs!$D$23)) -> 0.92
A19: Rent (SAR per sqm a year) | C19: =IF(C$4<1,0,Inputs!$D$21*(1+Inputs!$D$24)^(C$4-1)) -> 0 | D19: =IF(D$4<1,0,Inputs!$D$21*(1+Inputs!$D$24)^(D$4-1)) -> 1350 | E19: =IF(E$4<1,0,Inputs!$D$21*(1+Inputs!$D$24)^(E$4-1)) -> 1383.75 | F19: =IF(F$4<1,0,Inputs!$D$21*(1+Inputs!$D$24)^(F$4-1)) -> 1418.3438 | G19: =IF(G$4<1,0,Inputs!$D$21*(1+Inputs!$D$24)^(G$4-1)) -> 1453.8023 | H19: =IF(H$4<1,0,Inputs!$D$21*(1+Inputs!$D$24)^(H$4-1)) -> 1490.1474 | I19: =IF(I$4<1,0,Inputs!$D$21*(1+Inputs!$D$24)^(I$4-1)) -> 1527.4011 | J19: =IF(J$4<1,0,Inputs!$D$21*(1+Inputs!$D$24)^(J$4-1)) -> 1565.5861
A20: Gross rent | C20: =Inputs!$D$20*C19*C18 -> 0 | D20: =Inputs!$D$20*D19*D18 -> 42768000 | E20: =Inputs!$D$20*E19*E18 -> 45829800 | F20: =Inputs!$D$20*F19*F18 -> 46975545 | G20: =Inputs!$D$20*G19*G18 -> 48149934 | H20: =Inputs!$D$20*H19*H18 -> 49353682 | I20: =Inputs!$D$20*I19*I18 -> 50587524 | J20: =Inputs!$D$20*J19*J18 -> 51852212
A21: Operating costs | C21: =C20*Inputs!$D$25 -> 0 | D21: =D20*Inputs!$D$25 -> 9408960 | E21: =E20*Inputs!$D$25 -> 10082556 | F21: =F20*Inputs!$D$25 -> 10334620 | G21: =G20*Inputs!$D$25 -> 10592985 | H21: =H20*Inputs!$D$25 -> 10857810 | I21: =I20*Inputs!$D$25 -> 11129255 | J21: =J20*Inputs!$D$25 -> 11407487
A22: Net operating income | C22: =C20-C21 -> 0 | D22: =D20-D21 -> 33359040 | E22: =E20-E21 -> 35747244 | F22: =F20-F21 -> 36640925 | G22: =G20-G21 -> 37556948 | H22: =H20-H21 -> 38495872 | I22: =I20-I21 -> 39458269 | J22: =J20-J21 -> 40444725
A23: Capital expenditure | C23: =IF(C$4<1,0,IF(C$4=1,Inputs!$D$26,Inputs!$D$19*Inputs!$D$27)) -> 0 | D23: =IF(D$4<1,0,IF(D$4=1,Inputs!$D$26,Inputs!$D$19*Inputs!$D$27)) -> 8000000 | E23: =IF(E$4<1,0,IF(E$4=1,Inputs!$D$26,Inputs!$D$19*Inputs!$D$27)) -> 2400000 | F23: =IF(F$4<1,0,IF(F$4=1,Inputs!$D$26,Inputs!$D$19*Inputs!$D$27)) -> 2400000 | G23: =IF(G$4<1,0,IF(G$4=1,Inputs!$D$26,Inputs!$D$19*Inputs!$D$27)) -> 2400000 | H23: =IF(H$4<1,0,IF(H$4=1,Inputs!$D$26,Inputs!$D$19*Inputs!$D$27)) -> 2400000 | I23: =IF(I$4<1,0,IF(I$4=1,Inputs!$D$26,Inputs!$D$19*Inputs!$D$27)) -> 2400000 | J23: =IF(J$4<1,0,IF(J$4=1,Inputs!$D$26,Inputs!$D$19*Inputs!$D$27)) -> 2400000
A24: Valuation at year end | C24: =IF(C$4<1,Inputs!$D$19,C22*(1+Inputs!$D$24)/Inputs!$D$28) -> 480000000 | D24: =IF(D$4<1,Inputs!$D$19,D22*(1+Inputs!$D$24)/Inputs!$D$28) -> 427412700 | E24: =IF(E$4<1,Inputs!$D$19,E22*(1+Inputs!$D$24)/Inputs!$D$28) -> 4.5801156e+08 | F24: =IF(F$4<1,Inputs!$D$19,F22*(1+Inputs!$D$24)/Inputs!$D$28) -> 4.6946185e+08 | G24: =IF(G$4<1,Inputs!$D$19,G22*(1+Inputs!$D$24)/Inputs!$D$28) -> 4.811984e+08 | H24: =IF(H$4<1,Inputs!$D$19,H22*(1+Inputs!$D$24)/Inputs!$D$28) -> 4.9322836e+08 | I24: =IF(I$4<1,Inputs!$D$19,I22*(1+Inputs!$D$24)/Inputs!$D$28) -> 5.0555907e+08 | J24: =IF(J$4<1,Inputs!$D$19,J22*(1+Inputs!$D$24)/Inputs!$D$28) -> 5.1819804e+08
A25: Exit value net of disposal costs | C25: =C$5*C24*(1-Inputs!$C$16) -> 0 | D25: =D$5*D24*(1-Inputs!$C$16) -> 0 | E25: =E$5*E24*(1-Inputs!$C$16) -> 0 | F25: =F$5*F24*(1-Inputs!$C$16) -> 0 | G25: =G$5*G24*(1-Inputs!$C$16) -> 0 | H25: =H$5*H24*(1-Inputs!$C$16) -> 0 | I25: =I$5*I24*(1-Inputs!$C$16) -> 0 | J25: =J$5*J24*(1-Inputs!$C$16) -> 5.1042507e+08
A27: Dammam Logistics Park
A28: Occupancy | C28: =IF(C$4<1,0,IF(C$4=1,Inputs!$E$22,Inputs!$E$23)) -> 0 | D28: =IF(D$4<1,0,IF(D$4=1,Inputs!$E$22,Inputs!$E$23)) -> 0.95 | E28: =IF(E$4<1,0,IF(E$4=1,Inputs!$E$22,Inputs!$E$23)) -> 0.96 | F28: =IF(F$4<1,0,IF(F$4=1,Inputs!$E$22,Inputs!$E$23)) -> 0.96 | G28: =IF(G$4<1,0,IF(G$4=1,Inputs!$E$22,Inputs!$E$23)) -> 0.96 | H28: =IF(H$4<1,0,IF(H$4=1,Inputs!$E$22,Inputs!$E$23)) -> 0.96 | I28: =IF(I$4<1,0,IF(I$4=1,Inputs!$E$22,Inputs!$E$23)) -> 0.96 | J28: =IF(J$4<1,0,IF(J$4=1,Inputs!$E$22,Inputs!$E$23)) -> 0.96
A29: Rent (SAR per sqm a year) | C29: =IF(C$4<1,0,Inputs!$E$21*(1+Inputs!$E$24)^(C$4-1)) -> 0 | D29: =IF(D$4<1,0,Inputs!$E$21*(1+Inputs!$E$24)^(D$4-1)) -> 330 | E29: =IF(E$4<1,0,Inputs!$E$21*(1+Inputs!$E$24)^(E$4-1)) -> 339.9 | F29: =IF(F$4<1,0,Inputs!$E$21*(1+Inputs!$E$24)^(F$4-1)) -> 350.097 | G29: =IF(G$4<1,0,Inputs!$E$21*(1+Inputs!$E$24)^(G$4-1)) -> 360.59991 | H29: =IF(H$4<1,0,Inputs!$E$21*(1+Inputs!$E$24)^(H$4-1)) -> 371.41791 | I29: =IF(I$4<1,0,Inputs!$E$21*(1+Inputs!$E$24)^(I$4-1)) -> 382.56044 | J29: =IF(J$4<1,0,Inputs!$E$21*(1+Inputs!$E$24)^(J$4-1)) -> 394.03726
A30: Gross rent | C30: =Inputs!$E$20*C29*C28 -> 0 | D30: =Inputs!$E$20*D29*D28 -> 43890000 | E30: =Inputs!$E$20*E29*E28 -> 45682560 | F30: =Inputs!$E$20*F29*F28 -> 47053037 | G30: =Inputs!$E$20*G29*G28 -> 48464628 | H30: =Inputs!$E$20*H29*H28 -> 49918567 | I30: =Inputs!$E$20*I29*I28 -> 51416124 | J30: =Inputs!$E$20*J29*J28 -> 52958607
A31: Operating costs | C31: =C30*Inputs!$E$25 -> 0 | D31: =D30*Inputs!$E$25 -> 3511200 | E31: =E30*Inputs!$E$25 -> 3654604.8 | F31: =F30*Inputs!$E$25 -> 3764242.9 | G31: =G30*Inputs!$E$25 -> 3877170.2 | H31: =H30*Inputs!$E$25 -> 3993485.3 | I31: =I30*Inputs!$E$25 -> 4113289.9 | J31: =J30*Inputs!$E$25 -> 4236688.6
A32: Net operating income | C32: =C30-C31 -> 0 | D32: =D30-D31 -> 40378800 | E32: =E30-E31 -> 42027955 | F32: =F30-F31 -> 43288794 | G32: =G30-G31 -> 44587458 | H32: =H30-H31 -> 45925081 | I32: =I30-I31 -> 47302834 | J32: =J30-J31 -> 48721919
A33: Capital expenditure | C33: =IF(C$4<1,0,IF(C$4=1,Inputs!$E$26,Inputs!$E$19*Inputs!$E$27)) -> 0 | D33: =IF(D$4<1,0,IF(D$4=1,Inputs!$E$26,Inputs!$E$19*Inputs!$E$27)) -> 3000000 | E33: =IF(E$4<1,0,IF(E$4=1,Inputs!$E$26,Inputs!$E$19*Inputs!$E$27)) -> 1140000 | F33: =IF(F$4<1,0,IF(F$4=1,Inputs!$E$26,Inputs!$E$19*Inputs!$E$27)) -> 1140000 | G33: =IF(G$4<1,0,IF(G$4=1,Inputs!$E$26,Inputs!$E$19*Inputs!$E$27)) -> 1140000 | H33: =IF(H$4<1,0,IF(H$4=1,Inputs!$E$26,Inputs!$E$19*Inputs!$E$27)) -> 1140000 | I33: =IF(I$4<1,0,IF(I$4=1,Inputs!$E$26,Inputs!$E$19*Inputs!$E$27)) -> 1140000 | J33: =IF(J$4<1,0,IF(J$4=1,Inputs!$E$26,Inputs!$E$19*Inputs!$E$27)) -> 1140000
A34: Valuation at year end | C34: =IF(C$4<1,Inputs!$E$19,C32*(1+Inputs!$E$24)/Inputs!$E$28) -> 380000000 | D34: =IF(D$4<1,Inputs!$E$19,D32*(1+Inputs!$E$24)/Inputs!$E$28) -> 5.7365743e+08 | E34: =IF(E$4<1,Inputs!$E$19,E32*(1+Inputs!$E$24)/Inputs!$E$28) -> 5.9708681e+08 | F34: =IF(F$4<1,Inputs!$E$19,F32*(1+Inputs!$E$24)/Inputs!$E$28) -> 6.1499942e+08 | G34: =IF(G$4<1,Inputs!$E$19,G32*(1+Inputs!$E$24)/Inputs!$E$28) -> 6.334494e+08 | H34: =IF(H$4<1,Inputs!$E$19,H32*(1+Inputs!$E$24)/Inputs!$E$28) -> 6.5245288e+08 | I34: =IF(I$4<1,Inputs!$E$19,I32*(1+Inputs!$E$24)/Inputs!$E$28) -> 6.7202647e+08 | J34: =IF(J$4<1,Inputs!$E$19,J32*(1+Inputs!$E$24)/Inputs!$E$28) -> 6.9218726e+08
A35: Exit value net of disposal costs | C35: =C$5*C34*(1-Inputs!$C$16) -> 0 | D35: =D$5*D34*(1-Inputs!$C$16) -> 0 | E35: =E$5*E34*(1-Inputs!$C$16) -> 0 | F35: =F$5*F34*(1-Inputs!$C$16) -> 0 | G35: =G$5*G34*(1-Inputs!$C$16) -> 0 | H35: =H$5*H34*(1-Inputs!$C$16) -> 0 | I35: =I$5*I34*(1-Inputs!$C$16) -> 0 | J35: =J$5*J34*(1-Inputs!$C$16) -> 6.8180445e+08

Sheet Fund
A1: FUND – ANNUAL (SAR)
A3: Year | C3: 2024 | D3: 2025 | E3: 2026 | F3: 2027 | G3: 2028 | H3: 2029 | I3: 2030 | J3: 2031
A4: Acquisition price | C4: =IF(Assets!C$4=0,Inputs!$C$19+Inputs!$D$19+Inputs!$E$19,0) -> 1480000000 | D4: =IF(Assets!D$4=0,Inputs!$C$19+Inputs!$D$19+Inputs!$E$19,0) -> 0 | E4: =IF(Assets!E$4=0,Inputs!$C$19+Inputs!$D$19+Inputs!$E$19,0) -> 0 | F4: =IF(Assets!F$4=0,Inputs!$C$19+Inputs!$D$19+Inputs!$E$19,0) -> 0 | G4: =IF(Assets!G$4=0,Inputs!$C$19+Inputs!$D$19+Inputs!$E$19,0) -> 0 | H4: =IF(Assets!H$4=0,Inputs!$C$19+Inputs!$D$19+Inputs!$E$19,0) -> 0 | I4: =IF(Assets!I$4=0,Inputs!$C$19+Inputs!$D$19+Inputs!$E$19,0) -> 0 | J4: =IF(Assets!J$4=0,Inputs!$C$19+Inputs!$D$19+Inputs!$E$19,0) -> 0
A5: Acquisition costs | C5: =C4*Inputs!$C$8 -> 81400000 | D5: =D4*Inputs!$C$8 -> 0 | E5: =E4*Inputs!$C$8 -> 0 | F5: =F4*Inputs!$C$8 -> 0 | G5: =G4*Inputs!$C$8 -> 0 | H5: =H4*Inputs!$C$8 -> 0 | I5: =I4*Inputs!$C$8 -> 0 | J5: =J4*Inputs!$C$8 -> 0
A6: Debt drawn | C6: =C4*Inputs!$C$7 -> 518000000 | D6: =D4*Inputs!$C$7 -> 0 | E6: =E4*Inputs!$C$7 -> 0 | F6: =F4*Inputs!$C$7 -> 0 | G6: =G4*Inputs!$C$7 -> 0 | H6: =H4*Inputs!$C$7 -> 0 | I6: =I4*Inputs!$C$7 -> 0 | J6: =J4*Inputs!$C$7 -> 0
A7: Equity raised | C7: =C4+C5-C6 -> 1043400000 | D7: =D4+D5-D6 -> 0 | E7: =E4+E5-E6 -> 0 | F7: =F4+F5-F6 -> 0 | G7: =G4+G5-G6 -> 0 | H7: =H4+H5-H6 -> 0 | I7: =I4+I5-I6 -> 0 | J7: =J4+J5-J6 -> 0
A8: Units in issue | C8: =$C$7/Inputs!$C$6 -> 104340000 | D8: =$C$7/Inputs!$C$6 -> 104340000 | E8: =$C$7/Inputs!$C$6 -> 104340000 | F8: =$C$7/Inputs!$C$6 -> 104340000 | G8: =$C$7/Inputs!$C$6 -> 104340000 | H8: =$C$7/Inputs!$C$6 -> 104340000 | I8: =$C$7/Inputs!$C$6 -> 104340000 | J8: =$C$7/Inputs!$C$6 -> 104340000
A9: Net operating income | C9: =Assets!C12+Assets!C22+Assets!C32 -> 0 | D9: =Assets!D12+Assets!D22+Assets!D32 -> 125102640 | E9: =Assets!E12+Assets!E22+Assets!E32 -> 132444468 | F9: =Assets!F12+Assets!F22+Assets!F32 -> 1.3623907e+08 | G9: =Assets!G12+Assets!G22+Assets!G32 -> 1.4014303e+08 | H9: =Assets!H12+Assets!H22+Assets!H32 -> 1.4415954e+08 | I9: =Assets!I12+Assets!I22+Assets!I32 -> 1.4829185e+08 | J9: =Assets!J12+Assets!J22+Assets!J32 -> 1.5254331e+08
A10: Capital expenditure | C10: =Assets!C13+Assets!C23+Assets!C33 -> 0 | D10: =Assets!D13+Assets!D23+Assets!D33 -> 23000000 | E10: =Assets!E13+Assets!E23+Assets!E33 -> 6640000 | F10: =Assets!F13+Assets!F23+Assets!F33 -> 6640000 | G10: =Assets!G13+Assets!G23+Assets!G33 -> 6640000 | H10: =Assets!H13+Assets!H23+Assets!H33 -> 6640000 | I10: =Assets!I13+Assets!I23+Assets!I33 -> 6640000 | J10: =Assets!J13+Assets!J23+Assets!J33 -> 6640000
A11: Gross asset value | C11: =Assets!C14+Assets!C24+Assets!C34 -> 1480000000 | D11: =Assets!D14+Assets!D24+Assets!D34 -> 1.7064801e+09 | E11: =Assets!E14+Assets!E24+Assets!E34 -> 1.8058897e+09 | F11: =Assets!F14+Assets!F24+Assets!F34 -> 1.8577763e+09 | G11: =Assets!G14+Assets!G24+Assets!G34 -> 1.9111623e+09 | H11: =Assets!H14+Assets!H24+Assets!H34 -> 1.9660912e+09 | I11: =Assets!I14+Assets!I24+Assets!I34 -> 2.0226077e+09 | J11: =Assets!J14+Assets!J24+Assets!J34 -> 2.0807582e+09
A12: Debt outstanding | C12: =IF(Assets!C$5=1,0,$C$6) -> 518000000 | D12: =IF(Assets!D$5=1,0,$C$6) -> 518000000 | E12: =IF(Assets!E$5=1,0,$C$6) -> 518000000 | F12: =IF(Assets!F$5=1,0,$C$6) -> 518000000 | G12: =IF(Assets!G$5=1,0,$C$6) -> 518000000 | H12: =IF(Assets!H$5=1,0,$C$6) -> 518000000 | I12: =IF(Assets!I$5=1,0,$C$6) -> 518000000 | J12: =IF(Assets!J$5=1,0,$C$6) -> 0
A13: Net asset value | C13: =C11-$C$6 -> 962000000 | D13: =D11-$C$6 -> 1.1884801e+09 | E13: =E11-$C$6 -> 1.2878897e+09 | F13: =F11-$C$6 -> 1.3397763e+09 | G13: =G11-$C$6 -> 1.3931623e+09 | H13: =H11-$C$6 -> 1.4480912e+09 | I13: =I11-$C$6 -> 1.5046077e+09 | J13: =J11-$C$6 -> 1.5627582e+09
A14: Management fee | C14: =IF(Assets!C$4<1,0,C13*Inputs!$C$11) -> 0 | D14: =IF(Assets!D$4<1,0,D13*Inputs!$C$11) -> 10102080 | E14: =IF(Assets!E$4<1,0,E13*Inputs!$C$11) -> 10947062 | F14: =IF(Assets!F$4<1,0,F13*Inputs!$C$11) -> 11388099 | G14: =IF(Assets!G$4<1,0,G13*Inputs!$C$11) -> 11841879 | H14: =IF(Assets!H$4<1,0,H13*Inputs!$C$11) -> 12308775 | I14: =IF(Assets!I$4<1,0,I13*Inputs!$C$11) -> 12789166 | J14: =IF(Assets!J$4<1,0,J13*Inputs!$C$11) -> 13283445
A15: Fund administration and custody fees | C15: =IF(Assets!C$4<1,0,Inputs!$C$12*(1+Inputs!$C$13)^(Assets!C$4-1)) -> 0 | D15: =IF(Assets!D$4<1,0,Inputs!$C$12*(1+Inputs!$C$13)^(Assets!D$4-1)) -> 4500000 | E15: =IF(Assets!E$4<1,0,Inputs!$C$12*(1+Inputs!$C$13)^(Assets!E$4-1)) -> 4635000 | F15: =IF(Assets!F$4<1,0,Inputs!$C$12*(1+Inputs!$C$13)^(Assets!F$4-1)) -> 4774050 | G15: =IF(Assets!G$4<1,0,Inputs!$C$12*(1+Inputs!$C$13)^(Assets!G$4-1)) -> 4917271.5 | H15: =IF(Assets!H$4<1,0,Inputs!$C$12*(1+Inputs!$C$13)^(Assets!H$4-1)) -> 5064789.6 | I15: =IF(Assets!I$4<1,0,Inputs!$C$12*(1+Inputs!$C$13)^(Assets!I$4-1)) -> 5216733.3 | J15: =IF(Assets!J$4<1,0,Inputs!$C$12*(1+Inputs!$C$13)^(Assets!J$4-1)) -> 5373235.3
A16: Interest | C16: =IF(Assets!C$4<1,0,$C$6*(Inputs!$C$9+Inputs!$C$10/10000)) -> 0 | D16: =IF(Assets!D$4<1,0,$C$6*(Inputs!$C$9+Inputs!$C$10/10000)) -> 38850000 | E16: =IF(Assets!E$4<1,0,$C$6*(Inputs!$C$9+Inputs!$C$10/10000)) -> 38850000 | F16: =IF(Assets!F$4<1,0,$C$6*(Inputs!$C$9+Inputs!$C$10/10000)) -> 38850000 | G16: =IF(Assets!G$4<1,0,$C$6*(Inputs!$C$9+Inputs!$C$10/10000)) -> 38850000 | H16: =IF(Assets!H$4<1,0,$C$6*(Inputs!$C$9+Inputs!$C$10/10000)) -> 38850000 | I16: =IF(Assets!I$4<1,0,$C$6*(Inputs!$C$9+Inputs!$C$10/10000)) -> 38850000 | J16: =IF(Assets!J$4<1,0,$C$6*(Inputs!$C$9+Inputs!$C$10/10000)) -> 38850000
A17: Cash available for distribution | C17: =C9-C10-C14-C15-C16 -> 0 | D17: =D9-D10-D14-D15-D16 -> 48650560 | E17: =E9-E10-E14-E15-E16 -> 71372406 | F17: =F9-F10-F14-F15-F16 -> 74586917 | G17: =G9-G10-G14-G15-G16 -> 77893882 | H17: =H9-H10-H14-H15-H16 -> 81295975 | I17: =I9-I10-I14-I15-I16 -> 84795947 | J17: =J9-J10-J14-J15-J16 -> 88396630
A18: Distributions to unitholders | C18: =MAX(0,C17*Inputs!$C$14) -> 0 | D18: =MAX(0,D17*Inputs!$C$14) -> 43785504 | E18: =MAX(0,E17*Inputs!$C$14) -> 64235165 | F18: =MAX(0,F17*Inputs!$C$14) -> 67128226 | G18: =MAX(0,G17*Inputs!$C$14) -> 70104494 | H18: =MAX(0,H17*Inputs!$C$14) -> 73166377 | I18: =MAX(0,I17*Inputs!$C$14) -> 76316352 | J18: =MAX(0,J17*Inputs!$C$14) -> 79556967
A19: Exit proceeds net of debt | C19: =IF(Assets!C$5=1,Assets!C15+Assets!C25+Assets!C35-$C$6+SUM($C17:C17)-SUM($C18:C18),0) -> 0 | D19: =IF(Assets!D$5=1,Assets!D15+Assets!D25+Assets!D35-$C$6+SUM($C17:D17)-SUM($C18:D18),0) -> 0 | E19: =IF(Assets!E$5=1,Assets!E15+Assets!E25+Assets!E35-$C$6+SUM($C17:E17)-SUM($C18:E18),0) -> 0 | F19: =IF(Assets!F$5=1,Assets!F15+Assets!F25+Assets!F35-$C$6+SUM($C17:F17)-SUM($C18:F18),0) -> 0 | G19: =IF(Assets!G$5=1,Assets!G15+Assets!G25+Assets!G35-$C$6+SUM($C17:G17)-SUM($C18:G18),0) -> 0 | H19: =IF(Assets!H$5=1,Assets!H15+Assets!H25+Assets!H35-$C$6+SUM($C17:H17)-SUM($C18:H18),0) -> 0 | I19: =IF(Assets!I$5=1,Assets!I15+Assets!I25+Assets!I35-$C$6+SUM($C17:I17)-SUM($C18:I18),0) -> 0 | J19: =IF(Assets!J$5=1,Assets!J15+Assets!J25+Assets!J35-$C$6+SUM($C17:J17)-SUM($C18:J18),0) -> 1.584246e+09
A20: Cash flow to unitholders | C20: =-C7+C18+C19 -> -1043400000 | D20: =-D7+D18+D19 -> 43785504 | E20: =-E7+E18+E19 -> 64235165 | F20: =-F7+F18+F19 -> 67128226 | G20: =-G7+G18+G19 -> 70104494 | H20: =-H7+H18+H19 -> 73166377 | I20: =-I7+I18+I19 -> 76316352 | J20: =-J7+J18+J19 -> 1.663803e+09
A21: Distribution yield on equity | C21: =IF(Assets!C$4<1,0,C18/$C$7) -> 0 | D21: =IF(Assets!D$4<1,0,D18/$C$7) -> 0.041964255 | E21: =IF(Assets!E$4<1,0,E18/$C$7) -> 0.061563317 | F21: =IF(Assets!F$4<1,0,F18/$C$7) -> 0.064336041 | G21: =IF(Assets!G$4<1,0,G18/$C$7) -> 0.067188513 | H21: =IF(Assets!H$4<1,0,H18/$C$7) -> 0.070123038 | I21: =IF(Assets!I$4<1,0,I18/$C$7) -> 0.07314199 | J21: =IF(Assets!J$4<1,0,J18/$C$7) -> 0.076247812
A22: NAV per unit (SAR) | C22: =C13/C8 -> 9.2198582 | D22: =D13/D8 -> 11.390455 | E22: =E13/E8 -> 12.343202 | F22: =F13/F8 -> 12.840486 | G22: =G13/G8 -> 13.35214 | H22: =H13/H8 -> 13.878581 | I22: =I13/I8 -> 14.420239 | J22: =J13/J8 -> 14.977556
A23: Loan to value | C23: =IF(C11=0,0,$C$6/C11) -> 0.35 | D23: =IF(D11=0,0,$C$6/D11) -> 0.30354882 | E23: =IF(E11=0,0,$C$6/E11) -> 0.28683923 | F23: =IF(F11=0,0,$C$6/F11) -> 0.27882797 | G23: =IF(G11=0,0,$C$6/G11) -> 0.27103925 | H23: =IF(H11=0,0,$C$6/H11) -> 0.26346693 | I23: =IF(I11=0,0,$C$6/I11) -> 0.25610502 | J23: =IF(J11=0,0,$C$6/J11) -> 0.24894772
A24: Interest cover (NOI / interest) | C24: =IF(C16=0,0,C9/C16) -> 0 | D24: =IF(D16=0,0,D9/D16) -> 3.2201452 | E24: =IF(E16=0,0,E9/E16) -> 3.409124 | F24: =IF(F16=0,0,F9/F16) -> 3.5067971 | G24: =IF(G16=0,0,G9/G16) -> 3.6072853 | H24: =IF(H16=0,0,H9/H16) -> 3.7106703 | I24: =IF(I16=0,0,I9/I16) -> 3.8170359 | J24: =IF(J16=0,0,J9/J16) -> 3.9264687
