Workbook

Sheet Inputs
A1: Input | B1: Value
A2: Land cost | B2: 120000
A3: Construction cost | B3: 400000
A4: Professional fees % | B4: 0.08
A5: Contingency % | B5: 0.05
A6: Marketing % | B6: 0.03
A7: Sale price per unit | B7: 1800
A8: Units | B8: 400
A9: Rent growth | B9: 0.03
A10: Exit yield | B10: 0.07
A11: Interest rate | B11: 0.06
A12: Debt % | B12: 0.55

Sheet Model
A1: Model (SAR 000)
A3: Year | E3: 2026 | F3: 2027 | G3: 2028 | H3: 2030 | I3: 2031 | J3: 2032 | K3: 2033 | L3: 2034 | N3: Total
A4: S-curve | E4: 0.3 | F4: 0.4 | G4: 0.25 | H4: 0 | I4: 0 | J4: 0 | K4: 0 | L4: 0
A5: Sales phasing | E5: 0 | F5: 0.2 | G5: 0.4 | H5: 0.4 | I5: 0 | J5: 0 | K5: 0 | L5: 0
A10: Land | E10: =Inputs!$B$2*IF(E3=$E$3,1,0) -> 120000 | F10: =Inputs!$B$2*IF(F3=$E$3,1,0) -> 0 | G10: =Inputs!$B$2*IF(G3=$E$3,1,0) -> 0 | H10: =Inputs!$B$2*IF(H3=$E$3,1,0) -> 0 | I10: =Inputs!$B$2*IF(I3=$E$3,1,0) -> 0 | J10: =Inputs!$B$2*IF(J3=$E$3,1,0) -> 0 | K10: =Inputs!$B$2*IF(K3=$E$3,1,0) -> 0 | L10: =Inputs!$B$2*IF(L3=$E$3,1,0) -> 0 | N10: =SUM(E10:L10) -> 120000
A11: Construction | E11: =Inputs!$B$3*E4 -> 120000 | F11: =Inputs!$B$3*F4 -> 160000 | G11: =Inputs!$B$3*G4 -> 100000 | H11: =Inputs!$B$3*H4 -> 0 | I11: =Inputs!$B$3*I4 -> 0 | J11: =Inputs!$B$3*J4 -> 0 | K11: =Inputs!$B$3*K4 -> 0 | L11: =Inputs!$B$3*L4 -> 0 | N11: =SUM(E11:L11) -> 380000
A12: Professional fees | E12: =E11*Inputs!$B$4 -> 9600 | F12: =F11*Inputs!$B$4 -> 12800 | G12: =G11*Inputs!$B$4 -> 8000 | H12: =H11*Inputs!$B$4 -> 0 | I12: =I11*Inputs!$B$4 -> 0 | J12: =J11*Inputs!$B$4 -> 0 | K12: =K11*Inputs!$B$4 -> 0 | L12: =L11*Inputs!$B$4 -> 0 | N12: =SUM(E12:L12) -> 30400
A13: Contingency | E13: =E11*Inputs!$B$5 -> 6000 | F13: =F11*Inputs!$B$5 -> 8000 | G13: =G11*Inputs!$B$5 -> 5000 | H13: =H11*Inputs!$B$5 -> 0 | I13: =I11*Inputs!$B$5 -> 0 | J13: =J11*Inputs!$B$5 -> 0 | K13: =K11*Inputs!$B$5 -> 0 | L13: =L11*Inputs!$B$5 -> 0 | N13: =SUM(E13:L13) -> 19000
A14: Marketing | E14: =E17*Inputs!$B$6 -> 0 | F14: =F17*Inputs!$B$6 -> 4406.4 | G14: =G17*Inputs!$B$6 -> 8989.056 | H14: =H17*Inputs!$B$6 -> 9168.8371 | I14: =I17*Inputs!$B$6 -> 0 | J14: =J17*Inputs!$B$6 -> 0 | K14: =K17*Inputs!$B$6 -> 0 | L14: =L17*Inputs!$B$6 -> 0 | N14: =SUM(E14:L14) -> 22564.293
A15: Total cost | E15: =SUM(E10:E13) -> 255600 | F15: =SUM(F10:F13) -> 180800 | G15: =SUM(G10:G13) -> 113000 | H15: =SUM(H10:H13) -> 0 | I15: =SUM(I10:I13) -> 0 | J15: =SUM(J10:J13) -> 0 | K15: =SUM(K10:K13) -> 0 | L15: =SUM(L10:L13) -> 0 | N15: =SUM(E15:L15) -> 549400
A17: Sales revenue | E17: =Inputs!$B$7*Inputs!$B$8*E5*E18 -> 0 | F17: =Inputs!$B$7*Inputs!$B$8*F5*F18 -> 146880 | G17: =Inputs!$B$7*Inputs!$B$8*G5*G18 -> 299635.2 | H17: =Inputs!$B$7*Inputs!$B$8*H5*H18 -> 305627.9 | I17: =Inputs!$B$7*Inputs!$B$8*I5*I18 -> 0 | J17: =Inputs!$B$7*Inputs!$B$8*J5*J18 -> 0 | K17: =Inputs!$B$7*Inputs!$B$8*K5*K18 -> 0 | L17: =Inputs!$B$7*Inputs!$B$8*L5*L18 -> 0 | N17: =SUM(E17:L17) -> 752143.1
A18: Sales price index | E18: =1 -> 1 | F18: =E18*1.02 -> 1.02 | G18: =F18*1.02 -> 1.0404 | H18: =G18*1.02 -> 1.061208 | I18: =H18*1.02 -> 1.0824322 | J18: =I18*1.02 -> 1.1040808 | K18: =J18*1.02 -> 1.1261624 | L18: =K18 -> 1.1261624
A19: Net profit (sum) | E19: =E20 -> 255600 | F19: =F20 -> 327680 | G19: =G20 -> 412635.2 | H19: =H20 -> 305627.9 | I19: =I20 -> 0 | J19: =J20 -> 0 | K19: =K20 -> 0 | L19: =L20 -> 0 | N19: =SUM(E19:L19) -> 1301543.1
A20: Net profit | E20: =E17+E15 -> 255600 | F20: =F17+F15 -> 327680 | G20: =G17+G15 -> 412635.2 | H20: =H17+H15 -> 305627.9 | I20: =I17+I15 -> 0 | J20: =J17+J15 -> 0 | K20: =K17+K15 -> 0 | L20: =L17+L15 -> 0 | N20: =SUM(E20:L20) -> 1301543.1
A22: Debt drawn | E22: =E15*Inputs!$B$12 -> 140580 | F22: =F15*Inputs!$B$12 -> 99440 | G22: =G15*Inputs!$B$12 -> 62150 | H22: =H15*Inputs!$B$12 -> 0 | I22: =I15*Inputs!$B$12 -> 0 | J22: =J15*Inputs!$B$12 -> 0 | K22: =K15*Inputs!$B$12 -> 0 | L22: =L15*Inputs!$B$12 -> 0 | N22: =SUM(E22:L22) -> 302170
A23: Interest | E23: =E22*Inputs!$B$11 -> 8434.8 | F23: =F22*Inputs!$B$11 -> 5966.4 | G23: =G22*Inputs!$B$11 -> 3729 | H23: =H22*Inputs!$B$11 -> 0 | I23: =I22*Inputs!$B$11 -> 0 | J23: =J22*Inputs!$B$11 -> 0 | K23: =K22*Inputs!$B$11 -> 0 | L23: =L22*Inputs!$B$11 -> 0 | N23: =SUM(E23:L23) -> 18130.2
A25: Net cash flow | E25: =E17-E15-E23 -> -264034.8 | F25: =F17-F15-F23 -> -39886.4 | G25: =G17-G15-G23 -> 182906.2 | H25: =H17-H15-H23 -> 305627.9 | I25: =I17-I15-I23 -> 0 | J25: =J17-J15-J23 -> 0 | K25: =K17-K15-K23 -> 0 | L25: 150000 | N25: =SUM(E25:L25) -> 334612.9

Sheet Dashboard
A1: Dashboard
A3: Levered IRR | B3: =IRR(Model!E25:L25) -> 0.26300846
A4: Total development cost | B4: =Model!N15 -> 549400
A5: Gross revenue | B5: =Model!N17 -> 752143.1
A6: Net profit | B6: 310000
A7: Net profit check | B7: =Model!N19 -> 1301543.1
A8: Peak debt | B8: =MAX(Model!E22:L22) -> 140580
A9: Profit on cost | B9: =B6/B4 -> 0.56425191

Sheet Checks
A1: Checks
A3: Check: sources - uses | B3: =Model!N22-Model!N15*Inputs!B12+1 -> 1
A4: Check: phasing | B4: =SUM(Model!E5:L5)-1 -> 0
