Workbook
Name DiscRate: Inputs!$B$5

Sheet Inputs
A1: HARBOUR LEASE-UP – EXCEL 365 (USD)
A2: Purchase price | B2: 60000000
A3: Rent growth | B3: 0.025
A4: Exit yield | B4: 0.065
A5: Discount rate | B5: 0.09
A6: Hold (years) | B6: 10

Sheet Leases
A1: Tenant | B1: Area | C1: Rent psm | D1: Start year
A2: Anchor | B2: 12000 | C2: 180 | D2: 1
A3: Gym | B3: 3000 | C3: 150 | D3: 2
A4: Cafe | B4: 800 | C4: 320 | D4: 1
A5: Anchor | B5: 4000 | C5: 175 | D5: 3
A6: Clinic | B6: 2500 | C6: 210 | D6: 4

Sheet Cash Flow
A1: Year | B1: =_xlfn.SEQUENCE(1,10)
A2: Date | B2: =DATE(2026+B1,12,31) | C2: =DATE(2026+C1,12,31) | D2: =DATE(2026+D1,12,31) | E2: =DATE(2026+E1,12,31) | F2: =DATE(2026+F1,12,31) | G2: =DATE(2026+G1,12,31) | H2: =DATE(2026+H1,12,31) | I2: =DATE(2026+I1,12,31) | ... K2: =DATE(2026+K1,12,31)
A3: Rent | B3: =SUMPRODUCT((Leases[Start year]<=B1)*Leases[Area]*Leases[Rent psm])*(1+Inputs!$B$3)^(B1-1) | C3: =SUMPRODUCT((Leases[Start year]<=C1)*Leases[Area]*Leases[Rent psm])*(1+Inputs!$B$3)^(C1-1) | D3: =SUMPRODUCT((Leases[Start year]<=D1)*Leases[Area]*Leases[Rent psm])*(1+Inputs!$B$3)^(D1-1) | E3: =SUMPRODUCT((Leases[Start year]<=E1)*Leases[Area]*Leases[Rent psm])*(1+Inputs!$B$3)^(E1-1) | F3: =SUMPRODUCT((Leases[Start year]<=F1)*Leases[Area]*Leases[Rent psm])*(1+Inputs!$B$3)^(F1-1) | G3: =SUMPRODUCT((Leases[Start year]<=G1)*Leases[Area]*Leases[Rent psm])*(1+Inputs!$B$3)^(G1-1) | H3: =SUMPRODUCT((Leases[Start year]<=H1)*Leases[Area]*Leases[Rent psm])*(1+Inputs!$B$3)^(H1-1) | I3: =SUMPRODUCT((Leases[Start year]<=I1)*Leases[Area]*Leases[Rent psm])*(1+Inputs!$B$3)^(I1-1) | ... K3: =SUMPRODUCT((Leases[Start year]<=K1)*Leases[Area]*Leases[Rent psm])*(1+Inputs!$B$3)^(K1-1)
A4: Purchase and sale | B4: =IF(B1=1,-Inputs!$B$2,0)+IF(B1=Inputs!$B$6,B3*(1+Inputs!$B$3)/Inputs!$B$4,0) | C4: =IF(C1=1,-Inputs!$B$2,0)+IF(C1=Inputs!$B$6,C3*(1+Inputs!$B$3)/Inputs!$B$4,0) | D4: =IF(D1=1,-Inputs!$B$2,0)+IF(D1=Inputs!$B$6,D3*(1+Inputs!$B$3)/Inputs!$B$4,0) | E4: =IF(E1=1,-Inputs!$B$2,0)+IF(E1=Inputs!$B$6,E3*(1+Inputs!$B$3)/Inputs!$B$4,0) | F4: =IF(F1=1,-Inputs!$B$2,0)+IF(F1=Inputs!$B$6,F3*(1+Inputs!$B$3)/Inputs!$B$4,0) | G4: =IF(G1=1,-Inputs!$B$2,0)+IF(G1=Inputs!$B$6,G3*(1+Inputs!$B$3)/Inputs!$B$4,0) | H4: =IF(H1=1,-Inputs!$B$2,0)+IF(H1=Inputs!$B$6,H3*(1+Inputs!$B$3)/Inputs!$B$4,0) | I4: =IF(I1=1,-Inputs!$B$2,0)+IF(I1=Inputs!$B$6,I3*(1+Inputs!$B$3)/Inputs!$B$4,0) | ... K4: =IF(K1=1,-Inputs!$B$2,0)+IF(K1=Inputs!$B$6,K3*(1+Inputs!$B$3)/Inputs!$B$4,0)
A5: Net cash flow | B5: =B3+B4 | C5: =C3+C4 | D5: =D3+D4 | E5: =E3+E4 | F5: =F3+F4 | G5: =G3+G4 | H5: =H3+H4 | I5: =I3+I4 | ... K5: =K3+K4

Sheet Returns
A1: Unlevered IRR | B1: =IRR('Cash Flow'!B5:K5)
A2: NPV at the discount rate | B2: =XNPV(DiscRate,'Cash Flow'!B5:K5,'Cash Flow'!B2:K2)
A3: Net profit | B3: =SUM('Cash Flow'!B5:K5)
A4: Tenants | B4: =COUNTA(_xlfn.UNIQUE(Leases[Tenant]))
A5: Anchor area | B5: =SUM(_xlfn._xlws.FILTER(Leases[Area],Leases[Tenant]="Anchor"))
A6: Total area | B6: =SUM(Leases[Area])
