Workbook

Sheet Inputs
A1: AL MANAR TOWERS JV – DEVELOPMENT (SAR)
A2: Land | B2: 50000000
A3: Construction cost | B3: 200000000
A4: Loan to cost | B4: 0.6
A5: Interest rate | B5: 0.08
A6: Stabilised rent | B6: 30000000
A7: Rent growth | B7: 0.03
A8: Exit yield | B8: 0.075
A9: Hold period (years) | B9: 8
A10: Selling costs | B10: 0.02
A11: LP share of equity | B11: 0.9
A12: Preferred return | B12: 0.08
A13: LP share above the pref | B13: 0.8

Sheet Cash Flow
A1: Year | B1: 1 | C1: 2 | D1: 3 | E1: 4 | F1: 5 | G1: 6 | H1: 7 | I1: 8 | J1: 9 | K1: 10
A2: Land | B2: =Inputs!$B$2 | C2: 0 | D2: 0 | E2: 0 | F2: 0 | G2: 0 | H2: 0 | I2: 0 | J2: 0 | K2: 0
A3: Construction | B3: =Inputs!$B$3*0.3 | C3: =Inputs!$B$3*0.4 | D3: =Inputs!$B$3*0.3 | E3: 0 | F3: 0 | G3: 0 | H3: 0 | I3: 0 | J3: 0 | K3: 0
A4: Interest | B4: =Inputs!$B$5*(0+B6/2)*(B1<=Inputs!$B$9) | C4: =Inputs!$B$5*(B7+C6/2)*(C1<=Inputs!$B$9) | D4: =Inputs!$B$5*(C7+D6/2)*(D1<=Inputs!$B$9) | E4: =Inputs!$B$5*(D7+E6/2)*(E1<=Inputs!$B$9) | F4: =Inputs!$B$5*(E7+F6/2)*(F1<=Inputs!$B$9) | G4: =Inputs!$B$5*(F7+G6/2)*(G1<=Inputs!$B$9) | H4: =Inputs!$B$5*(G7+H6/2)*(H1<=Inputs!$B$9) | I4: =Inputs!$B$5*(H7+I6/2)*(I1<=Inputs!$B$9) | J4: =Inputs!$B$5*(I7+J6/2)*(J1<=Inputs!$B$9) | K4: =Inputs!$B$5*(J7+K6/2)*(K1<=Inputs!$B$9)
A5: Total cost | B5: =B2+B3+IF(B1<=3,B4,0) | C5: =C2+C3+IF(C1<=3,C4,0) | D5: =D2+D3+IF(D1<=3,D4,0) | E5: =E2+E3+IF(E1<=3,E4,0) | F5: =F2+F3+IF(F1<=3,F4,0) | G5: =G2+G3+IF(G1<=3,G4,0) | H5: =H2+H3+IF(H1<=3,H4,0) | I5: =I2+I3+IF(I1<=3,I4,0) | ... K5: =K2+K3+IF(K1<=3,K4,0)
A6: Loan draw | B6: =IF(B1<=3,Inputs!$B$4*B5,0) | C6: =IF(C1<=3,Inputs!$B$4*C5,0) | D6: =IF(D1<=3,Inputs!$B$4*D5,0) | E6: =IF(E1<=3,Inputs!$B$4*E5,0) | F6: =IF(F1<=3,Inputs!$B$4*F5,0) | G6: =IF(G1<=3,Inputs!$B$4*G5,0) | H6: =IF(H1<=3,Inputs!$B$4*H5,0) | I6: =IF(I1<=3,Inputs!$B$4*I5,0) | ... K6: =IF(K1<=3,Inputs!$B$4*K5,0)
A7: Loan balance | B7: =IF(B1<=Inputs!$B$9,0+B6-B10,0) | C7: =IF(C1<=Inputs!$B$9,B7+C6-C10,0) | D7: =IF(D1<=Inputs!$B$9,C7+D6-D10,0) | E7: =IF(E1<=Inputs!$B$9,D7+E6-E10,0) | F7: =IF(F1<=Inputs!$B$9,E7+F6-F10,0) | G7: =IF(G1<=Inputs!$B$9,F7+G6-G10,0) | H7: =IF(H1<=Inputs!$B$9,G7+H6-H10,0) | I7: =IF(I1<=Inputs!$B$9,H7+I6-I10,0) | J7: =IF(J1<=Inputs!$B$9,I7+J6-J10,0) | K7: =IF(K1<=Inputs!$B$9,J7+K6-K10,0)
A8: NOI | B8: =IF(AND(B1>3,B1<=Inputs!$B$9),Inputs!$B$6*(1+Inputs!$B$7)^(B1-4),0) | C8: =IF(AND(C1>3,C1<=Inputs!$B$9),Inputs!$B$6*(1+Inputs!$B$7)^(C1-4),0) | D8: =IF(AND(D1>3,D1<=Inputs!$B$9),Inputs!$B$6*(1+Inputs!$B$7)^(D1-4),0) | E8: =IF(AND(E1>3,E1<=Inputs!$B$9),Inputs!$B$6*(1+Inputs!$B$7)^(E1-4),0) | F8: =IF(AND(F1>3,F1<=Inputs!$B$9),Inputs!$B$6*(1+Inputs!$B$7)^(F1-4),0) | G8: =IF(AND(G1>3,G1<=Inputs!$B$9),Inputs!$B$6*(1+Inputs!$B$7)^(G1-4),0) | H8: =IF(AND(H1>3,H1<=Inputs!$B$9),Inputs!$B$6*(1+Inputs!$B$7)^(H1-4),0) | I8: =IF(AND(I1>3,I1<=Inputs!$B$9),Inputs!$B$6*(1+Inputs!$B$7)^(I1-4),0) | ... K8: =IF(AND(K1>3,K1<=Inputs!$B$9),Inputs!$B$6*(1+Inputs!$B$7)^(K1-4),0)
A9: Sale proceeds | B9: =IF(B1=Inputs!$B$9,Inputs!$B$6*(1+Inputs!$B$7)^(B1-3)/Inputs!$B$8*(1-Inputs!$B$10),0) | C9: =IF(C1=Inputs!$B$9,Inputs!$B$6*(1+Inputs!$B$7)^(C1-3)/Inputs!$B$8*(1-Inputs!$B$10),0) | D9: =IF(D1=Inputs!$B$9,Inputs!$B$6*(1+Inputs!$B$7)^(D1-3)/Inputs!$B$8*(1-Inputs!$B$10),0) | E9: =IF(E1=Inputs!$B$9,Inputs!$B$6*(1+Inputs!$B$7)^(E1-3)/Inputs!$B$8*(1-Inputs!$B$10),0) | F9: =IF(F1=Inputs!$B$9,Inputs!$B$6*(1+Inputs!$B$7)^(F1-3)/Inputs!$B$8*(1-Inputs!$B$10),0) | G9: =IF(G1=Inputs!$B$9,Inputs!$B$6*(1+Inputs!$B$7)^(G1-3)/Inputs!$B$8*(1-Inputs!$B$10),0) | H9: =IF(H1=Inputs!$B$9,Inputs!$B$6*(1+Inputs!$B$7)^(H1-3)/Inputs!$B$8*(1-Inputs!$B$10),0) | I9: =IF(I1=Inputs!$B$9,Inputs!$B$6*(1+Inputs!$B$7)^(I1-3)/Inputs!$B$8*(1-Inputs!$B$10),0) | ... K9: =IF(K1=Inputs!$B$9,Inputs!$B$6*(1+Inputs!$B$7)^(K1-3)/Inputs!$B$8*(1-Inputs!$B$10),0)
A10: Loan repayment | B10: =IF(B1=Inputs!$B$9,0+B6,0) | C10: =IF(C1=Inputs!$B$9,B7+C6,0) | D10: =IF(D1=Inputs!$B$9,C7+D6,0) | E10: =IF(E1=Inputs!$B$9,D7+E6,0) | F10: =IF(F1=Inputs!$B$9,E7+F6,0) | G10: =IF(G1=Inputs!$B$9,F7+G6,0) | H10: =IF(H1=Inputs!$B$9,G7+H6,0) | I10: =IF(I1=Inputs!$B$9,H7+I6,0) | J10: =IF(J1=Inputs!$B$9,I7+J6,0) | K10: =IF(K1=Inputs!$B$9,J7+K6,0)
A11: Unlevered cash flow | B11: =-B2-B3+B8+B9 | C11: =-C2-C3+C8+C9 | D11: =-D2-D3+D8+D9 | E11: =-E2-E3+E8+E9 | F11: =-F2-F3+F8+F9 | G11: =-G2-G3+G8+G9 | H11: =-H2-H3+H8+H9 | I11: =-I2-I3+I8+I9 | ... K11: =-K2-K3+K8+K9
A12: Equity cash flow | B12: =-B5+B6+B8-IF(B1>3,B4,0)+B9-B10 | C12: =-C5+C6+C8-IF(C1>3,C4,0)+C9-C10 | D12: =-D5+D6+D8-IF(D1>3,D4,0)+D9-D10 | E12: =-E5+E6+E8-IF(E1>3,E4,0)+E9-E10 | F12: =-F5+F6+F8-IF(F1>3,F4,0)+F9-F10 | G12: =-G5+G6+G8-IF(G1>3,G4,0)+G9-G10 | H12: =-H5+H6+H8-IF(H1>3,H4,0)+H9-H10 | I12: =-I5+I6+I8-IF(I1>3,I4,0)+I9-I10 | ... K12: =-K5+K6+K8-IF(K1>3,K4,0)+K9-K10
A13: LP contribution | B13: =MAX(0,-B12)*Inputs!$B$11 | C13: =MAX(0,-C12)*Inputs!$B$11 | D13: =MAX(0,-D12)*Inputs!$B$11 | E13: =MAX(0,-E12)*Inputs!$B$11 | F13: =MAX(0,-F12)*Inputs!$B$11 | G13: =MAX(0,-G12)*Inputs!$B$11 | H13: =MAX(0,-H12)*Inputs!$B$11 | I13: =MAX(0,-I12)*Inputs!$B$11 | ... K13: =MAX(0,-K12)*Inputs!$B$11
A14: GP contribution | B14: =MAX(0,-B12)*(1-Inputs!$B$11) | C14: =MAX(0,-C12)*(1-Inputs!$B$11) | D14: =MAX(0,-D12)*(1-Inputs!$B$11) | E14: =MAX(0,-E12)*(1-Inputs!$B$11) | F14: =MAX(0,-F12)*(1-Inputs!$B$11) | G14: =MAX(0,-G12)*(1-Inputs!$B$11) | H14: =MAX(0,-H12)*(1-Inputs!$B$11) | I14: =MAX(0,-I12)*(1-Inputs!$B$11) | ... K14: =MAX(0,-K12)*(1-Inputs!$B$11)
A15: Distributions | B15: =MAX(0,B12) | C15: =MAX(0,C12) | D15: =MAX(0,D12) | E15: =MAX(0,E12) | F15: =MAX(0,F12) | G15: =MAX(0,G12) | H15: =MAX(0,H12) | I15: =MAX(0,I12) | ... K15: =MAX(0,K12)
A16: Hurdle balance | B16: =0*(1+Inputs!$B$12)+B13-B17 | C16: =B16*(1+Inputs!$B$12)+C13-C17 | D16: =C16*(1+Inputs!$B$12)+D13-D17 | E16: =D16*(1+Inputs!$B$12)+E13-E17 | F16: =E16*(1+Inputs!$B$12)+F13-F17 | G16: =F16*(1+Inputs!$B$12)+G13-G17 | H16: =G16*(1+Inputs!$B$12)+H13-H17 | I16: =H16*(1+Inputs!$B$12)+I13-I17 | J16: =I16*(1+Inputs!$B$12)+J13-J17 | K16: =J16*(1+Inputs!$B$12)+K13-K17
A17: LP to pref | B17: =MIN(B15,MAX(0,0*(1+Inputs!$B$12)+B13)) | C17: =MIN(C15,MAX(0,B16*(1+Inputs!$B$12)+C13)) | D17: =MIN(D15,MAX(0,C16*(1+Inputs!$B$12)+D13)) | E17: =MIN(E15,MAX(0,D16*(1+Inputs!$B$12)+E13)) | F17: =MIN(F15,MAX(0,E16*(1+Inputs!$B$12)+F13)) | G17: =MIN(G15,MAX(0,F16*(1+Inputs!$B$12)+G13)) | H17: =MIN(H15,MAX(0,G16*(1+Inputs!$B$12)+H13)) | I17: =MIN(I15,MAX(0,H16*(1+Inputs!$B$12)+I13)) | J17: =MIN(J15,MAX(0,I16*(1+Inputs!$B$12)+J13)) | K17: =MIN(K15,MAX(0,J16*(1+Inputs!$B$12)+K13))
A18: Above the pref | B18: =B15-B17 | C18: =C15-C17 | D18: =D15-D17 | E18: =E15-E17 | F18: =F15-F17 | G18: =G15-G17 | H18: =H15-H17 | I18: =I15-I17 | ... K18: =K15-K17
A19: LP cash flow | B19: =-B13+B17+B18*Inputs!$B$13 | C19: =-C13+C17+C18*Inputs!$B$13 | D19: =-D13+D17+D18*Inputs!$B$13 | E19: =-E13+E17+E18*Inputs!$B$13 | F19: =-F13+F17+F18*Inputs!$B$13 | G19: =-G13+G17+G18*Inputs!$B$13 | H19: =-H13+H17+H18*Inputs!$B$13 | I19: =-I13+I17+I18*Inputs!$B$13 | ... K19: =-K13+K17+K18*Inputs!$B$13
A20: GP cash flow | B20: =-B14+B18*(1-Inputs!$B$13) | C20: =-C14+C18*(1-Inputs!$B$13) | D20: =-D14+D18*(1-Inputs!$B$13) | E20: =-E14+E18*(1-Inputs!$B$13) | F20: =-F14+F18*(1-Inputs!$B$13) | G20: =-G14+G18*(1-Inputs!$B$13) | H20: =-H14+H18*(1-Inputs!$B$13) | I20: =-I14+I18*(1-Inputs!$B$13) | ... K20: =-K14+K18*(1-Inputs!$B$13)

Sheet Returns
A1: Levered IRR | B1: =IRR('Cash Flow'!B12:K12)
A2: Unlevered IRR | B2: =IRR('Cash Flow'!B11:K11)
A3: LP IRR | B3: =IRR('Cash Flow'!B19:K19)
A4: GP IRR | B4: =IRR('Cash Flow'!B20:K20)
A5: Net profit | B5: =SUM('Cash Flow'!B12:K12)
A6: Peak debt | B6: =MAX('Cash Flow'!B7:K7)
A7: Equity multiple | B7: =SUMIF('Cash Flow'!B12:K12,">0")/-SUMIF('Cash Flow'!B12:K12,"<0")
A8: Waterfall tier reached | B8: =IF(SUM('Cash Flow'!B18:K18)>0,"Promote","Pref only")
