Workbook
Name EQCF: OFFSET(Monthly!$C$13,0,0,1,COUNT(Monthly!$C$2:$BJ$2))
Name UCF: OFFSET(Monthly!$C$8,0,0,1,COUNT(Monthly!$C$2:$BJ$2))

Sheet Inputs
A1: AL BAHR MIXED-USE – PHASED DEVELOPMENT (SAR '000)
A2: Case | B2: Base
A4: Scenario inputs | B4: Base | C4: Downside | D4: Upside | E4: Live
A5: Residential sale price per sqm | B5: 12 | C5: 10.8 | D5: 13 | E5: =INDEX(B5:D5,MATCH($B$2,$B$4:$D$4,0))
A6: Retail rent per sqm pa | B6: 1.2 | C6: 1 | D6: 1.3 | E6: =INDEX(B6:D6,MATCH($B$2,$B$4:$D$4,0))
A7: Construction cost per sqm | B7: 4.5 | C7: 4.9 | D7: 4.3 | E7: =INDEX(B7:D7,MATCH($B$2,$B$4:$D$4,0))
A8: Exit yield | B8: 0.07 | C8: 0.0775 | D8: 0.065 | E8: =INDEX(B8:D8,MATCH($B$2,$B$4:$D$4,0))
A10: Residential NSA (sqm) | B10: 30000
A11: Retail NLA (sqm) | B11: 8000
A12: GFA (sqm) | B12: 50000
A13: Land cost (SAR '000) | B13: 120000
A14: Construction start (month) | B14: 1
A15: Construction months | B15: 24
A16: Launch month | B16: 6
A17: Deposit share at launch | B17: 0.3
A18: Sales period (months after launch) | B18: 24
A19: Lease-up start (month) | B19: 25
A20: Lease-up months | B20: 12
A21: Hold (months) | B21: 60
... A24: Selling costs | B24: 0.02

Sheet Drivers
A1: Drivers (monthly)
A2: Month | C2: 1 | D2: 2 | E2: 3 | F2: 4 | G2: 5 | H2: 6 | I2: 7 | J2: 8 | K2: 9 | L2: 10 | M2: 11 | N2: 12 | O2: 13 | P2: 14 | Q2: 15 | R2: 16 | S2: 17 | T2: 18 | U2: 19 | V2: 20 | W2: 21 | X2: 22 | Y2: 23 | Z2: 24 | AA2: 25 | AB2: 26 | AC2: 27 | AD2: 28 | AE2: 29 | AF2: 30 | AG2: 31 | AH2: 32 | AI2: 33 | AJ2: 34 | AK2: 35 | AL2: 36 | AM2: 37 | AN2: 38 | AO2: 39 | AP2: 40 | AQ2: 41 | AR2: 42 | AS2: 43 | AT2: 44 | AU2: 45 | AV2: 46 | AW2: 47 | AX2: 48 | AY2: 49 | AZ2: 50 | BA2: 51 | BB2: 52 | BC2: 53 | BD2: 54 | BE2: 55 | BF2: 56 | BG2: 57 | BH2: 58 | BI2: 59 | BJ2: 60
A3: Construction S-curve weight | C3: =IF(AND(C$2>=Inputs!$B$14,C$2<Inputs!$B$14+Inputs!$B$15),SIN(PI()*(C$2-Inputs!$B$14+0.5)/Inputs!$B$15),0) | D3: =IF(AND(D$2>=Inputs!$B$14,D$2<Inputs!$B$14+Inputs!$B$15),SIN(PI()*(D$2-Inputs!$B$14+0.5)/Inputs!$B$15),0) | E3: =IF(AND(E$2>=Inputs!$B$14,E$2<Inputs!$B$14+Inputs!$B$15),SIN(PI()*(E$2-Inputs!$B$14+0.5)/Inputs!$B$15),0) | F3: =IF(AND(F$2>=Inputs!$B$14,F$2<Inputs!$B$14+Inputs!$B$15),SIN(PI()*(F$2-Inputs!$B$14+0.5)/Inputs!$B$15),0) | G3: =IF(AND(G$2>=Inputs!$B$14,G$2<Inputs!$B$14+Inputs!$B$15),SIN(PI()*(G$2-Inputs!$B$14+0.5)/Inputs!$B$15),0) | H3: =IF(AND(H$2>=Inputs!$B$14,H$2<Inputs!$B$14+Inputs!$B$15),SIN(PI()*(H$2-Inputs!$B$14+0.5)/Inputs!$B$15),0) | I3: =IF(AND(I$2>=Inputs!$B$14,I$2<Inputs!$B$14+Inputs!$B$15),SIN(PI()*(I$2-Inputs!$B$14+0.5)/Inputs!$B$15),0) | J3: =IF(AND(J$2>=Inputs!$B$14,J$2<Inputs!$B$14+Inputs!$B$15),SIN(PI()*(J$2-Inputs!$B$14+0.5)/Inputs!$B$15),0) | ... BJ3: =IF(AND(BJ$2>=Inputs!$B$14,BJ$2<Inputs!$B$14+Inputs!$B$15),SIN(PI()*(BJ$2-Inputs!$B$14+0.5)/Inputs!$B$15),0)
A4: Construction share | C4: =C3/SUM($C$3:$BJ$3) | D4: =D3/SUM($C$3:$BJ$3) | E4: =E3/SUM($C$3:$BJ$3) | F4: =F3/SUM($C$3:$BJ$3) | G4: =G3/SUM($C$3:$BJ$3) | H4: =H3/SUM($C$3:$BJ$3) | I4: =I3/SUM($C$3:$BJ$3) | J4: =J3/SUM($C$3:$BJ$3) | ... BJ4: =BJ3/SUM($C$3:$BJ$3)
A5: Sales share | C5: =IF(C$2=Inputs!$B$16,Inputs!$B$17,IF(AND(C$2>Inputs!$B$16,C$2<=Inputs!$B$16+Inputs!$B$18),(1-Inputs!$B$17)/Inputs!$B$18,0)) | D5: =IF(D$2=Inputs!$B$16,Inputs!$B$17,IF(AND(D$2>Inputs!$B$16,D$2<=Inputs!$B$16+Inputs!$B$18),(1-Inputs!$B$17)/Inputs!$B$18,0)) | E5: =IF(E$2=Inputs!$B$16,Inputs!$B$17,IF(AND(E$2>Inputs!$B$16,E$2<=Inputs!$B$16+Inputs!$B$18),(1-Inputs!$B$17)/Inputs!$B$18,0)) | F5: =IF(F$2=Inputs!$B$16,Inputs!$B$17,IF(AND(F$2>Inputs!$B$16,F$2<=Inputs!$B$16+Inputs!$B$18),(1-Inputs!$B$17)/Inputs!$B$18,0)) | G5: =IF(G$2=Inputs!$B$16,Inputs!$B$17,IF(AND(G$2>Inputs!$B$16,G$2<=Inputs!$B$16+Inputs!$B$18),(1-Inputs!$B$17)/Inputs!$B$18,0)) | H5: =IF(H$2=Inputs!$B$16,Inputs!$B$17,IF(AND(H$2>Inputs!$B$16,H$2<=Inputs!$B$16+Inputs!$B$18),(1-Inputs!$B$17)/Inputs!$B$18,0)) | I5: =IF(I$2=Inputs!$B$16,Inputs!$B$17,IF(AND(I$2>Inputs!$B$16,I$2<=Inputs!$B$16+Inputs!$B$18),(1-Inputs!$B$17)/Inputs!$B$18,0)) | J5: =IF(J$2=Inputs!$B$16,Inputs!$B$17,IF(AND(J$2>Inputs!$B$16,J$2<=Inputs!$B$16+Inputs!$B$18),(1-Inputs!$B$17)/Inputs!$B$18,0)) | ... BJ5: =IF(BJ$2=Inputs!$B$16,Inputs!$B$17,IF(AND(BJ$2>Inputs!$B$16,BJ$2<=Inputs!$B$16+Inputs!$B$18),(1-Inputs!$B$17)/Inputs!$B$18,0))
A6: Retail occupancy | C6: =IF(C$2<Inputs!$B$19,0,MIN(1,(C$2-Inputs!$B$19+1)/Inputs!$B$20)) | D6: =IF(D$2<Inputs!$B$19,0,MIN(1,(D$2-Inputs!$B$19+1)/Inputs!$B$20)) | E6: =IF(E$2<Inputs!$B$19,0,MIN(1,(E$2-Inputs!$B$19+1)/Inputs!$B$20)) | F6: =IF(F$2<Inputs!$B$19,0,MIN(1,(F$2-Inputs!$B$19+1)/Inputs!$B$20)) | G6: =IF(G$2<Inputs!$B$19,0,MIN(1,(G$2-Inputs!$B$19+1)/Inputs!$B$20)) | H6: =IF(H$2<Inputs!$B$19,0,MIN(1,(H$2-Inputs!$B$19+1)/Inputs!$B$20)) | I6: =IF(I$2<Inputs!$B$19,0,MIN(1,(I$2-Inputs!$B$19+1)/Inputs!$B$20)) | J6: =IF(J$2<Inputs!$B$19,0,MIN(1,(J$2-Inputs!$B$19+1)/Inputs!$B$20)) | ... BJ6: =IF(BJ$2<Inputs!$B$19,0,MIN(1,(BJ$2-Inputs!$B$19+1)/Inputs!$B$20))
A7: Year | C7: =INT((C$2-1)/12)+1 | D7: =INT((D$2-1)/12)+1 | E7: =INT((E$2-1)/12)+1 | F7: =INT((F$2-1)/12)+1 | G7: =INT((G$2-1)/12)+1 | H7: =INT((H$2-1)/12)+1 | I7: =INT((I$2-1)/12)+1 | J7: =INT((J$2-1)/12)+1 | ... BJ7: =INT((BJ$2-1)/12)+1

Sheet Monthly
A1: Monthly cash flow (SAR '000)
A2: Month | C2: =Drivers!C2 | D2: =Drivers!D2 | E2: =Drivers!E2 | F2: =Drivers!F2 | G2: =Drivers!G2 | H2: =Drivers!H2 | I2: =Drivers!I2 | J2: =Drivers!J2 | ... BJ2: =Drivers!BJ2
A3: Land | C3: =IF(C$2=1,Inputs!$B$13,0) | D3: =IF(D$2=1,Inputs!$B$13,0) | E3: =IF(E$2=1,Inputs!$B$13,0) | F3: =IF(F$2=1,Inputs!$B$13,0) | G3: =IF(G$2=1,Inputs!$B$13,0) | H3: =IF(H$2=1,Inputs!$B$13,0) | I3: =IF(I$2=1,Inputs!$B$13,0) | J3: =IF(J$2=1,Inputs!$B$13,0) | ... BJ3: =IF(BJ$2=1,Inputs!$B$13,0)
A4: Construction | C4: =Inputs!$E$7*Inputs!$B$12*Drivers!C4 | D4: =Inputs!$E$7*Inputs!$B$12*Drivers!D4 | E4: =Inputs!$E$7*Inputs!$B$12*Drivers!E4 | F4: =Inputs!$E$7*Inputs!$B$12*Drivers!F4 | G4: =Inputs!$E$7*Inputs!$B$12*Drivers!G4 | H4: =Inputs!$E$7*Inputs!$B$12*Drivers!H4 | I4: =Inputs!$E$7*Inputs!$B$12*Drivers!I4 | J4: =Inputs!$E$7*Inputs!$B$12*Drivers!J4 | ... BJ4: =Inputs!$E$7*Inputs!$B$12*Drivers!BJ4
A5: Residential sales | C5: =Inputs!$E$5*Inputs!$B$10*Drivers!C5 | D5: =Inputs!$E$5*Inputs!$B$10*Drivers!D5 | E5: =Inputs!$E$5*Inputs!$B$10*Drivers!E5 | F5: =Inputs!$E$5*Inputs!$B$10*Drivers!F5 | G5: =Inputs!$E$5*Inputs!$B$10*Drivers!G5 | H5: =Inputs!$E$5*Inputs!$B$10*Drivers!H5 | I5: =Inputs!$E$5*Inputs!$B$10*Drivers!I5 | J5: =Inputs!$E$5*Inputs!$B$10*Drivers!J5 | ... BJ5: =Inputs!$E$5*Inputs!$B$10*Drivers!BJ5
A6: Retail rent | C6: =IF(C$2<=Inputs!$B$21,Inputs!$E$6*Inputs!$B$11*Drivers!C6/12,0) | D6: =IF(D$2<=Inputs!$B$21,Inputs!$E$6*Inputs!$B$11*Drivers!D6/12,0) | E6: =IF(E$2<=Inputs!$B$21,Inputs!$E$6*Inputs!$B$11*Drivers!E6/12,0) | F6: =IF(F$2<=Inputs!$B$21,Inputs!$E$6*Inputs!$B$11*Drivers!F6/12,0) | G6: =IF(G$2<=Inputs!$B$21,Inputs!$E$6*Inputs!$B$11*Drivers!G6/12,0) | H6: =IF(H$2<=Inputs!$B$21,Inputs!$E$6*Inputs!$B$11*Drivers!H6/12,0) | I6: =IF(I$2<=Inputs!$B$21,Inputs!$E$6*Inputs!$B$11*Drivers!I6/12,0) | J6: =IF(J$2<=Inputs!$B$21,Inputs!$E$6*Inputs!$B$11*Drivers!J6/12,0) | ... BJ6: =IF(BJ$2<=Inputs!$B$21,Inputs!$E$6*Inputs!$B$11*Drivers!BJ6/12,0)
A7: Retail sale | C7: =IF(C$2=Inputs!$B$21,Inputs!$E$6*Inputs!$B$11/Inputs!$E$8*(1-Inputs!$B$24),0) | D7: =IF(D$2=Inputs!$B$21,Inputs!$E$6*Inputs!$B$11/Inputs!$E$8*(1-Inputs!$B$24),0) | E7: =IF(E$2=Inputs!$B$21,Inputs!$E$6*Inputs!$B$11/Inputs!$E$8*(1-Inputs!$B$24),0) | F7: =IF(F$2=Inputs!$B$21,Inputs!$E$6*Inputs!$B$11/Inputs!$E$8*(1-Inputs!$B$24),0) | G7: =IF(G$2=Inputs!$B$21,Inputs!$E$6*Inputs!$B$11/Inputs!$E$8*(1-Inputs!$B$24),0) | H7: =IF(H$2=Inputs!$B$21,Inputs!$E$6*Inputs!$B$11/Inputs!$E$8*(1-Inputs!$B$24),0) | I7: =IF(I$2=Inputs!$B$21,Inputs!$E$6*Inputs!$B$11/Inputs!$E$8*(1-Inputs!$B$24),0) | J7: =IF(J$2=Inputs!$B$21,Inputs!$E$6*Inputs!$B$11/Inputs!$E$8*(1-Inputs!$B$24),0) | ... BJ7: =IF(BJ$2=Inputs!$B$21,Inputs!$E$6*Inputs!$B$11/Inputs!$E$8*(1-Inputs!$B$24),0)
A8: Unlevered cash flow | C8: =-C3-C4+C5+C6+C7 | D8: =-D3-D4+D5+D6+D7 | E8: =-E3-E4+E5+E6+E7 | F8: =-F3-F4+F5+F6+F7 | G8: =-G3-G4+G5+G6+G7 | H8: =-H3-H4+H5+H6+H7 | I8: =-I3-I4+I5+I6+I7 | J8: =-J3-J4+J5+J6+J7 | ... BJ8: =-BJ3-BJ4+BJ5+BJ6+BJ7
A9: Loan draw | C9: =Inputs!$B$22*(C3+C4) | D9: =Inputs!$B$22*(D3+D4) | E9: =Inputs!$B$22*(E3+E4) | F9: =Inputs!$B$22*(F3+F4) | G9: =Inputs!$B$22*(G3+G4) | H9: =Inputs!$B$22*(H3+H4) | I9: =Inputs!$B$22*(I3+I4) | J9: =Inputs!$B$22*(J3+J4) | ... BJ9: =Inputs!$B$22*(BJ3+BJ4)
A10: Interest (capitalised) | C10: =Inputs!$B$23/12*0 | D10: =Inputs!$B$23/12*C12 | E10: =Inputs!$B$23/12*D12 | F10: =Inputs!$B$23/12*E12 | G10: =Inputs!$B$23/12*F12 | H10: =Inputs!$B$23/12*G12 | I10: =Inputs!$B$23/12*H12 | J10: =Inputs!$B$23/12*I12 | K10: =Inputs!$B$23/12*J12 | ... BI10: =Inputs!$B$23/12*BH12 | BJ10: 0
A11: Loan repayment | C11: =IF(C$2=Inputs!$B$21,0+C9+C10,MIN(0+C9+C10,C5+C6)) | D11: =IF(D$2=Inputs!$B$21,C12+D9+D10,MIN(C12+D9+D10,D5+D6)) | E11: =IF(E$2=Inputs!$B$21,D12+E9+E10,MIN(D12+E9+E10,E5+E6)) | F11: =IF(F$2=Inputs!$B$21,E12+F9+F10,MIN(E12+F9+F10,F5+F6)) | G11: =IF(G$2=Inputs!$B$21,F12+G9+G10,MIN(F12+G9+G10,G5+G6)) | H11: =IF(H$2=Inputs!$B$21,G12+H9+H10,MIN(G12+H9+H10,H5+H6)) | I11: =IF(I$2=Inputs!$B$21,H12+I9+I10,MIN(H12+I9+I10,I5+I6)) | J11: =IF(J$2=Inputs!$B$21,I12+J9+J10,MIN(I12+J9+J10,J5+J6)) | K11: =IF(K$2=Inputs!$B$21,J12+K9+K10,MIN(J12+K9+K10,K5+K6)) | ... BJ11: =IF(BJ$2=Inputs!$B$21,BI12+BJ9+BJ10,MIN(BI12+BJ9+BJ10,BJ5+BJ6))
A12: Loan balance | C12: =0+C9+C10-C11 | D12: =C12+D9+D10-D11 | E12: =D12+E9+E10-E11 | F12: =E12+F9+F10-F11 | G12: =F12+G9+G10-G11 | H12: =G12+H9+H10-H11 | I12: =H12+I9+I10-I11 | J12: =I12+J9+J10-J11 | K12: =J12+K9+K10-K11 | ... BJ12: =BI12+BJ9+BJ10-BJ11
A13: Equity cash flow | C13: =C8+C9-C11 | D13: =D8+D9-D11 | E13: =E8+E9-E11 | F13: =F8+F9-F11 | G13: =G8+G9-G11 | H13: =H8+H9-H11 | I13: =I8+I9-I11 | J13: =J8+J9-J11 | ... BJ13: =BJ8+BJ9-BJ11

Sheet Annual
A1: Annual roll-up (SAR '000)
A2: Year | C2: 1 | D2: 2 | E2: 3 | F2: 4 | G2: 5
A3: Unlevered cash flow | C3: =SUMIF(Drivers!$C$7:$BJ$7,C$2,Monthly!$C$8:$BJ$8) | D3: =SUMIF(Drivers!$C$7:$BJ$7,D$2,Monthly!$C$8:$BJ$8) | E3: =SUMIF(Drivers!$C$7:$BJ$7,E$2,Monthly!$C$8:$BJ$8) | F3: =SUMIF(Drivers!$C$7:$BJ$7,F$2,Monthly!$C$8:$BJ$8) | G3: =SUMIF(Drivers!$C$7:$BJ$7,G$2,Monthly!$C$8:$BJ$8)
A4: Equity cash flow | C4: =SUMIF(Drivers!$C$7:$BJ$7,C$2,Monthly!$C$13:$BJ$13) | D4: =SUMIF(Drivers!$C$7:$BJ$7,D$2,Monthly!$C$13:$BJ$13) | E4: =SUMIF(Drivers!$C$7:$BJ$7,E$2,Monthly!$C$13:$BJ$13) | F4: =SUMIF(Drivers!$C$7:$BJ$7,F$2,Monthly!$C$13:$BJ$13) | G4: =SUMIF(Drivers!$C$7:$BJ$7,G$2,Monthly!$C$13:$BJ$13)
A5: Residential sales | C5: =SUMIF(Drivers!$C$7:$BJ$7,C$2,Monthly!$C$5:$BJ$5) | D5: =SUMIF(Drivers!$C$7:$BJ$7,D$2,Monthly!$C$5:$BJ$5) | E5: =SUMIF(Drivers!$C$7:$BJ$7,E$2,Monthly!$C$5:$BJ$5) | F5: =SUMIF(Drivers!$C$7:$BJ$7,F$2,Monthly!$C$5:$BJ$5) | G5: =SUMIF(Drivers!$C$7:$BJ$7,G$2,Monthly!$C$5:$BJ$5)
A6: Interest (capitalised) | C6: =SUMIF(Drivers!$C$7:$BJ$7,C$2,Monthly!$C$10:$BJ$10) | D6: =SUMIF(Drivers!$C$7:$BJ$7,D$2,Monthly!$C$10:$BJ$10) | E6: =SUMIF(Drivers!$C$7:$BJ$7,E$2,Monthly!$C$10:$BJ$10) | F6: =SUMIF(Drivers!$C$7:$BJ$7,F$2,Monthly!$C$10:$BJ$10) | G6: =SUMIF(Drivers!$C$7:$BJ$7,G$2,Monthly!$C$10:$BJ$10)
A7: Loan balance (year end) | C7: =INDEX(Monthly!$C$12:$BJ$12,1,C$2*12) | D7: =INDEX(Monthly!$C$12:$BJ$12,1,D$2*12) | E7: =INDEX(Monthly!$C$12:$BJ$12,1,E$2*12) | F7: =INDEX(Monthly!$C$12:$BJ$12,1,F$2*12) | G7: =INDEX(Monthly!$C$12:$BJ$12,1,G$2*12)

Sheet Returns
A1: Returns (SAR '000)
A2: Levered IRR | B2: =(1+IRR(EQCF,0.02))^12-1
A3: Unlevered IRR | B3: =(1+IRR(UCF))^12-1
A4: Net profit | B4: =SUM(Monthly!C13:BJ13)
A5: Total development cost | B5: =SUM(Monthly!C3:BJ3)+SUM(Monthly!C4:BJ4)+SUM(Monthly!C10:BJ10)
A6: Profit on cost | B6: =B4/B5
A7: Peak debt | B7: =MAX(Monthly!C12:BJ12)
A8: Case run | B8: =Inputs!B2
