Workbook

Sheet Fund
A1: GULF VALUE-ADD FUND II (USD m)
A2: Quarter | C2: 1 | D2: 2 | E2: 3 | F2: 4 | G2: 5 | H2: 6 | I2: 7 | J2: 8 | K2: 9 | L2: 10 | M2: 11 | N2: 12 | O2: 13 | P2: 14 | Q2: 15 | R2: 16
A3: Date | C3: =EDATE(Inputs!$B$2,3*(C2-1)) | D3: =EDATE(Inputs!$B$2,3*(D2-1)) | E3: =EDATE(Inputs!$B$2,3*(E2-1)) | F3: =EDATE(Inputs!$B$2,3*(F2-1)) | G3: =EDATE(Inputs!$B$2,3*(G2-1)) | H3: =EDATE(Inputs!$B$2,3*(H2-1)) | I3: =EDATE(Inputs!$B$2,3*(I2-1)) | J3: =EDATE(Inputs!$B$2,3*(J2-1)) | ... R3: =EDATE(Inputs!$B$2,3*(R2-1))
A5: Deal | B5: Currency
A6: Riyadh Office | B6: =INDIRECT("'"&$A6&"'!$B$3") | C6: =INDEX(INDIRECT("'"&$A6&"'!$C$22:$R$22"),1,C$2) | D6: =INDEX(INDIRECT("'"&$A6&"'!$C$22:$R$22"),1,D$2) | E6: =INDEX(INDIRECT("'"&$A6&"'!$C$22:$R$22"),1,E$2) | F6: =INDEX(INDIRECT("'"&$A6&"'!$C$22:$R$22"),1,F$2) | G6: =INDEX(INDIRECT("'"&$A6&"'!$C$22:$R$22"),1,G$2) | H6: =INDEX(INDIRECT("'"&$A6&"'!$C$22:$R$22"),1,H$2) | I6: =INDEX(INDIRECT("'"&$A6&"'!$C$22:$R$22"),1,I$2) | J6: =INDEX(INDIRECT("'"&$A6&"'!$C$22:$R$22"),1,J$2) | ... R6: =INDEX(INDIRECT("'"&$A6&"'!$C$22:$R$22"),1,R$2)
A7: Jeddah Logistics | B7: =INDIRECT("'"&$A7&"'!$B$3") | C7: =INDEX(INDIRECT("'"&$A7&"'!$C$22:$R$22"),1,C$2) | D7: =INDEX(INDIRECT("'"&$A7&"'!$C$22:$R$22"),1,D$2) | E7: =INDEX(INDIRECT("'"&$A7&"'!$C$22:$R$22"),1,E$2) | F7: =INDEX(INDIRECT("'"&$A7&"'!$C$22:$R$22"),1,F$2) | G7: =INDEX(INDIRECT("'"&$A7&"'!$C$22:$R$22"),1,G$2) | H7: =INDEX(INDIRECT("'"&$A7&"'!$C$22:$R$22"),1,H$2) | I7: =INDEX(INDIRECT("'"&$A7&"'!$C$22:$R$22"),1,I$2) | J7: =INDEX(INDIRECT("'"&$A7&"'!$C$22:$R$22"),1,J$2) | ... R7: =INDEX(INDIRECT("'"&$A7&"'!$C$22:$R$22"),1,R$2)
A8: Dubai Residential | B8: =INDIRECT("'"&$A8&"'!$B$3") | C8: =INDEX(INDIRECT("'"&$A8&"'!$C$22:$R$22"),1,C$2) | D8: =INDEX(INDIRECT("'"&$A8&"'!$C$22:$R$22"),1,D$2) | E8: =INDEX(INDIRECT("'"&$A8&"'!$C$22:$R$22"),1,E$2) | F8: =INDEX(INDIRECT("'"&$A8&"'!$C$22:$R$22"),1,F$2) | G8: =INDEX(INDIRECT("'"&$A8&"'!$C$22:$R$22"),1,G$2) | H8: =INDEX(INDIRECT("'"&$A8&"'!$C$22:$R$22"),1,H$2) | I8: =INDEX(INDIRECT("'"&$A8&"'!$C$22:$R$22"),1,I$2) | J8: =INDEX(INDIRECT("'"&$A8&"'!$C$22:$R$22"),1,J$2) | ... R8: =INDEX(INDIRECT("'"&$A8&"'!$C$22:$R$22"),1,R$2)
A10: Gross cash flow (USD m) | C10: =SUM(C6:C8) | D10: =SUM(D6:D8) | E10: =SUM(E6:E8) | F10: =SUM(F6:F8) | G10: =SUM(G6:G8) | H10: =SUM(H6:H8) | I10: =SUM(I6:I8) | J10: =SUM(J6:J8) | ... R10: =SUM(R6:R8)
A11: Management fee | C11: =Inputs!$B$3*Inputs!$B$4/4 | D11: =Inputs!$B$3*Inputs!$B$4/4 | E11: =Inputs!$B$3*Inputs!$B$4/4 | F11: =Inputs!$B$3*Inputs!$B$4/4 | G11: =Inputs!$B$3*Inputs!$B$4/4 | H11: =Inputs!$B$3*Inputs!$B$4/4 | I11: =Inputs!$B$3*Inputs!$B$4/4 | J11: =Inputs!$B$3*Inputs!$B$4/4 | ... R11: =Inputs!$B$3*Inputs!$B$4/4
A12: Net cash flow | C12: =C10-C11 | D12: =D10-D11 | E12: =E10-E11 | F12: =F10-F11 | G12: =G10-G11 | H12: =H10-H11 | I12: =I10-I11 | J12: =J10-J11 | ... R12: =R10-R11
A13: LP contribution | C13: =MAX(0,-C12) | D13: =MAX(0,-D12) | E13: =MAX(0,-E12) | F13: =MAX(0,-F12) | G13: =MAX(0,-G12) | H13: =MAX(0,-H12) | I13: =MAX(0,-I12) | J13: =MAX(0,-J12) | ... R13: =MAX(0,-R12)
A14: Distributable | C14: =MAX(0,C12) | D14: =MAX(0,D12) | E14: =MAX(0,E12) | F14: =MAX(0,F12) | G14: =MAX(0,G12) | H14: =MAX(0,H12) | I14: =MAX(0,I12) | J14: =MAX(0,J12) | ... R14: =MAX(0,R12)
A15: Hurdle balance | C15: =0*(1+Inputs!$B$5)^(1/4)+C13-C16 | D15: =C15*(1+Inputs!$B$5)^(1/4)+D13-D16 | E15: =D15*(1+Inputs!$B$5)^(1/4)+E13-E16 | F15: =E15*(1+Inputs!$B$5)^(1/4)+F13-F16 | G15: =F15*(1+Inputs!$B$5)^(1/4)+G13-G16 | H15: =G15*(1+Inputs!$B$5)^(1/4)+H13-H16 | I15: =H15*(1+Inputs!$B$5)^(1/4)+I13-I16 | J15: =I15*(1+Inputs!$B$5)^(1/4)+J13-J16 | K15: =J15*(1+Inputs!$B$5)^(1/4)+K13-K16 | ... R15: =Q15*(1+Inputs!$B$5)^(1/4)+R13-R16
A16: LP preferred return | C16: =MIN(C14,0*(1+Inputs!$B$5)^(1/4)+C13) | D16: =MIN(D14,C15*(1+Inputs!$B$5)^(1/4)+D13) | E16: =MIN(E14,D15*(1+Inputs!$B$5)^(1/4)+E13) | F16: =MIN(F14,E15*(1+Inputs!$B$5)^(1/4)+F13) | G16: =MIN(G14,F15*(1+Inputs!$B$5)^(1/4)+G13) | H16: =MIN(H14,G15*(1+Inputs!$B$5)^(1/4)+H13) | I16: =MIN(I14,H15*(1+Inputs!$B$5)^(1/4)+I13) | J16: =MIN(J14,I15*(1+Inputs!$B$5)^(1/4)+J13) | K16: =MIN(K14,J15*(1+Inputs!$B$5)^(1/4)+K13) | ... R16: =MIN(R14,Q15*(1+Inputs!$B$5)^(1/4)+R13)
A17: Cumulative pref paid | C17: =0+C16 | D17: =C17+D16 | E17: =D17+E16 | F17: =E17+F16 | G17: =F17+G16 | H17: =G17+H16 | I17: =H17+I16 | J17: =I17+J16 | K17: =J17+K16 | ... R17: =Q17+R16
A18: GP catch-up | C18: =MIN(C14-C16,MAX(0,Inputs!$B$6/(1-Inputs!$B$6)*C17-0)) | D18: =MIN(D14-D16,MAX(0,Inputs!$B$6/(1-Inputs!$B$6)*D17-C19)) | E18: =MIN(E14-E16,MAX(0,Inputs!$B$6/(1-Inputs!$B$6)*E17-D19)) | F18: =MIN(F14-F16,MAX(0,Inputs!$B$6/(1-Inputs!$B$6)*F17-E19)) | G18: =MIN(G14-G16,MAX(0,Inputs!$B$6/(1-Inputs!$B$6)*G17-F19)) | H18: =MIN(H14-H16,MAX(0,Inputs!$B$6/(1-Inputs!$B$6)*H17-G19)) | I18: =MIN(I14-I16,MAX(0,Inputs!$B$6/(1-Inputs!$B$6)*I17-H19)) | J18: =MIN(J14-J16,MAX(0,Inputs!$B$6/(1-Inputs!$B$6)*J17-I19)) | K18: =MIN(K14-K16,MAX(0,Inputs!$B$6/(1-Inputs!$B$6)*K17-J19)) | ... R18: =MIN(R14-R16,MAX(0,Inputs!$B$6/(1-Inputs!$B$6)*R17-Q19))
A19: Cumulative catch-up | C19: =0+C18 | D19: =C19+D18 | E19: =D19+E18 | F19: =E19+F18 | G19: =F19+G18 | H19: =G19+H18 | I19: =H19+I18 | J19: =I19+J18 | K19: =J19+K18 | ... R19: =Q19+R18
A20: Residual | C20: =C14-C16-C18 | D20: =D14-D16-D18 | E20: =E14-E16-E18 | F20: =F14-F16-F18 | G20: =G14-G16-G18 | H20: =H14-H16-H18 | I20: =I14-I16-I18 | J20: =J14-J16-J18 | ... R20: =R14-R16-R18
A21: LP net cash flow | C21: =-C13+C16+(1-Inputs!$B$6)*C20 | D21: =-D13+D16+(1-Inputs!$B$6)*D20 | E21: =-E13+E16+(1-Inputs!$B$6)*E20 | F21: =-F13+F16+(1-Inputs!$B$6)*F20 | G21: =-G13+G16+(1-Inputs!$B$6)*G20 | H21: =-H13+H16+(1-Inputs!$B$6)*H20 | I21: =-I13+I16+(1-Inputs!$B$6)*I20 | J21: =-J13+J16+(1-Inputs!$B$6)*J20 | ... R21: =-R13+R16+(1-Inputs!$B$6)*R20
A22: GP carry | C22: =C18+Inputs!$B$6*C20 | D22: =D18+Inputs!$B$6*D20 | E22: =E18+Inputs!$B$6*E20 | F22: =F18+Inputs!$B$6*F20 | G22: =G18+Inputs!$B$6*G20 | H22: =H18+Inputs!$B$6*H20 | I22: =I18+Inputs!$B$6*I20 | J22: =J18+Inputs!$B$6*J20 | ... R22: =R18+Inputs!$B$6*R20

Sheet Inputs
A1: GULF VALUE-ADD FUND II – FUND TERMS (USD m)
A2: First quarter end | B2: 46112
A3: Committed capital (USD m) | B3: 250
A4: Management fee (pa, on committed) | B4: 0.015
A5: Preferred return | B5: 0.08
A6: Carried interest | B6: 0.2

Sheet FX
A1: Currency | B1: Per USD
A2: USD | B2: 1
A3: SAR | B3: 3.75
A4: AED | B4: 3.6725

Sheet Riyadh Office
A1: Riyadh Office – deal cash flow (SAR m)
A2: Deal | B2: Riyadh Office
A3: Currency | B3: SAR
A4: Purchase price (m) | B4: 300
A5: Acquisition quarter | B5: 1
A6: NOI yield on cost | B6: 0.075
A7: Capex (share of price, over 4 quarters) | B7: 0.1
A8: Exit quarter | B8: 12
A9: Exit yield | B9: 0.065
A10: Rent growth pa | B10: 0.03
A11: Selling costs | B11: 0.015
A12: FX per USD | B12: =VLOOKUP(B3,FX!$A$2:$B$4,2,FALSE)
A14: Quarter | C14: =Fund!C2 | D14: =Fund!D2 | E14: =Fund!E2 | F14: =Fund!F2 | G14: =Fund!G2 | H14: =Fund!H2 | I14: =Fund!I2 | J14: =Fund!J2 | ... R14: =Fund!R2
A15: Purchase | C15: =IF(C$14=$B$5,-$B$4,0) | D15: =IF(D$14=$B$5,-$B$4,0) | E15: =IF(E$14=$B$5,-$B$4,0) | F15: =IF(F$14=$B$5,-$B$4,0) | G15: =IF(G$14=$B$5,-$B$4,0) | H15: =IF(H$14=$B$5,-$B$4,0) | I15: =IF(I$14=$B$5,-$B$4,0) | J15: =IF(J$14=$B$5,-$B$4,0) | ... R15: =IF(R$14=$B$5,-$B$4,0)
A16: Capex | C16: =IF(AND(C$14>$B$5,C$14<=$B$5+4),-$B$4*$B$7/4,0) | D16: =IF(AND(D$14>$B$5,D$14<=$B$5+4),-$B$4*$B$7/4,0) | E16: =IF(AND(E$14>$B$5,E$14<=$B$5+4),-$B$4*$B$7/4,0) | F16: =IF(AND(F$14>$B$5,F$14<=$B$5+4),-$B$4*$B$7/4,0) | G16: =IF(AND(G$14>$B$5,G$14<=$B$5+4),-$B$4*$B$7/4,0) | H16: =IF(AND(H$14>$B$5,H$14<=$B$5+4),-$B$4*$B$7/4,0) | I16: =IF(AND(I$14>$B$5,I$14<=$B$5+4),-$B$4*$B$7/4,0) | J16: =IF(AND(J$14>$B$5,J$14<=$B$5+4),-$B$4*$B$7/4,0) | ... R16: =IF(AND(R$14>$B$5,R$14<=$B$5+4),-$B$4*$B$7/4,0)
A17: NOI | C17: =IF(AND(C$14>$B$5,C$14<=$B$8),$B$4*$B$6/4*(1+$B$10)^INT((C$14-$B$5-1)/4),0) | D17: =IF(AND(D$14>$B$5,D$14<=$B$8),$B$4*$B$6/4*(1+$B$10)^INT((D$14-$B$5-1)/4),0) | E17: =IF(AND(E$14>$B$5,E$14<=$B$8),$B$4*$B$6/4*(1+$B$10)^INT((E$14-$B$5-1)/4),0) | F17: =IF(AND(F$14>$B$5,F$14<=$B$8),$B$4*$B$6/4*(1+$B$10)^INT((F$14-$B$5-1)/4),0) | G17: =IF(AND(G$14>$B$5,G$14<=$B$8),$B$4*$B$6/4*(1+$B$10)^INT((G$14-$B$5-1)/4),0) | H17: =IF(AND(H$14>$B$5,H$14<=$B$8),$B$4*$B$6/4*(1+$B$10)^INT((H$14-$B$5-1)/4),0) | I17: =IF(AND(I$14>$B$5,I$14<=$B$8),$B$4*$B$6/4*(1+$B$10)^INT((I$14-$B$5-1)/4),0) | J17: =IF(AND(J$14>$B$5,J$14<=$B$8),$B$4*$B$6/4*(1+$B$10)^INT((J$14-$B$5-1)/4),0) | ... R17: =IF(AND(R$14>$B$5,R$14<=$B$8),$B$4*$B$6/4*(1+$B$10)^INT((R$14-$B$5-1)/4),0)
A18: Sale proceeds | C18: =IF(C$14=$B$8,$B$4*$B$6*(1+$B$10)^INT((C$14-$B$5-1)/4)/$B$9*(1-$B$11),0) | D18: =IF(D$14=$B$8,$B$4*$B$6*(1+$B$10)^INT((D$14-$B$5-1)/4)/$B$9*(1-$B$11),0) | E18: =IF(E$14=$B$8,$B$4*$B$6*(1+$B$10)^INT((E$14-$B$5-1)/4)/$B$9*(1-$B$11),0) | F18: =IF(F$14=$B$8,$B$4*$B$6*(1+$B$10)^INT((F$14-$B$5-1)/4)/$B$9*(1-$B$11),0) | G18: =IF(G$14=$B$8,$B$4*$B$6*(1+$B$10)^INT((G$14-$B$5-1)/4)/$B$9*(1-$B$11),0) | H18: =IF(H$14=$B$8,$B$4*$B$6*(1+$B$10)^INT((H$14-$B$5-1)/4)/$B$9*(1-$B$11),0) | I18: =IF(I$14=$B$8,$B$4*$B$6*(1+$B$10)^INT((I$14-$B$5-1)/4)/$B$9*(1-$B$11),0) | J18: =IF(J$14=$B$8,$B$4*$B$6*(1+$B$10)^INT((J$14-$B$5-1)/4)/$B$9*(1-$B$11),0) | ... R18: =IF(R$14=$B$8,$B$4*$B$6*(1+$B$10)^INT((R$14-$B$5-1)/4)/$B$9*(1-$B$11),0)
A20: Net cash flow (SAR m) | C20: =SUM(C15:C18) | D20: =SUM(D15:D18) | E20: =SUM(E15:E18) | F20: =SUM(F15:F18) | G20: =SUM(G15:G18) | H20: =SUM(H15:H18) | I20: =SUM(I15:I18) | J20: =SUM(J15:J18) | ... R20: =SUM(R15:R18)
A22: Net cash flow (USD m) | C22: =C20/$B$12 | D22: =D20/$B$12 | E22: =E20/$B$12 | F22: =F20/$B$12 | G22: =G20/$B$12 | H22: =H20/$B$12 | I22: =I20/$B$12 | J22: =J20/$B$12 | ... R22: =R20/$B$12

Sheet Jeddah Logistics
A1: Jeddah Logistics – deal cash flow (SAR m)
A2: Deal | B2: Jeddah Logistics
A3: Currency | B3: SAR
A4: Purchase price (m) | B4: 180
A5: Acquisition quarter | B5: 1
A6: NOI yield on cost | B6: 0.08
A7: Capex (share of price, over 4 quarters) | B7: 0.1
A8: Exit quarter | B8: 14
A9: Exit yield | B9: 0.07
A10: Rent growth pa | B10: 0.04
A11: Selling costs | B11: 0.015
A12: FX per USD | B12: =VLOOKUP(B3,FX!$A$2:$B$4,2,FALSE)
A14: Quarter | C14: =Fund!C2 | D14: =Fund!D2 | E14: =Fund!E2 | F14: =Fund!F2 | G14: =Fund!G2 | H14: =Fund!H2 | I14: =Fund!I2 | J14: =Fund!J2 | ... R14: =Fund!R2
A15: Purchase | C15: =IF(C$14=$B$5,-$B$4,0) | D15: =IF(D$14=$B$5,-$B$4,0) | E15: =IF(E$14=$B$5,-$B$4,0) | F15: =IF(F$14=$B$5,-$B$4,0) | G15: =IF(G$14=$B$5,-$B$4,0) | H15: =IF(H$14=$B$5,-$B$4,0) | I15: =IF(I$14=$B$5,-$B$4,0) | J15: =IF(J$14=$B$5,-$B$4,0) | ... R15: =IF(R$14=$B$5,-$B$4,0)
A16: Capex | C16: =IF(AND(C$14>$B$5,C$14<=$B$5+4),-$B$4*$B$7/4,0) | D16: =IF(AND(D$14>$B$5,D$14<=$B$5+4),-$B$4*$B$7/4,0) | E16: =IF(AND(E$14>$B$5,E$14<=$B$5+4),-$B$4*$B$7/4,0) | F16: =IF(AND(F$14>$B$5,F$14<=$B$5+4),-$B$4*$B$7/4,0) | G16: =IF(AND(G$14>$B$5,G$14<=$B$5+4),-$B$4*$B$7/4,0) | H16: =IF(AND(H$14>$B$5,H$14<=$B$5+4),-$B$4*$B$7/4,0) | I16: =IF(AND(I$14>$B$5,I$14<=$B$5+4),-$B$4*$B$7/4,0) | J16: =IF(AND(J$14>$B$5,J$14<=$B$5+4),-$B$4*$B$7/4,0) | ... R16: =IF(AND(R$14>$B$5,R$14<=$B$5+4),-$B$4*$B$7/4,0)
A17: NOI | C17: =IF(AND(C$14>$B$5,C$14<=$B$8),$B$4*$B$6/4*(1+$B$10)^INT((C$14-$B$5-1)/4),0) | D17: =IF(AND(D$14>$B$5,D$14<=$B$8),$B$4*$B$6/4*(1+$B$10)^INT((D$14-$B$5-1)/4),0) | E17: =IF(AND(E$14>$B$5,E$14<=$B$8),$B$4*$B$6/4*(1+$B$10)^INT((E$14-$B$5-1)/4),0) | F17: =IF(AND(F$14>$B$5,F$14<=$B$8),$B$4*$B$6/4*(1+$B$10)^INT((F$14-$B$5-1)/4),0) | G17: =IF(AND(G$14>$B$5,G$14<=$B$8),$B$4*$B$6/4*(1+$B$10)^INT((G$14-$B$5-1)/4),0) | H17: =IF(AND(H$14>$B$5,H$14<=$B$8),$B$4*$B$6/4*(1+$B$10)^INT((H$14-$B$5-1)/4),0) | I17: =IF(AND(I$14>$B$5,I$14<=$B$8),$B$4*$B$6/4*(1+$B$10)^INT((I$14-$B$5-1)/4),0) | J17: =IF(AND(J$14>$B$5,J$14<=$B$8),$B$4*$B$6/4*(1+$B$10)^INT((J$14-$B$5-1)/4),0) | ... R17: =IF(AND(R$14>$B$5,R$14<=$B$8),$B$4*$B$6/4*(1+$B$10)^INT((R$14-$B$5-1)/4),0)
A18: Sale proceeds | C18: =IF(C$14=$B$8,$B$4*$B$6*(1+$B$10)^INT((C$14-$B$5-1)/4)/'Riyadh Office'!$B$9*(1-$B$11),0) | D18: =IF(D$14=$B$8,$B$4*$B$6*(1+$B$10)^INT((D$14-$B$5-1)/4)/'Riyadh Office'!$B$9*(1-$B$11),0) | E18: =IF(E$14=$B$8,$B$4*$B$6*(1+$B$10)^INT((E$14-$B$5-1)/4)/'Riyadh Office'!$B$9*(1-$B$11),0) | F18: =IF(F$14=$B$8,$B$4*$B$6*(1+$B$10)^INT((F$14-$B$5-1)/4)/'Riyadh Office'!$B$9*(1-$B$11),0) | G18: =IF(G$14=$B$8,$B$4*$B$6*(1+$B$10)^INT((G$14-$B$5-1)/4)/'Riyadh Office'!$B$9*(1-$B$11),0) | H18: =IF(H$14=$B$8,$B$4*$B$6*(1+$B$10)^INT((H$14-$B$5-1)/4)/'Riyadh Office'!$B$9*(1-$B$11),0) | I18: =IF(I$14=$B$8,$B$4*$B$6*(1+$B$10)^INT((I$14-$B$5-1)/4)/'Riyadh Office'!$B$9*(1-$B$11),0) | J18: =IF(J$14=$B$8,$B$4*$B$6*(1+$B$10)^INT((J$14-$B$5-1)/4)/'Riyadh Office'!$B$9*(1-$B$11),0) | ... R18: =IF(R$14=$B$8,$B$4*$B$6*(1+$B$10)^INT((R$14-$B$5-1)/4)/'Riyadh Office'!$B$9*(1-$B$11),0)
A20: Net cash flow (SAR m) | C20: =SUM(C15:C18) | D20: =SUM(D15:D18) | E20: =SUM(E15:E18) | F20: =SUM(F15:F18) | G20: =SUM(G15:G18) | H20: =SUM(H15:H18) | I20: =SUM(I15:I18) | J20: =SUM(J15:J18) | ... R20: =SUM(R15:R18)
A22: Net cash flow (USD m) | C22: =C20/$B$12 | D22: =D20/$B$12 | E22: =E20/$B$12 | F22: =F20/$B$12 | G22: =G20/$B$12 | H22: =H20/$B$12 | I22: =I20/$B$12 | J22: =J20/$B$12 | ... R22: =R20/$B$12

Sheet Dubai Residential
A1: Dubai Residential – deal cash flow (AED m)
A2: Deal | B2: Dubai Residential
A3: Currency | B3: AED
A4: Purchase price (m) | B4: 220
A5: Acquisition quarter | B5: 3
A6: NOI yield on cost | B6: 0.065
A7: Capex (share of price, over 4 quarters) | B7: 0.1
A8: Exit quarter | B8: 14
A9: Exit yield | B9: 0.06
A10: Rent growth pa | B10: 0.02
A11: Selling costs | B11: 0.015
A12: FX per USD | B12: =VLOOKUP(B3,FX!$A$2:$B$4,2,FALSE)
A14: Quarter | C14: =Fund!C2 | D14: =Fund!D2 | E14: =Fund!E2 | F14: =Fund!F2 | G14: =Fund!G2 | H14: =Fund!H2 | I14: =Fund!I2 | J14: =Fund!J2 | ... R14: =Fund!R2
A15: Purchase | C15: =IF(C$14=$B$5,-$B$4,0) | D15: =IF(D$14=$B$5,-$B$4,0) | E15: =IF(E$14=$B$5,-$B$4,0) | F15: =IF(F$14=$B$5,-$B$4,0) | G15: =IF(G$14=$B$5,-$B$4,0) | H15: =IF(H$14=$B$5,-$B$4,0) | I15: =IF(I$14=$B$5,-$B$4,0) | J15: =IF(J$14=$B$5,-$B$4,0) | ... R15: =IF(R$14=$B$5,-$B$4,0)
A16: Capex | C16: =IF(AND(C$14>$B$5,C$14<=$B$5+4),-$B$4*$B$7/4,0) | D16: =IF(AND(D$14>$B$5,D$14<=$B$5+4),-$B$4*$B$7/4,0) | E16: =IF(AND(E$14>$B$5,E$14<=$B$5+4),-$B$4*$B$7/4,0) | F16: =IF(AND(F$14>$B$5,F$14<=$B$5+4),-$B$4*$B$7/4,0) | G16: =IF(AND(G$14>$B$5,G$14<=$B$5+4),-$B$4*$B$7/4,0) | H16: =IF(AND(H$14>$B$5,H$14<=$B$5+4),-$B$4*$B$7/4,0) | I16: =IF(AND(I$14>$B$5,I$14<=$B$5+4),-$B$4*$B$7/4,0) | J16: =IF(AND(J$14>$B$5,J$14<=$B$5+4),-$B$4*$B$7/4,0) | ... R16: =IF(AND(R$14>$B$5,R$14<=$B$5+4),-$B$4*$B$7/4,0)
A17: NOI | C17: =IF(AND(C$14>$B$5,C$14<=$B$8),$B$4*$B$6/4*(1+$B$10)^INT((C$14-$B$5-1)/4),0) | D17: =IF(AND(D$14>$B$5,D$14<=$B$8),$B$4*$B$6/4*(1+$B$10)^INT((D$14-$B$5-1)/4),0) | E17: =IF(AND(E$14>$B$5,E$14<=$B$8),$B$4*$B$6/4*(1+$B$10)^INT((E$14-$B$5-1)/4),0) | F17: =IF(AND(F$14>$B$5,F$14<=$B$8),$B$4*$B$6/4*(1+$B$10)^INT((F$14-$B$5-1)/4),0) | G17: =IF(AND(G$14>$B$5,G$14<=$B$8),$B$4*$B$6/4*(1+$B$10)^INT((G$14-$B$5-1)/4),0) | H17: =IF(AND(H$14>$B$5,H$14<=$B$8),$B$4*$B$6/4*(1+$B$10)^INT((H$14-$B$5-1)/4),0) | I17: =IF(AND(I$14>$B$5,I$14<=$B$8),$B$4*$B$6/4*(1+$B$10)^INT((I$14-$B$5-1)/4),0) | J17: =IF(AND(J$14>$B$5,J$14<=$B$8),$B$4*$B$6/4*(1+$B$10)^INT((J$14-$B$5-1)/4),0) | ... R17: =IF(AND(R$14>$B$5,R$14<=$B$8),$B$4*$B$6/4*(1+$B$10)^INT((R$14-$B$5-1)/4),0)
A18: Sale proceeds | C18: =IF(C$14=$B$8,$B$4*$B$6*(1+$B$10)^INT((C$14-$B$5-1)/4)/$B$9*(1-$B$11),0) | D18: =IF(D$14=$B$8,$B$4*$B$6*(1+$B$10)^INT((D$14-$B$5-1)/4)/$B$9*(1-$B$11),0) | E18: =IF(E$14=$B$8,$B$4*$B$6*(1+$B$10)^INT((E$14-$B$5-1)/4)/$B$9*(1-$B$11),0) | F18: =IF(F$14=$B$8,$B$4*$B$6*(1+$B$10)^INT((F$14-$B$5-1)/4)/$B$9*(1-$B$11),0) | G18: =IF(G$14=$B$8,$B$4*$B$6*(1+$B$10)^INT((G$14-$B$5-1)/4)/$B$9*(1-$B$11),0) | H18: =IF(H$14=$B$8,$B$4*$B$6*(1+$B$10)^INT((H$14-$B$5-1)/4)/$B$9*(1-$B$11),0) | I18: =IF(I$14=$B$8,$B$4*$B$6*(1+$B$10)^INT((I$14-$B$5-1)/4)/$B$9*(1-$B$11),0) | J18: =IF(J$14=$B$8,$B$4*$B$6*(1+$B$10)^INT((J$14-$B$5-1)/4)/$B$9*(1-$B$11),0) | ... R18: =IF(R$14=$B$8,$B$4*$B$6*(1+$B$10)^INT((R$14-$B$5-1)/4)/$B$9*(1-$B$11),0)
A20: Net cash flow (AED m) | C20: =SUM(C15:C18) | D20: =SUM(D15:D18) | E20: =SUM(E15:E18) | F20: =SUM(F15:F18) | G20: =SUM(G15:G18) | H20: =SUM(H15:H18) | I20: =SUM(I15:I18) | J20: =SUM(J15:J18) | ... R20: =SUM(R15:R18)
A22: Net cash flow (USD m) | C22: =C20/$B$12 | D22: =D20/$B$12 | E22: =E20/$B$12 | F22: =F20/$B$12 | G22: =G20/$B$12 | H22: =H20/$B$12 | I22: =I20/$B$12 | J22: =J20/$B$12 | ... R22: =R20/$B$12

Sheet Returns
A1: Fund returns (USD m)
A2: LP net IRR | B2: =XIRR(Fund!C21:R21,Fund!C3:R3)
A3: Gross IRR | B3: =XIRR(Fund!C10:R10,Fund!C3:R3)
A4: TVPI | B4: =(SUM(Fund!C16:R16)+(1-Inputs!B6)*SUM(Fund!C20:R20))/SUM(Fund!C13:R13)
A5: Total carry | B5: =SUM(Fund!C22:R22)
A6: LP profit | B6: =SUM(Fund!C21:R21)
A7: Committed capital | B7: =Inputs!B3

Sheet Checks
A1: Checks (all should be 0)
A2: Deals sum to the fund gross | B2: =ROUND(SUM(Fund!C10:R10)-(SUM('Riyadh Office'!C22:R22)+SUM('Jeddah Logistics'!C22:R22)+SUM('Dubai Residential'!C22:R22)),6)
A3: Waterfall distributes everything | B3: =ROUND(SUM(Fund!C14:R14)-SUM(Fund!C16:R16)-SUM(Fund!C18:R18)-SUM(Fund!C20:R20),6)
