Workbook

Sheet Rent Roll
A1: 1 FARRINGDON STREET – REFURBISHMENT (GBP)
A3: Tenant | B3: Area (sq ft) | C3: Passing rent (£/sq ft) | D3: Lease expiry (year) | E3: Renewal probability | F3: ERV (£/sq ft) | G3: Void if vacated (months)
A4: Arden Legal | B4: 18000 | C4: 58 | D4: 2 | E4: 0.6 | F4: 72 | G4: 12
A5: Blue Cedar Media | B5: 12500 | C5: 61 | D5: 3 | E5: 0.5 | F5: 72 | G5: 12
A6: Corvex Capital | B6: 22000 | C6: 66 | D6: 5 | E6: 0.75 | F6: 74 | G6: 9
A7: Dunmore Health | B7: 9000 | C7: 52 | D7: 1 | E7: 0.4 | F7: 70 | G7: 15
A8: Elmstone Partners | B8: 15500 | C8: 63 | D8: 4 | E8: 0.65 | F8: 73 | G8: 12

Sheet Inputs
A1: REFURBISHMENT & EXIT
A3: Purchase price | C3: 78000000
A4: Purchase costs | C4: 0.068
A5: Refurbishment cost (£/sq ft) | C5: 145
A6: Exit yield | C6: 0.0525
A7: Hold (years) | C7: 6
A8: LTV | C8: 0.55
A9: Interest rate | C9: 0.0595
A10: ERV growth | C10: 0.025

Sheet CF
A1: ANNUAL CASH FLOW (£)
A3: Year | B3: 0 | C3: 1 | D3: 2 | E3: 3 | F3: 4 | G3: 5 | H3: 6 | I3: 7
A5: Arden Legal rent | B5: =IF(OR(B$3=0,B$3>Inputs!$C$7+1),0,IF(B$3<='Rent Roll'!$D$4,'Rent Roll'!$B$4*'Rent Roll'!$C$4,'Rent Roll'!$B$4*'Rent Roll'!$F$4*(1+Inputs!$C$10)^B$3*('Rent Roll'!$E$4+(1-'Rent Roll'!$E$4)*MAX(0,1-'Rent Roll'!$G$4/12*(B$3='Rent Roll'!$D$4+1))))) -> 0 | C5: =IF(OR(C$3=0,C$3>Inputs!$C$7+1),0,IF(C$3<='Rent Roll'!$D$4,'Rent Roll'!$B$4*'Rent Roll'!$C$4,'Rent Roll'!$B$4*'Rent Roll'!$F$4*(1+Inputs!$C$10)^C$3*('Rent Roll'!$E$4+(1-'Rent Roll'!$E$4)*MAX(0,1-'Rent Roll'!$G$4/12*(C$3='Rent Roll'!$D$4+1))))) -> 1044000 | D5: =IF(OR(D$3=0,D$3>Inputs!$C$7+1),0,IF(D$3<='Rent Roll'!$D$4,'Rent Roll'!$B$4*'Rent Roll'!$C$4,'Rent Roll'!$B$4*'Rent Roll'!$F$4*(1+Inputs!$C$10)^D$3*('Rent Roll'!$E$4+(1-'Rent Roll'!$E$4)*MAX(0,1-'Rent Roll'!$G$4/12*(D$3='Rent Roll'!$D$4+1))))) -> 1044000 | E5: =IF(OR(E$3=0,E$3>Inputs!$C$7+1),0,IF(E$3<='Rent Roll'!$D$4,'Rent Roll'!$B$4*'Rent Roll'!$C$4,'Rent Roll'!$B$4*'Rent Roll'!$F$4*(1+Inputs!$C$10)^E$3*('Rent Roll'!$E$4+(1-'Rent Roll'!$E$4)*MAX(0,1-'Rent Roll'!$G$4/12*(E$3='Rent Roll'!$D$4+1))))) -> 837390.15 | F5: =IF(OR(F$3=0,F$3>Inputs!$C$7+1),0,IF(F$3<='Rent Roll'!$D$4,'Rent Roll'!$B$4*'Rent Roll'!$C$4,'Rent Roll'!$B$4*'Rent Roll'!$F$4*(1+Inputs!$C$10)^F$3*('Rent Roll'!$E$4+(1-'Rent Roll'!$E$4)*MAX(0,1-'Rent Roll'!$G$4/12*(F$3='Rent Roll'!$D$4+1))))) -> 1430541.5 | G5: =IF(OR(G$3=0,G$3>Inputs!$C$7+1),0,IF(G$3<='Rent Roll'!$D$4,'Rent Roll'!$B$4*'Rent Roll'!$C$4,'Rent Roll'!$B$4*'Rent Roll'!$F$4*(1+Inputs!$C$10)^G$3*('Rent Roll'!$E$4+(1-'Rent Roll'!$E$4)*MAX(0,1-'Rent Roll'!$G$4/12*(G$3='Rent Roll'!$D$4+1))))) -> 1466305 | H5: =IF(OR(H$3=0,H$3>Inputs!$C$7+1),0,IF(H$3<='Rent Roll'!$D$4,'Rent Roll'!$B$4*'Rent Roll'!$C$4,'Rent Roll'!$B$4*'Rent Roll'!$F$4*(1+Inputs!$C$10)^H$3*('Rent Roll'!$E$4+(1-'Rent Roll'!$E$4)*MAX(0,1-'Rent Roll'!$G$4/12*(H$3='Rent Roll'!$D$4+1))))) -> 1502962.7 | I5: =IF(OR(I$3=0,I$3>Inputs!$C$7+1),0,IF(I$3<='Rent Roll'!$D$4,'Rent Roll'!$B$4*'Rent Roll'!$C$4,'Rent Roll'!$B$4*'Rent Roll'!$F$4*(1+Inputs!$C$10)^I$3*('Rent Roll'!$E$4+(1-'Rent Roll'!$E$4)*MAX(0,1-'Rent Roll'!$G$4/12*(I$3='Rent Roll'!$D$4+1))))) -> 1540536.7
A6: Blue Cedar Media rent | B6: =IF(OR(B$3=0,B$3>Inputs!$C$7+1),0,IF(B$3<='Rent Roll'!$D$5,'Rent Roll'!$B$5*'Rent Roll'!$C$5,'Rent Roll'!$B$5*'Rent Roll'!$F$5*(1+Inputs!$C$10)^B$3*('Rent Roll'!$E$5+(1-'Rent Roll'!$E$5)*MAX(0,1-'Rent Roll'!$G$5/12*(B$3='Rent Roll'!$D$5+1))))) -> 0 | C6: =IF(OR(C$3=0,C$3>Inputs!$C$7+1),0,IF(C$3<='Rent Roll'!$D$5,'Rent Roll'!$B$5*'Rent Roll'!$C$5,'Rent Roll'!$B$5*'Rent Roll'!$F$5*(1+Inputs!$C$10)^C$3*('Rent Roll'!$E$5+(1-'Rent Roll'!$E$5)*MAX(0,1-'Rent Roll'!$G$5/12*(C$3='Rent Roll'!$D$5+1))))) -> 762500 | D6: =IF(OR(D$3=0,D$3>Inputs!$C$7+1),0,IF(D$3<='Rent Roll'!$D$5,'Rent Roll'!$B$5*'Rent Roll'!$C$5,'Rent Roll'!$B$5*'Rent Roll'!$F$5*(1+Inputs!$C$10)^D$3*('Rent Roll'!$E$5+(1-'Rent Roll'!$E$5)*MAX(0,1-'Rent Roll'!$G$5/12*(D$3='Rent Roll'!$D$5+1))))) -> 762500 | E6: =IF(OR(E$3=0,E$3>Inputs!$C$7+1),0,IF(E$3<='Rent Roll'!$D$5,'Rent Roll'!$B$5*'Rent Roll'!$C$5,'Rent Roll'!$B$5*'Rent Roll'!$F$5*(1+Inputs!$C$10)^E$3*('Rent Roll'!$E$5+(1-'Rent Roll'!$E$5)*MAX(0,1-'Rent Roll'!$G$5/12*(E$3='Rent Roll'!$D$5+1))))) -> 762500 | F6: =IF(OR(F$3=0,F$3>Inputs!$C$7+1),0,IF(F$3<='Rent Roll'!$D$5,'Rent Roll'!$B$5*'Rent Roll'!$C$5,'Rent Roll'!$B$5*'Rent Roll'!$F$5*(1+Inputs!$C$10)^F$3*('Rent Roll'!$E$5+(1-'Rent Roll'!$E$5)*MAX(0,1-'Rent Roll'!$G$5/12*(F$3='Rent Roll'!$D$5+1))))) -> 496715.8 | G6: =IF(OR(G$3=0,G$3>Inputs!$C$7+1),0,IF(G$3<='Rent Roll'!$D$5,'Rent Roll'!$B$5*'Rent Roll'!$C$5,'Rent Roll'!$B$5*'Rent Roll'!$F$5*(1+Inputs!$C$10)^G$3*('Rent Roll'!$E$5+(1-'Rent Roll'!$E$5)*MAX(0,1-'Rent Roll'!$G$5/12*(G$3='Rent Roll'!$D$5+1))))) -> 1018267.4 | H6: =IF(OR(H$3=0,H$3>Inputs!$C$7+1),0,IF(H$3<='Rent Roll'!$D$5,'Rent Roll'!$B$5*'Rent Roll'!$C$5,'Rent Roll'!$B$5*'Rent Roll'!$F$5*(1+Inputs!$C$10)^H$3*('Rent Roll'!$E$5+(1-'Rent Roll'!$E$5)*MAX(0,1-'Rent Roll'!$G$5/12*(H$3='Rent Roll'!$D$5+1))))) -> 1043724.1 | I6: =IF(OR(I$3=0,I$3>Inputs!$C$7+1),0,IF(I$3<='Rent Roll'!$D$5,'Rent Roll'!$B$5*'Rent Roll'!$C$5,'Rent Roll'!$B$5*'Rent Roll'!$F$5*(1+Inputs!$C$10)^I$3*('Rent Roll'!$E$5+(1-'Rent Roll'!$E$5)*MAX(0,1-'Rent Roll'!$G$5/12*(I$3='Rent Roll'!$D$5+1))))) -> 1069817.2
A7: Corvex Capital rent | B7: =IF(OR(B$3=0,B$3>Inputs!$C$7+1),0,IF(B$3<='Rent Roll'!$D$6,'Rent Roll'!$B$6*'Rent Roll'!$C$6,'Rent Roll'!$B$6*'Rent Roll'!$F$6*(1+Inputs!$C$10)^B$3*('Rent Roll'!$E$6+(1-'Rent Roll'!$E$6)*MAX(0,1-'Rent Roll'!$G$6/12*(B$3='Rent Roll'!$D$6+1))))) -> 0 | C7: =IF(OR(C$3=0,C$3>Inputs!$C$7+1),0,IF(C$3<='Rent Roll'!$D$6,'Rent Roll'!$B$6*'Rent Roll'!$C$6,'Rent Roll'!$B$6*'Rent Roll'!$F$6*(1+Inputs!$C$10)^C$3*('Rent Roll'!$E$6+(1-'Rent Roll'!$E$6)*MAX(0,1-'Rent Roll'!$G$6/12*(C$3='Rent Roll'!$D$6+1))))) -> 1452000 | D7: =IF(OR(D$3=0,D$3>Inputs!$C$7+1),0,IF(D$3<='Rent Roll'!$D$6,'Rent Roll'!$B$6*'Rent Roll'!$C$6,'Rent Roll'!$B$6*'Rent Roll'!$F$6*(1+Inputs!$C$10)^D$3*('Rent Roll'!$E$6+(1-'Rent Roll'!$E$6)*MAX(0,1-'Rent Roll'!$G$6/12*(D$3='Rent Roll'!$D$6+1))))) -> 1452000 | E7: =IF(OR(E$3=0,E$3>Inputs!$C$7+1),0,IF(E$3<='Rent Roll'!$D$6,'Rent Roll'!$B$6*'Rent Roll'!$C$6,'Rent Roll'!$B$6*'Rent Roll'!$F$6*(1+Inputs!$C$10)^E$3*('Rent Roll'!$E$6+(1-'Rent Roll'!$E$6)*MAX(0,1-'Rent Roll'!$G$6/12*(E$3='Rent Roll'!$D$6+1))))) -> 1452000 | F7: =IF(OR(F$3=0,F$3>Inputs!$C$7+1),0,IF(F$3<='Rent Roll'!$D$6,'Rent Roll'!$B$6*'Rent Roll'!$C$6,'Rent Roll'!$B$6*'Rent Roll'!$F$6*(1+Inputs!$C$10)^F$3*('Rent Roll'!$E$6+(1-'Rent Roll'!$E$6)*MAX(0,1-'Rent Roll'!$G$6/12*(F$3='Rent Roll'!$D$6+1))))) -> 1452000 | G7: =IF(OR(G$3=0,G$3>Inputs!$C$7+1),0,IF(G$3<='Rent Roll'!$D$6,'Rent Roll'!$B$6*'Rent Roll'!$C$6,'Rent Roll'!$B$6*'Rent Roll'!$F$6*(1+Inputs!$C$10)^G$3*('Rent Roll'!$E$6+(1-'Rent Roll'!$E$6)*MAX(0,1-'Rent Roll'!$G$6/12*(G$3='Rent Roll'!$D$6+1))))) -> 1452000 | H7: =IF(OR(H$3=0,H$3>Inputs!$C$7+1),0,IF(H$3<='Rent Roll'!$D$6,'Rent Roll'!$B$6*'Rent Roll'!$C$6,'Rent Roll'!$B$6*'Rent Roll'!$F$6*(1+Inputs!$C$10)^H$3*('Rent Roll'!$E$6+(1-'Rent Roll'!$E$6)*MAX(0,1-'Rent Roll'!$G$6/12*(H$3='Rent Roll'!$D$6+1))))) -> 1533984.5 | I7: =IF(OR(I$3=0,I$3>Inputs!$C$7+1),0,IF(I$3<='Rent Roll'!$D$6,'Rent Roll'!$B$6*'Rent Roll'!$C$6,'Rent Roll'!$B$6*'Rent Roll'!$F$6*(1+Inputs!$C$10)^I$3*('Rent Roll'!$E$6+(1-'Rent Roll'!$E$6)*MAX(0,1-'Rent Roll'!$G$6/12*(I$3='Rent Roll'!$D$6+1))))) -> 1935180.4
A8: Dunmore Health rent | B8: =IF(OR(B$3=0,B$3>Inputs!$C$7+1),0,IF(B$3<='Rent Roll'!$D$7,'Rent Roll'!$B$7*'Rent Roll'!$C$7,'Rent Roll'!$B$7*'Rent Roll'!$F$7*(1+Inputs!$C$10)^B$3*('Rent Roll'!$E$7+(1-'Rent Roll'!$E$7)*MAX(0,1-'Rent Roll'!$G$7/12*(B$3='Rent Roll'!$D$7+1))))) -> 0 | C8: =IF(OR(C$3=0,C$3>Inputs!$C$7+1),0,IF(C$3<='Rent Roll'!$D$7,'Rent Roll'!$B$7*'Rent Roll'!$C$7,'Rent Roll'!$B$7*'Rent Roll'!$F$7*(1+Inputs!$C$10)^C$3*('Rent Roll'!$E$7+(1-'Rent Roll'!$E$7)*MAX(0,1-'Rent Roll'!$G$7/12*(C$3='Rent Roll'!$D$7+1))))) -> 468000 | D8: =IF(OR(D$3=0,D$3>Inputs!$C$7+1),0,IF(D$3<='Rent Roll'!$D$7,'Rent Roll'!$B$7*'Rent Roll'!$C$7,'Rent Roll'!$B$7*'Rent Roll'!$F$7*(1+Inputs!$C$10)^D$3*('Rent Roll'!$E$7+(1-'Rent Roll'!$E$7)*MAX(0,1-'Rent Roll'!$G$7/12*(D$3='Rent Roll'!$D$7+1))))) -> 264757.5 | E8: =IF(OR(E$3=0,E$3>Inputs!$C$7+1),0,IF(E$3<='Rent Roll'!$D$7,'Rent Roll'!$B$7*'Rent Roll'!$C$7,'Rent Roll'!$B$7*'Rent Roll'!$F$7*(1+Inputs!$C$10)^E$3*('Rent Roll'!$E$7+(1-'Rent Roll'!$E$7)*MAX(0,1-'Rent Roll'!$G$7/12*(E$3='Rent Roll'!$D$7+1))))) -> 678441.09 | F8: =IF(OR(F$3=0,F$3>Inputs!$C$7+1),0,IF(F$3<='Rent Roll'!$D$7,'Rent Roll'!$B$7*'Rent Roll'!$C$7,'Rent Roll'!$B$7*'Rent Roll'!$F$7*(1+Inputs!$C$10)^F$3*('Rent Roll'!$E$7+(1-'Rent Roll'!$E$7)*MAX(0,1-'Rent Roll'!$G$7/12*(F$3='Rent Roll'!$D$7+1))))) -> 695402.12 | G8: =IF(OR(G$3=0,G$3>Inputs!$C$7+1),0,IF(G$3<='Rent Roll'!$D$7,'Rent Roll'!$B$7*'Rent Roll'!$C$7,'Rent Roll'!$B$7*'Rent Roll'!$F$7*(1+Inputs!$C$10)^G$3*('Rent Roll'!$E$7+(1-'Rent Roll'!$E$7)*MAX(0,1-'Rent Roll'!$G$7/12*(G$3='Rent Roll'!$D$7+1))))) -> 712787.17 | H8: =IF(OR(H$3=0,H$3>Inputs!$C$7+1),0,IF(H$3<='Rent Roll'!$D$7,'Rent Roll'!$B$7*'Rent Roll'!$C$7,'Rent Roll'!$B$7*'Rent Roll'!$F$7*(1+Inputs!$C$10)^H$3*('Rent Roll'!$E$7+(1-'Rent Roll'!$E$7)*MAX(0,1-'Rent Roll'!$G$7/12*(H$3='Rent Roll'!$D$7+1))))) -> 730606.85 | I8: =IF(OR(I$3=0,I$3>Inputs!$C$7+1),0,IF(I$3<='Rent Roll'!$D$7,'Rent Roll'!$B$7*'Rent Roll'!$C$7,'Rent Roll'!$B$7*'Rent Roll'!$F$7*(1+Inputs!$C$10)^I$3*('Rent Roll'!$E$7+(1-'Rent Roll'!$E$7)*MAX(0,1-'Rent Roll'!$G$7/12*(I$3='Rent Roll'!$D$7+1))))) -> 748872.02
A9: Elmstone Partners rent | B9: =IF(OR(B$3=0,B$3>Inputs!$C$7+1),0,IF(B$3<='Rent Roll'!$D$8,'Rent Roll'!$B$8*'Rent Roll'!$C$8,'Rent Roll'!$B$8*'Rent Roll'!$F$8*(1+Inputs!$C$10)^B$3*('Rent Roll'!$E$8+(1-'Rent Roll'!$E$8)*MAX(0,1-'Rent Roll'!$G$8/12*(B$3='Rent Roll'!$D$8+1))))) -> 0 | C9: =IF(OR(C$3=0,C$3>Inputs!$C$7+1),0,IF(C$3<='Rent Roll'!$D$8,'Rent Roll'!$B$8*'Rent Roll'!$C$8,'Rent Roll'!$B$8*'Rent Roll'!$F$8*(1+Inputs!$C$10)^C$3*('Rent Roll'!$E$8+(1-'Rent Roll'!$E$8)*MAX(0,1-'Rent Roll'!$G$8/12*(C$3='Rent Roll'!$D$8+1))))) -> 976500 | D9: =IF(OR(D$3=0,D$3>Inputs!$C$7+1),0,IF(D$3<='Rent Roll'!$D$8,'Rent Roll'!$B$8*'Rent Roll'!$C$8,'Rent Roll'!$B$8*'Rent Roll'!$F$8*(1+Inputs!$C$10)^D$3*('Rent Roll'!$E$8+(1-'Rent Roll'!$E$8)*MAX(0,1-'Rent Roll'!$G$8/12*(D$3='Rent Roll'!$D$8+1))))) -> 976500 | E9: =IF(OR(E$3=0,E$3>Inputs!$C$7+1),0,IF(E$3<='Rent Roll'!$D$8,'Rent Roll'!$B$8*'Rent Roll'!$C$8,'Rent Roll'!$B$8*'Rent Roll'!$F$8*(1+Inputs!$C$10)^E$3*('Rent Roll'!$E$8+(1-'Rent Roll'!$E$8)*MAX(0,1-'Rent Roll'!$G$8/12*(E$3='Rent Roll'!$D$8+1))))) -> 976500 | F9: =IF(OR(F$3=0,F$3>Inputs!$C$7+1),0,IF(F$3<='Rent Roll'!$D$8,'Rent Roll'!$B$8*'Rent Roll'!$C$8,'Rent Roll'!$B$8*'Rent Roll'!$F$8*(1+Inputs!$C$10)^F$3*('Rent Roll'!$E$8+(1-'Rent Roll'!$E$8)*MAX(0,1-'Rent Roll'!$G$8/12*(F$3='Rent Roll'!$D$8+1))))) -> 976500 | G9: =IF(OR(G$3=0,G$3>Inputs!$C$7+1),0,IF(G$3<='Rent Roll'!$D$8,'Rent Roll'!$B$8*'Rent Roll'!$C$8,'Rent Roll'!$B$8*'Rent Roll'!$F$8*(1+Inputs!$C$10)^G$3*('Rent Roll'!$E$8+(1-'Rent Roll'!$E$8)*MAX(0,1-'Rent Roll'!$G$8/12*(G$3='Rent Roll'!$D$8+1))))) -> 832122.46 | H9: =IF(OR(H$3=0,H$3>Inputs!$C$7+1),0,IF(H$3<='Rent Roll'!$D$8,'Rent Roll'!$B$8*'Rent Roll'!$C$8,'Rent Roll'!$B$8*'Rent Roll'!$F$8*(1+Inputs!$C$10)^H$3*('Rent Roll'!$E$8+(1-'Rent Roll'!$E$8)*MAX(0,1-'Rent Roll'!$G$8/12*(H$3='Rent Roll'!$D$8+1))))) -> 1312193.1 | I9: =IF(OR(I$3=0,I$3>Inputs!$C$7+1),0,IF(I$3<='Rent Roll'!$D$8,'Rent Roll'!$B$8*'Rent Roll'!$C$8,'Rent Roll'!$B$8*'Rent Roll'!$F$8*(1+Inputs!$C$10)^I$3*('Rent Roll'!$E$8+(1-'Rent Roll'!$E$8)*MAX(0,1-'Rent Roll'!$G$8/12*(I$3='Rent Roll'!$D$8+1))))) -> 1344997.9
A10: Net rent | B10: =SUM(B5:B9)*0.95 -> 0 | C10: =SUM(C5:C9)*0.95 -> 4467850 | D10: =SUM(D5:D9)*0.95 -> 4274769.6 | E10: =SUM(E5:E9)*0.95 -> 4471489.7 | F10: =SUM(F5:F9)*0.95 -> 4798601.5 | G10: =SUM(G5:G9)*0.95 -> 5207408 | H10: =SUM(H5:H9)*0.95 -> 5817297.6 | I10: =SUM(I5:I9)*0.95 -> 6307434.1
A11: Refurbishment | B11: =IF(B$3=1,-SUM('Rent Roll'!$B$4:$B$8)*Inputs!$C$5,0) -> 0 | C11: =IF(C$3=1,-SUM('Rent Roll'!$B$4:$B$8)*Inputs!$C$5,0) -> -11165000 | D11: =IF(D$3=1,-SUM('Rent Roll'!$B$4:$B$8)*Inputs!$C$5,0) -> 0 | E11: =IF(E$3=1,-SUM('Rent Roll'!$B$4:$B$8)*Inputs!$C$5,0) -> 0 | F11: =IF(F$3=1,-SUM('Rent Roll'!$B$4:$B$8)*Inputs!$C$5,0) -> 0 | G11: =IF(G$3=1,-SUM('Rent Roll'!$B$4:$B$8)*Inputs!$C$5,0) -> 0 | H11: =IF(H$3=1,-SUM('Rent Roll'!$B$4:$B$8)*Inputs!$C$5,0) -> 0 | I11: =IF(I$3=1,-SUM('Rent Roll'!$B$4:$B$8)*Inputs!$C$5,0) -> 0
A12: Acquisition | B12: =IF(B$3=0,-Inputs!$C$3*(1+Inputs!$C$4),0) -> -83304000 | C12: =IF(C$3=0,-Inputs!$C$3*(1+Inputs!$C$4),0) -> 0 | D12: =IF(D$3=0,-Inputs!$C$3*(1+Inputs!$C$4),0) -> 0 | E12: =IF(E$3=0,-Inputs!$C$3*(1+Inputs!$C$4),0) -> 0 | F12: =IF(F$3=0,-Inputs!$C$3*(1+Inputs!$C$4),0) -> 0 | G12: =IF(G$3=0,-Inputs!$C$3*(1+Inputs!$C$4),0) -> 0 | H12: =IF(H$3=0,-Inputs!$C$3*(1+Inputs!$C$4),0) -> 0 | I12: =IF(I$3=0,-Inputs!$C$3*(1+Inputs!$C$4),0) -> 0
A13: Sale | B13: =IF(B$3=Inputs!$C$7,C10/Inputs!$C$6,0) -> 0 | C13: =IF(C$3=Inputs!$C$7,D10/Inputs!$C$6,0) -> 0 | D13: =IF(D$3=Inputs!$C$7,E10/Inputs!$C$6,0) -> 0 | E13: =IF(E$3=Inputs!$C$7,F10/Inputs!$C$6,0) -> 0 | F13: =IF(F$3=Inputs!$C$7,G10/Inputs!$C$6,0) -> 0 | G13: =IF(G$3=Inputs!$C$7,H10/Inputs!$C$6,0) -> 0 | H13: =IF(H$3=Inputs!$C$7,I10/Inputs!$C$6,0) -> 1.201416e+08 | I13: =0 -> 0
A14: Unlevered | B14: =B10+B11+B12+B13 -> -83304000 | C14: =C10+C11+C12+C13 -> -6697150 | D14: =D10+D11+D12+D13 -> 4274769.6 | E14: =E10+E11+E12+E13 -> 4471489.7 | F14: =F10+F11+F12+F13 -> 4798601.5 | G14: =G10+G11+G12+G13 -> 5207408 | H14: =H10+H11+H12+H13 -> 1.259589e+08 | I14: =I10+I11+I12+I13 -> 6307434.1
A15: Debt | B15: =IF(B$3=0,Inputs!$C$3*Inputs!$C$8,IF(B$3<=Inputs!$C$7,-Inputs!$C$3*Inputs!$C$8*Inputs!$C$9,0))-IF(B$3=Inputs!$C$7,Inputs!$C$3*Inputs!$C$8,0) -> 42900000 | C15: =IF(C$3=0,Inputs!$C$3*Inputs!$C$8,IF(C$3<=Inputs!$C$7,-Inputs!$C$3*Inputs!$C$8*Inputs!$C$9,0))-IF(C$3=Inputs!$C$7,Inputs!$C$3*Inputs!$C$8,0) -> -2552550 | D15: =IF(D$3=0,Inputs!$C$3*Inputs!$C$8,IF(D$3<=Inputs!$C$7,-Inputs!$C$3*Inputs!$C$8*Inputs!$C$9,0))-IF(D$3=Inputs!$C$7,Inputs!$C$3*Inputs!$C$8,0) -> -2552550 | E15: =IF(E$3=0,Inputs!$C$3*Inputs!$C$8,IF(E$3<=Inputs!$C$7,-Inputs!$C$3*Inputs!$C$8*Inputs!$C$9,0))-IF(E$3=Inputs!$C$7,Inputs!$C$3*Inputs!$C$8,0) -> -2552550 | F15: =IF(F$3=0,Inputs!$C$3*Inputs!$C$8,IF(F$3<=Inputs!$C$7,-Inputs!$C$3*Inputs!$C$8*Inputs!$C$9,0))-IF(F$3=Inputs!$C$7,Inputs!$C$3*Inputs!$C$8,0) -> -2552550 | G15: =IF(G$3=0,Inputs!$C$3*Inputs!$C$8,IF(G$3<=Inputs!$C$7,-Inputs!$C$3*Inputs!$C$8*Inputs!$C$9,0))-IF(G$3=Inputs!$C$7,Inputs!$C$3*Inputs!$C$8,0) -> -2552550 | H15: =IF(H$3=0,Inputs!$C$3*Inputs!$C$8,IF(H$3<=Inputs!$C$7,-Inputs!$C$3*Inputs!$C$8*Inputs!$C$9,0))-IF(H$3=Inputs!$C$7,Inputs!$C$3*Inputs!$C$8,0) -> -45452550 | I15: =IF(I$3=0,Inputs!$C$3*Inputs!$C$8,IF(I$3<=Inputs!$C$7,-Inputs!$C$3*Inputs!$C$8*Inputs!$C$9,0))-IF(I$3=Inputs!$C$7,Inputs!$C$3*Inputs!$C$8,0) -> 0
A16: Levered | B16: =B14+B15 -> -40404000 | C16: =C14+C15 -> -9249700 | D16: =D14+D15 -> 1722219.6 | E16: =E14+E15 -> 1918939.7 | F16: =F14+F15 -> 2246051.5 | G16: =G14+G15 -> 2654858 | H16: =H14+H15 -> 80506349 | I16: =I14+I15 -> 6307434.1

Sheet Summary
A3: Levered IRR | C3: =IRR(CF!$B$16:$I$16) -> 0.12265553
A4: Unlevered IRR | C4: =IRR(CF!$B$14:$I$14) -> 0.096331333
A5: Equity multiple | C5: =SUMIF(CF!$B$16:$I$16,">0")/-SUMIF(CF!$B$16:$I$16,"<0") -> 1.9204178
A6: Net profit | C6: =SUM(CF!$B$16:$I$16) -> 45702152
A7: WAULT at purchase (years) | C7: =SUMPRODUCT('Rent Roll'!B4:B8,'Rent Roll'!C4:C8,'Rent Roll'!D4:D8)/SUMPRODUCT('Rent Roll'!B4:B8,'Rent Roll'!C4:C8) -> 3.4041038
