Workbook

Sheet Control
A1: RIVERSIDE STUDENT LIVING – INVESTMENT MODEL
A3: Active case (1 = Base, 2 = Downside, 3 = Upside) | C3: 1
A4: Currency | C4: GBP

Sheet Assumptions
A1: Assumption | B1: Unit | C1: Base | D1: Downside | E1: Upside | F1: Live
A2: Beds | B2: beds | C2: 650 | D2: 650 | E2: 650 | F2: =CHOOSE(Control!$C$3,C2,D2,E2) -> 650
A3: Weekly rent | B3: £/bed/week | C3: 215 | D3: 200 | E3: 225 | F3: =CHOOSE(Control!$C$3,C3,D3,E3) -> 215
A4: Let weeks | B4: weeks/yr | C4: 51 | D4: 51 | E4: 51 | F4: =CHOOSE(Control!$C$3,C4,D4,E4) -> 51
A5: Occupancy | B5: % | C5: 0.97 | D5: 0.92 | E5: 0.98 | F5: =CHOOSE(Control!$C$3,C5,D5,E5) -> 0.97
A6: Rental growth | B6: % p.a. | C6: 0.03 | D6: 0.02 | E6: 0.035 | F6: =CHOOSE(Control!$C$3,C6,D6,E6) -> 0.03
A7: Operating costs | B7: £/bed/yr | C7: 2900 | D7: 3100 | E7: 2800 | F7: =CHOOSE(Control!$C$3,C7,D7,E7) -> 2900
A8: Cost inflation | B8: % p.a. | C8: 0.03 | D8: 0.035 | E8: 0.03 | F8: =CHOOSE(Control!$C$3,C8,D8,E8) -> 0.03
A9: Total development cost | B9: £ | C9: 78000000 | D9: 78000000 | E9: 78000000 | F9: =CHOOSE(Control!$C$3,C9,D9,E9) -> 78000000
A10: Exit yield | B10: % | C10: 0.05 | D10: 0.055 | E10: 0.0475 | F10: =CHOOSE(Control!$C$3,C10,D10,E10) -> 0.05
A11: Senior loan to cost | B11: % | C11: 0.55 | D11: 0.55 | E11: 0.55 | F11: =CHOOSE(Control!$C$3,C11,D11,E11) -> 0.55
A12: Interest rate | B12: % | C12: 0.0625 | D12: 0.0725 | E12: 0.0575 | F12: =CHOOSE(Control!$C$3,C12,D12,E12) -> 0.0625
A13: Refinance year | B13: year | C13: 3 | D13: 3 | E13: 3 | F13: =CHOOSE(Control!$C$3,C13,D13,E13) -> 3
... A15: Hold period | B15: years | C15: 7 | D15: 7 | E15: 7 | F15: =CHOOSE(Control!$C$3,C15,D15,E15) -> 7

Sheet Operations
A1: ANNUAL CASH FLOW (£)
A3: Year | C3: 0 | D3: 1 | E3: 2 | F3: 3 | G3: 4 | H3: 5 | I3: 6 | J3: 7
A5: Development cost | C5: =IF(C$3=0,-Assumptions!$F$9,0) -> -78000000 | D5: =IF(D$3=0,-Assumptions!$F$9,0) -> 0 | E5: =IF(E$3=0,-Assumptions!$F$9,0) -> 0 | F5: =IF(F$3=0,-Assumptions!$F$9,0) -> 0 | G5: =IF(G$3=0,-Assumptions!$F$9,0) -> 0 | H5: =IF(H$3=0,-Assumptions!$F$9,0) -> 0 | I5: =IF(I$3=0,-Assumptions!$F$9,0) -> 0 | J5: =IF(J$3=0,-Assumptions!$F$9,0) -> 0
A6: Gross rental income | C6: =IF(AND(C$3>=1,C$3<=Assumptions!$F$15),Assumptions!$F$2*Assumptions!$F$3*Assumptions!$F$4*Assumptions!$F$5*(1+Assumptions!$F$6)^(C$3-1),0) -> 0 | D6: =IF(AND(D$3>=1,D$3<=Assumptions!$F$15),Assumptions!$F$2*Assumptions!$F$3*Assumptions!$F$4*Assumptions!$F$5*(1+Assumptions!$F$6)^(D$3-1),0) -> 6913432.5 | E6: =IF(AND(E$3>=1,E$3<=Assumptions!$F$15),Assumptions!$F$2*Assumptions!$F$3*Assumptions!$F$4*Assumptions!$F$5*(1+Assumptions!$F$6)^(E$3-1),0) -> 7120835.5 | F6: =IF(AND(F$3>=1,F$3<=Assumptions!$F$15),Assumptions!$F$2*Assumptions!$F$3*Assumptions!$F$4*Assumptions!$F$5*(1+Assumptions!$F$6)^(F$3-1),0) -> 7334460.5 | G6: =IF(AND(G$3>=1,G$3<=Assumptions!$F$15),Assumptions!$F$2*Assumptions!$F$3*Assumptions!$F$4*Assumptions!$F$5*(1+Assumptions!$F$6)^(G$3-1),0) -> 7554494.4 | H6: =IF(AND(H$3>=1,H$3<=Assumptions!$F$15),Assumptions!$F$2*Assumptions!$F$3*Assumptions!$F$4*Assumptions!$F$5*(1+Assumptions!$F$6)^(H$3-1),0) -> 7781129.2 | I6: =IF(AND(I$3>=1,I$3<=Assumptions!$F$15),Assumptions!$F$2*Assumptions!$F$3*Assumptions!$F$4*Assumptions!$F$5*(1+Assumptions!$F$6)^(I$3-1),0) -> 8014563.1 | J6: =IF(AND(J$3>=1,J$3<=Assumptions!$F$15),Assumptions!$F$2*Assumptions!$F$3*Assumptions!$F$4*Assumptions!$F$5*(1+Assumptions!$F$6)^(J$3-1),0) -> 8255000
A7: Operating costs | C7: =IF(C6>0,-Assumptions!$F$2*Assumptions!$F$7*(1+Assumptions!$F$8)^(C$3-1),0) -> 0 | D7: =IF(D6>0,-Assumptions!$F$2*Assumptions!$F$7*(1+Assumptions!$F$8)^(D$3-1),0) -> -1885000 | E7: =IF(E6>0,-Assumptions!$F$2*Assumptions!$F$7*(1+Assumptions!$F$8)^(E$3-1),0) -> -1941550 | F7: =IF(F6>0,-Assumptions!$F$2*Assumptions!$F$7*(1+Assumptions!$F$8)^(F$3-1),0) -> -1999796.5 | G7: =IF(G6>0,-Assumptions!$F$2*Assumptions!$F$7*(1+Assumptions!$F$8)^(G$3-1),0) -> -2059790.4 | H7: =IF(H6>0,-Assumptions!$F$2*Assumptions!$F$7*(1+Assumptions!$F$8)^(H$3-1),0) -> -2121584.1 | I7: =IF(I6>0,-Assumptions!$F$2*Assumptions!$F$7*(1+Assumptions!$F$8)^(I$3-1),0) -> -2185231.6 | J7: =IF(J6>0,-Assumptions!$F$2*Assumptions!$F$7*(1+Assumptions!$F$8)^(J$3-1),0) -> -2250788.6
A8: Net operating income | C8: =C6+C7 -> 0 | D8: =D6+D7 -> 5028432.5 | E8: =E6+E7 -> 5179285.5 | F8: =F6+F7 -> 5334664 | G8: =G6+G7 -> 5494704 | H8: =H6+H7 -> 5659545.1 | I8: =I6+I7 -> 5829331.4 | J8: =J6+J7 -> 6004211.4
A9: Exit value | C9: =IF(C$3=Assumptions!$F$15,C8*(1+Assumptions!$F$6)/Assumptions!$F$10,0) -> 0 | D9: =IF(D$3=Assumptions!$F$15,D8*(1+Assumptions!$F$6)/Assumptions!$F$10,0) -> 0 | E9: =IF(E$3=Assumptions!$F$15,E8*(1+Assumptions!$F$6)/Assumptions!$F$10,0) -> 0 | F9: =IF(F$3=Assumptions!$F$15,F8*(1+Assumptions!$F$6)/Assumptions!$F$10,0) -> 0 | G9: =IF(G$3=Assumptions!$F$15,G8*(1+Assumptions!$F$6)/Assumptions!$F$10,0) -> 0 | H9: =IF(H$3=Assumptions!$F$15,H8*(1+Assumptions!$F$6)/Assumptions!$F$10,0) -> 0 | I9: =IF(I$3=Assumptions!$F$15,I8*(1+Assumptions!$F$6)/Assumptions!$F$10,0) -> 0 | J9: =IF(J$3=Assumptions!$F$15,J8*(1+Assumptions!$F$6)/Assumptions!$F$10,0) -> 1.2368675e+08
A10: Unlevered cash flow | C10: =C5+C8+C9 -> -78000000 | D10: =D5+D8+D9 -> 5028432.5 | E10: =E5+E8+E9 -> 5179285.5 | F10: =F5+F8+F9 -> 5334664 | G10: =G5+G8+G9 -> 5494704 | H10: =H5+H8+H9 -> 5659545.1 | I10: =I5+I8+I9 -> 5829331.4 | J10: =J5+J8+J9 -> 1.2969097e+08
A11: Opening debt | C11: =IF(C$3=0,Assumptions!$F$9*Assumptions!$F$11,B13) -> 42900000 | D11: =IF(D$3=0,Assumptions!$F$9*Assumptions!$F$11,C13) -> 42900000 | E11: =IF(E$3=0,Assumptions!$F$9*Assumptions!$F$11,D13) -> 42900000 | F11: =IF(F$3=0,Assumptions!$F$9*Assumptions!$F$11,E13) -> 42900000 | G11: =IF(G$3=0,Assumptions!$F$9*Assumptions!$F$11,F13) -> 65936448 | H11: =IF(H$3=0,Assumptions!$F$9*Assumptions!$F$11,G13) -> 65936448 | I11: =IF(I$3=0,Assumptions!$F$9*Assumptions!$F$11,H13) -> 65936448 | J11: =IF(J$3=0,Assumptions!$F$9*Assumptions!$F$11,I13) -> 65936448
A12: Refinance proceeds | C12: =IF(C$3=Assumptions!$F$13,MAX(0,Assumptions!$F$14*C8*(1+Assumptions!$F$6)/Assumptions!$F$10-C11),0) -> 0 | D12: =IF(D$3=Assumptions!$F$13,MAX(0,Assumptions!$F$14*D8*(1+Assumptions!$F$6)/Assumptions!$F$10-D11),0) -> 0 | E12: =IF(E$3=Assumptions!$F$13,MAX(0,Assumptions!$F$14*E8*(1+Assumptions!$F$6)/Assumptions!$F$10-E11),0) -> 0 | F12: =IF(F$3=Assumptions!$F$13,MAX(0,Assumptions!$F$14*F8*(1+Assumptions!$F$6)/Assumptions!$F$10-F11),0) -> 23036448 | G12: =IF(G$3=Assumptions!$F$13,MAX(0,Assumptions!$F$14*G8*(1+Assumptions!$F$6)/Assumptions!$F$10-G11),0) -> 0 | H12: =IF(H$3=Assumptions!$F$13,MAX(0,Assumptions!$F$14*H8*(1+Assumptions!$F$6)/Assumptions!$F$10-H11),0) -> 0 | I12: =IF(I$3=Assumptions!$F$13,MAX(0,Assumptions!$F$14*I8*(1+Assumptions!$F$6)/Assumptions!$F$10-I11),0) -> 0 | J12: =IF(J$3=Assumptions!$F$13,MAX(0,Assumptions!$F$14*J8*(1+Assumptions!$F$6)/Assumptions!$F$10-J11),0) -> 0
A13: Closing debt | C13: =IF(C$3=Assumptions!$F$15,0,C11+C12) -> 42900000 | D13: =IF(D$3=Assumptions!$F$15,0,D11+D12) -> 42900000 | E13: =IF(E$3=Assumptions!$F$15,0,E11+E12) -> 42900000 | F13: =IF(F$3=Assumptions!$F$15,0,F11+F12) -> 65936448 | G13: =IF(G$3=Assumptions!$F$15,0,G11+G12) -> 65936448 | H13: =IF(H$3=Assumptions!$F$15,0,H11+H12) -> 65936448 | I13: =IF(I$3=Assumptions!$F$15,0,I11+I12) -> 65936448 | J13: =IF(J$3=Assumptions!$F$15,0,J11+J12) -> 0
A14: Interest | C14: =IF(C$3=0,0,-C11*Assumptions!$F$12) -> 0 | D14: =IF(D$3=0,0,-D11*Assumptions!$F$12) -> -2681250 | E14: =IF(E$3=0,0,-E11*Assumptions!$F$12) -> -2681250 | F14: =IF(F$3=0,0,-F11*Assumptions!$F$12) -> -2681250 | G14: =IF(G$3=0,0,-G11*Assumptions!$F$12) -> -4121028 | H14: =IF(H$3=0,0,-H11*Assumptions!$F$12) -> -4121028 | I14: =IF(I$3=0,0,-I11*Assumptions!$F$12) -> -4121028 | J14: =IF(J$3=0,0,-J11*Assumptions!$F$12) -> -4121028
A15: DSCR | C15: =IF(C14<0,C8/-C14,"") | D15: =IF(D14<0,D8/-D14,"") -> 1.8754061 | E15: =IF(E14<0,E8/-E14,"") -> 1.9316682 | F15: =IF(F14<0,F8/-F14,"") -> 1.9896183 | G15: =IF(G14<0,G8/-G14,"") -> 1.3333333 | H15: =IF(H14<0,H8/-H14,"") -> 1.3733333 | I15: =IF(I14<0,I8/-I14,"") -> 1.4145333 | J15: =IF(J14<0,J8/-J14,"") -> 1.4569693
A16: Debt flows | C16: =IF(C$3=0,C11,C12+C14-IF(C$3=Assumptions!$F$15,C11,0)) -> 42900000 | D16: =IF(D$3=0,D11,D12+D14-IF(D$3=Assumptions!$F$15,D11,0)) -> -2681250 | E16: =IF(E$3=0,E11,E12+E14-IF(E$3=Assumptions!$F$15,E11,0)) -> -2681250 | F16: =IF(F$3=0,F11,F12+F14-IF(F$3=Assumptions!$F$15,F11,0)) -> 20355198 | G16: =IF(G$3=0,G11,G12+G14-IF(G$3=Assumptions!$F$15,G11,0)) -> -4121028 | H16: =IF(H$3=0,H11,H12+H14-IF(H$3=Assumptions!$F$15,H11,0)) -> -4121028 | I16: =IF(I$3=0,I11,I12+I14-IF(I$3=Assumptions!$F$15,I11,0)) -> -4121028 | J16: =IF(J$3=0,J11,J12+J14-IF(J$3=Assumptions!$F$15,J11,0)) -> -70057475
A17: Levered cash flow | C17: =C10+C16 -> -35100000 | D17: =D10+D16 -> 2347182.5 | E17: =E10+E16 -> 2498035.5 | F17: =F10+F16 -> 25689862 | G17: =G10+G16 -> 1373676 | H17: =H10+H16 -> 1538517.1 | I17: =I10+I16 -> 1708303.5 | J17: =J10+J16 -> 59633490

Sheet Summary
A1: RETURNS
A3: Levered IRR | C3: =IRR(Operations!$C$17:$J$17) -> 0.21386016
A4: Unlevered IRR | C4: =IRR(Operations!$C$10:$J$10) -> 0.12649518
A5: Equity multiple | C5: =SUMIF(Operations!$C$17:$J$17,">0")/-SUMIF(Operations!$C$17:$J$17,"<0") -> 2.7005432
A6: Yield on cost | C6: =Operations!D8/Assumptions!$F$9 -> 0.064467083
A7: Minimum DSCR | C7: =MIN(Operations!$C$15:$J$15) -> 1.3333333
A8: Net profit | C8: =SUM(Operations!$C$17:$J$17) -> 59689066
A9: Total development cost | C9: =Assumptions!$F$9 -> 78000000
A10: Cash-on-cash yield (year 2) | C10: =Operations!E17/-Operations!C17 -> 0.071169102
