Workbook

Sheet Options
A1: AL MALQA TOWER – OPTION APPRAISAL (SAR)
A3: Selected option (A or B) | C3: A
A5: Assumption | B5: Unit | C5: Option A | D5: Option B | E5: Selected
A6: Residential NSA | B6: sqm | C6: 38000 | D6: 30000 | E6: =IF($C$3="A",C6,D6) -> 38000
A7: Residential sale price | B7: SAR/sqm | C7: 14200 | D7: 15500 | E7: =IF($C$3="A",C7,D7) -> 14200
A8: Off-plan sales in year 1 | B8: % | C8: 0.4 | D8: 0.3 | E8: =IF($C$3="A",C8,D8) -> 0.4
A9: Office GLA | B9: sqm | C9: 9000 | D9: 16000 | E9: =IF($C$3="A",C9,D9) -> 9000
A10: Office rent | B10: SAR/sqm/yr | C10: 1650 | D10: 1650 | E10: =IF($C$3="A",C10,D10) -> 1650
A11: Office exit yield | B11: % | C11: 0.08 | D11: 0.08 | E11: =IF($C$3="A",C11,D11) -> 0.08
A12: Build cost | B12: SAR/sqm GFA | C12: 4300 | D12: 4600 | E12: =IF($C$3="A",C12,D12) -> 4300
A13: GFA | B13: sqm | C13: 62000 | D13: 64000 | E13: =IF($C$3="A",C13,D13) -> 62000
A14: Land cost | B14: SAR | C14: 180000000 | D14: 180000000 | E14: =IF($C$3="A",C14,D14) -> 180000000
A15: Construction period | B15: years | C15: 3 | D15: 3 | E15: =IF($C$3="A",C15,D15) -> 3
A16: Murabaha LTC | B16: % | C16: 0.55 | D16: 0.55 | E16: =IF($C$3="A",C16,D16) -> 0.55
A17: Profit rate | B17: % | C17: 0.065 | D17: 0.065 | E17: =IF($C$3="A",C17,D17) -> 0.065

Sheet Cash Flow
A1: ANNUAL CASH FLOW (SAR)
A3: Year | B3: 0 | C3: 1 | D3: 2 | E3: 3 | F3: 4 | G3: 5 | H3: 6
A5: Land | B5: =IF(B$3=0,-Options!$E$14,0) -> -180000000 | C5: =IF(C$3=0,-Options!$E$14,0) -> 0 | D5: =IF(D$3=0,-Options!$E$14,0) -> 0 | E5: =IF(E$3=0,-Options!$E$14,0) -> 0 | F5: =IF(F$3=0,-Options!$E$14,0) -> 0 | G5: =IF(G$3=0,-Options!$E$14,0) -> 0 | H5: =IF(H$3=0,-Options!$E$14,0) -> 0
A6: Construction | B6: =IF(AND(B$3>=1,B$3<=Options!$E$15),-Options!$E$13*Options!$E$12/Options!$E$15,0) -> 0 | C6: =IF(AND(C$3>=1,C$3<=Options!$E$15),-Options!$E$13*Options!$E$12/Options!$E$15,0) -> -88866667 | D6: =IF(AND(D$3>=1,D$3<=Options!$E$15),-Options!$E$13*Options!$E$12/Options!$E$15,0) -> -88866667 | E6: =IF(AND(E$3>=1,E$3<=Options!$E$15),-Options!$E$13*Options!$E$12/Options!$E$15,0) -> -88866667 | F6: =IF(AND(F$3>=1,F$3<=Options!$E$15),-Options!$E$13*Options!$E$12/Options!$E$15,0) -> 0 | G6: =IF(AND(G$3>=1,G$3<=Options!$E$15),-Options!$E$13*Options!$E$12/Options!$E$15,0) -> 0 | H6: =IF(AND(H$3>=1,H$3<=Options!$E$15),-Options!$E$13*Options!$E$12/Options!$E$15,0) -> 0
A7: Residential sales | B7: =IF(B$3=1,Options!$E$6*Options!$E$7*Options!$E$8,IF(B$3=Options!$E$15+1,Options!$E$6*Options!$E$7*(1-Options!$E$8),0)) -> 0 | C7: =IF(C$3=1,Options!$E$6*Options!$E$7*Options!$E$8,IF(C$3=Options!$E$15+1,Options!$E$6*Options!$E$7*(1-Options!$E$8),0)) -> 215840000 | D7: =IF(D$3=1,Options!$E$6*Options!$E$7*Options!$E$8,IF(D$3=Options!$E$15+1,Options!$E$6*Options!$E$7*(1-Options!$E$8),0)) -> 0 | E7: =IF(E$3=1,Options!$E$6*Options!$E$7*Options!$E$8,IF(E$3=Options!$E$15+1,Options!$E$6*Options!$E$7*(1-Options!$E$8),0)) -> 0 | F7: =IF(F$3=1,Options!$E$6*Options!$E$7*Options!$E$8,IF(F$3=Options!$E$15+1,Options!$E$6*Options!$E$7*(1-Options!$E$8),0)) -> 323760000 | G7: =IF(G$3=1,Options!$E$6*Options!$E$7*Options!$E$8,IF(G$3=Options!$E$15+1,Options!$E$6*Options!$E$7*(1-Options!$E$8),0)) -> 0 | H7: =IF(H$3=1,Options!$E$6*Options!$E$7*Options!$E$8,IF(H$3=Options!$E$15+1,Options!$E$6*Options!$E$7*(1-Options!$E$8),0)) -> 0
A8: Office NOI | B8: =IF(AND(B$3>Options!$E$15,B$3<=Options!$E$15+2),Options!$E$9*Options!$E$10*0.92,0) -> 0 | C8: =IF(AND(C$3>Options!$E$15,C$3<=Options!$E$15+2),Options!$E$9*Options!$E$10*0.92,0) -> 0 | D8: =IF(AND(D$3>Options!$E$15,D$3<=Options!$E$15+2),Options!$E$9*Options!$E$10*0.92,0) -> 0 | E8: =IF(AND(E$3>Options!$E$15,E$3<=Options!$E$15+2),Options!$E$9*Options!$E$10*0.92,0) -> 0 | F8: =IF(AND(F$3>Options!$E$15,F$3<=Options!$E$15+2),Options!$E$9*Options!$E$10*0.92,0) -> 13662000 | G8: =IF(AND(G$3>Options!$E$15,G$3<=Options!$E$15+2),Options!$E$9*Options!$E$10*0.92,0) -> 13662000 | H8: =IF(AND(H$3>Options!$E$15,H$3<=Options!$E$15+2),Options!$E$9*Options!$E$10*0.92,0) -> 0
A9: Office sale | B9: =IF(B$3=Options!$E$15+2,Options!$E$9*Options!$E$10*0.92/Options!$E$11,0) -> 0 | C9: =IF(C$3=Options!$E$15+2,Options!$E$9*Options!$E$10*0.92/Options!$E$11,0) -> 0 | D9: =IF(D$3=Options!$E$15+2,Options!$E$9*Options!$E$10*0.92/Options!$E$11,0) -> 0 | E9: =IF(E$3=Options!$E$15+2,Options!$E$9*Options!$E$10*0.92/Options!$E$11,0) -> 0 | F9: =IF(F$3=Options!$E$15+2,Options!$E$9*Options!$E$10*0.92/Options!$E$11,0) -> 0 | G9: =IF(G$3=Options!$E$15+2,Options!$E$9*Options!$E$10*0.92/Options!$E$11,0) -> 170775000 | H9: =IF(H$3=Options!$E$15+2,Options!$E$9*Options!$E$10*0.92/Options!$E$11,0) -> 0
A10: Unlevered | B10: =SUM(B5:B9) -> -180000000 | C10: =SUM(C5:C9) -> 1.2697333e+08 | D10: =SUM(D5:D9) -> -88866667 | E10: =SUM(E5:E9) -> -88866667 | F10: =SUM(F5:F9) -> 337422000 | G10: =SUM(G5:G9) -> 184437000 | H10: =SUM(H5:H9) -> 0
A11: Debt drawn | B11: =-B6*Options!$E$16 -> 0 | C11: =-C6*Options!$E$16 -> 48876667 | D11: =-D6*Options!$E$16 -> 48876667 | E11: =-E6*Options!$E$16 -> 48876667 | F11: =-F6*Options!$E$16 -> 0 | G11: =-G6*Options!$E$16 -> 0 | H11: =-H6*Options!$E$16 -> 0
A12: Profit on debt | B12: =-(0)*Options!$E$17 -> 0 | C12: =-(SUM($B$11:B11)+SUM($B$13:B13))*Options!$E$17 -> 0 | D12: =-(SUM($B$11:C11)+SUM($B$13:C13))*Options!$E$17 -> -3176983.3 | E12: =-(SUM($B$11:D11)+SUM($B$13:D13))*Options!$E$17 -> -6353966.7 | F12: =-(SUM($B$11:E11)+SUM($B$13:E13))*Options!$E$17 -> -9530950 | G12: =-(SUM($B$11:F11)+SUM($B$13:F13))*Options!$E$17 -> 0 | H12: =-(SUM($B$11:G11)+SUM($B$13:G13))*Options!$E$17 -> 0
A13: Debt repaid | B13: =IF(B$3=Options!$E$15+1,-(0+B11),0) -> 0 | C13: =IF(C$3=Options!$E$15+1,-(SUM($B$11:B11)+SUM($B$13:B13)+C11),0) -> 0 | D13: =IF(D$3=Options!$E$15+1,-(SUM($B$11:C11)+SUM($B$13:C13)+D11),0) -> 0 | E13: =IF(E$3=Options!$E$15+1,-(SUM($B$11:D11)+SUM($B$13:D13)+E11),0) -> 0 | F13: =IF(F$3=Options!$E$15+1,-(SUM($B$11:E11)+SUM($B$13:E13)+F11),0) -> -146630000 | G13: =IF(G$3=Options!$E$15+1,-(SUM($B$11:F11)+SUM($B$13:F13)+G11),0) -> 0 | H13: =IF(H$3=Options!$E$15+1,-(SUM($B$11:G11)+SUM($B$13:G13)+H11),0) -> 0
A14: Levered | B14: =B10+B11+B12+B13 -> -180000000 | C14: =C10+C11+C12+C13 -> 175850000 | D14: =D10+D11+D12+D13 -> -43166983 | E14: =E10+E11+E12+E13 -> -46343967 | F14: =F10+F11+F12+F13 -> 181261050 | G14: =G10+G11+G12+G13 -> 184437000 | H14: =H10+H11+H12+H13 -> 0

Sheet Results
A3: Equity IRR | B3: =IRR('Cash Flow'!$B$14:$H$14) -> 0.3605151
A4: Project IRR | B4: =IRR('Cash Flow'!$B$10:$H$10) -> 0.28398774
A5: Net profit | B5: =SUM('Cash Flow'!$B$14:$H$14) -> 272037100
A6: Total development cost | B6: =-SUM('Cash Flow'!$B$5:$H$5)-SUM('Cash Flow'!$B$6:$H$6) -> 446600000
A7: Profit on cost | B7: =B5/B6 -> 0.6091292
A8: Gross development value | B8: =SUM('Cash Flow'!$B$7:$H$7)+SUM('Cash Flow'!$B$9:$H$9) -> 710375000
A9: Equity multiple | B9: =SUMIF('Cash Flow'!$B$14:$H$14,">0")/-SUMIF('Cash Flow'!$B$14:$H$14,"<0") -> 2.0093731
A12: Option shown | B12: =Options!C3 -> A
