Workbook

Sheet Assets
A1: EUROPEAN LOGISTICS FUND I – FUND MODEL (EUR m)
A3: Asset | B3: Equity in (EUR m) | C3: Entry year | D3: Exit year | E3: Exit multiple on equity | F3: Annual yield to equity
A4: Lyon DC | B4: 42 | C4: 0 | D4: 5 | E4: 1.65 | F4: 0.05
A5: Rotterdam XXL | B5: 58 | C5: 0 | D5: 6 | E5: 1.8 | F5: 0.045
A6: Milan last-mile | B6: 35 | C6: 1 | D6: 5 | E6: 1.55 | F6: 0.055
A7: Poznan park | B7: 28 | C7: 1 | D7: 6 | E7: 1.7 | F7: 0.06

Sheet Fund
A1: FUND CASH FLOWS (EUR m)
A3: Year | B3: 0 | C3: 1 | D3: 2 | E3: 3 | F3: 4 | G3: 5 | H3: 6 | I3: 7
A5: Gross equity calls | B5: =-SUMIF(Assets!$C$4:$C$7,B$3,Assets!$B$4:$B$7) -> -100 | C5: =-SUMIF(Assets!$C$4:$C$7,C$3,Assets!$B$4:$B$7) -> -63 | D5: =-SUMIF(Assets!$C$4:$C$7,D$3,Assets!$B$4:$B$7) -> 0 | E5: =-SUMIF(Assets!$C$4:$C$7,E$3,Assets!$B$4:$B$7) -> 0 | F5: =-SUMIF(Assets!$C$4:$C$7,F$3,Assets!$B$4:$B$7) -> 0 | G5: =-SUMIF(Assets!$C$4:$C$7,G$3,Assets!$B$4:$B$7) -> 0 | H5: =-SUMIF(Assets!$C$4:$C$7,H$3,Assets!$B$4:$B$7) -> 0 | I5: =-SUMIF(Assets!$C$4:$C$7,I$3,Assets!$B$4:$B$7) -> 0
A6: Gross distributions | B6: =SUMPRODUCT((Assets!$C$4:$C$7<B$3)*(Assets!$D$4:$D$7>=B$3)*Assets!$B$4:$B$7*Assets!$F$4:$F$7)+SUMPRODUCT((Assets!$D$4:$D$7=B$3)*Assets!$B$4:$B$7*Assets!$E$4:$E$7) -> 0 | C6: =SUMPRODUCT((Assets!$C$4:$C$7<C$3)*(Assets!$D$4:$D$7>=C$3)*Assets!$B$4:$B$7*Assets!$F$4:$F$7)+SUMPRODUCT((Assets!$D$4:$D$7=C$3)*Assets!$B$4:$B$7*Assets!$E$4:$E$7) -> 4.71 | D6: =SUMPRODUCT((Assets!$C$4:$C$7<D$3)*(Assets!$D$4:$D$7>=D$3)*Assets!$B$4:$B$7*Assets!$F$4:$F$7)+SUMPRODUCT((Assets!$D$4:$D$7=D$3)*Assets!$B$4:$B$7*Assets!$E$4:$E$7) -> 8.315 | E6: =SUMPRODUCT((Assets!$C$4:$C$7<E$3)*(Assets!$D$4:$D$7>=E$3)*Assets!$B$4:$B$7*Assets!$F$4:$F$7)+SUMPRODUCT((Assets!$D$4:$D$7=E$3)*Assets!$B$4:$B$7*Assets!$E$4:$E$7) -> 8.315 | F6: =SUMPRODUCT((Assets!$C$4:$C$7<F$3)*(Assets!$D$4:$D$7>=F$3)*Assets!$B$4:$B$7*Assets!$F$4:$F$7)+SUMPRODUCT((Assets!$D$4:$D$7=F$3)*Assets!$B$4:$B$7*Assets!$E$4:$E$7) -> 8.315 | G6: =SUMPRODUCT((Assets!$C$4:$C$7<G$3)*(Assets!$D$4:$D$7>=G$3)*Assets!$B$4:$B$7*Assets!$F$4:$F$7)+SUMPRODUCT((Assets!$D$4:$D$7=G$3)*Assets!$B$4:$B$7*Assets!$E$4:$E$7) -> 131.865 | H6: =SUMPRODUCT((Assets!$C$4:$C$7<H$3)*(Assets!$D$4:$D$7>=H$3)*Assets!$B$4:$B$7*Assets!$F$4:$F$7)+SUMPRODUCT((Assets!$D$4:$D$7=H$3)*Assets!$B$4:$B$7*Assets!$E$4:$E$7) -> 156.29 | I6: =SUMPRODUCT((Assets!$C$4:$C$7<I$3)*(Assets!$D$4:$D$7>=I$3)*Assets!$B$4:$B$7*Assets!$F$4:$F$7)+SUMPRODUCT((Assets!$D$4:$D$7=I$3)*Assets!$B$4:$B$7*Assets!$E$4:$E$7) -> 0
A7: Gross cash flow | B7: =B5+B6 -> -100 | C7: =C5+C6 -> -58.29 | D7: =D5+D6 -> 8.315 | E7: =E5+E6 -> 8.315 | F7: =F5+F6 -> 8.315 | G7: =G5+G6 -> 131.865 | H7: =H5+H6 -> 156.29 | I7: =I5+I6 -> 0
A8: Management fee | B8: =IF(B$3<=6,-$B$17*$B$14,0) -> -2.445 | C8: =IF(C$3<=6,-$B$17*$B$14,0) -> -2.445 | D8: =IF(D$3<=6,-$B$17*$B$14,0) -> -2.445 | E8: =IF(E$3<=6,-$B$17*$B$14,0) -> -2.445 | F8: =IF(F$3<=6,-$B$17*$B$14,0) -> -2.445 | G8: =IF(G$3<=6,-$B$17*$B$14,0) -> -2.445 | H8: =IF(H$3<=6,-$B$17*$B$14,0) -> -2.445 | I8: =IF(I$3<=6,-$B$17*$B$14,0) -> 0
A9: Net before carry | B9: =B7+B8 -> -102.445 | C9: =C7+C8 -> -60.735 | D9: =D7+D8 -> 5.87 | E9: =E7+E8 -> 5.87 | F9: =F7+F8 -> 5.87 | G9: =G7+G8 -> 129.42 | H9: =H7+H8 -> 153.845 | I9: =I7+I8 -> 0
A10: Carry | B10: =IF(B$3=7,0,IF(B$3=6,-MAX(0,SUM($B$9:B9)-$B$16*$B$17*4)*$B$15,0)) -> 0 | C10: =IF(C$3=7,0,IF(C$3=6,-MAX(0,SUM($B$9:C9)-$B$16*$B$17*4)*$B$15,0)) -> 0 | D10: =IF(D$3=7,0,IF(D$3=6,-MAX(0,SUM($B$9:D9)-$B$16*$B$17*4)*$B$15,0)) -> 0 | E10: =IF(E$3=7,0,IF(E$3=6,-MAX(0,SUM($B$9:E9)-$B$16*$B$17*4)*$B$15,0)) -> 0 | F10: =IF(F$3=7,0,IF(F$3=6,-MAX(0,SUM($B$9:F9)-$B$16*$B$17*4)*$B$15,0)) -> 0 | G10: =IF(G$3=7,0,IF(G$3=6,-MAX(0,SUM($B$9:G9)-$B$16*$B$17*4)*$B$15,0)) -> 0 | H10: =IF(H$3=7,0,IF(H$3=6,-MAX(0,SUM($B$9:H9)-$B$16*$B$17*4)*$B$15,0)) -> -17.107 | I10: =IF(I$3=7,0,IF(I$3=6,-MAX(0,SUM($B$9:I9)-$B$16*$B$17*4)*$B$15,0)) -> 0
A11: LP net cash flow | B11: =B9+B10 -> -102.445 | C11: =C9+C10 -> -60.735 | D11: =D9+D10 -> 5.87 | E11: =E9+E10 -> 5.87 | F11: =F9+F10 -> 5.87 | G11: =G9+G10 -> 129.42 | H11: =H9+H10 -> 136.738 | I11: =I9+I10 -> 0
A14: Management fee (% of committed p.a.) | B14: 0.015
A15: Carried interest | B15: 0.2
A16: Hurdle (simple, on contributions) | B16: 0.08
A17: Commitments (EUR m) | B17: =SUM(Assets!B4:B7) -> 163

Sheet Fund Returns
A3: Gross IRR | B3: =IRR(Fund!$B$7:$I$7) -> 0.14835568
A4: Net IRR to LPs | B4: =IRR(Fund!$B$11:$I$11) -> 0.11800389
A5: Gross MOIC | B5: =SUMIF(Fund!$B$7:$I$7,">0")/-SUMIF(Fund!$B$7:$I$7,"<0") -> 1.978015
A6: Net TVPI | B6: =SUMIF(Fund!$B$11:$I$11,">0")/-SUMIF(Fund!$B$11:$I$11,"<0") -> 1.7389876
A7: Total carry (EUR m) | B7: =-SUM(Fund!$B$10:$I$10) -> 17.107
A8: Net profit to LPs (EUR m) | B8: =SUM(Fund!$B$11:$I$11) -> 120.588
