Workbook

Sheet Assumptions
A1: ZÜRICH NORD LOGISTICS – REFINANCING (CHF)
C2: Source / note
A3: Net operating income (CHF p.a.) | B3: 9400000 | C3: 2025 actual 9,260,000
A4: Valuation (CHF) | B4: 212000000 | C4: Wüest 2026
A5: Target LTV | B5: 0.55
A6: SARON | B6: 0.0075 | C6: SNB, 0.75
A7: Credit margin (bps) | B7: 165 | C7: term sheet 165
A8: Swap cost (bps) | B8: 35
A9: Amortisation (% p.a.) | B9: 0.01
A10: NOI growth | B10: 0.015
A11: Exit yield | B11: 0.0425
A12: Hold (years) | B12: 7

Sheet Debt
A3: Year | B3: 0 | C3: 1 | D3: 2 | E3: 3 | F3: 4 | G3: 5 | H3: 6 | I3: 7 | J3: 8
A4: NOI | B4: =IF(AND(B$3>=1,B$3<=Assumptions!$B$12),Assumptions!$B$3*(1+Assumptions!$B$10)^(B$3-1),0) -> 0 | C4: =IF(AND(C$3>=1,C$3<=Assumptions!$B$12),Assumptions!$B$3*(1+Assumptions!$B$10)^(C$3-1),0) -> 9400000 | D4: =IF(AND(D$3>=1,D$3<=Assumptions!$B$12),Assumptions!$B$3*(1+Assumptions!$B$10)^(D$3-1),0) -> 9541000 | E4: =IF(AND(E$3>=1,E$3<=Assumptions!$B$12),Assumptions!$B$3*(1+Assumptions!$B$10)^(E$3-1),0) -> 9684115 | F4: =IF(AND(F$3>=1,F$3<=Assumptions!$B$12),Assumptions!$B$3*(1+Assumptions!$B$10)^(F$3-1),0) -> 9829376.7 | G4: =IF(AND(G$3>=1,G$3<=Assumptions!$B$12),Assumptions!$B$3*(1+Assumptions!$B$10)^(G$3-1),0) -> 9976817.4 | H4: =IF(AND(H$3>=1,H$3<=Assumptions!$B$12),Assumptions!$B$3*(1+Assumptions!$B$10)^(H$3-1),0) -> 10126470 | I4: =IF(AND(I$3>=1,I$3<=Assumptions!$B$12),Assumptions!$B$3*(1+Assumptions!$B$10)^(I$3-1),0) -> 10278367 | J4: =IF(AND(J$3>=1,J$3<=Assumptions!$B$12),Assumptions!$B$3*(1+Assumptions!$B$10)^(J$3-1),0) -> 0
A5: Loan balance | B5: =Assumptions!$B$4*Assumptions!$B$5 -> 116600000 | C5: =IF(C$3>Assumptions!$B$12,0,B5-C7) -> 115434000 | D5: =IF(D$3>Assumptions!$B$12,0,C5-D7) -> 114268000 | E5: =IF(E$3>Assumptions!$B$12,0,D5-E7) -> 113102000 | F5: =IF(F$3>Assumptions!$B$12,0,E5-F7) -> 111936000 | G5: =IF(G$3>Assumptions!$B$12,0,F5-G7) -> 110770000 | H5: =IF(H$3>Assumptions!$B$12,0,G5-H7) -> 109604000 | I5: =IF(I$3>Assumptions!$B$12,0,H5-I7) -> 108438000 | J5: =IF(J$3>Assumptions!$B$12,0,I5-J7) -> 0
A6: Interest | B6: =0 -> 0 | C6: =IF(C$3<=Assumptions!$B$12,B5*(Assumptions!$B$6+(Assumptions!$B$7+Assumptions!$B$8)/10000),0) -> 3206500 | D6: =IF(D$3<=Assumptions!$B$12,C5*(Assumptions!$B$6+(Assumptions!$B$7+Assumptions!$B$8)/10000),0) -> 3174435 | E6: =IF(E$3<=Assumptions!$B$12,D5*(Assumptions!$B$6+(Assumptions!$B$7+Assumptions!$B$8)/10000),0) -> 3142370 | F6: =IF(F$3<=Assumptions!$B$12,E5*(Assumptions!$B$6+(Assumptions!$B$7+Assumptions!$B$8)/10000),0) -> 3110305 | G6: =IF(G$3<=Assumptions!$B$12,F5*(Assumptions!$B$6+(Assumptions!$B$7+Assumptions!$B$8)/10000),0) -> 3078240 | H6: =IF(H$3<=Assumptions!$B$12,G5*(Assumptions!$B$6+(Assumptions!$B$7+Assumptions!$B$8)/10000),0) -> 3046175 | I6: =IF(I$3<=Assumptions!$B$12,H5*(Assumptions!$B$6+(Assumptions!$B$7+Assumptions!$B$8)/10000),0) -> 3014110 | J6: =IF(J$3<=Assumptions!$B$12,I5*(Assumptions!$B$6+(Assumptions!$B$7+Assumptions!$B$8)/10000),0) -> 0
A7: Amortisation | B7: =0 -> 0 | C7: =IF(C$3<=Assumptions!$B$12,Assumptions!$B$4*Assumptions!$B$5*Assumptions!$B$9,0) -> 1166000 | D7: =IF(D$3<=Assumptions!$B$12,Assumptions!$B$4*Assumptions!$B$5*Assumptions!$B$9,0) -> 1166000 | E7: =IF(E$3<=Assumptions!$B$12,Assumptions!$B$4*Assumptions!$B$5*Assumptions!$B$9,0) -> 1166000 | F7: =IF(F$3<=Assumptions!$B$12,Assumptions!$B$4*Assumptions!$B$5*Assumptions!$B$9,0) -> 1166000 | G7: =IF(G$3<=Assumptions!$B$12,Assumptions!$B$4*Assumptions!$B$5*Assumptions!$B$9,0) -> 1166000 | H7: =IF(H$3<=Assumptions!$B$12,Assumptions!$B$4*Assumptions!$B$5*Assumptions!$B$9,0) -> 1166000 | I7: =IF(I$3<=Assumptions!$B$12,Assumptions!$B$4*Assumptions!$B$5*Assumptions!$B$9,0) -> 1166000 | J7: =IF(J$3<=Assumptions!$B$12,Assumptions!$B$4*Assumptions!$B$5*Assumptions!$B$9,0) -> 0
A8: Debt service | B8: =B6+B7 -> 0 | C8: =C6+C7 -> 4372500 | D8: =D6+D7 -> 4340435 | E8: =E6+E7 -> 4308370 | F8: =F6+F7 -> 4276305 | G8: =G6+G7 -> 4244240 | H8: =H6+H7 -> 4212175 | I8: =I6+I7 -> 4180110 | J8: =J6+J7 -> 0
A9: DSCR | B9: =IF(B8>0,B4/B8,"") | C9: =IF(C8>0,C4/C8,"") -> 2.1497999 | D9: =IF(D8>0,D4/D8,"") -> 2.1981668 | E9: =IF(E8>0,E4/E8,"") -> 2.2477445 | F9: =IF(F8>0,F4/F8,"") -> 2.2985677 | G9: =IF(G8>0,G4/G8,"") -> 2.3506723 | H9: =IF(H8>0,H4/H8,"") -> 2.4040952 | I9: =IF(I8>0,I4/I8,"") -> 2.4588747 | J9: =IF(J8>0,J4/J8,"")
A10: ICR | B10: =IF(B6>0,B4/B6,"") | C10: =IF(C6>0,C4/C6,"") -> 2.9315453 | D10: =IF(D6>0,D4/D6,"") -> 3.0055742 | E10: =IF(E6>0,E4/E6,"") -> 3.081787 | F10: =IF(F6>0,F4/F6,"") -> 3.1602614 | G10: =IF(G6>0,G4/G6,"") -> 3.2410785 | H10: =IF(H6>0,H4/H6,"") -> 3.324323 | I10: =IF(I6>0,I4/I6,"") -> 3.4100835 | J10: =IF(J6>0,J4/J6,"")
A11: Equity cash flow | B11: =-Assumptions!$B$4*(1-Assumptions!$B$5) -> -95400000 | C11: =IF(C$3<=Assumptions!$B$12,C4-C8,0)+IF(C$3=Assumptions!$B$12,C4*(1+Assumptions!$B$10)/Assumptions!$B$11-C5,0) -> 5027500 | D11: =IF(D$3<=Assumptions!$B$12,D4-D8,0)+IF(D$3=Assumptions!$B$12,D4*(1+Assumptions!$B$10)/Assumptions!$B$11-D5,0) -> 5200565 | E11: =IF(E$3<=Assumptions!$B$12,E4-E8,0)+IF(E$3=Assumptions!$B$12,E4*(1+Assumptions!$B$10)/Assumptions!$B$11-E5,0) -> 5375745 | F11: =IF(F$3<=Assumptions!$B$12,F4-F8,0)+IF(F$3=Assumptions!$B$12,F4*(1+Assumptions!$B$10)/Assumptions!$B$11-F5,0) -> 5553071.7 | G11: =IF(G$3<=Assumptions!$B$12,G4-G8,0)+IF(G$3=Assumptions!$B$12,G4*(1+Assumptions!$B$10)/Assumptions!$B$11-G5,0) -> 5732577.4 | H11: =IF(H$3<=Assumptions!$B$12,H4-H8,0)+IF(H$3=Assumptions!$B$12,H4*(1+Assumptions!$B$10)/Assumptions!$B$11-H5,0) -> 5914294.6 | I11: =IF(I$3<=Assumptions!$B$12,I4-I8,0)+IF(I$3=Assumptions!$B$12,I4*(1+Assumptions!$B$10)/Assumptions!$B$11-I5,0) -> 1.4313184e+08 | J11: =IF(J$3<=Assumptions!$B$12,J4-J8,0)+IF(J$3=Assumptions!$B$12,J4*(1+Assumptions!$B$10)/Assumptions!$B$11-J5,0) -> 0

Sheet KPIs
A3: Levered IRR | B3: =IRR(Debt!$B$11:$J$11) -> 0.10309162
A4: Minimum DSCR | B4: =MIN(Debt!$B$9:$J$9) -> 2.1497999
A5: Minimum ICR | B5: =MIN(Debt!$B$10:$J$10) -> 2.9315453
A6: All-in interest rate | B6: =(Assumptions!$B$6+(Assumptions!$B$7+Assumptions!$B$8)/10000) -> 0.0275
A7: Equity multiple | B7: =SUMIF(Debt!$B$11:$J$11,">0")/-SUMIF(Debt!$B$11:$J$11,"<0") -> 1.8441886
A8: Net profit | B8: =SUM(Debt!$B$11:$J$11) -> 80535591
