Workbook

Sheet Phasing
A1: AL REEM MASTER PLAN – PHASED DEVELOPMENT (AED)
A3: Phase | B3: Sellable area (sqm) | C3: Start year | D3: Build years | E3: Sale price (AED/sqm) | F3: Build cost (AED/sqm) | G3: Include (1/0)
A4: Phase 1 | B4: 85000 | C4: 1 | D4: 3 | E4: 16500 | F4: 10400 | G4: 1
A5: Phase 2 | B5: 110000 | C5: 3 | D5: 3 | E5: 17200 | F5: 10800 | G5: 1
A6: Phase 3 | B6: 95000 | C6: 6 | D6: 3 | E6: 18000 | F6: 11200 | G6: 1

Sheet Assumptions
A2: Infrastructure & land (AED) | B2: 420000000
A3: Sales collected in year after completion | B3: 0.7
A4: Discount rate | B4: 0.1

Sheet Cash Flow
A3: Year | B3: 0 | C3: 1 | D3: 2 | E3: 3 | F3: 4 | G3: 5 | H3: 6 | I3: 7 | J3: 8 | K3: 9 | L3: 10 | M3: 11
A4: Construction | B4: =-SUMPRODUCT(Phasing!$G$4:$G$6,Phasing!$B$4:$B$6,Phasing!$F$4:$F$6,(Phasing!$C$4:$C$6<=B$3)*(Phasing!$C$4:$C$6+Phasing!$D$4:$D$6>B$3)/Phasing!$D$4:$D$6) -> 0 | C4: =-SUMPRODUCT(Phasing!$G$4:$G$6,Phasing!$B$4:$B$6,Phasing!$F$4:$F$6,(Phasing!$C$4:$C$6<=C$3)*(Phasing!$C$4:$C$6+Phasing!$D$4:$D$6>C$3)/Phasing!$D$4:$D$6) -> -2.9466667e+08 | D4: =-SUMPRODUCT(Phasing!$G$4:$G$6,Phasing!$B$4:$B$6,Phasing!$F$4:$F$6,(Phasing!$C$4:$C$6<=D$3)*(Phasing!$C$4:$C$6+Phasing!$D$4:$D$6>D$3)/Phasing!$D$4:$D$6) -> -2.9466667e+08 | E4: =-SUMPRODUCT(Phasing!$G$4:$G$6,Phasing!$B$4:$B$6,Phasing!$F$4:$F$6,(Phasing!$C$4:$C$6<=E$3)*(Phasing!$C$4:$C$6+Phasing!$D$4:$D$6>E$3)/Phasing!$D$4:$D$6) -> -6.9066667e+08 | F4: =-SUMPRODUCT(Phasing!$G$4:$G$6,Phasing!$B$4:$B$6,Phasing!$F$4:$F$6,(Phasing!$C$4:$C$6<=F$3)*(Phasing!$C$4:$C$6+Phasing!$D$4:$D$6>F$3)/Phasing!$D$4:$D$6) -> -396000000 | G4: =-SUMPRODUCT(Phasing!$G$4:$G$6,Phasing!$B$4:$B$6,Phasing!$F$4:$F$6,(Phasing!$C$4:$C$6<=G$3)*(Phasing!$C$4:$C$6+Phasing!$D$4:$D$6>G$3)/Phasing!$D$4:$D$6) -> -396000000 | H4: =-SUMPRODUCT(Phasing!$G$4:$G$6,Phasing!$B$4:$B$6,Phasing!$F$4:$F$6,(Phasing!$C$4:$C$6<=H$3)*(Phasing!$C$4:$C$6+Phasing!$D$4:$D$6>H$3)/Phasing!$D$4:$D$6) -> -3.5466667e+08 | I4: =-SUMPRODUCT(Phasing!$G$4:$G$6,Phasing!$B$4:$B$6,Phasing!$F$4:$F$6,(Phasing!$C$4:$C$6<=I$3)*(Phasing!$C$4:$C$6+Phasing!$D$4:$D$6>I$3)/Phasing!$D$4:$D$6) -> -3.5466667e+08 | ... M4: =-SUMPRODUCT(Phasing!$G$4:$G$6,Phasing!$B$4:$B$6,Phasing!$F$4:$F$6,(Phasing!$C$4:$C$6<=M$3)*(Phasing!$C$4:$C$6+Phasing!$D$4:$D$6>M$3)/Phasing!$D$4:$D$6) -> 0
A5: Sales | B5: =SUMPRODUCT(Phasing!$G$4:$G$6,Phasing!$B$4:$B$6,Phasing!$E$4:$E$6,(Phasing!$C$4:$C$6+Phasing!$D$4:$D$6=B$3)*Assumptions!$B$3+(Phasing!$C$4:$C$6+Phasing!$D$4:$D$6+1=B$3)*(1-Assumptions!$B$3)) -> 0 | C5: =SUMPRODUCT(Phasing!$G$4:$G$6,Phasing!$B$4:$B$6,Phasing!$E$4:$E$6,(Phasing!$C$4:$C$6+Phasing!$D$4:$D$6=C$3)*Assumptions!$B$3+(Phasing!$C$4:$C$6+Phasing!$D$4:$D$6+1=C$3)*(1-Assumptions!$B$3)) -> 0 | D5: =SUMPRODUCT(Phasing!$G$4:$G$6,Phasing!$B$4:$B$6,Phasing!$E$4:$E$6,(Phasing!$C$4:$C$6+Phasing!$D$4:$D$6=D$3)*Assumptions!$B$3+(Phasing!$C$4:$C$6+Phasing!$D$4:$D$6+1=D$3)*(1-Assumptions!$B$3)) -> 0 | E5: =SUMPRODUCT(Phasing!$G$4:$G$6,Phasing!$B$4:$B$6,Phasing!$E$4:$E$6,(Phasing!$C$4:$C$6+Phasing!$D$4:$D$6=E$3)*Assumptions!$B$3+(Phasing!$C$4:$C$6+Phasing!$D$4:$D$6+1=E$3)*(1-Assumptions!$B$3)) -> 0 | F5: =SUMPRODUCT(Phasing!$G$4:$G$6,Phasing!$B$4:$B$6,Phasing!$E$4:$E$6,(Phasing!$C$4:$C$6+Phasing!$D$4:$D$6=F$3)*Assumptions!$B$3+(Phasing!$C$4:$C$6+Phasing!$D$4:$D$6+1=F$3)*(1-Assumptions!$B$3)) -> 981750000 | G5: =SUMPRODUCT(Phasing!$G$4:$G$6,Phasing!$B$4:$B$6,Phasing!$E$4:$E$6,(Phasing!$C$4:$C$6+Phasing!$D$4:$D$6=G$3)*Assumptions!$B$3+(Phasing!$C$4:$C$6+Phasing!$D$4:$D$6+1=G$3)*(1-Assumptions!$B$3)) -> 420750000 | H5: =SUMPRODUCT(Phasing!$G$4:$G$6,Phasing!$B$4:$B$6,Phasing!$E$4:$E$6,(Phasing!$C$4:$C$6+Phasing!$D$4:$D$6=H$3)*Assumptions!$B$3+(Phasing!$C$4:$C$6+Phasing!$D$4:$D$6+1=H$3)*(1-Assumptions!$B$3)) -> 1324400000 | I5: =SUMPRODUCT(Phasing!$G$4:$G$6,Phasing!$B$4:$B$6,Phasing!$E$4:$E$6,(Phasing!$C$4:$C$6+Phasing!$D$4:$D$6=I$3)*Assumptions!$B$3+(Phasing!$C$4:$C$6+Phasing!$D$4:$D$6+1=I$3)*(1-Assumptions!$B$3)) -> 567600000 | ... M5: =SUMPRODUCT(Phasing!$G$4:$G$6,Phasing!$B$4:$B$6,Phasing!$E$4:$E$6,(Phasing!$C$4:$C$6+Phasing!$D$4:$D$6=M$3)*Assumptions!$B$3+(Phasing!$C$4:$C$6+Phasing!$D$4:$D$6+1=M$3)*(1-Assumptions!$B$3)) -> 0
A6: Land & infrastructure | B6: =IF(B$3=0,-Assumptions!$B$2,0) -> -420000000 | C6: =IF(C$3=0,-Assumptions!$B$2,0) -> 0 | D6: =IF(D$3=0,-Assumptions!$B$2,0) -> 0 | E6: =IF(E$3=0,-Assumptions!$B$2,0) -> 0 | F6: =IF(F$3=0,-Assumptions!$B$2,0) -> 0 | G6: =IF(G$3=0,-Assumptions!$B$2,0) -> 0 | H6: =IF(H$3=0,-Assumptions!$B$2,0) -> 0 | I6: =IF(I$3=0,-Assumptions!$B$2,0) -> 0 | ... M6: =IF(M$3=0,-Assumptions!$B$2,0) -> 0
A7: Net cash flow | B7: =SUM(B4:B6) -> -420000000 | C7: =SUM(C4:C6) -> -2.9466667e+08 | D7: =SUM(D4:D6) -> -2.9466667e+08 | E7: =SUM(E4:E6) -> -6.9066667e+08 | F7: =SUM(F4:F6) -> 585750000 | G7: =SUM(G4:G6) -> 24750000 | H7: =SUM(H4:H6) -> 9.6973333e+08 | I7: =SUM(I4:I6) -> 2.1293333e+08 | ... M7: =SUM(M4:M6) -> 0

Sheet Summary
A3: Project IRR | B3: =IRR('Cash Flow'!B7:M7) -> 0.12275399
A4: NPV @ discount rate | B4: =NPV(Assumptions!B4,'Cash Flow'!C7:M7)+'Cash Flow'!B7 -> 1.6176148e+08
A5: Net profit | B5: =SUM('Cash Flow'!B7:M7) -> 1448500000
A6: Gross development value | B6: =SUM('Cash Flow'!B5:M5) -> 5004500000
A7: Total development cost | B7: =-SUM('Cash Flow'!B4:M4)-SUM('Cash Flow'!B6:M6) -> 3556000000
A8: Profit on cost | B8: =B5/B7 -> 0.40733971
