Workbook

Sheet Lease
A1: LUSAIL PLOT 14 – GROUND LEASE (LESSOR) – QAR
A3: Initial ground rent (QAR p.a.) | B3: 6200000 | D3: per lease schedule
A4: CPI assumption | B4: 0.025 | D4: IMF 2025 outlook 2.5
A5: Review every (years) | B5: 5 | D5: clause 7.2
A6: Fixed uplift at review | B6: 0.1 | D6: or CPI, whichever higher
A7: Term (years) | B7: 30
A8: Discount rate | B8: 0.075 | D8: board WACC 7.5
A9: Land value today (QAR) | B9: 68000000 | D9: valuer 2026

Sheet Rent Schedule
A3: Year | B3: 0 | C3: 1 | D3: 2 | E3: 3 | F3: 4 | G3: 5 | H3: 6 | I3: 7 | J3: 8 | K3: 9 | L3: 10 | M3: 11 | N3: 12 | O3: 13 | P3: 14 | Q3: 15 | R3: 16 | S3: 17 | T3: 18 | U3: 19 | V3: 20 | W3: 21 | X3: 22 | Y3: 23 | Z3: 24 | AA3: 25 | AB3: 26 | AC3: 27 | AD3: 28 | AE3: 29 | AF3: 30
A4: Rent | B4: 0 | C4: =IF(C3>Lease!$B$7,0,IF(C3=1,Lease!$B$3,IF(MOD(C3-1,Lease!$B$5)=0,B4*MAX(1+Lease!$B$6,(1+Lease!$B$4)^Lease!$B$5),B4))) -> 6200000 | D4: =IF(D3>Lease!$B$7,0,IF(D3=1,Lease!$B$3,IF(MOD(D3-1,Lease!$B$5)=0,C4*MAX(1+Lease!$B$6,(1+Lease!$B$4)^Lease!$B$5),C4))) -> 6200000 | E4: =IF(E3>Lease!$B$7,0,IF(E3=1,Lease!$B$3,IF(MOD(E3-1,Lease!$B$5)=0,D4*MAX(1+Lease!$B$6,(1+Lease!$B$4)^Lease!$B$5),D4))) -> 6200000 | F4: =IF(F3>Lease!$B$7,0,IF(F3=1,Lease!$B$3,IF(MOD(F3-1,Lease!$B$5)=0,E4*MAX(1+Lease!$B$6,(1+Lease!$B$4)^Lease!$B$5),E4))) -> 6200000 | G4: =IF(G3>Lease!$B$7,0,IF(G3=1,Lease!$B$3,IF(MOD(G3-1,Lease!$B$5)=0,F4*MAX(1+Lease!$B$6,(1+Lease!$B$4)^Lease!$B$5),F4))) -> 6200000 | H4: =IF(H3>Lease!$B$7,0,IF(H3=1,Lease!$B$3,IF(MOD(H3-1,Lease!$B$5)=0,G4*MAX(1+Lease!$B$6,(1+Lease!$B$4)^Lease!$B$5),G4))) -> 7014730.9 | I4: =IF(I3>Lease!$B$7,0,IF(I3=1,Lease!$B$3,IF(MOD(I3-1,Lease!$B$5)=0,H4*MAX(1+Lease!$B$6,(1+Lease!$B$4)^Lease!$B$5),H4))) -> 7014730.9 | J4: =IF(J3>Lease!$B$7,0,IF(J3=1,Lease!$B$3,IF(MOD(J3-1,Lease!$B$5)=0,I4*MAX(1+Lease!$B$6,(1+Lease!$B$4)^Lease!$B$5),I4))) -> 7014730.9 | ... AF4: =IF(AF3>Lease!$B$7,0,IF(AF3=1,Lease!$B$3,IF(MOD(AF3-1,Lease!$B$5)=0,AE4*MAX(1+Lease!$B$6,(1+Lease!$B$4)^Lease!$B$5),AE4))) -> 11494453
A5: Cash flow | B5: =-Lease!$B$9 -> -68000000 | C5: =C4 -> 6200000 | D5: =D4 -> 6200000 | E5: =E4 -> 6200000 | F5: =F4 -> 6200000 | G5: =G4 -> 6200000 | H5: =H4 -> 7014730.9 | I5: =I4 -> 7014730.9 | J5: =J4 -> 7014730.9 | ... AF5: =AF4 -> 11494453

Sheet Valuation
A3: NPV of rent | B3: =NPV(Lease!$B$8,'Rent Schedule'!C4:AF4) -> 90013593
A4: Lessor IRR | B4: =IRR('Rent Schedule'!B5:AF5) -> 0.10231049
A5: Initial yield on land | B5: =Lease!$B$3/Lease!$B$9 -> 0.091176471
A6: Total rent over term | B6: =SUM('Rent Schedule'!C4:AF4) -> 2.589229e+08
A7: Net profit | B7: =B3-Lease!$B$9 -> 22013593
