Workbook
Name Rate: Data!$G$2
Name CFs: Data!$B$2:$B$13

Sheet Data
A1: Period | B1: CF | C1: Date | D1: Cat | E1: Rent | G1: Rate | H1: Len | I1: Txt
A2: 1 | B2: -1000 | C2: 46053 | D2: Retail | E2: 100 | G2: 0.08 | H2: 6 | I2: 5 | J2: TRUE
A3: 2 | B3: 50 | C3: =EOMONTH(DATE(2026,1,31),1) -> 46081 | D3: Office | E3: 107 | I3: =""
A4: 3 | B4: 60 | C4: =EOMONTH(DATE(2026,1,31),2) -> 46112 | D4: Retail | E4: 114 | I4: abc
A5: 4 | B5: 70 | C5: =EOMONTH(DATE(2026,1,31),3) -> 46142 | D5: Hotel | E5: 121
A6: 5 | B6: 80 | C6: =EOMONTH(DATE(2026,1,31),4) -> 46173 | D6: Office | E6: 128
A7: 6 | B7: 90 | C7: =EOMONTH(DATE(2026,1,31),5) -> 46203 | D7: Retail | E7: 135
A8: 7 | B8: 100 | C8: =EOMONTH(DATE(2026,1,31),6) -> 46234 | D8: Hotel | E8: 142
A9: 8 | B9: 110 | C9: =EOMONTH(DATE(2026,1,31),7) -> 46265 | D9: Office | E9: 149
A10: 9 | B10: 120 | C10: =EOMONTH(DATE(2026,1,31),8) -> 46295 | D10: Retail | E10: 156
A11: 10 | B11: 130 | C11: =EOMONTH(DATE(2026,1,31),9) -> 46326 | D11: Hotel | E11: 163
A12: 11 | B12: 140 | C12: =EOMONTH(DATE(2026,1,31),10) -> 46356 | D12: Office | E12: 170
A13: 12 | B13: 1200 | C13: =EOMONTH(DATE(2026,1,31),11) -> 46387 | D13: Retail | E13: 177

Sheet S1
A1: 10

Sheet S2
A1: 20

Sheet S3
A1: 30

Sheet Units
A1: Unit | B1: Area | C1: Price
A2: A | B2: 100 | C2: 1.5
A3: B | B3: 120 | C3: 1.6
A4: C | B4: 90 | C4: 1.4

Sheet F
A1: Label | B1: Formula | C1: Excel expected
A2: NPV | B2: =NPV(0.08,Data!B3:B13)+Data!B2 -> 109.93182
A3: IRR | B3: =IRR(Data!B2:B13) -> 0.093951751
A4: IRR guess | B4: =IRR(Data!B2:B13,0.2) -> 0.093951751
A5: XNPV | B5: =XNPV(0.08,Data!B2:B13,Data!C2:C13) -> 1030.8
A6: XIRR | B6: =XIRR(Data!B2:B13,Data!C2:C13) -> 1.95217
A7: MIRR | B7: =MIRR(Data!B2:B13,0.06,0.1) -> 0.09558594
A8: PMT | B8: =PMT(0.07/12,240,-1000000) -> 7752.9894
A9: IPMT | B9: =IPMT(0.07/12,5,240,-1000000) -> 5788.1479
A10: PPMT | B10: =PPMT(0.07/12,5,240,-1000000) -> 1964.8415
A11: PV | B11: =PV(0.06,10,-50000,0) -> 368004.35
A12: FV | B12: =FV(0.05/12,120,-1000) -> 155282.28
A13: NPER | B13: =NPER(0.06/12,-2000,200000) -> 138.97572
A14: RATE | B14: =RATE(240,-7752.99,1000000) -> 0.0058333342
A15: CUMIPMT | B15: =CUMIPMT(0.07/12,240,1000000,1,12,0) -> -69246.371
A16: CUMPRINC | B16: =CUMPRINC(0.07/12,240,1000000,1,12,0) -> -23789.501
A17: EFFECT | B17: =EFFECT(0.06,12) -> 0.061677812
A18: NOMINAL | B18: =NOMINAL(0.0617,12) -> 0.060021003
A19: SLN | B19: =SLN(100000,10000,10) -> 9000
A20: DB | B20: =DB(100000,10000,10,1) -> 20600
A21: DDB | B21: =DDB(100000,10000,10,1) -> 20000
A22: Named range NPV | B22: =NPV(Rate,CFs) -> 101.78872
A23: DATE | B23: =DATE(2026,2,30) -> 46083 | C23: 46083
A24: EDATE end-month | B24: =EDATE(DATE(2026,1,31),1) -> 46081 | C24: 46081
A25: EOMONTH negative | B25: =EOMONTH(DATE(2026,3,15),-1) -> 46081 | C25: 46081
A26: YEARFRAC basis 0 | B26: =YEARFRAC(DATE(2026,1,31),DATE(2026,3,31),0) -> 0.16666667
A27: YEARFRAC basis 1 | B27: =YEARFRAC(DATE(2026,1,1),DATE(2027,7,1),1) -> 1.4958904
A28: YEARFRAC basis 3 | B28: =YEARFRAC(DATE(2026,1,1),DATE(2027,7,1),3) -> 1.4958904
A29: DAYS360 | B29: =DAYS360(DATE(2026,1,31),DATE(2026,3,31)) -> 60 | C29: 60
A30: DAYS | B30: =_xlfn.DAYS(DATE(2026,12,31),DATE(2026,1,1)) -> 364 | C30: 364
A31: DATEDIF m | B31: =DATEDIF(DATE(2026,1,31),DATE(2026,7,30),"m") -> 5 | C31: 5
A32: DATEDIF y | B32: =DATEDIF(DATE(2020,2,29),DATE(2026,2,28),"y") -> 5 | C32: 5
A33: NETWORKDAYS | B33: =NETWORKDAYS(DATE(2026,1,1),DATE(2026,1,31)) -> 22 | C33: 22
A34: WORKDAY | B34: =WORKDAY(DATE(2026,1,1),10) -> 46037 | C34: 46037
A35: WEEKDAY 2 | B35: =WEEKDAY(DATE(2026,1,1),2) -> 4 | C35: 4
A36: YEAR of text date | B36: =YEAR("2026-03-15") -> 2026 | C36: 2026
A37: 1900 leap serial | B37: =DATE(1900,3,1) -> 61 | C37: 61
A38: Month count from dates | B38: =(YEAR(Data!C13)-YEAR(Data!C2))*12+MONTH(Data!C13)-MONTH(Data!C2) -> 11 | C38: 11
A39: INDEX/MATCH exact | B39: =INDEX(Data!E2:E13,MATCH("Hotel",Data!D2:D13,0)) -> 121 | C39: 121
A40: MATCH approx | B40: =MATCH(105,Data!E2:E13,1) -> 1 | C40: 1
A41: MATCH descending | B41: =MATCH(25,{50,40,30,20,10},-1) -> 3 | C41: 3
A42: VLOOKUP exact | B42: =VLOOKUP(5,Data!A2:E13,5,FALSE) -> 128 | C42: 128
A43: VLOOKUP approx | B43: =VLOOKUP(5.5,Data!A2:E13,2,TRUE) -> 80 | C43: 80
A44: HLOOKUP | B44: =HLOOKUP("b",{"a","b";1,2},2,FALSE) -> 2 | C44: 2
A45: LOOKUP | B45: =LOOKUP(2,1/(Data!D2:D13="Office"),Data!E2:E13) -> 170 | C45: 170
A46: OFFSET variable width | B46: =SUM(OFFSET(Data!B2,0,0,Data!H2,1)) -> -650 | C46: -650
A47: OFFSET in NPV | B47: =NPV(0.08,OFFSET(Data!B3,0,0,Data!H2-1,1)) -> 273.35976
A48: INDIRECT text | B48: =INDIRECT("Data!B"&(1+Data!H2)) -> 90 | C48: 90
A49: INDIRECT sheet name | B49: =INDIRECT("'S2'!A1") -> 20 | C49: 20
A50: CHOOSE | B50: =CHOOSE(2,"Base","Upside","Downside") -> Upside | C50: Upside
A51: XLOOKUP | B51: =_xlfn.XLOOKUP("Hotel",Data!D2:D13,Data!E2:E13) -> 121 | C51: 121
A52: XLOOKUP not found | B52: =_xlfn.XLOOKUP("Spa",Data!D2:D13,Data!E2:E13,"none") -> none | C52: none
A53: XMATCH | B53: =_xlfn.XMATCH("Office",Data!D2:D13) -> 2 | C53: 2
A54: ROWS/COLUMNS | B54: =ROWS(Data!A2:E13)*COLUMNS(Data!A2:E13) -> 60 | C54: 60
A55: Structured ref sum | B55: =SUM(UnitTbl[Area]) -> 310 | C55: 310
A56: Structured ref sumproduct | B56: =SUMPRODUCT(UnitTbl[Area],UnitTbl[Price]) -> 468 | C56: 468
A57: 3D sum | B57: =SUM(S1:S3!A1) -> 60 | C57: 60
A58: Whole column sum | B58: =SUM(Data!E:E) -> 1662 | C58: 1662
A59: SUMIF | B59: =SUMIF(Data!D2:D13,"Retail",Data!B2:B13) -> 470 | C59: 470
A60: SUMIFS two | B60: =SUMIFS(Data!B2:B13,Data!D2:D13,"Office",Data!A2:A13,">4") -> 330 | C60: 330
A61: SUMIFS wildcard | B61: =SUMIFS(Data!E2:E13,Data!D2:D13,"Ho*") -> 426 | C61: 426
A62: COUNTIFS | B62: =COUNTIFS(Data!D2:D13,"<>Retail",Data!E2:E13,">=120") -> 6 | C62: 6
A63: AVERAGEIFS | B63: =AVERAGEIFS(Data!E2:E13,Data!D2:D13,"Retail") -> 136.4 | C63: 136.4
A64: MAXIFS | B64: =_xlfn.MAXIFS(Data!E2:E13,Data!D2:D13,"Office") -> 170 | C64: 170
A65: MINIFS | B65: =_xlfn.MINIFS(Data!E2:E13,Data!D2:D13,"Hotel") -> 121 | C65: 121
A66: SUMPRODUCT condition | B66: =SUMPRODUCT((Data!D2:D13="Retail")*Data!E2:E13) -> 682 | C66: 682
A67: SUMPRODUCT -- | B67: =SUMPRODUCT(--(Data!A2:A13>6),Data!B2:B13) -> 1800 | C67: 1800
A68: COUNTA | B68: =COUNTA(Data!D2:D13) -> 12 | C68: 12
A69: COUNTBLANK | B69: =COUNTBLANK(Data!I2:I5) -> 2 | C69: 2
A70: ROUND half | B70: =ROUND(2.5,0) -> 3 | C70: 3
A71: ROUND negative half | B71: =ROUND(-2.5,0) -> -3 | C71: -3
A72: ROUND float | B72: =ROUND(1.005,2) -> 1.01 | C72: 1.01
A73: ROUNDUP | B73: =ROUNDUP(3.14159,3) -> 3.142 | C73: 3.142
A74: ROUNDDOWN | B74: =ROUNDDOWN(-3.14159,2) -> -3.14 | C74: -3.14
A75: MROUND | B75: =MROUND(17,5) -> 15 | C75: 15
A76: CEILING | B76: =CEILING(4.3,0.5) -> 4.5 | C76: 4.5
A77: CEILING.MATH negative | B77: =_xlfn.CEILING.MATH(-4.3,1) -> -4 | C77: -4
A78: FLOOR.MATH | B78: =_xlfn.FLOOR.MATH(4.7,2) -> 4 | C78: 4
A79: INT negative | B79: =INT(-1.25) -> -2 | C79: -2
A80: TRUNC | B80: =TRUNC(-1.25) -> -1 | C80: -1
A81: MOD negative | B81: =MOD(-7,3) -> 2 | C81: 2
A82: QUOTIENT | B82: =QUOTIENT(-7,3) -> -2 | C82: -2
A83: POWER fraction | B83: =POWER(1.08,1/12) -> 1.006434
A84: SQRT | B84: =SQRT(2) -> 1.4142136
A85: LN | B85: =LN(10) -> 2.3025851
A86: PRODUCT growth | B86: =PRODUCT(1.03,1.03,1.03) -> 1.092727 | C86: 1.092727
A87: IFS | B87: =_xlfn.IFS(5>6,"a",5>4,"b",TRUE,"c") -> b | C87: b
A88: SWITCH | B88: =_xlfn.SWITCH(2,1,"one",2,"two","other") -> two | C88: two
A89: IFERROR div0 | B89: =IFERROR(1/0,0) -> 0 | C89: 0
A90: IFNA | B90: =_xlfn.IFNA(MATCH("x",{"a","b"},0),-1) -> -1 | C90: -1
A91: XOR | B91: =_xlfn.XOR(TRUE,FALSE) -> TRUE | C91: TRUE
A92: AND with range | B92: =AND(Data!E2:E13>0) -> TRUE | C92: TRUE
A93: Empty cell arithmetic | B93: =Data!I5+1 -> 1 | C93: 1
A94: Empty string arithmetic | B94: =Data!I3+1 -> #VALUE! | C94: #VALUE!
A95: Text number arithmetic | B95: =Data!I2+1 -> 6 | C95: 6
A96: Boolean arithmetic | B96: =Data!J2+1 -> 2 | C96: 2
A97: Text compare case | B97: =IF("abc"="ABC",1,0) -> 1 | C97: 1
A98: Error propagation in SUM | B98: =IFERROR(SUM(Data!B2,1/0),-1) -> -1 | C98: -1
A99: TEXT percent | B99: =TEXT(0.1234,"0.0%") -> 12.3% | C99: 12.3%
A100: TEXT thousands | B100: =TEXT(1234567.891,"#,##0.00") -> 1,234,567.89 | C100: 1,234,567.89
...
