Workbook

Sheet Inputs
A1: OFFICE ACQUISITION (USD)
A2: Purchase price | B2: 50000000
A3: Agency fee | B3: 0.02
A4: Rent year 1 | B4: 4000000
A5: Rent growth | B5: 0.03
A6: Exit yield | B6: 0.07
A7: Hold (years) | B7: 5

Sheet Cash Flow
A1: CASH FLOW
A3: Year | C3: 2026 | D3: 2027 | E3: 2028 | F3: 2029 | G3: 2030 | H3: 2031
A5: Acquisition | C5: =-Inputs!$B$2 -> -50000000 | D5: 0 | E5: 0 | F5: 0 | G5: 0 | H5: 0
A6: Acquisition costs | C6: =-Inputs!$B$2*(Inputs!$B$3) -> -1000000 | D6: 0 | E6: 0 | F6: 0 | G6: 0 | H6: 0
A7: Rent | C7: 0 | D7: =Inputs!$B$4*(1+Inputs!$B$5)^0 -> 4000000 | E7: =Inputs!$B$4*(1+Inputs!$B$5)^1 -> 4120000 | F7: =Inputs!$B$4*(1+Inputs!$B$5)^2 -> 4243600 | G7: =Inputs!$B$4*(1+Inputs!$B$5)^3 -> 4370908 | H7: =Inputs!$B$4*(1+Inputs!$B$5)^4 -> 4502035.2
A8: Sale | C8: =IF(0=Inputs!$B$7,C7*(1+Inputs!$B$5)/Inputs!$B$6,0) -> 0 | D8: =IF(1=Inputs!$B$7,D7*(1+Inputs!$B$5)/Inputs!$B$6,0) -> 0 | E8: =IF(2=Inputs!$B$7,E7*(1+Inputs!$B$5)/Inputs!$B$6,0) -> 0 | F8: =IF(3=Inputs!$B$7,F7*(1+Inputs!$B$5)/Inputs!$B$6,0) -> 0 | G8: =IF(4=Inputs!$B$7,G7*(1+Inputs!$B$5)/Inputs!$B$6,0) -> 0 | H8: =IF(5=Inputs!$B$7,H7*(1+Inputs!$B$5)/Inputs!$B$6,0) -> 66244233
A9: Net cash flow | C9: =SUM(C5:C8) -> -51000000 | D9: =SUM(D5:D8) -> 4000000 | E9: =SUM(E5:E8) -> 4120000 | F9: =SUM(F5:F8) -> 4243600 | G9: =SUM(G5:G8) -> 4370908 | H9: =SUM(H5:H8) -> 70746268

Sheet Returns
A3: Unlevered IRR | B3: =IRR('Cash Flow'!C9:H9) -> 0.12891352
A4: Net profit | B4: =SUM('Cash Flow'!C9:H9) -> 36480776
