Workbook

Sheet Inputs
A1: RIVERBEND APARTMENTS (USD)
A3: Purchase price | B3: 30000000
A4: Senior loan | B4: 21000000
A5: Initial capital (equity) | B5: 10000000
A6: Sponsor acquisition fee | B6: 216700
A7: Investor manager acquisition fee | B7: 300000
A8: Gross collections year 1 | B8: 3200000
A9: Rent growth | B9: 0.05
A10: Operating expenses (share of collections) | B10: 0.38
A11: Property management fee (share of collections) | B11: 0.0225
A12: Asset management fee (share of collections) | B12: 0.015
A13: Interest rate | B13: 0.055
A14: Refinancing loan | B14: 36000000
... A27: Tier 3 promote to Sponsor | B27: 0.3
A29: Working capital reserve | B29: =Inputs!$B$4+Inputs!$B$5-Inputs!$B$3-Inputs!$B$6-Inputs!$B$7 -> 483300

Sheet Cash Flow
A1: CASH FLOW (USD)
A3: Year | C3: 2026 | D3: 2027 | E3: 2028 | F3: 2029 | G3: 2030 | H3: 2031 | I3: 2032 | J3: 2033
A4: Period | C4: 0 | D4: =C4+1 -> 1 | E4: =D4+1 -> 2 | F4: =E4+1 -> 3 | G4: =F4+1 -> 4 | H4: =G4+1 -> 5 | I4: =H4+1 -> 6 | J4: =I4+1 -> 7
A6: Gross collections | C6: =IF(C$4>=1,Inputs!$B$8*(1+Inputs!$B$9)^(C$4-1),0) -> 0 | D6: =IF(D$4>=1,Inputs!$B$8*(1+Inputs!$B$9)^(D$4-1),0) -> 3200000 | E6: =IF(E$4>=1,Inputs!$B$8*(1+Inputs!$B$9)^(E$4-1),0) -> 3360000 | F6: =IF(F$4>=1,Inputs!$B$8*(1+Inputs!$B$9)^(F$4-1),0) -> 3528000 | G6: =IF(G$4>=1,Inputs!$B$8*(1+Inputs!$B$9)^(G$4-1),0) -> 3704400 | H6: =IF(H$4>=1,Inputs!$B$8*(1+Inputs!$B$9)^(H$4-1),0) -> 3889620 | I6: =IF(I$4>=1,Inputs!$B$8*(1+Inputs!$B$9)^(I$4-1),0) -> 4084101 | J6: =IF(J$4>=1,Inputs!$B$8*(1+Inputs!$B$9)^(J$4-1),0) -> 4288306
A7: Operating expenses | C7: =-C6*Inputs!$B$10 -> 0 | D7: =-D6*Inputs!$B$10 -> -1216000 | E7: =-E6*Inputs!$B$10 -> -1276800 | F7: =-F6*Inputs!$B$10 -> -1340640 | G7: =-G6*Inputs!$B$10 -> -1407672 | H7: =-H6*Inputs!$B$10 -> -1478055.6 | I7: =-I6*Inputs!$B$10 -> -1551958.4 | J7: =-J6*Inputs!$B$10 -> -1629556.3
A8: Property management fee | C8: =-C6*Inputs!$B$11 -> 0 | D8: =-D6*Inputs!$B$11 -> -72000 | E8: =-E6*Inputs!$B$11 -> -75600 | F8: =-F6*Inputs!$B$11 -> -79380 | G8: =-G6*Inputs!$B$11 -> -83349 | H8: =-H6*Inputs!$B$11 -> -87516.45 | I8: =-I6*Inputs!$B$11 -> -91892.273 | J8: =-J6*Inputs!$B$11 -> -96486.886
A9: Asset management fee | C9: =-C6*Inputs!$B$12 -> 0 | D9: =-D6*Inputs!$B$12 -> -48000 | E9: =-E6*Inputs!$B$12 -> -50400 | F9: =-F6*Inputs!$B$12 -> -52920 | G9: =-G6*Inputs!$B$12 -> -55566 | H9: =-H6*Inputs!$B$12 -> -58344.3 | I9: =-I6*Inputs!$B$12 -> -61261.515 | J9: =-J6*Inputs!$B$12 -> -64324.591
A10: Net operating income | C10: =SUM(C6:C9) -> 0 | D10: =SUM(D6:D9) -> 1864000 | E10: =SUM(E6:E9) -> 1957200 | F10: =SUM(F6:F9) -> 2055060 | G10: =SUM(G6:G9) -> 2157813 | H10: =SUM(H6:H9) -> 2265703.6 | I10: =SUM(I6:I9) -> 2378988.8 | J10: =SUM(J6:J9) -> 2497938.3
A11: Interest | C11: =IF(C$4>=1,-IF(C$4>Inputs!$B$15,Inputs!$B$14,Inputs!$B$4)*Inputs!$B$13,0) -> 0 | D11: =IF(D$4>=1,-IF(D$4>Inputs!$B$15,Inputs!$B$14,Inputs!$B$4)*Inputs!$B$13,0) -> -1155000 | E11: =IF(E$4>=1,-IF(E$4>Inputs!$B$15,Inputs!$B$14,Inputs!$B$4)*Inputs!$B$13,0) -> -1155000 | F11: =IF(F$4>=1,-IF(F$4>Inputs!$B$15,Inputs!$B$14,Inputs!$B$4)*Inputs!$B$13,0) -> -1155000 | G11: =IF(G$4>=1,-IF(G$4>Inputs!$B$15,Inputs!$B$14,Inputs!$B$4)*Inputs!$B$13,0) -> -1980000 | H11: =IF(H$4>=1,-IF(H$4>Inputs!$B$15,Inputs!$B$14,Inputs!$B$4)*Inputs!$B$13,0) -> -1980000 | I11: =IF(I$4>=1,-IF(I$4>Inputs!$B$15,Inputs!$B$14,Inputs!$B$4)*Inputs!$B$13,0) -> -1980000 | J11: =IF(J$4>=1,-IF(J$4>Inputs!$B$15,Inputs!$B$14,Inputs!$B$4)*Inputs!$B$13,0) -> -1980000
A12: Refinancing proceeds | C12: =IF(C$4=Inputs!$B$15,Inputs!$B$14-Inputs!$B$4,0) -> 0 | D12: =IF(D$4=Inputs!$B$15,Inputs!$B$14-Inputs!$B$4,0) -> 0 | E12: =IF(E$4=Inputs!$B$15,Inputs!$B$14-Inputs!$B$4,0) -> 0 | F12: =IF(F$4=Inputs!$B$15,Inputs!$B$14-Inputs!$B$4,0) -> 15000000 | G12: =IF(G$4=Inputs!$B$15,Inputs!$B$14-Inputs!$B$4,0) -> 0 | H12: =IF(H$4=Inputs!$B$15,Inputs!$B$14-Inputs!$B$4,0) -> 0 | I12: =IF(I$4=Inputs!$B$15,Inputs!$B$14-Inputs!$B$4,0) -> 0 | J12: =IF(J$4=Inputs!$B$15,Inputs!$B$14-Inputs!$B$4,0) -> 0
A13: Sale proceeds (net of debt) | C13: =IF(C$4=Inputs!$B$18,C10*(1+Inputs!$B$9)/Inputs!$B$16*(1-Inputs!$B$17)-Inputs!$B$14+Inputs!$B$29,0) -> 0 | D13: =IF(D$4=Inputs!$B$18,D10*(1+Inputs!$B$9)/Inputs!$B$16*(1-Inputs!$B$17)-Inputs!$B$14+Inputs!$B$29,0) -> 0 | E13: =IF(E$4=Inputs!$B$18,E10*(1+Inputs!$B$9)/Inputs!$B$16*(1-Inputs!$B$17)-Inputs!$B$14+Inputs!$B$29,0) -> 0 | F13: =IF(F$4=Inputs!$B$18,F10*(1+Inputs!$B$9)/Inputs!$B$16*(1-Inputs!$B$17)-Inputs!$B$14+Inputs!$B$29,0) -> 0 | G13: =IF(G$4=Inputs!$B$18,G10*(1+Inputs!$B$9)/Inputs!$B$16*(1-Inputs!$B$17)-Inputs!$B$14+Inputs!$B$29,0) -> 0 | H13: =IF(H$4=Inputs!$B$18,H10*(1+Inputs!$B$9)/Inputs!$B$16*(1-Inputs!$B$17)-Inputs!$B$14+Inputs!$B$29,0) -> 0 | I13: =IF(I$4=Inputs!$B$18,I10*(1+Inputs!$B$9)/Inputs!$B$16*(1-Inputs!$B$17)-Inputs!$B$14+Inputs!$B$29,0) -> 0 | J13: =IF(J$4=Inputs!$B$18,J10*(1+Inputs!$B$9)/Inputs!$B$16*(1-Inputs!$B$17)-Inputs!$B$14+Inputs!$B$29,0) -> 13442890
A14: Distributable cash | C14: =IF(C$4>=1,MAX(0,C10+C11+C12+C13),0) -> 0 | D14: =IF(D$4>=1,MAX(0,D10+D11+D12+D13),0) -> 709000 | E14: =IF(E$4>=1,MAX(0,E10+E11+E12+E13),0) -> 802200 | F14: =IF(F$4>=1,MAX(0,F10+F11+F12+F13),0) -> 15900060 | G14: =IF(G$4>=1,MAX(0,G10+G11+G12+G13),0) -> 177813 | H14: =IF(H$4>=1,MAX(0,H10+H11+H12+H13),0) -> 285703.65 | I14: =IF(I$4>=1,MAX(0,I10+I11+I12+I13),0) -> 398988.83 | J14: =IF(J$4>=1,MAX(0,J10+J11+J12+J13),0) -> 13960828
A15: Equity contributions | C15: =IF(C$4=0,Inputs!$B$5,0) -> 10000000 | D15: =IF(D$4=0,Inputs!$B$5,0) -> 0 | E15: =IF(E$4=0,Inputs!$B$5,0) -> 0 | F15: =IF(F$4=0,Inputs!$B$5,0) -> 0 | G15: =IF(G$4=0,Inputs!$B$5,0) -> 0 | H15: =IF(H$4=0,Inputs!$B$5,0) -> 0 | I15: =IF(I$4=0,Inputs!$B$5,0) -> 0 | J15: =IF(J$4=0,Inputs!$B$5,0) -> 0

Sheet Waterfall
A1: DISTRIBUTION WATERFALL (USD)
A3: Year | C3: ='Cash Flow'!C3 -> 2026 | D3: ='Cash Flow'!D3 -> 2027 | E3: ='Cash Flow'!E3 -> 2028 | F3: ='Cash Flow'!F3 -> 2029 | G3: ='Cash Flow'!G3 -> 2030 | H3: ='Cash Flow'!H3 -> 2031 | I3: ='Cash Flow'!I3 -> 2032 | J3: ='Cash Flow'!J3 -> 2033
A4: Period | C4: ='Cash Flow'!C4 -> 0 | D4: ='Cash Flow'!D4 -> 1 | E4: ='Cash Flow'!E4 -> 2 | F4: ='Cash Flow'!F4 -> 3 | G4: ='Cash Flow'!G4 -> 4 | H4: ='Cash Flow'!H4 -> 5 | I4: ='Cash Flow'!I4 -> 6 | J4: ='Cash Flow'!J4 -> 7
A6: Contributions | C6: ='Cash Flow'!C15 -> 10000000 | D6: ='Cash Flow'!D15 -> 0 | E6: ='Cash Flow'!E15 -> 0 | F6: ='Cash Flow'!F15 -> 0 | G6: ='Cash Flow'!G15 -> 0 | H6: ='Cash Flow'!H15 -> 0 | I6: ='Cash Flow'!I15 -> 0 | J6: ='Cash Flow'!J15 -> 0
A7: Distributable cash | C7: ='Cash Flow'!C14 -> 0 | D7: ='Cash Flow'!D14 -> 709000 | E7: ='Cash Flow'!E14 -> 802200 | F7: ='Cash Flow'!F14 -> 15900060 | G7: ='Cash Flow'!G14 -> 177813 | H7: ='Cash Flow'!H14 -> 285703.65 | I7: ='Cash Flow'!I14 -> 398988.83 | J7: ='Cash Flow'!J14 -> 13960828
A9: Hurdle 1 balance before distribution | C9: =C6 -> 10000000 | D9: =C11*(1+Inputs!$B$22)+D6 -> 11000000 | E9: =D11*(1+Inputs!$B$22)+E6 -> 11320100 | F9: =E11*(1+Inputs!$B$22)+F6 -> 11569690 | G9: =F11*(1+Inputs!$B$22)+G6 -> -2445956.6 | H9: =G11*(1+Inputs!$B$22)+H6 -> -2690552.2 | I9: =H11*(1+Inputs!$B$22)+I6 -> -2959607.4 | J9: =I11*(1+Inputs!$B$22)+J6 -> -3255568.2
A10: Tier 1 distribution (to 10% IRR) | C10: =MIN(C7,MAX(0,C9)) -> 0 | D10: =MIN(D7,MAX(0,D9)) -> 709000 | E10: =MIN(E7,MAX(0,E9)) -> 802200 | F10: =MIN(F7,MAX(0,F9)) -> 11569690 | G10: =MIN(G7,MAX(0,G9)) -> 0 | H10: =MIN(H7,MAX(0,H9)) -> 0 | I10: =MIN(I7,MAX(0,I9)) -> 0 | J10: =MIN(J7,MAX(0,J9)) -> 0
A11: Hurdle 1 balance after distribution | C11: =C9-C10-C14 -> 10000000 | D11: =D9-D10-D14 -> 10291000 | E11: =E9-E10-E14 -> 10517900 | F11: =F9-F10-F14 -> -2223596.9 | G11: =G9-G10-G14 -> -2445956.6 | H11: =H9-H10-H14 -> -2690552.2 | I11: =I9-I10-I14 -> -2959607.4 | J11: =J9-J10-J14 -> -3255568.2
A13: Hurdle 2 Investor balance before distribution | C13: =C6*Inputs!$B$20 -> 8950000 | D13: =C15*(1+Inputs!$B$23)+D6*Inputs!$B$20 -> 10292500 | E13: =D15*(1+Inputs!$B$23)+E6*Inputs!$B$20 -> 11106637 | F13: =E15*(1+Inputs!$B$23)+F6*Inputs!$B$20 -> 11946968 | G13: =F15*(1+Inputs!$B$23)+G6*Inputs!$B$20 -> 0 | H13: =G15*(1+Inputs!$B$23)+H6*Inputs!$B$20 -> 0 | I13: =H15*(1+Inputs!$B$23)+I6*Inputs!$B$20 -> 0 | J13: =I15*(1+Inputs!$B$23)+J6*Inputs!$B$20 -> 0
A14: Tier 2 distribution (to Investor 17% IRR) | C14: =MIN(C7-C10,MAX(0,C13-C10*Inputs!$B$20)/(Inputs!$B$24*Inputs!$B$20)) -> 0 | D14: =MIN(D7-D10,MAX(0,D13-D10*Inputs!$B$20)/(Inputs!$B$24*Inputs!$B$20)) -> 0 | E14: =MIN(E7-E10,MAX(0,E13-E10*Inputs!$B$20)/(Inputs!$B$24*Inputs!$B$20)) -> 0 | F14: =MIN(F7-F10,MAX(0,F13-F10*Inputs!$B$20)/(Inputs!$B$24*Inputs!$B$20)) -> 2223596.9 | G14: =MIN(G7-G10,MAX(0,G13-G10*Inputs!$B$20)/(Inputs!$B$24*Inputs!$B$20)) -> 0 | H14: =MIN(H7-H10,MAX(0,H13-H10*Inputs!$B$20)/(Inputs!$B$24*Inputs!$B$20)) -> 0 | I14: =MIN(I7-I10,MAX(0,I13-I10*Inputs!$B$20)/(Inputs!$B$24*Inputs!$B$20)) -> 0 | J14: =MIN(J7-J10,MAX(0,J13-J10*Inputs!$B$20)/(Inputs!$B$24*Inputs!$B$20)) -> 0
A15: Hurdle 2 Investor balance after distribution | C15: =C13-C10*Inputs!$B$20-C14*Inputs!$B$24*Inputs!$B$20 -> 8950000 | D15: =D13-D10*Inputs!$B$20-D14*Inputs!$B$24*Inputs!$B$20 -> 9657945 | E15: =E13-E10*Inputs!$B$20-E14*Inputs!$B$24*Inputs!$B$20 -> 10388668 | F15: =F13-F10*Inputs!$B$20-F14*Inputs!$B$24*Inputs!$B$20 -> 0 | G15: =G13-G10*Inputs!$B$20-G14*Inputs!$B$24*Inputs!$B$20 -> 0 | H15: =H13-H10*Inputs!$B$20-H14*Inputs!$B$24*Inputs!$B$20 -> 0 | I15: =I13-I10*Inputs!$B$20-I14*Inputs!$B$24*Inputs!$B$20 -> 0 | J15: =J13-J10*Inputs!$B$20-J14*Inputs!$B$24*Inputs!$B$20 -> 0
A17: Tier 3 distribution (thereafter) | C17: =C7-C10-C14 -> 0 | D17: =D7-D10-D14 -> 0 | E17: =E7-E10-E14 -> 0 | F17: =F7-F10-F14 -> 2106773.1 | G17: =G7-G10-G14 -> 177813 | H17: =H7-H10-H14 -> 285703.65 | I17: =I7-I10-I14 -> 398988.83 | J17: =J7-J10-J14 -> 13960828
A19: Promote to Sponsor | C19: =C14*Inputs!$B$25+C17*Inputs!$B$27 -> 0 | D19: =D14*Inputs!$B$25+D17*Inputs!$B$27 -> 0 | E19: =E14*Inputs!$B$25+E17*Inputs!$B$27 -> 0 | F19: =F14*Inputs!$B$25+F17*Inputs!$B$27 -> 1076751.3 | G19: =G14*Inputs!$B$25+G17*Inputs!$B$27 -> 53343.9 | H19: =H14*Inputs!$B$25+H17*Inputs!$B$27 -> 85711.095 | I19: =I14*Inputs!$B$25+I17*Inputs!$B$27 -> 119696.65 | J19: =J14*Inputs!$B$25+J17*Inputs!$B$27 -> 4188248.5
A20: Distributed to partners pro rata | C20: =C10+C14*Inputs!$B$24+C17*Inputs!$B$26 -> 0 | D20: =D10+D14*Inputs!$B$24+D17*Inputs!$B$26 -> 709000 | E20: =E10+E14*Inputs!$B$24+E17*Inputs!$B$26 -> 802200 | F20: =F10+F14*Inputs!$B$24+F17*Inputs!$B$26 -> 14823309 | G20: =G10+G14*Inputs!$B$24+G17*Inputs!$B$26 -> 124469.1 | H20: =H10+H14*Inputs!$B$24+H17*Inputs!$B$26 -> 199992.56 | I20: =I10+I14*Inputs!$B$24+I17*Inputs!$B$26 -> 279292.18 | J20: =J10+J14*Inputs!$B$24+J17*Inputs!$B$26 -> 9772579.9
A21: Investor net cash flow | C21: =-C6*Inputs!$B$20+C20*Inputs!$B$20 -> -8950000 | D21: =-D6*Inputs!$B$20+D20*Inputs!$B$20 -> 634555 | E21: =-E6*Inputs!$B$20+E20*Inputs!$B$20 -> 717969 | F21: =-F6*Inputs!$B$20+F20*Inputs!$B$20 -> 13266861 | G21: =-G6*Inputs!$B$20+G20*Inputs!$B$20 -> 111399.84 | H21: =-H6*Inputs!$B$20+H20*Inputs!$B$20 -> 178993.34 | I21: =-I6*Inputs!$B$20+I20*Inputs!$B$20 -> 249966.5 | J21: =-J6*Inputs!$B$20+J20*Inputs!$B$20 -> 8746459
A22: Sponsor net cash flow | C22: =-C6*Inputs!$B$21+C20*Inputs!$B$21+C19 -> -1000000 | D22: =-D6*Inputs!$B$21+D20*Inputs!$B$21+D19 -> 70900 | E22: =-E6*Inputs!$B$21+E20*Inputs!$B$21+E19 -> 80220 | F22: =-F6*Inputs!$B$21+F20*Inputs!$B$21+F19 -> 2559082.2 | G22: =-G6*Inputs!$B$21+G20*Inputs!$B$21+G19 -> 65790.81 | H22: =-H6*Inputs!$B$21+H20*Inputs!$B$21+H19 -> 105710.35 | I22: =-I6*Inputs!$B$21+I20*Inputs!$B$21+I19 -> 147625.87 | J22: =-J6*Inputs!$B$21+J20*Inputs!$B$21+J19 -> 5165506.5
A23: GP net cash flow | C23: =-C6*Inputs!$B$19+C20*Inputs!$B$19 -> -50000 | D23: =-D6*Inputs!$B$19+D20*Inputs!$B$19 -> 3545 | E23: =-E6*Inputs!$B$19+E20*Inputs!$B$19 -> 4011 | F23: =-F6*Inputs!$B$19+F20*Inputs!$B$19 -> 74116.543 | G23: =-G6*Inputs!$B$19+G20*Inputs!$B$19 -> 622.3455 | H23: =-H6*Inputs!$B$19+H20*Inputs!$B$19 -> 999.96278 | I23: =-I6*Inputs!$B$19+I20*Inputs!$B$19 -> 1396.4609 | J23: =-J6*Inputs!$B$19+J20*Inputs!$B$19 -> 48862.9
A25: Equity net cash flow | C25: =C7-C6 -> -10000000 | D25: =D7-D6 -> 709000 | E25: =E7-E6 -> 802200 | F25: =F7-F6 -> 15900060 | G25: =G7-G6 -> 177813 | H25: =H7-H6 -> 285703.65 | I25: =I7-I6 -> 398988.83 | J25: =J7-J6 -> 13960828

Sheet Returns
A1: RETURNS
A3: Levered IRR | B3: =IRR(Waterfall!C25:J25) -> 0.32412417
A4: LP IRR | B4: =IRR(Waterfall!C21:J21) -> 0.28056897
A5: Sponsor IRR | B5: =IRR(Waterfall!C22:J22) -> 0.56606951
A6: Carried interest (promote) total | B6: =SUM(Waterfall!C19:J19) -> 5523751.5
A7: Equity multiple | B7: =SUM(Waterfall!C7:J7)/SUM(Waterfall!C6:J6) -> 3.2234594
