Workbook

Sheet Inputs
A1: CEDAR PARK – ROLES (USD)
A2: Purchase price | B2: 50000000
A3: NOI yield on cost | B3: 0.08
A4: GFA | B4: 10000
A5: Fit-out cost per sqm | B5: 500
A6: Rent uplift | B6: 300000
A7: Exit yield | B7: 0.07

Sheet Cash Flow
A1: Year | B1: 0 | C1: 1 | D1: 2 | E1: 3 | F1: 4 | G1: 5
A2: NOI | B2: =0 | C2: =Inputs!$B$2*Inputs!$B$3 | D2: =Inputs!$B$2*Inputs!$B$3 | E2: =Inputs!$B$2*Inputs!$B$3 | F2: =Inputs!$B$2*Inputs!$B$3 | G2: =Inputs!$B$2*Inputs!$B$3
A3: Fit-out | B3: =-Inputs!$B$4*Inputs!$B$5 | C3: =0 | D3: =0 | E3: =0 | F3: =0 | G3: =0
A4: Rent uplift | B4: =0 | C4: =-Inputs!$B$6 | D4: =-Inputs!$B$6 | E4: =-Inputs!$B$6 | F4: =-Inputs!$B$6 | G4: =-Inputs!$B$6
A5: Net cash flow | B5: =IF(B1=0,-Inputs!$B$2,0)+B2+B3+B4+IF(B1=5,B2/Inputs!$B$7,0) | C5: =IF(C1=0,-Inputs!$B$2,0)+C2+C3+C4+IF(C1=5,C2/Inputs!$B$7,0) | D5: =IF(D1=0,-Inputs!$B$2,0)+D2+D3+D4+IF(D1=5,D2/Inputs!$B$7,0) | E5: =IF(E1=0,-Inputs!$B$2,0)+E2+E3+E4+IF(E1=5,E2/Inputs!$B$7,0) | F5: =IF(F1=0,-Inputs!$B$2,0)+F2+F3+F4+IF(F1=5,F2/Inputs!$B$7,0) | G5: =IF(G1=0,-Inputs!$B$2,0)+G2+G3+G4+IF(G1=5,G2/Inputs!$B$7,0)

Sheet Returns
A1: Unlevered IRR | B1: =IRR('Cash Flow'!B5:G5)
A2: Net profit | B2: =SUM('Cash Flow'!B5:G5)
