Workbook

Sheet Inputs
A1: NORTH QUAY – QUARTERLY (USD)
A2: First quarter end | B2: 46477
A3: Price | B3: 40000000
A4: Acquisition quarter | B4: 2
A5: Exit quarter | B5: 10
A6: NOI yield | B6: 0.07
A7: Exit yield | B7: 0.065
A8: Preferred return | B8: 0.08

Sheet Cash Flow
A1: Quarter | B1: 1 | C1: 2 | D1: 3 | E1: 4 | F1: 5 | G1: 6 | H1: 7 | I1: 8 | J1: 9 | K1: 10 | L1: 11 | M1: 12
A2: Date | B2: =EDATE(Inputs!$B$2,3*(B1-1)) | C2: =EDATE(Inputs!$B$2,3*(C1-1)) | D2: =EDATE(Inputs!$B$2,3*(D1-1)) | E2: =EDATE(Inputs!$B$2,3*(E1-1)) | F2: =EDATE(Inputs!$B$2,3*(F1-1)) | G2: =EDATE(Inputs!$B$2,3*(G1-1)) | H2: =EDATE(Inputs!$B$2,3*(H1-1)) | I2: =EDATE(Inputs!$B$2,3*(I1-1)) | ... M2: =EDATE(Inputs!$B$2,3*(M1-1))
A3: Net cash flow | B3: =IF(B1=Inputs!$B$4,-Inputs!$B$3,0)+IF(AND(B1>Inputs!$B$4,B1<=Inputs!$B$5),Inputs!$B$3*Inputs!$B$6/4,0)+IF(B1=Inputs!$B$5,Inputs!$B$3*Inputs!$B$6/Inputs!$B$7,0) | C3: =IF(C1=Inputs!$B$4,-Inputs!$B$3,0)+IF(AND(C1>Inputs!$B$4,C1<=Inputs!$B$5),Inputs!$B$3*Inputs!$B$6/4,0)+IF(C1=Inputs!$B$5,Inputs!$B$3*Inputs!$B$6/Inputs!$B$7,0) | D3: =IF(D1=Inputs!$B$4,-Inputs!$B$3,0)+IF(AND(D1>Inputs!$B$4,D1<=Inputs!$B$5),Inputs!$B$3*Inputs!$B$6/4,0)+IF(D1=Inputs!$B$5,Inputs!$B$3*Inputs!$B$6/Inputs!$B$7,0) | E3: =IF(E1=Inputs!$B$4,-Inputs!$B$3,0)+IF(AND(E1>Inputs!$B$4,E1<=Inputs!$B$5),Inputs!$B$3*Inputs!$B$6/4,0)+IF(E1=Inputs!$B$5,Inputs!$B$3*Inputs!$B$6/Inputs!$B$7,0) | F3: =IF(F1=Inputs!$B$4,-Inputs!$B$3,0)+IF(AND(F1>Inputs!$B$4,F1<=Inputs!$B$5),Inputs!$B$3*Inputs!$B$6/4,0)+IF(F1=Inputs!$B$5,Inputs!$B$3*Inputs!$B$6/Inputs!$B$7,0) | G3: =IF(G1=Inputs!$B$4,-Inputs!$B$3,0)+IF(AND(G1>Inputs!$B$4,G1<=Inputs!$B$5),Inputs!$B$3*Inputs!$B$6/4,0)+IF(G1=Inputs!$B$5,Inputs!$B$3*Inputs!$B$6/Inputs!$B$7,0) | H3: =IF(H1=Inputs!$B$4,-Inputs!$B$3,0)+IF(AND(H1>Inputs!$B$4,H1<=Inputs!$B$5),Inputs!$B$3*Inputs!$B$6/4,0)+IF(H1=Inputs!$B$5,Inputs!$B$3*Inputs!$B$6/Inputs!$B$7,0) | I3: =IF(I1=Inputs!$B$4,-Inputs!$B$3,0)+IF(AND(I1>Inputs!$B$4,I1<=Inputs!$B$5),Inputs!$B$3*Inputs!$B$6/4,0)+IF(I1=Inputs!$B$5,Inputs!$B$3*Inputs!$B$6/Inputs!$B$7,0) | ... M3: =IF(M1=Inputs!$B$4,-Inputs!$B$3,0)+IF(AND(M1>Inputs!$B$4,M1<=Inputs!$B$5),Inputs!$B$3*Inputs!$B$6/4,0)+IF(M1=Inputs!$B$5,Inputs!$B$3*Inputs!$B$6/Inputs!$B$7,0)
A4: Hurdle balance | B4: =0*(1+Inputs!$B$8)^(1/4)-B3 | C4: =B4*(1+Inputs!$B$8)^(1/4)-C3 | D4: =C4*(1+Inputs!$B$8)^(1/4)-D3 | E4: =D4*(1+Inputs!$B$8)^(1/4)-E3 | F4: =E4*(1+Inputs!$B$8)^(1/4)-F3 | G4: =F4*(1+Inputs!$B$8)^(1/4)-G3 | H4: =G4*(1+Inputs!$B$8)^(1/4)-H3 | I4: =H4*(1+Inputs!$B$8)^(1/4)-I3 | J4: =I4*(1+Inputs!$B$8)^(1/4)-J3 | ... M4: =L4*(1+Inputs!$B$8)^(1/4)-M3

Sheet Returns
A1: Unlevered IRR | B1: =XIRR('Cash Flow'!B3:M3,'Cash Flow'!B2:M2)
A2: Net profit | B2: =SUM('Cash Flow'!B3:M3)
