Workbook

Sheet Inputs
A1: AL RAWDA – DEVELOPMENT (SAR '000)
A2: Land | B2: 40000
A3: Construction | B3: 120000
A4: Sales | B4: 210000
A5: Loan to cost | B5: 0.5

Sheet Cash Flow
A1: Cash flow (SAR '000)
A2: Year | B2: 1 | C2: 2 | D2: 3 | E2: 4 | F2: 5
A3: Cost | B3: =-(Inputs!$B$2*1+Inputs!$B$3*0.6) | C3: =-(Inputs!$B$2*0+Inputs!$B$3*0.4) | D3: =-(Inputs!$B$2*0+Inputs!$B$3*0) | E3: =-(Inputs!$B$2*0+Inputs!$B$3*0) | F3: =-(Inputs!$B$2*0+Inputs!$B$3*0)
A4: Sales | B4: =Inputs!$B$4*0 | C4: =Inputs!$B$4*0.4 | D4: =Inputs!$B$4*0.6 | E4: =Inputs!$B$4*0 | F4: =Inputs!$B$4*0
A5: Loan balance | B5: =-SUM($B$3:B3)*Inputs!$B$5*0.5 | C5: =-SUM($B$3:C3)*Inputs!$B$5*1.0 | D5: =-SUM($B$3:D3)*Inputs!$B$5*0 | E5: =-SUM($B$3:E3)*Inputs!$B$5*0 | F5: =-SUM($B$3:F3)*Inputs!$B$5*0
A6: Equity cash flow | B6: =B3+B4+(B5-0) | C6: =C3+C4+(C5-B5) | D6: =D3+D4+(D5-C5) | E6: =E3+E4+(E5-D5) | F6: =F3+F4+(F5-E5)

Sheet Returns
A1: Returns (SAR '000)
A2: Net profit | B2: =SUM('Cash Flow'!B3:F4)
A3: Peak debt | B3: =MAX('Cash Flow'!B5:F5)
A4: Levered IRR | B4: =IRR('Cash Flow'!B6:F6)
