Workbook

Sheet Inputs
A1: TE AWA RETIREMENT VILLAGE – ORA / DMF MODEL (NZ$)
A3: Independent living units | B3: 160
A4: Occupation right price (NZ$) | B4: 780000
A5: Units sold per year (first sales) | B5: 45
A6: Build cost per unit (NZ$) | B6: 505000
A7: Land (NZ$) | B7: 21000000
A8: DMF (% of ORA) | B8: 0.3
A9: DMF accrual period (years) | B9: 3
A10: Average tenure (years) | B10: 8
A11: House price growth | B11: 0.035
A12: Weekly fee (NZ$) | B12: 165
A13: Village opex per unit (NZ$/yr) | B13: 9800
A14: Discount rate | B14: 0.09

Sheet Cash Flow
A3: Year | B3: 0 | C3: 1 | D3: 2 | E3: 3 | F3: 4 | G3: 5 | H3: 6 | I3: 7 | J3: 8 | K3: 9 | L3: 10 | M3: 11 | N3: 12 | O3: 13 | P3: 14 | Q3: 15
A4: First sales (units) | B4: =0 -> 0 | C4: =IF(C$3=0,0,MIN(Inputs!$B$5,Inputs!$B$3-B5)) -> 45 | D4: =IF(D$3=0,0,MIN(Inputs!$B$5,Inputs!$B$3-C5)) -> 45 | E4: =IF(E$3=0,0,MIN(Inputs!$B$5,Inputs!$B$3-D5)) -> 45 | F4: =IF(F$3=0,0,MIN(Inputs!$B$5,Inputs!$B$3-E5)) -> 25 | G4: =IF(G$3=0,0,MIN(Inputs!$B$5,Inputs!$B$3-F5)) -> 0 | H4: =IF(H$3=0,0,MIN(Inputs!$B$5,Inputs!$B$3-G5)) -> 0 | I4: =IF(I$3=0,0,MIN(Inputs!$B$5,Inputs!$B$3-H5)) -> 0 | J4: =IF(J$3=0,0,MIN(Inputs!$B$5,Inputs!$B$3-I5)) -> 0 | ... Q4: =IF(Q$3=0,0,MIN(Inputs!$B$5,Inputs!$B$3-P5)) -> 0
A5: Cumulative sold | B5: =B4 -> 0 | C5: =B5+C4 -> 45 | D5: =C5+D4 -> 90 | E5: =D5+E4 -> 135 | F5: =E5+F4 -> 160 | G5: =F5+G4 -> 160 | H5: =G5+H4 -> 160 | I5: =H5+I4 -> 160 | J5: =I5+J4 -> 160 | ... Q5: =P5+Q4 -> 160
A6: ORA receipts (first sales) | B6: =B4*Inputs!$B$4*(1+Inputs!$B$11)^B$3 -> 0 | C6: =C4*Inputs!$B$4*(1+Inputs!$B$11)^C$3 -> 36328500 | D6: =D4*Inputs!$B$4*(1+Inputs!$B$11)^D$3 -> 37599998 | E6: =E4*Inputs!$B$4*(1+Inputs!$B$11)^E$3 -> 38915997 | F6: =F4*Inputs!$B$4*(1+Inputs!$B$11)^F$3 -> 22376699 | G6: =G4*Inputs!$B$4*(1+Inputs!$B$11)^G$3 -> 0 | H6: =H4*Inputs!$B$4*(1+Inputs!$B$11)^H$3 -> 0 | I6: =I4*Inputs!$B$4*(1+Inputs!$B$11)^I$3 -> 0 | ... Q6: =Q4*Inputs!$B$4*(1+Inputs!$B$11)^Q$3 -> 0
A7: Resales (units) | B7: =0 -> 0 | C7: =B5/Inputs!$B$10 -> 0 | D7: =C5/Inputs!$B$10 -> 5.625 | E7: =D5/Inputs!$B$10 -> 11.25 | F7: =E5/Inputs!$B$10 -> 16.875 | G7: =F5/Inputs!$B$10 -> 20 | H7: =G5/Inputs!$B$10 -> 20 | I7: =H5/Inputs!$B$10 -> 20 | J7: =I5/Inputs!$B$10 -> 20 | ... Q7: =P5/Inputs!$B$10 -> 20
A8: DMF on resales | B8: =B7*Inputs!$B$4*Inputs!$B$8*MIN(1,Inputs!$B$10/Inputs!$B$9) -> 0 | C8: =C7*Inputs!$B$4*Inputs!$B$8*MIN(1,Inputs!$B$10/Inputs!$B$9) -> 0 | D8: =D7*Inputs!$B$4*Inputs!$B$8*MIN(1,Inputs!$B$10/Inputs!$B$9) -> 1316250 | E8: =E7*Inputs!$B$4*Inputs!$B$8*MIN(1,Inputs!$B$10/Inputs!$B$9) -> 2632500 | F8: =F7*Inputs!$B$4*Inputs!$B$8*MIN(1,Inputs!$B$10/Inputs!$B$9) -> 3948750 | G8: =G7*Inputs!$B$4*Inputs!$B$8*MIN(1,Inputs!$B$10/Inputs!$B$9) -> 4680000 | H8: =H7*Inputs!$B$4*Inputs!$B$8*MIN(1,Inputs!$B$10/Inputs!$B$9) -> 4680000 | I8: =I7*Inputs!$B$4*Inputs!$B$8*MIN(1,Inputs!$B$10/Inputs!$B$9) -> 4680000 | ... Q8: =Q7*Inputs!$B$4*Inputs!$B$8*MIN(1,Inputs!$B$10/Inputs!$B$9) -> 4680000
A9: Resale gain | B9: =B7*Inputs!$B$4*((1+Inputs!$B$11)^B$3-(1+Inputs!$B$11)^MAX(0,B$3-Inputs!$B$10)) -> 0 | C9: =C7*Inputs!$B$4*((1+Inputs!$B$11)^C$3-(1+Inputs!$B$11)^MAX(0,C$3-Inputs!$B$10)) -> 0 | D9: =D7*Inputs!$B$4*((1+Inputs!$B$11)^D$3-(1+Inputs!$B$11)^MAX(0,D$3-Inputs!$B$10)) -> 312499.69 | E9: =E7*Inputs!$B$4*((1+Inputs!$B$11)^E$3-(1+Inputs!$B$11)^MAX(0,E$3-Inputs!$B$10)) -> 953999.35 | F9: =F7*Inputs!$B$4*((1+Inputs!$B$11)^F$3-(1+Inputs!$B$11)^MAX(0,F$3-Inputs!$B$10)) -> 1941771.5 | G9: =G7*Inputs!$B$4*((1+Inputs!$B$11)^G$3-(1+Inputs!$B$11)^MAX(0,G$3-Inputs!$B$10)) -> 2927906.4 | H9: =H7*Inputs!$B$4*((1+Inputs!$B$11)^H$3-(1+Inputs!$B$11)^MAX(0,H$3-Inputs!$B$10)) -> 3576383.1 | I9: =I7*Inputs!$B$4*((1+Inputs!$B$11)^I$3-(1+Inputs!$B$11)^MAX(0,I$3-Inputs!$B$10)) -> 4247556.5 | ... Q9: =Q7*Inputs!$B$4*((1+Inputs!$B$11)^Q$3-(1+Inputs!$B$11)^MAX(0,Q$3-Inputs!$B$10)) -> 6287885.3
A10: Weekly fees | B10: =B5*Inputs!$B$12*52 -> 0 | C10: =C5*Inputs!$B$12*52 -> 386100 | D10: =D5*Inputs!$B$12*52 -> 772200 | E10: =E5*Inputs!$B$12*52 -> 1158300 | F10: =F5*Inputs!$B$12*52 -> 1372800 | G10: =G5*Inputs!$B$12*52 -> 1372800 | H10: =H5*Inputs!$B$12*52 -> 1372800 | I10: =I5*Inputs!$B$12*52 -> 1372800 | ... Q10: =Q5*Inputs!$B$12*52 -> 1372800
A11: Village opex | B11: =-B5*Inputs!$B$13 -> 0 | C11: =-C5*Inputs!$B$13 -> -441000 | D11: =-D5*Inputs!$B$13 -> -882000 | E11: =-E5*Inputs!$B$13 -> -1323000 | F11: =-F5*Inputs!$B$13 -> -1568000 | G11: =-G5*Inputs!$B$13 -> -1568000 | H11: =-H5*Inputs!$B$13 -> -1568000 | I11: =-I5*Inputs!$B$13 -> -1568000 | ... Q11: =-Q5*Inputs!$B$13 -> -1568000
A12: Build cost | B12: =-IF(B$3<=3,Inputs!$B$3*Inputs!$B$6/4,0) -> -20200000 | C12: =-IF(C$3<=3,Inputs!$B$3*Inputs!$B$6/4,0) -> -20200000 | D12: =-IF(D$3<=3,Inputs!$B$3*Inputs!$B$6/4,0) -> -20200000 | E12: =-IF(E$3<=3,Inputs!$B$3*Inputs!$B$6/4,0) -> -20200000 | F12: =-IF(F$3<=3,Inputs!$B$3*Inputs!$B$6/4,0) -> 0 | G12: =-IF(G$3<=3,Inputs!$B$3*Inputs!$B$6/4,0) -> 0 | H12: =-IF(H$3<=3,Inputs!$B$3*Inputs!$B$6/4,0) -> 0 | I12: =-IF(I$3<=3,Inputs!$B$3*Inputs!$B$6/4,0) -> 0 | ... Q12: =-IF(Q$3<=3,Inputs!$B$3*Inputs!$B$6/4,0) -> 0
A13: Land | B13: =IF(B$3=0,-Inputs!$B$7,0) -> -21000000 | C13: =IF(C$3=0,-Inputs!$B$7,0) -> 0 | D13: =IF(D$3=0,-Inputs!$B$7,0) -> 0 | E13: =IF(E$3=0,-Inputs!$B$7,0) -> 0 | F13: =IF(F$3=0,-Inputs!$B$7,0) -> 0 | G13: =IF(G$3=0,-Inputs!$B$7,0) -> 0 | H13: =IF(H$3=0,-Inputs!$B$7,0) -> 0 | I13: =IF(I$3=0,-Inputs!$B$7,0) -> 0 | ... Q13: =IF(Q$3=0,-Inputs!$B$7,0) -> 0
A14: Net cash flow | B14: =SUM(B6,B8:B13) -> -41200000 | C14: =SUM(C6,C8:C13) -> 16073600 | D14: =SUM(D6,D8:D13) -> 18918947 | E14: =SUM(E6,E8:E13) -> 22137797 | F14: =SUM(F6,F8:F13) -> 28072020 | G14: =SUM(G6,G8:G13) -> 7412706.4 | H14: =SUM(H6,H8:H13) -> 8061183.1 | I14: =SUM(I6,I8:I13) -> 8732356.5 | ... Q14: =SUM(Q6,Q8:Q13) -> 10772685

Sheet Summary
A3: Project IRR | B3: =IRR('Cash Flow'!B14:Q14) -> 0.40851981
A4: NPV | B4: =NPV(Inputs!$B$14,'Cash Flow'!C14:Q14)+'Cash Flow'!B14 -> 71102113
A5: Development margin | B5: =(SUM('Cash Flow'!B6:Q6)+SUM('Cash Flow'!B12:Q13))/-SUM('Cash Flow'!B12:Q13) -> 0.32830249
A6: Net profit | B6: =SUM('Cash Flow'!B14:Q14) -> 1.4882245e+08
A7: Total development cost | B7: =-SUM('Cash Flow'!B12:Q13) -> 101800000
A8: Annual DMF at stabilisation | B8: ='Cash Flow'!Q8 -> 4680000
