Workbook

Sheet Inputs
A1: JAHRA HOSPITAL PPP – AVAILABILITY PAYMENT MODEL (KWD)
A3: Annual availability payment (KWD) | B3: 21500000
A4: Indexation of the unitary charge | B4: 0.02
A5: Performance deductions (% of payment) | B5: 0.015
A6: Construction cost (KWD) | B6: 148000000
A7: Construction period (years) | B7: 3
A8: Operating period (years) | B8: 25
A9: Hard FM cost (KWD/yr) | B9: 3100000
A10: FM cost inflation | B10: 0.025
A11: Lifecycle (% of capex p.a.) | B11: 0.012
A12: Senior debt gearing | B12: 0.85
A13: Senior debt rate | B13: 0.058
A14: Debt tenor after completion (years) | B14: 22

Sheet Model
A3: Year | B3: 0 | C3: 1 | D3: 2 | E3: 3 | F3: 4 | G3: 5 | H3: 6 | I3: 7 | J3: 8 | K3: 9 | L3: 10 | M3: 11 | N3: 12 | O3: 13 | P3: 14 | Q3: 15 | R3: 16 | S3: 17 | T3: 18 | U3: 19 | V3: 20 | W3: 21 | X3: 22 | Y3: 23 | Z3: 24 | AA3: 25 | AB3: 26 | AC3: 27 | AD3: 28
A4: Unitary charge | B4: =Inputs!$B$3*(1+Inputs!$B$4)^MAX(0,B$3-Inputs!$B$7-1)*(B$3>Inputs!$B$7)*(B$3<=Inputs!$B$7+Inputs!$B$8) -> 0 | C4: =Inputs!$B$3*(1+Inputs!$B$4)^MAX(0,C$3-Inputs!$B$7-1)*(C$3>Inputs!$B$7)*(C$3<=Inputs!$B$7+Inputs!$B$8) -> 0 | D4: =Inputs!$B$3*(1+Inputs!$B$4)^MAX(0,D$3-Inputs!$B$7-1)*(D$3>Inputs!$B$7)*(D$3<=Inputs!$B$7+Inputs!$B$8) -> 0 | E4: =Inputs!$B$3*(1+Inputs!$B$4)^MAX(0,E$3-Inputs!$B$7-1)*(E$3>Inputs!$B$7)*(E$3<=Inputs!$B$7+Inputs!$B$8) -> 0 | F4: =Inputs!$B$3*(1+Inputs!$B$4)^MAX(0,F$3-Inputs!$B$7-1)*(F$3>Inputs!$B$7)*(F$3<=Inputs!$B$7+Inputs!$B$8) -> 21500000 | G4: =Inputs!$B$3*(1+Inputs!$B$4)^MAX(0,G$3-Inputs!$B$7-1)*(G$3>Inputs!$B$7)*(G$3<=Inputs!$B$7+Inputs!$B$8) -> 21930000 | H4: =Inputs!$B$3*(1+Inputs!$B$4)^MAX(0,H$3-Inputs!$B$7-1)*(H$3>Inputs!$B$7)*(H$3<=Inputs!$B$7+Inputs!$B$8) -> 22368600 | I4: =Inputs!$B$3*(1+Inputs!$B$4)^MAX(0,I$3-Inputs!$B$7-1)*(I$3>Inputs!$B$7)*(I$3<=Inputs!$B$7+Inputs!$B$8) -> 22815972 | ... AD4: =Inputs!$B$3*(1+Inputs!$B$4)^MAX(0,AD$3-Inputs!$B$7-1)*(AD$3>Inputs!$B$7)*(AD$3<=Inputs!$B$7+Inputs!$B$8) -> 34581401
A5: Deductions | B5: =-B4*Inputs!$B$5 -> 0 | C5: =-C4*Inputs!$B$5 -> 0 | D5: =-D4*Inputs!$B$5 -> 0 | E5: =-E4*Inputs!$B$5 -> 0 | F5: =-F4*Inputs!$B$5 -> -322500 | G5: =-G4*Inputs!$B$5 -> -328950 | H5: =-H4*Inputs!$B$5 -> -335529 | I5: =-I4*Inputs!$B$5 -> -342239.58 | ... AD5: =-AD4*Inputs!$B$5 -> -518721.01
A6: FM costs | B6: =-Inputs!$B$9*(1+Inputs!$B$10)^MAX(0,B$3-Inputs!$B$7-1)*(B$3>Inputs!$B$7)*(B$3<=Inputs!$B$7+Inputs!$B$8) -> 0 | C6: =-Inputs!$B$9*(1+Inputs!$B$10)^MAX(0,C$3-Inputs!$B$7-1)*(C$3>Inputs!$B$7)*(C$3<=Inputs!$B$7+Inputs!$B$8) -> 0 | D6: =-Inputs!$B$9*(1+Inputs!$B$10)^MAX(0,D$3-Inputs!$B$7-1)*(D$3>Inputs!$B$7)*(D$3<=Inputs!$B$7+Inputs!$B$8) -> 0 | E6: =-Inputs!$B$9*(1+Inputs!$B$10)^MAX(0,E$3-Inputs!$B$7-1)*(E$3>Inputs!$B$7)*(E$3<=Inputs!$B$7+Inputs!$B$8) -> 0 | F6: =-Inputs!$B$9*(1+Inputs!$B$10)^MAX(0,F$3-Inputs!$B$7-1)*(F$3>Inputs!$B$7)*(F$3<=Inputs!$B$7+Inputs!$B$8) -> -3100000 | G6: =-Inputs!$B$9*(1+Inputs!$B$10)^MAX(0,G$3-Inputs!$B$7-1)*(G$3>Inputs!$B$7)*(G$3<=Inputs!$B$7+Inputs!$B$8) -> -3177500 | H6: =-Inputs!$B$9*(1+Inputs!$B$10)^MAX(0,H$3-Inputs!$B$7-1)*(H$3>Inputs!$B$7)*(H$3<=Inputs!$B$7+Inputs!$B$8) -> -3256937.5 | I6: =-Inputs!$B$9*(1+Inputs!$B$10)^MAX(0,I$3-Inputs!$B$7-1)*(I$3>Inputs!$B$7)*(I$3<=Inputs!$B$7+Inputs!$B$8) -> -3338360.9 | ... AD6: =-Inputs!$B$9*(1+Inputs!$B$10)^MAX(0,AD$3-Inputs!$B$7-1)*(AD$3>Inputs!$B$7)*(AD$3<=Inputs!$B$7+Inputs!$B$8) -> -5607050.4
A7: Lifecycle | B7: =-Inputs!$B$6*Inputs!$B$11*(B$3>Inputs!$B$7)*(B$3<=Inputs!$B$7+Inputs!$B$8) -> 0 | C7: =-Inputs!$B$6*Inputs!$B$11*(C$3>Inputs!$B$7)*(C$3<=Inputs!$B$7+Inputs!$B$8) -> 0 | D7: =-Inputs!$B$6*Inputs!$B$11*(D$3>Inputs!$B$7)*(D$3<=Inputs!$B$7+Inputs!$B$8) -> 0 | E7: =-Inputs!$B$6*Inputs!$B$11*(E$3>Inputs!$B$7)*(E$3<=Inputs!$B$7+Inputs!$B$8) -> 0 | F7: =-Inputs!$B$6*Inputs!$B$11*(F$3>Inputs!$B$7)*(F$3<=Inputs!$B$7+Inputs!$B$8) -> -1776000 | G7: =-Inputs!$B$6*Inputs!$B$11*(G$3>Inputs!$B$7)*(G$3<=Inputs!$B$7+Inputs!$B$8) -> -1776000 | H7: =-Inputs!$B$6*Inputs!$B$11*(H$3>Inputs!$B$7)*(H$3<=Inputs!$B$7+Inputs!$B$8) -> -1776000 | I7: =-Inputs!$B$6*Inputs!$B$11*(I$3>Inputs!$B$7)*(I$3<=Inputs!$B$7+Inputs!$B$8) -> -1776000 | ... AD7: =-Inputs!$B$6*Inputs!$B$11*(AD$3>Inputs!$B$7)*(AD$3<=Inputs!$B$7+Inputs!$B$8) -> -1776000
A8: Construction | B8: =-IF(B$3<Inputs!$B$7,Inputs!$B$6/Inputs!$B$7,0) -> -49333333 | C8: =-IF(C$3<Inputs!$B$7,Inputs!$B$6/Inputs!$B$7,0) -> -49333333 | D8: =-IF(D$3<Inputs!$B$7,Inputs!$B$6/Inputs!$B$7,0) -> -49333333 | E8: =-IF(E$3<Inputs!$B$7,Inputs!$B$6/Inputs!$B$7,0) -> 0 | F8: =-IF(F$3<Inputs!$B$7,Inputs!$B$6/Inputs!$B$7,0) -> 0 | G8: =-IF(G$3<Inputs!$B$7,Inputs!$B$6/Inputs!$B$7,0) -> 0 | H8: =-IF(H$3<Inputs!$B$7,Inputs!$B$6/Inputs!$B$7,0) -> 0 | I8: =-IF(I$3<Inputs!$B$7,Inputs!$B$6/Inputs!$B$7,0) -> 0 | ... AD8: =-IF(AD$3<Inputs!$B$7,Inputs!$B$6/Inputs!$B$7,0) -> 0
A9: Debt drawdown | B9: =-B8*Inputs!$B$12 -> 41933333 | C9: =-C8*Inputs!$B$12 -> 41933333 | D9: =-D8*Inputs!$B$12 -> 41933333 | E9: =-E8*Inputs!$B$12 -> 0 | F9: =-F8*Inputs!$B$12 -> 0 | G9: =-G8*Inputs!$B$12 -> 0 | H9: =-H8*Inputs!$B$12 -> 0 | I9: =-I8*Inputs!$B$12 -> 0 | ... AD9: =-AD8*Inputs!$B$12 -> 0
A10: Debt service | B10: =IF(AND(B$3>Inputs!$B$7,B$3<=Inputs!$B$7+Inputs!$B$14),PMT(Inputs!$B$13,Inputs!$B$14,Inputs!$B$6*Inputs!$B$12),0) -> 0 | C10: =IF(AND(C$3>Inputs!$B$7,C$3<=Inputs!$B$7+Inputs!$B$14),PMT(Inputs!$B$13,Inputs!$B$14,Inputs!$B$6*Inputs!$B$12),0) -> 0 | D10: =IF(AND(D$3>Inputs!$B$7,D$3<=Inputs!$B$7+Inputs!$B$14),PMT(Inputs!$B$13,Inputs!$B$14,Inputs!$B$6*Inputs!$B$12),0) -> 0 | E10: =IF(AND(E$3>Inputs!$B$7,E$3<=Inputs!$B$7+Inputs!$B$14),PMT(Inputs!$B$13,Inputs!$B$14,Inputs!$B$6*Inputs!$B$12),0) -> 0 | F10: =IF(AND(F$3>Inputs!$B$7,F$3<=Inputs!$B$7+Inputs!$B$14),PMT(Inputs!$B$13,Inputs!$B$14,Inputs!$B$6*Inputs!$B$12),0) -> -10266179 | G10: =IF(AND(G$3>Inputs!$B$7,G$3<=Inputs!$B$7+Inputs!$B$14),PMT(Inputs!$B$13,Inputs!$B$14,Inputs!$B$6*Inputs!$B$12),0) -> -10266179 | H10: =IF(AND(H$3>Inputs!$B$7,H$3<=Inputs!$B$7+Inputs!$B$14),PMT(Inputs!$B$13,Inputs!$B$14,Inputs!$B$6*Inputs!$B$12),0) -> -10266179 | I10: =IF(AND(I$3>Inputs!$B$7,I$3<=Inputs!$B$7+Inputs!$B$14),PMT(Inputs!$B$13,Inputs!$B$14,Inputs!$B$6*Inputs!$B$12),0) -> -10266179 | ... AD10: =IF(AND(AD$3>Inputs!$B$7,AD$3<=Inputs!$B$7+Inputs!$B$14),PMT(Inputs!$B$13,Inputs!$B$14,Inputs!$B$6*Inputs!$B$12),0) -> 0
A11: Equity cash flow | B11: =B12+B9+B10 -> -7400000 | C11: =C12+C9+C10 -> -7400000 | D11: =D12+D9+D10 -> -7400000 | E11: =E12+E9+E10 -> 0 | F11: =F12+F9+F10 -> 6035320.9 | G11: =G12+G9+G10 -> 6381370.9 | H11: =H12+H9+H10 -> 6733954.4 | I11: =I12+I9+I10 -> 7093192.4 | ... AD11: =AD12+AD9+AD10 -> 26679629
A12: Project cash flow | B12: =SUM(B4:B8) -> -49333333 | C12: =SUM(C4:C8) -> -49333333 | D12: =SUM(D4:D8) -> -49333333 | E12: =SUM(E4:E8) -> 0 | F12: =SUM(F4:F8) -> 16301500 | G12: =SUM(G4:G8) -> 16647550 | H12: =SUM(H4:H8) -> 17000134 | I12: =SUM(I4:I8) -> 17359371 | ... AD12: =SUM(AD4:AD8) -> 26679629
A13: CFADS | B13: =SUM(B4:B7) -> 0 | C13: =SUM(C4:C7) -> 0 | D13: =SUM(D4:D7) -> 0 | E13: =SUM(E4:E7) -> 0 | F13: =SUM(F4:F7) -> 16301500 | G13: =SUM(G4:G7) -> 16647550 | H13: =SUM(H4:H7) -> 17000134 | I13: =SUM(I4:I7) -> 17359371 | ... AD13: =SUM(AD4:AD7) -> 26679629
A14: DSCR | B14: =IF(B10<0,B13/-B10,"") | C14: =IF(C10<0,C13/-C10,"") | D14: =IF(D10<0,D13/-D10,"") | E14: =IF(E10<0,E13/-E10,"") | F14: =IF(F10<0,F13/-F10,"") -> 1.5878838 | G14: =IF(G10<0,G13/-G10,"") -> 1.6215916 | H14: =IF(H10<0,H13/-H10,"") -> 1.6559358 | I14: =IF(I10<0,I13/-I10,"") -> 1.6909282 | ... AD14: =IF(AD10<0,AD13/-AD10,"")

Sheet Outputs
A3: Equity IRR | B3: =IRR(Model!B11:AD11) -> 0.22586209
A4: Project IRR | B4: =IRR(Model!B12:AD12) -> 0.097086765
A5: Minimum DSCR | B5: =MIN(Model!B14:AD14) -> 1.5878838
A6: Average DSCR | B6: =AVERAGE(Model!B14:AD14) -> 1.9905492
A7: Equity invested | B7: =-SUMIF(Model!B11:AD11,"<0") -> 22200000
A8: Net profit | B8: =SUM(Model!B12:AD12) -> 3.800326e+08
