Workbook

Sheet Inputs
A1: KENDALL WORKS – OFFICE TO LAB CONVERSION (USD)
A3: Acquisition price | B3: 182000000
A4: Conversion cost ($/rsf) | B4: 310
A5: Closing costs | B5: 0.02
A6: Exit cap rate | B6: 0.0575
A7: Non-recoverable opex ($/rsf) | B7: 4.5
A8: Rent bumps (annual) | B8: 0.03
A9: Loan to cost | B9: 0.55
A10: Loan rate (SOFR + spread) | B10: 0.0725
A11: Hold (years) | B11: 6

Sheet Lease-Up
A1: Suite | B1: RSF | C1: Base rent ($/rsf NNN) | D1: Lease start (year) | E1: Free rent (months) | F1: TI allowance ($/rsf) | G1: Term (years)
A2: Suite 100 | B2: 62000 | C2: 98 | D2: 1 | E2: 10 | F2: 185 | G2: 10
A3: Suite 200 | B3: 58000 | C3: 96 | D3: 2 | E3: 9 | F3: 175 | G3: 10
A4: Suite 300 | B4: 71000 | C4: 94 | D4: 2 | E4: 12 | F4: 190 | G4: 12
A5: Suite 400 | B5: 45000 | C5: 99 | D5: 3 | E5: 8 | F5: 160 | G5: 7

Sheet Cash Flow
A3: Year | B3: 0 | C3: 1 | D3: 2 | E3: 3 | F3: 4 | G3: 5 | H3: 6 | I3: 7
A4: Rental income | B4: =SUMPRODUCT('Lease-Up'!$B$2:$B$5,'Lease-Up'!$C$2:$C$5,('Lease-Up'!$D$2:$D$5<=B$3)*(1+Inputs!$B$8)^(B$3-'Lease-Up'!$D$2:$D$5))*(B$3<=Inputs!$B$11) -> 0 | C4: =SUMPRODUCT('Lease-Up'!$B$2:$B$5,'Lease-Up'!$C$2:$C$5,('Lease-Up'!$D$2:$D$5<=C$3)*(1+Inputs!$B$8)^(C$3-'Lease-Up'!$D$2:$D$5))*(C$3<=Inputs!$B$11) -> 6076000 | D4: =SUMPRODUCT('Lease-Up'!$B$2:$B$5,'Lease-Up'!$C$2:$C$5,('Lease-Up'!$D$2:$D$5<=D$3)*(1+Inputs!$B$8)^(D$3-'Lease-Up'!$D$2:$D$5))*(D$3<=Inputs!$B$11) -> 18500280 | E4: =SUMPRODUCT('Lease-Up'!$B$2:$B$5,'Lease-Up'!$C$2:$C$5,('Lease-Up'!$D$2:$D$5<=E$3)*(1+Inputs!$B$8)^(E$3-'Lease-Up'!$D$2:$D$5))*(E$3<=Inputs!$B$11) -> 23510288 | F4: =SUMPRODUCT('Lease-Up'!$B$2:$B$5,'Lease-Up'!$C$2:$C$5,('Lease-Up'!$D$2:$D$5<=F$3)*(1+Inputs!$B$8)^(F$3-'Lease-Up'!$D$2:$D$5))*(F$3<=Inputs!$B$11) -> 24215597 | G4: =SUMPRODUCT('Lease-Up'!$B$2:$B$5,'Lease-Up'!$C$2:$C$5,('Lease-Up'!$D$2:$D$5<=G$3)*(1+Inputs!$B$8)^(G$3-'Lease-Up'!$D$2:$D$5))*(G$3<=Inputs!$B$11) -> 24942065 | H4: =SUMPRODUCT('Lease-Up'!$B$2:$B$5,'Lease-Up'!$C$2:$C$5,('Lease-Up'!$D$2:$D$5<=H$3)*(1+Inputs!$B$8)^(H$3-'Lease-Up'!$D$2:$D$5))*(H$3<=Inputs!$B$11) -> 25690327 | I4: =SUMPRODUCT('Lease-Up'!$B$2:$B$5,'Lease-Up'!$C$2:$C$5,('Lease-Up'!$D$2:$D$5<=I$3)*(1+Inputs!$B$8)^(I$3-'Lease-Up'!$D$2:$D$5))*(I$3<=Inputs!$B$11) -> 0
A5: Free rent | B5: =-SUMPRODUCT('Lease-Up'!$B$2:$B$5,'Lease-Up'!$C$2:$C$5,('Lease-Up'!$D$2:$D$5=B$3)*'Lease-Up'!$E$2:$E$5/12) -> 0 | C5: =-SUMPRODUCT('Lease-Up'!$B$2:$B$5,'Lease-Up'!$C$2:$C$5,('Lease-Up'!$D$2:$D$5=C$3)*'Lease-Up'!$E$2:$E$5/12) -> -5063333.3 | D5: =-SUMPRODUCT('Lease-Up'!$B$2:$B$5,'Lease-Up'!$C$2:$C$5,('Lease-Up'!$D$2:$D$5=D$3)*'Lease-Up'!$E$2:$E$5/12) -> -10850000 | E5: =-SUMPRODUCT('Lease-Up'!$B$2:$B$5,'Lease-Up'!$C$2:$C$5,('Lease-Up'!$D$2:$D$5=E$3)*'Lease-Up'!$E$2:$E$5/12) -> -2970000 | F5: =-SUMPRODUCT('Lease-Up'!$B$2:$B$5,'Lease-Up'!$C$2:$C$5,('Lease-Up'!$D$2:$D$5=F$3)*'Lease-Up'!$E$2:$E$5/12) -> 0 | G5: =-SUMPRODUCT('Lease-Up'!$B$2:$B$5,'Lease-Up'!$C$2:$C$5,('Lease-Up'!$D$2:$D$5=G$3)*'Lease-Up'!$E$2:$E$5/12) -> 0 | H5: =-SUMPRODUCT('Lease-Up'!$B$2:$B$5,'Lease-Up'!$C$2:$C$5,('Lease-Up'!$D$2:$D$5=H$3)*'Lease-Up'!$E$2:$E$5/12) -> 0 | I5: =-SUMPRODUCT('Lease-Up'!$B$2:$B$5,'Lease-Up'!$C$2:$C$5,('Lease-Up'!$D$2:$D$5=I$3)*'Lease-Up'!$E$2:$E$5/12) -> 0
A6: Opex | B6: =-SUM('Lease-Up'!$B$2:$B$5)*Inputs!$B$7*(B$3>=1)*(B$3<=Inputs!$B$11) -> 0 | C6: =-SUM('Lease-Up'!$B$2:$B$5)*Inputs!$B$7*(C$3>=1)*(C$3<=Inputs!$B$11) -> -1062000 | D6: =-SUM('Lease-Up'!$B$2:$B$5)*Inputs!$B$7*(D$3>=1)*(D$3<=Inputs!$B$11) -> -1062000 | E6: =-SUM('Lease-Up'!$B$2:$B$5)*Inputs!$B$7*(E$3>=1)*(E$3<=Inputs!$B$11) -> -1062000 | F6: =-SUM('Lease-Up'!$B$2:$B$5)*Inputs!$B$7*(F$3>=1)*(F$3<=Inputs!$B$11) -> -1062000 | G6: =-SUM('Lease-Up'!$B$2:$B$5)*Inputs!$B$7*(G$3>=1)*(G$3<=Inputs!$B$11) -> -1062000 | H6: =-SUM('Lease-Up'!$B$2:$B$5)*Inputs!$B$7*(H$3>=1)*(H$3<=Inputs!$B$11) -> -1062000 | I6: =-SUM('Lease-Up'!$B$2:$B$5)*Inputs!$B$7*(I$3>=1)*(I$3<=Inputs!$B$11) -> 0
A7: TI | B7: =-SUMPRODUCT('Lease-Up'!$B$2:$B$5,'Lease-Up'!$F$2:$F$5,--('Lease-Up'!$D$2:$D$5=B$3)) -> 0 | C7: =-SUMPRODUCT('Lease-Up'!$B$2:$B$5,'Lease-Up'!$F$2:$F$5,--('Lease-Up'!$D$2:$D$5=C$3)) -> -11470000 | D7: =-SUMPRODUCT('Lease-Up'!$B$2:$B$5,'Lease-Up'!$F$2:$F$5,--('Lease-Up'!$D$2:$D$5=D$3)) -> -23640000 | E7: =-SUMPRODUCT('Lease-Up'!$B$2:$B$5,'Lease-Up'!$F$2:$F$5,--('Lease-Up'!$D$2:$D$5=E$3)) -> -7200000 | F7: =-SUMPRODUCT('Lease-Up'!$B$2:$B$5,'Lease-Up'!$F$2:$F$5,--('Lease-Up'!$D$2:$D$5=F$3)) -> 0 | G7: =-SUMPRODUCT('Lease-Up'!$B$2:$B$5,'Lease-Up'!$F$2:$F$5,--('Lease-Up'!$D$2:$D$5=G$3)) -> 0 | H7: =-SUMPRODUCT('Lease-Up'!$B$2:$B$5,'Lease-Up'!$F$2:$F$5,--('Lease-Up'!$D$2:$D$5=H$3)) -> 0 | I7: =-SUMPRODUCT('Lease-Up'!$B$2:$B$5,'Lease-Up'!$F$2:$F$5,--('Lease-Up'!$D$2:$D$5=I$3)) -> 0
A8: Conversion | B8: =-SUM('Lease-Up'!$B$2:$B$5)*Inputs!$B$4*IF(B$3=0,0.6,IF(B$3=1,0.4,0)) -> -43896000 | C8: =-SUM('Lease-Up'!$B$2:$B$5)*Inputs!$B$4*IF(C$3=0,0.6,IF(C$3=1,0.4,0)) -> -29264000 | D8: =-SUM('Lease-Up'!$B$2:$B$5)*Inputs!$B$4*IF(D$3=0,0.6,IF(D$3=1,0.4,0)) -> 0 | E8: =-SUM('Lease-Up'!$B$2:$B$5)*Inputs!$B$4*IF(E$3=0,0.6,IF(E$3=1,0.4,0)) -> 0 | F8: =-SUM('Lease-Up'!$B$2:$B$5)*Inputs!$B$4*IF(F$3=0,0.6,IF(F$3=1,0.4,0)) -> 0 | G8: =-SUM('Lease-Up'!$B$2:$B$5)*Inputs!$B$4*IF(G$3=0,0.6,IF(G$3=1,0.4,0)) -> 0 | H8: =-SUM('Lease-Up'!$B$2:$B$5)*Inputs!$B$4*IF(H$3=0,0.6,IF(H$3=1,0.4,0)) -> 0 | I8: =-SUM('Lease-Up'!$B$2:$B$5)*Inputs!$B$4*IF(I$3=0,0.6,IF(I$3=1,0.4,0)) -> 0
A9: Acquisition | B9: =IF(B$3=0,-Inputs!$B$3*(1+Inputs!$B$5),0) -> -185640000 | C9: =IF(C$3=0,-Inputs!$B$3*(1+Inputs!$B$5),0) -> 0 | D9: =IF(D$3=0,-Inputs!$B$3*(1+Inputs!$B$5),0) -> 0 | E9: =IF(E$3=0,-Inputs!$B$3*(1+Inputs!$B$5),0) -> 0 | F9: =IF(F$3=0,-Inputs!$B$3*(1+Inputs!$B$5),0) -> 0 | G9: =IF(G$3=0,-Inputs!$B$3*(1+Inputs!$B$5),0) -> 0 | H9: =IF(H$3=0,-Inputs!$B$3*(1+Inputs!$B$5),0) -> 0 | I9: =IF(I$3=0,-Inputs!$B$3*(1+Inputs!$B$5),0) -> 0
A10: Sale | B10: =IF(B$3=Inputs!$B$11,SUMPRODUCT('Lease-Up'!$B$2:$B$5,'Lease-Up'!$C$2:$C$5,(1+Inputs!$B$8)^(B$3+1-'Lease-Up'!$D$2:$D$5))/Inputs!$B$6*0.98,0) -> 0 | C10: =IF(C$3=Inputs!$B$11,SUMPRODUCT('Lease-Up'!$B$2:$B$5,'Lease-Up'!$C$2:$C$5,(1+Inputs!$B$8)^(C$3+1-'Lease-Up'!$D$2:$D$5))/Inputs!$B$6*0.98,0) -> 0 | D10: =IF(D$3=Inputs!$B$11,SUMPRODUCT('Lease-Up'!$B$2:$B$5,'Lease-Up'!$C$2:$C$5,(1+Inputs!$B$8)^(D$3+1-'Lease-Up'!$D$2:$D$5))/Inputs!$B$6*0.98,0) -> 0 | E10: =IF(E$3=Inputs!$B$11,SUMPRODUCT('Lease-Up'!$B$2:$B$5,'Lease-Up'!$C$2:$C$5,(1+Inputs!$B$8)^(E$3+1-'Lease-Up'!$D$2:$D$5))/Inputs!$B$6*0.98,0) -> 0 | F10: =IF(F$3=Inputs!$B$11,SUMPRODUCT('Lease-Up'!$B$2:$B$5,'Lease-Up'!$C$2:$C$5,(1+Inputs!$B$8)^(F$3+1-'Lease-Up'!$D$2:$D$5))/Inputs!$B$6*0.98,0) -> 0 | G10: =IF(G$3=Inputs!$B$11,SUMPRODUCT('Lease-Up'!$B$2:$B$5,'Lease-Up'!$C$2:$C$5,(1+Inputs!$B$8)^(G$3+1-'Lease-Up'!$D$2:$D$5))/Inputs!$B$6*0.98,0) -> 0 | H10: =IF(H$3=Inputs!$B$11,SUMPRODUCT('Lease-Up'!$B$2:$B$5,'Lease-Up'!$C$2:$C$5,(1+Inputs!$B$8)^(H$3+1-'Lease-Up'!$D$2:$D$5))/Inputs!$B$6*0.98,0) -> 4.509881e+08 | I10: =IF(I$3=Inputs!$B$11,SUMPRODUCT('Lease-Up'!$B$2:$B$5,'Lease-Up'!$C$2:$C$5,(1+Inputs!$B$8)^(I$3+1-'Lease-Up'!$D$2:$D$5))/Inputs!$B$6*0.98,0) -> 0
A11: Unlevered cash flow | B11: =SUM(B4:B10) -> -229536000 | C11: =SUM(C4:C10) -> -40783333 | D11: =SUM(D4:D10) -> -17051720 | E11: =SUM(E4:E10) -> 12278288 | F11: =SUM(F4:F10) -> 23153597 | G11: =SUM(G4:G10) -> 23880065 | H11: =SUM(H4:H10) -> 4.7561643e+08 | I11: =SUM(I4:I10) -> 0
A12: Loan draw / (repay) | B12: =IF(B$3=0,(Inputs!$B$3*(1+Inputs!$B$5)+SUM('Lease-Up'!$B$2:$B$5)*Inputs!$B$4+SUMPRODUCT('Lease-Up'!$B$2:$B$5,'Lease-Up'!$F$2:$F$5))*Inputs!$B$9,IF(B$3=Inputs!$B$11,-(Inputs!$B$3*(1+Inputs!$B$5)+SUM('Lease-Up'!$B$2:$B$5)*Inputs!$B$4+SUMPRODUCT('Lease-Up'!$B$2:$B$5,'Lease-Up'!$F$2:$F$5))*Inputs!$B$9,0)) -> 165610500 | C12: =IF(C$3=0,(Inputs!$B$3*(1+Inputs!$B$5)+SUM('Lease-Up'!$B$2:$B$5)*Inputs!$B$4+SUMPRODUCT('Lease-Up'!$B$2:$B$5,'Lease-Up'!$F$2:$F$5))*Inputs!$B$9,IF(C$3=Inputs!$B$11,-(Inputs!$B$3*(1+Inputs!$B$5)+SUM('Lease-Up'!$B$2:$B$5)*Inputs!$B$4+SUMPRODUCT('Lease-Up'!$B$2:$B$5,'Lease-Up'!$F$2:$F$5))*Inputs!$B$9,0)) -> 0 | D12: =IF(D$3=0,(Inputs!$B$3*(1+Inputs!$B$5)+SUM('Lease-Up'!$B$2:$B$5)*Inputs!$B$4+SUMPRODUCT('Lease-Up'!$B$2:$B$5,'Lease-Up'!$F$2:$F$5))*Inputs!$B$9,IF(D$3=Inputs!$B$11,-(Inputs!$B$3*(1+Inputs!$B$5)+SUM('Lease-Up'!$B$2:$B$5)*Inputs!$B$4+SUMPRODUCT('Lease-Up'!$B$2:$B$5,'Lease-Up'!$F$2:$F$5))*Inputs!$B$9,0)) -> 0 | E12: =IF(E$3=0,(Inputs!$B$3*(1+Inputs!$B$5)+SUM('Lease-Up'!$B$2:$B$5)*Inputs!$B$4+SUMPRODUCT('Lease-Up'!$B$2:$B$5,'Lease-Up'!$F$2:$F$5))*Inputs!$B$9,IF(E$3=Inputs!$B$11,-(Inputs!$B$3*(1+Inputs!$B$5)+SUM('Lease-Up'!$B$2:$B$5)*Inputs!$B$4+SUMPRODUCT('Lease-Up'!$B$2:$B$5,'Lease-Up'!$F$2:$F$5))*Inputs!$B$9,0)) -> 0 | F12: =IF(F$3=0,(Inputs!$B$3*(1+Inputs!$B$5)+SUM('Lease-Up'!$B$2:$B$5)*Inputs!$B$4+SUMPRODUCT('Lease-Up'!$B$2:$B$5,'Lease-Up'!$F$2:$F$5))*Inputs!$B$9,IF(F$3=Inputs!$B$11,-(Inputs!$B$3*(1+Inputs!$B$5)+SUM('Lease-Up'!$B$2:$B$5)*Inputs!$B$4+SUMPRODUCT('Lease-Up'!$B$2:$B$5,'Lease-Up'!$F$2:$F$5))*Inputs!$B$9,0)) -> 0 | G12: =IF(G$3=0,(Inputs!$B$3*(1+Inputs!$B$5)+SUM('Lease-Up'!$B$2:$B$5)*Inputs!$B$4+SUMPRODUCT('Lease-Up'!$B$2:$B$5,'Lease-Up'!$F$2:$F$5))*Inputs!$B$9,IF(G$3=Inputs!$B$11,-(Inputs!$B$3*(1+Inputs!$B$5)+SUM('Lease-Up'!$B$2:$B$5)*Inputs!$B$4+SUMPRODUCT('Lease-Up'!$B$2:$B$5,'Lease-Up'!$F$2:$F$5))*Inputs!$B$9,0)) -> 0 | H12: =IF(H$3=0,(Inputs!$B$3*(1+Inputs!$B$5)+SUM('Lease-Up'!$B$2:$B$5)*Inputs!$B$4+SUMPRODUCT('Lease-Up'!$B$2:$B$5,'Lease-Up'!$F$2:$F$5))*Inputs!$B$9,IF(H$3=Inputs!$B$11,-(Inputs!$B$3*(1+Inputs!$B$5)+SUM('Lease-Up'!$B$2:$B$5)*Inputs!$B$4+SUMPRODUCT('Lease-Up'!$B$2:$B$5,'Lease-Up'!$F$2:$F$5))*Inputs!$B$9,0)) -> -165610500 | I12: =IF(I$3=0,(Inputs!$B$3*(1+Inputs!$B$5)+SUM('Lease-Up'!$B$2:$B$5)*Inputs!$B$4+SUMPRODUCT('Lease-Up'!$B$2:$B$5,'Lease-Up'!$F$2:$F$5))*Inputs!$B$9,IF(I$3=Inputs!$B$11,-(Inputs!$B$3*(1+Inputs!$B$5)+SUM('Lease-Up'!$B$2:$B$5)*Inputs!$B$4+SUMPRODUCT('Lease-Up'!$B$2:$B$5,'Lease-Up'!$F$2:$F$5))*Inputs!$B$9,0)) -> 0
A13: Interest | B13: =-(Inputs!$B$3*(1+Inputs!$B$5)+SUM('Lease-Up'!$B$2:$B$5)*Inputs!$B$4+SUMPRODUCT('Lease-Up'!$B$2:$B$5,'Lease-Up'!$F$2:$F$5))*Inputs!$B$9*Inputs!$B$10*(B$3>=1)*(B$3<=Inputs!$B$11) -> 0 | C13: =-(Inputs!$B$3*(1+Inputs!$B$5)+SUM('Lease-Up'!$B$2:$B$5)*Inputs!$B$4+SUMPRODUCT('Lease-Up'!$B$2:$B$5,'Lease-Up'!$F$2:$F$5))*Inputs!$B$9*Inputs!$B$10*(C$3>=1)*(C$3<=Inputs!$B$11) -> -12006761 | D13: =-(Inputs!$B$3*(1+Inputs!$B$5)+SUM('Lease-Up'!$B$2:$B$5)*Inputs!$B$4+SUMPRODUCT('Lease-Up'!$B$2:$B$5,'Lease-Up'!$F$2:$F$5))*Inputs!$B$9*Inputs!$B$10*(D$3>=1)*(D$3<=Inputs!$B$11) -> -12006761 | E13: =-(Inputs!$B$3*(1+Inputs!$B$5)+SUM('Lease-Up'!$B$2:$B$5)*Inputs!$B$4+SUMPRODUCT('Lease-Up'!$B$2:$B$5,'Lease-Up'!$F$2:$F$5))*Inputs!$B$9*Inputs!$B$10*(E$3>=1)*(E$3<=Inputs!$B$11) -> -12006761 | F13: =-(Inputs!$B$3*(1+Inputs!$B$5)+SUM('Lease-Up'!$B$2:$B$5)*Inputs!$B$4+SUMPRODUCT('Lease-Up'!$B$2:$B$5,'Lease-Up'!$F$2:$F$5))*Inputs!$B$9*Inputs!$B$10*(F$3>=1)*(F$3<=Inputs!$B$11) -> -12006761 | G13: =-(Inputs!$B$3*(1+Inputs!$B$5)+SUM('Lease-Up'!$B$2:$B$5)*Inputs!$B$4+SUMPRODUCT('Lease-Up'!$B$2:$B$5,'Lease-Up'!$F$2:$F$5))*Inputs!$B$9*Inputs!$B$10*(G$3>=1)*(G$3<=Inputs!$B$11) -> -12006761 | H13: =-(Inputs!$B$3*(1+Inputs!$B$5)+SUM('Lease-Up'!$B$2:$B$5)*Inputs!$B$4+SUMPRODUCT('Lease-Up'!$B$2:$B$5,'Lease-Up'!$F$2:$F$5))*Inputs!$B$9*Inputs!$B$10*(H$3>=1)*(H$3<=Inputs!$B$11) -> -12006761 | I13: =-(Inputs!$B$3*(1+Inputs!$B$5)+SUM('Lease-Up'!$B$2:$B$5)*Inputs!$B$4+SUMPRODUCT('Lease-Up'!$B$2:$B$5,'Lease-Up'!$F$2:$F$5))*Inputs!$B$9*Inputs!$B$10*(I$3>=1)*(I$3<=Inputs!$B$11) -> 0
A14: Levered cash flow | B14: =B11+B12+B13 -> -63925500 | C14: =C11+C12+C13 -> -52790095 | D14: =D11+D12+D13 -> -29058481 | E14: =E11+E12+E13 -> 271527.15 | F14: =F11+F12+F13 -> 11146836 | G14: =G11+G12+G13 -> 11873304 | H14: =H11+H12+H13 -> 2.9799917e+08 | I14: =I11+I12+I13 -> 0

Sheet Returns
A3: Unlevered IRR | B3: =IRR('Cash Flow'!B11:I11) -> 0.11885351
A4: Levered IRR | B4: =IRR('Cash Flow'!B14:I14) -> 0.16551883
A5: Equity multiple | B5: =SUMIF('Cash Flow'!B14:I14,">0")/-SUMIF('Cash Flow'!B14:I14,"<0") -> 2.2040327
A6: Total cost | B6: =-SUM('Cash Flow'!B7:I9) -> 301110000
A7: Net profit | B7: =SUM('Cash Flow'!B11:I11) -> 2.4755733e+08
A8: Yield on cost (stabilised) | B8: =SUMPRODUCT('Lease-Up'!B2:B5,'Lease-Up'!C2:C5)/B6 -> 0.075630168
