Workbook

Sheet Assumptions
A1: CAMPO SOLAR 48 MWp – PROJECT FINANCE MODEL (EUR)
A3: Capacity (MWp) | B3: 48
A4: Specific yield (kWh/kWp/yr) | B4: 1720
A5: Annual degradation | B5: 0.004
A6: PPA price (EUR/MWh) | B6: 52
A7: PPA term (years) | B7: 12
A8: Merchant price after PPA (EUR/MWh) | B8: 44
A9: Capex (EUR m/MWp) | B9: 0.62
A10: Opex (EUR k/MWp/yr) | B10: 13.5
A11: Opex indexation | B11: 0.02
A12: Asset life (years) | B12: 30
A13: Gearing | B13: 0.7
A14: Debt all-in rate | B14: 0.052
... A16: Corporate tax | B16: 0.25

Sheet Annual
A3: Year | B3: 0 | C3: 1 | D3: 2 | E3: 3 | F3: 4 | G3: 5 | H3: 6 | I3: 7 | J3: 8 | K3: 9 | L3: 10 | M3: 11 | N3: 12 | O3: 13 | P3: 14 | Q3: 15 | R3: 16 | S3: 17 | T3: 18 | U3: 19 | V3: 20 | W3: 21 | X3: 22 | Y3: 23 | Z3: 24 | AA3: 25 | AB3: 26 | AC3: 27 | AD3: 28 | AE3: 29 | AF3: 30
A4: Generation (MWh) | B4: =Assumptions!$B$3*Assumptions!$B$4*(1-Assumptions!$B$5)^MAX(0,B$3-1)*(B$3>=1)*(B$3<=Assumptions!$B$12) -> 0 | C4: =Assumptions!$B$3*Assumptions!$B$4*(1-Assumptions!$B$5)^MAX(0,C$3-1)*(C$3>=1)*(C$3<=Assumptions!$B$12) -> 82560 | D4: =Assumptions!$B$3*Assumptions!$B$4*(1-Assumptions!$B$5)^MAX(0,D$3-1)*(D$3>=1)*(D$3<=Assumptions!$B$12) -> 82229.76 | E4: =Assumptions!$B$3*Assumptions!$B$4*(1-Assumptions!$B$5)^MAX(0,E$3-1)*(E$3>=1)*(E$3<=Assumptions!$B$12) -> 81900.841 | F4: =Assumptions!$B$3*Assumptions!$B$4*(1-Assumptions!$B$5)^MAX(0,F$3-1)*(F$3>=1)*(F$3<=Assumptions!$B$12) -> 81573.238 | G4: =Assumptions!$B$3*Assumptions!$B$4*(1-Assumptions!$B$5)^MAX(0,G$3-1)*(G$3>=1)*(G$3<=Assumptions!$B$12) -> 81246.945 | H4: =Assumptions!$B$3*Assumptions!$B$4*(1-Assumptions!$B$5)^MAX(0,H$3-1)*(H$3>=1)*(H$3<=Assumptions!$B$12) -> 80921.957 | I4: =Assumptions!$B$3*Assumptions!$B$4*(1-Assumptions!$B$5)^MAX(0,I$3-1)*(I$3>=1)*(I$3<=Assumptions!$B$12) -> 80598.269 | ... AF4: =Assumptions!$B$3*Assumptions!$B$4*(1-Assumptions!$B$5)^MAX(0,AF$3-1)*(AF$3>=1)*(AF$3<=Assumptions!$B$12) -> 73500.535
A5: Price (EUR/MWh) | B5: =IF(B$3<=Assumptions!$B$7,Assumptions!$B$6,Assumptions!$B$8) -> 52 | C5: =IF(C$3<=Assumptions!$B$7,Assumptions!$B$6,Assumptions!$B$8) -> 52 | D5: =IF(D$3<=Assumptions!$B$7,Assumptions!$B$6,Assumptions!$B$8) -> 52 | E5: =IF(E$3<=Assumptions!$B$7,Assumptions!$B$6,Assumptions!$B$8) -> 52 | F5: =IF(F$3<=Assumptions!$B$7,Assumptions!$B$6,Assumptions!$B$8) -> 52 | G5: =IF(G$3<=Assumptions!$B$7,Assumptions!$B$6,Assumptions!$B$8) -> 52 | H5: =IF(H$3<=Assumptions!$B$7,Assumptions!$B$6,Assumptions!$B$8) -> 52 | I5: =IF(I$3<=Assumptions!$B$7,Assumptions!$B$6,Assumptions!$B$8) -> 52 | ... AF5: =IF(AF$3<=Assumptions!$B$7,Assumptions!$B$6,Assumptions!$B$8) -> 44
A6: Revenue | B6: =B4*B5 -> 0 | C6: =C4*C5 -> 4293120 | D6: =D4*D5 -> 4275947.5 | E6: =E4*E5 -> 4258843.7 | F6: =F4*F5 -> 4241808.4 | G6: =G4*G5 -> 4224841.1 | H6: =H4*H5 -> 4207941.8 | I6: =I4*I5 -> 4191110 | ... AF6: =AF4*AF5 -> 3234023.5
A7: Opex | B7: =-Assumptions!$B$3*Assumptions!$B$10*1000*(1+Assumptions!$B$11)^MAX(0,B$3-1)*(B$3>=1)*(B$3<=Assumptions!$B$12) -> 0 | C7: =-Assumptions!$B$3*Assumptions!$B$10*1000*(1+Assumptions!$B$11)^MAX(0,C$3-1)*(C$3>=1)*(C$3<=Assumptions!$B$12) -> -648000 | D7: =-Assumptions!$B$3*Assumptions!$B$10*1000*(1+Assumptions!$B$11)^MAX(0,D$3-1)*(D$3>=1)*(D$3<=Assumptions!$B$12) -> -660960 | E7: =-Assumptions!$B$3*Assumptions!$B$10*1000*(1+Assumptions!$B$11)^MAX(0,E$3-1)*(E$3>=1)*(E$3<=Assumptions!$B$12) -> -674179.2 | F7: =-Assumptions!$B$3*Assumptions!$B$10*1000*(1+Assumptions!$B$11)^MAX(0,F$3-1)*(F$3>=1)*(F$3<=Assumptions!$B$12) -> -687662.78 | G7: =-Assumptions!$B$3*Assumptions!$B$10*1000*(1+Assumptions!$B$11)^MAX(0,G$3-1)*(G$3>=1)*(G$3<=Assumptions!$B$12) -> -701416.04 | H7: =-Assumptions!$B$3*Assumptions!$B$10*1000*(1+Assumptions!$B$11)^MAX(0,H$3-1)*(H$3>=1)*(H$3<=Assumptions!$B$12) -> -715444.36 | I7: =-Assumptions!$B$3*Assumptions!$B$10*1000*(1+Assumptions!$B$11)^MAX(0,I$3-1)*(I$3>=1)*(I$3<=Assumptions!$B$12) -> -729753.25 | ... AF7: =-Assumptions!$B$3*Assumptions!$B$10*1000*(1+Assumptions!$B$11)^MAX(0,AF$3-1)*(AF$3>=1)*(AF$3<=Assumptions!$B$12) -> -1150747.4
A8: EBITDA | B8: =B6+B7 -> 0 | C8: =C6+C7 -> 3645120 | D8: =D6+D7 -> 3614987.5 | E8: =E6+E7 -> 3584664.5 | F8: =F6+F7 -> 3554145.6 | G8: =G6+G7 -> 3523425.1 | H8: =H6+H7 -> 3492497.4 | I8: =I6+I7 -> 3461356.7 | ... AF8: =AF6+AF7 -> 2083276.2
A9: Capex | B9: =IF(B$3=0,-Assumptions!$B$3*Assumptions!$B$9*1000000,0) -> -29760000 | C9: =IF(C$3=0,-Assumptions!$B$3*Assumptions!$B$9*1000000,0) -> 0 | D9: =IF(D$3=0,-Assumptions!$B$3*Assumptions!$B$9*1000000,0) -> 0 | E9: =IF(E$3=0,-Assumptions!$B$3*Assumptions!$B$9*1000000,0) -> 0 | F9: =IF(F$3=0,-Assumptions!$B$3*Assumptions!$B$9*1000000,0) -> 0 | G9: =IF(G$3=0,-Assumptions!$B$3*Assumptions!$B$9*1000000,0) -> 0 | H9: =IF(H$3=0,-Assumptions!$B$3*Assumptions!$B$9*1000000,0) -> 0 | I9: =IF(I$3=0,-Assumptions!$B$3*Assumptions!$B$9*1000000,0) -> 0 | ... AF9: =IF(AF$3=0,-Assumptions!$B$3*Assumptions!$B$9*1000000,0) -> 0
A10: Debt service | B10: =IF(AND(B$3>=1,B$3<=Assumptions!$B$15),PMT(Assumptions!$B$14,Assumptions!$B$15,Assumptions!$B$3*Assumptions!$B$9*1000000*Assumptions!$B$13),0) -> 0 | C10: =IF(AND(C$3>=1,C$3<=Assumptions!$B$15),PMT(Assumptions!$B$14,Assumptions!$B$15,Assumptions!$B$3*Assumptions!$B$9*1000000*Assumptions!$B$13),0) -> -1810052 | D10: =IF(AND(D$3>=1,D$3<=Assumptions!$B$15),PMT(Assumptions!$B$14,Assumptions!$B$15,Assumptions!$B$3*Assumptions!$B$9*1000000*Assumptions!$B$13),0) -> -1810052 | E10: =IF(AND(E$3>=1,E$3<=Assumptions!$B$15),PMT(Assumptions!$B$14,Assumptions!$B$15,Assumptions!$B$3*Assumptions!$B$9*1000000*Assumptions!$B$13),0) -> -1810052 | F10: =IF(AND(F$3>=1,F$3<=Assumptions!$B$15),PMT(Assumptions!$B$14,Assumptions!$B$15,Assumptions!$B$3*Assumptions!$B$9*1000000*Assumptions!$B$13),0) -> -1810052 | G10: =IF(AND(G$3>=1,G$3<=Assumptions!$B$15),PMT(Assumptions!$B$14,Assumptions!$B$15,Assumptions!$B$3*Assumptions!$B$9*1000000*Assumptions!$B$13),0) -> -1810052 | H10: =IF(AND(H$3>=1,H$3<=Assumptions!$B$15),PMT(Assumptions!$B$14,Assumptions!$B$15,Assumptions!$B$3*Assumptions!$B$9*1000000*Assumptions!$B$13),0) -> -1810052 | I10: =IF(AND(I$3>=1,I$3<=Assumptions!$B$15),PMT(Assumptions!$B$14,Assumptions!$B$15,Assumptions!$B$3*Assumptions!$B$9*1000000*Assumptions!$B$13),0) -> -1810052 | ... AF10: =IF(AND(AF$3>=1,AF$3<=Assumptions!$B$15),PMT(Assumptions!$B$14,Assumptions!$B$15,Assumptions!$B$3*Assumptions!$B$9*1000000*Assumptions!$B$13),0) -> 0
A11: Tax | B11: =-MAX(0,B8-Assumptions!$B$3*Assumptions!$B$9*1000000/Assumptions!$B$12*(B$3>=1)*(B$3<=Assumptions!$B$12))*Assumptions!$B$16 -> 0 | C11: =-MAX(0,C8-Assumptions!$B$3*Assumptions!$B$9*1000000/Assumptions!$B$12*(C$3>=1)*(C$3<=Assumptions!$B$12))*Assumptions!$B$16 -> -663280 | D11: =-MAX(0,D8-Assumptions!$B$3*Assumptions!$B$9*1000000/Assumptions!$B$12*(D$3>=1)*(D$3<=Assumptions!$B$12))*Assumptions!$B$16 -> -655746.88 | E11: =-MAX(0,E8-Assumptions!$B$3*Assumptions!$B$9*1000000/Assumptions!$B$12*(E$3>=1)*(E$3<=Assumptions!$B$12))*Assumptions!$B$16 -> -648166.13 | F11: =-MAX(0,F8-Assumptions!$B$3*Assumptions!$B$9*1000000/Assumptions!$B$12*(F$3>=1)*(F$3<=Assumptions!$B$12))*Assumptions!$B$16 -> -640536.39 | G11: =-MAX(0,G8-Assumptions!$B$3*Assumptions!$B$9*1000000/Assumptions!$B$12*(G$3>=1)*(G$3<=Assumptions!$B$12))*Assumptions!$B$16 -> -632856.27 | H11: =-MAX(0,H8-Assumptions!$B$3*Assumptions!$B$9*1000000/Assumptions!$B$12*(H$3>=1)*(H$3<=Assumptions!$B$12))*Assumptions!$B$16 -> -625124.35 | I11: =-MAX(0,I8-Assumptions!$B$3*Assumptions!$B$9*1000000/Assumptions!$B$12*(I$3>=1)*(I$3<=Assumptions!$B$12))*Assumptions!$B$16 -> -617339.19 | ... AF11: =-MAX(0,AF8-Assumptions!$B$3*Assumptions!$B$9*1000000/Assumptions!$B$12*(AF$3>=1)*(AF$3<=Assumptions!$B$12))*Assumptions!$B$16 -> -272819.04
A12: Project cash flow | B12: =B8+B9+B11 -> -29760000 | C12: =C8+C9+C11 -> 2981840 | D12: =D8+D9+D11 -> 2959240.6 | E12: =E8+E9+E11 -> 2936498.4 | F12: =F8+F9+F11 -> 2913609.2 | G12: =G8+G9+G11 -> 2890568.8 | H12: =H8+H9+H11 -> 2867373 | I12: =I8+I9+I11 -> 2844017.6 | ... AF12: =AF8+AF9+AF11 -> 1810457.1
A13: Equity cash flow | B13: =B12+B10+IF(B$3=0,Assumptions!$B$3*Assumptions!$B$9*1000000*Assumptions!$B$13,0) -> -8928000 | C13: =C12+C10+IF(C$3=0,Assumptions!$B$3*Assumptions!$B$9*1000000*Assumptions!$B$13,0) -> 1171788 | D13: =D12+D10+IF(D$3=0,Assumptions!$B$3*Assumptions!$B$9*1000000*Assumptions!$B$13,0) -> 1149188.7 | E13: =E12+E10+IF(E$3=0,Assumptions!$B$3*Assumptions!$B$9*1000000*Assumptions!$B$13,0) -> 1126446.4 | F13: =F12+F10+IF(F$3=0,Assumptions!$B$3*Assumptions!$B$9*1000000*Assumptions!$B$13,0) -> 1103557.2 | G13: =G12+G10+IF(G$3=0,Assumptions!$B$3*Assumptions!$B$9*1000000*Assumptions!$B$13,0) -> 1080516.8 | H13: =H12+H10+IF(H$3=0,Assumptions!$B$3*Assumptions!$B$9*1000000*Assumptions!$B$13,0) -> 1057321.1 | I13: =I12+I10+IF(I$3=0,Assumptions!$B$3*Assumptions!$B$9*1000000*Assumptions!$B$13,0) -> 1033965.6 | ... AF13: =AF12+AF10+IF(AF$3=0,Assumptions!$B$3*Assumptions!$B$9*1000000*Assumptions!$B$13,0) -> 1810457.1
A14: DSCR | B14: =IF(B10<0,B8/-B10,"") | C14: =IF(C10<0,C8/-C10,"") -> 2.0138206 | D14: =IF(D10<0,D8/-D10,"") -> 1.9971733 | E14: =IF(E10<0,E8/-E10,"") -> 1.9804208 | F14: =IF(F10<0,F8/-F10,"") -> 1.96356 | G14: =IF(G10<0,G8/-G10,"") -> 1.9465878 | H14: =IF(H10<0,H8/-H10,"") -> 1.9295012 | I14: =IF(I10<0,I8/-I10,"") -> 1.9122969 | ... AF14: =IF(AF10<0,AF8/-AF10,"")

Sheet Results
A3: Project IRR | B3: =IRR(Annual!B12:AF12) -> 0.078528105
A4: Equity IRR | B4: =IRR(Annual!B13:AF13) -> 0.11598263
A5: Minimum DSCR | B5: =MIN(Annual!C14:AF14) -> 1.3734483
A6: Average DSCR | B6: =AVERAGE(Annual!C14:AF14) -> 1.7522391
A7: Total capex | B7: =-Annual!B9 -> 29760000
A8: Net profit | B8: =SUM(Annual!B12:AF12) -> 40945293
A9: LCOE proxy (EUR/MWh) | B9: =(-Annual!B9-SUM(Annual!C7:AF7))/SUM(Annual!C4:AF4) -> 23.968915
