Workbook

Sheet Inputs
A1: MAPLE RIDGE TOWNHOMES – BUILD TO SELL (CAD)
A3: Townhomes | B3: 96
A4: Average sale price (C$) | B4: 845000
A5: Sales pace (homes per quarter) | B5: 12
A6: Sales start (quarter) | B6: 2
A7: Hard cost per home (C$) | B7: 410000
A8: Soft costs (% of hard) | B8: 0.16
A9: Land (C$) | B9: 18500000
A10: Development charges per home (C$) | B10: 62000
A11: Commission | B11: 0.04
A12: Price growth per quarter | B12: 0.006

Sheet Releases
A1: Release | B1: Homes
A2: 1 | B2: 24
A3: 2 | B3: 24
A4: 3 | B4: 24
A5: 4 | B5: 24

Sheet Quarterly
A3: Quarter | B3: 0 | C3: 1 | D3: 2 | E3: 3 | F3: 4 | G3: 5 | H3: 6 | I3: 7 | J3: 8 | K3: 9 | L3: 10 | M3: 11 | N3: 12 | O3: 13 | P3: 14 | Q3: 15 | R3: 16
A4: Homes available | B4: =IFERROR(SUM(OFFSET(Releases!$B$2,0,0,MIN(4,MAX(0,INT((B$3-Inputs!$B$6)/2)+1)),1)),0)*(B$3>=Inputs!$B$6) -> 0 | C4: =IFERROR(SUM(OFFSET(Releases!$B$2,0,0,MIN(4,MAX(0,INT((C$3-Inputs!$B$6)/2)+1)),1)),0)*(C$3>=Inputs!$B$6) -> 0 | D4: =IFERROR(SUM(OFFSET(Releases!$B$2,0,0,MIN(4,MAX(0,INT((D$3-Inputs!$B$6)/2)+1)),1)),0)*(D$3>=Inputs!$B$6) -> 24 | E4: =IFERROR(SUM(OFFSET(Releases!$B$2,0,0,MIN(4,MAX(0,INT((E$3-Inputs!$B$6)/2)+1)),1)),0)*(E$3>=Inputs!$B$6) -> 24 | F4: =IFERROR(SUM(OFFSET(Releases!$B$2,0,0,MIN(4,MAX(0,INT((F$3-Inputs!$B$6)/2)+1)),1)),0)*(F$3>=Inputs!$B$6) -> 48 | G4: =IFERROR(SUM(OFFSET(Releases!$B$2,0,0,MIN(4,MAX(0,INT((G$3-Inputs!$B$6)/2)+1)),1)),0)*(G$3>=Inputs!$B$6) -> 48 | H4: =IFERROR(SUM(OFFSET(Releases!$B$2,0,0,MIN(4,MAX(0,INT((H$3-Inputs!$B$6)/2)+1)),1)),0)*(H$3>=Inputs!$B$6) -> 72 | I4: =IFERROR(SUM(OFFSET(Releases!$B$2,0,0,MIN(4,MAX(0,INT((I$3-Inputs!$B$6)/2)+1)),1)),0)*(I$3>=Inputs!$B$6) -> 72 | ... R4: =IFERROR(SUM(OFFSET(Releases!$B$2,0,0,MIN(4,MAX(0,INT((R$3-Inputs!$B$6)/2)+1)),1)),0)*(R$3>=Inputs!$B$6) -> 96
A5: Homes sold | B5: =0 -> 0 | C5: =MAX(0,MIN(Inputs!$B$5,C4-B6))*(C$3>=Inputs!$B$6) -> 0 | D5: =MAX(0,MIN(Inputs!$B$5,D4-C6))*(D$3>=Inputs!$B$6) -> 12 | E5: =MAX(0,MIN(Inputs!$B$5,E4-D6))*(E$3>=Inputs!$B$6) -> 12 | F5: =MAX(0,MIN(Inputs!$B$5,F4-E6))*(F$3>=Inputs!$B$6) -> 12 | G5: =MAX(0,MIN(Inputs!$B$5,G4-F6))*(G$3>=Inputs!$B$6) -> 12 | H5: =MAX(0,MIN(Inputs!$B$5,H4-G6))*(H$3>=Inputs!$B$6) -> 12 | I5: =MAX(0,MIN(Inputs!$B$5,I4-H6))*(I$3>=Inputs!$B$6) -> 12 | J5: =MAX(0,MIN(Inputs!$B$5,J4-I6))*(J$3>=Inputs!$B$6) -> 12 | ... R5: =MAX(0,MIN(Inputs!$B$5,R4-Q6))*(R$3>=Inputs!$B$6) -> 0
A6: Cumulative sold | B6: =B5 -> 0 | C6: =B6+C5 -> 0 | D6: =C6+D5 -> 12 | E6: =D6+E5 -> 24 | F6: =E6+F5 -> 36 | G6: =F6+G5 -> 48 | H6: =G6+H5 -> 60 | I6: =H6+I5 -> 72 | J6: =I6+J5 -> 84 | ... R6: =Q6+R5 -> 96
A7: Revenue | B7: =B5*Inputs!$B$4*(1+Inputs!$B$12)^B$3 -> 0 | C7: =C5*Inputs!$B$4*(1+Inputs!$B$12)^C$3 -> 0 | D7: =D5*Inputs!$B$4*(1+Inputs!$B$12)^D$3 -> 10262045 | E7: =E5*Inputs!$B$4*(1+Inputs!$B$12)^E$3 -> 10323617 | F7: =F5*Inputs!$B$4*(1+Inputs!$B$12)^F$3 -> 10385559 | G7: =G5*Inputs!$B$4*(1+Inputs!$B$12)^G$3 -> 10447872 | H7: =H5*Inputs!$B$4*(1+Inputs!$B$12)^H$3 -> 10510560 | I7: =I5*Inputs!$B$4*(1+Inputs!$B$12)^I$3 -> 10573623 | ... R7: =R5*Inputs!$B$4*(1+Inputs!$B$12)^R$3 -> 0
A8: Hard & soft | B8: =-IF(AND(B$3>=1,B$3<=8),Inputs!$B$3*Inputs!$B$7*(1+Inputs!$B$8)/8,0) -> 0 | C8: =-IF(AND(C$3>=1,C$3<=8),Inputs!$B$3*Inputs!$B$7*(1+Inputs!$B$8)/8,0) -> -5707200 | D8: =-IF(AND(D$3>=1,D$3<=8),Inputs!$B$3*Inputs!$B$7*(1+Inputs!$B$8)/8,0) -> -5707200 | E8: =-IF(AND(E$3>=1,E$3<=8),Inputs!$B$3*Inputs!$B$7*(1+Inputs!$B$8)/8,0) -> -5707200 | F8: =-IF(AND(F$3>=1,F$3<=8),Inputs!$B$3*Inputs!$B$7*(1+Inputs!$B$8)/8,0) -> -5707200 | G8: =-IF(AND(G$3>=1,G$3<=8),Inputs!$B$3*Inputs!$B$7*(1+Inputs!$B$8)/8,0) -> -5707200 | H8: =-IF(AND(H$3>=1,H$3<=8),Inputs!$B$3*Inputs!$B$7*(1+Inputs!$B$8)/8,0) -> -5707200 | I8: =-IF(AND(I$3>=1,I$3<=8),Inputs!$B$3*Inputs!$B$7*(1+Inputs!$B$8)/8,0) -> -5707200 | ... R8: =-IF(AND(R$3>=1,R$3<=8),Inputs!$B$3*Inputs!$B$7*(1+Inputs!$B$8)/8,0) -> 0
A9: Land & charges | B9: =IF(B$3=0,-Inputs!$B$9-Inputs!$B$3*Inputs!$B$10,0) -> -24452000 | C9: =IF(C$3=0,-Inputs!$B$9-Inputs!$B$3*Inputs!$B$10,0) -> 0 | D9: =IF(D$3=0,-Inputs!$B$9-Inputs!$B$3*Inputs!$B$10,0) -> 0 | E9: =IF(E$3=0,-Inputs!$B$9-Inputs!$B$3*Inputs!$B$10,0) -> 0 | F9: =IF(F$3=0,-Inputs!$B$9-Inputs!$B$3*Inputs!$B$10,0) -> 0 | G9: =IF(G$3=0,-Inputs!$B$9-Inputs!$B$3*Inputs!$B$10,0) -> 0 | H9: =IF(H$3=0,-Inputs!$B$9-Inputs!$B$3*Inputs!$B$10,0) -> 0 | I9: =IF(I$3=0,-Inputs!$B$9-Inputs!$B$3*Inputs!$B$10,0) -> 0 | ... R9: =IF(R$3=0,-Inputs!$B$9-Inputs!$B$3*Inputs!$B$10,0) -> 0
A10: Commission | B10: =-B7*Inputs!$B$11 -> 0 | C10: =-C7*Inputs!$B$11 -> 0 | D10: =-D7*Inputs!$B$11 -> -410481.8 | E10: =-E7*Inputs!$B$11 -> -412944.69 | F10: =-F7*Inputs!$B$11 -> -415422.36 | G10: =-G7*Inputs!$B$11 -> -417914.89 | H10: =-H7*Inputs!$B$11 -> -420422.38 | I10: =-I7*Inputs!$B$11 -> -422944.92 | ... R10: =-R7*Inputs!$B$11 -> 0
A11: Net cash flow | B11: =SUM(B7:B10) -> -24452000 | C11: =SUM(C7:C10) -> -5707200 | D11: =SUM(D7:D10) -> 4144363.2 | E11: =SUM(E7:E10) -> 4203472.6 | F11: =SUM(F7:F10) -> 4262936.7 | G11: =SUM(G7:G10) -> 4322757.5 | H11: =SUM(H7:H10) -> 4382937.2 | I11: =SUM(I7:I10) -> 4443478 | ... R11: =SUM(R7:R10) -> 0

Sheet Summary
A3: Project IRR (annual) | B3: =(1+IRR(Quarterly!B11:R11))^4-1 -> 0.22995606
A4: Net profit | B4: =SUM(Quarterly!B11:R11) -> 10377979
A5: Total development cost | B5: =-SUM(Quarterly!B8:R9) -> 70109600
A6: Profit on cost | B6: =B4/B5 -> 0.14802508
A7: Homes unsold at the end | B7: =Inputs!$B$3-Quarterly!R6 -> 0
A8: Gross revenue | B8: =SUM(Quarterly!B7:R7) -> 83841228
