Workbook

Sheet Inputs
A1: MARINA GATE – MULTI-STOREY CAR PARK (AED)
A3: Bays | B3: 1450
A4: Tariff band (1 = Standard, 2 = Premium, 3 = Event) | B4: 1
A5: Weekday occupancy | B5: 0.62
A6: Weekend occupancy | B6: 0.78
A7: Turnover per bay per day | B7: 2.4
A8: Average stay (hours) | B8: 2.5
A9: Season ticket holders | B9: 260
A10: Season ticket (AED/month) | B10: 650
A11: Build cost per bay (AED) | B11: 95000
A12: Opex (% of revenue) | B12: 0.28
A13: Exit yield | B13: 0.08
A14: Hold (years) | B14: 10
A15: Tariff growth | B15: 0.03

Sheet Tariffs
A1: Band | B1: First hour (AED) | C1: Each extra hour (AED)
A2: 1 | B2: 10 | C2: 8
A3: 2 | B3: 15 | C3: 12
A4: 3 | B4: 25 | C4: 20

Sheet Operations
A3: Ticket per visit (AED) | B3: =CHOOSE(Inputs!$B$4,Tariffs!B2,Tariffs!B3,Tariffs!B4)+MAX(0,Inputs!$B$8-1)*CHOOSE(Inputs!$B$4,Tariffs!C2,Tariffs!C3,Tariffs!C4) -> 22
A4: Visits per year | B4: =(Inputs!$B$3-Inputs!$B$9)*Inputs!$B$7*(260*Inputs!$B$5+105*Inputs!$B$6) -> 694293.6
A5: Transient revenue | B5: =B3*B4 -> 15274459
A6: Season revenue | B6: =Inputs!$B$9*Inputs!$B$10*12 -> 2028000
A7: Revenue (year 1) | B7: =B5+B6 -> 17302459
A8: Opex | B8: =-B7*Inputs!$B$12 -> -4844688.6
A9: NOI (year 1) | B9: =B7+B8 -> 12457771
A10: Build cost | B10: =Inputs!$B$3*Inputs!$B$11 -> 137750000

Sheet Cash Flow
A3: Year | B3: 0 | C3: 1 | D3: 2 | E3: 3 | F3: 4 | G3: 5 | H3: 6 | I3: 7 | J3: 8 | K3: 9 | L3: 10 | M3: 11 | N3: 12
A4: NOI | B4: =IF(AND(B$3>=1,B$3<=Inputs!$B$14),Operations!$B$9*(1+Inputs!$B$15)^(B$3-1),0) -> 0 | C4: =IF(AND(C$3>=1,C$3<=Inputs!$B$14),Operations!$B$9*(1+Inputs!$B$15)^(C$3-1),0) -> 12457771 | D4: =IF(AND(D$3>=1,D$3<=Inputs!$B$14),Operations!$B$9*(1+Inputs!$B$15)^(D$3-1),0) -> 12831504 | E4: =IF(AND(E$3>=1,E$3<=Inputs!$B$14),Operations!$B$9*(1+Inputs!$B$15)^(E$3-1),0) -> 13216449 | F4: =IF(AND(F$3>=1,F$3<=Inputs!$B$14),Operations!$B$9*(1+Inputs!$B$15)^(F$3-1),0) -> 13612942 | G4: =IF(AND(G$3>=1,G$3<=Inputs!$B$14),Operations!$B$9*(1+Inputs!$B$15)^(G$3-1),0) -> 14021331 | H4: =IF(AND(H$3>=1,H$3<=Inputs!$B$14),Operations!$B$9*(1+Inputs!$B$15)^(H$3-1),0) -> 14441971 | I4: =IF(AND(I$3>=1,I$3<=Inputs!$B$14),Operations!$B$9*(1+Inputs!$B$15)^(I$3-1),0) -> 14875230 | ... N4: =IF(AND(N$3>=1,N$3<=Inputs!$B$14),Operations!$B$9*(1+Inputs!$B$15)^(N$3-1),0) -> 0
A5: Capex | B5: =IF(B$3=0,-Operations!$B$10,0) -> -137750000 | C5: =IF(C$3=0,-Operations!$B$10,0) -> 0 | D5: =IF(D$3=0,-Operations!$B$10,0) -> 0 | E5: =IF(E$3=0,-Operations!$B$10,0) -> 0 | F5: =IF(F$3=0,-Operations!$B$10,0) -> 0 | G5: =IF(G$3=0,-Operations!$B$10,0) -> 0 | H5: =IF(H$3=0,-Operations!$B$10,0) -> 0 | I5: =IF(I$3=0,-Operations!$B$10,0) -> 0 | ... N5: =IF(N$3=0,-Operations!$B$10,0) -> 0
A6: Sale | B6: =IF(B$3=Inputs!$B$14,Operations!$B$9*(1+Inputs!$B$15)^B$3/Inputs!$B$13,0) -> 0 | C6: =IF(C$3=Inputs!$B$14,Operations!$B$9*(1+Inputs!$B$15)^C$3/Inputs!$B$13,0) -> 0 | D6: =IF(D$3=Inputs!$B$14,Operations!$B$9*(1+Inputs!$B$15)^D$3/Inputs!$B$13,0) -> 0 | E6: =IF(E$3=Inputs!$B$14,Operations!$B$9*(1+Inputs!$B$15)^E$3/Inputs!$B$13,0) -> 0 | F6: =IF(F$3=Inputs!$B$14,Operations!$B$9*(1+Inputs!$B$15)^F$3/Inputs!$B$13,0) -> 0 | G6: =IF(G$3=Inputs!$B$14,Operations!$B$9*(1+Inputs!$B$15)^G$3/Inputs!$B$13,0) -> 0 | H6: =IF(H$3=Inputs!$B$14,Operations!$B$9*(1+Inputs!$B$15)^H$3/Inputs!$B$13,0) -> 0 | I6: =IF(I$3=Inputs!$B$14,Operations!$B$9*(1+Inputs!$B$15)^I$3/Inputs!$B$13,0) -> 0 | ... N6: =IF(N$3=Inputs!$B$14,Operations!$B$9*(1+Inputs!$B$15)^N$3/Inputs!$B$13,0) -> 0
A7: Net cash flow | B7: =SUM(B4:B6) -> -137750000 | C7: =SUM(C4:C6) -> 12457771 | D7: =SUM(D4:D6) -> 12831504 | E7: =SUM(E4:E6) -> 13216449 | F7: =SUM(F4:F6) -> 13612942 | G7: =SUM(G4:G6) -> 14021331 | H7: =SUM(H4:H6) -> 14441971 | I7: =SUM(I4:I6) -> 14875230 | ... N7: =SUM(N4:N6) -> 0

Sheet Summary
A3: Unlevered IRR | B3: =IRR('Cash Flow'!B7:N7) -> 0.12902675
A4: Yield on cost | B4: =Operations!B9/Operations!B10 -> 0.090437536
A5: Net profit | B5: =SUM('Cash Flow'!B7:N7) -> 2.143419e+08
A6: Total development cost | B6: =Operations!B10 -> 137750000
A7: Revenue per bay (AED/yr) | B7: =Operations!B7/Inputs!$B$3 -> 11932.73
