Workbook

Sheet Inputs
A1: KAFD TOWER 7 – MIXED-USE DEVELOPMENT (SAR) – MONTHLY
A3: Project start date | B3: 46388
A4: Construction (months) | B4: 30
A5: Land (SAR) | B5: 310000000
A6: Construction cost (SAR) | B6: 880000000
A7: Office NLA (sqm) | B7: 42000
A8: Office rent (SAR/sqm/yr) | B8: 2300
A9: Retail GLA (sqm) | B9: 6500
A10: Retail rent (SAR/sqm/yr) | B10: 3100
A11: Lease-up after completion (months) | B11: 18
A12: Exit yield | B12: 0.075
A13: Sale month after completion | B13: 24
A14: Discount rate | B14: 0.1

Sheet Monthly
A3: Month | B3: 0 | C3: 1 | D3: 2 | E3: 3 | F3: 4 | G3: 5 | H3: 6 | I3: 7 | J3: 8 | K3: 9 | L3: 10 | M3: 11 | N3: 12 | O3: 13 | P3: 14 | Q3: 15 | R3: 16 | S3: 17 | T3: 18 | U3: 19 | V3: 20 | W3: 21 | X3: 22 | Y3: 23 | Z3: 24 | AA3: 25 | AB3: 26 | AC3: 27 | AD3: 28 | AE3: 29 | AF3: 30 | AG3: 31 | AH3: 32 | AI3: 33 | AJ3: 34 | AK3: 35 | AL3: 36 | AM3: 37 | AN3: 38 | AO3: 39 | AP3: 40 | AQ3: 41 | AR3: 42 | AS3: 43 | AT3: 44 | AU3: 45 | AV3: 46 | AW3: 47 | AX3: 48 | AY3: 49 | AZ3: 50 | BA3: 51 | BB3: 52 | BC3: 53 | BD3: 54 | BE3: 55 | BF3: 56 | BG3: 57 | BH3: 58 | BI3: 59 | BJ3: 60 | BK3: 61 | BL3: 62 | BM3: 63 | BN3: 64 | BO3: 65 | BP3: 66 | BQ3: 67 | BR3: 68 | BS3: 69 | BT3: 70 | BU3: 71 | BV3: 72 | BW3: 73 | BX3: 74 | BY3: 75 | BZ3: 76 | CA3: 77 | CB3: 78
A4: Date | B4: =EDATE(Inputs!$B$3,B$3) -> 46388 | C4: =EDATE(Inputs!$B$3,C$3) -> 46419 | D4: =EDATE(Inputs!$B$3,D$3) -> 46447 | E4: =EDATE(Inputs!$B$3,E$3) -> 46478 | F4: =EDATE(Inputs!$B$3,F$3) -> 46508 | G4: =EDATE(Inputs!$B$3,G$3) -> 46539 | H4: =EDATE(Inputs!$B$3,H$3) -> 46569 | I4: =EDATE(Inputs!$B$3,I$3) -> 46600 | ... CB4: =EDATE(Inputs!$B$3,CB$3) -> 48761
A5: Land | B5: =IF(B$3=0,-Inputs!$B$5,0) -> -310000000 | C5: =IF(C$3=0,-Inputs!$B$5,0) -> 0 | D5: =IF(D$3=0,-Inputs!$B$5,0) -> 0 | E5: =IF(E$3=0,-Inputs!$B$5,0) -> 0 | F5: =IF(F$3=0,-Inputs!$B$5,0) -> 0 | G5: =IF(G$3=0,-Inputs!$B$5,0) -> 0 | H5: =IF(H$3=0,-Inputs!$B$5,0) -> 0 | I5: =IF(I$3=0,-Inputs!$B$5,0) -> 0 | ... CB5: =IF(CB$3=0,-Inputs!$B$5,0) -> 0
A6: Construction | B6: =IF(AND(B$3>=1,B$3<=Inputs!$B$4),-Inputs!$B$6/Inputs!$B$4,0) -> 0 | C6: =IF(AND(C$3>=1,C$3<=Inputs!$B$4),-Inputs!$B$6/Inputs!$B$4,0) -> -29333333 | D6: =IF(AND(D$3>=1,D$3<=Inputs!$B$4),-Inputs!$B$6/Inputs!$B$4,0) -> -29333333 | E6: =IF(AND(E$3>=1,E$3<=Inputs!$B$4),-Inputs!$B$6/Inputs!$B$4,0) -> -29333333 | F6: =IF(AND(F$3>=1,F$3<=Inputs!$B$4),-Inputs!$B$6/Inputs!$B$4,0) -> -29333333 | G6: =IF(AND(G$3>=1,G$3<=Inputs!$B$4),-Inputs!$B$6/Inputs!$B$4,0) -> -29333333 | H6: =IF(AND(H$3>=1,H$3<=Inputs!$B$4),-Inputs!$B$6/Inputs!$B$4,0) -> -29333333 | I6: =IF(AND(I$3>=1,I$3<=Inputs!$B$4),-Inputs!$B$6/Inputs!$B$4,0) -> -29333333 | ... CB6: =IF(AND(CB$3>=1,CB$3<=Inputs!$B$4),-Inputs!$B$6/Inputs!$B$4,0) -> 0
A7: Office rent | B7: =(B$3>Inputs!$B$4)*(B$3<=Inputs!$B$4+Inputs!$B$13)*Inputs!$B$7*Inputs!$B$8/12*MIN(1,MAX(0,(B$3-Inputs!$B$4)/Inputs!$B$11)) -> 0 | C7: =(C$3>Inputs!$B$4)*(C$3<=Inputs!$B$4+Inputs!$B$13)*Inputs!$B$7*Inputs!$B$8/12*MIN(1,MAX(0,(C$3-Inputs!$B$4)/Inputs!$B$11)) -> 0 | D7: =(D$3>Inputs!$B$4)*(D$3<=Inputs!$B$4+Inputs!$B$13)*Inputs!$B$7*Inputs!$B$8/12*MIN(1,MAX(0,(D$3-Inputs!$B$4)/Inputs!$B$11)) -> 0 | E7: =(E$3>Inputs!$B$4)*(E$3<=Inputs!$B$4+Inputs!$B$13)*Inputs!$B$7*Inputs!$B$8/12*MIN(1,MAX(0,(E$3-Inputs!$B$4)/Inputs!$B$11)) -> 0 | F7: =(F$3>Inputs!$B$4)*(F$3<=Inputs!$B$4+Inputs!$B$13)*Inputs!$B$7*Inputs!$B$8/12*MIN(1,MAX(0,(F$3-Inputs!$B$4)/Inputs!$B$11)) -> 0 | G7: =(G$3>Inputs!$B$4)*(G$3<=Inputs!$B$4+Inputs!$B$13)*Inputs!$B$7*Inputs!$B$8/12*MIN(1,MAX(0,(G$3-Inputs!$B$4)/Inputs!$B$11)) -> 0 | H7: =(H$3>Inputs!$B$4)*(H$3<=Inputs!$B$4+Inputs!$B$13)*Inputs!$B$7*Inputs!$B$8/12*MIN(1,MAX(0,(H$3-Inputs!$B$4)/Inputs!$B$11)) -> 0 | I7: =(I$3>Inputs!$B$4)*(I$3<=Inputs!$B$4+Inputs!$B$13)*Inputs!$B$7*Inputs!$B$8/12*MIN(1,MAX(0,(I$3-Inputs!$B$4)/Inputs!$B$11)) -> 0 | ... CB7: =(CB$3>Inputs!$B$4)*(CB$3<=Inputs!$B$4+Inputs!$B$13)*Inputs!$B$7*Inputs!$B$8/12*MIN(1,MAX(0,(CB$3-Inputs!$B$4)/Inputs!$B$11)) -> 0
A8: Retail rent | B8: =(B$3>Inputs!$B$4)*(B$3<=Inputs!$B$4+Inputs!$B$13)*Inputs!$B$9*Inputs!$B$10/12*MIN(1,MAX(0,(B$3-Inputs!$B$4)/Inputs!$B$11)) -> 0 | C8: =(C$3>Inputs!$B$4)*(C$3<=Inputs!$B$4+Inputs!$B$13)*Inputs!$B$9*Inputs!$B$10/12*MIN(1,MAX(0,(C$3-Inputs!$B$4)/Inputs!$B$11)) -> 0 | D8: =(D$3>Inputs!$B$4)*(D$3<=Inputs!$B$4+Inputs!$B$13)*Inputs!$B$9*Inputs!$B$10/12*MIN(1,MAX(0,(D$3-Inputs!$B$4)/Inputs!$B$11)) -> 0 | E8: =(E$3>Inputs!$B$4)*(E$3<=Inputs!$B$4+Inputs!$B$13)*Inputs!$B$9*Inputs!$B$10/12*MIN(1,MAX(0,(E$3-Inputs!$B$4)/Inputs!$B$11)) -> 0 | F8: =(F$3>Inputs!$B$4)*(F$3<=Inputs!$B$4+Inputs!$B$13)*Inputs!$B$9*Inputs!$B$10/12*MIN(1,MAX(0,(F$3-Inputs!$B$4)/Inputs!$B$11)) -> 0 | G8: =(G$3>Inputs!$B$4)*(G$3<=Inputs!$B$4+Inputs!$B$13)*Inputs!$B$9*Inputs!$B$10/12*MIN(1,MAX(0,(G$3-Inputs!$B$4)/Inputs!$B$11)) -> 0 | H8: =(H$3>Inputs!$B$4)*(H$3<=Inputs!$B$4+Inputs!$B$13)*Inputs!$B$9*Inputs!$B$10/12*MIN(1,MAX(0,(H$3-Inputs!$B$4)/Inputs!$B$11)) -> 0 | I8: =(I$3>Inputs!$B$4)*(I$3<=Inputs!$B$4+Inputs!$B$13)*Inputs!$B$9*Inputs!$B$10/12*MIN(1,MAX(0,(I$3-Inputs!$B$4)/Inputs!$B$11)) -> 0 | ... CB8: =(CB$3>Inputs!$B$4)*(CB$3<=Inputs!$B$4+Inputs!$B$13)*Inputs!$B$9*Inputs!$B$10/12*MIN(1,MAX(0,(CB$3-Inputs!$B$4)/Inputs!$B$11)) -> 0
A9: Sale | B9: =IF(B$3=Inputs!$B$4+Inputs!$B$13,(Inputs!$B$7*Inputs!$B$8+Inputs!$B$9*Inputs!$B$10)/Inputs!$B$12,0) -> 0 | C9: =IF(C$3=Inputs!$B$4+Inputs!$B$13,(Inputs!$B$7*Inputs!$B$8+Inputs!$B$9*Inputs!$B$10)/Inputs!$B$12,0) -> 0 | D9: =IF(D$3=Inputs!$B$4+Inputs!$B$13,(Inputs!$B$7*Inputs!$B$8+Inputs!$B$9*Inputs!$B$10)/Inputs!$B$12,0) -> 0 | E9: =IF(E$3=Inputs!$B$4+Inputs!$B$13,(Inputs!$B$7*Inputs!$B$8+Inputs!$B$9*Inputs!$B$10)/Inputs!$B$12,0) -> 0 | F9: =IF(F$3=Inputs!$B$4+Inputs!$B$13,(Inputs!$B$7*Inputs!$B$8+Inputs!$B$9*Inputs!$B$10)/Inputs!$B$12,0) -> 0 | G9: =IF(G$3=Inputs!$B$4+Inputs!$B$13,(Inputs!$B$7*Inputs!$B$8+Inputs!$B$9*Inputs!$B$10)/Inputs!$B$12,0) -> 0 | H9: =IF(H$3=Inputs!$B$4+Inputs!$B$13,(Inputs!$B$7*Inputs!$B$8+Inputs!$B$9*Inputs!$B$10)/Inputs!$B$12,0) -> 0 | I9: =IF(I$3=Inputs!$B$4+Inputs!$B$13,(Inputs!$B$7*Inputs!$B$8+Inputs!$B$9*Inputs!$B$10)/Inputs!$B$12,0) -> 0 | ... CB9: =IF(CB$3=Inputs!$B$4+Inputs!$B$13,(Inputs!$B$7*Inputs!$B$8+Inputs!$B$9*Inputs!$B$10)/Inputs!$B$12,0) -> 0
A10: Net cash flow | B10: =SUM(B5:B9) -> -310000000 | C10: =SUM(C5:C9) -> -29333333 | D10: =SUM(D5:D9) -> -29333333 | E10: =SUM(E5:E9) -> -29333333 | F10: =SUM(F5:F9) -> -29333333 | G10: =SUM(G5:G9) -> -29333333 | H10: =SUM(H5:H9) -> -29333333 | I10: =SUM(I5:I9) -> -29333333 | ... CB10: =SUM(CB5:CB9) -> 0

Sheet Summary
A3: Project IRR (XIRR) | B3: =XIRR(Monthly!B10:CB10,Monthly!B4:CB4) -> 0.10810452
A4: NPV (XNPV) | B4: =XNPV(Inputs!B14,Monthly!B10:CB10,Monthly!B4:CB4) -> 28756723
A5: Net profit | B5: =SUM(Monthly!B10:CB10) -> 517468750
A6: Total development cost | B6: =-SUM(Monthly!B5:CB6) -> 1190000000
A7: Profit on cost | B7: =B5/B6 -> 0.43484769
A8: Gross development value | B8: =SUM(Monthly!B9:CB9) -> 1.5566667e+09
A9: Completion date | B9: =EDATE(Inputs!B3,Inputs!B4) -> 47300
