Workbook

Sheet Assumptions
A1: COSTA AZUL RESORT – SEASONAL OPERATING MODEL (EUR)
A3: Keys | B3: 240
A4: F&B revenue (% of rooms) | B4: 0.45
A5: GOP margin | B5: 0.36
A6: FF&E reserve | B6: 0.04
A7: Purchase price | B7: 72000000
A8: Exit cap rate | B8: 0.075
A9: Hold (years) | B9: 5
A10: RevPAR growth | B10: 0.03

Sheet Seasonality
A1: Month | B1: Jan | C1: Feb | D1: Mar | E1: Apr | F1: May | G1: Jun | H1: Jul | I1: Aug | J1: Sep | K1: Oct | L1: Nov | M1: Dec
A2: Days | B2: 31 | C2: 28 | D2: 31 | E2: 30 | F2: 31 | G2: 30 | H2: 31 | I2: 31 | J2: 30 | K2: 31 | L2: 30 | M2: 31
A3: ADR (EUR) | B3: 120 | C3: 125 | D3: 140 | E3: 165 | F3: 190 | G3: 245 | H3: 290 | I3: 300 | J3: 220 | K3: 170 | L3: 130 | M3: 135
A4: Occupancy | B4: 0.42 | C4: 0.48 | D4: 0.58 | E4: 0.68 | F4: 0.76 | G4: 0.88 | H4: 0.94 | I4: 0.95 | J4: 0.84 | K4: 0.7 | L4: 0.5 | M4: 0.47
A5: Rooms revenue | B5: =B3*B4*B2*Assumptions!$B$3 -> 374976 | C5: =C3*C4*C2*Assumptions!$B$3 -> 403200 | D5: =D3*D4*D2*Assumptions!$B$3 -> 604128 | E5: =E3*E4*E2*Assumptions!$B$3 -> 807840 | F5: =F3*F4*F2*Assumptions!$B$3 -> 1074336 | G5: =G3*G4*G2*Assumptions!$B$3 -> 1552320 | H5: =H3*H4*H2*Assumptions!$B$3 -> 2028144 | I5: =I3*I4*I2*Assumptions!$B$3 -> 2120400 | ... M5: =M3*M4*M2*Assumptions!$B$3 -> 472068
A7: Annual rooms revenue | B7: =SUM(B5:M5) -> 12121332
A8: Annual RevPAR | B8: =B7/(Assumptions!$B$3*365) -> 138.37137

Sheet Cash Flow
A3: Year | B3: 0 | C3: 1 | D3: 2 | E3: 3 | F3: 4 | G3: 5 | H3: 6
A4: Total revenue | B4: =(B$3>=1)*(B$3<=Assumptions!$B$9)*Seasonality!$B$7*(1+Assumptions!$B$4)*(1+Assumptions!$B$10)^MAX(0,B$3-1) -> 0 | C4: =(C$3>=1)*(C$3<=Assumptions!$B$9)*Seasonality!$B$7*(1+Assumptions!$B$4)*(1+Assumptions!$B$10)^MAX(0,C$3-1) -> 17575931 | D4: =(D$3>=1)*(D$3<=Assumptions!$B$9)*Seasonality!$B$7*(1+Assumptions!$B$4)*(1+Assumptions!$B$10)^MAX(0,D$3-1) -> 18103209 | E4: =(E$3>=1)*(E$3<=Assumptions!$B$9)*Seasonality!$B$7*(1+Assumptions!$B$4)*(1+Assumptions!$B$10)^MAX(0,E$3-1) -> 18646306 | F4: =(F$3>=1)*(F$3<=Assumptions!$B$9)*Seasonality!$B$7*(1+Assumptions!$B$4)*(1+Assumptions!$B$10)^MAX(0,F$3-1) -> 19205695 | G4: =(G$3>=1)*(G$3<=Assumptions!$B$9)*Seasonality!$B$7*(1+Assumptions!$B$4)*(1+Assumptions!$B$10)^MAX(0,G$3-1) -> 19781866 | H4: =(H$3>=1)*(H$3<=Assumptions!$B$9)*Seasonality!$B$7*(1+Assumptions!$B$4)*(1+Assumptions!$B$10)^MAX(0,H$3-1) -> 0
A5: EBITDA | B5: =B4*(Assumptions!$B$5-Assumptions!$B$6) -> 0 | C5: =C4*(Assumptions!$B$5-Assumptions!$B$6) -> 5624298 | D5: =D4*(Assumptions!$B$5-Assumptions!$B$6) -> 5793027 | E5: =E4*(Assumptions!$B$5-Assumptions!$B$6) -> 5966817.8 | F5: =F4*(Assumptions!$B$5-Assumptions!$B$6) -> 6145822.3 | G5: =G4*(Assumptions!$B$5-Assumptions!$B$6) -> 6330197 | H5: =H4*(Assumptions!$B$5-Assumptions!$B$6) -> 0
A6: Sale | B6: =IF(B$3=Assumptions!$B$9,B5*(1+Assumptions!$B$10)/Assumptions!$B$8,0) -> 0 | C6: =IF(C$3=Assumptions!$B$9,C5*(1+Assumptions!$B$10)/Assumptions!$B$8,0) -> 0 | D6: =IF(D$3=Assumptions!$B$9,D5*(1+Assumptions!$B$10)/Assumptions!$B$8,0) -> 0 | E6: =IF(E$3=Assumptions!$B$9,E5*(1+Assumptions!$B$10)/Assumptions!$B$8,0) -> 0 | F6: =IF(F$3=Assumptions!$B$9,F5*(1+Assumptions!$B$10)/Assumptions!$B$8,0) -> 0 | G6: =IF(G$3=Assumptions!$B$9,G5*(1+Assumptions!$B$10)/Assumptions!$B$8,0) -> 86934706 | H6: =IF(H$3=Assumptions!$B$9,H5*(1+Assumptions!$B$10)/Assumptions!$B$8,0) -> 0
A7: Purchase | B7: =IF(B$3=0,-Assumptions!$B$7,0) -> -72000000 | C7: =IF(C$3=0,-Assumptions!$B$7,0) -> 0 | D7: =IF(D$3=0,-Assumptions!$B$7,0) -> 0 | E7: =IF(E$3=0,-Assumptions!$B$7,0) -> 0 | F7: =IF(F$3=0,-Assumptions!$B$7,0) -> 0 | G7: =IF(G$3=0,-Assumptions!$B$7,0) -> 0 | H7: =IF(H$3=0,-Assumptions!$B$7,0) -> 0
A8: Net cash flow | B8: =SUM(B5:B7) -> -72000000 | C8: =SUM(C5:C7) -> 5624298 | D8: =SUM(D5:D7) -> 5793027 | E8: =SUM(E5:E7) -> 5966817.8 | F8: =SUM(F5:F7) -> 6145822.3 | G8: =SUM(G5:G7) -> 93264903 | H8: =SUM(H5:H7) -> 0

Sheet Returns
A3: Unlevered IRR | B3: =IRR('Cash Flow'!B8:H8) -> 0.1153661
A4: Net profit | B4: =SUM('Cash Flow'!B8:H8) -> 44794868
A5: Year 1 EBITDA | B5: ='Cash Flow'!C5 -> 5624298
A6: Annual RevPAR (EUR) | B6: =Seasonality!B8 -> 138.37137
A7: Price per key | B7: =Assumptions!$B$7/Assumptions!$B$3 -> 300000
A8: Going-in yield | B8: ='Cash Flow'!C5/Assumptions!$B$7 -> 0.078115251
