Workbook

Sheet Inputs
A1: SARJAPUR GREENS – PLOTTED DEVELOPMENT (₹ crore)
A3: Land cost (₹ crore) | B3: 190
A4: Site (acres) | B4: 32
A5: Saleable plot area (%) | B5: 0.55
A6: Plot rate (₹ per sq ft) | B6: 4300
A7: Infrastructure cost (₹ per sq ft of plots) | B7: 650
A8: Approvals & fees (₹ crore) | B8: 6.5
A9: Marketing (% of sales) | B9: 0.03
A10: Tranche 1 sold (%) | B10: 0.4
A11: Tranche 2 sold (%) | B11: 0.35
A12: Rate escalation per tranche | B12: 0.06

Sheet Appraisal
A3: Saleable area (sq ft) | B3: =Inputs!$B$4*43560*Inputs!$B$5 -> 766656
A4: Tranche 3 sold (%) | B4: =1-Inputs!$B$10-Inputs!$B$11 -> 0.25
A5: Sales tranche 1 (₹ crore) | B5: =B3*Inputs!$B$10*Inputs!$B$6/10000000 -> 131.86483
A6: Sales tranche 2 (₹ crore) | B6: =B3*Inputs!$B$11*Inputs!$B$6*(1+Inputs!$B$12)/10000000 -> 122.30463
A7: Sales tranche 3 (₹ crore) | B7: =B3*B4*Inputs!$B$6*(1+Inputs!$B$12)^2/10000000 -> 92.602078
A8: Gross sales (₹ crore) | B8: =SUM(B5:B7) -> 346.77154
A9: Infrastructure (₹ crore) | B9: =B3*Inputs!$B$7/10000000 -> 49.83264
A10: Marketing (₹ crore) | B10: =B8*Inputs!$B$9 -> 10.403146
A11: Total cost (₹ crore) | B11: =Inputs!$B$3+Inputs!$B$8+B9+B10 -> 256.73579
A12: Net profit (₹ crore) | B12: =B8-B11 -> 90.035756
A13: Profit on cost | B13: =B12/B11 -> 0.35069422
A14: Project IRR (3-year) | B14: =IRR(Timeline!B6:E6) -> 0.21870798

Sheet Timeline
A3: Year | B3: 0 | C3: 1 | D3: 2 | E3: 3
A4: Inflows | B4: =0 -> 0 | C4: =Appraisal!B5 -> 131.86483 | D4: =Appraisal!B6 -> 122.30463 | E4: =Appraisal!B7 -> 92.602078
A5: Outflows | B5: =-Inputs!$B$3-Inputs!$B$8 -> -196.5 | C5: =-Appraisal!B9*0.6-Appraisal!B5*Inputs!$B$9 -> -33.855529 | D5: =-Appraisal!B9*0.4-Appraisal!B6*Inputs!$B$9 -> -23.602195 | E5: =-Appraisal!B7*Inputs!$B$9 -> -2.7780623
A6: Net | B6: =B4+B5 -> -196.5 | C6: =C4+C5 -> 98.009303 | D6: =D4+D5 -> 98.702437 | E6: =E4+E5 -> 89.824016
