Workbook

Sheet Inputs
A1: ASHBURN HALL 3 – DATA HALL LEASE-UP (USD)
A3: First month | B3: 46418
A4: IT capacity (MW) | B4: 24
A5: Rate ($/kW/month) | B5: 165
A6: MW leased per month | B6: 1.5
A7: Capex ($m/MW) | B7: 11.5
A8: Opex ($/kW/month) | B8: 22
A9: Exit multiple of annual EBITDA | B9: 18
A10: Exit after (months) | B10: 60

Sheet Monthly
A3: Month | B3: 0 | C3: 1 | D3: 2 | E3: 3 | F3: 4 | G3: 5 | H3: 6 | I3: 7 | J3: 8 | K3: 9 | L3: 10 | M3: 11 | N3: 12 | O3: 13 | P3: 14 | Q3: 15 | R3: 16 | S3: 17 | T3: 18 | U3: 19 | V3: 20 | W3: 21 | X3: 22 | Y3: 23 | Z3: 24 | AA3: 25 | AB3: 26 | AC3: 27 | AD3: 28 | AE3: 29 | AF3: 30 | AG3: 31 | AH3: 32 | AI3: 33 | AJ3: 34 | AK3: 35 | AL3: 36 | AM3: 37 | AN3: 38 | AO3: 39 | AP3: 40 | AQ3: 41 | AR3: 42 | AS3: 43 | AT3: 44 | AU3: 45 | AV3: 46 | AW3: 47 | AX3: 48 | AY3: 49 | AZ3: 50 | BA3: 51 | BB3: 52 | BC3: 53 | BD3: 54 | BE3: 55 | BF3: 56 | BG3: 57 | BH3: 58 | BI3: 59 | BJ3: 60
A4: Date | B4: =EOMONTH(Inputs!$B$3,B$3) -> 46418 | C4: =EOMONTH(Inputs!$B$3,C$3) -> 46446 | D4: =EOMONTH(Inputs!$B$3,D$3) -> 46477 | E4: =EOMONTH(Inputs!$B$3,E$3) -> 46507 | F4: =EOMONTH(Inputs!$B$3,F$3) -> 46538 | G4: =EOMONTH(Inputs!$B$3,G$3) -> 46568 | H4: =EOMONTH(Inputs!$B$3,H$3) -> 46599 | I4: =EOMONTH(Inputs!$B$3,I$3) -> 46630 | ... BJ4: =EOMONTH(Inputs!$B$3,BJ$3) -> 48244
A5: Year | B5: =YEAR(B4) -> 2027 | C5: =YEAR(C4) -> 2027 | D5: =YEAR(D4) -> 2027 | E5: =YEAR(E4) -> 2027 | F5: =YEAR(F4) -> 2027 | G5: =YEAR(G4) -> 2027 | H5: =YEAR(H4) -> 2027 | I5: =YEAR(I4) -> 2027 | ... BJ5: =YEAR(BJ4) -> 2032
A6: MW leased | B6: =MIN(Inputs!$B$4,Inputs!$B$6*B$3) -> 0 | C6: =MIN(Inputs!$B$4,Inputs!$B$6*C$3) -> 1.5 | D6: =MIN(Inputs!$B$4,Inputs!$B$6*D$3) -> 3 | E6: =MIN(Inputs!$B$4,Inputs!$B$6*E$3) -> 4.5 | F6: =MIN(Inputs!$B$4,Inputs!$B$6*F$3) -> 6 | G6: =MIN(Inputs!$B$4,Inputs!$B$6*G$3) -> 7.5 | H6: =MIN(Inputs!$B$4,Inputs!$B$6*H$3) -> 9 | I6: =MIN(Inputs!$B$4,Inputs!$B$6*I$3) -> 10.5 | ... BJ6: =MIN(Inputs!$B$4,Inputs!$B$6*BJ$3) -> 24
A7: Revenue | B7: =B6*1000*Inputs!$B$5 -> 0 | C7: =C6*1000*Inputs!$B$5 -> 247500 | D7: =D6*1000*Inputs!$B$5 -> 495000 | E7: =E6*1000*Inputs!$B$5 -> 742500 | F7: =F6*1000*Inputs!$B$5 -> 990000 | G7: =G6*1000*Inputs!$B$5 -> 1237500 | H7: =H6*1000*Inputs!$B$5 -> 1485000 | I7: =I6*1000*Inputs!$B$5 -> 1732500 | ... BJ7: =BJ6*1000*Inputs!$B$5 -> 3960000
A8: Opex | B8: =-B6*1000*Inputs!$B$8 -> 0 | C8: =-C6*1000*Inputs!$B$8 -> -33000 | D8: =-D6*1000*Inputs!$B$8 -> -66000 | E8: =-E6*1000*Inputs!$B$8 -> -99000 | F8: =-F6*1000*Inputs!$B$8 -> -132000 | G8: =-G6*1000*Inputs!$B$8 -> -165000 | H8: =-H6*1000*Inputs!$B$8 -> -198000 | I8: =-I6*1000*Inputs!$B$8 -> -231000 | ... BJ8: =-BJ6*1000*Inputs!$B$8 -> -528000
A9: Capex | B9: =IF(B$3=0,-Inputs!$B$4*Inputs!$B$7*1000000,0) -> -276000000 | C9: =IF(C$3=0,-Inputs!$B$4*Inputs!$B$7*1000000,0) -> 0 | D9: =IF(D$3=0,-Inputs!$B$4*Inputs!$B$7*1000000,0) -> 0 | E9: =IF(E$3=0,-Inputs!$B$4*Inputs!$B$7*1000000,0) -> 0 | F9: =IF(F$3=0,-Inputs!$B$4*Inputs!$B$7*1000000,0) -> 0 | G9: =IF(G$3=0,-Inputs!$B$4*Inputs!$B$7*1000000,0) -> 0 | H9: =IF(H$3=0,-Inputs!$B$4*Inputs!$B$7*1000000,0) -> 0 | I9: =IF(I$3=0,-Inputs!$B$4*Inputs!$B$7*1000000,0) -> 0 | ... BJ9: =IF(BJ$3=0,-Inputs!$B$4*Inputs!$B$7*1000000,0) -> 0
A10: Sale | B10: =IF(B$3=Inputs!$B$10,(B7+B8)*12*Inputs!$B$9,0) -> 0 | C10: =IF(C$3=Inputs!$B$10,(C7+C8)*12*Inputs!$B$9,0) -> 0 | D10: =IF(D$3=Inputs!$B$10,(D7+D8)*12*Inputs!$B$9,0) -> 0 | E10: =IF(E$3=Inputs!$B$10,(E7+E8)*12*Inputs!$B$9,0) -> 0 | F10: =IF(F$3=Inputs!$B$10,(F7+F8)*12*Inputs!$B$9,0) -> 0 | G10: =IF(G$3=Inputs!$B$10,(G7+G8)*12*Inputs!$B$9,0) -> 0 | H10: =IF(H$3=Inputs!$B$10,(H7+H8)*12*Inputs!$B$9,0) -> 0 | I10: =IF(I$3=Inputs!$B$10,(I7+I8)*12*Inputs!$B$9,0) -> 0 | ... BJ10: =IF(BJ$3=Inputs!$B$10,(BJ7+BJ8)*12*Inputs!$B$9,0) -> 741312000
A11: Net cash flow | B11: =SUM(B7:B10) -> -276000000 | C11: =SUM(C7:C10) -> 214500 | D11: =SUM(D7:D10) -> 429000 | E11: =SUM(E7:E10) -> 643500 | F11: =SUM(F7:F10) -> 858000 | G11: =SUM(G7:G10) -> 1072500 | H11: =SUM(H7:H10) -> 1287000 | I11: =SUM(I7:I10) -> 1501500 | ... BJ11: =SUM(BJ7:BJ10) -> 744744000

Sheet Annual
A1: Year | B1: Revenue | C1: EBITDA
A2: 2027 | B2: =SUMIFS(Monthly!$B$7:$BJ$7,Monthly!$B$5:$BJ$5,A2) -> 16335000 | C2: =SUMIFS(Monthly!$B$7:$BJ$7,Monthly!$B$5:$BJ$5,A2)+SUMIFS(Monthly!$B$8:$BJ$8,Monthly!$B$5:$BJ$5,A2) -> 14157000
A3: 2028 | B3: =SUMIFS(Monthly!$B$7:$BJ$7,Monthly!$B$5:$BJ$5,A3) -> 45045000 | C3: =SUMIFS(Monthly!$B$7:$BJ$7,Monthly!$B$5:$BJ$5,A3)+SUMIFS(Monthly!$B$8:$BJ$8,Monthly!$B$5:$BJ$5,A3) -> 39039000
A4: 2029 | B4: =SUMIFS(Monthly!$B$7:$BJ$7,Monthly!$B$5:$BJ$5,A4) -> 47520000 | C4: =SUMIFS(Monthly!$B$7:$BJ$7,Monthly!$B$5:$BJ$5,A4)+SUMIFS(Monthly!$B$8:$BJ$8,Monthly!$B$5:$BJ$5,A4) -> 41184000
A5: 2030 | B5: =SUMIFS(Monthly!$B$7:$BJ$7,Monthly!$B$5:$BJ$5,A5) -> 47520000 | C5: =SUMIFS(Monthly!$B$7:$BJ$7,Monthly!$B$5:$BJ$5,A5)+SUMIFS(Monthly!$B$8:$BJ$8,Monthly!$B$5:$BJ$5,A5) -> 41184000
A6: 2031 | B6: =SUMIFS(Monthly!$B$7:$BJ$7,Monthly!$B$5:$BJ$5,A6) -> 47520000 | C6: =SUMIFS(Monthly!$B$7:$BJ$7,Monthly!$B$5:$BJ$5,A6)+SUMIFS(Monthly!$B$8:$BJ$8,Monthly!$B$5:$BJ$5,A6) -> 41184000

Sheet Returns
A3: Unlevered IRR (annualised) | B3: =(1+IRR(Monthly!B11:BJ11,0.01))^12-1 -> 0.31580606
A4: Net profit | B4: =SUM(Monthly!B11:BJ11) -> 645492000
A5: Total capex | B5: =-Monthly!B9 -> 276000000
A6: Stabilised EBITDA (2031) | B6: =Annual!C6 -> 41184000
A7: Yield on cost (stabilised) | B7: =Annual!C6/B5 -> 0.14921739
