Workbook

Sheet Inputs
A1: AL YASMIN HEIGHTS – OFF-PLAN (WAFI) – SAR
A3: Apartments | B3: 220
A4: Average price (SAR) | B4: 1150000
A5: Sold off-plan | B5: 0.7
A6: Construction cost (SAR) | B6: 148000000
A7: Land (SAR) | B7: 62000000
A8: Construction (quarters) | B8: 10
A9: Bank finance rate | B9: 0.07

Sheet Milestones
A1: Construction complete | B1: Cumulative release from escrow
A2: 0 | B2: 0.1
A3: 0.2 | B3: 0.2
A4: 0.4 | B4: 0.4
A5: 0.6 | B5: 0.6
A6: 0.8 | B6: 0.8
A7: 1 | B7: 0.95

Sheet Quarterly
A3: Quarter | B3: 0 | C3: 1 | D3: 2 | E3: 3 | F3: 4 | G3: 5 | H3: 6 | I3: 7 | J3: 8 | K3: 9 | L3: 10 | M3: 11
A4: Completion | B4: =MIN(1,B$3/Inputs!$B$8) -> 0 | C4: =MIN(1,C$3/Inputs!$B$8) -> 0.1 | D4: =MIN(1,D$3/Inputs!$B$8) -> 0.2 | E4: =MIN(1,E$3/Inputs!$B$8) -> 0.3 | F4: =MIN(1,F$3/Inputs!$B$8) -> 0.4 | G4: =MIN(1,G$3/Inputs!$B$8) -> 0.5 | H4: =MIN(1,H$3/Inputs!$B$8) -> 0.6 | I4: =MIN(1,I$3/Inputs!$B$8) -> 0.7 | ... M4: =MIN(1,M$3/Inputs!$B$8) -> 1
A5: Escrow released (cumulative %) | B5: =INDEX(Milestones!$B$2:$B$7,MATCH(B4,Milestones!$A$2:$A$7,1))+IF(B$3>Inputs!$B$8,0.05,0) -> 0.1 | C5: =INDEX(Milestones!$B$2:$B$7,MATCH(C4,Milestones!$A$2:$A$7,1))+IF(C$3>Inputs!$B$8,0.05,0) -> 0.1 | D5: =INDEX(Milestones!$B$2:$B$7,MATCH(D4,Milestones!$A$2:$A$7,1))+IF(D$3>Inputs!$B$8,0.05,0) -> 0.2 | E5: =INDEX(Milestones!$B$2:$B$7,MATCH(E4,Milestones!$A$2:$A$7,1))+IF(E$3>Inputs!$B$8,0.05,0) -> 0.2 | F5: =INDEX(Milestones!$B$2:$B$7,MATCH(F4,Milestones!$A$2:$A$7,1))+IF(F$3>Inputs!$B$8,0.05,0) -> 0.4 | G5: =INDEX(Milestones!$B$2:$B$7,MATCH(G4,Milestones!$A$2:$A$7,1))+IF(G$3>Inputs!$B$8,0.05,0) -> 0.4 | H5: =INDEX(Milestones!$B$2:$B$7,MATCH(H4,Milestones!$A$2:$A$7,1))+IF(H$3>Inputs!$B$8,0.05,0) -> 0.6 | I5: =INDEX(Milestones!$B$2:$B$7,MATCH(I4,Milestones!$A$2:$A$7,1))+IF(I$3>Inputs!$B$8,0.05,0) -> 0.6 | ... M5: =INDEX(Milestones!$B$2:$B$7,MATCH(M4,Milestones!$A$2:$A$7,1))+IF(M$3>Inputs!$B$8,0.05,0) -> 1
A6: Escrow release | B6: =B5*Inputs!$B$3*Inputs!$B$5*Inputs!$B$4 -> 17710000 | C6: =(C5-B5)*Inputs!$B$3*Inputs!$B$5*Inputs!$B$4 -> 0 | D6: =(D5-C5)*Inputs!$B$3*Inputs!$B$5*Inputs!$B$4 -> 17710000 | E6: =(E5-D5)*Inputs!$B$3*Inputs!$B$5*Inputs!$B$4 -> 0 | F6: =(F5-E5)*Inputs!$B$3*Inputs!$B$5*Inputs!$B$4 -> 35420000 | G6: =(G5-F5)*Inputs!$B$3*Inputs!$B$5*Inputs!$B$4 -> 0 | H6: =(H5-G5)*Inputs!$B$3*Inputs!$B$5*Inputs!$B$4 -> 35420000 | I6: =(I5-H5)*Inputs!$B$3*Inputs!$B$5*Inputs!$B$4 -> 0 | J6: =(J5-I5)*Inputs!$B$3*Inputs!$B$5*Inputs!$B$4 -> 35420000 | ... M6: =(M5-L5)*Inputs!$B$3*Inputs!$B$5*Inputs!$B$4 -> 8855000
A7: Unsold sales at handover | B7: =IF(B$3=Inputs!$B$8+1,Inputs!$B$3*(1-Inputs!$B$5)*Inputs!$B$4,0) -> 0 | C7: =IF(C$3=Inputs!$B$8+1,Inputs!$B$3*(1-Inputs!$B$5)*Inputs!$B$4,0) -> 0 | D7: =IF(D$3=Inputs!$B$8+1,Inputs!$B$3*(1-Inputs!$B$5)*Inputs!$B$4,0) -> 0 | E7: =IF(E$3=Inputs!$B$8+1,Inputs!$B$3*(1-Inputs!$B$5)*Inputs!$B$4,0) -> 0 | F7: =IF(F$3=Inputs!$B$8+1,Inputs!$B$3*(1-Inputs!$B$5)*Inputs!$B$4,0) -> 0 | G7: =IF(G$3=Inputs!$B$8+1,Inputs!$B$3*(1-Inputs!$B$5)*Inputs!$B$4,0) -> 0 | H7: =IF(H$3=Inputs!$B$8+1,Inputs!$B$3*(1-Inputs!$B$5)*Inputs!$B$4,0) -> 0 | I7: =IF(I$3=Inputs!$B$8+1,Inputs!$B$3*(1-Inputs!$B$5)*Inputs!$B$4,0) -> 0 | ... M7: =IF(M$3=Inputs!$B$8+1,Inputs!$B$3*(1-Inputs!$B$5)*Inputs!$B$4,0) -> 75900000
A8: Construction | B8: =-IF(AND(B$3>=1,B$3<=Inputs!$B$8),Inputs!$B$6/Inputs!$B$8,0) -> 0 | C8: =-IF(AND(C$3>=1,C$3<=Inputs!$B$8),Inputs!$B$6/Inputs!$B$8,0) -> -14800000 | D8: =-IF(AND(D$3>=1,D$3<=Inputs!$B$8),Inputs!$B$6/Inputs!$B$8,0) -> -14800000 | E8: =-IF(AND(E$3>=1,E$3<=Inputs!$B$8),Inputs!$B$6/Inputs!$B$8,0) -> -14800000 | F8: =-IF(AND(F$3>=1,F$3<=Inputs!$B$8),Inputs!$B$6/Inputs!$B$8,0) -> -14800000 | G8: =-IF(AND(G$3>=1,G$3<=Inputs!$B$8),Inputs!$B$6/Inputs!$B$8,0) -> -14800000 | H8: =-IF(AND(H$3>=1,H$3<=Inputs!$B$8),Inputs!$B$6/Inputs!$B$8,0) -> -14800000 | I8: =-IF(AND(I$3>=1,I$3<=Inputs!$B$8),Inputs!$B$6/Inputs!$B$8,0) -> -14800000 | ... M8: =-IF(AND(M$3>=1,M$3<=Inputs!$B$8),Inputs!$B$6/Inputs!$B$8,0) -> 0
A9: Land | B9: =IF(B$3=0,-Inputs!$B$7,0) -> -62000000 | C9: =IF(C$3=0,-Inputs!$B$7,0) -> 0 | D9: =IF(D$3=0,-Inputs!$B$7,0) -> 0 | E9: =IF(E$3=0,-Inputs!$B$7,0) -> 0 | F9: =IF(F$3=0,-Inputs!$B$7,0) -> 0 | G9: =IF(G$3=0,-Inputs!$B$7,0) -> 0 | H9: =IF(H$3=0,-Inputs!$B$7,0) -> 0 | I9: =IF(I$3=0,-Inputs!$B$7,0) -> 0 | ... M9: =IF(M$3=0,-Inputs!$B$7,0) -> 0
A10: Net cash flow | B10: =SUM(B6:B9) -> -44290000 | C10: =SUM(C6:C9) -> -14800000 | D10: =SUM(D6:D9) -> 2910000 | E10: =SUM(E6:E9) -> -14800000 | F10: =SUM(F6:F9) -> 20620000 | G10: =SUM(G6:G9) -> -14800000 | H10: =SUM(H6:H9) -> 20620000 | I10: =SUM(I6:I9) -> -14800000 | ... M10: =SUM(M6:M9) -> 84755000

Sheet Summary
A3: Project IRR (annual) | B3: =(1+IRR(Quarterly!B10:M10))^4-1 -> 0.23888804
A4: Net profit | B4: =SUM(Quarterly!B10:M10) -> 43000000
A5: Gross revenue | B5: =SUM(Quarterly!B6:M7) -> 253000000
A6: Total development cost | B6: =-SUM(Quarterly!B8:M9) -> 210000000
A7: Profit on cost | B7: =B4/B6 -> 0.2047619
A8: Peak funding need | B8: =-MIN(Quarterly!B10:M10) -> 44290000
