Workbook

Sheet Premissas
A1: SHOPPING VILA NOVA – ACQUISITION (BRL)
A3: Purchase price (R$) | B3: 620000000
A4: NOI year 1 (R$) | B4: 61000000
A5: IPCA | B5: 0.045
A6: Real rent growth | B6: 0.01
A7: SELIC | B7: 0.1125
A8: Debt spread over SELIC | B8: 0.018
A9: LTV | B9: 0.45
A10: Exit cap rate | B10: 0.095
A11: Hold (years) | B11: 7
A12: Occupancy | B12: 0.94

Sheet Fluxo
A3: Year | B3: 0 | C3: 1 | D3: 2 | E3: 3 | F3: 4 | G3: 5 | H3: 6 | I3: 7 | J3: 8
A4: NOI | B4: =(B$3>=1)*(B$3<=Premissas!$B$11)*Premissas!$B$4*Premissas!$B$12/0.94*((1+Premissas!$B$5)*(1+Premissas!$B$6))^MAX(0,B$3-1) -> 0 | C4: =(C$3>=1)*(C$3<=Premissas!$B$11)*Premissas!$B$4*Premissas!$B$12/0.94*((1+Premissas!$B$5)*(1+Premissas!$B$6))^MAX(0,C$3-1) -> 61000000 | D4: =(D$3>=1)*(D$3<=Premissas!$B$11)*Premissas!$B$4*Premissas!$B$12/0.94*((1+Premissas!$B$5)*(1+Premissas!$B$6))^MAX(0,D$3-1) -> 64382450 | E4: =(E$3>=1)*(E$3<=Premissas!$B$11)*Premissas!$B$4*Premissas!$B$12/0.94*((1+Premissas!$B$5)*(1+Premissas!$B$6))^MAX(0,E$3-1) -> 67952457 | F4: =(F$3>=1)*(F$3<=Premissas!$B$11)*Premissas!$B$4*Premissas!$B$12/0.94*((1+Premissas!$B$5)*(1+Premissas!$B$6))^MAX(0,F$3-1) -> 71720421 | G4: =(G$3>=1)*(G$3<=Premissas!$B$11)*Premissas!$B$4*Premissas!$B$12/0.94*((1+Premissas!$B$5)*(1+Premissas!$B$6))^MAX(0,G$3-1) -> 75697318 | H4: =(H$3>=1)*(H$3<=Premissas!$B$11)*Premissas!$B$4*Premissas!$B$12/0.94*((1+Premissas!$B$5)*(1+Premissas!$B$6))^MAX(0,H$3-1) -> 79894734 | I4: =(I$3>=1)*(I$3<=Premissas!$B$11)*Premissas!$B$4*Premissas!$B$12/0.94*((1+Premissas!$B$5)*(1+Premissas!$B$6))^MAX(0,I$3-1) -> 84324897 | J4: =(J$3>=1)*(J$3<=Premissas!$B$11)*Premissas!$B$4*Premissas!$B$12/0.94*((1+Premissas!$B$5)*(1+Premissas!$B$6))^MAX(0,J$3-1) -> 0
A5: Sale | B5: =IF(B$3=Premissas!$B$11,B4*(1+Premissas!$B$5)/Premissas!$B$10,0) -> 0 | C5: =IF(C$3=Premissas!$B$11,C4*(1+Premissas!$B$5)/Premissas!$B$10,0) -> 0 | D5: =IF(D$3=Premissas!$B$11,D4*(1+Premissas!$B$5)/Premissas!$B$10,0) -> 0 | E5: =IF(E$3=Premissas!$B$11,E4*(1+Premissas!$B$5)/Premissas!$B$10,0) -> 0 | F5: =IF(F$3=Premissas!$B$11,F4*(1+Premissas!$B$5)/Premissas!$B$10,0) -> 0 | G5: =IF(G$3=Premissas!$B$11,G4*(1+Premissas!$B$5)/Premissas!$B$10,0) -> 0 | H5: =IF(H$3=Premissas!$B$11,H4*(1+Premissas!$B$5)/Premissas!$B$10,0) -> 0 | I5: =IF(I$3=Premissas!$B$11,I4*(1+Premissas!$B$5)/Premissas!$B$10,0) -> 9.2757387e+08 | J5: =IF(J$3=Premissas!$B$11,J4*(1+Premissas!$B$5)/Premissas!$B$10,0) -> 0
A6: Purchase | B6: =IF(B$3=0,-Premissas!$B$3,0) -> -620000000 | C6: =IF(C$3=0,-Premissas!$B$3,0) -> 0 | D6: =IF(D$3=0,-Premissas!$B$3,0) -> 0 | E6: =IF(E$3=0,-Premissas!$B$3,0) -> 0 | F6: =IF(F$3=0,-Premissas!$B$3,0) -> 0 | G6: =IF(G$3=0,-Premissas!$B$3,0) -> 0 | H6: =IF(H$3=0,-Premissas!$B$3,0) -> 0 | I6: =IF(I$3=0,-Premissas!$B$3,0) -> 0 | J6: =IF(J$3=0,-Premissas!$B$3,0) -> 0
A7: Unlevered | B7: =SUM(B4:B6) -> -620000000 | C7: =SUM(C4:C6) -> 61000000 | D7: =SUM(D4:D6) -> 64382450 | E7: =SUM(E4:E6) -> 67952457 | F7: =SUM(F4:F6) -> 71720421 | G7: =SUM(G4:G6) -> 75697318 | H7: =SUM(H4:H6) -> 79894734 | I7: =SUM(I4:I6) -> 1.0118988e+09 | J7: =SUM(J4:J6) -> 0
A8: Debt | B8: =IF(B$3=0,Premissas!$B$3*Premissas!$B$9,0)-(B$3>=1)*(B$3<=Premissas!$B$11)*Premissas!$B$3*Premissas!$B$9*(Premissas!$B$7+Premissas!$B$8)-IF(B$3=Premissas!$B$11,Premissas!$B$3*Premissas!$B$9,0) -> 279000000 | C8: =IF(C$3=0,Premissas!$B$3*Premissas!$B$9,0)-(C$3>=1)*(C$3<=Premissas!$B$11)*Premissas!$B$3*Premissas!$B$9*(Premissas!$B$7+Premissas!$B$8)-IF(C$3=Premissas!$B$11,Premissas!$B$3*Premissas!$B$9,0) -> -36409500 | D8: =IF(D$3=0,Premissas!$B$3*Premissas!$B$9,0)-(D$3>=1)*(D$3<=Premissas!$B$11)*Premissas!$B$3*Premissas!$B$9*(Premissas!$B$7+Premissas!$B$8)-IF(D$3=Premissas!$B$11,Premissas!$B$3*Premissas!$B$9,0) -> -36409500 | E8: =IF(E$3=0,Premissas!$B$3*Premissas!$B$9,0)-(E$3>=1)*(E$3<=Premissas!$B$11)*Premissas!$B$3*Premissas!$B$9*(Premissas!$B$7+Premissas!$B$8)-IF(E$3=Premissas!$B$11,Premissas!$B$3*Premissas!$B$9,0) -> -36409500 | F8: =IF(F$3=0,Premissas!$B$3*Premissas!$B$9,0)-(F$3>=1)*(F$3<=Premissas!$B$11)*Premissas!$B$3*Premissas!$B$9*(Premissas!$B$7+Premissas!$B$8)-IF(F$3=Premissas!$B$11,Premissas!$B$3*Premissas!$B$9,0) -> -36409500 | G8: =IF(G$3=0,Premissas!$B$3*Premissas!$B$9,0)-(G$3>=1)*(G$3<=Premissas!$B$11)*Premissas!$B$3*Premissas!$B$9*(Premissas!$B$7+Premissas!$B$8)-IF(G$3=Premissas!$B$11,Premissas!$B$3*Premissas!$B$9,0) -> -36409500 | H8: =IF(H$3=0,Premissas!$B$3*Premissas!$B$9,0)-(H$3>=1)*(H$3<=Premissas!$B$11)*Premissas!$B$3*Premissas!$B$9*(Premissas!$B$7+Premissas!$B$8)-IF(H$3=Premissas!$B$11,Premissas!$B$3*Premissas!$B$9,0) -> -36409500 | I8: =IF(I$3=0,Premissas!$B$3*Premissas!$B$9,0)-(I$3>=1)*(I$3<=Premissas!$B$11)*Premissas!$B$3*Premissas!$B$9*(Premissas!$B$7+Premissas!$B$8)-IF(I$3=Premissas!$B$11,Premissas!$B$3*Premissas!$B$9,0) -> -315409500 | J8: =IF(J$3=0,Premissas!$B$3*Premissas!$B$9,0)-(J$3>=1)*(J$3<=Premissas!$B$11)*Premissas!$B$3*Premissas!$B$9*(Premissas!$B$7+Premissas!$B$8)-IF(J$3=Premissas!$B$11,Premissas!$B$3*Premissas!$B$9,0) -> 0
A9: Levered | B9: =B7+B8 -> -341000000 | C9: =C7+C8 -> 24590500 | D9: =D7+D8 -> 27972950 | E9: =E7+E8 -> 31542957 | F9: =F7+F8 -> 35310921 | G9: =G7+G8 -> 39287818 | H9: =H7+H8 -> 43485234 | I9: =I7+I8 -> 6.9648927e+08 | J9: =J7+J8 -> 0

Sheet Resultados
A3: Unlevered IRR | B3: =IRR(Fluxo!B7:J7) -> 0.15669835
A4: Levered IRR | B4: =IRR(Fluxo!B9:J9) -> 0.17348609
A5: Net profit | B5: =SUM(Fluxo!B7:J7) -> 8.1254615e+08
A6: Real unlevered IRR (over IPCA) | B6: =(1+B3)/(1+Premissas!$B$5)-1 -> 0.10688838
A7: Going-in cap rate | B7: =Premissas!$B$4/Premissas!$B$3 -> 0.098387097
A8: Equity multiple | B8: =SUMIF(Fluxo!B9:J9,">0")/-SUMIF(Fluxo!B9:J9,"<0") -> 2.6354242
