Workbook

Sheet Inputs
A1: KOWLOON TONG STUDENT RESIDENCE (HKD)
A3: Beds | B3: 820
A4: Purchase price (HK$) | B4: 1450000000
A5: Nomination agreement share | B5: 0.6
A6: Nomination rate (HK$/bed/month) | B6: 7800
A7: Direct-let rate (HK$/bed/month) | B7: 9200
A8: Direct-let occupancy | B8: 0.88
A9: Academic months let | B9: 10
A10: Summer income (HK$) | B10: 9000000
A11: Opex ratio | B11: 0.3
A12: Exit yield | B12: 0.04
A13: Hold (years) | B13: 7

Sheet Cash Flow
A3: Year | B3: 0 | C3: 1 | D3: 2 | E3: 3 | F3: 4 | G3: 5 | H3: 6 | I3: 7 | J3: 8 | K3: 9
A4: NOI | B4: =(B$3>=1)*(B$3<=Inputs!$B$13)*((Inputs!$B$3*(Inputs!$B$5*Inputs!$B$6+(1-Inputs!$B$5)*Inputs!$B$7*Inputs!$B$8)*Inputs!$B$9+Inputs!$B$10)*(1-Inputs!$B$11))*1.025^MAX(0,B$3-1) -> 0 | C4: =(C$3>=1)*(C$3<=Inputs!$B$13)*((Inputs!$B$3*(Inputs!$B$5*Inputs!$B$6+(1-Inputs!$B$5)*Inputs!$B$7*Inputs!$B$8)*Inputs!$B$9+Inputs!$B$10)*(1-Inputs!$B$11))*1.025^MAX(0,C$3-1) -> 51751616 | D4: =(D$3>=1)*(D$3<=Inputs!$B$13)*((Inputs!$B$3*(Inputs!$B$5*Inputs!$B$6+(1-Inputs!$B$5)*Inputs!$B$7*Inputs!$B$8)*Inputs!$B$9+Inputs!$B$10)*(1-Inputs!$B$11))*1.025^MAX(0,D$3-1) -> 53045406 | E4: =(E$3>=1)*(E$3<=Inputs!$B$13)*((Inputs!$B$3*(Inputs!$B$5*Inputs!$B$6+(1-Inputs!$B$5)*Inputs!$B$7*Inputs!$B$8)*Inputs!$B$9+Inputs!$B$10)*(1-Inputs!$B$11))*1.025^MAX(0,E$3-1) -> 54371542 | F4: =(F$3>=1)*(F$3<=Inputs!$B$13)*((Inputs!$B$3*(Inputs!$B$5*Inputs!$B$6+(1-Inputs!$B$5)*Inputs!$B$7*Inputs!$B$8)*Inputs!$B$9+Inputs!$B$10)*(1-Inputs!$B$11))*1.025^MAX(0,F$3-1) -> 55730830 | G4: =(G$3>=1)*(G$3<=Inputs!$B$13)*((Inputs!$B$3*(Inputs!$B$5*Inputs!$B$6+(1-Inputs!$B$5)*Inputs!$B$7*Inputs!$B$8)*Inputs!$B$9+Inputs!$B$10)*(1-Inputs!$B$11))*1.025^MAX(0,G$3-1) -> 57124101 | H4: =(H$3>=1)*(H$3<=Inputs!$B$13)*((Inputs!$B$3*(Inputs!$B$5*Inputs!$B$6+(1-Inputs!$B$5)*Inputs!$B$7*Inputs!$B$8)*Inputs!$B$9+Inputs!$B$10)*(1-Inputs!$B$11))*1.025^MAX(0,H$3-1) -> 58552203 | I4: =(I$3>=1)*(I$3<=Inputs!$B$13)*((Inputs!$B$3*(Inputs!$B$5*Inputs!$B$6+(1-Inputs!$B$5)*Inputs!$B$7*Inputs!$B$8)*Inputs!$B$9+Inputs!$B$10)*(1-Inputs!$B$11))*1.025^MAX(0,I$3-1) -> 60016008 | ... K4: =(K$3>=1)*(K$3<=Inputs!$B$13)*((Inputs!$B$3*(Inputs!$B$5*Inputs!$B$6+(1-Inputs!$B$5)*Inputs!$B$7*Inputs!$B$8)*Inputs!$B$9+Inputs!$B$10)*(1-Inputs!$B$11))*1.025^MAX(0,K$3-1) -> 0
A5: Sale | B5: =IF(B$3=Inputs!$B$13,B4*1.025/Inputs!$B$12,0) -> 0 | C5: =IF(C$3=Inputs!$B$13,C4*1.025/Inputs!$B$12,0) -> 0 | D5: =IF(D$3=Inputs!$B$13,D4*1.025/Inputs!$B$12,0) -> 0 | E5: =IF(E$3=Inputs!$B$13,E4*1.025/Inputs!$B$12,0) -> 0 | F5: =IF(F$3=Inputs!$B$13,F4*1.025/Inputs!$B$12,0) -> 0 | G5: =IF(G$3=Inputs!$B$13,G4*1.025/Inputs!$B$12,0) -> 0 | H5: =IF(H$3=Inputs!$B$13,H4*1.025/Inputs!$B$12,0) -> 0 | I5: =IF(I$3=Inputs!$B$13,I4*1.025/Inputs!$B$12,0) -> 1.5379102e+09 | ... K5: =IF(K$3=Inputs!$B$13,K4*1.025/Inputs!$B$12,0) -> 0
A6: Purchase | B6: =IF(B$3=0,-Inputs!$B$4,0) -> -1450000000 | C6: =IF(C$3=0,-Inputs!$B$4,0) -> 0 | D6: =IF(D$3=0,-Inputs!$B$4,0) -> 0 | E6: =IF(E$3=0,-Inputs!$B$4,0) -> 0 | F6: =IF(F$3=0,-Inputs!$B$4,0) -> 0 | G6: =IF(G$3=0,-Inputs!$B$4,0) -> 0 | H6: =IF(H$3=0,-Inputs!$B$4,0) -> 0 | I6: =IF(I$3=0,-Inputs!$B$4,0) -> 0 | ... K6: =IF(K$3=0,-Inputs!$B$4,0) -> 0
A7: Net cash flow | B7: =SUM(B4:B6) -> -1450000000 | C7: =SUM(C4:C6) -> 51751616 | D7: =SUM(D4:D6) -> 53045406 | E7: =SUM(E4:E6) -> 54371542 | F7: =SUM(F4:F6) -> 55730830 | G7: =SUM(G4:G6) -> 57124101 | H7: =SUM(H4:H6) -> 58552203 | I7: =SUM(I4:I6) -> 1.5979262e+09 | ... K7: =SUM(K4:K6) -> 0

Sheet Returns
A3: Unlevered IRR | B3: =IRR('Cash Flow'!B7:K7) -> 0.045852846
A4: Net profit | B4: =SUM('Cash Flow'!B7:K7) -> 4.7850192e+08
A5: Going-in yield | B5: ='Cash Flow'!C4/Inputs!$B$4 -> 0.03569077
A6: Income secured by nominations | B6: =Inputs!$B$5*Inputs!$B$6/(Inputs!$B$5*Inputs!$B$6+(1-Inputs!$B$5)*Inputs!$B$7*Inputs!$B$8) -> 0.59102849
