Workbook

Sheet Loan Terms
A1: CANAL STREET – MEZZANINE LOAN (LENDER MODEL, USD)
A3: Commitment ($) | B3: 35000000
A4: Cash coupon | B4: 0.08
A5: PIK coupon | B5: 0.04
A6: Arrangement fee | B6: 0.015
A7: Exit fee | B7: 0.01
A8: Term (years) | B8: 4
A9: Property value ($) | B9: 190000000
A10: Senior loan ($) | B10: 105000000

Sheet Lender Cash Flow
A3: Year | B3: 0 | C3: 1 | D3: 2 | E3: 3 | F3: 4 | G3: 5
A4: Balance (with PIK) | B4: ='Loan Terms'!$B$3 -> 35000000 | C4: =IF(C$3<='Loan Terms'!$B$8,B4*(1+'Loan Terms'!$B$5),0) -> 36400000 | D4: =IF(D$3<='Loan Terms'!$B$8,C4*(1+'Loan Terms'!$B$5),0) -> 37856000 | E4: =IF(E$3<='Loan Terms'!$B$8,D4*(1+'Loan Terms'!$B$5),0) -> 39370240 | F4: =IF(F$3<='Loan Terms'!$B$8,E4*(1+'Loan Terms'!$B$5),0) -> 40945050 | G4: =IF(G$3<='Loan Terms'!$B$8,F4*(1+'Loan Terms'!$B$5),0) -> 0
A5: Drawdown | B5: =IF(B$3=0,-'Loan Terms'!$B$3,0) -> -35000000 | C5: =IF(C$3=0,-'Loan Terms'!$B$3,0) -> 0 | D5: =IF(D$3=0,-'Loan Terms'!$B$3,0) -> 0 | E5: =IF(E$3=0,-'Loan Terms'!$B$3,0) -> 0 | F5: =IF(F$3=0,-'Loan Terms'!$B$3,0) -> 0 | G5: =IF(G$3=0,-'Loan Terms'!$B$3,0) -> 0
A6: Fees | B6: =IF(B$3=0,'Loan Terms'!$B$3*'Loan Terms'!$B$6,0)+IF(B$3='Loan Terms'!$B$8,B4*'Loan Terms'!$B$7,0) -> 525000 | C6: =IF(C$3=0,'Loan Terms'!$B$3*'Loan Terms'!$B$6,0)+IF(C$3='Loan Terms'!$B$8,C4*'Loan Terms'!$B$7,0) -> 0 | D6: =IF(D$3=0,'Loan Terms'!$B$3*'Loan Terms'!$B$6,0)+IF(D$3='Loan Terms'!$B$8,D4*'Loan Terms'!$B$7,0) -> 0 | E6: =IF(E$3=0,'Loan Terms'!$B$3*'Loan Terms'!$B$6,0)+IF(E$3='Loan Terms'!$B$8,E4*'Loan Terms'!$B$7,0) -> 0 | F6: =IF(F$3=0,'Loan Terms'!$B$3*'Loan Terms'!$B$6,0)+IF(F$3='Loan Terms'!$B$8,F4*'Loan Terms'!$B$7,0) -> 409450.5 | G6: =IF(G$3=0,'Loan Terms'!$B$3*'Loan Terms'!$B$6,0)+IF(G$3='Loan Terms'!$B$8,G4*'Loan Terms'!$B$7,0) -> 0
A7: Cash interest | B7: =0 -> 0 | C7: =IF(C$3<='Loan Terms'!$B$8,B4*'Loan Terms'!$B$4,0) -> 2800000 | D7: =IF(D$3<='Loan Terms'!$B$8,C4*'Loan Terms'!$B$4,0) -> 2912000 | E7: =IF(E$3<='Loan Terms'!$B$8,D4*'Loan Terms'!$B$4,0) -> 3028480 | F7: =IF(F$3<='Loan Terms'!$B$8,E4*'Loan Terms'!$B$4,0) -> 3149619.2 | G7: =IF(G$3<='Loan Terms'!$B$8,F4*'Loan Terms'!$B$4,0) -> 0
A8: Repayment | B8: =IF(B$3='Loan Terms'!$B$8,B4,0) -> 0 | C8: =IF(C$3='Loan Terms'!$B$8,C4,0) -> 0 | D8: =IF(D$3='Loan Terms'!$B$8,D4,0) -> 0 | E8: =IF(E$3='Loan Terms'!$B$8,E4,0) -> 0 | F8: =IF(F$3='Loan Terms'!$B$8,F4,0) -> 40945050 | G8: =IF(G$3='Loan Terms'!$B$8,G4,0) -> 0
A9: Lender cash flow | B9: =SUM(B5:B8) -> -34475000 | C9: =SUM(C5:C8) -> 2800000 | D9: =SUM(D5:D8) -> 2912000 | E9: =SUM(E5:E8) -> 3028480 | F9: =SUM(F5:F8) -> 44504119 | G9: =SUM(G5:G8) -> 0

Sheet Lender Returns
A3: Lender IRR | B3: =IRR('Lender Cash Flow'!B9:G9) -> 0.12704418
A4: Lender MOIC | B4: =SUMIF('Lender Cash Flow'!B9:G9,">0")/-SUMIF('Lender Cash Flow'!B9:G9,"<0") -> 1.5444409
A5: Attachment LTV | B5: ='Loan Terms'!$B$10/'Loan Terms'!$B$9 -> 0.55263158
A6: Detachment LTV | B6: =('Loan Terms'!$B$10+'Loan Terms'!$B$3)/'Loan Terms'!$B$9 -> 0.73684211
A7: Net profit | B7: =SUM('Lender Cash Flow'!B9:G9) -> 18769599
