Workbook

Sheet Inputs
A1: WESTGATE RETAIL PARK (GBP)
A3: Case (Base, Low or High) | B3: Base
A4: Lettable area (sq ft) | B4: 210000
A5: Purchase price (£) | B5: 46000000
A6: Purchase costs | B6: 0.068
A7: Hold (years) | B7: 5

Sheet Cases
A1: Assumption | B1: Base | C1: Low | D1: High
A2: Rent (£/sq ft) | B2: 18.5 | C2: 16 | D2: 20
A3: Rental growth | B3: 0.02 | C3: 0 | D3: 0.03
A4: Exit yield | B4: 0.075 | C4: 0.085 | D4: 0.07
A5: Vacancy | B5: 0.06 | C5: 0.12 | D5: 0.04

Sheet Live
A1: Live case
A3: Rent (£/sq ft) | B3: =INDEX(INDIRECT(Inputs!$B$3),1) -> 18.5
A4: Rental growth | B4: =INDEX(INDIRECT(Inputs!$B$3),2) -> 0.02
A5: Exit yield | B5: =INDEX(INDIRECT(Inputs!$B$3),3) -> 0.075
A6: Vacancy | B6: =INDEX(INDIRECT(Inputs!$B$3),4) -> 0.06

Sheet Cash Flow
A3: Year | B3: 0 | C3: 1 | D3: 2 | E3: 3 | F3: 4 | G3: 5 | H3: 6
A4: Net rent | B4: =(B$3>=1)*(B$3<=Inputs!$B$7)*Inputs!$B$4*Live!$B$3*(1-Live!$B$6)*(1+Live!$B$4)^MAX(0,B$3-1) -> 0 | C4: =(C$3>=1)*(C$3<=Inputs!$B$7)*Inputs!$B$4*Live!$B$3*(1-Live!$B$6)*(1+Live!$B$4)^MAX(0,C$3-1) -> 3651900 | D4: =(D$3>=1)*(D$3<=Inputs!$B$7)*Inputs!$B$4*Live!$B$3*(1-Live!$B$6)*(1+Live!$B$4)^MAX(0,D$3-1) -> 3724938 | E4: =(E$3>=1)*(E$3<=Inputs!$B$7)*Inputs!$B$4*Live!$B$3*(1-Live!$B$6)*(1+Live!$B$4)^MAX(0,E$3-1) -> 3799436.8 | F4: =(F$3>=1)*(F$3<=Inputs!$B$7)*Inputs!$B$4*Live!$B$3*(1-Live!$B$6)*(1+Live!$B$4)^MAX(0,F$3-1) -> 3875425.5 | G4: =(G$3>=1)*(G$3<=Inputs!$B$7)*Inputs!$B$4*Live!$B$3*(1-Live!$B$6)*(1+Live!$B$4)^MAX(0,G$3-1) -> 3952934 | H4: =(H$3>=1)*(H$3<=Inputs!$B$7)*Inputs!$B$4*Live!$B$3*(1-Live!$B$6)*(1+Live!$B$4)^MAX(0,H$3-1) -> 0
A5: Sale | B5: =IF(B$3=Inputs!$B$7,Inputs!$B$4*Live!$B$3*(1-Live!$B$6)*(1+Live!$B$4)^B$3/Live!$B$5,0) -> 0 | C5: =IF(C$3=Inputs!$B$7,Inputs!$B$4*Live!$B$3*(1-Live!$B$6)*(1+Live!$B$4)^C$3/Live!$B$5,0) -> 0 | D5: =IF(D$3=Inputs!$B$7,Inputs!$B$4*Live!$B$3*(1-Live!$B$6)*(1+Live!$B$4)^D$3/Live!$B$5,0) -> 0 | E5: =IF(E$3=Inputs!$B$7,Inputs!$B$4*Live!$B$3*(1-Live!$B$6)*(1+Live!$B$4)^E$3/Live!$B$5,0) -> 0 | F5: =IF(F$3=Inputs!$B$7,Inputs!$B$4*Live!$B$3*(1-Live!$B$6)*(1+Live!$B$4)^F$3/Live!$B$5,0) -> 0 | G5: =IF(G$3=Inputs!$B$7,Inputs!$B$4*Live!$B$3*(1-Live!$B$6)*(1+Live!$B$4)^G$3/Live!$B$5,0) -> 53759902 | H5: =IF(H$3=Inputs!$B$7,Inputs!$B$4*Live!$B$3*(1-Live!$B$6)*(1+Live!$B$4)^H$3/Live!$B$5,0) -> 0
A6: Purchase | B6: =IF(B$3=0,-Inputs!$B$5*(1+Inputs!$B$6),0) -> -49128000 | C6: =IF(C$3=0,-Inputs!$B$5*(1+Inputs!$B$6),0) -> 0 | D6: =IF(D$3=0,-Inputs!$B$5*(1+Inputs!$B$6),0) -> 0 | E6: =IF(E$3=0,-Inputs!$B$5*(1+Inputs!$B$6),0) -> 0 | F6: =IF(F$3=0,-Inputs!$B$5*(1+Inputs!$B$6),0) -> 0 | G6: =IF(G$3=0,-Inputs!$B$5*(1+Inputs!$B$6),0) -> 0 | H6: =IF(H$3=0,-Inputs!$B$5*(1+Inputs!$B$6),0) -> 0
A7: Cash flow | B7: =SUM(B4:B6) -> -49128000 | C7: =SUM(C4:C6) -> 3651900 | D7: =SUM(D4:D6) -> 3724938 | E7: =SUM(E4:E6) -> 3799436.8 | F7: =SUM(F4:F6) -> 3875425.5 | G7: =SUM(G4:G6) -> 57712836 | H7: =SUM(H4:H6) -> 0

Sheet Returns
A3: Unlevered IRR | B3: =IRR('Cash Flow'!B7:H7) -> 0.092764482
A4: Net profit | B4: =SUM('Cash Flow'!B7:H7) -> 23636537
A5: Net initial yield | B5: ='Cash Flow'!C4/(Inputs!$B$5*(1+Inputs!$B$6)) -> 0.074334392
