Workbook

Sheet Inputs
A1: AL WAHA MIXED-USE – PHASED DEVELOPMENT (SAR)
A3: Active scenario (1 Base, 2 Downside, 3 Upside) | B3: 1
A4: Land (SAR) | B4: 240000000
A5: Real estate transaction tax | B5: 0.05
A6: Residential GFA (sqm) | B6: 60000
A7: Office GLA (sqm) | B7: 35000
A8: Retail GLA (sqm) | B8: 18000
A9: Phase 1 residential start (year) | B9: 1
A10: Phase 2 office start (year) | B10: 2
A11: Phase 3 retail start (year) | B11: 3
A12: Murabaha (% of cost) | B12: 0.55
A13: Murabaha profit rate | B13: 0.065
A14: Zakat | B14: 0.025
A15: Discount rate | B15: 0.1

Sheet Scenarios
A1: Assumption | B1: Base | C1: Downside | D1: Upside | E1: Live
A2: Residential sale price (SAR/sqm) | B2: 9500 | C2: 8400 | D2: 10200 | E2: =CHOOSE(Inputs!$B$3,B2,C2,D2) -> 9500
A3: Office rent (SAR/sqm/yr) | B3: 1100 | C3: 950 | D3: 1200 | E3: =CHOOSE(Inputs!$B$3,B3,C3,D3) -> 1100
A4: Retail rent (SAR/sqm/yr) | B4: 1600 | C4: 1350 | D4: 1750 | E4: =CHOOSE(Inputs!$B$3,B4,C4,D4) -> 1600
A5: Exit yield | B5: 0.075 | C5: 0.085 | D5: 0.07 | E5: =CHOOSE(Inputs!$B$3,B5,C5,D5) -> 0.075
A6: Construction cost (SAR/sqm) | B6: 4200 | C6: 4600 | D6: 4100 | E6: =CHOOSE(Inputs!$B$3,B6,C6,D6) -> 4200

Sheet Cash Flow
A3: Year | B3: 0 | C3: 1 | D3: 2 | E3: 3 | F3: 4 | G3: 5 | H3: 6 | I3: 7 | J3: 8 | K3: 9 | L3: 10 | M3: 11 | N3: 12
A4: Land and RETT | B4: =IF(B$3=0,Inputs!$B$4*(1+Inputs!$B$5),0) -> 252000000 | C4: =IF(C$3=0,Inputs!$B$4*(1+Inputs!$B$5),0) -> 0 | D4: =IF(D$3=0,Inputs!$B$4*(1+Inputs!$B$5),0) -> 0 | E4: =IF(E$3=0,Inputs!$B$4*(1+Inputs!$B$5),0) -> 0 | F4: =IF(F$3=0,Inputs!$B$4*(1+Inputs!$B$5),0) -> 0 | G4: =IF(G$3=0,Inputs!$B$4*(1+Inputs!$B$5),0) -> 0 | H4: =IF(H$3=0,Inputs!$B$4*(1+Inputs!$B$5),0) -> 0 | I4: =IF(I$3=0,Inputs!$B$4*(1+Inputs!$B$5),0) -> 0 | ... N4: =IF(N$3=0,Inputs!$B$4*(1+Inputs!$B$5),0) -> 0
A5: Residential build | B5: =IF(AND(B$3>=Inputs!$B$9,B$3<Inputs!$B$9+2),Inputs!$B$6*Scenarios!$E$6/2,0) -> 0 | C5: =IF(AND(C$3>=Inputs!$B$9,C$3<Inputs!$B$9+2),Inputs!$B$6*Scenarios!$E$6/2,0) -> 126000000 | D5: =IF(AND(D$3>=Inputs!$B$9,D$3<Inputs!$B$9+2),Inputs!$B$6*Scenarios!$E$6/2,0) -> 126000000 | E5: =IF(AND(E$3>=Inputs!$B$9,E$3<Inputs!$B$9+2),Inputs!$B$6*Scenarios!$E$6/2,0) -> 0 | F5: =IF(AND(F$3>=Inputs!$B$9,F$3<Inputs!$B$9+2),Inputs!$B$6*Scenarios!$E$6/2,0) -> 0 | G5: =IF(AND(G$3>=Inputs!$B$9,G$3<Inputs!$B$9+2),Inputs!$B$6*Scenarios!$E$6/2,0) -> 0 | H5: =IF(AND(H$3>=Inputs!$B$9,H$3<Inputs!$B$9+2),Inputs!$B$6*Scenarios!$E$6/2,0) -> 0 | I5: =IF(AND(I$3>=Inputs!$B$9,I$3<Inputs!$B$9+2),Inputs!$B$6*Scenarios!$E$6/2,0) -> 0 | ... N5: =IF(AND(N$3>=Inputs!$B$9,N$3<Inputs!$B$9+2),Inputs!$B$6*Scenarios!$E$6/2,0) -> 0
A6: Office build | B6: =IF(AND(B$3>=Inputs!$B$10,B$3<Inputs!$B$10+2),Inputs!$B$7*Scenarios!$E$6/2,0) -> 0 | C6: =IF(AND(C$3>=Inputs!$B$10,C$3<Inputs!$B$10+2),Inputs!$B$7*Scenarios!$E$6/2,0) -> 0 | D6: =IF(AND(D$3>=Inputs!$B$10,D$3<Inputs!$B$10+2),Inputs!$B$7*Scenarios!$E$6/2,0) -> 73500000 | E6: =IF(AND(E$3>=Inputs!$B$10,E$3<Inputs!$B$10+2),Inputs!$B$7*Scenarios!$E$6/2,0) -> 73500000 | F6: =IF(AND(F$3>=Inputs!$B$10,F$3<Inputs!$B$10+2),Inputs!$B$7*Scenarios!$E$6/2,0) -> 0 | G6: =IF(AND(G$3>=Inputs!$B$10,G$3<Inputs!$B$10+2),Inputs!$B$7*Scenarios!$E$6/2,0) -> 0 | H6: =IF(AND(H$3>=Inputs!$B$10,H$3<Inputs!$B$10+2),Inputs!$B$7*Scenarios!$E$6/2,0) -> 0 | I6: =IF(AND(I$3>=Inputs!$B$10,I$3<Inputs!$B$10+2),Inputs!$B$7*Scenarios!$E$6/2,0) -> 0 | ... N6: =IF(AND(N$3>=Inputs!$B$10,N$3<Inputs!$B$10+2),Inputs!$B$7*Scenarios!$E$6/2,0) -> 0
A7: Retail build | B7: =IF(AND(B$3>=Inputs!$B$11,B$3<Inputs!$B$11+2),Inputs!$B$8*Scenarios!$E$6/2,0) -> 0 | C7: =IF(AND(C$3>=Inputs!$B$11,C$3<Inputs!$B$11+2),Inputs!$B$8*Scenarios!$E$6/2,0) -> 0 | D7: =IF(AND(D$3>=Inputs!$B$11,D$3<Inputs!$B$11+2),Inputs!$B$8*Scenarios!$E$6/2,0) -> 0 | E7: =IF(AND(E$3>=Inputs!$B$11,E$3<Inputs!$B$11+2),Inputs!$B$8*Scenarios!$E$6/2,0) -> 37800000 | F7: =IF(AND(F$3>=Inputs!$B$11,F$3<Inputs!$B$11+2),Inputs!$B$8*Scenarios!$E$6/2,0) -> 37800000 | G7: =IF(AND(G$3>=Inputs!$B$11,G$3<Inputs!$B$11+2),Inputs!$B$8*Scenarios!$E$6/2,0) -> 0 | H7: =IF(AND(H$3>=Inputs!$B$11,H$3<Inputs!$B$11+2),Inputs!$B$8*Scenarios!$E$6/2,0) -> 0 | I7: =IF(AND(I$3>=Inputs!$B$11,I$3<Inputs!$B$11+2),Inputs!$B$8*Scenarios!$E$6/2,0) -> 0 | ... N7: =IF(AND(N$3>=Inputs!$B$11,N$3<Inputs!$B$11+2),Inputs!$B$8*Scenarios!$E$6/2,0) -> 0
A8: Total cost | B8: =SUM(B4:B7) -> 252000000 | C8: =SUM(C4:C7) -> 126000000 | D8: =SUM(D4:D7) -> 199500000 | E8: =SUM(E4:E7) -> 111300000 | F8: =SUM(F4:F7) -> 37800000 | G8: =SUM(G4:G7) -> 0 | H8: =SUM(H4:H7) -> 0 | I8: =SUM(I4:I7) -> 0 | ... N8: =SUM(N4:N7) -> 0
A9: Residential sales | B9: =IF(AND(B$3>=Inputs!$B$9+2,B$3<Inputs!$B$9+5),Inputs!$B$6*Scenarios!$E$2/3,0) -> 0 | C9: =IF(AND(C$3>=Inputs!$B$9+2,C$3<Inputs!$B$9+5),Inputs!$B$6*Scenarios!$E$2/3,0) -> 0 | D9: =IF(AND(D$3>=Inputs!$B$9+2,D$3<Inputs!$B$9+5),Inputs!$B$6*Scenarios!$E$2/3,0) -> 0 | E9: =IF(AND(E$3>=Inputs!$B$9+2,E$3<Inputs!$B$9+5),Inputs!$B$6*Scenarios!$E$2/3,0) -> 190000000 | F9: =IF(AND(F$3>=Inputs!$B$9+2,F$3<Inputs!$B$9+5),Inputs!$B$6*Scenarios!$E$2/3,0) -> 190000000 | G9: =IF(AND(G$3>=Inputs!$B$9+2,G$3<Inputs!$B$9+5),Inputs!$B$6*Scenarios!$E$2/3,0) -> 190000000 | H9: =IF(AND(H$3>=Inputs!$B$9+2,H$3<Inputs!$B$9+5),Inputs!$B$6*Scenarios!$E$2/3,0) -> 0 | I9: =IF(AND(I$3>=Inputs!$B$9+2,I$3<Inputs!$B$9+5),Inputs!$B$6*Scenarios!$E$2/3,0) -> 0 | ... N9: =IF(AND(N$3>=Inputs!$B$9+2,N$3<Inputs!$B$9+5),Inputs!$B$6*Scenarios!$E$2/3,0) -> 0
A10: Office NOI | B10: =IF(AND(B$3>=Inputs!$B$10+2,B$3<12),Inputs!$B$7*Scenarios!$E$3*0.9,0) -> 0 | C10: =IF(AND(C$3>=Inputs!$B$10+2,C$3<12),Inputs!$B$7*Scenarios!$E$3*0.9,0) -> 0 | D10: =IF(AND(D$3>=Inputs!$B$10+2,D$3<12),Inputs!$B$7*Scenarios!$E$3*0.9,0) -> 0 | E10: =IF(AND(E$3>=Inputs!$B$10+2,E$3<12),Inputs!$B$7*Scenarios!$E$3*0.9,0) -> 0 | F10: =IF(AND(F$3>=Inputs!$B$10+2,F$3<12),Inputs!$B$7*Scenarios!$E$3*0.9,0) -> 34650000 | G10: =IF(AND(G$3>=Inputs!$B$10+2,G$3<12),Inputs!$B$7*Scenarios!$E$3*0.9,0) -> 34650000 | H10: =IF(AND(H$3>=Inputs!$B$10+2,H$3<12),Inputs!$B$7*Scenarios!$E$3*0.9,0) -> 34650000 | I10: =IF(AND(I$3>=Inputs!$B$10+2,I$3<12),Inputs!$B$7*Scenarios!$E$3*0.9,0) -> 34650000 | ... N10: =IF(AND(N$3>=Inputs!$B$10+2,N$3<12),Inputs!$B$7*Scenarios!$E$3*0.9,0) -> 0
A11: Retail NOI | B11: =IF(AND(B$3>=Inputs!$B$11+2,B$3<12),Inputs!$B$8*Scenarios!$E$4*0.88,0) -> 0 | C11: =IF(AND(C$3>=Inputs!$B$11+2,C$3<12),Inputs!$B$8*Scenarios!$E$4*0.88,0) -> 0 | D11: =IF(AND(D$3>=Inputs!$B$11+2,D$3<12),Inputs!$B$8*Scenarios!$E$4*0.88,0) -> 0 | E11: =IF(AND(E$3>=Inputs!$B$11+2,E$3<12),Inputs!$B$8*Scenarios!$E$4*0.88,0) -> 0 | F11: =IF(AND(F$3>=Inputs!$B$11+2,F$3<12),Inputs!$B$8*Scenarios!$E$4*0.88,0) -> 0 | G11: =IF(AND(G$3>=Inputs!$B$11+2,G$3<12),Inputs!$B$8*Scenarios!$E$4*0.88,0) -> 25344000 | H11: =IF(AND(H$3>=Inputs!$B$11+2,H$3<12),Inputs!$B$8*Scenarios!$E$4*0.88,0) -> 25344000 | I11: =IF(AND(I$3>=Inputs!$B$11+2,I$3<12),Inputs!$B$8*Scenarios!$E$4*0.88,0) -> 25344000 | ... N11: =IF(AND(N$3>=Inputs!$B$11+2,N$3<12),Inputs!$B$8*Scenarios!$E$4*0.88,0) -> 0
A12: Exit value | B12: =IF(B$3=12,(Inputs!$B$7*Scenarios!$E$3*0.9+Inputs!$B$8*Scenarios!$E$4*0.88)/Scenarios!$E$5,0) -> 0 | C12: =IF(C$3=12,(Inputs!$B$7*Scenarios!$E$3*0.9+Inputs!$B$8*Scenarios!$E$4*0.88)/Scenarios!$E$5,0) -> 0 | D12: =IF(D$3=12,(Inputs!$B$7*Scenarios!$E$3*0.9+Inputs!$B$8*Scenarios!$E$4*0.88)/Scenarios!$E$5,0) -> 0 | E12: =IF(E$3=12,(Inputs!$B$7*Scenarios!$E$3*0.9+Inputs!$B$8*Scenarios!$E$4*0.88)/Scenarios!$E$5,0) -> 0 | F12: =IF(F$3=12,(Inputs!$B$7*Scenarios!$E$3*0.9+Inputs!$B$8*Scenarios!$E$4*0.88)/Scenarios!$E$5,0) -> 0 | G12: =IF(G$3=12,(Inputs!$B$7*Scenarios!$E$3*0.9+Inputs!$B$8*Scenarios!$E$4*0.88)/Scenarios!$E$5,0) -> 0 | H12: =IF(H$3=12,(Inputs!$B$7*Scenarios!$E$3*0.9+Inputs!$B$8*Scenarios!$E$4*0.88)/Scenarios!$E$5,0) -> 0 | I12: =IF(I$3=12,(Inputs!$B$7*Scenarios!$E$3*0.9+Inputs!$B$8*Scenarios!$E$4*0.88)/Scenarios!$E$5,0) -> 0 | ... N12: =IF(N$3=12,(Inputs!$B$7*Scenarios!$E$3*0.9+Inputs!$B$8*Scenarios!$E$4*0.88)/Scenarios!$E$5,0) -> 799920000
A13: Revenue | B13: =SUM(B9:B12) -> 0 | C13: =SUM(C9:C12) -> 0 | D13: =SUM(D9:D12) -> 0 | E13: =SUM(E9:E12) -> 190000000 | F13: =SUM(F9:F12) -> 224650000 | G13: =SUM(G9:G12) -> 249994000 | H13: =SUM(H9:H12) -> 59994000 | I13: =SUM(I9:I12) -> 59994000 | ... N13: =SUM(N9:N12) -> 799920000
A14: Murabaha drawn | B14: =B8*Inputs!$B$12 -> 138600000 | C14: =C8*Inputs!$B$12 -> 69300000 | D14: =D8*Inputs!$B$12 -> 109725000 | E14: =E8*Inputs!$B$12 -> 61215000 | F14: =F8*Inputs!$B$12 -> 20790000 | G14: =G8*Inputs!$B$12 -> 0 | H14: =H8*Inputs!$B$12 -> 0 | I14: =I8*Inputs!$B$12 -> 0 | ... N14: =N8*Inputs!$B$12 -> 0
A15: Murabaha profit | B15: =0*Inputs!$B$13 -> 0 | C15: =B17*Inputs!$B$13 -> 9009000 | D15: =C17*Inputs!$B$13 -> 14099085 | E15: =D17*Inputs!$B$13 -> 22147651 | F15: =E17*Inputs!$B$13 -> 15216223 | G15: =F17*Inputs!$B$13 -> 2954377.3 | H15: =G17*Inputs!$B$13 -> 0 | I15: =H17*Inputs!$B$13 -> 0 | J15: =I17*Inputs!$B$13 -> 0 | ... N15: =M17*Inputs!$B$13 -> 0
A16: Murabaha repaid | B16: =MIN(B13,0+B14+B15) -> 0 | C16: =MIN(C13,B17+C14+C15) -> 0 | D16: =MIN(D13,C17+D14+D15) -> 0 | E16: =MIN(E13,D17+E14+E15) -> 190000000 | F16: =MIN(F13,E17+F14+F15) -> 224650000 | G16: =MIN(G13,F17+G14+G15) -> 48406336 | H16: =MIN(H13,G17+H14+H15) -> 0 | I16: =MIN(I13,H17+I14+I15) -> 0 | J16: =MIN(J13,I17+J14+J15) -> 0 | ... N16: =MIN(N13,M17+N14+N15) -> 0
A17: Murabaha balance | B17: =0+B14+B15-B16 -> 138600000 | C17: =B17+C14+C15-C16 -> 216909000 | D17: =C17+D14+D15-D16 -> 340733085 | E17: =D17+E14+E15-E16 -> 2.3409574e+08 | F17: =E17+F14+F15-F16 -> 45451958 | G17: =F17+G14+G15-G16 -> 0 | H17: =G17+H14+H15-H16 -> 0 | I17: =H17+I14+I15-I16 -> 0 | J17: =I17+J14+J15-J16 -> 0 | ... N17: =M17+N14+N15-N16 -> 0
A18: Pre-zakat cash flow | B18: =B13-B8 -> -252000000 | C18: =C13-C8 -> -126000000 | D18: =D13-D8 -> -199500000 | E18: =E13-E8 -> 78700000 | F18: =F13-F8 -> 186850000 | G18: =G13-G8 -> 249994000 | H18: =H13-H8 -> 59994000 | I18: =I13-I8 -> 59994000 | ... N18: =N13-N8 -> 799920000
A19: Zakat | B19: =-MAX(0,B18-B15)*Inputs!$B$14 -> 0 | C19: =-MAX(0,C18-C15)*Inputs!$B$14 -> 0 | D19: =-MAX(0,D18-D15)*Inputs!$B$14 -> 0 | E19: =-MAX(0,E18-E15)*Inputs!$B$14 -> -1413808.7 | F19: =-MAX(0,F18-F15)*Inputs!$B$14 -> -4290844.4 | G19: =-MAX(0,G18-G15)*Inputs!$B$14 -> -6175990.6 | H19: =-MAX(0,H18-H15)*Inputs!$B$14 -> -1499850 | I19: =-MAX(0,I18-I15)*Inputs!$B$14 -> -1499850 | ... N19: =-MAX(0,N18-N15)*Inputs!$B$14 -> -19998000
A20: Unlevered cash flow | B20: =B18+B19 -> -252000000 | C20: =C18+C19 -> -126000000 | D20: =D18+D19 -> -199500000 | E20: =E18+E19 -> 77286191 | F20: =F18+F19 -> 1.8255916e+08 | G20: =G18+G19 -> 2.4381801e+08 | H20: =H18+H19 -> 58494150 | I20: =I18+I19 -> 58494150 | ... N20: =N18+N19 -> 779922000
A21: Equity cash flow | B21: =B20+B14-B16 -> -113400000 | C21: =C20+C14-C16 -> -56700000 | D21: =D20+D14-D16 -> -89775000 | E21: =E20+E14-E16 -> -51498809 | F21: =F20+F14-F16 -> -21300844 | G21: =G20+G14-G16 -> 1.9541167e+08 | H21: =H20+H14-H16 -> 58494150 | I21: =I20+I14-I16 -> 58494150 | ... N21: =N20+N14-N16 -> 779922000

Sheet Returns
A3: Project IRR | B3: =IRR('Cash Flow'!B20:N20) -> 0.15691472
A4: Equity IRR | B4: =IRR('Cash Flow'!B21:N21) -> 0.18789856
A5: NPV at the discount rate | B5: =NPV(Inputs!$B$15,'Cash Flow'!C20:N20)+'Cash Flow'!B20 -> 2.0941834e+08
A6: Profit after zakat | B6: =SUM('Cash Flow'!B20:N20) -> 1.0570503e+09
A7: Peak murabaha | B7: =MAX('Cash Flow'!B17:N17) -> 340733085
A8: Total development cost | B8: =SUM('Cash Flow'!B8:N8) -> 726600000
