Workbook

Sheet Assumptions
A1: HARBOR POINT CONDOMINIUMS – JV DEVELOPMENT (USD)
A3: Units | B3: 240
A4: Average sale price ($ per unit) | B4: 650000
A5: Sales start (month) | B5: 24
A6: Sales pace (units per month) | B6: 10
A7: Selling costs | B7: 0.03
A8: Land ($) | B8: 18000000
A9: Hard costs ($) | B9: 72000000
A10: Construction start (month) | B10: 3
A11: Soft costs (% of hard) | B11: 0.12
A12: Contingency (% of hard) | B12: 0.05
A13: Loan to cost | B13: 0.6
A14: Construction loan interest rate | B14: 0.075
... A20: LP share above tier 2 | B20: 0.6

Sheet Curve
A1: Month of build | B1: Share of hard cost
A2: 1 | B2: 0.00427757
A3: 2 | B3: 0.01275952
A4: 3 | B4: 0.02102315
A5: 4 | B5: 0.02892706
A6: 5 | B6: 0.03633603
A7: 6 | B7: 0.04312328
A8: 7 | B8: 0.04917268
A9: 8 | B9: 0.05438071
A10: 9 | B10: 0.05865828
A11: 10 | B11: 0.06193219
A12: 11 | B12: 0.06414643
A13: 12 | B13: 0.0652631
... A25: 24 | B25: 0.00427757
A26: Total | B26: =SUM(B2:B25) -> 1

Sheet Cash Flow
A3: Month | B3: 0 | C3: 1 | D3: 2 | E3: 3 | F3: 4 | G3: 5 | H3: 6 | I3: 7 | J3: 8 | K3: 9 | L3: 10 | M3: 11 | N3: 12 | O3: 13 | P3: 14 | Q3: 15 | R3: 16 | S3: 17 | T3: 18 | U3: 19 | V3: 20 | W3: 21 | X3: 22 | Y3: 23 | Z3: 24 | AA3: 25 | AB3: 26 | AC3: 27 | AD3: 28 | AE3: 29 | AF3: 30 | AG3: 31 | AH3: 32 | AI3: 33 | AJ3: 34 | AK3: 35 | AL3: 36 | AM3: 37 | AN3: 38 | AO3: 39 | AP3: 40 | AQ3: 41 | AR3: 42 | AS3: 43 | AT3: 44 | AU3: 45 | AV3: 46 | AW3: 47
A4: Land | B4: =IF(B$3=0,Assumptions!$B$8,0) -> 18000000 | C4: =IF(C$3=0,Assumptions!$B$8,0) -> 0 | D4: =IF(D$3=0,Assumptions!$B$8,0) -> 0 | E4: =IF(E$3=0,Assumptions!$B$8,0) -> 0 | F4: =IF(F$3=0,Assumptions!$B$8,0) -> 0 | G4: =IF(G$3=0,Assumptions!$B$8,0) -> 0 | H4: =IF(H$3=0,Assumptions!$B$8,0) -> 0 | I4: =IF(I$3=0,Assumptions!$B$8,0) -> 0 | ... AW4: =IF(AW$3=0,Assumptions!$B$8,0) -> 0
A5: Hard costs | B5: =IF(AND(B$3>=Assumptions!$B$10,B$3<Assumptions!$B$10+24),Assumptions!$B$9*INDEX(Curve!$B$2:$B$25,B$3-Assumptions!$B$10+1),0) -> 0 | C5: =IF(AND(C$3>=Assumptions!$B$10,C$3<Assumptions!$B$10+24),Assumptions!$B$9*INDEX(Curve!$B$2:$B$25,C$3-Assumptions!$B$10+1),0) -> 0 | D5: =IF(AND(D$3>=Assumptions!$B$10,D$3<Assumptions!$B$10+24),Assumptions!$B$9*INDEX(Curve!$B$2:$B$25,D$3-Assumptions!$B$10+1),0) -> 0 | E5: =IF(AND(E$3>=Assumptions!$B$10,E$3<Assumptions!$B$10+24),Assumptions!$B$9*INDEX(Curve!$B$2:$B$25,E$3-Assumptions!$B$10+1),0) -> 307985.04 | F5: =IF(AND(F$3>=Assumptions!$B$10,F$3<Assumptions!$B$10+24),Assumptions!$B$9*INDEX(Curve!$B$2:$B$25,F$3-Assumptions!$B$10+1),0) -> 918685.44 | G5: =IF(AND(G$3>=Assumptions!$B$10,G$3<Assumptions!$B$10+24),Assumptions!$B$9*INDEX(Curve!$B$2:$B$25,G$3-Assumptions!$B$10+1),0) -> 1513666.8 | H5: =IF(AND(H$3>=Assumptions!$B$10,H$3<Assumptions!$B$10+24),Assumptions!$B$9*INDEX(Curve!$B$2:$B$25,H$3-Assumptions!$B$10+1),0) -> 2082748.3 | I5: =IF(AND(I$3>=Assumptions!$B$10,I$3<Assumptions!$B$10+24),Assumptions!$B$9*INDEX(Curve!$B$2:$B$25,I$3-Assumptions!$B$10+1),0) -> 2616194.2 | ... AW5: =IF(AND(AW$3>=Assumptions!$B$10,AW$3<Assumptions!$B$10+24),Assumptions!$B$9*INDEX(Curve!$B$2:$B$25,AW$3-Assumptions!$B$10+1),0) -> 0
A6: Soft costs | B6: =B5*Assumptions!$B$11 -> 0 | C6: =C5*Assumptions!$B$11 -> 0 | D6: =D5*Assumptions!$B$11 -> 0 | E6: =E5*Assumptions!$B$11 -> 36958.205 | F6: =F5*Assumptions!$B$11 -> 110242.25 | G6: =G5*Assumptions!$B$11 -> 181640.02 | H6: =H5*Assumptions!$B$11 -> 249929.8 | I6: =I5*Assumptions!$B$11 -> 313943.3 | ... AW6: =AW5*Assumptions!$B$11 -> 0
A7: Contingency | B7: =B5*Assumptions!$B$12 -> 0 | C7: =C5*Assumptions!$B$12 -> 0 | D7: =D5*Assumptions!$B$12 -> 0 | E7: =E5*Assumptions!$B$12 -> 15399.252 | F7: =F5*Assumptions!$B$12 -> 45934.272 | G7: =G5*Assumptions!$B$12 -> 75683.34 | H7: =H5*Assumptions!$B$12 -> 104137.42 | I7: =I5*Assumptions!$B$12 -> 130809.71 | ... AW7: =AW5*Assumptions!$B$12 -> 0
A8: Arrangement fee | B8: =IF(B$3=0,Assumptions!$B$15*Assumptions!$B$13*SUM($B$10:$AW$10),0) -> 644159.86 | C8: =IF(C$3=0,Assumptions!$B$15*Assumptions!$B$13*SUM($B$10:$AW$10),0) -> 0 | D8: =IF(D$3=0,Assumptions!$B$15*Assumptions!$B$13*SUM($B$10:$AW$10),0) -> 0 | E8: =IF(E$3=0,Assumptions!$B$15*Assumptions!$B$13*SUM($B$10:$AW$10),0) -> 0 | F8: =IF(F$3=0,Assumptions!$B$15*Assumptions!$B$13*SUM($B$10:$AW$10),0) -> 0 | G8: =IF(G$3=0,Assumptions!$B$15*Assumptions!$B$13*SUM($B$10:$AW$10),0) -> 0 | H8: =IF(H$3=0,Assumptions!$B$15*Assumptions!$B$13*SUM($B$10:$AW$10),0) -> 0 | I8: =IF(I$3=0,Assumptions!$B$15*Assumptions!$B$13*SUM($B$10:$AW$10),0) -> 0 | ... AW8: =IF(AW$3=0,Assumptions!$B$15*Assumptions!$B$13*SUM($B$10:$AW$10),0) -> 0
A9: Interest (capitalised) | B9: =0 -> 0 | C9: =B18*Assumptions!$B$14/12 -> 0 | D9: =C18*Assumptions!$B$14/12 -> 0 | E9: =D18*Assumptions!$B$14/12 -> 0 | F9: =E18*Assumptions!$B$14/12 -> 0 | G9: =F18*Assumptions!$B$14/12 -> 0 | H9: =G18*Assumptions!$B$14/12 -> 0 | I9: =H18*Assumptions!$B$14/12 -> 0 | J9: =I18*Assumptions!$B$14/12 -> 0 | ... AW9: =AV18*Assumptions!$B$14/12 -> 0
A10: Total cost | B10: =SUM(B4:B9) -> 18644160 | C10: =SUM(C4:C9) -> 0 | D10: =SUM(D4:D9) -> 0 | E10: =SUM(E4:E9) -> 360342.5 | F10: =SUM(F4:F9) -> 1074862 | G10: =SUM(G4:G9) -> 1770990.2 | H10: =SUM(H4:H9) -> 2436815.5 | I10: =SUM(I4:I9) -> 3060947.2 | ... AW10: =SUM(AW4:AW9) -> 0
A11: Cumulative cost | B11: =B10 -> 18644160 | C11: =B11+C10 -> 18644160 | D11: =C11+D10 -> 18644160 | E11: =D11+E10 -> 19004502 | F11: =E11+F10 -> 20079364 | G11: =F11+G10 -> 21850354 | H11: =G11+H10 -> 24287170 | I11: =H11+I10 -> 27348117 | J11: =I11+J10 -> 30980822 | ... AW11: =AV11+AW10 -> 1.0735998e+08
A12: Equity drawn | B12: =MIN(B10,MAX(0,(1-Assumptions!$B$13)*SUM($B$10:$AW$10)-0)) -> 18644160 | C12: =MIN(C10,MAX(0,(1-Assumptions!$B$13)*SUM($B$10:$AW$10)-B13)) -> 0 | D12: =MIN(D10,MAX(0,(1-Assumptions!$B$13)*SUM($B$10:$AW$10)-C13)) -> 0 | E12: =MIN(E10,MAX(0,(1-Assumptions!$B$13)*SUM($B$10:$AW$10)-D13)) -> 360342.5 | F12: =MIN(F10,MAX(0,(1-Assumptions!$B$13)*SUM($B$10:$AW$10)-E13)) -> 1074862 | G12: =MIN(G10,MAX(0,(1-Assumptions!$B$13)*SUM($B$10:$AW$10)-F13)) -> 1770990.2 | H12: =MIN(H10,MAX(0,(1-Assumptions!$B$13)*SUM($B$10:$AW$10)-G13)) -> 2436815.5 | I12: =MIN(I10,MAX(0,(1-Assumptions!$B$13)*SUM($B$10:$AW$10)-H13)) -> 3060947.2 | J12: =MIN(J10,MAX(0,(1-Assumptions!$B$13)*SUM($B$10:$AW$10)-I13)) -> 3632705.1 | ... AW12: =MIN(AW10,MAX(0,(1-Assumptions!$B$13)*SUM($B$10:$AW$10)-AV13)) -> 0
A13: Cumulative equity | B13: =B12 -> 18644160 | C13: =B13+C12 -> 18644160 | D13: =C13+D12 -> 18644160 | E13: =D13+E12 -> 19004502 | F13: =E13+F12 -> 20079364 | G13: =F13+G12 -> 21850354 | H13: =G13+H12 -> 24287170 | I13: =H13+I12 -> 27348117 | J13: =I13+J12 -> 30980822 | ... AW13: =AV13+AW12 -> 42943991
A14: Debt drawn | B14: =B10-B12 -> 0 | C14: =C10-C12 -> 0 | D14: =D10-D12 -> 0 | E14: =E10-E12 -> 0 | F14: =F10-F12 -> 0 | G14: =G10-G12 -> 0 | H14: =H10-H12 -> 0 | I14: =I10-I12 -> 0 | ... AW14: =AW10-AW12 -> 0
A15: Units sold | B15: =IF(B$3>=Assumptions!$B$5,MIN(Assumptions!$B$6,Assumptions!$B$3-0),0) -> 0 | C15: =IF(C$3>=Assumptions!$B$5,MIN(Assumptions!$B$6,Assumptions!$B$3-B35),0) -> 0 | D15: =IF(D$3>=Assumptions!$B$5,MIN(Assumptions!$B$6,Assumptions!$B$3-C35),0) -> 0 | E15: =IF(E$3>=Assumptions!$B$5,MIN(Assumptions!$B$6,Assumptions!$B$3-D35),0) -> 0 | F15: =IF(F$3>=Assumptions!$B$5,MIN(Assumptions!$B$6,Assumptions!$B$3-E35),0) -> 0 | G15: =IF(G$3>=Assumptions!$B$5,MIN(Assumptions!$B$6,Assumptions!$B$3-F35),0) -> 0 | H15: =IF(H$3>=Assumptions!$B$5,MIN(Assumptions!$B$6,Assumptions!$B$3-G35),0) -> 0 | I15: =IF(I$3>=Assumptions!$B$5,MIN(Assumptions!$B$6,Assumptions!$B$3-H35),0) -> 0 | J15: =IF(J$3>=Assumptions!$B$5,MIN(Assumptions!$B$6,Assumptions!$B$3-I35),0) -> 0 | ... AW15: =IF(AW$3>=Assumptions!$B$5,MIN(Assumptions!$B$6,Assumptions!$B$3-AV35),0) -> 10
A16: Net sales revenue | B16: =B15*Assumptions!$B$4*(1-Assumptions!$B$7) -> 0 | C16: =C15*Assumptions!$B$4*(1-Assumptions!$B$7) -> 0 | D16: =D15*Assumptions!$B$4*(1-Assumptions!$B$7) -> 0 | E16: =E15*Assumptions!$B$4*(1-Assumptions!$B$7) -> 0 | F16: =F15*Assumptions!$B$4*(1-Assumptions!$B$7) -> 0 | G16: =G15*Assumptions!$B$4*(1-Assumptions!$B$7) -> 0 | H16: =H15*Assumptions!$B$4*(1-Assumptions!$B$7) -> 0 | I16: =I15*Assumptions!$B$4*(1-Assumptions!$B$7) -> 0 | ... AW16: =AW15*Assumptions!$B$4*(1-Assumptions!$B$7) -> 6305000
A17: Loan repayment | B17: =MIN(B16,0+B14) -> 0 | C17: =MIN(C16,B18+C14) -> 0 | D17: =MIN(D16,C18+D14) -> 0 | E17: =MIN(E16,D18+E14) -> 0 | F17: =MIN(F16,E18+F14) -> 0 | G17: =MIN(G16,F18+G14) -> 0 | H17: =MIN(H16,G18+H14) -> 0 | I17: =MIN(I16,H18+I14) -> 0 | J17: =MIN(J16,I18+J14) -> 0 | ... AW17: =MIN(AW16,AV18+AW14) -> 0
A18: Loan balance | B18: =0+B14-B17 -> 0 | C18: =B18+C14-C17 -> 0 | D18: =C18+D14-D17 -> 0 | E18: =D18+E14-E17 -> 0 | F18: =E18+F14-F17 -> 0 | G18: =F18+G14-G17 -> 0 | H18: =G18+H14-H17 -> 0 | I18: =H18+I14-I17 -> 0 | J18: =I18+J14-J17 -> 0 | ... AW18: =AV18+AW14-AW17 -> 0
A19: Distributions to equity | B19: =B16-B17 -> 0 | C19: =C16-C17 -> 0 | D19: =D16-D17 -> 0 | E19: =E16-E17 -> 0 | F19: =F16-F17 -> 0 | G19: =G16-G17 -> 0 | H19: =H16-H17 -> 0 | I19: =I16-I17 -> 0 | ... AW19: =AW16-AW17 -> 6305000
A20: Equity cash flow | B20: =B19-B12 -> -18644160 | C20: =C19-C12 -> 0 | D20: =D19-D12 -> 0 | E20: =E19-E12 -> -360342.5 | F20: =F19-F12 -> -1074862 | G20: =G19-G12 -> -1770990.2 | H20: =H19-H12 -> -2436815.5 | I20: =I19-I12 -> -3060947.2 | ... AW20: =AW19-AW12 -> 6305000
A21: Unlevered cash flow | B21: =B16-(B4+B5+B6+B7) -> -18000000 | C21: =C16-(C4+C5+C6+C7) -> 0 | D21: =D16-(D4+D5+D6+D7) -> 0 | E21: =E16-(E4+E5+E6+E7) -> -360342.5 | F21: =F16-(F4+F5+F6+F7) -> -1074862 | G21: =G16-(G4+G5+G6+G7) -> -1770990.2 | H21: =H16-(H4+H5+H6+H7) -> -2436815.5 | I21: =I16-(I4+I5+I6+I7) -> -3060947.2 | ... AW21: =AW16-(AW4+AW5+AW6+AW7) -> 6305000
A22: LP contribution | B22: =B12*Assumptions!$B$16 -> 16779744 | C22: =C12*Assumptions!$B$16 -> 0 | D22: =D12*Assumptions!$B$16 -> 0 | E22: =E12*Assumptions!$B$16 -> 324308.25 | F22: =F12*Assumptions!$B$16 -> 967375.77 | G22: =G12*Assumptions!$B$16 -> 1593891.1 | H22: =H12*Assumptions!$B$16 -> 2193134 | I22: =I12*Assumptions!$B$16 -> 2754852.5 | ... AW22: =AW12*Assumptions!$B$16 -> 0
A23: Tier 1 account (opening + growth) | B23: =0*(1+((1+Assumptions!$B$17)^(1/12)-1))+B22 -> 16779744 | C23: =B33*(1+((1+Assumptions!$B$17)^(1/12)-1))+C22 -> 16887705 | D23: =C33*(1+((1+Assumptions!$B$17)^(1/12)-1))+D22 -> 16996361 | E23: =D33*(1+((1+Assumptions!$B$17)^(1/12)-1))+E22 -> 17430025 | F23: =E33*(1+((1+Assumptions!$B$17)^(1/12)-1))+F22 -> 18509546 | G23: =F33*(1+((1+Assumptions!$B$17)^(1/12)-1))+G22 -> 20222528 | H23: =G33*(1+((1+Assumptions!$B$17)^(1/12)-1))+H22 -> 22545774 | I23: =H33*(1+((1+Assumptions!$B$17)^(1/12)-1))+I22 -> 25445687 | J23: =I33*(1+((1+Assumptions!$B$17)^(1/12)-1))+J22 -> 28878840 | ... AW23: =AV33*(1+((1+Assumptions!$B$17)^(1/12)-1))+AW22 -> 0
A24: Tier 1 distribution | B24: =MIN(B19,B23/Assumptions!$B$16) -> 0 | C24: =MIN(C19,C23/Assumptions!$B$16) -> 0 | D24: =MIN(D19,D23/Assumptions!$B$16) -> 0 | E24: =MIN(E19,E23/Assumptions!$B$16) -> 0 | F24: =MIN(F19,F23/Assumptions!$B$16) -> 0 | G24: =MIN(G19,G23/Assumptions!$B$16) -> 0 | H24: =MIN(H19,H23/Assumptions!$B$16) -> 0 | I24: =MIN(I19,I23/Assumptions!$B$16) -> 0 | ... AW24: =MIN(AW19,AW23/Assumptions!$B$16) -> 0
A25: LP tier 1 | B25: =B24*Assumptions!$B$16 -> 0 | C25: =C24*Assumptions!$B$16 -> 0 | D25: =D24*Assumptions!$B$16 -> 0 | E25: =E24*Assumptions!$B$16 -> 0 | F25: =F24*Assumptions!$B$16 -> 0 | G25: =G24*Assumptions!$B$16 -> 0 | H25: =H24*Assumptions!$B$16 -> 0 | I25: =I24*Assumptions!$B$16 -> 0 | ... AW25: =AW24*Assumptions!$B$16 -> 0
A26: Tier 2 account (opening + growth) | B26: =0*(1+((1+Assumptions!$B$18)^(1/12)-1))+B22 -> 16779744 | C26: =B34*(1+((1+Assumptions!$B$18)^(1/12)-1))+C22 -> 16976317 | D26: =C34*(1+((1+Assumptions!$B$18)^(1/12)-1))+D22 -> 17175193 | E26: =D34*(1+((1+Assumptions!$B$18)^(1/12)-1))+E22 -> 17700708 | F26: =E34*(1+((1+Assumptions!$B$18)^(1/12)-1))+F22 -> 18875446 | G26: =F34*(1+((1+Assumptions!$B$18)^(1/12)-1))+G22 -> 20690461 | H26: =G34*(1+((1+Assumptions!$B$18)^(1/12)-1))+H22 -> 23125982 | I26: =H34*(1+((1+Assumptions!$B$18)^(1/12)-1))+I22 -> 26151753 | J26: =I34*(1+((1+Assumptions!$B$18)^(1/12)-1))+J22 -> 29727554 | ... AW26: =AV34*(1+((1+Assumptions!$B$18)^(1/12)-1))+AW22 -> 0
A27: Tier 2 distribution | B27: =MIN(B19-B24,MAX(0,B26-B25)/Assumptions!$B$19) -> 0 | C27: =MIN(C19-C24,MAX(0,C26-C25)/Assumptions!$B$19) -> 0 | D27: =MIN(D19-D24,MAX(0,D26-D25)/Assumptions!$B$19) -> 0 | E27: =MIN(E19-E24,MAX(0,E26-E25)/Assumptions!$B$19) -> 0 | F27: =MIN(F19-F24,MAX(0,F26-F25)/Assumptions!$B$19) -> 0 | G27: =MIN(G19-G24,MAX(0,G26-G25)/Assumptions!$B$19) -> 0 | H27: =MIN(H19-H24,MAX(0,H26-H25)/Assumptions!$B$19) -> 0 | I27: =MIN(I19-I24,MAX(0,I26-I25)/Assumptions!$B$19) -> 0 | ... AW27: =MIN(AW19-AW24,MAX(0,AW26-AW25)/Assumptions!$B$19) -> 0
A28: LP tier 2 | B28: =B27*Assumptions!$B$19 -> 0 | C28: =C27*Assumptions!$B$19 -> 0 | D28: =D27*Assumptions!$B$19 -> 0 | E28: =E27*Assumptions!$B$19 -> 0 | F28: =F27*Assumptions!$B$19 -> 0 | G28: =G27*Assumptions!$B$19 -> 0 | H28: =H27*Assumptions!$B$19 -> 0 | I28: =I27*Assumptions!$B$19 -> 0 | ... AW28: =AW27*Assumptions!$B$19 -> 0
A29: Above tier 2 | B29: =B19-B24-B27 -> 0 | C29: =C19-C24-C27 -> 0 | D29: =D19-D24-D27 -> 0 | E29: =E19-E24-E27 -> 0 | F29: =F19-F24-F27 -> 0 | G29: =G19-G24-G27 -> 0 | H29: =H19-H24-H27 -> 0 | I29: =I19-I24-I27 -> 0 | ... AW29: =AW19-AW24-AW27 -> 6305000
A30: LP total | B30: =B25+B28+B29*Assumptions!$B$20 -> 0 | C30: =C25+C28+C29*Assumptions!$B$20 -> 0 | D30: =D25+D28+D29*Assumptions!$B$20 -> 0 | E30: =E25+E28+E29*Assumptions!$B$20 -> 0 | F30: =F25+F28+F29*Assumptions!$B$20 -> 0 | G30: =G25+G28+G29*Assumptions!$B$20 -> 0 | H30: =H25+H28+H29*Assumptions!$B$20 -> 0 | I30: =I25+I28+I29*Assumptions!$B$20 -> 0 | ... AW30: =AW25+AW28+AW29*Assumptions!$B$20 -> 3783000
A31: LP cash flow | B31: =B30-B22 -> -16779744 | C31: =C30-C22 -> 0 | D31: =D30-D22 -> 0 | E31: =E30-E22 -> -324308.25 | F31: =F30-F22 -> -967375.77 | G31: =G30-G22 -> -1593891.1 | H31: =H30-H22 -> -2193134 | I31: =I30-I22 -> -2754852.5 | ... AW31: =AW30-AW22 -> 3783000
A32: GP cash flow | B32: =B20-B31 -> -1864416 | C32: =C20-C31 -> 0 | D32: =D20-D31 -> 0 | E32: =E20-E31 -> -36034.25 | F32: =F20-F31 -> -107486.2 | G32: =G20-G31 -> -177099.02 | H32: =H20-H31 -> -243681.55 | I32: =I20-I31 -> -306094.72 | ... AW32: =AW20-AW31 -> 2522000
A33: Tier 1 account (closing) | B33: =B23-B25 -> 16779744 | C33: =C23-C25 -> 16887705 | D33: =D23-D25 -> 16996361 | E33: =E23-E25 -> 17430025 | F33: =F23-F25 -> 18509546 | G33: =G23-G25 -> 20222528 | H33: =H23-H25 -> 22545774 | I33: =I23-I25 -> 25445687 | ... AW33: =AW23-AW25 -> 0
A34: Tier 2 account (closing) | B34: =MAX(0,B26-B25-B28) -> 16779744 | C34: =MAX(0,C26-C25-C28) -> 16976317 | D34: =MAX(0,D26-D25-D28) -> 17175193 | E34: =MAX(0,E26-E25-E28) -> 17700708 | F34: =MAX(0,F26-F25-F28) -> 18875446 | G34: =MAX(0,G26-G25-G28) -> 20690461 | H34: =MAX(0,H26-H25-H28) -> 23125982 | I34: =MAX(0,I26-I25-I28) -> 26151753 | ... AW34: =MAX(0,AW26-AW25-AW28) -> 0
A35: Cumulative units sold | B35: =B15 -> 0 | C35: =B35+C15 -> 0 | D35: =C35+D15 -> 0 | E35: =D35+E15 -> 0 | F35: =E35+F15 -> 0 | G35: =F35+G15 -> 0 | H35: =G35+H15 -> 0 | I35: =H35+I15 -> 0 | J35: =I35+J15 -> 0 | ... AW35: =AV35+AW15 -> 240

Sheet Returns
A3: Unlevered IRR | B3: =(1+IRR('Cash Flow'!B21:AW21,0.01))^12-1 -> 0.22061411
A4: Levered IRR | B4: =(1+IRR('Cash Flow'!B20:AW20,0.01))^12-1 -> 0.26471928
A5: LP IRR | B5: =(1+IRR('Cash Flow'!B31:AW31,0.01))^12-1 -> 0.22270285
A6: GP IRR | B6: =(1+IRR('Cash Flow'!B32:AW32,0.01))^12-1 -> 0.53522582
A7: LP equity multiple | B7: =SUMIF('Cash Flow'!B31:AW31,">0")/-SUMIF('Cash Flow'!B31:AW31,"<0") -> 1.8123568
A8: Net profit | B8: =SUM('Cash Flow'!B20:AW20) -> 43960023
A9: Total development cost | B9: =SUM('Cash Flow'!B10:AW10) -> 1.0735998e+08
A10: Profit on cost | B10: =B8/B9 -> 0.40946379
A11: Peak debt | B11: =MAX('Cash Flow'!B18:AW18) -> 59036050
A12: GP promote ($) | B12: =SUM('Cash Flow'!B32:AW32)-(1-Assumptions!$B$16)*B8 -> 8166762.8
