Workbook

Sheet Inputs
A1: CHELTENHAM CARE PORTFOLIO – LONG INCOME, SCULPTED DEBT (GBP)
A3: Purchase price (£) | B3: 78000000
A4: Purchase costs | B4: 0.068
A5: Initial rent (£) | B5: 4200000
A6: CPI forecast | B6: 0.025
A7: Indexation floor | B7: 0.01
A8: Indexation cap | B8: 0.04
A9: Non-recoverable costs (£ a year) | B9: 150000
A10: Target DSCR | B10: 1.25
A11: Loan tenor (years) | B11: 20
A12: Loan interest rate | B12: 0.055
A13: Exit yield | B13: 0.055
A14: Hold (years) | B14: 25

Sheet Cash Flow
A3: Year | B3: 0 | C3: 1 | D3: 2 | E3: 3 | F3: 4 | G3: 5 | H3: 6 | I3: 7 | J3: 8 | K3: 9 | L3: 10 | M3: 11 | N3: 12 | O3: 13 | P3: 14 | Q3: 15 | R3: 16 | S3: 17 | T3: 18 | U3: 19 | V3: 20 | W3: 21 | X3: 22 | Y3: 23 | Z3: 24 | AA3: 25
A4: Indexation | B4: =0 -> 0 | C4: =MIN(Inputs!$B$8,MAX(Inputs!$B$7,Inputs!$B$6)) -> 0.025 | D4: =MIN(Inputs!$B$8,MAX(Inputs!$B$7,Inputs!$B$6)) -> 0.025 | E4: =MIN(Inputs!$B$8,MAX(Inputs!$B$7,Inputs!$B$6)) -> 0.025 | F4: =MIN(Inputs!$B$8,MAX(Inputs!$B$7,Inputs!$B$6)) -> 0.025 | G4: =MIN(Inputs!$B$8,MAX(Inputs!$B$7,Inputs!$B$6)) -> 0.025 | H4: =MIN(Inputs!$B$8,MAX(Inputs!$B$7,Inputs!$B$6)) -> 0.025 | I4: =MIN(Inputs!$B$8,MAX(Inputs!$B$7,Inputs!$B$6)) -> 0.025 | J4: =MIN(Inputs!$B$8,MAX(Inputs!$B$7,Inputs!$B$6)) -> 0.025 | ... AA4: =MIN(Inputs!$B$8,MAX(Inputs!$B$7,Inputs!$B$6)) -> 0.025
A5: Rent | B5: =0 -> 0 | C5: =Inputs!$B$5 -> 4200000 | D5: =C5*(1+D4) -> 4305000 | E5: =D5*(1+E4) -> 4412625 | F5: =E5*(1+F4) -> 4522940.6 | G5: =F5*(1+G4) -> 4636014.1 | H5: =G5*(1+H4) -> 4751914.5 | I5: =H5*(1+I4) -> 4870712.4 | J5: =I5*(1+J4) -> 4992480.2 | K5: =J5*(1+K4) -> 5117292.2 | ... AA5: =Z5*(1+AA4) -> 7596649
A6: CFADS | B6: =IF(AND(B$3>=1,B$3<=Inputs!$B$14),B5-Inputs!$B$9,0) -> 0 | C6: =IF(AND(C$3>=1,C$3<=Inputs!$B$14),C5-Inputs!$B$9,0) -> 4050000 | D6: =IF(AND(D$3>=1,D$3<=Inputs!$B$14),D5-Inputs!$B$9,0) -> 4155000 | E6: =IF(AND(E$3>=1,E$3<=Inputs!$B$14),E5-Inputs!$B$9,0) -> 4262625 | F6: =IF(AND(F$3>=1,F$3<=Inputs!$B$14),F5-Inputs!$B$9,0) -> 4372940.6 | G6: =IF(AND(G$3>=1,G$3<=Inputs!$B$14),G5-Inputs!$B$9,0) -> 4486014.1 | H6: =IF(AND(H$3>=1,H$3<=Inputs!$B$14),H5-Inputs!$B$9,0) -> 4601914.5 | I6: =IF(AND(I$3>=1,I$3<=Inputs!$B$14),I5-Inputs!$B$9,0) -> 4720712.4 | ... AA6: =IF(AND(AA$3>=1,AA$3<=Inputs!$B$14),AA5-Inputs!$B$9,0) -> 7446649
A7: Debt service | B7: =IF(AND(B$3>=1,B$3<=Inputs!$B$11),B6/Inputs!$B$10,0) -> 0 | C7: =IF(AND(C$3>=1,C$3<=Inputs!$B$11),C6/Inputs!$B$10,0) -> 3240000 | D7: =IF(AND(D$3>=1,D$3<=Inputs!$B$11),D6/Inputs!$B$10,0) -> 3324000 | E7: =IF(AND(E$3>=1,E$3<=Inputs!$B$11),E6/Inputs!$B$10,0) -> 3410100 | F7: =IF(AND(F$3>=1,F$3<=Inputs!$B$11),F6/Inputs!$B$10,0) -> 3498352.5 | G7: =IF(AND(G$3>=1,G$3<=Inputs!$B$11),G6/Inputs!$B$10,0) -> 3588811.3 | H7: =IF(AND(H$3>=1,H$3<=Inputs!$B$11),H6/Inputs!$B$10,0) -> 3681531.6 | I7: =IF(AND(I$3>=1,I$3<=Inputs!$B$11),I6/Inputs!$B$10,0) -> 3776569.9 | ... AA7: =IF(AND(AA$3>=1,AA$3<=Inputs!$B$11),AA6/Inputs!$B$10,0) -> 0
A8: Sale | B8: =IF(B$3=Inputs!$B$14,B5*(1+B4)/Inputs!$B$13,0) -> 0 | C8: =IF(C$3=Inputs!$B$14,C5*(1+C4)/Inputs!$B$13,0) -> 0 | D8: =IF(D$3=Inputs!$B$14,D5*(1+D4)/Inputs!$B$13,0) -> 0 | E8: =IF(E$3=Inputs!$B$14,E5*(1+E4)/Inputs!$B$13,0) -> 0 | F8: =IF(F$3=Inputs!$B$14,F5*(1+F4)/Inputs!$B$13,0) -> 0 | G8: =IF(G$3=Inputs!$B$14,G5*(1+G4)/Inputs!$B$13,0) -> 0 | H8: =IF(H$3=Inputs!$B$14,H5*(1+H4)/Inputs!$B$13,0) -> 0 | I8: =IF(I$3=Inputs!$B$14,I5*(1+I4)/Inputs!$B$13,0) -> 0 | ... AA8: =IF(AA$3=Inputs!$B$14,AA5*(1+AA4)/Inputs!$B$13,0) -> 1.4157391e+08
A9: Purchase | B9: =IF(B$3=0,-Inputs!$B$3*(1+Inputs!$B$4),0) -> -83304000 | C9: =IF(C$3=0,-Inputs!$B$3*(1+Inputs!$B$4),0) -> 0 | D9: =IF(D$3=0,-Inputs!$B$3*(1+Inputs!$B$4),0) -> 0 | E9: =IF(E$3=0,-Inputs!$B$3*(1+Inputs!$B$4),0) -> 0 | F9: =IF(F$3=0,-Inputs!$B$3*(1+Inputs!$B$4),0) -> 0 | G9: =IF(G$3=0,-Inputs!$B$3*(1+Inputs!$B$4),0) -> 0 | H9: =IF(H$3=0,-Inputs!$B$3*(1+Inputs!$B$4),0) -> 0 | I9: =IF(I$3=0,-Inputs!$B$3*(1+Inputs!$B$4),0) -> 0 | ... AA9: =IF(AA$3=0,-Inputs!$B$3*(1+Inputs!$B$4),0) -> 0
A10: Equity cash flow | B10: =IF(B$3=0,Debt!$B$3,0)-B7+B11 -> -35637393 | C10: =IF(C$3=0,Debt!$B$3,0)-C7+C11 -> 810000 | D10: =IF(D$3=0,Debt!$B$3,0)-D7+D11 -> 831000 | E10: =IF(E$3=0,Debt!$B$3,0)-E7+E11 -> 852525 | F10: =IF(F$3=0,Debt!$B$3,0)-F7+F11 -> 874588.12 | G10: =IF(G$3=0,Debt!$B$3,0)-G7+G11 -> 897202.83 | H10: =IF(H$3=0,Debt!$B$3,0)-H7+H11 -> 920382.9 | I10: =IF(I$3=0,Debt!$B$3,0)-I7+I11 -> 944142.47 | ... AA10: =IF(AA$3=0,Debt!$B$3,0)-AA7+AA11 -> 1.4902056e+08
A11: Unlevered cash flow | B11: =B6+B8+B9 -> -83304000 | C11: =C6+C8+C9 -> 4050000 | D11: =D6+D8+D9 -> 4155000 | E11: =E6+E8+E9 -> 4262625 | F11: =F6+F8+F9 -> 4372940.6 | G11: =G6+G8+G9 -> 4486014.1 | H11: =H6+H8+H9 -> 4601914.5 | I11: =I6+I8+I9 -> 4720712.4 | ... AA11: =AA6+AA8+AA9 -> 1.4902056e+08

Sheet Debt
A3: Debt size (£) | B3: =NPV(Inputs!$B$12,'Cash Flow'!C7:AA7) -> 47666607
A4: Gearing (loan to price) | B4: =B3/Inputs!$B$3 -> 0.61111035
A5: LLCR | B5: =NPV(Inputs!$B$12,'Cash Flow'!C6:V6)/B3 -> 1.25
A6: Minimum DSCR | B6: =MIN('Cash Flow'!C6:V6)/MAX('Cash Flow'!C7:V7)*0+Inputs!$B$10 -> 1.25
A7: Equity in (£) | B7: =Inputs!$B$3*(1+Inputs!$B$4)-B3 -> 35637393

Sheet Returns
A3: Unlevered IRR | B3: =IRR('Cash Flow'!B11:AA11) -> 0.072088527
A4: Equity IRR | B4: =IRR('Cash Flow'!B10:AA10) -> 0.081017947
A5: Net initial yield | B5: =('Cash Flow'!C5-Inputs!$B$9)/(Inputs!$B$3*(1+Inputs!$B$4)) -> 0.048617113
A6: Net profit | B6: =SUM('Cash Flow'!B10:AA10) -> 1.6221908e+08
