Workbook

Sheet Portfolio
A1: IBERIA HOTEL PORTFOLIO (EUR)
A3: Loan to value | B3: 0.55
A4: Interest rate | B4: 0.048
A5: Exit cap rate | B5: 0.07
A6: Hold (years) | B6: 5
A7: Acquisition costs | B7: 0.045

Sheet Lisbon
A1: LISBON HOTEL
A3: Keys | B3: 180
A4: ADR (€) | B4: 185
A5: Occupancy | B5: 0.78
A6: ADR growth | B6: 0.03
A7: F&B and other (% of rooms) | B7: 0.35
A8: GOP margin | B8: 0.36
A9: FF&E reserve | B9: 0.04
A10: Purchase price (€) | B10: 62000000
A13: Rooms revenue (year 1) | B13: =Lisbon!$B$3*365*Lisbon!$B$4*Lisbon!$B$5 -> 9480510
A14: Total revenue (year 1) | B14: =B13*(1+Lisbon!$B$7) -> 12798688
A15: EBITDA after FF&E (year 1) | B15: =B14*(Lisbon!$B$8-Lisbon!$B$9) -> 4095580.3

Sheet Porto
A1: PORTO HOTEL
A3: Keys | B3: 140
A4: ADR (€) | B4: 150
A5: Occupancy | B5: 0.74
A6: ADR growth | B6: 0.03
A7: F&B and other (% of rooms) | B7: 0.35
A8: GOP margin | B8: 0.34
A9: FF&E reserve | B9: 0.04
A10: Purchase price (€) | B10: 41000000
A13: Rooms revenue (year 1) | B13: =Porto!$B$3*365*Porto!$B$4*Porto!$B$5 -> 5672100
A14: Total revenue (year 1) | B14: =B13*(1+Porto!$B$7) -> 7657335
A15: EBITDA after FF&E (year 1) | B15: =B14*(Porto!$B$8-Porto!$B$9) -> 2297200.5

Sheet Madrid
A1: MADRID HOTEL
A3: Keys | B3: 220
A4: ADR (€) | B4: 170
A5: Occupancy | B5: 0.8
A6: ADR growth | B6: 0.03
A7: F&B and other (% of rooms) | B7: 0.35
A8: GOP margin | B8: 0.38
A9: FF&E reserve | B9: 0.04
A10: Purchase price (€) | B10: 88000000
A13: Rooms revenue (year 1) | B13: =Madrid!$B$3*365*Madrid!$B$4*Madrid!$B$5 -> 10920800
A14: Total revenue (year 1) | B14: =B13*(1+Madrid!$B$7) -> 14743080
A15: EBITDA after FF&E (year 1) | B15: =B14*(Madrid!$B$8-Madrid!$B$9) -> 5012647.2

Sheet Consolidated
A3: Year | B3: 0 | C3: 1 | D3: 2 | E3: 3 | F3: 4 | G3: 5 | H3: 6 | I3: 7
A4: EBITDA | B4: =(B$3>=1)*(B$3<=Portfolio!$B$6)*(Lisbon!$B$15*(1+Lisbon!$B$6)^(B$3-1)+Porto!$B$15*(1+Porto!$B$6)^(B$3-1)+Madrid!$B$15*(1+Madrid!$B$6)^(B$3-1)) -> 0 | C4: =(C$3>=1)*(C$3<=Portfolio!$B$6)*(Lisbon!$B$15*(1+Lisbon!$B$6)^(C$3-1)+Porto!$B$15*(1+Porto!$B$6)^(C$3-1)+Madrid!$B$15*(1+Madrid!$B$6)^(C$3-1)) -> 11405428 | D4: =(D$3>=1)*(D$3<=Portfolio!$B$6)*(Lisbon!$B$15*(1+Lisbon!$B$6)^(D$3-1)+Porto!$B$15*(1+Porto!$B$6)^(D$3-1)+Madrid!$B$15*(1+Madrid!$B$6)^(D$3-1)) -> 11747591 | E4: =(E$3>=1)*(E$3<=Portfolio!$B$6)*(Lisbon!$B$15*(1+Lisbon!$B$6)^(E$3-1)+Porto!$B$15*(1+Porto!$B$6)^(E$3-1)+Madrid!$B$15*(1+Madrid!$B$6)^(E$3-1)) -> 12100019 | F4: =(F$3>=1)*(F$3<=Portfolio!$B$6)*(Lisbon!$B$15*(1+Lisbon!$B$6)^(F$3-1)+Porto!$B$15*(1+Porto!$B$6)^(F$3-1)+Madrid!$B$15*(1+Madrid!$B$6)^(F$3-1)) -> 12463019 | G4: =(G$3>=1)*(G$3<=Portfolio!$B$6)*(Lisbon!$B$15*(1+Lisbon!$B$6)^(G$3-1)+Porto!$B$15*(1+Porto!$B$6)^(G$3-1)+Madrid!$B$15*(1+Madrid!$B$6)^(G$3-1)) -> 12836910 | H4: =(H$3>=1)*(H$3<=Portfolio!$B$6)*(Lisbon!$B$15*(1+Lisbon!$B$6)^(H$3-1)+Porto!$B$15*(1+Porto!$B$6)^(H$3-1)+Madrid!$B$15*(1+Madrid!$B$6)^(H$3-1)) -> 0 | I4: =(I$3>=1)*(I$3<=Portfolio!$B$6)*(Lisbon!$B$15*(1+Lisbon!$B$6)^(I$3-1)+Porto!$B$15*(1+Porto!$B$6)^(I$3-1)+Madrid!$B$15*(1+Madrid!$B$6)^(I$3-1)) -> 0
A5: Purchase | B5: =IF(B$3=0,-(Lisbon!$B$10+Porto!$B$10+Madrid!$B$10)*(1+Portfolio!$B$7),0) -> -199595000 | C5: =IF(C$3=0,-(Lisbon!$B$10+Porto!$B$10+Madrid!$B$10)*(1+Portfolio!$B$7),0) -> 0 | D5: =IF(D$3=0,-(Lisbon!$B$10+Porto!$B$10+Madrid!$B$10)*(1+Portfolio!$B$7),0) -> 0 | E5: =IF(E$3=0,-(Lisbon!$B$10+Porto!$B$10+Madrid!$B$10)*(1+Portfolio!$B$7),0) -> 0 | F5: =IF(F$3=0,-(Lisbon!$B$10+Porto!$B$10+Madrid!$B$10)*(1+Portfolio!$B$7),0) -> 0 | G5: =IF(G$3=0,-(Lisbon!$B$10+Porto!$B$10+Madrid!$B$10)*(1+Portfolio!$B$7),0) -> 0 | H5: =IF(H$3=0,-(Lisbon!$B$10+Porto!$B$10+Madrid!$B$10)*(1+Portfolio!$B$7),0) -> 0 | I5: =IF(I$3=0,-(Lisbon!$B$10+Porto!$B$10+Madrid!$B$10)*(1+Portfolio!$B$7),0) -> 0
A6: Sale | B6: =IF(B$3=Portfolio!$B$6,(Lisbon!$B$15*(1+Lisbon!$B$6)^B$3+Porto!$B$15*(1+Porto!$B$6)^B$3+Madrid!$B$15*(1+Madrid!$B$6)^B$3)/Portfolio!$B$5,0) -> 0 | C6: =IF(C$3=Portfolio!$B$6,(Lisbon!$B$15*(1+Lisbon!$B$6)^C$3+Porto!$B$15*(1+Porto!$B$6)^C$3+Madrid!$B$15*(1+Madrid!$B$6)^C$3)/Portfolio!$B$5,0) -> 0 | D6: =IF(D$3=Portfolio!$B$6,(Lisbon!$B$15*(1+Lisbon!$B$6)^D$3+Porto!$B$15*(1+Porto!$B$6)^D$3+Madrid!$B$15*(1+Madrid!$B$6)^D$3)/Portfolio!$B$5,0) -> 0 | E6: =IF(E$3=Portfolio!$B$6,(Lisbon!$B$15*(1+Lisbon!$B$6)^E$3+Porto!$B$15*(1+Porto!$B$6)^E$3+Madrid!$B$15*(1+Madrid!$B$6)^E$3)/Portfolio!$B$5,0) -> 0 | F6: =IF(F$3=Portfolio!$B$6,(Lisbon!$B$15*(1+Lisbon!$B$6)^F$3+Porto!$B$15*(1+Porto!$B$6)^F$3+Madrid!$B$15*(1+Madrid!$B$6)^F$3)/Portfolio!$B$5,0) -> 0 | G6: =IF(G$3=Portfolio!$B$6,(Lisbon!$B$15*(1+Lisbon!$B$6)^G$3+Porto!$B$15*(1+Porto!$B$6)^G$3+Madrid!$B$15*(1+Madrid!$B$6)^G$3)/Portfolio!$B$5,0) -> 1.8888596e+08 | H6: =IF(H$3=Portfolio!$B$6,(Lisbon!$B$15*(1+Lisbon!$B$6)^H$3+Porto!$B$15*(1+Porto!$B$6)^H$3+Madrid!$B$15*(1+Madrid!$B$6)^H$3)/Portfolio!$B$5,0) -> 0 | I6: =IF(I$3=Portfolio!$B$6,(Lisbon!$B$15*(1+Lisbon!$B$6)^I$3+Porto!$B$15*(1+Porto!$B$6)^I$3+Madrid!$B$15*(1+Madrid!$B$6)^I$3)/Portfolio!$B$5,0) -> 0
A7: Unlevered cash flow | B7: =SUM(B4:B6) -> -199595000 | C7: =SUM(C4:C6) -> 11405428 | D7: =SUM(D4:D6) -> 11747591 | E7: =SUM(E4:E6) -> 12100019 | F7: =SUM(F4:F6) -> 12463019 | G7: =SUM(G4:G6) -> 2.0172287e+08 | H7: =SUM(H4:H6) -> 0 | I7: =SUM(I4:I6) -> 0
A8: Debt | B8: =IF(B$3=0,(Lisbon!$B$10+Porto!$B$10+Madrid!$B$10)*Portfolio!$B$3,0)-IF(B$3=Portfolio!$B$6,(Lisbon!$B$10+Porto!$B$10+Madrid!$B$10)*Portfolio!$B$3,0) -> 105050000 | C8: =IF(C$3=0,(Lisbon!$B$10+Porto!$B$10+Madrid!$B$10)*Portfolio!$B$3,0)-IF(C$3=Portfolio!$B$6,(Lisbon!$B$10+Porto!$B$10+Madrid!$B$10)*Portfolio!$B$3,0) -> 0 | D8: =IF(D$3=0,(Lisbon!$B$10+Porto!$B$10+Madrid!$B$10)*Portfolio!$B$3,0)-IF(D$3=Portfolio!$B$6,(Lisbon!$B$10+Porto!$B$10+Madrid!$B$10)*Portfolio!$B$3,0) -> 0 | E8: =IF(E$3=0,(Lisbon!$B$10+Porto!$B$10+Madrid!$B$10)*Portfolio!$B$3,0)-IF(E$3=Portfolio!$B$6,(Lisbon!$B$10+Porto!$B$10+Madrid!$B$10)*Portfolio!$B$3,0) -> 0 | F8: =IF(F$3=0,(Lisbon!$B$10+Porto!$B$10+Madrid!$B$10)*Portfolio!$B$3,0)-IF(F$3=Portfolio!$B$6,(Lisbon!$B$10+Porto!$B$10+Madrid!$B$10)*Portfolio!$B$3,0) -> 0 | G8: =IF(G$3=0,(Lisbon!$B$10+Porto!$B$10+Madrid!$B$10)*Portfolio!$B$3,0)-IF(G$3=Portfolio!$B$6,(Lisbon!$B$10+Porto!$B$10+Madrid!$B$10)*Portfolio!$B$3,0) -> -105050000 | H8: =IF(H$3=0,(Lisbon!$B$10+Porto!$B$10+Madrid!$B$10)*Portfolio!$B$3,0)-IF(H$3=Portfolio!$B$6,(Lisbon!$B$10+Porto!$B$10+Madrid!$B$10)*Portfolio!$B$3,0) -> 0 | I8: =IF(I$3=0,(Lisbon!$B$10+Porto!$B$10+Madrid!$B$10)*Portfolio!$B$3,0)-IF(I$3=Portfolio!$B$6,(Lisbon!$B$10+Porto!$B$10+Madrid!$B$10)*Portfolio!$B$3,0) -> 0
A9: Interest | B9: =-(B$3>=1)*(B$3<=Portfolio!$B$6)*(Lisbon!$B$10+Porto!$B$10+Madrid!$B$10)*Portfolio!$B$3*Portfolio!$B$4 -> 0 | C9: =-(C$3>=1)*(C$3<=Portfolio!$B$6)*(Lisbon!$B$10+Porto!$B$10+Madrid!$B$10)*Portfolio!$B$3*Portfolio!$B$4 -> -5042400 | D9: =-(D$3>=1)*(D$3<=Portfolio!$B$6)*(Lisbon!$B$10+Porto!$B$10+Madrid!$B$10)*Portfolio!$B$3*Portfolio!$B$4 -> -5042400 | E9: =-(E$3>=1)*(E$3<=Portfolio!$B$6)*(Lisbon!$B$10+Porto!$B$10+Madrid!$B$10)*Portfolio!$B$3*Portfolio!$B$4 -> -5042400 | F9: =-(F$3>=1)*(F$3<=Portfolio!$B$6)*(Lisbon!$B$10+Porto!$B$10+Madrid!$B$10)*Portfolio!$B$3*Portfolio!$B$4 -> -5042400 | G9: =-(G$3>=1)*(G$3<=Portfolio!$B$6)*(Lisbon!$B$10+Porto!$B$10+Madrid!$B$10)*Portfolio!$B$3*Portfolio!$B$4 -> -5042400 | H9: =-(H$3>=1)*(H$3<=Portfolio!$B$6)*(Lisbon!$B$10+Porto!$B$10+Madrid!$B$10)*Portfolio!$B$3*Portfolio!$B$4 -> 0 | I9: =-(I$3>=1)*(I$3<=Portfolio!$B$6)*(Lisbon!$B$10+Porto!$B$10+Madrid!$B$10)*Portfolio!$B$3*Portfolio!$B$4 -> 0
A10: Equity cash flow | B10: =B7+B8+B9 -> -94545000 | C10: =C7+C8+C9 -> 6363028 | D10: =D7+D8+D9 -> 6705190.9 | E10: =E7+E8+E9 -> 7057618.6 | F10: =F7+F8+F9 -> 7420619.1 | G10: =G7+G8+G9 -> 91630467 | H10: =H7+H8+H9 -> 0 | I10: =I7+I8+I9 -> 0

Sheet Returns
A3: Unlevered IRR | B3: =IRR(Consolidated!B7:I7) -> 0.050804011
A4: Levered IRR | B4: =IRR(Consolidated!B10:I10) -> 0.054027854
A5: Equity multiple | B5: =SUMIF(Consolidated!B10:I10,">0")/-SUMIF(Consolidated!B10:I10,"<0") -> 1.2605312
A6: Net profit | B6: =SUM(Consolidated!B10:I10) -> 24631924
A7: Year 1 debt yield | B7: =Consolidated!C4/((Lisbon!$B$10+Porto!$B$10+Madrid!$B$10)*Portfolio!$B$3) -> 0.10857142
A8: Year 1 interest cover | B8: =-Consolidated!C4/Consolidated!C9 -> 2.2619047
