Workbook

Sheet Fund
A1: EUROPA VALUE-ADD FUND II – FUND MODEL (EUR)
A3: Commitments (€) | B3: 500000000
A4: First close | B4: 45747
A5: Investment period ends | B5: 46843
A6: Management fee on commitments (investment period) | B6: 0.015
A7: Management fee on invested cost (after) | B7: 0.0125
A8: Fund expenses a year (% of commitments) | B8: 0.002
A9: Capital call lag on the subscription line (quarters) | B9: 2
A10: Subscription line rate | B10: 0.055
A11: Preferred return | B11: 0.08
A12: Carried interest | B12: 0.2
A13: GP commitment | B13: 0.02

Sheet Deals
A1: Deal | B1: Acquisition date | C1: Equity (€) | D1: Exit date | E1: Gross multiple
A2: Milan offices | B2: 45838 | C2: 95000000 | D2: 47483 | E2: 1.75
A3: Lyon logistics | B3: 46022 | C3: 70000000 | D3: 47299 | E3: 1.9
A4: Madrid resi | B4: 46295 | C4: 85000000 | D4: 47756 | E4: 1.6
A5: Warsaw retail park | B5: 46477 | C5: 60000000 | D5: 47573 | E5: 1.45
A6: Lisbon hotel | B6: 46752 | C6: 90000000 | D6: 48029 | E6: 2.1

Sheet Cash Flow
A3: Quarter | B3: 0 | C3: 1 | D3: 2 | E3: 3 | F3: 4 | G3: 5 | H3: 6 | I3: 7 | J3: 8 | K3: 9 | L3: 10 | M3: 11 | N3: 12 | O3: 13 | P3: 14 | Q3: 15 | R3: 16 | S3: 17 | T3: 18 | U3: 19 | V3: 20 | W3: 21 | X3: 22 | Y3: 23 | Z3: 24 | AA3: 25 | AB3: 26 | AC3: 27 | AD3: 28
A4: Date | B4: =EOMONTH(Fund!$B$4,3*B$3) -> 45747 | C4: =EOMONTH(Fund!$B$4,3*C$3) -> 45838 | D4: =EOMONTH(Fund!$B$4,3*D$3) -> 45930 | E4: =EOMONTH(Fund!$B$4,3*E$3) -> 46022 | F4: =EOMONTH(Fund!$B$4,3*F$3) -> 46112 | G4: =EOMONTH(Fund!$B$4,3*G$3) -> 46203 | H4: =EOMONTH(Fund!$B$4,3*H$3) -> 46295 | I4: =EOMONTH(Fund!$B$4,3*I$3) -> 46387 | ... AD4: =EOMONTH(Fund!$B$4,3*AD$3) -> 48304
A5: Deal equity | B5: =SUMPRODUCT((Deals!$B$2:$B$6>(B4-1))*(Deals!$B$2:$B$6<=B4)*Deals!$C$2:$C$6) -> 0 | C5: =SUMPRODUCT((Deals!$B$2:$B$6>B4)*(Deals!$B$2:$B$6<=C4)*Deals!$C$2:$C$6) -> 95000000 | D5: =SUMPRODUCT((Deals!$B$2:$B$6>C4)*(Deals!$B$2:$B$6<=D4)*Deals!$C$2:$C$6) -> 0 | E5: =SUMPRODUCT((Deals!$B$2:$B$6>D4)*(Deals!$B$2:$B$6<=E4)*Deals!$C$2:$C$6) -> 70000000 | F5: =SUMPRODUCT((Deals!$B$2:$B$6>E4)*(Deals!$B$2:$B$6<=F4)*Deals!$C$2:$C$6) -> 0 | G5: =SUMPRODUCT((Deals!$B$2:$B$6>F4)*(Deals!$B$2:$B$6<=G4)*Deals!$C$2:$C$6) -> 0 | H5: =SUMPRODUCT((Deals!$B$2:$B$6>G4)*(Deals!$B$2:$B$6<=H4)*Deals!$C$2:$C$6) -> 85000000 | I5: =SUMPRODUCT((Deals!$B$2:$B$6>H4)*(Deals!$B$2:$B$6<=I4)*Deals!$C$2:$C$6) -> 0 | J5: =SUMPRODUCT((Deals!$B$2:$B$6>I4)*(Deals!$B$2:$B$6<=J4)*Deals!$C$2:$C$6) -> 60000000 | ... AD5: =SUMPRODUCT((Deals!$B$2:$B$6>AC4)*(Deals!$B$2:$B$6<=AD4)*Deals!$C$2:$C$6) -> 0
A6: Deal proceeds | B6: =SUMPRODUCT((Deals!$D$2:$D$6>(B4-1))*(Deals!$D$2:$D$6<=B4)*Deals!$C$2:$C$6*Deals!$E$2:$E$6) -> 0 | C6: =SUMPRODUCT((Deals!$D$2:$D$6>B4)*(Deals!$D$2:$D$6<=C4)*Deals!$C$2:$C$6*Deals!$E$2:$E$6) -> 0 | D6: =SUMPRODUCT((Deals!$D$2:$D$6>C4)*(Deals!$D$2:$D$6<=D4)*Deals!$C$2:$C$6*Deals!$E$2:$E$6) -> 0 | E6: =SUMPRODUCT((Deals!$D$2:$D$6>D4)*(Deals!$D$2:$D$6<=E4)*Deals!$C$2:$C$6*Deals!$E$2:$E$6) -> 0 | F6: =SUMPRODUCT((Deals!$D$2:$D$6>E4)*(Deals!$D$2:$D$6<=F4)*Deals!$C$2:$C$6*Deals!$E$2:$E$6) -> 0 | G6: =SUMPRODUCT((Deals!$D$2:$D$6>F4)*(Deals!$D$2:$D$6<=G4)*Deals!$C$2:$C$6*Deals!$E$2:$E$6) -> 0 | H6: =SUMPRODUCT((Deals!$D$2:$D$6>G4)*(Deals!$D$2:$D$6<=H4)*Deals!$C$2:$C$6*Deals!$E$2:$E$6) -> 0 | I6: =SUMPRODUCT((Deals!$D$2:$D$6>H4)*(Deals!$D$2:$D$6<=I4)*Deals!$C$2:$C$6*Deals!$E$2:$E$6) -> 0 | J6: =SUMPRODUCT((Deals!$D$2:$D$6>I4)*(Deals!$D$2:$D$6<=J4)*Deals!$C$2:$C$6*Deals!$E$2:$E$6) -> 0 | ... AD6: =SUMPRODUCT((Deals!$D$2:$D$6>AC4)*(Deals!$D$2:$D$6<=AD4)*Deals!$C$2:$C$6*Deals!$E$2:$E$6) -> 0
A7: Invested cost | B7: =SUMPRODUCT((Deals!$B$2:$B$6<=B4)*(Deals!$D$2:$D$6>B4)*Deals!$C$2:$C$6) -> 0 | C7: =SUMPRODUCT((Deals!$B$2:$B$6<=C4)*(Deals!$D$2:$D$6>C4)*Deals!$C$2:$C$6) -> 95000000 | D7: =SUMPRODUCT((Deals!$B$2:$B$6<=D4)*(Deals!$D$2:$D$6>D4)*Deals!$C$2:$C$6) -> 95000000 | E7: =SUMPRODUCT((Deals!$B$2:$B$6<=E4)*(Deals!$D$2:$D$6>E4)*Deals!$C$2:$C$6) -> 165000000 | F7: =SUMPRODUCT((Deals!$B$2:$B$6<=F4)*(Deals!$D$2:$D$6>F4)*Deals!$C$2:$C$6) -> 165000000 | G7: =SUMPRODUCT((Deals!$B$2:$B$6<=G4)*(Deals!$D$2:$D$6>G4)*Deals!$C$2:$C$6) -> 165000000 | H7: =SUMPRODUCT((Deals!$B$2:$B$6<=H4)*(Deals!$D$2:$D$6>H4)*Deals!$C$2:$C$6) -> 250000000 | I7: =SUMPRODUCT((Deals!$B$2:$B$6<=I4)*(Deals!$D$2:$D$6>I4)*Deals!$C$2:$C$6) -> 250000000 | ... AD7: =SUMPRODUCT((Deals!$B$2:$B$6<=AD4)*(Deals!$D$2:$D$6>AD4)*Deals!$C$2:$C$6) -> 0
A8: Management fee | B8: =IF(B4<=Fund!$B$5,Fund!$B$3*Fund!$B$6,B7*Fund!$B$7)/4 -> 1875000 | C8: =IF(C4<=Fund!$B$5,Fund!$B$3*Fund!$B$6,C7*Fund!$B$7)/4 -> 1875000 | D8: =IF(D4<=Fund!$B$5,Fund!$B$3*Fund!$B$6,D7*Fund!$B$7)/4 -> 1875000 | E8: =IF(E4<=Fund!$B$5,Fund!$B$3*Fund!$B$6,E7*Fund!$B$7)/4 -> 1875000 | F8: =IF(F4<=Fund!$B$5,Fund!$B$3*Fund!$B$6,F7*Fund!$B$7)/4 -> 1875000 | G8: =IF(G4<=Fund!$B$5,Fund!$B$3*Fund!$B$6,G7*Fund!$B$7)/4 -> 1875000 | H8: =IF(H4<=Fund!$B$5,Fund!$B$3*Fund!$B$6,H7*Fund!$B$7)/4 -> 1875000 | I8: =IF(I4<=Fund!$B$5,Fund!$B$3*Fund!$B$6,I7*Fund!$B$7)/4 -> 1875000 | ... AD8: =IF(AD4<=Fund!$B$5,Fund!$B$3*Fund!$B$6,AD7*Fund!$B$7)/4 -> 0
A9: Fund expenses | B9: =Fund!$B$3*Fund!$B$8/4 -> 250000 | C9: =Fund!$B$3*Fund!$B$8/4 -> 250000 | D9: =Fund!$B$3*Fund!$B$8/4 -> 250000 | E9: =Fund!$B$3*Fund!$B$8/4 -> 250000 | F9: =Fund!$B$3*Fund!$B$8/4 -> 250000 | G9: =Fund!$B$3*Fund!$B$8/4 -> 250000 | H9: =Fund!$B$3*Fund!$B$8/4 -> 250000 | I9: =Fund!$B$3*Fund!$B$8/4 -> 250000 | ... AD9: =Fund!$B$3*Fund!$B$8/4 -> 250000
A10: Sub line drawn | B10: =B5 -> 0 | C10: =C5 -> 95000000 | D10: =D5 -> 0 | E10: =E5 -> 70000000 | F10: =F5 -> 0 | G10: =G5 -> 0 | H10: =H5 -> 85000000 | I10: =I5 -> 0 | ... AD10: =AD5 -> 0
A11: Capital called | B11: =IF(B$3>=Fund!$B$9,OFFSET(B10,0,-Fund!$B$9),0)+B8+B9+B12 -> 2125000 | C11: =IF(C$3>=Fund!$B$9,OFFSET(C10,0,-Fund!$B$9),0)+C8+C9+C12 -> 2125000 | D11: =IF(D$3>=Fund!$B$9,OFFSET(D10,0,-Fund!$B$9),0)+D8+D9+D12 -> 3431250 | E11: =IF(E$3>=Fund!$B$9,OFFSET(E10,0,-Fund!$B$9),0)+E8+E9+E12 -> 98431250 | F11: =IF(F$3>=Fund!$B$9,OFFSET(F10,0,-Fund!$B$9),0)+F8+F9+F12 -> 3087500 | G11: =IF(G$3>=Fund!$B$9,OFFSET(G10,0,-Fund!$B$9),0)+G8+G9+G12 -> 73087500 | H11: =IF(H$3>=Fund!$B$9,OFFSET(H10,0,-Fund!$B$9),0)+H8+H9+H12 -> 2125000 | I11: =IF(I$3>=Fund!$B$9,OFFSET(I10,0,-Fund!$B$9),0)+I8+I9+I12 -> 3293750 | ... AD11: =IF(AD$3>=Fund!$B$9,OFFSET(AD10,0,-Fund!$B$9),0)+AD8+AD9+AD12 -> 250000
A12: Sub line interest | B12: =0 -> 0 | C12: =B13*Fund!$B$10/4 -> 0 | D12: =C13*Fund!$B$10/4 -> 1306250 | E12: =D13*Fund!$B$10/4 -> 1306250 | F12: =E13*Fund!$B$10/4 -> 962500 | G12: =F13*Fund!$B$10/4 -> 962500 | H12: =G13*Fund!$B$10/4 -> 0 | I12: =H13*Fund!$B$10/4 -> 1168750 | J12: =I13*Fund!$B$10/4 -> 1168750 | ... AD12: =AC13*Fund!$B$10/4 -> 0
A13: Sub line balance | B13: =B10-IF(B$3>=Fund!$B$9,OFFSET(B10,0,-Fund!$B$9),0) -> 0 | C13: =B13+C10-IF(C$3>=Fund!$B$9,OFFSET(C10,0,-Fund!$B$9),0) -> 95000000 | D13: =C13+D10-IF(D$3>=Fund!$B$9,OFFSET(D10,0,-Fund!$B$9),0) -> 95000000 | E13: =D13+E10-IF(E$3>=Fund!$B$9,OFFSET(E10,0,-Fund!$B$9),0) -> 70000000 | F13: =E13+F10-IF(F$3>=Fund!$B$9,OFFSET(F10,0,-Fund!$B$9),0) -> 70000000 | G13: =F13+G10-IF(G$3>=Fund!$B$9,OFFSET(G10,0,-Fund!$B$9),0) -> 0 | H13: =G13+H10-IF(H$3>=Fund!$B$9,OFFSET(H10,0,-Fund!$B$9),0) -> 85000000 | I13: =H13+I10-IF(I$3>=Fund!$B$9,OFFSET(I10,0,-Fund!$B$9),0) -> 85000000 | J13: =I13+J10-IF(J$3>=Fund!$B$9,OFFSET(J10,0,-Fund!$B$9),0) -> 60000000 | ... AD13: =AC13+AD10-IF(AD$3>=Fund!$B$9,OFFSET(AD10,0,-Fund!$B$9),0) -> 0
A14: Contributions | B14: =B11 -> 2125000 | C14: =C11 -> 2125000 | D14: =D11 -> 3431250 | E14: =E11 -> 98431250 | F14: =F11 -> 3087500 | G14: =G11 -> 73087500 | H14: =H11 -> 2125000 | I14: =I11 -> 3293750 | ... AD14: =AD11 -> 250000
A15: Distributable | B15: =B6 -> 0 | C15: =C6 -> 0 | D15: =D6 -> 0 | E15: =E6 -> 0 | F15: =F6 -> 0 | G15: =G6 -> 0 | H15: =H6 -> 0 | I15: =I6 -> 0 | ... AD15: =AD6 -> 0
A16: LP contributions | B16: =B14 -> 2125000 | C16: =C14 -> 2125000 | D16: =D14 -> 3431250 | E16: =E14 -> 98431250 | F16: =F14 -> 3087500 | G16: =G14 -> 73087500 | H16: =H14 -> 2125000 | I16: =I14 -> 3293750 | ... AD16: =AD14 -> 250000
A17: ROC account | B17: =B14 -> 2125000 | C17: =B17-B18+C14 -> 4250000 | D17: =C17-C18+D14 -> 7681250 | E17: =D17-D18+E14 -> 106112500 | F17: =E17-E18+F14 -> 109200000 | G17: =F17-F18+G14 -> 182287500 | H17: =G17-G18+H14 -> 184412500 | I17: =H17-H18+I14 -> 187706250 | J17: =I17-I18+J14 -> 276000000 | ... AD17: =AC17-AC18+AD14 -> 750000
A18: Return of capital | B18: =MIN(B15,B17) -> 0 | C18: =MIN(C15,C17) -> 0 | D18: =MIN(D15,D17) -> 0 | E18: =MIN(E15,E17) -> 0 | F18: =MIN(F15,F17) -> 0 | G18: =MIN(G15,G17) -> 0 | H18: =MIN(H15,H17) -> 0 | I18: =MIN(I15,I17) -> 0 | ... AD18: =MIN(AD15,AD17) -> 0
A19: Pref account | B19: =0 -> 0 | C19: =B19-B20+(B17-B18+B19-B20)*((1+Fund!$B$11)^((C4-B4)/365)-1) -> 41167.224 | D19: =C19-C20+(C17-C18+C19-C20)*((1+Fund!$B$11)^((D4-C4)/365)-1) -> 125221.62 | E19: =D19-D20+(D17-D18+D19-D20)*((1+Fund!$B$11)^((E4-D4)/365)-1) -> 278133 | F19: =E19-E20+(E17-E18+E19-E20)*((1+Fund!$B$11)^((F4-E4)/365)-1) -> 2316353.8 | G19: =F19-F20+(F17-F18+F19-F20)*((1+Fund!$B$11)^((G4-F4)/365)-1) -> 4476739.1 | H19: =G19-G20+(G17-G18+G19-G20)*((1+Fund!$B$11)^((H4-G4)/365)-1) -> 8135034.2 | I19: =H19-H20+(H17-H18+H19-H20)*((1+Fund!$B$11)^((I4-H4)/365)-1) -> 11906611 | J19: =I19-I20+(I17-I18+I19-I20)*((1+Fund!$B$11)^((J4-I4)/365)-1) -> 15730774 | ... AD19: =AC19-AC20+(AC17-AC18+AC19-AC20)*((1+Fund!$B$11)^((AD4-AC4)/365)-1) -> 14678.216
A20: Pref paid | B20: =MIN(B15-B18,B19) -> 0 | C20: =MIN(C15-C18,C19) -> 0 | D20: =MIN(D15-D18,D19) -> 0 | E20: =MIN(E15-E18,E19) -> 0 | F20: =MIN(F15-F18,F19) -> 0 | G20: =MIN(G15-G18,G19) -> 0 | H20: =MIN(H15-H18,H19) -> 0 | I20: =MIN(I15-I18,I19) -> 0 | ... AD20: =MIN(AD15-AD18,AD19) -> 0
A21: Catch-up account | B21: =B20*Fund!$B$12/(1-Fund!$B$12) -> 0 | C21: =B21-B22+C20*Fund!$B$12/(1-Fund!$B$12) -> 0 | D21: =C21-C22+D20*Fund!$B$12/(1-Fund!$B$12) -> 0 | E21: =D21-D22+E20*Fund!$B$12/(1-Fund!$B$12) -> 0 | F21: =E21-E22+F20*Fund!$B$12/(1-Fund!$B$12) -> 0 | G21: =F21-F22+G20*Fund!$B$12/(1-Fund!$B$12) -> 0 | H21: =G21-G22+H20*Fund!$B$12/(1-Fund!$B$12) -> 0 | I21: =H21-H22+I20*Fund!$B$12/(1-Fund!$B$12) -> 0 | J21: =I21-I22+J20*Fund!$B$12/(1-Fund!$B$12) -> 0 | ... AD21: =AC21-AC22+AD20*Fund!$B$12/(1-Fund!$B$12) -> 0
A22: Catch-up to GP | B22: =MIN(B15-B18-B20,B21) -> 0 | C22: =MIN(C15-C18-C20,C21) -> 0 | D22: =MIN(D15-D18-D20,D21) -> 0 | E22: =MIN(E15-E18-E20,E21) -> 0 | F22: =MIN(F15-F18-F20,F21) -> 0 | G22: =MIN(G15-G18-G20,G21) -> 0 | H22: =MIN(H15-H18-H20,H21) -> 0 | I22: =MIN(I15-I18-I20,I21) -> 0 | ... AD22: =MIN(AD15-AD18-AD20,AD21) -> 0
A23: Split 80/20 LP | B23: =(B15-B18-B20-B22)*(1-Fund!$B$12) -> 0 | C23: =(C15-C18-C20-C22)*(1-Fund!$B$12) -> 0 | D23: =(D15-D18-D20-D22)*(1-Fund!$B$12) -> 0 | E23: =(E15-E18-E20-E22)*(1-Fund!$B$12) -> 0 | F23: =(F15-F18-F20-F22)*(1-Fund!$B$12) -> 0 | G23: =(G15-G18-G20-G22)*(1-Fund!$B$12) -> 0 | H23: =(H15-H18-H20-H22)*(1-Fund!$B$12) -> 0 | I23: =(I15-I18-I20-I22)*(1-Fund!$B$12) -> 0 | ... AD23: =(AD15-AD18-AD20-AD22)*(1-Fund!$B$12) -> 0
A24: Split 80/20 GP | B24: =(B15-B18-B20-B22)*Fund!$B$12 -> 0 | C24: =(C15-C18-C20-C22)*Fund!$B$12 -> 0 | D24: =(D15-D18-D20-D22)*Fund!$B$12 -> 0 | E24: =(E15-E18-E20-E22)*Fund!$B$12 -> 0 | F24: =(F15-F18-F20-F22)*Fund!$B$12 -> 0 | G24: =(G15-G18-G20-G22)*Fund!$B$12 -> 0 | H24: =(H15-H18-H20-H22)*Fund!$B$12 -> 0 | I24: =(I15-I18-I20-I22)*Fund!$B$12 -> 0 | ... AD24: =(AD15-AD18-AD20-AD22)*Fund!$B$12 -> 0
A25: LP distributions | B25: =B18+B20+B23 -> 0 | C25: =C18+C20+C23 -> 0 | D25: =D18+D20+D23 -> 0 | E25: =E18+E20+E23 -> 0 | F25: =F18+F20+F23 -> 0 | G25: =G18+G20+G23 -> 0 | H25: =H18+H20+H23 -> 0 | I25: =I18+I20+I23 -> 0 | ... AD25: =AD18+AD20+AD23 -> 0
A26: GP carry | B26: =B22+B24 -> 0 | C26: =C22+C24 -> 0 | D26: =D22+D24 -> 0 | E26: =E22+E24 -> 0 | F26: =F22+F24 -> 0 | G26: =G22+G24 -> 0 | H26: =H22+H24 -> 0 | I26: =I22+I24 -> 0 | ... AD26: =AD22+AD24 -> 0
A27: LP net cash flow | B27: =B25-B16 -> -2125000 | C27: =C25-C16 -> -2125000 | D27: =D25-D16 -> -3431250 | E27: =E25-E16 -> -98431250 | F27: =F25-F16 -> -3087500 | G27: =G25-G16 -> -73087500 | H27: =H25-H16 -> -2125000 | I27: =I25-I16 -> -3293750 | ... AD27: =AD25-AD16 -> -250000
A28: Gross deal cash flow | B28: =B6-B5 -> 0 | C28: =C6-C5 -> -95000000 | D28: =D6-D5 -> 0 | E28: =E6-E5 -> -70000000 | F28: =F6-F5 -> 0 | G28: =G6-G5 -> 0 | H28: =H6-H5 -> -85000000 | I28: =I6-I5 -> 0 | ... AD28: =AD6-AD5 -> 0

Sheet Returns
A3: Gross IRR (deals) | B3: =XIRR('Cash Flow'!B28:AD28,'Cash Flow'!B4:AD4) -> 0.16228083
A4: LP net IRR | B4: =XIRR('Cash Flow'!B27:AD27,'Cash Flow'!B4:AD4) -> 0.12463258
A5: LP TVPI | B5: =SUM('Cash Flow'!B25:AD25)/SUM('Cash Flow'!B16:AD16) -> 1.4575179
A6: GP carried interest (€) | B6: =SUM('Cash Flow'!B26:AD26) -> 51928125
A7: Management fees (€) | B7: =SUM('Cash Flow'!B8:AD8) -> 34109375
A8: Sub line interest (€) | B8: =SUM('Cash Flow'!B12:AD12) -> 11000000
A9: Peak sub line balance (€) | B9: =MAX('Cash Flow'!B13:AD13) -> 95000000
A10: Total called (€) | B10: =SUM('Cash Flow'!B14:AD14) -> 452359375
A11: Carry as share of profit | B11: =B6/(SUM('Cash Flow'!B6:AD6)-B10) -> 0.2005794
