Workbook

Sheet Inputs
A1: ALDGATE YARD – US INVESTOR, GBP ASSET WITH FX HEDGE
A3: Purchase price (£) | B3: 180000000
A4: Purchase costs | B4: 0.068
A5: NOI year 1 (£) | B5: 10200000
A6: NOI growth | B6: 0.025
A7: Exit yield | B7: 0.0575
A8: Hold (years) | B8: 7
A9: GBP loan to value | B9: 0.5
A10: SONIA (flat) | B10: 0.04
A11: Loan margin | B11: 0.018
A12: GBP/USD spot | B12: 1.27
A13: GBP/USD drift a year | B13: -0.01
A14: Hedge ratio (of GBP equity) | B14: 0.75
A15: Hedge execution cost (bps a year) | B15: 15

Sheet Curves
A1: Year | B1: Forward points (annual, % of spot)
A2: 1 | B2: -0.005
A3: 2 | B3: -0.0055
A4: 3 | B4: -0.006
A5: 4 | B5: -0.0065
A6: 5 | B6: -0.007
A7: 6 | B7: -0.0075
A8: 7 | B8: -0.008
A9: 8 | B9: -0.0085
A10: 9 | B10: -0.009
A11: 10 | B11: -0.0095

Sheet Cash Flow
A3: Year | B3: 0 | C3: 1 | D3: 2 | E3: 3 | F3: 4 | G3: 5 | H3: 6 | I3: 7 | J3: 8 | K3: 9 | L3: 10
A4: NOI (£) | B4: =IF(AND(B$3>=1,B$3<=Inputs!$B$8),Inputs!$B$5*(1+Inputs!$B$6)^(B$3-1),0) -> 0 | C4: =IF(AND(C$3>=1,C$3<=Inputs!$B$8),Inputs!$B$5*(1+Inputs!$B$6)^(C$3-1),0) -> 10200000 | D4: =IF(AND(D$3>=1,D$3<=Inputs!$B$8),Inputs!$B$5*(1+Inputs!$B$6)^(D$3-1),0) -> 10455000 | E4: =IF(AND(E$3>=1,E$3<=Inputs!$B$8),Inputs!$B$5*(1+Inputs!$B$6)^(E$3-1),0) -> 10716375 | F4: =IF(AND(F$3>=1,F$3<=Inputs!$B$8),Inputs!$B$5*(1+Inputs!$B$6)^(F$3-1),0) -> 10984284 | G4: =IF(AND(G$3>=1,G$3<=Inputs!$B$8),Inputs!$B$5*(1+Inputs!$B$6)^(G$3-1),0) -> 11258891 | H4: =IF(AND(H$3>=1,H$3<=Inputs!$B$8),Inputs!$B$5*(1+Inputs!$B$6)^(H$3-1),0) -> 11540364 | I4: =IF(AND(I$3>=1,I$3<=Inputs!$B$8),Inputs!$B$5*(1+Inputs!$B$6)^(I$3-1),0) -> 11828873 | ... L4: =IF(AND(L$3>=1,L$3<=Inputs!$B$8),Inputs!$B$5*(1+Inputs!$B$6)^(L$3-1),0) -> 0
A5: Sale (£) | B5: =IF((B$3=Inputs!$B$8),Inputs!$B$5*(1+Inputs!$B$6)^B$3/Inputs!$B$7,0) -> 0 | C5: =IF((C$3=Inputs!$B$8),Inputs!$B$5*(1+Inputs!$B$6)^C$3/Inputs!$B$7,0) -> 0 | D5: =IF((D$3=Inputs!$B$8),Inputs!$B$5*(1+Inputs!$B$6)^D$3/Inputs!$B$7,0) -> 0 | E5: =IF((E$3=Inputs!$B$8),Inputs!$B$5*(1+Inputs!$B$6)^E$3/Inputs!$B$7,0) -> 0 | F5: =IF((F$3=Inputs!$B$8),Inputs!$B$5*(1+Inputs!$B$6)^F$3/Inputs!$B$7,0) -> 0 | G5: =IF((G$3=Inputs!$B$8),Inputs!$B$5*(1+Inputs!$B$6)^G$3/Inputs!$B$7,0) -> 0 | H5: =IF((H$3=Inputs!$B$8),Inputs!$B$5*(1+Inputs!$B$6)^H$3/Inputs!$B$7,0) -> 0 | I5: =IF((I$3=Inputs!$B$8),Inputs!$B$5*(1+Inputs!$B$6)^I$3/Inputs!$B$7,0) -> 2.1086252e+08 | ... L5: =IF((L$3=Inputs!$B$8),Inputs!$B$5*(1+Inputs!$B$6)^L$3/Inputs!$B$7,0) -> 0
A6: Purchase (£) | B6: =IF(B$3=0,-Inputs!$B$3*(1+Inputs!$B$4),0) -> -192240000 | C6: =IF(C$3=0,-Inputs!$B$3*(1+Inputs!$B$4),0) -> 0 | D6: =IF(D$3=0,-Inputs!$B$3*(1+Inputs!$B$4),0) -> 0 | E6: =IF(E$3=0,-Inputs!$B$3*(1+Inputs!$B$4),0) -> 0 | F6: =IF(F$3=0,-Inputs!$B$3*(1+Inputs!$B$4),0) -> 0 | G6: =IF(G$3=0,-Inputs!$B$3*(1+Inputs!$B$4),0) -> 0 | H6: =IF(H$3=0,-Inputs!$B$3*(1+Inputs!$B$4),0) -> 0 | I6: =IF(I$3=0,-Inputs!$B$3*(1+Inputs!$B$4),0) -> 0 | ... L6: =IF(L$3=0,-Inputs!$B$3*(1+Inputs!$B$4),0) -> 0
A7: Loan (£) | B7: =IF(B$3=0,Inputs!$B$3*Inputs!$B$9,0) -> 90000000 | C7: =IF(C$3=0,Inputs!$B$3*Inputs!$B$9,0) -> 0 | D7: =IF(D$3=0,Inputs!$B$3*Inputs!$B$9,0) -> 0 | E7: =IF(E$3=0,Inputs!$B$3*Inputs!$B$9,0) -> 0 | F7: =IF(F$3=0,Inputs!$B$3*Inputs!$B$9,0) -> 0 | G7: =IF(G$3=0,Inputs!$B$3*Inputs!$B$9,0) -> 0 | H7: =IF(H$3=0,Inputs!$B$3*Inputs!$B$9,0) -> 0 | I7: =IF(I$3=0,Inputs!$B$3*Inputs!$B$9,0) -> 0 | ... L7: =IF(L$3=0,Inputs!$B$3*Inputs!$B$9,0) -> 0
A8: Interest (£) | B8: =IF(AND(B$3>=1,B$3<=Inputs!$B$8),-Inputs!$B$3*Inputs!$B$9*(Inputs!$B$10+Inputs!$B$11),0) -> 0 | C8: =IF(AND(C$3>=1,C$3<=Inputs!$B$8),-Inputs!$B$3*Inputs!$B$9*(Inputs!$B$10+Inputs!$B$11),0) -> -5220000 | D8: =IF(AND(D$3>=1,D$3<=Inputs!$B$8),-Inputs!$B$3*Inputs!$B$9*(Inputs!$B$10+Inputs!$B$11),0) -> -5220000 | E8: =IF(AND(E$3>=1,E$3<=Inputs!$B$8),-Inputs!$B$3*Inputs!$B$9*(Inputs!$B$10+Inputs!$B$11),0) -> -5220000 | F8: =IF(AND(F$3>=1,F$3<=Inputs!$B$8),-Inputs!$B$3*Inputs!$B$9*(Inputs!$B$10+Inputs!$B$11),0) -> -5220000 | G8: =IF(AND(G$3>=1,G$3<=Inputs!$B$8),-Inputs!$B$3*Inputs!$B$9*(Inputs!$B$10+Inputs!$B$11),0) -> -5220000 | H8: =IF(AND(H$3>=1,H$3<=Inputs!$B$8),-Inputs!$B$3*Inputs!$B$9*(Inputs!$B$10+Inputs!$B$11),0) -> -5220000 | I8: =IF(AND(I$3>=1,I$3<=Inputs!$B$8),-Inputs!$B$3*Inputs!$B$9*(Inputs!$B$10+Inputs!$B$11),0) -> -5220000 | ... L8: =IF(AND(L$3>=1,L$3<=Inputs!$B$8),-Inputs!$B$3*Inputs!$B$9*(Inputs!$B$10+Inputs!$B$11),0) -> 0
A9: Repayment (£) | B9: =IF((B$3=Inputs!$B$8),-Inputs!$B$3*Inputs!$B$9,0) -> 0 | C9: =IF((C$3=Inputs!$B$8),-Inputs!$B$3*Inputs!$B$9,0) -> 0 | D9: =IF((D$3=Inputs!$B$8),-Inputs!$B$3*Inputs!$B$9,0) -> 0 | E9: =IF((E$3=Inputs!$B$8),-Inputs!$B$3*Inputs!$B$9,0) -> 0 | F9: =IF((F$3=Inputs!$B$8),-Inputs!$B$3*Inputs!$B$9,0) -> 0 | G9: =IF((G$3=Inputs!$B$8),-Inputs!$B$3*Inputs!$B$9,0) -> 0 | H9: =IF((H$3=Inputs!$B$8),-Inputs!$B$3*Inputs!$B$9,0) -> 0 | I9: =IF((I$3=Inputs!$B$8),-Inputs!$B$3*Inputs!$B$9,0) -> -90000000 | ... L9: =IF((L$3=Inputs!$B$8),-Inputs!$B$3*Inputs!$B$9,0) -> 0
A10: Equity cash flow (£) | B10: =SUM(B4:B9) -> -102240000 | C10: =SUM(C4:C9) -> 4980000 | D10: =SUM(D4:D9) -> 5235000 | E10: =SUM(E4:E9) -> 5496375 | F10: =SUM(F4:F9) -> 5764284.4 | G10: =SUM(G4:G9) -> 6038891.5 | H10: =SUM(H4:H9) -> 6320363.8 | I10: =SUM(I4:I9) -> 1.2747139e+08 | ... L10: =SUM(L4:L9) -> 0
A11: GBP/USD spot | B11: =Inputs!$B$12*(1+Inputs!$B$13)^B$3 -> 1.27 | C11: =Inputs!$B$12*(1+Inputs!$B$13)^C$3 -> 1.2573 | D11: =Inputs!$B$12*(1+Inputs!$B$13)^D$3 -> 1.244727 | E11: =Inputs!$B$12*(1+Inputs!$B$13)^E$3 -> 1.2322797 | F11: =Inputs!$B$12*(1+Inputs!$B$13)^F$3 -> 1.2199569 | G11: =Inputs!$B$12*(1+Inputs!$B$13)^G$3 -> 1.2077574 | H11: =Inputs!$B$12*(1+Inputs!$B$13)^H$3 -> 1.1956798 | I11: =Inputs!$B$12*(1+Inputs!$B$13)^I$3 -> 1.183723 | ... L11: =Inputs!$B$12*(1+Inputs!$B$13)^L$3 -> 1.1485652
A12: Equity (£) hedged notional | B12: =IF(AND(B$3>=1,B$3<=Inputs!$B$8),Inputs!$B$3*(1+Inputs!$B$4)-Inputs!$B$3*Inputs!$B$9*Inputs!$B$14,0) -> 0 | C12: =IF(AND(C$3>=1,C$3<=Inputs!$B$8),Inputs!$B$3*(1+Inputs!$B$4)-Inputs!$B$3*Inputs!$B$9*Inputs!$B$14,0) -> 124740000 | D12: =IF(AND(D$3>=1,D$3<=Inputs!$B$8),Inputs!$B$3*(1+Inputs!$B$4)-Inputs!$B$3*Inputs!$B$9*Inputs!$B$14,0) -> 124740000 | E12: =IF(AND(E$3>=1,E$3<=Inputs!$B$8),Inputs!$B$3*(1+Inputs!$B$4)-Inputs!$B$3*Inputs!$B$9*Inputs!$B$14,0) -> 124740000 | F12: =IF(AND(F$3>=1,F$3<=Inputs!$B$8),Inputs!$B$3*(1+Inputs!$B$4)-Inputs!$B$3*Inputs!$B$9*Inputs!$B$14,0) -> 124740000 | G12: =IF(AND(G$3>=1,G$3<=Inputs!$B$8),Inputs!$B$3*(1+Inputs!$B$4)-Inputs!$B$3*Inputs!$B$9*Inputs!$B$14,0) -> 124740000 | H12: =IF(AND(H$3>=1,H$3<=Inputs!$B$8),Inputs!$B$3*(1+Inputs!$B$4)-Inputs!$B$3*Inputs!$B$9*Inputs!$B$14,0) -> 124740000 | I12: =IF(AND(I$3>=1,I$3<=Inputs!$B$8),Inputs!$B$3*(1+Inputs!$B$4)-Inputs!$B$3*Inputs!$B$9*Inputs!$B$14,0) -> 124740000 | ... L12: =IF(AND(L$3>=1,L$3<=Inputs!$B$8),Inputs!$B$3*(1+Inputs!$B$4)-Inputs!$B$3*Inputs!$B$9*Inputs!$B$14,0) -> 0
A13: Forward rate locked | B13: =0 -> 0 | C13: =IF(AND(C$3>=1,C$3<=Inputs!$B$8),B11*(1+INDEX(Curves!$B$2:$B$11,C$3)),0) -> 1.26365 | D13: =IF(AND(D$3>=1,D$3<=Inputs!$B$8),C11*(1+INDEX(Curves!$B$2:$B$11,D$3)),0) -> 1.2503849 | E13: =IF(AND(E$3>=1,E$3<=Inputs!$B$8),D11*(1+INDEX(Curves!$B$2:$B$11,E$3)),0) -> 1.2372586 | F13: =IF(AND(F$3>=1,F$3<=Inputs!$B$8),E11*(1+INDEX(Curves!$B$2:$B$11,F$3)),0) -> 1.2242699 | G13: =IF(AND(G$3>=1,G$3<=Inputs!$B$8),F11*(1+INDEX(Curves!$B$2:$B$11,G$3)),0) -> 1.2114172 | H13: =IF(AND(H$3>=1,H$3<=Inputs!$B$8),G11*(1+INDEX(Curves!$B$2:$B$11,H$3)),0) -> 1.1986992 | I13: =IF(AND(I$3>=1,I$3<=Inputs!$B$8),H11*(1+INDEX(Curves!$B$2:$B$11,I$3)),0) -> 1.1861144 | J13: =IF(AND(J$3>=1,J$3<=Inputs!$B$8),I11*(1+INDEX(Curves!$B$2:$B$11,J$3)),0) -> 0 | ... L13: =IF(AND(L$3>=1,L$3<=Inputs!$B$8),K11*(1+INDEX(Curves!$B$2:$B$11,L$3)),0) -> 0
A14: Hedge settlement ($) | B14: =B12*(B13-B11)-B12*B11*Inputs!$B$15/10000 -> 0 | C14: =C12*(C13-C11)-C12*C11*Inputs!$B$15/10000 -> 556845.6 | D14: =D12*(D13-D11)-D12*D11*Inputs!$B$15/10000 -> 472859.34 | E14: =E12*(E13-E11)-E12*E11*Inputs!$B$15/10000 -> 390497.12 | F14: =F12*(F13-F11)-F12*F11*Inputs!$B$15/10000 -> 309734.87 | G14: =G12*(G13-G11)-G12*G11*Inputs!$B$15/10000 -> 230548.8 | H14: =H12*(H13-H11)-H12*H11*Inputs!$B$15/10000 -> 152915.49 | I14: =I12*(I13-I11)-I12*I11*Inputs!$B$15/10000 -> 76811.785 | ... L14: =L12*(L13-L11)-L12*L11*Inputs!$B$15/10000 -> 0
A15: Equity cash flow unhedged ($) | B15: =B10*B11 -> -129844800 | C15: =C10*C11 -> 6261354 | D15: =D10*D11 -> 6516145.8 | E15: =E10*E11 -> 6773071.5 | F15: =F10*F11 -> 7032178.7 | G15: =G10*G11 -> 7293515.7 | H15: =H10*H11 -> 7557131.2 | I15: =I10*I11 -> 1.5089081e+08 | ... L15: =L10*L11 -> 0
A16: Equity cash flow hedged ($) | B16: =B15+B14 -> -129844800 | C16: =C15+C14 -> 6818199.6 | D16: =D15+D14 -> 6989005.2 | E16: =E15+E14 -> 7163568.6 | F16: =F15+F14 -> 7341913.6 | G16: =G15+G14 -> 7524064.5 | H16: =H15+H14 -> 7710046.7 | I16: =I15+I14 -> 1.5096763e+08 | ... L16: =L15+L14 -> 0

Sheet Returns
A3: Levered IRR (GBP) | B3: =IRR('Cash Flow'!B10:L10) -> 0.07637516
A4: Levered IRR (USD, unhedged) | B4: =IRR('Cash Flow'!B15:L15) -> 0.065611409
A5: Levered IRR (USD, hedged) | B5: =IRR('Cash Flow'!B16:L16) -> 0.06807528
A6: Equity multiple (USD, hedged) | B6: =SUMIF('Cash Flow'!B16:L16,">0")/-SUMIF('Cash Flow'!B16:L16,"<0") -> 1.4980532
A7: Hedge result ($) | B7: =SUM('Cash Flow'!B14:L14) -> 2190213
A8: Net profit (USD, hedged) | B8: =SUM('Cash Flow'!B16:L16) -> 64669624
