Workbook

Sheet Inputs
A1: CEDAR HOLLOW APARTMENTS – AFTER-TAX INVESTMENT MODEL (USD)
A3: Purchase price ($) | B3: 85000000
A4: Land share of price | B4: 0.2
A5: Cost segregation (share of building, 5-year property) | B5: 0.2
A6: Bonus depreciation | B6: 0.6
A7: NOI year 1 ($) | B7: 4900000
A8: NOI growth | B8: 0.03
A9: Loan to value | B9: 0.65
A10: Interest rate | B10: 0.061
A11: Interest-only (years) | B11: 3
A12: Amortisation (years) | B12: 30
A13: Hold (years) | B13: 7
A14: Exit cap rate | B14: 0.055
... A18: Capital gains rate (incl. NIIT) | B18: 0.238

Sheet Cash Flow
A3: Year | B3: 0 | C3: 1 | D3: 2 | E3: 3 | F3: 4 | G3: 5 | H3: 6 | I3: 7 | J3: 8 | K3: 9 | L3: 10
A4: NOI | B4: =IF(AND(B$3>=1,B$3<=Inputs!$B$13),Inputs!$B$7*(1+Inputs!$B$8)^(B$3-1),0) -> 0 | C4: =IF(AND(C$3>=1,C$3<=Inputs!$B$13),Inputs!$B$7*(1+Inputs!$B$8)^(C$3-1),0) -> 4900000 | D4: =IF(AND(D$3>=1,D$3<=Inputs!$B$13),Inputs!$B$7*(1+Inputs!$B$8)^(D$3-1),0) -> 5047000 | E4: =IF(AND(E$3>=1,E$3<=Inputs!$B$13),Inputs!$B$7*(1+Inputs!$B$8)^(E$3-1),0) -> 5198410 | F4: =IF(AND(F$3>=1,F$3<=Inputs!$B$13),Inputs!$B$7*(1+Inputs!$B$8)^(F$3-1),0) -> 5354362.3 | G4: =IF(AND(G$3>=1,G$3<=Inputs!$B$13),Inputs!$B$7*(1+Inputs!$B$8)^(G$3-1),0) -> 5514993.2 | H4: =IF(AND(H$3>=1,H$3<=Inputs!$B$13),Inputs!$B$7*(1+Inputs!$B$8)^(H$3-1),0) -> 5680443 | I4: =IF(AND(I$3>=1,I$3<=Inputs!$B$13),Inputs!$B$7*(1+Inputs!$B$8)^(I$3-1),0) -> 5850856.3 | ... L4: =IF(AND(L$3>=1,L$3<=Inputs!$B$13),Inputs!$B$7*(1+Inputs!$B$8)^(L$3-1),0) -> 0
A5: Loan opening | B5: =0 -> 0 | C5: =B8 -> 55250000 | D5: =C8 -> 55250000 | E5: =D8 -> 55250000 | F5: =E8 -> 55250000 | G5: =F8 -> 54563355 | H5: =G8 -> 53834825 | I5: =H8 -> 53061854 | J5: =I8 -> 0 | ... L5: =K8 -> 0
A6: Interest | B6: =IF(AND(B$3>=1,B$3<=Inputs!$B$13),B5*Inputs!$B$10,0) -> 0 | C6: =IF(AND(C$3>=1,C$3<=Inputs!$B$13),C5*Inputs!$B$10,0) -> 3370250 | D6: =IF(AND(D$3>=1,D$3<=Inputs!$B$13),D5*Inputs!$B$10,0) -> 3370250 | E6: =IF(AND(E$3>=1,E$3<=Inputs!$B$13),E5*Inputs!$B$10,0) -> 3370250 | F6: =IF(AND(F$3>=1,F$3<=Inputs!$B$13),F5*Inputs!$B$10,0) -> 3370250 | G6: =IF(AND(G$3>=1,G$3<=Inputs!$B$13),G5*Inputs!$B$10,0) -> 3328364.7 | H6: =IF(AND(H$3>=1,H$3<=Inputs!$B$13),H5*Inputs!$B$10,0) -> 3283924.3 | I6: =IF(AND(I$3>=1,I$3<=Inputs!$B$13),I5*Inputs!$B$10,0) -> 3236773.1 | ... L6: =IF(AND(L$3>=1,L$3<=Inputs!$B$13),L5*Inputs!$B$10,0) -> 0
A7: Principal | B7: =IF(AND(AND(B$3>=1,B$3<=Inputs!$B$13),B$3>Inputs!$B$11),PMT(Inputs!$B$10,Inputs!$B$12,-Inputs!$B$3*Inputs!$B$9)-B6,0) -> 0 | C7: =IF(AND(AND(C$3>=1,C$3<=Inputs!$B$13),C$3>Inputs!$B$11),PMT(Inputs!$B$10,Inputs!$B$12,-Inputs!$B$3*Inputs!$B$9)-C6,0) -> 0 | D7: =IF(AND(AND(D$3>=1,D$3<=Inputs!$B$13),D$3>Inputs!$B$11),PMT(Inputs!$B$10,Inputs!$B$12,-Inputs!$B$3*Inputs!$B$9)-D6,0) -> 0 | E7: =IF(AND(AND(E$3>=1,E$3<=Inputs!$B$13),E$3>Inputs!$B$11),PMT(Inputs!$B$10,Inputs!$B$12,-Inputs!$B$3*Inputs!$B$9)-E6,0) -> 0 | F7: =IF(AND(AND(F$3>=1,F$3<=Inputs!$B$13),F$3>Inputs!$B$11),PMT(Inputs!$B$10,Inputs!$B$12,-Inputs!$B$3*Inputs!$B$9)-F6,0) -> 686644.98 | G7: =IF(AND(AND(G$3>=1,G$3<=Inputs!$B$13),G$3>Inputs!$B$11),PMT(Inputs!$B$10,Inputs!$B$12,-Inputs!$B$3*Inputs!$B$9)-G6,0) -> 728530.32 | H7: =IF(AND(AND(H$3>=1,H$3<=Inputs!$B$13),H$3>Inputs!$B$11),PMT(Inputs!$B$10,Inputs!$B$12,-Inputs!$B$3*Inputs!$B$9)-H6,0) -> 772970.67 | I7: =IF(AND(AND(I$3>=1,I$3<=Inputs!$B$13),I$3>Inputs!$B$11),PMT(Inputs!$B$10,Inputs!$B$12,-Inputs!$B$3*Inputs!$B$9)-I6,0) -> 820121.88 | ... L7: =IF(AND(AND(L$3>=1,L$3<=Inputs!$B$13),L$3>Inputs!$B$11),PMT(Inputs!$B$10,Inputs!$B$12,-Inputs!$B$3*Inputs!$B$9)-L6,0) -> 0
A8: Loan closing | B8: =Inputs!$B$3*Inputs!$B$9 -> 55250000 | C8: =IF(C$3>=Inputs!$B$13,0,C5-C7) -> 55250000 | D8: =IF(D$3>=Inputs!$B$13,0,D5-D7) -> 55250000 | E8: =IF(E$3>=Inputs!$B$13,0,E5-E7) -> 55250000 | F8: =IF(F$3>=Inputs!$B$13,0,F5-F7) -> 54563355 | G8: =IF(G$3>=Inputs!$B$13,0,G5-G7) -> 53834825 | H8: =IF(H$3>=Inputs!$B$13,0,H5-H7) -> 53061854 | I8: =IF(I$3>=Inputs!$B$13,0,I5-I7) -> 0 | J8: =IF(J$3>=Inputs!$B$13,0,J5-J7) -> 0 | ... L8: =IF(L$3>=Inputs!$B$13,0,L5-L7) -> 0
A9: Debt service | B9: =B6+B7 -> 0 | C9: =C6+C7 -> 3370250 | D9: =D6+D7 -> 3370250 | E9: =E6+E7 -> 3370250 | F9: =F6+F7 -> 4056895 | G9: =G6+G7 -> 4056895 | H9: =H6+H7 -> 4056895 | I9: =I6+I7 -> 4056895 | ... L9: =L6+L7 -> 0
A10: Building depreciation | B10: =IF(AND(B$3>=1,B$3<=Inputs!$B$13),Inputs!$B$3*(1-Inputs!$B$4)*(1-Inputs!$B$5)/27.5*IF(B$3=1,11.5/12,1)*IF((B$3=Inputs!$B$13),11.5/12,1),0) -> 0 | C10: =IF(AND(C$3>=1,C$3<=Inputs!$B$13),Inputs!$B$3*(1-Inputs!$B$4)*(1-Inputs!$B$5)/27.5*IF(C$3=1,11.5/12,1)*IF((C$3=Inputs!$B$13),11.5/12,1),0) -> 1895757.6 | D10: =IF(AND(D$3>=1,D$3<=Inputs!$B$13),Inputs!$B$3*(1-Inputs!$B$4)*(1-Inputs!$B$5)/27.5*IF(D$3=1,11.5/12,1)*IF((D$3=Inputs!$B$13),11.5/12,1),0) -> 1978181.8 | E10: =IF(AND(E$3>=1,E$3<=Inputs!$B$13),Inputs!$B$3*(1-Inputs!$B$4)*(1-Inputs!$B$5)/27.5*IF(E$3=1,11.5/12,1)*IF((E$3=Inputs!$B$13),11.5/12,1),0) -> 1978181.8 | F10: =IF(AND(F$3>=1,F$3<=Inputs!$B$13),Inputs!$B$3*(1-Inputs!$B$4)*(1-Inputs!$B$5)/27.5*IF(F$3=1,11.5/12,1)*IF((F$3=Inputs!$B$13),11.5/12,1),0) -> 1978181.8 | G10: =IF(AND(G$3>=1,G$3<=Inputs!$B$13),Inputs!$B$3*(1-Inputs!$B$4)*(1-Inputs!$B$5)/27.5*IF(G$3=1,11.5/12,1)*IF((G$3=Inputs!$B$13),11.5/12,1),0) -> 1978181.8 | H10: =IF(AND(H$3>=1,H$3<=Inputs!$B$13),Inputs!$B$3*(1-Inputs!$B$4)*(1-Inputs!$B$5)/27.5*IF(H$3=1,11.5/12,1)*IF((H$3=Inputs!$B$13),11.5/12,1),0) -> 1978181.8 | I10: =IF(AND(I$3>=1,I$3<=Inputs!$B$13),Inputs!$B$3*(1-Inputs!$B$4)*(1-Inputs!$B$5)/27.5*IF(I$3=1,11.5/12,1)*IF((I$3=Inputs!$B$13),11.5/12,1),0) -> 1895757.6 | ... L10: =IF(AND(L$3>=1,L$3<=Inputs!$B$13),Inputs!$B$3*(1-Inputs!$B$4)*(1-Inputs!$B$5)/27.5*IF(L$3=1,11.5/12,1)*IF((L$3=Inputs!$B$13),11.5/12,1),0) -> 0
A11: Cost seg depreciation | B11: =IF(AND(B$3>=1,B$3<=Inputs!$B$13),IF(B$3=1,Inputs!$B$3*(1-Inputs!$B$4)*Inputs!$B$5*Inputs!$B$6,0)+IF(B$3<=5,Inputs!$B$3*(1-Inputs!$B$4)*Inputs!$B$5*(1-Inputs!$B$6)/5,0),0) -> 0 | C11: =IF(AND(C$3>=1,C$3<=Inputs!$B$13),IF(C$3=1,Inputs!$B$3*(1-Inputs!$B$4)*Inputs!$B$5*Inputs!$B$6,0)+IF(C$3<=5,Inputs!$B$3*(1-Inputs!$B$4)*Inputs!$B$5*(1-Inputs!$B$6)/5,0),0) -> 9248000 | D11: =IF(AND(D$3>=1,D$3<=Inputs!$B$13),IF(D$3=1,Inputs!$B$3*(1-Inputs!$B$4)*Inputs!$B$5*Inputs!$B$6,0)+IF(D$3<=5,Inputs!$B$3*(1-Inputs!$B$4)*Inputs!$B$5*(1-Inputs!$B$6)/5,0),0) -> 1088000 | E11: =IF(AND(E$3>=1,E$3<=Inputs!$B$13),IF(E$3=1,Inputs!$B$3*(1-Inputs!$B$4)*Inputs!$B$5*Inputs!$B$6,0)+IF(E$3<=5,Inputs!$B$3*(1-Inputs!$B$4)*Inputs!$B$5*(1-Inputs!$B$6)/5,0),0) -> 1088000 | F11: =IF(AND(F$3>=1,F$3<=Inputs!$B$13),IF(F$3=1,Inputs!$B$3*(1-Inputs!$B$4)*Inputs!$B$5*Inputs!$B$6,0)+IF(F$3<=5,Inputs!$B$3*(1-Inputs!$B$4)*Inputs!$B$5*(1-Inputs!$B$6)/5,0),0) -> 1088000 | G11: =IF(AND(G$3>=1,G$3<=Inputs!$B$13),IF(G$3=1,Inputs!$B$3*(1-Inputs!$B$4)*Inputs!$B$5*Inputs!$B$6,0)+IF(G$3<=5,Inputs!$B$3*(1-Inputs!$B$4)*Inputs!$B$5*(1-Inputs!$B$6)/5,0),0) -> 1088000 | H11: =IF(AND(H$3>=1,H$3<=Inputs!$B$13),IF(H$3=1,Inputs!$B$3*(1-Inputs!$B$4)*Inputs!$B$5*Inputs!$B$6,0)+IF(H$3<=5,Inputs!$B$3*(1-Inputs!$B$4)*Inputs!$B$5*(1-Inputs!$B$6)/5,0),0) -> 0 | I11: =IF(AND(I$3>=1,I$3<=Inputs!$B$13),IF(I$3=1,Inputs!$B$3*(1-Inputs!$B$4)*Inputs!$B$5*Inputs!$B$6,0)+IF(I$3<=5,Inputs!$B$3*(1-Inputs!$B$4)*Inputs!$B$5*(1-Inputs!$B$6)/5,0),0) -> 0 | ... L11: =IF(AND(L$3>=1,L$3<=Inputs!$B$13),IF(L$3=1,Inputs!$B$3*(1-Inputs!$B$4)*Inputs!$B$5*Inputs!$B$6,0)+IF(L$3<=5,Inputs!$B$3*(1-Inputs!$B$4)*Inputs!$B$5*(1-Inputs!$B$6)/5,0),0) -> 0
A12: Taxable income | B12: =B4-B6-B10-B11 -> 0 | C12: =C4-C6-C10-C11 -> -9614007.6 | D12: =D4-D6-D10-D11 -> -1389431.8 | E12: =E4-E6-E10-E11 -> -1238021.8 | F12: =F4-F6-F10-F11 -> -1082069.5 | G12: =G4-G6-G10-G11 -> -879553.31 | H12: =H4-H6-H10-H11 -> 418336.84 | I12: =I4-I6-I10-I11 -> 718325.58 | ... L12: =L4-L6-L10-L11 -> 0
A13: Loss carried in | B13: =0 -> 0 | C13: =B15 -> 0 | D13: =C15 -> 9614007.6 | E13: =D15 -> 11003439 | F13: =E15 -> 12241461 | G13: =F15 -> 13323531 | H13: =G15 -> 14203084 | I13: =H15 -> 13784747 | J13: =I15 -> 13066422 | ... L13: =K15 -> 13066422
A14: Loss used | B14: =IF(B12>0,MIN(B12,B13),0) -> 0 | C14: =IF(C12>0,MIN(C12,C13),0) -> 0 | D14: =IF(D12>0,MIN(D12,D13),0) -> 0 | E14: =IF(E12>0,MIN(E12,E13),0) -> 0 | F14: =IF(F12>0,MIN(F12,F13),0) -> 0 | G14: =IF(G12>0,MIN(G12,G13),0) -> 0 | H14: =IF(H12>0,MIN(H12,H13),0) -> 418336.84 | I14: =IF(I12>0,MIN(I12,I13),0) -> 718325.58 | ... L14: =IF(L12>0,MIN(L12,L13),0) -> 0
A15: Loss carried out | B15: =B13-B14+MAX(0,-B12) -> 0 | C15: =C13-C14+MAX(0,-C12) -> 9614007.6 | D15: =D13-D14+MAX(0,-D12) -> 11003439 | E15: =E13-E14+MAX(0,-E12) -> 12241461 | F15: =F13-F14+MAX(0,-F12) -> 13323531 | G15: =G13-G14+MAX(0,-G12) -> 14203084 | H15: =H13-H14+MAX(0,-H12) -> 13784747 | I15: =I13-I14+MAX(0,-I12) -> 13066422 | ... L15: =L13-L14+MAX(0,-L12) -> 13066422
A16: Tax on operations | B16: =MAX(0,B12-B14)*Inputs!$B$16 -> 0 | C16: =MAX(0,C12-C14)*Inputs!$B$16 -> 0 | D16: =MAX(0,D12-D14)*Inputs!$B$16 -> 0 | E16: =MAX(0,E12-E14)*Inputs!$B$16 -> 0 | F16: =MAX(0,F12-F14)*Inputs!$B$16 -> 0 | G16: =MAX(0,G12-G14)*Inputs!$B$16 -> 0 | H16: =MAX(0,H12-H14)*Inputs!$B$16 -> 0 | I16: =MAX(0,I12-I14)*Inputs!$B$16 -> 0 | ... L16: =MAX(0,L12-L14)*Inputs!$B$16 -> 0
A17: Pre-tax equity cash flow | B17: =-(Inputs!$B$3-Inputs!$B$3*Inputs!$B$9) -> -29750000 | C17: =C4-C9+IF((C$3=Inputs!$B$13),C18-C19-C5+C7,0) -> 1529750 | D17: =D4-D9+IF((D$3=Inputs!$B$13),D18-D19-D5+D7,0) -> 1676750 | E17: =E4-E9+IF((E$3=Inputs!$B$13),E18-E19-E5+E7,0) -> 1828160 | F17: =F4-F9+IF((F$3=Inputs!$B$13),F18-F19-F5+F7,0) -> 1297467.3 | G17: =G4-G9+IF((G$3=Inputs!$B$13),G18-G19-G5+G7,0) -> 1458098.2 | H17: =H4-H9+IF((H$3=Inputs!$B$13),H18-H19-H5+H7,0) -> 1623548 | I17: =I4-I9+IF((I$3=Inputs!$B$13),I18-I19-I5+I7,0) -> 56931398 | J17: =J4-J9+IF((J$3=Inputs!$B$13),J18-J19-J5+J7,0) -> 0 | ... L17: =L4-L9+IF((L$3=Inputs!$B$13),L18-L19-L5+L7,0) -> 0
A18: Sale price | B18: =IF((B$3=Inputs!$B$13),Inputs!$B$7*(1+Inputs!$B$8)^B$3/Inputs!$B$14,0) -> 0 | C18: =IF((C$3=Inputs!$B$13),Inputs!$B$7*(1+Inputs!$B$8)^C$3/Inputs!$B$14,0) -> 0 | D18: =IF((D$3=Inputs!$B$13),Inputs!$B$7*(1+Inputs!$B$8)^D$3/Inputs!$B$14,0) -> 0 | E18: =IF((E$3=Inputs!$B$13),Inputs!$B$7*(1+Inputs!$B$8)^E$3/Inputs!$B$14,0) -> 0 | F18: =IF((F$3=Inputs!$B$13),Inputs!$B$7*(1+Inputs!$B$8)^F$3/Inputs!$B$14,0) -> 0 | G18: =IF((G$3=Inputs!$B$13),Inputs!$B$7*(1+Inputs!$B$8)^G$3/Inputs!$B$14,0) -> 0 | H18: =IF((H$3=Inputs!$B$13),Inputs!$B$7*(1+Inputs!$B$8)^H$3/Inputs!$B$14,0) -> 0 | I18: =IF((I$3=Inputs!$B$13),Inputs!$B$7*(1+Inputs!$B$8)^I$3/Inputs!$B$14,0) -> 1.0957058e+08 | ... L18: =IF((L$3=Inputs!$B$13),Inputs!$B$7*(1+Inputs!$B$8)^L$3/Inputs!$B$14,0) -> 0
A19: Sale costs | B19: =B18*Inputs!$B$15 -> 0 | C19: =C18*Inputs!$B$15 -> 0 | D19: =D18*Inputs!$B$15 -> 0 | E19: =E18*Inputs!$B$15 -> 0 | F19: =F18*Inputs!$B$15 -> 0 | G19: =G18*Inputs!$B$15 -> 0 | H19: =H18*Inputs!$B$15 -> 0 | I19: =I18*Inputs!$B$15 -> 2191411.6 | ... L19: =L18*Inputs!$B$15 -> 0
A20: Tax at sale | B20: =IF((B$3=Inputs!$B$13),MAX(0,MIN(SUM($C11:B11),B18-B19-(Inputs!$B$3-SUM($C10:B10)-SUM($C11:B11)))-B15)*Inputs!$B$16+MIN(SUM($C10:B10),MAX(0,B18-B19-(Inputs!$B$3-SUM($C10:B10))))*Inputs!$B$17+MAX(0,B18-B19-Inputs!$B$3)*Inputs!$B$18-MAX(0,B15-SUM($C11:B11))*Inputs!$B$16,0) -> 0 | C20: =IF((C$3=Inputs!$B$13),MAX(0,MIN(SUM($C11:C11),C18-C19-(Inputs!$B$3-SUM($C10:C10)-SUM($C11:C11)))-C15)*Inputs!$B$16+MIN(SUM($C10:C10),MAX(0,C18-C19-(Inputs!$B$3-SUM($C10:C10))))*Inputs!$B$17+MAX(0,C18-C19-Inputs!$B$3)*Inputs!$B$18-MAX(0,C15-SUM($C11:C11))*Inputs!$B$16,0) -> 0 | D20: =IF((D$3=Inputs!$B$13),MAX(0,MIN(SUM($C11:D11),D18-D19-(Inputs!$B$3-SUM($C10:D10)-SUM($C11:D11)))-D15)*Inputs!$B$16+MIN(SUM($C10:D10),MAX(0,D18-D19-(Inputs!$B$3-SUM($C10:D10))))*Inputs!$B$17+MAX(0,D18-D19-Inputs!$B$3)*Inputs!$B$18-MAX(0,D15-SUM($C11:D11))*Inputs!$B$16,0) -> 0 | E20: =IF((E$3=Inputs!$B$13),MAX(0,MIN(SUM($C11:E11),E18-E19-(Inputs!$B$3-SUM($C10:E10)-SUM($C11:E11)))-E15)*Inputs!$B$16+MIN(SUM($C10:E10),MAX(0,E18-E19-(Inputs!$B$3-SUM($C10:E10))))*Inputs!$B$17+MAX(0,E18-E19-Inputs!$B$3)*Inputs!$B$18-MAX(0,E15-SUM($C11:E11))*Inputs!$B$16,0) -> 0 | F20: =IF((F$3=Inputs!$B$13),MAX(0,MIN(SUM($C11:F11),F18-F19-(Inputs!$B$3-SUM($C10:F10)-SUM($C11:F11)))-F15)*Inputs!$B$16+MIN(SUM($C10:F10),MAX(0,F18-F19-(Inputs!$B$3-SUM($C10:F10))))*Inputs!$B$17+MAX(0,F18-F19-Inputs!$B$3)*Inputs!$B$18-MAX(0,F15-SUM($C11:F11))*Inputs!$B$16,0) -> 0 | G20: =IF((G$3=Inputs!$B$13),MAX(0,MIN(SUM($C11:G11),G18-G19-(Inputs!$B$3-SUM($C10:G10)-SUM($C11:G11)))-G15)*Inputs!$B$16+MIN(SUM($C10:G10),MAX(0,G18-G19-(Inputs!$B$3-SUM($C10:G10))))*Inputs!$B$17+MAX(0,G18-G19-Inputs!$B$3)*Inputs!$B$18-MAX(0,G15-SUM($C11:G11))*Inputs!$B$16,0) -> 0 | H20: =IF((H$3=Inputs!$B$13),MAX(0,MIN(SUM($C11:H11),H18-H19-(Inputs!$B$3-SUM($C10:H10)-SUM($C11:H11)))-H15)*Inputs!$B$16+MIN(SUM($C10:H10),MAX(0,H18-H19-(Inputs!$B$3-SUM($C10:H10))))*Inputs!$B$17+MAX(0,H18-H19-Inputs!$B$3)*Inputs!$B$18-MAX(0,H15-SUM($C11:H11))*Inputs!$B$16,0) -> 0 | I20: =IF((I$3=Inputs!$B$13),MAX(0,MIN(SUM($C11:I11),I18-I19-(Inputs!$B$3-SUM($C10:I10)-SUM($C11:I11)))-I15)*Inputs!$B$16+MIN(SUM($C10:I10),MAX(0,I18-I19-(Inputs!$B$3-SUM($C10:I10))))*Inputs!$B$17+MAX(0,I18-I19-Inputs!$B$3)*Inputs!$B$18-MAX(0,I15-SUM($C11:I11))*Inputs!$B$16,0) -> 8944272.3 | ... L20: =IF((L$3=Inputs!$B$13),MAX(0,MIN(SUM($C11:L11),L18-L19-(Inputs!$B$3-SUM($C10:L10)-SUM($C11:L11)))-L15)*Inputs!$B$16+MIN(SUM($C10:L10),MAX(0,L18-L19-(Inputs!$B$3-SUM($C10:L10))))*Inputs!$B$17+MAX(0,L18-L19-Inputs!$B$3)*Inputs!$B$18-MAX(0,L15-SUM($C11:L11))*Inputs!$B$16,0) -> 0
A21: After-tax equity cash flow | B21: =B17-B16-B20 -> -29750000 | C21: =C17-C16-C20 -> 1529750 | D21: =D17-D16-D20 -> 1676750 | E21: =E17-E16-E20 -> 1828160 | F21: =F17-F16-F20 -> 1297467.3 | G21: =G17-G16-G20 -> 1458098.2 | H21: =H17-H16-H20 -> 1623548 | I21: =I17-I16-I20 -> 47987126 | ... L21: =L17-L16-L20 -> 0

Sheet Returns
A3: Levered IRR (pre-tax) | B3: =IRR('Cash Flow'!B17:L17) -> 0.13455512
A4: After-tax IRR | B4: =IRR('Cash Flow'!B21:L21) -> 0.11016512
A5: After-tax equity multiple | B5: =SUMIF('Cash Flow'!B21:L21,">0")/-SUMIF('Cash Flow'!B21:L21,"<0") -> 1.929442
A6: Tax at sale ($) | B6: =SUM('Cash Flow'!B20:L20) -> 8944272.3
A7: Depreciation taken ($) | B7: =SUM('Cash Flow'!B10:L10)+SUM('Cash Flow'!B11:L11) -> 27282424
A8: Net profit after tax ($) | B8: =SUM('Cash Flow'!B21:L21) -> 27650899
A9: Year 1 tax shield ($) | B9: =-MIN(0,'Cash Flow'!C12)*Inputs!$B$16 -> 3557182.8
