Workbook

Sheet Inputs
A1: LAKESHORE PLAZA – RECAPITALISATION, CAPITAL STACK AND CASH TRAP (USD)
A3: Purchase price ($) | B3: 250000000
A4: Closing costs | B4: 0.02
A5: NOI, year 1 ($) | B5: 15500000
A6: NOI growth a year | B6: 0.03
A7: Capital reserve a quarter ($) | B7: 500000
A8: Hold (quarters) | B8: 28
A9: Exit cap rate | B9: 0.0625
A10: Selling costs | B10: 0.015
A11: Senior loan to value | B11: 0.55
A12: Senior margin over SOFR | B12: 0.0225
A13: Senior amortisation a year (of original) | B13: 0.01
A14: Cash trap: senior DSCR below | B14: 1.25
... A18: Preferred return (accrues) | B18: 0.12

Sheet Curves
A1: Quarter | B1: SOFR forward
A2: 1 | B2: 0.041942
A3: 2 | B3: 0.041009
A4: 3 | B4: 0.040186
A5: 4 | B5: 0.039459
A6: 5 | B6: 0.038817
A7: 6 | B7: 0.038251
A8: 7 | B8: 0.037752
A9: 8 | B9: 0.037311
A10: 9 | B10: 0.036922
A11: 10 | B11: 0.036579
A12: 11 | B12: 0.036276
A13: 12 | B13: 0.036008
... A41: 40 | B41: 0.034061

Sheet Cash Flow
A3: Quarter | B3: 0 | C3: 1 | D3: 2 | E3: 3 | F3: 4 | G3: 5 | H3: 6 | I3: 7 | J3: 8 | K3: 9 | L3: 10 | M3: 11 | N3: 12 | O3: 13 | P3: 14 | Q3: 15 | R3: 16 | S3: 17 | T3: 18 | U3: 19 | V3: 20 | W3: 21 | X3: 22 | Y3: 23 | Z3: 24 | AA3: 25 | AB3: 26 | AC3: 27 | AD3: 28 | AE3: 29 | AF3: 30 | AG3: 31 | AH3: 32 | AI3: 33 | AJ3: 34 | AK3: 35 | AL3: 36 | AM3: 37 | AN3: 38 | AO3: 39 | AP3: 40
A4: SOFR | B4: =0 -> 0 | C4: =INDEX(Curves!$B$2:$B$41,C$3) -> 0.041942 | D4: =INDEX(Curves!$B$2:$B$41,D$3) -> 0.041009 | E4: =INDEX(Curves!$B$2:$B$41,E$3) -> 0.040186 | F4: =INDEX(Curves!$B$2:$B$41,F$3) -> 0.039459 | G4: =INDEX(Curves!$B$2:$B$41,G$3) -> 0.038817 | H4: =INDEX(Curves!$B$2:$B$41,H$3) -> 0.038251 | I4: =INDEX(Curves!$B$2:$B$41,I$3) -> 0.037752 | J4: =INDEX(Curves!$B$2:$B$41,J$3) -> 0.037311 | ... AP4: =INDEX(Curves!$B$2:$B$41,AP$3) -> 0.034061
A5: NOI | B5: =IF(AND(B$3>=1,B$3<=Inputs!$B$8),Inputs!$B$5/4*(1+Inputs!$B$6)^((B$3-1)/4),0) -> 0 | C5: =IF(AND(C$3>=1,C$3<=Inputs!$B$8),Inputs!$B$5/4*(1+Inputs!$B$6)^((C$3-1)/4),0) -> 3875000 | D5: =IF(AND(D$3>=1,D$3<=Inputs!$B$8),Inputs!$B$5/4*(1+Inputs!$B$6)^((D$3-1)/4),0) -> 3903741.2 | E5: =IF(AND(E$3>=1,E$3<=Inputs!$B$8),Inputs!$B$5/4*(1+Inputs!$B$6)^((E$3-1)/4),0) -> 3932695.5 | F5: =IF(AND(F$3>=1,F$3<=Inputs!$B$8),Inputs!$B$5/4*(1+Inputs!$B$6)^((F$3-1)/4),0) -> 3961864.6 | G5: =IF(AND(G$3>=1,G$3<=Inputs!$B$8),Inputs!$B$5/4*(1+Inputs!$B$6)^((G$3-1)/4),0) -> 3991250 | H5: =IF(AND(H$3>=1,H$3<=Inputs!$B$8),Inputs!$B$5/4*(1+Inputs!$B$6)^((H$3-1)/4),0) -> 4020853.4 | I5: =IF(AND(I$3>=1,I$3<=Inputs!$B$8),Inputs!$B$5/4*(1+Inputs!$B$6)^((I$3-1)/4),0) -> 4050676.3 | ... AP5: =IF(AND(AP$3>=1,AP$3<=Inputs!$B$8),Inputs!$B$5/4*(1+Inputs!$B$6)^((AP$3-1)/4),0) -> 0
A6: Capital reserve | B6: =IF(AND(B$3>=1,B$3<=Inputs!$B$8),Inputs!$B$7,0) -> 0 | C6: =IF(AND(C$3>=1,C$3<=Inputs!$B$8),Inputs!$B$7,0) -> 500000 | D6: =IF(AND(D$3>=1,D$3<=Inputs!$B$8),Inputs!$B$7,0) -> 500000 | E6: =IF(AND(E$3>=1,E$3<=Inputs!$B$8),Inputs!$B$7,0) -> 500000 | F6: =IF(AND(F$3>=1,F$3<=Inputs!$B$8),Inputs!$B$7,0) -> 500000 | G6: =IF(AND(G$3>=1,G$3<=Inputs!$B$8),Inputs!$B$7,0) -> 500000 | H6: =IF(AND(H$3>=1,H$3<=Inputs!$B$8),Inputs!$B$7,0) -> 500000 | I6: =IF(AND(I$3>=1,I$3<=Inputs!$B$8),Inputs!$B$7,0) -> 500000 | ... AP6: =IF(AND(AP$3>=1,AP$3<=Inputs!$B$8),Inputs!$B$7,0) -> 0
A7: CFADS | B7: =B5-B6 -> 0 | C7: =C5-C6 -> 3375000 | D7: =D5-D6 -> 3403741.2 | E7: =E5-E6 -> 3432695.5 | F7: =F5-F6 -> 3461864.6 | G7: =G5-G6 -> 3491250 | H7: =H5-H6 -> 3520853.4 | I7: =I5-I6 -> 3550676.3 | ... AP7: =AP5-AP6 -> 0
A8: Senior opening | B8: =0 -> 0 | C8: =B27 -> 137500000 | D8: =C27 -> 137156250 | E8: =D27 -> 136812500 | F8: =E27 -> 136468750 | G8: =F27 -> 136125000 | H8: =G27 -> 135781250 | I8: =H27 -> 135437500 | J8: =I27 -> 135093750 | ... AP8: =AO27 -> 0
A9: Senior interest | B9: =B8*(B4+Inputs!$B$12)/4 -> 0 | C9: =C8*(C4+Inputs!$B$12)/4 -> 2215193.8 | D9: =D8*(D4+Inputs!$B$12)/4 -> 2177664.1 | E9: =E8*(E4+Inputs!$B$12)/4 -> 2144057.1 | F9: =F8*(F4+Inputs!$B$12)/4 -> 2113866.8 | G9: =G8*(G4+Inputs!$B$12)/4 -> 2086694.2 | H9: =H8*(H4+Inputs!$B$12)/4 -> 2062211.7 | I9: =I8*(I4+Inputs!$B$12)/4 -> 2040095.1 | ... AP9: =AP8*(AP4+Inputs!$B$12)/4 -> 0
A10: Senior amortisation | B10: =IF(AND(B$3>=1,B$3<=Inputs!$B$8),MIN(B8,Inputs!$B$3*Inputs!$B$11*Inputs!$B$13/4),0) -> 0 | C10: =IF(AND(C$3>=1,C$3<=Inputs!$B$8),MIN(C8,Inputs!$B$3*Inputs!$B$11*Inputs!$B$13/4),0) -> 343750 | D10: =IF(AND(D$3>=1,D$3<=Inputs!$B$8),MIN(D8,Inputs!$B$3*Inputs!$B$11*Inputs!$B$13/4),0) -> 343750 | E10: =IF(AND(E$3>=1,E$3<=Inputs!$B$8),MIN(E8,Inputs!$B$3*Inputs!$B$11*Inputs!$B$13/4),0) -> 343750 | F10: =IF(AND(F$3>=1,F$3<=Inputs!$B$8),MIN(F8,Inputs!$B$3*Inputs!$B$11*Inputs!$B$13/4),0) -> 343750 | G10: =IF(AND(G$3>=1,G$3<=Inputs!$B$8),MIN(G8,Inputs!$B$3*Inputs!$B$11*Inputs!$B$13/4),0) -> 343750 | H10: =IF(AND(H$3>=1,H$3<=Inputs!$B$8),MIN(H8,Inputs!$B$3*Inputs!$B$11*Inputs!$B$13/4),0) -> 343750 | I10: =IF(AND(I$3>=1,I$3<=Inputs!$B$8),MIN(I8,Inputs!$B$3*Inputs!$B$11*Inputs!$B$13/4),0) -> 343750 | ... AP10: =IF(AND(AP$3>=1,AP$3<=Inputs!$B$8),MIN(AP8,Inputs!$B$3*Inputs!$B$11*Inputs!$B$13/4),0) -> 0
A11: Senior debt service | B11: =B9+B10 -> 0 | C11: =C9+C10 -> 2558943.8 | D11: =D9+D10 -> 2521414.1 | E11: =E9+E10 -> 2487807.1 | F11: =F9+F10 -> 2457616.8 | G11: =G9+G10 -> 2430444.2 | H11: =H9+H10 -> 2405961.7 | I11: =I9+I10 -> 2383845.1 | ... AP11: =AP9+AP10 -> 0
A12: Senior DSCR | B12: =IF(B11>0,B7/B11,99) -> 99 | C12: =IF(C11>0,C7/C11,99) -> 1.3189036 | D12: =IF(D11>0,D7/D11,99) -> 1.3499334 | E12: =IF(E11>0,E7/E11,99) -> 1.3798077 | F12: =IF(F11>0,F7/F11,99) -> 1.4086267 | G12: =IF(G11>0,G7/G11,99) -> 1.4364658 | H12: =IF(H11>0,H7/H11,99) -> 1.4633871 | I12: =IF(I11>0,I7/I11,99) -> 1.4894745 | ... AP12: =IF(AP11>0,AP7/AP11,99) -> 99
A13: Cash after senior | B13: =B7-B11 -> 0 | C13: =C7-C11 -> 816056.25 | D13: =D7-D11 -> 882327.08 | E13: =E7-E11 -> 944888.39 | F13: =F7-F11 -> 1004247.7 | G13: =G7-G11 -> 1060805.8 | H13: =H7-H11 -> 1114891.7 | I13: =I7-I11 -> 1166831.3 | ... AP13: =AP7-AP11 -> 0
A14: Equity cure | B14: =MAX(0,-B13) -> 0 | C14: =MAX(0,-C13) -> 0 | D14: =MAX(0,-D13) -> 0 | E14: =MAX(0,-E13) -> 0 | F14: =MAX(0,-F13) -> 0 | G14: =MAX(0,-G13) -> 0 | H14: =MAX(0,-H13) -> 0 | I14: =MAX(0,-I13) -> 0 | ... AP14: =MAX(0,-AP13) -> 0
A15: Mezz opening | B15: =0 -> 0 | C15: =B28 -> 37500000 | D15: =C28 -> 37715194 | E15: =D28 -> 37870034 | F15: =E28 -> 37966572 | G15: =F28 -> 38006405 | H15: =G28 -> 38006405 | I15: =H28 -> 38006405 | J15: =I28 -> 38006405 | ... AP15: =AO28 -> 0
A16: Mezz interest due | B16: =B15*Inputs!$B$16/4 -> 0 | C16: =C15*Inputs!$B$16/4 -> 1031250 | D16: =D15*Inputs!$B$16/4 -> 1037167.8 | E16: =E15*Inputs!$B$16/4 -> 1041425.9 | F16: =F15*Inputs!$B$16/4 -> 1044080.7 | G16: =G15*Inputs!$B$16/4 -> 1045176.1 | H16: =H15*Inputs!$B$16/4 -> 1045176.1 | I16: =I15*Inputs!$B$16/4 -> 1045176.1 | ... AP16: =AP15*Inputs!$B$16/4 -> 0
A17: Mezz interest paid | B17: =MIN(MAX(0,B13),B16) -> 0 | C17: =MIN(MAX(0,C13),C16) -> 816056.25 | D17: =MIN(MAX(0,D13),D16) -> 882327.08 | E17: =MIN(MAX(0,E13),E16) -> 944888.39 | F17: =MIN(MAX(0,F13),F16) -> 1004247.7 | G17: =MIN(MAX(0,G13),G16) -> 1045176.1 | H17: =MIN(MAX(0,H13),H16) -> 1045176.1 | I17: =MIN(MAX(0,I13),I16) -> 1045176.1 | ... AP17: =MIN(MAX(0,AP13),AP16) -> 0
A18: Mezz PIK | B18: =B16-B17 -> 0 | C18: =C16-C17 -> 215193.75 | D18: =D16-D17 -> 154840.75 | E18: =E16-E17 -> 96537.561 | F18: =F16-F17 -> 39832.986 | G18: =G16-G17 -> 0 | H18: =H16-H17 -> 0 | I18: =I16-I17 -> 0 | ... AP18: =AP16-AP17 -> 0
A19: Cash after mezz | B19: =MAX(0,B13)-B17 -> 0 | C19: =MAX(0,C13)-C17 -> 0 | D19: =MAX(0,D13)-D17 -> 0 | E19: =MAX(0,E13)-E17 -> 0 | F19: =MAX(0,F13)-F17 -> 0 | G19: =MAX(0,G13)-G17 -> 15629.705 | H19: =MAX(0,H13)-H17 -> 69715.569 | I19: =MAX(0,I13)-I17 -> 121655.14 | ... AP19: =MAX(0,AP13)-AP17 -> 0
A20: Pref opening | B20: =0 -> 0 | C20: =B29 -> 25000000 | D20: =C29 -> 25750000 | E20: =D29 -> 26522500 | F20: =E29 -> 27318175 | G20: =F29 -> 28137720 | H20: =G29 -> 28966222 | I20: =H29 -> 29765493 | J20: =I29 -> 30536803 | ... AP20: =AO29 -> 0
A21: Pref accrual | B21: =B20*Inputs!$B$18/4 -> 0 | C21: =C20*Inputs!$B$18/4 -> 750000 | D21: =D20*Inputs!$B$18/4 -> 772500 | E21: =E20*Inputs!$B$18/4 -> 795675 | F21: =F20*Inputs!$B$18/4 -> 819545.25 | G21: =G20*Inputs!$B$18/4 -> 844131.61 | H21: =H20*Inputs!$B$18/4 -> 868986.66 | I21: =I20*Inputs!$B$18/4 -> 892964.8 | ... AP21: =AP20*Inputs!$B$18/4 -> 0
A22: Pref paid | B22: =MIN(B19,B20+B21) -> 0 | C22: =MIN(C19,C20+C21) -> 0 | D22: =MIN(D19,D20+D21) -> 0 | E22: =MIN(E19,E20+E21) -> 0 | F22: =MIN(F19,F20+F21) -> 0 | G22: =MIN(G19,G20+G21) -> 15629.705 | H22: =MIN(H19,H20+H21) -> 69715.569 | I22: =MIN(I19,I20+I21) -> 121655.14 | ... AP22: =MIN(AP19,AP20+AP21) -> 0
A23: Residual cash | B23: =B19-B22 -> 0 | C23: =C19-C22 -> 0 | D23: =D19-D22 -> 0 | E23: =E19-E22 -> 0 | F23: =F19-F22 -> 0 | G23: =G19-G22 -> 0 | H23: =H19-H22 -> 0 | I23: =I19-I22 -> 0 | ... AP23: =AP19-AP22 -> 0
A24: Cash trap on | B24: =IF(AND(AND(B$3>=1,B$3<=Inputs!$B$8),B12<Inputs!$B$14),1,0) -> 0 | C24: =IF(AND(AND(C$3>=1,C$3<=Inputs!$B$8),C12<Inputs!$B$14),1,0) -> 0 | D24: =IF(AND(AND(D$3>=1,D$3<=Inputs!$B$8),D12<Inputs!$B$14),1,0) -> 0 | E24: =IF(AND(AND(E$3>=1,E$3<=Inputs!$B$8),E12<Inputs!$B$14),1,0) -> 0 | F24: =IF(AND(AND(F$3>=1,F$3<=Inputs!$B$8),F12<Inputs!$B$14),1,0) -> 0 | G24: =IF(AND(AND(G$3>=1,G$3<=Inputs!$B$8),G12<Inputs!$B$14),1,0) -> 0 | H24: =IF(AND(AND(H$3>=1,H$3<=Inputs!$B$8),H12<Inputs!$B$14),1,0) -> 0 | I24: =IF(AND(AND(I$3>=1,I$3<=Inputs!$B$8),I12<Inputs!$B$14),1,0) -> 0 | ... AP24: =IF(AND(AND(AP$3>=1,AP$3<=Inputs!$B$8),AP12<Inputs!$B$14),1,0) -> 0
A25: Cash swept | B25: =MIN(B24*B23,B8-B10) -> 0 | C25: =MIN(C24*C23,C8-C10) -> 0 | D25: =MIN(D24*D23,D8-D10) -> 0 | E25: =MIN(E24*E23,E8-E10) -> 0 | F25: =MIN(F24*F23,F8-F10) -> 0 | G25: =MIN(G24*G23,G8-G10) -> 0 | H25: =MIN(H24*H23,H8-H10) -> 0 | I25: =MIN(I24*I23,I8-I10) -> 0 | ... AP25: =MIN(AP24*AP23,AP8-AP10) -> 0
A26: Distributions | B26: =B23-B25 -> 0 | C26: =C23-C25 -> 0 | D26: =D23-D25 -> 0 | E26: =E23-E25 -> 0 | F26: =F23-F25 -> 0 | G26: =G23-G25 -> 0 | H26: =H23-H25 -> 0 | I26: =I23-I25 -> 0 | ... AP26: =AP23-AP25 -> 0
A27: Senior closing | B27: =Inputs!$B$3*Inputs!$B$11 -> 137500000 | C27: =IF(C$3>=Inputs!$B$8,0,C8-C10-C25) -> 137156250 | D27: =IF(D$3>=Inputs!$B$8,0,D8-D10-D25) -> 136812500 | E27: =IF(E$3>=Inputs!$B$8,0,E8-E10-E25) -> 136468750 | F27: =IF(F$3>=Inputs!$B$8,0,F8-F10-F25) -> 136125000 | G27: =IF(G$3>=Inputs!$B$8,0,G8-G10-G25) -> 135781250 | H27: =IF(H$3>=Inputs!$B$8,0,H8-H10-H25) -> 135437500 | I27: =IF(I$3>=Inputs!$B$8,0,I8-I10-I25) -> 135093750 | J27: =IF(J$3>=Inputs!$B$8,0,J8-J10-J25) -> 134750000 | ... AP27: =IF(AP$3>=Inputs!$B$8,0,AP8-AP10-AP25) -> 0
A28: Mezz closing | B28: =Inputs!$B$3*Inputs!$B$15 -> 37500000 | C28: =IF(C$3>=Inputs!$B$8,0,C15+C18) -> 37715194 | D28: =IF(D$3>=Inputs!$B$8,0,D15+D18) -> 37870034 | E28: =IF(E$3>=Inputs!$B$8,0,E15+E18) -> 37966572 | F28: =IF(F$3>=Inputs!$B$8,0,F15+F18) -> 38006405 | G28: =IF(G$3>=Inputs!$B$8,0,G15+G18) -> 38006405 | H28: =IF(H$3>=Inputs!$B$8,0,H15+H18) -> 38006405 | I28: =IF(I$3>=Inputs!$B$8,0,I15+I18) -> 38006405 | J28: =IF(J$3>=Inputs!$B$8,0,J15+J18) -> 38006405 | ... AP28: =IF(AP$3>=Inputs!$B$8,0,AP15+AP18) -> 0
A29: Pref closing | B29: =Inputs!$B$3*Inputs!$B$17 -> 25000000 | C29: =IF(C$3>=Inputs!$B$8,0,C20+C21-C22) -> 25750000 | D29: =IF(D$3>=Inputs!$B$8,0,D20+D21-D22) -> 26522500 | E29: =IF(E$3>=Inputs!$B$8,0,E20+E21-E22) -> 27318175 | F29: =IF(F$3>=Inputs!$B$8,0,F20+F21-F22) -> 28137720 | G29: =IF(G$3>=Inputs!$B$8,0,G20+G21-G22) -> 28966222 | H29: =IF(H$3>=Inputs!$B$8,0,H20+H21-H22) -> 29765493 | I29: =IF(I$3>=Inputs!$B$8,0,I20+I21-I22) -> 30536803 | J29: =IF(J$3>=Inputs!$B$8,0,J20+J21-J22) -> 31281136 | ... AP29: =IF(AP$3>=Inputs!$B$8,0,AP20+AP21-AP22) -> 0
A30: Gross sale | B30: =IF((B$3=Inputs!$B$8),B5*4*(1+Inputs!$B$6)/Inputs!$B$9,0) -> 0 | C30: =IF((C$3=Inputs!$B$8),C5*4*(1+Inputs!$B$6)/Inputs!$B$9,0) -> 0 | D30: =IF((D$3=Inputs!$B$8),D5*4*(1+Inputs!$B$6)/Inputs!$B$9,0) -> 0 | E30: =IF((E$3=Inputs!$B$8),E5*4*(1+Inputs!$B$6)/Inputs!$B$9,0) -> 0 | F30: =IF((F$3=Inputs!$B$8),F5*4*(1+Inputs!$B$6)/Inputs!$B$9,0) -> 0 | G30: =IF((G$3=Inputs!$B$8),G5*4*(1+Inputs!$B$6)/Inputs!$B$9,0) -> 0 | H30: =IF((H$3=Inputs!$B$8),H5*4*(1+Inputs!$B$6)/Inputs!$B$9,0) -> 0 | I30: =IF((I$3=Inputs!$B$8),I5*4*(1+Inputs!$B$6)/Inputs!$B$9,0) -> 0 | ... AP30: =IF((AP$3=Inputs!$B$8),AP5*4*(1+Inputs!$B$6)/Inputs!$B$9,0) -> 0
A31: Net sale | B31: =B30*(1-Inputs!$B$10) -> 0 | C31: =C30*(1-Inputs!$B$10) -> 0 | D31: =D30*(1-Inputs!$B$10) -> 0 | E31: =E30*(1-Inputs!$B$10) -> 0 | F31: =F30*(1-Inputs!$B$10) -> 0 | G31: =G30*(1-Inputs!$B$10) -> 0 | H31: =H30*(1-Inputs!$B$10) -> 0 | I31: =I30*(1-Inputs!$B$10) -> 0 | ... AP31: =AP30*(1-Inputs!$B$10) -> 0
A32: Common at exit | B32: =IF((B$3=Inputs!$B$8),B31-(B8-B10-B25)-(B15+B18)-(B20+B21-B22),0) -> 0 | C32: =IF((C$3=Inputs!$B$8),C31-(C8-C10-C25)-(C15+C18)-(C20+C21-C22),0) -> 0 | D32: =IF((D$3=Inputs!$B$8),D31-(D8-D10-D25)-(D15+D18)-(D20+D21-D22),0) -> 0 | E32: =IF((E$3=Inputs!$B$8),E31-(E8-E10-E25)-(E15+E18)-(E20+E21-E22),0) -> 0 | F32: =IF((F$3=Inputs!$B$8),F31-(F8-F10-F25)-(F15+F18)-(F20+F21-F22),0) -> 0 | G32: =IF((G$3=Inputs!$B$8),G31-(G8-G10-G25)-(G15+G18)-(G20+G21-G22),0) -> 0 | H32: =IF((H$3=Inputs!$B$8),H31-(H8-H10-H25)-(H15+H18)-(H20+H21-H22),0) -> 0 | I32: =IF((I$3=Inputs!$B$8),I31-(I8-I10-I25)-(I15+I18)-(I20+I21-I22),0) -> 0 | ... AP32: =IF((AP$3=Inputs!$B$8),AP31-(AP8-AP10-AP25)-(AP15+AP18)-(AP20+AP21-AP22),0) -> 0
A33: Common cash flow | B33: =-(Inputs!$B$3*(1+Inputs!$B$4)-Inputs!$B$3*Inputs!$B$11-Inputs!$B$3*Inputs!$B$15-Inputs!$B$3*Inputs!$B$17) -> -55000000 | C33: =C26-C14+C32 -> 0 | D33: =D26-D14+D32 -> 0 | E33: =E26-E14+E32 -> 0 | F33: =F26-F14+F32 -> 0 | G33: =G26-G14+G32 -> 0 | H33: =H26-H14+H32 -> 0 | I33: =I26-I14+I32 -> 0 | J33: =J26-J14+J32 -> 0 | ... AP33: =AP26-AP14+AP32 -> 0
A34: Senior cash flow | B34: =-Inputs!$B$3*Inputs!$B$11 -> -137500000 | C34: =C11+C25+IF((C$3=Inputs!$B$8),C8-C10-C25,0) -> 2558943.8 | D34: =D11+D25+IF((D$3=Inputs!$B$8),D8-D10-D25,0) -> 2521414.1 | E34: =E11+E25+IF((E$3=Inputs!$B$8),E8-E10-E25,0) -> 2487807.1 | F34: =F11+F25+IF((F$3=Inputs!$B$8),F8-F10-F25,0) -> 2457616.8 | G34: =G11+G25+IF((G$3=Inputs!$B$8),G8-G10-G25,0) -> 2430444.2 | H34: =H11+H25+IF((H$3=Inputs!$B$8),H8-H10-H25,0) -> 2405961.7 | I34: =I11+I25+IF((I$3=Inputs!$B$8),I8-I10-I25,0) -> 2383845.1 | J34: =J11+J25+IF((J$3=Inputs!$B$8),J8-J10-J25,0) -> 2363773.1 | ... AP34: =AP11+AP25+IF((AP$3=Inputs!$B$8),AP8-AP10-AP25,0) -> 0
A35: Mezz cash flow | B35: =-Inputs!$B$3*Inputs!$B$15 -> -37500000 | C35: =C17+IF((C$3=Inputs!$B$8),C15+C18,0) -> 816056.25 | D35: =D17+IF((D$3=Inputs!$B$8),D15+D18,0) -> 882327.08 | E35: =E17+IF((E$3=Inputs!$B$8),E15+E18,0) -> 944888.39 | F35: =F17+IF((F$3=Inputs!$B$8),F15+F18,0) -> 1004247.7 | G35: =G17+IF((G$3=Inputs!$B$8),G15+G18,0) -> 1045176.1 | H35: =H17+IF((H$3=Inputs!$B$8),H15+H18,0) -> 1045176.1 | I35: =I17+IF((I$3=Inputs!$B$8),I15+I18,0) -> 1045176.1 | J35: =J17+IF((J$3=Inputs!$B$8),J15+J18,0) -> 1045176.1 | ... AP35: =AP17+IF((AP$3=Inputs!$B$8),AP15+AP18,0) -> 0
A36: Pref cash flow | B36: =-Inputs!$B$3*Inputs!$B$17 -> -25000000 | C36: =C22+IF((C$3=Inputs!$B$8),C20+C21-C22,0) -> 0 | D36: =D22+IF((D$3=Inputs!$B$8),D20+D21-D22,0) -> 0 | E36: =E22+IF((E$3=Inputs!$B$8),E20+E21-E22,0) -> 0 | F36: =F22+IF((F$3=Inputs!$B$8),F20+F21-F22,0) -> 0 | G36: =G22+IF((G$3=Inputs!$B$8),G20+G21-G22,0) -> 15629.705 | H36: =H22+IF((H$3=Inputs!$B$8),H20+H21-H22,0) -> 69715.569 | I36: =I22+IF((I$3=Inputs!$B$8),I20+I21-I22,0) -> 121655.14 | J36: =J22+IF((J$3=Inputs!$B$8),J20+J21-J22,0) -> 171771.29 | ... AP36: =AP22+IF((AP$3=Inputs!$B$8),AP20+AP21-AP22,0) -> 0

Sheet Returns
A3: Common equity IRR | B3: =(1+IRR('Cash Flow'!B33:AP33,0.03))^4-1 -> 0.090114619
A4: Common equity multiple | B4: =SUMIF('Cash Flow'!B33:AP33,">0")/-SUMIF('Cash Flow'!B33:AP33,"<0") -> 1.8293851
A5: Mezzanine IRR | B5: =(1+IRR('Cash Flow'!B35:AP35,0.02))^4-1 -> 0.11462126
A6: Preferred equity IRR | B6: =(1+IRR('Cash Flow'!B36:AP36,0.02))^4-1 -> 0.12550881
A7: Senior IRR | B7: =(1+IRR('Cash Flow'!B34:AP34,0.01))^4-1 -> 0.06044823
A8: Minimum senior DSCR | B8: =MIN('Cash Flow'!C12:AP12) -> 1.3189036
A9: Quarters in cash trap | B9: =SUM('Cash Flow'!B24:AP24) -> 0
A10: Cash swept to senior ($) | B10: =SUM('Cash Flow'!B25:AP25) -> 0
A11: Peak mezzanine balance with PIK ($) | B11: =MAX('Cash Flow'!B28:AP28) -> 38006405
A12: Equity cures ($) | B12: =SUM('Cash Flow'!B14:AP14) -> 0
A13: Net sale proceeds ($) | B13: =SUM('Cash Flow'!B31:AP31) -> 3.0716831e+08
