Workbook

Sheet Inputs
A1: 70 FENCHURCH AVENUE – MULTI-LET OFFICE DCF (GBP)
A3: Valuation date | B3: 46023
A4: Purchase price (£) | B4: 245000000
A5: Purchase costs | B5: 0.068
A6: ERV growth a year | B6: 0.025
A7: Void on a new letting (months) | B7: 12
A8: Rent free, new letting (months) | B8: 18
A9: Rent free, renewal (months) | B9: 6
A10: Fit-out contribution, new (£/sq ft) | B10: 60
A11: Fit-out contribution, renewal (£/sq ft) | B11: 20
A12: Letting fees (% of first-year rent) | B12: 0.15
A13: Non-recoverable costs (% of rent) | B13: 0.04
A14: Discount rate | B14: 0.075
... A16: Sale costs | B16: 0.018

Sheet Tenancy
A1: Floor | B1: Tenant | C1: Area (sq ft) | D1: Passing rent (£/sq ft) | E1: Lease expiry | F1: ERV (£/sq ft) | G1: Renewal probability
A2: Ground | B2: Fenchurch Retail | C2: 12000 | D2: 72 | E2: 48023 | F2: 70 | G2: 0.6
A3: 1 | B3: Halden Insurance | C3: 21000 | D3: 61.5 | E3: 46470 | F3: 68 | G3: 0.55
A4: 2 | B4: Halden Insurance | C4: 21000 | D4: 61.5 | E4: 46470 | F4: 68 | G4: 0.55
A5: 3 | B5: Marlow Legal | C5: 21000 | D5: 64 | E5: 47389 | F5: 68 | G5: 0.7
A6: 4 | B6: Vacant | C6: 21000 | D6: 0 | E6: 46023 | F6: 68 | G6: 0
A7: 5 | B7: Coral Re | C7: 20500 | D7: 66 | E7: 48572 | F7: 69 | G7: 0.65
A8: 6 | B8: Tessel Bank | C8: 20500 | D8: 63 | E8: 46927 | F8: 69 | G8: 0.5
A9: 7 | B9: Tessel Bank | C9: 20500 | D9: 63 | E9: 46927 | F9: 69 | G9: 0.5
A10: 8 | B10: Arkwright Partners | C10: 19000 | D10: 70 | E10: 49027 | F10: 72 | G10: 0.6
A11: 9 | B11: Arkwright Partners | C11: 19000 | D11: 70 | E11: 49027 | F11: 72 | G11: 0.6
A12: 10 | B12: Nimbus Capital | C12: 17000 | D12: 78 | E12: 47841 | F12: 76 | G12: 0.45
A13: 11 | B13: Nimbus Capital | C13: 17000 | D13: 78 | E13: 47841 | F13: 76 | G13: 0.45

Sheet Rent
A2: Year | B2: Year start | C2: 1 | D2: 2 | E2: 3 | F2: 4 | G2: 5 | H2: 6 | I2: 7 | J2: 8 | K2: 9 | L2: 10 | M2: 11
A3: Year start date | C3: =EDATE(Inputs!$B$3,12*0) -> 46023 | D3: =EDATE(Inputs!$B$3,12*1) -> 46388 | E3: =EDATE(Inputs!$B$3,12*2) -> 46753 | F3: =EDATE(Inputs!$B$3,12*3) -> 47119 | G3: =EDATE(Inputs!$B$3,12*4) -> 47484 | H3: =EDATE(Inputs!$B$3,12*5) -> 47849 | I3: =EDATE(Inputs!$B$3,12*6) -> 48214 | J3: =EDATE(Inputs!$B$3,12*7) -> 48580 | K3: =EDATE(Inputs!$B$3,12*8) -> 48945 | L3: =EDATE(Inputs!$B$3,12*9) -> 49310 | M3: =EDATE(Inputs!$B$3,12*10) -> 49675
A4: Tenant rows: rent received (probability-weighted)
A5: =Tenancy!B2&" · "&Tenancy!A2 -> Fenchurch Retail · Ground | C5: =Tenancy!$C$2*(Tenancy!$D$2*MAX(0,MIN(1,YEARFRAC(C$3,MIN(Tenancy!$E$2,EDATE(C$3,12)),1)*(Tenancy!$E$2>C$3)))+Tenancy!$F$2*(1+Inputs!$B$6)^(C$2-1)*IF(Tenancy!$E$2<EDATE(C$3,12),Tenancy!$G$2*MAX(0,MAX(0,MIN(12,DATEDIF(MAX(Tenancy!$E$2,C$3),EDATE(C$3,12),"m")))-MAX(0,Inputs!$B$9-IF(Tenancy!$E$2<C$3,DATEDIF(Tenancy!$E$2,C$3,"m"),0)))/12+(1-Tenancy!$G$2)*MAX(0,MAX(0,MIN(12,DATEDIF(MAX(Tenancy!$E$2,C$3),EDATE(C$3,12),"m")))-MAX(0,Inputs!$B$7+Inputs!$B$8-IF(Tenancy!$E$2<C$3,DATEDIF(Tenancy!$E$2,C$3,"m"),0)))/12,0)) -> 864000 | D5: =Tenancy!$C$2*(Tenancy!$D$2*MAX(0,MIN(1,YEARFRAC(D$3,MIN(Tenancy!$E$2,EDATE(D$3,12)),1)*(Tenancy!$E$2>D$3)))+Tenancy!$F$2*(1+Inputs!$B$6)^(D$2-1)*IF(Tenancy!$E$2<EDATE(D$3,12),Tenancy!$G$2*MAX(0,MAX(0,MIN(12,DATEDIF(MAX(Tenancy!$E$2,D$3),EDATE(D$3,12),"m")))-MAX(0,Inputs!$B$9-IF(Tenancy!$E$2<D$3,DATEDIF(Tenancy!$E$2,D$3,"m"),0)))/12+(1-Tenancy!$G$2)*MAX(0,MAX(0,MIN(12,DATEDIF(MAX(Tenancy!$E$2,D$3),EDATE(D$3,12),"m")))-MAX(0,Inputs!$B$7+Inputs!$B$8-IF(Tenancy!$E$2<D$3,DATEDIF(Tenancy!$E$2,D$3,"m"),0)))/12,0)) -> 864000 | E5: =Tenancy!$C$2*(Tenancy!$D$2*MAX(0,MIN(1,YEARFRAC(E$3,MIN(Tenancy!$E$2,EDATE(E$3,12)),1)*(Tenancy!$E$2>E$3)))+Tenancy!$F$2*(1+Inputs!$B$6)^(E$2-1)*IF(Tenancy!$E$2<EDATE(E$3,12),Tenancy!$G$2*MAX(0,MAX(0,MIN(12,DATEDIF(MAX(Tenancy!$E$2,E$3),EDATE(E$3,12),"m")))-MAX(0,Inputs!$B$9-IF(Tenancy!$E$2<E$3,DATEDIF(Tenancy!$E$2,E$3,"m"),0)))/12+(1-Tenancy!$G$2)*MAX(0,MAX(0,MIN(12,DATEDIF(MAX(Tenancy!$E$2,E$3),EDATE(E$3,12),"m")))-MAX(0,Inputs!$B$7+Inputs!$B$8-IF(Tenancy!$E$2<E$3,DATEDIF(Tenancy!$E$2,E$3,"m"),0)))/12,0)) -> 864000 | F5: =Tenancy!$C$2*(Tenancy!$D$2*MAX(0,MIN(1,YEARFRAC(F$3,MIN(Tenancy!$E$2,EDATE(F$3,12)),1)*(Tenancy!$E$2>F$3)))+Tenancy!$F$2*(1+Inputs!$B$6)^(F$2-1)*IF(Tenancy!$E$2<EDATE(F$3,12),Tenancy!$G$2*MAX(0,MAX(0,MIN(12,DATEDIF(MAX(Tenancy!$E$2,F$3),EDATE(F$3,12),"m")))-MAX(0,Inputs!$B$9-IF(Tenancy!$E$2<F$3,DATEDIF(Tenancy!$E$2,F$3,"m"),0)))/12+(1-Tenancy!$G$2)*MAX(0,MAX(0,MIN(12,DATEDIF(MAX(Tenancy!$E$2,F$3),EDATE(F$3,12),"m")))-MAX(0,Inputs!$B$7+Inputs!$B$8-IF(Tenancy!$E$2<F$3,DATEDIF(Tenancy!$E$2,F$3,"m"),0)))/12,0)) -> 864000 | G5: =Tenancy!$C$2*(Tenancy!$D$2*MAX(0,MIN(1,YEARFRAC(G$3,MIN(Tenancy!$E$2,EDATE(G$3,12)),1)*(Tenancy!$E$2>G$3)))+Tenancy!$F$2*(1+Inputs!$B$6)^(G$2-1)*IF(Tenancy!$E$2<EDATE(G$3,12),Tenancy!$G$2*MAX(0,MAX(0,MIN(12,DATEDIF(MAX(Tenancy!$E$2,G$3),EDATE(G$3,12),"m")))-MAX(0,Inputs!$B$9-IF(Tenancy!$E$2<G$3,DATEDIF(Tenancy!$E$2,G$3,"m"),0)))/12+(1-Tenancy!$G$2)*MAX(0,MAX(0,MIN(12,DATEDIF(MAX(Tenancy!$E$2,G$3),EDATE(G$3,12),"m")))-MAX(0,Inputs!$B$7+Inputs!$B$8-IF(Tenancy!$E$2<G$3,DATEDIF(Tenancy!$E$2,G$3,"m"),0)))/12,0)) -> 864000 | H5: =Tenancy!$C$2*(Tenancy!$D$2*MAX(0,MIN(1,YEARFRAC(H$3,MIN(Tenancy!$E$2,EDATE(H$3,12)),1)*(Tenancy!$E$2>H$3)))+Tenancy!$F$2*(1+Inputs!$B$6)^(H$2-1)*IF(Tenancy!$E$2<EDATE(H$3,12),Tenancy!$G$2*MAX(0,MAX(0,MIN(12,DATEDIF(MAX(Tenancy!$E$2,H$3),EDATE(H$3,12),"m")))-MAX(0,Inputs!$B$9-IF(Tenancy!$E$2<H$3,DATEDIF(Tenancy!$E$2,H$3,"m"),0)))/12+(1-Tenancy!$G$2)*MAX(0,MAX(0,MIN(12,DATEDIF(MAX(Tenancy!$E$2,H$3),EDATE(H$3,12),"m")))-MAX(0,Inputs!$B$7+Inputs!$B$8-IF(Tenancy!$E$2<H$3,DATEDIF(Tenancy!$E$2,H$3,"m"),0)))/12,0)) -> 411879.45 | I5: =Tenancy!$C$2*(Tenancy!$D$2*MAX(0,MIN(1,YEARFRAC(I$3,MIN(Tenancy!$E$2,EDATE(I$3,12)),1)*(Tenancy!$E$2>I$3)))+Tenancy!$F$2*(1+Inputs!$B$6)^(I$2-1)*IF(Tenancy!$E$2<EDATE(I$3,12),Tenancy!$G$2*MAX(0,MAX(0,MIN(12,DATEDIF(MAX(Tenancy!$E$2,I$3),EDATE(I$3,12),"m")))-MAX(0,Inputs!$B$9-IF(Tenancy!$E$2<I$3,DATEDIF(Tenancy!$E$2,I$3,"m"),0)))/12+(1-Tenancy!$G$2)*MAX(0,MAX(0,MIN(12,DATEDIF(MAX(Tenancy!$E$2,I$3),EDATE(I$3,12),"m")))-MAX(0,Inputs!$B$7+Inputs!$B$8-IF(Tenancy!$E$2<I$3,DATEDIF(Tenancy!$E$2,I$3,"m"),0)))/12,0)) -> 584485.48 | J5: =Tenancy!$C$2*(Tenancy!$D$2*MAX(0,MIN(1,YEARFRAC(J$3,MIN(Tenancy!$E$2,EDATE(J$3,12)),1)*(Tenancy!$E$2>J$3)))+Tenancy!$F$2*(1+Inputs!$B$6)^(J$2-1)*IF(Tenancy!$E$2<EDATE(J$3,12),Tenancy!$G$2*MAX(0,MAX(0,MIN(12,DATEDIF(MAX(Tenancy!$E$2,J$3),EDATE(J$3,12),"m")))-MAX(0,Inputs!$B$9-IF(Tenancy!$E$2<J$3,DATEDIF(Tenancy!$E$2,J$3,"m"),0)))/12+(1-Tenancy!$G$2)*MAX(0,MAX(0,MIN(12,DATEDIF(MAX(Tenancy!$E$2,J$3),EDATE(J$3,12),"m")))-MAX(0,Inputs!$B$7+Inputs!$B$8-IF(Tenancy!$E$2<J$3,DATEDIF(Tenancy!$E$2,J$3,"m"),0)))/12,0)) -> 599097.62 | ... M5: =Tenancy!$C$2*(Tenancy!$D$2*MAX(0,MIN(1,YEARFRAC(M$3,MIN(Tenancy!$E$2,EDATE(M$3,12)),1)*(Tenancy!$E$2>M$3)))+Tenancy!$F$2*(1+Inputs!$B$6)^(M$2-1)*IF(Tenancy!$E$2<EDATE(M$3,12),Tenancy!$G$2*MAX(0,MAX(0,MIN(12,DATEDIF(MAX(Tenancy!$E$2,M$3),EDATE(M$3,12),"m")))-MAX(0,Inputs!$B$9-IF(Tenancy!$E$2<M$3,DATEDIF(Tenancy!$E$2,M$3,"m"),0)))/12+(1-Tenancy!$G$2)*MAX(0,MAX(0,MIN(12,DATEDIF(MAX(Tenancy!$E$2,M$3),EDATE(M$3,12),"m")))-MAX(0,Inputs!$B$7+Inputs!$B$8-IF(Tenancy!$E$2<M$3,DATEDIF(Tenancy!$E$2,M$3,"m"),0)))/12,0)) -> 1075271
A6: =Tenancy!B3&" · "&Tenancy!A3 -> Halden Insurance · 1 | C6: =Tenancy!$C$3*(Tenancy!$D$3*MAX(0,MIN(1,YEARFRAC(C$3,MIN(Tenancy!$E$3,EDATE(C$3,12)),1)*(Tenancy!$E$3>C$3)))+Tenancy!$F$3*(1+Inputs!$B$6)^(C$2-1)*IF(Tenancy!$E$3<EDATE(C$3,12),Tenancy!$G$3*MAX(0,MAX(0,MIN(12,DATEDIF(MAX(Tenancy!$E$3,C$3),EDATE(C$3,12),"m")))-MAX(0,Inputs!$B$9-IF(Tenancy!$E$3<C$3,DATEDIF(Tenancy!$E$3,C$3,"m"),0)))/12+(1-Tenancy!$G$3)*MAX(0,MAX(0,MIN(12,DATEDIF(MAX(Tenancy!$E$3,C$3),EDATE(C$3,12),"m")))-MAX(0,Inputs!$B$7+Inputs!$B$8-IF(Tenancy!$E$3<C$3,DATEDIF(Tenancy!$E$3,C$3,"m"),0)))/12,0)) -> 1291500 | D6: =Tenancy!$C$3*(Tenancy!$D$3*MAX(0,MIN(1,YEARFRAC(D$3,MIN(Tenancy!$E$3,EDATE(D$3,12)),1)*(Tenancy!$E$3>D$3)))+Tenancy!$F$3*(1+Inputs!$B$6)^(D$2-1)*IF(Tenancy!$E$3<EDATE(D$3,12),Tenancy!$G$3*MAX(0,MAX(0,MIN(12,DATEDIF(MAX(Tenancy!$E$3,D$3),EDATE(D$3,12),"m")))-MAX(0,Inputs!$B$9-IF(Tenancy!$E$3<D$3,DATEDIF(Tenancy!$E$3,D$3,"m"),0)))/12+(1-Tenancy!$G$3)*MAX(0,MAX(0,MIN(12,DATEDIF(MAX(Tenancy!$E$3,D$3),EDATE(D$3,12),"m")))-MAX(0,Inputs!$B$7+Inputs!$B$8-IF(Tenancy!$E$3<D$3,DATEDIF(Tenancy!$E$3,D$3,"m"),0)))/12,0)) -> 491403.96 | E6: =Tenancy!$C$3*(Tenancy!$D$3*MAX(0,MIN(1,YEARFRAC(E$3,MIN(Tenancy!$E$3,EDATE(E$3,12)),1)*(Tenancy!$E$3>E$3)))+Tenancy!$F$3*(1+Inputs!$B$6)^(E$2-1)*IF(Tenancy!$E$3<EDATE(E$3,12),Tenancy!$G$3*MAX(0,MAX(0,MIN(12,DATEDIF(MAX(Tenancy!$E$3,E$3),EDATE(E$3,12),"m")))-MAX(0,Inputs!$B$9-IF(Tenancy!$E$3<E$3,DATEDIF(Tenancy!$E$3,E$3,"m"),0)))/12+(1-Tenancy!$G$3)*MAX(0,MAX(0,MIN(12,DATEDIF(MAX(Tenancy!$E$3,E$3),EDATE(E$3,12),"m")))-MAX(0,Inputs!$B$7+Inputs!$B$8-IF(Tenancy!$E$3<E$3,DATEDIF(Tenancy!$E$3,E$3,"m"),0)))/12,0)) -> 825160.88 | F6: =Tenancy!$C$3*(Tenancy!$D$3*MAX(0,MIN(1,YEARFRAC(F$3,MIN(Tenancy!$E$3,EDATE(F$3,12)),1)*(Tenancy!$E$3>F$3)))+Tenancy!$F$3*(1+Inputs!$B$6)^(F$2-1)*IF(Tenancy!$E$3<EDATE(F$3,12),Tenancy!$G$3*MAX(0,MAX(0,MIN(12,DATEDIF(MAX(Tenancy!$E$3,F$3),EDATE(F$3,12),"m")))-MAX(0,Inputs!$B$9-IF(Tenancy!$E$3<F$3,DATEDIF(Tenancy!$E$3,F$3,"m"),0)))/12+(1-Tenancy!$G$3)*MAX(0,MAX(0,MIN(12,DATEDIF(MAX(Tenancy!$E$3,F$3),EDATE(F$3,12),"m")))-MAX(0,Inputs!$B$7+Inputs!$B$8-IF(Tenancy!$E$3<F$3,DATEDIF(Tenancy!$E$3,F$3,"m"),0)))/12,0)) -> 1018792.4 | G6: =Tenancy!$C$3*(Tenancy!$D$3*MAX(0,MIN(1,YEARFRAC(G$3,MIN(Tenancy!$E$3,EDATE(G$3,12)),1)*(Tenancy!$E$3>G$3)))+Tenancy!$F$3*(1+Inputs!$B$6)^(G$2-1)*IF(Tenancy!$E$3<EDATE(G$3,12),Tenancy!$G$3*MAX(0,MAX(0,MIN(12,DATEDIF(MAX(Tenancy!$E$3,G$3),EDATE(G$3,12),"m")))-MAX(0,Inputs!$B$9-IF(Tenancy!$E$3<G$3,DATEDIF(Tenancy!$E$3,G$3,"m"),0)))/12+(1-Tenancy!$G$3)*MAX(0,MAX(0,MIN(12,DATEDIF(MAX(Tenancy!$E$3,G$3),EDATE(G$3,12),"m")))-MAX(0,Inputs!$B$7+Inputs!$B$8-IF(Tenancy!$E$3<G$3,DATEDIF(Tenancy!$E$3,G$3,"m"),0)))/12,0)) -> 1576244.8 | H6: =Tenancy!$C$3*(Tenancy!$D$3*MAX(0,MIN(1,YEARFRAC(H$3,MIN(Tenancy!$E$3,EDATE(H$3,12)),1)*(Tenancy!$E$3>H$3)))+Tenancy!$F$3*(1+Inputs!$B$6)^(H$2-1)*IF(Tenancy!$E$3<EDATE(H$3,12),Tenancy!$G$3*MAX(0,MAX(0,MIN(12,DATEDIF(MAX(Tenancy!$E$3,H$3),EDATE(H$3,12),"m")))-MAX(0,Inputs!$B$9-IF(Tenancy!$E$3<H$3,DATEDIF(Tenancy!$E$3,H$3,"m"),0)))/12+(1-Tenancy!$G$3)*MAX(0,MAX(0,MIN(12,DATEDIF(MAX(Tenancy!$E$3,H$3),EDATE(H$3,12),"m")))-MAX(0,Inputs!$B$7+Inputs!$B$8-IF(Tenancy!$E$3<H$3,DATEDIF(Tenancy!$E$3,H$3,"m"),0)))/12,0)) -> 1615650.9 | I6: =Tenancy!$C$3*(Tenancy!$D$3*MAX(0,MIN(1,YEARFRAC(I$3,MIN(Tenancy!$E$3,EDATE(I$3,12)),1)*(Tenancy!$E$3>I$3)))+Tenancy!$F$3*(1+Inputs!$B$6)^(I$2-1)*IF(Tenancy!$E$3<EDATE(I$3,12),Tenancy!$G$3*MAX(0,MAX(0,MIN(12,DATEDIF(MAX(Tenancy!$E$3,I$3),EDATE(I$3,12),"m")))-MAX(0,Inputs!$B$9-IF(Tenancy!$E$3<I$3,DATEDIF(Tenancy!$E$3,I$3,"m"),0)))/12+(1-Tenancy!$G$3)*MAX(0,MAX(0,MIN(12,DATEDIF(MAX(Tenancy!$E$3,I$3),EDATE(I$3,12),"m")))-MAX(0,Inputs!$B$7+Inputs!$B$8-IF(Tenancy!$E$3<I$3,DATEDIF(Tenancy!$E$3,I$3,"m"),0)))/12,0)) -> 1656042.2 | J6: =Tenancy!$C$3*(Tenancy!$D$3*MAX(0,MIN(1,YEARFRAC(J$3,MIN(Tenancy!$E$3,EDATE(J$3,12)),1)*(Tenancy!$E$3>J$3)))+Tenancy!$F$3*(1+Inputs!$B$6)^(J$2-1)*IF(Tenancy!$E$3<EDATE(J$3,12),Tenancy!$G$3*MAX(0,MAX(0,MIN(12,DATEDIF(MAX(Tenancy!$E$3,J$3),EDATE(J$3,12),"m")))-MAX(0,Inputs!$B$9-IF(Tenancy!$E$3<J$3,DATEDIF(Tenancy!$E$3,J$3,"m"),0)))/12+(1-Tenancy!$G$3)*MAX(0,MAX(0,MIN(12,DATEDIF(MAX(Tenancy!$E$3,J$3),EDATE(J$3,12),"m")))-MAX(0,Inputs!$B$7+Inputs!$B$8-IF(Tenancy!$E$3<J$3,DATEDIF(Tenancy!$E$3,J$3,"m"),0)))/12,0)) -> 1697443.3 | ... M6: =Tenancy!$C$3*(Tenancy!$D$3*MAX(0,MIN(1,YEARFRAC(M$3,MIN(Tenancy!$E$3,EDATE(M$3,12)),1)*(Tenancy!$E$3>M$3)))+Tenancy!$F$3*(1+Inputs!$B$6)^(M$2-1)*IF(Tenancy!$E$3<EDATE(M$3,12),Tenancy!$G$3*MAX(0,MAX(0,MIN(12,DATEDIF(MAX(Tenancy!$E$3,M$3),EDATE(M$3,12),"m")))-MAX(0,Inputs!$B$9-IF(Tenancy!$E$3<M$3,DATEDIF(Tenancy!$E$3,M$3,"m"),0)))/12+(1-Tenancy!$G$3)*MAX(0,MAX(0,MIN(12,DATEDIF(MAX(Tenancy!$E$3,M$3),EDATE(M$3,12),"m")))-MAX(0,Inputs!$B$7+Inputs!$B$8-IF(Tenancy!$E$3<M$3,DATEDIF(Tenancy!$E$3,M$3,"m"),0)))/12,0)) -> 1827960.7
A7: =Tenancy!B4&" · "&Tenancy!A4 -> Halden Insurance · 2 | C7: =Tenancy!$C$4*(Tenancy!$D$4*MAX(0,MIN(1,YEARFRAC(C$3,MIN(Tenancy!$E$4,EDATE(C$3,12)),1)*(Tenancy!$E$4>C$3)))+Tenancy!$F$4*(1+Inputs!$B$6)^(C$2-1)*IF(Tenancy!$E$4<EDATE(C$3,12),Tenancy!$G$4*MAX(0,MAX(0,MIN(12,DATEDIF(MAX(Tenancy!$E$4,C$3),EDATE(C$3,12),"m")))-MAX(0,Inputs!$B$9-IF(Tenancy!$E$4<C$3,DATEDIF(Tenancy!$E$4,C$3,"m"),0)))/12+(1-Tenancy!$G$4)*MAX(0,MAX(0,MIN(12,DATEDIF(MAX(Tenancy!$E$4,C$3),EDATE(C$3,12),"m")))-MAX(0,Inputs!$B$7+Inputs!$B$8-IF(Tenancy!$E$4<C$3,DATEDIF(Tenancy!$E$4,C$3,"m"),0)))/12,0)) -> 1291500 | D7: =Tenancy!$C$4*(Tenancy!$D$4*MAX(0,MIN(1,YEARFRAC(D$3,MIN(Tenancy!$E$4,EDATE(D$3,12)),1)*(Tenancy!$E$4>D$3)))+Tenancy!$F$4*(1+Inputs!$B$6)^(D$2-1)*IF(Tenancy!$E$4<EDATE(D$3,12),Tenancy!$G$4*MAX(0,MAX(0,MIN(12,DATEDIF(MAX(Tenancy!$E$4,D$3),EDATE(D$3,12),"m")))-MAX(0,Inputs!$B$9-IF(Tenancy!$E$4<D$3,DATEDIF(Tenancy!$E$4,D$3,"m"),0)))/12+(1-Tenancy!$G$4)*MAX(0,MAX(0,MIN(12,DATEDIF(MAX(Tenancy!$E$4,D$3),EDATE(D$3,12),"m")))-MAX(0,Inputs!$B$7+Inputs!$B$8-IF(Tenancy!$E$4<D$3,DATEDIF(Tenancy!$E$4,D$3,"m"),0)))/12,0)) -> 491403.96 | E7: =Tenancy!$C$4*(Tenancy!$D$4*MAX(0,MIN(1,YEARFRAC(E$3,MIN(Tenancy!$E$4,EDATE(E$3,12)),1)*(Tenancy!$E$4>E$3)))+Tenancy!$F$4*(1+Inputs!$B$6)^(E$2-1)*IF(Tenancy!$E$4<EDATE(E$3,12),Tenancy!$G$4*MAX(0,MAX(0,MIN(12,DATEDIF(MAX(Tenancy!$E$4,E$3),EDATE(E$3,12),"m")))-MAX(0,Inputs!$B$9-IF(Tenancy!$E$4<E$3,DATEDIF(Tenancy!$E$4,E$3,"m"),0)))/12+(1-Tenancy!$G$4)*MAX(0,MAX(0,MIN(12,DATEDIF(MAX(Tenancy!$E$4,E$3),EDATE(E$3,12),"m")))-MAX(0,Inputs!$B$7+Inputs!$B$8-IF(Tenancy!$E$4<E$3,DATEDIF(Tenancy!$E$4,E$3,"m"),0)))/12,0)) -> 825160.88 | F7: =Tenancy!$C$4*(Tenancy!$D$4*MAX(0,MIN(1,YEARFRAC(F$3,MIN(Tenancy!$E$4,EDATE(F$3,12)),1)*(Tenancy!$E$4>F$3)))+Tenancy!$F$4*(1+Inputs!$B$6)^(F$2-1)*IF(Tenancy!$E$4<EDATE(F$3,12),Tenancy!$G$4*MAX(0,MAX(0,MIN(12,DATEDIF(MAX(Tenancy!$E$4,F$3),EDATE(F$3,12),"m")))-MAX(0,Inputs!$B$9-IF(Tenancy!$E$4<F$3,DATEDIF(Tenancy!$E$4,F$3,"m"),0)))/12+(1-Tenancy!$G$4)*MAX(0,MAX(0,MIN(12,DATEDIF(MAX(Tenancy!$E$4,F$3),EDATE(F$3,12),"m")))-MAX(0,Inputs!$B$7+Inputs!$B$8-IF(Tenancy!$E$4<F$3,DATEDIF(Tenancy!$E$4,F$3,"m"),0)))/12,0)) -> 1018792.4 | G7: =Tenancy!$C$4*(Tenancy!$D$4*MAX(0,MIN(1,YEARFRAC(G$3,MIN(Tenancy!$E$4,EDATE(G$3,12)),1)*(Tenancy!$E$4>G$3)))+Tenancy!$F$4*(1+Inputs!$B$6)^(G$2-1)*IF(Tenancy!$E$4<EDATE(G$3,12),Tenancy!$G$4*MAX(0,MAX(0,MIN(12,DATEDIF(MAX(Tenancy!$E$4,G$3),EDATE(G$3,12),"m")))-MAX(0,Inputs!$B$9-IF(Tenancy!$E$4<G$3,DATEDIF(Tenancy!$E$4,G$3,"m"),0)))/12+(1-Tenancy!$G$4)*MAX(0,MAX(0,MIN(12,DATEDIF(MAX(Tenancy!$E$4,G$3),EDATE(G$3,12),"m")))-MAX(0,Inputs!$B$7+Inputs!$B$8-IF(Tenancy!$E$4<G$3,DATEDIF(Tenancy!$E$4,G$3,"m"),0)))/12,0)) -> 1576244.8 | H7: =Tenancy!$C$4*(Tenancy!$D$4*MAX(0,MIN(1,YEARFRAC(H$3,MIN(Tenancy!$E$4,EDATE(H$3,12)),1)*(Tenancy!$E$4>H$3)))+Tenancy!$F$4*(1+Inputs!$B$6)^(H$2-1)*IF(Tenancy!$E$4<EDATE(H$3,12),Tenancy!$G$4*MAX(0,MAX(0,MIN(12,DATEDIF(MAX(Tenancy!$E$4,H$3),EDATE(H$3,12),"m")))-MAX(0,Inputs!$B$9-IF(Tenancy!$E$4<H$3,DATEDIF(Tenancy!$E$4,H$3,"m"),0)))/12+(1-Tenancy!$G$4)*MAX(0,MAX(0,MIN(12,DATEDIF(MAX(Tenancy!$E$4,H$3),EDATE(H$3,12),"m")))-MAX(0,Inputs!$B$7+Inputs!$B$8-IF(Tenancy!$E$4<H$3,DATEDIF(Tenancy!$E$4,H$3,"m"),0)))/12,0)) -> 1615650.9 | I7: =Tenancy!$C$4*(Tenancy!$D$4*MAX(0,MIN(1,YEARFRAC(I$3,MIN(Tenancy!$E$4,EDATE(I$3,12)),1)*(Tenancy!$E$4>I$3)))+Tenancy!$F$4*(1+Inputs!$B$6)^(I$2-1)*IF(Tenancy!$E$4<EDATE(I$3,12),Tenancy!$G$4*MAX(0,MAX(0,MIN(12,DATEDIF(MAX(Tenancy!$E$4,I$3),EDATE(I$3,12),"m")))-MAX(0,Inputs!$B$9-IF(Tenancy!$E$4<I$3,DATEDIF(Tenancy!$E$4,I$3,"m"),0)))/12+(1-Tenancy!$G$4)*MAX(0,MAX(0,MIN(12,DATEDIF(MAX(Tenancy!$E$4,I$3),EDATE(I$3,12),"m")))-MAX(0,Inputs!$B$7+Inputs!$B$8-IF(Tenancy!$E$4<I$3,DATEDIF(Tenancy!$E$4,I$3,"m"),0)))/12,0)) -> 1656042.2 | J7: =Tenancy!$C$4*(Tenancy!$D$4*MAX(0,MIN(1,YEARFRAC(J$3,MIN(Tenancy!$E$4,EDATE(J$3,12)),1)*(Tenancy!$E$4>J$3)))+Tenancy!$F$4*(1+Inputs!$B$6)^(J$2-1)*IF(Tenancy!$E$4<EDATE(J$3,12),Tenancy!$G$4*MAX(0,MAX(0,MIN(12,DATEDIF(MAX(Tenancy!$E$4,J$3),EDATE(J$3,12),"m")))-MAX(0,Inputs!$B$9-IF(Tenancy!$E$4<J$3,DATEDIF(Tenancy!$E$4,J$3,"m"),0)))/12+(1-Tenancy!$G$4)*MAX(0,MAX(0,MIN(12,DATEDIF(MAX(Tenancy!$E$4,J$3),EDATE(J$3,12),"m")))-MAX(0,Inputs!$B$7+Inputs!$B$8-IF(Tenancy!$E$4<J$3,DATEDIF(Tenancy!$E$4,J$3,"m"),0)))/12,0)) -> 1697443.3 | ... M7: =Tenancy!$C$4*(Tenancy!$D$4*MAX(0,MIN(1,YEARFRAC(M$3,MIN(Tenancy!$E$4,EDATE(M$3,12)),1)*(Tenancy!$E$4>M$3)))+Tenancy!$F$4*(1+Inputs!$B$6)^(M$2-1)*IF(Tenancy!$E$4<EDATE(M$3,12),Tenancy!$G$4*MAX(0,MAX(0,MIN(12,DATEDIF(MAX(Tenancy!$E$4,M$3),EDATE(M$3,12),"m")))-MAX(0,Inputs!$B$9-IF(Tenancy!$E$4<M$3,DATEDIF(Tenancy!$E$4,M$3,"m"),0)))/12+(1-Tenancy!$G$4)*MAX(0,MAX(0,MIN(12,DATEDIF(MAX(Tenancy!$E$4,M$3),EDATE(M$3,12),"m")))-MAX(0,Inputs!$B$7+Inputs!$B$8-IF(Tenancy!$E$4<M$3,DATEDIF(Tenancy!$E$4,M$3,"m"),0)))/12,0)) -> 1827960.7
A8: =Tenancy!B5&" · "&Tenancy!A5 -> Marlow Legal · 3 | C8: =Tenancy!$C$5*(Tenancy!$D$5*MAX(0,MIN(1,YEARFRAC(C$3,MIN(Tenancy!$E$5,EDATE(C$3,12)),1)*(Tenancy!$E$5>C$3)))+Tenancy!$F$5*(1+Inputs!$B$6)^(C$2-1)*IF(Tenancy!$E$5<EDATE(C$3,12),Tenancy!$G$5*MAX(0,MAX(0,MIN(12,DATEDIF(MAX(Tenancy!$E$5,C$3),EDATE(C$3,12),"m")))-MAX(0,Inputs!$B$9-IF(Tenancy!$E$5<C$3,DATEDIF(Tenancy!$E$5,C$3,"m"),0)))/12+(1-Tenancy!$G$5)*MAX(0,MAX(0,MIN(12,DATEDIF(MAX(Tenancy!$E$5,C$3),EDATE(C$3,12),"m")))-MAX(0,Inputs!$B$7+Inputs!$B$8-IF(Tenancy!$E$5<C$3,DATEDIF(Tenancy!$E$5,C$3,"m"),0)))/12,0)) -> 1344000 | D8: =Tenancy!$C$5*(Tenancy!$D$5*MAX(0,MIN(1,YEARFRAC(D$3,MIN(Tenancy!$E$5,EDATE(D$3,12)),1)*(Tenancy!$E$5>D$3)))+Tenancy!$F$5*(1+Inputs!$B$6)^(D$2-1)*IF(Tenancy!$E$5<EDATE(D$3,12),Tenancy!$G$5*MAX(0,MAX(0,MIN(12,DATEDIF(MAX(Tenancy!$E$5,D$3),EDATE(D$3,12),"m")))-MAX(0,Inputs!$B$9-IF(Tenancy!$E$5<D$3,DATEDIF(Tenancy!$E$5,D$3,"m"),0)))/12+(1-Tenancy!$G$5)*MAX(0,MAX(0,MIN(12,DATEDIF(MAX(Tenancy!$E$5,D$3),EDATE(D$3,12),"m")))-MAX(0,Inputs!$B$7+Inputs!$B$8-IF(Tenancy!$E$5<D$3,DATEDIF(Tenancy!$E$5,D$3,"m"),0)))/12,0)) -> 1344000 | E8: =Tenancy!$C$5*(Tenancy!$D$5*MAX(0,MIN(1,YEARFRAC(E$3,MIN(Tenancy!$E$5,EDATE(E$3,12)),1)*(Tenancy!$E$5>E$3)))+Tenancy!$F$5*(1+Inputs!$B$6)^(E$2-1)*IF(Tenancy!$E$5<EDATE(E$3,12),Tenancy!$G$5*MAX(0,MAX(0,MIN(12,DATEDIF(MAX(Tenancy!$E$5,E$3),EDATE(E$3,12),"m")))-MAX(0,Inputs!$B$9-IF(Tenancy!$E$5<E$3,DATEDIF(Tenancy!$E$5,E$3,"m"),0)))/12+(1-Tenancy!$G$5)*MAX(0,MAX(0,MIN(12,DATEDIF(MAX(Tenancy!$E$5,E$3),EDATE(E$3,12),"m")))-MAX(0,Inputs!$B$7+Inputs!$B$8-IF(Tenancy!$E$5<E$3,DATEDIF(Tenancy!$E$5,E$3,"m"),0)))/12,0)) -> 1344000 | F8: =Tenancy!$C$5*(Tenancy!$D$5*MAX(0,MIN(1,YEARFRAC(F$3,MIN(Tenancy!$E$5,EDATE(F$3,12)),1)*(Tenancy!$E$5>F$3)))+Tenancy!$F$5*(1+Inputs!$B$6)^(F$2-1)*IF(Tenancy!$E$5<EDATE(F$3,12),Tenancy!$G$5*MAX(0,MAX(0,MIN(12,DATEDIF(MAX(Tenancy!$E$5,F$3),EDATE(F$3,12),"m")))-MAX(0,Inputs!$B$9-IF(Tenancy!$E$5<F$3,DATEDIF(Tenancy!$E$5,F$3,"m"),0)))/12+(1-Tenancy!$G$5)*MAX(0,MAX(0,MIN(12,DATEDIF(MAX(Tenancy!$E$5,F$3),EDATE(F$3,12),"m")))-MAX(0,Inputs!$B$7+Inputs!$B$8-IF(Tenancy!$E$5<F$3,DATEDIF(Tenancy!$E$5,F$3,"m"),0)))/12,0)) -> 994191.78 | G8: =Tenancy!$C$5*(Tenancy!$D$5*MAX(0,MIN(1,YEARFRAC(G$3,MIN(Tenancy!$E$5,EDATE(G$3,12)),1)*(Tenancy!$E$5>G$3)))+Tenancy!$F$5*(1+Inputs!$B$6)^(G$2-1)*IF(Tenancy!$E$5<EDATE(G$3,12),Tenancy!$G$5*MAX(0,MAX(0,MIN(12,DATEDIF(MAX(Tenancy!$E$5,G$3),EDATE(G$3,12),"m")))-MAX(0,Inputs!$B$9-IF(Tenancy!$E$5<G$3,DATEDIF(Tenancy!$E$5,G$3,"m"),0)))/12+(1-Tenancy!$G$5)*MAX(0,MAX(0,MIN(12,DATEDIF(MAX(Tenancy!$E$5,G$3),EDATE(G$3,12),"m")))-MAX(0,Inputs!$B$7+Inputs!$B$8-IF(Tenancy!$E$5<G$3,DATEDIF(Tenancy!$E$5,G$3,"m"),0)))/12,0)) -> 827528.52 | H8: =Tenancy!$C$5*(Tenancy!$D$5*MAX(0,MIN(1,YEARFRAC(H$3,MIN(Tenancy!$E$5,EDATE(H$3,12)),1)*(Tenancy!$E$5>H$3)))+Tenancy!$F$5*(1+Inputs!$B$6)^(H$2-1)*IF(Tenancy!$E$5<EDATE(H$3,12),Tenancy!$G$5*MAX(0,MAX(0,MIN(12,DATEDIF(MAX(Tenancy!$E$5,H$3),EDATE(H$3,12),"m")))-MAX(0,Inputs!$B$9-IF(Tenancy!$E$5<H$3,DATEDIF(Tenancy!$E$5,H$3,"m"),0)))/12+(1-Tenancy!$G$5)*MAX(0,MAX(0,MIN(12,DATEDIF(MAX(Tenancy!$E$5,H$3),EDATE(H$3,12),"m")))-MAX(0,Inputs!$B$7+Inputs!$B$8-IF(Tenancy!$E$5<H$3,DATEDIF(Tenancy!$E$5,H$3,"m"),0)))/12,0)) -> 1130955.6 | I8: =Tenancy!$C$5*(Tenancy!$D$5*MAX(0,MIN(1,YEARFRAC(I$3,MIN(Tenancy!$E$5,EDATE(I$3,12)),1)*(Tenancy!$E$5>I$3)))+Tenancy!$F$5*(1+Inputs!$B$6)^(I$2-1)*IF(Tenancy!$E$5<EDATE(I$3,12),Tenancy!$G$5*MAX(0,MAX(0,MIN(12,DATEDIF(MAX(Tenancy!$E$5,I$3),EDATE(I$3,12),"m")))-MAX(0,Inputs!$B$9-IF(Tenancy!$E$5<I$3,DATEDIF(Tenancy!$E$5,I$3,"m"),0)))/12+(1-Tenancy!$G$5)*MAX(0,MAX(0,MIN(12,DATEDIF(MAX(Tenancy!$E$5,I$3),EDATE(I$3,12),"m")))-MAX(0,Inputs!$B$7+Inputs!$B$8-IF(Tenancy!$E$5<I$3,DATEDIF(Tenancy!$E$5,I$3,"m"),0)))/12,0)) -> 1531839 | J8: =Tenancy!$C$5*(Tenancy!$D$5*MAX(0,MIN(1,YEARFRAC(J$3,MIN(Tenancy!$E$5,EDATE(J$3,12)),1)*(Tenancy!$E$5>J$3)))+Tenancy!$F$5*(1+Inputs!$B$6)^(J$2-1)*IF(Tenancy!$E$5<EDATE(J$3,12),Tenancy!$G$5*MAX(0,MAX(0,MIN(12,DATEDIF(MAX(Tenancy!$E$5,J$3),EDATE(J$3,12),"m")))-MAX(0,Inputs!$B$9-IF(Tenancy!$E$5<J$3,DATEDIF(Tenancy!$E$5,J$3,"m"),0)))/12+(1-Tenancy!$G$5)*MAX(0,MAX(0,MIN(12,DATEDIF(MAX(Tenancy!$E$5,J$3),EDATE(J$3,12),"m")))-MAX(0,Inputs!$B$7+Inputs!$B$8-IF(Tenancy!$E$5<J$3,DATEDIF(Tenancy!$E$5,J$3,"m"),0)))/12,0)) -> 1697443.3 | ... M8: =Tenancy!$C$5*(Tenancy!$D$5*MAX(0,MIN(1,YEARFRAC(M$3,MIN(Tenancy!$E$5,EDATE(M$3,12)),1)*(Tenancy!$E$5>M$3)))+Tenancy!$F$5*(1+Inputs!$B$6)^(M$2-1)*IF(Tenancy!$E$5<EDATE(M$3,12),Tenancy!$G$5*MAX(0,MAX(0,MIN(12,DATEDIF(MAX(Tenancy!$E$5,M$3),EDATE(M$3,12),"m")))-MAX(0,Inputs!$B$9-IF(Tenancy!$E$5<M$3,DATEDIF(Tenancy!$E$5,M$3,"m"),0)))/12+(1-Tenancy!$G$5)*MAX(0,MAX(0,MIN(12,DATEDIF(MAX(Tenancy!$E$5,M$3),EDATE(M$3,12),"m")))-MAX(0,Inputs!$B$7+Inputs!$B$8-IF(Tenancy!$E$5<M$3,DATEDIF(Tenancy!$E$5,M$3,"m"),0)))/12,0)) -> 1827960.7
A9: =Tenancy!B6&" · "&Tenancy!A6 -> Vacant · 4 | C9: =Tenancy!$C$6*(Tenancy!$D$6*MAX(0,MIN(1,YEARFRAC(C$3,MIN(Tenancy!$E$6,EDATE(C$3,12)),1)*(Tenancy!$E$6>C$3)))+Tenancy!$F$6*(1+Inputs!$B$6)^(C$2-1)*IF(Tenancy!$E$6<EDATE(C$3,12),Tenancy!$G$6*MAX(0,MAX(0,MIN(12,DATEDIF(MAX(Tenancy!$E$6,C$3),EDATE(C$3,12),"m")))-MAX(0,Inputs!$B$9-IF(Tenancy!$E$6<C$3,DATEDIF(Tenancy!$E$6,C$3,"m"),0)))/12+(1-Tenancy!$G$6)*MAX(0,MAX(0,MIN(12,DATEDIF(MAX(Tenancy!$E$6,C$3),EDATE(C$3,12),"m")))-MAX(0,Inputs!$B$7+Inputs!$B$8-IF(Tenancy!$E$6<C$3,DATEDIF(Tenancy!$E$6,C$3,"m"),0)))/12,0)) -> 0 | D9: =Tenancy!$C$6*(Tenancy!$D$6*MAX(0,MIN(1,YEARFRAC(D$3,MIN(Tenancy!$E$6,EDATE(D$3,12)),1)*(Tenancy!$E$6>D$3)))+Tenancy!$F$6*(1+Inputs!$B$6)^(D$2-1)*IF(Tenancy!$E$6<EDATE(D$3,12),Tenancy!$G$6*MAX(0,MAX(0,MIN(12,DATEDIF(MAX(Tenancy!$E$6,D$3),EDATE(D$3,12),"m")))-MAX(0,Inputs!$B$9-IF(Tenancy!$E$6<D$3,DATEDIF(Tenancy!$E$6,D$3,"m"),0)))/12+(1-Tenancy!$G$6)*MAX(0,MAX(0,MIN(12,DATEDIF(MAX(Tenancy!$E$6,D$3),EDATE(D$3,12),"m")))-MAX(0,Inputs!$B$7+Inputs!$B$8-IF(Tenancy!$E$6<D$3,DATEDIF(Tenancy!$E$6,D$3,"m"),0)))/12,0)) -> 0 | E9: =Tenancy!$C$6*(Tenancy!$D$6*MAX(0,MIN(1,YEARFRAC(E$3,MIN(Tenancy!$E$6,EDATE(E$3,12)),1)*(Tenancy!$E$6>E$3)))+Tenancy!$F$6*(1+Inputs!$B$6)^(E$2-1)*IF(Tenancy!$E$6<EDATE(E$3,12),Tenancy!$G$6*MAX(0,MAX(0,MIN(12,DATEDIF(MAX(Tenancy!$E$6,E$3),EDATE(E$3,12),"m")))-MAX(0,Inputs!$B$9-IF(Tenancy!$E$6<E$3,DATEDIF(Tenancy!$E$6,E$3,"m"),0)))/12+(1-Tenancy!$G$6)*MAX(0,MAX(0,MIN(12,DATEDIF(MAX(Tenancy!$E$6,E$3),EDATE(E$3,12),"m")))-MAX(0,Inputs!$B$7+Inputs!$B$8-IF(Tenancy!$E$6<E$3,DATEDIF(Tenancy!$E$6,E$3,"m"),0)))/12,0)) -> 750146.25 | F9: =Tenancy!$C$6*(Tenancy!$D$6*MAX(0,MIN(1,YEARFRAC(F$3,MIN(Tenancy!$E$6,EDATE(F$3,12)),1)*(Tenancy!$E$6>F$3)))+Tenancy!$F$6*(1+Inputs!$B$6)^(F$2-1)*IF(Tenancy!$E$6<EDATE(F$3,12),Tenancy!$G$6*MAX(0,MAX(0,MIN(12,DATEDIF(MAX(Tenancy!$E$6,F$3),EDATE(F$3,12),"m")))-MAX(0,Inputs!$B$9-IF(Tenancy!$E$6<F$3,DATEDIF(Tenancy!$E$6,F$3,"m"),0)))/12+(1-Tenancy!$G$6)*MAX(0,MAX(0,MIN(12,DATEDIF(MAX(Tenancy!$E$6,F$3),EDATE(F$3,12),"m")))-MAX(0,Inputs!$B$7+Inputs!$B$8-IF(Tenancy!$E$6<F$3,DATEDIF(Tenancy!$E$6,F$3,"m"),0)))/12,0)) -> 1537799.8 | G9: =Tenancy!$C$6*(Tenancy!$D$6*MAX(0,MIN(1,YEARFRAC(G$3,MIN(Tenancy!$E$6,EDATE(G$3,12)),1)*(Tenancy!$E$6>G$3)))+Tenancy!$F$6*(1+Inputs!$B$6)^(G$2-1)*IF(Tenancy!$E$6<EDATE(G$3,12),Tenancy!$G$6*MAX(0,MAX(0,MIN(12,DATEDIF(MAX(Tenancy!$E$6,G$3),EDATE(G$3,12),"m")))-MAX(0,Inputs!$B$9-IF(Tenancy!$E$6<G$3,DATEDIF(Tenancy!$E$6,G$3,"m"),0)))/12+(1-Tenancy!$G$6)*MAX(0,MAX(0,MIN(12,DATEDIF(MAX(Tenancy!$E$6,G$3),EDATE(G$3,12),"m")))-MAX(0,Inputs!$B$7+Inputs!$B$8-IF(Tenancy!$E$6<G$3,DATEDIF(Tenancy!$E$6,G$3,"m"),0)))/12,0)) -> 1576244.8 | H9: =Tenancy!$C$6*(Tenancy!$D$6*MAX(0,MIN(1,YEARFRAC(H$3,MIN(Tenancy!$E$6,EDATE(H$3,12)),1)*(Tenancy!$E$6>H$3)))+Tenancy!$F$6*(1+Inputs!$B$6)^(H$2-1)*IF(Tenancy!$E$6<EDATE(H$3,12),Tenancy!$G$6*MAX(0,MAX(0,MIN(12,DATEDIF(MAX(Tenancy!$E$6,H$3),EDATE(H$3,12),"m")))-MAX(0,Inputs!$B$9-IF(Tenancy!$E$6<H$3,DATEDIF(Tenancy!$E$6,H$3,"m"),0)))/12+(1-Tenancy!$G$6)*MAX(0,MAX(0,MIN(12,DATEDIF(MAX(Tenancy!$E$6,H$3),EDATE(H$3,12),"m")))-MAX(0,Inputs!$B$7+Inputs!$B$8-IF(Tenancy!$E$6<H$3,DATEDIF(Tenancy!$E$6,H$3,"m"),0)))/12,0)) -> 1615650.9 | I9: =Tenancy!$C$6*(Tenancy!$D$6*MAX(0,MIN(1,YEARFRAC(I$3,MIN(Tenancy!$E$6,EDATE(I$3,12)),1)*(Tenancy!$E$6>I$3)))+Tenancy!$F$6*(1+Inputs!$B$6)^(I$2-1)*IF(Tenancy!$E$6<EDATE(I$3,12),Tenancy!$G$6*MAX(0,MAX(0,MIN(12,DATEDIF(MAX(Tenancy!$E$6,I$3),EDATE(I$3,12),"m")))-MAX(0,Inputs!$B$9-IF(Tenancy!$E$6<I$3,DATEDIF(Tenancy!$E$6,I$3,"m"),0)))/12+(1-Tenancy!$G$6)*MAX(0,MAX(0,MIN(12,DATEDIF(MAX(Tenancy!$E$6,I$3),EDATE(I$3,12),"m")))-MAX(0,Inputs!$B$7+Inputs!$B$8-IF(Tenancy!$E$6<I$3,DATEDIF(Tenancy!$E$6,I$3,"m"),0)))/12,0)) -> 1656042.2 | J9: =Tenancy!$C$6*(Tenancy!$D$6*MAX(0,MIN(1,YEARFRAC(J$3,MIN(Tenancy!$E$6,EDATE(J$3,12)),1)*(Tenancy!$E$6>J$3)))+Tenancy!$F$6*(1+Inputs!$B$6)^(J$2-1)*IF(Tenancy!$E$6<EDATE(J$3,12),Tenancy!$G$6*MAX(0,MAX(0,MIN(12,DATEDIF(MAX(Tenancy!$E$6,J$3),EDATE(J$3,12),"m")))-MAX(0,Inputs!$B$9-IF(Tenancy!$E$6<J$3,DATEDIF(Tenancy!$E$6,J$3,"m"),0)))/12+(1-Tenancy!$G$6)*MAX(0,MAX(0,MIN(12,DATEDIF(MAX(Tenancy!$E$6,J$3),EDATE(J$3,12),"m")))-MAX(0,Inputs!$B$7+Inputs!$B$8-IF(Tenancy!$E$6<J$3,DATEDIF(Tenancy!$E$6,J$3,"m"),0)))/12,0)) -> 1697443.3 | ... M9: =Tenancy!$C$6*(Tenancy!$D$6*MAX(0,MIN(1,YEARFRAC(M$3,MIN(Tenancy!$E$6,EDATE(M$3,12)),1)*(Tenancy!$E$6>M$3)))+Tenancy!$F$6*(1+Inputs!$B$6)^(M$2-1)*IF(Tenancy!$E$6<EDATE(M$3,12),Tenancy!$G$6*MAX(0,MAX(0,MIN(12,DATEDIF(MAX(Tenancy!$E$6,M$3),EDATE(M$3,12),"m")))-MAX(0,Inputs!$B$9-IF(Tenancy!$E$6<M$3,DATEDIF(Tenancy!$E$6,M$3,"m"),0)))/12+(1-Tenancy!$G$6)*MAX(0,MAX(0,MIN(12,DATEDIF(MAX(Tenancy!$E$6,M$3),EDATE(M$3,12),"m")))-MAX(0,Inputs!$B$7+Inputs!$B$8-IF(Tenancy!$E$6<M$3,DATEDIF(Tenancy!$E$6,M$3,"m"),0)))/12,0)) -> 1827960.7
A10: =Tenancy!B7&" · "&Tenancy!A7 -> Coral Re · 5 | C10: =Tenancy!$C$7*(Tenancy!$D$7*MAX(0,MIN(1,YEARFRAC(C$3,MIN(Tenancy!$E$7,EDATE(C$3,12)),1)*(Tenancy!$E$7>C$3)))+Tenancy!$F$7*(1+Inputs!$B$6)^(C$2-1)*IF(Tenancy!$E$7<EDATE(C$3,12),Tenancy!$G$7*MAX(0,MAX(0,MIN(12,DATEDIF(MAX(Tenancy!$E$7,C$3),EDATE(C$3,12),"m")))-MAX(0,Inputs!$B$9-IF(Tenancy!$E$7<C$3,DATEDIF(Tenancy!$E$7,C$3,"m"),0)))/12+(1-Tenancy!$G$7)*MAX(0,MAX(0,MIN(12,DATEDIF(MAX(Tenancy!$E$7,C$3),EDATE(C$3,12),"m")))-MAX(0,Inputs!$B$7+Inputs!$B$8-IF(Tenancy!$E$7<C$3,DATEDIF(Tenancy!$E$7,C$3,"m"),0)))/12,0)) -> 1353000 | D10: =Tenancy!$C$7*(Tenancy!$D$7*MAX(0,MIN(1,YEARFRAC(D$3,MIN(Tenancy!$E$7,EDATE(D$3,12)),1)*(Tenancy!$E$7>D$3)))+Tenancy!$F$7*(1+Inputs!$B$6)^(D$2-1)*IF(Tenancy!$E$7<EDATE(D$3,12),Tenancy!$G$7*MAX(0,MAX(0,MIN(12,DATEDIF(MAX(Tenancy!$E$7,D$3),EDATE(D$3,12),"m")))-MAX(0,Inputs!$B$9-IF(Tenancy!$E$7<D$3,DATEDIF(Tenancy!$E$7,D$3,"m"),0)))/12+(1-Tenancy!$G$7)*MAX(0,MAX(0,MIN(12,DATEDIF(MAX(Tenancy!$E$7,D$3),EDATE(D$3,12),"m")))-MAX(0,Inputs!$B$7+Inputs!$B$8-IF(Tenancy!$E$7<D$3,DATEDIF(Tenancy!$E$7,D$3,"m"),0)))/12,0)) -> 1353000 | E10: =Tenancy!$C$7*(Tenancy!$D$7*MAX(0,MIN(1,YEARFRAC(E$3,MIN(Tenancy!$E$7,EDATE(E$3,12)),1)*(Tenancy!$E$7>E$3)))+Tenancy!$F$7*(1+Inputs!$B$6)^(E$2-1)*IF(Tenancy!$E$7<EDATE(E$3,12),Tenancy!$G$7*MAX(0,MAX(0,MIN(12,DATEDIF(MAX(Tenancy!$E$7,E$3),EDATE(E$3,12),"m")))-MAX(0,Inputs!$B$9-IF(Tenancy!$E$7<E$3,DATEDIF(Tenancy!$E$7,E$3,"m"),0)))/12+(1-Tenancy!$G$7)*MAX(0,MAX(0,MIN(12,DATEDIF(MAX(Tenancy!$E$7,E$3),EDATE(E$3,12),"m")))-MAX(0,Inputs!$B$7+Inputs!$B$8-IF(Tenancy!$E$7<E$3,DATEDIF(Tenancy!$E$7,E$3,"m"),0)))/12,0)) -> 1353000 | F10: =Tenancy!$C$7*(Tenancy!$D$7*MAX(0,MIN(1,YEARFRAC(F$3,MIN(Tenancy!$E$7,EDATE(F$3,12)),1)*(Tenancy!$E$7>F$3)))+Tenancy!$F$7*(1+Inputs!$B$6)^(F$2-1)*IF(Tenancy!$E$7<EDATE(F$3,12),Tenancy!$G$7*MAX(0,MAX(0,MIN(12,DATEDIF(MAX(Tenancy!$E$7,F$3),EDATE(F$3,12),"m")))-MAX(0,Inputs!$B$9-IF(Tenancy!$E$7<F$3,DATEDIF(Tenancy!$E$7,F$3,"m"),0)))/12+(1-Tenancy!$G$7)*MAX(0,MAX(0,MIN(12,DATEDIF(MAX(Tenancy!$E$7,F$3),EDATE(F$3,12),"m")))-MAX(0,Inputs!$B$7+Inputs!$B$8-IF(Tenancy!$E$7<F$3,DATEDIF(Tenancy!$E$7,F$3,"m"),0)))/12,0)) -> 1353000 | G10: =Tenancy!$C$7*(Tenancy!$D$7*MAX(0,MIN(1,YEARFRAC(G$3,MIN(Tenancy!$E$7,EDATE(G$3,12)),1)*(Tenancy!$E$7>G$3)))+Tenancy!$F$7*(1+Inputs!$B$6)^(G$2-1)*IF(Tenancy!$E$7<EDATE(G$3,12),Tenancy!$G$7*MAX(0,MAX(0,MIN(12,DATEDIF(MAX(Tenancy!$E$7,G$3),EDATE(G$3,12),"m")))-MAX(0,Inputs!$B$9-IF(Tenancy!$E$7<G$3,DATEDIF(Tenancy!$E$7,G$3,"m"),0)))/12+(1-Tenancy!$G$7)*MAX(0,MAX(0,MIN(12,DATEDIF(MAX(Tenancy!$E$7,G$3),EDATE(G$3,12),"m")))-MAX(0,Inputs!$B$7+Inputs!$B$8-IF(Tenancy!$E$7<G$3,DATEDIF(Tenancy!$E$7,G$3,"m"),0)))/12,0)) -> 1353000 | H10: =Tenancy!$C$7*(Tenancy!$D$7*MAX(0,MIN(1,YEARFRAC(H$3,MIN(Tenancy!$E$7,EDATE(H$3,12)),1)*(Tenancy!$E$7>H$3)))+Tenancy!$F$7*(1+Inputs!$B$6)^(H$2-1)*IF(Tenancy!$E$7<EDATE(H$3,12),Tenancy!$G$7*MAX(0,MAX(0,MIN(12,DATEDIF(MAX(Tenancy!$E$7,H$3),EDATE(H$3,12),"m")))-MAX(0,Inputs!$B$9-IF(Tenancy!$E$7<H$3,DATEDIF(Tenancy!$E$7,H$3,"m"),0)))/12+(1-Tenancy!$G$7)*MAX(0,MAX(0,MIN(12,DATEDIF(MAX(Tenancy!$E$7,H$3),EDATE(H$3,12),"m")))-MAX(0,Inputs!$B$7+Inputs!$B$8-IF(Tenancy!$E$7<H$3,DATEDIF(Tenancy!$E$7,H$3,"m"),0)))/12,0)) -> 1353000 | I10: =Tenancy!$C$7*(Tenancy!$D$7*MAX(0,MIN(1,YEARFRAC(I$3,MIN(Tenancy!$E$7,EDATE(I$3,12)),1)*(Tenancy!$E$7>I$3)))+Tenancy!$F$7*(1+Inputs!$B$6)^(I$2-1)*IF(Tenancy!$E$7<EDATE(I$3,12),Tenancy!$G$7*MAX(0,MAX(0,MIN(12,DATEDIF(MAX(Tenancy!$E$7,I$3),EDATE(I$3,12),"m")))-MAX(0,Inputs!$B$9-IF(Tenancy!$E$7<I$3,DATEDIF(Tenancy!$E$7,I$3,"m"),0)))/12+(1-Tenancy!$G$7)*MAX(0,MAX(0,MIN(12,DATEDIF(MAX(Tenancy!$E$7,I$3),EDATE(I$3,12),"m")))-MAX(0,Inputs!$B$7+Inputs!$B$8-IF(Tenancy!$E$7<I$3,DATEDIF(Tenancy!$E$7,I$3,"m"),0)))/12,0)) -> 1323426.2 | J10: =Tenancy!$C$7*(Tenancy!$D$7*MAX(0,MIN(1,YEARFRAC(J$3,MIN(Tenancy!$E$7,EDATE(J$3,12)),1)*(Tenancy!$E$7>J$3)))+Tenancy!$F$7*(1+Inputs!$B$6)^(J$2-1)*IF(Tenancy!$E$7<EDATE(J$3,12),Tenancy!$G$7*MAX(0,MAX(0,MIN(12,DATEDIF(MAX(Tenancy!$E$7,J$3),EDATE(J$3,12),"m")))-MAX(0,Inputs!$B$9-IF(Tenancy!$E$7<J$3,DATEDIF(Tenancy!$E$7,J$3,"m"),0)))/12+(1-Tenancy!$G$7)*MAX(0,MAX(0,MIN(12,DATEDIF(MAX(Tenancy!$E$7,J$3),EDATE(J$3,12),"m")))-MAX(0,Inputs!$B$7+Inputs!$B$8-IF(Tenancy!$E$7<J$3,DATEDIF(Tenancy!$E$7,J$3,"m"),0)))/12,0)) -> 546453.7 | ... M10: =Tenancy!$C$7*(Tenancy!$D$7*MAX(0,MIN(1,YEARFRAC(M$3,MIN(Tenancy!$E$7,EDATE(M$3,12)),1)*(Tenancy!$E$7>M$3)))+Tenancy!$F$7*(1+Inputs!$B$6)^(M$2-1)*IF(Tenancy!$E$7<EDATE(M$3,12),Tenancy!$G$7*MAX(0,MAX(0,MIN(12,DATEDIF(MAX(Tenancy!$E$7,M$3),EDATE(M$3,12),"m")))-MAX(0,Inputs!$B$9-IF(Tenancy!$E$7<M$3,DATEDIF(Tenancy!$E$7,M$3,"m"),0)))/12+(1-Tenancy!$G$7)*MAX(0,MAX(0,MIN(12,DATEDIF(MAX(Tenancy!$E$7,M$3),EDATE(M$3,12),"m")))-MAX(0,Inputs!$B$7+Inputs!$B$8-IF(Tenancy!$E$7<M$3,DATEDIF(Tenancy!$E$7,M$3,"m"),0)))/12,0)) -> 1810679.6
A11: =Tenancy!B8&" · "&Tenancy!A8 -> Tessel Bank · 6 | C11: =Tenancy!$C$8*(Tenancy!$D$8*MAX(0,MIN(1,YEARFRAC(C$3,MIN(Tenancy!$E$8,EDATE(C$3,12)),1)*(Tenancy!$E$8>C$3)))+Tenancy!$F$8*(1+Inputs!$B$6)^(C$2-1)*IF(Tenancy!$E$8<EDATE(C$3,12),Tenancy!$G$8*MAX(0,MAX(0,MIN(12,DATEDIF(MAX(Tenancy!$E$8,C$3),EDATE(C$3,12),"m")))-MAX(0,Inputs!$B$9-IF(Tenancy!$E$8<C$3,DATEDIF(Tenancy!$E$8,C$3,"m"),0)))/12+(1-Tenancy!$G$8)*MAX(0,MAX(0,MIN(12,DATEDIF(MAX(Tenancy!$E$8,C$3),EDATE(C$3,12),"m")))-MAX(0,Inputs!$B$7+Inputs!$B$8-IF(Tenancy!$E$8<C$3,DATEDIF(Tenancy!$E$8,C$3,"m"),0)))/12,0)) -> 1291500 | D11: =Tenancy!$C$8*(Tenancy!$D$8*MAX(0,MIN(1,YEARFRAC(D$3,MIN(Tenancy!$E$8,EDATE(D$3,12)),1)*(Tenancy!$E$8>D$3)))+Tenancy!$F$8*(1+Inputs!$B$6)^(D$2-1)*IF(Tenancy!$E$8<EDATE(D$3,12),Tenancy!$G$8*MAX(0,MAX(0,MIN(12,DATEDIF(MAX(Tenancy!$E$8,D$3),EDATE(D$3,12),"m")))-MAX(0,Inputs!$B$9-IF(Tenancy!$E$8<D$3,DATEDIF(Tenancy!$E$8,D$3,"m"),0)))/12+(1-Tenancy!$G$8)*MAX(0,MAX(0,MIN(12,DATEDIF(MAX(Tenancy!$E$8,D$3),EDATE(D$3,12),"m")))-MAX(0,Inputs!$B$7+Inputs!$B$8-IF(Tenancy!$E$8<D$3,DATEDIF(Tenancy!$E$8,D$3,"m"),0)))/12,0)) -> 1291500 | E11: =Tenancy!$C$8*(Tenancy!$D$8*MAX(0,MIN(1,YEARFRAC(E$3,MIN(Tenancy!$E$8,EDATE(E$3,12)),1)*(Tenancy!$E$8>E$3)))+Tenancy!$F$8*(1+Inputs!$B$6)^(E$2-1)*IF(Tenancy!$E$8<EDATE(E$3,12),Tenancy!$G$8*MAX(0,MAX(0,MIN(12,DATEDIF(MAX(Tenancy!$E$8,E$3),EDATE(E$3,12),"m")))-MAX(0,Inputs!$B$9-IF(Tenancy!$E$8<E$3,DATEDIF(Tenancy!$E$8,E$3,"m"),0)))/12+(1-Tenancy!$G$8)*MAX(0,MAX(0,MIN(12,DATEDIF(MAX(Tenancy!$E$8,E$3),EDATE(E$3,12),"m")))-MAX(0,Inputs!$B$7+Inputs!$B$8-IF(Tenancy!$E$8<E$3,DATEDIF(Tenancy!$E$8,E$3,"m"),0)))/12,0)) -> 613991.8 | F11: =Tenancy!$C$8*(Tenancy!$D$8*MAX(0,MIN(1,YEARFRAC(F$3,MIN(Tenancy!$E$8,EDATE(F$3,12)),1)*(Tenancy!$E$8>F$3)))+Tenancy!$F$8*(1+Inputs!$B$6)^(F$2-1)*IF(Tenancy!$E$8<EDATE(F$3,12),Tenancy!$G$8*MAX(0,MAX(0,MIN(12,DATEDIF(MAX(Tenancy!$E$8,F$3),EDATE(F$3,12),"m")))-MAX(0,Inputs!$B$9-IF(Tenancy!$E$8<F$3,DATEDIF(Tenancy!$E$8,F$3,"m"),0)))/12+(1-Tenancy!$G$8)*MAX(0,MAX(0,MIN(12,DATEDIF(MAX(Tenancy!$E$8,F$3),EDATE(F$3,12),"m")))-MAX(0,Inputs!$B$7+Inputs!$B$8-IF(Tenancy!$E$8<F$3,DATEDIF(Tenancy!$E$8,F$3,"m"),0)))/12,0)) -> 761630.89 | G11: =Tenancy!$C$8*(Tenancy!$D$8*MAX(0,MIN(1,YEARFRAC(G$3,MIN(Tenancy!$E$8,EDATE(G$3,12)),1)*(Tenancy!$E$8>G$3)))+Tenancy!$F$8*(1+Inputs!$B$6)^(G$2-1)*IF(Tenancy!$E$8<EDATE(G$3,12),Tenancy!$G$8*MAX(0,MAX(0,MIN(12,DATEDIF(MAX(Tenancy!$E$8,G$3),EDATE(G$3,12),"m")))-MAX(0,Inputs!$B$9-IF(Tenancy!$E$8<G$3,DATEDIF(Tenancy!$E$8,G$3,"m"),0)))/12+(1-Tenancy!$G$8)*MAX(0,MAX(0,MIN(12,DATEDIF(MAX(Tenancy!$E$8,G$3),EDATE(G$3,12),"m")))-MAX(0,Inputs!$B$7+Inputs!$B$8-IF(Tenancy!$E$8<G$3,DATEDIF(Tenancy!$E$8,G$3,"m"),0)))/12,0)) -> 780671.67 | H11: =Tenancy!$C$8*(Tenancy!$D$8*MAX(0,MIN(1,YEARFRAC(H$3,MIN(Tenancy!$E$8,EDATE(H$3,12)),1)*(Tenancy!$E$8>H$3)))+Tenancy!$F$8*(1+Inputs!$B$6)^(H$2-1)*IF(Tenancy!$E$8<EDATE(H$3,12),Tenancy!$G$8*MAX(0,MAX(0,MIN(12,DATEDIF(MAX(Tenancy!$E$8,H$3),EDATE(H$3,12),"m")))-MAX(0,Inputs!$B$9-IF(Tenancy!$E$8<H$3,DATEDIF(Tenancy!$E$8,H$3,"m"),0)))/12+(1-Tenancy!$G$8)*MAX(0,MAX(0,MIN(12,DATEDIF(MAX(Tenancy!$E$8,H$3),EDATE(H$3,12),"m")))-MAX(0,Inputs!$B$7+Inputs!$B$8-IF(Tenancy!$E$8<H$3,DATEDIF(Tenancy!$E$8,H$3,"m"),0)))/12,0)) -> 1600376.9 | I11: =Tenancy!$C$8*(Tenancy!$D$8*MAX(0,MIN(1,YEARFRAC(I$3,MIN(Tenancy!$E$8,EDATE(I$3,12)),1)*(Tenancy!$E$8>I$3)))+Tenancy!$F$8*(1+Inputs!$B$6)^(I$2-1)*IF(Tenancy!$E$8<EDATE(I$3,12),Tenancy!$G$8*MAX(0,MAX(0,MIN(12,DATEDIF(MAX(Tenancy!$E$8,I$3),EDATE(I$3,12),"m")))-MAX(0,Inputs!$B$9-IF(Tenancy!$E$8<I$3,DATEDIF(Tenancy!$E$8,I$3,"m"),0)))/12+(1-Tenancy!$G$8)*MAX(0,MAX(0,MIN(12,DATEDIF(MAX(Tenancy!$E$8,I$3),EDATE(I$3,12),"m")))-MAX(0,Inputs!$B$7+Inputs!$B$8-IF(Tenancy!$E$8<I$3,DATEDIF(Tenancy!$E$8,I$3,"m"),0)))/12,0)) -> 1640386.3 | J11: =Tenancy!$C$8*(Tenancy!$D$8*MAX(0,MIN(1,YEARFRAC(J$3,MIN(Tenancy!$E$8,EDATE(J$3,12)),1)*(Tenancy!$E$8>J$3)))+Tenancy!$F$8*(1+Inputs!$B$6)^(J$2-1)*IF(Tenancy!$E$8<EDATE(J$3,12),Tenancy!$G$8*MAX(0,MAX(0,MIN(12,DATEDIF(MAX(Tenancy!$E$8,J$3),EDATE(J$3,12),"m")))-MAX(0,Inputs!$B$9-IF(Tenancy!$E$8<J$3,DATEDIF(Tenancy!$E$8,J$3,"m"),0)))/12+(1-Tenancy!$G$8)*MAX(0,MAX(0,MIN(12,DATEDIF(MAX(Tenancy!$E$8,J$3),EDATE(J$3,12),"m")))-MAX(0,Inputs!$B$7+Inputs!$B$8-IF(Tenancy!$E$8<J$3,DATEDIF(Tenancy!$E$8,J$3,"m"),0)))/12,0)) -> 1681396 | ... M11: =Tenancy!$C$8*(Tenancy!$D$8*MAX(0,MIN(1,YEARFRAC(M$3,MIN(Tenancy!$E$8,EDATE(M$3,12)),1)*(Tenancy!$E$8>M$3)))+Tenancy!$F$8*(1+Inputs!$B$6)^(M$2-1)*IF(Tenancy!$E$8<EDATE(M$3,12),Tenancy!$G$8*MAX(0,MAX(0,MIN(12,DATEDIF(MAX(Tenancy!$E$8,M$3),EDATE(M$3,12),"m")))-MAX(0,Inputs!$B$9-IF(Tenancy!$E$8<M$3,DATEDIF(Tenancy!$E$8,M$3,"m"),0)))/12+(1-Tenancy!$G$8)*MAX(0,MAX(0,MIN(12,DATEDIF(MAX(Tenancy!$E$8,M$3),EDATE(M$3,12),"m")))-MAX(0,Inputs!$B$7+Inputs!$B$8-IF(Tenancy!$E$8<M$3,DATEDIF(Tenancy!$E$8,M$3,"m"),0)))/12,0)) -> 1810679.6
A12: =Tenancy!B9&" · "&Tenancy!A9 -> Tessel Bank · 7 | C12: =Tenancy!$C$9*(Tenancy!$D$9*MAX(0,MIN(1,YEARFRAC(C$3,MIN(Tenancy!$E$9,EDATE(C$3,12)),1)*(Tenancy!$E$9>C$3)))+Tenancy!$F$9*(1+Inputs!$B$6)^(C$2-1)*IF(Tenancy!$E$9<EDATE(C$3,12),Tenancy!$G$9*MAX(0,MAX(0,MIN(12,DATEDIF(MAX(Tenancy!$E$9,C$3),EDATE(C$3,12),"m")))-MAX(0,Inputs!$B$9-IF(Tenancy!$E$9<C$3,DATEDIF(Tenancy!$E$9,C$3,"m"),0)))/12+(1-Tenancy!$G$9)*MAX(0,MAX(0,MIN(12,DATEDIF(MAX(Tenancy!$E$9,C$3),EDATE(C$3,12),"m")))-MAX(0,Inputs!$B$7+Inputs!$B$8-IF(Tenancy!$E$9<C$3,DATEDIF(Tenancy!$E$9,C$3,"m"),0)))/12,0)) -> 1291500 | D12: =Tenancy!$C$9*(Tenancy!$D$9*MAX(0,MIN(1,YEARFRAC(D$3,MIN(Tenancy!$E$9,EDATE(D$3,12)),1)*(Tenancy!$E$9>D$3)))+Tenancy!$F$9*(1+Inputs!$B$6)^(D$2-1)*IF(Tenancy!$E$9<EDATE(D$3,12),Tenancy!$G$9*MAX(0,MAX(0,MIN(12,DATEDIF(MAX(Tenancy!$E$9,D$3),EDATE(D$3,12),"m")))-MAX(0,Inputs!$B$9-IF(Tenancy!$E$9<D$3,DATEDIF(Tenancy!$E$9,D$3,"m"),0)))/12+(1-Tenancy!$G$9)*MAX(0,MAX(0,MIN(12,DATEDIF(MAX(Tenancy!$E$9,D$3),EDATE(D$3,12),"m")))-MAX(0,Inputs!$B$7+Inputs!$B$8-IF(Tenancy!$E$9<D$3,DATEDIF(Tenancy!$E$9,D$3,"m"),0)))/12,0)) -> 1291500 | E12: =Tenancy!$C$9*(Tenancy!$D$9*MAX(0,MIN(1,YEARFRAC(E$3,MIN(Tenancy!$E$9,EDATE(E$3,12)),1)*(Tenancy!$E$9>E$3)))+Tenancy!$F$9*(1+Inputs!$B$6)^(E$2-1)*IF(Tenancy!$E$9<EDATE(E$3,12),Tenancy!$G$9*MAX(0,MAX(0,MIN(12,DATEDIF(MAX(Tenancy!$E$9,E$3),EDATE(E$3,12),"m")))-MAX(0,Inputs!$B$9-IF(Tenancy!$E$9<E$3,DATEDIF(Tenancy!$E$9,E$3,"m"),0)))/12+(1-Tenancy!$G$9)*MAX(0,MAX(0,MIN(12,DATEDIF(MAX(Tenancy!$E$9,E$3),EDATE(E$3,12),"m")))-MAX(0,Inputs!$B$7+Inputs!$B$8-IF(Tenancy!$E$9<E$3,DATEDIF(Tenancy!$E$9,E$3,"m"),0)))/12,0)) -> 613991.8 | F12: =Tenancy!$C$9*(Tenancy!$D$9*MAX(0,MIN(1,YEARFRAC(F$3,MIN(Tenancy!$E$9,EDATE(F$3,12)),1)*(Tenancy!$E$9>F$3)))+Tenancy!$F$9*(1+Inputs!$B$6)^(F$2-1)*IF(Tenancy!$E$9<EDATE(F$3,12),Tenancy!$G$9*MAX(0,MAX(0,MIN(12,DATEDIF(MAX(Tenancy!$E$9,F$3),EDATE(F$3,12),"m")))-MAX(0,Inputs!$B$9-IF(Tenancy!$E$9<F$3,DATEDIF(Tenancy!$E$9,F$3,"m"),0)))/12+(1-Tenancy!$G$9)*MAX(0,MAX(0,MIN(12,DATEDIF(MAX(Tenancy!$E$9,F$3),EDATE(F$3,12),"m")))-MAX(0,Inputs!$B$7+Inputs!$B$8-IF(Tenancy!$E$9<F$3,DATEDIF(Tenancy!$E$9,F$3,"m"),0)))/12,0)) -> 761630.89 | G12: =Tenancy!$C$9*(Tenancy!$D$9*MAX(0,MIN(1,YEARFRAC(G$3,MIN(Tenancy!$E$9,EDATE(G$3,12)),1)*(Tenancy!$E$9>G$3)))+Tenancy!$F$9*(1+Inputs!$B$6)^(G$2-1)*IF(Tenancy!$E$9<EDATE(G$3,12),Tenancy!$G$9*MAX(0,MAX(0,MIN(12,DATEDIF(MAX(Tenancy!$E$9,G$3),EDATE(G$3,12),"m")))-MAX(0,Inputs!$B$9-IF(Tenancy!$E$9<G$3,DATEDIF(Tenancy!$E$9,G$3,"m"),0)))/12+(1-Tenancy!$G$9)*MAX(0,MAX(0,MIN(12,DATEDIF(MAX(Tenancy!$E$9,G$3),EDATE(G$3,12),"m")))-MAX(0,Inputs!$B$7+Inputs!$B$8-IF(Tenancy!$E$9<G$3,DATEDIF(Tenancy!$E$9,G$3,"m"),0)))/12,0)) -> 780671.67 | H12: =Tenancy!$C$9*(Tenancy!$D$9*MAX(0,MIN(1,YEARFRAC(H$3,MIN(Tenancy!$E$9,EDATE(H$3,12)),1)*(Tenancy!$E$9>H$3)))+Tenancy!$F$9*(1+Inputs!$B$6)^(H$2-1)*IF(Tenancy!$E$9<EDATE(H$3,12),Tenancy!$G$9*MAX(0,MAX(0,MIN(12,DATEDIF(MAX(Tenancy!$E$9,H$3),EDATE(H$3,12),"m")))-MAX(0,Inputs!$B$9-IF(Tenancy!$E$9<H$3,DATEDIF(Tenancy!$E$9,H$3,"m"),0)))/12+(1-Tenancy!$G$9)*MAX(0,MAX(0,MIN(12,DATEDIF(MAX(Tenancy!$E$9,H$3),EDATE(H$3,12),"m")))-MAX(0,Inputs!$B$7+Inputs!$B$8-IF(Tenancy!$E$9<H$3,DATEDIF(Tenancy!$E$9,H$3,"m"),0)))/12,0)) -> 1600376.9 | I12: =Tenancy!$C$9*(Tenancy!$D$9*MAX(0,MIN(1,YEARFRAC(I$3,MIN(Tenancy!$E$9,EDATE(I$3,12)),1)*(Tenancy!$E$9>I$3)))+Tenancy!$F$9*(1+Inputs!$B$6)^(I$2-1)*IF(Tenancy!$E$9<EDATE(I$3,12),Tenancy!$G$9*MAX(0,MAX(0,MIN(12,DATEDIF(MAX(Tenancy!$E$9,I$3),EDATE(I$3,12),"m")))-MAX(0,Inputs!$B$9-IF(Tenancy!$E$9<I$3,DATEDIF(Tenancy!$E$9,I$3,"m"),0)))/12+(1-Tenancy!$G$9)*MAX(0,MAX(0,MIN(12,DATEDIF(MAX(Tenancy!$E$9,I$3),EDATE(I$3,12),"m")))-MAX(0,Inputs!$B$7+Inputs!$B$8-IF(Tenancy!$E$9<I$3,DATEDIF(Tenancy!$E$9,I$3,"m"),0)))/12,0)) -> 1640386.3 | J12: =Tenancy!$C$9*(Tenancy!$D$9*MAX(0,MIN(1,YEARFRAC(J$3,MIN(Tenancy!$E$9,EDATE(J$3,12)),1)*(Tenancy!$E$9>J$3)))+Tenancy!$F$9*(1+Inputs!$B$6)^(J$2-1)*IF(Tenancy!$E$9<EDATE(J$3,12),Tenancy!$G$9*MAX(0,MAX(0,MIN(12,DATEDIF(MAX(Tenancy!$E$9,J$3),EDATE(J$3,12),"m")))-MAX(0,Inputs!$B$9-IF(Tenancy!$E$9<J$3,DATEDIF(Tenancy!$E$9,J$3,"m"),0)))/12+(1-Tenancy!$G$9)*MAX(0,MAX(0,MIN(12,DATEDIF(MAX(Tenancy!$E$9,J$3),EDATE(J$3,12),"m")))-MAX(0,Inputs!$B$7+Inputs!$B$8-IF(Tenancy!$E$9<J$3,DATEDIF(Tenancy!$E$9,J$3,"m"),0)))/12,0)) -> 1681396 | ... M12: =Tenancy!$C$9*(Tenancy!$D$9*MAX(0,MIN(1,YEARFRAC(M$3,MIN(Tenancy!$E$9,EDATE(M$3,12)),1)*(Tenancy!$E$9>M$3)))+Tenancy!$F$9*(1+Inputs!$B$6)^(M$2-1)*IF(Tenancy!$E$9<EDATE(M$3,12),Tenancy!$G$9*MAX(0,MAX(0,MIN(12,DATEDIF(MAX(Tenancy!$E$9,M$3),EDATE(M$3,12),"m")))-MAX(0,Inputs!$B$9-IF(Tenancy!$E$9<M$3,DATEDIF(Tenancy!$E$9,M$3,"m"),0)))/12+(1-Tenancy!$G$9)*MAX(0,MAX(0,MIN(12,DATEDIF(MAX(Tenancy!$E$9,M$3),EDATE(M$3,12),"m")))-MAX(0,Inputs!$B$7+Inputs!$B$8-IF(Tenancy!$E$9<M$3,DATEDIF(Tenancy!$E$9,M$3,"m"),0)))/12,0)) -> 1810679.6
A13: =Tenancy!B10&" · "&Tenancy!A10 -> Arkwright Partners · 8 | C13: =Tenancy!$C$10*(Tenancy!$D$10*MAX(0,MIN(1,YEARFRAC(C$3,MIN(Tenancy!$E$10,EDATE(C$3,12)),1)*(Tenancy!$E$10>C$3)))+Tenancy!$F$10*(1+Inputs!$B$6)^(C$2-1)*IF(Tenancy!$E$10<EDATE(C$3,12),Tenancy!$G$10*MAX(0,MAX(0,MIN(12,DATEDIF(MAX(Tenancy!$E$10,C$3),EDATE(C$3,12),"m")))-MAX(0,Inputs!$B$9-IF(Tenancy!$E$10<C$3,DATEDIF(Tenancy!$E$10,C$3,"m"),0)))/12+(1-Tenancy!$G$10)*MAX(0,MAX(0,MIN(12,DATEDIF(MAX(Tenancy!$E$10,C$3),EDATE(C$3,12),"m")))-MAX(0,Inputs!$B$7+Inputs!$B$8-IF(Tenancy!$E$10<C$3,DATEDIF(Tenancy!$E$10,C$3,"m"),0)))/12,0)) -> 1330000 | D13: =Tenancy!$C$10*(Tenancy!$D$10*MAX(0,MIN(1,YEARFRAC(D$3,MIN(Tenancy!$E$10,EDATE(D$3,12)),1)*(Tenancy!$E$10>D$3)))+Tenancy!$F$10*(1+Inputs!$B$6)^(D$2-1)*IF(Tenancy!$E$10<EDATE(D$3,12),Tenancy!$G$10*MAX(0,MAX(0,MIN(12,DATEDIF(MAX(Tenancy!$E$10,D$3),EDATE(D$3,12),"m")))-MAX(0,Inputs!$B$9-IF(Tenancy!$E$10<D$3,DATEDIF(Tenancy!$E$10,D$3,"m"),0)))/12+(1-Tenancy!$G$10)*MAX(0,MAX(0,MIN(12,DATEDIF(MAX(Tenancy!$E$10,D$3),EDATE(D$3,12),"m")))-MAX(0,Inputs!$B$7+Inputs!$B$8-IF(Tenancy!$E$10<D$3,DATEDIF(Tenancy!$E$10,D$3,"m"),0)))/12,0)) -> 1330000 | E13: =Tenancy!$C$10*(Tenancy!$D$10*MAX(0,MIN(1,YEARFRAC(E$3,MIN(Tenancy!$E$10,EDATE(E$3,12)),1)*(Tenancy!$E$10>E$3)))+Tenancy!$F$10*(1+Inputs!$B$6)^(E$2-1)*IF(Tenancy!$E$10<EDATE(E$3,12),Tenancy!$G$10*MAX(0,MAX(0,MIN(12,DATEDIF(MAX(Tenancy!$E$10,E$3),EDATE(E$3,12),"m")))-MAX(0,Inputs!$B$9-IF(Tenancy!$E$10<E$3,DATEDIF(Tenancy!$E$10,E$3,"m"),0)))/12+(1-Tenancy!$G$10)*MAX(0,MAX(0,MIN(12,DATEDIF(MAX(Tenancy!$E$10,E$3),EDATE(E$3,12),"m")))-MAX(0,Inputs!$B$7+Inputs!$B$8-IF(Tenancy!$E$10<E$3,DATEDIF(Tenancy!$E$10,E$3,"m"),0)))/12,0)) -> 1330000 | F13: =Tenancy!$C$10*(Tenancy!$D$10*MAX(0,MIN(1,YEARFRAC(F$3,MIN(Tenancy!$E$10,EDATE(F$3,12)),1)*(Tenancy!$E$10>F$3)))+Tenancy!$F$10*(1+Inputs!$B$6)^(F$2-1)*IF(Tenancy!$E$10<EDATE(F$3,12),Tenancy!$G$10*MAX(0,MAX(0,MIN(12,DATEDIF(MAX(Tenancy!$E$10,F$3),EDATE(F$3,12),"m")))-MAX(0,Inputs!$B$9-IF(Tenancy!$E$10<F$3,DATEDIF(Tenancy!$E$10,F$3,"m"),0)))/12+(1-Tenancy!$G$10)*MAX(0,MAX(0,MIN(12,DATEDIF(MAX(Tenancy!$E$10,F$3),EDATE(F$3,12),"m")))-MAX(0,Inputs!$B$7+Inputs!$B$8-IF(Tenancy!$E$10<F$3,DATEDIF(Tenancy!$E$10,F$3,"m"),0)))/12,0)) -> 1330000 | G13: =Tenancy!$C$10*(Tenancy!$D$10*MAX(0,MIN(1,YEARFRAC(G$3,MIN(Tenancy!$E$10,EDATE(G$3,12)),1)*(Tenancy!$E$10>G$3)))+Tenancy!$F$10*(1+Inputs!$B$6)^(G$2-1)*IF(Tenancy!$E$10<EDATE(G$3,12),Tenancy!$G$10*MAX(0,MAX(0,MIN(12,DATEDIF(MAX(Tenancy!$E$10,G$3),EDATE(G$3,12),"m")))-MAX(0,Inputs!$B$9-IF(Tenancy!$E$10<G$3,DATEDIF(Tenancy!$E$10,G$3,"m"),0)))/12+(1-Tenancy!$G$10)*MAX(0,MAX(0,MIN(12,DATEDIF(MAX(Tenancy!$E$10,G$3),EDATE(G$3,12),"m")))-MAX(0,Inputs!$B$7+Inputs!$B$8-IF(Tenancy!$E$10<G$3,DATEDIF(Tenancy!$E$10,G$3,"m"),0)))/12,0)) -> 1330000 | H13: =Tenancy!$C$10*(Tenancy!$D$10*MAX(0,MIN(1,YEARFRAC(H$3,MIN(Tenancy!$E$10,EDATE(H$3,12)),1)*(Tenancy!$E$10>H$3)))+Tenancy!$F$10*(1+Inputs!$B$6)^(H$2-1)*IF(Tenancy!$E$10<EDATE(H$3,12),Tenancy!$G$10*MAX(0,MAX(0,MIN(12,DATEDIF(MAX(Tenancy!$E$10,H$3),EDATE(H$3,12),"m")))-MAX(0,Inputs!$B$9-IF(Tenancy!$E$10<H$3,DATEDIF(Tenancy!$E$10,H$3,"m"),0)))/12+(1-Tenancy!$G$10)*MAX(0,MAX(0,MIN(12,DATEDIF(MAX(Tenancy!$E$10,H$3),EDATE(H$3,12),"m")))-MAX(0,Inputs!$B$7+Inputs!$B$8-IF(Tenancy!$E$10<H$3,DATEDIF(Tenancy!$E$10,H$3,"m"),0)))/12,0)) -> 1330000 | I13: =Tenancy!$C$10*(Tenancy!$D$10*MAX(0,MIN(1,YEARFRAC(I$3,MIN(Tenancy!$E$10,EDATE(I$3,12)),1)*(Tenancy!$E$10>I$3)))+Tenancy!$F$10*(1+Inputs!$B$6)^(I$2-1)*IF(Tenancy!$E$10<EDATE(I$3,12),Tenancy!$G$10*MAX(0,MAX(0,MIN(12,DATEDIF(MAX(Tenancy!$E$10,I$3),EDATE(I$3,12),"m")))-MAX(0,Inputs!$B$9-IF(Tenancy!$E$10<I$3,DATEDIF(Tenancy!$E$10,I$3,"m"),0)))/12+(1-Tenancy!$G$10)*MAX(0,MAX(0,MIN(12,DATEDIF(MAX(Tenancy!$E$10,I$3),EDATE(I$3,12),"m")))-MAX(0,Inputs!$B$7+Inputs!$B$8-IF(Tenancy!$E$10<I$3,DATEDIF(Tenancy!$E$10,I$3,"m"),0)))/12,0)) -> 1330000 | J13: =Tenancy!$C$10*(Tenancy!$D$10*MAX(0,MIN(1,YEARFRAC(J$3,MIN(Tenancy!$E$10,EDATE(J$3,12)),1)*(Tenancy!$E$10>J$3)))+Tenancy!$F$10*(1+Inputs!$B$6)^(J$2-1)*IF(Tenancy!$E$10<EDATE(J$3,12),Tenancy!$G$10*MAX(0,MAX(0,MIN(12,DATEDIF(MAX(Tenancy!$E$10,J$3),EDATE(J$3,12),"m")))-MAX(0,Inputs!$B$9-IF(Tenancy!$E$10<J$3,DATEDIF(Tenancy!$E$10,J$3,"m"),0)))/12+(1-Tenancy!$G$10)*MAX(0,MAX(0,MIN(12,DATEDIF(MAX(Tenancy!$E$10,J$3),EDATE(J$3,12),"m")))-MAX(0,Inputs!$B$7+Inputs!$B$8-IF(Tenancy!$E$10<J$3,DATEDIF(Tenancy!$E$10,J$3,"m"),0)))/12,0)) -> 1330000 | ... M13: =Tenancy!$C$10*(Tenancy!$D$10*MAX(0,MIN(1,YEARFRAC(M$3,MIN(Tenancy!$E$10,EDATE(M$3,12)),1)*(Tenancy!$E$10>M$3)))+Tenancy!$F$10*(1+Inputs!$B$6)^(M$2-1)*IF(Tenancy!$E$10<EDATE(M$3,12),Tenancy!$G$10*MAX(0,MAX(0,MIN(12,DATEDIF(MAX(Tenancy!$E$10,M$3),EDATE(M$3,12),"m")))-MAX(0,Inputs!$B$9-IF(Tenancy!$E$10<M$3,DATEDIF(Tenancy!$E$10,M$3,"m"),0)))/12+(1-Tenancy!$G$10)*MAX(0,MAX(0,MIN(12,DATEDIF(MAX(Tenancy!$E$10,M$3),EDATE(M$3,12),"m")))-MAX(0,Inputs!$B$7+Inputs!$B$8-IF(Tenancy!$E$10<M$3,DATEDIF(Tenancy!$E$10,M$3,"m"),0)))/12,0)) -> 1225809
A14: =Tenancy!B11&" · "&Tenancy!A11 -> Arkwright Partners · 9 | C14: =Tenancy!$C$11*(Tenancy!$D$11*MAX(0,MIN(1,YEARFRAC(C$3,MIN(Tenancy!$E$11,EDATE(C$3,12)),1)*(Tenancy!$E$11>C$3)))+Tenancy!$F$11*(1+Inputs!$B$6)^(C$2-1)*IF(Tenancy!$E$11<EDATE(C$3,12),Tenancy!$G$11*MAX(0,MAX(0,MIN(12,DATEDIF(MAX(Tenancy!$E$11,C$3),EDATE(C$3,12),"m")))-MAX(0,Inputs!$B$9-IF(Tenancy!$E$11<C$3,DATEDIF(Tenancy!$E$11,C$3,"m"),0)))/12+(1-Tenancy!$G$11)*MAX(0,MAX(0,MIN(12,DATEDIF(MAX(Tenancy!$E$11,C$3),EDATE(C$3,12),"m")))-MAX(0,Inputs!$B$7+Inputs!$B$8-IF(Tenancy!$E$11<C$3,DATEDIF(Tenancy!$E$11,C$3,"m"),0)))/12,0)) -> 1330000 | D14: =Tenancy!$C$11*(Tenancy!$D$11*MAX(0,MIN(1,YEARFRAC(D$3,MIN(Tenancy!$E$11,EDATE(D$3,12)),1)*(Tenancy!$E$11>D$3)))+Tenancy!$F$11*(1+Inputs!$B$6)^(D$2-1)*IF(Tenancy!$E$11<EDATE(D$3,12),Tenancy!$G$11*MAX(0,MAX(0,MIN(12,DATEDIF(MAX(Tenancy!$E$11,D$3),EDATE(D$3,12),"m")))-MAX(0,Inputs!$B$9-IF(Tenancy!$E$11<D$3,DATEDIF(Tenancy!$E$11,D$3,"m"),0)))/12+(1-Tenancy!$G$11)*MAX(0,MAX(0,MIN(12,DATEDIF(MAX(Tenancy!$E$11,D$3),EDATE(D$3,12),"m")))-MAX(0,Inputs!$B$7+Inputs!$B$8-IF(Tenancy!$E$11<D$3,DATEDIF(Tenancy!$E$11,D$3,"m"),0)))/12,0)) -> 1330000 | E14: =Tenancy!$C$11*(Tenancy!$D$11*MAX(0,MIN(1,YEARFRAC(E$3,MIN(Tenancy!$E$11,EDATE(E$3,12)),1)*(Tenancy!$E$11>E$3)))+Tenancy!$F$11*(1+Inputs!$B$6)^(E$2-1)*IF(Tenancy!$E$11<EDATE(E$3,12),Tenancy!$G$11*MAX(0,MAX(0,MIN(12,DATEDIF(MAX(Tenancy!$E$11,E$3),EDATE(E$3,12),"m")))-MAX(0,Inputs!$B$9-IF(Tenancy!$E$11<E$3,DATEDIF(Tenancy!$E$11,E$3,"m"),0)))/12+(1-Tenancy!$G$11)*MAX(0,MAX(0,MIN(12,DATEDIF(MAX(Tenancy!$E$11,E$3),EDATE(E$3,12),"m")))-MAX(0,Inputs!$B$7+Inputs!$B$8-IF(Tenancy!$E$11<E$3,DATEDIF(Tenancy!$E$11,E$3,"m"),0)))/12,0)) -> 1330000 | F14: =Tenancy!$C$11*(Tenancy!$D$11*MAX(0,MIN(1,YEARFRAC(F$3,MIN(Tenancy!$E$11,EDATE(F$3,12)),1)*(Tenancy!$E$11>F$3)))+Tenancy!$F$11*(1+Inputs!$B$6)^(F$2-1)*IF(Tenancy!$E$11<EDATE(F$3,12),Tenancy!$G$11*MAX(0,MAX(0,MIN(12,DATEDIF(MAX(Tenancy!$E$11,F$3),EDATE(F$3,12),"m")))-MAX(0,Inputs!$B$9-IF(Tenancy!$E$11<F$3,DATEDIF(Tenancy!$E$11,F$3,"m"),0)))/12+(1-Tenancy!$G$11)*MAX(0,MAX(0,MIN(12,DATEDIF(MAX(Tenancy!$E$11,F$3),EDATE(F$3,12),"m")))-MAX(0,Inputs!$B$7+Inputs!$B$8-IF(Tenancy!$E$11<F$3,DATEDIF(Tenancy!$E$11,F$3,"m"),0)))/12,0)) -> 1330000 | G14: =Tenancy!$C$11*(Tenancy!$D$11*MAX(0,MIN(1,YEARFRAC(G$3,MIN(Tenancy!$E$11,EDATE(G$3,12)),1)*(Tenancy!$E$11>G$3)))+Tenancy!$F$11*(1+Inputs!$B$6)^(G$2-1)*IF(Tenancy!$E$11<EDATE(G$3,12),Tenancy!$G$11*MAX(0,MAX(0,MIN(12,DATEDIF(MAX(Tenancy!$E$11,G$3),EDATE(G$3,12),"m")))-MAX(0,Inputs!$B$9-IF(Tenancy!$E$11<G$3,DATEDIF(Tenancy!$E$11,G$3,"m"),0)))/12+(1-Tenancy!$G$11)*MAX(0,MAX(0,MIN(12,DATEDIF(MAX(Tenancy!$E$11,G$3),EDATE(G$3,12),"m")))-MAX(0,Inputs!$B$7+Inputs!$B$8-IF(Tenancy!$E$11<G$3,DATEDIF(Tenancy!$E$11,G$3,"m"),0)))/12,0)) -> 1330000 | H14: =Tenancy!$C$11*(Tenancy!$D$11*MAX(0,MIN(1,YEARFRAC(H$3,MIN(Tenancy!$E$11,EDATE(H$3,12)),1)*(Tenancy!$E$11>H$3)))+Tenancy!$F$11*(1+Inputs!$B$6)^(H$2-1)*IF(Tenancy!$E$11<EDATE(H$3,12),Tenancy!$G$11*MAX(0,MAX(0,MIN(12,DATEDIF(MAX(Tenancy!$E$11,H$3),EDATE(H$3,12),"m")))-MAX(0,Inputs!$B$9-IF(Tenancy!$E$11<H$3,DATEDIF(Tenancy!$E$11,H$3,"m"),0)))/12+(1-Tenancy!$G$11)*MAX(0,MAX(0,MIN(12,DATEDIF(MAX(Tenancy!$E$11,H$3),EDATE(H$3,12),"m")))-MAX(0,Inputs!$B$7+Inputs!$B$8-IF(Tenancy!$E$11<H$3,DATEDIF(Tenancy!$E$11,H$3,"m"),0)))/12,0)) -> 1330000 | I14: =Tenancy!$C$11*(Tenancy!$D$11*MAX(0,MIN(1,YEARFRAC(I$3,MIN(Tenancy!$E$11,EDATE(I$3,12)),1)*(Tenancy!$E$11>I$3)))+Tenancy!$F$11*(1+Inputs!$B$6)^(I$2-1)*IF(Tenancy!$E$11<EDATE(I$3,12),Tenancy!$G$11*MAX(0,MAX(0,MIN(12,DATEDIF(MAX(Tenancy!$E$11,I$3),EDATE(I$3,12),"m")))-MAX(0,Inputs!$B$9-IF(Tenancy!$E$11<I$3,DATEDIF(Tenancy!$E$11,I$3,"m"),0)))/12+(1-Tenancy!$G$11)*MAX(0,MAX(0,MIN(12,DATEDIF(MAX(Tenancy!$E$11,I$3),EDATE(I$3,12),"m")))-MAX(0,Inputs!$B$7+Inputs!$B$8-IF(Tenancy!$E$11<I$3,DATEDIF(Tenancy!$E$11,I$3,"m"),0)))/12,0)) -> 1330000 | J14: =Tenancy!$C$11*(Tenancy!$D$11*MAX(0,MIN(1,YEARFRAC(J$3,MIN(Tenancy!$E$11,EDATE(J$3,12)),1)*(Tenancy!$E$11>J$3)))+Tenancy!$F$11*(1+Inputs!$B$6)^(J$2-1)*IF(Tenancy!$E$11<EDATE(J$3,12),Tenancy!$G$11*MAX(0,MAX(0,MIN(12,DATEDIF(MAX(Tenancy!$E$11,J$3),EDATE(J$3,12),"m")))-MAX(0,Inputs!$B$9-IF(Tenancy!$E$11<J$3,DATEDIF(Tenancy!$E$11,J$3,"m"),0)))/12+(1-Tenancy!$G$11)*MAX(0,MAX(0,MIN(12,DATEDIF(MAX(Tenancy!$E$11,J$3),EDATE(J$3,12),"m")))-MAX(0,Inputs!$B$7+Inputs!$B$8-IF(Tenancy!$E$11<J$3,DATEDIF(Tenancy!$E$11,J$3,"m"),0)))/12,0)) -> 1330000 | ... M14: =Tenancy!$C$11*(Tenancy!$D$11*MAX(0,MIN(1,YEARFRAC(M$3,MIN(Tenancy!$E$11,EDATE(M$3,12)),1)*(Tenancy!$E$11>M$3)))+Tenancy!$F$11*(1+Inputs!$B$6)^(M$2-1)*IF(Tenancy!$E$11<EDATE(M$3,12),Tenancy!$G$11*MAX(0,MAX(0,MIN(12,DATEDIF(MAX(Tenancy!$E$11,M$3),EDATE(M$3,12),"m")))-MAX(0,Inputs!$B$9-IF(Tenancy!$E$11<M$3,DATEDIF(Tenancy!$E$11,M$3,"m"),0)))/12+(1-Tenancy!$G$11)*MAX(0,MAX(0,MIN(12,DATEDIF(MAX(Tenancy!$E$11,M$3),EDATE(M$3,12),"m")))-MAX(0,Inputs!$B$7+Inputs!$B$8-IF(Tenancy!$E$11<M$3,DATEDIF(Tenancy!$E$11,M$3,"m"),0)))/12,0)) -> 1225809
A15: =Tenancy!B12&" · "&Tenancy!A12 -> Nimbus Capital · 10 | C15: =Tenancy!$C$12*(Tenancy!$D$12*MAX(0,MIN(1,YEARFRAC(C$3,MIN(Tenancy!$E$12,EDATE(C$3,12)),1)*(Tenancy!$E$12>C$3)))+Tenancy!$F$12*(1+Inputs!$B$6)^(C$2-1)*IF(Tenancy!$E$12<EDATE(C$3,12),Tenancy!$G$12*MAX(0,MAX(0,MIN(12,DATEDIF(MAX(Tenancy!$E$12,C$3),EDATE(C$3,12),"m")))-MAX(0,Inputs!$B$9-IF(Tenancy!$E$12<C$3,DATEDIF(Tenancy!$E$12,C$3,"m"),0)))/12+(1-Tenancy!$G$12)*MAX(0,MAX(0,MIN(12,DATEDIF(MAX(Tenancy!$E$12,C$3),EDATE(C$3,12),"m")))-MAX(0,Inputs!$B$7+Inputs!$B$8-IF(Tenancy!$E$12<C$3,DATEDIF(Tenancy!$E$12,C$3,"m"),0)))/12,0)) -> 1326000 | D15: =Tenancy!$C$12*(Tenancy!$D$12*MAX(0,MIN(1,YEARFRAC(D$3,MIN(Tenancy!$E$12,EDATE(D$3,12)),1)*(Tenancy!$E$12>D$3)))+Tenancy!$F$12*(1+Inputs!$B$6)^(D$2-1)*IF(Tenancy!$E$12<EDATE(D$3,12),Tenancy!$G$12*MAX(0,MAX(0,MIN(12,DATEDIF(MAX(Tenancy!$E$12,D$3),EDATE(D$3,12),"m")))-MAX(0,Inputs!$B$9-IF(Tenancy!$E$12<D$3,DATEDIF(Tenancy!$E$12,D$3,"m"),0)))/12+(1-Tenancy!$G$12)*MAX(0,MAX(0,MIN(12,DATEDIF(MAX(Tenancy!$E$12,D$3),EDATE(D$3,12),"m")))-MAX(0,Inputs!$B$7+Inputs!$B$8-IF(Tenancy!$E$12<D$3,DATEDIF(Tenancy!$E$12,D$3,"m"),0)))/12,0)) -> 1326000 | E15: =Tenancy!$C$12*(Tenancy!$D$12*MAX(0,MIN(1,YEARFRAC(E$3,MIN(Tenancy!$E$12,EDATE(E$3,12)),1)*(Tenancy!$E$12>E$3)))+Tenancy!$F$12*(1+Inputs!$B$6)^(E$2-1)*IF(Tenancy!$E$12<EDATE(E$3,12),Tenancy!$G$12*MAX(0,MAX(0,MIN(12,DATEDIF(MAX(Tenancy!$E$12,E$3),EDATE(E$3,12),"m")))-MAX(0,Inputs!$B$9-IF(Tenancy!$E$12<E$3,DATEDIF(Tenancy!$E$12,E$3,"m"),0)))/12+(1-Tenancy!$G$12)*MAX(0,MAX(0,MIN(12,DATEDIF(MAX(Tenancy!$E$12,E$3),EDATE(E$3,12),"m")))-MAX(0,Inputs!$B$7+Inputs!$B$8-IF(Tenancy!$E$12<E$3,DATEDIF(Tenancy!$E$12,E$3,"m"),0)))/12,0)) -> 1326000 | F15: =Tenancy!$C$12*(Tenancy!$D$12*MAX(0,MIN(1,YEARFRAC(F$3,MIN(Tenancy!$E$12,EDATE(F$3,12)),1)*(Tenancy!$E$12>F$3)))+Tenancy!$F$12*(1+Inputs!$B$6)^(F$2-1)*IF(Tenancy!$E$12<EDATE(F$3,12),Tenancy!$G$12*MAX(0,MAX(0,MIN(12,DATEDIF(MAX(Tenancy!$E$12,F$3),EDATE(F$3,12),"m")))-MAX(0,Inputs!$B$9-IF(Tenancy!$E$12<F$3,DATEDIF(Tenancy!$E$12,F$3,"m"),0)))/12+(1-Tenancy!$G$12)*MAX(0,MAX(0,MIN(12,DATEDIF(MAX(Tenancy!$E$12,F$3),EDATE(F$3,12),"m")))-MAX(0,Inputs!$B$7+Inputs!$B$8-IF(Tenancy!$E$12<F$3,DATEDIF(Tenancy!$E$12,F$3,"m"),0)))/12,0)) -> 1326000 | G15: =Tenancy!$C$12*(Tenancy!$D$12*MAX(0,MIN(1,YEARFRAC(G$3,MIN(Tenancy!$E$12,EDATE(G$3,12)),1)*(Tenancy!$E$12>G$3)))+Tenancy!$F$12*(1+Inputs!$B$6)^(G$2-1)*IF(Tenancy!$E$12<EDATE(G$3,12),Tenancy!$G$12*MAX(0,MAX(0,MIN(12,DATEDIF(MAX(Tenancy!$E$12,G$3),EDATE(G$3,12),"m")))-MAX(0,Inputs!$B$9-IF(Tenancy!$E$12<G$3,DATEDIF(Tenancy!$E$12,G$3,"m"),0)))/12+(1-Tenancy!$G$12)*MAX(0,MAX(0,MIN(12,DATEDIF(MAX(Tenancy!$E$12,G$3),EDATE(G$3,12),"m")))-MAX(0,Inputs!$B$7+Inputs!$B$8-IF(Tenancy!$E$12<G$3,DATEDIF(Tenancy!$E$12,G$3,"m"),0)))/12,0)) -> 1296937 | H15: =Tenancy!$C$12*(Tenancy!$D$12*MAX(0,MIN(1,YEARFRAC(H$3,MIN(Tenancy!$E$12,EDATE(H$3,12)),1)*(Tenancy!$E$12>H$3)))+Tenancy!$F$12*(1+Inputs!$B$6)^(H$2-1)*IF(Tenancy!$E$12<EDATE(H$3,12),Tenancy!$G$12*MAX(0,MAX(0,MIN(12,DATEDIF(MAX(Tenancy!$E$12,H$3),EDATE(H$3,12),"m")))-MAX(0,Inputs!$B$9-IF(Tenancy!$E$12<H$3,DATEDIF(Tenancy!$E$12,H$3,"m"),0)))/12+(1-Tenancy!$G$12)*MAX(0,MAX(0,MIN(12,DATEDIF(MAX(Tenancy!$E$12,H$3),EDATE(H$3,12),"m")))-MAX(0,Inputs!$B$7+Inputs!$B$8-IF(Tenancy!$E$12<H$3,DATEDIF(Tenancy!$E$12,H$3,"m"),0)))/12,0)) -> 328900.37 | I15: =Tenancy!$C$12*(Tenancy!$D$12*MAX(0,MIN(1,YEARFRAC(I$3,MIN(Tenancy!$E$12,EDATE(I$3,12)),1)*(Tenancy!$E$12>I$3)))+Tenancy!$F$12*(1+Inputs!$B$6)^(I$2-1)*IF(Tenancy!$E$12<EDATE(I$3,12),Tenancy!$G$12*MAX(0,MAX(0,MIN(12,DATEDIF(MAX(Tenancy!$E$12,I$3),EDATE(I$3,12),"m")))-MAX(0,Inputs!$B$9-IF(Tenancy!$E$12<I$3,DATEDIF(Tenancy!$E$12,I$3,"m"),0)))/12+(1-Tenancy!$G$12)*MAX(0,MAX(0,MIN(12,DATEDIF(MAX(Tenancy!$E$12,I$3),EDATE(I$3,12),"m")))-MAX(0,Inputs!$B$7+Inputs!$B$8-IF(Tenancy!$E$12<I$3,DATEDIF(Tenancy!$E$12,I$3,"m"),0)))/12,0)) -> 674245.75 | J15: =Tenancy!$C$12*(Tenancy!$D$12*MAX(0,MIN(1,YEARFRAC(J$3,MIN(Tenancy!$E$12,EDATE(J$3,12)),1)*(Tenancy!$E$12>J$3)))+Tenancy!$F$12*(1+Inputs!$B$6)^(J$2-1)*IF(Tenancy!$E$12<EDATE(J$3,12),Tenancy!$G$12*MAX(0,MAX(0,MIN(12,DATEDIF(MAX(Tenancy!$E$12,J$3),EDATE(J$3,12),"m")))-MAX(0,Inputs!$B$9-IF(Tenancy!$E$12<J$3,DATEDIF(Tenancy!$E$12,J$3,"m"),0)))/12+(1-Tenancy!$G$12)*MAX(0,MAX(0,MIN(12,DATEDIF(MAX(Tenancy!$E$12,J$3),EDATE(J$3,12),"m")))-MAX(0,Inputs!$B$7+Inputs!$B$8-IF(Tenancy!$E$12<J$3,DATEDIF(Tenancy!$E$12,J$3,"m"),0)))/12,0)) -> 1113441.9 | ... M15: =Tenancy!$C$12*(Tenancy!$D$12*MAX(0,MIN(1,YEARFRAC(M$3,MIN(Tenancy!$E$12,EDATE(M$3,12)),1)*(Tenancy!$E$12>M$3)))+Tenancy!$F$12*(1+Inputs!$B$6)^(M$2-1)*IF(Tenancy!$E$12<EDATE(M$3,12),Tenancy!$G$12*MAX(0,MAX(0,MIN(12,DATEDIF(MAX(Tenancy!$E$12,M$3),EDATE(M$3,12),"m")))-MAX(0,Inputs!$B$9-IF(Tenancy!$E$12<M$3,DATEDIF(Tenancy!$E$12,M$3,"m"),0)))/12+(1-Tenancy!$G$12)*MAX(0,MAX(0,MIN(12,DATEDIF(MAX(Tenancy!$E$12,M$3),EDATE(M$3,12),"m")))-MAX(0,Inputs!$B$7+Inputs!$B$8-IF(Tenancy!$E$12<M$3,DATEDIF(Tenancy!$E$12,M$3,"m"),0)))/12,0)) -> 1653869.2
A16: =Tenancy!B13&" · "&Tenancy!A13 -> Nimbus Capital · 11 | C16: =Tenancy!$C$13*(Tenancy!$D$13*MAX(0,MIN(1,YEARFRAC(C$3,MIN(Tenancy!$E$13,EDATE(C$3,12)),1)*(Tenancy!$E$13>C$3)))+Tenancy!$F$13*(1+Inputs!$B$6)^(C$2-1)*IF(Tenancy!$E$13<EDATE(C$3,12),Tenancy!$G$13*MAX(0,MAX(0,MIN(12,DATEDIF(MAX(Tenancy!$E$13,C$3),EDATE(C$3,12),"m")))-MAX(0,Inputs!$B$9-IF(Tenancy!$E$13<C$3,DATEDIF(Tenancy!$E$13,C$3,"m"),0)))/12+(1-Tenancy!$G$13)*MAX(0,MAX(0,MIN(12,DATEDIF(MAX(Tenancy!$E$13,C$3),EDATE(C$3,12),"m")))-MAX(0,Inputs!$B$7+Inputs!$B$8-IF(Tenancy!$E$13<C$3,DATEDIF(Tenancy!$E$13,C$3,"m"),0)))/12,0)) -> 1326000 | D16: =Tenancy!$C$13*(Tenancy!$D$13*MAX(0,MIN(1,YEARFRAC(D$3,MIN(Tenancy!$E$13,EDATE(D$3,12)),1)*(Tenancy!$E$13>D$3)))+Tenancy!$F$13*(1+Inputs!$B$6)^(D$2-1)*IF(Tenancy!$E$13<EDATE(D$3,12),Tenancy!$G$13*MAX(0,MAX(0,MIN(12,DATEDIF(MAX(Tenancy!$E$13,D$3),EDATE(D$3,12),"m")))-MAX(0,Inputs!$B$9-IF(Tenancy!$E$13<D$3,DATEDIF(Tenancy!$E$13,D$3,"m"),0)))/12+(1-Tenancy!$G$13)*MAX(0,MAX(0,MIN(12,DATEDIF(MAX(Tenancy!$E$13,D$3),EDATE(D$3,12),"m")))-MAX(0,Inputs!$B$7+Inputs!$B$8-IF(Tenancy!$E$13<D$3,DATEDIF(Tenancy!$E$13,D$3,"m"),0)))/12,0)) -> 1326000 | E16: =Tenancy!$C$13*(Tenancy!$D$13*MAX(0,MIN(1,YEARFRAC(E$3,MIN(Tenancy!$E$13,EDATE(E$3,12)),1)*(Tenancy!$E$13>E$3)))+Tenancy!$F$13*(1+Inputs!$B$6)^(E$2-1)*IF(Tenancy!$E$13<EDATE(E$3,12),Tenancy!$G$13*MAX(0,MAX(0,MIN(12,DATEDIF(MAX(Tenancy!$E$13,E$3),EDATE(E$3,12),"m")))-MAX(0,Inputs!$B$9-IF(Tenancy!$E$13<E$3,DATEDIF(Tenancy!$E$13,E$3,"m"),0)))/12+(1-Tenancy!$G$13)*MAX(0,MAX(0,MIN(12,DATEDIF(MAX(Tenancy!$E$13,E$3),EDATE(E$3,12),"m")))-MAX(0,Inputs!$B$7+Inputs!$B$8-IF(Tenancy!$E$13<E$3,DATEDIF(Tenancy!$E$13,E$3,"m"),0)))/12,0)) -> 1326000 | F16: =Tenancy!$C$13*(Tenancy!$D$13*MAX(0,MIN(1,YEARFRAC(F$3,MIN(Tenancy!$E$13,EDATE(F$3,12)),1)*(Tenancy!$E$13>F$3)))+Tenancy!$F$13*(1+Inputs!$B$6)^(F$2-1)*IF(Tenancy!$E$13<EDATE(F$3,12),Tenancy!$G$13*MAX(0,MAX(0,MIN(12,DATEDIF(MAX(Tenancy!$E$13,F$3),EDATE(F$3,12),"m")))-MAX(0,Inputs!$B$9-IF(Tenancy!$E$13<F$3,DATEDIF(Tenancy!$E$13,F$3,"m"),0)))/12+(1-Tenancy!$G$13)*MAX(0,MAX(0,MIN(12,DATEDIF(MAX(Tenancy!$E$13,F$3),EDATE(F$3,12),"m")))-MAX(0,Inputs!$B$7+Inputs!$B$8-IF(Tenancy!$E$13<F$3,DATEDIF(Tenancy!$E$13,F$3,"m"),0)))/12,0)) -> 1326000 | G16: =Tenancy!$C$13*(Tenancy!$D$13*MAX(0,MIN(1,YEARFRAC(G$3,MIN(Tenancy!$E$13,EDATE(G$3,12)),1)*(Tenancy!$E$13>G$3)))+Tenancy!$F$13*(1+Inputs!$B$6)^(G$2-1)*IF(Tenancy!$E$13<EDATE(G$3,12),Tenancy!$G$13*MAX(0,MAX(0,MIN(12,DATEDIF(MAX(Tenancy!$E$13,G$3),EDATE(G$3,12),"m")))-MAX(0,Inputs!$B$9-IF(Tenancy!$E$13<G$3,DATEDIF(Tenancy!$E$13,G$3,"m"),0)))/12+(1-Tenancy!$G$13)*MAX(0,MAX(0,MIN(12,DATEDIF(MAX(Tenancy!$E$13,G$3),EDATE(G$3,12),"m")))-MAX(0,Inputs!$B$7+Inputs!$B$8-IF(Tenancy!$E$13<G$3,DATEDIF(Tenancy!$E$13,G$3,"m"),0)))/12,0)) -> 1296937 | H16: =Tenancy!$C$13*(Tenancy!$D$13*MAX(0,MIN(1,YEARFRAC(H$3,MIN(Tenancy!$E$13,EDATE(H$3,12)),1)*(Tenancy!$E$13>H$3)))+Tenancy!$F$13*(1+Inputs!$B$6)^(H$2-1)*IF(Tenancy!$E$13<EDATE(H$3,12),Tenancy!$G$13*MAX(0,MAX(0,MIN(12,DATEDIF(MAX(Tenancy!$E$13,H$3),EDATE(H$3,12),"m")))-MAX(0,Inputs!$B$9-IF(Tenancy!$E$13<H$3,DATEDIF(Tenancy!$E$13,H$3,"m"),0)))/12+(1-Tenancy!$G$13)*MAX(0,MAX(0,MIN(12,DATEDIF(MAX(Tenancy!$E$13,H$3),EDATE(H$3,12),"m")))-MAX(0,Inputs!$B$7+Inputs!$B$8-IF(Tenancy!$E$13<H$3,DATEDIF(Tenancy!$E$13,H$3,"m"),0)))/12,0)) -> 328900.37 | I16: =Tenancy!$C$13*(Tenancy!$D$13*MAX(0,MIN(1,YEARFRAC(I$3,MIN(Tenancy!$E$13,EDATE(I$3,12)),1)*(Tenancy!$E$13>I$3)))+Tenancy!$F$13*(1+Inputs!$B$6)^(I$2-1)*IF(Tenancy!$E$13<EDATE(I$3,12),Tenancy!$G$13*MAX(0,MAX(0,MIN(12,DATEDIF(MAX(Tenancy!$E$13,I$3),EDATE(I$3,12),"m")))-MAX(0,Inputs!$B$9-IF(Tenancy!$E$13<I$3,DATEDIF(Tenancy!$E$13,I$3,"m"),0)))/12+(1-Tenancy!$G$13)*MAX(0,MAX(0,MIN(12,DATEDIF(MAX(Tenancy!$E$13,I$3),EDATE(I$3,12),"m")))-MAX(0,Inputs!$B$7+Inputs!$B$8-IF(Tenancy!$E$13<I$3,DATEDIF(Tenancy!$E$13,I$3,"m"),0)))/12,0)) -> 674245.75 | J16: =Tenancy!$C$13*(Tenancy!$D$13*MAX(0,MIN(1,YEARFRAC(J$3,MIN(Tenancy!$E$13,EDATE(J$3,12)),1)*(Tenancy!$E$13>J$3)))+Tenancy!$F$13*(1+Inputs!$B$6)^(J$2-1)*IF(Tenancy!$E$13<EDATE(J$3,12),Tenancy!$G$13*MAX(0,MAX(0,MIN(12,DATEDIF(MAX(Tenancy!$E$13,J$3),EDATE(J$3,12),"m")))-MAX(0,Inputs!$B$9-IF(Tenancy!$E$13<J$3,DATEDIF(Tenancy!$E$13,J$3,"m"),0)))/12+(1-Tenancy!$G$13)*MAX(0,MAX(0,MIN(12,DATEDIF(MAX(Tenancy!$E$13,J$3),EDATE(J$3,12),"m")))-MAX(0,Inputs!$B$7+Inputs!$B$8-IF(Tenancy!$E$13<J$3,DATEDIF(Tenancy!$E$13,J$3,"m"),0)))/12,0)) -> 1113441.9 | ... M16: =Tenancy!$C$13*(Tenancy!$D$13*MAX(0,MIN(1,YEARFRAC(M$3,MIN(Tenancy!$E$13,EDATE(M$3,12)),1)*(Tenancy!$E$13>M$3)))+Tenancy!$F$13*(1+Inputs!$B$6)^(M$2-1)*IF(Tenancy!$E$13<EDATE(M$3,12),Tenancy!$G$13*MAX(0,MAX(0,MIN(12,DATEDIF(MAX(Tenancy!$E$13,M$3),EDATE(M$3,12),"m")))-MAX(0,Inputs!$B$9-IF(Tenancy!$E$13<M$3,DATEDIF(Tenancy!$E$13,M$3,"m"),0)))/12+(1-Tenancy!$G$13)*MAX(0,MAX(0,MIN(12,DATEDIF(MAX(Tenancy!$E$13,M$3),EDATE(M$3,12),"m")))-MAX(0,Inputs!$B$7+Inputs!$B$8-IF(Tenancy!$E$13<M$3,DATEDIF(Tenancy!$E$13,M$3,"m"),0)))/12,0)) -> 1653869.2
A17: Rent received | C17: =SUM(C5:C16) -> 14039000 | D17: =SUM(D5:D16) -> 12438808 | E17: =SUM(E5:E16) -> 12501452 | F17: =SUM(F5:F16) -> 13621838 | G17: =SUM(G5:G16) -> 14588480 | H17: =SUM(H5:H16) -> 14261342 | I17: =SUM(I5:I16) -> 15697142 | J17: =SUM(J5:J16) -> 16185000 | ... M17: =SUM(M5:M16) -> 19578509
A18: Leasing costs (probability-weighted) | C18: =SUMPRODUCT((Tenancy!$E$2:$E$13>=C$3)*(Tenancy!$E$2:$E$13<EDATE(C$3,12))*Tenancy!$C$2:$C$13*(Tenancy!$G$2:$G$13*(Inputs!$B$11+Inputs!$B$12*Tenancy!$F$2:$F$13*(1+Inputs!$B$6)^(C$2-1))+(1-Tenancy!$G$2:$G$13)*(Inputs!$B$10+Inputs!$B$12*Tenancy!$F$2:$F$13*(1+Inputs!$B$6)^(C$2-1)))) -> 1474200 | D18: =SUMPRODUCT((Tenancy!$E$2:$E$13>=D$3)*(Tenancy!$E$2:$E$13<EDATE(D$3,12))*Tenancy!$C$2:$C$13*(Tenancy!$G$2:$G$13*(Inputs!$B$11+Inputs!$B$12*Tenancy!$F$2:$F$13*(1+Inputs!$B$6)^(D$2-1))+(1-Tenancy!$G$2:$G$13)*(Inputs!$B$10+Inputs!$B$12*Tenancy!$F$2:$F$13*(1+Inputs!$B$6)^(D$2-1)))) -> 2035110 | E18: =SUMPRODUCT((Tenancy!$E$2:$E$13>=E$3)*(Tenancy!$E$2:$E$13<EDATE(E$3,12))*Tenancy!$C$2:$C$13*(Tenancy!$G$2:$G$13*(Inputs!$B$11+Inputs!$B$12*Tenancy!$F$2:$F$13*(1+Inputs!$B$6)^(E$2-1))+(1-Tenancy!$G$2:$G$13)*(Inputs!$B$10+Inputs!$B$12*Tenancy!$F$2:$F$13*(1+Inputs!$B$6)^(E$2-1)))) -> 2085832.7 | F18: =SUMPRODUCT((Tenancy!$E$2:$E$13>=F$3)*(Tenancy!$E$2:$E$13<EDATE(F$3,12))*Tenancy!$C$2:$C$13*(Tenancy!$G$2:$G$13*(Inputs!$B$11+Inputs!$B$12*Tenancy!$F$2:$F$13*(1+Inputs!$B$6)^(F$2-1))+(1-Tenancy!$G$2:$G$13)*(Inputs!$B$10+Inputs!$B$12*Tenancy!$F$2:$F$13*(1+Inputs!$B$6)^(F$2-1)))) -> 902669.97 | G18: =SUMPRODUCT((Tenancy!$E$2:$E$13>=G$3)*(Tenancy!$E$2:$E$13<EDATE(G$3,12))*Tenancy!$C$2:$C$13*(Tenancy!$G$2:$G$13*(Inputs!$B$11+Inputs!$B$12*Tenancy!$F$2:$F$13*(1+Inputs!$B$6)^(G$2-1))+(1-Tenancy!$G$2:$G$13)*(Inputs!$B$10+Inputs!$B$12*Tenancy!$F$2:$F$13*(1+Inputs!$B$6)^(G$2-1)))) -> 1855837.9 | H18: =SUMPRODUCT((Tenancy!$E$2:$E$13>=H$3)*(Tenancy!$E$2:$E$13<EDATE(H$3,12))*Tenancy!$C$2:$C$13*(Tenancy!$G$2:$G$13*(Inputs!$B$11+Inputs!$B$12*Tenancy!$F$2:$F$13*(1+Inputs!$B$6)^(H$2-1))+(1-Tenancy!$G$2:$G$13)*(Inputs!$B$10+Inputs!$B$12*Tenancy!$F$2:$F$13*(1+Inputs!$B$6)^(H$2-1)))) -> 574557.43 | I18: =SUMPRODUCT((Tenancy!$E$2:$E$13>=I$3)*(Tenancy!$E$2:$E$13<EDATE(I$3,12))*Tenancy!$C$2:$C$13*(Tenancy!$G$2:$G$13*(Inputs!$B$11+Inputs!$B$12*Tenancy!$F$2:$F$13*(1+Inputs!$B$6)^(I$2-1))+(1-Tenancy!$G$2:$G$13)*(Inputs!$B$10+Inputs!$B$12*Tenancy!$F$2:$F$13*(1+Inputs!$B$6)^(I$2-1)))) -> 943057.95 | J18: =SUMPRODUCT((Tenancy!$E$2:$E$13>=J$3)*(Tenancy!$E$2:$E$13<EDATE(J$3,12))*Tenancy!$C$2:$C$13*(Tenancy!$G$2:$G$13*(Inputs!$B$11+Inputs!$B$12*Tenancy!$F$2:$F$13*(1+Inputs!$B$6)^(J$2-1))+(1-Tenancy!$G$2:$G$13)*(Inputs!$B$10+Inputs!$B$12*Tenancy!$F$2:$F$13*(1+Inputs!$B$6)^(J$2-1)))) -> 0 | ... M18: =SUMPRODUCT((Tenancy!$E$2:$E$13>=M$3)*(Tenancy!$E$2:$E$13<EDATE(M$3,12))*Tenancy!$C$2:$C$13*(Tenancy!$G$2:$G$13*(Inputs!$B$11+Inputs!$B$12*Tenancy!$F$2:$F$13*(1+Inputs!$B$6)^(M$2-1))+(1-Tenancy!$G$2:$G$13)*(Inputs!$B$10+Inputs!$B$12*Tenancy!$F$2:$F$13*(1+Inputs!$B$6)^(M$2-1)))) -> 0
A19: Non-recoverable costs | C19: =C17*Inputs!$B$13 -> 561560 | D19: =D17*Inputs!$B$13 -> 497552.32 | E19: =E17*Inputs!$B$13 -> 500058.06 | F19: =F17*Inputs!$B$13 -> 544873.53 | G19: =G17*Inputs!$B$13 -> 583539.21 | H19: =H17*Inputs!$B$13 -> 570453.7 | I19: =I17*Inputs!$B$13 -> 627885.66 | J19: =J17*Inputs!$B$13 -> 647400.01 | ... M19: =M17*Inputs!$B$13 -> 783140.36
A20: Net operating income | C20: =C17-C19 -> 13477440 | D20: =D17-D19 -> 11941256 | E20: =E17-E19 -> 12001394 | F20: =F17-F19 -> 13076965 | G20: =G17-G19 -> 14004941 | H20: =H17-H19 -> 13690889 | I20: =I17-I19 -> 15069256 | J20: =J17-J19 -> 15537600 | ... M20: =M17-M19 -> 18795369
A21: Exit value | C21: =IF(C$2=10,D20/Inputs!$B$15*(1-Inputs!$B$16),0) -> 0 | D21: =IF(D$2=10,E20/Inputs!$B$15*(1-Inputs!$B$16),0) -> 0 | E21: =IF(E$2=10,F20/Inputs!$B$15*(1-Inputs!$B$16),0) -> 0 | F21: =IF(F$2=10,G20/Inputs!$B$15*(1-Inputs!$B$16),0) -> 0 | G21: =IF(G$2=10,H20/Inputs!$B$15*(1-Inputs!$B$16),0) -> 0 | H21: =IF(H$2=10,I20/Inputs!$B$15*(1-Inputs!$B$16),0) -> 0 | I21: =IF(I$2=10,J20/Inputs!$B$15*(1-Inputs!$B$16),0) -> 0 | J21: =IF(J$2=10,K20/Inputs!$B$15*(1-Inputs!$B$16),0) -> 0 | ... L21: =IF(L$2=10,M20/Inputs!$B$15*(1-Inputs!$B$16),0) -> 3.515629e+08 | M21: =0 -> 0
A22: Net cash flow | C22: =IF(C$2<=10,C20-C18+C21,0) -> 12003240 | D22: =IF(D$2<=10,D20-D18+D21,0) -> 9906145.6 | E22: =IF(E$2<=10,E20-E18+E21,0) -> 9915560.8 | F22: =IF(F$2<=10,F20-F18+F21,0) -> 12174295 | G22: =IF(G$2<=10,G20-G18+G21,0) -> 12149103 | H22: =IF(H$2<=10,H20-H18+H21,0) -> 13116331 | I22: =IF(I$2<=10,I20-I18+I21,0) -> 14126198 | J22: =IF(J$2<=10,J20-J18+J21,0) -> 15537600 | ... M22: =IF(M$2<=10,M20-M18+M21,0) -> 0

Sheet Valuation
A3: Net present value (£) | B3: =NPV(Inputs!$B$14,Rent!C22:L22) -> 2.576295e+08
A4: Value less price and costs (£) | B4: =B3-Inputs!$B$4*(1+Inputs!$B$5) -> -4030496.2
A5: Unlevered IRR | B5: =IRR(Valuation!B12:L12) -> 0.073022229
A6: Year 1 net operating income (£) | B6: =Rent!C20 -> 13477440
A7: Net initial yield | B7: =B6/(Inputs!$B$4*(1+Inputs!$B$5)) -> 0.051507452
A8: WAULT to expiry (years) | B8: =SUMPRODUCT(Tenancy!C2:C13,Tenancy!D2:D13,(Tenancy!E2:E13-Inputs!$B$3)/365.25)/SUMPRODUCT(Tenancy!C2:C13,Tenancy!D2:D13) -> 4.5466986
A9: Exit value (£) | B9: =SUM(Rent!C21:L21) -> 3.515629e+08
A12: IRR cash flow | B12: =-Inputs!$B$4*(1+Inputs!$B$5) -> -261660000 | C12: =Rent!C22 -> 12003240 | D12: =Rent!D22 -> 9906145.6 | E12: =Rent!E22 -> 9915560.8 | F12: =Rent!F22 -> 12174295 | G12: =Rent!G22 -> 12149103 | H12: =Rent!H22 -> 13116331 | I12: =Rent!I22 -> 14126198 | J12: =Rent!J22 -> 15537600 | ... L12: =Rent!L22 -> 3.6927505e+08
