Workbook

Sheet Inputs
A1: CAPE AZURE RESORT – MONTHLY OPERATING MODEL (ZAR)
A3: Keys | B3: 240
A4: ADR, year 1 average (R) | B4: 4200
A5: Stabilised occupancy | B5: 0.72
A6: ADR growth a year | B6: 0.055
A7: Other revenue (% of rooms) | B7: 0.55
A8: Rooms department cost (% of rooms) | B8: 0.24
A9: Other departments cost (% of other revenue) | B9: 0.68
A10: Undistributed (% of revenue) | B10: 0.19
A11: Fixed costs a month (R) | B11: 2600000
A12: Fixed cost growth a year | B12: 0.06
A13: Base fee (% of revenue) | B13: 0.025
A14: Incentive fee (% above owner priority) | B14: 0.15
... A24: Exit cap rate | B24: 0.095

Sheet Seasonality
A1: Month | B1: Occupancy index | C1: ADR index
A2: 1 | B2: 1.22 | C2: 1.35
A3: 2 | B3: 1.15 | C3: 1.25
A4: 3 | B4: 1.05 | C4: 1.1
A5: 4 | B5: 0.95 | C5: 0.95
A6: 5 | B6: 0.82 | C6: 0.85
A7: 6 | B7: 0.75 | C7: 0.8
A8: 7 | B8: 0.8 | C8: 0.82
A9: 8 | B9: 0.85 | C9: 0.85
A10: 9 | B10: 0.92 | C10: 0.9
A11: 10 | B11: 1 | C11: 0.98
A12: 11 | B12: 1.12 | C12: 1.1
A13: 12 | B13: 1.37 | C13: 1.45

Sheet Cash Flow
A3: Month | B3: 0 | C3: 1 | D3: 2 | E3: 3 | F3: 4 | G3: 5 | H3: 6 | I3: 7 | J3: 8 | K3: 9 | L3: 10 | M3: 11 | N3: 12 | O3: 13 | P3: 14 | Q3: 15 | R3: 16 | S3: 17 | T3: 18 | U3: 19 | V3: 20 | W3: 21 | X3: 22 | Y3: 23 | Z3: 24 | AA3: 25 | AB3: 26 | AC3: 27 | AD3: 28 | AE3: 29 | AF3: 30 | AG3: 31 | AH3: 32 | AI3: 33 | AJ3: 34 | AK3: 35 | AL3: 36 | AM3: 37 | AN3: 38 | AO3: 39 | AP3: 40 | AQ3: 41 | AR3: 42 | AS3: 43 | AT3: 44 | AU3: 45 | AV3: 46 | AW3: 47 | AX3: 48 | AY3: 49 | AZ3: 50 | BA3: 51 | BB3: 52 | BC3: 53 | BD3: 54 | BE3: 55 | BF3: 56 | BG3: 57 | BH3: 58 | BI3: 59 | BJ3: 60 | BK3: 61 | BL3: 62 | BM3: 63 | BN3: 64 | BO3: 65 | BP3: 66 | BQ3: 67 | BR3: 68 | BS3: 69 | BT3: 70 | BU3: 71 | BV3: 72 | BW3: 73 | BX3: 74 | BY3: 75 | BZ3: 76 | CA3: 77 | CB3: 78 | CC3: 79 | CD3: 80 | CE3: 81 | CF3: 82 | CG3: 83 | CH3: 84 | CI3: 85 | CJ3: 86 | CK3: 87 | CL3: 88 | CM3: 89 | CN3: 90 | CO3: 91 | CP3: 92 | CQ3: 93 | CR3: 94 | CS3: 95 | CT3: 96 | CU3: 97 | CV3: 98 | CW3: 99 | CX3: 100 | CY3: 101 | CZ3: 102 | DA3: 103 | DB3: 104 | DC3: 105 | DD3: 106 | DE3: 107 | DF3: 108 | DG3: 109 | DH3: 110 | DI3: 111 | DJ3: 112 | DK3: 113 | DL3: 114 | DM3: 115 | DN3: 116 | DO3: 117 | DP3: 118 | DQ3: 119 | DR3: 120
A4: Year | B4: =IF(B$3=0,0,INT((B$3-1)/12)+1) -> 0 | C4: =IF(C$3=0,0,INT((C$3-1)/12)+1) -> 1 | D4: =IF(D$3=0,0,INT((D$3-1)/12)+1) -> 1 | E4: =IF(E$3=0,0,INT((E$3-1)/12)+1) -> 1 | F4: =IF(F$3=0,0,INT((F$3-1)/12)+1) -> 1 | G4: =IF(G$3=0,0,INT((G$3-1)/12)+1) -> 1 | H4: =IF(H$3=0,0,INT((H$3-1)/12)+1) -> 1 | I4: =IF(I$3=0,0,INT((I$3-1)/12)+1) -> 1 | ... DR4: =IF(DR$3=0,0,INT((DR$3-1)/12)+1) -> 10
A5: Month of year | B5: =IF(B$3=0,0,MOD(B$3-1,12)+1) -> 0 | C5: =IF(C$3=0,0,MOD(C$3-1,12)+1) -> 1 | D5: =IF(D$3=0,0,MOD(D$3-1,12)+1) -> 2 | E5: =IF(E$3=0,0,MOD(E$3-1,12)+1) -> 3 | F5: =IF(F$3=0,0,MOD(F$3-1,12)+1) -> 4 | G5: =IF(G$3=0,0,MOD(G$3-1,12)+1) -> 5 | H5: =IF(H$3=0,0,MOD(H$3-1,12)+1) -> 6 | I5: =IF(I$3=0,0,MOD(I$3-1,12)+1) -> 7 | ... DR5: =IF(DR$3=0,0,MOD(DR$3-1,12)+1) -> 12
A6: Ramp-up | B6: =CHOOSE(MIN(4,MAX(1,B4+1)),0,0.86,0.95,1) -> 0 | C6: =CHOOSE(MIN(4,MAX(1,C4+1)),0,0.86,0.95,1) -> 0.86 | D6: =CHOOSE(MIN(4,MAX(1,D4+1)),0,0.86,0.95,1) -> 0.86 | E6: =CHOOSE(MIN(4,MAX(1,E4+1)),0,0.86,0.95,1) -> 0.86 | F6: =CHOOSE(MIN(4,MAX(1,F4+1)),0,0.86,0.95,1) -> 0.86 | G6: =CHOOSE(MIN(4,MAX(1,G4+1)),0,0.86,0.95,1) -> 0.86 | H6: =CHOOSE(MIN(4,MAX(1,H4+1)),0,0.86,0.95,1) -> 0.86 | I6: =CHOOSE(MIN(4,MAX(1,I4+1)),0,0.86,0.95,1) -> 0.86 | ... DR6: =CHOOSE(MIN(4,MAX(1,DR4+1)),0,0.86,0.95,1) -> 1
A7: PIP | B7: =IF(AND(B$3>=Inputs!$B$16,B$3<Inputs!$B$16+Inputs!$B$17),1,0) -> 0 | C7: =IF(AND(C$3>=Inputs!$B$16,C$3<Inputs!$B$16+Inputs!$B$17),1,0) -> 0 | D7: =IF(AND(D$3>=Inputs!$B$16,D$3<Inputs!$B$16+Inputs!$B$17),1,0) -> 0 | E7: =IF(AND(E$3>=Inputs!$B$16,E$3<Inputs!$B$16+Inputs!$B$17),1,0) -> 0 | F7: =IF(AND(F$3>=Inputs!$B$16,F$3<Inputs!$B$16+Inputs!$B$17),1,0) -> 0 | G7: =IF(AND(G$3>=Inputs!$B$16,G$3<Inputs!$B$16+Inputs!$B$17),1,0) -> 0 | H7: =IF(AND(H$3>=Inputs!$B$16,H$3<Inputs!$B$16+Inputs!$B$17),1,0) -> 0 | I7: =IF(AND(I$3>=Inputs!$B$16,I$3<Inputs!$B$16+Inputs!$B$17),1,0) -> 0 | ... DR7: =IF(AND(DR$3>=Inputs!$B$16,DR$3<Inputs!$B$16+Inputs!$B$17),1,0) -> 0
A8: Occupancy | B8: =IF((B$3>=1),MIN(0.98,Inputs!$B$5*B6*INDEX(Seasonality!$B$2:$B$13,B5)/AVERAGE(Seasonality!$B$2:$B$13))*(1-Inputs!$B$18*B7),0) -> 0 | C8: =IF((C$3>=1),MIN(0.98,Inputs!$B$5*C6*INDEX(Seasonality!$B$2:$B$13,C5)/AVERAGE(Seasonality!$B$2:$B$13))*(1-Inputs!$B$18*C7),0) -> 0.755424 | D8: =IF((D$3>=1),MIN(0.98,Inputs!$B$5*D6*INDEX(Seasonality!$B$2:$B$13,D5)/AVERAGE(Seasonality!$B$2:$B$13))*(1-Inputs!$B$18*D7),0) -> 0.71208 | E8: =IF((E$3>=1),MIN(0.98,Inputs!$B$5*E6*INDEX(Seasonality!$B$2:$B$13,E5)/AVERAGE(Seasonality!$B$2:$B$13))*(1-Inputs!$B$18*E7),0) -> 0.65016 | F8: =IF((F$3>=1),MIN(0.98,Inputs!$B$5*F6*INDEX(Seasonality!$B$2:$B$13,F5)/AVERAGE(Seasonality!$B$2:$B$13))*(1-Inputs!$B$18*F7),0) -> 0.58824 | G8: =IF((G$3>=1),MIN(0.98,Inputs!$B$5*G6*INDEX(Seasonality!$B$2:$B$13,G5)/AVERAGE(Seasonality!$B$2:$B$13))*(1-Inputs!$B$18*G7),0) -> 0.507744 | H8: =IF((H$3>=1),MIN(0.98,Inputs!$B$5*H6*INDEX(Seasonality!$B$2:$B$13,H5)/AVERAGE(Seasonality!$B$2:$B$13))*(1-Inputs!$B$18*H7),0) -> 0.4644 | I8: =IF((I$3>=1),MIN(0.98,Inputs!$B$5*I6*INDEX(Seasonality!$B$2:$B$13,I5)/AVERAGE(Seasonality!$B$2:$B$13))*(1-Inputs!$B$18*I7),0) -> 0.49536 | ... DR8: =IF((DR$3>=1),MIN(0.98,Inputs!$B$5*DR6*INDEX(Seasonality!$B$2:$B$13,DR5)/AVERAGE(Seasonality!$B$2:$B$13))*(1-Inputs!$B$18*DR7),0) -> 0.98
A9: ADR | B9: =IF((B$3>=1),Inputs!$B$4*(1+Inputs!$B$6)^(B4-1)*INDEX(Seasonality!$C$2:$C$13,B5)/AVERAGE(Seasonality!$C$2:$C$13),0) -> 0 | C9: =IF((C$3>=1),Inputs!$B$4*(1+Inputs!$B$6)^(C4-1)*INDEX(Seasonality!$C$2:$C$13,C5)/AVERAGE(Seasonality!$C$2:$C$13),0) -> 5487.0968 | D9: =IF((D$3>=1),Inputs!$B$4*(1+Inputs!$B$6)^(D4-1)*INDEX(Seasonality!$C$2:$C$13,D5)/AVERAGE(Seasonality!$C$2:$C$13),0) -> 5080.6452 | E9: =IF((E$3>=1),Inputs!$B$4*(1+Inputs!$B$6)^(E4-1)*INDEX(Seasonality!$C$2:$C$13,E5)/AVERAGE(Seasonality!$C$2:$C$13),0) -> 4470.9677 | F9: =IF((F$3>=1),Inputs!$B$4*(1+Inputs!$B$6)^(F4-1)*INDEX(Seasonality!$C$2:$C$13,F5)/AVERAGE(Seasonality!$C$2:$C$13),0) -> 3861.2903 | G9: =IF((G$3>=1),Inputs!$B$4*(1+Inputs!$B$6)^(G4-1)*INDEX(Seasonality!$C$2:$C$13,G5)/AVERAGE(Seasonality!$C$2:$C$13),0) -> 3454.8387 | H9: =IF((H$3>=1),Inputs!$B$4*(1+Inputs!$B$6)^(H4-1)*INDEX(Seasonality!$C$2:$C$13,H5)/AVERAGE(Seasonality!$C$2:$C$13),0) -> 3251.6129 | I9: =IF((I$3>=1),Inputs!$B$4*(1+Inputs!$B$6)^(I4-1)*INDEX(Seasonality!$C$2:$C$13,I5)/AVERAGE(Seasonality!$C$2:$C$13),0) -> 3332.9032 | ... DR9: =IF((DR$3>=1),Inputs!$B$4*(1+Inputs!$B$6)^(DR4-1)*INDEX(Seasonality!$C$2:$C$13,DR5)/AVERAGE(Seasonality!$C$2:$C$13),0) -> 9542.2104
A10: Room nights | B10: =Inputs!$B$3*B8*DAY(EOMONTH(DATE(2026,B5+((B$3=0)*1),1),0)) -> 0 | C10: =Inputs!$B$3*C8*DAY(EOMONTH(DATE(2026,C5+((C$3=0)*1),1),0)) -> 5620.3546 | D10: =Inputs!$B$3*D8*DAY(EOMONTH(DATE(2026,D5+((D$3=0)*1),1),0)) -> 4785.1776 | E10: =Inputs!$B$3*E8*DAY(EOMONTH(DATE(2026,E5+((E$3=0)*1),1),0)) -> 4837.1904 | F10: =Inputs!$B$3*F8*DAY(EOMONTH(DATE(2026,F5+((F$3=0)*1),1),0)) -> 4235.328 | G10: =Inputs!$B$3*G8*DAY(EOMONTH(DATE(2026,G5+((G$3=0)*1),1),0)) -> 3777.6154 | H10: =Inputs!$B$3*H8*DAY(EOMONTH(DATE(2026,H5+((H$3=0)*1),1),0)) -> 3343.68 | I10: =Inputs!$B$3*I8*DAY(EOMONTH(DATE(2026,I5+((I$3=0)*1),1),0)) -> 3685.4784 | ... DR10: =Inputs!$B$3*DR8*DAY(EOMONTH(DATE(2026,DR5+((DR$3=0)*1),1),0)) -> 7291.2
A11: Rooms revenue | B11: =B10*B9 -> 0 | C11: =C10*C9 -> 30839429 | D11: =D10*D9 -> 24311789 | E11: =E10*E9 -> 21626922 | F11: =F10*F9 -> 16353831 | G11: =G10*G9 -> 13051052 | H11: =H10*H9 -> 10872353 | I11: =I10*I9 -> 12283343 | ... DR11: =DR10*DR9 -> 69574165
A12: Other revenue | B12: =B11*Inputs!$B$7 -> 0 | C12: =C11*Inputs!$B$7 -> 16961686 | D12: =D11*Inputs!$B$7 -> 13371484 | E12: =E11*Inputs!$B$7 -> 11894807 | F12: =F11*Inputs!$B$7 -> 8994607.1 | G12: =G11*Inputs!$B$7 -> 7178078.5 | H12: =H11*Inputs!$B$7 -> 5979794.2 | I12: =I11*Inputs!$B$7 -> 6755838.6 | ... DR12: =DR11*Inputs!$B$7 -> 38265791
A13: Total revenue | B13: =B11+B12 -> 0 | C13: =C11+C12 -> 47801116 | D13: =D11+D12 -> 37683274 | E13: =E11+E12 -> 33521729 | F13: =F11+F12 -> 25348438 | G13: =G11+G12 -> 20229130 | H13: =H11+H12 -> 16852147 | I13: =I11+I12 -> 19039181 | ... DR13: =DR11+DR12 -> 1.0783996e+08
A14: Departmental costs | B14: =B11*Inputs!$B$8+B12*Inputs!$B$9 -> 0 | C14: =C11*Inputs!$B$8+C12*Inputs!$B$9 -> 18935410 | D14: =D11*Inputs!$B$8+D12*Inputs!$B$9 -> 14927439 | E14: =E11*Inputs!$B$8+E12*Inputs!$B$9 -> 13278930 | F14: =F11*Inputs!$B$8+F12*Inputs!$B$9 -> 10041252 | G14: =G11*Inputs!$B$8+G12*Inputs!$B$9 -> 8013345.8 | H14: =H11*Inputs!$B$8+H12*Inputs!$B$9 -> 6675624.8 | I14: =I11*Inputs!$B$8+I12*Inputs!$B$9 -> 7541972.5 | ... DR14: =DR11*Inputs!$B$8+DR12*Inputs!$B$9 -> 42718537
A15: Undistributed | B15: =B13*Inputs!$B$10 -> 0 | C15: =C13*Inputs!$B$10 -> 9082212 | D15: =D13*Inputs!$B$10 -> 7159822 | E15: =E13*Inputs!$B$10 -> 6369128.6 | F15: =F13*Inputs!$B$10 -> 4816203.2 | G15: =G13*Inputs!$B$10 -> 3843534.7 | H15: =H13*Inputs!$B$10 -> 3201908 | I15: =I13*Inputs!$B$10 -> 3617444.5 | ... DR15: =DR13*Inputs!$B$10 -> 20489592
A16: Fixed costs | B16: =IF((B$3>=1),Inputs!$B$11*(1+Inputs!$B$12)^(B4-1),0) -> 0 | C16: =IF((C$3>=1),Inputs!$B$11*(1+Inputs!$B$12)^(C4-1),0) -> 2600000 | D16: =IF((D$3>=1),Inputs!$B$11*(1+Inputs!$B$12)^(D4-1),0) -> 2600000 | E16: =IF((E$3>=1),Inputs!$B$11*(1+Inputs!$B$12)^(E4-1),0) -> 2600000 | F16: =IF((F$3>=1),Inputs!$B$11*(1+Inputs!$B$12)^(F4-1),0) -> 2600000 | G16: =IF((G$3>=1),Inputs!$B$11*(1+Inputs!$B$12)^(G4-1),0) -> 2600000 | H16: =IF((H$3>=1),Inputs!$B$11*(1+Inputs!$B$12)^(H4-1),0) -> 2600000 | I16: =IF((I$3>=1),Inputs!$B$11*(1+Inputs!$B$12)^(I4-1),0) -> 2600000 | ... DR16: =IF((DR$3>=1),Inputs!$B$11*(1+Inputs!$B$12)^(DR4-1),0) -> 4392645.3
A17: GOP | B17: =B13-B14-B15-B16 -> 0 | C17: =C13-C14-C15-C16 -> 17183494 | D17: =D13-D14-D15-D16 -> 12996013 | E17: =E13-E14-E15-E16 -> 11273671 | F17: =F13-F14-F15-F16 -> 7890982.6 | G17: =G13-G14-G15-G16 -> 5772249.7 | H17: =H13-H14-H15-H16 -> 4374614.5 | I17: =I13-I14-I15-I16 -> 5279764.4 | ... DR17: =DR13-DR14-DR15-DR16 -> 40239181
A18: Base fee | B18: =B13*Inputs!$B$13 -> 0 | C18: =C13*Inputs!$B$13 -> 1195027.9 | D18: =D13*Inputs!$B$13 -> 942081.84 | E18: =E13*Inputs!$B$13 -> 838043.24 | F18: =F13*Inputs!$B$13 -> 633710.95 | G18: =G13*Inputs!$B$13 -> 505728.26 | H18: =H13*Inputs!$B$13 -> 421303.68 | I18: =I13*Inputs!$B$13 -> 475979.54 | ... DR18: =DR13*Inputs!$B$13 -> 2695998.9
A19: FF&E reserve | B19: =B13*IF(B4<=1,0.02,IF(B4=2,0.03,0.04)) -> 0 | C19: =C13*IF(C4<=1,0.02,IF(C4=2,0.03,0.04)) -> 956022.31 | D19: =D13*IF(D4<=1,0.02,IF(D4=2,0.03,0.04)) -> 753665.47 | E19: =E13*IF(E4<=1,0.02,IF(E4=2,0.03,0.04)) -> 670434.59 | F19: =F13*IF(F4<=1,0.02,IF(F4=2,0.03,0.04)) -> 506968.76 | G19: =G13*IF(G4<=1,0.02,IF(G4=2,0.03,0.04)) -> 404582.61 | H19: =H13*IF(H4<=1,0.02,IF(H4=2,0.03,0.04)) -> 337042.94 | I19: =I13*IF(I4<=1,0.02,IF(I4=2,0.03,0.04)) -> 380783.63 | ... DR19: =DR13*IF(DR4<=1,0.02,IF(DR4=2,0.03,0.04)) -> 4313598.2
A20: NOI before incentive fee | B20: =B17-B18-B19 -> 0 | C20: =C17-C18-C19 -> 15032444 | D20: =D17-D18-D19 -> 11300266 | E20: =E17-E18-E19 -> 9765192.8 | F20: =F17-F18-F19 -> 6750302.9 | G20: =G17-G18-G19 -> 4861938.9 | H20: =H17-H18-H19 -> 3616267.8 | I20: =I17-I18-I19 -> 4423001.3 | ... DR20: =DR17-DR18-DR19 -> 33229584
A21: Owner priority | B21: =IF((B$3>=1),(Inputs!$B$20+Inputs!$B$19-Inputs!$B$21)*Inputs!$B$15/12,0) -> 0 | C21: =IF((C$3>=1),(Inputs!$B$20+Inputs!$B$19-Inputs!$B$21)*Inputs!$B$15/12,0) -> 12550000 | D21: =IF((D$3>=1),(Inputs!$B$20+Inputs!$B$19-Inputs!$B$21)*Inputs!$B$15/12,0) -> 12550000 | E21: =IF((E$3>=1),(Inputs!$B$20+Inputs!$B$19-Inputs!$B$21)*Inputs!$B$15/12,0) -> 12550000 | F21: =IF((F$3>=1),(Inputs!$B$20+Inputs!$B$19-Inputs!$B$21)*Inputs!$B$15/12,0) -> 12550000 | G21: =IF((G$3>=1),(Inputs!$B$20+Inputs!$B$19-Inputs!$B$21)*Inputs!$B$15/12,0) -> 12550000 | H21: =IF((H$3>=1),(Inputs!$B$20+Inputs!$B$19-Inputs!$B$21)*Inputs!$B$15/12,0) -> 12550000 | I21: =IF((I$3>=1),(Inputs!$B$20+Inputs!$B$19-Inputs!$B$21)*Inputs!$B$15/12,0) -> 12550000 | ... DR21: =IF((DR$3>=1),(Inputs!$B$20+Inputs!$B$19-Inputs!$B$21)*Inputs!$B$15/12,0) -> 12550000
A22: Incentive fee | B22: =MAX(0,B20-B21)*Inputs!$B$14 -> 0 | C22: =MAX(0,C20-C21)*Inputs!$B$14 -> 372366.56 | D22: =MAX(0,D20-D21)*Inputs!$B$14 -> 0 | E22: =MAX(0,E20-E21)*Inputs!$B$14 -> 0 | F22: =MAX(0,F20-F21)*Inputs!$B$14 -> 0 | G22: =MAX(0,G20-G21)*Inputs!$B$14 -> 0 | H22: =MAX(0,H20-H21)*Inputs!$B$14 -> 0 | I22: =MAX(0,I20-I21)*Inputs!$B$14 -> 0 | ... DR22: =MAX(0,DR20-DR21)*Inputs!$B$14 -> 3101937.6
A23: NOI | B23: =B20-B22 -> 0 | C23: =C20-C22 -> 14660077 | D23: =D20-D22 -> 11300266 | E23: =E20-E22 -> 9765192.8 | F23: =F20-F22 -> 6750302.9 | G23: =G20-G22 -> 4861938.9 | H23: =H20-H22 -> 3616267.8 | I23: =I20-I22 -> 4423001.3 | ... DR23: =DR20-DR22 -> 30127647
A24: PIP capex | B24: =IF(B7=1,Inputs!$B$19/Inputs!$B$17,0) -> 0 | C24: =IF(C7=1,Inputs!$B$19/Inputs!$B$17,0) -> 0 | D24: =IF(D7=1,Inputs!$B$19/Inputs!$B$17,0) -> 0 | E24: =IF(E7=1,Inputs!$B$19/Inputs!$B$17,0) -> 0 | F24: =IF(F7=1,Inputs!$B$19/Inputs!$B$17,0) -> 0 | G24: =IF(G7=1,Inputs!$B$19/Inputs!$B$17,0) -> 0 | H24: =IF(H7=1,Inputs!$B$19/Inputs!$B$17,0) -> 0 | I24: =IF(I7=1,Inputs!$B$19/Inputs!$B$17,0) -> 0 | ... DR24: =IF(DR7=1,Inputs!$B$19/Inputs!$B$17,0) -> 0
A25: Interest | B25: =IF((B$3>=1),Inputs!$B$20*Inputs!$B$22*Inputs!$B$23/12,0) -> 0 | C25: =IF((C$3>=1),Inputs!$B$20*Inputs!$B$22*Inputs!$B$23/12,0) -> 6343750 | D25: =IF((D$3>=1),Inputs!$B$20*Inputs!$B$22*Inputs!$B$23/12,0) -> 6343750 | E25: =IF((E$3>=1),Inputs!$B$20*Inputs!$B$22*Inputs!$B$23/12,0) -> 6343750 | F25: =IF((F$3>=1),Inputs!$B$20*Inputs!$B$22*Inputs!$B$23/12,0) -> 6343750 | G25: =IF((G$3>=1),Inputs!$B$20*Inputs!$B$22*Inputs!$B$23/12,0) -> 6343750 | H25: =IF((H$3>=1),Inputs!$B$20*Inputs!$B$22*Inputs!$B$23/12,0) -> 6343750 | I25: =IF((I$3>=1),Inputs!$B$20*Inputs!$B$22*Inputs!$B$23/12,0) -> 6343750 | ... DR25: =IF((DR$3>=1),Inputs!$B$20*Inputs!$B$22*Inputs!$B$23/12,0) -> 6343750
A26: Sale | B26: =0 -> 0 | C26: =0 -> 0 | D26: =0 -> 0 | E26: =0 -> 0 | F26: =0 -> 0 | G26: =0 -> 0 | H26: =0 -> 0 | I26: =0 -> 0 | ... L26: =0 -> 0 | M26: =IF(M$3=120,SUM(B23:M23)/Inputs!$B$24-Inputs!$B$20*Inputs!$B$22,0) -> 0 | N26: =IF(N$3=120,SUM(C23:N23)/Inputs!$B$24-Inputs!$B$20*Inputs!$B$22,0) -> 0 | O26: =IF(O$3=120,SUM(D23:O23)/Inputs!$B$24-Inputs!$B$20*Inputs!$B$22,0) -> 0 | P26: =IF(P$3=120,SUM(E23:P23)/Inputs!$B$24-Inputs!$B$20*Inputs!$B$22,0) -> 0 | Q26: =IF(Q$3=120,SUM(F23:Q23)/Inputs!$B$24-Inputs!$B$20*Inputs!$B$22,0) -> 0 | R26: =IF(R$3=120,SUM(G23:R23)/Inputs!$B$24-Inputs!$B$20*Inputs!$B$22,0) -> 0 | S26: =IF(S$3=120,SUM(H23:S23)/Inputs!$B$24-Inputs!$B$20*Inputs!$B$22,0) -> 0 | T26: =IF(T$3=120,SUM(I23:T23)/Inputs!$B$24-Inputs!$B$20*Inputs!$B$22,0) -> 0 | ... DR26: =IF(DR$3=120,SUM(DG23:DR23)/Inputs!$B$24-Inputs!$B$20*Inputs!$B$22,0) -> 1.1561537e+09
A27: Equity cash flow | B27: =-(Inputs!$B$20*(1-Inputs!$B$22)-Inputs!$B$21) -> -685000000 | C27: =C23-C24-C25+C26 -> 8316327.2 | D27: =D23-D24-D25+D26 -> 4956515.6 | E27: =E23-E24-E25+E26 -> 3421442.8 | F27: =F23-F24-F25+F26 -> 406552.89 | G27: =G23-G24-G25+G26 -> -1481811.1 | H27: =H23-H24-H25+H26 -> -2727482.2 | I27: =I23-I24-I25+I26 -> -1920748.7 | J27: =J23-J24-J25+J26 -> -1208813.4 | ... DR27: =DR23-DR24-DR25+DR26 -> 1.1799376e+09
A28: Unlevered cash flow | B28: =-(Inputs!$B$20-Inputs!$B$21) -> -1410000000 | C28: =C23-C24+IF(C$3=120,C26+Inputs!$B$20*Inputs!$B$22,0) -> 14660077 | D28: =D23-D24+IF(D$3=120,D26+Inputs!$B$20*Inputs!$B$22,0) -> 11300266 | E28: =E23-E24+IF(E$3=120,E26+Inputs!$B$20*Inputs!$B$22,0) -> 9765192.8 | F28: =F23-F24+IF(F$3=120,F26+Inputs!$B$20*Inputs!$B$22,0) -> 6750302.9 | G28: =G23-G24+IF(G$3=120,G26+Inputs!$B$20*Inputs!$B$22,0) -> 4861938.9 | H28: =H23-H24+IF(H$3=120,H26+Inputs!$B$20*Inputs!$B$22,0) -> 3616267.8 | I28: =I23-I24+IF(I$3=120,I26+Inputs!$B$20*Inputs!$B$22,0) -> 4423001.3 | J28: =J23-J24+IF(J$3=120,J26+Inputs!$B$20*Inputs!$B$22,0) -> 5134936.6 | ... DR28: =DR23-DR24+IF(DR$3=120,DR26+Inputs!$B$20*Inputs!$B$22,0) -> 1.9112814e+09

Sheet Returns
A3: Levered IRR | B3: =(1+IRR('Cash Flow'!B27:DR27,0.01))^12-1 -> 0.11195543
A4: Unlevered IRR | B4: =(1+IRR('Cash Flow'!B28:DR28,0.01))^12-1 -> 0.11117965
A5: Equity multiple | B5: =SUMIF('Cash Flow'!B27:DR27,">0")/-SUMIF('Cash Flow'!B27:DR27,"<0") -> 2.2860271
A6: NOI, year 3 (R) | B6: =SUMIF('Cash Flow'!B4:DR4,3,'Cash Flow'!B23:DR23) -> 1.2702842e+08
A7: Incentive fees paid (R) | B7: =SUM('Cash Flow'!B22:DR22) -> 44342646
A8: RevPAR, year 1 (R) | B8: =SUMIF('Cash Flow'!B4:DR4,1,'Cash Flow'!B11:DR11)/(Inputs!$B$3*365) -> 2691.1211
A9: Net profit (R) | B9: =SUM('Cash Flow'!B27:DR27) -> 1.0222562e+09
