Workbook

Sheet Inputs
A1: MAPLE GROVE SENIOR LIVING – CARE AND LABOUR MODEL (CAD)
A3: Development cost (C$) | B3: 165000000
A4: Loan to cost | B4: 0.7
A5: Interest rate | B5: 0.0525
A6: Amortisation (years) | B6: 35
A7: Lease-up (move-ins a month, all levels) | B7: 9
A8: Stabilised occupancy | B8: 0.93
A9: Fee growth a year | B9: 0.04
A10: Care wage (C$ an hour) | B10: 34
A11: Wage growth a year | B11: 0.05
A12: In-house care staff (FTE) | B12: 70
A13: Hours per FTE a year | B13: 1950
A14: Agency premium over wage | B14: 0.6
... A19: Hold (years) | B19: 10

Sheet Levels
A1: Level | B1: Units | C1: Monthly fee (C$) | D1: Care hours per resident day | E1: Share of move-ins
A2: Independent living | B2: 120 | C2: 4900 | D2: 0.4 | E2: 0.45
A3: Assisted living | B3: 80 | C3: 7600 | D3: 2.5 | E3: 0.4
A4: Memory care | B4: 40 | C4: 10400 | D4: 4.5 | E4: 0.15

Sheet Cash Flow
A3: Year | B3: 0 | C3: 1 | D3: 2 | E3: 3 | F3: 4 | G3: 5 | H3: 6 | I3: 7 | J3: 8 | K3: 9 | L3: 10
A4: IL occupied | B4: =IF(AND(B$3>=1,B$3<=Inputs!$B$19),MIN(Levels!$B$2*Inputs!$B$8,((B$3-0.5)*12*Inputs!$B$7)*Levels!$E$2),0) -> 0 | C4: =IF(AND(C$3>=1,C$3<=Inputs!$B$19),MIN(Levels!$B$2*Inputs!$B$8,((C$3-0.5)*12*Inputs!$B$7)*Levels!$E$2),0) -> 24.3 | D4: =IF(AND(D$3>=1,D$3<=Inputs!$B$19),MIN(Levels!$B$2*Inputs!$B$8,((D$3-0.5)*12*Inputs!$B$7)*Levels!$E$2),0) -> 72.9 | E4: =IF(AND(E$3>=1,E$3<=Inputs!$B$19),MIN(Levels!$B$2*Inputs!$B$8,((E$3-0.5)*12*Inputs!$B$7)*Levels!$E$2),0) -> 111.6 | F4: =IF(AND(F$3>=1,F$3<=Inputs!$B$19),MIN(Levels!$B$2*Inputs!$B$8,((F$3-0.5)*12*Inputs!$B$7)*Levels!$E$2),0) -> 111.6 | G4: =IF(AND(G$3>=1,G$3<=Inputs!$B$19),MIN(Levels!$B$2*Inputs!$B$8,((G$3-0.5)*12*Inputs!$B$7)*Levels!$E$2),0) -> 111.6 | H4: =IF(AND(H$3>=1,H$3<=Inputs!$B$19),MIN(Levels!$B$2*Inputs!$B$8,((H$3-0.5)*12*Inputs!$B$7)*Levels!$E$2),0) -> 111.6 | I4: =IF(AND(I$3>=1,I$3<=Inputs!$B$19),MIN(Levels!$B$2*Inputs!$B$8,((I$3-0.5)*12*Inputs!$B$7)*Levels!$E$2),0) -> 111.6 | ... L4: =IF(AND(L$3>=1,L$3<=Inputs!$B$19),MIN(Levels!$B$2*Inputs!$B$8,((L$3-0.5)*12*Inputs!$B$7)*Levels!$E$2),0) -> 111.6
A5: AL occupied | B5: =IF(AND(B$3>=1,B$3<=Inputs!$B$19),MIN(Levels!$B$3*Inputs!$B$8,((B$3-0.5)*12*Inputs!$B$7)*Levels!$E$3),0) -> 0 | C5: =IF(AND(C$3>=1,C$3<=Inputs!$B$19),MIN(Levels!$B$3*Inputs!$B$8,((C$3-0.5)*12*Inputs!$B$7)*Levels!$E$3),0) -> 21.6 | D5: =IF(AND(D$3>=1,D$3<=Inputs!$B$19),MIN(Levels!$B$3*Inputs!$B$8,((D$3-0.5)*12*Inputs!$B$7)*Levels!$E$3),0) -> 64.8 | E5: =IF(AND(E$3>=1,E$3<=Inputs!$B$19),MIN(Levels!$B$3*Inputs!$B$8,((E$3-0.5)*12*Inputs!$B$7)*Levels!$E$3),0) -> 74.4 | F5: =IF(AND(F$3>=1,F$3<=Inputs!$B$19),MIN(Levels!$B$3*Inputs!$B$8,((F$3-0.5)*12*Inputs!$B$7)*Levels!$E$3),0) -> 74.4 | G5: =IF(AND(G$3>=1,G$3<=Inputs!$B$19),MIN(Levels!$B$3*Inputs!$B$8,((G$3-0.5)*12*Inputs!$B$7)*Levels!$E$3),0) -> 74.4 | H5: =IF(AND(H$3>=1,H$3<=Inputs!$B$19),MIN(Levels!$B$3*Inputs!$B$8,((H$3-0.5)*12*Inputs!$B$7)*Levels!$E$3),0) -> 74.4 | I5: =IF(AND(I$3>=1,I$3<=Inputs!$B$19),MIN(Levels!$B$3*Inputs!$B$8,((I$3-0.5)*12*Inputs!$B$7)*Levels!$E$3),0) -> 74.4 | ... L5: =IF(AND(L$3>=1,L$3<=Inputs!$B$19),MIN(Levels!$B$3*Inputs!$B$8,((L$3-0.5)*12*Inputs!$B$7)*Levels!$E$3),0) -> 74.4
A6: MC occupied | B6: =IF(AND(B$3>=1,B$3<=Inputs!$B$19),MIN(Levels!$B$4*Inputs!$B$8,((B$3-0.5)*12*Inputs!$B$7)*Levels!$E$4),0) -> 0 | C6: =IF(AND(C$3>=1,C$3<=Inputs!$B$19),MIN(Levels!$B$4*Inputs!$B$8,((C$3-0.5)*12*Inputs!$B$7)*Levels!$E$4),0) -> 8.1 | D6: =IF(AND(D$3>=1,D$3<=Inputs!$B$19),MIN(Levels!$B$4*Inputs!$B$8,((D$3-0.5)*12*Inputs!$B$7)*Levels!$E$4),0) -> 24.3 | E6: =IF(AND(E$3>=1,E$3<=Inputs!$B$19),MIN(Levels!$B$4*Inputs!$B$8,((E$3-0.5)*12*Inputs!$B$7)*Levels!$E$4),0) -> 37.2 | F6: =IF(AND(F$3>=1,F$3<=Inputs!$B$19),MIN(Levels!$B$4*Inputs!$B$8,((F$3-0.5)*12*Inputs!$B$7)*Levels!$E$4),0) -> 37.2 | G6: =IF(AND(G$3>=1,G$3<=Inputs!$B$19),MIN(Levels!$B$4*Inputs!$B$8,((G$3-0.5)*12*Inputs!$B$7)*Levels!$E$4),0) -> 37.2 | H6: =IF(AND(H$3>=1,H$3<=Inputs!$B$19),MIN(Levels!$B$4*Inputs!$B$8,((H$3-0.5)*12*Inputs!$B$7)*Levels!$E$4),0) -> 37.2 | I6: =IF(AND(I$3>=1,I$3<=Inputs!$B$19),MIN(Levels!$B$4*Inputs!$B$8,((I$3-0.5)*12*Inputs!$B$7)*Levels!$E$4),0) -> 37.2 | ... L6: =IF(AND(L$3>=1,L$3<=Inputs!$B$19),MIN(Levels!$B$4*Inputs!$B$8,((L$3-0.5)*12*Inputs!$B$7)*Levels!$E$4),0) -> 37.2
A7: Revenue | B7: =12*(B4*Levels!$C$2+B5*Levels!$C$3+B6*Levels!$C$4)*(1+Inputs!$B$9)^MAX(0,B$3-1) -> 0 | C7: =12*(C4*Levels!$C$2+C5*Levels!$C$3+C6*Levels!$C$4)*(1+Inputs!$B$9)^MAX(0,C$3-1) -> 4409640 | D7: =12*(D4*Levels!$C$2+D5*Levels!$C$3+D6*Levels!$C$4)*(1+Inputs!$B$9)^MAX(0,D$3-1) -> 13758077 | E7: =12*(E4*Levels!$C$2+E5*Levels!$C$3+E6*Levels!$C$4)*(1+Inputs!$B$9)^MAX(0,E$3-1) -> 19457897 | F7: =12*(F4*Levels!$C$2+F5*Levels!$C$3+F6*Levels!$C$4)*(1+Inputs!$B$9)^MAX(0,F$3-1) -> 20236213 | G7: =12*(G4*Levels!$C$2+G5*Levels!$C$3+G6*Levels!$C$4)*(1+Inputs!$B$9)^MAX(0,G$3-1) -> 21045662 | H7: =12*(H4*Levels!$C$2+H5*Levels!$C$3+H6*Levels!$C$4)*(1+Inputs!$B$9)^MAX(0,H$3-1) -> 21887488 | I7: =12*(I4*Levels!$C$2+I5*Levels!$C$3+I6*Levels!$C$4)*(1+Inputs!$B$9)^MAX(0,I$3-1) -> 22762988 | ... L7: =12*(L4*Levels!$C$2+L5*Levels!$C$3+L6*Levels!$C$4)*(1+Inputs!$B$9)^MAX(0,L$3-1) -> 25605266
A8: Care hours needed | B8: =365*(B4*Levels!$D$2+B5*Levels!$D$3+B6*Levels!$D$4) -> 0 | C8: =365*(C4*Levels!$D$2+C5*Levels!$D$3+C6*Levels!$D$4) -> 36562.05 | D8: =365*(D4*Levels!$D$2+D5*Levels!$D$3+D6*Levels!$D$4) -> 109686.15 | E8: =365*(E4*Levels!$D$2+E5*Levels!$D$3+E6*Levels!$D$4) -> 145284.6 | F8: =365*(F4*Levels!$D$2+F5*Levels!$D$3+F6*Levels!$D$4) -> 145284.6 | G8: =365*(G4*Levels!$D$2+G5*Levels!$D$3+G6*Levels!$D$4) -> 145284.6 | H8: =365*(H4*Levels!$D$2+H5*Levels!$D$3+H6*Levels!$D$4) -> 145284.6 | I8: =365*(I4*Levels!$D$2+I5*Levels!$D$3+I6*Levels!$D$4) -> 145284.6 | ... L8: =365*(L4*Levels!$D$2+L5*Levels!$D$3+L6*Levels!$D$4) -> 145284.6
A9: In-house hours | B9: =MIN(B8,Inputs!$B$12*Inputs!$B$13) -> 0 | C9: =MIN(C8,Inputs!$B$12*Inputs!$B$13) -> 36562.05 | D9: =MIN(D8,Inputs!$B$12*Inputs!$B$13) -> 109686.15 | E9: =MIN(E8,Inputs!$B$12*Inputs!$B$13) -> 136500 | F9: =MIN(F8,Inputs!$B$12*Inputs!$B$13) -> 136500 | G9: =MIN(G8,Inputs!$B$12*Inputs!$B$13) -> 136500 | H9: =MIN(H8,Inputs!$B$12*Inputs!$B$13) -> 136500 | I9: =MIN(I8,Inputs!$B$12*Inputs!$B$13) -> 136500 | ... L9: =MIN(L8,Inputs!$B$12*Inputs!$B$13) -> 136500
A10: Agency hours | B10: =B8-B9 -> 0 | C10: =C8-C9 -> 0 | D10: =D8-D9 -> 0 | E10: =E8-E9 -> 8784.6 | F10: =F8-F9 -> 8784.6 | G10: =G8-G9 -> 8784.6 | H10: =H8-H9 -> 8784.6 | I10: =I8-I9 -> 8784.6 | ... L10: =L8-L9 -> 8784.6
A11: Care labour | B11: =(B9+B10*(1+Inputs!$B$14))*Inputs!$B$10*(1+Inputs!$B$11)^MAX(0,B$3-1) -> 0 | C11: =(C9+C10*(1+Inputs!$B$14))*Inputs!$B$10*(1+Inputs!$B$11)^MAX(0,C$3-1) -> 1243109.7 | D11: =(D9+D10*(1+Inputs!$B$14))*Inputs!$B$10*(1+Inputs!$B$11)^MAX(0,D$3-1) -> 3915795.6 | E11: =(E9+E10*(1+Inputs!$B$14))*Inputs!$B$10*(1+Inputs!$B$11)^MAX(0,E$3-1) -> 5643567.7 | F11: =(F9+F10*(1+Inputs!$B$14))*Inputs!$B$10*(1+Inputs!$B$11)^MAX(0,F$3-1) -> 5925746.1 | G11: =(G9+G10*(1+Inputs!$B$14))*Inputs!$B$10*(1+Inputs!$B$11)^MAX(0,G$3-1) -> 6222033.4 | H11: =(H9+H10*(1+Inputs!$B$14))*Inputs!$B$10*(1+Inputs!$B$11)^MAX(0,H$3-1) -> 6533135 | I11: =(I9+I10*(1+Inputs!$B$14))*Inputs!$B$10*(1+Inputs!$B$11)^MAX(0,I$3-1) -> 6859791.8 | ... L11: =(L9+L10*(1+Inputs!$B$14))*Inputs!$B$10*(1+Inputs!$B$11)^MAX(0,L$3-1) -> 7941066.5
A12: Other opex | B12: =12*Inputs!$B$15*(B4+B5+B6)*(1+0.03)^MAX(0,B$3-1) -> 0 | C12: =12*Inputs!$B$15*(C4+C5+C6)*(1+0.03)^MAX(0,C$3-1) -> 939600 | D12: =12*Inputs!$B$15*(D4+D5+D6)*(1+0.03)^MAX(0,D$3-1) -> 2903364 | E12: =12*Inputs!$B$15*(E4+E5+E6)*(1+0.03)^MAX(0,E$3-1) -> 4120196.1 | F12: =12*Inputs!$B$15*(F4+F5+F6)*(1+0.03)^MAX(0,F$3-1) -> 4243802 | G12: =12*Inputs!$B$15*(G4+G5+G6)*(1+0.03)^MAX(0,G$3-1) -> 4371116.1 | H12: =12*Inputs!$B$15*(H4+H5+H6)*(1+0.03)^MAX(0,H$3-1) -> 4502249.5 | I12: =12*Inputs!$B$15*(I4+I5+I6)*(1+0.03)^MAX(0,I$3-1) -> 4637317 | ... L12: =12*Inputs!$B$15*(L4+L5+L6)*(1+0.03)^MAX(0,L$3-1) -> 5067321.5
A13: Management fee | B13: =B7*Inputs!$B$16 -> 0 | C13: =C7*Inputs!$B$16 -> 220482 | D13: =D7*Inputs!$B$16 -> 687903.84 | E13: =E7*Inputs!$B$16 -> 972894.87 | F13: =F7*Inputs!$B$16 -> 1011810.7 | G13: =G7*Inputs!$B$16 -> 1052283.1 | H13: =H7*Inputs!$B$16 -> 1094374.4 | I13: =I7*Inputs!$B$16 -> 1138149.4 | ... L13: =L7*Inputs!$B$16 -> 1280263.3
A14: Capital reserve | B14: =IF(AND(B$3>=1,B$3<=Inputs!$B$19),Inputs!$B$17*SUM(Levels!$B$2:$B$4),0) -> 0 | C14: =IF(AND(C$3>=1,C$3<=Inputs!$B$19),Inputs!$B$17*SUM(Levels!$B$2:$B$4),0) -> 180000 | D14: =IF(AND(D$3>=1,D$3<=Inputs!$B$19),Inputs!$B$17*SUM(Levels!$B$2:$B$4),0) -> 180000 | E14: =IF(AND(E$3>=1,E$3<=Inputs!$B$19),Inputs!$B$17*SUM(Levels!$B$2:$B$4),0) -> 180000 | F14: =IF(AND(F$3>=1,F$3<=Inputs!$B$19),Inputs!$B$17*SUM(Levels!$B$2:$B$4),0) -> 180000 | G14: =IF(AND(G$3>=1,G$3<=Inputs!$B$19),Inputs!$B$17*SUM(Levels!$B$2:$B$4),0) -> 180000 | H14: =IF(AND(H$3>=1,H$3<=Inputs!$B$19),Inputs!$B$17*SUM(Levels!$B$2:$B$4),0) -> 180000 | I14: =IF(AND(I$3>=1,I$3<=Inputs!$B$19),Inputs!$B$17*SUM(Levels!$B$2:$B$4),0) -> 180000 | ... L14: =IF(AND(L$3>=1,L$3<=Inputs!$B$19),Inputs!$B$17*SUM(Levels!$B$2:$B$4),0) -> 180000
A15: NOI | B15: =B7-B11-B12-B13-B14 -> 0 | C15: =C7-C11-C12-C13-C14 -> 1826448.3 | D15: =D7-D11-D12-D13-D14 -> 6071013.4 | E15: =E7-E11-E12-E13-E14 -> 8541238.8 | F15: =F7-F11-F12-F13-F14 -> 8874854.7 | G15: =G7-G11-G12-G13-G14 -> 9220229.4 | H15: =H7-H11-H12-H13-H14 -> 9577729.4 | I15: =I7-I11-I12-I13-I14 -> 9947729.7 | ... L15: =L7-L11-L12-L13-L14 -> 11136614
A16: Loan balance | B16: =Inputs!$B$3*Inputs!$B$4 -> 115500000 | C16: =IF(C$3>=Inputs!$B$19,0,B16-C18) -> 1.1428598e+08 | D16: =IF(D$3>=Inputs!$B$19,0,C16-D18) -> 1.1300823e+08 | E16: =IF(E$3>=Inputs!$B$19,0,D16-E18) -> 1.116634e+08 | F16: =IF(F$3>=Inputs!$B$19,0,E16-F18) -> 1.1024796e+08 | G16: =IF(G$3>=Inputs!$B$19,0,F16-G18) -> 1.0875821e+08 | H16: =IF(H$3>=Inputs!$B$19,0,G16-H18) -> 1.0719025e+08 | I16: =IF(I$3>=Inputs!$B$19,0,H16-I18) -> 1.0553997e+08 | J16: =IF(J$3>=Inputs!$B$19,0,I16-J18) -> 1.0380306e+08 | ... L16: =IF(L$3>=Inputs!$B$19,0,K16-L18) -> 0
A17: Interest | B17: =0 -> 0 | C17: =IF(AND(C$3>=1,C$3<=Inputs!$B$19),B16*Inputs!$B$5,0) -> 6063750 | D17: =IF(AND(D$3>=1,D$3<=Inputs!$B$19),C16*Inputs!$B$5,0) -> 6000014.2 | E17: =IF(AND(E$3>=1,E$3<=Inputs!$B$19),D16*Inputs!$B$5,0) -> 5932932.2 | F17: =IF(AND(F$3>=1,F$3<=Inputs!$B$19),E16*Inputs!$B$5,0) -> 5862328.4 | G17: =IF(AND(G$3>=1,G$3<=Inputs!$B$19),F16*Inputs!$B$5,0) -> 5788017.9 | H17: =IF(AND(H$3>=1,H$3<=Inputs!$B$19),G16*Inputs!$B$5,0) -> 5709806.1 | I17: =IF(AND(I$3>=1,I$3<=Inputs!$B$19),H16*Inputs!$B$5,0) -> 5627488.3 | J17: =IF(AND(J$3>=1,J$3<=Inputs!$B$19),I16*Inputs!$B$5,0) -> 5540848.7 | ... L17: =IF(AND(L$3>=1,L$3<=Inputs!$B$19),K16*Inputs!$B$5,0) -> 5353685
A18: Principal | B18: =0 -> 0 | C18: =IF(AND(C$3>=1,C$3<=Inputs!$B$19),PMT(Inputs!$B$5,Inputs!$B$6,-Inputs!$B$3*Inputs!$B$4)-C17,0) -> 1214016.1 | D18: =IF(AND(D$3>=1,D$3<=Inputs!$B$19),PMT(Inputs!$B$5,Inputs!$B$6,-Inputs!$B$3*Inputs!$B$4)-D17,0) -> 1277751.9 | E18: =IF(AND(E$3>=1,E$3<=Inputs!$B$19),PMT(Inputs!$B$5,Inputs!$B$6,-Inputs!$B$3*Inputs!$B$4)-E17,0) -> 1344833.9 | F18: =IF(AND(F$3>=1,F$3<=Inputs!$B$19),PMT(Inputs!$B$5,Inputs!$B$6,-Inputs!$B$3*Inputs!$B$4)-F17,0) -> 1415437.7 | G18: =IF(AND(G$3>=1,G$3<=Inputs!$B$19),PMT(Inputs!$B$5,Inputs!$B$6,-Inputs!$B$3*Inputs!$B$4)-G17,0) -> 1489748.1 | H18: =IF(AND(H$3>=1,H$3<=Inputs!$B$19),PMT(Inputs!$B$5,Inputs!$B$6,-Inputs!$B$3*Inputs!$B$4)-H17,0) -> 1567959.9 | I18: =IF(AND(I$3>=1,I$3<=Inputs!$B$19),PMT(Inputs!$B$5,Inputs!$B$6,-Inputs!$B$3*Inputs!$B$4)-I17,0) -> 1650277.8 | J18: =IF(AND(J$3>=1,J$3<=Inputs!$B$19),PMT(Inputs!$B$5,Inputs!$B$6,-Inputs!$B$3*Inputs!$B$4)-J17,0) -> 1736917.4 | ... L18: =IF(AND(L$3>=1,L$3<=Inputs!$B$19),PMT(Inputs!$B$5,Inputs!$B$6,-Inputs!$B$3*Inputs!$B$4)-L17,0) -> 1924081.1
A19: Debt service | B19: =B17+B18 -> 0 | C19: =C17+C18 -> 7277766.1 | D19: =D17+D18 -> 7277766.1 | E19: =E17+E18 -> 7277766.1 | F19: =F17+F18 -> 7277766.1 | G19: =G17+G18 -> 7277766.1 | H19: =H17+H18 -> 7277766.1 | I19: =I17+I18 -> 7277766.1 | ... L19: =L17+L18 -> 7277766.1
A20: DSCR | B20: =IF(B19>0,B15/B19,99) -> 99 | C20: =IF(C19>0,C15/C19,99) -> 0.25096277 | D20: =IF(D19>0,D15/D19,99) -> 0.83418639 | E20: =IF(E19>0,E15/E19,99) -> 1.1736072 | F20: =IF(F19>0,F15/F19,99) -> 1.2194476 | G20: =IF(G19>0,G15/G19,99) -> 1.2669038 | H20: =IF(H19>0,H15/H19,99) -> 1.316026 | I20: =IF(I19>0,I15/I19,99) -> 1.3668658 | ... L20: =IF(L19>0,L15/L19,99) -> 1.5302243
A21: Sale | B21: =0 -> 0 | C21: =IF(C$3=Inputs!$B$19,C15*(1+Inputs!$B$9)/Inputs!$B$18-(B16-C18),0) -> 0 | D21: =IF(D$3=Inputs!$B$19,D15*(1+Inputs!$B$9)/Inputs!$B$18-(C16-D18),0) -> 0 | E21: =IF(E$3=Inputs!$B$19,E15*(1+Inputs!$B$9)/Inputs!$B$18-(D16-E18),0) -> 0 | F21: =IF(F$3=Inputs!$B$19,F15*(1+Inputs!$B$9)/Inputs!$B$18-(E16-F18),0) -> 0 | G21: =IF(G$3=Inputs!$B$19,G15*(1+Inputs!$B$9)/Inputs!$B$18-(F16-G18),0) -> 0 | H21: =IF(H$3=Inputs!$B$19,H15*(1+Inputs!$B$9)/Inputs!$B$18-(G16-H18),0) -> 0 | I21: =IF(I$3=Inputs!$B$19,I15*(1+Inputs!$B$9)/Inputs!$B$18-(H16-I18),0) -> 0 | J21: =IF(J$3=Inputs!$B$19,J15*(1+Inputs!$B$9)/Inputs!$B$18-(I16-J18),0) -> 0 | ... L21: =IF(L$3=Inputs!$B$19,L15*(1+Inputs!$B$9)/Inputs!$B$18-(K16-L18),0) -> 71535484
A22: Equity cash flow | B22: =-Inputs!$B$3*(1-Inputs!$B$4) -> -49500000 | C22: =C15-C19+C21 -> -5451317.8 | D22: =D15-D19+D21 -> -1206752.7 | E22: =E15-E19+E21 -> 1263472.8 | F22: =F15-F19+F21 -> 1597088.6 | G22: =G15-G19+G21 -> 1942463.3 | H22: =H15-H19+H21 -> 2299963.3 | I22: =I15-I19+I21 -> 2669963.7 | J22: =J15-J19+J21 -> 3052848.1 | ... L22: =L15-L19+L21 -> 75394333

Sheet Returns
A3: Levered IRR | B3: =IRR('Cash Flow'!B22:L22) -> 0.054711963
A4: Equity multiple | B4: =SUMIF('Cash Flow'!B22:L22,">0")/-SUMIF('Cash Flow'!B22:L22,"<0") -> 1.6323414
A5: Minimum DSCR from year 3 | B5: =MIN('Cash Flow'!E20:L20) -> 1.1736072
A6: Agency labour, year 5 (C$) | B6: ='Cash Flow'!G10*Inputs!$B$10*(1+Inputs!$B$14)*(1+Inputs!$B$11)^4 -> 580868.85
A7: NOI margin, year 5 | B7: ='Cash Flow'!G15/'Cash Flow'!G7 -> 0.43810594
A8: Net profit (C$) | B8: =SUM('Cash Flow'!B22:L22) -> 35511071
