Workbook

Sheet Inputs
A1: SEVEN HILLS – NEW CAIRO COMPOUND (EGP)
A3: First quarter end | B3: 46112
A4: Down payment | B4: 0.1
A5: Payment on delivery | B5: 0.05
A6: Instalment period (quarters) | B6: 28
A7: Price escalation a quarter | B7: 0.04
A8: Cost escalation a quarter | B8: 0.035
A9: Sales commission | B9: 0.03
A10: Land price (EGP) | B10: 2400000000
A11: Land down payment | B11: 0.2
A12: Land instalments (half-yearly) | B12: 8
A13: Discount rate | B13: 0.25
A14: Corporate tax | B14: 0.225

Sheet Products
A1: Product | B1: Units | C1: Size (sqm) | D1: Price at launch (EGP/sqm) | E1: Launch quarter | F1: Sales a quarter (units) | G1: Construction start quarter | H1: Build (quarters) | I1: Build cost (EGP/sqm)
A2: Villas | B2: 180 | C2: 320 | D2: 62000 | E2: 1 | F2: 9 | G2: 2 | H2: 10 | I2: 21000
A3: Townhouses | B3: 260 | C3: 230 | D3: 55000 | E3: 2 | F3: 14 | G3: 3 | H3: 9 | I3: 19000
A4: Apartments | B4: 900 | C4: 140 | D4: 48000 | E4: 1 | F4: 45 | G4: 2 | H4: 12 | I4: 17000
A5: Retail | B5: 60 | C5: 180 | D5: 70000 | E5: 6 | F5: 4 | G5: 8 | H5: 8 | I5: 20000

Sheet Cash Flow
A3: Quarter | B3: 0 | C3: 1 | D3: 2 | E3: 3 | F3: 4 | G3: 5 | H3: 6 | I3: 7 | J3: 8 | K3: 9 | L3: 10 | M3: 11 | N3: 12 | O3: 13 | P3: 14 | Q3: 15 | R3: 16 | S3: 17 | T3: 18 | U3: 19 | V3: 20 | W3: 21 | X3: 22 | Y3: 23 | Z3: 24 | AA3: 25 | AB3: 26 | AC3: 27 | AD3: 28 | AE3: 29 | AF3: 30 | AG3: 31 | AH3: 32 | AI3: 33 | AJ3: 34 | AK3: 35 | AL3: 36 | AM3: 37 | AN3: 38 | AO3: 39 | AP3: 40
A4: Date | B4: =EOMONTH(Inputs!$B$3,3*B$3) -> 46112 | C4: =EOMONTH(Inputs!$B$3,3*C$3) -> 46203 | D4: =EOMONTH(Inputs!$B$3,3*D$3) -> 46295 | E4: =EOMONTH(Inputs!$B$3,3*E$3) -> 46387 | F4: =EOMONTH(Inputs!$B$3,3*F$3) -> 46477 | G4: =EOMONTH(Inputs!$B$3,3*G$3) -> 46568 | H4: =EOMONTH(Inputs!$B$3,3*H$3) -> 46660 | I4: =EOMONTH(Inputs!$B$3,3*I$3) -> 46752 | ... AP4: =EOMONTH(Inputs!$B$3,3*AP$3) -> 49765
A5: Villas · units sold | B5: =IF(B$3>=Products!$E$2,MIN(Products!$F$2,Products!$B$2-0),0) -> 0 | C5: =IF(C$3>=Products!$E$2,MIN(Products!$F$2,Products!$B$2-B6),0) -> 9 | D5: =IF(D$3>=Products!$E$2,MIN(Products!$F$2,Products!$B$2-C6),0) -> 9 | E5: =IF(E$3>=Products!$E$2,MIN(Products!$F$2,Products!$B$2-D6),0) -> 9 | F5: =IF(F$3>=Products!$E$2,MIN(Products!$F$2,Products!$B$2-E6),0) -> 9 | G5: =IF(G$3>=Products!$E$2,MIN(Products!$F$2,Products!$B$2-F6),0) -> 9 | H5: =IF(H$3>=Products!$E$2,MIN(Products!$F$2,Products!$B$2-G6),0) -> 9 | I5: =IF(I$3>=Products!$E$2,MIN(Products!$F$2,Products!$B$2-H6),0) -> 9 | J5: =IF(J$3>=Products!$E$2,MIN(Products!$F$2,Products!$B$2-I6),0) -> 9 | ... AP5: =IF(AP$3>=Products!$E$2,MIN(Products!$F$2,Products!$B$2-AO6),0) -> 0
A6: Villas · cumulative units | B6: =B5 -> 0 | C6: =B6+C5 -> 9 | D6: =C6+D5 -> 18 | E6: =D6+E5 -> 27 | F6: =E6+F5 -> 36 | G6: =F6+G5 -> 45 | H6: =G6+H5 -> 54 | I6: =H6+I5 -> 63 | J6: =I6+J5 -> 72 | ... AP6: =AO6+AP5 -> 180
A7: Villas · sales value | B7: =B5*Products!$C$2*Products!$D$2*(1+Inputs!$B$7)^MAX(0,B$3-Products!$E$2) -> 0 | C7: =C5*Products!$C$2*Products!$D$2*(1+Inputs!$B$7)^MAX(0,C$3-Products!$E$2) -> 178560000 | D7: =D5*Products!$C$2*Products!$D$2*(1+Inputs!$B$7)^MAX(0,D$3-Products!$E$2) -> 185702400 | E7: =E5*Products!$C$2*Products!$D$2*(1+Inputs!$B$7)^MAX(0,E$3-Products!$E$2) -> 193130496 | F7: =F5*Products!$C$2*Products!$D$2*(1+Inputs!$B$7)^MAX(0,F$3-Products!$E$2) -> 2.0085572e+08 | G7: =G5*Products!$C$2*Products!$D$2*(1+Inputs!$B$7)^MAX(0,G$3-Products!$E$2) -> 2.0888994e+08 | H7: =H5*Products!$C$2*Products!$D$2*(1+Inputs!$B$7)^MAX(0,H$3-Products!$E$2) -> 2.1724554e+08 | I7: =I5*Products!$C$2*Products!$D$2*(1+Inputs!$B$7)^MAX(0,I$3-Products!$E$2) -> 2.2593536e+08 | ... AP7: =AP5*Products!$C$2*Products!$D$2*(1+Inputs!$B$7)^MAX(0,AP$3-Products!$E$2) -> 0
A8: Villas · instalments | B8: =(1-Inputs!$B$4-Inputs!$B$5)/Inputs!$B$6*SUMIFS($B$7:$AP$7,$B$3:$AP$3,">="&(B$3-Inputs!$B$6),$B$3:$AP$3,"<="&(B$3-1)) -> 0 | C8: =(1-Inputs!$B$4-Inputs!$B$5)/Inputs!$B$6*SUMIFS($B$7:$AP$7,$B$3:$AP$3,">="&(C$3-Inputs!$B$6),$B$3:$AP$3,"<="&(C$3-1)) -> 0 | D8: =(1-Inputs!$B$4-Inputs!$B$5)/Inputs!$B$6*SUMIFS($B$7:$AP$7,$B$3:$AP$3,">="&(D$3-Inputs!$B$6),$B$3:$AP$3,"<="&(D$3-1)) -> 5420571.4 | E8: =(1-Inputs!$B$4-Inputs!$B$5)/Inputs!$B$6*SUMIFS($B$7:$AP$7,$B$3:$AP$3,">="&(E$3-Inputs!$B$6),$B$3:$AP$3,"<="&(E$3-1)) -> 11057966 | F8: =(1-Inputs!$B$4-Inputs!$B$5)/Inputs!$B$6*SUMIFS($B$7:$AP$7,$B$3:$AP$3,">="&(F$3-Inputs!$B$6),$B$3:$AP$3,"<="&(F$3-1)) -> 16920856 | G8: =(1-Inputs!$B$4-Inputs!$B$5)/Inputs!$B$6*SUMIFS($B$7:$AP$7,$B$3:$AP$3,">="&(G$3-Inputs!$B$6),$B$3:$AP$3,"<="&(G$3-1)) -> 23018261 | H8: =(1-Inputs!$B$4-Inputs!$B$5)/Inputs!$B$6*SUMIFS($B$7:$AP$7,$B$3:$AP$3,">="&(H$3-Inputs!$B$6),$B$3:$AP$3,"<="&(H$3-1)) -> 29359563 | I8: =(1-Inputs!$B$4-Inputs!$B$5)/Inputs!$B$6*SUMIFS($B$7:$AP$7,$B$3:$AP$3,">="&(I$3-Inputs!$B$6),$B$3:$AP$3,"<="&(I$3-1)) -> 35954517 | ... AP8: =(1-Inputs!$B$4-Inputs!$B$5)/Inputs!$B$6*SUMIFS($B$7:$AP$7,$B$3:$AP$3,">="&(AP$3-Inputs!$B$6),$B$3:$AP$3,"<="&(AP$3-1)) -> 88310471
A9: Villas · delivery | B9: =Inputs!$B$5*(IF(B$3=(Products!$G$2+Products!$H$2),SUMIFS($B$7:$AP$7,$B$3:$AP$3,"<="&(Products!$G$2+Products!$H$2)),0)+IF(B$3>(Products!$G$2+Products!$H$2),B7,0)) -> 0 | C9: =Inputs!$B$5*(IF(C$3=(Products!$G$2+Products!$H$2),SUMIFS($B$7:$AP$7,$B$3:$AP$3,"<="&(Products!$G$2+Products!$H$2)),0)+IF(C$3>(Products!$G$2+Products!$H$2),C7,0)) -> 0 | D9: =Inputs!$B$5*(IF(D$3=(Products!$G$2+Products!$H$2),SUMIFS($B$7:$AP$7,$B$3:$AP$3,"<="&(Products!$G$2+Products!$H$2)),0)+IF(D$3>(Products!$G$2+Products!$H$2),D7,0)) -> 0 | E9: =Inputs!$B$5*(IF(E$3=(Products!$G$2+Products!$H$2),SUMIFS($B$7:$AP$7,$B$3:$AP$3,"<="&(Products!$G$2+Products!$H$2)),0)+IF(E$3>(Products!$G$2+Products!$H$2),E7,0)) -> 0 | F9: =Inputs!$B$5*(IF(F$3=(Products!$G$2+Products!$H$2),SUMIFS($B$7:$AP$7,$B$3:$AP$3,"<="&(Products!$G$2+Products!$H$2)),0)+IF(F$3>(Products!$G$2+Products!$H$2),F7,0)) -> 0 | G9: =Inputs!$B$5*(IF(G$3=(Products!$G$2+Products!$H$2),SUMIFS($B$7:$AP$7,$B$3:$AP$3,"<="&(Products!$G$2+Products!$H$2)),0)+IF(G$3>(Products!$G$2+Products!$H$2),G7,0)) -> 0 | H9: =Inputs!$B$5*(IF(H$3=(Products!$G$2+Products!$H$2),SUMIFS($B$7:$AP$7,$B$3:$AP$3,"<="&(Products!$G$2+Products!$H$2)),0)+IF(H$3>(Products!$G$2+Products!$H$2),H7,0)) -> 0 | I9: =Inputs!$B$5*(IF(I$3=(Products!$G$2+Products!$H$2),SUMIFS($B$7:$AP$7,$B$3:$AP$3,"<="&(Products!$G$2+Products!$H$2)),0)+IF(I$3>(Products!$G$2+Products!$H$2),I7,0)) -> 0 | ... AP9: =Inputs!$B$5*(IF(AP$3=(Products!$G$2+Products!$H$2),SUMIFS($B$7:$AP$7,$B$3:$AP$3,"<="&(Products!$G$2+Products!$H$2)),0)+IF(AP$3>(Products!$G$2+Products!$H$2),AP7,0)) -> 0
A10: Villas · collections | B10: =Inputs!$B$4*B7+B8+B9 -> 0 | C10: =Inputs!$B$4*C7+C8+C9 -> 17856000 | D10: =Inputs!$B$4*D7+D8+D9 -> 23990811 | E10: =Inputs!$B$4*E7+E8+E9 -> 30371015 | F10: =Inputs!$B$4*F7+F8+F9 -> 37006427 | G10: =Inputs!$B$4*G7+G8+G9 -> 43907256 | H10: =Inputs!$B$4*H7+H8+H9 -> 51084118 | I10: =Inputs!$B$4*I7+I8+I9 -> 58548054 | ... AP10: =Inputs!$B$4*AP7+AP8+AP9 -> 88310471
A11: Villas · build cost | B11: =IF(AND(B$3>=Products!$G$2,B$3<(Products!$G$2+Products!$H$2)),Products!$B$2*Products!$C$2*Products!$I$2*(1+Inputs!$B$8)^B$3/Products!$H$2,0) -> 0 | C11: =IF(AND(C$3>=Products!$G$2,C$3<(Products!$G$2+Products!$H$2)),Products!$B$2*Products!$C$2*Products!$I$2*(1+Inputs!$B$8)^C$3/Products!$H$2,0) -> 0 | D11: =IF(AND(D$3>=Products!$G$2,D$3<(Products!$G$2+Products!$H$2)),Products!$B$2*Products!$C$2*Products!$I$2*(1+Inputs!$B$8)^D$3/Products!$H$2,0) -> 129575376 | E11: =IF(AND(E$3>=Products!$G$2,E$3<(Products!$G$2+Products!$H$2)),Products!$B$2*Products!$C$2*Products!$I$2*(1+Inputs!$B$8)^E$3/Products!$H$2,0) -> 1.3411051e+08 | F11: =IF(AND(F$3>=Products!$G$2,F$3<(Products!$G$2+Products!$H$2)),Products!$B$2*Products!$C$2*Products!$I$2*(1+Inputs!$B$8)^F$3/Products!$H$2,0) -> 1.3880438e+08 | G11: =IF(AND(G$3>=Products!$G$2,G$3<(Products!$G$2+Products!$H$2)),Products!$B$2*Products!$C$2*Products!$I$2*(1+Inputs!$B$8)^G$3/Products!$H$2,0) -> 1.4366254e+08 | H11: =IF(AND(H$3>=Products!$G$2,H$3<(Products!$G$2+Products!$H$2)),Products!$B$2*Products!$C$2*Products!$I$2*(1+Inputs!$B$8)^H$3/Products!$H$2,0) -> 1.4869072e+08 | I11: =IF(AND(I$3>=Products!$G$2,I$3<(Products!$G$2+Products!$H$2)),Products!$B$2*Products!$C$2*Products!$I$2*(1+Inputs!$B$8)^I$3/Products!$H$2,0) -> 1.538949e+08 | ... AP11: =IF(AND(AP$3>=Products!$G$2,AP$3<(Products!$G$2+Products!$H$2)),Products!$B$2*Products!$C$2*Products!$I$2*(1+Inputs!$B$8)^AP$3/Products!$H$2,0) -> 0
A12: Townhouses · units sold | B12: =IF(B$3>=Products!$E$3,MIN(Products!$F$3,Products!$B$3-0),0) -> 0 | C12: =IF(C$3>=Products!$E$3,MIN(Products!$F$3,Products!$B$3-B13),0) -> 0 | D12: =IF(D$3>=Products!$E$3,MIN(Products!$F$3,Products!$B$3-C13),0) -> 14 | E12: =IF(E$3>=Products!$E$3,MIN(Products!$F$3,Products!$B$3-D13),0) -> 14 | F12: =IF(F$3>=Products!$E$3,MIN(Products!$F$3,Products!$B$3-E13),0) -> 14 | G12: =IF(G$3>=Products!$E$3,MIN(Products!$F$3,Products!$B$3-F13),0) -> 14 | H12: =IF(H$3>=Products!$E$3,MIN(Products!$F$3,Products!$B$3-G13),0) -> 14 | I12: =IF(I$3>=Products!$E$3,MIN(Products!$F$3,Products!$B$3-H13),0) -> 14 | J12: =IF(J$3>=Products!$E$3,MIN(Products!$F$3,Products!$B$3-I13),0) -> 14 | ... AP12: =IF(AP$3>=Products!$E$3,MIN(Products!$F$3,Products!$B$3-AO13),0) -> 0
A13: Townhouses · cumulative units | B13: =B12 -> 0 | C13: =B13+C12 -> 0 | D13: =C13+D12 -> 14 | E13: =D13+E12 -> 28 | F13: =E13+F12 -> 42 | G13: =F13+G12 -> 56 | H13: =G13+H12 -> 70 | I13: =H13+I12 -> 84 | J13: =I13+J12 -> 98 | ... AP13: =AO13+AP12 -> 260
A14: Townhouses · sales value | B14: =B12*Products!$C$3*Products!$D$3*(1+Inputs!$B$7)^MAX(0,B$3-Products!$E$3) -> 0 | C14: =C12*Products!$C$3*Products!$D$3*(1+Inputs!$B$7)^MAX(0,C$3-Products!$E$3) -> 0 | D14: =D12*Products!$C$3*Products!$D$3*(1+Inputs!$B$7)^MAX(0,D$3-Products!$E$3) -> 177100000 | E14: =E12*Products!$C$3*Products!$D$3*(1+Inputs!$B$7)^MAX(0,E$3-Products!$E$3) -> 184184000 | F14: =F12*Products!$C$3*Products!$D$3*(1+Inputs!$B$7)^MAX(0,F$3-Products!$E$3) -> 191551360 | G14: =G12*Products!$C$3*Products!$D$3*(1+Inputs!$B$7)^MAX(0,G$3-Products!$E$3) -> 1.9921341e+08 | H14: =H12*Products!$C$3*Products!$D$3*(1+Inputs!$B$7)^MAX(0,H$3-Products!$E$3) -> 2.0718195e+08 | I14: =I12*Products!$C$3*Products!$D$3*(1+Inputs!$B$7)^MAX(0,I$3-Products!$E$3) -> 2.1546923e+08 | ... AP14: =AP12*Products!$C$3*Products!$D$3*(1+Inputs!$B$7)^MAX(0,AP$3-Products!$E$3) -> 0
A15: Townhouses · instalments | B15: =(1-Inputs!$B$4-Inputs!$B$5)/Inputs!$B$6*SUMIFS($B$14:$AP$14,$B$3:$AP$3,">="&(B$3-Inputs!$B$6),$B$3:$AP$3,"<="&(B$3-1)) -> 0 | C15: =(1-Inputs!$B$4-Inputs!$B$5)/Inputs!$B$6*SUMIFS($B$14:$AP$14,$B$3:$AP$3,">="&(C$3-Inputs!$B$6),$B$3:$AP$3,"<="&(C$3-1)) -> 0 | D15: =(1-Inputs!$B$4-Inputs!$B$5)/Inputs!$B$6*SUMIFS($B$14:$AP$14,$B$3:$AP$3,">="&(D$3-Inputs!$B$6),$B$3:$AP$3,"<="&(D$3-1)) -> 0 | E15: =(1-Inputs!$B$4-Inputs!$B$5)/Inputs!$B$6*SUMIFS($B$14:$AP$14,$B$3:$AP$3,">="&(E$3-Inputs!$B$6),$B$3:$AP$3,"<="&(E$3-1)) -> 5376250 | F15: =(1-Inputs!$B$4-Inputs!$B$5)/Inputs!$B$6*SUMIFS($B$14:$AP$14,$B$3:$AP$3,">="&(F$3-Inputs!$B$6),$B$3:$AP$3,"<="&(F$3-1)) -> 10967550 | G15: =(1-Inputs!$B$4-Inputs!$B$5)/Inputs!$B$6*SUMIFS($B$14:$AP$14,$B$3:$AP$3,">="&(G$3-Inputs!$B$6),$B$3:$AP$3,"<="&(G$3-1)) -> 16782502 | H15: =(1-Inputs!$B$4-Inputs!$B$5)/Inputs!$B$6*SUMIFS($B$14:$AP$14,$B$3:$AP$3,">="&(H$3-Inputs!$B$6),$B$3:$AP$3,"<="&(H$3-1)) -> 22830052 | I15: =(1-Inputs!$B$4-Inputs!$B$5)/Inputs!$B$6*SUMIFS($B$14:$AP$14,$B$3:$AP$3,">="&(I$3-Inputs!$B$6),$B$3:$AP$3,"<="&(I$3-1)) -> 29119504 | ... AP15: =(1-Inputs!$B$4-Inputs!$B$5)/Inputs!$B$6*SUMIFS($B$14:$AP$14,$B$3:$AP$3,">="&(AP$3-Inputs!$B$6),$B$3:$AP$3,"<="&(AP$3-1)) -> 79551915
A16: Townhouses · delivery | B16: =Inputs!$B$5*(IF(B$3=(Products!$G$3+Products!$H$3),SUMIFS($B$14:$AP$14,$B$3:$AP$3,"<="&(Products!$G$3+Products!$H$3)),0)+IF(B$3>(Products!$G$3+Products!$H$3),B14,0)) -> 0 | C16: =Inputs!$B$5*(IF(C$3=(Products!$G$3+Products!$H$3),SUMIFS($B$14:$AP$14,$B$3:$AP$3,"<="&(Products!$G$3+Products!$H$3)),0)+IF(C$3>(Products!$G$3+Products!$H$3),C14,0)) -> 0 | D16: =Inputs!$B$5*(IF(D$3=(Products!$G$3+Products!$H$3),SUMIFS($B$14:$AP$14,$B$3:$AP$3,"<="&(Products!$G$3+Products!$H$3)),0)+IF(D$3>(Products!$G$3+Products!$H$3),D14,0)) -> 0 | E16: =Inputs!$B$5*(IF(E$3=(Products!$G$3+Products!$H$3),SUMIFS($B$14:$AP$14,$B$3:$AP$3,"<="&(Products!$G$3+Products!$H$3)),0)+IF(E$3>(Products!$G$3+Products!$H$3),E14,0)) -> 0 | F16: =Inputs!$B$5*(IF(F$3=(Products!$G$3+Products!$H$3),SUMIFS($B$14:$AP$14,$B$3:$AP$3,"<="&(Products!$G$3+Products!$H$3)),0)+IF(F$3>(Products!$G$3+Products!$H$3),F14,0)) -> 0 | G16: =Inputs!$B$5*(IF(G$3=(Products!$G$3+Products!$H$3),SUMIFS($B$14:$AP$14,$B$3:$AP$3,"<="&(Products!$G$3+Products!$H$3)),0)+IF(G$3>(Products!$G$3+Products!$H$3),G14,0)) -> 0 | H16: =Inputs!$B$5*(IF(H$3=(Products!$G$3+Products!$H$3),SUMIFS($B$14:$AP$14,$B$3:$AP$3,"<="&(Products!$G$3+Products!$H$3)),0)+IF(H$3>(Products!$G$3+Products!$H$3),H14,0)) -> 0 | I16: =Inputs!$B$5*(IF(I$3=(Products!$G$3+Products!$H$3),SUMIFS($B$14:$AP$14,$B$3:$AP$3,"<="&(Products!$G$3+Products!$H$3)),0)+IF(I$3>(Products!$G$3+Products!$H$3),I14,0)) -> 0 | ... AP16: =Inputs!$B$5*(IF(AP$3=(Products!$G$3+Products!$H$3),SUMIFS($B$14:$AP$14,$B$3:$AP$3,"<="&(Products!$G$3+Products!$H$3)),0)+IF(AP$3>(Products!$G$3+Products!$H$3),AP14,0)) -> 0
A17: Townhouses · collections | B17: =Inputs!$B$4*B14+B15+B16 -> 0 | C17: =Inputs!$B$4*C14+C15+C16 -> 0 | D17: =Inputs!$B$4*D14+D15+D16 -> 17710000 | E17: =Inputs!$B$4*E14+E15+E16 -> 23794650 | F17: =Inputs!$B$4*F14+F15+F16 -> 30122686 | G17: =Inputs!$B$4*G14+G15+G16 -> 36703843 | H17: =Inputs!$B$4*H14+H15+H16 -> 43548247 | I17: =Inputs!$B$4*I14+I15+I16 -> 50666427 | ... AP17: =Inputs!$B$4*AP14+AP15+AP16 -> 79551915
A18: Townhouses · build cost | B18: =IF(AND(B$3>=Products!$G$3,B$3<(Products!$G$3+Products!$H$3)),Products!$B$3*Products!$C$3*Products!$I$3*(1+Inputs!$B$8)^B$3/Products!$H$3,0) -> 0 | C18: =IF(AND(C$3>=Products!$G$3,C$3<(Products!$G$3+Products!$H$3)),Products!$B$3*Products!$C$3*Products!$I$3*(1+Inputs!$B$8)^C$3/Products!$H$3,0) -> 0 | D18: =IF(AND(D$3>=Products!$G$3,D$3<(Products!$G$3+Products!$H$3)),Products!$B$3*Products!$C$3*Products!$I$3*(1+Inputs!$B$8)^D$3/Products!$H$3,0) -> 0 | E18: =IF(AND(E$3>=Products!$G$3,E$3<(Products!$G$3+Products!$H$3)),Products!$B$3*Products!$C$3*Products!$I$3*(1+Inputs!$B$8)^E$3/Products!$H$3,0) -> 1.3996947e+08 | F18: =IF(AND(F$3>=Products!$G$3,F$3<(Products!$G$3+Products!$H$3)),Products!$B$3*Products!$C$3*Products!$I$3*(1+Inputs!$B$8)^F$3/Products!$H$3,0) -> 1.448684e+08 | G18: =IF(AND(G$3>=Products!$G$3,G$3<(Products!$G$3+Products!$H$3)),Products!$B$3*Products!$C$3*Products!$I$3*(1+Inputs!$B$8)^G$3/Products!$H$3,0) -> 1.499388e+08 | H18: =IF(AND(H$3>=Products!$G$3,H$3<(Products!$G$3+Products!$H$3)),Products!$B$3*Products!$C$3*Products!$I$3*(1+Inputs!$B$8)^H$3/Products!$H$3,0) -> 1.5518666e+08 | I18: =IF(AND(I$3>=Products!$G$3,I$3<(Products!$G$3+Products!$H$3)),Products!$B$3*Products!$C$3*Products!$I$3*(1+Inputs!$B$8)^I$3/Products!$H$3,0) -> 1.6061819e+08 | ... AP18: =IF(AND(AP$3>=Products!$G$3,AP$3<(Products!$G$3+Products!$H$3)),Products!$B$3*Products!$C$3*Products!$I$3*(1+Inputs!$B$8)^AP$3/Products!$H$3,0) -> 0
A19: Apartments · units sold | B19: =IF(B$3>=Products!$E$4,MIN(Products!$F$4,Products!$B$4-0),0) -> 0 | C19: =IF(C$3>=Products!$E$4,MIN(Products!$F$4,Products!$B$4-B20),0) -> 45 | D19: =IF(D$3>=Products!$E$4,MIN(Products!$F$4,Products!$B$4-C20),0) -> 45 | E19: =IF(E$3>=Products!$E$4,MIN(Products!$F$4,Products!$B$4-D20),0) -> 45 | F19: =IF(F$3>=Products!$E$4,MIN(Products!$F$4,Products!$B$4-E20),0) -> 45 | G19: =IF(G$3>=Products!$E$4,MIN(Products!$F$4,Products!$B$4-F20),0) -> 45 | H19: =IF(H$3>=Products!$E$4,MIN(Products!$F$4,Products!$B$4-G20),0) -> 45 | I19: =IF(I$3>=Products!$E$4,MIN(Products!$F$4,Products!$B$4-H20),0) -> 45 | J19: =IF(J$3>=Products!$E$4,MIN(Products!$F$4,Products!$B$4-I20),0) -> 45 | ... AP19: =IF(AP$3>=Products!$E$4,MIN(Products!$F$4,Products!$B$4-AO20),0) -> 0
A20: Apartments · cumulative units | B20: =B19 -> 0 | C20: =B20+C19 -> 45 | D20: =C20+D19 -> 90 | E20: =D20+E19 -> 135 | F20: =E20+F19 -> 180 | G20: =F20+G19 -> 225 | H20: =G20+H19 -> 270 | I20: =H20+I19 -> 315 | J20: =I20+J19 -> 360 | ... AP20: =AO20+AP19 -> 900
A21: Apartments · sales value | B21: =B19*Products!$C$4*Products!$D$4*(1+Inputs!$B$7)^MAX(0,B$3-Products!$E$4) -> 0 | C21: =C19*Products!$C$4*Products!$D$4*(1+Inputs!$B$7)^MAX(0,C$3-Products!$E$4) -> 302400000 | D21: =D19*Products!$C$4*Products!$D$4*(1+Inputs!$B$7)^MAX(0,D$3-Products!$E$4) -> 314496000 | E21: =E19*Products!$C$4*Products!$D$4*(1+Inputs!$B$7)^MAX(0,E$3-Products!$E$4) -> 327075840 | F21: =F19*Products!$C$4*Products!$D$4*(1+Inputs!$B$7)^MAX(0,F$3-Products!$E$4) -> 3.4015887e+08 | G21: =G19*Products!$C$4*Products!$D$4*(1+Inputs!$B$7)^MAX(0,G$3-Products!$E$4) -> 3.5376523e+08 | H21: =H19*Products!$C$4*Products!$D$4*(1+Inputs!$B$7)^MAX(0,H$3-Products!$E$4) -> 3.6791584e+08 | I21: =I19*Products!$C$4*Products!$D$4*(1+Inputs!$B$7)^MAX(0,I$3-Products!$E$4) -> 3.8263247e+08 | ... AP21: =AP19*Products!$C$4*Products!$D$4*(1+Inputs!$B$7)^MAX(0,AP$3-Products!$E$4) -> 0
A22: Apartments · instalments | B22: =(1-Inputs!$B$4-Inputs!$B$5)/Inputs!$B$6*SUMIFS($B$21:$AP$21,$B$3:$AP$3,">="&(B$3-Inputs!$B$6),$B$3:$AP$3,"<="&(B$3-1)) -> 0 | C22: =(1-Inputs!$B$4-Inputs!$B$5)/Inputs!$B$6*SUMIFS($B$21:$AP$21,$B$3:$AP$3,">="&(C$3-Inputs!$B$6),$B$3:$AP$3,"<="&(C$3-1)) -> 0 | D22: =(1-Inputs!$B$4-Inputs!$B$5)/Inputs!$B$6*SUMIFS($B$21:$AP$21,$B$3:$AP$3,">="&(D$3-Inputs!$B$6),$B$3:$AP$3,"<="&(D$3-1)) -> 9180000 | E22: =(1-Inputs!$B$4-Inputs!$B$5)/Inputs!$B$6*SUMIFS($B$21:$AP$21,$B$3:$AP$3,">="&(E$3-Inputs!$B$6),$B$3:$AP$3,"<="&(E$3-1)) -> 18727200 | F22: =(1-Inputs!$B$4-Inputs!$B$5)/Inputs!$B$6*SUMIFS($B$21:$AP$21,$B$3:$AP$3,">="&(F$3-Inputs!$B$6),$B$3:$AP$3,"<="&(F$3-1)) -> 28656288 | G22: =(1-Inputs!$B$4-Inputs!$B$5)/Inputs!$B$6*SUMIFS($B$21:$AP$21,$B$3:$AP$3,">="&(G$3-Inputs!$B$6),$B$3:$AP$3,"<="&(G$3-1)) -> 38982540 | H22: =(1-Inputs!$B$4-Inputs!$B$5)/Inputs!$B$6*SUMIFS($B$21:$AP$21,$B$3:$AP$3,">="&(H$3-Inputs!$B$6),$B$3:$AP$3,"<="&(H$3-1)) -> 49721841 | I22: =(1-Inputs!$B$4-Inputs!$B$5)/Inputs!$B$6*SUMIFS($B$21:$AP$21,$B$3:$AP$3,">="&(I$3-Inputs!$B$6),$B$3:$AP$3,"<="&(I$3-1)) -> 60890715 | ... AP22: =(1-Inputs!$B$4-Inputs!$B$5)/Inputs!$B$6*SUMIFS($B$21:$AP$21,$B$3:$AP$3,">="&(AP$3-Inputs!$B$6),$B$3:$AP$3,"<="&(AP$3-1)) -> 1.4955806e+08
A23: Apartments · delivery | B23: =Inputs!$B$5*(IF(B$3=(Products!$G$4+Products!$H$4),SUMIFS($B$21:$AP$21,$B$3:$AP$3,"<="&(Products!$G$4+Products!$H$4)),0)+IF(B$3>(Products!$G$4+Products!$H$4),B21,0)) -> 0 | C23: =Inputs!$B$5*(IF(C$3=(Products!$G$4+Products!$H$4),SUMIFS($B$21:$AP$21,$B$3:$AP$3,"<="&(Products!$G$4+Products!$H$4)),0)+IF(C$3>(Products!$G$4+Products!$H$4),C21,0)) -> 0 | D23: =Inputs!$B$5*(IF(D$3=(Products!$G$4+Products!$H$4),SUMIFS($B$21:$AP$21,$B$3:$AP$3,"<="&(Products!$G$4+Products!$H$4)),0)+IF(D$3>(Products!$G$4+Products!$H$4),D21,0)) -> 0 | E23: =Inputs!$B$5*(IF(E$3=(Products!$G$4+Products!$H$4),SUMIFS($B$21:$AP$21,$B$3:$AP$3,"<="&(Products!$G$4+Products!$H$4)),0)+IF(E$3>(Products!$G$4+Products!$H$4),E21,0)) -> 0 | F23: =Inputs!$B$5*(IF(F$3=(Products!$G$4+Products!$H$4),SUMIFS($B$21:$AP$21,$B$3:$AP$3,"<="&(Products!$G$4+Products!$H$4)),0)+IF(F$3>(Products!$G$4+Products!$H$4),F21,0)) -> 0 | G23: =Inputs!$B$5*(IF(G$3=(Products!$G$4+Products!$H$4),SUMIFS($B$21:$AP$21,$B$3:$AP$3,"<="&(Products!$G$4+Products!$H$4)),0)+IF(G$3>(Products!$G$4+Products!$H$4),G21,0)) -> 0 | H23: =Inputs!$B$5*(IF(H$3=(Products!$G$4+Products!$H$4),SUMIFS($B$21:$AP$21,$B$3:$AP$3,"<="&(Products!$G$4+Products!$H$4)),0)+IF(H$3>(Products!$G$4+Products!$H$4),H21,0)) -> 0 | I23: =Inputs!$B$5*(IF(I$3=(Products!$G$4+Products!$H$4),SUMIFS($B$21:$AP$21,$B$3:$AP$3,"<="&(Products!$G$4+Products!$H$4)),0)+IF(I$3>(Products!$G$4+Products!$H$4),I21,0)) -> 0 | ... AP23: =Inputs!$B$5*(IF(AP$3=(Products!$G$4+Products!$H$4),SUMIFS($B$21:$AP$21,$B$3:$AP$3,"<="&(Products!$G$4+Products!$H$4)),0)+IF(AP$3>(Products!$G$4+Products!$H$4),AP21,0)) -> 0
A24: Apartments · collections | B24: =Inputs!$B$4*B21+B22+B23 -> 0 | C24: =Inputs!$B$4*C21+C22+C23 -> 30240000 | D24: =Inputs!$B$4*D21+D22+D23 -> 40629600 | E24: =Inputs!$B$4*E21+E22+E23 -> 51434784 | F24: =Inputs!$B$4*F21+F22+F23 -> 62672175 | G24: =Inputs!$B$4*G21+G22+G23 -> 74359062 | H24: =Inputs!$B$4*H21+H22+H23 -> 86513425 | I24: =Inputs!$B$4*I21+I22+I23 -> 99153962 | ... AP24: =Inputs!$B$4*AP21+AP22+AP23 -> 1.4955806e+08
A25: Apartments · build cost | B25: =IF(AND(B$3>=Products!$G$4,B$3<(Products!$G$4+Products!$H$4)),Products!$B$4*Products!$C$4*Products!$I$4*(1+Inputs!$B$8)^B$3/Products!$H$4,0) -> 0 | C25: =IF(AND(C$3>=Products!$G$4,C$3<(Products!$G$4+Products!$H$4)),Products!$B$4*Products!$C$4*Products!$I$4*(1+Inputs!$B$8)^C$3/Products!$H$4,0) -> 0 | D25: =IF(AND(D$3>=Products!$G$4,D$3<(Products!$G$4+Products!$H$4)),Products!$B$4*Products!$C$4*Products!$I$4*(1+Inputs!$B$8)^D$3/Products!$H$4,0) -> 1.9121366e+08 | E25: =IF(AND(E$3>=Products!$G$4,E$3<(Products!$G$4+Products!$H$4)),Products!$B$4*Products!$C$4*Products!$I$4*(1+Inputs!$B$8)^E$3/Products!$H$4,0) -> 1.9790614e+08 | F25: =IF(AND(F$3>=Products!$G$4,F$3<(Products!$G$4+Products!$H$4)),Products!$B$4*Products!$C$4*Products!$I$4*(1+Inputs!$B$8)^F$3/Products!$H$4,0) -> 2.0483286e+08 | G25: =IF(AND(G$3>=Products!$G$4,G$3<(Products!$G$4+Products!$H$4)),Products!$B$4*Products!$C$4*Products!$I$4*(1+Inputs!$B$8)^G$3/Products!$H$4,0) -> 2.1200201e+08 | H25: =IF(AND(H$3>=Products!$G$4,H$3<(Products!$G$4+Products!$H$4)),Products!$B$4*Products!$C$4*Products!$I$4*(1+Inputs!$B$8)^H$3/Products!$H$4,0) -> 2.1942208e+08 | I25: =IF(AND(I$3>=Products!$G$4,I$3<(Products!$G$4+Products!$H$4)),Products!$B$4*Products!$C$4*Products!$I$4*(1+Inputs!$B$8)^I$3/Products!$H$4,0) -> 2.2710185e+08 | ... AP25: =IF(AND(AP$3>=Products!$G$4,AP$3<(Products!$G$4+Products!$H$4)),Products!$B$4*Products!$C$4*Products!$I$4*(1+Inputs!$B$8)^AP$3/Products!$H$4,0) -> 0
A26: Retail · units sold | B26: =IF(B$3>=Products!$E$5,MIN(Products!$F$5,Products!$B$5-0),0) -> 0 | C26: =IF(C$3>=Products!$E$5,MIN(Products!$F$5,Products!$B$5-B27),0) -> 0 | D26: =IF(D$3>=Products!$E$5,MIN(Products!$F$5,Products!$B$5-C27),0) -> 0 | E26: =IF(E$3>=Products!$E$5,MIN(Products!$F$5,Products!$B$5-D27),0) -> 0 | F26: =IF(F$3>=Products!$E$5,MIN(Products!$F$5,Products!$B$5-E27),0) -> 0 | G26: =IF(G$3>=Products!$E$5,MIN(Products!$F$5,Products!$B$5-F27),0) -> 0 | H26: =IF(H$3>=Products!$E$5,MIN(Products!$F$5,Products!$B$5-G27),0) -> 4 | I26: =IF(I$3>=Products!$E$5,MIN(Products!$F$5,Products!$B$5-H27),0) -> 4 | J26: =IF(J$3>=Products!$E$5,MIN(Products!$F$5,Products!$B$5-I27),0) -> 4 | ... AP26: =IF(AP$3>=Products!$E$5,MIN(Products!$F$5,Products!$B$5-AO27),0) -> 0
A27: Retail · cumulative units | B27: =B26 -> 0 | C27: =B27+C26 -> 0 | D27: =C27+D26 -> 0 | E27: =D27+E26 -> 0 | F27: =E27+F26 -> 0 | G27: =F27+G26 -> 0 | H27: =G27+H26 -> 4 | I27: =H27+I26 -> 8 | J27: =I27+J26 -> 12 | ... AP27: =AO27+AP26 -> 60
A28: Retail · sales value | B28: =B26*Products!$C$5*Products!$D$5*(1+Inputs!$B$7)^MAX(0,B$3-Products!$E$5) -> 0 | C28: =C26*Products!$C$5*Products!$D$5*(1+Inputs!$B$7)^MAX(0,C$3-Products!$E$5) -> 0 | D28: =D26*Products!$C$5*Products!$D$5*(1+Inputs!$B$7)^MAX(0,D$3-Products!$E$5) -> 0 | E28: =E26*Products!$C$5*Products!$D$5*(1+Inputs!$B$7)^MAX(0,E$3-Products!$E$5) -> 0 | F28: =F26*Products!$C$5*Products!$D$5*(1+Inputs!$B$7)^MAX(0,F$3-Products!$E$5) -> 0 | G28: =G26*Products!$C$5*Products!$D$5*(1+Inputs!$B$7)^MAX(0,G$3-Products!$E$5) -> 0 | H28: =H26*Products!$C$5*Products!$D$5*(1+Inputs!$B$7)^MAX(0,H$3-Products!$E$5) -> 50400000 | I28: =I26*Products!$C$5*Products!$D$5*(1+Inputs!$B$7)^MAX(0,I$3-Products!$E$5) -> 52416000 | ... AP28: =AP26*Products!$C$5*Products!$D$5*(1+Inputs!$B$7)^MAX(0,AP$3-Products!$E$5) -> 0
A29: Retail · instalments | B29: =(1-Inputs!$B$4-Inputs!$B$5)/Inputs!$B$6*SUMIFS($B$28:$AP$28,$B$3:$AP$3,">="&(B$3-Inputs!$B$6),$B$3:$AP$3,"<="&(B$3-1)) -> 0 | C29: =(1-Inputs!$B$4-Inputs!$B$5)/Inputs!$B$6*SUMIFS($B$28:$AP$28,$B$3:$AP$3,">="&(C$3-Inputs!$B$6),$B$3:$AP$3,"<="&(C$3-1)) -> 0 | D29: =(1-Inputs!$B$4-Inputs!$B$5)/Inputs!$B$6*SUMIFS($B$28:$AP$28,$B$3:$AP$3,">="&(D$3-Inputs!$B$6),$B$3:$AP$3,"<="&(D$3-1)) -> 0 | E29: =(1-Inputs!$B$4-Inputs!$B$5)/Inputs!$B$6*SUMIFS($B$28:$AP$28,$B$3:$AP$3,">="&(E$3-Inputs!$B$6),$B$3:$AP$3,"<="&(E$3-1)) -> 0 | F29: =(1-Inputs!$B$4-Inputs!$B$5)/Inputs!$B$6*SUMIFS($B$28:$AP$28,$B$3:$AP$3,">="&(F$3-Inputs!$B$6),$B$3:$AP$3,"<="&(F$3-1)) -> 0 | G29: =(1-Inputs!$B$4-Inputs!$B$5)/Inputs!$B$6*SUMIFS($B$28:$AP$28,$B$3:$AP$3,">="&(G$3-Inputs!$B$6),$B$3:$AP$3,"<="&(G$3-1)) -> 0 | H29: =(1-Inputs!$B$4-Inputs!$B$5)/Inputs!$B$6*SUMIFS($B$28:$AP$28,$B$3:$AP$3,">="&(H$3-Inputs!$B$6),$B$3:$AP$3,"<="&(H$3-1)) -> 0 | I29: =(1-Inputs!$B$4-Inputs!$B$5)/Inputs!$B$6*SUMIFS($B$28:$AP$28,$B$3:$AP$3,">="&(I$3-Inputs!$B$6),$B$3:$AP$3,"<="&(I$3-1)) -> 1530000 | ... AP29: =(1-Inputs!$B$4-Inputs!$B$5)/Inputs!$B$6*SUMIFS($B$28:$AP$28,$B$3:$AP$3,">="&(AP$3-Inputs!$B$6),$B$3:$AP$3,"<="&(AP$3-1)) -> 20487637
A30: Retail · delivery | B30: =Inputs!$B$5*(IF(B$3=(Products!$G$5+Products!$H$5),SUMIFS($B$28:$AP$28,$B$3:$AP$3,"<="&(Products!$G$5+Products!$H$5)),0)+IF(B$3>(Products!$G$5+Products!$H$5),B28,0)) -> 0 | C30: =Inputs!$B$5*(IF(C$3=(Products!$G$5+Products!$H$5),SUMIFS($B$28:$AP$28,$B$3:$AP$3,"<="&(Products!$G$5+Products!$H$5)),0)+IF(C$3>(Products!$G$5+Products!$H$5),C28,0)) -> 0 | D30: =Inputs!$B$5*(IF(D$3=(Products!$G$5+Products!$H$5),SUMIFS($B$28:$AP$28,$B$3:$AP$3,"<="&(Products!$G$5+Products!$H$5)),0)+IF(D$3>(Products!$G$5+Products!$H$5),D28,0)) -> 0 | E30: =Inputs!$B$5*(IF(E$3=(Products!$G$5+Products!$H$5),SUMIFS($B$28:$AP$28,$B$3:$AP$3,"<="&(Products!$G$5+Products!$H$5)),0)+IF(E$3>(Products!$G$5+Products!$H$5),E28,0)) -> 0 | F30: =Inputs!$B$5*(IF(F$3=(Products!$G$5+Products!$H$5),SUMIFS($B$28:$AP$28,$B$3:$AP$3,"<="&(Products!$G$5+Products!$H$5)),0)+IF(F$3>(Products!$G$5+Products!$H$5),F28,0)) -> 0 | G30: =Inputs!$B$5*(IF(G$3=(Products!$G$5+Products!$H$5),SUMIFS($B$28:$AP$28,$B$3:$AP$3,"<="&(Products!$G$5+Products!$H$5)),0)+IF(G$3>(Products!$G$5+Products!$H$5),G28,0)) -> 0 | H30: =Inputs!$B$5*(IF(H$3=(Products!$G$5+Products!$H$5),SUMIFS($B$28:$AP$28,$B$3:$AP$3,"<="&(Products!$G$5+Products!$H$5)),0)+IF(H$3>(Products!$G$5+Products!$H$5),H28,0)) -> 0 | I30: =Inputs!$B$5*(IF(I$3=(Products!$G$5+Products!$H$5),SUMIFS($B$28:$AP$28,$B$3:$AP$3,"<="&(Products!$G$5+Products!$H$5)),0)+IF(I$3>(Products!$G$5+Products!$H$5),I28,0)) -> 0 | ... AP30: =Inputs!$B$5*(IF(AP$3=(Products!$G$5+Products!$H$5),SUMIFS($B$28:$AP$28,$B$3:$AP$3,"<="&(Products!$G$5+Products!$H$5)),0)+IF(AP$3>(Products!$G$5+Products!$H$5),AP28,0)) -> 0
A31: Retail · collections | B31: =Inputs!$B$4*B28+B29+B30 -> 0 | C31: =Inputs!$B$4*C28+C29+C30 -> 0 | D31: =Inputs!$B$4*D28+D29+D30 -> 0 | E31: =Inputs!$B$4*E28+E29+E30 -> 0 | F31: =Inputs!$B$4*F28+F29+F30 -> 0 | G31: =Inputs!$B$4*G28+G29+G30 -> 0 | H31: =Inputs!$B$4*H28+H29+H30 -> 5040000 | I31: =Inputs!$B$4*I28+I29+I30 -> 6771600 | ... AP31: =Inputs!$B$4*AP28+AP29+AP30 -> 20487637
A32: Retail · build cost | B32: =IF(AND(B$3>=Products!$G$5,B$3<(Products!$G$5+Products!$H$5)),Products!$B$5*Products!$C$5*Products!$I$5*(1+Inputs!$B$8)^B$3/Products!$H$5,0) -> 0 | C32: =IF(AND(C$3>=Products!$G$5,C$3<(Products!$G$5+Products!$H$5)),Products!$B$5*Products!$C$5*Products!$I$5*(1+Inputs!$B$8)^C$3/Products!$H$5,0) -> 0 | D32: =IF(AND(D$3>=Products!$G$5,D$3<(Products!$G$5+Products!$H$5)),Products!$B$5*Products!$C$5*Products!$I$5*(1+Inputs!$B$8)^D$3/Products!$H$5,0) -> 0 | E32: =IF(AND(E$3>=Products!$G$5,E$3<(Products!$G$5+Products!$H$5)),Products!$B$5*Products!$C$5*Products!$I$5*(1+Inputs!$B$8)^E$3/Products!$H$5,0) -> 0 | F32: =IF(AND(F$3>=Products!$G$5,F$3<(Products!$G$5+Products!$H$5)),Products!$B$5*Products!$C$5*Products!$I$5*(1+Inputs!$B$8)^F$3/Products!$H$5,0) -> 0 | G32: =IF(AND(G$3>=Products!$G$5,G$3<(Products!$G$5+Products!$H$5)),Products!$B$5*Products!$C$5*Products!$I$5*(1+Inputs!$B$8)^G$3/Products!$H$5,0) -> 0 | H32: =IF(AND(H$3>=Products!$G$5,H$3<(Products!$G$5+Products!$H$5)),Products!$B$5*Products!$C$5*Products!$I$5*(1+Inputs!$B$8)^H$3/Products!$H$5,0) -> 0 | I32: =IF(AND(I$3>=Products!$G$5,I$3<(Products!$G$5+Products!$H$5)),Products!$B$5*Products!$C$5*Products!$I$5*(1+Inputs!$B$8)^I$3/Products!$H$5,0) -> 0 | ... AP32: =IF(AND(AP$3>=Products!$G$5,AP$3<(Products!$G$5+Products!$H$5)),Products!$B$5*Products!$C$5*Products!$I$5*(1+Inputs!$B$8)^AP$3/Products!$H$5,0) -> 0
A33: Collections | B33: =B10+B17+B24+B31 -> 0 | C33: =C10+C17+C24+C31 -> 48096000 | D33: =D10+D17+D24+D31 -> 82330411 | E33: =E10+E17+E24+E31 -> 1.0560045e+08 | F33: =F10+F17+F24+F31 -> 1.2980129e+08 | G33: =G10+G17+G24+G31 -> 1.5497016e+08 | H33: =H10+H17+H24+H31 -> 1.8618579e+08 | I33: =I10+I17+I24+I31 -> 2.1514004e+08 | ... AP33: =AP10+AP17+AP24+AP31 -> 3.3790808e+08
A34: Sales value | B34: =B7+B14+B21+B28 -> 0 | C34: =C7+C14+C21+C28 -> 480960000 | D34: =D7+D14+D21+D28 -> 677298400 | E34: =E7+E14+E21+E28 -> 704390336 | F34: =F7+F14+F21+F28 -> 7.3256595e+08 | G34: =G7+G14+G21+G28 -> 7.6186859e+08 | H34: =H7+H14+H21+H28 -> 8.4274333e+08 | I34: =I7+I14+I21+I28 -> 8.7645306e+08 | ... AP34: =AP7+AP14+AP21+AP28 -> 0
A35: Build cost | B35: =B11+B18+B25+B32 -> 0 | C35: =C11+C18+C25+C32 -> 0 | D35: =D11+D18+D25+D32 -> 3.2078904e+08 | E35: =E11+E18+E25+E32 -> 4.7198613e+08 | F35: =F11+F18+F25+F32 -> 4.8850564e+08 | G35: =G11+G18+G25+G32 -> 5.0560334e+08 | H35: =H11+H18+H25+H32 -> 5.2329946e+08 | I35: =I11+I18+I25+I32 -> 5.4161494e+08 | ... AP35: =AP11+AP18+AP25+AP32 -> 0
A36: Commissions | B36: =B34*Inputs!$B$9 -> 0 | C36: =C34*Inputs!$B$9 -> 14428800 | D36: =D34*Inputs!$B$9 -> 20318952 | E36: =E34*Inputs!$B$9 -> 21131710 | F36: =F34*Inputs!$B$9 -> 21976978 | G36: =G34*Inputs!$B$9 -> 22856058 | H36: =H34*Inputs!$B$9 -> 25282300 | I36: =I34*Inputs!$B$9 -> 26293592 | ... AP36: =AP34*Inputs!$B$9 -> 0
A37: Land | B37: =IF(B$3=0,Inputs!$B$10*Inputs!$B$11,IF(AND(MOD(B$3,2)=0,B$3<=2*Inputs!$B$12),Inputs!$B$10*(1-Inputs!$B$11)/Inputs!$B$12,0)) -> 480000000 | C37: =IF(C$3=0,Inputs!$B$10*Inputs!$B$11,IF(AND(MOD(C$3,2)=0,C$3<=2*Inputs!$B$12),Inputs!$B$10*(1-Inputs!$B$11)/Inputs!$B$12,0)) -> 0 | D37: =IF(D$3=0,Inputs!$B$10*Inputs!$B$11,IF(AND(MOD(D$3,2)=0,D$3<=2*Inputs!$B$12),Inputs!$B$10*(1-Inputs!$B$11)/Inputs!$B$12,0)) -> 240000000 | E37: =IF(E$3=0,Inputs!$B$10*Inputs!$B$11,IF(AND(MOD(E$3,2)=0,E$3<=2*Inputs!$B$12),Inputs!$B$10*(1-Inputs!$B$11)/Inputs!$B$12,0)) -> 0 | F37: =IF(F$3=0,Inputs!$B$10*Inputs!$B$11,IF(AND(MOD(F$3,2)=0,F$3<=2*Inputs!$B$12),Inputs!$B$10*(1-Inputs!$B$11)/Inputs!$B$12,0)) -> 240000000 | G37: =IF(G$3=0,Inputs!$B$10*Inputs!$B$11,IF(AND(MOD(G$3,2)=0,G$3<=2*Inputs!$B$12),Inputs!$B$10*(1-Inputs!$B$11)/Inputs!$B$12,0)) -> 0 | H37: =IF(H$3=0,Inputs!$B$10*Inputs!$B$11,IF(AND(MOD(H$3,2)=0,H$3<=2*Inputs!$B$12),Inputs!$B$10*(1-Inputs!$B$11)/Inputs!$B$12,0)) -> 240000000 | I37: =IF(I$3=0,Inputs!$B$10*Inputs!$B$11,IF(AND(MOD(I$3,2)=0,I$3<=2*Inputs!$B$12),Inputs!$B$10*(1-Inputs!$B$11)/Inputs!$B$12,0)) -> 0 | ... AP37: =IF(AP$3=0,Inputs!$B$10*Inputs!$B$11,IF(AND(MOD(AP$3,2)=0,AP$3<=2*Inputs!$B$12),Inputs!$B$10*(1-Inputs!$B$11)/Inputs!$B$12,0)) -> 0
A38: Pre-tax cash flow | B38: =B33-B35-B36-B37 -> -480000000 | C38: =C33-C35-C36-C37 -> 33667200 | D38: =D33-D35-D36-D37 -> -4.9877758e+08 | E38: =E33-E35-E36-E37 -> -3.8751739e+08 | F38: =F33-F35-F36-F37 -> -6.2068133e+08 | G38: =G33-G35-G36-G37 -> -3.7348923e+08 | H38: =H33-H35-H36-H37 -> -6.0239597e+08 | I38: =I33-I35-I36-I37 -> -3.5276849e+08 | ... AP38: =AP33-AP35-AP36-AP37 -> 3.3790808e+08
A39: Cumulative cash | B39: =B38 -> -480000000 | C39: =B39+C38 -> -446332800 | D39: =C39+D38 -> -9.4511038e+08 | E39: =D39+E38 -> -1.3326278e+09 | F39: =E39+F38 -> -1.9533091e+09 | G39: =F39+G38 -> -2.3267983e+09 | H39: =G39+H38 -> -2.9291943e+09 | I39: =H39+I38 -> -3.2819628e+09 | J39: =I39+J38 -> -3.900181e+09 | ... AP39: =AO39+AP38 -> 9.5680897e+09
A40: Tax | B40: =MAX(0,B39)*Inputs!$B$14 -> 0 | C40: =MAX(0,C39)*Inputs!$B$14-MAX(0,B39)*Inputs!$B$14 -> 0 | D40: =MAX(0,D39)*Inputs!$B$14-MAX(0,C39)*Inputs!$B$14 -> 0 | E40: =MAX(0,E39)*Inputs!$B$14-MAX(0,D39)*Inputs!$B$14 -> 0 | F40: =MAX(0,F39)*Inputs!$B$14-MAX(0,E39)*Inputs!$B$14 -> 0 | G40: =MAX(0,G39)*Inputs!$B$14-MAX(0,F39)*Inputs!$B$14 -> 0 | H40: =MAX(0,H39)*Inputs!$B$14-MAX(0,G39)*Inputs!$B$14 -> 0 | I40: =MAX(0,I39)*Inputs!$B$14-MAX(0,H39)*Inputs!$B$14 -> 0 | J40: =MAX(0,J39)*Inputs!$B$14-MAX(0,I39)*Inputs!$B$14 -> 0 | ... AP40: =MAX(0,AP39)*Inputs!$B$14-MAX(0,AO39)*Inputs!$B$14 -> 76029318
A41: Net cash flow | B41: =B38-B40 -> -480000000 | C41: =C38-C40 -> 33667200 | D41: =D38-D40 -> -4.9877758e+08 | E41: =E38-E40 -> -3.8751739e+08 | F41: =F38-F40 -> -6.2068133e+08 | G41: =G38-G40 -> -3.7348923e+08 | H41: =H38-H40 -> -6.0239597e+08 | I41: =I38-I40 -> -3.5276849e+08 | ... AP41: =AP38-AP40 -> 2.6187876e+08

Sheet Returns
A3: Project IRR (XIRR) | B3: =XIRR('Cash Flow'!B41:AP41,'Cash Flow'!B4:AP4) -> 0.209446
A4: NPV at the discount rate (EGP) | B4: =XNPV(Inputs!$B$13,'Cash Flow'!B41:AP41,'Cash Flow'!B4:AP4) -> -5.135854e+08
A5: Net profit (EGP) | B5: =SUM('Cash Flow'!B41:AP41) -> 7.4152696e+09
A6: Peak funding (EGP) | B6: =-MIN('Cash Flow'!B39:AP39) -> 5.2167457e+09
A7: Total sales value (EGP) | B7: =SUM('Cash Flow'!B34:AP34) -> 2.0078069e+10
A8: Receivables outstanding at the horizon (EGP) | B8: =B7-SUM('Cash Flow'!B33:AP33) -> 1.4223475e+09
A9: Total development cost (EGP) | B9: =SUM('Cash Flow'!B35:AP35)+SUM('Cash Flow'!B37:AP37)+SUM('Cash Flow'!B36:AP36) -> 9.0876315e+09
