Workbook

Sheet Inputs
A1: MERIDIAN LOGISTICS REIT – NAV, ISSUANCE AND AFFO (SGD)
A3: Units outstanding (m) | B3: 2800
A4: Debt (S$ m) | B4: 2100
A5: Cost of debt | B5: 0.038
A6: G&A (S$ m a year) | B6: 28
A7: Maintenance capex (% of NOI) | B7: 0.12
A8: Payout (% of AFFO) | B8: 0.9
A9: Issue price premium to NAV | B9: 0.05
A10: Acquisitions a year (S$ m) | B10: 450
A11: Acquisition cap rate | B11: 0.0625
A12: Acquisitions funded by equity | B12: 0.6
A13: Same-property NOI growth | B13: 0.025
A14: Portfolio valuation cap rate shift (bps) | B14: 0
A15: Acquisition fee | B15: 0.01

Sheet Assets
A1: Asset | B1: NOI (S$ m) | C1: Cap rate
A2: Tuas Megahub | B2: 62 | C2: 0.0575
A3: Changi Air Cargo | B3: 48 | C3: 0.0525
A4: Jurong Cold Chain | B4: 37 | C4: 0.06
A5: Woodlands Flex | B5: 29 | C5: 0.065
A6: Sydney Moorebank | B6: 55 | C6: 0.0475
A7: Osaka Bay DC | B7: 41 | C7: 0.0425

Sheet Projection
A3: Year | B3: 0 | C3: 1 | D3: 2 | E3: 3 | F3: 4 | G3: 5
A4: Same-property NOI | B4: =SUM(Assets!$B$2:$B$7)*(1+Inputs!$B$13)^B$3 -> 272 | C4: =SUM(Assets!$B$2:$B$7)*(1+Inputs!$B$13)^C$3 -> 278.8 | D4: =SUM(Assets!$B$2:$B$7)*(1+Inputs!$B$13)^D$3 -> 285.77 | E4: =SUM(Assets!$B$2:$B$7)*(1+Inputs!$B$13)^E$3 -> 292.91425 | F4: =SUM(Assets!$B$2:$B$7)*(1+Inputs!$B$13)^F$3 -> 300.23711 | G4: =SUM(Assets!$B$2:$B$7)*(1+Inputs!$B$13)^G$3 -> 307.74303
A5: Acquired NOI | B5: =0 -> 0 | C5: =B5*(1+Inputs!$B$13)+B8*Inputs!$B$11 -> 28.125 | D5: =C5*(1+Inputs!$B$13)+C8*Inputs!$B$11 -> 56.953125 | E5: =D5*(1+Inputs!$B$13)+D8*Inputs!$B$11 -> 86.501953 | F5: =E5*(1+Inputs!$B$13)+E8*Inputs!$B$11 -> 116.7895 | G5: =F5*(1+Inputs!$B$13)+F8*Inputs!$B$11 -> 147.83424
A6: NOI | B6: =B4+B5 -> 272 | C6: =C4+C5 -> 306.925 | D6: =D4+D5 -> 342.72312 | E6: =E4+E5 -> 379.4162 | F6: =F4+F5 -> 417.02661 | G6: =G4+G5 -> 455.57727
A7: Portfolio value | B7: =SUMPRODUCT(Assets!$B$2:$B$7/(Assets!$C$2:$C$7+Inputs!$B$14/10000))*(1+Inputs!$B$13)^B$3+B5/(SUMPRODUCT(Assets!$B$2:$B$7,Assets!$C$2:$C$7)/SUM(Assets!$B$2:$B$7)+Inputs!$B$14/10000) -> 5177.9677 | C7: =SUMPRODUCT(Assets!$B$2:$B$7/(Assets!$C$2:$C$7+Inputs!$B$14/10000))*(1+Inputs!$B$13)^C$3+C5/(SUMPRODUCT(Assets!$B$2:$B$7,Assets!$C$2:$C$7)/SUM(Assets!$B$2:$B$7)+Inputs!$B$14/10000) -> 5833.3708 | D7: =SUMPRODUCT(Assets!$B$2:$B$7/(Assets!$C$2:$C$7+Inputs!$B$14/10000))*(1+Inputs!$B$13)^D$3+D5/(SUMPRODUCT(Assets!$B$2:$B$7,Assets!$C$2:$C$7)/SUM(Assets!$B$2:$B$7)+Inputs!$B$14/10000) -> 6505.1591 | E7: =SUMPRODUCT(Assets!$B$2:$B$7/(Assets!$C$2:$C$7+Inputs!$B$14/10000))*(1+Inputs!$B$13)^E$3+E5/(SUMPRODUCT(Assets!$B$2:$B$7,Assets!$C$2:$C$7)/SUM(Assets!$B$2:$B$7)+Inputs!$B$14/10000) -> 7193.742 | F7: =SUMPRODUCT(Assets!$B$2:$B$7/(Assets!$C$2:$C$7+Inputs!$B$14/10000))*(1+Inputs!$B$13)^F$3+F5/(SUMPRODUCT(Assets!$B$2:$B$7,Assets!$C$2:$C$7)/SUM(Assets!$B$2:$B$7)+Inputs!$B$14/10000) -> 7899.5394 | G7: =SUMPRODUCT(Assets!$B$2:$B$7/(Assets!$C$2:$C$7+Inputs!$B$14/10000))*(1+Inputs!$B$13)^G$3+G5/(SUMPRODUCT(Assets!$B$2:$B$7,Assets!$C$2:$C$7)/SUM(Assets!$B$2:$B$7)+Inputs!$B$14/10000) -> 8622.9819
A8: Acquisitions | B8: =Inputs!$B$10 -> 450 | C8: =Inputs!$B$10 -> 450 | D8: =Inputs!$B$10 -> 450 | E8: =Inputs!$B$10 -> 450 | F8: =Inputs!$B$10 -> 450 | G8: =0 -> 0
A9: Equity raised | B9: =B8*(1+Inputs!$B$15)*Inputs!$B$12 -> 272.7 | C9: =C8*(1+Inputs!$B$15)*Inputs!$B$12 -> 272.7 | D9: =D8*(1+Inputs!$B$15)*Inputs!$B$12 -> 272.7 | E9: =E8*(1+Inputs!$B$15)*Inputs!$B$12 -> 272.7 | F9: =F8*(1+Inputs!$B$15)*Inputs!$B$12 -> 272.7 | G9: =G8*(1+Inputs!$B$15)*Inputs!$B$12 -> 0
A10: Debt drawn | B10: =B8*(1+Inputs!$B$15)*(1-Inputs!$B$12) -> 181.8 | C10: =C8*(1+Inputs!$B$15)*(1-Inputs!$B$12) -> 181.8 | D10: =D8*(1+Inputs!$B$15)*(1-Inputs!$B$12) -> 181.8 | E10: =E8*(1+Inputs!$B$15)*(1-Inputs!$B$12) -> 181.8 | F10: =F8*(1+Inputs!$B$15)*(1-Inputs!$B$12) -> 181.8 | G10: =G8*(1+Inputs!$B$15)*(1-Inputs!$B$12) -> 0
A11: Debt | B11: =Inputs!$B$4+B10 -> 2281.8 | C11: =B11+C10 -> 2463.6 | D11: =C11+D10 -> 2645.4 | E11: =D11+E10 -> 2827.2 | F11: =E11+F10 -> 3009 | G11: =F11+G10 -> 3009
A12: Interest | B12: =0 -> 0 | C12: =B11*Inputs!$B$5 -> 86.7084 | D12: =C11*Inputs!$B$5 -> 93.6168 | E12: =D11*Inputs!$B$5 -> 100.5252 | F12: =E11*Inputs!$B$5 -> 107.4336 | G12: =F11*Inputs!$B$5 -> 114.342
A13: FFO | B13: =0 -> 0 | C13: =C6-C12-Inputs!$B$6 -> 192.2166 | D13: =D6-D12-Inputs!$B$6 -> 221.10632 | E13: =E6-E12-Inputs!$B$6 -> 250.891 | F13: =F6-F12-Inputs!$B$6 -> 281.59301 | G13: =G6-G12-Inputs!$B$6 -> 313.23527
A14: AFFO | B14: =0 -> 0 | C14: =C13-C6*Inputs!$B$7 -> 155.3856 | D14: =D13-D6*Inputs!$B$7 -> 179.97955 | E14: =E13-E6*Inputs!$B$7 -> 205.36106 | F14: =F13-F6*Inputs!$B$7 -> 231.54982 | G14: =G13-G6*Inputs!$B$7 -> 258.566
A15: Units | B15: =Inputs!$B$3+B17 -> 3036.2598 | C15: =B15+C17 -> 3271.9204 | D15: =C15+D17 -> 3494.3852 | E15: =D15+E17 -> 3704.9635 | F15: =E15+F17 -> 3904.74 | G15: =F15+G17 -> 3904.74
A16: Issue price | B16: =(SUMPRODUCT(Assets!$B$2:$B$7/(Assets!$C$2:$C$7+Inputs!$B$14/10000))-Inputs!$B$4)/Inputs!$B$3*(1+Inputs!$B$9) -> 1.1542379 | C16: =B19*(1+Inputs!$B$9) -> 1.1571724 | D16: =C19*(1+Inputs!$B$9) -> 1.225812 | E16: =D19*(1+Inputs!$B$9) -> 1.2950052 | F16: =E19*(1+Inputs!$B$9) -> 1.3650253 | G16: =F19*(1+Inputs!$B$9) -> 1.4360921
A17: New units | B17: =B9/B16 -> 236.25979 | C17: =C9/C16 -> 235.66064 | D17: =D9/D16 -> 222.46478 | E17: =E9/E16 -> 210.57831 | F17: =F9/F16 -> 199.77651 | G17: =G9/G16 -> 0
A18: NAV | B18: =B7+B8-B11 -> 3346.1677 | C18: =C7+C8-C11 -> 3819.7708 | D18: =D7+D8-D11 -> 4309.7591 | E18: =E7+E8-E11 -> 4816.542 | F18: =F7+F8-F11 -> 5340.5394 | G18: =G7+G8-G11 -> 5613.9819
A19: NAV per unit | B19: =B18/B15 -> 1.102069 | C19: =C18/C15 -> 1.16744 | D19: =D18/D15 -> 1.2333383 | E19: =E18/E15 -> 1.3000241 | F19: =F18/F15 -> 1.3677068 | G19: =G18/G15 -> 1.4377351
A20: AFFO per unit | B20: =0 -> 0 | C20: =C14/B15 -> 0.051176649 | D20: =D14/C15 -> 0.055007313 | E20: =E14/D15 -> 0.058768867 | F20: =F14/E15 -> 0.062497192 | G20: =G14/F15 -> 0.066218493
A21: Distribution per unit | B21: =B20*Inputs!$B$8 -> 0 | C21: =C20*Inputs!$B$8 -> 0.046058984 | D21: =D20*Inputs!$B$8 -> 0.049506581 | E21: =E20*Inputs!$B$8 -> 0.05289198 | F21: =F20*Inputs!$B$8 -> 0.056247473 | G21: =G20*Inputs!$B$8 -> 0.059596644
A22: LTV | B22: =B11/(B7+B8) -> 0.40543943 | C22: =C11/(C7+C8) -> 0.39208254 | D22: =D11/(D7+D8) -> 0.38035076 | E22: =E11/(E7+E8) -> 0.3698712 | F22: =F11/(F7+F8) -> 0.36037916 | G22: =G11/(G7+G8) -> 0.34895121
A23: Unit price | B23: =B19*(1+Inputs!$B$9) -> 1.1571724 | C23: =C19*(1+Inputs!$B$9) -> 1.225812 | D23: =D19*(1+Inputs!$B$9) -> 1.2950052 | E23: =E19*(1+Inputs!$B$9) -> 1.3650253 | F23: =F19*(1+Inputs!$B$9) -> 1.4360921 | G23: =G19*(1+Inputs!$B$9) -> 1.5096219
A25: Unitholder cash flow | B25: =-B23 -> -1.1571724 | C25: =C21 -> 0.046058984 | D25: =D21 -> 0.049506581 | E25: =E21 -> 0.05289198 | F25: =F21 -> 0.056247473 | G25: =G21+G23 -> 1.5692185

Sheet Returns
A3: Total unitholder return (IRR) | B3: =IRR(Projection!B25:G25) -> 0.095488625
A4: AFFO per unit, year 1 (S$) | B4: =Projection!C20 -> 0.051176649
A5: AFFO per unit CAGR (years 1-5) | B5: =(Projection!G20/Projection!C20)^(1/4)-1 -> 0.0665393
A6: NAV per unit, year 5 (S$) | B6: =Projection!G19 -> 1.4377351
A7: LTV, year 5 | B7: =Projection!G22 -> 0.34895121
A8: Units issued (m) | B8: =SUM(Projection!B17:G17) -> 1104.74
A9: NAV per unit today (S$) | B9: =Projection!B19 -> 1.102069
