Workbook

Sheet Inputs
A1: HARBOUR VIEW APARTMENTS – FLOATING DEBT, HEDGES AND REFINANCE (USD)
A3: Purchase price ($) | B3: 120000000
A4: Closing costs | B4: 0.015
A5: NOI year 1 ($) | B5: 6600000
A6: NOI growth a year | B6: 0.035
A7: Bridge loan to cost | B7: 0.65
A8: Bridge margin over SOFR | B8: 0.0275
A9: Swapped share of the loan | B9: 0.5
A10: Swap fixed rate | B10: 0.036
A11: Cap strike | B11: 0.045
A12: Cap premium (% of capped notional) | B12: 0.012
A13: Refinance month | B13: 36
A14: Refinance max LTV | B14: 0.6
... A22: Selling costs | B22: 0.015

Sheet SOFR
A1: Month | B1: SOFR forward
A2: 1 | B2: 0.042764
A3: 2 | B3: 0.042552
A4: 3 | B4: 0.04236
A5: 4 | B5: 0.042182
A6: 5 | B6: 0.042014
A7: 6 | B7: 0.041853
A8: 7 | B8: 0.041693
A9: 8 | B9: 0.041532
A10: 9 | B10: 0.041366
A11: 10 | B11: 0.041191
A12: 11 | B12: 0.041006
A13: 12 | B13: 0.040807
... A61: 60 | B61: 0.034774

Sheet Cash Flow
A3: Month | B3: 0 | C3: 1 | D3: 2 | E3: 3 | F3: 4 | G3: 5 | H3: 6 | I3: 7 | J3: 8 | K3: 9 | L3: 10 | M3: 11 | N3: 12 | O3: 13 | P3: 14 | Q3: 15 | R3: 16 | S3: 17 | T3: 18 | U3: 19 | V3: 20 | W3: 21 | X3: 22 | Y3: 23 | Z3: 24 | AA3: 25 | AB3: 26 | AC3: 27 | AD3: 28 | AE3: 29 | AF3: 30 | AG3: 31 | AH3: 32 | AI3: 33 | AJ3: 34 | AK3: 35 | AL3: 36 | AM3: 37 | AN3: 38 | AO3: 39 | AP3: 40 | AQ3: 41 | AR3: 42 | AS3: 43 | AT3: 44 | AU3: 45 | AV3: 46 | AW3: 47 | AX3: 48 | AY3: 49 | AZ3: 50 | BA3: 51 | BB3: 52 | BC3: 53 | BD3: 54 | BE3: 55 | BF3: 56 | BG3: 57 | BH3: 58 | BI3: 59 | BJ3: 60
A4: SOFR | B4: =0 -> 0 | C4: =INDEX(SOFR!$B$2:$B$61,C$3) -> 0.042764 | D4: =INDEX(SOFR!$B$2:$B$61,D$3) -> 0.042552 | E4: =INDEX(SOFR!$B$2:$B$61,E$3) -> 0.04236 | F4: =INDEX(SOFR!$B$2:$B$61,F$3) -> 0.042182 | G4: =INDEX(SOFR!$B$2:$B$61,G$3) -> 0.042014 | H4: =INDEX(SOFR!$B$2:$B$61,H$3) -> 0.041853 | I4: =INDEX(SOFR!$B$2:$B$61,I$3) -> 0.041693 | J4: =INDEX(SOFR!$B$2:$B$61,J$3) -> 0.041532 | ... BJ4: =INDEX(SOFR!$B$2:$B$61,BJ$3) -> 0.034774
A5: NOI | B5: =IF(AND(B$3>=1,B$3<=Inputs!$B$20),Inputs!$B$5/12*(1+Inputs!$B$6)^((B$3-1)/12),0) -> 0 | C5: =IF(AND(C$3>=1,C$3<=Inputs!$B$20),Inputs!$B$5/12*(1+Inputs!$B$6)^((C$3-1)/12),0) -> 550000 | D5: =IF(AND(D$3>=1,D$3<=Inputs!$B$20),Inputs!$B$5/12*(1+Inputs!$B$6)^((D$3-1)/12),0) -> 551578.99 | E5: =IF(AND(E$3>=1,E$3<=Inputs!$B$20),Inputs!$B$5/12*(1+Inputs!$B$6)^((E$3-1)/12),0) -> 553162.52 | F5: =IF(AND(F$3>=1,F$3<=Inputs!$B$20),Inputs!$B$5/12*(1+Inputs!$B$6)^((F$3-1)/12),0) -> 554750.6 | G5: =IF(AND(G$3>=1,G$3<=Inputs!$B$20),Inputs!$B$5/12*(1+Inputs!$B$6)^((G$3-1)/12),0) -> 556343.23 | H5: =IF(AND(H$3>=1,H$3<=Inputs!$B$20),Inputs!$B$5/12*(1+Inputs!$B$6)^((H$3-1)/12),0) -> 557940.43 | I5: =IF(AND(I$3>=1,I$3<=Inputs!$B$20),Inputs!$B$5/12*(1+Inputs!$B$6)^((I$3-1)/12),0) -> 559542.22 | ... BJ5: =IF(AND(BJ$3>=1,BJ$3<=Inputs!$B$20),Inputs!$B$5/12*(1+Inputs!$B$6)^((BJ$3-1)/12),0) -> 651357.49
A6: Bridge balance | B6: =IF(B$3<Inputs!$B$13,Inputs!$B$3*Inputs!$B$7,0) -> 78000000 | C6: =IF(C$3<Inputs!$B$13,Inputs!$B$3*Inputs!$B$7,0) -> 78000000 | D6: =IF(D$3<Inputs!$B$13,Inputs!$B$3*Inputs!$B$7,0) -> 78000000 | E6: =IF(E$3<Inputs!$B$13,Inputs!$B$3*Inputs!$B$7,0) -> 78000000 | F6: =IF(F$3<Inputs!$B$13,Inputs!$B$3*Inputs!$B$7,0) -> 78000000 | G6: =IF(G$3<Inputs!$B$13,Inputs!$B$3*Inputs!$B$7,0) -> 78000000 | H6: =IF(H$3<Inputs!$B$13,Inputs!$B$3*Inputs!$B$7,0) -> 78000000 | I6: =IF(I$3<Inputs!$B$13,Inputs!$B$3*Inputs!$B$7,0) -> 78000000 | ... BJ6: =IF(BJ$3<Inputs!$B$13,Inputs!$B$3*Inputs!$B$7,0) -> 0
A7: Floating interest | B7: =(B$3>=1)*(B$3<=Inputs!$B$13)*Inputs!$B$3*Inputs!$B$7*(B4+Inputs!$B$8)/12 -> 0 | C7: =(C$3>=1)*(C$3<=Inputs!$B$13)*Inputs!$B$3*Inputs!$B$7*(C4+Inputs!$B$8)/12 -> 456716 | D7: =(D$3>=1)*(D$3<=Inputs!$B$13)*Inputs!$B$3*Inputs!$B$7*(D4+Inputs!$B$8)/12 -> 455338 | E7: =(E$3>=1)*(E$3<=Inputs!$B$13)*Inputs!$B$3*Inputs!$B$7*(E4+Inputs!$B$8)/12 -> 454090 | F7: =(F$3>=1)*(F$3<=Inputs!$B$13)*Inputs!$B$3*Inputs!$B$7*(F4+Inputs!$B$8)/12 -> 452933 | G7: =(G$3>=1)*(G$3<=Inputs!$B$13)*Inputs!$B$3*Inputs!$B$7*(G4+Inputs!$B$8)/12 -> 451841 | H7: =(H$3>=1)*(H$3<=Inputs!$B$13)*Inputs!$B$3*Inputs!$B$7*(H4+Inputs!$B$8)/12 -> 450794.5 | I7: =(I$3>=1)*(I$3<=Inputs!$B$13)*Inputs!$B$3*Inputs!$B$7*(I4+Inputs!$B$8)/12 -> 449754.5 | ... BJ7: =(BJ$3>=1)*(BJ$3<=Inputs!$B$13)*Inputs!$B$3*Inputs!$B$7*(BJ4+Inputs!$B$8)/12 -> 0
A8: Swap net payment | B8: =(B$3>=1)*(B$3<=Inputs!$B$13)*Inputs!$B$3*Inputs!$B$7*Inputs!$B$9*(Inputs!$B$10-B4)/12 -> 0 | C8: =(C$3>=1)*(C$3<=Inputs!$B$13)*Inputs!$B$3*Inputs!$B$7*Inputs!$B$9*(Inputs!$B$10-C4)/12 -> -21983 | D8: =(D$3>=1)*(D$3<=Inputs!$B$13)*Inputs!$B$3*Inputs!$B$7*Inputs!$B$9*(Inputs!$B$10-D4)/12 -> -21294 | E8: =(E$3>=1)*(E$3<=Inputs!$B$13)*Inputs!$B$3*Inputs!$B$7*Inputs!$B$9*(Inputs!$B$10-E4)/12 -> -20670 | F8: =(F$3>=1)*(F$3<=Inputs!$B$13)*Inputs!$B$3*Inputs!$B$7*Inputs!$B$9*(Inputs!$B$10-F4)/12 -> -20091.5 | G8: =(G$3>=1)*(G$3<=Inputs!$B$13)*Inputs!$B$3*Inputs!$B$7*Inputs!$B$9*(Inputs!$B$10-G4)/12 -> -19545.5 | H8: =(H$3>=1)*(H$3<=Inputs!$B$13)*Inputs!$B$3*Inputs!$B$7*Inputs!$B$9*(Inputs!$B$10-H4)/12 -> -19022.25 | I8: =(I$3>=1)*(I$3<=Inputs!$B$13)*Inputs!$B$3*Inputs!$B$7*Inputs!$B$9*(Inputs!$B$10-I4)/12 -> -18502.25 | ... BJ8: =(BJ$3>=1)*(BJ$3<=Inputs!$B$13)*Inputs!$B$3*Inputs!$B$7*Inputs!$B$9*(Inputs!$B$10-BJ4)/12 -> 0
A9: Cap payoff | B9: =(B$3>=1)*(B$3<=Inputs!$B$13)*Inputs!$B$3*Inputs!$B$7*(1-Inputs!$B$9)*MAX(0,B4-Inputs!$B$11)/12 -> 0 | C9: =(C$3>=1)*(C$3<=Inputs!$B$13)*Inputs!$B$3*Inputs!$B$7*(1-Inputs!$B$9)*MAX(0,C4-Inputs!$B$11)/12 -> 0 | D9: =(D$3>=1)*(D$3<=Inputs!$B$13)*Inputs!$B$3*Inputs!$B$7*(1-Inputs!$B$9)*MAX(0,D4-Inputs!$B$11)/12 -> 0 | E9: =(E$3>=1)*(E$3<=Inputs!$B$13)*Inputs!$B$3*Inputs!$B$7*(1-Inputs!$B$9)*MAX(0,E4-Inputs!$B$11)/12 -> 0 | F9: =(F$3>=1)*(F$3<=Inputs!$B$13)*Inputs!$B$3*Inputs!$B$7*(1-Inputs!$B$9)*MAX(0,F4-Inputs!$B$11)/12 -> 0 | G9: =(G$3>=1)*(G$3<=Inputs!$B$13)*Inputs!$B$3*Inputs!$B$7*(1-Inputs!$B$9)*MAX(0,G4-Inputs!$B$11)/12 -> 0 | H9: =(H$3>=1)*(H$3<=Inputs!$B$13)*Inputs!$B$3*Inputs!$B$7*(1-Inputs!$B$9)*MAX(0,H4-Inputs!$B$11)/12 -> 0 | I9: =(I$3>=1)*(I$3<=Inputs!$B$13)*Inputs!$B$3*Inputs!$B$7*(1-Inputs!$B$9)*MAX(0,I4-Inputs!$B$11)/12 -> 0 | ... BJ9: =(BJ$3>=1)*(BJ$3<=Inputs!$B$13)*Inputs!$B$3*Inputs!$B$7*(1-Inputs!$B$9)*MAX(0,BJ4-Inputs!$B$11)/12 -> 0
A10: Cap premium | B10: =IF(B$3=0,Inputs!$B$3*Inputs!$B$7*(1-Inputs!$B$9)*Inputs!$B$12,0) -> 468000 | C10: =IF(C$3=0,Inputs!$B$3*Inputs!$B$7*(1-Inputs!$B$9)*Inputs!$B$12,0) -> 0 | D10: =IF(D$3=0,Inputs!$B$3*Inputs!$B$7*(1-Inputs!$B$9)*Inputs!$B$12,0) -> 0 | E10: =IF(E$3=0,Inputs!$B$3*Inputs!$B$7*(1-Inputs!$B$9)*Inputs!$B$12,0) -> 0 | F10: =IF(F$3=0,Inputs!$B$3*Inputs!$B$7*(1-Inputs!$B$9)*Inputs!$B$12,0) -> 0 | G10: =IF(G$3=0,Inputs!$B$3*Inputs!$B$7*(1-Inputs!$B$9)*Inputs!$B$12,0) -> 0 | H10: =IF(H$3=0,Inputs!$B$3*Inputs!$B$7*(1-Inputs!$B$9)*Inputs!$B$12,0) -> 0 | I10: =IF(I$3=0,Inputs!$B$3*Inputs!$B$7*(1-Inputs!$B$9)*Inputs!$B$12,0) -> 0 | ... BJ10: =IF(BJ$3=0,Inputs!$B$3*Inputs!$B$7*(1-Inputs!$B$9)*Inputs!$B$12,0) -> 0
A11: Bridge interest, net of hedges | B11: =B7+B8-B9 -> 0 | C11: =C7+C8-C9 -> 434733 | D11: =D7+D8-D9 -> 434044 | E11: =E7+E8-E9 -> 433420 | F11: =F7+F8-F9 -> 432841.5 | G11: =G7+G8-G9 -> 432295.5 | H11: =H7+H8-H9 -> 431772.25 | I11: =I7+I8-I9 -> 431252.25 | ... BJ11: =BJ7+BJ8-BJ9 -> 0
A12: Value at refinance | B12: =IF(B$3=Inputs!$B$13,Inputs!$B$5*(1+Inputs!$B$6)^((Inputs!$B$13)/12)/Inputs!$B$19,0) -> 0 | C12: =IF(C$3=Inputs!$B$13,Inputs!$B$5*(1+Inputs!$B$6)^((Inputs!$B$13)/12)/Inputs!$B$19,0) -> 0 | D12: =IF(D$3=Inputs!$B$13,Inputs!$B$5*(1+Inputs!$B$6)^((Inputs!$B$13)/12)/Inputs!$B$19,0) -> 0 | E12: =IF(E$3=Inputs!$B$13,Inputs!$B$5*(1+Inputs!$B$6)^((Inputs!$B$13)/12)/Inputs!$B$19,0) -> 0 | F12: =IF(F$3=Inputs!$B$13,Inputs!$B$5*(1+Inputs!$B$6)^((Inputs!$B$13)/12)/Inputs!$B$19,0) -> 0 | G12: =IF(G$3=Inputs!$B$13,Inputs!$B$5*(1+Inputs!$B$6)^((Inputs!$B$13)/12)/Inputs!$B$19,0) -> 0 | H12: =IF(H$3=Inputs!$B$13,Inputs!$B$5*(1+Inputs!$B$6)^((Inputs!$B$13)/12)/Inputs!$B$19,0) -> 0 | I12: =IF(I$3=Inputs!$B$13,Inputs!$B$5*(1+Inputs!$B$6)^((Inputs!$B$13)/12)/Inputs!$B$19,0) -> 0 | ... BJ12: =IF(BJ$3=Inputs!$B$13,Inputs!$B$5*(1+Inputs!$B$6)^((Inputs!$B$13)/12)/Inputs!$B$19,0) -> 0
A13: LTV test | B13: =B12*Inputs!$B$14 -> 0 | C13: =C12*Inputs!$B$14 -> 0 | D13: =D12*Inputs!$B$14 -> 0 | E13: =E12*Inputs!$B$14 -> 0 | F13: =F12*Inputs!$B$14 -> 0 | G13: =G12*Inputs!$B$14 -> 0 | H13: =H12*Inputs!$B$14 -> 0 | I13: =I12*Inputs!$B$14 -> 0 | ... BJ13: =BJ12*Inputs!$B$14 -> 0
A14: DSCR test | B14: =IF(B$3=Inputs!$B$13,Inputs!$B$5*(1+Inputs!$B$6)^((Inputs!$B$13)/12)/Inputs!$B$15/12/PMT(Inputs!$B$17/12,Inputs!$B$18*12,-1),0) -> 0 | C14: =IF(C$3=Inputs!$B$13,Inputs!$B$5*(1+Inputs!$B$6)^((Inputs!$B$13)/12)/Inputs!$B$15/12/PMT(Inputs!$B$17/12,Inputs!$B$18*12,-1),0) -> 0 | D14: =IF(D$3=Inputs!$B$13,Inputs!$B$5*(1+Inputs!$B$6)^((Inputs!$B$13)/12)/Inputs!$B$15/12/PMT(Inputs!$B$17/12,Inputs!$B$18*12,-1),0) -> 0 | E14: =IF(E$3=Inputs!$B$13,Inputs!$B$5*(1+Inputs!$B$6)^((Inputs!$B$13)/12)/Inputs!$B$15/12/PMT(Inputs!$B$17/12,Inputs!$B$18*12,-1),0) -> 0 | F14: =IF(F$3=Inputs!$B$13,Inputs!$B$5*(1+Inputs!$B$6)^((Inputs!$B$13)/12)/Inputs!$B$15/12/PMT(Inputs!$B$17/12,Inputs!$B$18*12,-1),0) -> 0 | G14: =IF(G$3=Inputs!$B$13,Inputs!$B$5*(1+Inputs!$B$6)^((Inputs!$B$13)/12)/Inputs!$B$15/12/PMT(Inputs!$B$17/12,Inputs!$B$18*12,-1),0) -> 0 | H14: =IF(H$3=Inputs!$B$13,Inputs!$B$5*(1+Inputs!$B$6)^((Inputs!$B$13)/12)/Inputs!$B$15/12/PMT(Inputs!$B$17/12,Inputs!$B$18*12,-1),0) -> 0 | I14: =IF(I$3=Inputs!$B$13,Inputs!$B$5*(1+Inputs!$B$6)^((Inputs!$B$13)/12)/Inputs!$B$15/12/PMT(Inputs!$B$17/12,Inputs!$B$18*12,-1),0) -> 0 | ... BJ14: =IF(BJ$3=Inputs!$B$13,Inputs!$B$5*(1+Inputs!$B$6)^((Inputs!$B$13)/12)/Inputs!$B$15/12/PMT(Inputs!$B$17/12,Inputs!$B$18*12,-1),0) -> 0
A15: Debt yield test | B15: =IF(B$3=Inputs!$B$13,Inputs!$B$5*(1+Inputs!$B$6)^((Inputs!$B$13)/12)/Inputs!$B$16,0) -> 0 | C15: =IF(C$3=Inputs!$B$13,Inputs!$B$5*(1+Inputs!$B$6)^((Inputs!$B$13)/12)/Inputs!$B$16,0) -> 0 | D15: =IF(D$3=Inputs!$B$13,Inputs!$B$5*(1+Inputs!$B$6)^((Inputs!$B$13)/12)/Inputs!$B$16,0) -> 0 | E15: =IF(E$3=Inputs!$B$13,Inputs!$B$5*(1+Inputs!$B$6)^((Inputs!$B$13)/12)/Inputs!$B$16,0) -> 0 | F15: =IF(F$3=Inputs!$B$13,Inputs!$B$5*(1+Inputs!$B$6)^((Inputs!$B$13)/12)/Inputs!$B$16,0) -> 0 | G15: =IF(G$3=Inputs!$B$13,Inputs!$B$5*(1+Inputs!$B$6)^((Inputs!$B$13)/12)/Inputs!$B$16,0) -> 0 | H15: =IF(H$3=Inputs!$B$13,Inputs!$B$5*(1+Inputs!$B$6)^((Inputs!$B$13)/12)/Inputs!$B$16,0) -> 0 | I15: =IF(I$3=Inputs!$B$13,Inputs!$B$5*(1+Inputs!$B$6)^((Inputs!$B$13)/12)/Inputs!$B$16,0) -> 0 | ... BJ15: =IF(BJ$3=Inputs!$B$13,Inputs!$B$5*(1+Inputs!$B$6)^((Inputs!$B$13)/12)/Inputs!$B$16,0) -> 0
A16: Refinance loan | B16: =IF(B$3=Inputs!$B$13,MIN(B13,B14,B15),0) -> 0 | C16: =IF(C$3=Inputs!$B$13,MIN(C13,C14,C15),0) -> 0 | D16: =IF(D$3=Inputs!$B$13,MIN(D13,D14,D15),0) -> 0 | E16: =IF(E$3=Inputs!$B$13,MIN(E13,E14,E15),0) -> 0 | F16: =IF(F$3=Inputs!$B$13,MIN(F13,F14,F15),0) -> 0 | G16: =IF(G$3=Inputs!$B$13,MIN(G13,G14,G15),0) -> 0 | H16: =IF(H$3=Inputs!$B$13,MIN(H13,H14,H15),0) -> 0 | I16: =IF(I$3=Inputs!$B$13,MIN(I13,I14,I15),0) -> 0 | ... BJ16: =IF(BJ$3=Inputs!$B$13,MIN(BJ13,BJ14,BJ15),0) -> 0
A17: Refinance payoff of bridge | B17: =IF(B$3=Inputs!$B$13,Inputs!$B$3*Inputs!$B$7,0) -> 0 | C17: =IF(C$3=Inputs!$B$13,Inputs!$B$3*Inputs!$B$7,0) -> 0 | D17: =IF(D$3=Inputs!$B$13,Inputs!$B$3*Inputs!$B$7,0) -> 0 | E17: =IF(E$3=Inputs!$B$13,Inputs!$B$3*Inputs!$B$7,0) -> 0 | F17: =IF(F$3=Inputs!$B$13,Inputs!$B$3*Inputs!$B$7,0) -> 0 | G17: =IF(G$3=Inputs!$B$13,Inputs!$B$3*Inputs!$B$7,0) -> 0 | H17: =IF(H$3=Inputs!$B$13,Inputs!$B$3*Inputs!$B$7,0) -> 0 | I17: =IF(I$3=Inputs!$B$13,Inputs!$B$3*Inputs!$B$7,0) -> 0 | ... BJ17: =IF(BJ$3=Inputs!$B$13,Inputs!$B$3*Inputs!$B$7,0) -> 0
A18: Cash-out | B18: =B16-B17 -> 0 | C18: =C16-C17 -> 0 | D18: =D16-D17 -> 0 | E18: =E16-E17 -> 0 | F18: =F16-F17 -> 0 | G18: =G16-G17 -> 0 | H18: =H16-H17 -> 0 | I18: =I16-I17 -> 0 | ... BJ18: =BJ16-BJ17 -> 0
A19: Perm balance | B19: =0 -> 0 | C19: =IF(C$3=Inputs!$B$13,C16,IF(C$3>Inputs!$B$13,B19-C21,0)) -> 0 | D19: =IF(D$3=Inputs!$B$13,D16,IF(D$3>Inputs!$B$13,C19-D21,0)) -> 0 | E19: =IF(E$3=Inputs!$B$13,E16,IF(E$3>Inputs!$B$13,D19-E21,0)) -> 0 | F19: =IF(F$3=Inputs!$B$13,F16,IF(F$3>Inputs!$B$13,E19-F21,0)) -> 0 | G19: =IF(G$3=Inputs!$B$13,G16,IF(G$3>Inputs!$B$13,F19-G21,0)) -> 0 | H19: =IF(H$3=Inputs!$B$13,H16,IF(H$3>Inputs!$B$13,G19-H21,0)) -> 0 | I19: =IF(I$3=Inputs!$B$13,I16,IF(I$3>Inputs!$B$13,H19-I21,0)) -> 0 | J19: =IF(J$3=Inputs!$B$13,J16,IF(J$3>Inputs!$B$13,I19-J21,0)) -> 0 | ... BJ19: =IF(BJ$3=Inputs!$B$13,BJ16,IF(BJ$3>Inputs!$B$13,BI19-BJ21,0)) -> 81499559
A20: Perm interest | B20: =0 -> 0 | C20: =(C$3>Inputs!$B$13)*(C$3<=Inputs!$B$20)*B19*Inputs!$B$17/12 -> 0 | D20: =(D$3>Inputs!$B$13)*(D$3<=Inputs!$B$20)*C19*Inputs!$B$17/12 -> 0 | E20: =(E$3>Inputs!$B$13)*(E$3<=Inputs!$B$20)*D19*Inputs!$B$17/12 -> 0 | F20: =(F$3>Inputs!$B$13)*(F$3<=Inputs!$B$20)*E19*Inputs!$B$17/12 -> 0 | G20: =(G$3>Inputs!$B$13)*(G$3<=Inputs!$B$20)*F19*Inputs!$B$17/12 -> 0 | H20: =(H$3>Inputs!$B$13)*(H$3<=Inputs!$B$20)*G19*Inputs!$B$17/12 -> 0 | I20: =(I$3>Inputs!$B$13)*(I$3<=Inputs!$B$20)*H19*Inputs!$B$17/12 -> 0 | J20: =(J$3>Inputs!$B$13)*(J$3<=Inputs!$B$20)*I19*Inputs!$B$17/12 -> 0 | ... BJ20: =(BJ$3>Inputs!$B$13)*(BJ$3<=Inputs!$B$20)*BI19*Inputs!$B$17/12 -> 380740.24
A21: Perm principal | B21: =0 -> 0 | C21: =IF((C$3>Inputs!$B$13)*(C$3<=Inputs!$B$20),B19*PMT(Inputs!$B$17/12,Inputs!$B$18*12,-1)-C20,0) -> 0 | D21: =IF((D$3>Inputs!$B$13)*(D$3<=Inputs!$B$20),C19*PMT(Inputs!$B$17/12,Inputs!$B$18*12,-1)-D20,0) -> 0 | E21: =IF((E$3>Inputs!$B$13)*(E$3<=Inputs!$B$20),D19*PMT(Inputs!$B$17/12,Inputs!$B$18*12,-1)-E20,0) -> 0 | F21: =IF((F$3>Inputs!$B$13)*(F$3<=Inputs!$B$20),E19*PMT(Inputs!$B$17/12,Inputs!$B$18*12,-1)-F20,0) -> 0 | G21: =IF((G$3>Inputs!$B$13)*(G$3<=Inputs!$B$20),F19*PMT(Inputs!$B$17/12,Inputs!$B$18*12,-1)-G20,0) -> 0 | H21: =IF((H$3>Inputs!$B$13)*(H$3<=Inputs!$B$20),G19*PMT(Inputs!$B$17/12,Inputs!$B$18*12,-1)-H20,0) -> 0 | I21: =IF((I$3>Inputs!$B$13)*(I$3<=Inputs!$B$20),H19*PMT(Inputs!$B$17/12,Inputs!$B$18*12,-1)-I20,0) -> 0 | J21: =IF((J$3>Inputs!$B$13)*(J$3<=Inputs!$B$20),I19*PMT(Inputs!$B$17/12,Inputs!$B$18*12,-1)-J20,0) -> 0 | ... BJ21: =IF((BJ$3>Inputs!$B$13)*(BJ$3<=Inputs!$B$20),BI19*PMT(Inputs!$B$17/12,Inputs!$B$18*12,-1)-BJ20,0) -> 87634.692
A22: Debt service | B22: =B11+B20+B21 -> 0 | C22: =C11+C20+C21 -> 434733 | D22: =D11+D20+D21 -> 434044 | E22: =E11+E20+E21 -> 433420 | F22: =F11+F20+F21 -> 432841.5 | G22: =G11+G20+G21 -> 432295.5 | H22: =H11+H20+H21 -> 431772.25 | I22: =I11+I20+I21 -> 431252.25 | ... BJ22: =BJ11+BJ20+BJ21 -> 468374.93
A23: DSCR (trailing month) | B23: =IF(B22>0,B5/B22,99) -> 99 | C23: =IF(C22>0,C5/C22,99) -> 1.2651444 | D23: =IF(D22>0,D5/D22,99) -> 1.2707905 | E23: =IF(E22>0,E5/E22,99) -> 1.2762736 | F23: =IF(F22>0,F5/F22,99) -> 1.2816484 | G23: =IF(G22>0,G5/G22,99) -> 1.2869512 | H23: =IF(H22>0,H5/H22,99) -> 1.29221 | I23: =IF(I22>0,I5/I22,99) -> 1.2974824 | ... BJ23: =IF(BJ22>0,BJ5/BJ22,99) -> 1.3906754
A24: Sale | B24: =IF(B$3=Inputs!$B$20,Inputs!$B$5*(1+Inputs!$B$6)^(B$3/12)/Inputs!$B$21*(1-Inputs!$B$22)-B19,0) -> 0 | C24: =IF(C$3=Inputs!$B$20,Inputs!$B$5*(1+Inputs!$B$6)^(C$3/12)/Inputs!$B$21*(1-Inputs!$B$22)-C19,0) -> 0 | D24: =IF(D$3=Inputs!$B$20,Inputs!$B$5*(1+Inputs!$B$6)^(D$3/12)/Inputs!$B$21*(1-Inputs!$B$22)-D19,0) -> 0 | E24: =IF(E$3=Inputs!$B$20,Inputs!$B$5*(1+Inputs!$B$6)^(E$3/12)/Inputs!$B$21*(1-Inputs!$B$22)-E19,0) -> 0 | F24: =IF(F$3=Inputs!$B$20,Inputs!$B$5*(1+Inputs!$B$6)^(F$3/12)/Inputs!$B$21*(1-Inputs!$B$22)-F19,0) -> 0 | G24: =IF(G$3=Inputs!$B$20,Inputs!$B$5*(1+Inputs!$B$6)^(G$3/12)/Inputs!$B$21*(1-Inputs!$B$22)-G19,0) -> 0 | H24: =IF(H$3=Inputs!$B$20,Inputs!$B$5*(1+Inputs!$B$6)^(H$3/12)/Inputs!$B$21*(1-Inputs!$B$22)-H19,0) -> 0 | I24: =IF(I$3=Inputs!$B$20,Inputs!$B$5*(1+Inputs!$B$6)^(I$3/12)/Inputs!$B$21*(1-Inputs!$B$22)-I19,0) -> 0 | ... BJ24: =IF(BJ$3=Inputs!$B$20,Inputs!$B$5*(1+Inputs!$B$6)^(BJ$3/12)/Inputs!$B$21*(1-Inputs!$B$22)-BJ19,0) -> 58884963
A25: Equity cash flow | B25: =-(Inputs!$B$3*(1+Inputs!$B$4)-Inputs!$B$3*Inputs!$B$7)-B10 -> -44268000 | C25: =C5-C22+C18+C24 -> 115267 | D25: =D5-D22+D18+D24 -> 117534.99 | E25: =E5-E22+E18+E24 -> 119742.52 | F25: =F5-F22+F18+F24 -> 121909.1 | G25: =G5-G22+G18+G24 -> 124047.73 | H25: =H5-H22+H18+H24 -> 126168.18 | I25: =I5-I22+I18+I24 -> 128289.97 | J25: =J5-J22+J18+J24 -> 130419.61 | ... BJ25: =BJ5-BJ22+BJ18+BJ24 -> 59067945

Sheet Returns
A3: Levered IRR | B3: =(1+IRR('Cash Flow'!B25:BJ25,0.01))^12-1 -> 0.12125967
A4: Equity multiple | B4: =SUMIF('Cash Flow'!B25:BJ25,">0")/-SUMIF('Cash Flow'!B25:BJ25,"<0") -> 1.670232
A5: Refinance loan ($) | B5: =SUM('Cash Flow'!B16:BJ16) -> 83629005
A6: Cash-out at refinance ($) | B6: =SUM('Cash Flow'!B18:BJ18) -> 5629005.4
A7: Refinance sized by | B7: =IF(B5=SUM('Cash Flow'!B13:BJ13),"LTV",IF(B5=SUM('Cash Flow'!B14:BJ14),"DSCR","Debt yield")) -> LTV
A8: Hedge result ($) | B8: =SUM('Cash Flow'!B9:BJ9)-SUM('Cash Flow'!B8:BJ8)-SUM('Cash Flow'!B10:BJ10) -> -175467.5
A9: Minimum DSCR | B9: =MIN('Cash Flow'!C23:BJ23) -> 1.2651444
A10: Net profit ($) | B10: =SUM('Cash Flow'!B25:BJ25) -> 29669832
