Workbook

Sheet Inputs
A1: RIVERSIDE SCHOOLS PPP – AVAILABILITY PROJECT FINANCE (GBP)
A3: Case (1 Sponsor, 2 Lenders) | B3: 1
A4: Financial close | B4: 46203
A5: Construction cost (£) | B5: 148000000
A6: Construction (half-years) | B6: 5
A7: Concession (half-years from completion) | B7: 50
A8: Unitary payment a year (£) | B8: 21500000
A9: RPI indexation | B9: 0.03
A10: Operating cost a year (£) | B10: 4200000
A11: Target DSCR (sculpting) | B11: 1.3
A12: Senior all-in rate | B12: 0.052
A13: Debt tenor (half-years) | B13: 40
A14: DSRA (half-years of debt service) | B14: 1
... A20: Operating cost uplift · Lenders case | B20: 0.1

Sheet Lifecycle
A1: Half-year | B1: Lifecycle cost (£, real)
A2: 1 | B2: 0
A3: 2 | B3: 0
A4: 3 | B4: 0
A5: 4 | B5: 900000
A6: 5 | B6: 0
A7: 6 | B7: 0
A8: 7 | B8: 0
A9: 8 | B9: 900000
A10: 9 | B10: 0
A11: 10 | B11: 2600000
A12: 11 | B12: 0
A13: 12 | B13: 900000
... A61: 60 | B61: 2600000

Sheet Cash Flow
A3: Half-year | B3: 0 | C3: 1 | D3: 2 | E3: 3 | F3: 4 | G3: 5 | H3: 6 | I3: 7 | J3: 8 | K3: 9 | L3: 10 | M3: 11 | N3: 12 | O3: 13 | P3: 14 | Q3: 15 | R3: 16 | S3: 17 | T3: 18 | U3: 19 | V3: 20 | W3: 21 | X3: 22 | Y3: 23 | Z3: 24 | AA3: 25 | AB3: 26 | AC3: 27 | AD3: 28 | AE3: 29 | AF3: 30 | AG3: 31 | AH3: 32 | AI3: 33 | AJ3: 34 | AK3: 35 | AL3: 36 | AM3: 37 | AN3: 38 | AO3: 39 | AP3: 40 | AQ3: 41 | AR3: 42 | AS3: 43 | AT3: 44 | AU3: 45 | AV3: 46 | AW3: 47 | AX3: 48 | AY3: 49 | AZ3: 50 | BA3: 51 | BB3: 52 | BC3: 53 | BD3: 54 | BE3: 55
A4: Date | B4: =EDATE(Inputs!$B$4,6*B$3) -> 46203 | C4: =EDATE(Inputs!$B$4,6*C$3) -> 46386 | D4: =EDATE(Inputs!$B$4,6*D$3) -> 46568 | E4: =EDATE(Inputs!$B$4,6*E$3) -> 46751 | F4: =EDATE(Inputs!$B$4,6*F$3) -> 46934 | G4: =EDATE(Inputs!$B$4,6*G$3) -> 47117 | H4: =EDATE(Inputs!$B$4,6*H$3) -> 47299 | I4: =EDATE(Inputs!$B$4,6*I$3) -> 47482 | ... BE4: =EDATE(Inputs!$B$4,6*BE$3) -> 56248
A5: Construction | B5: =IF(AND(B$3>=1,B$3<=Inputs!$B$6),Inputs!$B$5/Inputs!$B$6,0) -> 0 | C5: =IF(AND(C$3>=1,C$3<=Inputs!$B$6),Inputs!$B$5/Inputs!$B$6,0) -> 29600000 | D5: =IF(AND(D$3>=1,D$3<=Inputs!$B$6),Inputs!$B$5/Inputs!$B$6,0) -> 29600000 | E5: =IF(AND(E$3>=1,E$3<=Inputs!$B$6),Inputs!$B$5/Inputs!$B$6,0) -> 29600000 | F5: =IF(AND(F$3>=1,F$3<=Inputs!$B$6),Inputs!$B$5/Inputs!$B$6,0) -> 29600000 | G5: =IF(AND(G$3>=1,G$3<=Inputs!$B$6),Inputs!$B$5/Inputs!$B$6,0) -> 29600000 | H5: =IF(AND(H$3>=1,H$3<=Inputs!$B$6),Inputs!$B$5/Inputs!$B$6,0) -> 0 | I5: =IF(AND(I$3>=1,I$3<=Inputs!$B$6),Inputs!$B$5/Inputs!$B$6,0) -> 0 | ... BE5: =IF(AND(BE$3>=1,BE$3<=Inputs!$B$6),Inputs!$B$5/Inputs!$B$6,0) -> 0
A6: Operating | B6: =IF(AND(B$3>Inputs!$B$6,B$3<=Inputs!$B$6+Inputs!$B$7),1,0) -> 0 | C6: =IF(AND(C$3>Inputs!$B$6,C$3<=Inputs!$B$6+Inputs!$B$7),1,0) -> 0 | D6: =IF(AND(D$3>Inputs!$B$6,D$3<=Inputs!$B$6+Inputs!$B$7),1,0) -> 0 | E6: =IF(AND(E$3>Inputs!$B$6,E$3<=Inputs!$B$6+Inputs!$B$7),1,0) -> 0 | F6: =IF(AND(F$3>Inputs!$B$6,F$3<=Inputs!$B$6+Inputs!$B$7),1,0) -> 0 | G6: =IF(AND(G$3>Inputs!$B$6,G$3<=Inputs!$B$6+Inputs!$B$7),1,0) -> 0 | H6: =IF(AND(H$3>Inputs!$B$6,H$3<=Inputs!$B$6+Inputs!$B$7),1,0) -> 1 | I6: =IF(AND(I$3>Inputs!$B$6,I$3<=Inputs!$B$6+Inputs!$B$7),1,0) -> 1 | ... BE6: =IF(AND(BE$3>Inputs!$B$6,BE$3<=Inputs!$B$6+Inputs!$B$7),1,0) -> 1
A7: Unitary payment | B7: =B6*Inputs!$B$8/2*(1+Inputs!$B$9)^INT((B$3-Inputs!$B$6-1)/2) -> 0 | C7: =C6*Inputs!$B$8/2*(1+Inputs!$B$9)^INT((C$3-Inputs!$B$6-1)/2) -> 0 | D7: =D6*Inputs!$B$8/2*(1+Inputs!$B$9)^INT((D$3-Inputs!$B$6-1)/2) -> 0 | E7: =E6*Inputs!$B$8/2*(1+Inputs!$B$9)^INT((E$3-Inputs!$B$6-1)/2) -> 0 | F7: =F6*Inputs!$B$8/2*(1+Inputs!$B$9)^INT((F$3-Inputs!$B$6-1)/2) -> 0 | G7: =G6*Inputs!$B$8/2*(1+Inputs!$B$9)^INT((G$3-Inputs!$B$6-1)/2) -> 0 | H7: =H6*Inputs!$B$8/2*(1+Inputs!$B$9)^INT((H$3-Inputs!$B$6-1)/2) -> 10750000 | I7: =I6*Inputs!$B$8/2*(1+Inputs!$B$9)^INT((I$3-Inputs!$B$6-1)/2) -> 10750000 | ... BE7: =BE6*Inputs!$B$8/2*(1+Inputs!$B$9)^INT((BE$3-Inputs!$B$6-1)/2) -> 21852537
A8: Deductions | B8: =B7*IF(Inputs!$B$3=1,Inputs!$B$18,Inputs!$B$19) -> 0 | C8: =C7*IF(Inputs!$B$3=1,Inputs!$B$18,Inputs!$B$19) -> 0 | D8: =D7*IF(Inputs!$B$3=1,Inputs!$B$18,Inputs!$B$19) -> 0 | E8: =E7*IF(Inputs!$B$3=1,Inputs!$B$18,Inputs!$B$19) -> 0 | F8: =F7*IF(Inputs!$B$3=1,Inputs!$B$18,Inputs!$B$19) -> 0 | G8: =G7*IF(Inputs!$B$3=1,Inputs!$B$18,Inputs!$B$19) -> 0 | H8: =H7*IF(Inputs!$B$3=1,Inputs!$B$18,Inputs!$B$19) -> 53750 | I8: =I7*IF(Inputs!$B$3=1,Inputs!$B$18,Inputs!$B$19) -> 53750 | ... BE8: =BE7*IF(Inputs!$B$3=1,Inputs!$B$18,Inputs!$B$19) -> 109262.68
A9: Operating cost | B9: =B6*Inputs!$B$10*IF(Inputs!$B$3=1,1,1+Inputs!$B$20)/2*(1+Inputs!$B$9)^INT((B$3-Inputs!$B$6-1)/2) -> 0 | C9: =C6*Inputs!$B$10*IF(Inputs!$B$3=1,1,1+Inputs!$B$20)/2*(1+Inputs!$B$9)^INT((C$3-Inputs!$B$6-1)/2) -> 0 | D9: =D6*Inputs!$B$10*IF(Inputs!$B$3=1,1,1+Inputs!$B$20)/2*(1+Inputs!$B$9)^INT((D$3-Inputs!$B$6-1)/2) -> 0 | E9: =E6*Inputs!$B$10*IF(Inputs!$B$3=1,1,1+Inputs!$B$20)/2*(1+Inputs!$B$9)^INT((E$3-Inputs!$B$6-1)/2) -> 0 | F9: =F6*Inputs!$B$10*IF(Inputs!$B$3=1,1,1+Inputs!$B$20)/2*(1+Inputs!$B$9)^INT((F$3-Inputs!$B$6-1)/2) -> 0 | G9: =G6*Inputs!$B$10*IF(Inputs!$B$3=1,1,1+Inputs!$B$20)/2*(1+Inputs!$B$9)^INT((G$3-Inputs!$B$6-1)/2) -> 0 | H9: =H6*Inputs!$B$10*IF(Inputs!$B$3=1,1,1+Inputs!$B$20)/2*(1+Inputs!$B$9)^INT((H$3-Inputs!$B$6-1)/2) -> 2100000 | I9: =I6*Inputs!$B$10*IF(Inputs!$B$3=1,1,1+Inputs!$B$20)/2*(1+Inputs!$B$9)^INT((I$3-Inputs!$B$6-1)/2) -> 2100000 | ... BE9: =BE6*Inputs!$B$10*IF(Inputs!$B$3=1,1,1+Inputs!$B$20)/2*(1+Inputs!$B$9)^INT((BE$3-Inputs!$B$6-1)/2) -> 4268867.6
A10: Lifecycle | B10: =B6*IFERROR(INDEX(Lifecycle!$B$2:$B$61,B$3-Inputs!$B$6),0)*(1+Inputs!$B$9)^INT((B$3-Inputs!$B$6-1)/2) -> 0 | C10: =C6*IFERROR(INDEX(Lifecycle!$B$2:$B$61,C$3-Inputs!$B$6),0)*(1+Inputs!$B$9)^INT((C$3-Inputs!$B$6-1)/2) -> 0 | D10: =D6*IFERROR(INDEX(Lifecycle!$B$2:$B$61,D$3-Inputs!$B$6),0)*(1+Inputs!$B$9)^INT((D$3-Inputs!$B$6-1)/2) -> 0 | E10: =E6*IFERROR(INDEX(Lifecycle!$B$2:$B$61,E$3-Inputs!$B$6),0)*(1+Inputs!$B$9)^INT((E$3-Inputs!$B$6-1)/2) -> 0 | F10: =F6*IFERROR(INDEX(Lifecycle!$B$2:$B$61,F$3-Inputs!$B$6),0)*(1+Inputs!$B$9)^INT((F$3-Inputs!$B$6-1)/2) -> 0 | G10: =G6*IFERROR(INDEX(Lifecycle!$B$2:$B$61,G$3-Inputs!$B$6),0)*(1+Inputs!$B$9)^INT((G$3-Inputs!$B$6-1)/2) -> 0 | H10: =H6*IFERROR(INDEX(Lifecycle!$B$2:$B$61,H$3-Inputs!$B$6),0)*(1+Inputs!$B$9)^INT((H$3-Inputs!$B$6-1)/2) -> 0 | I10: =I6*IFERROR(INDEX(Lifecycle!$B$2:$B$61,I$3-Inputs!$B$6),0)*(1+Inputs!$B$9)^INT((I$3-Inputs!$B$6-1)/2) -> 0 | ... BE10: =BE6*IFERROR(INDEX(Lifecycle!$B$2:$B$61,BE$3-Inputs!$B$6),0)*(1+Inputs!$B$9)^INT((BE$3-Inputs!$B$6-1)/2) -> 5285264.7
A11: MRA deposit | B11: =B6*SUMPRODUCT((Lifecycle!$A$2:$A$61>B$3-Inputs!$B$6)*(Lifecycle!$A$2:$A$61<=B$3-Inputs!$B$6+Inputs!$B$15)*Lifecycle!$B$2:$B$61)*(1+Inputs!$B$9)^INT((B$3-Inputs!$B$6-1)/2)/Inputs!$B$15 -> 0 | C11: =C6*SUMPRODUCT((Lifecycle!$A$2:$A$61>C$3-Inputs!$B$6)*(Lifecycle!$A$2:$A$61<=C$3-Inputs!$B$6+Inputs!$B$15)*Lifecycle!$B$2:$B$61)*(1+Inputs!$B$9)^INT((C$3-Inputs!$B$6-1)/2)/Inputs!$B$15 -> 0 | D11: =D6*SUMPRODUCT((Lifecycle!$A$2:$A$61>D$3-Inputs!$B$6)*(Lifecycle!$A$2:$A$61<=D$3-Inputs!$B$6+Inputs!$B$15)*Lifecycle!$B$2:$B$61)*(1+Inputs!$B$9)^INT((D$3-Inputs!$B$6-1)/2)/Inputs!$B$15 -> 0 | E11: =E6*SUMPRODUCT((Lifecycle!$A$2:$A$61>E$3-Inputs!$B$6)*(Lifecycle!$A$2:$A$61<=E$3-Inputs!$B$6+Inputs!$B$15)*Lifecycle!$B$2:$B$61)*(1+Inputs!$B$9)^INT((E$3-Inputs!$B$6-1)/2)/Inputs!$B$15 -> 0 | F11: =F6*SUMPRODUCT((Lifecycle!$A$2:$A$61>F$3-Inputs!$B$6)*(Lifecycle!$A$2:$A$61<=F$3-Inputs!$B$6+Inputs!$B$15)*Lifecycle!$B$2:$B$61)*(1+Inputs!$B$9)^INT((F$3-Inputs!$B$6-1)/2)/Inputs!$B$15 -> 0 | G11: =G6*SUMPRODUCT((Lifecycle!$A$2:$A$61>G$3-Inputs!$B$6)*(Lifecycle!$A$2:$A$61<=G$3-Inputs!$B$6+Inputs!$B$15)*Lifecycle!$B$2:$B$61)*(1+Inputs!$B$9)^INT((G$3-Inputs!$B$6-1)/2)/Inputs!$B$15 -> 0 | H11: =H6*SUMPRODUCT((Lifecycle!$A$2:$A$61>H$3-Inputs!$B$6)*(Lifecycle!$A$2:$A$61<=H$3-Inputs!$B$6+Inputs!$B$15)*Lifecycle!$B$2:$B$61)*(1+Inputs!$B$9)^INT((H$3-Inputs!$B$6-1)/2)/Inputs!$B$15 -> 300000 | I11: =I6*SUMPRODUCT((Lifecycle!$A$2:$A$61>I$3-Inputs!$B$6)*(Lifecycle!$A$2:$A$61<=I$3-Inputs!$B$6+Inputs!$B$15)*Lifecycle!$B$2:$B$61)*(1+Inputs!$B$9)^INT((I$3-Inputs!$B$6-1)/2)/Inputs!$B$15 -> 300000 | ... BE11: =BE6*SUMPRODUCT((Lifecycle!$A$2:$A$61>BE$3-Inputs!$B$6)*(Lifecycle!$A$2:$A$61<=BE$3-Inputs!$B$6+Inputs!$B$15)*Lifecycle!$B$2:$B$61)*(1+Inputs!$B$9)^INT((BE$3-Inputs!$B$6-1)/2)/Inputs!$B$15 -> 609838.23
A12: MRA release | B12: =B10 -> 0 | C12: =C10 -> 0 | D12: =D10 -> 0 | E12: =E10 -> 0 | F12: =F10 -> 0 | G12: =G10 -> 0 | H12: =H10 -> 0 | I12: =I10 -> 0 | ... BE12: =BE10 -> 5285264.7
A13: CFADS | B13: =B7-B8-B9-B11 -> 0 | C13: =C7-C8-C9-C11 -> 0 | D13: =D7-D8-D9-D11 -> 0 | E13: =E7-E8-E9-E11 -> 0 | F13: =F7-F8-F9-F11 -> 0 | G13: =G7-G8-G9-G11 -> 0 | H13: =H7-H8-H9-H11 -> 8296250 | I13: =I7-I8-I9-I11 -> 8296250 | ... BE13: =BE7-BE8-BE9-BE11 -> 16864568
A14: Debt service (sculpted) | B14: =IF(AND(B$3>Inputs!$B$6,B$3<=Inputs!$B$6+Inputs!$B$13),B13/Inputs!$B$11,0) -> 0 | C14: =IF(AND(C$3>Inputs!$B$6,C$3<=Inputs!$B$6+Inputs!$B$13),C13/Inputs!$B$11,0) -> 0 | D14: =IF(AND(D$3>Inputs!$B$6,D$3<=Inputs!$B$6+Inputs!$B$13),D13/Inputs!$B$11,0) -> 0 | E14: =IF(AND(E$3>Inputs!$B$6,E$3<=Inputs!$B$6+Inputs!$B$13),E13/Inputs!$B$11,0) -> 0 | F14: =IF(AND(F$3>Inputs!$B$6,F$3<=Inputs!$B$6+Inputs!$B$13),F13/Inputs!$B$11,0) -> 0 | G14: =IF(AND(G$3>Inputs!$B$6,G$3<=Inputs!$B$6+Inputs!$B$13),G13/Inputs!$B$11,0) -> 0 | H14: =IF(AND(H$3>Inputs!$B$6,H$3<=Inputs!$B$6+Inputs!$B$13),H13/Inputs!$B$11,0) -> 6381730.8 | I14: =IF(AND(I$3>Inputs!$B$6,I$3<=Inputs!$B$6+Inputs!$B$13),I13/Inputs!$B$11,0) -> 6381730.8 | ... BE14: =IF(AND(BE$3>Inputs!$B$6,BE$3<=Inputs!$B$6+Inputs!$B$13),BE13/Inputs!$B$11,0) -> 0
A15: Debt balance | B15: =0 -> 0 | C15: =IF(C$3<=Inputs!$B$6,SUM($B$5:C5)*0.85,MAX(0,B15-C17)) -> 25160000 | D15: =IF(D$3<=Inputs!$B$6,SUM($B$5:D5)*0.85,MAX(0,C15-D17)) -> 50320000 | E15: =IF(E$3<=Inputs!$B$6,SUM($B$5:E5)*0.85,MAX(0,D15-E17)) -> 75480000 | F15: =IF(F$3<=Inputs!$B$6,SUM($B$5:F5)*0.85,MAX(0,E15-F17)) -> 100640000 | G15: =IF(G$3<=Inputs!$B$6,SUM($B$5:G5)*0.85,MAX(0,F15-G17)) -> 125800000 | H15: =IF(H$3<=Inputs!$B$6,SUM($B$5:H5)*0.85,MAX(0,G15-H17)) -> 1.2268907e+08 | I15: =IF(I$3<=Inputs!$B$6,SUM($B$5:I5)*0.85,MAX(0,H15-I17)) -> 1.1949725e+08 | J15: =IF(J$3<=Inputs!$B$6,SUM($B$5:J5)*0.85,MAX(0,I15-J17)) -> 1.16031e+08 | ... BE15: =IF(BE$3<=Inputs!$B$6,SUM($B$5:BE5)*0.85,MAX(0,BD15-BE17)) -> 0
A16: Interest | B16: =0 -> 0 | C16: =IF(C$3>Inputs!$B$6,B15*Inputs!$B$12/2,0) -> 0 | D16: =IF(D$3>Inputs!$B$6,C15*Inputs!$B$12/2,0) -> 0 | E16: =IF(E$3>Inputs!$B$6,D15*Inputs!$B$12/2,0) -> 0 | F16: =IF(F$3>Inputs!$B$6,E15*Inputs!$B$12/2,0) -> 0 | G16: =IF(G$3>Inputs!$B$6,F15*Inputs!$B$12/2,0) -> 0 | H16: =IF(H$3>Inputs!$B$6,G15*Inputs!$B$12/2,0) -> 3270800 | I16: =IF(I$3>Inputs!$B$6,H15*Inputs!$B$12/2,0) -> 3189915.8 | J16: =IF(J$3>Inputs!$B$6,I15*Inputs!$B$12/2,0) -> 3106928.6 | ... BE16: =IF(BE$3>Inputs!$B$6,BD15*Inputs!$B$12/2,0) -> 0
A17: Principal | B17: =0 -> 0 | C17: =IF(AND(C$3>Inputs!$B$6,C$3<=Inputs!$B$6+Inputs!$B$13),MIN(B15,C14-C16),0) -> 0 | D17: =IF(AND(D$3>Inputs!$B$6,D$3<=Inputs!$B$6+Inputs!$B$13),MIN(C15,D14-D16),0) -> 0 | E17: =IF(AND(E$3>Inputs!$B$6,E$3<=Inputs!$B$6+Inputs!$B$13),MIN(D15,E14-E16),0) -> 0 | F17: =IF(AND(F$3>Inputs!$B$6,F$3<=Inputs!$B$6+Inputs!$B$13),MIN(E15,F14-F16),0) -> 0 | G17: =IF(AND(G$3>Inputs!$B$6,G$3<=Inputs!$B$6+Inputs!$B$13),MIN(F15,G14-G16),0) -> 0 | H17: =IF(AND(H$3>Inputs!$B$6,H$3<=Inputs!$B$6+Inputs!$B$13),MIN(G15,H14-H16),0) -> 3110930.8 | I17: =IF(AND(I$3>Inputs!$B$6,I$3<=Inputs!$B$6+Inputs!$B$13),MIN(H15,I14-I16),0) -> 3191815 | J17: =IF(AND(J$3>Inputs!$B$6,J$3<=Inputs!$B$6+Inputs!$B$13),MIN(I15,J14-J16),0) -> 3466254.1 | ... BE17: =IF(AND(BE$3>Inputs!$B$6,BE$3<=Inputs!$B$6+Inputs!$B$13),MIN(BD15,BE14-BE16),0) -> 0
A18: DSRA balance | B18: =IF(AND(B$3>Inputs!$B$6,B$3<=Inputs!$B$6+Inputs!$B$13),C14*Inputs!$B$14,0) -> 0 | C18: =IF(AND(C$3>Inputs!$B$6,C$3<=Inputs!$B$6+Inputs!$B$13),D14*Inputs!$B$14,0) -> 0 | D18: =IF(AND(D$3>Inputs!$B$6,D$3<=Inputs!$B$6+Inputs!$B$13),E14*Inputs!$B$14,0) -> 0 | E18: =IF(AND(E$3>Inputs!$B$6,E$3<=Inputs!$B$6+Inputs!$B$13),F14*Inputs!$B$14,0) -> 0 | F18: =IF(AND(F$3>Inputs!$B$6,F$3<=Inputs!$B$6+Inputs!$B$13),G14*Inputs!$B$14,0) -> 0 | G18: =IF(AND(G$3>Inputs!$B$6,G$3<=Inputs!$B$6+Inputs!$B$13),H14*Inputs!$B$14,0) -> 0 | H18: =IF(AND(H$3>Inputs!$B$6,H$3<=Inputs!$B$6+Inputs!$B$13),I14*Inputs!$B$14,0) -> 6381730.8 | I18: =IF(AND(I$3>Inputs!$B$6,I$3<=Inputs!$B$6+Inputs!$B$13),J14*Inputs!$B$14,0) -> 6573182.7 | ... BD18: =IF(AND(BD$3>Inputs!$B$6,BD$3<=Inputs!$B$6+Inputs!$B$13),BE14*Inputs!$B$14,0) -> 0 | BE18: =IF(AND(BE$3>Inputs!$B$6,BE$3<=Inputs!$B$6+Inputs!$B$13),BE14*Inputs!$B$14,0) -> 0
A19: DSRA movement | B19: =B18 -> 0 | C19: =C18-B18 -> 0 | D19: =D18-C18 -> 0 | E19: =E18-D18 -> 0 | F19: =F18-E18 -> 0 | G19: =G18-F18 -> 0 | H19: =H18-G18 -> 6381730.8 | I19: =I18-H18 -> 191451.92 | J19: =J18-I18 -> 237692.31 | ... BE19: =BE18-BD18 -> 0
A20: Capital allowances pool | B20: =0 -> 0 | C20: =IF(C$3<=Inputs!$B$6,SUM($B$5:C5),B20-C21) -> 29600000 | D20: =IF(D$3<=Inputs!$B$6,SUM($B$5:D5),C20-D21) -> 59200000 | E20: =IF(E$3<=Inputs!$B$6,SUM($B$5:E5),D20-E21) -> 88800000 | F20: =IF(F$3<=Inputs!$B$6,SUM($B$5:F5),E20-F21) -> 118400000 | G20: =IF(G$3<=Inputs!$B$6,SUM($B$5:G5),F20-G21) -> 148000000 | H20: =IF(H$3<=Inputs!$B$6,SUM($B$5:H5),G20-H21) -> 143560000 | I20: =IF(I$3<=Inputs!$B$6,SUM($B$5:I5),H20-I21) -> 139253200 | J20: =IF(J$3<=Inputs!$B$6,SUM($B$5:J5),I20-J21) -> 135075604 | ... BE20: =IF(BE$3<=Inputs!$B$6,SUM($B$5:BE5),BD20-BE21) -> 32273676
A21: Capital allowances | B21: =0 -> 0 | C21: =IF(C$3>Inputs!$B$6,B20*Inputs!$B$16/2,0) -> 0 | D21: =IF(D$3>Inputs!$B$6,C20*Inputs!$B$16/2,0) -> 0 | E21: =IF(E$3>Inputs!$B$6,D20*Inputs!$B$16/2,0) -> 0 | F21: =IF(F$3>Inputs!$B$6,E20*Inputs!$B$16/2,0) -> 0 | G21: =IF(G$3>Inputs!$B$6,F20*Inputs!$B$16/2,0) -> 0 | H21: =IF(H$3>Inputs!$B$6,G20*Inputs!$B$16/2,0) -> 4440000 | I21: =IF(I$3>Inputs!$B$6,H20*Inputs!$B$16/2,0) -> 4306800 | J21: =IF(J$3>Inputs!$B$6,I20*Inputs!$B$16/2,0) -> 4177596 | ... BE21: =IF(BE$3>Inputs!$B$6,BD20*Inputs!$B$16/2,0) -> 998154.91
A22: Taxable profit | B22: =B13-B16-B21 -> 0 | C22: =C13-C16-C21 -> 0 | D22: =D13-D16-D21 -> 0 | E22: =E13-E16-E21 -> 0 | F22: =F13-F16-F21 -> 0 | G22: =G13-G16-G21 -> 0 | H22: =H13-H16-H21 -> 585450 | I22: =I13-I16-I21 -> 799534.2 | ... BE22: =BE13-BE16-BE21 -> 15866413
A23: Tax | B23: =MAX(0,B22)*Inputs!$B$17 -> 0 | C23: =MAX(0,C22)*Inputs!$B$17 -> 0 | D23: =MAX(0,D22)*Inputs!$B$17 -> 0 | E23: =MAX(0,E22)*Inputs!$B$17 -> 0 | F23: =MAX(0,F22)*Inputs!$B$17 -> 0 | G23: =MAX(0,G22)*Inputs!$B$17 -> 0 | H23: =MAX(0,H22)*Inputs!$B$17 -> 146362.5 | I23: =MAX(0,I22)*Inputs!$B$17 -> 199883.55 | ... BE23: =MAX(0,BE22)*Inputs!$B$17 -> 3966603.3
A24: Equity cash flow | B24: =-B5*0.15 -> 0 | C24: =IF(AND(C$3>=1,C$3<=Inputs!$B$6),-C5*0.15,C13-C14-C19-C23+IF(C$3=Inputs!$B$6+Inputs!$B$7,SUM($B$11:C11)-SUM($B$12:C12),0)) -> -4440000 | D24: =IF(AND(D$3>=1,D$3<=Inputs!$B$6),-D5*0.15,D13-D14-D19-D23+IF(D$3=Inputs!$B$6+Inputs!$B$7,SUM($B$11:D11)-SUM($B$12:D12),0)) -> -4440000 | E24: =IF(AND(E$3>=1,E$3<=Inputs!$B$6),-E5*0.15,E13-E14-E19-E23+IF(E$3=Inputs!$B$6+Inputs!$B$7,SUM($B$11:E11)-SUM($B$12:E12),0)) -> -4440000 | F24: =IF(AND(F$3>=1,F$3<=Inputs!$B$6),-F5*0.15,F13-F14-F19-F23+IF(F$3=Inputs!$B$6+Inputs!$B$7,SUM($B$11:F11)-SUM($B$12:F12),0)) -> -4440000 | G24: =IF(AND(G$3>=1,G$3<=Inputs!$B$6),-G5*0.15,G13-G14-G19-G23+IF(G$3=Inputs!$B$6+Inputs!$B$7,SUM($B$11:G11)-SUM($B$12:G12),0)) -> -4440000 | H24: =IF(AND(H$3>=1,H$3<=Inputs!$B$6),-H5*0.15,H13-H14-H19-H23+IF(H$3=Inputs!$B$6+Inputs!$B$7,SUM($B$11:H11)-SUM($B$12:H12),0)) -> -4613574 | I24: =IF(AND(I$3>=1,I$3<=Inputs!$B$6),-I5*0.15,I13-I14-I19-I23+IF(I$3=Inputs!$B$6+Inputs!$B$7,SUM($B$11:I11)-SUM($B$12:I12),0)) -> 1523183.8 | J24: =IF(AND(J$3>=1,J$3<=Inputs!$B$6),-J5*0.15,J13-J14-J19-J23+IF(J$3=Inputs!$B$6+Inputs!$B$7,SUM($B$11:J11)-SUM($B$12:J12),0)) -> 1419109.3 | ... BE24: =IF(AND(BE$3>=1,BE$3<=Inputs!$B$6),-BE5*0.15,BE13-BE14-BE19-BE23+IF(BE$3=Inputs!$B$6+Inputs!$B$7,SUM($B$11:BE11)-SUM($B$12:BE12),0)) -> 13475617
A25: DSCR | B25: =IF(B14>0,B13/B14,0) -> 0 | C25: =IF(C14>0,C13/C14,0) -> 0 | D25: =IF(D14>0,D13/D14,0) -> 0 | E25: =IF(E14>0,E13/E14,0) -> 0 | F25: =IF(F14>0,F13/F14,0) -> 0 | G25: =IF(G14>0,G13/G14,0) -> 0 | H25: =IF(H14>0,H13/H14,0) -> 1.3 | I25: =IF(I14>0,I13/I14,0) -> 1.3 | ... BE25: =IF(BE14>0,BE13/BE14,0) -> 0
A26: PV of CFADS remaining | B26: =0 -> 0 | C26: =IF(AND(C$3>Inputs!$B$6,C$3<=Inputs!$B$6+Inputs!$B$13),SUMPRODUCT((C$3:$BE$3>C$3-1)*(C$3:$BE$3<=Inputs!$B$6+Inputs!$B$13)*C$13:$BE$13/(1+Inputs!$B$12/2)^(C$3:$BE$3-C$3+1)),0) -> 0 | D26: =IF(AND(D$3>Inputs!$B$6,D$3<=Inputs!$B$6+Inputs!$B$13),SUMPRODUCT((D$3:$BE$3>D$3-1)*(D$3:$BE$3<=Inputs!$B$6+Inputs!$B$13)*D$13:$BE$13/(1+Inputs!$B$12/2)^(D$3:$BE$3-D$3+1)),0) -> 0 | E26: =IF(AND(E$3>Inputs!$B$6,E$3<=Inputs!$B$6+Inputs!$B$13),SUMPRODUCT((E$3:$BE$3>E$3-1)*(E$3:$BE$3<=Inputs!$B$6+Inputs!$B$13)*E$13:$BE$13/(1+Inputs!$B$12/2)^(E$3:$BE$3-E$3+1)),0) -> 0 | F26: =IF(AND(F$3>Inputs!$B$6,F$3<=Inputs!$B$6+Inputs!$B$13),SUMPRODUCT((F$3:$BE$3>F$3-1)*(F$3:$BE$3<=Inputs!$B$6+Inputs!$B$13)*F$13:$BE$13/(1+Inputs!$B$12/2)^(F$3:$BE$3-F$3+1)),0) -> 0 | G26: =IF(AND(G$3>Inputs!$B$6,G$3<=Inputs!$B$6+Inputs!$B$13),SUMPRODUCT((G$3:$BE$3>G$3-1)*(G$3:$BE$3<=Inputs!$B$6+Inputs!$B$13)*G$13:$BE$13/(1+Inputs!$B$12/2)^(G$3:$BE$3-G$3+1)),0) -> 0 | H26: =IF(AND(H$3>Inputs!$B$6,H$3<=Inputs!$B$6+Inputs!$B$13),SUMPRODUCT((H$3:$BE$3>H$3-1)*(H$3:$BE$3<=Inputs!$B$6+Inputs!$B$13)*H$13:$BE$13/(1+Inputs!$B$12/2)^(H$3:$BE$3-H$3+1)),0) -> 2.5733673e+08 | I26: =IF(AND(I$3>Inputs!$B$6,I$3<=Inputs!$B$6+Inputs!$B$13),SUMPRODUCT((I$3:$BE$3>I$3-1)*(I$3:$BE$3<=Inputs!$B$6+Inputs!$B$13)*I$13:$BE$13/(1+Inputs!$B$12/2)^(I$3:$BE$3-I$3+1)),0) -> 2.5573124e+08 | J26: =IF(AND(J$3>Inputs!$B$6,J$3<=Inputs!$B$6+Inputs!$B$13),SUMPRODUCT((J$3:$BE$3>J$3-1)*(J$3:$BE$3<=Inputs!$B$6+Inputs!$B$13)*J$13:$BE$13/(1+Inputs!$B$12/2)^(J$3:$BE$3-J$3+1)),0) -> 2.54084e+08 | ... BE26: =IF(AND(BE$3>Inputs!$B$6,BE$3<=Inputs!$B$6+Inputs!$B$13),SUMPRODUCT((BE$3:$BE$3>BE$3-1)*(BE$3:$BE$3<=Inputs!$B$6+Inputs!$B$13)*BE$13:$BE$13/(1+Inputs!$B$12/2)^(BE$3:$BE$3-BE$3+1)),0) -> 0
A27: LLCR | B27: =0 -> 0 | C27: =IF(AND(AND(C$3>Inputs!$B$6,C$3<=Inputs!$B$6+Inputs!$B$13),B15>0),C26/B15,0) -> 0 | D27: =IF(AND(AND(D$3>Inputs!$B$6,D$3<=Inputs!$B$6+Inputs!$B$13),C15>0),D26/C15,0) -> 0 | E27: =IF(AND(AND(E$3>Inputs!$B$6,E$3<=Inputs!$B$6+Inputs!$B$13),D15>0),E26/D15,0) -> 0 | F27: =IF(AND(AND(F$3>Inputs!$B$6,F$3<=Inputs!$B$6+Inputs!$B$13),E15>0),F26/E15,0) -> 0 | G27: =IF(AND(AND(G$3>Inputs!$B$6,G$3<=Inputs!$B$6+Inputs!$B$13),F15>0),G26/F15,0) -> 0 | H27: =IF(AND(AND(H$3>Inputs!$B$6,H$3<=Inputs!$B$6+Inputs!$B$13),G15>0),H26/G15,0) -> 2.045602 | I27: =IF(AND(AND(I$3>Inputs!$B$6,I$3<=Inputs!$B$6+Inputs!$B$13),H15>0),I26/H15,0) -> 2.0843849 | J27: =IF(AND(AND(J$3>Inputs!$B$6,J$3<=Inputs!$B$6+Inputs!$B$13),I15>0),J26/I15,0) -> 2.1262748 | ... BE27: =IF(AND(AND(BE$3>Inputs!$B$6,BE$3<=Inputs!$B$6+Inputs!$B$13),BD15>0),BE26/BD15,0) -> 0

Sheet Returns
A3: Equity IRR (XIRR) | B3: =XIRR('Cash Flow'!B24:BE24,'Cash Flow'!B4:BE4) -> 0.10240417
A4: Minimum DSCR | B4: =_xlfn.MINIFS('Cash Flow'!C25:BE25,'Cash Flow'!C25:BE25,">0") -> 1.3
A5: Minimum LLCR | B5: =_xlfn.MINIFS('Cash Flow'!C27:BE27,'Cash Flow'!C27:BE27,">0") -> 2.045602
A6: Senior debt at completion (£) | B6: =MAX('Cash Flow'!B15:BE15) -> 125800000
A7: Gearing | B7: =B6/Inputs!$B$5 -> 0.85
A8: Tax paid (£) | B8: =SUM('Cash Flow'!B23:BE23) -> 1.0776341e+08
A9: Lifecycle spend (£) | B9: =SUM('Cash Flow'!B10:BE10) -> 33064252
A10: Net profit to equity (£) | B10: =SUM('Cash Flow'!B24:BE24) -> 1.2678839e+08
A11: Case in use | B11: =IF(Inputs!$B$3=1,"Sponsor","Lenders") -> Sponsor
