Workbook

Sheet Inputs
A1: PIER 9 CO-INVESTMENT – TWO-TIER WATERFALL (USD)
A3: Project cost ex interest ($) | B3: 240000000
A4: Construction loan to cost (ex interest) | B4: 0.6
A5: Loan rate | B5: 0.08
A6: Build (months) | B6: 24
A7: Revenue ($) | B7: 345000000
A8: Sales start (month) | B8: 22
A9: Sales period (months) | B9: 18
A10: Developer co-invest (% of equity) | B10: 0.1
A11: Deal pref | B11: 0.09
A12: Developer promote above pref | B12: 0.25
A13: GP commitment (% of vehicle) | B13: 0.05
A14: Vehicle pref | B14: 0.08
... A16: Vehicle catch-up share | B16: 0.8

Sheet Cash Flow
A3: Month | B3: 0 | C3: 1 | D3: 2 | E3: 3 | F3: 4 | G3: 5 | H3: 6 | I3: 7 | J3: 8 | K3: 9 | L3: 10 | M3: 11 | N3: 12 | O3: 13 | P3: 14 | Q3: 15 | R3: 16 | S3: 17 | T3: 18 | U3: 19 | V3: 20 | W3: 21 | X3: 22 | Y3: 23 | Z3: 24 | AA3: 25 | AB3: 26 | AC3: 27 | AD3: 28 | AE3: 29 | AF3: 30 | AG3: 31 | AH3: 32 | AI3: 33 | AJ3: 34 | AK3: 35 | AL3: 36 | AM3: 37 | AN3: 38 | AO3: 39 | AP3: 40 | AQ3: 41 | AR3: 42 | AS3: 43 | AT3: 44 | AU3: 45 | AV3: 46 | AW3: 47 | AX3: 48
A4: Build cost | B4: =IF(AND(B$3>=1,B$3<=Inputs!$B$6),Inputs!$B$3/Inputs!$B$6,0) -> 0 | C4: =IF(AND(C$3>=1,C$3<=Inputs!$B$6),Inputs!$B$3/Inputs!$B$6,0) -> 10000000 | D4: =IF(AND(D$3>=1,D$3<=Inputs!$B$6),Inputs!$B$3/Inputs!$B$6,0) -> 10000000 | E4: =IF(AND(E$3>=1,E$3<=Inputs!$B$6),Inputs!$B$3/Inputs!$B$6,0) -> 10000000 | F4: =IF(AND(F$3>=1,F$3<=Inputs!$B$6),Inputs!$B$3/Inputs!$B$6,0) -> 10000000 | G4: =IF(AND(G$3>=1,G$3<=Inputs!$B$6),Inputs!$B$3/Inputs!$B$6,0) -> 10000000 | H4: =IF(AND(H$3>=1,H$3<=Inputs!$B$6),Inputs!$B$3/Inputs!$B$6,0) -> 10000000 | I4: =IF(AND(I$3>=1,I$3<=Inputs!$B$6),Inputs!$B$3/Inputs!$B$6,0) -> 10000000 | ... AX4: =IF(AND(AX$3>=1,AX$3<=Inputs!$B$6),Inputs!$B$3/Inputs!$B$6,0) -> 0
A5: Interest capitalised | B5: =0 -> 0 | C5: =B12*Inputs!$B$5/12 -> 0 | D5: =C12*Inputs!$B$5/12 -> 0 | E5: =D12*Inputs!$B$5/12 -> 0 | F5: =E12*Inputs!$B$5/12 -> 0 | G5: =F12*Inputs!$B$5/12 -> 0 | H5: =G12*Inputs!$B$5/12 -> 0 | I5: =H12*Inputs!$B$5/12 -> 0 | J5: =I12*Inputs!$B$5/12 -> 0 | ... AX5: =AW12*Inputs!$B$5/12 -> 0
A6: Total cost | B6: =B4+B5 -> 0 | C6: =C4+C5 -> 10000000 | D6: =D4+D5 -> 10000000 | E6: =E4+E5 -> 10000000 | F6: =F4+F5 -> 10000000 | G6: =G4+G5 -> 10000000 | H6: =H4+H5 -> 10000000 | I6: =I4+I5 -> 10000000 | ... AX6: =AX4+AX5 -> 0
A7: Equity drawn | B7: =MIN(B6,MAX(0,(1-Inputs!$B$4)*Inputs!$B$3-0)) -> 0 | C7: =MIN(C6,MAX(0,(1-Inputs!$B$4)*Inputs!$B$3-B8)) -> 10000000 | D7: =MIN(D6,MAX(0,(1-Inputs!$B$4)*Inputs!$B$3-C8)) -> 10000000 | E7: =MIN(E6,MAX(0,(1-Inputs!$B$4)*Inputs!$B$3-D8)) -> 10000000 | F7: =MIN(F6,MAX(0,(1-Inputs!$B$4)*Inputs!$B$3-E8)) -> 10000000 | G7: =MIN(G6,MAX(0,(1-Inputs!$B$4)*Inputs!$B$3-F8)) -> 10000000 | H7: =MIN(H6,MAX(0,(1-Inputs!$B$4)*Inputs!$B$3-G8)) -> 10000000 | I7: =MIN(I6,MAX(0,(1-Inputs!$B$4)*Inputs!$B$3-H8)) -> 10000000 | J7: =MIN(J6,MAX(0,(1-Inputs!$B$4)*Inputs!$B$3-I8)) -> 10000000 | ... AX7: =MIN(AX6,MAX(0,(1-Inputs!$B$4)*Inputs!$B$3-AW8)) -> 0
A8: Cumulative equity | B8: =B7 -> 0 | C8: =B8+C7 -> 10000000 | D8: =C8+D7 -> 20000000 | E8: =D8+E7 -> 30000000 | F8: =E8+F7 -> 40000000 | G8: =F8+G7 -> 50000000 | H8: =G8+H7 -> 60000000 | I8: =H8+I7 -> 70000000 | J8: =I8+J7 -> 80000000 | ... AX8: =AW8+AX7 -> 96000000
A9: Loan drawn | B9: =B6-B7 -> 0 | C9: =C6-C7 -> 0 | D9: =D6-D7 -> 0 | E9: =E6-E7 -> 0 | F9: =F6-F7 -> 0 | G9: =G6-G7 -> 0 | H9: =H6-H7 -> 0 | I9: =I6-I7 -> 0 | ... AX9: =AX6-AX7 -> 0
A10: Revenue | B10: =IF(AND(B$3>=Inputs!$B$8,B$3<Inputs!$B$8+Inputs!$B$9),Inputs!$B$7/Inputs!$B$9,0) -> 0 | C10: =IF(AND(C$3>=Inputs!$B$8,C$3<Inputs!$B$8+Inputs!$B$9),Inputs!$B$7/Inputs!$B$9,0) -> 0 | D10: =IF(AND(D$3>=Inputs!$B$8,D$3<Inputs!$B$8+Inputs!$B$9),Inputs!$B$7/Inputs!$B$9,0) -> 0 | E10: =IF(AND(E$3>=Inputs!$B$8,E$3<Inputs!$B$8+Inputs!$B$9),Inputs!$B$7/Inputs!$B$9,0) -> 0 | F10: =IF(AND(F$3>=Inputs!$B$8,F$3<Inputs!$B$8+Inputs!$B$9),Inputs!$B$7/Inputs!$B$9,0) -> 0 | G10: =IF(AND(G$3>=Inputs!$B$8,G$3<Inputs!$B$8+Inputs!$B$9),Inputs!$B$7/Inputs!$B$9,0) -> 0 | H10: =IF(AND(H$3>=Inputs!$B$8,H$3<Inputs!$B$8+Inputs!$B$9),Inputs!$B$7/Inputs!$B$9,0) -> 0 | I10: =IF(AND(I$3>=Inputs!$B$8,I$3<Inputs!$B$8+Inputs!$B$9),Inputs!$B$7/Inputs!$B$9,0) -> 0 | ... AX10: =IF(AND(AX$3>=Inputs!$B$8,AX$3<Inputs!$B$8+Inputs!$B$9),Inputs!$B$7/Inputs!$B$9,0) -> 0
A11: Repayment | B11: =MIN(B10,0+B9) -> 0 | C11: =MIN(C10,B12+C9) -> 0 | D11: =MIN(D10,C12+D9) -> 0 | E11: =MIN(E10,D12+E9) -> 0 | F11: =MIN(F10,E12+F9) -> 0 | G11: =MIN(G10,F12+G9) -> 0 | H11: =MIN(H10,G12+H9) -> 0 | I11: =MIN(I10,H12+I9) -> 0 | J11: =MIN(J10,I12+J9) -> 0 | ... AX11: =MIN(AX10,AW12+AX9) -> 0
A12: Loan balance | B12: =0+B9-B11 -> 0 | C12: =B12+C9-C11 -> 0 | D12: =C12+D9-D11 -> 0 | E12: =D12+E9-E11 -> 0 | F12: =E12+F9-F11 -> 0 | G12: =F12+G9-G11 -> 0 | H12: =G12+H9-H11 -> 0 | I12: =H12+I9-I11 -> 0 | J12: =I12+J9-J11 -> 0 | ... AX12: =AW12+AX9-AX11 -> 0
A13: Deal equity cash flow | B13: =B10-B11-B7 -> 0 | C13: =C10-C11-C7 -> -10000000 | D13: =D10-D11-D7 -> -10000000 | E13: =E10-E11-E7 -> -10000000 | F13: =F10-F11-F7 -> -10000000 | G13: =G10-G11-G7 -> -10000000 | H13: =H10-H11-H7 -> -10000000 | I13: =I10-I11-I7 -> -10000000 | ... AX13: =AX10-AX11-AX7 -> 0
A14: Capital partner contribution | B14: =B7*(1-Inputs!$B$10) -> 0 | C14: =C7*(1-Inputs!$B$10) -> 9000000 | D14: =D7*(1-Inputs!$B$10) -> 9000000 | E14: =E7*(1-Inputs!$B$10) -> 9000000 | F14: =F7*(1-Inputs!$B$10) -> 9000000 | G14: =G7*(1-Inputs!$B$10) -> 9000000 | H14: =H7*(1-Inputs!$B$10) -> 9000000 | I14: =I7*(1-Inputs!$B$10) -> 9000000 | ... AX14: =AX7*(1-Inputs!$B$10) -> 0
A15: Developer contribution | B15: =B7*Inputs!$B$10 -> 0 | C15: =C7*Inputs!$B$10 -> 1000000 | D15: =D7*Inputs!$B$10 -> 1000000 | E15: =E7*Inputs!$B$10 -> 1000000 | F15: =F7*Inputs!$B$10 -> 1000000 | G15: =G7*Inputs!$B$10 -> 1000000 | H15: =H7*Inputs!$B$10 -> 1000000 | I15: =I7*Inputs!$B$10 -> 1000000 | ... AX15: =AX7*Inputs!$B$10 -> 0
A16: Distributions | B16: =B10-B11 -> 0 | C16: =C10-C11 -> 0 | D16: =D10-D11 -> 0 | E16: =E10-E11 -> 0 | F16: =F10-F11 -> 0 | G16: =G10-G11 -> 0 | H16: =H10-H11 -> 0 | I16: =I10-I11 -> 0 | ... AX16: =AX10-AX11 -> 0
A17: Deal ROC | B17: =MIN(B16,0) -> 0 | C17: =MIN(C16,SUM($B7:C7)-SUM($B17:B17)) -> 0 | D17: =MIN(D16,SUM($B7:D7)-SUM($B17:C17)) -> 0 | E17: =MIN(E16,SUM($B7:E7)-SUM($B17:D17)) -> 0 | F17: =MIN(F16,SUM($B7:F7)-SUM($B17:E17)) -> 0 | G17: =MIN(G16,SUM($B7:G7)-SUM($B17:F17)) -> 0 | H17: =MIN(H16,SUM($B7:H7)-SUM($B17:G17)) -> 0 | I17: =MIN(I16,SUM($B7:I7)-SUM($B17:H17)) -> 0 | J17: =MIN(J16,SUM($B7:J7)-SUM($B17:I17)) -> 0 | ... AX17: =MIN(AX16,SUM($B7:AX7)-SUM($B17:AW17)) -> 0
A18: Deal pref account | B18: =0 -> 0 | C18: =(B18-B19)*(1+((1+Inputs!$B$11)^(1/12)-1))+(SUM($B7:B7)-SUM($B17:B17))*((1+Inputs!$B$11)^(1/12)-1) -> 0 | D18: =(C18-C19)*(1+((1+Inputs!$B$11)^(1/12)-1))+(SUM($B7:C7)-SUM($B17:C17))*((1+Inputs!$B$11)^(1/12)-1) -> 72073.233 | E18: =(D18-D19)*(1+((1+Inputs!$B$11)^(1/12)-1))+(SUM($B7:D7)-SUM($B17:D17))*((1+Inputs!$B$11)^(1/12)-1) -> 216739.15 | F18: =(E18-E19)*(1+((1+Inputs!$B$11)^(1/12)-1))+(SUM($B7:E7)-SUM($B17:E17))*((1+Inputs!$B$11)^(1/12)-1) -> 434520.96 | G18: =(F18-F19)*(1+((1+Inputs!$B$11)^(1/12)-1))+(SUM($B7:F7)-SUM($B17:F17))*((1+Inputs!$B$11)^(1/12)-1) -> 725945.63 | H18: =(G18-G19)*(1+((1+Inputs!$B$11)^(1/12)-1))+(SUM($B7:G7)-SUM($B17:G17))*((1+Inputs!$B$11)^(1/12)-1) -> 1091543.9 | I18: =(H18-H19)*(1+((1+Inputs!$B$11)^(1/12)-1))+(SUM($B7:H7)-SUM($B17:H17))*((1+Inputs!$B$11)^(1/12)-1) -> 1531850.4 | J18: =(I18-I19)*(1+((1+Inputs!$B$11)^(1/12)-1))+(SUM($B7:I7)-SUM($B17:I17))*((1+Inputs!$B$11)^(1/12)-1) -> 2047403.6 | ... AX18: =(AW18-AW19)*(1+((1+Inputs!$B$11)^(1/12)-1))+(SUM($B7:AW7)-SUM($B17:AW17))*((1+Inputs!$B$11)^(1/12)-1) -> 0
A19: Deal pref paid | B19: =MIN(B16-B17,B18) -> 0 | C19: =MIN(C16-C17,C18) -> 0 | D19: =MIN(D16-D17,D18) -> 0 | E19: =MIN(E16-E17,E18) -> 0 | F19: =MIN(F16-F17,F18) -> 0 | G19: =MIN(G16-G17,G18) -> 0 | H19: =MIN(H16-H17,H18) -> 0 | I19: =MIN(I16-I17,I18) -> 0 | ... AX19: =MIN(AX16-AX17,AX18) -> 0
A20: Promote | B20: =(B16-B17-B19)*Inputs!$B$12 -> 0 | C20: =(C16-C17-C19)*Inputs!$B$12 -> 0 | D20: =(D16-D17-D19)*Inputs!$B$12 -> 0 | E20: =(E16-E17-E19)*Inputs!$B$12 -> 0 | F20: =(F16-F17-F19)*Inputs!$B$12 -> 0 | G20: =(G16-G17-G19)*Inputs!$B$12 -> 0 | H20: =(H16-H17-H19)*Inputs!$B$12 -> 0 | I20: =(I16-I17-I19)*Inputs!$B$12 -> 0 | ... AX20: =(AX16-AX17-AX19)*Inputs!$B$12 -> 0
A21: Capital partner share | B21: =(B17+B19)*(1-Inputs!$B$10)+(B16-B17-B19-B20)*(1-Inputs!$B$10) -> 0 | C21: =(C17+C19)*(1-Inputs!$B$10)+(C16-C17-C19-C20)*(1-Inputs!$B$10) -> 0 | D21: =(D17+D19)*(1-Inputs!$B$10)+(D16-D17-D19-D20)*(1-Inputs!$B$10) -> 0 | E21: =(E17+E19)*(1-Inputs!$B$10)+(E16-E17-E19-E20)*(1-Inputs!$B$10) -> 0 | F21: =(F17+F19)*(1-Inputs!$B$10)+(F16-F17-F19-F20)*(1-Inputs!$B$10) -> 0 | G21: =(G17+G19)*(1-Inputs!$B$10)+(G16-G17-G19-G20)*(1-Inputs!$B$10) -> 0 | H21: =(H17+H19)*(1-Inputs!$B$10)+(H16-H17-H19-H20)*(1-Inputs!$B$10) -> 0 | I21: =(I17+I19)*(1-Inputs!$B$10)+(I16-I17-I19-I20)*(1-Inputs!$B$10) -> 0 | ... AX21: =(AX17+AX19)*(1-Inputs!$B$10)+(AX16-AX17-AX19-AX20)*(1-Inputs!$B$10) -> 0
A22: Developer total | B22: =B16-B21 -> 0 | C22: =C16-C21 -> 0 | D22: =D16-D21 -> 0 | E22: =E16-E21 -> 0 | F22: =F16-F21 -> 0 | G22: =G16-G21 -> 0 | H22: =H16-H21 -> 0 | I22: =I16-I21 -> 0 | ... AX22: =AX16-AX21 -> 0
A23: Capital partner cash flow | B23: =B21-B14 -> 0 | C23: =C21-C14 -> -9000000 | D23: =D21-D14 -> -9000000 | E23: =E21-E14 -> -9000000 | F23: =F21-F14 -> -9000000 | G23: =G21-G14 -> -9000000 | H23: =H21-H14 -> -9000000 | I23: =I21-I14 -> -9000000 | ... AX23: =AX21-AX14 -> 0
A24: LP contribution | B24: =B14*(1-Inputs!$B$13) -> 0 | C24: =C14*(1-Inputs!$B$13) -> 8550000 | D24: =D14*(1-Inputs!$B$13) -> 8550000 | E24: =E14*(1-Inputs!$B$13) -> 8550000 | F24: =F14*(1-Inputs!$B$13) -> 8550000 | G24: =G14*(1-Inputs!$B$13) -> 8550000 | H24: =H14*(1-Inputs!$B$13) -> 8550000 | I24: =I14*(1-Inputs!$B$13) -> 8550000 | ... AX24: =AX14*(1-Inputs!$B$13) -> 0
A25: GP contribution | B25: =B14*Inputs!$B$13 -> 0 | C25: =C14*Inputs!$B$13 -> 450000 | D25: =D14*Inputs!$B$13 -> 450000 | E25: =E14*Inputs!$B$13 -> 450000 | F25: =F14*Inputs!$B$13 -> 450000 | G25: =G14*Inputs!$B$13 -> 450000 | H25: =H14*Inputs!$B$13 -> 450000 | I25: =I14*Inputs!$B$13 -> 450000 | ... AX25: =AX14*Inputs!$B$13 -> 0
A26: Vehicle ROC | B26: =MIN(B21,0) -> 0 | C26: =MIN(C21,SUM($B14:C14)-SUM($B26:B26)) -> 0 | D26: =MIN(D21,SUM($B14:D14)-SUM($B26:C26)) -> 0 | E26: =MIN(E21,SUM($B14:E14)-SUM($B26:D26)) -> 0 | F26: =MIN(F21,SUM($B14:F14)-SUM($B26:E26)) -> 0 | G26: =MIN(G21,SUM($B14:G14)-SUM($B26:F26)) -> 0 | H26: =MIN(H21,SUM($B14:H14)-SUM($B26:G26)) -> 0 | I26: =MIN(I21,SUM($B14:I14)-SUM($B26:H26)) -> 0 | J26: =MIN(J21,SUM($B14:J14)-SUM($B26:I26)) -> 0 | ... AX26: =MIN(AX21,SUM($B14:AX14)-SUM($B26:AW26)) -> 0
A27: Vehicle pref account | B27: =0 -> 0 | C27: =(B27-B28)*(1+((1+Inputs!$B$14)^(1/12)-1))+(SUM($B14:B14)-SUM($B26:B26))*((1+Inputs!$B$14)^(1/12)-1) -> 0 | D27: =(C27-C28)*(1+((1+Inputs!$B$14)^(1/12)-1))+(SUM($B14:C14)-SUM($B26:C26))*((1+Inputs!$B$14)^(1/12)-1) -> 57906.271 | E27: =(D27-D28)*(1+((1+Inputs!$B$14)^(1/12)-1))+(SUM($B14:D14)-SUM($B26:D26))*((1+Inputs!$B$14)^(1/12)-1) -> 174091.38 | F27: =(E27-E28)*(1+((1+Inputs!$B$14)^(1/12)-1))+(SUM($B14:E14)-SUM($B26:E26))*((1+Inputs!$B$14)^(1/12)-1) -> 348930.31 | G27: =(F27-F28)*(1+((1+Inputs!$B$14)^(1/12)-1))+(SUM($B14:F14)-SUM($B26:F26))*((1+Inputs!$B$14)^(1/12)-1) -> 582800.42 | H27: =(G27-G28)*(1+((1+Inputs!$B$14)^(1/12)-1))+(SUM($B14:G14)-SUM($B26:G26))*((1+Inputs!$B$14)^(1/12)-1) -> 876081.53 | I27: =(H27-H28)*(1+((1+Inputs!$B$14)^(1/12)-1))+(SUM($B14:H14)-SUM($B26:H26))*((1+Inputs!$B$14)^(1/12)-1) -> 1229155.9 | J27: =(I27-I28)*(1+((1+Inputs!$B$14)^(1/12)-1))+(SUM($B14:I14)-SUM($B26:I26))*((1+Inputs!$B$14)^(1/12)-1) -> 1642408.2 | ... AX27: =(AW27-AW28)*(1+((1+Inputs!$B$14)^(1/12)-1))+(SUM($B14:AW14)-SUM($B26:AW26))*((1+Inputs!$B$14)^(1/12)-1) -> 0
A28: Vehicle pref paid | B28: =MIN(B21-B26,B27) -> 0 | C28: =MIN(C21-C26,C27) -> 0 | D28: =MIN(D21-D26,D27) -> 0 | E28: =MIN(E21-E26,E27) -> 0 | F28: =MIN(F21-F26,F27) -> 0 | G28: =MIN(G21-G26,G27) -> 0 | H28: =MIN(H21-H26,H27) -> 0 | I28: =MIN(I21-I26,I27) -> 0 | ... AX28: =MIN(AX21-AX26,AX27) -> 0
A29: Vehicle catch-up account | B29: =B28*Inputs!$B$15/(1-Inputs!$B$15) -> 0 | C29: =B29-B30+C28*Inputs!$B$15/(1-Inputs!$B$15) -> 0 | D29: =C29-C30+D28*Inputs!$B$15/(1-Inputs!$B$15) -> 0 | E29: =D29-D30+E28*Inputs!$B$15/(1-Inputs!$B$15) -> 0 | F29: =E29-E30+F28*Inputs!$B$15/(1-Inputs!$B$15) -> 0 | G29: =F29-F30+G28*Inputs!$B$15/(1-Inputs!$B$15) -> 0 | H29: =G29-G30+H28*Inputs!$B$15/(1-Inputs!$B$15) -> 0 | I29: =H29-H30+I28*Inputs!$B$15/(1-Inputs!$B$15) -> 0 | J29: =I29-I30+J28*Inputs!$B$15/(1-Inputs!$B$15) -> 0 | ... AX29: =AW29-AW30+AX28*Inputs!$B$15/(1-Inputs!$B$15) -> 0
A30: Catch-up to GP | B30: =MIN((B21-B26-B28)*Inputs!$B$16,B29) -> 0 | C30: =MIN((C21-C26-C28)*Inputs!$B$16,C29) -> 0 | D30: =MIN((D21-D26-D28)*Inputs!$B$16,D29) -> 0 | E30: =MIN((E21-E26-E28)*Inputs!$B$16,E29) -> 0 | F30: =MIN((F21-F26-F28)*Inputs!$B$16,F29) -> 0 | G30: =MIN((G21-G26-G28)*Inputs!$B$16,G29) -> 0 | H30: =MIN((H21-H26-H28)*Inputs!$B$16,H29) -> 0 | I30: =MIN((I21-I26-I28)*Inputs!$B$16,I29) -> 0 | ... AX30: =MIN((AX21-AX26-AX28)*Inputs!$B$16,AX29) -> 0
A31: Split LP | B31: =(B21-B26-B28-B30)*(1-Inputs!$B$15) -> 0 | C31: =(C21-C26-C28-C30)*(1-Inputs!$B$15) -> 0 | D31: =(D21-D26-D28-D30)*(1-Inputs!$B$15) -> 0 | E31: =(E21-E26-E28-E30)*(1-Inputs!$B$15) -> 0 | F31: =(F21-F26-F28-F30)*(1-Inputs!$B$15) -> 0 | G31: =(G21-G26-G28-G30)*(1-Inputs!$B$15) -> 0 | H31: =(H21-H26-H28-H30)*(1-Inputs!$B$15) -> 0 | I31: =(I21-I26-I28-I30)*(1-Inputs!$B$15) -> 0 | ... AX31: =(AX21-AX26-AX28-AX30)*(1-Inputs!$B$15) -> 0
A32: Split GP | B32: =(B21-B26-B28-B30)*Inputs!$B$15 -> 0 | C32: =(C21-C26-C28-C30)*Inputs!$B$15 -> 0 | D32: =(D21-D26-D28-D30)*Inputs!$B$15 -> 0 | E32: =(E21-E26-E28-E30)*Inputs!$B$15 -> 0 | F32: =(F21-F26-F28-F30)*Inputs!$B$15 -> 0 | G32: =(G21-G26-G28-G30)*Inputs!$B$15 -> 0 | H32: =(H21-H26-H28-H30)*Inputs!$B$15 -> 0 | I32: =(I21-I26-I28-I30)*Inputs!$B$15 -> 0 | ... AX32: =(AX21-AX26-AX28-AX30)*Inputs!$B$15 -> 0
A33: LP cash flow | B33: =(B26+B28+B31)*(1-Inputs!$B$13)+B31*0-B24 -> 0 | C33: =(C26+C28+C31)*(1-Inputs!$B$13)+C31*0-C24 -> -8550000 | D33: =(D26+D28+D31)*(1-Inputs!$B$13)+D31*0-D24 -> -8550000 | E33: =(E26+E28+E31)*(1-Inputs!$B$13)+E31*0-E24 -> -8550000 | F33: =(F26+F28+F31)*(1-Inputs!$B$13)+F31*0-F24 -> -8550000 | G33: =(G26+G28+G31)*(1-Inputs!$B$13)+G31*0-G24 -> -8550000 | H33: =(H26+H28+H31)*(1-Inputs!$B$13)+H31*0-H24 -> -8550000 | I33: =(I26+I28+I31)*(1-Inputs!$B$13)+I31*0-I24 -> -8550000 | ... AX33: =(AX26+AX28+AX31)*(1-Inputs!$B$13)+AX31*0-AX24 -> 0
A34: GP cash flow | B34: =B23-B33 -> 0 | C34: =C23-C33 -> -450000 | D34: =D23-D33 -> -450000 | E34: =E23-E33 -> -450000 | F34: =F23-F33 -> -450000 | G34: =G23-G33 -> -450000 | H34: =H23-H33 -> -450000 | I34: =I23-I33 -> -450000 | ... AX34: =AX23-AX33 -> 0

Sheet Returns
A3: Deal IRR (unlevered equity) | B3: =(1+IRR('Cash Flow'!B13:AX13,0.01))^12-1 -> 0.3329116
A4: Capital partner IRR (after promote) | B4: =(1+IRR('Cash Flow'!B23:AX23,0.01))^12-1 -> 0.28060352
A5: LP net IRR (after promote and carry) | B5: =(1+IRR('Cash Flow'!B33:AX33,0.01))^12-1 -> 0.23403864
A6: GP IRR | B6: =(1+IRR('Cash Flow'!B34:AX34,0.01))^12-1 -> 0.86147606
A7: LP equity multiple | B7: =SUMIF('Cash Flow'!B33:AX33,">0")/-SUMIF('Cash Flow'!B33:AX33,"<0") -> 1.6488364
A8: Developer promote ($) | B8: =SUM('Cash Flow'!B20:AX20) -> 19056009
A9: GP carry ($) | B9: =SUM('Cash Flow'!B30:AX30)+SUM('Cash Flow'!B32:AX32) -> 14014866
A10: Interest capitalised ($) | B10: =SUM('Cash Flow'!B5:AX5) -> 8083623.7
A11: Peak loan ($) | B11: =MAX('Cash Flow'!B12:AX12) -> 1.180443e+08
A12: Net profit ($) | B12: =SUM('Cash Flow'!B13:AX13) -> 96916376
