Workbook

Sheet Inputs
A1: NORTHGATE EUROPEAN LOGISTICS – EIGHT ASSETS, FOUR COUNTRIES (EUR)
A3: Valuation date | B3: 46023
A4: Portfolio price (EUR) | B4: 610000000
A5: Purchase costs | B5: 0.04
A6: Loan to value | B6: 0.5
A7: All-in rate | B7: 0.045
A8: LTV covenant | B8: 0.6
A9: Cash trap LTV | B9: 0.55
A10: Exit yield (blended) | B10: 0.055
A11: Hold (years) | B11: 7
A12: Void on expiry (months) | B12: 9
A13: Renewal probability | B13: 0.6
A14: Non-recoverable (% of rent) | B14: 0.03

Sheet Countries
A1: Country | B1: Currency | C1: FX to EUR | D1: CPI | E1: Indexation floor | F1: Indexation cap
A2: Germany | B2: EUR | C2: 1 | D2: 0.022 | E2: 0 | F2: 0.05
A3: Poland | B3: PLN | C3: 0.2315 | D3: 0.045 | E3: 0.01 | F3: 0.04
A4: Sweden | B4: SEK | C4: 0.0875 | D4: 0.02 | E4: 0 | F4: 0.03
A5: UK | B5: GBP | C5: 1.17 | D5: 0.03 | E5: 0.01 | F5: 0.05

Sheet Assets
A1: Asset | B1: Country | C1: Area (sqm) | D1: Rent (local/sqm/yr) | E1: Lease expiry | F1: ERV (local/sqm/yr) | G1: Disposal date | H1: Disposal yield
A2: Hamburg Nord | B2: Germany | C2: 48000 | D2: 62 | E2: 47938 | F2: 66
A3: Leipzig Park | B3: Germany | C3: 61000 | D3: 55 | E3: 47026 | F3: 60 | G3: 47483 | H3: 0.052
A4: Warsaw West | B4: Poland | C4: 72000 | D4: 260 | E4: 47664 | F4: 280
A5: Lodz Hub | B5: Poland | C5: 55000 | D5: 240 | E5: 46752 | F5: 265
A6: Malmo Gate | B6: Sweden | C6: 38000 | D6: 780 | E6: 48579 | F6: 800
A7: Gothenburg Port | B7: Sweden | C7: 44000 | D7: 760 | E7: 47299 | F7: 810 | G7: 47664 | H7: 0.05
A8: Midlands Cross | B8: UK | C8: 66000 | D8: 88 | E8: 48669 | F8: 96
A9: Thames Gateway | B9: UK | C9: 52000 | D9: 98 | E9: 46843 | F9: 104

Sheet Cash Flow
A3: Year | B3: 0 | C3: 1 | D3: 2 | E3: 3 | F3: 4 | G3: 5 | H3: 6 | I3: 7 | J3: 8 | K3: 9 | L3: 10
A4: Year start | B4: =EDATE(Inputs!$B$3,12*B3) -> 46023 | C4: =EDATE(Inputs!$B$3,12*C3) -> 46388 | D4: =EDATE(Inputs!$B$3,12*D3) -> 46753 | E4: =EDATE(Inputs!$B$3,12*E3) -> 47119 | F4: =EDATE(Inputs!$B$3,12*F3) -> 47484 | G4: =EDATE(Inputs!$B$3,12*G3) -> 47849 | H4: =EDATE(Inputs!$B$3,12*H3) -> 48214 | I4: =EDATE(Inputs!$B$3,12*I3) -> 48580 | ... L4: =EDATE(Inputs!$B$3,12*L3) -> 49675
A5: Hamburg Nord · rent (EUR) | B5: =IF(AND(B$3>=1,B$3<=Inputs!$B$11,OR(Assets!$G$2="",B$4<Assets!$G$2)),Assets!$C$2*(Assets!$D$2*(1+MIN(INDEX(Countries!$F$2:$F$5,MATCH(Assets!$B$2,Countries!$A$2:$A$5,0)),MAX(INDEX(Countries!$E$2:$E$5,MATCH(Assets!$B$2,Countries!$A$2:$A$5,0)),INDEX(Countries!$D$2:$D$5,MATCH(Assets!$B$2,Countries!$A$2:$A$5,0)))))^(B$3-1)*MAX(0,MIN(1,YEARFRAC(B$4,MIN(Assets!$E$2,EDATE(B$4,12)),1)*(Assets!$E$2>B$4)))+Assets!$F$2*(1+MIN(INDEX(Countries!$F$2:$F$5,MATCH(Assets!$B$2,Countries!$A$2:$A$5,0)),MAX(INDEX(Countries!$E$2:$E$5,MATCH(Assets!$B$2,Countries!$A$2:$A$5,0)),INDEX(Countries!$D$2:$D$5,MATCH(Assets!$B$2,Countries!$A$2:$A$5,0)))))^(B$3-1)*IF(Assets!$E$2<EDATE(B$4,12),(Inputs!$B$13*MAX(0,MIN(12,DATEDIF(MAX(Assets!$E$2,B$4),EDATE(B$4,12),"m")))+(1-Inputs!$B$13)*MAX(0,MAX(0,MIN(12,DATEDIF(MAX(Assets!$E$2,B$4),EDATE(B$4,12),"m")))-MAX(0,Inputs!$B$12-IF(Assets!$E$2<B$4,DATEDIF(Assets!$E$2,B$4,"m"),0))))/12,0))*INDEX(Countries!$C$2:$C$5,MATCH(Assets!$B$2,Countries!$A$2:$A$5,0)),0) -> 0 | C5: =IF(AND(C$3>=1,C$3<=Inputs!$B$11,OR(Assets!$G$2="",C$4<Assets!$G$2)),Assets!$C$2*(Assets!$D$2*(1+MIN(INDEX(Countries!$F$2:$F$5,MATCH(Assets!$B$2,Countries!$A$2:$A$5,0)),MAX(INDEX(Countries!$E$2:$E$5,MATCH(Assets!$B$2,Countries!$A$2:$A$5,0)),INDEX(Countries!$D$2:$D$5,MATCH(Assets!$B$2,Countries!$A$2:$A$5,0)))))^(C$3-1)*MAX(0,MIN(1,YEARFRAC(C$4,MIN(Assets!$E$2,EDATE(C$4,12)),1)*(Assets!$E$2>C$4)))+Assets!$F$2*(1+MIN(INDEX(Countries!$F$2:$F$5,MATCH(Assets!$B$2,Countries!$A$2:$A$5,0)),MAX(INDEX(Countries!$E$2:$E$5,MATCH(Assets!$B$2,Countries!$A$2:$A$5,0)),INDEX(Countries!$D$2:$D$5,MATCH(Assets!$B$2,Countries!$A$2:$A$5,0)))))^(C$3-1)*IF(Assets!$E$2<EDATE(C$4,12),(Inputs!$B$13*MAX(0,MIN(12,DATEDIF(MAX(Assets!$E$2,C$4),EDATE(C$4,12),"m")))+(1-Inputs!$B$13)*MAX(0,MAX(0,MIN(12,DATEDIF(MAX(Assets!$E$2,C$4),EDATE(C$4,12),"m")))-MAX(0,Inputs!$B$12-IF(Assets!$E$2<C$4,DATEDIF(Assets!$E$2,C$4,"m"),0))))/12,0))*INDEX(Countries!$C$2:$C$5,MATCH(Assets!$B$2,Countries!$A$2:$A$5,0)),0) -> 2976000 | D5: =IF(AND(D$3>=1,D$3<=Inputs!$B$11,OR(Assets!$G$2="",D$4<Assets!$G$2)),Assets!$C$2*(Assets!$D$2*(1+MIN(INDEX(Countries!$F$2:$F$5,MATCH(Assets!$B$2,Countries!$A$2:$A$5,0)),MAX(INDEX(Countries!$E$2:$E$5,MATCH(Assets!$B$2,Countries!$A$2:$A$5,0)),INDEX(Countries!$D$2:$D$5,MATCH(Assets!$B$2,Countries!$A$2:$A$5,0)))))^(D$3-1)*MAX(0,MIN(1,YEARFRAC(D$4,MIN(Assets!$E$2,EDATE(D$4,12)),1)*(Assets!$E$2>D$4)))+Assets!$F$2*(1+MIN(INDEX(Countries!$F$2:$F$5,MATCH(Assets!$B$2,Countries!$A$2:$A$5,0)),MAX(INDEX(Countries!$E$2:$E$5,MATCH(Assets!$B$2,Countries!$A$2:$A$5,0)),INDEX(Countries!$D$2:$D$5,MATCH(Assets!$B$2,Countries!$A$2:$A$5,0)))))^(D$3-1)*IF(Assets!$E$2<EDATE(D$4,12),(Inputs!$B$13*MAX(0,MIN(12,DATEDIF(MAX(Assets!$E$2,D$4),EDATE(D$4,12),"m")))+(1-Inputs!$B$13)*MAX(0,MAX(0,MIN(12,DATEDIF(MAX(Assets!$E$2,D$4),EDATE(D$4,12),"m")))-MAX(0,Inputs!$B$12-IF(Assets!$E$2<D$4,DATEDIF(Assets!$E$2,D$4,"m"),0))))/12,0))*INDEX(Countries!$C$2:$C$5,MATCH(Assets!$B$2,Countries!$A$2:$A$5,0)),0) -> 3041472 | E5: =IF(AND(E$3>=1,E$3<=Inputs!$B$11,OR(Assets!$G$2="",E$4<Assets!$G$2)),Assets!$C$2*(Assets!$D$2*(1+MIN(INDEX(Countries!$F$2:$F$5,MATCH(Assets!$B$2,Countries!$A$2:$A$5,0)),MAX(INDEX(Countries!$E$2:$E$5,MATCH(Assets!$B$2,Countries!$A$2:$A$5,0)),INDEX(Countries!$D$2:$D$5,MATCH(Assets!$B$2,Countries!$A$2:$A$5,0)))))^(E$3-1)*MAX(0,MIN(1,YEARFRAC(E$4,MIN(Assets!$E$2,EDATE(E$4,12)),1)*(Assets!$E$2>E$4)))+Assets!$F$2*(1+MIN(INDEX(Countries!$F$2:$F$5,MATCH(Assets!$B$2,Countries!$A$2:$A$5,0)),MAX(INDEX(Countries!$E$2:$E$5,MATCH(Assets!$B$2,Countries!$A$2:$A$5,0)),INDEX(Countries!$D$2:$D$5,MATCH(Assets!$B$2,Countries!$A$2:$A$5,0)))))^(E$3-1)*IF(Assets!$E$2<EDATE(E$4,12),(Inputs!$B$13*MAX(0,MIN(12,DATEDIF(MAX(Assets!$E$2,E$4),EDATE(E$4,12),"m")))+(1-Inputs!$B$13)*MAX(0,MAX(0,MIN(12,DATEDIF(MAX(Assets!$E$2,E$4),EDATE(E$4,12),"m")))-MAX(0,Inputs!$B$12-IF(Assets!$E$2<E$4,DATEDIF(Assets!$E$2,E$4,"m"),0))))/12,0))*INDEX(Countries!$C$2:$C$5,MATCH(Assets!$B$2,Countries!$A$2:$A$5,0)),0) -> 3108384.4 | F5: =IF(AND(F$3>=1,F$3<=Inputs!$B$11,OR(Assets!$G$2="",F$4<Assets!$G$2)),Assets!$C$2*(Assets!$D$2*(1+MIN(INDEX(Countries!$F$2:$F$5,MATCH(Assets!$B$2,Countries!$A$2:$A$5,0)),MAX(INDEX(Countries!$E$2:$E$5,MATCH(Assets!$B$2,Countries!$A$2:$A$5,0)),INDEX(Countries!$D$2:$D$5,MATCH(Assets!$B$2,Countries!$A$2:$A$5,0)))))^(F$3-1)*MAX(0,MIN(1,YEARFRAC(F$4,MIN(Assets!$E$2,EDATE(F$4,12)),1)*(Assets!$E$2>F$4)))+Assets!$F$2*(1+MIN(INDEX(Countries!$F$2:$F$5,MATCH(Assets!$B$2,Countries!$A$2:$A$5,0)),MAX(INDEX(Countries!$E$2:$E$5,MATCH(Assets!$B$2,Countries!$A$2:$A$5,0)),INDEX(Countries!$D$2:$D$5,MATCH(Assets!$B$2,Countries!$A$2:$A$5,0)))))^(F$3-1)*IF(Assets!$E$2<EDATE(F$4,12),(Inputs!$B$13*MAX(0,MIN(12,DATEDIF(MAX(Assets!$E$2,F$4),EDATE(F$4,12),"m")))+(1-Inputs!$B$13)*MAX(0,MAX(0,MIN(12,DATEDIF(MAX(Assets!$E$2,F$4),EDATE(F$4,12),"m")))-MAX(0,Inputs!$B$12-IF(Assets!$E$2<F$4,DATEDIF(Assets!$E$2,F$4,"m"),0))))/12,0))*INDEX(Countries!$C$2:$C$5,MATCH(Assets!$B$2,Countries!$A$2:$A$5,0)),0) -> 3176768.8 | G5: =IF(AND(G$3>=1,G$3<=Inputs!$B$11,OR(Assets!$G$2="",G$4<Assets!$G$2)),Assets!$C$2*(Assets!$D$2*(1+MIN(INDEX(Countries!$F$2:$F$5,MATCH(Assets!$B$2,Countries!$A$2:$A$5,0)),MAX(INDEX(Countries!$E$2:$E$5,MATCH(Assets!$B$2,Countries!$A$2:$A$5,0)),INDEX(Countries!$D$2:$D$5,MATCH(Assets!$B$2,Countries!$A$2:$A$5,0)))))^(G$3-1)*MAX(0,MIN(1,YEARFRAC(G$4,MIN(Assets!$E$2,EDATE(G$4,12)),1)*(Assets!$E$2>G$4)))+Assets!$F$2*(1+MIN(INDEX(Countries!$F$2:$F$5,MATCH(Assets!$B$2,Countries!$A$2:$A$5,0)),MAX(INDEX(Countries!$E$2:$E$5,MATCH(Assets!$B$2,Countries!$A$2:$A$5,0)),INDEX(Countries!$D$2:$D$5,MATCH(Assets!$B$2,Countries!$A$2:$A$5,0)))))^(G$3-1)*IF(Assets!$E$2<EDATE(G$4,12),(Inputs!$B$13*MAX(0,MIN(12,DATEDIF(MAX(Assets!$E$2,G$4),EDATE(G$4,12),"m")))+(1-Inputs!$B$13)*MAX(0,MAX(0,MIN(12,DATEDIF(MAX(Assets!$E$2,G$4),EDATE(G$4,12),"m")))-MAX(0,Inputs!$B$12-IF(Assets!$E$2<G$4,DATEDIF(Assets!$E$2,G$4,"m"),0))))/12,0))*INDEX(Countries!$C$2:$C$5,MATCH(Assets!$B$2,Countries!$A$2:$A$5,0)),0) -> 2346904.6 | H5: =IF(AND(H$3>=1,H$3<=Inputs!$B$11,OR(Assets!$G$2="",H$4<Assets!$G$2)),Assets!$C$2*(Assets!$D$2*(1+MIN(INDEX(Countries!$F$2:$F$5,MATCH(Assets!$B$2,Countries!$A$2:$A$5,0)),MAX(INDEX(Countries!$E$2:$E$5,MATCH(Assets!$B$2,Countries!$A$2:$A$5,0)),INDEX(Countries!$D$2:$D$5,MATCH(Assets!$B$2,Countries!$A$2:$A$5,0)))))^(H$3-1)*MAX(0,MIN(1,YEARFRAC(H$4,MIN(Assets!$E$2,EDATE(H$4,12)),1)*(Assets!$E$2>H$4)))+Assets!$F$2*(1+MIN(INDEX(Countries!$F$2:$F$5,MATCH(Assets!$B$2,Countries!$A$2:$A$5,0)),MAX(INDEX(Countries!$E$2:$E$5,MATCH(Assets!$B$2,Countries!$A$2:$A$5,0)),INDEX(Countries!$D$2:$D$5,MATCH(Assets!$B$2,Countries!$A$2:$A$5,0)))))^(H$3-1)*IF(Assets!$E$2<EDATE(H$4,12),(Inputs!$B$13*MAX(0,MIN(12,DATEDIF(MAX(Assets!$E$2,H$4),EDATE(H$4,12),"m")))+(1-Inputs!$B$13)*MAX(0,MAX(0,MIN(12,DATEDIF(MAX(Assets!$E$2,H$4),EDATE(H$4,12),"m")))-MAX(0,Inputs!$B$12-IF(Assets!$E$2<H$4,DATEDIF(Assets!$E$2,H$4,"m"),0))))/12,0))*INDEX(Countries!$C$2:$C$5,MATCH(Assets!$B$2,Countries!$A$2:$A$5,0)),0) -> 3532154.2 | I5: =IF(AND(I$3>=1,I$3<=Inputs!$B$11,OR(Assets!$G$2="",I$4<Assets!$G$2)),Assets!$C$2*(Assets!$D$2*(1+MIN(INDEX(Countries!$F$2:$F$5,MATCH(Assets!$B$2,Countries!$A$2:$A$5,0)),MAX(INDEX(Countries!$E$2:$E$5,MATCH(Assets!$B$2,Countries!$A$2:$A$5,0)),INDEX(Countries!$D$2:$D$5,MATCH(Assets!$B$2,Countries!$A$2:$A$5,0)))))^(I$3-1)*MAX(0,MIN(1,YEARFRAC(I$4,MIN(Assets!$E$2,EDATE(I$4,12)),1)*(Assets!$E$2>I$4)))+Assets!$F$2*(1+MIN(INDEX(Countries!$F$2:$F$5,MATCH(Assets!$B$2,Countries!$A$2:$A$5,0)),MAX(INDEX(Countries!$E$2:$E$5,MATCH(Assets!$B$2,Countries!$A$2:$A$5,0)),INDEX(Countries!$D$2:$D$5,MATCH(Assets!$B$2,Countries!$A$2:$A$5,0)))))^(I$3-1)*IF(Assets!$E$2<EDATE(I$4,12),(Inputs!$B$13*MAX(0,MIN(12,DATEDIF(MAX(Assets!$E$2,I$4),EDATE(I$4,12),"m")))+(1-Inputs!$B$13)*MAX(0,MAX(0,MIN(12,DATEDIF(MAX(Assets!$E$2,I$4),EDATE(I$4,12),"m")))-MAX(0,Inputs!$B$12-IF(Assets!$E$2<I$4,DATEDIF(Assets!$E$2,I$4,"m"),0))))/12,0))*INDEX(Countries!$C$2:$C$5,MATCH(Assets!$B$2,Countries!$A$2:$A$5,0)),0) -> 3609861.6 | ... L5: =IF(AND(L$3>=1,L$3<=Inputs!$B$11,OR(Assets!$G$2="",L$4<Assets!$G$2)),Assets!$C$2*(Assets!$D$2*(1+MIN(INDEX(Countries!$F$2:$F$5,MATCH(Assets!$B$2,Countries!$A$2:$A$5,0)),MAX(INDEX(Countries!$E$2:$E$5,MATCH(Assets!$B$2,Countries!$A$2:$A$5,0)),INDEX(Countries!$D$2:$D$5,MATCH(Assets!$B$2,Countries!$A$2:$A$5,0)))))^(L$3-1)*MAX(0,MIN(1,YEARFRAC(L$4,MIN(Assets!$E$2,EDATE(L$4,12)),1)*(Assets!$E$2>L$4)))+Assets!$F$2*(1+MIN(INDEX(Countries!$F$2:$F$5,MATCH(Assets!$B$2,Countries!$A$2:$A$5,0)),MAX(INDEX(Countries!$E$2:$E$5,MATCH(Assets!$B$2,Countries!$A$2:$A$5,0)),INDEX(Countries!$D$2:$D$5,MATCH(Assets!$B$2,Countries!$A$2:$A$5,0)))))^(L$3-1)*IF(Assets!$E$2<EDATE(L$4,12),(Inputs!$B$13*MAX(0,MIN(12,DATEDIF(MAX(Assets!$E$2,L$4),EDATE(L$4,12),"m")))+(1-Inputs!$B$13)*MAX(0,MAX(0,MIN(12,DATEDIF(MAX(Assets!$E$2,L$4),EDATE(L$4,12),"m")))-MAX(0,Inputs!$B$12-IF(Assets!$E$2<L$4,DATEDIF(Assets!$E$2,L$4,"m"),0))))/12,0))*INDEX(Countries!$C$2:$C$5,MATCH(Assets!$B$2,Countries!$A$2:$A$5,0)),0) -> 0
A6: Hamburg Nord · disposal (EUR) | B6: =IF(AND(Assets!$G$2<>"",Assets!$G$2>=B$4,Assets!$G$2<EDATE(B$4,12)),Assets!$C$2*Assets!$F$2*(1+MIN(INDEX(Countries!$F$2:$F$5,MATCH(Assets!$B$2,Countries!$A$2:$A$5,0)),MAX(INDEX(Countries!$E$2:$E$5,MATCH(Assets!$B$2,Countries!$A$2:$A$5,0)),INDEX(Countries!$D$2:$D$5,MATCH(Assets!$B$2,Countries!$A$2:$A$5,0)))))^(B$3-1)*INDEX(Countries!$C$2:$C$5,MATCH(Assets!$B$2,Countries!$A$2:$A$5,0))/Assets!$H$2,0) -> 0 | C6: =IF(AND(Assets!$G$2<>"",Assets!$G$2>=C$4,Assets!$G$2<EDATE(C$4,12)),Assets!$C$2*Assets!$F$2*(1+MIN(INDEX(Countries!$F$2:$F$5,MATCH(Assets!$B$2,Countries!$A$2:$A$5,0)),MAX(INDEX(Countries!$E$2:$E$5,MATCH(Assets!$B$2,Countries!$A$2:$A$5,0)),INDEX(Countries!$D$2:$D$5,MATCH(Assets!$B$2,Countries!$A$2:$A$5,0)))))^(C$3-1)*INDEX(Countries!$C$2:$C$5,MATCH(Assets!$B$2,Countries!$A$2:$A$5,0))/Assets!$H$2,0) -> 0 | D6: =IF(AND(Assets!$G$2<>"",Assets!$G$2>=D$4,Assets!$G$2<EDATE(D$4,12)),Assets!$C$2*Assets!$F$2*(1+MIN(INDEX(Countries!$F$2:$F$5,MATCH(Assets!$B$2,Countries!$A$2:$A$5,0)),MAX(INDEX(Countries!$E$2:$E$5,MATCH(Assets!$B$2,Countries!$A$2:$A$5,0)),INDEX(Countries!$D$2:$D$5,MATCH(Assets!$B$2,Countries!$A$2:$A$5,0)))))^(D$3-1)*INDEX(Countries!$C$2:$C$5,MATCH(Assets!$B$2,Countries!$A$2:$A$5,0))/Assets!$H$2,0) -> 0 | E6: =IF(AND(Assets!$G$2<>"",Assets!$G$2>=E$4,Assets!$G$2<EDATE(E$4,12)),Assets!$C$2*Assets!$F$2*(1+MIN(INDEX(Countries!$F$2:$F$5,MATCH(Assets!$B$2,Countries!$A$2:$A$5,0)),MAX(INDEX(Countries!$E$2:$E$5,MATCH(Assets!$B$2,Countries!$A$2:$A$5,0)),INDEX(Countries!$D$2:$D$5,MATCH(Assets!$B$2,Countries!$A$2:$A$5,0)))))^(E$3-1)*INDEX(Countries!$C$2:$C$5,MATCH(Assets!$B$2,Countries!$A$2:$A$5,0))/Assets!$H$2,0) -> 0 | F6: =IF(AND(Assets!$G$2<>"",Assets!$G$2>=F$4,Assets!$G$2<EDATE(F$4,12)),Assets!$C$2*Assets!$F$2*(1+MIN(INDEX(Countries!$F$2:$F$5,MATCH(Assets!$B$2,Countries!$A$2:$A$5,0)),MAX(INDEX(Countries!$E$2:$E$5,MATCH(Assets!$B$2,Countries!$A$2:$A$5,0)),INDEX(Countries!$D$2:$D$5,MATCH(Assets!$B$2,Countries!$A$2:$A$5,0)))))^(F$3-1)*INDEX(Countries!$C$2:$C$5,MATCH(Assets!$B$2,Countries!$A$2:$A$5,0))/Assets!$H$2,0) -> 0 | G6: =IF(AND(Assets!$G$2<>"",Assets!$G$2>=G$4,Assets!$G$2<EDATE(G$4,12)),Assets!$C$2*Assets!$F$2*(1+MIN(INDEX(Countries!$F$2:$F$5,MATCH(Assets!$B$2,Countries!$A$2:$A$5,0)),MAX(INDEX(Countries!$E$2:$E$5,MATCH(Assets!$B$2,Countries!$A$2:$A$5,0)),INDEX(Countries!$D$2:$D$5,MATCH(Assets!$B$2,Countries!$A$2:$A$5,0)))))^(G$3-1)*INDEX(Countries!$C$2:$C$5,MATCH(Assets!$B$2,Countries!$A$2:$A$5,0))/Assets!$H$2,0) -> 0 | H6: =IF(AND(Assets!$G$2<>"",Assets!$G$2>=H$4,Assets!$G$2<EDATE(H$4,12)),Assets!$C$2*Assets!$F$2*(1+MIN(INDEX(Countries!$F$2:$F$5,MATCH(Assets!$B$2,Countries!$A$2:$A$5,0)),MAX(INDEX(Countries!$E$2:$E$5,MATCH(Assets!$B$2,Countries!$A$2:$A$5,0)),INDEX(Countries!$D$2:$D$5,MATCH(Assets!$B$2,Countries!$A$2:$A$5,0)))))^(H$3-1)*INDEX(Countries!$C$2:$C$5,MATCH(Assets!$B$2,Countries!$A$2:$A$5,0))/Assets!$H$2,0) -> 0 | I6: =IF(AND(Assets!$G$2<>"",Assets!$G$2>=I$4,Assets!$G$2<EDATE(I$4,12)),Assets!$C$2*Assets!$F$2*(1+MIN(INDEX(Countries!$F$2:$F$5,MATCH(Assets!$B$2,Countries!$A$2:$A$5,0)),MAX(INDEX(Countries!$E$2:$E$5,MATCH(Assets!$B$2,Countries!$A$2:$A$5,0)),INDEX(Countries!$D$2:$D$5,MATCH(Assets!$B$2,Countries!$A$2:$A$5,0)))))^(I$3-1)*INDEX(Countries!$C$2:$C$5,MATCH(Assets!$B$2,Countries!$A$2:$A$5,0))/Assets!$H$2,0) -> 0 | ... L6: =IF(AND(Assets!$G$2<>"",Assets!$G$2>=L$4,Assets!$G$2<EDATE(L$4,12)),Assets!$C$2*Assets!$F$2*(1+MIN(INDEX(Countries!$F$2:$F$5,MATCH(Assets!$B$2,Countries!$A$2:$A$5,0)),MAX(INDEX(Countries!$E$2:$E$5,MATCH(Assets!$B$2,Countries!$A$2:$A$5,0)),INDEX(Countries!$D$2:$D$5,MATCH(Assets!$B$2,Countries!$A$2:$A$5,0)))))^(L$3-1)*INDEX(Countries!$C$2:$C$5,MATCH(Assets!$B$2,Countries!$A$2:$A$5,0))/Assets!$H$2,0) -> 0
A7: Leipzig Park · rent (EUR) | B7: =IF(AND(B$3>=1,B$3<=Inputs!$B$11,OR(Assets!$G$3="",B$4<Assets!$G$3)),Assets!$C$3*(Assets!$D$3*(1+MIN(INDEX(Countries!$F$2:$F$5,MATCH(Assets!$B$3,Countries!$A$2:$A$5,0)),MAX(INDEX(Countries!$E$2:$E$5,MATCH(Assets!$B$3,Countries!$A$2:$A$5,0)),INDEX(Countries!$D$2:$D$5,MATCH(Assets!$B$3,Countries!$A$2:$A$5,0)))))^(B$3-1)*MAX(0,MIN(1,YEARFRAC(B$4,MIN(Assets!$E$3,EDATE(B$4,12)),1)*(Assets!$E$3>B$4)))+Assets!$F$3*(1+MIN(INDEX(Countries!$F$2:$F$5,MATCH(Assets!$B$3,Countries!$A$2:$A$5,0)),MAX(INDEX(Countries!$E$2:$E$5,MATCH(Assets!$B$3,Countries!$A$2:$A$5,0)),INDEX(Countries!$D$2:$D$5,MATCH(Assets!$B$3,Countries!$A$2:$A$5,0)))))^(B$3-1)*IF(Assets!$E$3<EDATE(B$4,12),(Inputs!$B$13*MAX(0,MIN(12,DATEDIF(MAX(Assets!$E$3,B$4),EDATE(B$4,12),"m")))+(1-Inputs!$B$13)*MAX(0,MAX(0,MIN(12,DATEDIF(MAX(Assets!$E$3,B$4),EDATE(B$4,12),"m")))-MAX(0,Inputs!$B$12-IF(Assets!$E$3<B$4,DATEDIF(Assets!$E$3,B$4,"m"),0))))/12,0))*INDEX(Countries!$C$2:$C$5,MATCH(Assets!$B$3,Countries!$A$2:$A$5,0)),0) -> 0 | C7: =IF(AND(C$3>=1,C$3<=Inputs!$B$11,OR(Assets!$G$3="",C$4<Assets!$G$3)),Assets!$C$3*(Assets!$D$3*(1+MIN(INDEX(Countries!$F$2:$F$5,MATCH(Assets!$B$3,Countries!$A$2:$A$5,0)),MAX(INDEX(Countries!$E$2:$E$5,MATCH(Assets!$B$3,Countries!$A$2:$A$5,0)),INDEX(Countries!$D$2:$D$5,MATCH(Assets!$B$3,Countries!$A$2:$A$5,0)))))^(C$3-1)*MAX(0,MIN(1,YEARFRAC(C$4,MIN(Assets!$E$3,EDATE(C$4,12)),1)*(Assets!$E$3>C$4)))+Assets!$F$3*(1+MIN(INDEX(Countries!$F$2:$F$5,MATCH(Assets!$B$3,Countries!$A$2:$A$5,0)),MAX(INDEX(Countries!$E$2:$E$5,MATCH(Assets!$B$3,Countries!$A$2:$A$5,0)),INDEX(Countries!$D$2:$D$5,MATCH(Assets!$B$3,Countries!$A$2:$A$5,0)))))^(C$3-1)*IF(Assets!$E$3<EDATE(C$4,12),(Inputs!$B$13*MAX(0,MIN(12,DATEDIF(MAX(Assets!$E$3,C$4),EDATE(C$4,12),"m")))+(1-Inputs!$B$13)*MAX(0,MAX(0,MIN(12,DATEDIF(MAX(Assets!$E$3,C$4),EDATE(C$4,12),"m")))-MAX(0,Inputs!$B$12-IF(Assets!$E$3<C$4,DATEDIF(Assets!$E$3,C$4,"m"),0))))/12,0))*INDEX(Countries!$C$2:$C$5,MATCH(Assets!$B$3,Countries!$A$2:$A$5,0)),0) -> 3355000 | D7: =IF(AND(D$3>=1,D$3<=Inputs!$B$11,OR(Assets!$G$3="",D$4<Assets!$G$3)),Assets!$C$3*(Assets!$D$3*(1+MIN(INDEX(Countries!$F$2:$F$5,MATCH(Assets!$B$3,Countries!$A$2:$A$5,0)),MAX(INDEX(Countries!$E$2:$E$5,MATCH(Assets!$B$3,Countries!$A$2:$A$5,0)),INDEX(Countries!$D$2:$D$5,MATCH(Assets!$B$3,Countries!$A$2:$A$5,0)))))^(D$3-1)*MAX(0,MIN(1,YEARFRAC(D$4,MIN(Assets!$E$3,EDATE(D$4,12)),1)*(Assets!$E$3>D$4)))+Assets!$F$3*(1+MIN(INDEX(Countries!$F$2:$F$5,MATCH(Assets!$B$3,Countries!$A$2:$A$5,0)),MAX(INDEX(Countries!$E$2:$E$5,MATCH(Assets!$B$3,Countries!$A$2:$A$5,0)),INDEX(Countries!$D$2:$D$5,MATCH(Assets!$B$3,Countries!$A$2:$A$5,0)))))^(D$3-1)*IF(Assets!$E$3<EDATE(D$4,12),(Inputs!$B$13*MAX(0,MIN(12,DATEDIF(MAX(Assets!$E$3,D$4),EDATE(D$4,12),"m")))+(1-Inputs!$B$13)*MAX(0,MAX(0,MIN(12,DATEDIF(MAX(Assets!$E$3,D$4),EDATE(D$4,12),"m")))-MAX(0,Inputs!$B$12-IF(Assets!$E$3<D$4,DATEDIF(Assets!$E$3,D$4,"m"),0))))/12,0))*INDEX(Countries!$C$2:$C$5,MATCH(Assets!$B$3,Countries!$A$2:$A$5,0)),0) -> 3118633 | E7: =IF(AND(E$3>=1,E$3<=Inputs!$B$11,OR(Assets!$G$3="",E$4<Assets!$G$3)),Assets!$C$3*(Assets!$D$3*(1+MIN(INDEX(Countries!$F$2:$F$5,MATCH(Assets!$B$3,Countries!$A$2:$A$5,0)),MAX(INDEX(Countries!$E$2:$E$5,MATCH(Assets!$B$3,Countries!$A$2:$A$5,0)),INDEX(Countries!$D$2:$D$5,MATCH(Assets!$B$3,Countries!$A$2:$A$5,0)))))^(E$3-1)*MAX(0,MIN(1,YEARFRAC(E$4,MIN(Assets!$E$3,EDATE(E$4,12)),1)*(Assets!$E$3>E$4)))+Assets!$F$3*(1+MIN(INDEX(Countries!$F$2:$F$5,MATCH(Assets!$B$3,Countries!$A$2:$A$5,0)),MAX(INDEX(Countries!$E$2:$E$5,MATCH(Assets!$B$3,Countries!$A$2:$A$5,0)),INDEX(Countries!$D$2:$D$5,MATCH(Assets!$B$3,Countries!$A$2:$A$5,0)))))^(E$3-1)*IF(Assets!$E$3<EDATE(E$4,12),(Inputs!$B$13*MAX(0,MIN(12,DATEDIF(MAX(Assets!$E$3,E$4),EDATE(E$4,12),"m")))+(1-Inputs!$B$13)*MAX(0,MAX(0,MIN(12,DATEDIF(MAX(Assets!$E$3,E$4),EDATE(E$4,12),"m")))-MAX(0,Inputs!$B$12-IF(Assets!$E$3<E$4,DATEDIF(Assets!$E$3,E$4,"m"),0))))/12,0))*INDEX(Countries!$C$2:$C$5,MATCH(Assets!$B$3,Countries!$A$2:$A$5,0)),0) -> 3058249.2 | F7: =IF(AND(F$3>=1,F$3<=Inputs!$B$11,OR(Assets!$G$3="",F$4<Assets!$G$3)),Assets!$C$3*(Assets!$D$3*(1+MIN(INDEX(Countries!$F$2:$F$5,MATCH(Assets!$B$3,Countries!$A$2:$A$5,0)),MAX(INDEX(Countries!$E$2:$E$5,MATCH(Assets!$B$3,Countries!$A$2:$A$5,0)),INDEX(Countries!$D$2:$D$5,MATCH(Assets!$B$3,Countries!$A$2:$A$5,0)))))^(F$3-1)*MAX(0,MIN(1,YEARFRAC(F$4,MIN(Assets!$E$3,EDATE(F$4,12)),1)*(Assets!$E$3>F$4)))+Assets!$F$3*(1+MIN(INDEX(Countries!$F$2:$F$5,MATCH(Assets!$B$3,Countries!$A$2:$A$5,0)),MAX(INDEX(Countries!$E$2:$E$5,MATCH(Assets!$B$3,Countries!$A$2:$A$5,0)),INDEX(Countries!$D$2:$D$5,MATCH(Assets!$B$3,Countries!$A$2:$A$5,0)))))^(F$3-1)*IF(Assets!$E$3<EDATE(F$4,12),(Inputs!$B$13*MAX(0,MIN(12,DATEDIF(MAX(Assets!$E$3,F$4),EDATE(F$4,12),"m")))+(1-Inputs!$B$13)*MAX(0,MAX(0,MIN(12,DATEDIF(MAX(Assets!$E$3,F$4),EDATE(F$4,12),"m")))-MAX(0,Inputs!$B$12-IF(Assets!$E$3<F$4,DATEDIF(Assets!$E$3,F$4,"m"),0))))/12,0))*INDEX(Countries!$C$2:$C$5,MATCH(Assets!$B$3,Countries!$A$2:$A$5,0)),0) -> 0 | G7: =IF(AND(G$3>=1,G$3<=Inputs!$B$11,OR(Assets!$G$3="",G$4<Assets!$G$3)),Assets!$C$3*(Assets!$D$3*(1+MIN(INDEX(Countries!$F$2:$F$5,MATCH(Assets!$B$3,Countries!$A$2:$A$5,0)),MAX(INDEX(Countries!$E$2:$E$5,MATCH(Assets!$B$3,Countries!$A$2:$A$5,0)),INDEX(Countries!$D$2:$D$5,MATCH(Assets!$B$3,Countries!$A$2:$A$5,0)))))^(G$3-1)*MAX(0,MIN(1,YEARFRAC(G$4,MIN(Assets!$E$3,EDATE(G$4,12)),1)*(Assets!$E$3>G$4)))+Assets!$F$3*(1+MIN(INDEX(Countries!$F$2:$F$5,MATCH(Assets!$B$3,Countries!$A$2:$A$5,0)),MAX(INDEX(Countries!$E$2:$E$5,MATCH(Assets!$B$3,Countries!$A$2:$A$5,0)),INDEX(Countries!$D$2:$D$5,MATCH(Assets!$B$3,Countries!$A$2:$A$5,0)))))^(G$3-1)*IF(Assets!$E$3<EDATE(G$4,12),(Inputs!$B$13*MAX(0,MIN(12,DATEDIF(MAX(Assets!$E$3,G$4),EDATE(G$4,12),"m")))+(1-Inputs!$B$13)*MAX(0,MAX(0,MIN(12,DATEDIF(MAX(Assets!$E$3,G$4),EDATE(G$4,12),"m")))-MAX(0,Inputs!$B$12-IF(Assets!$E$3<G$4,DATEDIF(Assets!$E$3,G$4,"m"),0))))/12,0))*INDEX(Countries!$C$2:$C$5,MATCH(Assets!$B$3,Countries!$A$2:$A$5,0)),0) -> 0 | H7: =IF(AND(H$3>=1,H$3<=Inputs!$B$11,OR(Assets!$G$3="",H$4<Assets!$G$3)),Assets!$C$3*(Assets!$D$3*(1+MIN(INDEX(Countries!$F$2:$F$5,MATCH(Assets!$B$3,Countries!$A$2:$A$5,0)),MAX(INDEX(Countries!$E$2:$E$5,MATCH(Assets!$B$3,Countries!$A$2:$A$5,0)),INDEX(Countries!$D$2:$D$5,MATCH(Assets!$B$3,Countries!$A$2:$A$5,0)))))^(H$3-1)*MAX(0,MIN(1,YEARFRAC(H$4,MIN(Assets!$E$3,EDATE(H$4,12)),1)*(Assets!$E$3>H$4)))+Assets!$F$3*(1+MIN(INDEX(Countries!$F$2:$F$5,MATCH(Assets!$B$3,Countries!$A$2:$A$5,0)),MAX(INDEX(Countries!$E$2:$E$5,MATCH(Assets!$B$3,Countries!$A$2:$A$5,0)),INDEX(Countries!$D$2:$D$5,MATCH(Assets!$B$3,Countries!$A$2:$A$5,0)))))^(H$3-1)*IF(Assets!$E$3<EDATE(H$4,12),(Inputs!$B$13*MAX(0,MIN(12,DATEDIF(MAX(Assets!$E$3,H$4),EDATE(H$4,12),"m")))+(1-Inputs!$B$13)*MAX(0,MAX(0,MIN(12,DATEDIF(MAX(Assets!$E$3,H$4),EDATE(H$4,12),"m")))-MAX(0,Inputs!$B$12-IF(Assets!$E$3<H$4,DATEDIF(Assets!$E$3,H$4,"m"),0))))/12,0))*INDEX(Countries!$C$2:$C$5,MATCH(Assets!$B$3,Countries!$A$2:$A$5,0)),0) -> 0 | I7: =IF(AND(I$3>=1,I$3<=Inputs!$B$11,OR(Assets!$G$3="",I$4<Assets!$G$3)),Assets!$C$3*(Assets!$D$3*(1+MIN(INDEX(Countries!$F$2:$F$5,MATCH(Assets!$B$3,Countries!$A$2:$A$5,0)),MAX(INDEX(Countries!$E$2:$E$5,MATCH(Assets!$B$3,Countries!$A$2:$A$5,0)),INDEX(Countries!$D$2:$D$5,MATCH(Assets!$B$3,Countries!$A$2:$A$5,0)))))^(I$3-1)*MAX(0,MIN(1,YEARFRAC(I$4,MIN(Assets!$E$3,EDATE(I$4,12)),1)*(Assets!$E$3>I$4)))+Assets!$F$3*(1+MIN(INDEX(Countries!$F$2:$F$5,MATCH(Assets!$B$3,Countries!$A$2:$A$5,0)),MAX(INDEX(Countries!$E$2:$E$5,MATCH(Assets!$B$3,Countries!$A$2:$A$5,0)),INDEX(Countries!$D$2:$D$5,MATCH(Assets!$B$3,Countries!$A$2:$A$5,0)))))^(I$3-1)*IF(Assets!$E$3<EDATE(I$4,12),(Inputs!$B$13*MAX(0,MIN(12,DATEDIF(MAX(Assets!$E$3,I$4),EDATE(I$4,12),"m")))+(1-Inputs!$B$13)*MAX(0,MAX(0,MIN(12,DATEDIF(MAX(Assets!$E$3,I$4),EDATE(I$4,12),"m")))-MAX(0,Inputs!$B$12-IF(Assets!$E$3<I$4,DATEDIF(Assets!$E$3,I$4,"m"),0))))/12,0))*INDEX(Countries!$C$2:$C$5,MATCH(Assets!$B$3,Countries!$A$2:$A$5,0)),0) -> 0 | ... L7: =IF(AND(L$3>=1,L$3<=Inputs!$B$11,OR(Assets!$G$3="",L$4<Assets!$G$3)),Assets!$C$3*(Assets!$D$3*(1+MIN(INDEX(Countries!$F$2:$F$5,MATCH(Assets!$B$3,Countries!$A$2:$A$5,0)),MAX(INDEX(Countries!$E$2:$E$5,MATCH(Assets!$B$3,Countries!$A$2:$A$5,0)),INDEX(Countries!$D$2:$D$5,MATCH(Assets!$B$3,Countries!$A$2:$A$5,0)))))^(L$3-1)*MAX(0,MIN(1,YEARFRAC(L$4,MIN(Assets!$E$3,EDATE(L$4,12)),1)*(Assets!$E$3>L$4)))+Assets!$F$3*(1+MIN(INDEX(Countries!$F$2:$F$5,MATCH(Assets!$B$3,Countries!$A$2:$A$5,0)),MAX(INDEX(Countries!$E$2:$E$5,MATCH(Assets!$B$3,Countries!$A$2:$A$5,0)),INDEX(Countries!$D$2:$D$5,MATCH(Assets!$B$3,Countries!$A$2:$A$5,0)))))^(L$3-1)*IF(Assets!$E$3<EDATE(L$4,12),(Inputs!$B$13*MAX(0,MIN(12,DATEDIF(MAX(Assets!$E$3,L$4),EDATE(L$4,12),"m")))+(1-Inputs!$B$13)*MAX(0,MAX(0,MIN(12,DATEDIF(MAX(Assets!$E$3,L$4),EDATE(L$4,12),"m")))-MAX(0,Inputs!$B$12-IF(Assets!$E$3<L$4,DATEDIF(Assets!$E$3,L$4,"m"),0))))/12,0))*INDEX(Countries!$C$2:$C$5,MATCH(Assets!$B$3,Countries!$A$2:$A$5,0)),0) -> 0
A8: Leipzig Park · disposal (EUR) | B8: =IF(AND(Assets!$G$3<>"",Assets!$G$3>=B$4,Assets!$G$3<EDATE(B$4,12)),Assets!$C$3*Assets!$F$3*(1+MIN(INDEX(Countries!$F$2:$F$5,MATCH(Assets!$B$3,Countries!$A$2:$A$5,0)),MAX(INDEX(Countries!$E$2:$E$5,MATCH(Assets!$B$3,Countries!$A$2:$A$5,0)),INDEX(Countries!$D$2:$D$5,MATCH(Assets!$B$3,Countries!$A$2:$A$5,0)))))^(B$3-1)*INDEX(Countries!$C$2:$C$5,MATCH(Assets!$B$3,Countries!$A$2:$A$5,0))/Assets!$H$3,0) -> 0 | C8: =IF(AND(Assets!$G$3<>"",Assets!$G$3>=C$4,Assets!$G$3<EDATE(C$4,12)),Assets!$C$3*Assets!$F$3*(1+MIN(INDEX(Countries!$F$2:$F$5,MATCH(Assets!$B$3,Countries!$A$2:$A$5,0)),MAX(INDEX(Countries!$E$2:$E$5,MATCH(Assets!$B$3,Countries!$A$2:$A$5,0)),INDEX(Countries!$D$2:$D$5,MATCH(Assets!$B$3,Countries!$A$2:$A$5,0)))))^(C$3-1)*INDEX(Countries!$C$2:$C$5,MATCH(Assets!$B$3,Countries!$A$2:$A$5,0))/Assets!$H$3,0) -> 0 | D8: =IF(AND(Assets!$G$3<>"",Assets!$G$3>=D$4,Assets!$G$3<EDATE(D$4,12)),Assets!$C$3*Assets!$F$3*(1+MIN(INDEX(Countries!$F$2:$F$5,MATCH(Assets!$B$3,Countries!$A$2:$A$5,0)),MAX(INDEX(Countries!$E$2:$E$5,MATCH(Assets!$B$3,Countries!$A$2:$A$5,0)),INDEX(Countries!$D$2:$D$5,MATCH(Assets!$B$3,Countries!$A$2:$A$5,0)))))^(D$3-1)*INDEX(Countries!$C$2:$C$5,MATCH(Assets!$B$3,Countries!$A$2:$A$5,0))/Assets!$H$3,0) -> 0 | E8: =IF(AND(Assets!$G$3<>"",Assets!$G$3>=E$4,Assets!$G$3<EDATE(E$4,12)),Assets!$C$3*Assets!$F$3*(1+MIN(INDEX(Countries!$F$2:$F$5,MATCH(Assets!$B$3,Countries!$A$2:$A$5,0)),MAX(INDEX(Countries!$E$2:$E$5,MATCH(Assets!$B$3,Countries!$A$2:$A$5,0)),INDEX(Countries!$D$2:$D$5,MATCH(Assets!$B$3,Countries!$A$2:$A$5,0)))))^(E$3-1)*INDEX(Countries!$C$2:$C$5,MATCH(Assets!$B$3,Countries!$A$2:$A$5,0))/Assets!$H$3,0) -> 73515605 | F8: =IF(AND(Assets!$G$3<>"",Assets!$G$3>=F$4,Assets!$G$3<EDATE(F$4,12)),Assets!$C$3*Assets!$F$3*(1+MIN(INDEX(Countries!$F$2:$F$5,MATCH(Assets!$B$3,Countries!$A$2:$A$5,0)),MAX(INDEX(Countries!$E$2:$E$5,MATCH(Assets!$B$3,Countries!$A$2:$A$5,0)),INDEX(Countries!$D$2:$D$5,MATCH(Assets!$B$3,Countries!$A$2:$A$5,0)))))^(F$3-1)*INDEX(Countries!$C$2:$C$5,MATCH(Assets!$B$3,Countries!$A$2:$A$5,0))/Assets!$H$3,0) -> 0 | G8: =IF(AND(Assets!$G$3<>"",Assets!$G$3>=G$4,Assets!$G$3<EDATE(G$4,12)),Assets!$C$3*Assets!$F$3*(1+MIN(INDEX(Countries!$F$2:$F$5,MATCH(Assets!$B$3,Countries!$A$2:$A$5,0)),MAX(INDEX(Countries!$E$2:$E$5,MATCH(Assets!$B$3,Countries!$A$2:$A$5,0)),INDEX(Countries!$D$2:$D$5,MATCH(Assets!$B$3,Countries!$A$2:$A$5,0)))))^(G$3-1)*INDEX(Countries!$C$2:$C$5,MATCH(Assets!$B$3,Countries!$A$2:$A$5,0))/Assets!$H$3,0) -> 0 | H8: =IF(AND(Assets!$G$3<>"",Assets!$G$3>=H$4,Assets!$G$3<EDATE(H$4,12)),Assets!$C$3*Assets!$F$3*(1+MIN(INDEX(Countries!$F$2:$F$5,MATCH(Assets!$B$3,Countries!$A$2:$A$5,0)),MAX(INDEX(Countries!$E$2:$E$5,MATCH(Assets!$B$3,Countries!$A$2:$A$5,0)),INDEX(Countries!$D$2:$D$5,MATCH(Assets!$B$3,Countries!$A$2:$A$5,0)))))^(H$3-1)*INDEX(Countries!$C$2:$C$5,MATCH(Assets!$B$3,Countries!$A$2:$A$5,0))/Assets!$H$3,0) -> 0 | I8: =IF(AND(Assets!$G$3<>"",Assets!$G$3>=I$4,Assets!$G$3<EDATE(I$4,12)),Assets!$C$3*Assets!$F$3*(1+MIN(INDEX(Countries!$F$2:$F$5,MATCH(Assets!$B$3,Countries!$A$2:$A$5,0)),MAX(INDEX(Countries!$E$2:$E$5,MATCH(Assets!$B$3,Countries!$A$2:$A$5,0)),INDEX(Countries!$D$2:$D$5,MATCH(Assets!$B$3,Countries!$A$2:$A$5,0)))))^(I$3-1)*INDEX(Countries!$C$2:$C$5,MATCH(Assets!$B$3,Countries!$A$2:$A$5,0))/Assets!$H$3,0) -> 0 | ... L8: =IF(AND(Assets!$G$3<>"",Assets!$G$3>=L$4,Assets!$G$3<EDATE(L$4,12)),Assets!$C$3*Assets!$F$3*(1+MIN(INDEX(Countries!$F$2:$F$5,MATCH(Assets!$B$3,Countries!$A$2:$A$5,0)),MAX(INDEX(Countries!$E$2:$E$5,MATCH(Assets!$B$3,Countries!$A$2:$A$5,0)),INDEX(Countries!$D$2:$D$5,MATCH(Assets!$B$3,Countries!$A$2:$A$5,0)))))^(L$3-1)*INDEX(Countries!$C$2:$C$5,MATCH(Assets!$B$3,Countries!$A$2:$A$5,0))/Assets!$H$3,0) -> 0
A9: Warsaw West · rent (EUR) | B9: =IF(AND(B$3>=1,B$3<=Inputs!$B$11,OR(Assets!$G$4="",B$4<Assets!$G$4)),Assets!$C$4*(Assets!$D$4*(1+MIN(INDEX(Countries!$F$2:$F$5,MATCH(Assets!$B$4,Countries!$A$2:$A$5,0)),MAX(INDEX(Countries!$E$2:$E$5,MATCH(Assets!$B$4,Countries!$A$2:$A$5,0)),INDEX(Countries!$D$2:$D$5,MATCH(Assets!$B$4,Countries!$A$2:$A$5,0)))))^(B$3-1)*MAX(0,MIN(1,YEARFRAC(B$4,MIN(Assets!$E$4,EDATE(B$4,12)),1)*(Assets!$E$4>B$4)))+Assets!$F$4*(1+MIN(INDEX(Countries!$F$2:$F$5,MATCH(Assets!$B$4,Countries!$A$2:$A$5,0)),MAX(INDEX(Countries!$E$2:$E$5,MATCH(Assets!$B$4,Countries!$A$2:$A$5,0)),INDEX(Countries!$D$2:$D$5,MATCH(Assets!$B$4,Countries!$A$2:$A$5,0)))))^(B$3-1)*IF(Assets!$E$4<EDATE(B$4,12),(Inputs!$B$13*MAX(0,MIN(12,DATEDIF(MAX(Assets!$E$4,B$4),EDATE(B$4,12),"m")))+(1-Inputs!$B$13)*MAX(0,MAX(0,MIN(12,DATEDIF(MAX(Assets!$E$4,B$4),EDATE(B$4,12),"m")))-MAX(0,Inputs!$B$12-IF(Assets!$E$4<B$4,DATEDIF(Assets!$E$4,B$4,"m"),0))))/12,0))*INDEX(Countries!$C$2:$C$5,MATCH(Assets!$B$4,Countries!$A$2:$A$5,0)),0) -> 0 | C9: =IF(AND(C$3>=1,C$3<=Inputs!$B$11,OR(Assets!$G$4="",C$4<Assets!$G$4)),Assets!$C$4*(Assets!$D$4*(1+MIN(INDEX(Countries!$F$2:$F$5,MATCH(Assets!$B$4,Countries!$A$2:$A$5,0)),MAX(INDEX(Countries!$E$2:$E$5,MATCH(Assets!$B$4,Countries!$A$2:$A$5,0)),INDEX(Countries!$D$2:$D$5,MATCH(Assets!$B$4,Countries!$A$2:$A$5,0)))))^(C$3-1)*MAX(0,MIN(1,YEARFRAC(C$4,MIN(Assets!$E$4,EDATE(C$4,12)),1)*(Assets!$E$4>C$4)))+Assets!$F$4*(1+MIN(INDEX(Countries!$F$2:$F$5,MATCH(Assets!$B$4,Countries!$A$2:$A$5,0)),MAX(INDEX(Countries!$E$2:$E$5,MATCH(Assets!$B$4,Countries!$A$2:$A$5,0)),INDEX(Countries!$D$2:$D$5,MATCH(Assets!$B$4,Countries!$A$2:$A$5,0)))))^(C$3-1)*IF(Assets!$E$4<EDATE(C$4,12),(Inputs!$B$13*MAX(0,MIN(12,DATEDIF(MAX(Assets!$E$4,C$4),EDATE(C$4,12),"m")))+(1-Inputs!$B$13)*MAX(0,MAX(0,MIN(12,DATEDIF(MAX(Assets!$E$4,C$4),EDATE(C$4,12),"m")))-MAX(0,Inputs!$B$12-IF(Assets!$E$4<C$4,DATEDIF(Assets!$E$4,C$4,"m"),0))))/12,0))*INDEX(Countries!$C$2:$C$5,MATCH(Assets!$B$4,Countries!$A$2:$A$5,0)),0) -> 4333680 | D9: =IF(AND(D$3>=1,D$3<=Inputs!$B$11,OR(Assets!$G$4="",D$4<Assets!$G$4)),Assets!$C$4*(Assets!$D$4*(1+MIN(INDEX(Countries!$F$2:$F$5,MATCH(Assets!$B$4,Countries!$A$2:$A$5,0)),MAX(INDEX(Countries!$E$2:$E$5,MATCH(Assets!$B$4,Countries!$A$2:$A$5,0)),INDEX(Countries!$D$2:$D$5,MATCH(Assets!$B$4,Countries!$A$2:$A$5,0)))))^(D$3-1)*MAX(0,MIN(1,YEARFRAC(D$4,MIN(Assets!$E$4,EDATE(D$4,12)),1)*(Assets!$E$4>D$4)))+Assets!$F$4*(1+MIN(INDEX(Countries!$F$2:$F$5,MATCH(Assets!$B$4,Countries!$A$2:$A$5,0)),MAX(INDEX(Countries!$E$2:$E$5,MATCH(Assets!$B$4,Countries!$A$2:$A$5,0)),INDEX(Countries!$D$2:$D$5,MATCH(Assets!$B$4,Countries!$A$2:$A$5,0)))))^(D$3-1)*IF(Assets!$E$4<EDATE(D$4,12),(Inputs!$B$13*MAX(0,MIN(12,DATEDIF(MAX(Assets!$E$4,D$4),EDATE(D$4,12),"m")))+(1-Inputs!$B$13)*MAX(0,MAX(0,MIN(12,DATEDIF(MAX(Assets!$E$4,D$4),EDATE(D$4,12),"m")))-MAX(0,Inputs!$B$12-IF(Assets!$E$4<D$4,DATEDIF(Assets!$E$4,D$4,"m"),0))))/12,0))*INDEX(Countries!$C$2:$C$5,MATCH(Assets!$B$4,Countries!$A$2:$A$5,0)),0) -> 4507027.2 | E9: =IF(AND(E$3>=1,E$3<=Inputs!$B$11,OR(Assets!$G$4="",E$4<Assets!$G$4)),Assets!$C$4*(Assets!$D$4*(1+MIN(INDEX(Countries!$F$2:$F$5,MATCH(Assets!$B$4,Countries!$A$2:$A$5,0)),MAX(INDEX(Countries!$E$2:$E$5,MATCH(Assets!$B$4,Countries!$A$2:$A$5,0)),INDEX(Countries!$D$2:$D$5,MATCH(Assets!$B$4,Countries!$A$2:$A$5,0)))))^(E$3-1)*MAX(0,MIN(1,YEARFRAC(E$4,MIN(Assets!$E$4,EDATE(E$4,12)),1)*(Assets!$E$4>E$4)))+Assets!$F$4*(1+MIN(INDEX(Countries!$F$2:$F$5,MATCH(Assets!$B$4,Countries!$A$2:$A$5,0)),MAX(INDEX(Countries!$E$2:$E$5,MATCH(Assets!$B$4,Countries!$A$2:$A$5,0)),INDEX(Countries!$D$2:$D$5,MATCH(Assets!$B$4,Countries!$A$2:$A$5,0)))))^(E$3-1)*IF(Assets!$E$4<EDATE(E$4,12),(Inputs!$B$13*MAX(0,MIN(12,DATEDIF(MAX(Assets!$E$4,E$4),EDATE(E$4,12),"m")))+(1-Inputs!$B$13)*MAX(0,MAX(0,MIN(12,DATEDIF(MAX(Assets!$E$4,E$4),EDATE(E$4,12),"m")))-MAX(0,Inputs!$B$12-IF(Assets!$E$4<E$4,DATEDIF(Assets!$E$4,E$4,"m"),0))))/12,0))*INDEX(Countries!$C$2:$C$5,MATCH(Assets!$B$4,Countries!$A$2:$A$5,0)),0) -> 4687308.3 | F9: =IF(AND(F$3>=1,F$3<=Inputs!$B$11,OR(Assets!$G$4="",F$4<Assets!$G$4)),Assets!$C$4*(Assets!$D$4*(1+MIN(INDEX(Countries!$F$2:$F$5,MATCH(Assets!$B$4,Countries!$A$2:$A$5,0)),MAX(INDEX(Countries!$E$2:$E$5,MATCH(Assets!$B$4,Countries!$A$2:$A$5,0)),INDEX(Countries!$D$2:$D$5,MATCH(Assets!$B$4,Countries!$A$2:$A$5,0)))))^(F$3-1)*MAX(0,MIN(1,YEARFRAC(F$4,MIN(Assets!$E$4,EDATE(F$4,12)),1)*(Assets!$E$4>F$4)))+Assets!$F$4*(1+MIN(INDEX(Countries!$F$2:$F$5,MATCH(Assets!$B$4,Countries!$A$2:$A$5,0)),MAX(INDEX(Countries!$E$2:$E$5,MATCH(Assets!$B$4,Countries!$A$2:$A$5,0)),INDEX(Countries!$D$2:$D$5,MATCH(Assets!$B$4,Countries!$A$2:$A$5,0)))))^(F$3-1)*IF(Assets!$E$4<EDATE(F$4,12),(Inputs!$B$13*MAX(0,MIN(12,DATEDIF(MAX(Assets!$E$4,F$4),EDATE(F$4,12),"m")))+(1-Inputs!$B$13)*MAX(0,MAX(0,MIN(12,DATEDIF(MAX(Assets!$E$4,F$4),EDATE(F$4,12),"m")))-MAX(0,Inputs!$B$12-IF(Assets!$E$4<F$4,DATEDIF(Assets!$E$4,F$4,"m"),0))))/12,0))*INDEX(Countries!$C$2:$C$5,MATCH(Assets!$B$4,Countries!$A$2:$A$5,0)),0) -> 3978946.8 | G9: =IF(AND(G$3>=1,G$3<=Inputs!$B$11,OR(Assets!$G$4="",G$4<Assets!$G$4)),Assets!$C$4*(Assets!$D$4*(1+MIN(INDEX(Countries!$F$2:$F$5,MATCH(Assets!$B$4,Countries!$A$2:$A$5,0)),MAX(INDEX(Countries!$E$2:$E$5,MATCH(Assets!$B$4,Countries!$A$2:$A$5,0)),INDEX(Countries!$D$2:$D$5,MATCH(Assets!$B$4,Countries!$A$2:$A$5,0)))))^(G$3-1)*MAX(0,MIN(1,YEARFRAC(G$4,MIN(Assets!$E$4,EDATE(G$4,12)),1)*(Assets!$E$4>G$4)))+Assets!$F$4*(1+MIN(INDEX(Countries!$F$2:$F$5,MATCH(Assets!$B$4,Countries!$A$2:$A$5,0)),MAX(INDEX(Countries!$E$2:$E$5,MATCH(Assets!$B$4,Countries!$A$2:$A$5,0)),INDEX(Countries!$D$2:$D$5,MATCH(Assets!$B$4,Countries!$A$2:$A$5,0)))))^(G$3-1)*IF(Assets!$E$4<EDATE(G$4,12),(Inputs!$B$13*MAX(0,MIN(12,DATEDIF(MAX(Assets!$E$4,G$4),EDATE(G$4,12),"m")))+(1-Inputs!$B$13)*MAX(0,MAX(0,MIN(12,DATEDIF(MAX(Assets!$E$4,G$4),EDATE(G$4,12),"m")))-MAX(0,Inputs!$B$12-IF(Assets!$E$4<G$4,DATEDIF(Assets!$E$4,G$4,"m"),0))))/12,0))*INDEX(Countries!$C$2:$C$5,MATCH(Assets!$B$4,Countries!$A$2:$A$5,0)),0) -> 4913799 | H9: =IF(AND(H$3>=1,H$3<=Inputs!$B$11,OR(Assets!$G$4="",H$4<Assets!$G$4)),Assets!$C$4*(Assets!$D$4*(1+MIN(INDEX(Countries!$F$2:$F$5,MATCH(Assets!$B$4,Countries!$A$2:$A$5,0)),MAX(INDEX(Countries!$E$2:$E$5,MATCH(Assets!$B$4,Countries!$A$2:$A$5,0)),INDEX(Countries!$D$2:$D$5,MATCH(Assets!$B$4,Countries!$A$2:$A$5,0)))))^(H$3-1)*MAX(0,MIN(1,YEARFRAC(H$4,MIN(Assets!$E$4,EDATE(H$4,12)),1)*(Assets!$E$4>H$4)))+Assets!$F$4*(1+MIN(INDEX(Countries!$F$2:$F$5,MATCH(Assets!$B$4,Countries!$A$2:$A$5,0)),MAX(INDEX(Countries!$E$2:$E$5,MATCH(Assets!$B$4,Countries!$A$2:$A$5,0)),INDEX(Countries!$D$2:$D$5,MATCH(Assets!$B$4,Countries!$A$2:$A$5,0)))))^(H$3-1)*IF(Assets!$E$4<EDATE(H$4,12),(Inputs!$B$13*MAX(0,MIN(12,DATEDIF(MAX(Assets!$E$4,H$4),EDATE(H$4,12),"m")))+(1-Inputs!$B$13)*MAX(0,MAX(0,MIN(12,DATEDIF(MAX(Assets!$E$4,H$4),EDATE(H$4,12),"m")))-MAX(0,Inputs!$B$12-IF(Assets!$E$4<H$4,DATEDIF(Assets!$E$4,H$4,"m"),0))))/12,0))*INDEX(Countries!$C$2:$C$5,MATCH(Assets!$B$4,Countries!$A$2:$A$5,0)),0) -> 5678167.8 | I9: =IF(AND(I$3>=1,I$3<=Inputs!$B$11,OR(Assets!$G$4="",I$4<Assets!$G$4)),Assets!$C$4*(Assets!$D$4*(1+MIN(INDEX(Countries!$F$2:$F$5,MATCH(Assets!$B$4,Countries!$A$2:$A$5,0)),MAX(INDEX(Countries!$E$2:$E$5,MATCH(Assets!$B$4,Countries!$A$2:$A$5,0)),INDEX(Countries!$D$2:$D$5,MATCH(Assets!$B$4,Countries!$A$2:$A$5,0)))))^(I$3-1)*MAX(0,MIN(1,YEARFRAC(I$4,MIN(Assets!$E$4,EDATE(I$4,12)),1)*(Assets!$E$4>I$4)))+Assets!$F$4*(1+MIN(INDEX(Countries!$F$2:$F$5,MATCH(Assets!$B$4,Countries!$A$2:$A$5,0)),MAX(INDEX(Countries!$E$2:$E$5,MATCH(Assets!$B$4,Countries!$A$2:$A$5,0)),INDEX(Countries!$D$2:$D$5,MATCH(Assets!$B$4,Countries!$A$2:$A$5,0)))))^(I$3-1)*IF(Assets!$E$4<EDATE(I$4,12),(Inputs!$B$13*MAX(0,MIN(12,DATEDIF(MAX(Assets!$E$4,I$4),EDATE(I$4,12),"m")))+(1-Inputs!$B$13)*MAX(0,MAX(0,MIN(12,DATEDIF(MAX(Assets!$E$4,I$4),EDATE(I$4,12),"m")))-MAX(0,Inputs!$B$12-IF(Assets!$E$4<I$4,DATEDIF(Assets!$E$4,I$4,"m"),0))))/12,0))*INDEX(Countries!$C$2:$C$5,MATCH(Assets!$B$4,Countries!$A$2:$A$5,0)),0) -> 5905294.5 | ... L9: =IF(AND(L$3>=1,L$3<=Inputs!$B$11,OR(Assets!$G$4="",L$4<Assets!$G$4)),Assets!$C$4*(Assets!$D$4*(1+MIN(INDEX(Countries!$F$2:$F$5,MATCH(Assets!$B$4,Countries!$A$2:$A$5,0)),MAX(INDEX(Countries!$E$2:$E$5,MATCH(Assets!$B$4,Countries!$A$2:$A$5,0)),INDEX(Countries!$D$2:$D$5,MATCH(Assets!$B$4,Countries!$A$2:$A$5,0)))))^(L$3-1)*MAX(0,MIN(1,YEARFRAC(L$4,MIN(Assets!$E$4,EDATE(L$4,12)),1)*(Assets!$E$4>L$4)))+Assets!$F$4*(1+MIN(INDEX(Countries!$F$2:$F$5,MATCH(Assets!$B$4,Countries!$A$2:$A$5,0)),MAX(INDEX(Countries!$E$2:$E$5,MATCH(Assets!$B$4,Countries!$A$2:$A$5,0)),INDEX(Countries!$D$2:$D$5,MATCH(Assets!$B$4,Countries!$A$2:$A$5,0)))))^(L$3-1)*IF(Assets!$E$4<EDATE(L$4,12),(Inputs!$B$13*MAX(0,MIN(12,DATEDIF(MAX(Assets!$E$4,L$4),EDATE(L$4,12),"m")))+(1-Inputs!$B$13)*MAX(0,MAX(0,MIN(12,DATEDIF(MAX(Assets!$E$4,L$4),EDATE(L$4,12),"m")))-MAX(0,Inputs!$B$12-IF(Assets!$E$4<L$4,DATEDIF(Assets!$E$4,L$4,"m"),0))))/12,0))*INDEX(Countries!$C$2:$C$5,MATCH(Assets!$B$4,Countries!$A$2:$A$5,0)),0) -> 0
A10: Warsaw West · disposal (EUR) | B10: =IF(AND(Assets!$G$4<>"",Assets!$G$4>=B$4,Assets!$G$4<EDATE(B$4,12)),Assets!$C$4*Assets!$F$4*(1+MIN(INDEX(Countries!$F$2:$F$5,MATCH(Assets!$B$4,Countries!$A$2:$A$5,0)),MAX(INDEX(Countries!$E$2:$E$5,MATCH(Assets!$B$4,Countries!$A$2:$A$5,0)),INDEX(Countries!$D$2:$D$5,MATCH(Assets!$B$4,Countries!$A$2:$A$5,0)))))^(B$3-1)*INDEX(Countries!$C$2:$C$5,MATCH(Assets!$B$4,Countries!$A$2:$A$5,0))/Assets!$H$4,0) -> 0 | C10: =IF(AND(Assets!$G$4<>"",Assets!$G$4>=C$4,Assets!$G$4<EDATE(C$4,12)),Assets!$C$4*Assets!$F$4*(1+MIN(INDEX(Countries!$F$2:$F$5,MATCH(Assets!$B$4,Countries!$A$2:$A$5,0)),MAX(INDEX(Countries!$E$2:$E$5,MATCH(Assets!$B$4,Countries!$A$2:$A$5,0)),INDEX(Countries!$D$2:$D$5,MATCH(Assets!$B$4,Countries!$A$2:$A$5,0)))))^(C$3-1)*INDEX(Countries!$C$2:$C$5,MATCH(Assets!$B$4,Countries!$A$2:$A$5,0))/Assets!$H$4,0) -> 0 | D10: =IF(AND(Assets!$G$4<>"",Assets!$G$4>=D$4,Assets!$G$4<EDATE(D$4,12)),Assets!$C$4*Assets!$F$4*(1+MIN(INDEX(Countries!$F$2:$F$5,MATCH(Assets!$B$4,Countries!$A$2:$A$5,0)),MAX(INDEX(Countries!$E$2:$E$5,MATCH(Assets!$B$4,Countries!$A$2:$A$5,0)),INDEX(Countries!$D$2:$D$5,MATCH(Assets!$B$4,Countries!$A$2:$A$5,0)))))^(D$3-1)*INDEX(Countries!$C$2:$C$5,MATCH(Assets!$B$4,Countries!$A$2:$A$5,0))/Assets!$H$4,0) -> 0 | E10: =IF(AND(Assets!$G$4<>"",Assets!$G$4>=E$4,Assets!$G$4<EDATE(E$4,12)),Assets!$C$4*Assets!$F$4*(1+MIN(INDEX(Countries!$F$2:$F$5,MATCH(Assets!$B$4,Countries!$A$2:$A$5,0)),MAX(INDEX(Countries!$E$2:$E$5,MATCH(Assets!$B$4,Countries!$A$2:$A$5,0)),INDEX(Countries!$D$2:$D$5,MATCH(Assets!$B$4,Countries!$A$2:$A$5,0)))))^(E$3-1)*INDEX(Countries!$C$2:$C$5,MATCH(Assets!$B$4,Countries!$A$2:$A$5,0))/Assets!$H$4,0) -> 0 | F10: =IF(AND(Assets!$G$4<>"",Assets!$G$4>=F$4,Assets!$G$4<EDATE(F$4,12)),Assets!$C$4*Assets!$F$4*(1+MIN(INDEX(Countries!$F$2:$F$5,MATCH(Assets!$B$4,Countries!$A$2:$A$5,0)),MAX(INDEX(Countries!$E$2:$E$5,MATCH(Assets!$B$4,Countries!$A$2:$A$5,0)),INDEX(Countries!$D$2:$D$5,MATCH(Assets!$B$4,Countries!$A$2:$A$5,0)))))^(F$3-1)*INDEX(Countries!$C$2:$C$5,MATCH(Assets!$B$4,Countries!$A$2:$A$5,0))/Assets!$H$4,0) -> 0 | G10: =IF(AND(Assets!$G$4<>"",Assets!$G$4>=G$4,Assets!$G$4<EDATE(G$4,12)),Assets!$C$4*Assets!$F$4*(1+MIN(INDEX(Countries!$F$2:$F$5,MATCH(Assets!$B$4,Countries!$A$2:$A$5,0)),MAX(INDEX(Countries!$E$2:$E$5,MATCH(Assets!$B$4,Countries!$A$2:$A$5,0)),INDEX(Countries!$D$2:$D$5,MATCH(Assets!$B$4,Countries!$A$2:$A$5,0)))))^(G$3-1)*INDEX(Countries!$C$2:$C$5,MATCH(Assets!$B$4,Countries!$A$2:$A$5,0))/Assets!$H$4,0) -> 0 | H10: =IF(AND(Assets!$G$4<>"",Assets!$G$4>=H$4,Assets!$G$4<EDATE(H$4,12)),Assets!$C$4*Assets!$F$4*(1+MIN(INDEX(Countries!$F$2:$F$5,MATCH(Assets!$B$4,Countries!$A$2:$A$5,0)),MAX(INDEX(Countries!$E$2:$E$5,MATCH(Assets!$B$4,Countries!$A$2:$A$5,0)),INDEX(Countries!$D$2:$D$5,MATCH(Assets!$B$4,Countries!$A$2:$A$5,0)))))^(H$3-1)*INDEX(Countries!$C$2:$C$5,MATCH(Assets!$B$4,Countries!$A$2:$A$5,0))/Assets!$H$4,0) -> 0 | I10: =IF(AND(Assets!$G$4<>"",Assets!$G$4>=I$4,Assets!$G$4<EDATE(I$4,12)),Assets!$C$4*Assets!$F$4*(1+MIN(INDEX(Countries!$F$2:$F$5,MATCH(Assets!$B$4,Countries!$A$2:$A$5,0)),MAX(INDEX(Countries!$E$2:$E$5,MATCH(Assets!$B$4,Countries!$A$2:$A$5,0)),INDEX(Countries!$D$2:$D$5,MATCH(Assets!$B$4,Countries!$A$2:$A$5,0)))))^(I$3-1)*INDEX(Countries!$C$2:$C$5,MATCH(Assets!$B$4,Countries!$A$2:$A$5,0))/Assets!$H$4,0) -> 0 | ... L10: =IF(AND(Assets!$G$4<>"",Assets!$G$4>=L$4,Assets!$G$4<EDATE(L$4,12)),Assets!$C$4*Assets!$F$4*(1+MIN(INDEX(Countries!$F$2:$F$5,MATCH(Assets!$B$4,Countries!$A$2:$A$5,0)),MAX(INDEX(Countries!$E$2:$E$5,MATCH(Assets!$B$4,Countries!$A$2:$A$5,0)),INDEX(Countries!$D$2:$D$5,MATCH(Assets!$B$4,Countries!$A$2:$A$5,0)))))^(L$3-1)*INDEX(Countries!$C$2:$C$5,MATCH(Assets!$B$4,Countries!$A$2:$A$5,0))/Assets!$H$4,0) -> 0
A11: Lodz Hub · rent (EUR) | B11: =IF(AND(B$3>=1,B$3<=Inputs!$B$11,OR(Assets!$G$5="",B$4<Assets!$G$5)),Assets!$C$5*(Assets!$D$5*(1+MIN(INDEX(Countries!$F$2:$F$5,MATCH(Assets!$B$5,Countries!$A$2:$A$5,0)),MAX(INDEX(Countries!$E$2:$E$5,MATCH(Assets!$B$5,Countries!$A$2:$A$5,0)),INDEX(Countries!$D$2:$D$5,MATCH(Assets!$B$5,Countries!$A$2:$A$5,0)))))^(B$3-1)*MAX(0,MIN(1,YEARFRAC(B$4,MIN(Assets!$E$5,EDATE(B$4,12)),1)*(Assets!$E$5>B$4)))+Assets!$F$5*(1+MIN(INDEX(Countries!$F$2:$F$5,MATCH(Assets!$B$5,Countries!$A$2:$A$5,0)),MAX(INDEX(Countries!$E$2:$E$5,MATCH(Assets!$B$5,Countries!$A$2:$A$5,0)),INDEX(Countries!$D$2:$D$5,MATCH(Assets!$B$5,Countries!$A$2:$A$5,0)))))^(B$3-1)*IF(Assets!$E$5<EDATE(B$4,12),(Inputs!$B$13*MAX(0,MIN(12,DATEDIF(MAX(Assets!$E$5,B$4),EDATE(B$4,12),"m")))+(1-Inputs!$B$13)*MAX(0,MAX(0,MIN(12,DATEDIF(MAX(Assets!$E$5,B$4),EDATE(B$4,12),"m")))-MAX(0,Inputs!$B$12-IF(Assets!$E$5<B$4,DATEDIF(Assets!$E$5,B$4,"m"),0))))/12,0))*INDEX(Countries!$C$2:$C$5,MATCH(Assets!$B$5,Countries!$A$2:$A$5,0)),0) -> 0 | C11: =IF(AND(C$3>=1,C$3<=Inputs!$B$11,OR(Assets!$G$5="",C$4<Assets!$G$5)),Assets!$C$5*(Assets!$D$5*(1+MIN(INDEX(Countries!$F$2:$F$5,MATCH(Assets!$B$5,Countries!$A$2:$A$5,0)),MAX(INDEX(Countries!$E$2:$E$5,MATCH(Assets!$B$5,Countries!$A$2:$A$5,0)),INDEX(Countries!$D$2:$D$5,MATCH(Assets!$B$5,Countries!$A$2:$A$5,0)))))^(C$3-1)*MAX(0,MIN(1,YEARFRAC(C$4,MIN(Assets!$E$5,EDATE(C$4,12)),1)*(Assets!$E$5>C$4)))+Assets!$F$5*(1+MIN(INDEX(Countries!$F$2:$F$5,MATCH(Assets!$B$5,Countries!$A$2:$A$5,0)),MAX(INDEX(Countries!$E$2:$E$5,MATCH(Assets!$B$5,Countries!$A$2:$A$5,0)),INDEX(Countries!$D$2:$D$5,MATCH(Assets!$B$5,Countries!$A$2:$A$5,0)))))^(C$3-1)*IF(Assets!$E$5<EDATE(C$4,12),(Inputs!$B$13*MAX(0,MIN(12,DATEDIF(MAX(Assets!$E$5,C$4),EDATE(C$4,12),"m")))+(1-Inputs!$B$13)*MAX(0,MAX(0,MIN(12,DATEDIF(MAX(Assets!$E$5,C$4),EDATE(C$4,12),"m")))-MAX(0,Inputs!$B$12-IF(Assets!$E$5<C$4,DATEDIF(Assets!$E$5,C$4,"m"),0))))/12,0))*INDEX(Countries!$C$2:$C$5,MATCH(Assets!$B$5,Countries!$A$2:$A$5,0)),0) -> 3047427.9 | D11: =IF(AND(D$3>=1,D$3<=Inputs!$B$11,OR(Assets!$G$5="",D$4<Assets!$G$5)),Assets!$C$5*(Assets!$D$5*(1+MIN(INDEX(Countries!$F$2:$F$5,MATCH(Assets!$B$5,Countries!$A$2:$A$5,0)),MAX(INDEX(Countries!$E$2:$E$5,MATCH(Assets!$B$5,Countries!$A$2:$A$5,0)),INDEX(Countries!$D$2:$D$5,MATCH(Assets!$B$5,Countries!$A$2:$A$5,0)))))^(D$3-1)*MAX(0,MIN(1,YEARFRAC(D$4,MIN(Assets!$E$5,EDATE(D$4,12)),1)*(Assets!$E$5>D$4)))+Assets!$F$5*(1+MIN(INDEX(Countries!$F$2:$F$5,MATCH(Assets!$B$5,Countries!$A$2:$A$5,0)),MAX(INDEX(Countries!$E$2:$E$5,MATCH(Assets!$B$5,Countries!$A$2:$A$5,0)),INDEX(Countries!$D$2:$D$5,MATCH(Assets!$B$5,Countries!$A$2:$A$5,0)))))^(D$3-1)*IF(Assets!$E$5<EDATE(D$4,12),(Inputs!$B$13*MAX(0,MIN(12,DATEDIF(MAX(Assets!$E$5,D$4),EDATE(D$4,12),"m")))+(1-Inputs!$B$13)*MAX(0,MAX(0,MIN(12,DATEDIF(MAX(Assets!$E$5,D$4),EDATE(D$4,12),"m")))-MAX(0,Inputs!$B$12-IF(Assets!$E$5<D$4,DATEDIF(Assets!$E$5,D$4,"m"),0))))/12,0))*INDEX(Countries!$C$2:$C$5,MATCH(Assets!$B$5,Countries!$A$2:$A$5,0)),0) -> 2456353.9 | E11: =IF(AND(E$3>=1,E$3<=Inputs!$B$11,OR(Assets!$G$5="",E$4<Assets!$G$5)),Assets!$C$5*(Assets!$D$5*(1+MIN(INDEX(Countries!$F$2:$F$5,MATCH(Assets!$B$5,Countries!$A$2:$A$5,0)),MAX(INDEX(Countries!$E$2:$E$5,MATCH(Assets!$B$5,Countries!$A$2:$A$5,0)),INDEX(Countries!$D$2:$D$5,MATCH(Assets!$B$5,Countries!$A$2:$A$5,0)))))^(E$3-1)*MAX(0,MIN(1,YEARFRAC(E$4,MIN(Assets!$E$5,EDATE(E$4,12)),1)*(Assets!$E$5>E$4)))+Assets!$F$5*(1+MIN(INDEX(Countries!$F$2:$F$5,MATCH(Assets!$B$5,Countries!$A$2:$A$5,0)),MAX(INDEX(Countries!$E$2:$E$5,MATCH(Assets!$B$5,Countries!$A$2:$A$5,0)),INDEX(Countries!$D$2:$D$5,MATCH(Assets!$B$5,Countries!$A$2:$A$5,0)))))^(E$3-1)*IF(Assets!$E$5<EDATE(E$4,12),(Inputs!$B$13*MAX(0,MIN(12,DATEDIF(MAX(Assets!$E$5,E$4),EDATE(E$4,12),"m")))+(1-Inputs!$B$13)*MAX(0,MAX(0,MIN(12,DATEDIF(MAX(Assets!$E$5,E$4),EDATE(E$4,12),"m")))-MAX(0,Inputs!$B$12-IF(Assets!$E$5<E$4,DATEDIF(Assets!$E$5,E$4,"m"),0))))/12,0))*INDEX(Countries!$C$2:$C$5,MATCH(Assets!$B$5,Countries!$A$2:$A$5,0)),0) -> 3649440.1 | F11: =IF(AND(F$3>=1,F$3<=Inputs!$B$11,OR(Assets!$G$5="",F$4<Assets!$G$5)),Assets!$C$5*(Assets!$D$5*(1+MIN(INDEX(Countries!$F$2:$F$5,MATCH(Assets!$B$5,Countries!$A$2:$A$5,0)),MAX(INDEX(Countries!$E$2:$E$5,MATCH(Assets!$B$5,Countries!$A$2:$A$5,0)),INDEX(Countries!$D$2:$D$5,MATCH(Assets!$B$5,Countries!$A$2:$A$5,0)))))^(F$3-1)*MAX(0,MIN(1,YEARFRAC(F$4,MIN(Assets!$E$5,EDATE(F$4,12)),1)*(Assets!$E$5>F$4)))+Assets!$F$5*(1+MIN(INDEX(Countries!$F$2:$F$5,MATCH(Assets!$B$5,Countries!$A$2:$A$5,0)),MAX(INDEX(Countries!$E$2:$E$5,MATCH(Assets!$B$5,Countries!$A$2:$A$5,0)),INDEX(Countries!$D$2:$D$5,MATCH(Assets!$B$5,Countries!$A$2:$A$5,0)))))^(F$3-1)*IF(Assets!$E$5<EDATE(F$4,12),(Inputs!$B$13*MAX(0,MIN(12,DATEDIF(MAX(Assets!$E$5,F$4),EDATE(F$4,12),"m")))+(1-Inputs!$B$13)*MAX(0,MAX(0,MIN(12,DATEDIF(MAX(Assets!$E$5,F$4),EDATE(F$4,12),"m")))-MAX(0,Inputs!$B$12-IF(Assets!$E$5<F$4,DATEDIF(Assets!$E$5,F$4,"m"),0))))/12,0))*INDEX(Countries!$C$2:$C$5,MATCH(Assets!$B$5,Countries!$A$2:$A$5,0)),0) -> 3795417.7 | G11: =IF(AND(G$3>=1,G$3<=Inputs!$B$11,OR(Assets!$G$5="",G$4<Assets!$G$5)),Assets!$C$5*(Assets!$D$5*(1+MIN(INDEX(Countries!$F$2:$F$5,MATCH(Assets!$B$5,Countries!$A$2:$A$5,0)),MAX(INDEX(Countries!$E$2:$E$5,MATCH(Assets!$B$5,Countries!$A$2:$A$5,0)),INDEX(Countries!$D$2:$D$5,MATCH(Assets!$B$5,Countries!$A$2:$A$5,0)))))^(G$3-1)*MAX(0,MIN(1,YEARFRAC(G$4,MIN(Assets!$E$5,EDATE(G$4,12)),1)*(Assets!$E$5>G$4)))+Assets!$F$5*(1+MIN(INDEX(Countries!$F$2:$F$5,MATCH(Assets!$B$5,Countries!$A$2:$A$5,0)),MAX(INDEX(Countries!$E$2:$E$5,MATCH(Assets!$B$5,Countries!$A$2:$A$5,0)),INDEX(Countries!$D$2:$D$5,MATCH(Assets!$B$5,Countries!$A$2:$A$5,0)))))^(G$3-1)*IF(Assets!$E$5<EDATE(G$4,12),(Inputs!$B$13*MAX(0,MIN(12,DATEDIF(MAX(Assets!$E$5,G$4),EDATE(G$4,12),"m")))+(1-Inputs!$B$13)*MAX(0,MAX(0,MIN(12,DATEDIF(MAX(Assets!$E$5,G$4),EDATE(G$4,12),"m")))-MAX(0,Inputs!$B$12-IF(Assets!$E$5<G$4,DATEDIF(Assets!$E$5,G$4,"m"),0))))/12,0))*INDEX(Countries!$C$2:$C$5,MATCH(Assets!$B$5,Countries!$A$2:$A$5,0)),0) -> 3947234.4 | H11: =IF(AND(H$3>=1,H$3<=Inputs!$B$11,OR(Assets!$G$5="",H$4<Assets!$G$5)),Assets!$C$5*(Assets!$D$5*(1+MIN(INDEX(Countries!$F$2:$F$5,MATCH(Assets!$B$5,Countries!$A$2:$A$5,0)),MAX(INDEX(Countries!$E$2:$E$5,MATCH(Assets!$B$5,Countries!$A$2:$A$5,0)),INDEX(Countries!$D$2:$D$5,MATCH(Assets!$B$5,Countries!$A$2:$A$5,0)))))^(H$3-1)*MAX(0,MIN(1,YEARFRAC(H$4,MIN(Assets!$E$5,EDATE(H$4,12)),1)*(Assets!$E$5>H$4)))+Assets!$F$5*(1+MIN(INDEX(Countries!$F$2:$F$5,MATCH(Assets!$B$5,Countries!$A$2:$A$5,0)),MAX(INDEX(Countries!$E$2:$E$5,MATCH(Assets!$B$5,Countries!$A$2:$A$5,0)),INDEX(Countries!$D$2:$D$5,MATCH(Assets!$B$5,Countries!$A$2:$A$5,0)))))^(H$3-1)*IF(Assets!$E$5<EDATE(H$4,12),(Inputs!$B$13*MAX(0,MIN(12,DATEDIF(MAX(Assets!$E$5,H$4),EDATE(H$4,12),"m")))+(1-Inputs!$B$13)*MAX(0,MAX(0,MIN(12,DATEDIF(MAX(Assets!$E$5,H$4),EDATE(H$4,12),"m")))-MAX(0,Inputs!$B$12-IF(Assets!$E$5<H$4,DATEDIF(Assets!$E$5,H$4,"m"),0))))/12,0))*INDEX(Countries!$C$2:$C$5,MATCH(Assets!$B$5,Countries!$A$2:$A$5,0)),0) -> 4105123.8 | I11: =IF(AND(I$3>=1,I$3<=Inputs!$B$11,OR(Assets!$G$5="",I$4<Assets!$G$5)),Assets!$C$5*(Assets!$D$5*(1+MIN(INDEX(Countries!$F$2:$F$5,MATCH(Assets!$B$5,Countries!$A$2:$A$5,0)),MAX(INDEX(Countries!$E$2:$E$5,MATCH(Assets!$B$5,Countries!$A$2:$A$5,0)),INDEX(Countries!$D$2:$D$5,MATCH(Assets!$B$5,Countries!$A$2:$A$5,0)))))^(I$3-1)*MAX(0,MIN(1,YEARFRAC(I$4,MIN(Assets!$E$5,EDATE(I$4,12)),1)*(Assets!$E$5>I$4)))+Assets!$F$5*(1+MIN(INDEX(Countries!$F$2:$F$5,MATCH(Assets!$B$5,Countries!$A$2:$A$5,0)),MAX(INDEX(Countries!$E$2:$E$5,MATCH(Assets!$B$5,Countries!$A$2:$A$5,0)),INDEX(Countries!$D$2:$D$5,MATCH(Assets!$B$5,Countries!$A$2:$A$5,0)))))^(I$3-1)*IF(Assets!$E$5<EDATE(I$4,12),(Inputs!$B$13*MAX(0,MIN(12,DATEDIF(MAX(Assets!$E$5,I$4),EDATE(I$4,12),"m")))+(1-Inputs!$B$13)*MAX(0,MAX(0,MIN(12,DATEDIF(MAX(Assets!$E$5,I$4),EDATE(I$4,12),"m")))-MAX(0,Inputs!$B$12-IF(Assets!$E$5<I$4,DATEDIF(Assets!$E$5,I$4,"m"),0))))/12,0))*INDEX(Countries!$C$2:$C$5,MATCH(Assets!$B$5,Countries!$A$2:$A$5,0)),0) -> 4269328.7 | ... L11: =IF(AND(L$3>=1,L$3<=Inputs!$B$11,OR(Assets!$G$5="",L$4<Assets!$G$5)),Assets!$C$5*(Assets!$D$5*(1+MIN(INDEX(Countries!$F$2:$F$5,MATCH(Assets!$B$5,Countries!$A$2:$A$5,0)),MAX(INDEX(Countries!$E$2:$E$5,MATCH(Assets!$B$5,Countries!$A$2:$A$5,0)),INDEX(Countries!$D$2:$D$5,MATCH(Assets!$B$5,Countries!$A$2:$A$5,0)))))^(L$3-1)*MAX(0,MIN(1,YEARFRAC(L$4,MIN(Assets!$E$5,EDATE(L$4,12)),1)*(Assets!$E$5>L$4)))+Assets!$F$5*(1+MIN(INDEX(Countries!$F$2:$F$5,MATCH(Assets!$B$5,Countries!$A$2:$A$5,0)),MAX(INDEX(Countries!$E$2:$E$5,MATCH(Assets!$B$5,Countries!$A$2:$A$5,0)),INDEX(Countries!$D$2:$D$5,MATCH(Assets!$B$5,Countries!$A$2:$A$5,0)))))^(L$3-1)*IF(Assets!$E$5<EDATE(L$4,12),(Inputs!$B$13*MAX(0,MIN(12,DATEDIF(MAX(Assets!$E$5,L$4),EDATE(L$4,12),"m")))+(1-Inputs!$B$13)*MAX(0,MAX(0,MIN(12,DATEDIF(MAX(Assets!$E$5,L$4),EDATE(L$4,12),"m")))-MAX(0,Inputs!$B$12-IF(Assets!$E$5<L$4,DATEDIF(Assets!$E$5,L$4,"m"),0))))/12,0))*INDEX(Countries!$C$2:$C$5,MATCH(Assets!$B$5,Countries!$A$2:$A$5,0)),0) -> 0
A12: Lodz Hub · disposal (EUR) | B12: =IF(AND(Assets!$G$5<>"",Assets!$G$5>=B$4,Assets!$G$5<EDATE(B$4,12)),Assets!$C$5*Assets!$F$5*(1+MIN(INDEX(Countries!$F$2:$F$5,MATCH(Assets!$B$5,Countries!$A$2:$A$5,0)),MAX(INDEX(Countries!$E$2:$E$5,MATCH(Assets!$B$5,Countries!$A$2:$A$5,0)),INDEX(Countries!$D$2:$D$5,MATCH(Assets!$B$5,Countries!$A$2:$A$5,0)))))^(B$3-1)*INDEX(Countries!$C$2:$C$5,MATCH(Assets!$B$5,Countries!$A$2:$A$5,0))/Assets!$H$5,0) -> 0 | C12: =IF(AND(Assets!$G$5<>"",Assets!$G$5>=C$4,Assets!$G$5<EDATE(C$4,12)),Assets!$C$5*Assets!$F$5*(1+MIN(INDEX(Countries!$F$2:$F$5,MATCH(Assets!$B$5,Countries!$A$2:$A$5,0)),MAX(INDEX(Countries!$E$2:$E$5,MATCH(Assets!$B$5,Countries!$A$2:$A$5,0)),INDEX(Countries!$D$2:$D$5,MATCH(Assets!$B$5,Countries!$A$2:$A$5,0)))))^(C$3-1)*INDEX(Countries!$C$2:$C$5,MATCH(Assets!$B$5,Countries!$A$2:$A$5,0))/Assets!$H$5,0) -> 0 | D12: =IF(AND(Assets!$G$5<>"",Assets!$G$5>=D$4,Assets!$G$5<EDATE(D$4,12)),Assets!$C$5*Assets!$F$5*(1+MIN(INDEX(Countries!$F$2:$F$5,MATCH(Assets!$B$5,Countries!$A$2:$A$5,0)),MAX(INDEX(Countries!$E$2:$E$5,MATCH(Assets!$B$5,Countries!$A$2:$A$5,0)),INDEX(Countries!$D$2:$D$5,MATCH(Assets!$B$5,Countries!$A$2:$A$5,0)))))^(D$3-1)*INDEX(Countries!$C$2:$C$5,MATCH(Assets!$B$5,Countries!$A$2:$A$5,0))/Assets!$H$5,0) -> 0 | E12: =IF(AND(Assets!$G$5<>"",Assets!$G$5>=E$4,Assets!$G$5<EDATE(E$4,12)),Assets!$C$5*Assets!$F$5*(1+MIN(INDEX(Countries!$F$2:$F$5,MATCH(Assets!$B$5,Countries!$A$2:$A$5,0)),MAX(INDEX(Countries!$E$2:$E$5,MATCH(Assets!$B$5,Countries!$A$2:$A$5,0)),INDEX(Countries!$D$2:$D$5,MATCH(Assets!$B$5,Countries!$A$2:$A$5,0)))))^(E$3-1)*INDEX(Countries!$C$2:$C$5,MATCH(Assets!$B$5,Countries!$A$2:$A$5,0))/Assets!$H$5,0) -> 0 | F12: =IF(AND(Assets!$G$5<>"",Assets!$G$5>=F$4,Assets!$G$5<EDATE(F$4,12)),Assets!$C$5*Assets!$F$5*(1+MIN(INDEX(Countries!$F$2:$F$5,MATCH(Assets!$B$5,Countries!$A$2:$A$5,0)),MAX(INDEX(Countries!$E$2:$E$5,MATCH(Assets!$B$5,Countries!$A$2:$A$5,0)),INDEX(Countries!$D$2:$D$5,MATCH(Assets!$B$5,Countries!$A$2:$A$5,0)))))^(F$3-1)*INDEX(Countries!$C$2:$C$5,MATCH(Assets!$B$5,Countries!$A$2:$A$5,0))/Assets!$H$5,0) -> 0 | G12: =IF(AND(Assets!$G$5<>"",Assets!$G$5>=G$4,Assets!$G$5<EDATE(G$4,12)),Assets!$C$5*Assets!$F$5*(1+MIN(INDEX(Countries!$F$2:$F$5,MATCH(Assets!$B$5,Countries!$A$2:$A$5,0)),MAX(INDEX(Countries!$E$2:$E$5,MATCH(Assets!$B$5,Countries!$A$2:$A$5,0)),INDEX(Countries!$D$2:$D$5,MATCH(Assets!$B$5,Countries!$A$2:$A$5,0)))))^(G$3-1)*INDEX(Countries!$C$2:$C$5,MATCH(Assets!$B$5,Countries!$A$2:$A$5,0))/Assets!$H$5,0) -> 0 | H12: =IF(AND(Assets!$G$5<>"",Assets!$G$5>=H$4,Assets!$G$5<EDATE(H$4,12)),Assets!$C$5*Assets!$F$5*(1+MIN(INDEX(Countries!$F$2:$F$5,MATCH(Assets!$B$5,Countries!$A$2:$A$5,0)),MAX(INDEX(Countries!$E$2:$E$5,MATCH(Assets!$B$5,Countries!$A$2:$A$5,0)),INDEX(Countries!$D$2:$D$5,MATCH(Assets!$B$5,Countries!$A$2:$A$5,0)))))^(H$3-1)*INDEX(Countries!$C$2:$C$5,MATCH(Assets!$B$5,Countries!$A$2:$A$5,0))/Assets!$H$5,0) -> 0 | I12: =IF(AND(Assets!$G$5<>"",Assets!$G$5>=I$4,Assets!$G$5<EDATE(I$4,12)),Assets!$C$5*Assets!$F$5*(1+MIN(INDEX(Countries!$F$2:$F$5,MATCH(Assets!$B$5,Countries!$A$2:$A$5,0)),MAX(INDEX(Countries!$E$2:$E$5,MATCH(Assets!$B$5,Countries!$A$2:$A$5,0)),INDEX(Countries!$D$2:$D$5,MATCH(Assets!$B$5,Countries!$A$2:$A$5,0)))))^(I$3-1)*INDEX(Countries!$C$2:$C$5,MATCH(Assets!$B$5,Countries!$A$2:$A$5,0))/Assets!$H$5,0) -> 0 | ... L12: =IF(AND(Assets!$G$5<>"",Assets!$G$5>=L$4,Assets!$G$5<EDATE(L$4,12)),Assets!$C$5*Assets!$F$5*(1+MIN(INDEX(Countries!$F$2:$F$5,MATCH(Assets!$B$5,Countries!$A$2:$A$5,0)),MAX(INDEX(Countries!$E$2:$E$5,MATCH(Assets!$B$5,Countries!$A$2:$A$5,0)),INDEX(Countries!$D$2:$D$5,MATCH(Assets!$B$5,Countries!$A$2:$A$5,0)))))^(L$3-1)*INDEX(Countries!$C$2:$C$5,MATCH(Assets!$B$5,Countries!$A$2:$A$5,0))/Assets!$H$5,0) -> 0
A13: Malmo Gate · rent (EUR) | B13: =IF(AND(B$3>=1,B$3<=Inputs!$B$11,OR(Assets!$G$6="",B$4<Assets!$G$6)),Assets!$C$6*(Assets!$D$6*(1+MIN(INDEX(Countries!$F$2:$F$5,MATCH(Assets!$B$6,Countries!$A$2:$A$5,0)),MAX(INDEX(Countries!$E$2:$E$5,MATCH(Assets!$B$6,Countries!$A$2:$A$5,0)),INDEX(Countries!$D$2:$D$5,MATCH(Assets!$B$6,Countries!$A$2:$A$5,0)))))^(B$3-1)*MAX(0,MIN(1,YEARFRAC(B$4,MIN(Assets!$E$6,EDATE(B$4,12)),1)*(Assets!$E$6>B$4)))+Assets!$F$6*(1+MIN(INDEX(Countries!$F$2:$F$5,MATCH(Assets!$B$6,Countries!$A$2:$A$5,0)),MAX(INDEX(Countries!$E$2:$E$5,MATCH(Assets!$B$6,Countries!$A$2:$A$5,0)),INDEX(Countries!$D$2:$D$5,MATCH(Assets!$B$6,Countries!$A$2:$A$5,0)))))^(B$3-1)*IF(Assets!$E$6<EDATE(B$4,12),(Inputs!$B$13*MAX(0,MIN(12,DATEDIF(MAX(Assets!$E$6,B$4),EDATE(B$4,12),"m")))+(1-Inputs!$B$13)*MAX(0,MAX(0,MIN(12,DATEDIF(MAX(Assets!$E$6,B$4),EDATE(B$4,12),"m")))-MAX(0,Inputs!$B$12-IF(Assets!$E$6<B$4,DATEDIF(Assets!$E$6,B$4,"m"),0))))/12,0))*INDEX(Countries!$C$2:$C$5,MATCH(Assets!$B$6,Countries!$A$2:$A$5,0)),0) -> 0 | C13: =IF(AND(C$3>=1,C$3<=Inputs!$B$11,OR(Assets!$G$6="",C$4<Assets!$G$6)),Assets!$C$6*(Assets!$D$6*(1+MIN(INDEX(Countries!$F$2:$F$5,MATCH(Assets!$B$6,Countries!$A$2:$A$5,0)),MAX(INDEX(Countries!$E$2:$E$5,MATCH(Assets!$B$6,Countries!$A$2:$A$5,0)),INDEX(Countries!$D$2:$D$5,MATCH(Assets!$B$6,Countries!$A$2:$A$5,0)))))^(C$3-1)*MAX(0,MIN(1,YEARFRAC(C$4,MIN(Assets!$E$6,EDATE(C$4,12)),1)*(Assets!$E$6>C$4)))+Assets!$F$6*(1+MIN(INDEX(Countries!$F$2:$F$5,MATCH(Assets!$B$6,Countries!$A$2:$A$5,0)),MAX(INDEX(Countries!$E$2:$E$5,MATCH(Assets!$B$6,Countries!$A$2:$A$5,0)),INDEX(Countries!$D$2:$D$5,MATCH(Assets!$B$6,Countries!$A$2:$A$5,0)))))^(C$3-1)*IF(Assets!$E$6<EDATE(C$4,12),(Inputs!$B$13*MAX(0,MIN(12,DATEDIF(MAX(Assets!$E$6,C$4),EDATE(C$4,12),"m")))+(1-Inputs!$B$13)*MAX(0,MAX(0,MIN(12,DATEDIF(MAX(Assets!$E$6,C$4),EDATE(C$4,12),"m")))-MAX(0,Inputs!$B$12-IF(Assets!$E$6<C$4,DATEDIF(Assets!$E$6,C$4,"m"),0))))/12,0))*INDEX(Countries!$C$2:$C$5,MATCH(Assets!$B$6,Countries!$A$2:$A$5,0)),0) -> 2593500 | D13: =IF(AND(D$3>=1,D$3<=Inputs!$B$11,OR(Assets!$G$6="",D$4<Assets!$G$6)),Assets!$C$6*(Assets!$D$6*(1+MIN(INDEX(Countries!$F$2:$F$5,MATCH(Assets!$B$6,Countries!$A$2:$A$5,0)),MAX(INDEX(Countries!$E$2:$E$5,MATCH(Assets!$B$6,Countries!$A$2:$A$5,0)),INDEX(Countries!$D$2:$D$5,MATCH(Assets!$B$6,Countries!$A$2:$A$5,0)))))^(D$3-1)*MAX(0,MIN(1,YEARFRAC(D$4,MIN(Assets!$E$6,EDATE(D$4,12)),1)*(Assets!$E$6>D$4)))+Assets!$F$6*(1+MIN(INDEX(Countries!$F$2:$F$5,MATCH(Assets!$B$6,Countries!$A$2:$A$5,0)),MAX(INDEX(Countries!$E$2:$E$5,MATCH(Assets!$B$6,Countries!$A$2:$A$5,0)),INDEX(Countries!$D$2:$D$5,MATCH(Assets!$B$6,Countries!$A$2:$A$5,0)))))^(D$3-1)*IF(Assets!$E$6<EDATE(D$4,12),(Inputs!$B$13*MAX(0,MIN(12,DATEDIF(MAX(Assets!$E$6,D$4),EDATE(D$4,12),"m")))+(1-Inputs!$B$13)*MAX(0,MAX(0,MIN(12,DATEDIF(MAX(Assets!$E$6,D$4),EDATE(D$4,12),"m")))-MAX(0,Inputs!$B$12-IF(Assets!$E$6<D$4,DATEDIF(Assets!$E$6,D$4,"m"),0))))/12,0))*INDEX(Countries!$C$2:$C$5,MATCH(Assets!$B$6,Countries!$A$2:$A$5,0)),0) -> 2645370 | E13: =IF(AND(E$3>=1,E$3<=Inputs!$B$11,OR(Assets!$G$6="",E$4<Assets!$G$6)),Assets!$C$6*(Assets!$D$6*(1+MIN(INDEX(Countries!$F$2:$F$5,MATCH(Assets!$B$6,Countries!$A$2:$A$5,0)),MAX(INDEX(Countries!$E$2:$E$5,MATCH(Assets!$B$6,Countries!$A$2:$A$5,0)),INDEX(Countries!$D$2:$D$5,MATCH(Assets!$B$6,Countries!$A$2:$A$5,0)))))^(E$3-1)*MAX(0,MIN(1,YEARFRAC(E$4,MIN(Assets!$E$6,EDATE(E$4,12)),1)*(Assets!$E$6>E$4)))+Assets!$F$6*(1+MIN(INDEX(Countries!$F$2:$F$5,MATCH(Assets!$B$6,Countries!$A$2:$A$5,0)),MAX(INDEX(Countries!$E$2:$E$5,MATCH(Assets!$B$6,Countries!$A$2:$A$5,0)),INDEX(Countries!$D$2:$D$5,MATCH(Assets!$B$6,Countries!$A$2:$A$5,0)))))^(E$3-1)*IF(Assets!$E$6<EDATE(E$4,12),(Inputs!$B$13*MAX(0,MIN(12,DATEDIF(MAX(Assets!$E$6,E$4),EDATE(E$4,12),"m")))+(1-Inputs!$B$13)*MAX(0,MAX(0,MIN(12,DATEDIF(MAX(Assets!$E$6,E$4),EDATE(E$4,12),"m")))-MAX(0,Inputs!$B$12-IF(Assets!$E$6<E$4,DATEDIF(Assets!$E$6,E$4,"m"),0))))/12,0))*INDEX(Countries!$C$2:$C$5,MATCH(Assets!$B$6,Countries!$A$2:$A$5,0)),0) -> 2698277.4 | F13: =IF(AND(F$3>=1,F$3<=Inputs!$B$11,OR(Assets!$G$6="",F$4<Assets!$G$6)),Assets!$C$6*(Assets!$D$6*(1+MIN(INDEX(Countries!$F$2:$F$5,MATCH(Assets!$B$6,Countries!$A$2:$A$5,0)),MAX(INDEX(Countries!$E$2:$E$5,MATCH(Assets!$B$6,Countries!$A$2:$A$5,0)),INDEX(Countries!$D$2:$D$5,MATCH(Assets!$B$6,Countries!$A$2:$A$5,0)))))^(F$3-1)*MAX(0,MIN(1,YEARFRAC(F$4,MIN(Assets!$E$6,EDATE(F$4,12)),1)*(Assets!$E$6>F$4)))+Assets!$F$6*(1+MIN(INDEX(Countries!$F$2:$F$5,MATCH(Assets!$B$6,Countries!$A$2:$A$5,0)),MAX(INDEX(Countries!$E$2:$E$5,MATCH(Assets!$B$6,Countries!$A$2:$A$5,0)),INDEX(Countries!$D$2:$D$5,MATCH(Assets!$B$6,Countries!$A$2:$A$5,0)))))^(F$3-1)*IF(Assets!$E$6<EDATE(F$4,12),(Inputs!$B$13*MAX(0,MIN(12,DATEDIF(MAX(Assets!$E$6,F$4),EDATE(F$4,12),"m")))+(1-Inputs!$B$13)*MAX(0,MAX(0,MIN(12,DATEDIF(MAX(Assets!$E$6,F$4),EDATE(F$4,12),"m")))-MAX(0,Inputs!$B$12-IF(Assets!$E$6<F$4,DATEDIF(Assets!$E$6,F$4,"m"),0))))/12,0))*INDEX(Countries!$C$2:$C$5,MATCH(Assets!$B$6,Countries!$A$2:$A$5,0)),0) -> 2752242.9 | G13: =IF(AND(G$3>=1,G$3<=Inputs!$B$11,OR(Assets!$G$6="",G$4<Assets!$G$6)),Assets!$C$6*(Assets!$D$6*(1+MIN(INDEX(Countries!$F$2:$F$5,MATCH(Assets!$B$6,Countries!$A$2:$A$5,0)),MAX(INDEX(Countries!$E$2:$E$5,MATCH(Assets!$B$6,Countries!$A$2:$A$5,0)),INDEX(Countries!$D$2:$D$5,MATCH(Assets!$B$6,Countries!$A$2:$A$5,0)))))^(G$3-1)*MAX(0,MIN(1,YEARFRAC(G$4,MIN(Assets!$E$6,EDATE(G$4,12)),1)*(Assets!$E$6>G$4)))+Assets!$F$6*(1+MIN(INDEX(Countries!$F$2:$F$5,MATCH(Assets!$B$6,Countries!$A$2:$A$5,0)),MAX(INDEX(Countries!$E$2:$E$5,MATCH(Assets!$B$6,Countries!$A$2:$A$5,0)),INDEX(Countries!$D$2:$D$5,MATCH(Assets!$B$6,Countries!$A$2:$A$5,0)))))^(G$3-1)*IF(Assets!$E$6<EDATE(G$4,12),(Inputs!$B$13*MAX(0,MIN(12,DATEDIF(MAX(Assets!$E$6,G$4),EDATE(G$4,12),"m")))+(1-Inputs!$B$13)*MAX(0,MAX(0,MIN(12,DATEDIF(MAX(Assets!$E$6,G$4),EDATE(G$4,12),"m")))-MAX(0,Inputs!$B$12-IF(Assets!$E$6<G$4,DATEDIF(Assets!$E$6,G$4,"m"),0))))/12,0))*INDEX(Countries!$C$2:$C$5,MATCH(Assets!$B$6,Countries!$A$2:$A$5,0)),0) -> 2807287.8 | H13: =IF(AND(H$3>=1,H$3<=Inputs!$B$11,OR(Assets!$G$6="",H$4<Assets!$G$6)),Assets!$C$6*(Assets!$D$6*(1+MIN(INDEX(Countries!$F$2:$F$5,MATCH(Assets!$B$6,Countries!$A$2:$A$5,0)),MAX(INDEX(Countries!$E$2:$E$5,MATCH(Assets!$B$6,Countries!$A$2:$A$5,0)),INDEX(Countries!$D$2:$D$5,MATCH(Assets!$B$6,Countries!$A$2:$A$5,0)))))^(H$3-1)*MAX(0,MIN(1,YEARFRAC(H$4,MIN(Assets!$E$6,EDATE(H$4,12)),1)*(Assets!$E$6>H$4)))+Assets!$F$6*(1+MIN(INDEX(Countries!$F$2:$F$5,MATCH(Assets!$B$6,Countries!$A$2:$A$5,0)),MAX(INDEX(Countries!$E$2:$E$5,MATCH(Assets!$B$6,Countries!$A$2:$A$5,0)),INDEX(Countries!$D$2:$D$5,MATCH(Assets!$B$6,Countries!$A$2:$A$5,0)))))^(H$3-1)*IF(Assets!$E$6<EDATE(H$4,12),(Inputs!$B$13*MAX(0,MIN(12,DATEDIF(MAX(Assets!$E$6,H$4),EDATE(H$4,12),"m")))+(1-Inputs!$B$13)*MAX(0,MAX(0,MIN(12,DATEDIF(MAX(Assets!$E$6,H$4),EDATE(H$4,12),"m")))-MAX(0,Inputs!$B$12-IF(Assets!$E$6<H$4,DATEDIF(Assets!$E$6,H$4,"m"),0))))/12,0))*INDEX(Countries!$C$2:$C$5,MATCH(Assets!$B$6,Countries!$A$2:$A$5,0)),0) -> 2855610 | I13: =IF(AND(I$3>=1,I$3<=Inputs!$B$11,OR(Assets!$G$6="",I$4<Assets!$G$6)),Assets!$C$6*(Assets!$D$6*(1+MIN(INDEX(Countries!$F$2:$F$5,MATCH(Assets!$B$6,Countries!$A$2:$A$5,0)),MAX(INDEX(Countries!$E$2:$E$5,MATCH(Assets!$B$6,Countries!$A$2:$A$5,0)),INDEX(Countries!$D$2:$D$5,MATCH(Assets!$B$6,Countries!$A$2:$A$5,0)))))^(I$3-1)*MAX(0,MIN(1,YEARFRAC(I$4,MIN(Assets!$E$6,EDATE(I$4,12)),1)*(Assets!$E$6>I$4)))+Assets!$F$6*(1+MIN(INDEX(Countries!$F$2:$F$5,MATCH(Assets!$B$6,Countries!$A$2:$A$5,0)),MAX(INDEX(Countries!$E$2:$E$5,MATCH(Assets!$B$6,Countries!$A$2:$A$5,0)),INDEX(Countries!$D$2:$D$5,MATCH(Assets!$B$6,Countries!$A$2:$A$5,0)))))^(I$3-1)*IF(Assets!$E$6<EDATE(I$4,12),(Inputs!$B$13*MAX(0,MIN(12,DATEDIF(MAX(Assets!$E$6,I$4),EDATE(I$4,12),"m")))+(1-Inputs!$B$13)*MAX(0,MAX(0,MIN(12,DATEDIF(MAX(Assets!$E$6,I$4),EDATE(I$4,12),"m")))-MAX(0,Inputs!$B$12-IF(Assets!$E$6<I$4,DATEDIF(Assets!$E$6,I$4,"m"),0))))/12,0))*INDEX(Countries!$C$2:$C$5,MATCH(Assets!$B$6,Countries!$A$2:$A$5,0)),0) -> 2096914.4 | ... L13: =IF(AND(L$3>=1,L$3<=Inputs!$B$11,OR(Assets!$G$6="",L$4<Assets!$G$6)),Assets!$C$6*(Assets!$D$6*(1+MIN(INDEX(Countries!$F$2:$F$5,MATCH(Assets!$B$6,Countries!$A$2:$A$5,0)),MAX(INDEX(Countries!$E$2:$E$5,MATCH(Assets!$B$6,Countries!$A$2:$A$5,0)),INDEX(Countries!$D$2:$D$5,MATCH(Assets!$B$6,Countries!$A$2:$A$5,0)))))^(L$3-1)*MAX(0,MIN(1,YEARFRAC(L$4,MIN(Assets!$E$6,EDATE(L$4,12)),1)*(Assets!$E$6>L$4)))+Assets!$F$6*(1+MIN(INDEX(Countries!$F$2:$F$5,MATCH(Assets!$B$6,Countries!$A$2:$A$5,0)),MAX(INDEX(Countries!$E$2:$E$5,MATCH(Assets!$B$6,Countries!$A$2:$A$5,0)),INDEX(Countries!$D$2:$D$5,MATCH(Assets!$B$6,Countries!$A$2:$A$5,0)))))^(L$3-1)*IF(Assets!$E$6<EDATE(L$4,12),(Inputs!$B$13*MAX(0,MIN(12,DATEDIF(MAX(Assets!$E$6,L$4),EDATE(L$4,12),"m")))+(1-Inputs!$B$13)*MAX(0,MAX(0,MIN(12,DATEDIF(MAX(Assets!$E$6,L$4),EDATE(L$4,12),"m")))-MAX(0,Inputs!$B$12-IF(Assets!$E$6<L$4,DATEDIF(Assets!$E$6,L$4,"m"),0))))/12,0))*INDEX(Countries!$C$2:$C$5,MATCH(Assets!$B$6,Countries!$A$2:$A$5,0)),0) -> 0
A14: Malmo Gate · disposal (EUR) | B14: =IF(AND(Assets!$G$6<>"",Assets!$G$6>=B$4,Assets!$G$6<EDATE(B$4,12)),Assets!$C$6*Assets!$F$6*(1+MIN(INDEX(Countries!$F$2:$F$5,MATCH(Assets!$B$6,Countries!$A$2:$A$5,0)),MAX(INDEX(Countries!$E$2:$E$5,MATCH(Assets!$B$6,Countries!$A$2:$A$5,0)),INDEX(Countries!$D$2:$D$5,MATCH(Assets!$B$6,Countries!$A$2:$A$5,0)))))^(B$3-1)*INDEX(Countries!$C$2:$C$5,MATCH(Assets!$B$6,Countries!$A$2:$A$5,0))/Assets!$H$6,0) -> 0 | C14: =IF(AND(Assets!$G$6<>"",Assets!$G$6>=C$4,Assets!$G$6<EDATE(C$4,12)),Assets!$C$6*Assets!$F$6*(1+MIN(INDEX(Countries!$F$2:$F$5,MATCH(Assets!$B$6,Countries!$A$2:$A$5,0)),MAX(INDEX(Countries!$E$2:$E$5,MATCH(Assets!$B$6,Countries!$A$2:$A$5,0)),INDEX(Countries!$D$2:$D$5,MATCH(Assets!$B$6,Countries!$A$2:$A$5,0)))))^(C$3-1)*INDEX(Countries!$C$2:$C$5,MATCH(Assets!$B$6,Countries!$A$2:$A$5,0))/Assets!$H$6,0) -> 0 | D14: =IF(AND(Assets!$G$6<>"",Assets!$G$6>=D$4,Assets!$G$6<EDATE(D$4,12)),Assets!$C$6*Assets!$F$6*(1+MIN(INDEX(Countries!$F$2:$F$5,MATCH(Assets!$B$6,Countries!$A$2:$A$5,0)),MAX(INDEX(Countries!$E$2:$E$5,MATCH(Assets!$B$6,Countries!$A$2:$A$5,0)),INDEX(Countries!$D$2:$D$5,MATCH(Assets!$B$6,Countries!$A$2:$A$5,0)))))^(D$3-1)*INDEX(Countries!$C$2:$C$5,MATCH(Assets!$B$6,Countries!$A$2:$A$5,0))/Assets!$H$6,0) -> 0 | E14: =IF(AND(Assets!$G$6<>"",Assets!$G$6>=E$4,Assets!$G$6<EDATE(E$4,12)),Assets!$C$6*Assets!$F$6*(1+MIN(INDEX(Countries!$F$2:$F$5,MATCH(Assets!$B$6,Countries!$A$2:$A$5,0)),MAX(INDEX(Countries!$E$2:$E$5,MATCH(Assets!$B$6,Countries!$A$2:$A$5,0)),INDEX(Countries!$D$2:$D$5,MATCH(Assets!$B$6,Countries!$A$2:$A$5,0)))))^(E$3-1)*INDEX(Countries!$C$2:$C$5,MATCH(Assets!$B$6,Countries!$A$2:$A$5,0))/Assets!$H$6,0) -> 0 | F14: =IF(AND(Assets!$G$6<>"",Assets!$G$6>=F$4,Assets!$G$6<EDATE(F$4,12)),Assets!$C$6*Assets!$F$6*(1+MIN(INDEX(Countries!$F$2:$F$5,MATCH(Assets!$B$6,Countries!$A$2:$A$5,0)),MAX(INDEX(Countries!$E$2:$E$5,MATCH(Assets!$B$6,Countries!$A$2:$A$5,0)),INDEX(Countries!$D$2:$D$5,MATCH(Assets!$B$6,Countries!$A$2:$A$5,0)))))^(F$3-1)*INDEX(Countries!$C$2:$C$5,MATCH(Assets!$B$6,Countries!$A$2:$A$5,0))/Assets!$H$6,0) -> 0 | G14: =IF(AND(Assets!$G$6<>"",Assets!$G$6>=G$4,Assets!$G$6<EDATE(G$4,12)),Assets!$C$6*Assets!$F$6*(1+MIN(INDEX(Countries!$F$2:$F$5,MATCH(Assets!$B$6,Countries!$A$2:$A$5,0)),MAX(INDEX(Countries!$E$2:$E$5,MATCH(Assets!$B$6,Countries!$A$2:$A$5,0)),INDEX(Countries!$D$2:$D$5,MATCH(Assets!$B$6,Countries!$A$2:$A$5,0)))))^(G$3-1)*INDEX(Countries!$C$2:$C$5,MATCH(Assets!$B$6,Countries!$A$2:$A$5,0))/Assets!$H$6,0) -> 0 | H14: =IF(AND(Assets!$G$6<>"",Assets!$G$6>=H$4,Assets!$G$6<EDATE(H$4,12)),Assets!$C$6*Assets!$F$6*(1+MIN(INDEX(Countries!$F$2:$F$5,MATCH(Assets!$B$6,Countries!$A$2:$A$5,0)),MAX(INDEX(Countries!$E$2:$E$5,MATCH(Assets!$B$6,Countries!$A$2:$A$5,0)),INDEX(Countries!$D$2:$D$5,MATCH(Assets!$B$6,Countries!$A$2:$A$5,0)))))^(H$3-1)*INDEX(Countries!$C$2:$C$5,MATCH(Assets!$B$6,Countries!$A$2:$A$5,0))/Assets!$H$6,0) -> 0 | I14: =IF(AND(Assets!$G$6<>"",Assets!$G$6>=I$4,Assets!$G$6<EDATE(I$4,12)),Assets!$C$6*Assets!$F$6*(1+MIN(INDEX(Countries!$F$2:$F$5,MATCH(Assets!$B$6,Countries!$A$2:$A$5,0)),MAX(INDEX(Countries!$E$2:$E$5,MATCH(Assets!$B$6,Countries!$A$2:$A$5,0)),INDEX(Countries!$D$2:$D$5,MATCH(Assets!$B$6,Countries!$A$2:$A$5,0)))))^(I$3-1)*INDEX(Countries!$C$2:$C$5,MATCH(Assets!$B$6,Countries!$A$2:$A$5,0))/Assets!$H$6,0) -> 0 | ... L14: =IF(AND(Assets!$G$6<>"",Assets!$G$6>=L$4,Assets!$G$6<EDATE(L$4,12)),Assets!$C$6*Assets!$F$6*(1+MIN(INDEX(Countries!$F$2:$F$5,MATCH(Assets!$B$6,Countries!$A$2:$A$5,0)),MAX(INDEX(Countries!$E$2:$E$5,MATCH(Assets!$B$6,Countries!$A$2:$A$5,0)),INDEX(Countries!$D$2:$D$5,MATCH(Assets!$B$6,Countries!$A$2:$A$5,0)))))^(L$3-1)*INDEX(Countries!$C$2:$C$5,MATCH(Assets!$B$6,Countries!$A$2:$A$5,0))/Assets!$H$6,0) -> 0
A15: Gothenburg Port · rent (EUR) | B15: =IF(AND(B$3>=1,B$3<=Inputs!$B$11,OR(Assets!$G$7="",B$4<Assets!$G$7)),Assets!$C$7*(Assets!$D$7*(1+MIN(INDEX(Countries!$F$2:$F$5,MATCH(Assets!$B$7,Countries!$A$2:$A$5,0)),MAX(INDEX(Countries!$E$2:$E$5,MATCH(Assets!$B$7,Countries!$A$2:$A$5,0)),INDEX(Countries!$D$2:$D$5,MATCH(Assets!$B$7,Countries!$A$2:$A$5,0)))))^(B$3-1)*MAX(0,MIN(1,YEARFRAC(B$4,MIN(Assets!$E$7,EDATE(B$4,12)),1)*(Assets!$E$7>B$4)))+Assets!$F$7*(1+MIN(INDEX(Countries!$F$2:$F$5,MATCH(Assets!$B$7,Countries!$A$2:$A$5,0)),MAX(INDEX(Countries!$E$2:$E$5,MATCH(Assets!$B$7,Countries!$A$2:$A$5,0)),INDEX(Countries!$D$2:$D$5,MATCH(Assets!$B$7,Countries!$A$2:$A$5,0)))))^(B$3-1)*IF(Assets!$E$7<EDATE(B$4,12),(Inputs!$B$13*MAX(0,MIN(12,DATEDIF(MAX(Assets!$E$7,B$4),EDATE(B$4,12),"m")))+(1-Inputs!$B$13)*MAX(0,MAX(0,MIN(12,DATEDIF(MAX(Assets!$E$7,B$4),EDATE(B$4,12),"m")))-MAX(0,Inputs!$B$12-IF(Assets!$E$7<B$4,DATEDIF(Assets!$E$7,B$4,"m"),0))))/12,0))*INDEX(Countries!$C$2:$C$5,MATCH(Assets!$B$7,Countries!$A$2:$A$5,0)),0) -> 0 | C15: =IF(AND(C$3>=1,C$3<=Inputs!$B$11,OR(Assets!$G$7="",C$4<Assets!$G$7)),Assets!$C$7*(Assets!$D$7*(1+MIN(INDEX(Countries!$F$2:$F$5,MATCH(Assets!$B$7,Countries!$A$2:$A$5,0)),MAX(INDEX(Countries!$E$2:$E$5,MATCH(Assets!$B$7,Countries!$A$2:$A$5,0)),INDEX(Countries!$D$2:$D$5,MATCH(Assets!$B$7,Countries!$A$2:$A$5,0)))))^(C$3-1)*MAX(0,MIN(1,YEARFRAC(C$4,MIN(Assets!$E$7,EDATE(C$4,12)),1)*(Assets!$E$7>C$4)))+Assets!$F$7*(1+MIN(INDEX(Countries!$F$2:$F$5,MATCH(Assets!$B$7,Countries!$A$2:$A$5,0)),MAX(INDEX(Countries!$E$2:$E$5,MATCH(Assets!$B$7,Countries!$A$2:$A$5,0)),INDEX(Countries!$D$2:$D$5,MATCH(Assets!$B$7,Countries!$A$2:$A$5,0)))))^(C$3-1)*IF(Assets!$E$7<EDATE(C$4,12),(Inputs!$B$13*MAX(0,MIN(12,DATEDIF(MAX(Assets!$E$7,C$4),EDATE(C$4,12),"m")))+(1-Inputs!$B$13)*MAX(0,MAX(0,MIN(12,DATEDIF(MAX(Assets!$E$7,C$4),EDATE(C$4,12),"m")))-MAX(0,Inputs!$B$12-IF(Assets!$E$7<C$4,DATEDIF(Assets!$E$7,C$4,"m"),0))))/12,0))*INDEX(Countries!$C$2:$C$5,MATCH(Assets!$B$7,Countries!$A$2:$A$5,0)),0) -> 2926000 | D15: =IF(AND(D$3>=1,D$3<=Inputs!$B$11,OR(Assets!$G$7="",D$4<Assets!$G$7)),Assets!$C$7*(Assets!$D$7*(1+MIN(INDEX(Countries!$F$2:$F$5,MATCH(Assets!$B$7,Countries!$A$2:$A$5,0)),MAX(INDEX(Countries!$E$2:$E$5,MATCH(Assets!$B$7,Countries!$A$2:$A$5,0)),INDEX(Countries!$D$2:$D$5,MATCH(Assets!$B$7,Countries!$A$2:$A$5,0)))))^(D$3-1)*MAX(0,MIN(1,YEARFRAC(D$4,MIN(Assets!$E$7,EDATE(D$4,12)),1)*(Assets!$E$7>D$4)))+Assets!$F$7*(1+MIN(INDEX(Countries!$F$2:$F$5,MATCH(Assets!$B$7,Countries!$A$2:$A$5,0)),MAX(INDEX(Countries!$E$2:$E$5,MATCH(Assets!$B$7,Countries!$A$2:$A$5,0)),INDEX(Countries!$D$2:$D$5,MATCH(Assets!$B$7,Countries!$A$2:$A$5,0)))))^(D$3-1)*IF(Assets!$E$7<EDATE(D$4,12),(Inputs!$B$13*MAX(0,MIN(12,DATEDIF(MAX(Assets!$E$7,D$4),EDATE(D$4,12),"m")))+(1-Inputs!$B$13)*MAX(0,MAX(0,MIN(12,DATEDIF(MAX(Assets!$E$7,D$4),EDATE(D$4,12),"m")))-MAX(0,Inputs!$B$12-IF(Assets!$E$7<D$4,DATEDIF(Assets!$E$7,D$4,"m"),0))))/12,0))*INDEX(Countries!$C$2:$C$5,MATCH(Assets!$B$7,Countries!$A$2:$A$5,0)),0) -> 2984520 | E15: =IF(AND(E$3>=1,E$3<=Inputs!$B$11,OR(Assets!$G$7="",E$4<Assets!$G$7)),Assets!$C$7*(Assets!$D$7*(1+MIN(INDEX(Countries!$F$2:$F$5,MATCH(Assets!$B$7,Countries!$A$2:$A$5,0)),MAX(INDEX(Countries!$E$2:$E$5,MATCH(Assets!$B$7,Countries!$A$2:$A$5,0)),INDEX(Countries!$D$2:$D$5,MATCH(Assets!$B$7,Countries!$A$2:$A$5,0)))))^(E$3-1)*MAX(0,MIN(1,YEARFRAC(E$4,MIN(Assets!$E$7,EDATE(E$4,12)),1)*(Assets!$E$7>E$4)))+Assets!$F$7*(1+MIN(INDEX(Countries!$F$2:$F$5,MATCH(Assets!$B$7,Countries!$A$2:$A$5,0)),MAX(INDEX(Countries!$E$2:$E$5,MATCH(Assets!$B$7,Countries!$A$2:$A$5,0)),INDEX(Countries!$D$2:$D$5,MATCH(Assets!$B$7,Countries!$A$2:$A$5,0)))))^(E$3-1)*IF(Assets!$E$7<EDATE(E$4,12),(Inputs!$B$13*MAX(0,MIN(12,DATEDIF(MAX(Assets!$E$7,E$4),EDATE(E$4,12),"m")))+(1-Inputs!$B$13)*MAX(0,MAX(0,MIN(12,DATEDIF(MAX(Assets!$E$7,E$4),EDATE(E$4,12),"m")))-MAX(0,Inputs!$B$12-IF(Assets!$E$7<E$4,DATEDIF(Assets!$E$7,E$4,"m"),0))))/12,0))*INDEX(Countries!$C$2:$C$5,MATCH(Assets!$B$7,Countries!$A$2:$A$5,0)),0) -> 2474600.7 | F15: =IF(AND(F$3>=1,F$3<=Inputs!$B$11,OR(Assets!$G$7="",F$4<Assets!$G$7)),Assets!$C$7*(Assets!$D$7*(1+MIN(INDEX(Countries!$F$2:$F$5,MATCH(Assets!$B$7,Countries!$A$2:$A$5,0)),MAX(INDEX(Countries!$E$2:$E$5,MATCH(Assets!$B$7,Countries!$A$2:$A$5,0)),INDEX(Countries!$D$2:$D$5,MATCH(Assets!$B$7,Countries!$A$2:$A$5,0)))))^(F$3-1)*MAX(0,MIN(1,YEARFRAC(F$4,MIN(Assets!$E$7,EDATE(F$4,12)),1)*(Assets!$E$7>F$4)))+Assets!$F$7*(1+MIN(INDEX(Countries!$F$2:$F$5,MATCH(Assets!$B$7,Countries!$A$2:$A$5,0)),MAX(INDEX(Countries!$E$2:$E$5,MATCH(Assets!$B$7,Countries!$A$2:$A$5,0)),INDEX(Countries!$D$2:$D$5,MATCH(Assets!$B$7,Countries!$A$2:$A$5,0)))))^(F$3-1)*IF(Assets!$E$7<EDATE(F$4,12),(Inputs!$B$13*MAX(0,MIN(12,DATEDIF(MAX(Assets!$E$7,F$4),EDATE(F$4,12),"m")))+(1-Inputs!$B$13)*MAX(0,MAX(0,MIN(12,DATEDIF(MAX(Assets!$E$7,F$4),EDATE(F$4,12),"m")))-MAX(0,Inputs!$B$12-IF(Assets!$E$7<F$4,DATEDIF(Assets!$E$7,F$4,"m"),0))))/12,0))*INDEX(Countries!$C$2:$C$5,MATCH(Assets!$B$7,Countries!$A$2:$A$5,0)),0) -> 2978439.4 | G15: =IF(AND(G$3>=1,G$3<=Inputs!$B$11,OR(Assets!$G$7="",G$4<Assets!$G$7)),Assets!$C$7*(Assets!$D$7*(1+MIN(INDEX(Countries!$F$2:$F$5,MATCH(Assets!$B$7,Countries!$A$2:$A$5,0)),MAX(INDEX(Countries!$E$2:$E$5,MATCH(Assets!$B$7,Countries!$A$2:$A$5,0)),INDEX(Countries!$D$2:$D$5,MATCH(Assets!$B$7,Countries!$A$2:$A$5,0)))))^(G$3-1)*MAX(0,MIN(1,YEARFRAC(G$4,MIN(Assets!$E$7,EDATE(G$4,12)),1)*(Assets!$E$7>G$4)))+Assets!$F$7*(1+MIN(INDEX(Countries!$F$2:$F$5,MATCH(Assets!$B$7,Countries!$A$2:$A$5,0)),MAX(INDEX(Countries!$E$2:$E$5,MATCH(Assets!$B$7,Countries!$A$2:$A$5,0)),INDEX(Countries!$D$2:$D$5,MATCH(Assets!$B$7,Countries!$A$2:$A$5,0)))))^(G$3-1)*IF(Assets!$E$7<EDATE(G$4,12),(Inputs!$B$13*MAX(0,MIN(12,DATEDIF(MAX(Assets!$E$7,G$4),EDATE(G$4,12),"m")))+(1-Inputs!$B$13)*MAX(0,MAX(0,MIN(12,DATEDIF(MAX(Assets!$E$7,G$4),EDATE(G$4,12),"m")))-MAX(0,Inputs!$B$12-IF(Assets!$E$7<G$4,DATEDIF(Assets!$E$7,G$4,"m"),0))))/12,0))*INDEX(Countries!$C$2:$C$5,MATCH(Assets!$B$7,Countries!$A$2:$A$5,0)),0) -> 0 | H15: =IF(AND(H$3>=1,H$3<=Inputs!$B$11,OR(Assets!$G$7="",H$4<Assets!$G$7)),Assets!$C$7*(Assets!$D$7*(1+MIN(INDEX(Countries!$F$2:$F$5,MATCH(Assets!$B$7,Countries!$A$2:$A$5,0)),MAX(INDEX(Countries!$E$2:$E$5,MATCH(Assets!$B$7,Countries!$A$2:$A$5,0)),INDEX(Countries!$D$2:$D$5,MATCH(Assets!$B$7,Countries!$A$2:$A$5,0)))))^(H$3-1)*MAX(0,MIN(1,YEARFRAC(H$4,MIN(Assets!$E$7,EDATE(H$4,12)),1)*(Assets!$E$7>H$4)))+Assets!$F$7*(1+MIN(INDEX(Countries!$F$2:$F$5,MATCH(Assets!$B$7,Countries!$A$2:$A$5,0)),MAX(INDEX(Countries!$E$2:$E$5,MATCH(Assets!$B$7,Countries!$A$2:$A$5,0)),INDEX(Countries!$D$2:$D$5,MATCH(Assets!$B$7,Countries!$A$2:$A$5,0)))))^(H$3-1)*IF(Assets!$E$7<EDATE(H$4,12),(Inputs!$B$13*MAX(0,MIN(12,DATEDIF(MAX(Assets!$E$7,H$4),EDATE(H$4,12),"m")))+(1-Inputs!$B$13)*MAX(0,MAX(0,MIN(12,DATEDIF(MAX(Assets!$E$7,H$4),EDATE(H$4,12),"m")))-MAX(0,Inputs!$B$12-IF(Assets!$E$7<H$4,DATEDIF(Assets!$E$7,H$4,"m"),0))))/12,0))*INDEX(Countries!$C$2:$C$5,MATCH(Assets!$B$7,Countries!$A$2:$A$5,0)),0) -> 0 | I15: =IF(AND(I$3>=1,I$3<=Inputs!$B$11,OR(Assets!$G$7="",I$4<Assets!$G$7)),Assets!$C$7*(Assets!$D$7*(1+MIN(INDEX(Countries!$F$2:$F$5,MATCH(Assets!$B$7,Countries!$A$2:$A$5,0)),MAX(INDEX(Countries!$E$2:$E$5,MATCH(Assets!$B$7,Countries!$A$2:$A$5,0)),INDEX(Countries!$D$2:$D$5,MATCH(Assets!$B$7,Countries!$A$2:$A$5,0)))))^(I$3-1)*MAX(0,MIN(1,YEARFRAC(I$4,MIN(Assets!$E$7,EDATE(I$4,12)),1)*(Assets!$E$7>I$4)))+Assets!$F$7*(1+MIN(INDEX(Countries!$F$2:$F$5,MATCH(Assets!$B$7,Countries!$A$2:$A$5,0)),MAX(INDEX(Countries!$E$2:$E$5,MATCH(Assets!$B$7,Countries!$A$2:$A$5,0)),INDEX(Countries!$D$2:$D$5,MATCH(Assets!$B$7,Countries!$A$2:$A$5,0)))))^(I$3-1)*IF(Assets!$E$7<EDATE(I$4,12),(Inputs!$B$13*MAX(0,MIN(12,DATEDIF(MAX(Assets!$E$7,I$4),EDATE(I$4,12),"m")))+(1-Inputs!$B$13)*MAX(0,MAX(0,MIN(12,DATEDIF(MAX(Assets!$E$7,I$4),EDATE(I$4,12),"m")))-MAX(0,Inputs!$B$12-IF(Assets!$E$7<I$4,DATEDIF(Assets!$E$7,I$4,"m"),0))))/12,0))*INDEX(Countries!$C$2:$C$5,MATCH(Assets!$B$7,Countries!$A$2:$A$5,0)),0) -> 0 | ... L15: =IF(AND(L$3>=1,L$3<=Inputs!$B$11,OR(Assets!$G$7="",L$4<Assets!$G$7)),Assets!$C$7*(Assets!$D$7*(1+MIN(INDEX(Countries!$F$2:$F$5,MATCH(Assets!$B$7,Countries!$A$2:$A$5,0)),MAX(INDEX(Countries!$E$2:$E$5,MATCH(Assets!$B$7,Countries!$A$2:$A$5,0)),INDEX(Countries!$D$2:$D$5,MATCH(Assets!$B$7,Countries!$A$2:$A$5,0)))))^(L$3-1)*MAX(0,MIN(1,YEARFRAC(L$4,MIN(Assets!$E$7,EDATE(L$4,12)),1)*(Assets!$E$7>L$4)))+Assets!$F$7*(1+MIN(INDEX(Countries!$F$2:$F$5,MATCH(Assets!$B$7,Countries!$A$2:$A$5,0)),MAX(INDEX(Countries!$E$2:$E$5,MATCH(Assets!$B$7,Countries!$A$2:$A$5,0)),INDEX(Countries!$D$2:$D$5,MATCH(Assets!$B$7,Countries!$A$2:$A$5,0)))))^(L$3-1)*IF(Assets!$E$7<EDATE(L$4,12),(Inputs!$B$13*MAX(0,MIN(12,DATEDIF(MAX(Assets!$E$7,L$4),EDATE(L$4,12),"m")))+(1-Inputs!$B$13)*MAX(0,MAX(0,MIN(12,DATEDIF(MAX(Assets!$E$7,L$4),EDATE(L$4,12),"m")))-MAX(0,Inputs!$B$12-IF(Assets!$E$7<L$4,DATEDIF(Assets!$E$7,L$4,"m"),0))))/12,0))*INDEX(Countries!$C$2:$C$5,MATCH(Assets!$B$7,Countries!$A$2:$A$5,0)),0) -> 0
A16: Gothenburg Port · disposal (EUR) | B16: =IF(AND(Assets!$G$7<>"",Assets!$G$7>=B$4,Assets!$G$7<EDATE(B$4,12)),Assets!$C$7*Assets!$F$7*(1+MIN(INDEX(Countries!$F$2:$F$5,MATCH(Assets!$B$7,Countries!$A$2:$A$5,0)),MAX(INDEX(Countries!$E$2:$E$5,MATCH(Assets!$B$7,Countries!$A$2:$A$5,0)),INDEX(Countries!$D$2:$D$5,MATCH(Assets!$B$7,Countries!$A$2:$A$5,0)))))^(B$3-1)*INDEX(Countries!$C$2:$C$5,MATCH(Assets!$B$7,Countries!$A$2:$A$5,0))/Assets!$H$7,0) -> 0 | C16: =IF(AND(Assets!$G$7<>"",Assets!$G$7>=C$4,Assets!$G$7<EDATE(C$4,12)),Assets!$C$7*Assets!$F$7*(1+MIN(INDEX(Countries!$F$2:$F$5,MATCH(Assets!$B$7,Countries!$A$2:$A$5,0)),MAX(INDEX(Countries!$E$2:$E$5,MATCH(Assets!$B$7,Countries!$A$2:$A$5,0)),INDEX(Countries!$D$2:$D$5,MATCH(Assets!$B$7,Countries!$A$2:$A$5,0)))))^(C$3-1)*INDEX(Countries!$C$2:$C$5,MATCH(Assets!$B$7,Countries!$A$2:$A$5,0))/Assets!$H$7,0) -> 0 | D16: =IF(AND(Assets!$G$7<>"",Assets!$G$7>=D$4,Assets!$G$7<EDATE(D$4,12)),Assets!$C$7*Assets!$F$7*(1+MIN(INDEX(Countries!$F$2:$F$5,MATCH(Assets!$B$7,Countries!$A$2:$A$5,0)),MAX(INDEX(Countries!$E$2:$E$5,MATCH(Assets!$B$7,Countries!$A$2:$A$5,0)),INDEX(Countries!$D$2:$D$5,MATCH(Assets!$B$7,Countries!$A$2:$A$5,0)))))^(D$3-1)*INDEX(Countries!$C$2:$C$5,MATCH(Assets!$B$7,Countries!$A$2:$A$5,0))/Assets!$H$7,0) -> 0 | E16: =IF(AND(Assets!$G$7<>"",Assets!$G$7>=E$4,Assets!$G$7<EDATE(E$4,12)),Assets!$C$7*Assets!$F$7*(1+MIN(INDEX(Countries!$F$2:$F$5,MATCH(Assets!$B$7,Countries!$A$2:$A$5,0)),MAX(INDEX(Countries!$E$2:$E$5,MATCH(Assets!$B$7,Countries!$A$2:$A$5,0)),INDEX(Countries!$D$2:$D$5,MATCH(Assets!$B$7,Countries!$A$2:$A$5,0)))))^(E$3-1)*INDEX(Countries!$C$2:$C$5,MATCH(Assets!$B$7,Countries!$A$2:$A$5,0))/Assets!$H$7,0) -> 0 | F16: =IF(AND(Assets!$G$7<>"",Assets!$G$7>=F$4,Assets!$G$7<EDATE(F$4,12)),Assets!$C$7*Assets!$F$7*(1+MIN(INDEX(Countries!$F$2:$F$5,MATCH(Assets!$B$7,Countries!$A$2:$A$5,0)),MAX(INDEX(Countries!$E$2:$E$5,MATCH(Assets!$B$7,Countries!$A$2:$A$5,0)),INDEX(Countries!$D$2:$D$5,MATCH(Assets!$B$7,Countries!$A$2:$A$5,0)))))^(F$3-1)*INDEX(Countries!$C$2:$C$5,MATCH(Assets!$B$7,Countries!$A$2:$A$5,0))/Assets!$H$7,0) -> 66187543 | G16: =IF(AND(Assets!$G$7<>"",Assets!$G$7>=G$4,Assets!$G$7<EDATE(G$4,12)),Assets!$C$7*Assets!$F$7*(1+MIN(INDEX(Countries!$F$2:$F$5,MATCH(Assets!$B$7,Countries!$A$2:$A$5,0)),MAX(INDEX(Countries!$E$2:$E$5,MATCH(Assets!$B$7,Countries!$A$2:$A$5,0)),INDEX(Countries!$D$2:$D$5,MATCH(Assets!$B$7,Countries!$A$2:$A$5,0)))))^(G$3-1)*INDEX(Countries!$C$2:$C$5,MATCH(Assets!$B$7,Countries!$A$2:$A$5,0))/Assets!$H$7,0) -> 0 | H16: =IF(AND(Assets!$G$7<>"",Assets!$G$7>=H$4,Assets!$G$7<EDATE(H$4,12)),Assets!$C$7*Assets!$F$7*(1+MIN(INDEX(Countries!$F$2:$F$5,MATCH(Assets!$B$7,Countries!$A$2:$A$5,0)),MAX(INDEX(Countries!$E$2:$E$5,MATCH(Assets!$B$7,Countries!$A$2:$A$5,0)),INDEX(Countries!$D$2:$D$5,MATCH(Assets!$B$7,Countries!$A$2:$A$5,0)))))^(H$3-1)*INDEX(Countries!$C$2:$C$5,MATCH(Assets!$B$7,Countries!$A$2:$A$5,0))/Assets!$H$7,0) -> 0 | I16: =IF(AND(Assets!$G$7<>"",Assets!$G$7>=I$4,Assets!$G$7<EDATE(I$4,12)),Assets!$C$7*Assets!$F$7*(1+MIN(INDEX(Countries!$F$2:$F$5,MATCH(Assets!$B$7,Countries!$A$2:$A$5,0)),MAX(INDEX(Countries!$E$2:$E$5,MATCH(Assets!$B$7,Countries!$A$2:$A$5,0)),INDEX(Countries!$D$2:$D$5,MATCH(Assets!$B$7,Countries!$A$2:$A$5,0)))))^(I$3-1)*INDEX(Countries!$C$2:$C$5,MATCH(Assets!$B$7,Countries!$A$2:$A$5,0))/Assets!$H$7,0) -> 0 | ... L16: =IF(AND(Assets!$G$7<>"",Assets!$G$7>=L$4,Assets!$G$7<EDATE(L$4,12)),Assets!$C$7*Assets!$F$7*(1+MIN(INDEX(Countries!$F$2:$F$5,MATCH(Assets!$B$7,Countries!$A$2:$A$5,0)),MAX(INDEX(Countries!$E$2:$E$5,MATCH(Assets!$B$7,Countries!$A$2:$A$5,0)),INDEX(Countries!$D$2:$D$5,MATCH(Assets!$B$7,Countries!$A$2:$A$5,0)))))^(L$3-1)*INDEX(Countries!$C$2:$C$5,MATCH(Assets!$B$7,Countries!$A$2:$A$5,0))/Assets!$H$7,0) -> 0
A17: Midlands Cross · rent (EUR) | B17: =IF(AND(B$3>=1,B$3<=Inputs!$B$11,OR(Assets!$G$8="",B$4<Assets!$G$8)),Assets!$C$8*(Assets!$D$8*(1+MIN(INDEX(Countries!$F$2:$F$5,MATCH(Assets!$B$8,Countries!$A$2:$A$5,0)),MAX(INDEX(Countries!$E$2:$E$5,MATCH(Assets!$B$8,Countries!$A$2:$A$5,0)),INDEX(Countries!$D$2:$D$5,MATCH(Assets!$B$8,Countries!$A$2:$A$5,0)))))^(B$3-1)*MAX(0,MIN(1,YEARFRAC(B$4,MIN(Assets!$E$8,EDATE(B$4,12)),1)*(Assets!$E$8>B$4)))+Assets!$F$8*(1+MIN(INDEX(Countries!$F$2:$F$5,MATCH(Assets!$B$8,Countries!$A$2:$A$5,0)),MAX(INDEX(Countries!$E$2:$E$5,MATCH(Assets!$B$8,Countries!$A$2:$A$5,0)),INDEX(Countries!$D$2:$D$5,MATCH(Assets!$B$8,Countries!$A$2:$A$5,0)))))^(B$3-1)*IF(Assets!$E$8<EDATE(B$4,12),(Inputs!$B$13*MAX(0,MIN(12,DATEDIF(MAX(Assets!$E$8,B$4),EDATE(B$4,12),"m")))+(1-Inputs!$B$13)*MAX(0,MAX(0,MIN(12,DATEDIF(MAX(Assets!$E$8,B$4),EDATE(B$4,12),"m")))-MAX(0,Inputs!$B$12-IF(Assets!$E$8<B$4,DATEDIF(Assets!$E$8,B$4,"m"),0))))/12,0))*INDEX(Countries!$C$2:$C$5,MATCH(Assets!$B$8,Countries!$A$2:$A$5,0)),0) -> 0 | C17: =IF(AND(C$3>=1,C$3<=Inputs!$B$11,OR(Assets!$G$8="",C$4<Assets!$G$8)),Assets!$C$8*(Assets!$D$8*(1+MIN(INDEX(Countries!$F$2:$F$5,MATCH(Assets!$B$8,Countries!$A$2:$A$5,0)),MAX(INDEX(Countries!$E$2:$E$5,MATCH(Assets!$B$8,Countries!$A$2:$A$5,0)),INDEX(Countries!$D$2:$D$5,MATCH(Assets!$B$8,Countries!$A$2:$A$5,0)))))^(C$3-1)*MAX(0,MIN(1,YEARFRAC(C$4,MIN(Assets!$E$8,EDATE(C$4,12)),1)*(Assets!$E$8>C$4)))+Assets!$F$8*(1+MIN(INDEX(Countries!$F$2:$F$5,MATCH(Assets!$B$8,Countries!$A$2:$A$5,0)),MAX(INDEX(Countries!$E$2:$E$5,MATCH(Assets!$B$8,Countries!$A$2:$A$5,0)),INDEX(Countries!$D$2:$D$5,MATCH(Assets!$B$8,Countries!$A$2:$A$5,0)))))^(C$3-1)*IF(Assets!$E$8<EDATE(C$4,12),(Inputs!$B$13*MAX(0,MIN(12,DATEDIF(MAX(Assets!$E$8,C$4),EDATE(C$4,12),"m")))+(1-Inputs!$B$13)*MAX(0,MAX(0,MIN(12,DATEDIF(MAX(Assets!$E$8,C$4),EDATE(C$4,12),"m")))-MAX(0,Inputs!$B$12-IF(Assets!$E$8<C$4,DATEDIF(Assets!$E$8,C$4,"m"),0))))/12,0))*INDEX(Countries!$C$2:$C$5,MATCH(Assets!$B$8,Countries!$A$2:$A$5,0)),0) -> 6795360 | D17: =IF(AND(D$3>=1,D$3<=Inputs!$B$11,OR(Assets!$G$8="",D$4<Assets!$G$8)),Assets!$C$8*(Assets!$D$8*(1+MIN(INDEX(Countries!$F$2:$F$5,MATCH(Assets!$B$8,Countries!$A$2:$A$5,0)),MAX(INDEX(Countries!$E$2:$E$5,MATCH(Assets!$B$8,Countries!$A$2:$A$5,0)),INDEX(Countries!$D$2:$D$5,MATCH(Assets!$B$8,Countries!$A$2:$A$5,0)))))^(D$3-1)*MAX(0,MIN(1,YEARFRAC(D$4,MIN(Assets!$E$8,EDATE(D$4,12)),1)*(Assets!$E$8>D$4)))+Assets!$F$8*(1+MIN(INDEX(Countries!$F$2:$F$5,MATCH(Assets!$B$8,Countries!$A$2:$A$5,0)),MAX(INDEX(Countries!$E$2:$E$5,MATCH(Assets!$B$8,Countries!$A$2:$A$5,0)),INDEX(Countries!$D$2:$D$5,MATCH(Assets!$B$8,Countries!$A$2:$A$5,0)))))^(D$3-1)*IF(Assets!$E$8<EDATE(D$4,12),(Inputs!$B$13*MAX(0,MIN(12,DATEDIF(MAX(Assets!$E$8,D$4),EDATE(D$4,12),"m")))+(1-Inputs!$B$13)*MAX(0,MAX(0,MIN(12,DATEDIF(MAX(Assets!$E$8,D$4),EDATE(D$4,12),"m")))-MAX(0,Inputs!$B$12-IF(Assets!$E$8<D$4,DATEDIF(Assets!$E$8,D$4,"m"),0))))/12,0))*INDEX(Countries!$C$2:$C$5,MATCH(Assets!$B$8,Countries!$A$2:$A$5,0)),0) -> 6999220.8 | E17: =IF(AND(E$3>=1,E$3<=Inputs!$B$11,OR(Assets!$G$8="",E$4<Assets!$G$8)),Assets!$C$8*(Assets!$D$8*(1+MIN(INDEX(Countries!$F$2:$F$5,MATCH(Assets!$B$8,Countries!$A$2:$A$5,0)),MAX(INDEX(Countries!$E$2:$E$5,MATCH(Assets!$B$8,Countries!$A$2:$A$5,0)),INDEX(Countries!$D$2:$D$5,MATCH(Assets!$B$8,Countries!$A$2:$A$5,0)))))^(E$3-1)*MAX(0,MIN(1,YEARFRAC(E$4,MIN(Assets!$E$8,EDATE(E$4,12)),1)*(Assets!$E$8>E$4)))+Assets!$F$8*(1+MIN(INDEX(Countries!$F$2:$F$5,MATCH(Assets!$B$8,Countries!$A$2:$A$5,0)),MAX(INDEX(Countries!$E$2:$E$5,MATCH(Assets!$B$8,Countries!$A$2:$A$5,0)),INDEX(Countries!$D$2:$D$5,MATCH(Assets!$B$8,Countries!$A$2:$A$5,0)))))^(E$3-1)*IF(Assets!$E$8<EDATE(E$4,12),(Inputs!$B$13*MAX(0,MIN(12,DATEDIF(MAX(Assets!$E$8,E$4),EDATE(E$4,12),"m")))+(1-Inputs!$B$13)*MAX(0,MAX(0,MIN(12,DATEDIF(MAX(Assets!$E$8,E$4),EDATE(E$4,12),"m")))-MAX(0,Inputs!$B$12-IF(Assets!$E$8<E$4,DATEDIF(Assets!$E$8,E$4,"m"),0))))/12,0))*INDEX(Countries!$C$2:$C$5,MATCH(Assets!$B$8,Countries!$A$2:$A$5,0)),0) -> 7209197.4 | F17: =IF(AND(F$3>=1,F$3<=Inputs!$B$11,OR(Assets!$G$8="",F$4<Assets!$G$8)),Assets!$C$8*(Assets!$D$8*(1+MIN(INDEX(Countries!$F$2:$F$5,MATCH(Assets!$B$8,Countries!$A$2:$A$5,0)),MAX(INDEX(Countries!$E$2:$E$5,MATCH(Assets!$B$8,Countries!$A$2:$A$5,0)),INDEX(Countries!$D$2:$D$5,MATCH(Assets!$B$8,Countries!$A$2:$A$5,0)))))^(F$3-1)*MAX(0,MIN(1,YEARFRAC(F$4,MIN(Assets!$E$8,EDATE(F$4,12)),1)*(Assets!$E$8>F$4)))+Assets!$F$8*(1+MIN(INDEX(Countries!$F$2:$F$5,MATCH(Assets!$B$8,Countries!$A$2:$A$5,0)),MAX(INDEX(Countries!$E$2:$E$5,MATCH(Assets!$B$8,Countries!$A$2:$A$5,0)),INDEX(Countries!$D$2:$D$5,MATCH(Assets!$B$8,Countries!$A$2:$A$5,0)))))^(F$3-1)*IF(Assets!$E$8<EDATE(F$4,12),(Inputs!$B$13*MAX(0,MIN(12,DATEDIF(MAX(Assets!$E$8,F$4),EDATE(F$4,12),"m")))+(1-Inputs!$B$13)*MAX(0,MAX(0,MIN(12,DATEDIF(MAX(Assets!$E$8,F$4),EDATE(F$4,12),"m")))-MAX(0,Inputs!$B$12-IF(Assets!$E$8<F$4,DATEDIF(Assets!$E$8,F$4,"m"),0))))/12,0))*INDEX(Countries!$C$2:$C$5,MATCH(Assets!$B$8,Countries!$A$2:$A$5,0)),0) -> 7425473.3 | G17: =IF(AND(G$3>=1,G$3<=Inputs!$B$11,OR(Assets!$G$8="",G$4<Assets!$G$8)),Assets!$C$8*(Assets!$D$8*(1+MIN(INDEX(Countries!$F$2:$F$5,MATCH(Assets!$B$8,Countries!$A$2:$A$5,0)),MAX(INDEX(Countries!$E$2:$E$5,MATCH(Assets!$B$8,Countries!$A$2:$A$5,0)),INDEX(Countries!$D$2:$D$5,MATCH(Assets!$B$8,Countries!$A$2:$A$5,0)))))^(G$3-1)*MAX(0,MIN(1,YEARFRAC(G$4,MIN(Assets!$E$8,EDATE(G$4,12)),1)*(Assets!$E$8>G$4)))+Assets!$F$8*(1+MIN(INDEX(Countries!$F$2:$F$5,MATCH(Assets!$B$8,Countries!$A$2:$A$5,0)),MAX(INDEX(Countries!$E$2:$E$5,MATCH(Assets!$B$8,Countries!$A$2:$A$5,0)),INDEX(Countries!$D$2:$D$5,MATCH(Assets!$B$8,Countries!$A$2:$A$5,0)))))^(G$3-1)*IF(Assets!$E$8<EDATE(G$4,12),(Inputs!$B$13*MAX(0,MIN(12,DATEDIF(MAX(Assets!$E$8,G$4),EDATE(G$4,12),"m")))+(1-Inputs!$B$13)*MAX(0,MAX(0,MIN(12,DATEDIF(MAX(Assets!$E$8,G$4),EDATE(G$4,12),"m")))-MAX(0,Inputs!$B$12-IF(Assets!$E$8<G$4,DATEDIF(Assets!$E$8,G$4,"m"),0))))/12,0))*INDEX(Countries!$C$2:$C$5,MATCH(Assets!$B$8,Countries!$A$2:$A$5,0)),0) -> 7648237.5 | H17: =IF(AND(H$3>=1,H$3<=Inputs!$B$11,OR(Assets!$G$8="",H$4<Assets!$G$8)),Assets!$C$8*(Assets!$D$8*(1+MIN(INDEX(Countries!$F$2:$F$5,MATCH(Assets!$B$8,Countries!$A$2:$A$5,0)),MAX(INDEX(Countries!$E$2:$E$5,MATCH(Assets!$B$8,Countries!$A$2:$A$5,0)),INDEX(Countries!$D$2:$D$5,MATCH(Assets!$B$8,Countries!$A$2:$A$5,0)))))^(H$3-1)*MAX(0,MIN(1,YEARFRAC(H$4,MIN(Assets!$E$8,EDATE(H$4,12)),1)*(Assets!$E$8>H$4)))+Assets!$F$8*(1+MIN(INDEX(Countries!$F$2:$F$5,MATCH(Assets!$B$8,Countries!$A$2:$A$5,0)),MAX(INDEX(Countries!$E$2:$E$5,MATCH(Assets!$B$8,Countries!$A$2:$A$5,0)),INDEX(Countries!$D$2:$D$5,MATCH(Assets!$B$8,Countries!$A$2:$A$5,0)))))^(H$3-1)*IF(Assets!$E$8<EDATE(H$4,12),(Inputs!$B$13*MAX(0,MIN(12,DATEDIF(MAX(Assets!$E$8,H$4),EDATE(H$4,12),"m")))+(1-Inputs!$B$13)*MAX(0,MAX(0,MIN(12,DATEDIF(MAX(Assets!$E$8,H$4),EDATE(H$4,12),"m")))-MAX(0,Inputs!$B$12-IF(Assets!$E$8<H$4,DATEDIF(Assets!$E$8,H$4,"m"),0))))/12,0))*INDEX(Countries!$C$2:$C$5,MATCH(Assets!$B$8,Countries!$A$2:$A$5,0)),0) -> 7877684.7 | I17: =IF(AND(I$3>=1,I$3<=Inputs!$B$11,OR(Assets!$G$8="",I$4<Assets!$G$8)),Assets!$C$8*(Assets!$D$8*(1+MIN(INDEX(Countries!$F$2:$F$5,MATCH(Assets!$B$8,Countries!$A$2:$A$5,0)),MAX(INDEX(Countries!$E$2:$E$5,MATCH(Assets!$B$8,Countries!$A$2:$A$5,0)),INDEX(Countries!$D$2:$D$5,MATCH(Assets!$B$8,Countries!$A$2:$A$5,0)))))^(I$3-1)*MAX(0,MIN(1,YEARFRAC(I$4,MIN(Assets!$E$8,EDATE(I$4,12)),1)*(Assets!$E$8>I$4)))+Assets!$F$8*(1+MIN(INDEX(Countries!$F$2:$F$5,MATCH(Assets!$B$8,Countries!$A$2:$A$5,0)),MAX(INDEX(Countries!$E$2:$E$5,MATCH(Assets!$B$8,Countries!$A$2:$A$5,0)),INDEX(Countries!$D$2:$D$5,MATCH(Assets!$B$8,Countries!$A$2:$A$5,0)))))^(I$3-1)*IF(Assets!$E$8<EDATE(I$4,12),(Inputs!$B$13*MAX(0,MIN(12,DATEDIF(MAX(Assets!$E$8,I$4),EDATE(I$4,12),"m")))+(1-Inputs!$B$13)*MAX(0,MAX(0,MIN(12,DATEDIF(MAX(Assets!$E$8,I$4),EDATE(I$4,12),"m")))-MAX(0,Inputs!$B$12-IF(Assets!$E$8<I$4,DATEDIF(Assets!$E$8,I$4,"m"),0))))/12,0))*INDEX(Countries!$C$2:$C$5,MATCH(Assets!$B$8,Countries!$A$2:$A$5,0)),0) -> 5961729.7 | ... L17: =IF(AND(L$3>=1,L$3<=Inputs!$B$11,OR(Assets!$G$8="",L$4<Assets!$G$8)),Assets!$C$8*(Assets!$D$8*(1+MIN(INDEX(Countries!$F$2:$F$5,MATCH(Assets!$B$8,Countries!$A$2:$A$5,0)),MAX(INDEX(Countries!$E$2:$E$5,MATCH(Assets!$B$8,Countries!$A$2:$A$5,0)),INDEX(Countries!$D$2:$D$5,MATCH(Assets!$B$8,Countries!$A$2:$A$5,0)))))^(L$3-1)*MAX(0,MIN(1,YEARFRAC(L$4,MIN(Assets!$E$8,EDATE(L$4,12)),1)*(Assets!$E$8>L$4)))+Assets!$F$8*(1+MIN(INDEX(Countries!$F$2:$F$5,MATCH(Assets!$B$8,Countries!$A$2:$A$5,0)),MAX(INDEX(Countries!$E$2:$E$5,MATCH(Assets!$B$8,Countries!$A$2:$A$5,0)),INDEX(Countries!$D$2:$D$5,MATCH(Assets!$B$8,Countries!$A$2:$A$5,0)))))^(L$3-1)*IF(Assets!$E$8<EDATE(L$4,12),(Inputs!$B$13*MAX(0,MIN(12,DATEDIF(MAX(Assets!$E$8,L$4),EDATE(L$4,12),"m")))+(1-Inputs!$B$13)*MAX(0,MAX(0,MIN(12,DATEDIF(MAX(Assets!$E$8,L$4),EDATE(L$4,12),"m")))-MAX(0,Inputs!$B$12-IF(Assets!$E$8<L$4,DATEDIF(Assets!$E$8,L$4,"m"),0))))/12,0))*INDEX(Countries!$C$2:$C$5,MATCH(Assets!$B$8,Countries!$A$2:$A$5,0)),0) -> 0
A18: Midlands Cross · disposal (EUR) | B18: =IF(AND(Assets!$G$8<>"",Assets!$G$8>=B$4,Assets!$G$8<EDATE(B$4,12)),Assets!$C$8*Assets!$F$8*(1+MIN(INDEX(Countries!$F$2:$F$5,MATCH(Assets!$B$8,Countries!$A$2:$A$5,0)),MAX(INDEX(Countries!$E$2:$E$5,MATCH(Assets!$B$8,Countries!$A$2:$A$5,0)),INDEX(Countries!$D$2:$D$5,MATCH(Assets!$B$8,Countries!$A$2:$A$5,0)))))^(B$3-1)*INDEX(Countries!$C$2:$C$5,MATCH(Assets!$B$8,Countries!$A$2:$A$5,0))/Assets!$H$8,0) -> 0 | C18: =IF(AND(Assets!$G$8<>"",Assets!$G$8>=C$4,Assets!$G$8<EDATE(C$4,12)),Assets!$C$8*Assets!$F$8*(1+MIN(INDEX(Countries!$F$2:$F$5,MATCH(Assets!$B$8,Countries!$A$2:$A$5,0)),MAX(INDEX(Countries!$E$2:$E$5,MATCH(Assets!$B$8,Countries!$A$2:$A$5,0)),INDEX(Countries!$D$2:$D$5,MATCH(Assets!$B$8,Countries!$A$2:$A$5,0)))))^(C$3-1)*INDEX(Countries!$C$2:$C$5,MATCH(Assets!$B$8,Countries!$A$2:$A$5,0))/Assets!$H$8,0) -> 0 | D18: =IF(AND(Assets!$G$8<>"",Assets!$G$8>=D$4,Assets!$G$8<EDATE(D$4,12)),Assets!$C$8*Assets!$F$8*(1+MIN(INDEX(Countries!$F$2:$F$5,MATCH(Assets!$B$8,Countries!$A$2:$A$5,0)),MAX(INDEX(Countries!$E$2:$E$5,MATCH(Assets!$B$8,Countries!$A$2:$A$5,0)),INDEX(Countries!$D$2:$D$5,MATCH(Assets!$B$8,Countries!$A$2:$A$5,0)))))^(D$3-1)*INDEX(Countries!$C$2:$C$5,MATCH(Assets!$B$8,Countries!$A$2:$A$5,0))/Assets!$H$8,0) -> 0 | E18: =IF(AND(Assets!$G$8<>"",Assets!$G$8>=E$4,Assets!$G$8<EDATE(E$4,12)),Assets!$C$8*Assets!$F$8*(1+MIN(INDEX(Countries!$F$2:$F$5,MATCH(Assets!$B$8,Countries!$A$2:$A$5,0)),MAX(INDEX(Countries!$E$2:$E$5,MATCH(Assets!$B$8,Countries!$A$2:$A$5,0)),INDEX(Countries!$D$2:$D$5,MATCH(Assets!$B$8,Countries!$A$2:$A$5,0)))))^(E$3-1)*INDEX(Countries!$C$2:$C$5,MATCH(Assets!$B$8,Countries!$A$2:$A$5,0))/Assets!$H$8,0) -> 0 | F18: =IF(AND(Assets!$G$8<>"",Assets!$G$8>=F$4,Assets!$G$8<EDATE(F$4,12)),Assets!$C$8*Assets!$F$8*(1+MIN(INDEX(Countries!$F$2:$F$5,MATCH(Assets!$B$8,Countries!$A$2:$A$5,0)),MAX(INDEX(Countries!$E$2:$E$5,MATCH(Assets!$B$8,Countries!$A$2:$A$5,0)),INDEX(Countries!$D$2:$D$5,MATCH(Assets!$B$8,Countries!$A$2:$A$5,0)))))^(F$3-1)*INDEX(Countries!$C$2:$C$5,MATCH(Assets!$B$8,Countries!$A$2:$A$5,0))/Assets!$H$8,0) -> 0 | G18: =IF(AND(Assets!$G$8<>"",Assets!$G$8>=G$4,Assets!$G$8<EDATE(G$4,12)),Assets!$C$8*Assets!$F$8*(1+MIN(INDEX(Countries!$F$2:$F$5,MATCH(Assets!$B$8,Countries!$A$2:$A$5,0)),MAX(INDEX(Countries!$E$2:$E$5,MATCH(Assets!$B$8,Countries!$A$2:$A$5,0)),INDEX(Countries!$D$2:$D$5,MATCH(Assets!$B$8,Countries!$A$2:$A$5,0)))))^(G$3-1)*INDEX(Countries!$C$2:$C$5,MATCH(Assets!$B$8,Countries!$A$2:$A$5,0))/Assets!$H$8,0) -> 0 | H18: =IF(AND(Assets!$G$8<>"",Assets!$G$8>=H$4,Assets!$G$8<EDATE(H$4,12)),Assets!$C$8*Assets!$F$8*(1+MIN(INDEX(Countries!$F$2:$F$5,MATCH(Assets!$B$8,Countries!$A$2:$A$5,0)),MAX(INDEX(Countries!$E$2:$E$5,MATCH(Assets!$B$8,Countries!$A$2:$A$5,0)),INDEX(Countries!$D$2:$D$5,MATCH(Assets!$B$8,Countries!$A$2:$A$5,0)))))^(H$3-1)*INDEX(Countries!$C$2:$C$5,MATCH(Assets!$B$8,Countries!$A$2:$A$5,0))/Assets!$H$8,0) -> 0 | I18: =IF(AND(Assets!$G$8<>"",Assets!$G$8>=I$4,Assets!$G$8<EDATE(I$4,12)),Assets!$C$8*Assets!$F$8*(1+MIN(INDEX(Countries!$F$2:$F$5,MATCH(Assets!$B$8,Countries!$A$2:$A$5,0)),MAX(INDEX(Countries!$E$2:$E$5,MATCH(Assets!$B$8,Countries!$A$2:$A$5,0)),INDEX(Countries!$D$2:$D$5,MATCH(Assets!$B$8,Countries!$A$2:$A$5,0)))))^(I$3-1)*INDEX(Countries!$C$2:$C$5,MATCH(Assets!$B$8,Countries!$A$2:$A$5,0))/Assets!$H$8,0) -> 0 | ... L18: =IF(AND(Assets!$G$8<>"",Assets!$G$8>=L$4,Assets!$G$8<EDATE(L$4,12)),Assets!$C$8*Assets!$F$8*(1+MIN(INDEX(Countries!$F$2:$F$5,MATCH(Assets!$B$8,Countries!$A$2:$A$5,0)),MAX(INDEX(Countries!$E$2:$E$5,MATCH(Assets!$B$8,Countries!$A$2:$A$5,0)),INDEX(Countries!$D$2:$D$5,MATCH(Assets!$B$8,Countries!$A$2:$A$5,0)))))^(L$3-1)*INDEX(Countries!$C$2:$C$5,MATCH(Assets!$B$8,Countries!$A$2:$A$5,0))/Assets!$H$8,0) -> 0
A19: Thames Gateway · rent (EUR) | B19: =IF(AND(B$3>=1,B$3<=Inputs!$B$11,OR(Assets!$G$9="",B$4<Assets!$G$9)),Assets!$C$9*(Assets!$D$9*(1+MIN(INDEX(Countries!$F$2:$F$5,MATCH(Assets!$B$9,Countries!$A$2:$A$5,0)),MAX(INDEX(Countries!$E$2:$E$5,MATCH(Assets!$B$9,Countries!$A$2:$A$5,0)),INDEX(Countries!$D$2:$D$5,MATCH(Assets!$B$9,Countries!$A$2:$A$5,0)))))^(B$3-1)*MAX(0,MIN(1,YEARFRAC(B$4,MIN(Assets!$E$9,EDATE(B$4,12)),1)*(Assets!$E$9>B$4)))+Assets!$F$9*(1+MIN(INDEX(Countries!$F$2:$F$5,MATCH(Assets!$B$9,Countries!$A$2:$A$5,0)),MAX(INDEX(Countries!$E$2:$E$5,MATCH(Assets!$B$9,Countries!$A$2:$A$5,0)),INDEX(Countries!$D$2:$D$5,MATCH(Assets!$B$9,Countries!$A$2:$A$5,0)))))^(B$3-1)*IF(Assets!$E$9<EDATE(B$4,12),(Inputs!$B$13*MAX(0,MIN(12,DATEDIF(MAX(Assets!$E$9,B$4),EDATE(B$4,12),"m")))+(1-Inputs!$B$13)*MAX(0,MAX(0,MIN(12,DATEDIF(MAX(Assets!$E$9,B$4),EDATE(B$4,12),"m")))-MAX(0,Inputs!$B$12-IF(Assets!$E$9<B$4,DATEDIF(Assets!$E$9,B$4,"m"),0))))/12,0))*INDEX(Countries!$C$2:$C$5,MATCH(Assets!$B$9,Countries!$A$2:$A$5,0)),0) -> 0 | C19: =IF(AND(C$3>=1,C$3<=Inputs!$B$11,OR(Assets!$G$9="",C$4<Assets!$G$9)),Assets!$C$9*(Assets!$D$9*(1+MIN(INDEX(Countries!$F$2:$F$5,MATCH(Assets!$B$9,Countries!$A$2:$A$5,0)),MAX(INDEX(Countries!$E$2:$E$5,MATCH(Assets!$B$9,Countries!$A$2:$A$5,0)),INDEX(Countries!$D$2:$D$5,MATCH(Assets!$B$9,Countries!$A$2:$A$5,0)))))^(C$3-1)*MAX(0,MIN(1,YEARFRAC(C$4,MIN(Assets!$E$9,EDATE(C$4,12)),1)*(Assets!$E$9>C$4)))+Assets!$F$9*(1+MIN(INDEX(Countries!$F$2:$F$5,MATCH(Assets!$B$9,Countries!$A$2:$A$5,0)),MAX(INDEX(Countries!$E$2:$E$5,MATCH(Assets!$B$9,Countries!$A$2:$A$5,0)),INDEX(Countries!$D$2:$D$5,MATCH(Assets!$B$9,Countries!$A$2:$A$5,0)))))^(C$3-1)*IF(Assets!$E$9<EDATE(C$4,12),(Inputs!$B$13*MAX(0,MIN(12,DATEDIF(MAX(Assets!$E$9,C$4),EDATE(C$4,12),"m")))+(1-Inputs!$B$13)*MAX(0,MAX(0,MIN(12,DATEDIF(MAX(Assets!$E$9,C$4),EDATE(C$4,12),"m")))-MAX(0,Inputs!$B$12-IF(Assets!$E$9<C$4,DATEDIF(Assets!$E$9,C$4,"m"),0))))/12,0))*INDEX(Countries!$C$2:$C$5,MATCH(Assets!$B$9,Countries!$A$2:$A$5,0)),0) -> 5962320 | D19: =IF(AND(D$3>=1,D$3<=Inputs!$B$11,OR(Assets!$G$9="",D$4<Assets!$G$9)),Assets!$C$9*(Assets!$D$9*(1+MIN(INDEX(Countries!$F$2:$F$5,MATCH(Assets!$B$9,Countries!$A$2:$A$5,0)),MAX(INDEX(Countries!$E$2:$E$5,MATCH(Assets!$B$9,Countries!$A$2:$A$5,0)),INDEX(Countries!$D$2:$D$5,MATCH(Assets!$B$9,Countries!$A$2:$A$5,0)))))^(D$3-1)*MAX(0,MIN(1,YEARFRAC(D$4,MIN(Assets!$E$9,EDATE(D$4,12)),1)*(Assets!$E$9>D$4)))+Assets!$F$9*(1+MIN(INDEX(Countries!$F$2:$F$5,MATCH(Assets!$B$9,Countries!$A$2:$A$5,0)),MAX(INDEX(Countries!$E$2:$E$5,MATCH(Assets!$B$9,Countries!$A$2:$A$5,0)),INDEX(Countries!$D$2:$D$5,MATCH(Assets!$B$9,Countries!$A$2:$A$5,0)))))^(D$3-1)*IF(Assets!$E$9<EDATE(D$4,12),(Inputs!$B$13*MAX(0,MIN(12,DATEDIF(MAX(Assets!$E$9,D$4),EDATE(D$4,12),"m")))+(1-Inputs!$B$13)*MAX(0,MAX(0,MIN(12,DATEDIF(MAX(Assets!$E$9,D$4),EDATE(D$4,12),"m")))-MAX(0,Inputs!$B$12-IF(Assets!$E$9<D$4,DATEDIF(Assets!$E$9,D$4,"m"),0))))/12,0))*INDEX(Countries!$C$2:$C$5,MATCH(Assets!$B$9,Countries!$A$2:$A$5,0)),0) -> 4442860 | E19: =IF(AND(E$3>=1,E$3<=Inputs!$B$11,OR(Assets!$G$9="",E$4<Assets!$G$9)),Assets!$C$9*(Assets!$D$9*(1+MIN(INDEX(Countries!$F$2:$F$5,MATCH(Assets!$B$9,Countries!$A$2:$A$5,0)),MAX(INDEX(Countries!$E$2:$E$5,MATCH(Assets!$B$9,Countries!$A$2:$A$5,0)),INDEX(Countries!$D$2:$D$5,MATCH(Assets!$B$9,Countries!$A$2:$A$5,0)))))^(E$3-1)*MAX(0,MIN(1,YEARFRAC(E$4,MIN(Assets!$E$9,EDATE(E$4,12)),1)*(Assets!$E$9>E$4)))+Assets!$F$9*(1+MIN(INDEX(Countries!$F$2:$F$5,MATCH(Assets!$B$9,Countries!$A$2:$A$5,0)),MAX(INDEX(Countries!$E$2:$E$5,MATCH(Assets!$B$9,Countries!$A$2:$A$5,0)),INDEX(Countries!$D$2:$D$5,MATCH(Assets!$B$9,Countries!$A$2:$A$5,0)))))^(E$3-1)*IF(Assets!$E$9<EDATE(E$4,12),(Inputs!$B$13*MAX(0,MIN(12,DATEDIF(MAX(Assets!$E$9,E$4),EDATE(E$4,12),"m")))+(1-Inputs!$B$13)*MAX(0,MAX(0,MIN(12,DATEDIF(MAX(Assets!$E$9,E$4),EDATE(E$4,12),"m")))-MAX(0,Inputs!$B$12-IF(Assets!$E$9<E$4,DATEDIF(Assets!$E$9,E$4,"m"),0))))/12,0))*INDEX(Countries!$C$2:$C$5,MATCH(Assets!$B$9,Countries!$A$2:$A$5,0)),0) -> 6712696.2 | F19: =IF(AND(F$3>=1,F$3<=Inputs!$B$11,OR(Assets!$G$9="",F$4<Assets!$G$9)),Assets!$C$9*(Assets!$D$9*(1+MIN(INDEX(Countries!$F$2:$F$5,MATCH(Assets!$B$9,Countries!$A$2:$A$5,0)),MAX(INDEX(Countries!$E$2:$E$5,MATCH(Assets!$B$9,Countries!$A$2:$A$5,0)),INDEX(Countries!$D$2:$D$5,MATCH(Assets!$B$9,Countries!$A$2:$A$5,0)))))^(F$3-1)*MAX(0,MIN(1,YEARFRAC(F$4,MIN(Assets!$E$9,EDATE(F$4,12)),1)*(Assets!$E$9>F$4)))+Assets!$F$9*(1+MIN(INDEX(Countries!$F$2:$F$5,MATCH(Assets!$B$9,Countries!$A$2:$A$5,0)),MAX(INDEX(Countries!$E$2:$E$5,MATCH(Assets!$B$9,Countries!$A$2:$A$5,0)),INDEX(Countries!$D$2:$D$5,MATCH(Assets!$B$9,Countries!$A$2:$A$5,0)))))^(F$3-1)*IF(Assets!$E$9<EDATE(F$4,12),(Inputs!$B$13*MAX(0,MIN(12,DATEDIF(MAX(Assets!$E$9,F$4),EDATE(F$4,12),"m")))+(1-Inputs!$B$13)*MAX(0,MAX(0,MIN(12,DATEDIF(MAX(Assets!$E$9,F$4),EDATE(F$4,12),"m")))-MAX(0,Inputs!$B$12-IF(Assets!$E$9<F$4,DATEDIF(Assets!$E$9,F$4,"m"),0))))/12,0))*INDEX(Countries!$C$2:$C$5,MATCH(Assets!$B$9,Countries!$A$2:$A$5,0)),0) -> 6914077.1 | G19: =IF(AND(G$3>=1,G$3<=Inputs!$B$11,OR(Assets!$G$9="",G$4<Assets!$G$9)),Assets!$C$9*(Assets!$D$9*(1+MIN(INDEX(Countries!$F$2:$F$5,MATCH(Assets!$B$9,Countries!$A$2:$A$5,0)),MAX(INDEX(Countries!$E$2:$E$5,MATCH(Assets!$B$9,Countries!$A$2:$A$5,0)),INDEX(Countries!$D$2:$D$5,MATCH(Assets!$B$9,Countries!$A$2:$A$5,0)))))^(G$3-1)*MAX(0,MIN(1,YEARFRAC(G$4,MIN(Assets!$E$9,EDATE(G$4,12)),1)*(Assets!$E$9>G$4)))+Assets!$F$9*(1+MIN(INDEX(Countries!$F$2:$F$5,MATCH(Assets!$B$9,Countries!$A$2:$A$5,0)),MAX(INDEX(Countries!$E$2:$E$5,MATCH(Assets!$B$9,Countries!$A$2:$A$5,0)),INDEX(Countries!$D$2:$D$5,MATCH(Assets!$B$9,Countries!$A$2:$A$5,0)))))^(G$3-1)*IF(Assets!$E$9<EDATE(G$4,12),(Inputs!$B$13*MAX(0,MIN(12,DATEDIF(MAX(Assets!$E$9,G$4),EDATE(G$4,12),"m")))+(1-Inputs!$B$13)*MAX(0,MAX(0,MIN(12,DATEDIF(MAX(Assets!$E$9,G$4),EDATE(G$4,12),"m")))-MAX(0,Inputs!$B$12-IF(Assets!$E$9<G$4,DATEDIF(Assets!$E$9,G$4,"m"),0))))/12,0))*INDEX(Countries!$C$2:$C$5,MATCH(Assets!$B$9,Countries!$A$2:$A$5,0)),0) -> 7121499.4 | H19: =IF(AND(H$3>=1,H$3<=Inputs!$B$11,OR(Assets!$G$9="",H$4<Assets!$G$9)),Assets!$C$9*(Assets!$D$9*(1+MIN(INDEX(Countries!$F$2:$F$5,MATCH(Assets!$B$9,Countries!$A$2:$A$5,0)),MAX(INDEX(Countries!$E$2:$E$5,MATCH(Assets!$B$9,Countries!$A$2:$A$5,0)),INDEX(Countries!$D$2:$D$5,MATCH(Assets!$B$9,Countries!$A$2:$A$5,0)))))^(H$3-1)*MAX(0,MIN(1,YEARFRAC(H$4,MIN(Assets!$E$9,EDATE(H$4,12)),1)*(Assets!$E$9>H$4)))+Assets!$F$9*(1+MIN(INDEX(Countries!$F$2:$F$5,MATCH(Assets!$B$9,Countries!$A$2:$A$5,0)),MAX(INDEX(Countries!$E$2:$E$5,MATCH(Assets!$B$9,Countries!$A$2:$A$5,0)),INDEX(Countries!$D$2:$D$5,MATCH(Assets!$B$9,Countries!$A$2:$A$5,0)))))^(H$3-1)*IF(Assets!$E$9<EDATE(H$4,12),(Inputs!$B$13*MAX(0,MIN(12,DATEDIF(MAX(Assets!$E$9,H$4),EDATE(H$4,12),"m")))+(1-Inputs!$B$13)*MAX(0,MAX(0,MIN(12,DATEDIF(MAX(Assets!$E$9,H$4),EDATE(H$4,12),"m")))-MAX(0,Inputs!$B$12-IF(Assets!$E$9<H$4,DATEDIF(Assets!$E$9,H$4,"m"),0))))/12,0))*INDEX(Countries!$C$2:$C$5,MATCH(Assets!$B$9,Countries!$A$2:$A$5,0)),0) -> 7335144.4 | I19: =IF(AND(I$3>=1,I$3<=Inputs!$B$11,OR(Assets!$G$9="",I$4<Assets!$G$9)),Assets!$C$9*(Assets!$D$9*(1+MIN(INDEX(Countries!$F$2:$F$5,MATCH(Assets!$B$9,Countries!$A$2:$A$5,0)),MAX(INDEX(Countries!$E$2:$E$5,MATCH(Assets!$B$9,Countries!$A$2:$A$5,0)),INDEX(Countries!$D$2:$D$5,MATCH(Assets!$B$9,Countries!$A$2:$A$5,0)))))^(I$3-1)*MAX(0,MIN(1,YEARFRAC(I$4,MIN(Assets!$E$9,EDATE(I$4,12)),1)*(Assets!$E$9>I$4)))+Assets!$F$9*(1+MIN(INDEX(Countries!$F$2:$F$5,MATCH(Assets!$B$9,Countries!$A$2:$A$5,0)),MAX(INDEX(Countries!$E$2:$E$5,MATCH(Assets!$B$9,Countries!$A$2:$A$5,0)),INDEX(Countries!$D$2:$D$5,MATCH(Assets!$B$9,Countries!$A$2:$A$5,0)))))^(I$3-1)*IF(Assets!$E$9<EDATE(I$4,12),(Inputs!$B$13*MAX(0,MIN(12,DATEDIF(MAX(Assets!$E$9,I$4),EDATE(I$4,12),"m")))+(1-Inputs!$B$13)*MAX(0,MAX(0,MIN(12,DATEDIF(MAX(Assets!$E$9,I$4),EDATE(I$4,12),"m")))-MAX(0,Inputs!$B$12-IF(Assets!$E$9<I$4,DATEDIF(Assets!$E$9,I$4,"m"),0))))/12,0))*INDEX(Countries!$C$2:$C$5,MATCH(Assets!$B$9,Countries!$A$2:$A$5,0)),0) -> 7555198.7 | ... L19: =IF(AND(L$3>=1,L$3<=Inputs!$B$11,OR(Assets!$G$9="",L$4<Assets!$G$9)),Assets!$C$9*(Assets!$D$9*(1+MIN(INDEX(Countries!$F$2:$F$5,MATCH(Assets!$B$9,Countries!$A$2:$A$5,0)),MAX(INDEX(Countries!$E$2:$E$5,MATCH(Assets!$B$9,Countries!$A$2:$A$5,0)),INDEX(Countries!$D$2:$D$5,MATCH(Assets!$B$9,Countries!$A$2:$A$5,0)))))^(L$3-1)*MAX(0,MIN(1,YEARFRAC(L$4,MIN(Assets!$E$9,EDATE(L$4,12)),1)*(Assets!$E$9>L$4)))+Assets!$F$9*(1+MIN(INDEX(Countries!$F$2:$F$5,MATCH(Assets!$B$9,Countries!$A$2:$A$5,0)),MAX(INDEX(Countries!$E$2:$E$5,MATCH(Assets!$B$9,Countries!$A$2:$A$5,0)),INDEX(Countries!$D$2:$D$5,MATCH(Assets!$B$9,Countries!$A$2:$A$5,0)))))^(L$3-1)*IF(Assets!$E$9<EDATE(L$4,12),(Inputs!$B$13*MAX(0,MIN(12,DATEDIF(MAX(Assets!$E$9,L$4),EDATE(L$4,12),"m")))+(1-Inputs!$B$13)*MAX(0,MAX(0,MIN(12,DATEDIF(MAX(Assets!$E$9,L$4),EDATE(L$4,12),"m")))-MAX(0,Inputs!$B$12-IF(Assets!$E$9<L$4,DATEDIF(Assets!$E$9,L$4,"m"),0))))/12,0))*INDEX(Countries!$C$2:$C$5,MATCH(Assets!$B$9,Countries!$A$2:$A$5,0)),0) -> 0
A20: Thames Gateway · disposal (EUR) | B20: =IF(AND(Assets!$G$9<>"",Assets!$G$9>=B$4,Assets!$G$9<EDATE(B$4,12)),Assets!$C$9*Assets!$F$9*(1+MIN(INDEX(Countries!$F$2:$F$5,MATCH(Assets!$B$9,Countries!$A$2:$A$5,0)),MAX(INDEX(Countries!$E$2:$E$5,MATCH(Assets!$B$9,Countries!$A$2:$A$5,0)),INDEX(Countries!$D$2:$D$5,MATCH(Assets!$B$9,Countries!$A$2:$A$5,0)))))^(B$3-1)*INDEX(Countries!$C$2:$C$5,MATCH(Assets!$B$9,Countries!$A$2:$A$5,0))/Assets!$H$9,0) -> 0 | C20: =IF(AND(Assets!$G$9<>"",Assets!$G$9>=C$4,Assets!$G$9<EDATE(C$4,12)),Assets!$C$9*Assets!$F$9*(1+MIN(INDEX(Countries!$F$2:$F$5,MATCH(Assets!$B$9,Countries!$A$2:$A$5,0)),MAX(INDEX(Countries!$E$2:$E$5,MATCH(Assets!$B$9,Countries!$A$2:$A$5,0)),INDEX(Countries!$D$2:$D$5,MATCH(Assets!$B$9,Countries!$A$2:$A$5,0)))))^(C$3-1)*INDEX(Countries!$C$2:$C$5,MATCH(Assets!$B$9,Countries!$A$2:$A$5,0))/Assets!$H$9,0) -> 0 | D20: =IF(AND(Assets!$G$9<>"",Assets!$G$9>=D$4,Assets!$G$9<EDATE(D$4,12)),Assets!$C$9*Assets!$F$9*(1+MIN(INDEX(Countries!$F$2:$F$5,MATCH(Assets!$B$9,Countries!$A$2:$A$5,0)),MAX(INDEX(Countries!$E$2:$E$5,MATCH(Assets!$B$9,Countries!$A$2:$A$5,0)),INDEX(Countries!$D$2:$D$5,MATCH(Assets!$B$9,Countries!$A$2:$A$5,0)))))^(D$3-1)*INDEX(Countries!$C$2:$C$5,MATCH(Assets!$B$9,Countries!$A$2:$A$5,0))/Assets!$H$9,0) -> 0 | E20: =IF(AND(Assets!$G$9<>"",Assets!$G$9>=E$4,Assets!$G$9<EDATE(E$4,12)),Assets!$C$9*Assets!$F$9*(1+MIN(INDEX(Countries!$F$2:$F$5,MATCH(Assets!$B$9,Countries!$A$2:$A$5,0)),MAX(INDEX(Countries!$E$2:$E$5,MATCH(Assets!$B$9,Countries!$A$2:$A$5,0)),INDEX(Countries!$D$2:$D$5,MATCH(Assets!$B$9,Countries!$A$2:$A$5,0)))))^(E$3-1)*INDEX(Countries!$C$2:$C$5,MATCH(Assets!$B$9,Countries!$A$2:$A$5,0))/Assets!$H$9,0) -> 0 | F20: =IF(AND(Assets!$G$9<>"",Assets!$G$9>=F$4,Assets!$G$9<EDATE(F$4,12)),Assets!$C$9*Assets!$F$9*(1+MIN(INDEX(Countries!$F$2:$F$5,MATCH(Assets!$B$9,Countries!$A$2:$A$5,0)),MAX(INDEX(Countries!$E$2:$E$5,MATCH(Assets!$B$9,Countries!$A$2:$A$5,0)),INDEX(Countries!$D$2:$D$5,MATCH(Assets!$B$9,Countries!$A$2:$A$5,0)))))^(F$3-1)*INDEX(Countries!$C$2:$C$5,MATCH(Assets!$B$9,Countries!$A$2:$A$5,0))/Assets!$H$9,0) -> 0 | G20: =IF(AND(Assets!$G$9<>"",Assets!$G$9>=G$4,Assets!$G$9<EDATE(G$4,12)),Assets!$C$9*Assets!$F$9*(1+MIN(INDEX(Countries!$F$2:$F$5,MATCH(Assets!$B$9,Countries!$A$2:$A$5,0)),MAX(INDEX(Countries!$E$2:$E$5,MATCH(Assets!$B$9,Countries!$A$2:$A$5,0)),INDEX(Countries!$D$2:$D$5,MATCH(Assets!$B$9,Countries!$A$2:$A$5,0)))))^(G$3-1)*INDEX(Countries!$C$2:$C$5,MATCH(Assets!$B$9,Countries!$A$2:$A$5,0))/Assets!$H$9,0) -> 0 | H20: =IF(AND(Assets!$G$9<>"",Assets!$G$9>=H$4,Assets!$G$9<EDATE(H$4,12)),Assets!$C$9*Assets!$F$9*(1+MIN(INDEX(Countries!$F$2:$F$5,MATCH(Assets!$B$9,Countries!$A$2:$A$5,0)),MAX(INDEX(Countries!$E$2:$E$5,MATCH(Assets!$B$9,Countries!$A$2:$A$5,0)),INDEX(Countries!$D$2:$D$5,MATCH(Assets!$B$9,Countries!$A$2:$A$5,0)))))^(H$3-1)*INDEX(Countries!$C$2:$C$5,MATCH(Assets!$B$9,Countries!$A$2:$A$5,0))/Assets!$H$9,0) -> 0 | I20: =IF(AND(Assets!$G$9<>"",Assets!$G$9>=I$4,Assets!$G$9<EDATE(I$4,12)),Assets!$C$9*Assets!$F$9*(1+MIN(INDEX(Countries!$F$2:$F$5,MATCH(Assets!$B$9,Countries!$A$2:$A$5,0)),MAX(INDEX(Countries!$E$2:$E$5,MATCH(Assets!$B$9,Countries!$A$2:$A$5,0)),INDEX(Countries!$D$2:$D$5,MATCH(Assets!$B$9,Countries!$A$2:$A$5,0)))))^(I$3-1)*INDEX(Countries!$C$2:$C$5,MATCH(Assets!$B$9,Countries!$A$2:$A$5,0))/Assets!$H$9,0) -> 0 | ... L20: =IF(AND(Assets!$G$9<>"",Assets!$G$9>=L$4,Assets!$G$9<EDATE(L$4,12)),Assets!$C$9*Assets!$F$9*(1+MIN(INDEX(Countries!$F$2:$F$5,MATCH(Assets!$B$9,Countries!$A$2:$A$5,0)),MAX(INDEX(Countries!$E$2:$E$5,MATCH(Assets!$B$9,Countries!$A$2:$A$5,0)),INDEX(Countries!$D$2:$D$5,MATCH(Assets!$B$9,Countries!$A$2:$A$5,0)))))^(L$3-1)*INDEX(Countries!$C$2:$C$5,MATCH(Assets!$B$9,Countries!$A$2:$A$5,0))/Assets!$H$9,0) -> 0
A21: Rent (EUR) | B21: =B5+B7+B9+B11+B13+B15+B17+B19 -> 0 | C21: =C5+C7+C9+C11+C13+C15+C17+C19 -> 31989288 | D21: =D5+D7+D9+D11+D13+D15+D17+D19 -> 30195457 | E21: =E5+E7+E9+E11+E13+E15+E17+E19 -> 33598154 | F21: =F5+F7+F9+F11+F13+F15+F17+F19 -> 31021366 | G21: =G5+G7+G9+G11+G13+G15+G17+G19 -> 28784963 | H21: =H5+H7+H9+H11+H13+H15+H17+H19 -> 31383885 | I21: =I5+I7+I9+I11+I13+I15+I17+I19 -> 29398328 | ... L21: =L5+L7+L9+L11+L13+L15+L17+L19 -> 0
A22: Non-recoverable | B22: =B21*Inputs!$B$14 -> 0 | C22: =C21*Inputs!$B$14 -> 959678.64 | D22: =D21*Inputs!$B$14 -> 905863.71 | E22: =E21*Inputs!$B$14 -> 1007944.6 | F22: =F21*Inputs!$B$14 -> 930640.99 | G22: =G21*Inputs!$B$14 -> 863548.88 | H22: =H21*Inputs!$B$14 -> 941516.54 | I22: =I21*Inputs!$B$14 -> 881949.83 | ... L22: =L21*Inputs!$B$14 -> 0
A23: NOI | B23: =B21-B22 -> 0 | C23: =C21-C22 -> 31029609 | D23: =D21-D22 -> 29289593 | E23: =E21-E22 -> 32590209 | F23: =F21-F22 -> 30090725 | G23: =G21-G22 -> 27921414 | H23: =H21-H22 -> 30442368 | I23: =I21-I22 -> 28516378 | ... L23: =L21-L22 -> 0
A24: Disposals | B24: =B6+B8+B10+B12+B14+B16+B18+B20 -> 0 | C24: =C6+C8+C10+C12+C14+C16+C18+C20 -> 0 | D24: =D6+D8+D10+D12+D14+D16+D18+D20 -> 0 | E24: =E6+E8+E10+E12+E14+E16+E18+E20 -> 73515605 | F24: =F6+F8+F10+F12+F14+F16+F18+F20 -> 66187543 | G24: =G6+G8+G10+G12+G14+G16+G18+G20 -> 0 | H24: =H6+H8+H10+H12+H14+H16+H18+H20 -> 0 | I24: =I6+I8+I10+I12+I14+I16+I18+I20 -> 0 | ... L24: =L6+L8+L10+L12+L14+L16+L18+L20 -> 0
A25: Exit | B25: =IF(B$3=Inputs!$B$11,B23*1.02/Inputs!$B$10,0) -> 0 | C25: =IF(C$3=Inputs!$B$11,C23*1.02/Inputs!$B$10,0) -> 0 | D25: =IF(D$3=Inputs!$B$11,D23*1.02/Inputs!$B$10,0) -> 0 | E25: =IF(E$3=Inputs!$B$11,E23*1.02/Inputs!$B$10,0) -> 0 | F25: =IF(F$3=Inputs!$B$11,F23*1.02/Inputs!$B$10,0) -> 0 | G25: =IF(G$3=Inputs!$B$11,G23*1.02/Inputs!$B$10,0) -> 0 | H25: =IF(H$3=Inputs!$B$11,H23*1.02/Inputs!$B$10,0) -> 0 | I25: =IF(I$3=Inputs!$B$11,I23*1.02/Inputs!$B$10,0) -> 5.2884919e+08 | ... L25: =IF(L$3=Inputs!$B$11,L23*1.02/Inputs!$B$10,0) -> 0
A26: Loan | B26: =Inputs!$B$4*Inputs!$B$6 -> 305000000 | C26: =IF(C$3=0,Inputs!$B$4*Inputs!$B$6,IF(C$3>=Inputs!$B$11,0,B26-MIN(B26,C24+C30))) -> 305000000 | D26: =IF(D$3=0,Inputs!$B$4*Inputs!$B$6,IF(D$3>=Inputs!$B$11,0,C26-MIN(C26,D24+D30))) -> 2.8943541e+08 | E26: =IF(E$3=0,Inputs!$B$4*Inputs!$B$6,IF(E$3>=Inputs!$B$11,0,D26-MIN(D26,E24+E30))) -> 2.159198e+08 | F26: =IF(F$3=0,Inputs!$B$4*Inputs!$B$6,IF(F$3>=Inputs!$B$11,0,E26-MIN(E26,F24+F30))) -> 1.4973226e+08 | G26: =IF(G$3=0,Inputs!$B$4*Inputs!$B$6,IF(G$3>=Inputs!$B$11,0,F26-MIN(F26,G24+G30))) -> 1.4973226e+08 | H26: =IF(H$3=0,Inputs!$B$4*Inputs!$B$6,IF(H$3>=Inputs!$B$11,0,G26-MIN(G26,H24+H30))) -> 1.4973226e+08 | I26: =IF(I$3=0,Inputs!$B$4*Inputs!$B$6,IF(I$3>=Inputs!$B$11,0,H26-MIN(H26,I24+I30))) -> 0 | J26: =IF(J$3=0,Inputs!$B$4*Inputs!$B$6,IF(J$3>=Inputs!$B$11,0,I26-MIN(I26,J24+J30))) -> 0 | ... L26: =IF(L$3=0,Inputs!$B$4*Inputs!$B$6,IF(L$3>=Inputs!$B$11,0,K26-MIN(K26,L24+L30))) -> 0
A27: Interest | B27: =0 -> 0 | C27: =IF(AND(C$3>=1,C$3<=Inputs!$B$11),B26*Inputs!$B$7,0) -> 13725000 | D27: =IF(AND(D$3>=1,D$3<=Inputs!$B$11),C26*Inputs!$B$7,0) -> 13725000 | E27: =IF(AND(E$3>=1,E$3<=Inputs!$B$11),D26*Inputs!$B$7,0) -> 13024593 | F27: =IF(AND(F$3>=1,F$3<=Inputs!$B$11),E26*Inputs!$B$7,0) -> 9716391.1 | G27: =IF(AND(G$3>=1,G$3<=Inputs!$B$11),F26*Inputs!$B$7,0) -> 6737951.7 | H27: =IF(AND(H$3>=1,H$3<=Inputs!$B$11),G26*Inputs!$B$7,0) -> 6737951.7 | I27: =IF(AND(I$3>=1,I$3<=Inputs!$B$11),H26*Inputs!$B$7,0) -> 6737951.7 | J27: =IF(AND(J$3>=1,J$3<=Inputs!$B$11),I26*Inputs!$B$7,0) -> 0 | ... L27: =IF(AND(L$3>=1,L$3<=Inputs!$B$11),K26*Inputs!$B$7,0) -> 0
A28: Value (EUR) | B28: =IF(B$3=0,'Cash Flow'!C23,B23)/Inputs!$B$10 -> 5.6417471e+08 | C28: =IF(C$3=0,'Cash Flow'!C23,C23)/Inputs!$B$10 -> 5.6417471e+08 | D28: =IF(D$3=0,'Cash Flow'!C23,D23)/Inputs!$B$10 -> 5.3253806e+08 | E28: =IF(E$3=0,'Cash Flow'!C23,E23)/Inputs!$B$10 -> 5.9254925e+08 | F28: =IF(F$3=0,'Cash Flow'!C23,F23)/Inputs!$B$10 -> 5.471041e+08 | G28: =IF(G$3=0,'Cash Flow'!C23,G23)/Inputs!$B$10 -> 5.0766207e+08 | H28: =IF(H$3=0,'Cash Flow'!C23,H23)/Inputs!$B$10 -> 5.534976e+08 | I28: =IF(I$3=0,'Cash Flow'!C23,I23)/Inputs!$B$10 -> 5.184796e+08 | J28: =IF(J$3=0,'Cash Flow'!C23,J23)/Inputs!$B$10 -> 0 | K28: =IF(K$3=0,'Cash Flow'!C23,K23)/Inputs!$B$10 -> 0 | L28: =IF(L$3=0,'Cash Flow'!C23,L23)/Inputs!$B$10 -> 0
A29: LTV | B29: =IF(B28>0,B26/B28,0) -> 0.54061267 | C29: =IF(C28>0,B26/C28,0) -> 0.54061267 | D29: =IF(D28>0,C26/D28,0) -> 0.57272902 | E29: =IF(E28>0,D26/E28,0) -> 0.48845797 | F29: =IF(F28>0,E26/F28,0) -> 0.39465945 | G29: =IF(G28>0,F26/G28,0) -> 0.29494474 | H29: =IF(H28>0,G26/H28,0) -> 0.27052016 | I29: =IF(I28>0,H26/I28,0) -> 0.28879103 | J29: =IF(J28>0,I26/J28,0) -> 0 | ... L29: =IF(L28>0,K26/L28,0) -> 0
A30: Cash trap | B30: =IF(AND(B$3>=1,B$3<Inputs!$B$11,B29>Inputs!$B$9),MAX(0,B23-B27),0) -> 0 | C30: =IF(AND(C$3>=1,C$3<Inputs!$B$11,C29>Inputs!$B$9),MAX(0,C23-C27),0) -> 0 | D30: =IF(AND(D$3>=1,D$3<Inputs!$B$11,D29>Inputs!$B$9),MAX(0,D23-D27),0) -> 15564593 | E30: =IF(AND(E$3>=1,E$3<Inputs!$B$11,E29>Inputs!$B$9),MAX(0,E23-E27),0) -> 0 | F30: =IF(AND(F$3>=1,F$3<Inputs!$B$11,F29>Inputs!$B$9),MAX(0,F23-F27),0) -> 0 | G30: =IF(AND(G$3>=1,G$3<Inputs!$B$11,G29>Inputs!$B$9),MAX(0,G23-G27),0) -> 0 | H30: =IF(AND(H$3>=1,H$3<Inputs!$B$11,H29>Inputs!$B$9),MAX(0,H23-H27),0) -> 0 | I30: =IF(AND(I$3>=1,I$3<Inputs!$B$11,I29>Inputs!$B$9),MAX(0,I23-I27),0) -> 0 | ... L30: =IF(AND(L$3>=1,L$3<Inputs!$B$11,L29>Inputs!$B$9),MAX(0,L23-L27),0) -> 0
A31: Equity cash flow | B31: =-Inputs!$B$4*(1+Inputs!$B$5)+Inputs!$B$4*Inputs!$B$6 -> -329400000 | C31: =C23-C27+C24+C25-(B26-C26)-C30+IF(C$3=Inputs!$B$11,SUM($C$30:C30),0) -> 17304609 | D31: =D23-D27+D24+D25-(C26-D26)-D30+IF(D$3=Inputs!$B$11,SUM($C$30:D30),0) -> -15564593 | E31: =E23-E27+E24+E25-(D26-E26)-E30+IF(E$3=Inputs!$B$11,SUM($C$30:E30),0) -> 19565616 | F31: =F23-F27+F24+F25-(E26-F26)-F30+IF(F$3=Inputs!$B$11,SUM($C$30:F30),0) -> 20374334 | G31: =G23-G27+G24+G25-(F26-G26)-G30+IF(G$3=Inputs!$B$11,SUM($C$30:G30),0) -> 21183462 | H31: =H23-H27+H24+H25-(G26-H26)-H30+IF(H$3=Inputs!$B$11,SUM($C$30:H30),0) -> 23704417 | I31: =I23-I27+I24+I25-(H26-I26)-I30+IF(I$3=Inputs!$B$11,SUM($C$30:I30),0) -> 4.1645995e+08 | J31: =J23-J27+J24+J25-(I26-J26)-J30+IF(J$3=Inputs!$B$11,SUM($C$30:J30),0) -> 0 | ... L31: =L23-L27+L24+L25-(K26-L26)-L30+IF(L$3=Inputs!$B$11,SUM($C$30:L30),0) -> 0
A32: Unlevered cash flow | B32: =-Inputs!$B$4*(1+Inputs!$B$5) -> -634400000 | C32: =C23+C24+C25 -> 31029609 | D32: =D23+D24+D25 -> 29289593 | E32: =E23+E24+E25 -> 1.0610581e+08 | F32: =F23+F24+F25 -> 96278268 | G32: =G23+G24+G25 -> 27921414 | H32: =H23+H24+H25 -> 30442368 | I32: =I23+I24+I25 -> 5.5736557e+08 | J32: =J23+J24+J25 -> 0 | ... L32: =L23+L24+L25 -> 0

Sheet Returns
A3: Levered IRR (XIRR) | B3: =XIRR('Cash Flow'!B31:L31,'Cash Flow'!B4:L4) -> 0.067374814
A4: Unlevered IRR (XIRR) | B4: =XIRR('Cash Flow'!B32:L32,'Cash Flow'!B4:L4) -> 0.059739847
A5: Equity multiple | B5: =SUMIF('Cash Flow'!B31:L31,">0")/-SUMIF('Cash Flow'!B31:L31,"<0") -> 1.5033206
A6: Net profit (EUR) | B6: =SUM('Cash Flow'!B31:L31) -> 1.7362779e+08
A7: Peak LTV | B7: =MAX('Cash Flow'!C29:L29) -> 0.57272902
A8: Years in cash trap | B8: =COUNTIF('Cash Flow'!C30:L30,">0") -> 1
A9: Year 1 NOI (EUR) | B9: ='Cash Flow'!C23 -> 31029609
A10: Disposal proceeds (EUR) | B10: =SUM('Cash Flow'!B24:L24) -> 1.3970315e+08
A11: Covenant breached | B11: =IF(B7>Inputs!$B$8,"Yes","No") -> No
