Workbook

Sheet Fund
A1: ATLAS OPPORTUNITY FUND III – FUND MODEL WITH FOUR DEALS (USD)
A3: Case (1 Base, 2 Downside, 3 Upside) | B3: 1
A4: Commitments ($) | B4: 400000000
A5: First close | B5: 46112
A6: Management fee on commitments (first 3 years) | B6: 0.0175
A7: Management fee on invested capital (after) | B7: 0.0125
A8: Fund facility (% of a call, bridged two quarters) | B8: 1
A9: Fund facility rate | B9: 0.065
A10: Preferred return | B10: 0.08
A11: GP catch-up | B11: 1
A12: Carried interest | B12: 0.2
A13: Second hurdle IRR | B13: 0.15
A14: Carry above the second hurdle | B14: 0.3

Sheet Deal A Logistics
A1: DEAL A LOGISTICS
A3: Equity ($) | B3: 60000000
A4: NOI year 1 ($) | B4: 8600000
A5: NOI growth | B5: 0.03
A6: Loan to value | B6: 0.55
A7: Interest rate | B7: 0.058
A8: Acquisition quarter | B8: 1
A9: Hold (quarters) | B9: 20
A10: Exit cap · Base | B10: 0.0575
A11: Exit cap · Downside | B11: 0.065
A12: Exit cap · Upside | B12: 0.0525
A14: Exit cap (live case) | B14: =CHOOSE(Fund_Case,'Deal A Logistics'!$B$10,'Deal A Logistics'!$B$11,'Deal A Logistics'!$B$12) -> 0.0575
A17: Quarter | B17: 0 | C17: 1 | D17: 2 | E17: 3 | F17: 4 | G17: 5 | H17: 6 | I17: 7 | J17: 8 | K17: 9 | L17: 10 | M17: 11 | N17: 12 | O17: 13 | P17: 14 | Q17: 15 | R17: 16 | S17: 17 | T17: 18 | U17: 19 | V17: 20 | W17: 21 | X17: 22 | Y17: 23 | Z17: 24 | AA17: 25 | AB17: 26 | AC17: 27 | AD17: 28 | AE17: 29 | AF17: 30 | AG17: 31 | AH17: 32
A18: NOI | B18: =IF(AND(B$17>'Deal A Logistics'!$B$8,B$17<='Deal A Logistics'!$B$8+'Deal A Logistics'!$B$9),'Deal A Logistics'!$B$4/4*(1+'Deal A Logistics'!$B$5)^((B$17-'Deal A Logistics'!$B$8-1)/4),0) -> 0 | C18: =IF(AND(C$17>'Deal A Logistics'!$B$8,C$17<='Deal A Logistics'!$B$8+'Deal A Logistics'!$B$9),'Deal A Logistics'!$B$4/4*(1+'Deal A Logistics'!$B$5)^((C$17-'Deal A Logistics'!$B$8-1)/4),0) -> 0 | D18: =IF(AND(D$17>'Deal A Logistics'!$B$8,D$17<='Deal A Logistics'!$B$8+'Deal A Logistics'!$B$9),'Deal A Logistics'!$B$4/4*(1+'Deal A Logistics'!$B$5)^((D$17-'Deal A Logistics'!$B$8-1)/4),0) -> 2150000 | E18: =IF(AND(E$17>'Deal A Logistics'!$B$8,E$17<='Deal A Logistics'!$B$8+'Deal A Logistics'!$B$9),'Deal A Logistics'!$B$4/4*(1+'Deal A Logistics'!$B$5)^((E$17-'Deal A Logistics'!$B$8-1)/4),0) -> 2165946.7 | F18: =IF(AND(F$17>'Deal A Logistics'!$B$8,F$17<='Deal A Logistics'!$B$8+'Deal A Logistics'!$B$9),'Deal A Logistics'!$B$4/4*(1+'Deal A Logistics'!$B$5)^((F$17-'Deal A Logistics'!$B$8-1)/4),0) -> 2182011.7 | G18: =IF(AND(G$17>'Deal A Logistics'!$B$8,G$17<='Deal A Logistics'!$B$8+'Deal A Logistics'!$B$9),'Deal A Logistics'!$B$4/4*(1+'Deal A Logistics'!$B$5)^((G$17-'Deal A Logistics'!$B$8-1)/4),0) -> 2198195.8 | H18: =IF(AND(H$17>'Deal A Logistics'!$B$8,H$17<='Deal A Logistics'!$B$8+'Deal A Logistics'!$B$9),'Deal A Logistics'!$B$4/4*(1+'Deal A Logistics'!$B$5)^((H$17-'Deal A Logistics'!$B$8-1)/4),0) -> 2214500 | I18: =IF(AND(I$17>'Deal A Logistics'!$B$8,I$17<='Deal A Logistics'!$B$8+'Deal A Logistics'!$B$9),'Deal A Logistics'!$B$4/4*(1+'Deal A Logistics'!$B$5)^((I$17-'Deal A Logistics'!$B$8-1)/4),0) -> 2230925.1 | ... AH18: =IF(AND(AH$17>'Deal A Logistics'!$B$8,AH$17<='Deal A Logistics'!$B$8+'Deal A Logistics'!$B$9),'Deal A Logistics'!$B$4/4*(1+'Deal A Logistics'!$B$5)^((AH$17-'Deal A Logistics'!$B$8-1)/4),0) -> 0
A19: Interest | B19: =IF(AND(B$17>'Deal A Logistics'!$B$8,B$17<='Deal A Logistics'!$B$8+'Deal A Logistics'!$B$9),('Deal A Logistics'!$B$3/(1-'Deal A Logistics'!$B$6))*'Deal A Logistics'!$B$6*'Deal A Logistics'!$B$7/4,0) -> 0 | C19: =IF(AND(C$17>'Deal A Logistics'!$B$8,C$17<='Deal A Logistics'!$B$8+'Deal A Logistics'!$B$9),('Deal A Logistics'!$B$3/(1-'Deal A Logistics'!$B$6))*'Deal A Logistics'!$B$6*'Deal A Logistics'!$B$7/4,0) -> 0 | D19: =IF(AND(D$17>'Deal A Logistics'!$B$8,D$17<='Deal A Logistics'!$B$8+'Deal A Logistics'!$B$9),('Deal A Logistics'!$B$3/(1-'Deal A Logistics'!$B$6))*'Deal A Logistics'!$B$6*'Deal A Logistics'!$B$7/4,0) -> 1063333.3 | E19: =IF(AND(E$17>'Deal A Logistics'!$B$8,E$17<='Deal A Logistics'!$B$8+'Deal A Logistics'!$B$9),('Deal A Logistics'!$B$3/(1-'Deal A Logistics'!$B$6))*'Deal A Logistics'!$B$6*'Deal A Logistics'!$B$7/4,0) -> 1063333.3 | F19: =IF(AND(F$17>'Deal A Logistics'!$B$8,F$17<='Deal A Logistics'!$B$8+'Deal A Logistics'!$B$9),('Deal A Logistics'!$B$3/(1-'Deal A Logistics'!$B$6))*'Deal A Logistics'!$B$6*'Deal A Logistics'!$B$7/4,0) -> 1063333.3 | G19: =IF(AND(G$17>'Deal A Logistics'!$B$8,G$17<='Deal A Logistics'!$B$8+'Deal A Logistics'!$B$9),('Deal A Logistics'!$B$3/(1-'Deal A Logistics'!$B$6))*'Deal A Logistics'!$B$6*'Deal A Logistics'!$B$7/4,0) -> 1063333.3 | H19: =IF(AND(H$17>'Deal A Logistics'!$B$8,H$17<='Deal A Logistics'!$B$8+'Deal A Logistics'!$B$9),('Deal A Logistics'!$B$3/(1-'Deal A Logistics'!$B$6))*'Deal A Logistics'!$B$6*'Deal A Logistics'!$B$7/4,0) -> 1063333.3 | I19: =IF(AND(I$17>'Deal A Logistics'!$B$8,I$17<='Deal A Logistics'!$B$8+'Deal A Logistics'!$B$9),('Deal A Logistics'!$B$3/(1-'Deal A Logistics'!$B$6))*'Deal A Logistics'!$B$6*'Deal A Logistics'!$B$7/4,0) -> 1063333.3 | ... AH19: =IF(AND(AH$17>'Deal A Logistics'!$B$8,AH$17<='Deal A Logistics'!$B$8+'Deal A Logistics'!$B$9),('Deal A Logistics'!$B$3/(1-'Deal A Logistics'!$B$6))*'Deal A Logistics'!$B$6*'Deal A Logistics'!$B$7/4,0) -> 0
A20: Purchase | B20: =IF(B$17='Deal A Logistics'!$B$8,-'Deal A Logistics'!$B$3,0) -> 0 | C20: =IF(C$17='Deal A Logistics'!$B$8,-'Deal A Logistics'!$B$3,0) -> -60000000 | D20: =IF(D$17='Deal A Logistics'!$B$8,-'Deal A Logistics'!$B$3,0) -> 0 | E20: =IF(E$17='Deal A Logistics'!$B$8,-'Deal A Logistics'!$B$3,0) -> 0 | F20: =IF(F$17='Deal A Logistics'!$B$8,-'Deal A Logistics'!$B$3,0) -> 0 | G20: =IF(G$17='Deal A Logistics'!$B$8,-'Deal A Logistics'!$B$3,0) -> 0 | H20: =IF(H$17='Deal A Logistics'!$B$8,-'Deal A Logistics'!$B$3,0) -> 0 | I20: =IF(I$17='Deal A Logistics'!$B$8,-'Deal A Logistics'!$B$3,0) -> 0 | ... AH20: =IF(AH$17='Deal A Logistics'!$B$8,-'Deal A Logistics'!$B$3,0) -> 0
A21: Sale | B21: =IF((B$17='Deal A Logistics'!$B$8+'Deal A Logistics'!$B$9),B18*4*(1+'Deal A Logistics'!$B$5)/$B$14-('Deal A Logistics'!$B$3/(1-'Deal A Logistics'!$B$6))*'Deal A Logistics'!$B$6,0) -> 0 | C21: =IF((C$17='Deal A Logistics'!$B$8+'Deal A Logistics'!$B$9),C18*4*(1+'Deal A Logistics'!$B$5)/$B$14-('Deal A Logistics'!$B$3/(1-'Deal A Logistics'!$B$6))*'Deal A Logistics'!$B$6,0) -> 0 | D21: =IF((D$17='Deal A Logistics'!$B$8+'Deal A Logistics'!$B$9),D18*4*(1+'Deal A Logistics'!$B$5)/$B$14-('Deal A Logistics'!$B$3/(1-'Deal A Logistics'!$B$6))*'Deal A Logistics'!$B$6,0) -> 0 | E21: =IF((E$17='Deal A Logistics'!$B$8+'Deal A Logistics'!$B$9),E18*4*(1+'Deal A Logistics'!$B$5)/$B$14-('Deal A Logistics'!$B$3/(1-'Deal A Logistics'!$B$6))*'Deal A Logistics'!$B$6,0) -> 0 | F21: =IF((F$17='Deal A Logistics'!$B$8+'Deal A Logistics'!$B$9),F18*4*(1+'Deal A Logistics'!$B$5)/$B$14-('Deal A Logistics'!$B$3/(1-'Deal A Logistics'!$B$6))*'Deal A Logistics'!$B$6,0) -> 0 | G21: =IF((G$17='Deal A Logistics'!$B$8+'Deal A Logistics'!$B$9),G18*4*(1+'Deal A Logistics'!$B$5)/$B$14-('Deal A Logistics'!$B$3/(1-'Deal A Logistics'!$B$6))*'Deal A Logistics'!$B$6,0) -> 0 | H21: =IF((H$17='Deal A Logistics'!$B$8+'Deal A Logistics'!$B$9),H18*4*(1+'Deal A Logistics'!$B$5)/$B$14-('Deal A Logistics'!$B$3/(1-'Deal A Logistics'!$B$6))*'Deal A Logistics'!$B$6,0) -> 0 | I21: =IF((I$17='Deal A Logistics'!$B$8+'Deal A Logistics'!$B$9),I18*4*(1+'Deal A Logistics'!$B$5)/$B$14-('Deal A Logistics'!$B$3/(1-'Deal A Logistics'!$B$6))*'Deal A Logistics'!$B$6,0) -> 0 | ... AH21: =IF((AH$17='Deal A Logistics'!$B$8+'Deal A Logistics'!$B$9),AH18*4*(1+'Deal A Logistics'!$B$5)/$B$14-('Deal A Logistics'!$B$3/(1-'Deal A Logistics'!$B$6))*'Deal A Logistics'!$B$6,0) -> 0
A22: Equity cash flow | B22: =B20+B18-B19+B21 -> 0 | C22: =C20+C18-C19+C21 -> -60000000 | D22: =D20+D18-D19+D21 -> 1086666.7 | E22: =E20+E18-E19+E21 -> 1102613.4 | F22: =F20+F18-F19+F21 -> 1118678.4 | G22: =G20+G18-G19+G21 -> 1134862.5 | H22: =H20+H18-H19+H21 -> 1151166.7 | I22: =I20+I18-I19+I21 -> 1167591.8 | ... AH22: =AH20+AH18-AH19+AH21 -> 0
A24: Deal IRR | B24: =(1+IRR(B22:AH22,0.02))^4-1 -> 0.18774538
A25: Deal equity multiple | B25: =SUMIF(B22:AH22,">0")/-SUMIF(B22:AH22,"<0") -> 2.1473817

Sheet Deal B Resi Dev
A1: DEAL B RESI DEV
A3: Equity ($) | B3: 70000000
A4: Development cost ex interest ($) | B4: 180000000
A5: Sales revenue ($) | B5: 265000000
A6: Loan to cost (ex interest) | B6: 0.6
A7: Loan rate | B7: 0.075
A8: Start quarter | B8: 2
A9: Build (quarters) | B9: 10
A10: Sales period (quarters) | B10: 6
A11: Cost overrun | B11: 0
A17: Quarter | B17: 0 | C17: 1 | D17: 2 | E17: 3 | F17: 4 | G17: 5 | H17: 6 | I17: 7 | J17: 8 | K17: 9 | L17: 10 | M17: 11 | N17: 12 | O17: 13 | P17: 14 | Q17: 15 | R17: 16 | S17: 17 | T17: 18 | U17: 19 | V17: 20 | W17: 21 | X17: 22 | Y17: 23 | Z17: 24 | AA17: 25 | AB17: 26 | AC17: 27 | AD17: 28 | AE17: 29 | AF17: 30 | AG17: 31 | AH17: 32
A18: Build cost | B18: =IF(AND(B$17>='Deal B Resi Dev'!$B$8,B$17<'Deal B Resi Dev'!$B$8+'Deal B Resi Dev'!$B$9),'Deal B Resi Dev'!$B$4*(1+'Deal B Resi Dev'!$B$11)/'Deal B Resi Dev'!$B$9,0) -> 0 | C18: =IF(AND(C$17>='Deal B Resi Dev'!$B$8,C$17<'Deal B Resi Dev'!$B$8+'Deal B Resi Dev'!$B$9),'Deal B Resi Dev'!$B$4*(1+'Deal B Resi Dev'!$B$11)/'Deal B Resi Dev'!$B$9,0) -> 0 | D18: =IF(AND(D$17>='Deal B Resi Dev'!$B$8,D$17<'Deal B Resi Dev'!$B$8+'Deal B Resi Dev'!$B$9),'Deal B Resi Dev'!$B$4*(1+'Deal B Resi Dev'!$B$11)/'Deal B Resi Dev'!$B$9,0) -> 18000000 | E18: =IF(AND(E$17>='Deal B Resi Dev'!$B$8,E$17<'Deal B Resi Dev'!$B$8+'Deal B Resi Dev'!$B$9),'Deal B Resi Dev'!$B$4*(1+'Deal B Resi Dev'!$B$11)/'Deal B Resi Dev'!$B$9,0) -> 18000000 | F18: =IF(AND(F$17>='Deal B Resi Dev'!$B$8,F$17<'Deal B Resi Dev'!$B$8+'Deal B Resi Dev'!$B$9),'Deal B Resi Dev'!$B$4*(1+'Deal B Resi Dev'!$B$11)/'Deal B Resi Dev'!$B$9,0) -> 18000000 | G18: =IF(AND(G$17>='Deal B Resi Dev'!$B$8,G$17<'Deal B Resi Dev'!$B$8+'Deal B Resi Dev'!$B$9),'Deal B Resi Dev'!$B$4*(1+'Deal B Resi Dev'!$B$11)/'Deal B Resi Dev'!$B$9,0) -> 18000000 | H18: =IF(AND(H$17>='Deal B Resi Dev'!$B$8,H$17<'Deal B Resi Dev'!$B$8+'Deal B Resi Dev'!$B$9),'Deal B Resi Dev'!$B$4*(1+'Deal B Resi Dev'!$B$11)/'Deal B Resi Dev'!$B$9,0) -> 18000000 | I18: =IF(AND(I$17>='Deal B Resi Dev'!$B$8,I$17<'Deal B Resi Dev'!$B$8+'Deal B Resi Dev'!$B$9),'Deal B Resi Dev'!$B$4*(1+'Deal B Resi Dev'!$B$11)/'Deal B Resi Dev'!$B$9,0) -> 18000000 | ... AH18: =IF(AND(AH$17>='Deal B Resi Dev'!$B$8,AH$17<'Deal B Resi Dev'!$B$8+'Deal B Resi Dev'!$B$9),'Deal B Resi Dev'!$B$4*(1+'Deal B Resi Dev'!$B$11)/'Deal B Resi Dev'!$B$9,0) -> 0
A19: Interest capitalised | B19: =0 -> 0 | C19: =B26*'Deal B Resi Dev'!$B$7/4 -> 0 | D19: =C26*'Deal B Resi Dev'!$B$7/4 -> 0 | E19: =D26*'Deal B Resi Dev'!$B$7/4 -> 0 | F19: =E26*'Deal B Resi Dev'!$B$7/4 -> 0 | G19: =F26*'Deal B Resi Dev'!$B$7/4 -> 0 | H19: =G26*'Deal B Resi Dev'!$B$7/4 -> 0 | I19: =H26*'Deal B Resi Dev'!$B$7/4 -> 337500 | J19: =I26*'Deal B Resi Dev'!$B$7/4 -> 681328.12 | ... AH19: =AG26*'Deal B Resi Dev'!$B$7/4 -> 0
A20: Total cost | B20: =B18+B19 -> 0 | C20: =C18+C19 -> 0 | D20: =D18+D19 -> 18000000 | E20: =E18+E19 -> 18000000 | F20: =F18+F19 -> 18000000 | G20: =G18+G19 -> 18000000 | H20: =H18+H19 -> 18000000 | I20: =I18+I19 -> 18337500 | ... AH20: =AH18+AH19 -> 0
A21: Equity drawn | B21: =MIN(B20,MAX(0,(1-'Deal B Resi Dev'!$B$6)*'Deal B Resi Dev'!$B$4*(1+'Deal B Resi Dev'!$B$11)-0)) -> 0 | C21: =MIN(C20,MAX(0,(1-'Deal B Resi Dev'!$B$6)*'Deal B Resi Dev'!$B$4*(1+'Deal B Resi Dev'!$B$11)-B22)) -> 0 | D21: =MIN(D20,MAX(0,(1-'Deal B Resi Dev'!$B$6)*'Deal B Resi Dev'!$B$4*(1+'Deal B Resi Dev'!$B$11)-C22)) -> 18000000 | E21: =MIN(E20,MAX(0,(1-'Deal B Resi Dev'!$B$6)*'Deal B Resi Dev'!$B$4*(1+'Deal B Resi Dev'!$B$11)-D22)) -> 18000000 | F21: =MIN(F20,MAX(0,(1-'Deal B Resi Dev'!$B$6)*'Deal B Resi Dev'!$B$4*(1+'Deal B Resi Dev'!$B$11)-E22)) -> 18000000 | G21: =MIN(G20,MAX(0,(1-'Deal B Resi Dev'!$B$6)*'Deal B Resi Dev'!$B$4*(1+'Deal B Resi Dev'!$B$11)-F22)) -> 18000000 | H21: =MIN(H20,MAX(0,(1-'Deal B Resi Dev'!$B$6)*'Deal B Resi Dev'!$B$4*(1+'Deal B Resi Dev'!$B$11)-G22)) -> 0 | I21: =MIN(I20,MAX(0,(1-'Deal B Resi Dev'!$B$6)*'Deal B Resi Dev'!$B$4*(1+'Deal B Resi Dev'!$B$11)-H22)) -> 0 | J21: =MIN(J20,MAX(0,(1-'Deal B Resi Dev'!$B$6)*'Deal B Resi Dev'!$B$4*(1+'Deal B Resi Dev'!$B$11)-I22)) -> 0 | ... AH21: =MIN(AH20,MAX(0,(1-'Deal B Resi Dev'!$B$6)*'Deal B Resi Dev'!$B$4*(1+'Deal B Resi Dev'!$B$11)-AG22)) -> 0
A22: Cumulative equity | B22: =B21 -> 0 | C22: =B22+C21 -> 0 | D22: =C22+D21 -> 18000000 | E22: =D22+E21 -> 36000000 | F22: =E22+F21 -> 54000000 | G22: =F22+G21 -> 72000000 | H22: =G22+H21 -> 72000000 | I22: =H22+I21 -> 72000000 | J22: =I22+J21 -> 72000000 | ... AH22: =AG22+AH21 -> 72000000
A23: Loan drawn | B23: =B20-B21 -> 0 | C23: =C20-C21 -> 0 | D23: =D20-D21 -> 0 | E23: =E20-E21 -> 0 | F23: =F20-F21 -> 0 | G23: =G20-G21 -> 0 | H23: =H20-H21 -> 18000000 | I23: =I20-I21 -> 18337500 | ... AH23: =AH20-AH21 -> 0
A24: Revenue | B24: =IF(AND(B$17>='Deal B Resi Dev'!$B$8+'Deal B Resi Dev'!$B$9,B$17<'Deal B Resi Dev'!$B$8+'Deal B Resi Dev'!$B$9+'Deal B Resi Dev'!$B$10),'Deal B Resi Dev'!$B$5/'Deal B Resi Dev'!$B$10,0) -> 0 | C24: =IF(AND(C$17>='Deal B Resi Dev'!$B$8+'Deal B Resi Dev'!$B$9,C$17<'Deal B Resi Dev'!$B$8+'Deal B Resi Dev'!$B$9+'Deal B Resi Dev'!$B$10),'Deal B Resi Dev'!$B$5/'Deal B Resi Dev'!$B$10,0) -> 0 | D24: =IF(AND(D$17>='Deal B Resi Dev'!$B$8+'Deal B Resi Dev'!$B$9,D$17<'Deal B Resi Dev'!$B$8+'Deal B Resi Dev'!$B$9+'Deal B Resi Dev'!$B$10),'Deal B Resi Dev'!$B$5/'Deal B Resi Dev'!$B$10,0) -> 0 | E24: =IF(AND(E$17>='Deal B Resi Dev'!$B$8+'Deal B Resi Dev'!$B$9,E$17<'Deal B Resi Dev'!$B$8+'Deal B Resi Dev'!$B$9+'Deal B Resi Dev'!$B$10),'Deal B Resi Dev'!$B$5/'Deal B Resi Dev'!$B$10,0) -> 0 | F24: =IF(AND(F$17>='Deal B Resi Dev'!$B$8+'Deal B Resi Dev'!$B$9,F$17<'Deal B Resi Dev'!$B$8+'Deal B Resi Dev'!$B$9+'Deal B Resi Dev'!$B$10),'Deal B Resi Dev'!$B$5/'Deal B Resi Dev'!$B$10,0) -> 0 | G24: =IF(AND(G$17>='Deal B Resi Dev'!$B$8+'Deal B Resi Dev'!$B$9,G$17<'Deal B Resi Dev'!$B$8+'Deal B Resi Dev'!$B$9+'Deal B Resi Dev'!$B$10),'Deal B Resi Dev'!$B$5/'Deal B Resi Dev'!$B$10,0) -> 0 | H24: =IF(AND(H$17>='Deal B Resi Dev'!$B$8+'Deal B Resi Dev'!$B$9,H$17<'Deal B Resi Dev'!$B$8+'Deal B Resi Dev'!$B$9+'Deal B Resi Dev'!$B$10),'Deal B Resi Dev'!$B$5/'Deal B Resi Dev'!$B$10,0) -> 0 | I24: =IF(AND(I$17>='Deal B Resi Dev'!$B$8+'Deal B Resi Dev'!$B$9,I$17<'Deal B Resi Dev'!$B$8+'Deal B Resi Dev'!$B$9+'Deal B Resi Dev'!$B$10),'Deal B Resi Dev'!$B$5/'Deal B Resi Dev'!$B$10,0) -> 0 | ... AH24: =IF(AND(AH$17>='Deal B Resi Dev'!$B$8+'Deal B Resi Dev'!$B$9,AH$17<'Deal B Resi Dev'!$B$8+'Deal B Resi Dev'!$B$9+'Deal B Resi Dev'!$B$10),'Deal B Resi Dev'!$B$5/'Deal B Resi Dev'!$B$10,0) -> 0
A25: Repayment | B25: =MIN(B24,0+B23) -> 0 | C25: =MIN(C24,B26+C23) -> 0 | D25: =MIN(D24,C26+D23) -> 0 | E25: =MIN(E24,D26+E23) -> 0 | F25: =MIN(F24,E26+F23) -> 0 | G25: =MIN(G24,F26+G23) -> 0 | H25: =MIN(H24,G26+H23) -> 0 | I25: =MIN(I24,H26+I23) -> 0 | J25: =MIN(J24,I26+J23) -> 0 | ... AH25: =MIN(AH24,AG26+AH23) -> 0
A26: Loan balance | B26: =0+B23-B25 -> 0 | C26: =B26+C23-C25 -> 0 | D26: =C26+D23-D25 -> 0 | E26: =D26+E23-E25 -> 0 | F26: =E26+F23-F25 -> 0 | G26: =F26+G23-G25 -> 0 | H26: =G26+H23-H25 -> 18000000 | I26: =H26+I23-I25 -> 36337500 | J26: =I26+J23-J25 -> 55018828 | ... AH26: =AG26+AH23-AH25 -> 0
A27: Equity cash flow | B27: =B24-B25-B21 -> 0 | C27: =C24-C25-C21 -> 0 | D27: =D24-D25-D21 -> -18000000 | E27: =E24-E25-E21 -> -18000000 | F27: =F24-F25-F21 -> -18000000 | G27: =G24-G25-G21 -> -18000000 | H27: =H24-H25-H21 -> 0 | I27: =I24-I25-I21 -> 0 | ... AH27: =AH24-AH25-AH21 -> 0
A29: Deal IRR | B29: =(1+IRR(B27:AH27,0.02))^4-1 -> 0.26354052
A30: Deal equity multiple | B30: =SUMIF(B27:AH27,">0")/-SUMIF(B27:AH27,"<0") -> 2.0530824

Sheet Deal C Office
A1: DEAL C OFFICE
A3: Equity ($) | B3: 55000000
A4: NOI year 1 ($) | B4: 9400000
A5: NOI growth | B5: 0.02
A6: Loan to value | B6: 0.6
A7: Interest rate | B7: 0.061
A8: Acquisition quarter | B8: 3
A9: Hold (quarters) | B9: 24
A10: Exit cap · Base | B10: 0.07
A11: Exit cap · Downside | B11: 0.08
A12: Exit cap · Upside | B12: 0.0625
A14: Exit cap (live case) | B14: =CHOOSE(Fund_Case,'Deal C Office'!$B$10,'Deal C Office'!$B$11,'Deal C Office'!$B$12) -> 0.07
A17: Quarter | B17: 0 | C17: 1 | D17: 2 | E17: 3 | F17: 4 | G17: 5 | H17: 6 | I17: 7 | J17: 8 | K17: 9 | L17: 10 | M17: 11 | N17: 12 | O17: 13 | P17: 14 | Q17: 15 | R17: 16 | S17: 17 | T17: 18 | U17: 19 | V17: 20 | W17: 21 | X17: 22 | Y17: 23 | Z17: 24 | AA17: 25 | AB17: 26 | AC17: 27 | AD17: 28 | AE17: 29 | AF17: 30 | AG17: 31 | AH17: 32
A18: NOI | B18: =IF(AND(B$17>'Deal C Office'!$B$8,B$17<='Deal C Office'!$B$8+'Deal C Office'!$B$9),'Deal C Office'!$B$4/4*(1+'Deal C Office'!$B$5)^((B$17-'Deal C Office'!$B$8-1)/4),0) -> 0 | C18: =IF(AND(C$17>'Deal C Office'!$B$8,C$17<='Deal C Office'!$B$8+'Deal C Office'!$B$9),'Deal C Office'!$B$4/4*(1+'Deal C Office'!$B$5)^((C$17-'Deal C Office'!$B$8-1)/4),0) -> 0 | D18: =IF(AND(D$17>'Deal C Office'!$B$8,D$17<='Deal C Office'!$B$8+'Deal C Office'!$B$9),'Deal C Office'!$B$4/4*(1+'Deal C Office'!$B$5)^((D$17-'Deal C Office'!$B$8-1)/4),0) -> 0 | E18: =IF(AND(E$17>'Deal C Office'!$B$8,E$17<='Deal C Office'!$B$8+'Deal C Office'!$B$9),'Deal C Office'!$B$4/4*(1+'Deal C Office'!$B$5)^((E$17-'Deal C Office'!$B$8-1)/4),0) -> 0 | F18: =IF(AND(F$17>'Deal C Office'!$B$8,F$17<='Deal C Office'!$B$8+'Deal C Office'!$B$9),'Deal C Office'!$B$4/4*(1+'Deal C Office'!$B$5)^((F$17-'Deal C Office'!$B$8-1)/4),0) -> 2350000 | G18: =IF(AND(G$17>'Deal C Office'!$B$8,G$17<='Deal C Office'!$B$8+'Deal C Office'!$B$9),'Deal C Office'!$B$4/4*(1+'Deal C Office'!$B$5)^((G$17-'Deal C Office'!$B$8-1)/4),0) -> 2361662.9 | H18: =IF(AND(H$17>'Deal C Office'!$B$8,H$17<='Deal C Office'!$B$8+'Deal C Office'!$B$9),'Deal C Office'!$B$4/4*(1+'Deal C Office'!$B$5)^((H$17-'Deal C Office'!$B$8-1)/4),0) -> 2373383.7 | I18: =IF(AND(I$17>'Deal C Office'!$B$8,I$17<='Deal C Office'!$B$8+'Deal C Office'!$B$9),'Deal C Office'!$B$4/4*(1+'Deal C Office'!$B$5)^((I$17-'Deal C Office'!$B$8-1)/4),0) -> 2385162.6 | ... AH18: =IF(AND(AH$17>'Deal C Office'!$B$8,AH$17<='Deal C Office'!$B$8+'Deal C Office'!$B$9),'Deal C Office'!$B$4/4*(1+'Deal C Office'!$B$5)^((AH$17-'Deal C Office'!$B$8-1)/4),0) -> 0
A19: Interest | B19: =IF(AND(B$17>'Deal C Office'!$B$8,B$17<='Deal C Office'!$B$8+'Deal C Office'!$B$9),('Deal C Office'!$B$3/(1-'Deal C Office'!$B$6))*'Deal C Office'!$B$6*'Deal C Office'!$B$7/4,0) -> 0 | C19: =IF(AND(C$17>'Deal C Office'!$B$8,C$17<='Deal C Office'!$B$8+'Deal C Office'!$B$9),('Deal C Office'!$B$3/(1-'Deal C Office'!$B$6))*'Deal C Office'!$B$6*'Deal C Office'!$B$7/4,0) -> 0 | D19: =IF(AND(D$17>'Deal C Office'!$B$8,D$17<='Deal C Office'!$B$8+'Deal C Office'!$B$9),('Deal C Office'!$B$3/(1-'Deal C Office'!$B$6))*'Deal C Office'!$B$6*'Deal C Office'!$B$7/4,0) -> 0 | E19: =IF(AND(E$17>'Deal C Office'!$B$8,E$17<='Deal C Office'!$B$8+'Deal C Office'!$B$9),('Deal C Office'!$B$3/(1-'Deal C Office'!$B$6))*'Deal C Office'!$B$6*'Deal C Office'!$B$7/4,0) -> 0 | F19: =IF(AND(F$17>'Deal C Office'!$B$8,F$17<='Deal C Office'!$B$8+'Deal C Office'!$B$9),('Deal C Office'!$B$3/(1-'Deal C Office'!$B$6))*'Deal C Office'!$B$6*'Deal C Office'!$B$7/4,0) -> 1258125 | G19: =IF(AND(G$17>'Deal C Office'!$B$8,G$17<='Deal C Office'!$B$8+'Deal C Office'!$B$9),('Deal C Office'!$B$3/(1-'Deal C Office'!$B$6))*'Deal C Office'!$B$6*'Deal C Office'!$B$7/4,0) -> 1258125 | H19: =IF(AND(H$17>'Deal C Office'!$B$8,H$17<='Deal C Office'!$B$8+'Deal C Office'!$B$9),('Deal C Office'!$B$3/(1-'Deal C Office'!$B$6))*'Deal C Office'!$B$6*'Deal C Office'!$B$7/4,0) -> 1258125 | I19: =IF(AND(I$17>'Deal C Office'!$B$8,I$17<='Deal C Office'!$B$8+'Deal C Office'!$B$9),('Deal C Office'!$B$3/(1-'Deal C Office'!$B$6))*'Deal C Office'!$B$6*'Deal C Office'!$B$7/4,0) -> 1258125 | ... AH19: =IF(AND(AH$17>'Deal C Office'!$B$8,AH$17<='Deal C Office'!$B$8+'Deal C Office'!$B$9),('Deal C Office'!$B$3/(1-'Deal C Office'!$B$6))*'Deal C Office'!$B$6*'Deal C Office'!$B$7/4,0) -> 0
A20: Purchase | B20: =IF(B$17='Deal C Office'!$B$8,-'Deal C Office'!$B$3,0) -> 0 | C20: =IF(C$17='Deal C Office'!$B$8,-'Deal C Office'!$B$3,0) -> 0 | D20: =IF(D$17='Deal C Office'!$B$8,-'Deal C Office'!$B$3,0) -> 0 | E20: =IF(E$17='Deal C Office'!$B$8,-'Deal C Office'!$B$3,0) -> -55000000 | F20: =IF(F$17='Deal C Office'!$B$8,-'Deal C Office'!$B$3,0) -> 0 | G20: =IF(G$17='Deal C Office'!$B$8,-'Deal C Office'!$B$3,0) -> 0 | H20: =IF(H$17='Deal C Office'!$B$8,-'Deal C Office'!$B$3,0) -> 0 | I20: =IF(I$17='Deal C Office'!$B$8,-'Deal C Office'!$B$3,0) -> 0 | ... AH20: =IF(AH$17='Deal C Office'!$B$8,-'Deal C Office'!$B$3,0) -> 0
A21: Sale | B21: =IF((B$17='Deal C Office'!$B$8+'Deal C Office'!$B$9),B18*4*(1+'Deal C Office'!$B$5)/$B$14-('Deal C Office'!$B$3/(1-'Deal C Office'!$B$6))*'Deal C Office'!$B$6,0) -> 0 | C21: =IF((C$17='Deal C Office'!$B$8+'Deal C Office'!$B$9),C18*4*(1+'Deal C Office'!$B$5)/$B$14-('Deal C Office'!$B$3/(1-'Deal C Office'!$B$6))*'Deal C Office'!$B$6,0) -> 0 | D21: =IF((D$17='Deal C Office'!$B$8+'Deal C Office'!$B$9),D18*4*(1+'Deal C Office'!$B$5)/$B$14-('Deal C Office'!$B$3/(1-'Deal C Office'!$B$6))*'Deal C Office'!$B$6,0) -> 0 | E21: =IF((E$17='Deal C Office'!$B$8+'Deal C Office'!$B$9),E18*4*(1+'Deal C Office'!$B$5)/$B$14-('Deal C Office'!$B$3/(1-'Deal C Office'!$B$6))*'Deal C Office'!$B$6,0) -> 0 | F21: =IF((F$17='Deal C Office'!$B$8+'Deal C Office'!$B$9),F18*4*(1+'Deal C Office'!$B$5)/$B$14-('Deal C Office'!$B$3/(1-'Deal C Office'!$B$6))*'Deal C Office'!$B$6,0) -> 0 | G21: =IF((G$17='Deal C Office'!$B$8+'Deal C Office'!$B$9),G18*4*(1+'Deal C Office'!$B$5)/$B$14-('Deal C Office'!$B$3/(1-'Deal C Office'!$B$6))*'Deal C Office'!$B$6,0) -> 0 | H21: =IF((H$17='Deal C Office'!$B$8+'Deal C Office'!$B$9),H18*4*(1+'Deal C Office'!$B$5)/$B$14-('Deal C Office'!$B$3/(1-'Deal C Office'!$B$6))*'Deal C Office'!$B$6,0) -> 0 | I21: =IF((I$17='Deal C Office'!$B$8+'Deal C Office'!$B$9),I18*4*(1+'Deal C Office'!$B$5)/$B$14-('Deal C Office'!$B$3/(1-'Deal C Office'!$B$6))*'Deal C Office'!$B$6,0) -> 0 | ... AH21: =IF((AH$17='Deal C Office'!$B$8+'Deal C Office'!$B$9),AH18*4*(1+'Deal C Office'!$B$5)/$B$14-('Deal C Office'!$B$3/(1-'Deal C Office'!$B$6))*'Deal C Office'!$B$6,0) -> 0
A22: Equity cash flow | B22: =B20+B18-B19+B21 -> 0 | C22: =C20+C18-C19+C21 -> 0 | D22: =D20+D18-D19+D21 -> 0 | E22: =E20+E18-E19+E21 -> -55000000 | F22: =F20+F18-F19+F21 -> 1091875 | G22: =G20+G18-G19+G21 -> 1103537.9 | H22: =H20+H18-H19+H21 -> 1115258.7 | I22: =I20+I18-I19+I21 -> 1127037.6 | ... AH22: =AH20+AH18-AH19+AH21 -> 0
A24: Deal IRR | B24: =(1+IRR(B22:AH22,0.02))^4-1 -> 0.12751928
A25: Deal equity multiple | B25: =SUMIF(B22:AH22,">0")/-SUMIF(B22:AH22,"<0") -> 1.8279007

Sheet Deal D Hotel
A1: DEAL D HOTEL
A3: Equity ($) | B3: 45000000
A4: NOI year 1 ($) | B4: 6900000
A5: NOI growth | B5: 0.04
A6: Loan to value | B6: 0.5
A7: Interest rate | B7: 0.07
A8: Acquisition quarter | B8: 5
A9: Hold (quarters) | B9: 22
A10: Exit cap · Base | B10: 0.075
A11: Exit cap · Downside | B11: 0.0875
A12: Exit cap · Upside | B12: 0.0675
A14: Exit cap (live case) | B14: =CHOOSE(Fund_Case,'Deal D Hotel'!$B$10,'Deal D Hotel'!$B$11,'Deal D Hotel'!$B$12) -> 0.075
A17: Quarter | B17: 0 | C17: 1 | D17: 2 | E17: 3 | F17: 4 | G17: 5 | H17: 6 | I17: 7 | J17: 8 | K17: 9 | L17: 10 | M17: 11 | N17: 12 | O17: 13 | P17: 14 | Q17: 15 | R17: 16 | S17: 17 | T17: 18 | U17: 19 | V17: 20 | W17: 21 | X17: 22 | Y17: 23 | Z17: 24 | AA17: 25 | AB17: 26 | AC17: 27 | AD17: 28 | AE17: 29 | AF17: 30 | AG17: 31 | AH17: 32
A18: NOI | B18: =IF(AND(B$17>'Deal D Hotel'!$B$8,B$17<='Deal D Hotel'!$B$8+'Deal D Hotel'!$B$9),'Deal D Hotel'!$B$4/4*(1+'Deal D Hotel'!$B$5)^((B$17-'Deal D Hotel'!$B$8-1)/4),0) -> 0 | C18: =IF(AND(C$17>'Deal D Hotel'!$B$8,C$17<='Deal D Hotel'!$B$8+'Deal D Hotel'!$B$9),'Deal D Hotel'!$B$4/4*(1+'Deal D Hotel'!$B$5)^((C$17-'Deal D Hotel'!$B$8-1)/4),0) -> 0 | D18: =IF(AND(D$17>'Deal D Hotel'!$B$8,D$17<='Deal D Hotel'!$B$8+'Deal D Hotel'!$B$9),'Deal D Hotel'!$B$4/4*(1+'Deal D Hotel'!$B$5)^((D$17-'Deal D Hotel'!$B$8-1)/4),0) -> 0 | E18: =IF(AND(E$17>'Deal D Hotel'!$B$8,E$17<='Deal D Hotel'!$B$8+'Deal D Hotel'!$B$9),'Deal D Hotel'!$B$4/4*(1+'Deal D Hotel'!$B$5)^((E$17-'Deal D Hotel'!$B$8-1)/4),0) -> 0 | F18: =IF(AND(F$17>'Deal D Hotel'!$B$8,F$17<='Deal D Hotel'!$B$8+'Deal D Hotel'!$B$9),'Deal D Hotel'!$B$4/4*(1+'Deal D Hotel'!$B$5)^((F$17-'Deal D Hotel'!$B$8-1)/4),0) -> 0 | G18: =IF(AND(G$17>'Deal D Hotel'!$B$8,G$17<='Deal D Hotel'!$B$8+'Deal D Hotel'!$B$9),'Deal D Hotel'!$B$4/4*(1+'Deal D Hotel'!$B$5)^((G$17-'Deal D Hotel'!$B$8-1)/4),0) -> 0 | H18: =IF(AND(H$17>'Deal D Hotel'!$B$8,H$17<='Deal D Hotel'!$B$8+'Deal D Hotel'!$B$9),'Deal D Hotel'!$B$4/4*(1+'Deal D Hotel'!$B$5)^((H$17-'Deal D Hotel'!$B$8-1)/4),0) -> 1725000 | I18: =IF(AND(I$17>'Deal D Hotel'!$B$8,I$17<='Deal D Hotel'!$B$8+'Deal D Hotel'!$B$9),'Deal D Hotel'!$B$4/4*(1+'Deal D Hotel'!$B$5)^((I$17-'Deal D Hotel'!$B$8-1)/4),0) -> 1741997.1 | ... AH18: =IF(AND(AH$17>'Deal D Hotel'!$B$8,AH$17<='Deal D Hotel'!$B$8+'Deal D Hotel'!$B$9),'Deal D Hotel'!$B$4/4*(1+'Deal D Hotel'!$B$5)^((AH$17-'Deal D Hotel'!$B$8-1)/4),0) -> 0
A19: Interest | B19: =IF(AND(B$17>'Deal D Hotel'!$B$8,B$17<='Deal D Hotel'!$B$8+'Deal D Hotel'!$B$9),('Deal D Hotel'!$B$3/(1-'Deal D Hotel'!$B$6))*'Deal D Hotel'!$B$6*'Deal D Hotel'!$B$7/4,0) -> 0 | C19: =IF(AND(C$17>'Deal D Hotel'!$B$8,C$17<='Deal D Hotel'!$B$8+'Deal D Hotel'!$B$9),('Deal D Hotel'!$B$3/(1-'Deal D Hotel'!$B$6))*'Deal D Hotel'!$B$6*'Deal D Hotel'!$B$7/4,0) -> 0 | D19: =IF(AND(D$17>'Deal D Hotel'!$B$8,D$17<='Deal D Hotel'!$B$8+'Deal D Hotel'!$B$9),('Deal D Hotel'!$B$3/(1-'Deal D Hotel'!$B$6))*'Deal D Hotel'!$B$6*'Deal D Hotel'!$B$7/4,0) -> 0 | E19: =IF(AND(E$17>'Deal D Hotel'!$B$8,E$17<='Deal D Hotel'!$B$8+'Deal D Hotel'!$B$9),('Deal D Hotel'!$B$3/(1-'Deal D Hotel'!$B$6))*'Deal D Hotel'!$B$6*'Deal D Hotel'!$B$7/4,0) -> 0 | F19: =IF(AND(F$17>'Deal D Hotel'!$B$8,F$17<='Deal D Hotel'!$B$8+'Deal D Hotel'!$B$9),('Deal D Hotel'!$B$3/(1-'Deal D Hotel'!$B$6))*'Deal D Hotel'!$B$6*'Deal D Hotel'!$B$7/4,0) -> 0 | G19: =IF(AND(G$17>'Deal D Hotel'!$B$8,G$17<='Deal D Hotel'!$B$8+'Deal D Hotel'!$B$9),('Deal D Hotel'!$B$3/(1-'Deal D Hotel'!$B$6))*'Deal D Hotel'!$B$6*'Deal D Hotel'!$B$7/4,0) -> 0 | H19: =IF(AND(H$17>'Deal D Hotel'!$B$8,H$17<='Deal D Hotel'!$B$8+'Deal D Hotel'!$B$9),('Deal D Hotel'!$B$3/(1-'Deal D Hotel'!$B$6))*'Deal D Hotel'!$B$6*'Deal D Hotel'!$B$7/4,0) -> 787500 | I19: =IF(AND(I$17>'Deal D Hotel'!$B$8,I$17<='Deal D Hotel'!$B$8+'Deal D Hotel'!$B$9),('Deal D Hotel'!$B$3/(1-'Deal D Hotel'!$B$6))*'Deal D Hotel'!$B$6*'Deal D Hotel'!$B$7/4,0) -> 787500 | ... AH19: =IF(AND(AH$17>'Deal D Hotel'!$B$8,AH$17<='Deal D Hotel'!$B$8+'Deal D Hotel'!$B$9),('Deal D Hotel'!$B$3/(1-'Deal D Hotel'!$B$6))*'Deal D Hotel'!$B$6*'Deal D Hotel'!$B$7/4,0) -> 0
A20: Purchase | B20: =IF(B$17='Deal D Hotel'!$B$8,-'Deal D Hotel'!$B$3,0) -> 0 | C20: =IF(C$17='Deal D Hotel'!$B$8,-'Deal D Hotel'!$B$3,0) -> 0 | D20: =IF(D$17='Deal D Hotel'!$B$8,-'Deal D Hotel'!$B$3,0) -> 0 | E20: =IF(E$17='Deal D Hotel'!$B$8,-'Deal D Hotel'!$B$3,0) -> 0 | F20: =IF(F$17='Deal D Hotel'!$B$8,-'Deal D Hotel'!$B$3,0) -> 0 | G20: =IF(G$17='Deal D Hotel'!$B$8,-'Deal D Hotel'!$B$3,0) -> -45000000 | H20: =IF(H$17='Deal D Hotel'!$B$8,-'Deal D Hotel'!$B$3,0) -> 0 | I20: =IF(I$17='Deal D Hotel'!$B$8,-'Deal D Hotel'!$B$3,0) -> 0 | ... AH20: =IF(AH$17='Deal D Hotel'!$B$8,-'Deal D Hotel'!$B$3,0) -> 0
A21: Sale | B21: =IF((B$17='Deal D Hotel'!$B$8+'Deal D Hotel'!$B$9),B18*4*(1+'Deal D Hotel'!$B$5)/$B$14-('Deal D Hotel'!$B$3/(1-'Deal D Hotel'!$B$6))*'Deal D Hotel'!$B$6,0) -> 0 | C21: =IF((C$17='Deal D Hotel'!$B$8+'Deal D Hotel'!$B$9),C18*4*(1+'Deal D Hotel'!$B$5)/$B$14-('Deal D Hotel'!$B$3/(1-'Deal D Hotel'!$B$6))*'Deal D Hotel'!$B$6,0) -> 0 | D21: =IF((D$17='Deal D Hotel'!$B$8+'Deal D Hotel'!$B$9),D18*4*(1+'Deal D Hotel'!$B$5)/$B$14-('Deal D Hotel'!$B$3/(1-'Deal D Hotel'!$B$6))*'Deal D Hotel'!$B$6,0) -> 0 | E21: =IF((E$17='Deal D Hotel'!$B$8+'Deal D Hotel'!$B$9),E18*4*(1+'Deal D Hotel'!$B$5)/$B$14-('Deal D Hotel'!$B$3/(1-'Deal D Hotel'!$B$6))*'Deal D Hotel'!$B$6,0) -> 0 | F21: =IF((F$17='Deal D Hotel'!$B$8+'Deal D Hotel'!$B$9),F18*4*(1+'Deal D Hotel'!$B$5)/$B$14-('Deal D Hotel'!$B$3/(1-'Deal D Hotel'!$B$6))*'Deal D Hotel'!$B$6,0) -> 0 | G21: =IF((G$17='Deal D Hotel'!$B$8+'Deal D Hotel'!$B$9),G18*4*(1+'Deal D Hotel'!$B$5)/$B$14-('Deal D Hotel'!$B$3/(1-'Deal D Hotel'!$B$6))*'Deal D Hotel'!$B$6,0) -> 0 | H21: =IF((H$17='Deal D Hotel'!$B$8+'Deal D Hotel'!$B$9),H18*4*(1+'Deal D Hotel'!$B$5)/$B$14-('Deal D Hotel'!$B$3/(1-'Deal D Hotel'!$B$6))*'Deal D Hotel'!$B$6,0) -> 0 | I21: =IF((I$17='Deal D Hotel'!$B$8+'Deal D Hotel'!$B$9),I18*4*(1+'Deal D Hotel'!$B$5)/$B$14-('Deal D Hotel'!$B$3/(1-'Deal D Hotel'!$B$6))*'Deal D Hotel'!$B$6,0) -> 0 | ... AH21: =IF((AH$17='Deal D Hotel'!$B$8+'Deal D Hotel'!$B$9),AH18*4*(1+'Deal D Hotel'!$B$5)/$B$14-('Deal D Hotel'!$B$3/(1-'Deal D Hotel'!$B$6))*'Deal D Hotel'!$B$6,0) -> 0
A22: Equity cash flow | B22: =B20+B18-B19+B21 -> 0 | C22: =C20+C18-C19+C21 -> 0 | D22: =D20+D18-D19+D21 -> 0 | E22: =E20+E18-E19+E21 -> 0 | F22: =F20+F18-F19+F21 -> 0 | G22: =G20+G18-G19+G21 -> -45000000 | H22: =H20+H18-H19+H21 -> 937500 | I22: =I20+I18-I19+I21 -> 954497.13 | ... AH22: =AH20+AH18-AH19+AH21 -> 0
A24: Deal IRR | B24: =(1+IRR(B22:AH22,0.02))^4-1 -> 0.17837408
A25: Deal equity multiple | B25: =SUMIF(B22:AH22,">0")/-SUMIF(B22:AH22,"<0") -> 2.1639588

Sheet Cash Flow
A3: Quarter | B3: 0 | C3: 1 | D3: 2 | E3: 3 | F3: 4 | G3: 5 | H3: 6 | I3: 7 | J3: 8 | K3: 9 | L3: 10 | M3: 11 | N3: 12 | O3: 13 | P3: 14 | Q3: 15 | R3: 16 | S3: 17 | T3: 18 | U3: 19 | V3: 20 | W3: 21 | X3: 22 | Y3: 23 | Z3: 24 | AA3: 25 | AB3: 26 | AC3: 27 | AD3: 28 | AE3: 29 | AF3: 30 | AG3: 31 | AH3: 32
A4: Date | B4: =EOMONTH(Fund!$B$5,3*B$3) -> 46112 | C4: =EOMONTH(Fund!$B$5,3*C$3) -> 46203 | D4: =EOMONTH(Fund!$B$5,3*D$3) -> 46295 | E4: =EOMONTH(Fund!$B$5,3*E$3) -> 46387 | F4: =EOMONTH(Fund!$B$5,3*F$3) -> 46477 | G4: =EOMONTH(Fund!$B$5,3*G$3) -> 46568 | H4: =EOMONTH(Fund!$B$5,3*H$3) -> 46660 | I4: =EOMONTH(Fund!$B$5,3*I$3) -> 46752 | ... AH4: =EOMONTH(Fund!$B$5,3*AH$3) -> 49034
A5: Deal cash flow (equity) | B5: ='Deal A Logistics'!B22+'Deal B Resi Dev'!B27+'Deal C Office'!B22+'Deal D Hotel'!B22 -> 0 | C5: ='Deal A Logistics'!C22+'Deal B Resi Dev'!C27+'Deal C Office'!C22+'Deal D Hotel'!C22 -> -60000000 | D5: ='Deal A Logistics'!D22+'Deal B Resi Dev'!D27+'Deal C Office'!D22+'Deal D Hotel'!D22 -> -16913333 | E5: ='Deal A Logistics'!E22+'Deal B Resi Dev'!E27+'Deal C Office'!E22+'Deal D Hotel'!E22 -> -71897387 | F5: ='Deal A Logistics'!F22+'Deal B Resi Dev'!F27+'Deal C Office'!F22+'Deal D Hotel'!F22 -> -15789447 | G5: ='Deal A Logistics'!G22+'Deal B Resi Dev'!G27+'Deal C Office'!G22+'Deal D Hotel'!G22 -> -60761600 | H5: ='Deal A Logistics'!H22+'Deal B Resi Dev'!H27+'Deal C Office'!H22+'Deal D Hotel'!H22 -> 3203925.3 | I5: ='Deal A Logistics'!I22+'Deal B Resi Dev'!I27+'Deal C Office'!I22+'Deal D Hotel'!I22 -> 3249126.5 | ... AH5: ='Deal A Logistics'!AH22+'Deal B Resi Dev'!AH27+'Deal C Office'!AH22+'Deal D Hotel'!AH22 -> 0
A6: Deal contributions | B6: =MAX(0,-B5) -> 0 | C6: =MAX(0,-C5) -> 60000000 | D6: =MAX(0,-D5) -> 16913333 | E6: =MAX(0,-E5) -> 71897387 | F6: =MAX(0,-F5) -> 15789447 | G6: =MAX(0,-G5) -> 60761600 | H6: =MAX(0,-H5) -> 0 | I6: =MAX(0,-I5) -> 0 | ... AH6: =MAX(0,-AH5) -> 0
A7: Deal distributions | B7: =MAX(0,B5) -> 0 | C7: =MAX(0,C5) -> 0 | D7: =MAX(0,D5) -> 0 | E7: =MAX(0,E5) -> 0 | F7: =MAX(0,F5) -> 0 | G7: =MAX(0,G5) -> 0 | H7: =MAX(0,H5) -> 3203925.3 | I7: =MAX(0,I5) -> 3249126.5 | ... AH7: =MAX(0,AH5) -> 0
A8: Invested capital | B8: =B6 -> 0 | C8: =B8+C6-MIN(C7,B8) -> 60000000 | D8: =C8+D6-MIN(D7,C8) -> 76913333 | E8: =D8+E6-MIN(E7,D8) -> 1.4881072e+08 | F8: =E8+F6-MIN(F7,E8) -> 1.6460017e+08 | G8: =F8+G6-MIN(G7,F8) -> 2.2536177e+08 | H8: =G8+H6-MIN(H7,G8) -> 2.2215784e+08 | I8: =H8+I6-MIN(I7,H8) -> 2.1890871e+08 | J8: =I8+J6-MIN(J7,I8) -> 2.1561404e+08 | ... AH8: =AG8+AH6-MIN(AH7,AG8) -> 0
A9: Management fee | B9: =IF(B$3<12,Fund!$B$4*Fund!$B$6,B8*Fund!$B$7)/4 -> 1750000 | C9: =IF(C$3<12,Fund!$B$4*Fund!$B$6,C8*Fund!$B$7)/4 -> 1750000 | D9: =IF(D$3<12,Fund!$B$4*Fund!$B$6,D8*Fund!$B$7)/4 -> 1750000 | E9: =IF(E$3<12,Fund!$B$4*Fund!$B$6,E8*Fund!$B$7)/4 -> 1750000 | F9: =IF(F$3<12,Fund!$B$4*Fund!$B$6,F8*Fund!$B$7)/4 -> 1750000 | G9: =IF(G$3<12,Fund!$B$4*Fund!$B$6,G8*Fund!$B$7)/4 -> 1750000 | H9: =IF(H$3<12,Fund!$B$4*Fund!$B$6,H8*Fund!$B$7)/4 -> 1750000 | I9: =IF(I$3<12,Fund!$B$4*Fund!$B$6,I8*Fund!$B$7)/4 -> 1750000 | ... AH9: =IF(AH$3<12,Fund!$B$4*Fund!$B$6,AH8*Fund!$B$7)/4 -> 0
A10: Facility drawn | B10: =B6*Fund!$B$8 -> 0 | C10: =C6*Fund!$B$8 -> 60000000 | D10: =D6*Fund!$B$8 -> 16913333 | E10: =E6*Fund!$B$8 -> 71897387 | F10: =F6*Fund!$B$8 -> 15789447 | G10: =G6*Fund!$B$8 -> 60761600 | H10: =H6*Fund!$B$8 -> 0 | I10: =I6*Fund!$B$8 -> 0 | ... AH10: =AH6*Fund!$B$8 -> 0
A11: Facility repaid | B11: =0 -> 0 | C11: =0 -> 0 | D11: =B10 -> 0 | E11: =C10 -> 60000000 | F11: =D10 -> 16913333 | G11: =E10 -> 71897387 | H11: =F10 -> 15789447 | I11: =G10 -> 60761600 | J11: =H10 -> 0 | K11: =I10 -> 0 | ... AH11: =AF10 -> 0
A12: Facility interest | B12: =0 -> 0 | C12: =B13*Fund!$B$9/4 -> 0 | D12: =C13*Fund!$B$9/4 -> 975000 | E12: =D13*Fund!$B$9/4 -> 1249841.7 | F12: =E13*Fund!$B$9/4 -> 1443174.2 | G12: =F13*Fund!$B$9/4 -> 1424911 | H12: =G13*Fund!$B$9/4 -> 1243954.5 | I12: =H13*Fund!$B$9/4 -> 987375.99 | J12: =I13*Fund!$B$9/4 -> 0 | ... AH12: =AG13*Fund!$B$9/4 -> 0
A13: Facility balance | B13: =B10-B11 -> 0 | C13: =B13+C10-C11 -> 60000000 | D13: =C13+D10-D11 -> 76913333 | E13: =D13+E10-E11 -> 88810720 | F13: =E13+F10-F11 -> 87686833 | G13: =F13+G10-G11 -> 76551046 | H13: =G13+H10-H11 -> 60761600 | I13: =H13+I10-I11 -> 0 | J13: =I13+J10-J11 -> 0 | ... AH13: =AG13+AH10-AH11 -> 0
A14: Capital called | B14: =B6-B10+B11+B9+B12 -> 1750000 | C14: =C6-C10+C11+C9+C12 -> 1750000 | D14: =D6-D10+D11+D9+D12 -> 2725000 | E14: =E6-E10+E11+E9+E12 -> 62999842 | F14: =F6-F10+F11+F9+F12 -> 20106508 | G14: =G6-G10+G11+G9+G12 -> 75072298 | H14: =H6-H10+H11+H9+H12 -> 18783401 | I14: =I6-I10+I11+I9+I12 -> 63498976 | ... AH14: =AH6-AH10+AH11+AH9+AH12 -> 0
A15: LP contributions | B15: =B14 -> 1750000 | C15: =C14 -> 1750000 | D15: =D14 -> 2725000 | E15: =E14 -> 62999842 | F15: =F14 -> 20106508 | G15: =G14 -> 75072298 | H15: =H14 -> 18783401 | I15: =I14 -> 63498976 | ... AH15: =AH14 -> 0
A16: Distributable | B16: =B7 -> 0 | C16: =C7 -> 0 | D16: =D7 -> 0 | E16: =E7 -> 0 | F16: =F7 -> 0 | G16: =G7 -> 0 | H16: =H7 -> 3203925.3 | I16: =I7 -> 3249126.5 | ... AH16: =AH7 -> 0
A17: ROC account | B17: =B15 -> 1750000 | C17: =B17-B18+C15 -> 3500000 | D17: =C17-C18+D15 -> 6225000 | E17: =D17-D18+E15 -> 69224842 | F17: =E17-E18+F15 -> 89331349 | G17: =F17-F18+G15 -> 1.6440365e+08 | H17: =G17-G18+H15 -> 1.8318705e+08 | I17: =H17-H18+I15 -> 2.434821e+08 | J17: =I17-I18+J15 -> 2.4198297e+08 | ... AH17: =AG17-AG18+AH15 -> 0
A18: Return of capital | B18: =MIN(B16,B17) -> 0 | C18: =MIN(C16,C17) -> 0 | D18: =MIN(D16,D17) -> 0 | E18: =MIN(E16,E17) -> 0 | F18: =MIN(F16,F17) -> 0 | G18: =MIN(G16,G17) -> 0 | H18: =MIN(H16,H17) -> 3203925.3 | I18: =MIN(I16,I17) -> 3249126.5 | ... AH18: =MIN(AH16,AH17) -> 0
A19: Pref account | B19: =0 -> 0 | C19: =(B19-B20)*(1+Fund!$B$10)^0.25+(B17-B18)*((1+Fund!$B$10)^0.25-1) -> 33996.457 | D19: =(C19-C20)*(1+Fund!$B$10)^0.25+(C17-C18)*((1+Fund!$B$10)^0.25-1) -> 102649.81 | E19: =(D19-D20)*(1+Fund!$B$10)^0.25+(D17-D18)*((1+Fund!$B$10)^0.25-1) -> 225574.19 | F19: =(E19-E20)*(1+Fund!$B$10)^0.25+(E17-E18)*((1+Fund!$B$10)^0.25-1) -> 1574756 | G19: =(F19-F20)*(1+Fund!$B$10)^0.25+(F17-F18)*((1+Fund!$B$10)^0.25-1) -> 3340747.7 | H19: =(G19-G20)*(1+Fund!$B$10)^0.25+(G17-G18)*((1+Fund!$B$10)^0.25-1) -> 6599442 | I19: =(H19-H20)*(1+Fund!$B$10)^0.25+(H17-H18)*((1+Fund!$B$10)^0.25-1) -> 10224097 | J19: =(I19-I20)*(1+Fund!$B$10)^0.25+(I17-I18)*((1+Fund!$B$10)^0.25-1) -> 15089613 | ... AH19: =(AG19-AG20)*(1+Fund!$B$10)^0.25+(AG17-AG18)*((1+Fund!$B$10)^0.25-1) -> 0
A20: Pref paid | B20: =MIN(B16-B18,B19) -> 0 | C20: =MIN(C16-C18,C19) -> 0 | D20: =MIN(D16-D18,D19) -> 0 | E20: =MIN(E16-E18,E19) -> 0 | F20: =MIN(F16-F18,F19) -> 0 | G20: =MIN(G16-G18,G19) -> 0 | H20: =MIN(H16-H18,H19) -> 0 | I20: =MIN(I16-I18,I19) -> 0 | ... AH20: =MIN(AH16-AH18,AH19) -> 0
A21: Catch-up account | B21: =B20*Fund!$B$12/(1-Fund!$B$12) -> 0 | C21: =B21-B22+C20*Fund!$B$12/(1-Fund!$B$12) -> 0 | D21: =C21-C22+D20*Fund!$B$12/(1-Fund!$B$12) -> 0 | E21: =D21-D22+E20*Fund!$B$12/(1-Fund!$B$12) -> 0 | F21: =E21-E22+F20*Fund!$B$12/(1-Fund!$B$12) -> 0 | G21: =F21-F22+G20*Fund!$B$12/(1-Fund!$B$12) -> 0 | H21: =G21-G22+H20*Fund!$B$12/(1-Fund!$B$12) -> 0 | I21: =H21-H22+I20*Fund!$B$12/(1-Fund!$B$12) -> 0 | J21: =I21-I22+J20*Fund!$B$12/(1-Fund!$B$12) -> 0 | ... AH21: =AG21-AG22+AH20*Fund!$B$12/(1-Fund!$B$12) -> 0
A22: Catch-up to GP | B22: =MIN((B16-B18-B20)*Fund!$B$11,B21) -> 0 | C22: =MIN((C16-C18-C20)*Fund!$B$11,C21) -> 0 | D22: =MIN((D16-D18-D20)*Fund!$B$11,D21) -> 0 | E22: =MIN((E16-E18-E20)*Fund!$B$11,E21) -> 0 | F22: =MIN((F16-F18-F20)*Fund!$B$11,F21) -> 0 | G22: =MIN((G16-G18-G20)*Fund!$B$11,G21) -> 0 | H22: =MIN((H16-H18-H20)*Fund!$B$11,H21) -> 0 | I22: =MIN((I16-I18-I20)*Fund!$B$11,I21) -> 0 | ... AH22: =MIN((AH16-AH18-AH20)*Fund!$B$11,AH21) -> 0
A23: Tier 2 account (15%) | B23: =0 -> 0 | C23: =MAX(0,(B23+B15)*(1+Fund!$B$13)^0.25-B28) -> 1812226.6 | D23: =MAX(0,(C23+C15)*(1+Fund!$B$13)^0.25-C28) -> 3688892.6 | E23: =MAX(0,(D23+D15)*(1+Fund!$B$13)^0.25-D28) -> 6641958.2 | F23: =MAX(0,(E23+E15)*(1+Fund!$B$13)^0.25-E28) -> 72118128 | G23: =MAX(0,(F23+F15)*(1+Fund!$B$13)^0.25-F28) -> 95503967 | H23: =MAX(0,(G23+G15)*(1+Fund!$B$13)^0.25-G28) -> 1.7664163e+08 | I23: =MAX(0,(H23+H15)*(1+Fund!$B$13)^0.25-H28) -> 1.9917004e+08 | J23: =MAX(0,(I23+I15)*(1+Fund!$B$13)^0.25-I28) -> 2.687599e+08 | ... AH23: =MAX(0,(AG23+AG15)*(1+Fund!$B$13)^0.25-AG28) -> 17137949
A24: Tier 2 split LP | B24: =MIN(B16-B18-B20-B22,MAX(0,B23-B18-B20)/(1-Fund!$B$12))*(1-Fund!$B$12) -> 0 | C24: =MIN(C16-C18-C20-C22,MAX(0,C23-C18-C20)/(1-Fund!$B$12))*(1-Fund!$B$12) -> 0 | D24: =MIN(D16-D18-D20-D22,MAX(0,D23-D18-D20)/(1-Fund!$B$12))*(1-Fund!$B$12) -> 0 | E24: =MIN(E16-E18-E20-E22,MAX(0,E23-E18-E20)/(1-Fund!$B$12))*(1-Fund!$B$12) -> 0 | F24: =MIN(F16-F18-F20-F22,MAX(0,F23-F18-F20)/(1-Fund!$B$12))*(1-Fund!$B$12) -> 0 | G24: =MIN(G16-G18-G20-G22,MAX(0,G23-G18-G20)/(1-Fund!$B$12))*(1-Fund!$B$12) -> 0 | H24: =MIN(H16-H18-H20-H22,MAX(0,H23-H18-H20)/(1-Fund!$B$12))*(1-Fund!$B$12) -> 0 | I24: =MIN(I16-I18-I20-I22,MAX(0,I23-I18-I20)/(1-Fund!$B$12))*(1-Fund!$B$12) -> 0 | ... AH24: =MIN(AH16-AH18-AH20-AH22,MAX(0,AH23-AH18-AH20)/(1-Fund!$B$12))*(1-Fund!$B$12) -> 0
A25: Tier 2 split GP | B25: =B24*Fund!$B$12/(1-Fund!$B$12) -> 0 | C25: =C24*Fund!$B$12/(1-Fund!$B$12) -> 0 | D25: =D24*Fund!$B$12/(1-Fund!$B$12) -> 0 | E25: =E24*Fund!$B$12/(1-Fund!$B$12) -> 0 | F25: =F24*Fund!$B$12/(1-Fund!$B$12) -> 0 | G25: =G24*Fund!$B$12/(1-Fund!$B$12) -> 0 | H25: =H24*Fund!$B$12/(1-Fund!$B$12) -> 0 | I25: =I24*Fund!$B$12/(1-Fund!$B$12) -> 0 | ... AH25: =AH24*Fund!$B$12/(1-Fund!$B$12) -> 0
A26: Above tier 2 LP | B26: =(B16-B18-B20-B22-B24-B25)*(1-Fund!$B$14) -> 0 | C26: =(C16-C18-C20-C22-C24-C25)*(1-Fund!$B$14) -> 0 | D26: =(D16-D18-D20-D22-D24-D25)*(1-Fund!$B$14) -> 0 | E26: =(E16-E18-E20-E22-E24-E25)*(1-Fund!$B$14) -> 0 | F26: =(F16-F18-F20-F22-F24-F25)*(1-Fund!$B$14) -> 0 | G26: =(G16-G18-G20-G22-G24-G25)*(1-Fund!$B$14) -> 0 | H26: =(H16-H18-H20-H22-H24-H25)*(1-Fund!$B$14) -> 0 | I26: =(I16-I18-I20-I22-I24-I25)*(1-Fund!$B$14) -> 0 | ... AH26: =(AH16-AH18-AH20-AH22-AH24-AH25)*(1-Fund!$B$14) -> 0
A27: Above tier 2 GP | B27: =(B16-B18-B20-B22-B24-B25)*Fund!$B$14 -> 0 | C27: =(C16-C18-C20-C22-C24-C25)*Fund!$B$14 -> 0 | D27: =(D16-D18-D20-D22-D24-D25)*Fund!$B$14 -> 0 | E27: =(E16-E18-E20-E22-E24-E25)*Fund!$B$14 -> 0 | F27: =(F16-F18-F20-F22-F24-F25)*Fund!$B$14 -> 0 | G27: =(G16-G18-G20-G22-G24-G25)*Fund!$B$14 -> 0 | H27: =(H16-H18-H20-H22-H24-H25)*Fund!$B$14 -> 0 | I27: =(I16-I18-I20-I22-I24-I25)*Fund!$B$14 -> 0 | ... AH27: =(AH16-AH18-AH20-AH22-AH24-AH25)*Fund!$B$14 -> 0
A28: LP distributions | B28: =B18+B20+B24+B26 -> 0 | C28: =C18+C20+C24+C26 -> 0 | D28: =D18+D20+D24+D26 -> 0 | E28: =E18+E20+E24+E26 -> 0 | F28: =F18+F20+F24+F26 -> 0 | G28: =G18+G20+G24+G26 -> 0 | H28: =H18+H20+H24+H26 -> 3203925.3 | I28: =I18+I20+I24+I26 -> 3249126.5 | ... AH28: =AH18+AH20+AH24+AH26 -> 0
A29: GP carry | B29: =B22+B25+B27 -> 0 | C29: =C22+C25+C27 -> 0 | D29: =D22+D25+D27 -> 0 | E29: =E22+E25+E27 -> 0 | F29: =F22+F25+F27 -> 0 | G29: =G22+G25+G27 -> 0 | H29: =H22+H25+H27 -> 0 | I29: =I22+I25+I27 -> 0 | ... AH29: =AH22+AH25+AH27 -> 0
A30: LP net cash flow | B30: =B28-B15 -> -1750000 | C30: =C28-C15 -> -1750000 | D30: =D28-D15 -> -2725000 | E30: =E28-E15 -> -62999842 | F30: =F28-F15 -> -20106508 | G30: =G28-G15 -> -75072298 | H30: =H28-H15 -> -15579476 | I30: =I28-I15 -> -60249849 | ... AH30: =AH28-AH15 -> 0
A31: Cumulative LP distributions | B31: =B28 -> 0 | C31: =B31+C28 -> 0 | D31: =C31+D28 -> 0 | E31: =D31+E28 -> 0 | F31: =E31+F28 -> 0 | G31: =F31+G28 -> 0 | H31: =G31+H28 -> 3203925.3 | I31: =H31+I28 -> 6453051.8 | J31: =I31+J28 -> 9747727.3 | ... AH31: =AG31+AH28 -> 4.2566173e+08
A32: DPI | B32: =IF(SUM($B$15:B15)>0,B31/SUM($B$15:B15),0) -> 0 | C32: =IF(SUM($B$15:C15)>0,C31/SUM($B$15:C15),0) -> 0 | D32: =IF(SUM($B$15:D15)>0,D31/SUM($B$15:D15),0) -> 0 | E32: =IF(SUM($B$15:E15)>0,E31/SUM($B$15:E15),0) -> 0 | F32: =IF(SUM($B$15:F15)>0,F31/SUM($B$15:F15),0) -> 0 | G32: =IF(SUM($B$15:G15)>0,G31/SUM($B$15:G15),0) -> 0 | H32: =IF(SUM($B$15:H15)>0,H31/SUM($B$15:H15),0) -> 0.017489912 | I32: =IF(SUM($B$15:I15)>0,I31/SUM($B$15:I15),0) -> 0.026158968 | ... AH32: =IF(SUM($B$15:AH15)>0,AH31/SUM($B$15:AH15),0) -> 1.6591668

Sheet Returns
A3: Gross IRR (deals, XIRR) | B3: =XIRR('Cash Flow'!B5:AH5,'Cash Flow'!B4:AH4) -> 0.18923187
A4: LP net IRR (XIRR) | B4: =XIRR('Cash Flow'!B30:AH30,'Cash Flow'!B4:AH4) -> 0.15271897
A5: LP TVPI | B5: =SUM('Cash Flow'!B28:AH28)/SUM('Cash Flow'!B15:AH15) -> 1.6591668
A6: DPI at year 4 | B6: ='Cash Flow'!R32 -> 0.55213926
A7: GP carried interest ($) | B7: =SUM('Cash Flow'!B29:AH29) -> 42277559
A8: Management fees ($) | B8: =SUM('Cash Flow'!B9:AH9) -> 23865468
A9: Facility interest ($) | B9: =SUM('Cash Flow'!B12:AH12) -> 7324257.4
A10: Total called ($) | B10: =SUM('Cash Flow'!B15:AH15) -> 2.5655149e+08
A11: Peak facility ($) | B11: =MAX('Cash Flow'!B13:AH13) -> 88810720
A12: Deal A IRR | B12: ='Deal A Logistics'!B24 -> 0.18774538
A13: Deal B IRR | B13: ='Deal B Resi Dev'!B29 -> 0.26354052
A14: Deal C IRR | B14: ='Deal C Office'!B24 -> 0.12751928
A15: Deal D IRR | B15: ='Deal D Hotel'!B24 -> 0.17837408
