Workbook

Sheet Inputs
A1: MARSA BRANDED RESIDENCES AND HOTEL – DUBAI (AED)
A3: Model start | B3: 46295
A4: Residences (units) | B4: 220
A5: Average unit size (sq ft) | B5: 1850
A6: Sale price (AED per sq ft) | B6: 3400
A7: Branding fee on sales | B7: 0.05
A8: Booking payment | B8: 0.1
A9: Each construction instalment | B9: 0.1
A10: Paid on handover | B10: 0.5
A11: Residences build cost (AED per sq ft) | B11: 1150
A12: Land (AED) | B12: 260000000
A13: Build (quarters) | B13: 12
A14: Hotel keys | B14: 250
... A26: Exit quarter | B26: 32
A30: Instalment milestones (% complete)
A31: Milestone 1 | B31: 0.2
A32: Milestone 2 | B32: 0.4
A33: Milestone 3 | B33: 0.6
A34: Milestone 4 | B34: 0.8
A36: Seasonality (occupancy index) Q1, Q2, Q3, Q4 | B36: 1.15 | C36: 0.95 | D36: 0.7 | E36: 1.2

Sheet Curves
A1: Build quarter | B1: Cumulative % complete | C1: Sales (% of units in the quarter) | D1: Hotel occupancy by year
A2: 1 | B2: 0.03 | C2: 0.18 | D2: 0.58
A3: 2 | B3: 0.08 | C3: 0.12 | D3: 0.66
A4: 3 | B4: 0.15 | C4: 0.09 | D4: 0.72
A5: 4 | B5: 0.24 | C5: 0.08 | D5: 0.74
A6: 5 | B6: 0.34 | C6: 0.07
A7: 6 | B7: 0.45 | C7: 0.07
A8: 7 | B8: 0.56 | C8: 0.06
A9: 8 | B9: 0.67 | C9: 0.06
A10: 9 | B10: 0.77 | C10: 0.05
A11: 10 | B11: 0.86 | C11: 0.05
A12: 11 | B12: 0.94 | C12: 0.04
A13: 12 | B13: 1 | C13: 0.04
A14: 13 | B14: 1 | C14: 0.03
A15: 14 | B15: 1 | C15: 0.02
A16: 15 | B16: 1 | C16: 0.02
A17: 16 | B17: 1 | C17: 0.02

Sheet Cash Flow
A3: Quarter | B3: 0 | C3: 1 | D3: 2 | E3: 3 | F3: 4 | G3: 5 | H3: 6 | I3: 7 | J3: 8 | K3: 9 | L3: 10 | M3: 11 | N3: 12 | O3: 13 | P3: 14 | Q3: 15 | R3: 16 | S3: 17 | T3: 18 | U3: 19 | V3: 20 | W3: 21 | X3: 22 | Y3: 23 | Z3: 24 | AA3: 25 | AB3: 26 | AC3: 27 | AD3: 28 | AE3: 29 | AF3: 30 | AG3: 31 | AH3: 32
A4: Date | B4: =EOMONTH(Inputs!$B$3,3*B$3) -> 46295 | C4: =EOMONTH(Inputs!$B$3,3*C$3) -> 46387 | D4: =EOMONTH(Inputs!$B$3,3*D$3) -> 46477 | E4: =EOMONTH(Inputs!$B$3,3*E$3) -> 46568 | F4: =EOMONTH(Inputs!$B$3,3*F$3) -> 46660 | G4: =EOMONTH(Inputs!$B$3,3*G$3) -> 46752 | H4: =EOMONTH(Inputs!$B$3,3*H$3) -> 46843 | I4: =EOMONTH(Inputs!$B$3,3*I$3) -> 46934 | ... AH4: =EOMONTH(Inputs!$B$3,3*AH$3) -> 49217
A5: Units sold | B5: =IF(AND(B$3>=1,B$3<=16),Inputs!$B$4*INDEX(Curves!$C$2:$C$17,MAX(1,B$3)),0) -> 0 | C5: =IF(AND(C$3>=1,C$3<=16),Inputs!$B$4*INDEX(Curves!$C$2:$C$17,MAX(1,C$3)),0) -> 39.6 | D5: =IF(AND(D$3>=1,D$3<=16),Inputs!$B$4*INDEX(Curves!$C$2:$C$17,MAX(1,D$3)),0) -> 26.4 | E5: =IF(AND(E$3>=1,E$3<=16),Inputs!$B$4*INDEX(Curves!$C$2:$C$17,MAX(1,E$3)),0) -> 19.8 | F5: =IF(AND(F$3>=1,F$3<=16),Inputs!$B$4*INDEX(Curves!$C$2:$C$17,MAX(1,F$3)),0) -> 17.6 | G5: =IF(AND(G$3>=1,G$3<=16),Inputs!$B$4*INDEX(Curves!$C$2:$C$17,MAX(1,G$3)),0) -> 15.4 | H5: =IF(AND(H$3>=1,H$3<=16),Inputs!$B$4*INDEX(Curves!$C$2:$C$17,MAX(1,H$3)),0) -> 15.4 | I5: =IF(AND(I$3>=1,I$3<=16),Inputs!$B$4*INDEX(Curves!$C$2:$C$17,MAX(1,I$3)),0) -> 13.2 | ... AH5: =IF(AND(AH$3>=1,AH$3<=16),Inputs!$B$4*INDEX(Curves!$C$2:$C$17,MAX(1,AH$3)),0) -> 0
A6: Sales value | B6: =B5*Inputs!$B$5*Inputs!$B$6 -> 0 | C6: =C5*Inputs!$B$5*Inputs!$B$6 -> 249084000 | D6: =D5*Inputs!$B$5*Inputs!$B$6 -> 166056000 | E6: =E5*Inputs!$B$5*Inputs!$B$6 -> 124542000 | F6: =F5*Inputs!$B$5*Inputs!$B$6 -> 110704000 | G6: =G5*Inputs!$B$5*Inputs!$B$6 -> 96866000 | H6: =H5*Inputs!$B$5*Inputs!$B$6 -> 96866000 | I6: =I5*Inputs!$B$5*Inputs!$B$6 -> 83028000 | ... AH6: =AH5*Inputs!$B$5*Inputs!$B$6 -> 0
A7: Cumulative sales value | B7: =SUM($B$6:B6) -> 0 | C7: =SUM($B$6:C6) -> 249084000 | D7: =SUM($B$6:D6) -> 415140000 | E7: =SUM($B$6:E6) -> 539682000 | F7: =SUM($B$6:F6) -> 650386000 | G7: =SUM($B$6:G6) -> 747252000 | H7: =SUM($B$6:H6) -> 844118000 | I7: =SUM($B$6:I6) -> 927146000 | ... AH7: =SUM($B$6:AH6) -> 1383800000
A8: Booking collected | B8: =IF(B$3<Inputs!$B$13,B6*Inputs!$B$8,0) -> 0 | C8: =IF(C$3<Inputs!$B$13,C6*Inputs!$B$8,0) -> 24908400 | D8: =IF(D$3<Inputs!$B$13,D6*Inputs!$B$8,0) -> 16605600 | E8: =IF(E$3<Inputs!$B$13,E6*Inputs!$B$8,0) -> 12454200 | F8: =IF(F$3<Inputs!$B$13,F6*Inputs!$B$8,0) -> 11070400 | G8: =IF(G$3<Inputs!$B$13,G6*Inputs!$B$8,0) -> 9686600 | H8: =IF(H$3<Inputs!$B$13,H6*Inputs!$B$8,0) -> 9686600 | I8: =IF(I$3<Inputs!$B$13,I6*Inputs!$B$8,0) -> 8302800 | ... AH8: =IF(AH$3<Inputs!$B$13,AH6*Inputs!$B$8,0) -> 0
A9: Milestone 1 collected | B9: =IF(B$3>=Inputs!$B$13,0,IF(B$3=(COUNTIF(Curves!$B$2:$B$13,"<"&Inputs!$B$31)+1),B7*Inputs!$B$9,IF(B$3>(COUNTIF(Curves!$B$2:$B$13,"<"&Inputs!$B$31)+1),B6*Inputs!$B$9,0))) -> 0 | C9: =IF(C$3>=Inputs!$B$13,0,IF(C$3=(COUNTIF(Curves!$B$2:$B$13,"<"&Inputs!$B$31)+1),C7*Inputs!$B$9,IF(C$3>(COUNTIF(Curves!$B$2:$B$13,"<"&Inputs!$B$31)+1),C6*Inputs!$B$9,0))) -> 0 | D9: =IF(D$3>=Inputs!$B$13,0,IF(D$3=(COUNTIF(Curves!$B$2:$B$13,"<"&Inputs!$B$31)+1),D7*Inputs!$B$9,IF(D$3>(COUNTIF(Curves!$B$2:$B$13,"<"&Inputs!$B$31)+1),D6*Inputs!$B$9,0))) -> 0 | E9: =IF(E$3>=Inputs!$B$13,0,IF(E$3=(COUNTIF(Curves!$B$2:$B$13,"<"&Inputs!$B$31)+1),E7*Inputs!$B$9,IF(E$3>(COUNTIF(Curves!$B$2:$B$13,"<"&Inputs!$B$31)+1),E6*Inputs!$B$9,0))) -> 0 | F9: =IF(F$3>=Inputs!$B$13,0,IF(F$3=(COUNTIF(Curves!$B$2:$B$13,"<"&Inputs!$B$31)+1),F7*Inputs!$B$9,IF(F$3>(COUNTIF(Curves!$B$2:$B$13,"<"&Inputs!$B$31)+1),F6*Inputs!$B$9,0))) -> 65038600 | G9: =IF(G$3>=Inputs!$B$13,0,IF(G$3=(COUNTIF(Curves!$B$2:$B$13,"<"&Inputs!$B$31)+1),G7*Inputs!$B$9,IF(G$3>(COUNTIF(Curves!$B$2:$B$13,"<"&Inputs!$B$31)+1),G6*Inputs!$B$9,0))) -> 9686600 | H9: =IF(H$3>=Inputs!$B$13,0,IF(H$3=(COUNTIF(Curves!$B$2:$B$13,"<"&Inputs!$B$31)+1),H7*Inputs!$B$9,IF(H$3>(COUNTIF(Curves!$B$2:$B$13,"<"&Inputs!$B$31)+1),H6*Inputs!$B$9,0))) -> 9686600 | I9: =IF(I$3>=Inputs!$B$13,0,IF(I$3=(COUNTIF(Curves!$B$2:$B$13,"<"&Inputs!$B$31)+1),I7*Inputs!$B$9,IF(I$3>(COUNTIF(Curves!$B$2:$B$13,"<"&Inputs!$B$31)+1),I6*Inputs!$B$9,0))) -> 8302800 | ... AH9: =IF(AH$3>=Inputs!$B$13,0,IF(AH$3=(COUNTIF(Curves!$B$2:$B$13,"<"&Inputs!$B$31)+1),AH7*Inputs!$B$9,IF(AH$3>(COUNTIF(Curves!$B$2:$B$13,"<"&Inputs!$B$31)+1),AH6*Inputs!$B$9,0))) -> 0
A10: Milestone 2 collected | B10: =IF(B$3>=Inputs!$B$13,0,IF(B$3=(COUNTIF(Curves!$B$2:$B$13,"<"&Inputs!$B$32)+1),B7*Inputs!$B$9,IF(B$3>(COUNTIF(Curves!$B$2:$B$13,"<"&Inputs!$B$32)+1),B6*Inputs!$B$9,0))) -> 0 | C10: =IF(C$3>=Inputs!$B$13,0,IF(C$3=(COUNTIF(Curves!$B$2:$B$13,"<"&Inputs!$B$32)+1),C7*Inputs!$B$9,IF(C$3>(COUNTIF(Curves!$B$2:$B$13,"<"&Inputs!$B$32)+1),C6*Inputs!$B$9,0))) -> 0 | D10: =IF(D$3>=Inputs!$B$13,0,IF(D$3=(COUNTIF(Curves!$B$2:$B$13,"<"&Inputs!$B$32)+1),D7*Inputs!$B$9,IF(D$3>(COUNTIF(Curves!$B$2:$B$13,"<"&Inputs!$B$32)+1),D6*Inputs!$B$9,0))) -> 0 | E10: =IF(E$3>=Inputs!$B$13,0,IF(E$3=(COUNTIF(Curves!$B$2:$B$13,"<"&Inputs!$B$32)+1),E7*Inputs!$B$9,IF(E$3>(COUNTIF(Curves!$B$2:$B$13,"<"&Inputs!$B$32)+1),E6*Inputs!$B$9,0))) -> 0 | F10: =IF(F$3>=Inputs!$B$13,0,IF(F$3=(COUNTIF(Curves!$B$2:$B$13,"<"&Inputs!$B$32)+1),F7*Inputs!$B$9,IF(F$3>(COUNTIF(Curves!$B$2:$B$13,"<"&Inputs!$B$32)+1),F6*Inputs!$B$9,0))) -> 0 | G10: =IF(G$3>=Inputs!$B$13,0,IF(G$3=(COUNTIF(Curves!$B$2:$B$13,"<"&Inputs!$B$32)+1),G7*Inputs!$B$9,IF(G$3>(COUNTIF(Curves!$B$2:$B$13,"<"&Inputs!$B$32)+1),G6*Inputs!$B$9,0))) -> 0 | H10: =IF(H$3>=Inputs!$B$13,0,IF(H$3=(COUNTIF(Curves!$B$2:$B$13,"<"&Inputs!$B$32)+1),H7*Inputs!$B$9,IF(H$3>(COUNTIF(Curves!$B$2:$B$13,"<"&Inputs!$B$32)+1),H6*Inputs!$B$9,0))) -> 84411800 | I10: =IF(I$3>=Inputs!$B$13,0,IF(I$3=(COUNTIF(Curves!$B$2:$B$13,"<"&Inputs!$B$32)+1),I7*Inputs!$B$9,IF(I$3>(COUNTIF(Curves!$B$2:$B$13,"<"&Inputs!$B$32)+1),I6*Inputs!$B$9,0))) -> 8302800 | ... AH10: =IF(AH$3>=Inputs!$B$13,0,IF(AH$3=(COUNTIF(Curves!$B$2:$B$13,"<"&Inputs!$B$32)+1),AH7*Inputs!$B$9,IF(AH$3>(COUNTIF(Curves!$B$2:$B$13,"<"&Inputs!$B$32)+1),AH6*Inputs!$B$9,0))) -> 0
A11: Milestone 3 collected | B11: =IF(B$3>=Inputs!$B$13,0,IF(B$3=(COUNTIF(Curves!$B$2:$B$13,"<"&Inputs!$B$33)+1),B7*Inputs!$B$9,IF(B$3>(COUNTIF(Curves!$B$2:$B$13,"<"&Inputs!$B$33)+1),B6*Inputs!$B$9,0))) -> 0 | C11: =IF(C$3>=Inputs!$B$13,0,IF(C$3=(COUNTIF(Curves!$B$2:$B$13,"<"&Inputs!$B$33)+1),C7*Inputs!$B$9,IF(C$3>(COUNTIF(Curves!$B$2:$B$13,"<"&Inputs!$B$33)+1),C6*Inputs!$B$9,0))) -> 0 | D11: =IF(D$3>=Inputs!$B$13,0,IF(D$3=(COUNTIF(Curves!$B$2:$B$13,"<"&Inputs!$B$33)+1),D7*Inputs!$B$9,IF(D$3>(COUNTIF(Curves!$B$2:$B$13,"<"&Inputs!$B$33)+1),D6*Inputs!$B$9,0))) -> 0 | E11: =IF(E$3>=Inputs!$B$13,0,IF(E$3=(COUNTIF(Curves!$B$2:$B$13,"<"&Inputs!$B$33)+1),E7*Inputs!$B$9,IF(E$3>(COUNTIF(Curves!$B$2:$B$13,"<"&Inputs!$B$33)+1),E6*Inputs!$B$9,0))) -> 0 | F11: =IF(F$3>=Inputs!$B$13,0,IF(F$3=(COUNTIF(Curves!$B$2:$B$13,"<"&Inputs!$B$33)+1),F7*Inputs!$B$9,IF(F$3>(COUNTIF(Curves!$B$2:$B$13,"<"&Inputs!$B$33)+1),F6*Inputs!$B$9,0))) -> 0 | G11: =IF(G$3>=Inputs!$B$13,0,IF(G$3=(COUNTIF(Curves!$B$2:$B$13,"<"&Inputs!$B$33)+1),G7*Inputs!$B$9,IF(G$3>(COUNTIF(Curves!$B$2:$B$13,"<"&Inputs!$B$33)+1),G6*Inputs!$B$9,0))) -> 0 | H11: =IF(H$3>=Inputs!$B$13,0,IF(H$3=(COUNTIF(Curves!$B$2:$B$13,"<"&Inputs!$B$33)+1),H7*Inputs!$B$9,IF(H$3>(COUNTIF(Curves!$B$2:$B$13,"<"&Inputs!$B$33)+1),H6*Inputs!$B$9,0))) -> 0 | I11: =IF(I$3>=Inputs!$B$13,0,IF(I$3=(COUNTIF(Curves!$B$2:$B$13,"<"&Inputs!$B$33)+1),I7*Inputs!$B$9,IF(I$3>(COUNTIF(Curves!$B$2:$B$13,"<"&Inputs!$B$33)+1),I6*Inputs!$B$9,0))) -> 0 | ... AH11: =IF(AH$3>=Inputs!$B$13,0,IF(AH$3=(COUNTIF(Curves!$B$2:$B$13,"<"&Inputs!$B$33)+1),AH7*Inputs!$B$9,IF(AH$3>(COUNTIF(Curves!$B$2:$B$13,"<"&Inputs!$B$33)+1),AH6*Inputs!$B$9,0))) -> 0
A12: Milestone 4 collected | B12: =IF(B$3>=Inputs!$B$13,0,IF(B$3=(COUNTIF(Curves!$B$2:$B$13,"<"&Inputs!$B$34)+1),B7*Inputs!$B$9,IF(B$3>(COUNTIF(Curves!$B$2:$B$13,"<"&Inputs!$B$34)+1),B6*Inputs!$B$9,0))) -> 0 | C12: =IF(C$3>=Inputs!$B$13,0,IF(C$3=(COUNTIF(Curves!$B$2:$B$13,"<"&Inputs!$B$34)+1),C7*Inputs!$B$9,IF(C$3>(COUNTIF(Curves!$B$2:$B$13,"<"&Inputs!$B$34)+1),C6*Inputs!$B$9,0))) -> 0 | D12: =IF(D$3>=Inputs!$B$13,0,IF(D$3=(COUNTIF(Curves!$B$2:$B$13,"<"&Inputs!$B$34)+1),D7*Inputs!$B$9,IF(D$3>(COUNTIF(Curves!$B$2:$B$13,"<"&Inputs!$B$34)+1),D6*Inputs!$B$9,0))) -> 0 | E12: =IF(E$3>=Inputs!$B$13,0,IF(E$3=(COUNTIF(Curves!$B$2:$B$13,"<"&Inputs!$B$34)+1),E7*Inputs!$B$9,IF(E$3>(COUNTIF(Curves!$B$2:$B$13,"<"&Inputs!$B$34)+1),E6*Inputs!$B$9,0))) -> 0 | F12: =IF(F$3>=Inputs!$B$13,0,IF(F$3=(COUNTIF(Curves!$B$2:$B$13,"<"&Inputs!$B$34)+1),F7*Inputs!$B$9,IF(F$3>(COUNTIF(Curves!$B$2:$B$13,"<"&Inputs!$B$34)+1),F6*Inputs!$B$9,0))) -> 0 | G12: =IF(G$3>=Inputs!$B$13,0,IF(G$3=(COUNTIF(Curves!$B$2:$B$13,"<"&Inputs!$B$34)+1),G7*Inputs!$B$9,IF(G$3>(COUNTIF(Curves!$B$2:$B$13,"<"&Inputs!$B$34)+1),G6*Inputs!$B$9,0))) -> 0 | H12: =IF(H$3>=Inputs!$B$13,0,IF(H$3=(COUNTIF(Curves!$B$2:$B$13,"<"&Inputs!$B$34)+1),H7*Inputs!$B$9,IF(H$3>(COUNTIF(Curves!$B$2:$B$13,"<"&Inputs!$B$34)+1),H6*Inputs!$B$9,0))) -> 0 | I12: =IF(I$3>=Inputs!$B$13,0,IF(I$3=(COUNTIF(Curves!$B$2:$B$13,"<"&Inputs!$B$34)+1),I7*Inputs!$B$9,IF(I$3>(COUNTIF(Curves!$B$2:$B$13,"<"&Inputs!$B$34)+1),I6*Inputs!$B$9,0))) -> 0 | ... AH12: =IF(AH$3>=Inputs!$B$13,0,IF(AH$3=(COUNTIF(Curves!$B$2:$B$13,"<"&Inputs!$B$34)+1),AH7*Inputs!$B$9,IF(AH$3>(COUNTIF(Curves!$B$2:$B$13,"<"&Inputs!$B$34)+1),AH6*Inputs!$B$9,0))) -> 0
A13: Handover collected | B13: =IF(B$3=Inputs!$B$13,B7*Inputs!$B$10+B6*(Inputs!$B$8+4*Inputs!$B$9),IF(B$3>Inputs!$B$13,B6,0)) -> 0 | C13: =IF(C$3=Inputs!$B$13,C7*Inputs!$B$10+C6*(Inputs!$B$8+4*Inputs!$B$9),IF(C$3>Inputs!$B$13,C6,0)) -> 0 | D13: =IF(D$3=Inputs!$B$13,D7*Inputs!$B$10+D6*(Inputs!$B$8+4*Inputs!$B$9),IF(D$3>Inputs!$B$13,D6,0)) -> 0 | E13: =IF(E$3=Inputs!$B$13,E7*Inputs!$B$10+E6*(Inputs!$B$8+4*Inputs!$B$9),IF(E$3>Inputs!$B$13,E6,0)) -> 0 | F13: =IF(F$3=Inputs!$B$13,F7*Inputs!$B$10+F6*(Inputs!$B$8+4*Inputs!$B$9),IF(F$3>Inputs!$B$13,F6,0)) -> 0 | G13: =IF(G$3=Inputs!$B$13,G7*Inputs!$B$10+G6*(Inputs!$B$8+4*Inputs!$B$9),IF(G$3>Inputs!$B$13,G6,0)) -> 0 | H13: =IF(H$3=Inputs!$B$13,H7*Inputs!$B$10+H6*(Inputs!$B$8+4*Inputs!$B$9),IF(H$3>Inputs!$B$13,H6,0)) -> 0 | I13: =IF(I$3=Inputs!$B$13,I7*Inputs!$B$10+I6*(Inputs!$B$8+4*Inputs!$B$9),IF(I$3>Inputs!$B$13,I6,0)) -> 0 | ... AH13: =IF(AH$3=Inputs!$B$13,AH7*Inputs!$B$10+AH6*(Inputs!$B$8+4*Inputs!$B$9),IF(AH$3>Inputs!$B$13,AH6,0)) -> 0
A14: Collections | B14: =SUM(B8:B13) -> 0 | C14: =SUM(C8:C13) -> 24908400 | D14: =SUM(D8:D13) -> 16605600 | E14: =SUM(E8:E13) -> 12454200 | F14: =SUM(F8:F13) -> 76109000 | G14: =SUM(G8:G13) -> 19373200 | H14: =SUM(H8:H13) -> 103785000 | I14: =SUM(I8:I13) -> 24908400 | ... AH14: =SUM(AH8:AH13) -> 0
A15: Escrow released | B15: =IF(B$3>=Inputs!$B$13,B14+0,MIN(0+B14,B18)) -> 0 | C15: =IF(C$3>=Inputs!$B$13,C14+B16,MIN(B16+C14,C18)) -> 14041500 | D15: =IF(D$3>=Inputs!$B$13,D14+C16,MIN(C16+D14,D18)) -> 23402500 | E15: =IF(E$3>=Inputs!$B$13,E14+D16,MIN(D16+E14,E18)) -> 16524200 | F15: =IF(F$3>=Inputs!$B$13,F14+E16,MIN(E16+F14,F18)) -> 42124500 | G15: =IF(G$3>=Inputs!$B$13,G14+F16,MIN(F16+G14,G18)) -> 46805000 | H15: =IF(H$3>=Inputs!$B$13,H14+G16,MIN(G16+H14,H18)) -> 51485500 | I15: =IF(I$3>=Inputs!$B$13,I14+H16,MIN(H16+I14,I18)) -> 51485500 | J15: =IF(J$3>=Inputs!$B$13,J14+I16,MIN(I16+J14,J18)) -> 51485500 | ... AH15: =IF(AH$3>=Inputs!$B$13,AH14+AG16,MIN(AG16+AH14,AH18)) -> 0
A16: Escrow balance | B16: =0+B14-B15 -> 0 | C16: =B16+C14-C15 -> 10866900 | D16: =C16+D14-D15 -> 4070000 | E16: =D16+E14-E15 -> 0 | F16: =E16+F14-F15 -> 33984500 | G16: =F16+G14-G15 -> 6552700 | H16: =G16+H14-H15 -> 58852200 | I16: =H16+I14-I15 -> 32275100 | J16: =I16+J14-J15 -> 106715400 | ... AH16: =AG16+AH14-AH15 -> 0
A17: Branding fee | B17: =B14*Inputs!$B$7 -> 0 | C17: =C14*Inputs!$B$7 -> 1245420 | D17: =D14*Inputs!$B$7 -> 830280 | E17: =E14*Inputs!$B$7 -> 622710 | F17: =F14*Inputs!$B$7 -> 3805450 | G17: =G14*Inputs!$B$7 -> 968660 | H17: =H14*Inputs!$B$7 -> 5189250 | I17: =I14*Inputs!$B$7 -> 1245420 | ... AH17: =AH14*Inputs!$B$7 -> 0
A18: Residence build cost | B18: =IF(AND(B$3>=1,B$3<=Inputs!$B$13),Inputs!$B$4*Inputs!$B$5*Inputs!$B$11*(INDEX(Curves!$B$2:$B$13,MAX(1,MIN(12,B$3)))-IF(B$3>1,INDEX(Curves!$B$2:$B$13,MAX(1,MIN(12,B$3-1))),0)),0) -> 0 | C18: =IF(AND(C$3>=1,C$3<=Inputs!$B$13),Inputs!$B$4*Inputs!$B$5*Inputs!$B$11*(INDEX(Curves!$B$2:$B$13,MAX(1,MIN(12,C$3)))-IF(C$3>1,INDEX(Curves!$B$2:$B$13,MAX(1,MIN(12,C$3-1))),0)),0) -> 14041500 | D18: =IF(AND(D$3>=1,D$3<=Inputs!$B$13),Inputs!$B$4*Inputs!$B$5*Inputs!$B$11*(INDEX(Curves!$B$2:$B$13,MAX(1,MIN(12,D$3)))-IF(D$3>1,INDEX(Curves!$B$2:$B$13,MAX(1,MIN(12,D$3-1))),0)),0) -> 23402500 | E18: =IF(AND(E$3>=1,E$3<=Inputs!$B$13),Inputs!$B$4*Inputs!$B$5*Inputs!$B$11*(INDEX(Curves!$B$2:$B$13,MAX(1,MIN(12,E$3)))-IF(E$3>1,INDEX(Curves!$B$2:$B$13,MAX(1,MIN(12,E$3-1))),0)),0) -> 32763500 | F18: =IF(AND(F$3>=1,F$3<=Inputs!$B$13),Inputs!$B$4*Inputs!$B$5*Inputs!$B$11*(INDEX(Curves!$B$2:$B$13,MAX(1,MIN(12,F$3)))-IF(F$3>1,INDEX(Curves!$B$2:$B$13,MAX(1,MIN(12,F$3-1))),0)),0) -> 42124500 | G18: =IF(AND(G$3>=1,G$3<=Inputs!$B$13),Inputs!$B$4*Inputs!$B$5*Inputs!$B$11*(INDEX(Curves!$B$2:$B$13,MAX(1,MIN(12,G$3)))-IF(G$3>1,INDEX(Curves!$B$2:$B$13,MAX(1,MIN(12,G$3-1))),0)),0) -> 46805000 | H18: =IF(AND(H$3>=1,H$3<=Inputs!$B$13),Inputs!$B$4*Inputs!$B$5*Inputs!$B$11*(INDEX(Curves!$B$2:$B$13,MAX(1,MIN(12,H$3)))-IF(H$3>1,INDEX(Curves!$B$2:$B$13,MAX(1,MIN(12,H$3-1))),0)),0) -> 51485500 | I18: =IF(AND(I$3>=1,I$3<=Inputs!$B$13),Inputs!$B$4*Inputs!$B$5*Inputs!$B$11*(INDEX(Curves!$B$2:$B$13,MAX(1,MIN(12,I$3)))-IF(I$3>1,INDEX(Curves!$B$2:$B$13,MAX(1,MIN(12,I$3-1))),0)),0) -> 51485500 | ... AH18: =IF(AND(AH$3>=1,AH$3<=Inputs!$B$13),Inputs!$B$4*Inputs!$B$5*Inputs!$B$11*(INDEX(Curves!$B$2:$B$13,MAX(1,MIN(12,AH$3)))-IF(AH$3>1,INDEX(Curves!$B$2:$B$13,MAX(1,MIN(12,AH$3-1))),0)),0) -> 0
A19: Hotel capex | B19: =IF(AND(B$3>=1,B$3<=Inputs!$B$13),Inputs!$B$14*Inputs!$B$15/Inputs!$B$13,0) -> 0 | C19: =IF(AND(C$3>=1,C$3<=Inputs!$B$13),Inputs!$B$14*Inputs!$B$15/Inputs!$B$13,0) -> 39583333 | D19: =IF(AND(D$3>=1,D$3<=Inputs!$B$13),Inputs!$B$14*Inputs!$B$15/Inputs!$B$13,0) -> 39583333 | E19: =IF(AND(E$3>=1,E$3<=Inputs!$B$13),Inputs!$B$14*Inputs!$B$15/Inputs!$B$13,0) -> 39583333 | F19: =IF(AND(F$3>=1,F$3<=Inputs!$B$13),Inputs!$B$14*Inputs!$B$15/Inputs!$B$13,0) -> 39583333 | G19: =IF(AND(G$3>=1,G$3<=Inputs!$B$13),Inputs!$B$14*Inputs!$B$15/Inputs!$B$13,0) -> 39583333 | H19: =IF(AND(H$3>=1,H$3<=Inputs!$B$13),Inputs!$B$14*Inputs!$B$15/Inputs!$B$13,0) -> 39583333 | I19: =IF(AND(I$3>=1,I$3<=Inputs!$B$13),Inputs!$B$14*Inputs!$B$15/Inputs!$B$13,0) -> 39583333 | ... AH19: =IF(AND(AH$3>=1,AH$3<=Inputs!$B$13),Inputs!$B$14*Inputs!$B$15/Inputs!$B$13,0) -> 0
A20: Land | B20: =IF(B$3=0,Inputs!$B$12,0) -> 260000000 | C20: =IF(C$3=0,Inputs!$B$12,0) -> 0 | D20: =IF(D$3=0,Inputs!$B$12,0) -> 0 | E20: =IF(E$3=0,Inputs!$B$12,0) -> 0 | F20: =IF(F$3=0,Inputs!$B$12,0) -> 0 | G20: =IF(G$3=0,Inputs!$B$12,0) -> 0 | H20: =IF(H$3=0,Inputs!$B$12,0) -> 0 | I20: =IF(I$3=0,Inputs!$B$12,0) -> 0 | ... AH20: =IF(AH$3=0,Inputs!$B$12,0) -> 0
A21: Hotel open | B21: =IF(AND(B$3>Inputs!$B$13,B$3<=Inputs!$B$26),1,0) -> 0 | C21: =IF(AND(C$3>Inputs!$B$13,C$3<=Inputs!$B$26),1,0) -> 0 | D21: =IF(AND(D$3>Inputs!$B$13,D$3<=Inputs!$B$26),1,0) -> 0 | E21: =IF(AND(E$3>Inputs!$B$13,E$3<=Inputs!$B$26),1,0) -> 0 | F21: =IF(AND(F$3>Inputs!$B$13,F$3<=Inputs!$B$26),1,0) -> 0 | G21: =IF(AND(G$3>Inputs!$B$13,G$3<=Inputs!$B$26),1,0) -> 0 | H21: =IF(AND(H$3>Inputs!$B$13,H$3<=Inputs!$B$26),1,0) -> 0 | I21: =IF(AND(I$3>Inputs!$B$13,I$3<=Inputs!$B$26),1,0) -> 0 | ... AH21: =IF(AND(AH$3>Inputs!$B$13,AH$3<=Inputs!$B$26),1,0) -> 1
A22: Year of operation | B22: =IF(B21=1,INT((B$3-Inputs!$B$13-1)/4)+1,0) -> 0 | C22: =IF(C21=1,INT((C$3-Inputs!$B$13-1)/4)+1,0) -> 0 | D22: =IF(D21=1,INT((D$3-Inputs!$B$13-1)/4)+1,0) -> 0 | E22: =IF(E21=1,INT((E$3-Inputs!$B$13-1)/4)+1,0) -> 0 | F22: =IF(F21=1,INT((F$3-Inputs!$B$13-1)/4)+1,0) -> 0 | G22: =IF(G21=1,INT((G$3-Inputs!$B$13-1)/4)+1,0) -> 0 | H22: =IF(H21=1,INT((H$3-Inputs!$B$13-1)/4)+1,0) -> 0 | I22: =IF(I21=1,INT((I$3-Inputs!$B$13-1)/4)+1,0) -> 0 | ... AH22: =IF(AH21=1,INT((AH$3-Inputs!$B$13-1)/4)+1,0) -> 5
A23: Occupancy | B23: =IF(B21=1,MIN(0.95,INDEX(Curves!$D$2:$D$5,MIN(4,B22))*INDEX(Inputs!$B$36:$E$36,INT((MONTH(B4)-1)/3)+1)),0) -> 0 | C23: =IF(C21=1,MIN(0.95,INDEX(Curves!$D$2:$D$5,MIN(4,C22))*INDEX(Inputs!$B$36:$E$36,INT((MONTH(C4)-1)/3)+1)),0) -> 0 | D23: =IF(D21=1,MIN(0.95,INDEX(Curves!$D$2:$D$5,MIN(4,D22))*INDEX(Inputs!$B$36:$E$36,INT((MONTH(D4)-1)/3)+1)),0) -> 0 | E23: =IF(E21=1,MIN(0.95,INDEX(Curves!$D$2:$D$5,MIN(4,E22))*INDEX(Inputs!$B$36:$E$36,INT((MONTH(E4)-1)/3)+1)),0) -> 0 | F23: =IF(F21=1,MIN(0.95,INDEX(Curves!$D$2:$D$5,MIN(4,F22))*INDEX(Inputs!$B$36:$E$36,INT((MONTH(F4)-1)/3)+1)),0) -> 0 | G23: =IF(G21=1,MIN(0.95,INDEX(Curves!$D$2:$D$5,MIN(4,G22))*INDEX(Inputs!$B$36:$E$36,INT((MONTH(G4)-1)/3)+1)),0) -> 0 | H23: =IF(H21=1,MIN(0.95,INDEX(Curves!$D$2:$D$5,MIN(4,H22))*INDEX(Inputs!$B$36:$E$36,INT((MONTH(H4)-1)/3)+1)),0) -> 0 | I23: =IF(I21=1,MIN(0.95,INDEX(Curves!$D$2:$D$5,MIN(4,I22))*INDEX(Inputs!$B$36:$E$36,INT((MONTH(I4)-1)/3)+1)),0) -> 0 | ... AH23: =IF(AH21=1,MIN(0.95,INDEX(Curves!$D$2:$D$5,MIN(4,AH22))*INDEX(Inputs!$B$36:$E$36,INT((MONTH(AH4)-1)/3)+1)),0) -> 0.518
A24: ADR | B24: =IF(B21=1,Inputs!$B$16*(1+Inputs!$B$17)^(B22-1),0) -> 0 | C24: =IF(C21=1,Inputs!$B$16*(1+Inputs!$B$17)^(C22-1),0) -> 0 | D24: =IF(D21=1,Inputs!$B$16*(1+Inputs!$B$17)^(D22-1),0) -> 0 | E24: =IF(E21=1,Inputs!$B$16*(1+Inputs!$B$17)^(E22-1),0) -> 0 | F24: =IF(F21=1,Inputs!$B$16*(1+Inputs!$B$17)^(F22-1),0) -> 0 | G24: =IF(G21=1,Inputs!$B$16*(1+Inputs!$B$17)^(G22-1),0) -> 0 | H24: =IF(H21=1,Inputs!$B$16*(1+Inputs!$B$17)^(H22-1),0) -> 0 | I24: =IF(I21=1,Inputs!$B$16*(1+Inputs!$B$17)^(I22-1),0) -> 0 | ... AH24: =IF(AH21=1,Inputs!$B$16*(1+Inputs!$B$17)^(AH22-1),0) -> 1696.2949
A25: Rooms revenue | B25: =Inputs!$B$14*91.25*B23*B24 -> 0 | C25: =Inputs!$B$14*91.25*C23*C24 -> 0 | D25: =Inputs!$B$14*91.25*D23*D24 -> 0 | E25: =Inputs!$B$14*91.25*E23*E24 -> 0 | F25: =Inputs!$B$14*91.25*F23*F24 -> 0 | G25: =Inputs!$B$14*91.25*G23*G24 -> 0 | H25: =Inputs!$B$14*91.25*H23*H24 -> 0 | I25: =Inputs!$B$14*91.25*I23*I24 -> 0 | ... AH25: =Inputs!$B$14*91.25*AH23*AH24 -> 20044905
A26: Total hotel revenue | B26: =B25*(1+Inputs!$B$18) -> 0 | C26: =C25*(1+Inputs!$B$18) -> 0 | D26: =D25*(1+Inputs!$B$18) -> 0 | E26: =E25*(1+Inputs!$B$18) -> 0 | F26: =F25*(1+Inputs!$B$18) -> 0 | G26: =G25*(1+Inputs!$B$18) -> 0 | H26: =H25*(1+Inputs!$B$18) -> 0 | I26: =I25*(1+Inputs!$B$18) -> 0 | ... AH26: =AH25*(1+Inputs!$B$18) -> 29065112
A27: GOP | B27: =B26*Inputs!$B$19 -> 0 | C27: =C26*Inputs!$B$19 -> 0 | D27: =D26*Inputs!$B$19 -> 0 | E27: =E26*Inputs!$B$19 -> 0 | F27: =F26*Inputs!$B$19 -> 0 | G27: =G26*Inputs!$B$19 -> 0 | H27: =H26*Inputs!$B$19 -> 0 | I27: =I26*Inputs!$B$19 -> 0 | ... AH27: =AH26*Inputs!$B$19 -> 11044743
A28: Base fee | B28: =B26*Inputs!$B$20 -> 0 | C28: =C26*Inputs!$B$20 -> 0 | D28: =D26*Inputs!$B$20 -> 0 | E28: =E26*Inputs!$B$20 -> 0 | F28: =F26*Inputs!$B$20 -> 0 | G28: =G26*Inputs!$B$20 -> 0 | H28: =H26*Inputs!$B$20 -> 0 | I28: =I26*Inputs!$B$20 -> 0 | ... AH28: =AH26*Inputs!$B$20 -> 871953.36
A29: FF&E reserve | B29: =IF(B21=1,B26*CHOOSE(MIN(3,B22),0.02,0.03,0.04),0) -> 0 | C29: =IF(C21=1,C26*CHOOSE(MIN(3,C22),0.02,0.03,0.04),0) -> 0 | D29: =IF(D21=1,D26*CHOOSE(MIN(3,D22),0.02,0.03,0.04),0) -> 0 | E29: =IF(E21=1,E26*CHOOSE(MIN(3,E22),0.02,0.03,0.04),0) -> 0 | F29: =IF(F21=1,F26*CHOOSE(MIN(3,F22),0.02,0.03,0.04),0) -> 0 | G29: =IF(G21=1,G26*CHOOSE(MIN(3,G22),0.02,0.03,0.04),0) -> 0 | H29: =IF(H21=1,H26*CHOOSE(MIN(3,H22),0.02,0.03,0.04),0) -> 0 | I29: =IF(I21=1,I26*CHOOSE(MIN(3,I22),0.02,0.03,0.04),0) -> 0 | ... AH29: =IF(AH21=1,AH26*CHOOSE(MIN(3,AH22),0.02,0.03,0.04),0) -> 1162604.5
A30: Owner's priority | B30: =B21*Inputs!$B$14*Inputs!$B$15*Inputs!$B$21/4 -> 0 | C30: =C21*Inputs!$B$14*Inputs!$B$15*Inputs!$B$21/4 -> 0 | D30: =D21*Inputs!$B$14*Inputs!$B$15*Inputs!$B$21/4 -> 0 | E30: =E21*Inputs!$B$14*Inputs!$B$15*Inputs!$B$21/4 -> 0 | F30: =F21*Inputs!$B$14*Inputs!$B$15*Inputs!$B$21/4 -> 0 | G30: =G21*Inputs!$B$14*Inputs!$B$15*Inputs!$B$21/4 -> 0 | H30: =H21*Inputs!$B$14*Inputs!$B$15*Inputs!$B$21/4 -> 0 | I30: =I21*Inputs!$B$14*Inputs!$B$15*Inputs!$B$21/4 -> 0 | ... AH30: =AH21*Inputs!$B$14*Inputs!$B$15*Inputs!$B$21/4 -> 11875000
A31: Incentive fee | B31: =MAX(0,B27-B28-B29-B30)*Inputs!$B$22 -> 0 | C31: =MAX(0,C27-C28-C29-C30)*Inputs!$B$22 -> 0 | D31: =MAX(0,D27-D28-D29-D30)*Inputs!$B$22 -> 0 | E31: =MAX(0,E27-E28-E29-E30)*Inputs!$B$22 -> 0 | F31: =MAX(0,F27-F28-F29-F30)*Inputs!$B$22 -> 0 | G31: =MAX(0,G27-G28-G29-G30)*Inputs!$B$22 -> 0 | H31: =MAX(0,H27-H28-H29-H30)*Inputs!$B$22 -> 0 | I31: =MAX(0,I27-I28-I29-I30)*Inputs!$B$22 -> 0 | ... AH31: =MAX(0,AH27-AH28-AH29-AH30)*Inputs!$B$22 -> 0
A32: Hotel EBITDA | B32: =B27-B28-B29-B31 -> 0 | C32: =C27-C28-C29-C31 -> 0 | D32: =D27-D28-D29-D31 -> 0 | E32: =E27-E28-E29-E31 -> 0 | F32: =F27-F28-F29-F31 -> 0 | G32: =G27-G28-G29-G31 -> 0 | H32: =H27-H28-H29-H31 -> 0 | I32: =I27-I28-I29-I31 -> 0 | ... AH32: =AH27-AH28-AH29-AH31 -> 9010184.8
A33: Pre-finance cash flow | B33: =B15-B17-B18-B19-B20+B32 -> -260000000 | C33: =C15-C17-C18-C19-C20+C32 -> -40828753 | D33: =D15-D17-D18-D19-D20+D32 -> -40413613 | E33: =E15-E17-E18-E19-E20+E32 -> -56445343 | F33: =F15-F17-F18-F19-F20+F32 -> -43388783 | G33: =G15-G17-G18-G19-G20+G32 -> -40551993 | H33: =H15-H17-H18-H19-H20+H32 -> -44772583 | I33: =I15-I17-I18-I19-I20+I32 -> -40828753 | ... AH33: =AH15-AH17-AH18-AH19-AH20+AH32 -> 9010184.8
A34: Opening facility | B34: =0 -> 0 | C34: =B39 -> 0 | D34: =C39 -> 0 | E34: =D39 -> 0 | F34: =E39 -> 0 | G34: =F39 -> 21076493 | H34: =G39 -> 62023671 | I34: =H39 -> 1.079592e+08 | J34: =I39 -> 1.5081219e+08 | ... AH34: =AG39 -> 0
A35: Interest | B35: =B34*Inputs!$B$24/4 -> 0 | C35: =C34*Inputs!$B$24/4 -> 0 | D35: =D34*Inputs!$B$24/4 -> 0 | E35: =E34*Inputs!$B$24/4 -> 0 | F35: =F34*Inputs!$B$24/4 -> 0 | G35: =G34*Inputs!$B$24/4 -> 395184.25 | H35: =H34*Inputs!$B$24/4 -> 1162943.8 | I35: =I34*Inputs!$B$24/4 -> 2024235 | ... AH35: =AH34*Inputs!$B$24/4 -> 0
A36: Equity drawn | B36: =MIN(MAX(0,-(B33-B35)),MAX(0,Inputs!$B$23-0)) -> 260000000 | C36: =MIN(MAX(0,-(C33-C35)),MAX(0,Inputs!$B$23-SUM($B$36:B36))) -> 40828753 | D36: =MIN(MAX(0,-(D33-D35)),MAX(0,Inputs!$B$23-SUM($B$36:C36))) -> 40413613 | E36: =MIN(MAX(0,-(E33-E35)),MAX(0,Inputs!$B$23-SUM($B$36:D36))) -> 56445343 | F36: =MIN(MAX(0,-(F33-F35)),MAX(0,Inputs!$B$23-SUM($B$36:E36))) -> 22312290 | G36: =MIN(MAX(0,-(G33-G35)),MAX(0,Inputs!$B$23-SUM($B$36:F36))) -> 0 | H36: =MIN(MAX(0,-(H33-H35)),MAX(0,Inputs!$B$23-SUM($B$36:G36))) -> 0 | I36: =MIN(MAX(0,-(I33-I35)),MAX(0,Inputs!$B$23-SUM($B$36:H36))) -> 0 | J36: =MIN(MAX(0,-(J33-J35)),MAX(0,Inputs!$B$23-SUM($B$36:I36))) -> 0 | ... AH36: =MIN(MAX(0,-(AH33-AH35)),MAX(0,Inputs!$B$23-SUM($B$36:AG36))) -> 0
A37: Facility drawn | B37: =MAX(0,-(B33-B35))-B36 -> 0 | C37: =MAX(0,-(C33-C35))-C36 -> 0 | D37: =MAX(0,-(D33-D35))-D36 -> 0 | E37: =MAX(0,-(E33-E35))-E36 -> 0 | F37: =MAX(0,-(F33-F35))-F36 -> 21076493 | G37: =MAX(0,-(G33-G35))-G36 -> 40947178 | H37: =MAX(0,-(H33-H35))-H36 -> 45935527 | I37: =MAX(0,-(I33-I35))-I36 -> 42852988 | ... AH37: =MAX(0,-(AH33-AH35))-AH36 -> 0
A38: Facility repaid | B38: =MIN(B34,MAX(0,B33-B35)) -> 0 | C38: =MIN(C34,MAX(0,C33-C35)) -> 0 | D38: =MIN(D34,MAX(0,D33-D35)) -> 0 | E38: =MIN(E34,MAX(0,E33-E35)) -> 0 | F38: =MIN(F34,MAX(0,F33-F35)) -> 0 | G38: =MIN(G34,MAX(0,G33-G35)) -> 0 | H38: =MIN(H34,MAX(0,H33-H35)) -> 0 | I38: =MIN(I34,MAX(0,I33-I35)) -> 0 | ... AH38: =MIN(AH34,MAX(0,AH33-AH35)) -> 0
A39: Facility balance | B39: =IF(B$3>=Inputs!$B$26,0,B34+B37-B38) -> 0 | C39: =IF(C$3>=Inputs!$B$26,0,C34+C37-C38) -> 0 | D39: =IF(D$3>=Inputs!$B$26,0,D34+D37-D38) -> 0 | E39: =IF(E$3>=Inputs!$B$26,0,E34+E37-E38) -> 0 | F39: =IF(F$3>=Inputs!$B$26,0,F34+F37-F38) -> 21076493 | G39: =IF(G$3>=Inputs!$B$26,0,G34+G37-G38) -> 62023671 | H39: =IF(H$3>=Inputs!$B$26,0,H34+H37-H38) -> 1.079592e+08 | I39: =IF(I$3>=Inputs!$B$26,0,I34+I37-I38) -> 1.5081219e+08 | ... AH39: =IF(AH$3>=Inputs!$B$26,0,AH34+AH37-AH38) -> 0
A40: Hotel sale | B40: =IF(B$3=Inputs!$B$26,SUM(B32:B32)*4/MIN(4,B$3-Inputs!$B$13)/Inputs!$B$25,0) -> 0 | C40: =IF(C$3=Inputs!$B$26,SUM(B32:C32)*4/MIN(4,C$3-Inputs!$B$13)/Inputs!$B$25,0) -> 0 | D40: =IF(D$3=Inputs!$B$26,SUM(B32:D32)*4/MIN(4,D$3-Inputs!$B$13)/Inputs!$B$25,0) -> 0 | E40: =IF(E$3=Inputs!$B$26,SUM(B32:E32)*4/MIN(4,E$3-Inputs!$B$13)/Inputs!$B$25,0) -> 0 | F40: =IF(F$3=Inputs!$B$26,SUM(C32:F32)*4/MIN(4,F$3-Inputs!$B$13)/Inputs!$B$25,0) -> 0 | G40: =IF(G$3=Inputs!$B$26,SUM(D32:G32)*4/MIN(4,G$3-Inputs!$B$13)/Inputs!$B$25,0) -> 0 | H40: =IF(H$3=Inputs!$B$26,SUM(E32:H32)*4/MIN(4,H$3-Inputs!$B$13)/Inputs!$B$25,0) -> 0 | I40: =IF(I$3=Inputs!$B$26,SUM(F32:I32)*4/MIN(4,I$3-Inputs!$B$13)/Inputs!$B$25,0) -> 0 | J40: =IF(J$3=Inputs!$B$26,SUM(G32:J32)*4/MIN(4,J$3-Inputs!$B$13)/Inputs!$B$25,0) -> 0 | K40: =IF(K$3=Inputs!$B$26,SUM(H32:K32)*4/MIN(4,K$3-Inputs!$B$13)/Inputs!$B$25,0) -> 0 | L40: =IF(L$3=Inputs!$B$26,SUM(I32:L32)*4/MIN(4,L$3-Inputs!$B$13)/Inputs!$B$25,0) -> 0 | ... AH40: =IF(AH$3=Inputs!$B$26,SUM(AE32:AH32)*4/MIN(4,AH$3-Inputs!$B$13)/Inputs!$B$25,0) -> 7.276949e+08
A41: Distributions | B41: =MAX(0,B33-B35-B38)+B40-IF(B$3=Inputs!$B$26,B34+B37-B38,0) -> 0 | C41: =MAX(0,C33-C35-C38)+C40-IF(C$3=Inputs!$B$26,C34+C37-C38,0) -> 0 | D41: =MAX(0,D33-D35-D38)+D40-IF(D$3=Inputs!$B$26,D34+D37-D38,0) -> 0 | E41: =MAX(0,E33-E35-E38)+E40-IF(E$3=Inputs!$B$26,E34+E37-E38,0) -> 0 | F41: =MAX(0,F33-F35-F38)+F40-IF(F$3=Inputs!$B$26,F34+F37-F38,0) -> 0 | G41: =MAX(0,G33-G35-G38)+G40-IF(G$3=Inputs!$B$26,G34+G37-G38,0) -> 0 | H41: =MAX(0,H33-H35-H38)+H40-IF(H$3=Inputs!$B$26,H34+H37-H38,0) -> 0 | I41: =MAX(0,I33-I35-I38)+I40-IF(I$3=Inputs!$B$26,I34+I37-I38,0) -> 0 | ... AH41: =MAX(0,AH33-AH35-AH38)+AH40-IF(AH$3=Inputs!$B$26,AH34+AH37-AH38,0) -> 7.3670509e+08
A42: Equity cash flow | B42: =IF(B$3>Inputs!$B$26,0,B41-B36) -> -260000000 | C42: =IF(C$3>Inputs!$B$26,0,C41-C36) -> -40828753 | D42: =IF(D$3>Inputs!$B$26,0,D41-D36) -> -40413613 | E42: =IF(E$3>Inputs!$B$26,0,E41-E36) -> -56445343 | F42: =IF(F$3>Inputs!$B$26,0,F41-F36) -> -22312290 | G42: =IF(G$3>Inputs!$B$26,0,G41-G36) -> 0 | H42: =IF(H$3>Inputs!$B$26,0,H41-H36) -> 0 | I42: =IF(I$3>Inputs!$B$26,0,I41-I36) -> 0 | ... AH42: =IF(AH$3>Inputs!$B$26,0,AH41-AH36) -> 7.3670509e+08

Sheet Returns
A3: Levered IRR (XIRR) | B3: =XIRR('Cash Flow'!$B$42:$AH$42,'Cash Flow'!$B$4:$AH$4) -> 0.2753915
A4: Equity multiple | B4: =SUMIF('Cash Flow'!$B$42:$AH$42,">0")/-SUMIF('Cash Flow'!$B$42:$AH$42,"<0") -> 3.4700197
A5: Residences profit (AED) | B5: =SUM('Cash Flow'!$B$14:$AH$14)-SUM('Cash Flow'!$B$17:$AH$17)-SUM('Cash Flow'!$B$18:$AH$18)-Inputs!$B$12*0.55 -> 703560000
A6: Hotel EBITDA, third year (AED) | B6: =SUMIF('Cash Flow'!$B$22:$AH$22,3,'Cash Flow'!$B$32:$AH$32) -> 46039016
A7: Sales collected by handover | B7: =SUMIF('Cash Flow'!$B$3:$AH$3,"<="&Inputs!$B$13,'Cash Flow'!$B$14:$AH$14)/SUM('Cash Flow'!$B$6:$AH$6) -> 0.91
A8: Operator incentive fee (AED) | B8: =SUM('Cash Flow'!$B$31:$AH$31) -> 1332365.6
A9: Peak facility (AED) | B9: =MAX('Cash Flow'!$B$39:$AH$39) -> 3.4202491e+08
A10: Peak escrow balance (AED) | B10: =MAX('Cash Flow'!$B$16:$AH$16) -> 187993300
A11: Equity drawn (AED) | B11: =SUM('Cash Flow'!$B$36:$AH$36) -> 420000000
A12: Net profit (AED) | B12: =SUM('Cash Flow'!$B$42:$AH$42) -> 1.0374083e+09
