Workbook

Sheet Inputs
A1: NORTHGATE DATA CENTRE CAMPUS – DEVELOPMENT AND HOLD (USD)
A3: Case (1 Base, 2 Downside, 3 Upside) | B3: 1
A4: Model start | B4: 46387
A5: Capex per MW ($, today) | B5: 11500000
A6: Cost inflation a year | B6: 0.03
A7: Rent per kW a month ($) · Base | B7: 118
A8: Rent per kW a month ($) · Downside | B8: 102
A9: Rent per kW a month ($) · Upside | B9: 130
A10: Rent escalation a year | B10: 0.025
A11: PUE | B11: 1.35
A12: Power tariff ($ per MWh) | B12: 85
A13: IT load utilisation | B13: 0.7
A14: Power cost recovered from tenants | B14: 0.9
... A26: Exit cap · Upside | B26: 0.0575
A28: Rent per kW (live case) | B28: =CHOOSE(Inputs!$B$3,Inputs!$B$7,Inputs!$B$8,Inputs!$B$9) -> 118
A29: Exit cap (live case) | B29: =CHOOSE(Inputs!$B$3,Inputs!$B$24,Inputs!$B$25,Inputs!$B$26) -> 0.0625

Sheet Phases
A1: Phase | B1: MW | C1: Start quarter | D1: Build (quarters) | E1: Pre-let · Base | F1: Pre-let · Downside | G1: Pre-let · Upside | H1: Lease-up of the rest (quarters) | I1: Pre-let (live case)
A2: Phase 1 | B2: 24 | C2: 1 | D2: 7 | E2: 0.6 | F2: 0.4 | G2: 0.75 | H2: 6 | I2: =CHOOSE(Inputs!$B$3,E2,F2,G2) -> 0.6
A3: Phase 2 | B3: 32 | C3: 6 | D3: 8 | E3: 0.5 | F3: 0.3 | G3: 0.65 | H3: 8 | I3: =CHOOSE(Inputs!$B$3,E3,F3,G3) -> 0.5
A4: Phase 3 | B4: 40 | C4: 13 | D4: 8 | E4: 0.35 | F4: 0.2 | G4: 0.5 | H4: 10 | I4: =CHOOSE(Inputs!$B$3,E4,F4,G4) -> 0.35

Sheet Cash Flow
A3: Quarter | B3: 0 | C3: 1 | D3: 2 | E3: 3 | F3: 4 | G3: 5 | H3: 6 | I3: 7 | J3: 8 | K3: 9 | L3: 10 | M3: 11 | N3: 12 | O3: 13 | P3: 14 | Q3: 15 | R3: 16 | S3: 17 | T3: 18 | U3: 19 | V3: 20 | W3: 21 | X3: 22 | Y3: 23 | Z3: 24 | AA3: 25 | AB3: 26 | AC3: 27 | AD3: 28 | AE3: 29 | AF3: 30 | AG3: 31 | AH3: 32 | AI3: 33 | AJ3: 34 | AK3: 35 | AL3: 36 | AM3: 37 | AN3: 38 | AO3: 39 | AP3: 40
A4: Date | B4: =EOMONTH(Inputs!$B$4,3*B$3) -> 46387 | C4: =EOMONTH(Inputs!$B$4,3*C$3) -> 46477 | D4: =EOMONTH(Inputs!$B$4,3*D$3) -> 46568 | E4: =EOMONTH(Inputs!$B$4,3*E$3) -> 46660 | F4: =EOMONTH(Inputs!$B$4,3*F$3) -> 46752 | G4: =EOMONTH(Inputs!$B$4,3*G$3) -> 46843 | H4: =EOMONTH(Inputs!$B$4,3*H$3) -> 46934 | I4: =EOMONTH(Inputs!$B$4,3*I$3) -> 47026 | ... AP4: =EOMONTH(Inputs!$B$4,3*AP$3) -> 50040
A5: P1 capex | B5: =IF(AND(B$3>=Phases!$C$2,B$3<Phases!$C$2+Phases!$D$2),Phases!$B$2*Inputs!$B$5*(1+Inputs!$B$6)^INT((Phases!$C$2-1)/4)/Phases!$D$2,0) -> 0 | C5: =IF(AND(C$3>=Phases!$C$2,C$3<Phases!$C$2+Phases!$D$2),Phases!$B$2*Inputs!$B$5*(1+Inputs!$B$6)^INT((Phases!$C$2-1)/4)/Phases!$D$2,0) -> 39428571 | D5: =IF(AND(D$3>=Phases!$C$2,D$3<Phases!$C$2+Phases!$D$2),Phases!$B$2*Inputs!$B$5*(1+Inputs!$B$6)^INT((Phases!$C$2-1)/4)/Phases!$D$2,0) -> 39428571 | E5: =IF(AND(E$3>=Phases!$C$2,E$3<Phases!$C$2+Phases!$D$2),Phases!$B$2*Inputs!$B$5*(1+Inputs!$B$6)^INT((Phases!$C$2-1)/4)/Phases!$D$2,0) -> 39428571 | F5: =IF(AND(F$3>=Phases!$C$2,F$3<Phases!$C$2+Phases!$D$2),Phases!$B$2*Inputs!$B$5*(1+Inputs!$B$6)^INT((Phases!$C$2-1)/4)/Phases!$D$2,0) -> 39428571 | G5: =IF(AND(G$3>=Phases!$C$2,G$3<Phases!$C$2+Phases!$D$2),Phases!$B$2*Inputs!$B$5*(1+Inputs!$B$6)^INT((Phases!$C$2-1)/4)/Phases!$D$2,0) -> 39428571 | H5: =IF(AND(H$3>=Phases!$C$2,H$3<Phases!$C$2+Phases!$D$2),Phases!$B$2*Inputs!$B$5*(1+Inputs!$B$6)^INT((Phases!$C$2-1)/4)/Phases!$D$2,0) -> 39428571 | I5: =IF(AND(I$3>=Phases!$C$2,I$3<Phases!$C$2+Phases!$D$2),Phases!$B$2*Inputs!$B$5*(1+Inputs!$B$6)^INT((Phases!$C$2-1)/4)/Phases!$D$2,0) -> 39428571 | ... AP5: =IF(AND(AP$3>=Phases!$C$2,AP$3<Phases!$C$2+Phases!$D$2),Phases!$B$2*Inputs!$B$5*(1+Inputs!$B$6)^INT((Phases!$C$2-1)/4)/Phases!$D$2,0) -> 0
A6: P1 leased MW | B6: =IF(B$3>=Phases!$C$2+Phases!$D$2,MIN(Phases!$B$2,Phases!$B$2*Phases!$I$2+Phases!$B$2*(1-Phases!$I$2)*MIN(1,(B$3-Phases!$C$2-Phases!$D$2+1)/Phases!$H$2)),0) -> 0 | C6: =IF(C$3>=Phases!$C$2+Phases!$D$2,MIN(Phases!$B$2,Phases!$B$2*Phases!$I$2+Phases!$B$2*(1-Phases!$I$2)*MIN(1,(C$3-Phases!$C$2-Phases!$D$2+1)/Phases!$H$2)),0) -> 0 | D6: =IF(D$3>=Phases!$C$2+Phases!$D$2,MIN(Phases!$B$2,Phases!$B$2*Phases!$I$2+Phases!$B$2*(1-Phases!$I$2)*MIN(1,(D$3-Phases!$C$2-Phases!$D$2+1)/Phases!$H$2)),0) -> 0 | E6: =IF(E$3>=Phases!$C$2+Phases!$D$2,MIN(Phases!$B$2,Phases!$B$2*Phases!$I$2+Phases!$B$2*(1-Phases!$I$2)*MIN(1,(E$3-Phases!$C$2-Phases!$D$2+1)/Phases!$H$2)),0) -> 0 | F6: =IF(F$3>=Phases!$C$2+Phases!$D$2,MIN(Phases!$B$2,Phases!$B$2*Phases!$I$2+Phases!$B$2*(1-Phases!$I$2)*MIN(1,(F$3-Phases!$C$2-Phases!$D$2+1)/Phases!$H$2)),0) -> 0 | G6: =IF(G$3>=Phases!$C$2+Phases!$D$2,MIN(Phases!$B$2,Phases!$B$2*Phases!$I$2+Phases!$B$2*(1-Phases!$I$2)*MIN(1,(G$3-Phases!$C$2-Phases!$D$2+1)/Phases!$H$2)),0) -> 0 | H6: =IF(H$3>=Phases!$C$2+Phases!$D$2,MIN(Phases!$B$2,Phases!$B$2*Phases!$I$2+Phases!$B$2*(1-Phases!$I$2)*MIN(1,(H$3-Phases!$C$2-Phases!$D$2+1)/Phases!$H$2)),0) -> 0 | I6: =IF(I$3>=Phases!$C$2+Phases!$D$2,MIN(Phases!$B$2,Phases!$B$2*Phases!$I$2+Phases!$B$2*(1-Phases!$I$2)*MIN(1,(I$3-Phases!$C$2-Phases!$D$2+1)/Phases!$H$2)),0) -> 0 | ... AP6: =IF(AP$3>=Phases!$C$2+Phases!$D$2,MIN(Phases!$B$2,Phases!$B$2*Phases!$I$2+Phases!$B$2*(1-Phases!$I$2)*MIN(1,(AP$3-Phases!$C$2-Phases!$D$2+1)/Phases!$H$2)),0) -> 24
A7: P1 rent | B7: =IF(B$3>=Phases!$C$2+Phases!$D$2,B6*1000*Inputs!$B$28*3*(1+Inputs!$B$10)^INT((B$3-Phases!$C$2-Phases!$D$2)/4),0) -> 0 | C7: =IF(C$3>=Phases!$C$2+Phases!$D$2,C6*1000*Inputs!$B$28*3*(1+Inputs!$B$10)^INT((C$3-Phases!$C$2-Phases!$D$2)/4),0) -> 0 | D7: =IF(D$3>=Phases!$C$2+Phases!$D$2,D6*1000*Inputs!$B$28*3*(1+Inputs!$B$10)^INT((D$3-Phases!$C$2-Phases!$D$2)/4),0) -> 0 | E7: =IF(E$3>=Phases!$C$2+Phases!$D$2,E6*1000*Inputs!$B$28*3*(1+Inputs!$B$10)^INT((E$3-Phases!$C$2-Phases!$D$2)/4),0) -> 0 | F7: =IF(F$3>=Phases!$C$2+Phases!$D$2,F6*1000*Inputs!$B$28*3*(1+Inputs!$B$10)^INT((F$3-Phases!$C$2-Phases!$D$2)/4),0) -> 0 | G7: =IF(G$3>=Phases!$C$2+Phases!$D$2,G6*1000*Inputs!$B$28*3*(1+Inputs!$B$10)^INT((G$3-Phases!$C$2-Phases!$D$2)/4),0) -> 0 | H7: =IF(H$3>=Phases!$C$2+Phases!$D$2,H6*1000*Inputs!$B$28*3*(1+Inputs!$B$10)^INT((H$3-Phases!$C$2-Phases!$D$2)/4),0) -> 0 | I7: =IF(I$3>=Phases!$C$2+Phases!$D$2,I6*1000*Inputs!$B$28*3*(1+Inputs!$B$10)^INT((I$3-Phases!$C$2-Phases!$D$2)/4),0) -> 0 | ... AP7: =IF(AP$3>=Phases!$C$2+Phases!$D$2,AP6*1000*Inputs!$B$28*3*(1+Inputs!$B$10)^INT((AP$3-Phases!$C$2-Phases!$D$2)/4),0) -> 10351551
A8: P2 capex | B8: =IF(AND(B$3>=Phases!$C$3,B$3<Phases!$C$3+Phases!$D$3),Phases!$B$3*Inputs!$B$5*(1+Inputs!$B$6)^INT((Phases!$C$3-1)/4)/Phases!$D$3,0) -> 0 | C8: =IF(AND(C$3>=Phases!$C$3,C$3<Phases!$C$3+Phases!$D$3),Phases!$B$3*Inputs!$B$5*(1+Inputs!$B$6)^INT((Phases!$C$3-1)/4)/Phases!$D$3,0) -> 0 | D8: =IF(AND(D$3>=Phases!$C$3,D$3<Phases!$C$3+Phases!$D$3),Phases!$B$3*Inputs!$B$5*(1+Inputs!$B$6)^INT((Phases!$C$3-1)/4)/Phases!$D$3,0) -> 0 | E8: =IF(AND(E$3>=Phases!$C$3,E$3<Phases!$C$3+Phases!$D$3),Phases!$B$3*Inputs!$B$5*(1+Inputs!$B$6)^INT((Phases!$C$3-1)/4)/Phases!$D$3,0) -> 0 | F8: =IF(AND(F$3>=Phases!$C$3,F$3<Phases!$C$3+Phases!$D$3),Phases!$B$3*Inputs!$B$5*(1+Inputs!$B$6)^INT((Phases!$C$3-1)/4)/Phases!$D$3,0) -> 0 | G8: =IF(AND(G$3>=Phases!$C$3,G$3<Phases!$C$3+Phases!$D$3),Phases!$B$3*Inputs!$B$5*(1+Inputs!$B$6)^INT((Phases!$C$3-1)/4)/Phases!$D$3,0) -> 0 | H8: =IF(AND(H$3>=Phases!$C$3,H$3<Phases!$C$3+Phases!$D$3),Phases!$B$3*Inputs!$B$5*(1+Inputs!$B$6)^INT((Phases!$C$3-1)/4)/Phases!$D$3,0) -> 47380000 | I8: =IF(AND(I$3>=Phases!$C$3,I$3<Phases!$C$3+Phases!$D$3),Phases!$B$3*Inputs!$B$5*(1+Inputs!$B$6)^INT((Phases!$C$3-1)/4)/Phases!$D$3,0) -> 47380000 | ... AP8: =IF(AND(AP$3>=Phases!$C$3,AP$3<Phases!$C$3+Phases!$D$3),Phases!$B$3*Inputs!$B$5*(1+Inputs!$B$6)^INT((Phases!$C$3-1)/4)/Phases!$D$3,0) -> 0
A9: P2 leased MW | B9: =IF(B$3>=Phases!$C$3+Phases!$D$3,MIN(Phases!$B$3,Phases!$B$3*Phases!$I$3+Phases!$B$3*(1-Phases!$I$3)*MIN(1,(B$3-Phases!$C$3-Phases!$D$3+1)/Phases!$H$3)),0) -> 0 | C9: =IF(C$3>=Phases!$C$3+Phases!$D$3,MIN(Phases!$B$3,Phases!$B$3*Phases!$I$3+Phases!$B$3*(1-Phases!$I$3)*MIN(1,(C$3-Phases!$C$3-Phases!$D$3+1)/Phases!$H$3)),0) -> 0 | D9: =IF(D$3>=Phases!$C$3+Phases!$D$3,MIN(Phases!$B$3,Phases!$B$3*Phases!$I$3+Phases!$B$3*(1-Phases!$I$3)*MIN(1,(D$3-Phases!$C$3-Phases!$D$3+1)/Phases!$H$3)),0) -> 0 | E9: =IF(E$3>=Phases!$C$3+Phases!$D$3,MIN(Phases!$B$3,Phases!$B$3*Phases!$I$3+Phases!$B$3*(1-Phases!$I$3)*MIN(1,(E$3-Phases!$C$3-Phases!$D$3+1)/Phases!$H$3)),0) -> 0 | F9: =IF(F$3>=Phases!$C$3+Phases!$D$3,MIN(Phases!$B$3,Phases!$B$3*Phases!$I$3+Phases!$B$3*(1-Phases!$I$3)*MIN(1,(F$3-Phases!$C$3-Phases!$D$3+1)/Phases!$H$3)),0) -> 0 | G9: =IF(G$3>=Phases!$C$3+Phases!$D$3,MIN(Phases!$B$3,Phases!$B$3*Phases!$I$3+Phases!$B$3*(1-Phases!$I$3)*MIN(1,(G$3-Phases!$C$3-Phases!$D$3+1)/Phases!$H$3)),0) -> 0 | H9: =IF(H$3>=Phases!$C$3+Phases!$D$3,MIN(Phases!$B$3,Phases!$B$3*Phases!$I$3+Phases!$B$3*(1-Phases!$I$3)*MIN(1,(H$3-Phases!$C$3-Phases!$D$3+1)/Phases!$H$3)),0) -> 0 | I9: =IF(I$3>=Phases!$C$3+Phases!$D$3,MIN(Phases!$B$3,Phases!$B$3*Phases!$I$3+Phases!$B$3*(1-Phases!$I$3)*MIN(1,(I$3-Phases!$C$3-Phases!$D$3+1)/Phases!$H$3)),0) -> 0 | ... AP9: =IF(AP$3>=Phases!$C$3+Phases!$D$3,MIN(Phases!$B$3,Phases!$B$3*Phases!$I$3+Phases!$B$3*(1-Phases!$I$3)*MIN(1,(AP$3-Phases!$C$3-Phases!$D$3+1)/Phases!$H$3)),0) -> 32
A10: P2 rent | B10: =IF(B$3>=Phases!$C$3+Phases!$D$3,B9*1000*Inputs!$B$28*3*(1+Inputs!$B$10)^INT((B$3-Phases!$C$3-Phases!$D$3)/4),0) -> 0 | C10: =IF(C$3>=Phases!$C$3+Phases!$D$3,C9*1000*Inputs!$B$28*3*(1+Inputs!$B$10)^INT((C$3-Phases!$C$3-Phases!$D$3)/4),0) -> 0 | D10: =IF(D$3>=Phases!$C$3+Phases!$D$3,D9*1000*Inputs!$B$28*3*(1+Inputs!$B$10)^INT((D$3-Phases!$C$3-Phases!$D$3)/4),0) -> 0 | E10: =IF(E$3>=Phases!$C$3+Phases!$D$3,E9*1000*Inputs!$B$28*3*(1+Inputs!$B$10)^INT((E$3-Phases!$C$3-Phases!$D$3)/4),0) -> 0 | F10: =IF(F$3>=Phases!$C$3+Phases!$D$3,F9*1000*Inputs!$B$28*3*(1+Inputs!$B$10)^INT((F$3-Phases!$C$3-Phases!$D$3)/4),0) -> 0 | G10: =IF(G$3>=Phases!$C$3+Phases!$D$3,G9*1000*Inputs!$B$28*3*(1+Inputs!$B$10)^INT((G$3-Phases!$C$3-Phases!$D$3)/4),0) -> 0 | H10: =IF(H$3>=Phases!$C$3+Phases!$D$3,H9*1000*Inputs!$B$28*3*(1+Inputs!$B$10)^INT((H$3-Phases!$C$3-Phases!$D$3)/4),0) -> 0 | I10: =IF(I$3>=Phases!$C$3+Phases!$D$3,I9*1000*Inputs!$B$28*3*(1+Inputs!$B$10)^INT((I$3-Phases!$C$3-Phases!$D$3)/4),0) -> 0 | ... AP10: =IF(AP$3>=Phases!$C$3+Phases!$D$3,AP9*1000*Inputs!$B$28*3*(1+Inputs!$B$10)^INT((AP$3-Phases!$C$3-Phases!$D$3)/4),0) -> 13137007
A11: P3 capex | B11: =IF(AND(B$3>=Phases!$C$4,B$3<Phases!$C$4+Phases!$D$4),Phases!$B$4*Inputs!$B$5*(1+Inputs!$B$6)^INT((Phases!$C$4-1)/4)/Phases!$D$4,0) -> 0 | C11: =IF(AND(C$3>=Phases!$C$4,C$3<Phases!$C$4+Phases!$D$4),Phases!$B$4*Inputs!$B$5*(1+Inputs!$B$6)^INT((Phases!$C$4-1)/4)/Phases!$D$4,0) -> 0 | D11: =IF(AND(D$3>=Phases!$C$4,D$3<Phases!$C$4+Phases!$D$4),Phases!$B$4*Inputs!$B$5*(1+Inputs!$B$6)^INT((Phases!$C$4-1)/4)/Phases!$D$4,0) -> 0 | E11: =IF(AND(E$3>=Phases!$C$4,E$3<Phases!$C$4+Phases!$D$4),Phases!$B$4*Inputs!$B$5*(1+Inputs!$B$6)^INT((Phases!$C$4-1)/4)/Phases!$D$4,0) -> 0 | F11: =IF(AND(F$3>=Phases!$C$4,F$3<Phases!$C$4+Phases!$D$4),Phases!$B$4*Inputs!$B$5*(1+Inputs!$B$6)^INT((Phases!$C$4-1)/4)/Phases!$D$4,0) -> 0 | G11: =IF(AND(G$3>=Phases!$C$4,G$3<Phases!$C$4+Phases!$D$4),Phases!$B$4*Inputs!$B$5*(1+Inputs!$B$6)^INT((Phases!$C$4-1)/4)/Phases!$D$4,0) -> 0 | H11: =IF(AND(H$3>=Phases!$C$4,H$3<Phases!$C$4+Phases!$D$4),Phases!$B$4*Inputs!$B$5*(1+Inputs!$B$6)^INT((Phases!$C$4-1)/4)/Phases!$D$4,0) -> 0 | I11: =IF(AND(I$3>=Phases!$C$4,I$3<Phases!$C$4+Phases!$D$4),Phases!$B$4*Inputs!$B$5*(1+Inputs!$B$6)^INT((Phases!$C$4-1)/4)/Phases!$D$4,0) -> 0 | ... AP11: =IF(AND(AP$3>=Phases!$C$4,AP$3<Phases!$C$4+Phases!$D$4),Phases!$B$4*Inputs!$B$5*(1+Inputs!$B$6)^INT((Phases!$C$4-1)/4)/Phases!$D$4,0) -> 0
A12: P3 leased MW | B12: =IF(B$3>=Phases!$C$4+Phases!$D$4,MIN(Phases!$B$4,Phases!$B$4*Phases!$I$4+Phases!$B$4*(1-Phases!$I$4)*MIN(1,(B$3-Phases!$C$4-Phases!$D$4+1)/Phases!$H$4)),0) -> 0 | C12: =IF(C$3>=Phases!$C$4+Phases!$D$4,MIN(Phases!$B$4,Phases!$B$4*Phases!$I$4+Phases!$B$4*(1-Phases!$I$4)*MIN(1,(C$3-Phases!$C$4-Phases!$D$4+1)/Phases!$H$4)),0) -> 0 | D12: =IF(D$3>=Phases!$C$4+Phases!$D$4,MIN(Phases!$B$4,Phases!$B$4*Phases!$I$4+Phases!$B$4*(1-Phases!$I$4)*MIN(1,(D$3-Phases!$C$4-Phases!$D$4+1)/Phases!$H$4)),0) -> 0 | E12: =IF(E$3>=Phases!$C$4+Phases!$D$4,MIN(Phases!$B$4,Phases!$B$4*Phases!$I$4+Phases!$B$4*(1-Phases!$I$4)*MIN(1,(E$3-Phases!$C$4-Phases!$D$4+1)/Phases!$H$4)),0) -> 0 | F12: =IF(F$3>=Phases!$C$4+Phases!$D$4,MIN(Phases!$B$4,Phases!$B$4*Phases!$I$4+Phases!$B$4*(1-Phases!$I$4)*MIN(1,(F$3-Phases!$C$4-Phases!$D$4+1)/Phases!$H$4)),0) -> 0 | G12: =IF(G$3>=Phases!$C$4+Phases!$D$4,MIN(Phases!$B$4,Phases!$B$4*Phases!$I$4+Phases!$B$4*(1-Phases!$I$4)*MIN(1,(G$3-Phases!$C$4-Phases!$D$4+1)/Phases!$H$4)),0) -> 0 | H12: =IF(H$3>=Phases!$C$4+Phases!$D$4,MIN(Phases!$B$4,Phases!$B$4*Phases!$I$4+Phases!$B$4*(1-Phases!$I$4)*MIN(1,(H$3-Phases!$C$4-Phases!$D$4+1)/Phases!$H$4)),0) -> 0 | I12: =IF(I$3>=Phases!$C$4+Phases!$D$4,MIN(Phases!$B$4,Phases!$B$4*Phases!$I$4+Phases!$B$4*(1-Phases!$I$4)*MIN(1,(I$3-Phases!$C$4-Phases!$D$4+1)/Phases!$H$4)),0) -> 0 | ... AP12: =IF(AP$3>=Phases!$C$4+Phases!$D$4,MIN(Phases!$B$4,Phases!$B$4*Phases!$I$4+Phases!$B$4*(1-Phases!$I$4)*MIN(1,(AP$3-Phases!$C$4-Phases!$D$4+1)/Phases!$H$4)),0) -> 40
A13: P3 rent | B13: =IF(B$3>=Phases!$C$4+Phases!$D$4,B12*1000*Inputs!$B$28*3*(1+Inputs!$B$10)^INT((B$3-Phases!$C$4-Phases!$D$4)/4),0) -> 0 | C13: =IF(C$3>=Phases!$C$4+Phases!$D$4,C12*1000*Inputs!$B$28*3*(1+Inputs!$B$10)^INT((C$3-Phases!$C$4-Phases!$D$4)/4),0) -> 0 | D13: =IF(D$3>=Phases!$C$4+Phases!$D$4,D12*1000*Inputs!$B$28*3*(1+Inputs!$B$10)^INT((D$3-Phases!$C$4-Phases!$D$4)/4),0) -> 0 | E13: =IF(E$3>=Phases!$C$4+Phases!$D$4,E12*1000*Inputs!$B$28*3*(1+Inputs!$B$10)^INT((E$3-Phases!$C$4-Phases!$D$4)/4),0) -> 0 | F13: =IF(F$3>=Phases!$C$4+Phases!$D$4,F12*1000*Inputs!$B$28*3*(1+Inputs!$B$10)^INT((F$3-Phases!$C$4-Phases!$D$4)/4),0) -> 0 | G13: =IF(G$3>=Phases!$C$4+Phases!$D$4,G12*1000*Inputs!$B$28*3*(1+Inputs!$B$10)^INT((G$3-Phases!$C$4-Phases!$D$4)/4),0) -> 0 | H13: =IF(H$3>=Phases!$C$4+Phases!$D$4,H12*1000*Inputs!$B$28*3*(1+Inputs!$B$10)^INT((H$3-Phases!$C$4-Phases!$D$4)/4),0) -> 0 | I13: =IF(I$3>=Phases!$C$4+Phases!$D$4,I12*1000*Inputs!$B$28*3*(1+Inputs!$B$10)^INT((I$3-Phases!$C$4-Phases!$D$4)/4),0) -> 0 | ... AP13: =IF(AP$3>=Phases!$C$4+Phases!$D$4,AP12*1000*Inputs!$B$28*3*(1+Inputs!$B$10)^INT((AP$3-Phases!$C$4-Phases!$D$4)/4),0) -> 15629991
A14: Capex | B14: =IF(B$3<=Inputs!$B$23,B5+B8+B11,0) -> 0 | C14: =IF(C$3<=Inputs!$B$23,C5+C8+C11,0) -> 39428571 | D14: =IF(D$3<=Inputs!$B$23,D5+D8+D11,0) -> 39428571 | E14: =IF(E$3<=Inputs!$B$23,E5+E8+E11,0) -> 39428571 | F14: =IF(F$3<=Inputs!$B$23,F5+F8+F11,0) -> 39428571 | G14: =IF(G$3<=Inputs!$B$23,G5+G8+G11,0) -> 39428571 | H14: =IF(H$3<=Inputs!$B$23,H5+H8+H11,0) -> 86808571 | I14: =IF(I$3<=Inputs!$B$23,I5+I8+I11,0) -> 86808571 | ... AP14: =IF(AP$3<=Inputs!$B$23,AP5+AP8+AP11,0) -> 0
A15: MW built | B15: =IF(B$3>=Phases!$C$2+Phases!$D$2,Phases!$B$2,0)+IF(B$3>=Phases!$C$3+Phases!$D$3,Phases!$B$3,0)+IF(B$3>=Phases!$C$4+Phases!$D$4,Phases!$B$4,0) -> 0 | C15: =IF(C$3>=Phases!$C$2+Phases!$D$2,Phases!$B$2,0)+IF(C$3>=Phases!$C$3+Phases!$D$3,Phases!$B$3,0)+IF(C$3>=Phases!$C$4+Phases!$D$4,Phases!$B$4,0) -> 0 | D15: =IF(D$3>=Phases!$C$2+Phases!$D$2,Phases!$B$2,0)+IF(D$3>=Phases!$C$3+Phases!$D$3,Phases!$B$3,0)+IF(D$3>=Phases!$C$4+Phases!$D$4,Phases!$B$4,0) -> 0 | E15: =IF(E$3>=Phases!$C$2+Phases!$D$2,Phases!$B$2,0)+IF(E$3>=Phases!$C$3+Phases!$D$3,Phases!$B$3,0)+IF(E$3>=Phases!$C$4+Phases!$D$4,Phases!$B$4,0) -> 0 | F15: =IF(F$3>=Phases!$C$2+Phases!$D$2,Phases!$B$2,0)+IF(F$3>=Phases!$C$3+Phases!$D$3,Phases!$B$3,0)+IF(F$3>=Phases!$C$4+Phases!$D$4,Phases!$B$4,0) -> 0 | G15: =IF(G$3>=Phases!$C$2+Phases!$D$2,Phases!$B$2,0)+IF(G$3>=Phases!$C$3+Phases!$D$3,Phases!$B$3,0)+IF(G$3>=Phases!$C$4+Phases!$D$4,Phases!$B$4,0) -> 0 | H15: =IF(H$3>=Phases!$C$2+Phases!$D$2,Phases!$B$2,0)+IF(H$3>=Phases!$C$3+Phases!$D$3,Phases!$B$3,0)+IF(H$3>=Phases!$C$4+Phases!$D$4,Phases!$B$4,0) -> 0 | I15: =IF(I$3>=Phases!$C$2+Phases!$D$2,Phases!$B$2,0)+IF(I$3>=Phases!$C$3+Phases!$D$3,Phases!$B$3,0)+IF(I$3>=Phases!$C$4+Phases!$D$4,Phases!$B$4,0) -> 0 | ... AP15: =IF(AP$3>=Phases!$C$2+Phases!$D$2,Phases!$B$2,0)+IF(AP$3>=Phases!$C$3+Phases!$D$3,Phases!$B$3,0)+IF(AP$3>=Phases!$C$4+Phases!$D$4,Phases!$B$4,0) -> 96
A16: Leased MW | B16: =B6+B9+B12 -> 0 | C16: =C6+C9+C12 -> 0 | D16: =D6+D9+D12 -> 0 | E16: =E6+E9+E12 -> 0 | F16: =F6+F9+F12 -> 0 | G16: =G6+G9+G12 -> 0 | H16: =H6+H9+H12 -> 0 | I16: =I6+I9+I12 -> 0 | ... AP16: =AP6+AP9+AP12 -> 96
A17: Occupancy | B17: =IF(B15>0,B16/B15,0) -> 0 | C17: =IF(C15>0,C16/C15,0) -> 0 | D17: =IF(D15>0,D16/D15,0) -> 0 | E17: =IF(E15>0,E16/E15,0) -> 0 | F17: =IF(F15>0,F16/F15,0) -> 0 | G17: =IF(G15>0,G16/G15,0) -> 0 | H17: =IF(H15>0,H16/H15,0) -> 0 | I17: =IF(I15>0,I16/I15,0) -> 0 | ... AP17: =IF(AP15>0,AP16/AP15,0) -> 1
A18: Rent | B18: =B7+B10+B13 -> 0 | C18: =C7+C10+C13 -> 0 | D18: =D7+D10+D13 -> 0 | E18: =E7+E10+E13 -> 0 | F18: =F7+F10+F13 -> 0 | G18: =G7+G10+G13 -> 0 | H18: =H7+H10+H13 -> 0 | I18: =I7+I10+I13 -> 0 | ... AP18: =AP7+AP10+AP13 -> 39118549
A19: Power cost | B19: =B16*Inputs!$B$13*Inputs!$B$11*2190*Inputs!$B$12 -> 0 | C19: =C16*Inputs!$B$13*Inputs!$B$11*2190*Inputs!$B$12 -> 0 | D19: =D16*Inputs!$B$13*Inputs!$B$11*2190*Inputs!$B$12 -> 0 | E19: =E16*Inputs!$B$13*Inputs!$B$11*2190*Inputs!$B$12 -> 0 | F19: =F16*Inputs!$B$13*Inputs!$B$11*2190*Inputs!$B$12 -> 0 | G19: =G16*Inputs!$B$13*Inputs!$B$11*2190*Inputs!$B$12 -> 0 | H19: =H16*Inputs!$B$13*Inputs!$B$11*2190*Inputs!$B$12 -> 0 | I19: =I16*Inputs!$B$13*Inputs!$B$11*2190*Inputs!$B$12 -> 0 | ... AP19: =AP16*Inputs!$B$13*Inputs!$B$11*2190*Inputs!$B$12 -> 16887528
A20: Power recovered | B20: =B19*Inputs!$B$14 -> 0 | C20: =C19*Inputs!$B$14 -> 0 | D20: =D19*Inputs!$B$14 -> 0 | E20: =E19*Inputs!$B$14 -> 0 | F20: =F19*Inputs!$B$14 -> 0 | G20: =G19*Inputs!$B$14 -> 0 | H20: =H19*Inputs!$B$14 -> 0 | I20: =I19*Inputs!$B$14 -> 0 | ... AP20: =AP19*Inputs!$B$14 -> 15198775
A21: Other opex | B21: =B18*Inputs!$B$15 -> 0 | C21: =C18*Inputs!$B$15 -> 0 | D21: =D18*Inputs!$B$15 -> 0 | E21: =E18*Inputs!$B$15 -> 0 | F21: =F18*Inputs!$B$15 -> 0 | G21: =G18*Inputs!$B$15 -> 0 | H21: =H18*Inputs!$B$15 -> 0 | I21: =I18*Inputs!$B$15 -> 0 | ... AP21: =AP18*Inputs!$B$15 -> 3129483.9
A22: NOI | B22: =B18+B20-B19-B21 -> 0 | C22: =C18+C20-C19-C21 -> 0 | D22: =D18+D20-D19-D21 -> 0 | E22: =E18+E20-E19-E21 -> 0 | F22: =F18+F20-F19-F21 -> 0 | G22: =G18+G20-G19-G21 -> 0 | H22: =H18+H20-H19-H21 -> 0 | I22: =I18+I20-I19-I21 -> 0 | ... AP22: =AP18+AP20-AP19-AP21 -> 34300312
A23: Converted | B23: =0 -> 0 | C23: =IF(B23=1,1,IF(AND(C15>0,C17>=Inputs!$B$18),1,0)) -> 0 | D23: =IF(C23=1,1,IF(AND(D15>0,D17>=Inputs!$B$18),1,0)) -> 0 | E23: =IF(D23=1,1,IF(AND(E15>0,E17>=Inputs!$B$18),1,0)) -> 0 | F23: =IF(E23=1,1,IF(AND(F15>0,F17>=Inputs!$B$18),1,0)) -> 0 | G23: =IF(F23=1,1,IF(AND(G15>0,G17>=Inputs!$B$18),1,0)) -> 0 | H23: =IF(G23=1,1,IF(AND(H15>0,H17>=Inputs!$B$18),1,0)) -> 0 | I23: =IF(H23=1,1,IF(AND(I15>0,I17>=Inputs!$B$18),1,0)) -> 0 | J23: =IF(I23=1,1,IF(AND(J15>0,J17>=Inputs!$B$18),1,0)) -> 0 | ... AP23: =IF(AO23=1,1,IF(AND(AP15>0,AP17>=Inputs!$B$18),1,0)) -> 1
A24: Opening loan | B24: =0 -> 0 | C24: =B31 -> 0 | D24: =C31 -> 25628571 | E24: =D31 -> 51801750 | F24: =E31 -> 78531109 | G24: =F31 -> 1.0582847e+08 | H24: =G31 -> 1.3370589e+08 | I24: =H31 -> 1.9297271e+08 | J24: =I31 -> 2.5349896e+08 | ... AP24: =AO31 -> 0
A25: Loan draw | B25: =B14*Inputs!$B$16 -> 0 | C25: =C14*Inputs!$B$16 -> 25628571 | D25: =D14*Inputs!$B$16 -> 25628571 | E25: =E14*Inputs!$B$16 -> 25628571 | F25: =F14*Inputs!$B$16 -> 25628571 | G25: =G14*Inputs!$B$16 -> 25628571 | H25: =H14*Inputs!$B$16 -> 56425571 | I25: =I14*Inputs!$B$16 -> 56425571 | ... AP25: =AP14*Inputs!$B$16 -> 0
A26: Interest capitalised | B26: =IF(B23=0,B24*Inputs!$B$17/4,0) -> 0 | C26: =IF(C23=0,C24*Inputs!$B$17/4,0) -> 0 | D26: =IF(D23=0,D24*Inputs!$B$17/4,0) -> 544607.14 | E26: =IF(E23=0,E24*Inputs!$B$17/4,0) -> 1100787.2 | F26: =IF(F23=0,F24*Inputs!$B$17/4,0) -> 1668786.1 | G26: =IF(G23=0,G24*Inputs!$B$17/4,0) -> 2248854.9 | H26: =IF(H23=0,H24*Inputs!$B$17/4,0) -> 2841250.2 | I26: =IF(I23=0,I24*Inputs!$B$17/4,0) -> 4100670.2 | ... AP26: =IF(AP23=0,AP24*Inputs!$B$17/4,0) -> 0
A27: Interest paid | B27: =IF(B23=1,B24*Inputs!$B$19/4,0) -> 0 | C27: =IF(C23=1,C24*Inputs!$B$19/4,0) -> 0 | D27: =IF(D23=1,D24*Inputs!$B$19/4,0) -> 0 | E27: =IF(E23=1,E24*Inputs!$B$19/4,0) -> 0 | F27: =IF(F23=1,F24*Inputs!$B$19/4,0) -> 0 | G27: =IF(G23=1,G24*Inputs!$B$19/4,0) -> 0 | H27: =IF(H23=1,H24*Inputs!$B$19/4,0) -> 0 | I27: =IF(I23=1,I24*Inputs!$B$19/4,0) -> 0 | ... AP27: =IF(AP23=1,AP24*Inputs!$B$19/4,0) -> 0
A28: Amortisation | B28: =IF(B23=1,MIN(B24,B24*Inputs!$B$20/4),0) -> 0 | C28: =IF(C23=1,MIN(C24,C24*Inputs!$B$20/4),0) -> 0 | D28: =IF(D23=1,MIN(D24,D24*Inputs!$B$20/4),0) -> 0 | E28: =IF(E23=1,MIN(E24,E24*Inputs!$B$20/4),0) -> 0 | F28: =IF(F23=1,MIN(F24,F24*Inputs!$B$20/4),0) -> 0 | G28: =IF(G23=1,MIN(G24,G24*Inputs!$B$20/4),0) -> 0 | H28: =IF(H23=1,MIN(H24,H24*Inputs!$B$20/4),0) -> 0 | I28: =IF(I23=1,MIN(I24,I24*Inputs!$B$20/4),0) -> 0 | ... AP28: =IF(AP23=1,MIN(AP24,AP24*Inputs!$B$20/4),0) -> 0
A29: DSCR | B29: =IF(B27+B28>0,B22/(B27+B28),0) -> 0 | C29: =IF(C27+C28>0,C22/(C27+C28),0) -> 0 | D29: =IF(D27+D28>0,D22/(D27+D28),0) -> 0 | E29: =IF(E27+E28>0,E22/(E27+E28),0) -> 0 | F29: =IF(F27+F28>0,F22/(F27+F28),0) -> 0 | G29: =IF(G27+G28>0,G22/(G27+G28),0) -> 0 | H29: =IF(H27+H28>0,H22/(H27+H28),0) -> 0 | I29: =IF(I27+I28>0,I22/(I27+I28),0) -> 0 | ... AP29: =IF(AP27+AP28>0,AP22/(AP27+AP28),0) -> 0
A30: Cash sweep | B30: =IF(AND(B23=1,B$3<Inputs!$B$23),MIN(B24-B28,MAX(0,B22-(B27+B28)*Inputs!$B$21)*Inputs!$B$22),0) -> 0 | C30: =IF(AND(C23=1,C$3<Inputs!$B$23),MIN(C24-C28,MAX(0,C22-(C27+C28)*Inputs!$B$21)*Inputs!$B$22),0) -> 0 | D30: =IF(AND(D23=1,D$3<Inputs!$B$23),MIN(D24-D28,MAX(0,D22-(D27+D28)*Inputs!$B$21)*Inputs!$B$22),0) -> 0 | E30: =IF(AND(E23=1,E$3<Inputs!$B$23),MIN(E24-E28,MAX(0,E22-(E27+E28)*Inputs!$B$21)*Inputs!$B$22),0) -> 0 | F30: =IF(AND(F23=1,F$3<Inputs!$B$23),MIN(F24-F28,MAX(0,F22-(F27+F28)*Inputs!$B$21)*Inputs!$B$22),0) -> 0 | G30: =IF(AND(G23=1,G$3<Inputs!$B$23),MIN(G24-G28,MAX(0,G22-(G27+G28)*Inputs!$B$21)*Inputs!$B$22),0) -> 0 | H30: =IF(AND(H23=1,H$3<Inputs!$B$23),MIN(H24-H28,MAX(0,H22-(H27+H28)*Inputs!$B$21)*Inputs!$B$22),0) -> 0 | I30: =IF(AND(I23=1,I$3<Inputs!$B$23),MIN(I24-I28,MAX(0,I22-(I27+I28)*Inputs!$B$21)*Inputs!$B$22),0) -> 0 | ... AP30: =IF(AND(AP23=1,AP$3<Inputs!$B$23),MIN(AP24-AP28,MAX(0,AP22-(AP27+AP28)*Inputs!$B$21)*Inputs!$B$22),0) -> 0
A31: Loan balance | B31: =IF(B$3>=Inputs!$B$23,0,B24+B25+B26-B28-B30) -> 0 | C31: =IF(C$3>=Inputs!$B$23,0,C24+C25+C26-C28-C30) -> 25628571 | D31: =IF(D$3>=Inputs!$B$23,0,D24+D25+D26-D28-D30) -> 51801750 | E31: =IF(E$3>=Inputs!$B$23,0,E24+E25+E26-E28-E30) -> 78531109 | F31: =IF(F$3>=Inputs!$B$23,0,F24+F25+F26-F28-F30) -> 1.0582847e+08 | G31: =IF(G$3>=Inputs!$B$23,0,G24+G25+G26-G28-G30) -> 1.3370589e+08 | H31: =IF(H$3>=Inputs!$B$23,0,H24+H25+H26-H28-H30) -> 1.9297271e+08 | I31: =IF(I$3>=Inputs!$B$23,0,I24+I25+I26-I28-I30) -> 2.5349896e+08 | ... AP31: =IF(AP$3>=Inputs!$B$23,0,AP24+AP25+AP26-AP28-AP30) -> 0
A32: Sale | B32: =IF(B$3=Inputs!$B$23,C22*4/Inputs!$B$29,0) -> 0 | C32: =IF(C$3=Inputs!$B$23,D22*4/Inputs!$B$29,0) -> 0 | D32: =IF(D$3=Inputs!$B$23,E22*4/Inputs!$B$29,0) -> 0 | E32: =IF(E$3=Inputs!$B$23,F22*4/Inputs!$B$29,0) -> 0 | F32: =IF(F$3=Inputs!$B$23,G22*4/Inputs!$B$29,0) -> 0 | G32: =IF(G$3=Inputs!$B$23,H22*4/Inputs!$B$29,0) -> 0 | H32: =IF(H$3=Inputs!$B$23,I22*4/Inputs!$B$29,0) -> 0 | I32: =IF(I$3=Inputs!$B$23,J22*4/Inputs!$B$29,0) -> 0 | ... AO32: =IF(AO$3=Inputs!$B$23,AP22*4/Inputs!$B$29,0) -> 0 | AP32: =IF(AP$3=Inputs!$B$23,AP22*4/Inputs!$B$29,0) -> 0
A33: Loan repaid at sale | B33: =IF(B$3=Inputs!$B$23,B24+B25+B26-B28,0) -> 0 | C33: =IF(C$3=Inputs!$B$23,C24+C25+C26-C28,0) -> 0 | D33: =IF(D$3=Inputs!$B$23,D24+D25+D26-D28,0) -> 0 | E33: =IF(E$3=Inputs!$B$23,E24+E25+E26-E28,0) -> 0 | F33: =IF(F$3=Inputs!$B$23,F24+F25+F26-F28,0) -> 0 | G33: =IF(G$3=Inputs!$B$23,G24+G25+G26-G28,0) -> 0 | H33: =IF(H$3=Inputs!$B$23,H24+H25+H26-H28,0) -> 0 | I33: =IF(I$3=Inputs!$B$23,I24+I25+I26-I28,0) -> 0 | ... AP33: =IF(AP$3=Inputs!$B$23,AP24+AP25+AP26-AP28,0) -> 0
A34: Equity in | B34: =B14*(1-Inputs!$B$16) -> 0 | C34: =C14*(1-Inputs!$B$16) -> 13800000 | D34: =D14*(1-Inputs!$B$16) -> 13800000 | E34: =E14*(1-Inputs!$B$16) -> 13800000 | F34: =F14*(1-Inputs!$B$16) -> 13800000 | G34: =G14*(1-Inputs!$B$16) -> 13800000 | H34: =H14*(1-Inputs!$B$16) -> 30383000 | I34: =I14*(1-Inputs!$B$16) -> 30383000 | ... AP34: =AP14*(1-Inputs!$B$16) -> 0
A35: Equity cash flow | B35: =IF(B$3>Inputs!$B$23,0,-B34+B22-B27-B28-B30+B32-B33) -> 0 | C35: =IF(C$3>Inputs!$B$23,0,-C34+C22-C27-C28-C30+C32-C33) -> -13800000 | D35: =IF(D$3>Inputs!$B$23,0,-D34+D22-D27-D28-D30+D32-D33) -> -13800000 | E35: =IF(E$3>Inputs!$B$23,0,-E34+E22-E27-E28-E30+E32-E33) -> -13800000 | F35: =IF(F$3>Inputs!$B$23,0,-F34+F22-F27-F28-F30+F32-F33) -> -13800000 | G35: =IF(G$3>Inputs!$B$23,0,-G34+G22-G27-G28-G30+G32-G33) -> -13800000 | H35: =IF(H$3>Inputs!$B$23,0,-H34+H22-H27-H28-H30+H32-H33) -> -30383000 | I35: =IF(I$3>Inputs!$B$23,0,-I34+I22-I27-I28-I30+I32-I33) -> -30383000 | ... AP35: =IF(AP$3>Inputs!$B$23,0,-AP34+AP22-AP27-AP28-AP30+AP32-AP33) -> 0
A36: Project cash flow | B36: =IF(B$3>Inputs!$B$23,0,-B14+B22+B32) -> 0 | C36: =IF(C$3>Inputs!$B$23,0,-C14+C22+C32) -> -39428571 | D36: =IF(D$3>Inputs!$B$23,0,-D14+D22+D32) -> -39428571 | E36: =IF(E$3>Inputs!$B$23,0,-E14+E22+E32) -> -39428571 | F36: =IF(F$3>Inputs!$B$23,0,-F14+F22+F32) -> -39428571 | G36: =IF(G$3>Inputs!$B$23,0,-G14+G22+G32) -> -39428571 | H36: =IF(H$3>Inputs!$B$23,0,-H14+H22+H32) -> -86808571 | I36: =IF(I$3>Inputs!$B$23,0,-I14+I22+I32) -> -86808571 | ... AP36: =IF(AP$3>Inputs!$B$23,0,-AP14+AP22+AP32) -> 0

Sheet Returns
A3: Levered IRR | B3: =(1+IRR('Cash Flow'!$B$35:$AP$35,0.03))^4-1 -> 0.27479643
A4: Project IRR | B4: =(1+IRR('Cash Flow'!$B$36:$AP$36,0.02))^4-1 -> 0.16908663
A5: Equity multiple | B5: =SUMIF('Cash Flow'!$B$35:$AP$35,">0")/-SUMIF('Cash Flow'!$B$35:$AP$35,"<0") -> 4.5683626
A6: Peak debt ($) | B6: =MAX('Cash Flow'!$B$31:$AP$31) -> 7.5638403e+08
A7: Minimum DSCR (after conversion) | B7: =_xlfn.MINIFS('Cash Flow'!$B$29:$AP$29,'Cash Flow'!$B$29:$AP$29,">0") -> 0.8527043
A8: Conversion quarter | B8: =IFERROR(MATCH(1,'Cash Flow'!$B$23:$AP$23,0)-1,"not reached") -> 11
A9: Total development cost ($) | B9: =SUM('Cash Flow'!$B$14:$AP$14) -> 1157694420
A10: Yield on cost (exit-year NOI) | B10: =INDEX('Cash Flow'!$B$22:$AP$22,Inputs!$B$23+1)*4/B9 -> 0.11547963
A11: Exit value ($) | B11: =SUM('Cash Flow'!$B$32:$AP$32) -> 2.1614881e+09
A12: Net profit ($) | B12: =SUM('Cash Flow'!$B$35:$AP$35) -> 1.3305714e+09
A13: Cash swept ($) | B13: =SUM('Cash Flow'!$B$30:$AP$30) -> 66991729
