Workbook

Sheet Inputs
A1: RAWDAT AL KHAIR COMMUNITY – OFF-PLAN WITH IJARA SUKUK (SAR)
A3: Model start | B3: 46387
A4: Villas | B4: 540
A5: Villa price (SAR) | B5: 2750000
A6: Apartments | B6: 880
A7: Apartment price (SAR) | B7: 1380000
A8: Buyer payment lag (quarters) | B8: 2
A9: Down payment | B9: 0.2
A10: Build (quarters) | B10: 14
A11: Villa build cost (SAR) | B11: 1350000
A12: Apartment build cost (SAR) | B12: 640000
A13: Infrastructure (SAR) | B13: 310000000
A14: Land (SAR) | B14: 450000000
... A20: Equity (SAR) | B20: 700000000

Sheet Sales Plan
A1: Quarter | B1: Villas sold | C1: Apartments sold
A2: 1 | B2: 30 | C2: 60
A3: 2 | B3: 40 | C3: 70
A4: 3 | B4: 45 | C4: 70
A5: 4 | B5: 45 | C5: 70
A6: 5 | B6: 45 | C6: 65
A7: 6 | B7: 40 | C7: 65
A8: 7 | B8: 40 | C8: 60
A9: 8 | B9: 35 | C9: 60
A10: 9 | B10: 35 | C10: 55
A11: 10 | B11: 30 | C11: 55
A12: 11 | B12: 30 | C12: 50
A13: 12 | B13: 30 | C13: 50
... A17: 16 | B17: 20 | C17: 30

Sheet Cash Flow
A3: Quarter | B3: 0 | C3: 1 | D3: 2 | E3: 3 | F3: 4 | G3: 5 | H3: 6 | I3: 7 | J3: 8 | K3: 9 | L3: 10 | M3: 11 | N3: 12 | O3: 13 | P3: 14 | Q3: 15 | R3: 16 | S3: 17 | T3: 18 | U3: 19 | V3: 20 | W3: 21 | X3: 22 | Y3: 23 | Z3: 24
A4: Date | B4: =EOMONTH(Inputs!$B$3,3*B$3) -> 46387 | C4: =EOMONTH(Inputs!$B$3,3*C$3) -> 46477 | D4: =EOMONTH(Inputs!$B$3,3*D$3) -> 46568 | E4: =EOMONTH(Inputs!$B$3,3*E$3) -> 46660 | F4: =EOMONTH(Inputs!$B$3,3*F$3) -> 46752 | G4: =EOMONTH(Inputs!$B$3,3*G$3) -> 46843 | H4: =EOMONTH(Inputs!$B$3,3*H$3) -> 46934 | I4: =EOMONTH(Inputs!$B$3,3*I$3) -> 47026 | ... Z4: =EOMONTH(Inputs!$B$3,3*Z$3) -> 48579
A5: Villas sold | B5: =IF(AND(B$3>=1,B$3<=16),INDEX('Sales Plan'!$B$2:$B$17,MAX(1,MIN(16,B$3))),0) -> 0 | C5: =IF(AND(C$3>=1,C$3<=16),INDEX('Sales Plan'!$B$2:$B$17,MAX(1,MIN(16,C$3))),0) -> 30 | D5: =IF(AND(D$3>=1,D$3<=16),INDEX('Sales Plan'!$B$2:$B$17,MAX(1,MIN(16,D$3))),0) -> 40 | E5: =IF(AND(E$3>=1,E$3<=16),INDEX('Sales Plan'!$B$2:$B$17,MAX(1,MIN(16,E$3))),0) -> 45 | F5: =IF(AND(F$3>=1,F$3<=16),INDEX('Sales Plan'!$B$2:$B$17,MAX(1,MIN(16,F$3))),0) -> 45 | G5: =IF(AND(G$3>=1,G$3<=16),INDEX('Sales Plan'!$B$2:$B$17,MAX(1,MIN(16,G$3))),0) -> 45 | H5: =IF(AND(H$3>=1,H$3<=16),INDEX('Sales Plan'!$B$2:$B$17,MAX(1,MIN(16,H$3))),0) -> 40 | I5: =IF(AND(I$3>=1,I$3<=16),INDEX('Sales Plan'!$B$2:$B$17,MAX(1,MIN(16,I$3))),0) -> 40 | ... Z5: =IF(AND(Z$3>=1,Z$3<=16),INDEX('Sales Plan'!$B$2:$B$17,MAX(1,MIN(16,Z$3))),0) -> 0
A6: Apartments sold | B6: =IF(AND(B$3>=1,B$3<=16),INDEX('Sales Plan'!$C$2:$C$17,MAX(1,MIN(16,B$3))),0) -> 0 | C6: =IF(AND(C$3>=1,C$3<=16),INDEX('Sales Plan'!$C$2:$C$17,MAX(1,MIN(16,C$3))),0) -> 60 | D6: =IF(AND(D$3>=1,D$3<=16),INDEX('Sales Plan'!$C$2:$C$17,MAX(1,MIN(16,D$3))),0) -> 70 | E6: =IF(AND(E$3>=1,E$3<=16),INDEX('Sales Plan'!$C$2:$C$17,MAX(1,MIN(16,E$3))),0) -> 70 | F6: =IF(AND(F$3>=1,F$3<=16),INDEX('Sales Plan'!$C$2:$C$17,MAX(1,MIN(16,F$3))),0) -> 70 | G6: =IF(AND(G$3>=1,G$3<=16),INDEX('Sales Plan'!$C$2:$C$17,MAX(1,MIN(16,G$3))),0) -> 65 | H6: =IF(AND(H$3>=1,H$3<=16),INDEX('Sales Plan'!$C$2:$C$17,MAX(1,MIN(16,H$3))),0) -> 65 | I6: =IF(AND(I$3>=1,I$3<=16),INDEX('Sales Plan'!$C$2:$C$17,MAX(1,MIN(16,I$3))),0) -> 60 | ... Z6: =IF(AND(Z$3>=1,Z$3<=16),INDEX('Sales Plan'!$C$2:$C$17,MAX(1,MIN(16,Z$3))),0) -> 0
A7: Contracted sales | B7: =B5*Inputs!$B$5+B6*Inputs!$B$7 -> 0 | C7: =C5*Inputs!$B$5+C6*Inputs!$B$7 -> 165300000 | D7: =D5*Inputs!$B$5+D6*Inputs!$B$7 -> 206600000 | E7: =E5*Inputs!$B$5+E6*Inputs!$B$7 -> 220350000 | F7: =F5*Inputs!$B$5+F6*Inputs!$B$7 -> 220350000 | G7: =G5*Inputs!$B$5+G6*Inputs!$B$7 -> 213450000 | H7: =H5*Inputs!$B$5+H6*Inputs!$B$7 -> 199700000 | I7: =I5*Inputs!$B$5+I6*Inputs!$B$7 -> 192800000 | ... Z7: =Z5*Inputs!$B$5+Z6*Inputs!$B$7 -> 0
A8: Down payments | B8: =B7*Inputs!$B$9 -> 0 | C8: =C7*Inputs!$B$9 -> 33060000 | D8: =D7*Inputs!$B$9 -> 41320000 | E8: =E7*Inputs!$B$9 -> 44070000 | F8: =F7*Inputs!$B$9 -> 44070000 | G8: =G7*Inputs!$B$9 -> 42690000 | H8: =H7*Inputs!$B$9 -> 39940000 | I8: =I7*Inputs!$B$9 -> 38560000 | ... Z8: =Z7*Inputs!$B$9 -> 0
A9: Balance due (lagged) | B9: =0 -> 0 | C9: =IF(AND(C$3<Inputs!$B$10,C$3>Inputs!$B$8),OFFSET(C7,0,-Inputs!$B$8)*0.4,0) -> 0 | D9: =IF(AND(D$3<Inputs!$B$10,D$3>Inputs!$B$8),OFFSET(D7,0,-Inputs!$B$8)*0.4,0) -> 0 | E9: =IF(AND(E$3<Inputs!$B$10,E$3>Inputs!$B$8),OFFSET(E7,0,-Inputs!$B$8)*0.4,0) -> 66120000 | F9: =IF(AND(F$3<Inputs!$B$10,F$3>Inputs!$B$8),OFFSET(F7,0,-Inputs!$B$8)*0.4,0) -> 82640000 | G9: =IF(AND(G$3<Inputs!$B$10,G$3>Inputs!$B$8),OFFSET(G7,0,-Inputs!$B$8)*0.4,0) -> 88140000 | H9: =IF(AND(H$3<Inputs!$B$10,H$3>Inputs!$B$8),OFFSET(H7,0,-Inputs!$B$8)*0.4,0) -> 88140000 | I9: =IF(AND(I$3<Inputs!$B$10,I$3>Inputs!$B$8),OFFSET(I7,0,-Inputs!$B$8)*0.4,0) -> 85380000 | J9: =IF(AND(J$3<Inputs!$B$10,J$3>Inputs!$B$8),OFFSET(J7,0,-Inputs!$B$8)*0.4,0) -> 79880000 | ... Z9: =IF(AND(Z$3<Inputs!$B$10,Z$3>Inputs!$B$8),OFFSET(Z7,0,-Inputs!$B$8)*0.4,0) -> 0
A10: Handover payments | B10: =0 -> 0 | C10: =IF(C$3=Inputs!$B$10,SUM($B$7:C7)*(1-Inputs!$B$9)-SUM($B$9:B9),IF(C$3>Inputs!$B$10,C7*(1-Inputs!$B$9),0)) -> 0 | D10: =IF(D$3=Inputs!$B$10,SUM($B$7:D7)*(1-Inputs!$B$9)-SUM($B$9:C9),IF(D$3>Inputs!$B$10,D7*(1-Inputs!$B$9),0)) -> 0 | E10: =IF(E$3=Inputs!$B$10,SUM($B$7:E7)*(1-Inputs!$B$9)-SUM($B$9:D9),IF(E$3>Inputs!$B$10,E7*(1-Inputs!$B$9),0)) -> 0 | F10: =IF(F$3=Inputs!$B$10,SUM($B$7:F7)*(1-Inputs!$B$9)-SUM($B$9:E9),IF(F$3>Inputs!$B$10,F7*(1-Inputs!$B$9),0)) -> 0 | G10: =IF(G$3=Inputs!$B$10,SUM($B$7:G7)*(1-Inputs!$B$9)-SUM($B$9:F9),IF(G$3>Inputs!$B$10,G7*(1-Inputs!$B$9),0)) -> 0 | H10: =IF(H$3=Inputs!$B$10,SUM($B$7:H7)*(1-Inputs!$B$9)-SUM($B$9:G9),IF(H$3>Inputs!$B$10,H7*(1-Inputs!$B$9),0)) -> 0 | I10: =IF(I$3=Inputs!$B$10,SUM($B$7:I7)*(1-Inputs!$B$9)-SUM($B$9:H9),IF(I$3>Inputs!$B$10,I7*(1-Inputs!$B$9),0)) -> 0 | J10: =IF(J$3=Inputs!$B$10,SUM($B$7:J7)*(1-Inputs!$B$9)-SUM($B$9:I9),IF(J$3>Inputs!$B$10,J7*(1-Inputs!$B$9),0)) -> 0 | ... Z10: =IF(Z$3=Inputs!$B$10,SUM($B$7:Z7)*(1-Inputs!$B$9)-SUM($B$9:Y9),IF(Z$3>Inputs!$B$10,Z7*(1-Inputs!$B$9),0)) -> 0
A11: Collections | B11: =B8+B9+B10 -> 0 | C11: =C8+C9+C10 -> 33060000 | D11: =D8+D9+D10 -> 41320000 | E11: =E8+E9+E10 -> 110190000 | F11: =F8+F9+F10 -> 126710000 | G11: =G8+G9+G10 -> 130830000 | H11: =H8+H9+H10 -> 128080000 | I11: =I8+I9+I10 -> 123940000 | ... Z11: =Z8+Z9+Z10 -> 0
A12: Construction | B12: =IF(AND(B$3>=1,B$3<=Inputs!$B$10),(Inputs!$B$4*Inputs!$B$11+Inputs!$B$6*Inputs!$B$12)/Inputs!$B$10,0) -> 0 | C12: =IF(AND(C$3>=1,C$3<=Inputs!$B$10),(Inputs!$B$4*Inputs!$B$11+Inputs!$B$6*Inputs!$B$12)/Inputs!$B$10,0) -> 92300000 | D12: =IF(AND(D$3>=1,D$3<=Inputs!$B$10),(Inputs!$B$4*Inputs!$B$11+Inputs!$B$6*Inputs!$B$12)/Inputs!$B$10,0) -> 92300000 | E12: =IF(AND(E$3>=1,E$3<=Inputs!$B$10),(Inputs!$B$4*Inputs!$B$11+Inputs!$B$6*Inputs!$B$12)/Inputs!$B$10,0) -> 92300000 | F12: =IF(AND(F$3>=1,F$3<=Inputs!$B$10),(Inputs!$B$4*Inputs!$B$11+Inputs!$B$6*Inputs!$B$12)/Inputs!$B$10,0) -> 92300000 | G12: =IF(AND(G$3>=1,G$3<=Inputs!$B$10),(Inputs!$B$4*Inputs!$B$11+Inputs!$B$6*Inputs!$B$12)/Inputs!$B$10,0) -> 92300000 | H12: =IF(AND(H$3>=1,H$3<=Inputs!$B$10),(Inputs!$B$4*Inputs!$B$11+Inputs!$B$6*Inputs!$B$12)/Inputs!$B$10,0) -> 92300000 | I12: =IF(AND(I$3>=1,I$3<=Inputs!$B$10),(Inputs!$B$4*Inputs!$B$11+Inputs!$B$6*Inputs!$B$12)/Inputs!$B$10,0) -> 92300000 | ... Z12: =IF(AND(Z$3>=1,Z$3<=Inputs!$B$10),(Inputs!$B$4*Inputs!$B$11+Inputs!$B$6*Inputs!$B$12)/Inputs!$B$10,0) -> 0
A13: Infrastructure | B13: =IF(AND(B$3>=1,B$3<=6),Inputs!$B$13/6,0) -> 0 | C13: =IF(AND(C$3>=1,C$3<=6),Inputs!$B$13/6,0) -> 51666667 | D13: =IF(AND(D$3>=1,D$3<=6),Inputs!$B$13/6,0) -> 51666667 | E13: =IF(AND(E$3>=1,E$3<=6),Inputs!$B$13/6,0) -> 51666667 | F13: =IF(AND(F$3>=1,F$3<=6),Inputs!$B$13/6,0) -> 51666667 | G13: =IF(AND(G$3>=1,G$3<=6),Inputs!$B$13/6,0) -> 51666667 | H13: =IF(AND(H$3>=1,H$3<=6),Inputs!$B$13/6,0) -> 51666667 | I13: =IF(AND(I$3>=1,I$3<=6),Inputs!$B$13/6,0) -> 0 | ... Z13: =IF(AND(Z$3>=1,Z$3<=6),Inputs!$B$13/6,0) -> 0
A14: Land | B14: =IF(B$3=0,Inputs!$B$14,0) -> 450000000 | C14: =IF(C$3=0,Inputs!$B$14,0) -> 0 | D14: =IF(D$3=0,Inputs!$B$14,0) -> 0 | E14: =IF(E$3=0,Inputs!$B$14,0) -> 0 | F14: =IF(F$3=0,Inputs!$B$14,0) -> 0 | G14: =IF(G$3=0,Inputs!$B$14,0) -> 0 | H14: =IF(H$3=0,Inputs!$B$14,0) -> 0 | I14: =IF(I$3=0,Inputs!$B$14,0) -> 0 | ... Z14: =IF(Z$3=0,Inputs!$B$14,0) -> 0
A15: Transaction tax absorbed | B15: =B7*0.05*Inputs!$B$15 -> 0 | C15: =C7*0.05*Inputs!$B$15 -> 2479500 | D15: =D7*0.05*Inputs!$B$15 -> 3099000 | E15: =E7*0.05*Inputs!$B$15 -> 3305250 | F15: =F7*0.05*Inputs!$B$15 -> 3305250 | G15: =G7*0.05*Inputs!$B$15 -> 3201750 | H15: =H7*0.05*Inputs!$B$15 -> 2995500 | I15: =I7*0.05*Inputs!$B$15 -> 2892000 | ... Z15: =Z7*0.05*Inputs!$B$15 -> 0
A16: Escrow released | B16: =IF(B$3>=Inputs!$B$10,0+B11,MIN(0+B11,B12+B13)) -> 0 | C16: =IF(C$3>=Inputs!$B$10,B17+C11,MIN(B17+C11,C12+C13)) -> 33060000 | D16: =IF(D$3>=Inputs!$B$10,C17+D11,MIN(C17+D11,D12+D13)) -> 41320000 | E16: =IF(E$3>=Inputs!$B$10,D17+E11,MIN(D17+E11,E12+E13)) -> 110190000 | F16: =IF(F$3>=Inputs!$B$10,E17+F11,MIN(E17+F11,F12+F13)) -> 126710000 | G16: =IF(G$3>=Inputs!$B$10,F17+G11,MIN(F17+G11,G12+G13)) -> 130830000 | H16: =IF(H$3>=Inputs!$B$10,G17+H11,MIN(G17+H11,H12+H13)) -> 128080000 | I16: =IF(I$3>=Inputs!$B$10,H17+I11,MIN(H17+I11,I12+I13)) -> 92300000 | J16: =IF(J$3>=Inputs!$B$10,I17+J11,MIN(I17+J11,J12+J13)) -> 92300000 | ... Z16: =IF(Z$3>=Inputs!$B$10,Y17+Z11,MIN(Y17+Z11,Z12+Z13)) -> 0
A17: Escrow balance | B17: =0+B11-B16 -> 0 | C17: =B17+C11-C16 -> 0 | D17: =C17+D11-D16 -> 0 | E17: =D17+E11-E16 -> 0 | F17: =E17+F11-F16 -> 0 | G17: =F17+G11-G16 -> 0 | H17: =G17+H11-H16 -> 0 | I17: =H17+I11-I16 -> 31640000 | J17: =I17+J11-J16 -> 55030000 | ... Z17: =Y17+Z11-Z16 -> 0
A18: Sukuk proceeds | B18: =IF(B$3=1,Inputs!$B$16,0) -> 0 | C18: =IF(C$3=1,Inputs!$B$16,0) -> 900000000 | D18: =IF(D$3=1,Inputs!$B$16,0) -> 0 | E18: =IF(E$3=1,Inputs!$B$16,0) -> 0 | F18: =IF(F$3=1,Inputs!$B$16,0) -> 0 | G18: =IF(G$3=1,Inputs!$B$16,0) -> 0 | H18: =IF(H$3=1,Inputs!$B$16,0) -> 0 | I18: =IF(I$3=1,Inputs!$B$16,0) -> 0 | ... Z18: =IF(Z$3=1,Inputs!$B$16,0) -> 0
A19: Periodic distribution | B19: =IF(AND(B$3>=2,B$3<=Inputs!$B$18),Inputs!$B$16*Inputs!$B$17/4,0) -> 0 | C19: =IF(AND(C$3>=2,C$3<=Inputs!$B$18),Inputs!$B$16*Inputs!$B$17/4,0) -> 0 | D19: =IF(AND(D$3>=2,D$3<=Inputs!$B$18),Inputs!$B$16*Inputs!$B$17/4,0) -> 15187500 | E19: =IF(AND(E$3>=2,E$3<=Inputs!$B$18),Inputs!$B$16*Inputs!$B$17/4,0) -> 15187500 | F19: =IF(AND(F$3>=2,F$3<=Inputs!$B$18),Inputs!$B$16*Inputs!$B$17/4,0) -> 15187500 | G19: =IF(AND(G$3>=2,G$3<=Inputs!$B$18),Inputs!$B$16*Inputs!$B$17/4,0) -> 15187500 | H19: =IF(AND(H$3>=2,H$3<=Inputs!$B$18),Inputs!$B$16*Inputs!$B$17/4,0) -> 15187500 | I19: =IF(AND(I$3>=2,I$3<=Inputs!$B$18),Inputs!$B$16*Inputs!$B$17/4,0) -> 15187500 | ... Z19: =IF(AND(Z$3>=2,Z$3<=Inputs!$B$18),Inputs!$B$16*Inputs!$B$17/4,0) -> 0
A20: Sukuk redemption | B20: =IF(B$3=Inputs!$B$18,Inputs!$B$16,0) -> 0 | C20: =IF(C$3=Inputs!$B$18,Inputs!$B$16,0) -> 0 | D20: =IF(D$3=Inputs!$B$18,Inputs!$B$16,0) -> 0 | E20: =IF(E$3=Inputs!$B$18,Inputs!$B$16,0) -> 0 | F20: =IF(F$3=Inputs!$B$18,Inputs!$B$16,0) -> 0 | G20: =IF(G$3=Inputs!$B$18,Inputs!$B$16,0) -> 0 | H20: =IF(H$3=Inputs!$B$18,Inputs!$B$16,0) -> 0 | I20: =IF(I$3=Inputs!$B$18,Inputs!$B$16,0) -> 0 | ... Z20: =IF(Z$3=Inputs!$B$18,Inputs!$B$16,0) -> 0
A21: Coverage ratio | B21: =IF(B19>0,MAX(0,0+(B16-B12-B13-B15))/B19,0) -> 0 | C21: =IF(C19>0,MAX(0,B27+(C16-C12-C13-C15))/C19,0) -> 0 | D21: =IF(D19>0,MAX(0,C27+(D16-D12-D13-D15))/D19,0) -> 44.830826 | E21: =IF(E19>0,MAX(0,D27+(E16-E12-E13-E15))/E19,0) -> 41.389218 | F21: =IF(F19>0,MAX(0,E27+(F16-F12-F13-F15))/F19,0) -> 39.035347 | G21: =IF(G19>0,MAX(0,F27+(G16-G12-G13-G15))/G19,0) -> 36.959567 | H21: =IF(H19>0,MAX(0,G27+(H16-H12-H13-H15))/H19,0) -> 34.716296 | I21: =IF(I19>0,MAX(0,H27+(I16-I12-I13-I15))/I19,0) -> 33.525877 | J21: =IF(J19>0,MAX(0,I27+(J16-J12-J13-J15))/J19,0) -> 32.349037 | ... Z21: =IF(Z19>0,MAX(0,Y27+(Z16-Z12-Z13-Z15))/Z19,0) -> 0
A22: Cumulative profit | B22: =SUM($B$16:B16)-SUM($B$12:B12)-SUM($B$13:B13)-SUM($B$15:B15)-SUM($B$19:B19)-Inputs!$B$14 -> -450000000 | C22: =SUM($B$16:C16)-SUM($B$12:C12)-SUM($B$13:C13)-SUM($B$15:C15)-SUM($B$19:C19)-Inputs!$B$14 -> -5.6338617e+08 | D22: =SUM($B$16:D16)-SUM($B$12:D12)-SUM($B$13:D13)-SUM($B$15:D15)-SUM($B$19:D19)-Inputs!$B$14 -> -6.8431933e+08 | E22: =SUM($B$16:E16)-SUM($B$12:E12)-SUM($B$13:E13)-SUM($B$15:E15)-SUM($B$19:E19)-Inputs!$B$14 -> -736588750 | F22: =SUM($B$16:F16)-SUM($B$12:F12)-SUM($B$13:F13)-SUM($B$15:F15)-SUM($B$19:F19)-Inputs!$B$14 -> -7.7233817e+08 | G22: =SUM($B$16:G16)-SUM($B$12:G12)-SUM($B$13:G13)-SUM($B$15:G15)-SUM($B$19:G19)-Inputs!$B$14 -> -8.0386408e+08 | H22: =SUM($B$16:H16)-SUM($B$12:H12)-SUM($B$13:H13)-SUM($B$15:H15)-SUM($B$19:H19)-Inputs!$B$14 -> -837933750 | I22: =SUM($B$16:I16)-SUM($B$12:I12)-SUM($B$13:I13)-SUM($B$15:I15)-SUM($B$19:I19)-Inputs!$B$14 -> -856013250 | ... Z22: =SUM($B$16:Z16)-SUM($B$12:Z12)-SUM($B$13:Z13)-SUM($B$15:Z15)-SUM($B$19:Z19)-Inputs!$B$14 -> 318146500
A23: Zakat | B23: =IF(MONTH(B4)=12,MAX(0,Inputs!$B$20+B22)*Inputs!$B$19,0) -> 6250000 | C23: =IF(MONTH(C4)=12,MAX(0,Inputs!$B$20+C22)*Inputs!$B$19,0) -> 0 | D23: =IF(MONTH(D4)=12,MAX(0,Inputs!$B$20+D22)*Inputs!$B$19,0) -> 0 | E23: =IF(MONTH(E4)=12,MAX(0,Inputs!$B$20+E22)*Inputs!$B$19,0) -> 0 | F23: =IF(MONTH(F4)=12,MAX(0,Inputs!$B$20+F22)*Inputs!$B$19,0) -> 0 | G23: =IF(MONTH(G4)=12,MAX(0,Inputs!$B$20+G22)*Inputs!$B$19,0) -> 0 | H23: =IF(MONTH(H4)=12,MAX(0,Inputs!$B$20+H22)*Inputs!$B$19,0) -> 0 | I23: =IF(MONTH(I4)=12,MAX(0,Inputs!$B$20+I22)*Inputs!$B$19,0) -> 0 | ... Z23: =IF(MONTH(Z4)=12,MAX(0,Inputs!$B$20+Z22)*Inputs!$B$19,0) -> 25453662
A24: Cash before equity | B24: =0+B16-B12-B13-B14-B15+B18-B19-B20-B23 -> -456250000 | C24: =B27+C16-C12-C13-C14-C15+C18-C19-C20-C23 -> 7.8661383e+08 | D24: =C27+D16-D12-D13-D14-D15+D18-D19-D20-D23 -> 6.6568067e+08 | E24: =D27+E16-E12-E13-E14-E15+E18-E19-E20-E23 -> 613411250 | F24: =E27+F16-F12-F13-F14-F15+F18-F19-F20-F23 -> 5.7766183e+08 | G24: =F27+G16-G12-G13-G14-G15+G18-G19-G20-G23 -> 5.4613592e+08 | H24: =G27+H16-H12-H13-H14-H15+H18-H19-H20-H23 -> 512066250 | I24: =H27+I16-I12-I13-I14-I15+I18-I19-I20-I23 -> 493986750 | J24: =I27+J16-J12-J13-J14-J15+J18-J19-J20-J23 -> 476113500 | ... Z24: =Y27+Z16-Z12-Z13-Z14-Z15+Z18-Z19-Z20-Z23 -> -25453662
A25: Equity in | B25: =MAX(0,-B24) -> 456250000 | C25: =MAX(0,-C24) -> 0 | D25: =MAX(0,-D24) -> 0 | E25: =MAX(0,-E24) -> 0 | F25: =MAX(0,-F24) -> 0 | G25: =MAX(0,-G24) -> 0 | H25: =MAX(0,-H24) -> 0 | I25: =MAX(0,-I24) -> 0 | ... Z25: =MAX(0,-Z24) -> 25453662
A26: Distributions | B26: =IF(B$3>=Inputs!$B$18,MAX(0,B24),0) -> 0 | C26: =IF(C$3>=Inputs!$B$18,MAX(0,C24),0) -> 0 | D26: =IF(D$3>=Inputs!$B$18,MAX(0,D24),0) -> 0 | E26: =IF(E$3>=Inputs!$B$18,MAX(0,E24),0) -> 0 | F26: =IF(F$3>=Inputs!$B$18,MAX(0,F24),0) -> 0 | G26: =IF(G$3>=Inputs!$B$18,MAX(0,G24),0) -> 0 | H26: =IF(H$3>=Inputs!$B$18,MAX(0,H24),0) -> 0 | I26: =IF(I$3>=Inputs!$B$18,MAX(0,I24),0) -> 0 | ... Z26: =IF(Z$3>=Inputs!$B$18,MAX(0,Z24),0) -> 0
A27: Cash balance | B27: =B24+B25-B26 -> 0 | C27: =C24+C25-C26 -> 7.8661383e+08 | D27: =D24+D25-D26 -> 6.6568067e+08 | E27: =E24+E25-E26 -> 613411250 | F27: =F24+F25-F26 -> 5.7766183e+08 | G27: =G24+G25-G26 -> 5.4613592e+08 | H27: =H24+H25-H26 -> 512066250 | I27: =I24+I25-I26 -> 493986750 | ... Z27: =Z24+Z25-Z26 -> 0
A28: Equity cash flow | B28: =B26-B25 -> -456250000 | C28: =C26-C25 -> 0 | D28: =D26-D25 -> 0 | E28: =E26-E25 -> 0 | F28: =F26-F25 -> 0 | G28: =G26-G25 -> 0 | H28: =H26-H25 -> 0 | I28: =I26-I25 -> 0 | ... Z28: =Z26-Z25 -> -25453662

Sheet Returns
A3: Levered IRR | B3: =(1+IRR('Cash Flow'!$B$28:$Z$28,0.02))^4-1 -> 0.086972905
A4: Net profit (SAR) | B4: =SUM('Cash Flow'!$B$28:$Z$28) -> 2.3401676e+08
A5: Minimum sukuk coverage | B5: =_xlfn.MINIFS('Cash Flow'!$B$21:$Z$21,'Cash Flow'!$B$19:$Z$19,">0") -> 26.594074
A6: Equity injected (SAR) | B6: =SUM('Cash Flow'!$B$25:$Z$25) -> 4.8170366e+08
A7: Zakat paid (SAR) | B7: =SUM('Cash Flow'!$B$23:$Z$23) -> 84129738
A8: Peak escrow balance (SAR) | B8: =MAX('Cash Flow'!$B$17:$Z$17) -> 93500000
A9: Units sold by handover | B9: =SUMIF('Cash Flow'!$B$3:$Z$3,"<="&Inputs!$B$10,'Cash Flow'!$B$5:$Z$5)+SUMIF('Cash Flow'!$B$3:$Z$3,"<="&Inputs!$B$10,'Cash Flow'!$B$6:$Z$6) -> 1310
A10: Transaction tax absorbed (SAR) | B10: =SUM('Cash Flow'!$B$15:$Z$15) -> 40491000
A11: Total revenue (SAR) | B11: =SUM('Cash Flow'!$B$7:$Z$7) -> 2699400000
A12: Sukuk distributions (SAR) | B12: =SUM('Cash Flow'!$B$19:$Z$19) -> 288562500
