Workbook

Sheet Inputs
A1: CASTLE QUAY STUDENT – FORWARD FUNDING (GBP)
A3: Funding date | B3: 46234
A4: Land (£) | B4: 18000000
A5: Beds | B5: 650
A6: Rent per bed a week (£) | B6: 289
A7: Weeks let a year | B7: 51
A8: Rent growth a year | B8: 0.03
A9: Voids | B9: 0.03
A10: Operating cost (% of income) | B10: 0.28
A11: Construction cost (£) | B11: 86000000
A12: Build (quarters) | B12: 9
A13: Delay (quarters) | B13: 0
A14: Long-stop (quarters) | B14: 10
... A20: Investor exit yield | B20: 0.05

Sheet Curve
A1: Share of build elapsed | B1: Cumulative cost
A2: 0 | B2: 0
A3: 0.1 | B3: 0.04
A4: 0.2 | B4: 0.11
A5: 0.3 | B5: 0.21
A6: 0.4 | B6: 0.33
A7: 0.5 | B7: 0.46
A8: 0.6 | B8: 0.59
A9: 0.7 | B9: 0.71
A10: 0.8 | B10: 0.82
A11: 0.9 | B11: 0.92
A12: 1 | B12: 1

Sheet SDLT
A1: Band from (£) | B1: Rate | C1: Tax below band (£)
A2: 0 | B2: 0 | C2: 0
A3: 150000 | B3: 0.02 | C3: 0
A4: 250000 | B4: 0.05 | C4: 2000

Sheet Cash Flow
A3: Quarter | B3: 0 | C3: 1 | D3: 2 | E3: 3 | F3: 4 | G3: 5 | H3: 6 | I3: 7 | J3: 8 | K3: 9 | L3: 10 | M3: 11 | N3: 12 | O3: 13 | P3: 14 | Q3: 15 | R3: 16 | S3: 17 | T3: 18 | U3: 19 | V3: 20 | W3: 21 | X3: 22 | Y3: 23 | Z3: 24 | AA3: 25 | AB3: 26 | AC3: 27 | AD3: 28 | AE3: 29 | AF3: 30 | AG3: 31 | AH3: 32 | AI3: 33 | AJ3: 34 | AK3: 35 | AL3: 36 | AM3: 37 | AN3: 38 | AO3: 39 | AP3: 40 | AQ3: 41 | AR3: 42 | AS3: 43 | AT3: 44 | AU3: 45 | AV3: 46 | AW3: 47 | AX3: 48 | AY3: 49 | AZ3: 50 | BA3: 51 | BB3: 52
A4: Date | B4: =EOMONTH(Inputs!$B$3,3*B$3) -> 46234 | C4: =EOMONTH(Inputs!$B$3,3*C$3) -> 46326 | D4: =EOMONTH(Inputs!$B$3,3*D$3) -> 46418 | E4: =EOMONTH(Inputs!$B$3,3*E$3) -> 46507 | F4: =EOMONTH(Inputs!$B$3,3*F$3) -> 46599 | G4: =EOMONTH(Inputs!$B$3,3*G$3) -> 46691 | H4: =EOMONTH(Inputs!$B$3,3*H$3) -> 46783 | I4: =EOMONTH(Inputs!$B$3,3*I$3) -> 46873 | ... BB4: =EOMONTH(Inputs!$B$3,3*BB$3) -> 50982
A5: Fiscal year | B5: ="FY"&TEXT(EDATE(B4,-3),"yy") -> FY26 | C5: ="FY"&TEXT(EDATE(C4,-3),"yy") -> FY26 | D5: ="FY"&TEXT(EDATE(D4,-3),"yy") -> FY26 | E5: ="FY"&TEXT(EDATE(E4,-3),"yy") -> FY27 | F5: ="FY"&TEXT(EDATE(F4,-3),"yy") -> FY27 | G5: ="FY"&TEXT(EDATE(G4,-3),"yy") -> FY27 | H5: ="FY"&TEXT(EDATE(H4,-3),"yy") -> FY27 | I5: ="FY"&TEXT(EDATE(I4,-3),"yy") -> FY28 | ... BB5: ="FY"&TEXT(EDATE(BB4,-3),"yy") -> FY39
A6: Elapsed share | B6: =MIN(1,B$3/(Inputs!$B$12+Inputs!$B$13)) -> 0 | C6: =MIN(1,C$3/(Inputs!$B$12+Inputs!$B$13)) -> 0.11111111 | D6: =MIN(1,D$3/(Inputs!$B$12+Inputs!$B$13)) -> 0.22222222 | E6: =MIN(1,E$3/(Inputs!$B$12+Inputs!$B$13)) -> 0.33333333 | F6: =MIN(1,F$3/(Inputs!$B$12+Inputs!$B$13)) -> 0.44444444 | G6: =MIN(1,G$3/(Inputs!$B$12+Inputs!$B$13)) -> 0.55555556 | H6: =MIN(1,H$3/(Inputs!$B$12+Inputs!$B$13)) -> 0.66666667 | I6: =MIN(1,I$3/(Inputs!$B$12+Inputs!$B$13)) -> 0.77777778 | ... BB6: =MIN(1,BB$3/(Inputs!$B$12+Inputs!$B$13)) -> 1
A7: Cumulative cost share | B7: =VLOOKUP(B6,Curve!$A$2:$B$12,2) -> 0 | C7: =VLOOKUP(C6,Curve!$A$2:$B$12,2) -> 0.04 | D7: =VLOOKUP(D6,Curve!$A$2:$B$12,2) -> 0.11 | E7: =VLOOKUP(E6,Curve!$A$2:$B$12,2) -> 0.21 | F7: =VLOOKUP(F6,Curve!$A$2:$B$12,2) -> 0.33 | G7: =VLOOKUP(G6,Curve!$A$2:$B$12,2) -> 0.46 | H7: =VLOOKUP(H6,Curve!$A$2:$B$12,2) -> 0.59 | I7: =VLOOKUP(I6,Curve!$A$2:$B$12,2) -> 0.71 | ... BB7: =VLOOKUP(BB6,Curve!$A$2:$B$12,2) -> 1
A8: Construction draw | B8: =0 -> 0 | C8: =IF(C$3<=(Inputs!$B$12+Inputs!$B$13),Inputs!$B$11*(C7-B7),0) -> 3440000 | D8: =IF(D$3<=(Inputs!$B$12+Inputs!$B$13),Inputs!$B$11*(D7-C7),0) -> 6020000 | E8: =IF(E$3<=(Inputs!$B$12+Inputs!$B$13),Inputs!$B$11*(E7-D7),0) -> 8600000 | F8: =IF(F$3<=(Inputs!$B$12+Inputs!$B$13),Inputs!$B$11*(F7-E7),0) -> 10320000 | G8: =IF(G$3<=(Inputs!$B$12+Inputs!$B$13),Inputs!$B$11*(G7-F7),0) -> 11180000 | H8: =IF(H$3<=(Inputs!$B$12+Inputs!$B$13),Inputs!$B$11*(H7-G7),0) -> 11180000 | I8: =IF(I$3<=(Inputs!$B$12+Inputs!$B$13),Inputs!$B$11*(I7-H7),0) -> 10320000 | J8: =IF(J$3<=(Inputs!$B$12+Inputs!$B$13),Inputs!$B$11*(J7-I7),0) -> 9460000 | ... BB8: =IF(BB$3<=(Inputs!$B$12+Inputs!$B$13),Inputs!$B$11*(BB7-BA7),0) -> 0
A9: Land | B9: =IF(B$3=0,Inputs!$B$4,0) -> 18000000 | C9: =IF(C$3=0,Inputs!$B$4,0) -> 0 | D9: =IF(D$3=0,Inputs!$B$4,0) -> 0 | E9: =IF(E$3=0,Inputs!$B$4,0) -> 0 | F9: =IF(F$3=0,Inputs!$B$4,0) -> 0 | G9: =IF(G$3=0,Inputs!$B$4,0) -> 0 | H9: =IF(H$3=0,Inputs!$B$4,0) -> 0 | I9: =IF(I$3=0,Inputs!$B$4,0) -> 0 | ... BB9: =IF(BB$3=0,Inputs!$B$4,0) -> 0
A10: Funds advanced | B10: =SUM($B$8:B8)+Inputs!$B$4 -> 18000000 | C10: =SUM($B$8:C8)+Inputs!$B$4 -> 21440000 | D10: =SUM($B$8:D8)+Inputs!$B$4 -> 27460000 | E10: =SUM($B$8:E8)+Inputs!$B$4 -> 36060000 | F10: =SUM($B$8:F8)+Inputs!$B$4 -> 46380000 | G10: =SUM($B$8:G8)+Inputs!$B$4 -> 57560000 | H10: =SUM($B$8:H8)+Inputs!$B$4 -> 68740000 | I10: =SUM($B$8:I8)+Inputs!$B$4 -> 79060000 | ... BB10: =SUM($B$8:BB8)+Inputs!$B$4 -> 104000000
A11: Coupon | B11: =0 -> 0 | C11: =IF(C$3<=(Inputs!$B$12+Inputs!$B$13),B10*Inputs!$B$16/4,0) -> 292500 | D11: =IF(D$3<=(Inputs!$B$12+Inputs!$B$13),C10*Inputs!$B$16/4,0) -> 348400 | E11: =IF(E$3<=(Inputs!$B$12+Inputs!$B$13),D10*Inputs!$B$16/4,0) -> 446225 | F11: =IF(F$3<=(Inputs!$B$12+Inputs!$B$13),E10*Inputs!$B$16/4,0) -> 585975 | G11: =IF(G$3<=(Inputs!$B$12+Inputs!$B$13),F10*Inputs!$B$16/4,0) -> 753675 | H11: =IF(H$3<=(Inputs!$B$12+Inputs!$B$13),G10*Inputs!$B$16/4,0) -> 935350 | I11: =IF(I$3<=(Inputs!$B$12+Inputs!$B$13),H10*Inputs!$B$16/4,0) -> 1117025 | J11: =IF(J$3<=(Inputs!$B$12+Inputs!$B$13),I10*Inputs!$B$16/4,0) -> 1284725 | ... BB11: =IF(BB$3<=(Inputs!$B$12+Inputs!$B$13),BA10*Inputs!$B$16/4,0) -> 0
A12: Penalty | B12: =IF(AND(B$3>Inputs!$B$14,B$3<=(Inputs!$B$12+Inputs!$B$13)),Inputs!$B$15,0) -> 0 | C12: =IF(AND(C$3>Inputs!$B$14,C$3<=(Inputs!$B$12+Inputs!$B$13)),Inputs!$B$15,0) -> 0 | D12: =IF(AND(D$3>Inputs!$B$14,D$3<=(Inputs!$B$12+Inputs!$B$13)),Inputs!$B$15,0) -> 0 | E12: =IF(AND(E$3>Inputs!$B$14,E$3<=(Inputs!$B$12+Inputs!$B$13)),Inputs!$B$15,0) -> 0 | F12: =IF(AND(F$3>Inputs!$B$14,F$3<=(Inputs!$B$12+Inputs!$B$13)),Inputs!$B$15,0) -> 0 | G12: =IF(AND(G$3>Inputs!$B$14,G$3<=(Inputs!$B$12+Inputs!$B$13)),Inputs!$B$15,0) -> 0 | H12: =IF(AND(H$3>Inputs!$B$14,H$3<=(Inputs!$B$12+Inputs!$B$13)),Inputs!$B$15,0) -> 0 | I12: =IF(AND(I$3>Inputs!$B$14,I$3<=(Inputs!$B$12+Inputs!$B$13)),Inputs!$B$15,0) -> 0 | ... BB12: =IF(AND(BB$3>Inputs!$B$14,BB$3<=(Inputs!$B$12+Inputs!$B$13)),Inputs!$B$15,0) -> 0
A13: Operating | B13: =IF(AND(B$3>(Inputs!$B$12+Inputs!$B$13),B$3<=(Inputs!$B$12+Inputs!$B$13)+Inputs!$B$19),1,0) -> 0 | C13: =IF(AND(C$3>(Inputs!$B$12+Inputs!$B$13),C$3<=(Inputs!$B$12+Inputs!$B$13)+Inputs!$B$19),1,0) -> 0 | D13: =IF(AND(D$3>(Inputs!$B$12+Inputs!$B$13),D$3<=(Inputs!$B$12+Inputs!$B$13)+Inputs!$B$19),1,0) -> 0 | E13: =IF(AND(E$3>(Inputs!$B$12+Inputs!$B$13),E$3<=(Inputs!$B$12+Inputs!$B$13)+Inputs!$B$19),1,0) -> 0 | F13: =IF(AND(F$3>(Inputs!$B$12+Inputs!$B$13),F$3<=(Inputs!$B$12+Inputs!$B$13)+Inputs!$B$19),1,0) -> 0 | G13: =IF(AND(G$3>(Inputs!$B$12+Inputs!$B$13),G$3<=(Inputs!$B$12+Inputs!$B$13)+Inputs!$B$19),1,0) -> 0 | H13: =IF(AND(H$3>(Inputs!$B$12+Inputs!$B$13),H$3<=(Inputs!$B$12+Inputs!$B$13)+Inputs!$B$19),1,0) -> 0 | I13: =IF(AND(I$3>(Inputs!$B$12+Inputs!$B$13),I$3<=(Inputs!$B$12+Inputs!$B$13)+Inputs!$B$19),1,0) -> 0 | ... BB13: =IF(AND(BB$3>(Inputs!$B$12+Inputs!$B$13),BB$3<=(Inputs!$B$12+Inputs!$B$13)+Inputs!$B$19),1,0) -> 0
A14: Gross income | B14: =B13*Inputs!$B$5*Inputs!$B$6*Inputs!$B$7/4*(1-Inputs!$B$9)*(1+Inputs!$B$8)^INT((B$3-(Inputs!$B$12+Inputs!$B$13)-1)/4) -> 0 | C14: =C13*Inputs!$B$5*Inputs!$B$6*Inputs!$B$7/4*(1-Inputs!$B$9)*(1+Inputs!$B$8)^INT((C$3-(Inputs!$B$12+Inputs!$B$13)-1)/4) -> 0 | D14: =D13*Inputs!$B$5*Inputs!$B$6*Inputs!$B$7/4*(1-Inputs!$B$9)*(1+Inputs!$B$8)^INT((D$3-(Inputs!$B$12+Inputs!$B$13)-1)/4) -> 0 | E14: =E13*Inputs!$B$5*Inputs!$B$6*Inputs!$B$7/4*(1-Inputs!$B$9)*(1+Inputs!$B$8)^INT((E$3-(Inputs!$B$12+Inputs!$B$13)-1)/4) -> 0 | F14: =F13*Inputs!$B$5*Inputs!$B$6*Inputs!$B$7/4*(1-Inputs!$B$9)*(1+Inputs!$B$8)^INT((F$3-(Inputs!$B$12+Inputs!$B$13)-1)/4) -> 0 | G14: =G13*Inputs!$B$5*Inputs!$B$6*Inputs!$B$7/4*(1-Inputs!$B$9)*(1+Inputs!$B$8)^INT((G$3-(Inputs!$B$12+Inputs!$B$13)-1)/4) -> 0 | H14: =H13*Inputs!$B$5*Inputs!$B$6*Inputs!$B$7/4*(1-Inputs!$B$9)*(1+Inputs!$B$8)^INT((H$3-(Inputs!$B$12+Inputs!$B$13)-1)/4) -> 0 | I14: =I13*Inputs!$B$5*Inputs!$B$6*Inputs!$B$7/4*(1-Inputs!$B$9)*(1+Inputs!$B$8)^INT((I$3-(Inputs!$B$12+Inputs!$B$13)-1)/4) -> 0 | ... BB14: =BB13*Inputs!$B$5*Inputs!$B$6*Inputs!$B$7/4*(1-Inputs!$B$9)*(1+Inputs!$B$8)^INT((BB$3-(Inputs!$B$12+Inputs!$B$13)-1)/4) -> 0
A15: Net operating income | B15: =B14*(1-Inputs!$B$10) -> 0 | C15: =C14*(1-Inputs!$B$10) -> 0 | D15: =D14*(1-Inputs!$B$10) -> 0 | E15: =E14*(1-Inputs!$B$10) -> 0 | F15: =F14*(1-Inputs!$B$10) -> 0 | G15: =G14*(1-Inputs!$B$10) -> 0 | H15: =H14*(1-Inputs!$B$10) -> 0 | I15: =I14*(1-Inputs!$B$10) -> 0 | ... BB15: =BB14*(1-Inputs!$B$10) -> 0
A16: Investor exit | B16: =IF(B$3=(Inputs!$B$12+Inputs!$B$13)+Inputs!$B$19,B15*4*(1+Inputs!$B$8)/Inputs!$B$20,0) -> 0 | C16: =IF(C$3=(Inputs!$B$12+Inputs!$B$13)+Inputs!$B$19,C15*4*(1+Inputs!$B$8)/Inputs!$B$20,0) -> 0 | D16: =IF(D$3=(Inputs!$B$12+Inputs!$B$13)+Inputs!$B$19,D15*4*(1+Inputs!$B$8)/Inputs!$B$20,0) -> 0 | E16: =IF(E$3=(Inputs!$B$12+Inputs!$B$13)+Inputs!$B$19,E15*4*(1+Inputs!$B$8)/Inputs!$B$20,0) -> 0 | F16: =IF(F$3=(Inputs!$B$12+Inputs!$B$13)+Inputs!$B$19,F15*4*(1+Inputs!$B$8)/Inputs!$B$20,0) -> 0 | G16: =IF(G$3=(Inputs!$B$12+Inputs!$B$13)+Inputs!$B$19,G15*4*(1+Inputs!$B$8)/Inputs!$B$20,0) -> 0 | H16: =IF(H$3=(Inputs!$B$12+Inputs!$B$13)+Inputs!$B$19,H15*4*(1+Inputs!$B$8)/Inputs!$B$20,0) -> 0 | I16: =IF(I$3=(Inputs!$B$12+Inputs!$B$13)+Inputs!$B$19,I15*4*(1+Inputs!$B$8)/Inputs!$B$20,0) -> 0 | ... BB16: =IF(BB$3=(Inputs!$B$12+Inputs!$B$13)+Inputs!$B$19,BB15*4*(1+Inputs!$B$8)/Inputs!$B$20,0) -> 0
A17: Investor cash flow | B17: =-B9-B8-IF(B$3=(Inputs!$B$12+Inputs!$B$13),Returns!$B$8+Returns!$B$7+Returns!$B$6*Inputs!$B$18,0)+B15+B16 -> -18000000 | C17: =-C9-C8-IF(C$3=(Inputs!$B$12+Inputs!$B$13),Returns!$B$8+Returns!$B$7+Returns!$B$6*Inputs!$B$18,0)+C15+C16 -> -3440000 | D17: =-D9-D8-IF(D$3=(Inputs!$B$12+Inputs!$B$13),Returns!$B$8+Returns!$B$7+Returns!$B$6*Inputs!$B$18,0)+D15+D16 -> -6020000 | E17: =-E9-E8-IF(E$3=(Inputs!$B$12+Inputs!$B$13),Returns!$B$8+Returns!$B$7+Returns!$B$6*Inputs!$B$18,0)+E15+E16 -> -8600000 | F17: =-F9-F8-IF(F$3=(Inputs!$B$12+Inputs!$B$13),Returns!$B$8+Returns!$B$7+Returns!$B$6*Inputs!$B$18,0)+F15+F16 -> -10320000 | G17: =-G9-G8-IF(G$3=(Inputs!$B$12+Inputs!$B$13),Returns!$B$8+Returns!$B$7+Returns!$B$6*Inputs!$B$18,0)+G15+G16 -> -11180000 | H17: =-H9-H8-IF(H$3=(Inputs!$B$12+Inputs!$B$13),Returns!$B$8+Returns!$B$7+Returns!$B$6*Inputs!$B$18,0)+H15+H16 -> -11180000 | I17: =-I9-I8-IF(I$3=(Inputs!$B$12+Inputs!$B$13),Returns!$B$8+Returns!$B$7+Returns!$B$6*Inputs!$B$18,0)+I15+I16 -> -10320000 | ... BB17: =-BB9-BB8-IF(BB$3=(Inputs!$B$12+Inputs!$B$13),Returns!$B$8+Returns!$B$7+Returns!$B$6*Inputs!$B$18,0)+BB15+BB16 -> 0

Sheet Returns
A3: Practical completion (quarter) | B3: =(Inputs!$B$12+Inputs!$B$13) -> 9
A4: Year-1 net rent (£) | B4: =Inputs!$B$5*Inputs!$B$6*Inputs!$B$7*(1-Inputs!$B$9)*(1-Inputs!$B$10) -> 6690916.4
A5: Gross value at NIY (£) | B5: =B4/Inputs!$B$17 -> 1.408614e+08
A6: Purchase price (£) | B6: =B5/(1+Inputs!$B$18)-B7 -> 1.3133816e+08
A7: SDLT (£) | B7: =VLOOKUP(B5,SDLT!$A$2:$C$4,3)+(B5-VLOOKUP(B5,SDLT!$A$2:$C$4,1))*VLOOKUP(B5,SDLT!$A$2:$C$4,2) -> 7032569.9
A8: Developer profit (£) | B8: =B6-Inputs!$B$4-Inputs!$B$11-SUM('Cash Flow'!$B$11:$BB$11)-SUM('Cash Flow'!$B$12:$BB$12) -> 20135831
A9: Funder's coupon (£) | B9: =SUM('Cash Flow'!$B$11:$BB$11) -> 7202325
A10: Delay penalties (£) | B10: =SUM('Cash Flow'!$B$12:$BB$12) -> 0
A11: Developer margin on price | B11: =B8/B6 -> 0.15331288
A12: Investor yield on cost | B12: =B4/(B6+B7+B6*Inputs!$B$18) -> 0.047542725
A13: Investor IRR (XIRR) | B13: =XIRR('Cash Flow'!$B$17:$BB$17,'Cash Flow'!$B$4:$BB$4) -> 0.073568457
A14: Net profit to investor (£) | B14: =SUM('Cash Flow'!$B$17:$BB$17) -> 1.2301202e+08
A16: NOI in FY30 (£) | B16: =INDEX('FY Summary'!$B$2:$B$14,MATCH("FY30",'FY Summary'!$A$2:$A$14,0)) -> 6943331.3

Sheet FY Summary
A1: Fiscal year | B1: Net operating income (£) | C1: Gross income (£)
A2: FY27 | B2: =SUMIF('Cash Flow'!$B$5:$BB$5,A2,'Cash Flow'!$B$15:$BB$15) -> 0 | C2: =SUMIF('Cash Flow'!$B$5:$BB$5,A2,'Cash Flow'!$B$14:$BB$14) -> 0
A3: FY28 | B3: =SUMIF('Cash Flow'!$B$5:$BB$5,A3,'Cash Flow'!$B$15:$BB$15) -> 1672729.1 | C3: =SUMIF('Cash Flow'!$B$5:$BB$5,A3,'Cash Flow'!$B$14:$BB$14) -> 2323234.9
A4: FY29 | B4: =SUMIF('Cash Flow'!$B$5:$BB$5,A4,'Cash Flow'!$B$15:$BB$15) -> 6741098.3 | C4: =SUMIF('Cash Flow'!$B$5:$BB$5,A4,'Cash Flow'!$B$14:$BB$14) -> 9362636.5
A5: FY30 | B5: =SUMIF('Cash Flow'!$B$5:$BB$5,A5,'Cash Flow'!$B$15:$BB$15) -> 6943331.3 | C5: =SUMIF('Cash Flow'!$B$5:$BB$5,A5,'Cash Flow'!$B$14:$BB$14) -> 9643515.6
A6: FY31 | B6: =SUMIF('Cash Flow'!$B$5:$BB$5,A6,'Cash Flow'!$B$15:$BB$15) -> 7151631.2 | C6: =SUMIF('Cash Flow'!$B$5:$BB$5,A6,'Cash Flow'!$B$14:$BB$14) -> 9932821.1
A7: FY32 | B7: =SUMIF('Cash Flow'!$B$5:$BB$5,A7,'Cash Flow'!$B$15:$BB$15) -> 7366180.1 | C7: =SUMIF('Cash Flow'!$B$5:$BB$5,A7,'Cash Flow'!$B$14:$BB$14) -> 10230806
A8: FY33 | B8: =SUMIF('Cash Flow'!$B$5:$BB$5,A8,'Cash Flow'!$B$15:$BB$15) -> 7587165.5 | C8: =SUMIF('Cash Flow'!$B$5:$BB$5,A8,'Cash Flow'!$B$14:$BB$14) -> 10537730
A9: FY34 | B9: =SUMIF('Cash Flow'!$B$5:$BB$5,A9,'Cash Flow'!$B$15:$BB$15) -> 7814780.5 | C9: =SUMIF('Cash Flow'!$B$5:$BB$5,A9,'Cash Flow'!$B$14:$BB$14) -> 10853862
A10: FY35 | B10: =SUMIF('Cash Flow'!$B$5:$BB$5,A10,'Cash Flow'!$B$15:$BB$15) -> 8049223.9 | C10: =SUMIF('Cash Flow'!$B$5:$BB$5,A10,'Cash Flow'!$B$14:$BB$14) -> 11179478
A11: FY36 | B11: =SUMIF('Cash Flow'!$B$5:$BB$5,A11,'Cash Flow'!$B$15:$BB$15) -> 8290700.6 | C11: =SUMIF('Cash Flow'!$B$5:$BB$5,A11,'Cash Flow'!$B$14:$BB$14) -> 11514862
A12: FY37 | B12: =SUMIF('Cash Flow'!$B$5:$BB$5,A12,'Cash Flow'!$B$15:$BB$15) -> 8539421.7 | C12: =SUMIF('Cash Flow'!$B$5:$BB$5,A12,'Cash Flow'!$B$14:$BB$14) -> 11860308
A13: FY38 | B13: =SUMIF('Cash Flow'!$B$5:$BB$5,A13,'Cash Flow'!$B$15:$BB$15) -> 6547596.3 | C13: =SUMIF('Cash Flow'!$B$5:$BB$5,A13,'Cash Flow'!$B$14:$BB$14) -> 9093883.7
A14: FY39 | B14: =SUMIF('Cash Flow'!$B$5:$BB$5,A14,'Cash Flow'!$B$15:$BB$15) -> 0 | C14: =SUMIF('Cash Flow'!$B$5:$BB$5,A14,'Cash Flow'!$B$14:$BB$14) -> 0
