Workbook

Sheet Inputs
A1: DUBAI CREEK TOWER PODIUM – CONTRACTOR TENDER (AED)
A3: Start date | B3: 46418
A4: Programme (months) | B4: 22
A5: Overhead and profit mark-up | B5: 0.11
A6: Retention | B6: 0.1
A7: Defects liability period (months) | B7: 12
A8: Client pays after (days) | B8: 60
A9: Liquidated damages a month (% of contract) | B9: 0.005
A10: LD cap (% of contract) | B10: 0.1
A11: Delay (months) | B11: 0
A12: Change orders (% of contract) | B12: 0.04
A13: Discount rate a year | B13: 0.09
A14: Advance payment | B14: 0.1

Sheet BOQ
A1: Item | B1: Quantity | C1: Unit rate (AED) | D1: Trade | E1: Cost (AED)
A2: Piling | B2: 18500 | C2: 1150 | D2: Substructure | E2: =B2*C2 -> 21275000
A3: Raft | B3: 9200 | C3: 2650 | D3: Substructure | E3: =B3*C3 -> 24380000
A4: Frame | B4: 41000 | C4: 1820 | D4: Structure | E4: =B4*C4 -> 74620000
A5: Facade | B5: 26500 | C5: 2400 | D5: Envelope | E5: =B5*C5 -> 63600000
A6: MEP | B6: 1 | C6: 98000000 | D6: Services | E6: =B6*C6 -> 98000000
A7: Fit-out | B7: 33000 | C7: 1350 | D7: Finishes | E7: =B7*C7 -> 44550000
A8: External works | B8: 1 | C8: 14000000 | D8: Externals | E8: =B8*C8 -> 14000000

Sheet Curve
A1: Share of programme | B1: Cumulative work
A2: 0 | B2: 0
A3: 0.1 | B3: 0.03
A4: 0.2 | B4: 0.09
A5: 0.3 | B5: 0.18
A6: 0.4 | B6: 0.3
A7: 0.5 | B7: 0.44
A8: 0.6 | B8: 0.58
A9: 0.7 | B9: 0.71
A10: 0.8 | B10: 0.83
A11: 0.9 | B11: 0.93
A12: 1 | B12: 1

Sheet Cash Flow
A3: Month | B3: 0 | C3: 1 | D3: 2 | E3: 3 | F3: 4 | G3: 5 | H3: 6 | I3: 7 | J3: 8 | K3: 9 | L3: 10 | M3: 11 | N3: 12 | O3: 13 | P3: 14 | Q3: 15 | R3: 16 | S3: 17 | T3: 18 | U3: 19 | V3: 20 | W3: 21 | X3: 22 | Y3: 23 | Z3: 24 | AA3: 25 | AB3: 26 | AC3: 27 | AD3: 28 | AE3: 29 | AF3: 30 | AG3: 31 | AH3: 32 | AI3: 33 | AJ3: 34 | AK3: 35 | AL3: 36 | AM3: 37 | AN3: 38 | AO3: 39 | AP3: 40 | AQ3: 41 | AR3: 42 | AS3: 43 | AT3: 44
A4: Date | B4: =EOMONTH(Inputs!$B$3,B$3) -> 46418 | C4: =EOMONTH(Inputs!$B$3,C$3) -> 46446 | D4: =EOMONTH(Inputs!$B$3,D$3) -> 46477 | E4: =EOMONTH(Inputs!$B$3,E$3) -> 46507 | F4: =EOMONTH(Inputs!$B$3,F$3) -> 46538 | G4: =EOMONTH(Inputs!$B$3,G$3) -> 46568 | H4: =EOMONTH(Inputs!$B$3,H$3) -> 46599 | I4: =EOMONTH(Inputs!$B$3,I$3) -> 46630 | ... AT4: =EOMONTH(Inputs!$B$3,AT$3) -> 47756
A5: Share of programme | B5: =MIN(1,B$3/(Inputs!$B$4+Inputs!$B$11)) -> 0 | C5: =MIN(1,C$3/(Inputs!$B$4+Inputs!$B$11)) -> 0.045454545 | D5: =MIN(1,D$3/(Inputs!$B$4+Inputs!$B$11)) -> 0.090909091 | E5: =MIN(1,E$3/(Inputs!$B$4+Inputs!$B$11)) -> 0.13636364 | F5: =MIN(1,F$3/(Inputs!$B$4+Inputs!$B$11)) -> 0.18181818 | G5: =MIN(1,G$3/(Inputs!$B$4+Inputs!$B$11)) -> 0.22727273 | H5: =MIN(1,H$3/(Inputs!$B$4+Inputs!$B$11)) -> 0.27272727 | I5: =MIN(1,I$3/(Inputs!$B$4+Inputs!$B$11)) -> 0.31818182 | ... AT5: =MIN(1,AT$3/(Inputs!$B$4+Inputs!$B$11)) -> 1
A6: Cumulative work | B6: =INDEX(Curve!$B$2:$B$12,MATCH(FLOOR(B5*10,1)/10,Curve!$A$2:$A$12,0))+IF(B5<1,(INDEX(Curve!$B$2:$B$12,MATCH(FLOOR(B5*10,1)/10,Curve!$A$2:$A$12,0)+1)-INDEX(Curve!$B$2:$B$12,MATCH(FLOOR(B5*10,1)/10,Curve!$A$2:$A$12,0)))*(B5*10-FLOOR(B5*10,1)),0) -> 0 | C6: =INDEX(Curve!$B$2:$B$12,MATCH(FLOOR(C5*10,1)/10,Curve!$A$2:$A$12,0))+IF(C5<1,(INDEX(Curve!$B$2:$B$12,MATCH(FLOOR(C5*10,1)/10,Curve!$A$2:$A$12,0)+1)-INDEX(Curve!$B$2:$B$12,MATCH(FLOOR(C5*10,1)/10,Curve!$A$2:$A$12,0)))*(C5*10-FLOOR(C5*10,1)),0) -> 0.013636364 | D6: =INDEX(Curve!$B$2:$B$12,MATCH(FLOOR(D5*10,1)/10,Curve!$A$2:$A$12,0))+IF(D5<1,(INDEX(Curve!$B$2:$B$12,MATCH(FLOOR(D5*10,1)/10,Curve!$A$2:$A$12,0)+1)-INDEX(Curve!$B$2:$B$12,MATCH(FLOOR(D5*10,1)/10,Curve!$A$2:$A$12,0)))*(D5*10-FLOOR(D5*10,1)),0) -> 0.027272727 | E6: =INDEX(Curve!$B$2:$B$12,MATCH(FLOOR(E5*10,1)/10,Curve!$A$2:$A$12,0))+IF(E5<1,(INDEX(Curve!$B$2:$B$12,MATCH(FLOOR(E5*10,1)/10,Curve!$A$2:$A$12,0)+1)-INDEX(Curve!$B$2:$B$12,MATCH(FLOOR(E5*10,1)/10,Curve!$A$2:$A$12,0)))*(E5*10-FLOOR(E5*10,1)),0) -> 0.051818182 | F6: =INDEX(Curve!$B$2:$B$12,MATCH(FLOOR(F5*10,1)/10,Curve!$A$2:$A$12,0))+IF(F5<1,(INDEX(Curve!$B$2:$B$12,MATCH(FLOOR(F5*10,1)/10,Curve!$A$2:$A$12,0)+1)-INDEX(Curve!$B$2:$B$12,MATCH(FLOOR(F5*10,1)/10,Curve!$A$2:$A$12,0)))*(F5*10-FLOOR(F5*10,1)),0) -> 0.079090909 | G6: =INDEX(Curve!$B$2:$B$12,MATCH(FLOOR(G5*10,1)/10,Curve!$A$2:$A$12,0))+IF(G5<1,(INDEX(Curve!$B$2:$B$12,MATCH(FLOOR(G5*10,1)/10,Curve!$A$2:$A$12,0)+1)-INDEX(Curve!$B$2:$B$12,MATCH(FLOOR(G5*10,1)/10,Curve!$A$2:$A$12,0)))*(G5*10-FLOOR(G5*10,1)),0) -> 0.11454545 | H6: =INDEX(Curve!$B$2:$B$12,MATCH(FLOOR(H5*10,1)/10,Curve!$A$2:$A$12,0))+IF(H5<1,(INDEX(Curve!$B$2:$B$12,MATCH(FLOOR(H5*10,1)/10,Curve!$A$2:$A$12,0)+1)-INDEX(Curve!$B$2:$B$12,MATCH(FLOOR(H5*10,1)/10,Curve!$A$2:$A$12,0)))*(H5*10-FLOOR(H5*10,1)),0) -> 0.15545455 | I6: =INDEX(Curve!$B$2:$B$12,MATCH(FLOOR(I5*10,1)/10,Curve!$A$2:$A$12,0))+IF(I5<1,(INDEX(Curve!$B$2:$B$12,MATCH(FLOOR(I5*10,1)/10,Curve!$A$2:$A$12,0)+1)-INDEX(Curve!$B$2:$B$12,MATCH(FLOOR(I5*10,1)/10,Curve!$A$2:$A$12,0)))*(I5*10-FLOOR(I5*10,1)),0) -> 0.20181818 | ... AT6: =INDEX(Curve!$B$2:$B$12,MATCH(FLOOR(AT5*10,1)/10,Curve!$A$2:$A$12,0))+IF(AT5<1,(INDEX(Curve!$B$2:$B$12,MATCH(FLOOR(AT5*10,1)/10,Curve!$A$2:$A$12,0)+1)-INDEX(Curve!$B$2:$B$12,MATCH(FLOOR(AT5*10,1)/10,Curve!$A$2:$A$12,0)))*(AT5*10-FLOOR(AT5*10,1)),0) -> 1
A7: Cost incurred | B7: =0 -> 0 | C7: =SUM(BOQ!$E$2:$E$8)*(1+Inputs!$B$12)*(C6-B6) -> 4827845.5 | D7: =SUM(BOQ!$E$2:$E$8)*(1+Inputs!$B$12)*(D6-C6) -> 4827845.5 | E7: =SUM(BOQ!$E$2:$E$8)*(1+Inputs!$B$12)*(E6-D6) -> 8690121.8 | F7: =SUM(BOQ!$E$2:$E$8)*(1+Inputs!$B$12)*(F6-E6) -> 9655690.9 | G7: =SUM(BOQ!$E$2:$E$8)*(1+Inputs!$B$12)*(G6-F6) -> 12552398 | H7: =SUM(BOQ!$E$2:$E$8)*(1+Inputs!$B$12)*(H6-G6) -> 14483536 | I7: =SUM(BOQ!$E$2:$E$8)*(1+Inputs!$B$12)*(I6-H6) -> 16414675 | J7: =SUM(BOQ!$E$2:$E$8)*(1+Inputs!$B$12)*(J6-I6) -> 19311382 | ... AT7: =SUM(BOQ!$E$2:$E$8)*(1+Inputs!$B$12)*(AT6-AS6) -> 0
A8: Valuation | B8: =0 -> 0 | C8: =(SUM(BOQ!$E$2:$E$8)*(1+Inputs!$B$5)*(1+Inputs!$B$12))*(C6-B6) -> 5358908.5 | D8: =(SUM(BOQ!$E$2:$E$8)*(1+Inputs!$B$5)*(1+Inputs!$B$12))*(D6-C6) -> 5358908.5 | E8: =(SUM(BOQ!$E$2:$E$8)*(1+Inputs!$B$5)*(1+Inputs!$B$12))*(E6-D6) -> 9646035.2 | F8: =(SUM(BOQ!$E$2:$E$8)*(1+Inputs!$B$5)*(1+Inputs!$B$12))*(F6-E6) -> 10717817 | G8: =(SUM(BOQ!$E$2:$E$8)*(1+Inputs!$B$5)*(1+Inputs!$B$12))*(G6-F6) -> 13933162 | H8: =(SUM(BOQ!$E$2:$E$8)*(1+Inputs!$B$5)*(1+Inputs!$B$12))*(H6-G6) -> 16076725 | I8: =(SUM(BOQ!$E$2:$E$8)*(1+Inputs!$B$5)*(1+Inputs!$B$12))*(I6-H6) -> 18220289 | J8: =(SUM(BOQ!$E$2:$E$8)*(1+Inputs!$B$5)*(1+Inputs!$B$12))*(J6-I6) -> 21435634 | ... AT8: =(SUM(BOQ!$E$2:$E$8)*(1+Inputs!$B$5)*(1+Inputs!$B$12))*(AT6-AS6) -> 0
A9: Advance recovery | B9: =B8*Inputs!$B$14 -> 0 | C9: =C8*Inputs!$B$14 -> 535890.85 | D9: =D8*Inputs!$B$14 -> 535890.85 | E9: =E8*Inputs!$B$14 -> 964603.52 | F9: =F8*Inputs!$B$14 -> 1071781.7 | G9: =G8*Inputs!$B$14 -> 1393316.2 | H9: =H8*Inputs!$B$14 -> 1607672.5 | I9: =I8*Inputs!$B$14 -> 1822028.9 | ... AT9: =AT8*Inputs!$B$14 -> 0
A10: Retention held | B10: =B8*Inputs!$B$6 -> 0 | C10: =C8*Inputs!$B$6 -> 535890.85 | D10: =D8*Inputs!$B$6 -> 535890.85 | E10: =E8*Inputs!$B$6 -> 964603.52 | F10: =F8*Inputs!$B$6 -> 1071781.7 | G10: =G8*Inputs!$B$6 -> 1393316.2 | H10: =H8*Inputs!$B$6 -> 1607672.5 | I10: =I8*Inputs!$B$6 -> 1822028.9 | ... AT10: =AT8*Inputs!$B$6 -> 0
A11: Certified net | B11: =B8-B9-B10 -> 0 | C11: =C8-C9-C10 -> 4287126.8 | D11: =D8-D9-D10 -> 4287126.8 | E11: =E8-E9-E10 -> 7716828.2 | F11: =F8-F9-F10 -> 8574253.5 | G11: =G8-G9-G10 -> 11146530 | H11: =H8-H9-H10 -> 12861380 | I11: =I8-I9-I10 -> 14576231 | ... AT11: =AT8-AT9-AT10 -> 0
A12: Client payment | B12: =0 -> 0 | C12: =IF(C$3>ROUNDUP(Inputs!$B$8/30,0),OFFSET(C11,0,-ROUNDUP(Inputs!$B$8/30,0)),0) -> 0 | D12: =IF(D$3>ROUNDUP(Inputs!$B$8/30,0),OFFSET(D11,0,-ROUNDUP(Inputs!$B$8/30,0)),0) -> 0 | E12: =IF(E$3>ROUNDUP(Inputs!$B$8/30,0),OFFSET(E11,0,-ROUNDUP(Inputs!$B$8/30,0)),0) -> 4287126.8 | F12: =IF(F$3>ROUNDUP(Inputs!$B$8/30,0),OFFSET(F11,0,-ROUNDUP(Inputs!$B$8/30,0)),0) -> 4287126.8 | G12: =IF(G$3>ROUNDUP(Inputs!$B$8/30,0),OFFSET(G11,0,-ROUNDUP(Inputs!$B$8/30,0)),0) -> 7716828.2 | H12: =IF(H$3>ROUNDUP(Inputs!$B$8/30,0),OFFSET(H11,0,-ROUNDUP(Inputs!$B$8/30,0)),0) -> 8574253.5 | I12: =IF(I$3>ROUNDUP(Inputs!$B$8/30,0),OFFSET(I11,0,-ROUNDUP(Inputs!$B$8/30,0)),0) -> 11146530 | J12: =IF(J$3>ROUNDUP(Inputs!$B$8/30,0),OFFSET(J11,0,-ROUNDUP(Inputs!$B$8/30,0)),0) -> 12861380 | ... AT12: =IF(AT$3>ROUNDUP(Inputs!$B$8/30,0),OFFSET(AT11,0,-ROUNDUP(Inputs!$B$8/30,0)),0) -> 0
A13: Retention release | B13: =IF(B$3=(Inputs!$B$4+Inputs!$B$11),SUM($B$10:B10)/2,0)+IF(B$3=(Inputs!$B$4+Inputs!$B$11)+Inputs!$B$7,SUM($B$10:$AT$10)/2,0) -> 0 | C13: =IF(C$3=(Inputs!$B$4+Inputs!$B$11),SUM($B$10:C10)/2,0)+IF(C$3=(Inputs!$B$4+Inputs!$B$11)+Inputs!$B$7,SUM($B$10:$AT$10)/2,0) -> 0 | D13: =IF(D$3=(Inputs!$B$4+Inputs!$B$11),SUM($B$10:D10)/2,0)+IF(D$3=(Inputs!$B$4+Inputs!$B$11)+Inputs!$B$7,SUM($B$10:$AT$10)/2,0) -> 0 | E13: =IF(E$3=(Inputs!$B$4+Inputs!$B$11),SUM($B$10:E10)/2,0)+IF(E$3=(Inputs!$B$4+Inputs!$B$11)+Inputs!$B$7,SUM($B$10:$AT$10)/2,0) -> 0 | F13: =IF(F$3=(Inputs!$B$4+Inputs!$B$11),SUM($B$10:F10)/2,0)+IF(F$3=(Inputs!$B$4+Inputs!$B$11)+Inputs!$B$7,SUM($B$10:$AT$10)/2,0) -> 0 | G13: =IF(G$3=(Inputs!$B$4+Inputs!$B$11),SUM($B$10:G10)/2,0)+IF(G$3=(Inputs!$B$4+Inputs!$B$11)+Inputs!$B$7,SUM($B$10:$AT$10)/2,0) -> 0 | H13: =IF(H$3=(Inputs!$B$4+Inputs!$B$11),SUM($B$10:H10)/2,0)+IF(H$3=(Inputs!$B$4+Inputs!$B$11)+Inputs!$B$7,SUM($B$10:$AT$10)/2,0) -> 0 | I13: =IF(I$3=(Inputs!$B$4+Inputs!$B$11),SUM($B$10:I10)/2,0)+IF(I$3=(Inputs!$B$4+Inputs!$B$11)+Inputs!$B$7,SUM($B$10:$AT$10)/2,0) -> 0 | ... AT13: =IF(AT$3=(Inputs!$B$4+Inputs!$B$11),SUM($B$10:AT10)/2,0)+IF(AT$3=(Inputs!$B$4+Inputs!$B$11)+Inputs!$B$7,SUM($B$10:$AT$10)/2,0) -> 0
A14: Advance received | B14: =IF(B$3=0,(SUM(BOQ!$E$2:$E$8)*(1+Inputs!$B$5)*(1+Inputs!$B$12))*Inputs!$B$14,0) -> 39298662 | C14: =IF(C$3=0,(SUM(BOQ!$E$2:$E$8)*(1+Inputs!$B$5)*(1+Inputs!$B$12))*Inputs!$B$14,0) -> 0 | D14: =IF(D$3=0,(SUM(BOQ!$E$2:$E$8)*(1+Inputs!$B$5)*(1+Inputs!$B$12))*Inputs!$B$14,0) -> 0 | E14: =IF(E$3=0,(SUM(BOQ!$E$2:$E$8)*(1+Inputs!$B$5)*(1+Inputs!$B$12))*Inputs!$B$14,0) -> 0 | F14: =IF(F$3=0,(SUM(BOQ!$E$2:$E$8)*(1+Inputs!$B$5)*(1+Inputs!$B$12))*Inputs!$B$14,0) -> 0 | G14: =IF(G$3=0,(SUM(BOQ!$E$2:$E$8)*(1+Inputs!$B$5)*(1+Inputs!$B$12))*Inputs!$B$14,0) -> 0 | H14: =IF(H$3=0,(SUM(BOQ!$E$2:$E$8)*(1+Inputs!$B$5)*(1+Inputs!$B$12))*Inputs!$B$14,0) -> 0 | I14: =IF(I$3=0,(SUM(BOQ!$E$2:$E$8)*(1+Inputs!$B$5)*(1+Inputs!$B$12))*Inputs!$B$14,0) -> 0 | ... AT14: =IF(AT$3=0,(SUM(BOQ!$E$2:$E$8)*(1+Inputs!$B$5)*(1+Inputs!$B$12))*Inputs!$B$14,0) -> 0
A15: LDs | B15: =IF(B$3=(Inputs!$B$4+Inputs!$B$11),MIN(Inputs!$B$10,Inputs!$B$9*Inputs!$B$11)*(SUM(BOQ!$E$2:$E$8)*(1+Inputs!$B$5)*(1+Inputs!$B$12)),0) -> 0 | C15: =IF(C$3=(Inputs!$B$4+Inputs!$B$11),MIN(Inputs!$B$10,Inputs!$B$9*Inputs!$B$11)*(SUM(BOQ!$E$2:$E$8)*(1+Inputs!$B$5)*(1+Inputs!$B$12)),0) -> 0 | D15: =IF(D$3=(Inputs!$B$4+Inputs!$B$11),MIN(Inputs!$B$10,Inputs!$B$9*Inputs!$B$11)*(SUM(BOQ!$E$2:$E$8)*(1+Inputs!$B$5)*(1+Inputs!$B$12)),0) -> 0 | E15: =IF(E$3=(Inputs!$B$4+Inputs!$B$11),MIN(Inputs!$B$10,Inputs!$B$9*Inputs!$B$11)*(SUM(BOQ!$E$2:$E$8)*(1+Inputs!$B$5)*(1+Inputs!$B$12)),0) -> 0 | F15: =IF(F$3=(Inputs!$B$4+Inputs!$B$11),MIN(Inputs!$B$10,Inputs!$B$9*Inputs!$B$11)*(SUM(BOQ!$E$2:$E$8)*(1+Inputs!$B$5)*(1+Inputs!$B$12)),0) -> 0 | G15: =IF(G$3=(Inputs!$B$4+Inputs!$B$11),MIN(Inputs!$B$10,Inputs!$B$9*Inputs!$B$11)*(SUM(BOQ!$E$2:$E$8)*(1+Inputs!$B$5)*(1+Inputs!$B$12)),0) -> 0 | H15: =IF(H$3=(Inputs!$B$4+Inputs!$B$11),MIN(Inputs!$B$10,Inputs!$B$9*Inputs!$B$11)*(SUM(BOQ!$E$2:$E$8)*(1+Inputs!$B$5)*(1+Inputs!$B$12)),0) -> 0 | I15: =IF(I$3=(Inputs!$B$4+Inputs!$B$11),MIN(Inputs!$B$10,Inputs!$B$9*Inputs!$B$11)*(SUM(BOQ!$E$2:$E$8)*(1+Inputs!$B$5)*(1+Inputs!$B$12)),0) -> 0 | ... AT15: =IF(AT$3=(Inputs!$B$4+Inputs!$B$11),MIN(Inputs!$B$10,Inputs!$B$9*Inputs!$B$11)*(SUM(BOQ!$E$2:$E$8)*(1+Inputs!$B$5)*(1+Inputs!$B$12)),0) -> 0
A16: Contractor cash flow | B16: =B12+B13+B14-B7-B15 -> 39298662 | C16: =C12+C13+C14-C7-C15 -> -4827845.5 | D16: =D12+D13+D14-D7-D15 -> -4827845.5 | E16: =E12+E13+E14-E7-E15 -> -4402995.1 | F16: =F12+F13+F14-F7-F15 -> -5368564.1 | G16: =G12+G13+G14-G7-G15 -> -4835570 | H16: =H12+H13+H14-H7-H15 -> -5909282.8 | I16: =I12+I13+I14-I7-I15 -> -5268145 | ... AT16: =AT12+AT13+AT14-AT7-AT15 -> 0
A17: Cumulative cash | B17: =SUM($B$16:B16) -> 39298662 | C17: =SUM($B$16:C16) -> 34470817 | D17: =SUM($B$16:D16) -> 29642971 | E17: =SUM($B$16:E16) -> 25239976 | F17: =SUM($B$16:F16) -> 19871412 | G17: =SUM($B$16:G16) -> 15035842 | H17: =SUM($B$16:H16) -> 9126559 | I17: =SUM($B$16:I16) -> 3858414.1 | ... AT17: =SUM($B$16:AT16) -> 38944620

Sheet Returns
A3: Contract sum (AED) | B3: =SUM(BOQ!$E$2:$E$8)*(1+Inputs!$B$5)*(1+Inputs!$B$12) -> 392986620
A4: Margin (AED) | B4: =SUM('Cash Flow'!$B$16:$AT$16) -> 38944620
A5: Margin on contract | B5: =B4/B3 -> 0.099099099
A6: Peak negative cash (AED) | B6: =-MIN('Cash Flow'!$B$17:$AT$17) -> 27487821
A7: NPV of the contract (AED) | B7: =NPV((1+Inputs!$B$13)^(1/12)-1,'Cash Flow'!$B$16:$AT$16) -> 30841371
A8: LDs (AED) | B8: =SUM('Cash Flow'!$B$15:$AT$15) -> 0
A9: Structure and envelope cost (AED) | B9: =SUMPRODUCT(((BOQ!$D$2:$D$8="Structure")+(BOQ!$D$2:$D$8="Envelope")>0)*BOQ!$E$2:$E$8) -> 138220000
A10: Net profit (AED) | B10: =B4 -> 38944620
