Workbook

Sheet Inputs
A1: SPREE QUARTIER – BERLIN RESIDENTIAL PORTFOLIO, MONTHLY (EUR)
A3: Acquisition date | B3: 46387
A4: Purchase price (€) | B4: 412000000
A5: Purchase costs | B5: 0.085
A6: Market rent (€/sqm/month) | B6: 16.5
A7: Market rent growth a year | B7: 0.035
A8: Rent cap (max increase over 3 years) | B8: 0.15
A9: Tenant turnover a year | B9: 0.08
A10: Non-recoverable costs (% of rent) | B10: 0.12
A11: Loan to value | B11: 0.55
A12: Interest rate | B12: 0.041
A13: Interest-only (months) | B13: 60
A14: Amortisation a year after interest-only | B14: 0.02
... A16: Refurbishment (€/sqm) | B16: 420

Sheet Groups
A1: Group | B1: Lettable area (sqm) | C1: In-place rent (€/sqm/month) | D1: Refurbishment cycle (years) | E1: First refurbishment (month)
A2: Altbau Mitte | B2: 38000 | C2: 11.2 | D2: 8 | E2: 14
A3: Plattenbau Ost | B3: 52000 | C3: 8.9 | D3: 8 | E3: 30
A4: Neubau Nord | B4: 21000 | C4: 14.8 | D4: 10 | E4: 70
A5: Gründerzeit West | B5: 29000 | C5: 12.6 | D5: 8 | E5: 48

Sheet Cash Flow
A3: Month | B3: 0 | C3: 1 | D3: 2 | E3: 3 | F3: 4 | G3: 5 | H3: 6 | I3: 7 | J3: 8 | K3: 9 | L3: 10 | M3: 11 | N3: 12 | O3: 13 | P3: 14 | Q3: 15 | R3: 16 | S3: 17 | T3: 18 | U3: 19 | V3: 20 | W3: 21 | X3: 22 | Y3: 23 | Z3: 24 | AA3: 25 | AB3: 26 | AC3: 27 | AD3: 28 | AE3: 29 | AF3: 30 | AG3: 31 | AH3: 32 | AI3: 33 | AJ3: 34 | AK3: 35 | AL3: 36 | AM3: 37 | AN3: 38 | AO3: 39 | AP3: 40 | AQ3: 41 | AR3: 42 | AS3: 43 | AT3: 44 | AU3: 45 | AV3: 46 | AW3: 47 | AX3: 48 | AY3: 49 | AZ3: 50 | BA3: 51 | BB3: 52 | BC3: 53 | BD3: 54 | BE3: 55 | BF3: 56 | BG3: 57 | BH3: 58 | BI3: 59 | BJ3: 60 | BK3: 61 | BL3: 62 | BM3: 63 | BN3: 64 | BO3: 65 | BP3: 66 | BQ3: 67 | BR3: 68 | BS3: 69 | BT3: 70 | BU3: 71 | BV3: 72 | BW3: 73 | BX3: 74 | BY3: 75 | BZ3: 76 | CA3: 77 | CB3: 78 | CC3: 79 | CD3: 80 | CE3: 81 | CF3: 82 | CG3: 83 | CH3: 84 | CI3: 85 | CJ3: 86 | CK3: 87 | CL3: 88 | CM3: 89 | CN3: 90 | CO3: 91 | CP3: 92 | CQ3: 93 | CR3: 94 | CS3: 95 | CT3: 96 | CU3: 97 | CV3: 98 | CW3: 99 | CX3: 100 | CY3: 101 | CZ3: 102 | DA3: 103 | DB3: 104 | DC3: 105 | DD3: 106 | DE3: 107 | DF3: 108 | DG3: 109 | DH3: 110 | DI3: 111 | DJ3: 112 | DK3: 113 | DL3: 114 | DM3: 115 | DN3: 116 | DO3: 117 | DP3: 118 | DQ3: 119 | DR3: 120 | DS3: 121 | DT3: 122 | DU3: 123 | DV3: 124 | DW3: 125 | DX3: 126 | DY3: 127 | DZ3: 128 | EA3: 129 | EB3: 130 | EC3: 131 | ED3: 132 | EE3: 133 | EF3: 134 | EG3: 135 | EH3: 136 | EI3: 137 | EJ3: 138 | EK3: 139 | EL3: 140 | EM3: 141 | EN3: 142 | EO3: 143 | EP3: 144 | EQ3: 145 | ER3: 146 | ES3: 147 | ET3: 148 | EU3: 149 | EV3: 150 | EW3: 151 | EX3: 152 | EY3: 153 | EZ3: 154 | FA3: 155 | FB3: 156 | FC3: 157 | FD3: 158 | FE3: 159 | FF3: 160 | FG3: 161 | FH3: 162 | FI3: 163 | FJ3: 164 | FK3: 165 | FL3: 166 | FM3: 167 | FN3: 168 | FO3: 169 | FP3: 170 | FQ3: 171 | FR3: 172 | FS3: 173 | FT3: 174 | FU3: 175 | FV3: 176 | FW3: 177 | FX3: 178 | FY3: 179 | FZ3: 180
A4: Date | B4: =EOMONTH(Inputs!$B$3,B$3) -> 46387 | C4: =EOMONTH(Inputs!$B$3,C$3) -> 46418 | D4: =EOMONTH(Inputs!$B$3,D$3) -> 46446 | E4: =EOMONTH(Inputs!$B$3,E$3) -> 46477 | F4: =EOMONTH(Inputs!$B$3,F$3) -> 46507 | G4: =EOMONTH(Inputs!$B$3,G$3) -> 46538 | H4: =EOMONTH(Inputs!$B$3,H$3) -> 46568 | I4: =EOMONTH(Inputs!$B$3,I$3) -> 46599 | ... FZ4: =EOMONTH(Inputs!$B$3,FZ$3) -> 51866
A5: Market rent | B5: =Inputs!$B$6*(1+Inputs!$B$7)^(B$3/12) -> 16.5 | C5: =Inputs!$B$6*(1+Inputs!$B$7)^(C$3/12) -> 16.54737 | D5: =Inputs!$B$6*(1+Inputs!$B$7)^(D$3/12) -> 16.594876 | E5: =Inputs!$B$6*(1+Inputs!$B$7)^(E$3/12) -> 16.642518 | F5: =Inputs!$B$6*(1+Inputs!$B$7)^(F$3/12) -> 16.690297 | G5: =Inputs!$B$6*(1+Inputs!$B$7)^(G$3/12) -> 16.738213 | H5: =Inputs!$B$6*(1+Inputs!$B$7)^(H$3/12) -> 16.786267 | I5: =Inputs!$B$6*(1+Inputs!$B$7)^(I$3/12) -> 16.834458 | ... FZ5: =Inputs!$B$6*(1+Inputs!$B$7)^(FZ$3/12) -> 27.643256
A6: Rent 1 | B6: =Groups!$C$2 -> 11.2 | C6: =MIN(C5,B6*(1-Inputs!$B$9/12)*(1+Inputs!$B$8)^(1/36)+C5*Inputs!$B$9/12) -> 11.278925 | D6: =MIN(D5,C6*(1-Inputs!$B$9/12)*(1+Inputs!$B$8)^(1/36)+D5*Inputs!$B$9/12) -> 11.357945 | E6: =MIN(E5,D6*(1-Inputs!$B$9/12)*(1+Inputs!$B$8)^(1/36)+E5*Inputs!$B$9/12) -> 11.437061 | F6: =MIN(F5,E6*(1-Inputs!$B$9/12)*(1+Inputs!$B$8)^(1/36)+F5*Inputs!$B$9/12) -> 11.516274 | G6: =MIN(G5,F6*(1-Inputs!$B$9/12)*(1+Inputs!$B$8)^(1/36)+G5*Inputs!$B$9/12) -> 11.595585 | H6: =MIN(H5,G6*(1-Inputs!$B$9/12)*(1+Inputs!$B$8)^(1/36)+H5*Inputs!$B$9/12) -> 11.674993 | I6: =MIN(I5,H6*(1-Inputs!$B$9/12)*(1+Inputs!$B$8)^(1/36)+I5*Inputs!$B$9/12) -> 11.754501 | J6: =MIN(J5,I6*(1-Inputs!$B$9/12)*(1+Inputs!$B$8)^(1/36)+J5*Inputs!$B$9/12) -> 11.834107 | ... FZ6: =MIN(FZ5,FY6*(1-Inputs!$B$9/12)*(1+Inputs!$B$8)^(1/36)+FZ5*Inputs!$B$9/12) -> 27.600623
A7: Refurb 1 | B7: =IF(AND(B$3>=Groups!$E$2,MOD(B$3-Groups!$E$2,Groups!$D$2*12)=0),Groups!$B$2*Inputs!$B$16,0) -> 0 | C7: =IF(AND(C$3>=Groups!$E$2,MOD(C$3-Groups!$E$2,Groups!$D$2*12)=0),Groups!$B$2*Inputs!$B$16,0) -> 0 | D7: =IF(AND(D$3>=Groups!$E$2,MOD(D$3-Groups!$E$2,Groups!$D$2*12)=0),Groups!$B$2*Inputs!$B$16,0) -> 0 | E7: =IF(AND(E$3>=Groups!$E$2,MOD(E$3-Groups!$E$2,Groups!$D$2*12)=0),Groups!$B$2*Inputs!$B$16,0) -> 0 | F7: =IF(AND(F$3>=Groups!$E$2,MOD(F$3-Groups!$E$2,Groups!$D$2*12)=0),Groups!$B$2*Inputs!$B$16,0) -> 0 | G7: =IF(AND(G$3>=Groups!$E$2,MOD(G$3-Groups!$E$2,Groups!$D$2*12)=0),Groups!$B$2*Inputs!$B$16,0) -> 0 | H7: =IF(AND(H$3>=Groups!$E$2,MOD(H$3-Groups!$E$2,Groups!$D$2*12)=0),Groups!$B$2*Inputs!$B$16,0) -> 0 | I7: =IF(AND(I$3>=Groups!$E$2,MOD(I$3-Groups!$E$2,Groups!$D$2*12)=0),Groups!$B$2*Inputs!$B$16,0) -> 0 | ... FZ7: =IF(AND(FZ$3>=Groups!$E$2,MOD(FZ$3-Groups!$E$2,Groups!$D$2*12)=0),Groups!$B$2*Inputs!$B$16,0) -> 0
A8: Rent 2 | B8: =Groups!$C$3 -> 8.9 | C8: =MIN(C5,B8*(1-Inputs!$B$9/12)*(1+Inputs!$B$8)^(1/36)+C5*Inputs!$B$9/12) -> 8.9853711 | D8: =MIN(D5,C8*(1-Inputs!$B$9/12)*(1+Inputs!$B$8)^(1/36)+D5*Inputs!$B$9/12) -> 9.0708196 | E8: =MIN(E5,D8*(1-Inputs!$B$9/12)*(1+Inputs!$B$8)^(1/36)+E5*Inputs!$B$9/12) -> 9.1563462 | F8: =MIN(F5,E8*(1-Inputs!$B$9/12)*(1+Inputs!$B$8)^(1/36)+F5*Inputs!$B$9/12) -> 9.2419517 | G8: =MIN(G5,F8*(1-Inputs!$B$9/12)*(1+Inputs!$B$8)^(1/36)+G5*Inputs!$B$9/12) -> 9.3276366 | H8: =MIN(H5,G8*(1-Inputs!$B$9/12)*(1+Inputs!$B$8)^(1/36)+H5*Inputs!$B$9/12) -> 9.4134018 | I8: =MIN(I5,H8*(1-Inputs!$B$9/12)*(1+Inputs!$B$8)^(1/36)+I5*Inputs!$B$9/12) -> 9.4992479 | J8: =MIN(J5,I8*(1-Inputs!$B$9/12)*(1+Inputs!$B$8)^(1/36)+J5*Inputs!$B$9/12) -> 9.5851755 | ... FZ8: =MIN(FZ5,FY8*(1-Inputs!$B$9/12)*(1+Inputs!$B$8)^(1/36)+FZ5*Inputs!$B$9/12) -> 26.212849
A9: Refurb 2 | B9: =IF(AND(B$3>=Groups!$E$3,MOD(B$3-Groups!$E$3,Groups!$D$3*12)=0),Groups!$B$3*Inputs!$B$16,0) -> 0 | C9: =IF(AND(C$3>=Groups!$E$3,MOD(C$3-Groups!$E$3,Groups!$D$3*12)=0),Groups!$B$3*Inputs!$B$16,0) -> 0 | D9: =IF(AND(D$3>=Groups!$E$3,MOD(D$3-Groups!$E$3,Groups!$D$3*12)=0),Groups!$B$3*Inputs!$B$16,0) -> 0 | E9: =IF(AND(E$3>=Groups!$E$3,MOD(E$3-Groups!$E$3,Groups!$D$3*12)=0),Groups!$B$3*Inputs!$B$16,0) -> 0 | F9: =IF(AND(F$3>=Groups!$E$3,MOD(F$3-Groups!$E$3,Groups!$D$3*12)=0),Groups!$B$3*Inputs!$B$16,0) -> 0 | G9: =IF(AND(G$3>=Groups!$E$3,MOD(G$3-Groups!$E$3,Groups!$D$3*12)=0),Groups!$B$3*Inputs!$B$16,0) -> 0 | H9: =IF(AND(H$3>=Groups!$E$3,MOD(H$3-Groups!$E$3,Groups!$D$3*12)=0),Groups!$B$3*Inputs!$B$16,0) -> 0 | I9: =IF(AND(I$3>=Groups!$E$3,MOD(I$3-Groups!$E$3,Groups!$D$3*12)=0),Groups!$B$3*Inputs!$B$16,0) -> 0 | ... FZ9: =IF(AND(FZ$3>=Groups!$E$3,MOD(FZ$3-Groups!$E$3,Groups!$D$3*12)=0),Groups!$B$3*Inputs!$B$16,0) -> 0
A10: Rent 3 | B10: =Groups!$C$4 -> 14.8 | C10: =MIN(C5,B10*(1-Inputs!$B$9/12)*(1+Inputs!$B$8)^(1/36)+C5*Inputs!$B$9/12) -> 14.868835 | D10: =MIN(D5,C10*(1-Inputs!$B$9/12)*(1+Inputs!$B$8)^(1/36)+D5*Inputs!$B$9/12) -> 14.937793 | E10: =MIN(E5,D10*(1-Inputs!$B$9/12)*(1+Inputs!$B$8)^(1/36)+E5*Inputs!$B$9/12) -> 15.006876 | F10: =MIN(F5,E10*(1-Inputs!$B$9/12)*(1+Inputs!$B$8)^(1/36)+F5*Inputs!$B$9/12) -> 15.076084 | G10: =MIN(G5,F10*(1-Inputs!$B$9/12)*(1+Inputs!$B$8)^(1/36)+G5*Inputs!$B$9/12) -> 15.145417 | H10: =MIN(H5,G10*(1-Inputs!$B$9/12)*(1+Inputs!$B$8)^(1/36)+H5*Inputs!$B$9/12) -> 15.214876 | I10: =MIN(I5,H10*(1-Inputs!$B$9/12)*(1+Inputs!$B$8)^(1/36)+I5*Inputs!$B$9/12) -> 15.284462 | J10: =MIN(J5,I10*(1-Inputs!$B$9/12)*(1+Inputs!$B$8)^(1/36)+J5*Inputs!$B$9/12) -> 15.354175 | ... FZ10: =MIN(FZ5,FY10*(1-Inputs!$B$9/12)*(1+Inputs!$B$8)^(1/36)+FZ5*Inputs!$B$9/12) -> 27.643256
A11: Refurb 3 | B11: =IF(AND(B$3>=Groups!$E$4,MOD(B$3-Groups!$E$4,Groups!$D$4*12)=0),Groups!$B$4*Inputs!$B$16,0) -> 0 | C11: =IF(AND(C$3>=Groups!$E$4,MOD(C$3-Groups!$E$4,Groups!$D$4*12)=0),Groups!$B$4*Inputs!$B$16,0) -> 0 | D11: =IF(AND(D$3>=Groups!$E$4,MOD(D$3-Groups!$E$4,Groups!$D$4*12)=0),Groups!$B$4*Inputs!$B$16,0) -> 0 | E11: =IF(AND(E$3>=Groups!$E$4,MOD(E$3-Groups!$E$4,Groups!$D$4*12)=0),Groups!$B$4*Inputs!$B$16,0) -> 0 | F11: =IF(AND(F$3>=Groups!$E$4,MOD(F$3-Groups!$E$4,Groups!$D$4*12)=0),Groups!$B$4*Inputs!$B$16,0) -> 0 | G11: =IF(AND(G$3>=Groups!$E$4,MOD(G$3-Groups!$E$4,Groups!$D$4*12)=0),Groups!$B$4*Inputs!$B$16,0) -> 0 | H11: =IF(AND(H$3>=Groups!$E$4,MOD(H$3-Groups!$E$4,Groups!$D$4*12)=0),Groups!$B$4*Inputs!$B$16,0) -> 0 | I11: =IF(AND(I$3>=Groups!$E$4,MOD(I$3-Groups!$E$4,Groups!$D$4*12)=0),Groups!$B$4*Inputs!$B$16,0) -> 0 | ... FZ11: =IF(AND(FZ$3>=Groups!$E$4,MOD(FZ$3-Groups!$E$4,Groups!$D$4*12)=0),Groups!$B$4*Inputs!$B$16,0) -> 0
A12: Rent 4 | B12: =Groups!$C$5 -> 12.6 | C12: =MIN(C5,B12*(1-Inputs!$B$9/12)*(1+Inputs!$B$8)^(1/36)+C5*Inputs!$B$9/12) -> 12.675001 | D12: =MIN(D5,C12*(1-Inputs!$B$9/12)*(1+Inputs!$B$8)^(1/36)+D5*Inputs!$B$9/12) -> 12.750108 | E12: =MIN(E5,D12*(1-Inputs!$B$9/12)*(1+Inputs!$B$8)^(1/36)+E5*Inputs!$B$9/12) -> 12.825323 | F12: =MIN(F5,E12*(1-Inputs!$B$9/12)*(1+Inputs!$B$8)^(1/36)+F5*Inputs!$B$9/12) -> 12.900645 | G12: =MIN(G5,F12*(1-Inputs!$B$9/12)*(1+Inputs!$B$8)^(1/36)+G5*Inputs!$B$9/12) -> 12.976075 | H12: =MIN(H5,G12*(1-Inputs!$B$9/12)*(1+Inputs!$B$8)^(1/36)+H5*Inputs!$B$9/12) -> 13.051615 | I12: =MIN(I5,H12*(1-Inputs!$B$9/12)*(1+Inputs!$B$8)^(1/36)+I5*Inputs!$B$9/12) -> 13.127263 | J12: =MIN(J5,I12*(1-Inputs!$B$9/12)*(1+Inputs!$B$8)^(1/36)+J5*Inputs!$B$9/12) -> 13.203023 | ... FZ12: =MIN(FZ5,FY12*(1-Inputs!$B$9/12)*(1+Inputs!$B$8)^(1/36)+FZ5*Inputs!$B$9/12) -> 27.643256
A13: Refurb 4 | B13: =IF(AND(B$3>=Groups!$E$5,MOD(B$3-Groups!$E$5,Groups!$D$5*12)=0),Groups!$B$5*Inputs!$B$16,0) -> 0 | C13: =IF(AND(C$3>=Groups!$E$5,MOD(C$3-Groups!$E$5,Groups!$D$5*12)=0),Groups!$B$5*Inputs!$B$16,0) -> 0 | D13: =IF(AND(D$3>=Groups!$E$5,MOD(D$3-Groups!$E$5,Groups!$D$5*12)=0),Groups!$B$5*Inputs!$B$16,0) -> 0 | E13: =IF(AND(E$3>=Groups!$E$5,MOD(E$3-Groups!$E$5,Groups!$D$5*12)=0),Groups!$B$5*Inputs!$B$16,0) -> 0 | F13: =IF(AND(F$3>=Groups!$E$5,MOD(F$3-Groups!$E$5,Groups!$D$5*12)=0),Groups!$B$5*Inputs!$B$16,0) -> 0 | G13: =IF(AND(G$3>=Groups!$E$5,MOD(G$3-Groups!$E$5,Groups!$D$5*12)=0),Groups!$B$5*Inputs!$B$16,0) -> 0 | H13: =IF(AND(H$3>=Groups!$E$5,MOD(H$3-Groups!$E$5,Groups!$D$5*12)=0),Groups!$B$5*Inputs!$B$16,0) -> 0 | I13: =IF(AND(I$3>=Groups!$E$5,MOD(I$3-Groups!$E$5,Groups!$D$5*12)=0),Groups!$B$5*Inputs!$B$16,0) -> 0 | ... FZ13: =IF(AND(FZ$3>=Groups!$E$5,MOD(FZ$3-Groups!$E$5,Groups!$D$5*12)=0),Groups!$B$5*Inputs!$B$16,0) -> 0
A14: Rent roll | B14: =B6*Groups!$B$2+B8*Groups!$B$3+B10*Groups!$B$4+B12*Groups!$B$5 -> 1564600 | C14: =C6*Groups!$B$2+C8*Groups!$B$3+C10*Groups!$B$4+C12*Groups!$B$5 -> 1575659 | D14: =D6*Groups!$B$2+D8*Groups!$B$3+D10*Groups!$B$4+D12*Groups!$B$5 -> 1586731.3 | E14: =E6*Groups!$B$2+E8*Groups!$B$3+E10*Groups!$B$4+E12*Groups!$B$5 -> 1597817.1 | F14: =F6*Groups!$B$2+F8*Groups!$B$3+F10*Groups!$B$4+F12*Groups!$B$5 -> 1608916.4 | G14: =G6*Groups!$B$2+G8*Groups!$B$3+G10*Groups!$B$4+G12*Groups!$B$5 -> 1620029.3 | H14: =H6*Groups!$B$2+H8*Groups!$B$3+H10*Groups!$B$4+H12*Groups!$B$5 -> 1631155.9 | I14: =I6*Groups!$B$2+I8*Groups!$B$3+I10*Groups!$B$4+I12*Groups!$B$5 -> 1642296.3 | ... FZ14: =FZ6*Groups!$B$2+FZ8*Groups!$B$3+FZ10*Groups!$B$4+FZ12*Groups!$B$5 -> 3794054.6
A15: Refurbishment | B15: =B7+B9+B11+B13 -> 0 | C15: =C7+C9+C11+C13 -> 0 | D15: =D7+D9+D11+D13 -> 0 | E15: =E7+E9+E11+E13 -> 0 | F15: =F7+F9+F11+F13 -> 0 | G15: =G7+G9+G11+G13 -> 0 | H15: =H7+H9+H11+H13 -> 0 | I15: =I7+I9+I11+I13 -> 0 | ... FZ15: =FZ7+FZ9+FZ11+FZ13 -> 0
A16: Net operating income | B16: =0 -> 0 | C16: =C14*(1-Inputs!$B$10) -> 1386579.9 | D16: =D14*(1-Inputs!$B$10) -> 1396323.6 | E16: =E14*(1-Inputs!$B$10) -> 1406079 | F16: =F14*(1-Inputs!$B$10) -> 1415846.4 | G16: =G14*(1-Inputs!$B$10) -> 1425625.8 | H16: =H14*(1-Inputs!$B$10) -> 1435417.2 | I16: =I14*(1-Inputs!$B$10) -> 1445220.7 | J16: =J14*(1-Inputs!$B$10) -> 1455036.5 | ... FZ16: =FZ14*(1-Inputs!$B$10) -> 3338768.1
A17: Loan balance | B17: =Inputs!$B$4*Inputs!$B$11 -> 226600000 | C17: =MAX(0,B17-C19)*IF(C$3<180,1,0) -> 226600000 | D17: =MAX(0,C17-D19)*IF(D$3<180,1,0) -> 226600000 | E17: =MAX(0,D17-E19)*IF(E$3<180,1,0) -> 226600000 | F17: =MAX(0,E17-F19)*IF(F$3<180,1,0) -> 226600000 | G17: =MAX(0,F17-G19)*IF(G$3<180,1,0) -> 226600000 | H17: =MAX(0,G17-H19)*IF(H$3<180,1,0) -> 226600000 | I17: =MAX(0,H17-I19)*IF(I$3<180,1,0) -> 226600000 | J17: =MAX(0,I17-J19)*IF(J$3<180,1,0) -> 226600000 | ... FZ17: =MAX(0,FY17-FZ19)*IF(FZ$3<180,1,0) -> 0
A18: Interest | B18: =0 -> 0 | C18: =B17*Inputs!$B$12/12 -> 774216.67 | D18: =C17*Inputs!$B$12/12 -> 774216.67 | E18: =D17*Inputs!$B$12/12 -> 774216.67 | F18: =E17*Inputs!$B$12/12 -> 774216.67 | G18: =F17*Inputs!$B$12/12 -> 774216.67 | H18: =G17*Inputs!$B$12/12 -> 774216.67 | I18: =H17*Inputs!$B$12/12 -> 774216.67 | J18: =I17*Inputs!$B$12/12 -> 774216.67 | ... FZ18: =FY17*Inputs!$B$12/12 -> 620663.69
A19: Amortisation | B19: =0 -> 0 | C19: =IF(C$3>Inputs!$B$13,Inputs!$B$4*Inputs!$B$11*Inputs!$B$14/12,0) -> 0 | D19: =IF(D$3>Inputs!$B$13,Inputs!$B$4*Inputs!$B$11*Inputs!$B$14/12,0) -> 0 | E19: =IF(E$3>Inputs!$B$13,Inputs!$B$4*Inputs!$B$11*Inputs!$B$14/12,0) -> 0 | F19: =IF(F$3>Inputs!$B$13,Inputs!$B$4*Inputs!$B$11*Inputs!$B$14/12,0) -> 0 | G19: =IF(G$3>Inputs!$B$13,Inputs!$B$4*Inputs!$B$11*Inputs!$B$14/12,0) -> 0 | H19: =IF(H$3>Inputs!$B$13,Inputs!$B$4*Inputs!$B$11*Inputs!$B$14/12,0) -> 0 | I19: =IF(I$3>Inputs!$B$13,Inputs!$B$4*Inputs!$B$11*Inputs!$B$14/12,0) -> 0 | J19: =IF(J$3>Inputs!$B$13,Inputs!$B$4*Inputs!$B$11*Inputs!$B$14/12,0) -> 0 | ... FZ19: =IF(FZ$3>Inputs!$B$13,Inputs!$B$4*Inputs!$B$11*Inputs!$B$14/12,0) -> 377666.67
A20: ICR | B20: =IF(B18>0,B16/B18,0) -> 0 | C20: =IF(C18>0,C16/C18,0) -> 1.7909456 | D20: =IF(D18>0,D16/D18,0) -> 1.8035307 | E20: =IF(E18>0,E16/E18,0) -> 1.8161312 | F20: =IF(F18>0,F16/F18,0) -> 1.828747 | G20: =IF(G18>0,G16/G18,0) -> 1.8413783 | H20: =IF(H18>0,H16/H18,0) -> 1.8540251 | I20: =IF(I18>0,I16/I18,0) -> 1.8666877 | ... FZ20: =IF(FZ18>0,FZ16/FZ18,0) -> 5.3793514
A21: Sale | B21: =IF(B$3=180,B16*12/Inputs!$B$15,0) -> 0 | C21: =IF(C$3=180,C16*12/Inputs!$B$15,0) -> 0 | D21: =IF(D$3=180,D16*12/Inputs!$B$15,0) -> 0 | E21: =IF(E$3=180,E16*12/Inputs!$B$15,0) -> 0 | F21: =IF(F$3=180,F16*12/Inputs!$B$15,0) -> 0 | G21: =IF(G$3=180,G16*12/Inputs!$B$15,0) -> 0 | H21: =IF(H$3=180,H16*12/Inputs!$B$15,0) -> 0 | I21: =IF(I$3=180,I16*12/Inputs!$B$15,0) -> 0 | ... FZ21: =IF(FZ$3=180,FZ16*12/Inputs!$B$15,0) -> 1.1783887e+09
A22: Equity cash flow | B22: =-Inputs!$B$4*(1+Inputs!$B$5-Inputs!$B$11) -> -220420000 | C22: =C16-C15-C18-C19+C21-IF(C$3=180,B17-C19,0) -> 612363.24 | D22: =D16-D15-D18-D19+D21-IF(D$3=180,C17-D19,0) -> 622106.89 | E22: =E16-E15-E18-E19+E21-IF(E$3=180,D17-E19,0) -> 631862.36 | F22: =F16-F15-F18-F19+F21-IF(F$3=180,E17-F19,0) -> 641629.74 | G22: =G16-G15-G18-G19+G21-IF(G$3=180,F17-G19,0) -> 651409.09 | H22: =H16-H15-H18-H19+H21-IF(H$3=180,G17-H19,0) -> 661200.5 | I22: =I16-I15-I18-I19+I21-IF(I$3=180,H17-I19,0) -> 671004.04 | J22: =J16-J15-J18-J19+J21-IF(J$3=180,I17-J19,0) -> 680819.81 | ... FZ22: =FZ16-FZ15-FZ18-FZ19+FZ21-IF(FZ$3=180,FY17-FZ19,0) -> 9.9944917e+08

Sheet Returns
A3: Levered IRR | B3: =(1+IRR('Cash Flow'!$B$22:$FZ$22,0.005))^12-1 -> 0.12069242
A4: Equity multiple | B4: =SUMIF('Cash Flow'!$B$22:$FZ$22,">0")/-SUMIF('Cash Flow'!$B$22:$FZ$22,"<0") -> 3.8433492
A5: Minimum ICR | B5: =_xlfn.MINIFS('Cash Flow'!$B$20:$FZ$20,'Cash Flow'!$B$20:$FZ$20,">0") -> 1.7909456
A6: Average rent at exit (€/sqm/month) | B6: =INDEX('Cash Flow'!$B$14:$FZ$14,180)/SUM(Groups!$B$2:$B$5) -> 27.001746
A7: Market rent at exit (€/sqm/month) | B7: =INDEX('Cash Flow'!$B$5:$FZ$5,180) -> 27.564122
A8: Reversion at exit | B8: =B7/B6-1 -> 0.020827408
A9: Refurbishment spend (€) | B9: =SUM('Cash Flow'!$B$15:$FZ$15) -> 108780000
A10: Peak debt (€) | B10: =MAX('Cash Flow'!$B$17:$FZ$17) -> 226600000
A11: Net profit (€) | B11: =SUM('Cash Flow'!$B$22:$FZ$22) -> 9.1152965e+08
