Workbook

Sheet Inputs
A1: KINGS WHARF – 99-YEAR GROUND LEASE (GBP)
A3: Lease start | B3: 46381
A4: Occupational rent year 1 (£) | B4: 4800000
A5: Ground rent share of occupational rent | B5: 0.12
A6: RPI a year | B6: 0.03
A7: Review collar · floor a year | B7: 0.01
A8: Review collar · cap a year | B8: 0.04
A9: Review every (years) | B9: 5
A10: Freeholder discount rate | B10: 0.045
A11: Leasehold discount rate | B11: 0.07
A12: Leasehold valuation year | B12: 10
A13: Lease term (years) | B13: 99

Sheet Cash Flow
A3: Year | B3: 1 | C3: 2 | D3: 3 | E3: 4 | F3: 5 | G3: 6 | H3: 7 | I3: 8 | J3: 9 | K3: 10 | L3: 11 | M3: 12 | N3: 13 | O3: 14 | P3: 15 | Q3: 16 | R3: 17 | S3: 18 | T3: 19 | U3: 20 | V3: 21 | W3: 22 | X3: 23 | Y3: 24 | Z3: 25 | AA3: 26 | AB3: 27 | AC3: 28 | AD3: 29 | AE3: 30 | AF3: 31 | AG3: 32 | AH3: 33 | AI3: 34 | AJ3: 35 | AK3: 36 | AL3: 37 | AM3: 38 | AN3: 39 | AO3: 40 | AP3: 41 | AQ3: 42 | AR3: 43 | AS3: 44 | AT3: 45 | AU3: 46 | AV3: 47 | AW3: 48 | AX3: 49 | AY3: 50 | AZ3: 51 | BA3: 52 | BB3: 53 | BC3: 54 | BD3: 55 | BE3: 56 | BF3: 57 | BG3: 58 | BH3: 59 | BI3: 60 | BJ3: 61 | BK3: 62 | BL3: 63 | BM3: 64 | BN3: 65 | BO3: 66 | BP3: 67 | BQ3: 68 | BR3: 69 | BS3: 70 | BT3: 71 | BU3: 72 | BV3: 73 | BW3: 74 | BX3: 75 | BY3: 76 | BZ3: 77 | CA3: 78 | CB3: 79 | CC3: 80 | CD3: 81 | CE3: 82 | CF3: 83 | CG3: 84 | CH3: 85 | CI3: 86 | CJ3: 87 | CK3: 88 | CL3: 89 | CM3: 90 | CN3: 91 | CO3: 92 | CP3: 93 | CQ3: 94 | CR3: 95 | CS3: 96 | CT3: 97 | CU3: 98 | CV3: 99 | CW3: 100
A4: Date | B4: =DATE(YEAR(Inputs!$B$3)+B$3-1,MONTH(Inputs!$B$3),DAY(Inputs!$B$3)) -> 46381 | C4: =DATE(YEAR(Inputs!$B$3)+C$3-1,MONTH(Inputs!$B$3),DAY(Inputs!$B$3)) -> 46746 | D4: =DATE(YEAR(Inputs!$B$3)+D$3-1,MONTH(Inputs!$B$3),DAY(Inputs!$B$3)) -> 47112 | E4: =DATE(YEAR(Inputs!$B$3)+E$3-1,MONTH(Inputs!$B$3),DAY(Inputs!$B$3)) -> 47477 | F4: =DATE(YEAR(Inputs!$B$3)+F$3-1,MONTH(Inputs!$B$3),DAY(Inputs!$B$3)) -> 47842 | G4: =DATE(YEAR(Inputs!$B$3)+G$3-1,MONTH(Inputs!$B$3),DAY(Inputs!$B$3)) -> 48207 | H4: =DATE(YEAR(Inputs!$B$3)+H$3-1,MONTH(Inputs!$B$3),DAY(Inputs!$B$3)) -> 48573 | I4: =DATE(YEAR(Inputs!$B$3)+I$3-1,MONTH(Inputs!$B$3),DAY(Inputs!$B$3)) -> 48938 | ... CW4: =DATE(YEAR(Inputs!$B$3)+CW$3-1,MONTH(Inputs!$B$3),DAY(Inputs!$B$3)) -> 82540
A5: Review year | B5: =IF(AND(B$3>1,MOD(B$3-1,Inputs!$B$9)=0),1,0) -> 0 | C5: =IF(AND(C$3>1,MOD(C$3-1,Inputs!$B$9)=0),1,0) -> 0 | D5: =IF(AND(D$3>1,MOD(D$3-1,Inputs!$B$9)=0),1,0) -> 0 | E5: =IF(AND(E$3>1,MOD(E$3-1,Inputs!$B$9)=0),1,0) -> 0 | F5: =IF(AND(F$3>1,MOD(F$3-1,Inputs!$B$9)=0),1,0) -> 0 | G5: =IF(AND(G$3>1,MOD(G$3-1,Inputs!$B$9)=0),1,0) -> 1 | H5: =IF(AND(H$3>1,MOD(H$3-1,Inputs!$B$9)=0),1,0) -> 0 | I5: =IF(AND(I$3>1,MOD(I$3-1,Inputs!$B$9)=0),1,0) -> 0 | ... CW5: =IF(AND(CW$3>1,MOD(CW$3-1,Inputs!$B$9)=0),1,0) -> 0
A6: Indexation since last review | B6: =MIN((1+Inputs!$B$8)^Inputs!$B$9,MAX((1+Inputs!$B$7)^Inputs!$B$9,(1+Inputs!$B$6)^Inputs!$B$9)) -> 1.1592741 | C6: =MIN((1+Inputs!$B$8)^Inputs!$B$9,MAX((1+Inputs!$B$7)^Inputs!$B$9,(1+Inputs!$B$6)^Inputs!$B$9)) -> 1.1592741 | D6: =MIN((1+Inputs!$B$8)^Inputs!$B$9,MAX((1+Inputs!$B$7)^Inputs!$B$9,(1+Inputs!$B$6)^Inputs!$B$9)) -> 1.1592741 | E6: =MIN((1+Inputs!$B$8)^Inputs!$B$9,MAX((1+Inputs!$B$7)^Inputs!$B$9,(1+Inputs!$B$6)^Inputs!$B$9)) -> 1.1592741 | F6: =MIN((1+Inputs!$B$8)^Inputs!$B$9,MAX((1+Inputs!$B$7)^Inputs!$B$9,(1+Inputs!$B$6)^Inputs!$B$9)) -> 1.1592741 | G6: =MIN((1+Inputs!$B$8)^Inputs!$B$9,MAX((1+Inputs!$B$7)^Inputs!$B$9,(1+Inputs!$B$6)^Inputs!$B$9)) -> 1.1592741 | H6: =MIN((1+Inputs!$B$8)^Inputs!$B$9,MAX((1+Inputs!$B$7)^Inputs!$B$9,(1+Inputs!$B$6)^Inputs!$B$9)) -> 1.1592741 | I6: =MIN((1+Inputs!$B$8)^Inputs!$B$9,MAX((1+Inputs!$B$7)^Inputs!$B$9,(1+Inputs!$B$6)^Inputs!$B$9)) -> 1.1592741 | ... CW6: =MIN((1+Inputs!$B$8)^Inputs!$B$9,MAX((1+Inputs!$B$7)^Inputs!$B$9,(1+Inputs!$B$6)^Inputs!$B$9)) -> 1.1592741
A7: Occupational rent | B7: =Inputs!$B$4 -> 4800000 | C7: =IF(C5=1,MAX(B7,B7*C6),B7)*IF(C$3<=Inputs!$B$13,1,0) -> 4800000 | D7: =IF(D5=1,MAX(C7,C7*D6),C7)*IF(D$3<=Inputs!$B$13,1,0) -> 4800000 | E7: =IF(E5=1,MAX(D7,D7*E6),D7)*IF(E$3<=Inputs!$B$13,1,0) -> 4800000 | F7: =IF(F5=1,MAX(E7,E7*F6),E7)*IF(F$3<=Inputs!$B$13,1,0) -> 4800000 | G7: =IF(G5=1,MAX(F7,F7*G6),F7)*IF(G$3<=Inputs!$B$13,1,0) -> 5564515.6 | H7: =IF(H5=1,MAX(G7,G7*H6),G7)*IF(H$3<=Inputs!$B$13,1,0) -> 5564515.6 | I7: =IF(I5=1,MAX(H7,H7*I6),H7)*IF(I$3<=Inputs!$B$13,1,0) -> 5564515.6 | J7: =IF(J5=1,MAX(I7,I7*J6),I7)*IF(J$3<=Inputs!$B$13,1,0) -> 5564515.6 | ... CW7: =IF(CW5=1,MAX(CV7,CV7*CW6),CV7)*IF(CW$3<=Inputs!$B$13,1,0) -> 0
A8: Ground rent | B8: =B7*Inputs!$B$5 -> 576000 | C8: =C7*Inputs!$B$5 -> 576000 | D8: =D7*Inputs!$B$5 -> 576000 | E8: =E7*Inputs!$B$5 -> 576000 | F8: =F7*Inputs!$B$5 -> 576000 | G8: =G7*Inputs!$B$5 -> 667741.87 | H8: =H7*Inputs!$B$5 -> 667741.87 | I8: =I7*Inputs!$B$5 -> 667741.87 | ... CW8: =CW7*Inputs!$B$5 -> 0
A9: Profit rent | B9: =B7-B8 -> 4224000 | C9: =C7-C8 -> 4224000 | D9: =D7-D8 -> 4224000 | E9: =E7-E8 -> 4224000 | F9: =F7-F8 -> 4224000 | G9: =G7-G8 -> 4896773.7 | H9: =H7-H8 -> 4896773.7 | I9: =I7-I8 -> 4896773.7 | ... CW9: =CW7-CW8 -> 0

Sheet Returns
A3: Freeholder value (XNPV of ground rent, £) | B3: =XNPV(Inputs!$B$10,'Cash Flow'!$B$8:$CW$8,'Cash Flow'!$B$4:$CW$4) -> 28809852
A4: Initial yield on freehold value | B4: =Inputs!$B$4*Inputs!$B$5/B3 -> 0.019993161
A5: Leasehold value at the valuation year (£) | B5: =NPV(Inputs!$B$11,OFFSET('Cash Flow'!$B$9,0,Inputs!$B$12,1,Inputs!$B$13-Inputs!$B$12)) -> 1.2968007e+08
A6: Ground rent in year 50 (£) | B6: =INDEX('Cash Flow'!$B$8:$CW$8,50) -> 2178199.2
A7: Last rent date | B7: =INDEX('Cash Flow'!$B$4:$CW$4,Inputs!$B$13) -> 82175
A8: Total ground rent over the term (£) | B8: =SUM('Cash Flow'!$B$8:$CW$8) -> 3.1988099e+08
A9: Ground rent in 2100 (£) | B9: =SUMPRODUCT((YEAR('Cash Flow'!$B$4:$CW$4)=2100)*'Cash Flow'!$B$8:$CW$8) -> 4560665.4
A10: Net profit (£) | B10: =SUM('Cash Flow'!$B$9:$CW$9) -> 2.3457939e+09
