Workbook

Sheet Inputs
A1: ELM PARK – RESIDENTIAL WITH A CONSTRUCTION LOAN (GBP)
A3: Land (£) | B3: 42000000
A4: Build cost (£) | B4: 118000000
A5: Build (months) | B5: 24
A6: Loan to cost | B6: 0.65
A7: Interest rate | B7: 0.075
A8: Commitment fee on undrawn | B8: 0.012
A9: Arrangement fee | B9: 0.015
A10: Sales (£) | B10: 212000000
A11: Sales period (months) | B11: 12

Sheet Cash Flow
A3: Month | B3: 0 | C3: 1 | D3: 2 | E3: 3 | F3: 4 | G3: 5 | H3: 6 | I3: 7 | J3: 8 | K3: 9 | L3: 10 | M3: 11 | N3: 12 | O3: 13 | P3: 14 | Q3: 15 | R3: 16 | S3: 17 | T3: 18 | U3: 19 | V3: 20 | W3: 21 | X3: 22 | Y3: 23 | Z3: 24 | AA3: 25 | AB3: 26 | AC3: 27 | AD3: 28 | AE3: 29 | AF3: 30 | AG3: 31 | AH3: 32 | AI3: 33 | AJ3: 34 | AK3: 35 | AL3: 36 | AM3: 37 | AN3: 38 | AO3: 39 | AP3: 40
A4: Build cost | B4: =IF(AND(B$3>=1,B$3<=Inputs!$B$5),Inputs!$B$4/Inputs!$B$5,0) -> 0 | C4: =IF(AND(C$3>=1,C$3<=Inputs!$B$5),Inputs!$B$4/Inputs!$B$5,0) -> 4916666.7 | D4: =IF(AND(D$3>=1,D$3<=Inputs!$B$5),Inputs!$B$4/Inputs!$B$5,0) -> 4916666.7 | E4: =IF(AND(E$3>=1,E$3<=Inputs!$B$5),Inputs!$B$4/Inputs!$B$5,0) -> 4916666.7 | F4: =IF(AND(F$3>=1,F$3<=Inputs!$B$5),Inputs!$B$4/Inputs!$B$5,0) -> 4916666.7 | G4: =IF(AND(G$3>=1,G$3<=Inputs!$B$5),Inputs!$B$4/Inputs!$B$5,0) -> 4916666.7 | H4: =IF(AND(H$3>=1,H$3<=Inputs!$B$5),Inputs!$B$4/Inputs!$B$5,0) -> 4916666.7 | I4: =IF(AND(I$3>=1,I$3<=Inputs!$B$5),Inputs!$B$4/Inputs!$B$5,0) -> 4916666.7 | ... AP4: =IF(AND(AP$3>=1,AP$3<=Inputs!$B$5),Inputs!$B$4/Inputs!$B$5,0) -> 0
A5: Land | B5: =IF(B$3=0,Inputs!$B$3,0) -> 42000000 | C5: =IF(C$3=0,Inputs!$B$3,0) -> 0 | D5: =IF(D$3=0,Inputs!$B$3,0) -> 0 | E5: =IF(E$3=0,Inputs!$B$3,0) -> 0 | F5: =IF(F$3=0,Inputs!$B$3,0) -> 0 | G5: =IF(G$3=0,Inputs!$B$3,0) -> 0 | H5: =IF(H$3=0,Inputs!$B$3,0) -> 0 | I5: =IF(I$3=0,Inputs!$B$3,0) -> 0 | ... AP5: =IF(AP$3=0,Inputs!$B$3,0) -> 0
A6: Arrangement fee | B6: =IF(B$3=0,B10*Inputs!$B$9,0) -> 1686397.8 | C6: =IF(C$3=0,C10*Inputs!$B$9,0) -> 0 | D6: =IF(D$3=0,D10*Inputs!$B$9,0) -> 0 | E6: =IF(E$3=0,E10*Inputs!$B$9,0) -> 0 | F6: =IF(F$3=0,F10*Inputs!$B$9,0) -> 0 | G6: =IF(G$3=0,G10*Inputs!$B$9,0) -> 0 | H6: =IF(H$3=0,H10*Inputs!$B$9,0) -> 0 | I6: =IF(I$3=0,I10*Inputs!$B$9,0) -> 0 | ... AP6: =IF(AP$3=0,AP10*Inputs!$B$9,0) -> 0
A7: Interest | B7: =0 -> 0 | C7: =IF(C$3<=Inputs!$B$5,B12*Inputs!$B$7/12,0) -> 177475.99 | D7: =IF(D$3<=Inputs!$B$5,C12*Inputs!$B$7/12,0) -> 198512.32 | E7: =IF(E$3<=Inputs!$B$5,D12*Inputs!$B$7/12,0) -> 219620.43 | F7: =IF(F$3<=Inputs!$B$5,E12*Inputs!$B$7/12,0) -> 240800.58 | G7: =IF(G$3<=Inputs!$B$5,F12*Inputs!$B$7/12,0) -> 262053 | H7: =IF(H$3<=Inputs!$B$5,G12*Inputs!$B$7/12,0) -> 283377.95 | I7: =IF(I$3<=Inputs!$B$5,H12*Inputs!$B$7/12,0) -> 304775.67 | J7: =IF(J$3<=Inputs!$B$5,I12*Inputs!$B$7/12,0) -> 326246.41 | ... AP7: =IF(AP$3<=Inputs!$B$5,AO12*Inputs!$B$7/12,0) -> 0
A8: Commitment fee | B8: =0 -> 0 | C8: =IF(C$3<=Inputs!$B$5,MAX(0,C10-B12)*Inputs!$B$8/12,0) -> 84030.362 | D8: =IF(D$3<=Inputs!$B$5,MAX(0,D10-C12)*Inputs!$B$8/12,0) -> 80664.55 | E8: =IF(E$3<=Inputs!$B$5,MAX(0,E10-D12)*Inputs!$B$8/12,0) -> 77287.251 | F8: =IF(F$3<=Inputs!$B$5,MAX(0,F10-E12)*Inputs!$B$8/12,0) -> 73898.428 | G8: =IF(G$3<=Inputs!$B$5,MAX(0,G10-F12)*Inputs!$B$8/12,0) -> 70498.04 | H8: =IF(H$3<=Inputs!$B$5,MAX(0,H10-G12)*Inputs!$B$8/12,0) -> 67086.049 | I8: =IF(I$3<=Inputs!$B$5,MAX(0,I10-H12)*Inputs!$B$8/12,0) -> 63662.414 | J8: =IF(J$3<=Inputs!$B$5,MAX(0,J10-I12)*Inputs!$B$8/12,0) -> 60227.096 | ... AP8: =IF(AP$3<=Inputs!$B$5,MAX(0,AP10-AO12)*Inputs!$B$8/12,0) -> 0
A9: Total cost | B9: =B4+B5+B6+B7+B8 -> 43686398 | C9: =C4+C5+C6+C7+C8 -> 5178173 | D9: =D4+D5+D6+D7+D8 -> 5195843.5 | E9: =E4+E5+E6+E7+E8 -> 5213574.4 | F9: =F4+F5+F6+F7+F8 -> 5231365.7 | G9: =G4+G5+G6+G7+G8 -> 5249217.7 | H9: =H4+H5+H6+H7+H8 -> 5267130.7 | I9: =I4+I5+I6+I7+I8 -> 5285104.7 | ... AP9: =AP4+AP5+AP6+AP7+AP8 -> 0
A10: Facility | B10: =(Inputs!$B$3+Inputs!$B$4)*Inputs!$B$6/(1-Inputs!$B$6*(Inputs!$B$7*Inputs!$B$5/24+Inputs!$B$8/2))*0+(SUM($B$4:$AP$4)+Inputs!$B$3+SUM($B$7:$AP$7)+SUM($B$8:$AP$8)+SUM($B$6:$AP$6))*Inputs!$B$6 -> 1.1242652e+08 | C10: =(Inputs!$B$3+Inputs!$B$4)*Inputs!$B$6/(1-Inputs!$B$6*(Inputs!$B$7*Inputs!$B$5/24+Inputs!$B$8/2))*0+(SUM($B$4:$AP$4)+Inputs!$B$3+SUM($B$7:$AP$7)+SUM($B$8:$AP$8)+SUM($B$6:$AP$6))*Inputs!$B$6 -> 1.1242652e+08 | D10: =(Inputs!$B$3+Inputs!$B$4)*Inputs!$B$6/(1-Inputs!$B$6*(Inputs!$B$7*Inputs!$B$5/24+Inputs!$B$8/2))*0+(SUM($B$4:$AP$4)+Inputs!$B$3+SUM($B$7:$AP$7)+SUM($B$8:$AP$8)+SUM($B$6:$AP$6))*Inputs!$B$6 -> 1.1242652e+08 | E10: =(Inputs!$B$3+Inputs!$B$4)*Inputs!$B$6/(1-Inputs!$B$6*(Inputs!$B$7*Inputs!$B$5/24+Inputs!$B$8/2))*0+(SUM($B$4:$AP$4)+Inputs!$B$3+SUM($B$7:$AP$7)+SUM($B$8:$AP$8)+SUM($B$6:$AP$6))*Inputs!$B$6 -> 1.1242652e+08 | F10: =(Inputs!$B$3+Inputs!$B$4)*Inputs!$B$6/(1-Inputs!$B$6*(Inputs!$B$7*Inputs!$B$5/24+Inputs!$B$8/2))*0+(SUM($B$4:$AP$4)+Inputs!$B$3+SUM($B$7:$AP$7)+SUM($B$8:$AP$8)+SUM($B$6:$AP$6))*Inputs!$B$6 -> 1.1242652e+08 | G10: =(Inputs!$B$3+Inputs!$B$4)*Inputs!$B$6/(1-Inputs!$B$6*(Inputs!$B$7*Inputs!$B$5/24+Inputs!$B$8/2))*0+(SUM($B$4:$AP$4)+Inputs!$B$3+SUM($B$7:$AP$7)+SUM($B$8:$AP$8)+SUM($B$6:$AP$6))*Inputs!$B$6 -> 1.1242652e+08 | H10: =(Inputs!$B$3+Inputs!$B$4)*Inputs!$B$6/(1-Inputs!$B$6*(Inputs!$B$7*Inputs!$B$5/24+Inputs!$B$8/2))*0+(SUM($B$4:$AP$4)+Inputs!$B$3+SUM($B$7:$AP$7)+SUM($B$8:$AP$8)+SUM($B$6:$AP$6))*Inputs!$B$6 -> 1.1242652e+08 | I10: =(Inputs!$B$3+Inputs!$B$4)*Inputs!$B$6/(1-Inputs!$B$6*(Inputs!$B$7*Inputs!$B$5/24+Inputs!$B$8/2))*0+(SUM($B$4:$AP$4)+Inputs!$B$3+SUM($B$7:$AP$7)+SUM($B$8:$AP$8)+SUM($B$6:$AP$6))*Inputs!$B$6 -> 1.1242652e+08 | ... AP10: =(Inputs!$B$3+Inputs!$B$4)*Inputs!$B$6/(1-Inputs!$B$6*(Inputs!$B$7*Inputs!$B$5/24+Inputs!$B$8/2))*0+(SUM($B$4:$AP$4)+Inputs!$B$3+SUM($B$7:$AP$7)+SUM($B$8:$AP$8)+SUM($B$6:$AP$6))*Inputs!$B$6 -> 1.1242652e+08
A11: Loan drawn | B11: =IF(B$3<=Inputs!$B$5,MIN(B9*Inputs!$B$6/(1),B10-0),0) -> 28396159 | C11: =IF(C$3<=Inputs!$B$5,MIN(C9*Inputs!$B$6/(1),C10-B12),0) -> 3365812.5 | D11: =IF(D$3<=Inputs!$B$5,MIN(D9*Inputs!$B$6/(1),D10-C12),0) -> 3377298.3 | E11: =IF(E$3<=Inputs!$B$5,MIN(E9*Inputs!$B$6/(1),E10-D12),0) -> 3388823.3 | F11: =IF(F$3<=Inputs!$B$5,MIN(F9*Inputs!$B$6/(1),F10-E12),0) -> 3400387.7 | G11: =IF(G$3<=Inputs!$B$5,MIN(G9*Inputs!$B$6/(1),G10-F12),0) -> 3411991.5 | H11: =IF(H$3<=Inputs!$B$5,MIN(H9*Inputs!$B$6/(1),H10-G12),0) -> 3423634.9 | I11: =IF(I$3<=Inputs!$B$5,MIN(I9*Inputs!$B$6/(1),I10-H12),0) -> 3435318.1 | J11: =IF(J$3<=Inputs!$B$5,MIN(J9*Inputs!$B$6/(1),J10-I12),0) -> 3447041.1 | ... AP11: =IF(AP$3<=Inputs!$B$5,MIN(AP9*Inputs!$B$6/(1),AP10-AO12),0) -> 0
A12: Loan balance | B12: =0+B11-B14 -> 28396159 | C12: =B12+C11-C14 -> 31761971 | D12: =C12+D11-D14 -> 35139269 | E12: =D12+E11-E14 -> 38528093 | F12: =E12+F11-F14 -> 41928480 | G12: =F12+G11-G14 -> 45340472 | H12: =G12+H11-H14 -> 48764107 | I12: =H12+I11-I14 -> 52199425 | J12: =I12+J11-J14 -> 55646466 | ... AP12: =AO12+AP11-AP14 -> 0
A13: Sales | B13: =IF(AND(B$3>Inputs!$B$5,B$3<=Inputs!$B$5+Inputs!$B$11),Inputs!$B$10/Inputs!$B$11,0) -> 0 | C13: =IF(AND(C$3>Inputs!$B$5,C$3<=Inputs!$B$5+Inputs!$B$11),Inputs!$B$10/Inputs!$B$11,0) -> 0 | D13: =IF(AND(D$3>Inputs!$B$5,D$3<=Inputs!$B$5+Inputs!$B$11),Inputs!$B$10/Inputs!$B$11,0) -> 0 | E13: =IF(AND(E$3>Inputs!$B$5,E$3<=Inputs!$B$5+Inputs!$B$11),Inputs!$B$10/Inputs!$B$11,0) -> 0 | F13: =IF(AND(F$3>Inputs!$B$5,F$3<=Inputs!$B$5+Inputs!$B$11),Inputs!$B$10/Inputs!$B$11,0) -> 0 | G13: =IF(AND(G$3>Inputs!$B$5,G$3<=Inputs!$B$5+Inputs!$B$11),Inputs!$B$10/Inputs!$B$11,0) -> 0 | H13: =IF(AND(H$3>Inputs!$B$5,H$3<=Inputs!$B$5+Inputs!$B$11),Inputs!$B$10/Inputs!$B$11,0) -> 0 | I13: =IF(AND(I$3>Inputs!$B$5,I$3<=Inputs!$B$5+Inputs!$B$11),Inputs!$B$10/Inputs!$B$11,0) -> 0 | ... AP13: =IF(AND(AP$3>Inputs!$B$5,AP$3<=Inputs!$B$5+Inputs!$B$11),Inputs!$B$10/Inputs!$B$11,0) -> 0
A14: Repayment | B14: =MIN(0+B11,B13) -> 0 | C14: =MIN(B12+C11,C13) -> 0 | D14: =MIN(C12+D11,D13) -> 0 | E14: =MIN(D12+E11,E13) -> 0 | F14: =MIN(E12+F11,F13) -> 0 | G14: =MIN(F12+G11,G13) -> 0 | H14: =MIN(G12+H11,H13) -> 0 | I14: =MIN(H12+I11,I13) -> 0 | J14: =MIN(I12+J11,J13) -> 0 | ... AP14: =MIN(AO12+AP11,AP13) -> 0
A15: Equity cash flow | B15: =B13-B14-(B9-B11) -> -15290239 | C15: =C13-C14-(C9-C11) -> -1812360.6 | D15: =D13-D14-(D9-D11) -> -1818545.2 | E15: =E13-E14-(E9-E11) -> -1824751 | F15: =F13-F14-(F9-F11) -> -1830978 | G15: =G13-G14-(G9-G11) -> -1837226.2 | H15: =H13-H14-(H9-H11) -> -1843495.7 | I15: =I13-I14-(I9-I11) -> -1849786.7 | ... AP15: =AP13-AP14-(AP9-AP11) -> 0

Sheet Returns
A3: Levered IRR | B3: =(1+IRR('Cash Flow'!$B$15:$AP$15,0.02))^12-1 -> 0.27200374
A4: Facility (£) | B4: ='Cash Flow'!B10 -> 1.1242652e+08
A5: Peak debt (£) | B5: =MAX('Cash Flow'!$B$12:$AP$12) -> 1.1242652e+08
A6: Interest and fees capitalised (£) | B6: =SUM('Cash Flow'!$B$7:$AP$7)+SUM('Cash Flow'!$B$8:$AP$8)+SUM('Cash Flow'!$B$6:$AP$6) -> 12963878
A7: Total cost (£) | B7: =SUM('Cash Flow'!$B$9:$AP$9) -> 1.7296388e+08
A8: Net profit (£) | B8: =SUM('Cash Flow'!$B$15:$AP$15) -> 39036122
A9: Profit on cost | B9: =B8/B7 -> 0.22568945
