Workbook

Sheet Inputs
A1: A-17 TOLL MOTORWAY – CONCESSION (EUR)
A3: Light vehicles a day (year 1) | B3: 38000
A4: Heavy vehicles a day (year 1) | B4: 6500
A5: Ramp-up years | B5: 4
A6: Traffic growth a year | B6: 0.022
A7: Tariff light (EUR) | B7: 4.2
A8: Tariff heavy (EUR) | B8: 11.5
A9: Tariff indexation | B9: 0.02
A10: Elasticity of traffic to tariff | B10: -0.25
A11: Tariff change vs base | B11: 0
A12: O&M a year (EUR) | B12: 21000000
A13: Major maintenance every (years) | B13: 8
A14: Major maintenance (EUR) | B14: 65000000
... A19: Construction cost (EUR) | B19: 1150000000

Sheet Cash Flow
A3: Year | B3: 0 | C3: 1 | D3: 2 | E3: 3 | F3: 4 | G3: 5 | H3: 6 | I3: 7 | J3: 8 | K3: 9 | L3: 10 | M3: 11 | N3: 12 | O3: 13 | P3: 14 | Q3: 15 | R3: 16 | S3: 17 | T3: 18 | U3: 19 | V3: 20 | W3: 21 | X3: 22 | Y3: 23 | Z3: 24 | AA3: 25 | AB3: 26 | AC3: 27 | AD3: 28 | AE3: 29 | AF3: 30
A4: Ramp-up factor | B4: =IF(B$3=0,0,MIN(1,0.6+0.4*(B$3-1)/Inputs!$B$5)) -> 0 | C4: =IF(C$3=0,0,MIN(1,0.6+0.4*(C$3-1)/Inputs!$B$5)) -> 0.6 | D4: =IF(D$3=0,0,MIN(1,0.6+0.4*(D$3-1)/Inputs!$B$5)) -> 0.7 | E4: =IF(E$3=0,0,MIN(1,0.6+0.4*(E$3-1)/Inputs!$B$5)) -> 0.8 | F4: =IF(F$3=0,0,MIN(1,0.6+0.4*(F$3-1)/Inputs!$B$5)) -> 0.9 | G4: =IF(G$3=0,0,MIN(1,0.6+0.4*(G$3-1)/Inputs!$B$5)) -> 1 | H4: =IF(H$3=0,0,MIN(1,0.6+0.4*(H$3-1)/Inputs!$B$5)) -> 1 | I4: =IF(I$3=0,0,MIN(1,0.6+0.4*(I$3-1)/Inputs!$B$5)) -> 1 | ... AF4: =IF(AF$3=0,0,MIN(1,0.6+0.4*(AF$3-1)/Inputs!$B$5)) -> 1
A5: Tariff light | B5: =MROUND(Inputs!$B$7*(1+Inputs!$B$11)*(1+Inputs!$B$9)^MAX(0,B$3-1),0.1) -> 4.2 | C5: =MROUND(Inputs!$B$7*(1+Inputs!$B$11)*(1+Inputs!$B$9)^MAX(0,C$3-1),0.1) -> 4.2 | D5: =MROUND(Inputs!$B$7*(1+Inputs!$B$11)*(1+Inputs!$B$9)^MAX(0,D$3-1),0.1) -> 4.3 | E5: =MROUND(Inputs!$B$7*(1+Inputs!$B$11)*(1+Inputs!$B$9)^MAX(0,E$3-1),0.1) -> 4.4 | F5: =MROUND(Inputs!$B$7*(1+Inputs!$B$11)*(1+Inputs!$B$9)^MAX(0,F$3-1),0.1) -> 4.5 | G5: =MROUND(Inputs!$B$7*(1+Inputs!$B$11)*(1+Inputs!$B$9)^MAX(0,G$3-1),0.1) -> 4.5 | H5: =MROUND(Inputs!$B$7*(1+Inputs!$B$11)*(1+Inputs!$B$9)^MAX(0,H$3-1),0.1) -> 4.6 | I5: =MROUND(Inputs!$B$7*(1+Inputs!$B$11)*(1+Inputs!$B$9)^MAX(0,I$3-1),0.1) -> 4.7 | ... AF5: =MROUND(Inputs!$B$7*(1+Inputs!$B$11)*(1+Inputs!$B$9)^MAX(0,AF$3-1),0.1) -> 7.5
A6: Tariff heavy | B6: =MROUND(Inputs!$B$8*(1+Inputs!$B$11)*(1+Inputs!$B$9)^MAX(0,B$3-1),0.1) -> 11.5 | C6: =MROUND(Inputs!$B$8*(1+Inputs!$B$11)*(1+Inputs!$B$9)^MAX(0,C$3-1),0.1) -> 11.5 | D6: =MROUND(Inputs!$B$8*(1+Inputs!$B$11)*(1+Inputs!$B$9)^MAX(0,D$3-1),0.1) -> 11.7 | E6: =MROUND(Inputs!$B$8*(1+Inputs!$B$11)*(1+Inputs!$B$9)^MAX(0,E$3-1),0.1) -> 12 | F6: =MROUND(Inputs!$B$8*(1+Inputs!$B$11)*(1+Inputs!$B$9)^MAX(0,F$3-1),0.1) -> 12.2 | G6: =MROUND(Inputs!$B$8*(1+Inputs!$B$11)*(1+Inputs!$B$9)^MAX(0,G$3-1),0.1) -> 12.4 | H6: =MROUND(Inputs!$B$8*(1+Inputs!$B$11)*(1+Inputs!$B$9)^MAX(0,H$3-1),0.1) -> 12.7 | I6: =MROUND(Inputs!$B$8*(1+Inputs!$B$11)*(1+Inputs!$B$9)^MAX(0,I$3-1),0.1) -> 13 | ... AF6: =MROUND(Inputs!$B$8*(1+Inputs!$B$11)*(1+Inputs!$B$9)^MAX(0,AF$3-1),0.1) -> 20.4
A7: Light traffic | B7: =IF(AND(B$3>=1,B$3<=Inputs!$B$18),Inputs!$B$3*365*B4*(1+Inputs!$B$6)^(B$3-1)*POWER(1+Inputs!$B$11,Inputs!$B$10),0) -> 0 | C7: =IF(AND(C$3>=1,C$3<=Inputs!$B$18),Inputs!$B$3*365*C4*(1+Inputs!$B$6)^(C$3-1)*POWER(1+Inputs!$B$11,Inputs!$B$10),0) -> 8322000 | D7: =IF(AND(D$3>=1,D$3<=Inputs!$B$18),Inputs!$B$3*365*D4*(1+Inputs!$B$6)^(D$3-1)*POWER(1+Inputs!$B$11,Inputs!$B$10),0) -> 9922598 | E7: =IF(AND(E$3>=1,E$3<=Inputs!$B$18),Inputs!$B$3*365*E4*(1+Inputs!$B$6)^(E$3-1)*POWER(1+Inputs!$B$11,Inputs!$B$10),0) -> 11589594 | F7: =IF(AND(F$3>=1,F$3<=Inputs!$B$18),Inputs!$B$3*365*F4*(1+Inputs!$B$6)^(F$3-1)*POWER(1+Inputs!$B$11,Inputs!$B$10),0) -> 13325136 | G7: =IF(AND(G$3>=1,G$3<=Inputs!$B$18),Inputs!$B$3*365*G4*(1+Inputs!$B$6)^(G$3-1)*POWER(1+Inputs!$B$11,Inputs!$B$10),0) -> 15131432 | H7: =IF(AND(H$3>=1,H$3<=Inputs!$B$18),Inputs!$B$3*365*H4*(1+Inputs!$B$6)^(H$3-1)*POWER(1+Inputs!$B$11,Inputs!$B$10),0) -> 15464324 | I7: =IF(AND(I$3>=1,I$3<=Inputs!$B$18),Inputs!$B$3*365*I4*(1+Inputs!$B$6)^(I$3-1)*POWER(1+Inputs!$B$11,Inputs!$B$10),0) -> 15804539 | ... AF7: =IF(AND(AF$3>=1,AF$3<=Inputs!$B$18),Inputs!$B$3*365*AF4*(1+Inputs!$B$6)^(AF$3-1)*POWER(1+Inputs!$B$11,Inputs!$B$10),0) -> 26070685
A8: Heavy traffic | B8: =IF(AND(B$3>=1,B$3<=Inputs!$B$18),Inputs!$B$4*365*B4*(1+Inputs!$B$6)^(B$3-1)*POWER(1+Inputs!$B$11,Inputs!$B$10),0) -> 0 | C8: =IF(AND(C$3>=1,C$3<=Inputs!$B$18),Inputs!$B$4*365*C4*(1+Inputs!$B$6)^(C$3-1)*POWER(1+Inputs!$B$11,Inputs!$B$10),0) -> 1423500 | D8: =IF(AND(D$3>=1,D$3<=Inputs!$B$18),Inputs!$B$4*365*D4*(1+Inputs!$B$6)^(D$3-1)*POWER(1+Inputs!$B$11,Inputs!$B$10),0) -> 1697286.5 | E8: =IF(AND(E$3>=1,E$3<=Inputs!$B$18),Inputs!$B$4*365*E4*(1+Inputs!$B$6)^(E$3-1)*POWER(1+Inputs!$B$11,Inputs!$B$10),0) -> 1982430.6 | F8: =IF(AND(F$3>=1,F$3<=Inputs!$B$18),Inputs!$B$4*365*F4*(1+Inputs!$B$6)^(F$3-1)*POWER(1+Inputs!$B$11,Inputs!$B$10),0) -> 2279299.6 | G8: =IF(AND(G$3>=1,G$3<=Inputs!$B$18),Inputs!$B$4*365*G4*(1+Inputs!$B$6)^(G$3-1)*POWER(1+Inputs!$B$11,Inputs!$B$10),0) -> 2588271.3 | H8: =IF(AND(H$3>=1,H$3<=Inputs!$B$18),Inputs!$B$4*365*H4*(1+Inputs!$B$6)^(H$3-1)*POWER(1+Inputs!$B$11,Inputs!$B$10),0) -> 2645213.3 | I8: =IF(AND(I$3>=1,I$3<=Inputs!$B$18),Inputs!$B$4*365*I4*(1+Inputs!$B$6)^(I$3-1)*POWER(1+Inputs!$B$11,Inputs!$B$10),0) -> 2703408 | ... AF8: =IF(AND(AF$3>=1,AF$3<=Inputs!$B$18),Inputs!$B$4*365*AF4*(1+Inputs!$B$6)^(AF$3-1)*POWER(1+Inputs!$B$11,Inputs!$B$10),0) -> 4459459.2
A9: Revenue | B9: =B7*B5+B8*B6 -> 0 | C9: =C7*C5+C8*C6 -> 51322650 | D9: =D7*D5+D8*D6 -> 62525423 | E9: =E7*E5+E8*E6 -> 74783383 | F9: =F7*F5+F8*F6 -> 87770568 | G9: =G7*G5+G8*G6 -> 1.0018601e+08 | H9: =H7*H5+H8*H6 -> 1.047301e+08 | I9: =I7*I5+I8*I6 -> 1.0942564e+08 | ... AF9: =AF7*AF5+AF8*AF6 -> 2.865031e+08
A10: O&M | B10: =IF(AND(B$3>=1,B$3<=Inputs!$B$18),Inputs!$B$12*(1+Inputs!$B$9)^(B$3-1),0) -> 0 | C10: =IF(AND(C$3>=1,C$3<=Inputs!$B$18),Inputs!$B$12*(1+Inputs!$B$9)^(C$3-1),0) -> 21000000 | D10: =IF(AND(D$3>=1,D$3<=Inputs!$B$18),Inputs!$B$12*(1+Inputs!$B$9)^(D$3-1),0) -> 21420000 | E10: =IF(AND(E$3>=1,E$3<=Inputs!$B$18),Inputs!$B$12*(1+Inputs!$B$9)^(E$3-1),0) -> 21848400 | F10: =IF(AND(F$3>=1,F$3<=Inputs!$B$18),Inputs!$B$12*(1+Inputs!$B$9)^(F$3-1),0) -> 22285368 | G10: =IF(AND(G$3>=1,G$3<=Inputs!$B$18),Inputs!$B$12*(1+Inputs!$B$9)^(G$3-1),0) -> 22731075 | H10: =IF(AND(H$3>=1,H$3<=Inputs!$B$18),Inputs!$B$12*(1+Inputs!$B$9)^(H$3-1),0) -> 23185697 | I10: =IF(AND(I$3>=1,I$3<=Inputs!$B$18),Inputs!$B$12*(1+Inputs!$B$9)^(I$3-1),0) -> 23649411 | ... AF10: =IF(AND(AF$3>=1,AF$3<=Inputs!$B$18),Inputs!$B$12*(1+Inputs!$B$9)^(AF$3-1),0) -> 37292738
A11: Major maintenance | B11: =IF(AND(B$3>=1,B$3<=Inputs!$B$18,MOD(B$3,Inputs!$B$13)=0),Inputs!$B$14*(1+Inputs!$B$9)^(B$3-1),0) -> 0 | C11: =IF(AND(C$3>=1,C$3<=Inputs!$B$18,MOD(C$3,Inputs!$B$13)=0),Inputs!$B$14*(1+Inputs!$B$9)^(C$3-1),0) -> 0 | D11: =IF(AND(D$3>=1,D$3<=Inputs!$B$18,MOD(D$3,Inputs!$B$13)=0),Inputs!$B$14*(1+Inputs!$B$9)^(D$3-1),0) -> 0 | E11: =IF(AND(E$3>=1,E$3<=Inputs!$B$18,MOD(E$3,Inputs!$B$13)=0),Inputs!$B$14*(1+Inputs!$B$9)^(E$3-1),0) -> 0 | F11: =IF(AND(F$3>=1,F$3<=Inputs!$B$18,MOD(F$3,Inputs!$B$13)=0),Inputs!$B$14*(1+Inputs!$B$9)^(F$3-1),0) -> 0 | G11: =IF(AND(G$3>=1,G$3<=Inputs!$B$18,MOD(G$3,Inputs!$B$13)=0),Inputs!$B$14*(1+Inputs!$B$9)^(G$3-1),0) -> 0 | H11: =IF(AND(H$3>=1,H$3<=Inputs!$B$18,MOD(H$3,Inputs!$B$13)=0),Inputs!$B$14*(1+Inputs!$B$9)^(H$3-1),0) -> 0 | I11: =IF(AND(I$3>=1,I$3<=Inputs!$B$18,MOD(I$3,Inputs!$B$13)=0),Inputs!$B$14*(1+Inputs!$B$9)^(I$3-1),0) -> 0 | ... AF11: =IF(AND(AF$3>=1,AF$3<=Inputs!$B$18,MOD(AF$3,Inputs!$B$13)=0),Inputs!$B$14*(1+Inputs!$B$9)^(AF$3-1),0) -> 0
A12: CFADS | B12: =B9-B10-B11 -> 0 | C12: =C9-C10-C11 -> 30322650 | D12: =D9-D10-D11 -> 41105423 | E12: =E9-E10-E11 -> 52934983 | F12: =F9-F10-F11 -> 65485200 | G12: =G9-G10-G11 -> 77454935 | H12: =H9-H10-H11 -> 81544403 | I12: =I9-I10-I11 -> 85776227 | ... AF12: =AF9-AF10-AF11 -> 2.4921037e+08
A13: Opening debt | B13: =Inputs!$B$15 -> 780000000 | C13: =B13-B15 -> 780000000 | D13: =C13-C15 -> 780000000 | E13: =D13-D15 -> 780000000 | F13: =E13-E15 -> 7.5590777e+08 | G13: =F13-F15 -> 7.3065911e+08 | H13: =G13-G15 -> 7.0419852e+08 | I13: =H13-H15 -> 6.7646782e+08 | J13: =I13-I15 -> 6.4740604e+08 | ... AF13: =AE13-AE15 -> 0
A14: Interest | B14: =0 -> 0 | C14: =C13*Inputs!$B$16 -> 37440000 | D14: =D13*Inputs!$B$16 -> 37440000 | E14: =E13*Inputs!$B$16 -> 37440000 | F14: =F13*Inputs!$B$16 -> 36283573 | G14: =G13*Inputs!$B$16 -> 35071637 | H14: =H13*Inputs!$B$16 -> 33801529 | I14: =I13*Inputs!$B$16 -> 32470455 | J14: =J13*Inputs!$B$16 -> 31075490 | ... AF14: =AF13*Inputs!$B$16 -> 0
A15: Repayment | B15: =0 -> 0 | C15: =IF(C$3=Inputs!$B$17,C13,IF(AND(C$3>2,C$3<Inputs!$B$17),MIN(C13,-PPMT(Inputs!$B$16,C$3-2,Inputs!$B$17-2,Inputs!$B$15)),0)) -> 0 | D15: =IF(D$3=Inputs!$B$17,D13,IF(AND(D$3>2,D$3<Inputs!$B$17),MIN(D13,-PPMT(Inputs!$B$16,D$3-2,Inputs!$B$17-2,Inputs!$B$15)),0)) -> 0 | E15: =IF(E$3=Inputs!$B$17,E13,IF(AND(E$3>2,E$3<Inputs!$B$17),MIN(E13,-PPMT(Inputs!$B$16,E$3-2,Inputs!$B$17-2,Inputs!$B$15)),0)) -> 24092230 | F15: =IF(F$3=Inputs!$B$17,F13,IF(AND(F$3>2,F$3<Inputs!$B$17),MIN(F13,-PPMT(Inputs!$B$16,F$3-2,Inputs!$B$17-2,Inputs!$B$15)),0)) -> 25248657 | G15: =IF(G$3=Inputs!$B$17,G13,IF(AND(G$3>2,G$3<Inputs!$B$17),MIN(G13,-PPMT(Inputs!$B$16,G$3-2,Inputs!$B$17-2,Inputs!$B$15)),0)) -> 26460593 | H15: =IF(H$3=Inputs!$B$17,H13,IF(AND(H$3>2,H$3<Inputs!$B$17),MIN(H13,-PPMT(Inputs!$B$16,H$3-2,Inputs!$B$17-2,Inputs!$B$15)),0)) -> 27730701 | I15: =IF(I$3=Inputs!$B$17,I13,IF(AND(I$3>2,I$3<Inputs!$B$17),MIN(I13,-PPMT(Inputs!$B$16,I$3-2,Inputs!$B$17-2,Inputs!$B$15)),0)) -> 29061775 | J15: =IF(J$3=Inputs!$B$17,J13,IF(AND(J$3>2,J$3<Inputs!$B$17),MIN(J13,-PPMT(Inputs!$B$16,J$3-2,Inputs!$B$17-2,Inputs!$B$15)),0)) -> 30456740 | ... AF15: =IF(AF$3=Inputs!$B$17,AF13,IF(AND(AF$3>2,AF$3<Inputs!$B$17),MIN(AF13,-PPMT(Inputs!$B$16,AF$3-2,Inputs!$B$17-2,Inputs!$B$15)),0)) -> 0
A16: DSCR | B16: =IF(B14+B15>0,B12/(B14+B15),0) -> 0 | C16: =IF(C14+C15>0,C12/(C14+C15),0) -> 0.80989984 | D16: =IF(D14+D15>0,D12/(D14+D15),0) -> 1.0979013 | E16: =IF(E14+E15>0,E12/(E14+E15),0) -> 0.86028059 | F16: =IF(F14+F15>0,F12/(F14+F15),0) -> 1.0642423 | G16: =IF(G14+G15>0,G12/(G14+G15),0) -> 1.2587702 | H16: =IF(H14+H15>0,H12/(H14+H15),0) -> 1.3252307 | I16: =IF(I14+I15>0,I12/(I14+I15),0) -> 1.3940048 | ... AF16: =IF(AF14+AF15>0,AF12/(AF14+AF15),0) -> 0
A17: Equity cash flow | B17: =-(Inputs!$B$19-Inputs!$B$15) -> -370000000 | C17: =C12-C14-C15 -> -7117350 | D17: =D12-D14-D15 -> 3665423.5 | E17: =E12-E14-E15 -> -8597246.9 | F17: =F12-F14-F15 -> 3952970.3 | G17: =G12-G14-G15 -> 15922705 | H17: =H12-H14-H15 -> 20012172 | I17: =I12-I14-I15 -> 24243997 | J17: =J12-J14-J15 -> -46318395 | ... AF17: =AF12-AF14-AF15 -> 2.4921037e+08

Sheet Returns
A3: Equity IRR | B3: =IRR('Cash Flow'!$B$17:$AF$17) -> 0.091532418
A4: Minimum DSCR | B4: =_xlfn.MINIFS('Cash Flow'!$B$16:$AF$16,'Cash Flow'!$B$16:$AF$16,">0") -> 0.24724986
A5: Average DSCR | B5: =AVERAGEIF('Cash Flow'!$B$16:$AF$16,">0") -> 1.6491202
A6: Tail (years after the debt) | B6: =Inputs!$B$18-Inputs!$B$17 -> 8
A7: Revenue over the concession (EUR) | B7: =SUM('Cash Flow'!$B$9:$AF$9) -> 4.9071172e+09
A8: Peak debt (EUR) | B8: =Inputs!$B$15 -> 780000000
A9: Net profit (EUR) | B9: =SUM('Cash Flow'!$B$17:$AF$17) -> 2.1150185e+09
