Workbook

Sheet Inputs
A1: WADI AL NAKHEEL – DATE PALM PLANTATION (SAR)
A3: Price per tonne, premium grade (SAR) | B3: 14500
A4: Standard grade discount | B4: 0.35
A5: Premium share of the crop | B5: 0.55
A6: Price growth a year | B6: 0.02
A7: Water and power per tree a year (SAR) | B7: 95
A8: Labour per tree a year (SAR) | B8: 140
A9: Cost growth a year | B9: 0.03
A10: Irrigation capex per tree (SAR) | B10: 260
A11: Irrigation life (years) | B11: 12
A12: Subsidy per tree, first 5 years (SAR) | B12: 60
A13: Land and planting (SAR) | B13: 185000000
A14: Discount rate | B14: 0.09

Sheet Blocks
A1: Block | B1: Trees | C1: Planted in year
A2: Block A | B2: 42000 | C2: 0
A3: Block B | B3: 38000 | C3: 2
A4: Block C | B4: 51000 | C4: 4
A5: Block D | B5: 29000 | C5: 7

Sheet Yield
A1: Tree age from (years) | B1: Kg per tree
A2: 0 | B2: 0
A3: 4 | B3: 8
A4: 6 | B4: 25
A5: 8 | B5: 45
A6: 10 | B6: 70
A7: 15 | B7: 85
A8: 25 | B8: 75
A9: 35 | B9: 55

Sheet Cash Flow
A3: Year | B3: 0 | C3: 1 | D3: 2 | E3: 3 | F3: 4 | G3: 5 | H3: 6 | I3: 7 | J3: 8 | K3: 9 | L3: 10 | M3: 11 | N3: 12 | O3: 13 | P3: 14 | Q3: 15 | R3: 16 | S3: 17 | T3: 18 | U3: 19 | V3: 20 | W3: 21 | X3: 22 | Y3: 23 | Z3: 24 | AA3: 25 | AB3: 26 | AC3: 27 | AD3: 28 | AE3: 29 | AF3: 30
A4: Block A kg | B4: =IF(B$3>=Blocks!$C$2,Blocks!$B$2*LOOKUP(B$3-Blocks!$C$2,Yield!$A$2:$A$9,Yield!$B$2:$B$9),0) -> 0 | C4: =IF(C$3>=Blocks!$C$2,Blocks!$B$2*LOOKUP(C$3-Blocks!$C$2,Yield!$A$2:$A$9,Yield!$B$2:$B$9),0) -> 0 | D4: =IF(D$3>=Blocks!$C$2,Blocks!$B$2*LOOKUP(D$3-Blocks!$C$2,Yield!$A$2:$A$9,Yield!$B$2:$B$9),0) -> 0 | E4: =IF(E$3>=Blocks!$C$2,Blocks!$B$2*LOOKUP(E$3-Blocks!$C$2,Yield!$A$2:$A$9,Yield!$B$2:$B$9),0) -> 0 | F4: =IF(F$3>=Blocks!$C$2,Blocks!$B$2*LOOKUP(F$3-Blocks!$C$2,Yield!$A$2:$A$9,Yield!$B$2:$B$9),0) -> 336000 | G4: =IF(G$3>=Blocks!$C$2,Blocks!$B$2*LOOKUP(G$3-Blocks!$C$2,Yield!$A$2:$A$9,Yield!$B$2:$B$9),0) -> 336000 | H4: =IF(H$3>=Blocks!$C$2,Blocks!$B$2*LOOKUP(H$3-Blocks!$C$2,Yield!$A$2:$A$9,Yield!$B$2:$B$9),0) -> 1050000 | I4: =IF(I$3>=Blocks!$C$2,Blocks!$B$2*LOOKUP(I$3-Blocks!$C$2,Yield!$A$2:$A$9,Yield!$B$2:$B$9),0) -> 1050000 | ... AF4: =IF(AF$3>=Blocks!$C$2,Blocks!$B$2*LOOKUP(AF$3-Blocks!$C$2,Yield!$A$2:$A$9,Yield!$B$2:$B$9),0) -> 3150000
A5: Block B kg | B5: =IF(B$3>=Blocks!$C$3,Blocks!$B$3*LOOKUP(B$3-Blocks!$C$3,Yield!$A$2:$A$9,Yield!$B$2:$B$9),0) -> 0 | C5: =IF(C$3>=Blocks!$C$3,Blocks!$B$3*LOOKUP(C$3-Blocks!$C$3,Yield!$A$2:$A$9,Yield!$B$2:$B$9),0) -> 0 | D5: =IF(D$3>=Blocks!$C$3,Blocks!$B$3*LOOKUP(D$3-Blocks!$C$3,Yield!$A$2:$A$9,Yield!$B$2:$B$9),0) -> 0 | E5: =IF(E$3>=Blocks!$C$3,Blocks!$B$3*LOOKUP(E$3-Blocks!$C$3,Yield!$A$2:$A$9,Yield!$B$2:$B$9),0) -> 0 | F5: =IF(F$3>=Blocks!$C$3,Blocks!$B$3*LOOKUP(F$3-Blocks!$C$3,Yield!$A$2:$A$9,Yield!$B$2:$B$9),0) -> 0 | G5: =IF(G$3>=Blocks!$C$3,Blocks!$B$3*LOOKUP(G$3-Blocks!$C$3,Yield!$A$2:$A$9,Yield!$B$2:$B$9),0) -> 0 | H5: =IF(H$3>=Blocks!$C$3,Blocks!$B$3*LOOKUP(H$3-Blocks!$C$3,Yield!$A$2:$A$9,Yield!$B$2:$B$9),0) -> 304000 | I5: =IF(I$3>=Blocks!$C$3,Blocks!$B$3*LOOKUP(I$3-Blocks!$C$3,Yield!$A$2:$A$9,Yield!$B$2:$B$9),0) -> 304000 | ... AF5: =IF(AF$3>=Blocks!$C$3,Blocks!$B$3*LOOKUP(AF$3-Blocks!$C$3,Yield!$A$2:$A$9,Yield!$B$2:$B$9),0) -> 2850000
A6: Block C kg | B6: =IF(B$3>=Blocks!$C$4,Blocks!$B$4*LOOKUP(B$3-Blocks!$C$4,Yield!$A$2:$A$9,Yield!$B$2:$B$9),0) -> 0 | C6: =IF(C$3>=Blocks!$C$4,Blocks!$B$4*LOOKUP(C$3-Blocks!$C$4,Yield!$A$2:$A$9,Yield!$B$2:$B$9),0) -> 0 | D6: =IF(D$3>=Blocks!$C$4,Blocks!$B$4*LOOKUP(D$3-Blocks!$C$4,Yield!$A$2:$A$9,Yield!$B$2:$B$9),0) -> 0 | E6: =IF(E$3>=Blocks!$C$4,Blocks!$B$4*LOOKUP(E$3-Blocks!$C$4,Yield!$A$2:$A$9,Yield!$B$2:$B$9),0) -> 0 | F6: =IF(F$3>=Blocks!$C$4,Blocks!$B$4*LOOKUP(F$3-Blocks!$C$4,Yield!$A$2:$A$9,Yield!$B$2:$B$9),0) -> 0 | G6: =IF(G$3>=Blocks!$C$4,Blocks!$B$4*LOOKUP(G$3-Blocks!$C$4,Yield!$A$2:$A$9,Yield!$B$2:$B$9),0) -> 0 | H6: =IF(H$3>=Blocks!$C$4,Blocks!$B$4*LOOKUP(H$3-Blocks!$C$4,Yield!$A$2:$A$9,Yield!$B$2:$B$9),0) -> 0 | I6: =IF(I$3>=Blocks!$C$4,Blocks!$B$4*LOOKUP(I$3-Blocks!$C$4,Yield!$A$2:$A$9,Yield!$B$2:$B$9),0) -> 0 | ... AF6: =IF(AF$3>=Blocks!$C$4,Blocks!$B$4*LOOKUP(AF$3-Blocks!$C$4,Yield!$A$2:$A$9,Yield!$B$2:$B$9),0) -> 3825000
A7: Block D kg | B7: =IF(B$3>=Blocks!$C$5,Blocks!$B$5*LOOKUP(B$3-Blocks!$C$5,Yield!$A$2:$A$9,Yield!$B$2:$B$9),0) -> 0 | C7: =IF(C$3>=Blocks!$C$5,Blocks!$B$5*LOOKUP(C$3-Blocks!$C$5,Yield!$A$2:$A$9,Yield!$B$2:$B$9),0) -> 0 | D7: =IF(D$3>=Blocks!$C$5,Blocks!$B$5*LOOKUP(D$3-Blocks!$C$5,Yield!$A$2:$A$9,Yield!$B$2:$B$9),0) -> 0 | E7: =IF(E$3>=Blocks!$C$5,Blocks!$B$5*LOOKUP(E$3-Blocks!$C$5,Yield!$A$2:$A$9,Yield!$B$2:$B$9),0) -> 0 | F7: =IF(F$3>=Blocks!$C$5,Blocks!$B$5*LOOKUP(F$3-Blocks!$C$5,Yield!$A$2:$A$9,Yield!$B$2:$B$9),0) -> 0 | G7: =IF(G$3>=Blocks!$C$5,Blocks!$B$5*LOOKUP(G$3-Blocks!$C$5,Yield!$A$2:$A$9,Yield!$B$2:$B$9),0) -> 0 | H7: =IF(H$3>=Blocks!$C$5,Blocks!$B$5*LOOKUP(H$3-Blocks!$C$5,Yield!$A$2:$A$9,Yield!$B$2:$B$9),0) -> 0 | I7: =IF(I$3>=Blocks!$C$5,Blocks!$B$5*LOOKUP(I$3-Blocks!$C$5,Yield!$A$2:$A$9,Yield!$B$2:$B$9),0) -> 0 | ... AF7: =IF(AF$3>=Blocks!$C$5,Blocks!$B$5*LOOKUP(AF$3-Blocks!$C$5,Yield!$A$2:$A$9,Yield!$B$2:$B$9),0) -> 2465000
A8: Trees bearing | B8: =IF(B$3>=Blocks!$C$2,Blocks!$B$2,0)+IF(B$3>=Blocks!$C$3,Blocks!$B$3,0)+IF(B$3>=Blocks!$C$4,Blocks!$B$4,0)+IF(B$3>=Blocks!$C$5,Blocks!$B$5,0) -> 42000 | C8: =IF(C$3>=Blocks!$C$2,Blocks!$B$2,0)+IF(C$3>=Blocks!$C$3,Blocks!$B$3,0)+IF(C$3>=Blocks!$C$4,Blocks!$B$4,0)+IF(C$3>=Blocks!$C$5,Blocks!$B$5,0) -> 42000 | D8: =IF(D$3>=Blocks!$C$2,Blocks!$B$2,0)+IF(D$3>=Blocks!$C$3,Blocks!$B$3,0)+IF(D$3>=Blocks!$C$4,Blocks!$B$4,0)+IF(D$3>=Blocks!$C$5,Blocks!$B$5,0) -> 80000 | E8: =IF(E$3>=Blocks!$C$2,Blocks!$B$2,0)+IF(E$3>=Blocks!$C$3,Blocks!$B$3,0)+IF(E$3>=Blocks!$C$4,Blocks!$B$4,0)+IF(E$3>=Blocks!$C$5,Blocks!$B$5,0) -> 80000 | F8: =IF(F$3>=Blocks!$C$2,Blocks!$B$2,0)+IF(F$3>=Blocks!$C$3,Blocks!$B$3,0)+IF(F$3>=Blocks!$C$4,Blocks!$B$4,0)+IF(F$3>=Blocks!$C$5,Blocks!$B$5,0) -> 131000 | G8: =IF(G$3>=Blocks!$C$2,Blocks!$B$2,0)+IF(G$3>=Blocks!$C$3,Blocks!$B$3,0)+IF(G$3>=Blocks!$C$4,Blocks!$B$4,0)+IF(G$3>=Blocks!$C$5,Blocks!$B$5,0) -> 131000 | H8: =IF(H$3>=Blocks!$C$2,Blocks!$B$2,0)+IF(H$3>=Blocks!$C$3,Blocks!$B$3,0)+IF(H$3>=Blocks!$C$4,Blocks!$B$4,0)+IF(H$3>=Blocks!$C$5,Blocks!$B$5,0) -> 131000 | I8: =IF(I$3>=Blocks!$C$2,Blocks!$B$2,0)+IF(I$3>=Blocks!$C$3,Blocks!$B$3,0)+IF(I$3>=Blocks!$C$4,Blocks!$B$4,0)+IF(I$3>=Blocks!$C$5,Blocks!$B$5,0) -> 160000 | ... AF8: =IF(AF$3>=Blocks!$C$2,Blocks!$B$2,0)+IF(AF$3>=Blocks!$C$3,Blocks!$B$3,0)+IF(AF$3>=Blocks!$C$4,Blocks!$B$4,0)+IF(AF$3>=Blocks!$C$5,Blocks!$B$5,0) -> 160000
A9: Crop (tonnes) | B9: =(B4+B5+B6+B7)/1000 -> 0 | C9: =(C4+C5+C6+C7)/1000 -> 0 | D9: =(D4+D5+D6+D7)/1000 -> 0 | E9: =(E4+E5+E6+E7)/1000 -> 0 | F9: =(F4+F5+F6+F7)/1000 -> 336 | G9: =(G4+G5+G6+G7)/1000 -> 336 | H9: =(H4+H5+H6+H7)/1000 -> 1354 | I9: =(I4+I5+I6+I7)/1000 -> 1354 | ... AF9: =(AF4+AF5+AF6+AF7)/1000 -> 12290
A10: Price index | B10: =(1+Inputs!$B$6)^B$3 -> 1 | C10: =(1+Inputs!$B$6)^C$3 -> 1.02 | D10: =(1+Inputs!$B$6)^D$3 -> 1.0404 | E10: =(1+Inputs!$B$6)^E$3 -> 1.061208 | F10: =(1+Inputs!$B$6)^F$3 -> 1.0824322 | G10: =(1+Inputs!$B$6)^G$3 -> 1.1040808 | H10: =(1+Inputs!$B$6)^H$3 -> 1.1261624 | I10: =(1+Inputs!$B$6)^I$3 -> 1.1486857 | ... AF10: =(1+Inputs!$B$6)^AF$3 -> 1.8113616
A11: Revenue | B11: =B9*Inputs!$B$3*B10*(Inputs!$B$5+(1-Inputs!$B$5)*(1-Inputs!$B$4)) -> 0 | C11: =C9*Inputs!$B$3*C10*(Inputs!$B$5+(1-Inputs!$B$5)*(1-Inputs!$B$4)) -> 0 | D11: =D9*Inputs!$B$3*D10*(Inputs!$B$5+(1-Inputs!$B$5)*(1-Inputs!$B$4)) -> 0 | E11: =E9*Inputs!$B$3*E10*(Inputs!$B$5+(1-Inputs!$B$5)*(1-Inputs!$B$4)) -> 0 | F11: =F9*Inputs!$B$3*F10*(Inputs!$B$5+(1-Inputs!$B$5)*(1-Inputs!$B$4)) -> 4443016 | G11: =G9*Inputs!$B$3*G10*(Inputs!$B$5+(1-Inputs!$B$5)*(1-Inputs!$B$4)) -> 4531876.3 | H11: =H9*Inputs!$B$3*H10*(Inputs!$B$5+(1-Inputs!$B$5)*(1-Inputs!$B$4)) -> 18627630 | I11: =I9*Inputs!$B$3*I10*(Inputs!$B$5+(1-Inputs!$B$5)*(1-Inputs!$B$4)) -> 19000183 | ... AF11: =AF9*Inputs!$B$3*AF10*(Inputs!$B$5+(1-Inputs!$B$5)*(1-Inputs!$B$4)) -> 2.7195368e+08
A12: Operating cost | B12: =B8*(Inputs!$B$7+Inputs!$B$8)*(1+Inputs!$B$9)^B$3 -> 9870000 | C12: =C8*(Inputs!$B$7+Inputs!$B$8)*(1+Inputs!$B$9)^C$3 -> 10166100 | D12: =D8*(Inputs!$B$7+Inputs!$B$8)*(1+Inputs!$B$9)^D$3 -> 19944920 | E12: =E8*(Inputs!$B$7+Inputs!$B$8)*(1+Inputs!$B$9)^E$3 -> 20543268 | F12: =F8*(Inputs!$B$7+Inputs!$B$8)*(1+Inputs!$B$9)^F$3 -> 34648789 | G12: =G8*(Inputs!$B$7+Inputs!$B$8)*(1+Inputs!$B$9)^G$3 -> 35688252 | H12: =H8*(Inputs!$B$7+Inputs!$B$8)*(1+Inputs!$B$9)^H$3 -> 36758900 | I12: =I8*(Inputs!$B$7+Inputs!$B$8)*(1+Inputs!$B$9)^I$3 -> 46243257 | ... AF12: =AF8*(Inputs!$B$7+Inputs!$B$8)*(1+Inputs!$B$9)^AF$3 -> 91265069
A13: Irrigation | B13: =IF(AND(B$3>=Blocks!$C$2,MOD(B$3-Blocks!$C$2,Inputs!$B$11)=0),Blocks!$B$2*Inputs!$B$10*(1+Inputs!$B$9)^B$3,0)+IF(AND(B$3>=Blocks!$C$3,MOD(B$3-Blocks!$C$3,Inputs!$B$11)=0),Blocks!$B$3*Inputs!$B$10*(1+Inputs!$B$9)^B$3,0)+IF(AND(B$3>=Blocks!$C$4,MOD(B$3-Blocks!$C$4,Inputs!$B$11)=0),Blocks!$B$4*Inputs!$B$10*(1+Inputs!$B$9)^B$3,0)+IF(AND(B$3>=Blocks!$C$5,MOD(B$3-Blocks!$C$5,Inputs!$B$11)=0),Blocks!$B$5*Inputs!$B$10*(1+Inputs!$B$9)^B$3,0) -> 10920000 | C13: =IF(AND(C$3>=Blocks!$C$2,MOD(C$3-Blocks!$C$2,Inputs!$B$11)=0),Blocks!$B$2*Inputs!$B$10*(1+Inputs!$B$9)^C$3,0)+IF(AND(C$3>=Blocks!$C$3,MOD(C$3-Blocks!$C$3,Inputs!$B$11)=0),Blocks!$B$3*Inputs!$B$10*(1+Inputs!$B$9)^C$3,0)+IF(AND(C$3>=Blocks!$C$4,MOD(C$3-Blocks!$C$4,Inputs!$B$11)=0),Blocks!$B$4*Inputs!$B$10*(1+Inputs!$B$9)^C$3,0)+IF(AND(C$3>=Blocks!$C$5,MOD(C$3-Blocks!$C$5,Inputs!$B$11)=0),Blocks!$B$5*Inputs!$B$10*(1+Inputs!$B$9)^C$3,0) -> 0 | D13: =IF(AND(D$3>=Blocks!$C$2,MOD(D$3-Blocks!$C$2,Inputs!$B$11)=0),Blocks!$B$2*Inputs!$B$10*(1+Inputs!$B$9)^D$3,0)+IF(AND(D$3>=Blocks!$C$3,MOD(D$3-Blocks!$C$3,Inputs!$B$11)=0),Blocks!$B$3*Inputs!$B$10*(1+Inputs!$B$9)^D$3,0)+IF(AND(D$3>=Blocks!$C$4,MOD(D$3-Blocks!$C$4,Inputs!$B$11)=0),Blocks!$B$4*Inputs!$B$10*(1+Inputs!$B$9)^D$3,0)+IF(AND(D$3>=Blocks!$C$5,MOD(D$3-Blocks!$C$5,Inputs!$B$11)=0),Blocks!$B$5*Inputs!$B$10*(1+Inputs!$B$9)^D$3,0) -> 10481692 | E13: =IF(AND(E$3>=Blocks!$C$2,MOD(E$3-Blocks!$C$2,Inputs!$B$11)=0),Blocks!$B$2*Inputs!$B$10*(1+Inputs!$B$9)^E$3,0)+IF(AND(E$3>=Blocks!$C$3,MOD(E$3-Blocks!$C$3,Inputs!$B$11)=0),Blocks!$B$3*Inputs!$B$10*(1+Inputs!$B$9)^E$3,0)+IF(AND(E$3>=Blocks!$C$4,MOD(E$3-Blocks!$C$4,Inputs!$B$11)=0),Blocks!$B$4*Inputs!$B$10*(1+Inputs!$B$9)^E$3,0)+IF(AND(E$3>=Blocks!$C$5,MOD(E$3-Blocks!$C$5,Inputs!$B$11)=0),Blocks!$B$5*Inputs!$B$10*(1+Inputs!$B$9)^E$3,0) -> 0 | F13: =IF(AND(F$3>=Blocks!$C$2,MOD(F$3-Blocks!$C$2,Inputs!$B$11)=0),Blocks!$B$2*Inputs!$B$10*(1+Inputs!$B$9)^F$3,0)+IF(AND(F$3>=Blocks!$C$3,MOD(F$3-Blocks!$C$3,Inputs!$B$11)=0),Blocks!$B$3*Inputs!$B$10*(1+Inputs!$B$9)^F$3,0)+IF(AND(F$3>=Blocks!$C$4,MOD(F$3-Blocks!$C$4,Inputs!$B$11)=0),Blocks!$B$4*Inputs!$B$10*(1+Inputs!$B$9)^F$3,0)+IF(AND(F$3>=Blocks!$C$5,MOD(F$3-Blocks!$C$5,Inputs!$B$11)=0),Blocks!$B$5*Inputs!$B$10*(1+Inputs!$B$9)^F$3,0) -> 14924247 | G13: =IF(AND(G$3>=Blocks!$C$2,MOD(G$3-Blocks!$C$2,Inputs!$B$11)=0),Blocks!$B$2*Inputs!$B$10*(1+Inputs!$B$9)^G$3,0)+IF(AND(G$3>=Blocks!$C$3,MOD(G$3-Blocks!$C$3,Inputs!$B$11)=0),Blocks!$B$3*Inputs!$B$10*(1+Inputs!$B$9)^G$3,0)+IF(AND(G$3>=Blocks!$C$4,MOD(G$3-Blocks!$C$4,Inputs!$B$11)=0),Blocks!$B$4*Inputs!$B$10*(1+Inputs!$B$9)^G$3,0)+IF(AND(G$3>=Blocks!$C$5,MOD(G$3-Blocks!$C$5,Inputs!$B$11)=0),Blocks!$B$5*Inputs!$B$10*(1+Inputs!$B$9)^G$3,0) -> 0 | H13: =IF(AND(H$3>=Blocks!$C$2,MOD(H$3-Blocks!$C$2,Inputs!$B$11)=0),Blocks!$B$2*Inputs!$B$10*(1+Inputs!$B$9)^H$3,0)+IF(AND(H$3>=Blocks!$C$3,MOD(H$3-Blocks!$C$3,Inputs!$B$11)=0),Blocks!$B$3*Inputs!$B$10*(1+Inputs!$B$9)^H$3,0)+IF(AND(H$3>=Blocks!$C$4,MOD(H$3-Blocks!$C$4,Inputs!$B$11)=0),Blocks!$B$4*Inputs!$B$10*(1+Inputs!$B$9)^H$3,0)+IF(AND(H$3>=Blocks!$C$5,MOD(H$3-Blocks!$C$5,Inputs!$B$11)=0),Blocks!$B$5*Inputs!$B$10*(1+Inputs!$B$9)^H$3,0) -> 0 | I13: =IF(AND(I$3>=Blocks!$C$2,MOD(I$3-Blocks!$C$2,Inputs!$B$11)=0),Blocks!$B$2*Inputs!$B$10*(1+Inputs!$B$9)^I$3,0)+IF(AND(I$3>=Blocks!$C$3,MOD(I$3-Blocks!$C$3,Inputs!$B$11)=0),Blocks!$B$3*Inputs!$B$10*(1+Inputs!$B$9)^I$3,0)+IF(AND(I$3>=Blocks!$C$4,MOD(I$3-Blocks!$C$4,Inputs!$B$11)=0),Blocks!$B$4*Inputs!$B$10*(1+Inputs!$B$9)^I$3,0)+IF(AND(I$3>=Blocks!$C$5,MOD(I$3-Blocks!$C$5,Inputs!$B$11)=0),Blocks!$B$5*Inputs!$B$10*(1+Inputs!$B$9)^I$3,0) -> 9273248.9 | ... AF13: =IF(AND(AF$3>=Blocks!$C$2,MOD(AF$3-Blocks!$C$2,Inputs!$B$11)=0),Blocks!$B$2*Inputs!$B$10*(1+Inputs!$B$9)^AF$3,0)+IF(AND(AF$3>=Blocks!$C$3,MOD(AF$3-Blocks!$C$3,Inputs!$B$11)=0),Blocks!$B$3*Inputs!$B$10*(1+Inputs!$B$9)^AF$3,0)+IF(AND(AF$3>=Blocks!$C$4,MOD(AF$3-Blocks!$C$4,Inputs!$B$11)=0),Blocks!$B$4*Inputs!$B$10*(1+Inputs!$B$9)^AF$3,0)+IF(AND(AF$3>=Blocks!$C$5,MOD(AF$3-Blocks!$C$5,Inputs!$B$11)=0),Blocks!$B$5*Inputs!$B$10*(1+Inputs!$B$9)^AF$3,0) -> 0
A14: Subsidy | B14: =IF(AND(B$3>=Blocks!$C$2,B$3<Blocks!$C$2+5),Blocks!$B$2*Inputs!$B$12,0)+IF(AND(B$3>=Blocks!$C$3,B$3<Blocks!$C$3+5),Blocks!$B$3*Inputs!$B$12,0)+IF(AND(B$3>=Blocks!$C$4,B$3<Blocks!$C$4+5),Blocks!$B$4*Inputs!$B$12,0)+IF(AND(B$3>=Blocks!$C$5,B$3<Blocks!$C$5+5),Blocks!$B$5*Inputs!$B$12,0) -> 2520000 | C14: =IF(AND(C$3>=Blocks!$C$2,C$3<Blocks!$C$2+5),Blocks!$B$2*Inputs!$B$12,0)+IF(AND(C$3>=Blocks!$C$3,C$3<Blocks!$C$3+5),Blocks!$B$3*Inputs!$B$12,0)+IF(AND(C$3>=Blocks!$C$4,C$3<Blocks!$C$4+5),Blocks!$B$4*Inputs!$B$12,0)+IF(AND(C$3>=Blocks!$C$5,C$3<Blocks!$C$5+5),Blocks!$B$5*Inputs!$B$12,0) -> 2520000 | D14: =IF(AND(D$3>=Blocks!$C$2,D$3<Blocks!$C$2+5),Blocks!$B$2*Inputs!$B$12,0)+IF(AND(D$3>=Blocks!$C$3,D$3<Blocks!$C$3+5),Blocks!$B$3*Inputs!$B$12,0)+IF(AND(D$3>=Blocks!$C$4,D$3<Blocks!$C$4+5),Blocks!$B$4*Inputs!$B$12,0)+IF(AND(D$3>=Blocks!$C$5,D$3<Blocks!$C$5+5),Blocks!$B$5*Inputs!$B$12,0) -> 4800000 | E14: =IF(AND(E$3>=Blocks!$C$2,E$3<Blocks!$C$2+5),Blocks!$B$2*Inputs!$B$12,0)+IF(AND(E$3>=Blocks!$C$3,E$3<Blocks!$C$3+5),Blocks!$B$3*Inputs!$B$12,0)+IF(AND(E$3>=Blocks!$C$4,E$3<Blocks!$C$4+5),Blocks!$B$4*Inputs!$B$12,0)+IF(AND(E$3>=Blocks!$C$5,E$3<Blocks!$C$5+5),Blocks!$B$5*Inputs!$B$12,0) -> 4800000 | F14: =IF(AND(F$3>=Blocks!$C$2,F$3<Blocks!$C$2+5),Blocks!$B$2*Inputs!$B$12,0)+IF(AND(F$3>=Blocks!$C$3,F$3<Blocks!$C$3+5),Blocks!$B$3*Inputs!$B$12,0)+IF(AND(F$3>=Blocks!$C$4,F$3<Blocks!$C$4+5),Blocks!$B$4*Inputs!$B$12,0)+IF(AND(F$3>=Blocks!$C$5,F$3<Blocks!$C$5+5),Blocks!$B$5*Inputs!$B$12,0) -> 7860000 | G14: =IF(AND(G$3>=Blocks!$C$2,G$3<Blocks!$C$2+5),Blocks!$B$2*Inputs!$B$12,0)+IF(AND(G$3>=Blocks!$C$3,G$3<Blocks!$C$3+5),Blocks!$B$3*Inputs!$B$12,0)+IF(AND(G$3>=Blocks!$C$4,G$3<Blocks!$C$4+5),Blocks!$B$4*Inputs!$B$12,0)+IF(AND(G$3>=Blocks!$C$5,G$3<Blocks!$C$5+5),Blocks!$B$5*Inputs!$B$12,0) -> 5340000 | H14: =IF(AND(H$3>=Blocks!$C$2,H$3<Blocks!$C$2+5),Blocks!$B$2*Inputs!$B$12,0)+IF(AND(H$3>=Blocks!$C$3,H$3<Blocks!$C$3+5),Blocks!$B$3*Inputs!$B$12,0)+IF(AND(H$3>=Blocks!$C$4,H$3<Blocks!$C$4+5),Blocks!$B$4*Inputs!$B$12,0)+IF(AND(H$3>=Blocks!$C$5,H$3<Blocks!$C$5+5),Blocks!$B$5*Inputs!$B$12,0) -> 5340000 | I14: =IF(AND(I$3>=Blocks!$C$2,I$3<Blocks!$C$2+5),Blocks!$B$2*Inputs!$B$12,0)+IF(AND(I$3>=Blocks!$C$3,I$3<Blocks!$C$3+5),Blocks!$B$3*Inputs!$B$12,0)+IF(AND(I$3>=Blocks!$C$4,I$3<Blocks!$C$4+5),Blocks!$B$4*Inputs!$B$12,0)+IF(AND(I$3>=Blocks!$C$5,I$3<Blocks!$C$5+5),Blocks!$B$5*Inputs!$B$12,0) -> 4800000 | ... AF14: =IF(AND(AF$3>=Blocks!$C$2,AF$3<Blocks!$C$2+5),Blocks!$B$2*Inputs!$B$12,0)+IF(AND(AF$3>=Blocks!$C$3,AF$3<Blocks!$C$3+5),Blocks!$B$3*Inputs!$B$12,0)+IF(AND(AF$3>=Blocks!$C$4,AF$3<Blocks!$C$4+5),Blocks!$B$4*Inputs!$B$12,0)+IF(AND(AF$3>=Blocks!$C$5,AF$3<Blocks!$C$5+5),Blocks!$B$5*Inputs!$B$12,0) -> 0
A15: Land and planting | B15: =IF(B$3=0,Inputs!$B$13,0) -> 185000000 | C15: =IF(C$3=0,Inputs!$B$13,0) -> 0 | D15: =IF(D$3=0,Inputs!$B$13,0) -> 0 | E15: =IF(E$3=0,Inputs!$B$13,0) -> 0 | F15: =IF(F$3=0,Inputs!$B$13,0) -> 0 | G15: =IF(G$3=0,Inputs!$B$13,0) -> 0 | H15: =IF(H$3=0,Inputs!$B$13,0) -> 0 | I15: =IF(I$3=0,Inputs!$B$13,0) -> 0 | ... AF15: =IF(AF$3=0,Inputs!$B$13,0) -> 0
A16: Net cash flow | B16: =B11-B12-B13+B14-B15 -> -203270000 | C16: =C11-C12-C13+C14-C15 -> -7646100 | D16: =D11-D12-D13+D14-D15 -> -25626612 | E16: =E11-E12-E13+E14-E15 -> -15743268 | F16: =F11-F12-F13+F14-F15 -> -37270020 | G16: =G11-G12-G13+G14-G15 -> -25816376 | H16: =H11-H12-H13+H14-H15 -> -12791270 | I16: =I11-I12-I13+I14-I15 -> -31716324 | ... AF16: =AF11-AF12-AF13+AF14-AF15 -> 1.8068862e+08
A17: Cumulative cash | B17: =SUM($B$16:B16) -> -203270000 | C17: =SUM($B$16:C16) -> -210916100 | D17: =SUM($B$16:D16) -> -236542712 | E17: =SUM($B$16:E16) -> -2.5228598e+08 | F17: =SUM($B$16:F16) -> -2.89556e+08 | G17: =SUM($B$16:G16) -> -3.1537238e+08 | H17: =SUM($B$16:H16) -> -3.2816365e+08 | I17: =SUM($B$16:I16) -> -3.5987997e+08 | ... AF17: =SUM($B$16:AF16) -> 2.5745199e+09

Sheet Returns
A3: Project IRR | B3: =IRR('Cash Flow'!$B$16:$AF$16) -> 0.11951126
A4: NPV at the discount rate (SAR) | B4: ='Cash Flow'!$B$16+NPV(Inputs!$B$14,'Cash Flow'!$C$16:$AF$16) -> 1.8675911e+08
A5: Peak crop (tonnes) | B5: =MAX('Cash Flow'!$B$9:$AF$9) -> 13600
A6: Payback year | B6: =IF(INDEX('Cash Flow'!$B$17:$AF$17,30+1)>0,COUNTIF('Cash Flow'!$B$17:$AF$17,"<=0"),"not reached") -> 15
A7: Revenue over 30 years (SAR) | B7: =SUM('Cash Flow'!$B$11:$AF$11) -> 4.6555882e+09
A8: Net profit (SAR) | B8: =SUM('Cash Flow'!$B$16:$AF$16) -> 2.5745199e+09
