Workbook

Sheet Inputs
A1: AL WASL GALLERIA – REGIONAL MALL, MONTHLY (AED)
A3: Model start | B3: 46387
A4: Market rent line shops (AED/sqm/yr) | B4: 2600
A5: Market rent growth | B5: 0.03
A6: Re-letting void (months) | B6: 6
A7: Tenant sales growth | B7: 0.04
A8: Service charge (AED/sqm/yr) | B8: 310
A9: Service charge recovery cap (AED/sqm/yr) | B9: 290
A10: Service charge growth | B10: 0.035
A11: Exit yield | B11: 0.075
A12: Purchase price (AED) | B12: 2650000000

Sheet Tenants
A1: Tenant | B1: Area (sqm) | C1: Base rent (AED/sqm/yr) | D1: Sales (AED/sqm/yr) | E1: Turnover rent share | F1: Lease expiry
A2: Hypermarket | B2: 22000 | C2: 650 | D2: 9500 | E2: 0.08 | F2: 49125
A3: Department store | B3: 15000 | C3: 820 | D3: 7800 | E3: 0.12 | F3: 48213
A4: Cinema | B4: 8000 | C4: 700 | D4: 5200 | E4: 0.15 | F4: 47208
A5: Fashion line shops | B5: 26000 | C5: 2450 | D5: 14500 | E5: 0.2 | F5: 47026
A6: F&B court | B6: 9000 | C6: 2900 | D6: 16800 | E6: 0.2 | F6: 46752
A7: Electronics | B7: 6000 | C7: 2300 | D7: 21000 | E7: 0.12 | F7: 47664

Sheet Cash Flow
A3: Month | B3: 0 | C3: 1 | D3: 2 | E3: 3 | F3: 4 | G3: 5 | H3: 6 | I3: 7 | J3: 8 | K3: 9 | L3: 10 | M3: 11 | N3: 12 | O3: 13 | P3: 14 | Q3: 15 | R3: 16 | S3: 17 | T3: 18 | U3: 19 | V3: 20 | W3: 21 | X3: 22 | Y3: 23 | Z3: 24 | AA3: 25 | AB3: 26 | AC3: 27 | AD3: 28 | AE3: 29 | AF3: 30 | AG3: 31 | AH3: 32 | AI3: 33 | AJ3: 34 | AK3: 35 | AL3: 36 | AM3: 37 | AN3: 38 | AO3: 39 | AP3: 40 | AQ3: 41 | AR3: 42 | AS3: 43 | AT3: 44 | AU3: 45 | AV3: 46 | AW3: 47 | AX3: 48 | AY3: 49 | AZ3: 50 | BA3: 51 | BB3: 52 | BC3: 53 | BD3: 54 | BE3: 55 | BF3: 56 | BG3: 57 | BH3: 58 | BI3: 59 | BJ3: 60 | BK3: 61 | BL3: 62 | BM3: 63 | BN3: 64 | BO3: 65 | BP3: 66 | BQ3: 67 | BR3: 68 | BS3: 69 | BT3: 70 | BU3: 71 | BV3: 72 | BW3: 73 | BX3: 74 | BY3: 75 | BZ3: 76 | CA3: 77 | CB3: 78 | CC3: 79 | CD3: 80 | CE3: 81 | CF3: 82 | CG3: 83 | CH3: 84 | CI3: 85 | CJ3: 86 | CK3: 87 | CL3: 88 | CM3: 89 | CN3: 90 | CO3: 91 | CP3: 92 | CQ3: 93 | CR3: 94 | CS3: 95 | CT3: 96 | CU3: 97 | CV3: 98 | CW3: 99 | CX3: 100 | CY3: 101 | CZ3: 102 | DA3: 103 | DB3: 104 | DC3: 105 | DD3: 106 | DE3: 107 | DF3: 108 | DG3: 109 | DH3: 110 | DI3: 111 | DJ3: 112 | DK3: 113 | DL3: 114 | DM3: 115 | DN3: 116 | DO3: 117 | DP3: 118 | DQ3: 119 | DR3: 120
A4: Date | B4: =EOMONTH(Inputs!$B$3,B$3) -> 46387 | C4: =EOMONTH(Inputs!$B$3,C$3) -> 46418 | D4: =EOMONTH(Inputs!$B$3,D$3) -> 46446 | E4: =EOMONTH(Inputs!$B$3,E$3) -> 46477 | F4: =EOMONTH(Inputs!$B$3,F$3) -> 46507 | G4: =EOMONTH(Inputs!$B$3,G$3) -> 46538 | H4: =EOMONTH(Inputs!$B$3,H$3) -> 46568 | I4: =EOMONTH(Inputs!$B$3,I$3) -> 46599 | ... DR4: =EOMONTH(Inputs!$B$3,DR$3) -> 50040
A5: Rent 1 | B5: =0 -> 0 | C5: =IF(C4<=Tenants!$F$2,Tenants!$B$2*Tenants!$C$2/12,IF(C4<=EOMONTH(Tenants!$F$2,Inputs!$B$6),0,Tenants!$B$2*Inputs!$B$4*(1+Inputs!$B$5)^(C$3/12)/12*IF(Tenants!$C$2<1000,0.35,1))) -> 1191666.7 | D5: =IF(D4<=Tenants!$F$2,Tenants!$B$2*Tenants!$C$2/12,IF(D4<=EOMONTH(Tenants!$F$2,Inputs!$B$6),0,Tenants!$B$2*Inputs!$B$4*(1+Inputs!$B$5)^(D$3/12)/12*IF(Tenants!$C$2<1000,0.35,1))) -> 1191666.7 | E5: =IF(E4<=Tenants!$F$2,Tenants!$B$2*Tenants!$C$2/12,IF(E4<=EOMONTH(Tenants!$F$2,Inputs!$B$6),0,Tenants!$B$2*Inputs!$B$4*(1+Inputs!$B$5)^(E$3/12)/12*IF(Tenants!$C$2<1000,0.35,1))) -> 1191666.7 | F5: =IF(F4<=Tenants!$F$2,Tenants!$B$2*Tenants!$C$2/12,IF(F4<=EOMONTH(Tenants!$F$2,Inputs!$B$6),0,Tenants!$B$2*Inputs!$B$4*(1+Inputs!$B$5)^(F$3/12)/12*IF(Tenants!$C$2<1000,0.35,1))) -> 1191666.7 | G5: =IF(G4<=Tenants!$F$2,Tenants!$B$2*Tenants!$C$2/12,IF(G4<=EOMONTH(Tenants!$F$2,Inputs!$B$6),0,Tenants!$B$2*Inputs!$B$4*(1+Inputs!$B$5)^(G$3/12)/12*IF(Tenants!$C$2<1000,0.35,1))) -> 1191666.7 | H5: =IF(H4<=Tenants!$F$2,Tenants!$B$2*Tenants!$C$2/12,IF(H4<=EOMONTH(Tenants!$F$2,Inputs!$B$6),0,Tenants!$B$2*Inputs!$B$4*(1+Inputs!$B$5)^(H$3/12)/12*IF(Tenants!$C$2<1000,0.35,1))) -> 1191666.7 | I5: =IF(I4<=Tenants!$F$2,Tenants!$B$2*Tenants!$C$2/12,IF(I4<=EOMONTH(Tenants!$F$2,Inputs!$B$6),0,Tenants!$B$2*Inputs!$B$4*(1+Inputs!$B$5)^(I$3/12)/12*IF(Tenants!$C$2<1000,0.35,1))) -> 1191666.7 | J5: =IF(J4<=Tenants!$F$2,Tenants!$B$2*Tenants!$C$2/12,IF(J4<=EOMONTH(Tenants!$F$2,Inputs!$B$6),0,Tenants!$B$2*Inputs!$B$4*(1+Inputs!$B$5)^(J$3/12)/12*IF(Tenants!$C$2<1000,0.35,1))) -> 1191666.7 | ... DR5: =IF(DR4<=Tenants!$F$2,Tenants!$B$2*Tenants!$C$2/12,IF(DR4<=EOMONTH(Tenants!$F$2,Inputs!$B$6),0,Tenants!$B$2*Inputs!$B$4*(1+Inputs!$B$5)^(DR$3/12)/12*IF(Tenants!$C$2<1000,0.35,1))) -> 2242100.5
A6: Rent 2 | B6: =0 -> 0 | C6: =IF(C4<=Tenants!$F$3,Tenants!$B$3*Tenants!$C$3/12,IF(C4<=EOMONTH(Tenants!$F$3,Inputs!$B$6),0,Tenants!$B$3*Inputs!$B$4*(1+Inputs!$B$5)^(C$3/12)/12*IF(Tenants!$C$3<1000,0.35,1))) -> 1025000 | D6: =IF(D4<=Tenants!$F$3,Tenants!$B$3*Tenants!$C$3/12,IF(D4<=EOMONTH(Tenants!$F$3,Inputs!$B$6),0,Tenants!$B$3*Inputs!$B$4*(1+Inputs!$B$5)^(D$3/12)/12*IF(Tenants!$C$3<1000,0.35,1))) -> 1025000 | E6: =IF(E4<=Tenants!$F$3,Tenants!$B$3*Tenants!$C$3/12,IF(E4<=EOMONTH(Tenants!$F$3,Inputs!$B$6),0,Tenants!$B$3*Inputs!$B$4*(1+Inputs!$B$5)^(E$3/12)/12*IF(Tenants!$C$3<1000,0.35,1))) -> 1025000 | F6: =IF(F4<=Tenants!$F$3,Tenants!$B$3*Tenants!$C$3/12,IF(F4<=EOMONTH(Tenants!$F$3,Inputs!$B$6),0,Tenants!$B$3*Inputs!$B$4*(1+Inputs!$B$5)^(F$3/12)/12*IF(Tenants!$C$3<1000,0.35,1))) -> 1025000 | G6: =IF(G4<=Tenants!$F$3,Tenants!$B$3*Tenants!$C$3/12,IF(G4<=EOMONTH(Tenants!$F$3,Inputs!$B$6),0,Tenants!$B$3*Inputs!$B$4*(1+Inputs!$B$5)^(G$3/12)/12*IF(Tenants!$C$3<1000,0.35,1))) -> 1025000 | H6: =IF(H4<=Tenants!$F$3,Tenants!$B$3*Tenants!$C$3/12,IF(H4<=EOMONTH(Tenants!$F$3,Inputs!$B$6),0,Tenants!$B$3*Inputs!$B$4*(1+Inputs!$B$5)^(H$3/12)/12*IF(Tenants!$C$3<1000,0.35,1))) -> 1025000 | I6: =IF(I4<=Tenants!$F$3,Tenants!$B$3*Tenants!$C$3/12,IF(I4<=EOMONTH(Tenants!$F$3,Inputs!$B$6),0,Tenants!$B$3*Inputs!$B$4*(1+Inputs!$B$5)^(I$3/12)/12*IF(Tenants!$C$3<1000,0.35,1))) -> 1025000 | J6: =IF(J4<=Tenants!$F$3,Tenants!$B$3*Tenants!$C$3/12,IF(J4<=EOMONTH(Tenants!$F$3,Inputs!$B$6),0,Tenants!$B$3*Inputs!$B$4*(1+Inputs!$B$5)^(J$3/12)/12*IF(Tenants!$C$3<1000,0.35,1))) -> 1025000 | ... DR6: =IF(DR4<=Tenants!$F$3,Tenants!$B$3*Tenants!$C$3/12,IF(DR4<=EOMONTH(Tenants!$F$3,Inputs!$B$6),0,Tenants!$B$3*Inputs!$B$4*(1+Inputs!$B$5)^(DR$3/12)/12*IF(Tenants!$C$3<1000,0.35,1))) -> 1528704.9
A7: Rent 3 | B7: =0 -> 0 | C7: =IF(C4<=Tenants!$F$4,Tenants!$B$4*Tenants!$C$4/12,IF(C4<=EOMONTH(Tenants!$F$4,Inputs!$B$6),0,Tenants!$B$4*Inputs!$B$4*(1+Inputs!$B$5)^(C$3/12)/12*IF(Tenants!$C$4<1000,0.35,1))) -> 466666.67 | D7: =IF(D4<=Tenants!$F$4,Tenants!$B$4*Tenants!$C$4/12,IF(D4<=EOMONTH(Tenants!$F$4,Inputs!$B$6),0,Tenants!$B$4*Inputs!$B$4*(1+Inputs!$B$5)^(D$3/12)/12*IF(Tenants!$C$4<1000,0.35,1))) -> 466666.67 | E7: =IF(E4<=Tenants!$F$4,Tenants!$B$4*Tenants!$C$4/12,IF(E4<=EOMONTH(Tenants!$F$4,Inputs!$B$6),0,Tenants!$B$4*Inputs!$B$4*(1+Inputs!$B$5)^(E$3/12)/12*IF(Tenants!$C$4<1000,0.35,1))) -> 466666.67 | F7: =IF(F4<=Tenants!$F$4,Tenants!$B$4*Tenants!$C$4/12,IF(F4<=EOMONTH(Tenants!$F$4,Inputs!$B$6),0,Tenants!$B$4*Inputs!$B$4*(1+Inputs!$B$5)^(F$3/12)/12*IF(Tenants!$C$4<1000,0.35,1))) -> 466666.67 | G7: =IF(G4<=Tenants!$F$4,Tenants!$B$4*Tenants!$C$4/12,IF(G4<=EOMONTH(Tenants!$F$4,Inputs!$B$6),0,Tenants!$B$4*Inputs!$B$4*(1+Inputs!$B$5)^(G$3/12)/12*IF(Tenants!$C$4<1000,0.35,1))) -> 466666.67 | H7: =IF(H4<=Tenants!$F$4,Tenants!$B$4*Tenants!$C$4/12,IF(H4<=EOMONTH(Tenants!$F$4,Inputs!$B$6),0,Tenants!$B$4*Inputs!$B$4*(1+Inputs!$B$5)^(H$3/12)/12*IF(Tenants!$C$4<1000,0.35,1))) -> 466666.67 | I7: =IF(I4<=Tenants!$F$4,Tenants!$B$4*Tenants!$C$4/12,IF(I4<=EOMONTH(Tenants!$F$4,Inputs!$B$6),0,Tenants!$B$4*Inputs!$B$4*(1+Inputs!$B$5)^(I$3/12)/12*IF(Tenants!$C$4<1000,0.35,1))) -> 466666.67 | J7: =IF(J4<=Tenants!$F$4,Tenants!$B$4*Tenants!$C$4/12,IF(J4<=EOMONTH(Tenants!$F$4,Inputs!$B$6),0,Tenants!$B$4*Inputs!$B$4*(1+Inputs!$B$5)^(J$3/12)/12*IF(Tenants!$C$4<1000,0.35,1))) -> 466666.67 | ... DR7: =IF(DR4<=Tenants!$F$4,Tenants!$B$4*Tenants!$C$4/12,IF(DR4<=EOMONTH(Tenants!$F$4,Inputs!$B$6),0,Tenants!$B$4*Inputs!$B$4*(1+Inputs!$B$5)^(DR$3/12)/12*IF(Tenants!$C$4<1000,0.35,1))) -> 815309.27
A8: Rent 4 | B8: =0 -> 0 | C8: =IF(C4<=Tenants!$F$5,Tenants!$B$5*Tenants!$C$5/12,IF(C4<=EOMONTH(Tenants!$F$5,Inputs!$B$6),0,Tenants!$B$5*Inputs!$B$4*(1+Inputs!$B$5)^(C$3/12)/12*IF(Tenants!$C$5<1000,0.35,1))) -> 5308333.3 | D8: =IF(D4<=Tenants!$F$5,Tenants!$B$5*Tenants!$C$5/12,IF(D4<=EOMONTH(Tenants!$F$5,Inputs!$B$6),0,Tenants!$B$5*Inputs!$B$4*(1+Inputs!$B$5)^(D$3/12)/12*IF(Tenants!$C$5<1000,0.35,1))) -> 5308333.3 | E8: =IF(E4<=Tenants!$F$5,Tenants!$B$5*Tenants!$C$5/12,IF(E4<=EOMONTH(Tenants!$F$5,Inputs!$B$6),0,Tenants!$B$5*Inputs!$B$4*(1+Inputs!$B$5)^(E$3/12)/12*IF(Tenants!$C$5<1000,0.35,1))) -> 5308333.3 | F8: =IF(F4<=Tenants!$F$5,Tenants!$B$5*Tenants!$C$5/12,IF(F4<=EOMONTH(Tenants!$F$5,Inputs!$B$6),0,Tenants!$B$5*Inputs!$B$4*(1+Inputs!$B$5)^(F$3/12)/12*IF(Tenants!$C$5<1000,0.35,1))) -> 5308333.3 | G8: =IF(G4<=Tenants!$F$5,Tenants!$B$5*Tenants!$C$5/12,IF(G4<=EOMONTH(Tenants!$F$5,Inputs!$B$6),0,Tenants!$B$5*Inputs!$B$4*(1+Inputs!$B$5)^(G$3/12)/12*IF(Tenants!$C$5<1000,0.35,1))) -> 5308333.3 | H8: =IF(H4<=Tenants!$F$5,Tenants!$B$5*Tenants!$C$5/12,IF(H4<=EOMONTH(Tenants!$F$5,Inputs!$B$6),0,Tenants!$B$5*Inputs!$B$4*(1+Inputs!$B$5)^(H$3/12)/12*IF(Tenants!$C$5<1000,0.35,1))) -> 5308333.3 | I8: =IF(I4<=Tenants!$F$5,Tenants!$B$5*Tenants!$C$5/12,IF(I4<=EOMONTH(Tenants!$F$5,Inputs!$B$6),0,Tenants!$B$5*Inputs!$B$4*(1+Inputs!$B$5)^(I$3/12)/12*IF(Tenants!$C$5<1000,0.35,1))) -> 5308333.3 | J8: =IF(J4<=Tenants!$F$5,Tenants!$B$5*Tenants!$C$5/12,IF(J4<=EOMONTH(Tenants!$F$5,Inputs!$B$6),0,Tenants!$B$5*Inputs!$B$4*(1+Inputs!$B$5)^(J$3/12)/12*IF(Tenants!$C$5<1000,0.35,1))) -> 5308333.3 | ... DR8: =IF(DR4<=Tenants!$F$5,Tenants!$B$5*Tenants!$C$5/12,IF(DR4<=EOMONTH(Tenants!$F$5,Inputs!$B$6),0,Tenants!$B$5*Inputs!$B$4*(1+Inputs!$B$5)^(DR$3/12)/12*IF(Tenants!$C$5<1000,0.35,1))) -> 7570728.9
A9: Rent 5 | B9: =0 -> 0 | C9: =IF(C4<=Tenants!$F$6,Tenants!$B$6*Tenants!$C$6/12,IF(C4<=EOMONTH(Tenants!$F$6,Inputs!$B$6),0,Tenants!$B$6*Inputs!$B$4*(1+Inputs!$B$5)^(C$3/12)/12*IF(Tenants!$C$6<1000,0.35,1))) -> 2175000 | D9: =IF(D4<=Tenants!$F$6,Tenants!$B$6*Tenants!$C$6/12,IF(D4<=EOMONTH(Tenants!$F$6,Inputs!$B$6),0,Tenants!$B$6*Inputs!$B$4*(1+Inputs!$B$5)^(D$3/12)/12*IF(Tenants!$C$6<1000,0.35,1))) -> 2175000 | E9: =IF(E4<=Tenants!$F$6,Tenants!$B$6*Tenants!$C$6/12,IF(E4<=EOMONTH(Tenants!$F$6,Inputs!$B$6),0,Tenants!$B$6*Inputs!$B$4*(1+Inputs!$B$5)^(E$3/12)/12*IF(Tenants!$C$6<1000,0.35,1))) -> 2175000 | F9: =IF(F4<=Tenants!$F$6,Tenants!$B$6*Tenants!$C$6/12,IF(F4<=EOMONTH(Tenants!$F$6,Inputs!$B$6),0,Tenants!$B$6*Inputs!$B$4*(1+Inputs!$B$5)^(F$3/12)/12*IF(Tenants!$C$6<1000,0.35,1))) -> 2175000 | G9: =IF(G4<=Tenants!$F$6,Tenants!$B$6*Tenants!$C$6/12,IF(G4<=EOMONTH(Tenants!$F$6,Inputs!$B$6),0,Tenants!$B$6*Inputs!$B$4*(1+Inputs!$B$5)^(G$3/12)/12*IF(Tenants!$C$6<1000,0.35,1))) -> 2175000 | H9: =IF(H4<=Tenants!$F$6,Tenants!$B$6*Tenants!$C$6/12,IF(H4<=EOMONTH(Tenants!$F$6,Inputs!$B$6),0,Tenants!$B$6*Inputs!$B$4*(1+Inputs!$B$5)^(H$3/12)/12*IF(Tenants!$C$6<1000,0.35,1))) -> 2175000 | I9: =IF(I4<=Tenants!$F$6,Tenants!$B$6*Tenants!$C$6/12,IF(I4<=EOMONTH(Tenants!$F$6,Inputs!$B$6),0,Tenants!$B$6*Inputs!$B$4*(1+Inputs!$B$5)^(I$3/12)/12*IF(Tenants!$C$6<1000,0.35,1))) -> 2175000 | J9: =IF(J4<=Tenants!$F$6,Tenants!$B$6*Tenants!$C$6/12,IF(J4<=EOMONTH(Tenants!$F$6,Inputs!$B$6),0,Tenants!$B$6*Inputs!$B$4*(1+Inputs!$B$5)^(J$3/12)/12*IF(Tenants!$C$6<1000,0.35,1))) -> 2175000 | ... DR9: =IF(DR4<=Tenants!$F$6,Tenants!$B$6*Tenants!$C$6/12,IF(DR4<=EOMONTH(Tenants!$F$6,Inputs!$B$6),0,Tenants!$B$6*Inputs!$B$4*(1+Inputs!$B$5)^(DR$3/12)/12*IF(Tenants!$C$6<1000,0.35,1))) -> 2620636.9
A10: Rent 6 | B10: =0 -> 0 | C10: =IF(C4<=Tenants!$F$7,Tenants!$B$7*Tenants!$C$7/12,IF(C4<=EOMONTH(Tenants!$F$7,Inputs!$B$6),0,Tenants!$B$7*Inputs!$B$4*(1+Inputs!$B$5)^(C$3/12)/12*IF(Tenants!$C$7<1000,0.35,1))) -> 1150000 | D10: =IF(D4<=Tenants!$F$7,Tenants!$B$7*Tenants!$C$7/12,IF(D4<=EOMONTH(Tenants!$F$7,Inputs!$B$6),0,Tenants!$B$7*Inputs!$B$4*(1+Inputs!$B$5)^(D$3/12)/12*IF(Tenants!$C$7<1000,0.35,1))) -> 1150000 | E10: =IF(E4<=Tenants!$F$7,Tenants!$B$7*Tenants!$C$7/12,IF(E4<=EOMONTH(Tenants!$F$7,Inputs!$B$6),0,Tenants!$B$7*Inputs!$B$4*(1+Inputs!$B$5)^(E$3/12)/12*IF(Tenants!$C$7<1000,0.35,1))) -> 1150000 | F10: =IF(F4<=Tenants!$F$7,Tenants!$B$7*Tenants!$C$7/12,IF(F4<=EOMONTH(Tenants!$F$7,Inputs!$B$6),0,Tenants!$B$7*Inputs!$B$4*(1+Inputs!$B$5)^(F$3/12)/12*IF(Tenants!$C$7<1000,0.35,1))) -> 1150000 | G10: =IF(G4<=Tenants!$F$7,Tenants!$B$7*Tenants!$C$7/12,IF(G4<=EOMONTH(Tenants!$F$7,Inputs!$B$6),0,Tenants!$B$7*Inputs!$B$4*(1+Inputs!$B$5)^(G$3/12)/12*IF(Tenants!$C$7<1000,0.35,1))) -> 1150000 | H10: =IF(H4<=Tenants!$F$7,Tenants!$B$7*Tenants!$C$7/12,IF(H4<=EOMONTH(Tenants!$F$7,Inputs!$B$6),0,Tenants!$B$7*Inputs!$B$4*(1+Inputs!$B$5)^(H$3/12)/12*IF(Tenants!$C$7<1000,0.35,1))) -> 1150000 | I10: =IF(I4<=Tenants!$F$7,Tenants!$B$7*Tenants!$C$7/12,IF(I4<=EOMONTH(Tenants!$F$7,Inputs!$B$6),0,Tenants!$B$7*Inputs!$B$4*(1+Inputs!$B$5)^(I$3/12)/12*IF(Tenants!$C$7<1000,0.35,1))) -> 1150000 | J10: =IF(J4<=Tenants!$F$7,Tenants!$B$7*Tenants!$C$7/12,IF(J4<=EOMONTH(Tenants!$F$7,Inputs!$B$6),0,Tenants!$B$7*Inputs!$B$4*(1+Inputs!$B$5)^(J$3/12)/12*IF(Tenants!$C$7<1000,0.35,1))) -> 1150000 | ... DR10: =IF(DR4<=Tenants!$F$7,Tenants!$B$7*Tenants!$C$7/12,IF(DR4<=EOMONTH(Tenants!$F$7,Inputs!$B$6),0,Tenants!$B$7*Inputs!$B$4*(1+Inputs!$B$5)^(DR$3/12)/12*IF(Tenants!$C$7<1000,0.35,1))) -> 1747091.3
A11: Base and re-let rent | B11: =B5+B6+B7+B8+B9+B10 -> 0 | C11: =C5+C6+C7+C8+C9+C10 -> 11316667 | D11: =D5+D6+D7+D8+D9+D10 -> 11316667 | E11: =E5+E6+E7+E8+E9+E10 -> 11316667 | F11: =F5+F6+F7+F8+F9+F10 -> 11316667 | G11: =G5+G6+G7+G8+G9+G10 -> 11316667 | H11: =H5+H6+H7+H8+H9+H10 -> 11316667 | I11: =I5+I6+I7+I8+I9+I10 -> 11316667 | ... DR11: =DR5+DR6+DR7+DR8+DR9+DR10 -> 16524572
A12: Turnover rent | B12: =0 -> 0 | C12: =IF(C4<=Tenants!$F$2,MAX(0,Tenants!$B$2*Tenants!$D$2*(1+Inputs!$B$7)^(C$3/12)/12*Tenants!$E$2-Tenants!$B$2*Tenants!$C$2/12),0)+IF(C4<=Tenants!$F$3,MAX(0,Tenants!$B$3*Tenants!$D$3*(1+Inputs!$B$7)^(C$3/12)/12*Tenants!$E$3-Tenants!$B$3*Tenants!$C$3/12),0)+IF(C4<=Tenants!$F$4,MAX(0,Tenants!$B$4*Tenants!$D$4*(1+Inputs!$B$7)^(C$3/12)/12*Tenants!$E$4-Tenants!$B$4*Tenants!$C$4/12),0)+IF(C4<=Tenants!$F$5,MAX(0,Tenants!$B$5*Tenants!$D$5*(1+Inputs!$B$7)^(C$3/12)/12*Tenants!$E$5-Tenants!$B$5*Tenants!$C$5/12),0)+IF(C4<=Tenants!$F$6,MAX(0,Tenants!$B$6*Tenants!$D$6*(1+Inputs!$B$7)^(C$3/12)/12*Tenants!$E$6-Tenants!$B$6*Tenants!$C$6/12),0)+IF(C4<=Tenants!$F$7,MAX(0,Tenants!$B$7*Tenants!$D$7*(1+Inputs!$B$7)^(C$3/12)/12*Tenants!$E$7-Tenants!$B$7*Tenants!$C$7/12),0) -> 1873038.8 | D12: =IF(D4<=Tenants!$F$2,MAX(0,Tenants!$B$2*Tenants!$D$2*(1+Inputs!$B$7)^(D$3/12)/12*Tenants!$E$2-Tenants!$B$2*Tenants!$C$2/12),0)+IF(D4<=Tenants!$F$3,MAX(0,Tenants!$B$3*Tenants!$D$3*(1+Inputs!$B$7)^(D$3/12)/12*Tenants!$E$3-Tenants!$B$3*Tenants!$C$3/12),0)+IF(D4<=Tenants!$F$4,MAX(0,Tenants!$B$4*Tenants!$D$4*(1+Inputs!$B$7)^(D$3/12)/12*Tenants!$E$4-Tenants!$B$4*Tenants!$C$4/12),0)+IF(D4<=Tenants!$F$5,MAX(0,Tenants!$B$5*Tenants!$D$5*(1+Inputs!$B$7)^(D$3/12)/12*Tenants!$E$5-Tenants!$B$5*Tenants!$C$5/12),0)+IF(D4<=Tenants!$F$6,MAX(0,Tenants!$B$6*Tenants!$D$6*(1+Inputs!$B$7)^(D$3/12)/12*Tenants!$E$6-Tenants!$B$6*Tenants!$C$6/12),0)+IF(D4<=Tenants!$F$7,MAX(0,Tenants!$B$7*Tenants!$D$7*(1+Inputs!$B$7)^(D$3/12)/12*Tenants!$E$7-Tenants!$B$7*Tenants!$C$7/12),0) -> 1916218.4 | E12: =IF(E4<=Tenants!$F$2,MAX(0,Tenants!$B$2*Tenants!$D$2*(1+Inputs!$B$7)^(E$3/12)/12*Tenants!$E$2-Tenants!$B$2*Tenants!$C$2/12),0)+IF(E4<=Tenants!$F$3,MAX(0,Tenants!$B$3*Tenants!$D$3*(1+Inputs!$B$7)^(E$3/12)/12*Tenants!$E$3-Tenants!$B$3*Tenants!$C$3/12),0)+IF(E4<=Tenants!$F$4,MAX(0,Tenants!$B$4*Tenants!$D$4*(1+Inputs!$B$7)^(E$3/12)/12*Tenants!$E$4-Tenants!$B$4*Tenants!$C$4/12),0)+IF(E4<=Tenants!$F$5,MAX(0,Tenants!$B$5*Tenants!$D$5*(1+Inputs!$B$7)^(E$3/12)/12*Tenants!$E$5-Tenants!$B$5*Tenants!$C$5/12),0)+IF(E4<=Tenants!$F$6,MAX(0,Tenants!$B$6*Tenants!$D$6*(1+Inputs!$B$7)^(E$3/12)/12*Tenants!$E$6-Tenants!$B$6*Tenants!$C$6/12),0)+IF(E4<=Tenants!$F$7,MAX(0,Tenants!$B$7*Tenants!$D$7*(1+Inputs!$B$7)^(E$3/12)/12*Tenants!$E$7-Tenants!$B$7*Tenants!$C$7/12),0) -> 1959539.5 | F12: =IF(F4<=Tenants!$F$2,MAX(0,Tenants!$B$2*Tenants!$D$2*(1+Inputs!$B$7)^(F$3/12)/12*Tenants!$E$2-Tenants!$B$2*Tenants!$C$2/12),0)+IF(F4<=Tenants!$F$3,MAX(0,Tenants!$B$3*Tenants!$D$3*(1+Inputs!$B$7)^(F$3/12)/12*Tenants!$E$3-Tenants!$B$3*Tenants!$C$3/12),0)+IF(F4<=Tenants!$F$4,MAX(0,Tenants!$B$4*Tenants!$D$4*(1+Inputs!$B$7)^(F$3/12)/12*Tenants!$E$4-Tenants!$B$4*Tenants!$C$4/12),0)+IF(F4<=Tenants!$F$5,MAX(0,Tenants!$B$5*Tenants!$D$5*(1+Inputs!$B$7)^(F$3/12)/12*Tenants!$E$5-Tenants!$B$5*Tenants!$C$5/12),0)+IF(F4<=Tenants!$F$6,MAX(0,Tenants!$B$6*Tenants!$D$6*(1+Inputs!$B$7)^(F$3/12)/12*Tenants!$E$6-Tenants!$B$6*Tenants!$C$6/12),0)+IF(F4<=Tenants!$F$7,MAX(0,Tenants!$B$7*Tenants!$D$7*(1+Inputs!$B$7)^(F$3/12)/12*Tenants!$E$7-Tenants!$B$7*Tenants!$C$7/12),0) -> 2003002.3 | G12: =IF(G4<=Tenants!$F$2,MAX(0,Tenants!$B$2*Tenants!$D$2*(1+Inputs!$B$7)^(G$3/12)/12*Tenants!$E$2-Tenants!$B$2*Tenants!$C$2/12),0)+IF(G4<=Tenants!$F$3,MAX(0,Tenants!$B$3*Tenants!$D$3*(1+Inputs!$B$7)^(G$3/12)/12*Tenants!$E$3-Tenants!$B$3*Tenants!$C$3/12),0)+IF(G4<=Tenants!$F$4,MAX(0,Tenants!$B$4*Tenants!$D$4*(1+Inputs!$B$7)^(G$3/12)/12*Tenants!$E$4-Tenants!$B$4*Tenants!$C$4/12),0)+IF(G4<=Tenants!$F$5,MAX(0,Tenants!$B$5*Tenants!$D$5*(1+Inputs!$B$7)^(G$3/12)/12*Tenants!$E$5-Tenants!$B$5*Tenants!$C$5/12),0)+IF(G4<=Tenants!$F$6,MAX(0,Tenants!$B$6*Tenants!$D$6*(1+Inputs!$B$7)^(G$3/12)/12*Tenants!$E$6-Tenants!$B$6*Tenants!$C$6/12),0)+IF(G4<=Tenants!$F$7,MAX(0,Tenants!$B$7*Tenants!$D$7*(1+Inputs!$B$7)^(G$3/12)/12*Tenants!$E$7-Tenants!$B$7*Tenants!$C$7/12),0) -> 2046607.4 | H12: =IF(H4<=Tenants!$F$2,MAX(0,Tenants!$B$2*Tenants!$D$2*(1+Inputs!$B$7)^(H$3/12)/12*Tenants!$E$2-Tenants!$B$2*Tenants!$C$2/12),0)+IF(H4<=Tenants!$F$3,MAX(0,Tenants!$B$3*Tenants!$D$3*(1+Inputs!$B$7)^(H$3/12)/12*Tenants!$E$3-Tenants!$B$3*Tenants!$C$3/12),0)+IF(H4<=Tenants!$F$4,MAX(0,Tenants!$B$4*Tenants!$D$4*(1+Inputs!$B$7)^(H$3/12)/12*Tenants!$E$4-Tenants!$B$4*Tenants!$C$4/12),0)+IF(H4<=Tenants!$F$5,MAX(0,Tenants!$B$5*Tenants!$D$5*(1+Inputs!$B$7)^(H$3/12)/12*Tenants!$E$5-Tenants!$B$5*Tenants!$C$5/12),0)+IF(H4<=Tenants!$F$6,MAX(0,Tenants!$B$6*Tenants!$D$6*(1+Inputs!$B$7)^(H$3/12)/12*Tenants!$E$6-Tenants!$B$6*Tenants!$C$6/12),0)+IF(H4<=Tenants!$F$7,MAX(0,Tenants!$B$7*Tenants!$D$7*(1+Inputs!$B$7)^(H$3/12)/12*Tenants!$E$7-Tenants!$B$7*Tenants!$C$7/12),0) -> 2090355.3 | I12: =IF(I4<=Tenants!$F$2,MAX(0,Tenants!$B$2*Tenants!$D$2*(1+Inputs!$B$7)^(I$3/12)/12*Tenants!$E$2-Tenants!$B$2*Tenants!$C$2/12),0)+IF(I4<=Tenants!$F$3,MAX(0,Tenants!$B$3*Tenants!$D$3*(1+Inputs!$B$7)^(I$3/12)/12*Tenants!$E$3-Tenants!$B$3*Tenants!$C$3/12),0)+IF(I4<=Tenants!$F$4,MAX(0,Tenants!$B$4*Tenants!$D$4*(1+Inputs!$B$7)^(I$3/12)/12*Tenants!$E$4-Tenants!$B$4*Tenants!$C$4/12),0)+IF(I4<=Tenants!$F$5,MAX(0,Tenants!$B$5*Tenants!$D$5*(1+Inputs!$B$7)^(I$3/12)/12*Tenants!$E$5-Tenants!$B$5*Tenants!$C$5/12),0)+IF(I4<=Tenants!$F$6,MAX(0,Tenants!$B$6*Tenants!$D$6*(1+Inputs!$B$7)^(I$3/12)/12*Tenants!$E$6-Tenants!$B$6*Tenants!$C$6/12),0)+IF(I4<=Tenants!$F$7,MAX(0,Tenants!$B$7*Tenants!$D$7*(1+Inputs!$B$7)^(I$3/12)/12*Tenants!$E$7-Tenants!$B$7*Tenants!$C$7/12),0) -> 2134246.4 | J12: =IF(J4<=Tenants!$F$2,MAX(0,Tenants!$B$2*Tenants!$D$2*(1+Inputs!$B$7)^(J$3/12)/12*Tenants!$E$2-Tenants!$B$2*Tenants!$C$2/12),0)+IF(J4<=Tenants!$F$3,MAX(0,Tenants!$B$3*Tenants!$D$3*(1+Inputs!$B$7)^(J$3/12)/12*Tenants!$E$3-Tenants!$B$3*Tenants!$C$3/12),0)+IF(J4<=Tenants!$F$4,MAX(0,Tenants!$B$4*Tenants!$D$4*(1+Inputs!$B$7)^(J$3/12)/12*Tenants!$E$4-Tenants!$B$4*Tenants!$C$4/12),0)+IF(J4<=Tenants!$F$5,MAX(0,Tenants!$B$5*Tenants!$D$5*(1+Inputs!$B$7)^(J$3/12)/12*Tenants!$E$5-Tenants!$B$5*Tenants!$C$5/12),0)+IF(J4<=Tenants!$F$6,MAX(0,Tenants!$B$6*Tenants!$D$6*(1+Inputs!$B$7)^(J$3/12)/12*Tenants!$E$6-Tenants!$B$6*Tenants!$C$6/12),0)+IF(J4<=Tenants!$F$7,MAX(0,Tenants!$B$7*Tenants!$D$7*(1+Inputs!$B$7)^(J$3/12)/12*Tenants!$E$7-Tenants!$B$7*Tenants!$C$7/12),0) -> 2178281.2 | ... DR12: =IF(DR4<=Tenants!$F$2,MAX(0,Tenants!$B$2*Tenants!$D$2*(1+Inputs!$B$7)^(DR$3/12)/12*Tenants!$E$2-Tenants!$B$2*Tenants!$C$2/12),0)+IF(DR4<=Tenants!$F$3,MAX(0,Tenants!$B$3*Tenants!$D$3*(1+Inputs!$B$7)^(DR$3/12)/12*Tenants!$E$3-Tenants!$B$3*Tenants!$C$3/12),0)+IF(DR4<=Tenants!$F$4,MAX(0,Tenants!$B$4*Tenants!$D$4*(1+Inputs!$B$7)^(DR$3/12)/12*Tenants!$E$4-Tenants!$B$4*Tenants!$C$4/12),0)+IF(DR4<=Tenants!$F$5,MAX(0,Tenants!$B$5*Tenants!$D$5*(1+Inputs!$B$7)^(DR$3/12)/12*Tenants!$E$5-Tenants!$B$5*Tenants!$C$5/12),0)+IF(DR4<=Tenants!$F$6,MAX(0,Tenants!$B$6*Tenants!$D$6*(1+Inputs!$B$7)^(DR$3/12)/12*Tenants!$E$6-Tenants!$B$6*Tenants!$C$6/12),0)+IF(DR4<=Tenants!$F$7,MAX(0,Tenants!$B$7*Tenants!$D$7*(1+Inputs!$B$7)^(DR$3/12)/12*Tenants!$E$7-Tenants!$B$7*Tenants!$C$7/12),0) -> 0
A13: Service charge cost | B13: =0 -> 0 | C13: =SUM(Tenants!$B$2:$B$7)*Inputs!$B$8*(1+Inputs!$B$10)^(C$3/12)/12 -> 2228044.8 | D13: =SUM(Tenants!$B$2:$B$7)*Inputs!$B$8*(1+Inputs!$B$10)^(D$3/12)/12 -> 2234441.3 | E13: =SUM(Tenants!$B$2:$B$7)*Inputs!$B$8*(1+Inputs!$B$10)^(E$3/12)/12 -> 2240856.2 | F13: =SUM(Tenants!$B$2:$B$7)*Inputs!$B$8*(1+Inputs!$B$10)^(F$3/12)/12 -> 2247289.5 | G13: =SUM(Tenants!$B$2:$B$7)*Inputs!$B$8*(1+Inputs!$B$10)^(G$3/12)/12 -> 2253741.2 | H13: =SUM(Tenants!$B$2:$B$7)*Inputs!$B$8*(1+Inputs!$B$10)^(H$3/12)/12 -> 2260211.5 | I13: =SUM(Tenants!$B$2:$B$7)*Inputs!$B$8*(1+Inputs!$B$10)^(I$3/12)/12 -> 2266700.3 | J13: =SUM(Tenants!$B$2:$B$7)*Inputs!$B$8*(1+Inputs!$B$10)^(J$3/12)/12 -> 2273207.8 | ... DR13: =SUM(Tenants!$B$2:$B$7)*Inputs!$B$8*(1+Inputs!$B$10)^(DR$3/12)/12 -> 3133880.2
A14: Service charge recovered | B14: =0 -> 0 | C14: =MIN(C13,SUM(Tenants!$B$2:$B$7)*Inputs!$B$9/12) -> 2078333.3 | D14: =MIN(D13,SUM(Tenants!$B$2:$B$7)*Inputs!$B$9/12) -> 2078333.3 | E14: =MIN(E13,SUM(Tenants!$B$2:$B$7)*Inputs!$B$9/12) -> 2078333.3 | F14: =MIN(F13,SUM(Tenants!$B$2:$B$7)*Inputs!$B$9/12) -> 2078333.3 | G14: =MIN(G13,SUM(Tenants!$B$2:$B$7)*Inputs!$B$9/12) -> 2078333.3 | H14: =MIN(H13,SUM(Tenants!$B$2:$B$7)*Inputs!$B$9/12) -> 2078333.3 | I14: =MIN(I13,SUM(Tenants!$B$2:$B$7)*Inputs!$B$9/12) -> 2078333.3 | J14: =MIN(J13,SUM(Tenants!$B$2:$B$7)*Inputs!$B$9/12) -> 2078333.3 | ... DR14: =MIN(DR13,SUM(Tenants!$B$2:$B$7)*Inputs!$B$9/12) -> 2078333.3
A15: Net operating income | B15: =B11+B12-B13+B14 -> 0 | C15: =C11+C12-C13+C14 -> 13039994 | D15: =D11+D12-D13+D14 -> 13076777 | E15: =E11+E12-E13+E14 -> 13113683 | F15: =F11+F12-F13+F14 -> 13150713 | G15: =G11+G12-G13+G14 -> 13187866 | H15: =H11+H12-H13+H14 -> 13225144 | I15: =I11+I12-I13+I14 -> 13262546 | ... DR15: =DR11+DR12-DR13+DR14 -> 15469025
A16: Equity cash flow | B16: =-Inputs!$B$12 -> -2650000000 | C16: =C15+IF(C$3=120,SUM(B15:C15)*12/MIN(12,C$3)/Inputs!$B$11,0) -> 13039994 | D16: =D15+IF(D$3=120,SUM(B15:D15)*12/MIN(12,D$3)/Inputs!$B$11,0) -> 13076777 | E16: =E15+IF(E$3=120,SUM(B15:E15)*12/MIN(12,E$3)/Inputs!$B$11,0) -> 13113683 | F16: =F15+IF(F$3=120,SUM(B15:F15)*12/MIN(12,F$3)/Inputs!$B$11,0) -> 13150713 | G16: =G15+IF(G$3=120,SUM(B15:G15)*12/MIN(12,G$3)/Inputs!$B$11,0) -> 13187866 | H16: =H15+IF(H$3=120,SUM(B15:H15)*12/MIN(12,H$3)/Inputs!$B$11,0) -> 13225144 | I16: =I15+IF(I$3=120,SUM(B15:I15)*12/MIN(12,I$3)/Inputs!$B$11,0) -> 13262546 | J16: =J15+IF(J$3=120,SUM(B15:J15)*12/MIN(12,J$3)/Inputs!$B$11,0) -> 13300073 | K16: =K15+IF(K$3=120,SUM(B15:K15)*12/MIN(12,K$3)/Inputs!$B$11,0) -> 13337726 | L16: =L15+IF(L$3=120,SUM(B15:L15)*12/MIN(12,L$3)/Inputs!$B$11,0) -> 13375505 | M16: =M15+IF(M$3=120,SUM(B15:M15)*12/MIN(12,M$3)/Inputs!$B$11,0) -> 13413410 | N16: =N15+IF(N$3=120,SUM(B15:N15)*12/MIN(12,N$3)/Inputs!$B$11,0) -> 13451442 | O16: =O15+IF(O$3=120,SUM(C15:O15)*12/MIN(12,O$3)/Inputs!$B$11,0) -> 10860221 | P16: =P15+IF(P$3=120,SUM(D15:P15)*12/MIN(12,P$3)/Inputs!$B$11,0) -> 10889899 | Q16: =Q15+IF(Q$3=120,SUM(E15:Q15)*12/MIN(12,Q$3)/Inputs!$B$11,0) -> 10919678 | R16: =R15+IF(R$3=120,SUM(F15:R15)*12/MIN(12,R$3)/Inputs!$B$11,0) -> 10949556 | S16: =S15+IF(S$3=120,SUM(G15:S15)*12/MIN(12,S$3)/Inputs!$B$11,0) -> 10979535 | T16: =T15+IF(T$3=120,SUM(H15:T15)*12/MIN(12,T$3)/Inputs!$B$11,0) -> 11009615 | U16: =U15+IF(U$3=120,SUM(I15:U15)*12/MIN(12,U$3)/Inputs!$B$11,0) -> 13083228 | ... DR16: =DR15+IF(DR$3=120,SUM(DF15:DR15)*12/MIN(12,DR$3)/Inputs!$B$11,0) -> 2.6640987e+09

Sheet Returns
A3: Unlevered IRR | B3: =(1+IRR('Cash Flow'!$B$16:$DR$16,0.006))^12-1 -> 0.059895291
A4: Turnover rent share of income | B4: =SUM('Cash Flow'!$B$12:$DR$12)/(SUM('Cash Flow'!$B$11:$DR$11)+SUM('Cash Flow'!$B$12:$DR$12)) -> 0.058405579
A5: Service charge leakage (AED) | B5: =SUM('Cash Flow'!$B$13:$DR$13)-SUM('Cash Flow'!$B$14:$DR$14) -> 69257167
A6: Leases expiring by 2030 | B6: =COUNTIFS(Tenants!$F$2:$F$7,"<="&DATE(2030,12,31)) -> 4
A7: Net initial yield | B7: =SUM('Cash Flow'!$C$15:$N$15)/Inputs!$B$12 -> 0.059975426
A8: Net profit (AED) | B8: =SUM('Cash Flow'!$B$16:$DR$16) -> 1.5680336e+09
