Workbook

Sheet Appraisal
A1: 14 CLARENDON ROAD – STUDENT HMO CONVERSION (GBP)
A3: Purchase price (£) | B3: 465000
A4: Bedrooms | B4: 9
A5: Rent per room a week (£) | B5: 148
A6: Weeks let a year | B6: 46
A7: Rent growth a year | B7: 4
A8: Bills and management (% of rent) | B8: 22
A9: Conversion cost per room (£) | B9: 1,250
A10: Main works (£) | B10: 138000
A11: Mortgage LTV | B11: 75
A12: Mortgage rate | B12: 5.4
A13: Exit yield | B13: 6.5
A14: Hold (years) | B14: 5

Sheet k
A1: Stamp duty, higher rate | B1: 0.05
A2: Legal and survey (£) | B2: 6500

Sheet Cash Flow
A3: Year | B3: 0 | C3: 1 | D3: 2 | E3: 3 | F3: 4 | G3: 5
A4: Rent | B4: =0 -> 0 | C4: =IF(C$3<=Appraisal!$B$14,Appraisal!$B$4*Appraisal!$B$5*Appraisal!$B$6*(1+Appraisal!$B$7/100)^(C$3-1),0) -> 61272 | D4: =IF(D$3<=Appraisal!$B$14,Appraisal!$B$4*Appraisal!$B$5*Appraisal!$B$6*(1+Appraisal!$B$7/100)^(D$3-1),0) -> 63722.88 | E4: =IF(E$3<=Appraisal!$B$14,Appraisal!$B$4*Appraisal!$B$5*Appraisal!$B$6*(1+Appraisal!$B$7/100)^(E$3-1),0) -> 66271.795 | F4: =IF(F$3<=Appraisal!$B$14,Appraisal!$B$4*Appraisal!$B$5*Appraisal!$B$6*(1+Appraisal!$B$7/100)^(F$3-1),0) -> 68922.667 | G4: =IF(G$3<=Appraisal!$B$14,Appraisal!$B$4*Appraisal!$B$5*Appraisal!$B$6*(1+Appraisal!$B$7/100)^(G$3-1),0) -> 71679.574
A5: Bills and management | B5: =B4*Appraisal!$B$8/100 -> 0 | C5: =C4*Appraisal!$B$8/100 -> 13479.84 | D5: =D4*Appraisal!$B$8/100 -> 14019.034 | E5: =E4*Appraisal!$B$8/100 -> 14579.795 | F5: =F4*Appraisal!$B$8/100 -> 15162.987 | G5: =G4*Appraisal!$B$8/100 -> 15769.506
A6: Mortgage interest | B6: =0 -> 0 | C6: =IF(C$3<=Appraisal!$B$14,(Appraisal!$B$3+Appraisal!$B$10+VALUE(Appraisal!$B$9)*Appraisal!$B$4)*Appraisal!$B$11/100*Appraisal!$B$12/100,0) -> 24877.125 | D6: =IF(D$3<=Appraisal!$B$14,(Appraisal!$B$3+Appraisal!$B$10+VALUE(Appraisal!$B$9)*Appraisal!$B$4)*Appraisal!$B$11/100*Appraisal!$B$12/100,0) -> 24877.125 | E6: =IF(E$3<=Appraisal!$B$14,(Appraisal!$B$3+Appraisal!$B$10+VALUE(Appraisal!$B$9)*Appraisal!$B$4)*Appraisal!$B$11/100*Appraisal!$B$12/100,0) -> 24877.125 | F6: =IF(F$3<=Appraisal!$B$14,(Appraisal!$B$3+Appraisal!$B$10+VALUE(Appraisal!$B$9)*Appraisal!$B$4)*Appraisal!$B$11/100*Appraisal!$B$12/100,0) -> 24877.125 | G6: =IF(G$3<=Appraisal!$B$14,(Appraisal!$B$3+Appraisal!$B$10+VALUE(Appraisal!$B$9)*Appraisal!$B$4)*Appraisal!$B$11/100*Appraisal!$B$12/100,0) -> 24877.125
A7: Capital costs | B7: =Appraisal!$B$3*(1+k!$B$1)+k!$B$2+Appraisal!$B$10+VALUE(Appraisal!$B$9)*Appraisal!$B$4 -> 644000 | C7: =0 -> 0 | D7: =0 -> 0 | E7: =0 -> 0 | F7: =0 -> 0 | G7: =0 -> 0
A8: Sale | B8: =IF(B$3=Appraisal!$B$14,(B4-B5)*(1+Appraisal!$B$7/100)/(Appraisal!$B$13/100)-(Appraisal!$B$3+Appraisal!$B$10+VALUE(Appraisal!$B$9)*Appraisal!$B$4)*Appraisal!$B$11/100,0) -> 0 | C8: =IF(C$3=Appraisal!$B$14,(C4-C5)*(1+Appraisal!$B$7/100)/(Appraisal!$B$13/100)-(Appraisal!$B$3+Appraisal!$B$10+VALUE(Appraisal!$B$9)*Appraisal!$B$4)*Appraisal!$B$11/100,0) -> 0 | D8: =IF(D$3=Appraisal!$B$14,(D4-D5)*(1+Appraisal!$B$7/100)/(Appraisal!$B$13/100)-(Appraisal!$B$3+Appraisal!$B$10+VALUE(Appraisal!$B$9)*Appraisal!$B$4)*Appraisal!$B$11/100,0) -> 0 | E8: =IF(E$3=Appraisal!$B$14,(E4-E5)*(1+Appraisal!$B$7/100)/(Appraisal!$B$13/100)-(Appraisal!$B$3+Appraisal!$B$10+VALUE(Appraisal!$B$9)*Appraisal!$B$4)*Appraisal!$B$11/100,0) -> 0 | F8: =IF(F$3=Appraisal!$B$14,(F4-F5)*(1+Appraisal!$B$7/100)/(Appraisal!$B$13/100)-(Appraisal!$B$3+Appraisal!$B$10+VALUE(Appraisal!$B$9)*Appraisal!$B$4)*Appraisal!$B$11/100,0) -> 0 | G8: =IF(G$3=Appraisal!$B$14,(G4-G5)*(1+Appraisal!$B$7/100)/(Appraisal!$B$13/100)-(Appraisal!$B$3+Appraisal!$B$10+VALUE(Appraisal!$B$9)*Appraisal!$B$4)*Appraisal!$B$11/100,0) -> 433873.58
A9: Equity cash flow | B9: =-B7*(1-Appraisal!$B$11/100) -> -161000 | C9: =C4-C5-C6+C8 -> 22915.035 | D9: =D4-D5-D6+D8 -> 24826.721 | E9: =E4-E5-E6+E8 -> 26814.875 | F9: =F4-F5-F6+F8 -> 28882.555 | G9: =G4-G5-G6+G8 -> 464906.52

Sheet Returns
A3: Equity IRR | B3: =IRR('Cash Flow'!$B$9:$G$9) -> 0.33519293
A4: Gross yield on cost | B4: ='Cash Flow'!C4/'Cash Flow'!B7 -> 0.095142857
A5: Total cost (£) | B5: ='Cash Flow'!B7 -> 644000
A6: Cash on cash, year 1 | B6: =('Cash Flow'!C4-'Cash Flow'!C5-'Cash Flow'!C6)/-'Cash Flow'!B9 -> 0.14232941
A7: Net profit (£) | B7: =SUM('Cash Flow'!$B$9:$G$9) -> 407345.71
