Workbook

Sheet Inputs
A1: AL MURJAN HOSPITAL PPP – AVAILABILITY-BASED (SAR)
A3: Availability payment, year 1 (SAR) | B3: 265000000
A4: Indexation | B4: 0.02
A5: KPI deductions share | B5: 0.015
A6: Facilities management a year (SAR) | B6: 72000000
A7: Lifecycle a year (SAR) | B7: 18000000
A8: Construction cost (SAR) | B8: 1950000000
A9: Gearing | B9: 0.82
A10: Senior rate | B10: 0.055
A11: Target DSCR | B11: 1.3
A12: Debt tenor (years) | B12: 22
A13: Operating term (years) | B13: 25
A14: DSRA, months of debt service | B14: 6
... A16: Discount rate for LLCR | B16: 0.055

Sheet Cash Flow
A3: Year | B3: 0 | C3: 1 | D3: 2 | E3: 3 | F3: 4 | G3: 5 | H3: 6 | I3: 7 | J3: 8 | K3: 9 | L3: 10 | M3: 11 | N3: 12 | O3: 13 | P3: 14 | Q3: 15 | R3: 16 | S3: 17 | T3: 18 | U3: 19 | V3: 20 | W3: 21 | X3: 22 | Y3: 23 | Z3: 24 | AA3: 25
A4: Availability payment | B4: =0 -> 0 | C4: =IF(C$3<=Inputs!$B$13,Inputs!$B$3*(1+Inputs!$B$4)^(C$3-1),0) -> 265000000 | D4: =IF(D$3<=Inputs!$B$13,Inputs!$B$3*(1+Inputs!$B$4)^(D$3-1),0) -> 270300000 | E4: =IF(E$3<=Inputs!$B$13,Inputs!$B$3*(1+Inputs!$B$4)^(E$3-1),0) -> 275706000 | F4: =IF(F$3<=Inputs!$B$13,Inputs!$B$3*(1+Inputs!$B$4)^(F$3-1),0) -> 281220120 | G4: =IF(G$3<=Inputs!$B$13,Inputs!$B$3*(1+Inputs!$B$4)^(G$3-1),0) -> 2.8684452e+08 | H4: =IF(H$3<=Inputs!$B$13,Inputs!$B$3*(1+Inputs!$B$4)^(H$3-1),0) -> 2.9258141e+08 | I4: =IF(I$3<=Inputs!$B$13,Inputs!$B$3*(1+Inputs!$B$4)^(I$3-1),0) -> 2.9843304e+08 | J4: =IF(J$3<=Inputs!$B$13,Inputs!$B$3*(1+Inputs!$B$4)^(J$3-1),0) -> 3.044017e+08 | ... AA4: =IF(AA$3<=Inputs!$B$13,Inputs!$B$3*(1+Inputs!$B$4)^(AA$3-1),0) -> 4.2623587e+08
A5: Deductions | B5: =B4*Inputs!$B$5 -> 0 | C5: =C4*Inputs!$B$5 -> 3975000 | D5: =D4*Inputs!$B$5 -> 4054500 | E5: =E4*Inputs!$B$5 -> 4135590 | F5: =F4*Inputs!$B$5 -> 4218301.8 | G5: =G4*Inputs!$B$5 -> 4302667.8 | H5: =H4*Inputs!$B$5 -> 4388721.2 | I5: =I4*Inputs!$B$5 -> 4476495.6 | ... AA5: =AA4*Inputs!$B$5 -> 6393538.1
A6: Revenue | B6: =B4-B5 -> 0 | C6: =C4-C5 -> 261025000 | D6: =D4-D5 -> 266245500 | E6: =E4-E5 -> 271570410 | F6: =F4-F5 -> 2.7700182e+08 | G6: =G4-G5 -> 2.8254185e+08 | H6: =H4-H5 -> 2.8819269e+08 | I6: =I4-I5 -> 2.9395655e+08 | ... AA6: =AA4-AA5 -> 4.1984233e+08
A7: FM | B7: =0 -> 0 | C7: =IF(C$3<=Inputs!$B$13,Inputs!$B$6*(1+Inputs!$B$4)^(C$3-1),0) -> 72000000 | D7: =IF(D$3<=Inputs!$B$13,Inputs!$B$6*(1+Inputs!$B$4)^(D$3-1),0) -> 73440000 | E7: =IF(E$3<=Inputs!$B$13,Inputs!$B$6*(1+Inputs!$B$4)^(E$3-1),0) -> 74908800 | F7: =IF(F$3<=Inputs!$B$13,Inputs!$B$6*(1+Inputs!$B$4)^(F$3-1),0) -> 76406976 | G7: =IF(G$3<=Inputs!$B$13,Inputs!$B$6*(1+Inputs!$B$4)^(G$3-1),0) -> 77935116 | H7: =IF(H$3<=Inputs!$B$13,Inputs!$B$6*(1+Inputs!$B$4)^(H$3-1),0) -> 79493818 | I7: =IF(I$3<=Inputs!$B$13,Inputs!$B$6*(1+Inputs!$B$4)^(I$3-1),0) -> 81083694 | J7: =IF(J$3<=Inputs!$B$13,Inputs!$B$6*(1+Inputs!$B$4)^(J$3-1),0) -> 82705368 | ... AA7: =IF(AA$3<=Inputs!$B$13,Inputs!$B$6*(1+Inputs!$B$4)^(AA$3-1),0) -> 1.1580748e+08
A8: Lifecycle | B8: =0 -> 0 | C8: =IF(C$3<=Inputs!$B$13,Inputs!$B$7*(1+Inputs!$B$4)^(C$3-1),0) -> 18000000 | D8: =IF(D$3<=Inputs!$B$13,Inputs!$B$7*(1+Inputs!$B$4)^(D$3-1),0) -> 18360000 | E8: =IF(E$3<=Inputs!$B$13,Inputs!$B$7*(1+Inputs!$B$4)^(E$3-1),0) -> 18727200 | F8: =IF(F$3<=Inputs!$B$13,Inputs!$B$7*(1+Inputs!$B$4)^(F$3-1),0) -> 19101744 | G8: =IF(G$3<=Inputs!$B$13,Inputs!$B$7*(1+Inputs!$B$4)^(G$3-1),0) -> 19483779 | H8: =IF(H$3<=Inputs!$B$13,Inputs!$B$7*(1+Inputs!$B$4)^(H$3-1),0) -> 19873454 | I8: =IF(I$3<=Inputs!$B$13,Inputs!$B$7*(1+Inputs!$B$4)^(I$3-1),0) -> 20270924 | J8: =IF(J$3<=Inputs!$B$13,Inputs!$B$7*(1+Inputs!$B$4)^(J$3-1),0) -> 20676342 | ... AA8: =IF(AA$3<=Inputs!$B$13,Inputs!$B$7*(1+Inputs!$B$4)^(AA$3-1),0) -> 28951870
A9: CFADS | B9: =B6-B7-B8 -> 0 | C9: =C6-C7-C8 -> 171025000 | D9: =D6-D7-D8 -> 174445500 | E9: =E6-E7-E8 -> 177934410 | F9: =F6-F7-F8 -> 1.814931e+08 | G9: =G6-G7-G8 -> 1.8512296e+08 | H9: =H6-H7-H8 -> 1.8882542e+08 | I9: =I6-I7-I8 -> 1.9260193e+08 | ... AA9: =AA6-AA7-AA8 -> 2.7508298e+08
A10: Opening debt | B10: =Inputs!$B$8*Inputs!$B$9 -> 1599000000 | C10: =B13 -> 1599000000 | D10: =C13 -> 1.5553873e+09 | E10: =D13 -> 1.5067448e+09 | F10: =E13 -> 1.4527431e+09 | G10: =F13 -> 1.3930339e+09 | H10: =G13 -> 1.3272485e+09 | I10: =H13 -> 1.2549968e+09 | J10: =I13 -> 1.1758663e+09 | ... AA10: =Z13 -> 0
A11: Interest | B11: =0 -> 0 | C11: =C10*Inputs!$B$10 -> 87945000 | D11: =D10*Inputs!$B$10 -> 85546302 | E11: =E10*Inputs!$B$10 -> 82870962 | F11: =F10*Inputs!$B$10 -> 79900871 | G11: =G10*Inputs!$B$10 -> 76616864 | H11: =H10*Inputs!$B$10 -> 72998667 | I11: =I10*Inputs!$B$10 -> 69024826 | J11: =J10*Inputs!$B$10 -> 64672648 | ... AA11: =AA10*Inputs!$B$10 -> 0
A12: Repayment | B12: =0 -> 0 | C12: =IF(C$3<Inputs!$B$12,MIN(C10,MAX(0,C9/Inputs!$B$11-C11)),IF(C$3=Inputs!$B$12,C10,0)) -> 43612692 | D12: =IF(D$3<Inputs!$B$12,MIN(D10,MAX(0,D9/Inputs!$B$11-D11)),IF(D$3=Inputs!$B$12,D10,0)) -> 48642544 | E12: =IF(E$3<Inputs!$B$12,MIN(E10,MAX(0,E9/Inputs!$B$11-E11)),IF(E$3=Inputs!$B$12,E10,0)) -> 54001661 | F12: =IF(F$3<Inputs!$B$12,MIN(F10,MAX(0,F9/Inputs!$B$11-F11)),IF(F$3=Inputs!$B$12,F10,0)) -> 59709205 | G12: =IF(G$3<Inputs!$B$12,MIN(G10,MAX(0,G9/Inputs!$B$11-G11)),IF(G$3=Inputs!$B$12,G10,0)) -> 65785413 | H12: =IF(H$3<Inputs!$B$12,MIN(H10,MAX(0,H9/Inputs!$B$11-H11)),IF(H$3=Inputs!$B$12,H10,0)) -> 72251656 | I12: =IF(I$3<Inputs!$B$12,MIN(I10,MAX(0,I9/Inputs!$B$11-I11)),IF(I$3=Inputs!$B$12,I10,0)) -> 79130503 | J12: =IF(J$3<Inputs!$B$12,MIN(J10,MAX(0,J9/Inputs!$B$11-J11)),IF(J$3=Inputs!$B$12,J10,0)) -> 86445788 | ... AA12: =IF(AA$3<Inputs!$B$12,MIN(AA10,MAX(0,AA9/Inputs!$B$11-AA11)),IF(AA$3=Inputs!$B$12,AA10,0)) -> 0
A13: Closing debt | B13: =B10-B12 -> 1599000000 | C13: =C10-C12 -> 1.5553873e+09 | D13: =D10-D12 -> 1.5067448e+09 | E13: =E10-E12 -> 1.4527431e+09 | F13: =F10-F12 -> 1.3930339e+09 | G13: =G10-G12 -> 1.3272485e+09 | H13: =H10-H12 -> 1.2549968e+09 | I13: =I10-I12 -> 1.1758663e+09 | ... AA13: =AA10-AA12 -> 0
A14: DSCR | B14: =IF(B11+B12>0,B9/(B11+B12),0) -> 0 | C14: =IF(C11+C12>0,C9/(C11+C12),0) -> 1.3 | D14: =IF(D11+D12>0,D9/(D11+D12),0) -> 1.3 | E14: =IF(E11+E12>0,E9/(E11+E12),0) -> 1.3 | F14: =IF(F11+F12>0,F9/(F11+F12),0) -> 1.3 | G14: =IF(G11+G12>0,G9/(G11+G12),0) -> 1.3 | H14: =IF(H11+H12>0,H9/(H11+H12),0) -> 1.3 | I14: =IF(I11+I12>0,I9/(I11+I12),0) -> 1.3 | ... AA14: =IF(AA11+AA12>0,AA9/(AA11+AA12),0) -> 0
A15: DSRA balance | B15: =(C10*Inputs!$B$10+IF(C$3<Inputs!$B$12,MIN(C10,MAX(0,C9/Inputs!$B$11-C10*Inputs!$B$10)),IF(C$3=Inputs!$B$12,C10,0)))*Inputs!$B$14/12 -> 65778846 | C15: =(D10*Inputs!$B$10+IF(D$3<Inputs!$B$12,MIN(D10,MAX(0,D9/Inputs!$B$11-D10*Inputs!$B$10)),IF(D$3=Inputs!$B$12,D10,0)))*Inputs!$B$14/12 -> 67094423 | D15: =(E10*Inputs!$B$10+IF(E$3<Inputs!$B$12,MIN(E10,MAX(0,E9/Inputs!$B$11-E10*Inputs!$B$10)),IF(E$3=Inputs!$B$12,E10,0)))*Inputs!$B$14/12 -> 68436312 | E15: =(F10*Inputs!$B$10+IF(F$3<Inputs!$B$12,MIN(F10,MAX(0,F9/Inputs!$B$11-F10*Inputs!$B$10)),IF(F$3=Inputs!$B$12,F10,0)))*Inputs!$B$14/12 -> 69805038 | F15: =(G10*Inputs!$B$10+IF(G$3<Inputs!$B$12,MIN(G10,MAX(0,G9/Inputs!$B$11-G10*Inputs!$B$10)),IF(G$3=Inputs!$B$12,G10,0)))*Inputs!$B$14/12 -> 71201139 | G15: =(H10*Inputs!$B$10+IF(H$3<Inputs!$B$12,MIN(H10,MAX(0,H9/Inputs!$B$11-H10*Inputs!$B$10)),IF(H$3=Inputs!$B$12,H10,0)))*Inputs!$B$14/12 -> 72625161 | H15: =(I10*Inputs!$B$10+IF(I$3<Inputs!$B$12,MIN(I10,MAX(0,I9/Inputs!$B$11-I10*Inputs!$B$10)),IF(I$3=Inputs!$B$12,I10,0)))*Inputs!$B$14/12 -> 74077665 | I15: =(J10*Inputs!$B$10+IF(J$3<Inputs!$B$12,MIN(J10,MAX(0,J9/Inputs!$B$11-J10*Inputs!$B$10)),IF(J$3=Inputs!$B$12,J10,0)))*Inputs!$B$14/12 -> 75559218 | ... Z15: =(AA10*Inputs!$B$10+IF(AA$3<Inputs!$B$12,MIN(AA10,MAX(0,AA9/Inputs!$B$11-AA10*Inputs!$B$10)),IF(AA$3=Inputs!$B$12,AA10,0)))*Inputs!$B$14/12 -> 0 | AA15: =0 -> 0
A16: DSRA movement | B16: =B15 -> 65778846 | C16: =C15-B15 -> 1315576.9 | D16: =D15-C15 -> 1341888.5 | E16: =E15-D15 -> 1368726.2 | F16: =F15-E15 -> 1396100.8 | G16: =G15-F15 -> 1424022.8 | H16: =H15-G15 -> 1452503.2 | I16: =I15-H15 -> 1481553.3 | J16: =J15-I15 -> 1511184.4 | ... AA16: =AA15-Z15 -> 0
A17: Zakat | B17: =MAX(0,B9-B11)*Inputs!$B$15 -> 0 | C17: =MAX(0,C9-C11)*Inputs!$B$15 -> 2077000 | D17: =MAX(0,D9-D11)*Inputs!$B$15 -> 2222480 | E17: =MAX(0,E9-E11)*Inputs!$B$15 -> 2376586.2 | F17: =MAX(0,F9-F11)*Inputs!$B$15 -> 2539805.7 | G17: =MAX(0,G9-G11)*Inputs!$B$15 -> 2712652.4 | H17: =MAX(0,H9-H11)*Inputs!$B$15 -> 2895668.8 | I17: =MAX(0,I9-I11)*Inputs!$B$15 -> 3089427.6 | ... AA17: =MAX(0,AA9-AA11)*Inputs!$B$15 -> 6877074.5
A18: Equity cash flow | B18: =-Inputs!$B$8*(1-Inputs!$B$9)-B16 -> -4.1677885e+08 | C18: =C9-C11-C12-C16-C17 -> 36074731 | D18: =D9-D11-D12-D16-D17 -> 36692285 | E18: =E9-E11-E12-E16-E17 -> 37316474 | F18: =F9-F11-F12-F16-F17 -> 37947116 | G18: =G9-G11-G12-G16-G17 -> 38584008 | H18: =H9-H11-H12-H16-H17 -> 39226925 | I18: =I9-I11-I12-I16-I17 -> 39875618 | J18: =J9-J11-J12-J16-J17 -> 40529813 | ... AA18: =AA9-AA11-AA12-AA16-AA17 -> 2.6820591e+08

Sheet Returns
A3: Equity IRR | B3: =IRR('Cash Flow'!$B$18:$AA$18) -> 0.13503355
A4: Minimum DSCR | B4: =_xlfn.MINIFS('Cash Flow'!$B$14:$AA$14,'Cash Flow'!$B$14:$AA$14,">0") -> 1.3
A5: LLCR at financial close | B5: =NPV(Inputs!$B$16,'Cash Flow'!$C$9:$X$9)/'Cash Flow'!$B$10 -> 1.6011631
A6: Peak DSRA (SAR) | B6: =MAX('Cash Flow'!$B$15:$AA$15) -> 88529666
A7: Debt outstanding at maturity (SAR) | B7: =INDEX('Cash Flow'!$B$13:$AA$13,Inputs!$B$12+1) -> 0
A8: Zakat over the term (SAR) | B8: =SUM('Cash Flow'!$B$17:$AA$17) -> 1.1369197e+08
A9: Net profit (SAR) | B9: =SUM('Cash Flow'!$B$18:$AA$18) -> 2.4839869e+09
