Workbook

Sheet Inputs
A1: NORDHAFEN LOGISTICS PORTFOLIO – QUARTERLY (EUR)
A3: Scenario | B3: Base | D3: Allowed: Base, Downside
A4: Model start | B4: 46387
A5: Portfolio price (EUR) | B5: 318000000
A6: Exit yield | B6: 0.0525
A7: Non-recoverable costs share | B7: 0.045
A8: Re-letting void (quarters) | B8: 2
A9: ERV uplift on re-letting | B9: 0.08

Sheet Scenarios
A1: Scenario | B1: CPI shift | C1: Void shift (quarters) | D1: Exit yield shift
A2: Base | B2: 0 | C2: 0 | D2: 0
A3: Downside | B3: -0.01 | C3: 2 | D3: 0.0075

Sheet CPI
A1: Country | B1: 2027 | C1: 2028 | D1: 2029 | E1: 2030 | F1: 2031 | G1: 2032 | H1: 2033
A2: DE | B2: 0.022 | C2: 0.021 | D2: 0.02 | E2: 0.02 | F2: 0.02 | G2: 0.02 | H2: 0.02
A3: NL | B3: 0.026 | C3: 0.024 | D3: 0.022 | E3: 0.021 | F3: 0.02 | G3: 0.02 | H3: 0.02
A4: PL | B4: 0.041 | C4: 0.035 | D4: 0.031 | E4: 0.029 | F4: 0.027 | G4: 0.026 | H4: 0.025
A5: CZ | B5: 0.033 | C5: 0.029 | D5: 0.026 | E5: 0.025 | F5: 0.024 | G5: 0.023 | H5: 0.022

Sheet Warehouses
A1: Asset | B1: Country | C1: Region | D1: Area (sqm) | E1: Rent (EUR/sqm/yr) | F1: Lease expiry | G1: Rent-free quarters
A2: Hamburg Süd | B2: DE | C2: North | D2: 62000 | E2: 78 | F2: 48029 | G2: 0
A3: Bremen GVZ | B3: DE | C3: North | D3: 41000 | E3: 72 | F3: 47118 | G3: 1
A4: Duisburg Logport | B4: DE | C4: West | D4: 55000 | E4: 81 | F4: 48669 | G4: 0
A5: Venlo | B5: NL | C5: West | D5: 48000 | E5: 84 | F5: 47391 | G5: 2
A6: Tilburg | B6: NL | C6: West | D6: 36000 | E6: 79 | F6: 48579 | G6: 0
A7: Poznań | B7: PL | C7: East | D7: 71000 | E7: 48 | F7: 47573 | G7: 1
A8: Wrocław | B8: PL | C8: East | D8: 52000 | E8: 46 | F8: 46752 | G8: 0
A9: Brno | B9: CZ | C9: East | D9: 39000 | E9: 55 | F9: 48213 | G9: 1

Sheet Cash Flow
A3: Quarter | B3: 0 | C3: 1 | D3: 2 | E3: 3 | F3: 4 | G3: 5 | H3: 6 | I3: 7 | J3: 8 | K3: 9 | L3: 10 | M3: 11 | N3: 12 | O3: 13 | P3: 14 | Q3: 15 | R3: 16 | S3: 17 | T3: 18 | U3: 19 | V3: 20 | W3: 21 | X3: 22 | Y3: 23 | Z3: 24 | AA3: 25 | AB3: 26 | AC3: 27 | AD3: 28
A4: Date | B4: =EOMONTH(Inputs!$B$4,3*B$3) -> 46387 | C4: =EOMONTH(Inputs!$B$4,3*C$3) -> 46477 | D4: =EOMONTH(Inputs!$B$4,3*D$3) -> 46568 | E4: =EOMONTH(Inputs!$B$4,3*E$3) -> 46660 | F4: =EOMONTH(Inputs!$B$4,3*F$3) -> 46752 | G4: =EOMONTH(Inputs!$B$4,3*G$3) -> 46843 | H4: =EOMONTH(Inputs!$B$4,3*H$3) -> 46934 | I4: =EOMONTH(Inputs!$B$4,3*I$3) -> 47026 | ... AD4: =EOMONTH(Inputs!$B$4,3*AD$3) -> 48944
A5: Year | B5: =MIN(2033,MAX(2027,YEAR(B4))) -> 2027 | C5: =MIN(2033,MAX(2027,YEAR(C4))) -> 2027 | D5: =MIN(2033,MAX(2027,YEAR(D4))) -> 2027 | E5: =MIN(2033,MAX(2027,YEAR(E4))) -> 2027 | F5: =MIN(2033,MAX(2027,YEAR(F4))) -> 2027 | G5: =MIN(2033,MAX(2027,YEAR(G4))) -> 2028 | H5: =MIN(2033,MAX(2027,YEAR(H4))) -> 2028 | I5: =MIN(2033,MAX(2027,YEAR(I4))) -> 2028 | ... AD5: =MIN(2033,MAX(2027,YEAR(AD4))) -> 2033
A6: Rent 1 | B6: =0 -> 0 | C6: =IF(C$3<=Warehouses!$G$2,0,IF(C4<=Warehouses!$F$2,Warehouses!$D$2*Warehouses!$E$2/4*(1+(INDEX(CPI!$B$2:$H$5,MATCH(Warehouses!$B$2,CPI!$A$2:$A$5,0),MATCH(C5,CPI!$B$1:$H$1,0))+INDEX(Scenarios!$B$2:$B$3,MATCH(Inputs!$B$3,Scenarios!$A$2:$A$3,0))))^(C$3/4),IF(C4<=EOMONTH(Warehouses!$F$2,3*(Inputs!$B$8+INDEX(Scenarios!$C$2:$C$3,MATCH(Inputs!$B$3,Scenarios!$A$2:$A$3,0)))),0,Warehouses!$D$2*Warehouses!$E$2/4*(1+(INDEX(CPI!$B$2:$H$5,MATCH(Warehouses!$B$2,CPI!$A$2:$A$5,0),MATCH(C5,CPI!$B$1:$H$1,0))+INDEX(Scenarios!$B$2:$B$3,MATCH(Inputs!$B$3,Scenarios!$A$2:$A$3,0))))^(C$3/4)*(1+Inputs!$B$9)))) -> 1215595.3 | D6: =IF(D$3<=Warehouses!$G$2,0,IF(D4<=Warehouses!$F$2,Warehouses!$D$2*Warehouses!$E$2/4*(1+(INDEX(CPI!$B$2:$H$5,MATCH(Warehouses!$B$2,CPI!$A$2:$A$5,0),MATCH(D5,CPI!$B$1:$H$1,0))+INDEX(Scenarios!$B$2:$B$3,MATCH(Inputs!$B$3,Scenarios!$A$2:$A$3,0))))^(D$3/4),IF(D4<=EOMONTH(Warehouses!$F$2,3*(Inputs!$B$8+INDEX(Scenarios!$C$2:$C$3,MATCH(Inputs!$B$3,Scenarios!$A$2:$A$3,0)))),0,Warehouses!$D$2*Warehouses!$E$2/4*(1+(INDEX(CPI!$B$2:$H$5,MATCH(Warehouses!$B$2,CPI!$A$2:$A$5,0),MATCH(D5,CPI!$B$1:$H$1,0))+INDEX(Scenarios!$B$2:$B$3,MATCH(Inputs!$B$3,Scenarios!$A$2:$A$3,0))))^(D$3/4)*(1+Inputs!$B$9)))) -> 1222226.6 | E6: =IF(E$3<=Warehouses!$G$2,0,IF(E4<=Warehouses!$F$2,Warehouses!$D$2*Warehouses!$E$2/4*(1+(INDEX(CPI!$B$2:$H$5,MATCH(Warehouses!$B$2,CPI!$A$2:$A$5,0),MATCH(E5,CPI!$B$1:$H$1,0))+INDEX(Scenarios!$B$2:$B$3,MATCH(Inputs!$B$3,Scenarios!$A$2:$A$3,0))))^(E$3/4),IF(E4<=EOMONTH(Warehouses!$F$2,3*(Inputs!$B$8+INDEX(Scenarios!$C$2:$C$3,MATCH(Inputs!$B$3,Scenarios!$A$2:$A$3,0)))),0,Warehouses!$D$2*Warehouses!$E$2/4*(1+(INDEX(CPI!$B$2:$H$5,MATCH(Warehouses!$B$2,CPI!$A$2:$A$5,0),MATCH(E5,CPI!$B$1:$H$1,0))+INDEX(Scenarios!$B$2:$B$3,MATCH(Inputs!$B$3,Scenarios!$A$2:$A$3,0))))^(E$3/4)*(1+Inputs!$B$9)))) -> 1228894.1 | F6: =IF(F$3<=Warehouses!$G$2,0,IF(F4<=Warehouses!$F$2,Warehouses!$D$2*Warehouses!$E$2/4*(1+(INDEX(CPI!$B$2:$H$5,MATCH(Warehouses!$B$2,CPI!$A$2:$A$5,0),MATCH(F5,CPI!$B$1:$H$1,0))+INDEX(Scenarios!$B$2:$B$3,MATCH(Inputs!$B$3,Scenarios!$A$2:$A$3,0))))^(F$3/4),IF(F4<=EOMONTH(Warehouses!$F$2,3*(Inputs!$B$8+INDEX(Scenarios!$C$2:$C$3,MATCH(Inputs!$B$3,Scenarios!$A$2:$A$3,0)))),0,Warehouses!$D$2*Warehouses!$E$2/4*(1+(INDEX(CPI!$B$2:$H$5,MATCH(Warehouses!$B$2,CPI!$A$2:$A$5,0),MATCH(F5,CPI!$B$1:$H$1,0))+INDEX(Scenarios!$B$2:$B$3,MATCH(Inputs!$B$3,Scenarios!$A$2:$A$3,0))))^(F$3/4)*(1+Inputs!$B$9)))) -> 1235598 | G6: =IF(G$3<=Warehouses!$G$2,0,IF(G4<=Warehouses!$F$2,Warehouses!$D$2*Warehouses!$E$2/4*(1+(INDEX(CPI!$B$2:$H$5,MATCH(Warehouses!$B$2,CPI!$A$2:$A$5,0),MATCH(G5,CPI!$B$1:$H$1,0))+INDEX(Scenarios!$B$2:$B$3,MATCH(Inputs!$B$3,Scenarios!$A$2:$A$3,0))))^(G$3/4),IF(G4<=EOMONTH(Warehouses!$F$2,3*(Inputs!$B$8+INDEX(Scenarios!$C$2:$C$3,MATCH(Inputs!$B$3,Scenarios!$A$2:$A$3,0)))),0,Warehouses!$D$2*Warehouses!$E$2/4*(1+(INDEX(CPI!$B$2:$H$5,MATCH(Warehouses!$B$2,CPI!$A$2:$A$5,0),MATCH(G5,CPI!$B$1:$H$1,0))+INDEX(Scenarios!$B$2:$B$3,MATCH(Inputs!$B$3,Scenarios!$A$2:$A$3,0))))^(G$3/4)*(1+Inputs!$B$9)))) -> 1240819.1 | H6: =IF(H$3<=Warehouses!$G$2,0,IF(H4<=Warehouses!$F$2,Warehouses!$D$2*Warehouses!$E$2/4*(1+(INDEX(CPI!$B$2:$H$5,MATCH(Warehouses!$B$2,CPI!$A$2:$A$5,0),MATCH(H5,CPI!$B$1:$H$1,0))+INDEX(Scenarios!$B$2:$B$3,MATCH(Inputs!$B$3,Scenarios!$A$2:$A$3,0))))^(H$3/4),IF(H4<=EOMONTH(Warehouses!$F$2,3*(Inputs!$B$8+INDEX(Scenarios!$C$2:$C$3,MATCH(Inputs!$B$3,Scenarios!$A$2:$A$3,0)))),0,Warehouses!$D$2*Warehouses!$E$2/4*(1+(INDEX(CPI!$B$2:$H$5,MATCH(Warehouses!$B$2,CPI!$A$2:$A$5,0),MATCH(H5,CPI!$B$1:$H$1,0))+INDEX(Scenarios!$B$2:$B$3,MATCH(Inputs!$B$3,Scenarios!$A$2:$A$3,0))))^(H$3/4)*(1+Inputs!$B$9)))) -> 1247282.7 | I6: =IF(I$3<=Warehouses!$G$2,0,IF(I4<=Warehouses!$F$2,Warehouses!$D$2*Warehouses!$E$2/4*(1+(INDEX(CPI!$B$2:$H$5,MATCH(Warehouses!$B$2,CPI!$A$2:$A$5,0),MATCH(I5,CPI!$B$1:$H$1,0))+INDEX(Scenarios!$B$2:$B$3,MATCH(Inputs!$B$3,Scenarios!$A$2:$A$3,0))))^(I$3/4),IF(I4<=EOMONTH(Warehouses!$F$2,3*(Inputs!$B$8+INDEX(Scenarios!$C$2:$C$3,MATCH(Inputs!$B$3,Scenarios!$A$2:$A$3,0)))),0,Warehouses!$D$2*Warehouses!$E$2/4*(1+(INDEX(CPI!$B$2:$H$5,MATCH(Warehouses!$B$2,CPI!$A$2:$A$5,0),MATCH(I5,CPI!$B$1:$H$1,0))+INDEX(Scenarios!$B$2:$B$3,MATCH(Inputs!$B$3,Scenarios!$A$2:$A$3,0))))^(I$3/4)*(1+Inputs!$B$9)))) -> 1253780 | J6: =IF(J$3<=Warehouses!$G$2,0,IF(J4<=Warehouses!$F$2,Warehouses!$D$2*Warehouses!$E$2/4*(1+(INDEX(CPI!$B$2:$H$5,MATCH(Warehouses!$B$2,CPI!$A$2:$A$5,0),MATCH(J5,CPI!$B$1:$H$1,0))+INDEX(Scenarios!$B$2:$B$3,MATCH(Inputs!$B$3,Scenarios!$A$2:$A$3,0))))^(J$3/4),IF(J4<=EOMONTH(Warehouses!$F$2,3*(Inputs!$B$8+INDEX(Scenarios!$C$2:$C$3,MATCH(Inputs!$B$3,Scenarios!$A$2:$A$3,0)))),0,Warehouses!$D$2*Warehouses!$E$2/4*(1+(INDEX(CPI!$B$2:$H$5,MATCH(Warehouses!$B$2,CPI!$A$2:$A$5,0),MATCH(J5,CPI!$B$1:$H$1,0))+INDEX(Scenarios!$B$2:$B$3,MATCH(Inputs!$B$3,Scenarios!$A$2:$A$3,0))))^(J$3/4)*(1+Inputs!$B$9)))) -> 1260311.2 | ... AD6: =IF(AD$3<=Warehouses!$G$2,0,IF(AD4<=Warehouses!$F$2,Warehouses!$D$2*Warehouses!$E$2/4*(1+(INDEX(CPI!$B$2:$H$5,MATCH(Warehouses!$B$2,CPI!$A$2:$A$5,0),MATCH(AD5,CPI!$B$1:$H$1,0))+INDEX(Scenarios!$B$2:$B$3,MATCH(Inputs!$B$3,Scenarios!$A$2:$A$3,0))))^(AD$3/4),IF(AD4<=EOMONTH(Warehouses!$F$2,3*(Inputs!$B$8+INDEX(Scenarios!$C$2:$C$3,MATCH(Inputs!$B$3,Scenarios!$A$2:$A$3,0)))),0,Warehouses!$D$2*Warehouses!$E$2/4*(1+(INDEX(CPI!$B$2:$H$5,MATCH(Warehouses!$B$2,CPI!$A$2:$A$5,0),MATCH(AD5,CPI!$B$1:$H$1,0))+INDEX(Scenarios!$B$2:$B$3,MATCH(Inputs!$B$3,Scenarios!$A$2:$A$3,0))))^(AD$3/4)*(1+Inputs!$B$9)))) -> 1499861.8
A7: Rent 2 | B7: =0 -> 0 | C7: =IF(C$3<=Warehouses!$G$3,0,IF(C4<=Warehouses!$F$3,Warehouses!$D$3*Warehouses!$E$3/4*(1+(INDEX(CPI!$B$2:$H$5,MATCH(Warehouses!$B$3,CPI!$A$2:$A$5,0),MATCH(C5,CPI!$B$1:$H$1,0))+INDEX(Scenarios!$B$2:$B$3,MATCH(Inputs!$B$3,Scenarios!$A$2:$A$3,0))))^(C$3/4),IF(C4<=EOMONTH(Warehouses!$F$3,3*(Inputs!$B$8+INDEX(Scenarios!$C$2:$C$3,MATCH(Inputs!$B$3,Scenarios!$A$2:$A$3,0)))),0,Warehouses!$D$3*Warehouses!$E$3/4*(1+(INDEX(CPI!$B$2:$H$5,MATCH(Warehouses!$B$3,CPI!$A$2:$A$5,0),MATCH(C5,CPI!$B$1:$H$1,0))+INDEX(Scenarios!$B$2:$B$3,MATCH(Inputs!$B$3,Scenarios!$A$2:$A$3,0))))^(C$3/4)*(1+Inputs!$B$9)))) -> 0 | D7: =IF(D$3<=Warehouses!$G$3,0,IF(D4<=Warehouses!$F$3,Warehouses!$D$3*Warehouses!$E$3/4*(1+(INDEX(CPI!$B$2:$H$5,MATCH(Warehouses!$B$3,CPI!$A$2:$A$5,0),MATCH(D5,CPI!$B$1:$H$1,0))+INDEX(Scenarios!$B$2:$B$3,MATCH(Inputs!$B$3,Scenarios!$A$2:$A$3,0))))^(D$3/4),IF(D4<=EOMONTH(Warehouses!$F$3,3*(Inputs!$B$8+INDEX(Scenarios!$C$2:$C$3,MATCH(Inputs!$B$3,Scenarios!$A$2:$A$3,0)))),0,Warehouses!$D$3*Warehouses!$E$3/4*(1+(INDEX(CPI!$B$2:$H$5,MATCH(Warehouses!$B$3,CPI!$A$2:$A$5,0),MATCH(D5,CPI!$B$1:$H$1,0))+INDEX(Scenarios!$B$2:$B$3,MATCH(Inputs!$B$3,Scenarios!$A$2:$A$3,0))))^(D$3/4)*(1+Inputs!$B$9)))) -> 746073.84 | E7: =IF(E$3<=Warehouses!$G$3,0,IF(E4<=Warehouses!$F$3,Warehouses!$D$3*Warehouses!$E$3/4*(1+(INDEX(CPI!$B$2:$H$5,MATCH(Warehouses!$B$3,CPI!$A$2:$A$5,0),MATCH(E5,CPI!$B$1:$H$1,0))+INDEX(Scenarios!$B$2:$B$3,MATCH(Inputs!$B$3,Scenarios!$A$2:$A$3,0))))^(E$3/4),IF(E4<=EOMONTH(Warehouses!$F$3,3*(Inputs!$B$8+INDEX(Scenarios!$C$2:$C$3,MATCH(Inputs!$B$3,Scenarios!$A$2:$A$3,0)))),0,Warehouses!$D$3*Warehouses!$E$3/4*(1+(INDEX(CPI!$B$2:$H$5,MATCH(Warehouses!$B$3,CPI!$A$2:$A$5,0),MATCH(E5,CPI!$B$1:$H$1,0))+INDEX(Scenarios!$B$2:$B$3,MATCH(Inputs!$B$3,Scenarios!$A$2:$A$3,0))))^(E$3/4)*(1+Inputs!$B$9)))) -> 750143.82 | F7: =IF(F$3<=Warehouses!$G$3,0,IF(F4<=Warehouses!$F$3,Warehouses!$D$3*Warehouses!$E$3/4*(1+(INDEX(CPI!$B$2:$H$5,MATCH(Warehouses!$B$3,CPI!$A$2:$A$5,0),MATCH(F5,CPI!$B$1:$H$1,0))+INDEX(Scenarios!$B$2:$B$3,MATCH(Inputs!$B$3,Scenarios!$A$2:$A$3,0))))^(F$3/4),IF(F4<=EOMONTH(Warehouses!$F$3,3*(Inputs!$B$8+INDEX(Scenarios!$C$2:$C$3,MATCH(Inputs!$B$3,Scenarios!$A$2:$A$3,0)))),0,Warehouses!$D$3*Warehouses!$E$3/4*(1+(INDEX(CPI!$B$2:$H$5,MATCH(Warehouses!$B$3,CPI!$A$2:$A$5,0),MATCH(F5,CPI!$B$1:$H$1,0))+INDEX(Scenarios!$B$2:$B$3,MATCH(Inputs!$B$3,Scenarios!$A$2:$A$3,0))))^(F$3/4)*(1+Inputs!$B$9)))) -> 754236 | G7: =IF(G$3<=Warehouses!$G$3,0,IF(G4<=Warehouses!$F$3,Warehouses!$D$3*Warehouses!$E$3/4*(1+(INDEX(CPI!$B$2:$H$5,MATCH(Warehouses!$B$3,CPI!$A$2:$A$5,0),MATCH(G5,CPI!$B$1:$H$1,0))+INDEX(Scenarios!$B$2:$B$3,MATCH(Inputs!$B$3,Scenarios!$A$2:$A$3,0))))^(G$3/4),IF(G4<=EOMONTH(Warehouses!$F$3,3*(Inputs!$B$8+INDEX(Scenarios!$C$2:$C$3,MATCH(Inputs!$B$3,Scenarios!$A$2:$A$3,0)))),0,Warehouses!$D$3*Warehouses!$E$3/4*(1+(INDEX(CPI!$B$2:$H$5,MATCH(Warehouses!$B$3,CPI!$A$2:$A$5,0),MATCH(G5,CPI!$B$1:$H$1,0))+INDEX(Scenarios!$B$2:$B$3,MATCH(Inputs!$B$3,Scenarios!$A$2:$A$3,0))))^(G$3/4)*(1+Inputs!$B$9)))) -> 757423.09 | H7: =IF(H$3<=Warehouses!$G$3,0,IF(H4<=Warehouses!$F$3,Warehouses!$D$3*Warehouses!$E$3/4*(1+(INDEX(CPI!$B$2:$H$5,MATCH(Warehouses!$B$3,CPI!$A$2:$A$5,0),MATCH(H5,CPI!$B$1:$H$1,0))+INDEX(Scenarios!$B$2:$B$3,MATCH(Inputs!$B$3,Scenarios!$A$2:$A$3,0))))^(H$3/4),IF(H4<=EOMONTH(Warehouses!$F$3,3*(Inputs!$B$8+INDEX(Scenarios!$C$2:$C$3,MATCH(Inputs!$B$3,Scenarios!$A$2:$A$3,0)))),0,Warehouses!$D$3*Warehouses!$E$3/4*(1+(INDEX(CPI!$B$2:$H$5,MATCH(Warehouses!$B$3,CPI!$A$2:$A$5,0),MATCH(H5,CPI!$B$1:$H$1,0))+INDEX(Scenarios!$B$2:$B$3,MATCH(Inputs!$B$3,Scenarios!$A$2:$A$3,0))))^(H$3/4)*(1+Inputs!$B$9)))) -> 761368.62 | I7: =IF(I$3<=Warehouses!$G$3,0,IF(I4<=Warehouses!$F$3,Warehouses!$D$3*Warehouses!$E$3/4*(1+(INDEX(CPI!$B$2:$H$5,MATCH(Warehouses!$B$3,CPI!$A$2:$A$5,0),MATCH(I5,CPI!$B$1:$H$1,0))+INDEX(Scenarios!$B$2:$B$3,MATCH(Inputs!$B$3,Scenarios!$A$2:$A$3,0))))^(I$3/4),IF(I4<=EOMONTH(Warehouses!$F$3,3*(Inputs!$B$8+INDEX(Scenarios!$C$2:$C$3,MATCH(Inputs!$B$3,Scenarios!$A$2:$A$3,0)))),0,Warehouses!$D$3*Warehouses!$E$3/4*(1+(INDEX(CPI!$B$2:$H$5,MATCH(Warehouses!$B$3,CPI!$A$2:$A$5,0),MATCH(I5,CPI!$B$1:$H$1,0))+INDEX(Scenarios!$B$2:$B$3,MATCH(Inputs!$B$3,Scenarios!$A$2:$A$3,0))))^(I$3/4)*(1+Inputs!$B$9)))) -> 765334.71 | J7: =IF(J$3<=Warehouses!$G$3,0,IF(J4<=Warehouses!$F$3,Warehouses!$D$3*Warehouses!$E$3/4*(1+(INDEX(CPI!$B$2:$H$5,MATCH(Warehouses!$B$3,CPI!$A$2:$A$5,0),MATCH(J5,CPI!$B$1:$H$1,0))+INDEX(Scenarios!$B$2:$B$3,MATCH(Inputs!$B$3,Scenarios!$A$2:$A$3,0))))^(J$3/4),IF(J4<=EOMONTH(Warehouses!$F$3,3*(Inputs!$B$8+INDEX(Scenarios!$C$2:$C$3,MATCH(Inputs!$B$3,Scenarios!$A$2:$A$3,0)))),0,Warehouses!$D$3*Warehouses!$E$3/4*(1+(INDEX(CPI!$B$2:$H$5,MATCH(Warehouses!$B$3,CPI!$A$2:$A$5,0),MATCH(J5,CPI!$B$1:$H$1,0))+INDEX(Scenarios!$B$2:$B$3,MATCH(Inputs!$B$3,Scenarios!$A$2:$A$3,0))))^(J$3/4)*(1+Inputs!$B$9)))) -> 769321.46 | ... AD7: =IF(AD$3<=Warehouses!$G$3,0,IF(AD4<=Warehouses!$F$3,Warehouses!$D$3*Warehouses!$E$3/4*(1+(INDEX(CPI!$B$2:$H$5,MATCH(Warehouses!$B$3,CPI!$A$2:$A$5,0),MATCH(AD5,CPI!$B$1:$H$1,0))+INDEX(Scenarios!$B$2:$B$3,MATCH(Inputs!$B$3,Scenarios!$A$2:$A$3,0))))^(AD$3/4),IF(AD4<=EOMONTH(Warehouses!$F$3,3*(Inputs!$B$8+INDEX(Scenarios!$C$2:$C$3,MATCH(Inputs!$B$3,Scenarios!$A$2:$A$3,0)))),0,Warehouses!$D$3*Warehouses!$E$3/4*(1+(INDEX(CPI!$B$2:$H$5,MATCH(Warehouses!$B$3,CPI!$A$2:$A$5,0),MATCH(AD5,CPI!$B$1:$H$1,0))+INDEX(Scenarios!$B$2:$B$3,MATCH(Inputs!$B$3,Scenarios!$A$2:$A$3,0))))^(AD$3/4)*(1+Inputs!$B$9)))) -> 915548.42
A8: Rent 3 | B8: =0 -> 0 | C8: =IF(C$3<=Warehouses!$G$4,0,IF(C4<=Warehouses!$F$4,Warehouses!$D$4*Warehouses!$E$4/4*(1+(INDEX(CPI!$B$2:$H$5,MATCH(Warehouses!$B$4,CPI!$A$2:$A$5,0),MATCH(C5,CPI!$B$1:$H$1,0))+INDEX(Scenarios!$B$2:$B$3,MATCH(Inputs!$B$3,Scenarios!$A$2:$A$3,0))))^(C$3/4),IF(C4<=EOMONTH(Warehouses!$F$4,3*(Inputs!$B$8+INDEX(Scenarios!$C$2:$C$3,MATCH(Inputs!$B$3,Scenarios!$A$2:$A$3,0)))),0,Warehouses!$D$4*Warehouses!$E$4/4*(1+(INDEX(CPI!$B$2:$H$5,MATCH(Warehouses!$B$4,CPI!$A$2:$A$5,0),MATCH(C5,CPI!$B$1:$H$1,0))+INDEX(Scenarios!$B$2:$B$3,MATCH(Inputs!$B$3,Scenarios!$A$2:$A$3,0))))^(C$3/4)*(1+Inputs!$B$9)))) -> 1119825.7 | D8: =IF(D$3<=Warehouses!$G$4,0,IF(D4<=Warehouses!$F$4,Warehouses!$D$4*Warehouses!$E$4/4*(1+(INDEX(CPI!$B$2:$H$5,MATCH(Warehouses!$B$4,CPI!$A$2:$A$5,0),MATCH(D5,CPI!$B$1:$H$1,0))+INDEX(Scenarios!$B$2:$B$3,MATCH(Inputs!$B$3,Scenarios!$A$2:$A$3,0))))^(D$3/4),IF(D4<=EOMONTH(Warehouses!$F$4,3*(Inputs!$B$8+INDEX(Scenarios!$C$2:$C$3,MATCH(Inputs!$B$3,Scenarios!$A$2:$A$3,0)))),0,Warehouses!$D$4*Warehouses!$E$4/4*(1+(INDEX(CPI!$B$2:$H$5,MATCH(Warehouses!$B$4,CPI!$A$2:$A$5,0),MATCH(D5,CPI!$B$1:$H$1,0))+INDEX(Scenarios!$B$2:$B$3,MATCH(Inputs!$B$3,Scenarios!$A$2:$A$3,0))))^(D$3/4)*(1+Inputs!$B$9)))) -> 1125934.6 | E8: =IF(E$3<=Warehouses!$G$4,0,IF(E4<=Warehouses!$F$4,Warehouses!$D$4*Warehouses!$E$4/4*(1+(INDEX(CPI!$B$2:$H$5,MATCH(Warehouses!$B$4,CPI!$A$2:$A$5,0),MATCH(E5,CPI!$B$1:$H$1,0))+INDEX(Scenarios!$B$2:$B$3,MATCH(Inputs!$B$3,Scenarios!$A$2:$A$3,0))))^(E$3/4),IF(E4<=EOMONTH(Warehouses!$F$4,3*(Inputs!$B$8+INDEX(Scenarios!$C$2:$C$3,MATCH(Inputs!$B$3,Scenarios!$A$2:$A$3,0)))),0,Warehouses!$D$4*Warehouses!$E$4/4*(1+(INDEX(CPI!$B$2:$H$5,MATCH(Warehouses!$B$4,CPI!$A$2:$A$5,0),MATCH(E5,CPI!$B$1:$H$1,0))+INDEX(Scenarios!$B$2:$B$3,MATCH(Inputs!$B$3,Scenarios!$A$2:$A$3,0))))^(E$3/4)*(1+Inputs!$B$9)))) -> 1132076.8 | F8: =IF(F$3<=Warehouses!$G$4,0,IF(F4<=Warehouses!$F$4,Warehouses!$D$4*Warehouses!$E$4/4*(1+(INDEX(CPI!$B$2:$H$5,MATCH(Warehouses!$B$4,CPI!$A$2:$A$5,0),MATCH(F5,CPI!$B$1:$H$1,0))+INDEX(Scenarios!$B$2:$B$3,MATCH(Inputs!$B$3,Scenarios!$A$2:$A$3,0))))^(F$3/4),IF(F4<=EOMONTH(Warehouses!$F$4,3*(Inputs!$B$8+INDEX(Scenarios!$C$2:$C$3,MATCH(Inputs!$B$3,Scenarios!$A$2:$A$3,0)))),0,Warehouses!$D$4*Warehouses!$E$4/4*(1+(INDEX(CPI!$B$2:$H$5,MATCH(Warehouses!$B$4,CPI!$A$2:$A$5,0),MATCH(F5,CPI!$B$1:$H$1,0))+INDEX(Scenarios!$B$2:$B$3,MATCH(Inputs!$B$3,Scenarios!$A$2:$A$3,0))))^(F$3/4)*(1+Inputs!$B$9)))) -> 1138252.5 | G8: =IF(G$3<=Warehouses!$G$4,0,IF(G4<=Warehouses!$F$4,Warehouses!$D$4*Warehouses!$E$4/4*(1+(INDEX(CPI!$B$2:$H$5,MATCH(Warehouses!$B$4,CPI!$A$2:$A$5,0),MATCH(G5,CPI!$B$1:$H$1,0))+INDEX(Scenarios!$B$2:$B$3,MATCH(Inputs!$B$3,Scenarios!$A$2:$A$3,0))))^(G$3/4),IF(G4<=EOMONTH(Warehouses!$F$4,3*(Inputs!$B$8+INDEX(Scenarios!$C$2:$C$3,MATCH(Inputs!$B$3,Scenarios!$A$2:$A$3,0)))),0,Warehouses!$D$4*Warehouses!$E$4/4*(1+(INDEX(CPI!$B$2:$H$5,MATCH(Warehouses!$B$4,CPI!$A$2:$A$5,0),MATCH(G5,CPI!$B$1:$H$1,0))+INDEX(Scenarios!$B$2:$B$3,MATCH(Inputs!$B$3,Scenarios!$A$2:$A$3,0))))^(G$3/4)*(1+Inputs!$B$9)))) -> 1143062.3 | H8: =IF(H$3<=Warehouses!$G$4,0,IF(H4<=Warehouses!$F$4,Warehouses!$D$4*Warehouses!$E$4/4*(1+(INDEX(CPI!$B$2:$H$5,MATCH(Warehouses!$B$4,CPI!$A$2:$A$5,0),MATCH(H5,CPI!$B$1:$H$1,0))+INDEX(Scenarios!$B$2:$B$3,MATCH(Inputs!$B$3,Scenarios!$A$2:$A$3,0))))^(H$3/4),IF(H4<=EOMONTH(Warehouses!$F$4,3*(Inputs!$B$8+INDEX(Scenarios!$C$2:$C$3,MATCH(Inputs!$B$3,Scenarios!$A$2:$A$3,0)))),0,Warehouses!$D$4*Warehouses!$E$4/4*(1+(INDEX(CPI!$B$2:$H$5,MATCH(Warehouses!$B$4,CPI!$A$2:$A$5,0),MATCH(H5,CPI!$B$1:$H$1,0))+INDEX(Scenarios!$B$2:$B$3,MATCH(Inputs!$B$3,Scenarios!$A$2:$A$3,0))))^(H$3/4)*(1+Inputs!$B$9)))) -> 1149016.7 | I8: =IF(I$3<=Warehouses!$G$4,0,IF(I4<=Warehouses!$F$4,Warehouses!$D$4*Warehouses!$E$4/4*(1+(INDEX(CPI!$B$2:$H$5,MATCH(Warehouses!$B$4,CPI!$A$2:$A$5,0),MATCH(I5,CPI!$B$1:$H$1,0))+INDEX(Scenarios!$B$2:$B$3,MATCH(Inputs!$B$3,Scenarios!$A$2:$A$3,0))))^(I$3/4),IF(I4<=EOMONTH(Warehouses!$F$4,3*(Inputs!$B$8+INDEX(Scenarios!$C$2:$C$3,MATCH(Inputs!$B$3,Scenarios!$A$2:$A$3,0)))),0,Warehouses!$D$4*Warehouses!$E$4/4*(1+(INDEX(CPI!$B$2:$H$5,MATCH(Warehouses!$B$4,CPI!$A$2:$A$5,0),MATCH(I5,CPI!$B$1:$H$1,0))+INDEX(Scenarios!$B$2:$B$3,MATCH(Inputs!$B$3,Scenarios!$A$2:$A$3,0))))^(I$3/4)*(1+Inputs!$B$9)))) -> 1155002.1 | J8: =IF(J$3<=Warehouses!$G$4,0,IF(J4<=Warehouses!$F$4,Warehouses!$D$4*Warehouses!$E$4/4*(1+(INDEX(CPI!$B$2:$H$5,MATCH(Warehouses!$B$4,CPI!$A$2:$A$5,0),MATCH(J5,CPI!$B$1:$H$1,0))+INDEX(Scenarios!$B$2:$B$3,MATCH(Inputs!$B$3,Scenarios!$A$2:$A$3,0))))^(J$3/4),IF(J4<=EOMONTH(Warehouses!$F$4,3*(Inputs!$B$8+INDEX(Scenarios!$C$2:$C$3,MATCH(Inputs!$B$3,Scenarios!$A$2:$A$3,0)))),0,Warehouses!$D$4*Warehouses!$E$4/4*(1+(INDEX(CPI!$B$2:$H$5,MATCH(Warehouses!$B$4,CPI!$A$2:$A$5,0),MATCH(J5,CPI!$B$1:$H$1,0))+INDEX(Scenarios!$B$2:$B$3,MATCH(Inputs!$B$3,Scenarios!$A$2:$A$3,0))))^(J$3/4)*(1+Inputs!$B$9)))) -> 1161018.7 | ... AD8: =IF(AD$3<=Warehouses!$G$4,0,IF(AD4<=Warehouses!$F$4,Warehouses!$D$4*Warehouses!$E$4/4*(1+(INDEX(CPI!$B$2:$H$5,MATCH(Warehouses!$B$4,CPI!$A$2:$A$5,0),MATCH(AD5,CPI!$B$1:$H$1,0))+INDEX(Scenarios!$B$2:$B$3,MATCH(Inputs!$B$3,Scenarios!$A$2:$A$3,0))))^(AD$3/4),IF(AD4<=EOMONTH(Warehouses!$F$4,3*(Inputs!$B$8+INDEX(Scenarios!$C$2:$C$3,MATCH(Inputs!$B$3,Scenarios!$A$2:$A$3,0)))),0,Warehouses!$D$4*Warehouses!$E$4/4*(1+(INDEX(CPI!$B$2:$H$5,MATCH(Warehouses!$B$4,CPI!$A$2:$A$5,0),MATCH(AD5,CPI!$B$1:$H$1,0))+INDEX(Scenarios!$B$2:$B$3,MATCH(Inputs!$B$3,Scenarios!$A$2:$A$3,0))))^(AD$3/4)*(1+Inputs!$B$9)))) -> 1381696.6
A9: Rent 4 | B9: =0 -> 0 | C9: =IF(C$3<=Warehouses!$G$5,0,IF(C4<=Warehouses!$F$5,Warehouses!$D$5*Warehouses!$E$5/4*(1+(INDEX(CPI!$B$2:$H$5,MATCH(Warehouses!$B$5,CPI!$A$2:$A$5,0),MATCH(C5,CPI!$B$1:$H$1,0))+INDEX(Scenarios!$B$2:$B$3,MATCH(Inputs!$B$3,Scenarios!$A$2:$A$3,0))))^(C$3/4),IF(C4<=EOMONTH(Warehouses!$F$5,3*(Inputs!$B$8+INDEX(Scenarios!$C$2:$C$3,MATCH(Inputs!$B$3,Scenarios!$A$2:$A$3,0)))),0,Warehouses!$D$5*Warehouses!$E$5/4*(1+(INDEX(CPI!$B$2:$H$5,MATCH(Warehouses!$B$5,CPI!$A$2:$A$5,0),MATCH(C5,CPI!$B$1:$H$1,0))+INDEX(Scenarios!$B$2:$B$3,MATCH(Inputs!$B$3,Scenarios!$A$2:$A$3,0))))^(C$3/4)*(1+Inputs!$B$9)))) -> 0 | D9: =IF(D$3<=Warehouses!$G$5,0,IF(D4<=Warehouses!$F$5,Warehouses!$D$5*Warehouses!$E$5/4*(1+(INDEX(CPI!$B$2:$H$5,MATCH(Warehouses!$B$5,CPI!$A$2:$A$5,0),MATCH(D5,CPI!$B$1:$H$1,0))+INDEX(Scenarios!$B$2:$B$3,MATCH(Inputs!$B$3,Scenarios!$A$2:$A$3,0))))^(D$3/4),IF(D4<=EOMONTH(Warehouses!$F$5,3*(Inputs!$B$8+INDEX(Scenarios!$C$2:$C$3,MATCH(Inputs!$B$3,Scenarios!$A$2:$A$3,0)))),0,Warehouses!$D$5*Warehouses!$E$5/4*(1+(INDEX(CPI!$B$2:$H$5,MATCH(Warehouses!$B$5,CPI!$A$2:$A$5,0),MATCH(D5,CPI!$B$1:$H$1,0))+INDEX(Scenarios!$B$2:$B$3,MATCH(Inputs!$B$3,Scenarios!$A$2:$A$3,0))))^(D$3/4)*(1+Inputs!$B$9)))) -> 0 | E9: =IF(E$3<=Warehouses!$G$5,0,IF(E4<=Warehouses!$F$5,Warehouses!$D$5*Warehouses!$E$5/4*(1+(INDEX(CPI!$B$2:$H$5,MATCH(Warehouses!$B$5,CPI!$A$2:$A$5,0),MATCH(E5,CPI!$B$1:$H$1,0))+INDEX(Scenarios!$B$2:$B$3,MATCH(Inputs!$B$3,Scenarios!$A$2:$A$3,0))))^(E$3/4),IF(E4<=EOMONTH(Warehouses!$F$5,3*(Inputs!$B$8+INDEX(Scenarios!$C$2:$C$3,MATCH(Inputs!$B$3,Scenarios!$A$2:$A$3,0)))),0,Warehouses!$D$5*Warehouses!$E$5/4*(1+(INDEX(CPI!$B$2:$H$5,MATCH(Warehouses!$B$5,CPI!$A$2:$A$5,0),MATCH(E5,CPI!$B$1:$H$1,0))+INDEX(Scenarios!$B$2:$B$3,MATCH(Inputs!$B$3,Scenarios!$A$2:$A$3,0))))^(E$3/4)*(1+Inputs!$B$9)))) -> 1027592.8 | F9: =IF(F$3<=Warehouses!$G$5,0,IF(F4<=Warehouses!$F$5,Warehouses!$D$5*Warehouses!$E$5/4*(1+(INDEX(CPI!$B$2:$H$5,MATCH(Warehouses!$B$5,CPI!$A$2:$A$5,0),MATCH(F5,CPI!$B$1:$H$1,0))+INDEX(Scenarios!$B$2:$B$3,MATCH(Inputs!$B$3,Scenarios!$A$2:$A$3,0))))^(F$3/4),IF(F4<=EOMONTH(Warehouses!$F$5,3*(Inputs!$B$8+INDEX(Scenarios!$C$2:$C$3,MATCH(Inputs!$B$3,Scenarios!$A$2:$A$3,0)))),0,Warehouses!$D$5*Warehouses!$E$5/4*(1+(INDEX(CPI!$B$2:$H$5,MATCH(Warehouses!$B$5,CPI!$A$2:$A$5,0),MATCH(F5,CPI!$B$1:$H$1,0))+INDEX(Scenarios!$B$2:$B$3,MATCH(Inputs!$B$3,Scenarios!$A$2:$A$3,0))))^(F$3/4)*(1+Inputs!$B$9)))) -> 1034208 | G9: =IF(G$3<=Warehouses!$G$5,0,IF(G4<=Warehouses!$F$5,Warehouses!$D$5*Warehouses!$E$5/4*(1+(INDEX(CPI!$B$2:$H$5,MATCH(Warehouses!$B$5,CPI!$A$2:$A$5,0),MATCH(G5,CPI!$B$1:$H$1,0))+INDEX(Scenarios!$B$2:$B$3,MATCH(Inputs!$B$3,Scenarios!$A$2:$A$3,0))))^(G$3/4),IF(G4<=EOMONTH(Warehouses!$F$5,3*(Inputs!$B$8+INDEX(Scenarios!$C$2:$C$3,MATCH(Inputs!$B$3,Scenarios!$A$2:$A$3,0)))),0,Warehouses!$D$5*Warehouses!$E$5/4*(1+(INDEX(CPI!$B$2:$H$5,MATCH(Warehouses!$B$5,CPI!$A$2:$A$5,0),MATCH(G5,CPI!$B$1:$H$1,0))+INDEX(Scenarios!$B$2:$B$3,MATCH(Inputs!$B$3,Scenarios!$A$2:$A$3,0))))^(G$3/4)*(1+Inputs!$B$9)))) -> 1038330.2 | H9: =IF(H$3<=Warehouses!$G$5,0,IF(H4<=Warehouses!$F$5,Warehouses!$D$5*Warehouses!$E$5/4*(1+(INDEX(CPI!$B$2:$H$5,MATCH(Warehouses!$B$5,CPI!$A$2:$A$5,0),MATCH(H5,CPI!$B$1:$H$1,0))+INDEX(Scenarios!$B$2:$B$3,MATCH(Inputs!$B$3,Scenarios!$A$2:$A$3,0))))^(H$3/4),IF(H4<=EOMONTH(Warehouses!$F$5,3*(Inputs!$B$8+INDEX(Scenarios!$C$2:$C$3,MATCH(Inputs!$B$3,Scenarios!$A$2:$A$3,0)))),0,Warehouses!$D$5*Warehouses!$E$5/4*(1+(INDEX(CPI!$B$2:$H$5,MATCH(Warehouses!$B$5,CPI!$A$2:$A$5,0),MATCH(H5,CPI!$B$1:$H$1,0))+INDEX(Scenarios!$B$2:$B$3,MATCH(Inputs!$B$3,Scenarios!$A$2:$A$3,0))))^(H$3/4)*(1+Inputs!$B$9)))) -> 1044504.9 | I9: =IF(I$3<=Warehouses!$G$5,0,IF(I4<=Warehouses!$F$5,Warehouses!$D$5*Warehouses!$E$5/4*(1+(INDEX(CPI!$B$2:$H$5,MATCH(Warehouses!$B$5,CPI!$A$2:$A$5,0),MATCH(I5,CPI!$B$1:$H$1,0))+INDEX(Scenarios!$B$2:$B$3,MATCH(Inputs!$B$3,Scenarios!$A$2:$A$3,0))))^(I$3/4),IF(I4<=EOMONTH(Warehouses!$F$5,3*(Inputs!$B$8+INDEX(Scenarios!$C$2:$C$3,MATCH(Inputs!$B$3,Scenarios!$A$2:$A$3,0)))),0,Warehouses!$D$5*Warehouses!$E$5/4*(1+(INDEX(CPI!$B$2:$H$5,MATCH(Warehouses!$B$5,CPI!$A$2:$A$5,0),MATCH(I5,CPI!$B$1:$H$1,0))+INDEX(Scenarios!$B$2:$B$3,MATCH(Inputs!$B$3,Scenarios!$A$2:$A$3,0))))^(I$3/4)*(1+Inputs!$B$9)))) -> 1050716.3 | J9: =IF(J$3<=Warehouses!$G$5,0,IF(J4<=Warehouses!$F$5,Warehouses!$D$5*Warehouses!$E$5/4*(1+(INDEX(CPI!$B$2:$H$5,MATCH(Warehouses!$B$5,CPI!$A$2:$A$5,0),MATCH(J5,CPI!$B$1:$H$1,0))+INDEX(Scenarios!$B$2:$B$3,MATCH(Inputs!$B$3,Scenarios!$A$2:$A$3,0))))^(J$3/4),IF(J4<=EOMONTH(Warehouses!$F$5,3*(Inputs!$B$8+INDEX(Scenarios!$C$2:$C$3,MATCH(Inputs!$B$3,Scenarios!$A$2:$A$3,0)))),0,Warehouses!$D$5*Warehouses!$E$5/4*(1+(INDEX(CPI!$B$2:$H$5,MATCH(Warehouses!$B$5,CPI!$A$2:$A$5,0),MATCH(J5,CPI!$B$1:$H$1,0))+INDEX(Scenarios!$B$2:$B$3,MATCH(Inputs!$B$3,Scenarios!$A$2:$A$3,0))))^(J$3/4)*(1+Inputs!$B$9)))) -> 1056964.6 | ... AD9: =IF(AD$3<=Warehouses!$G$5,0,IF(AD4<=Warehouses!$F$5,Warehouses!$D$5*Warehouses!$E$5/4*(1+(INDEX(CPI!$B$2:$H$5,MATCH(Warehouses!$B$5,CPI!$A$2:$A$5,0),MATCH(AD5,CPI!$B$1:$H$1,0))+INDEX(Scenarios!$B$2:$B$3,MATCH(Inputs!$B$3,Scenarios!$A$2:$A$3,0))))^(AD$3/4),IF(AD4<=EOMONTH(Warehouses!$F$5,3*(Inputs!$B$8+INDEX(Scenarios!$C$2:$C$3,MATCH(Inputs!$B$3,Scenarios!$A$2:$A$3,0)))),0,Warehouses!$D$5*Warehouses!$E$5/4*(1+(INDEX(CPI!$B$2:$H$5,MATCH(Warehouses!$B$5,CPI!$A$2:$A$5,0),MATCH(AD5,CPI!$B$1:$H$1,0))+INDEX(Scenarios!$B$2:$B$3,MATCH(Inputs!$B$3,Scenarios!$A$2:$A$3,0))))^(AD$3/4)*(1+Inputs!$B$9)))) -> 1250505.2
A10: Rent 5 | B10: =0 -> 0 | C10: =IF(C$3<=Warehouses!$G$6,0,IF(C4<=Warehouses!$F$6,Warehouses!$D$6*Warehouses!$E$6/4*(1+(INDEX(CPI!$B$2:$H$5,MATCH(Warehouses!$B$6,CPI!$A$2:$A$5,0),MATCH(C5,CPI!$B$1:$H$1,0))+INDEX(Scenarios!$B$2:$B$3,MATCH(Inputs!$B$3,Scenarios!$A$2:$A$3,0))))^(C$3/4),IF(C4<=EOMONTH(Warehouses!$F$6,3*(Inputs!$B$8+INDEX(Scenarios!$C$2:$C$3,MATCH(Inputs!$B$3,Scenarios!$A$2:$A$3,0)))),0,Warehouses!$D$6*Warehouses!$E$6/4*(1+(INDEX(CPI!$B$2:$H$5,MATCH(Warehouses!$B$6,CPI!$A$2:$A$5,0),MATCH(C5,CPI!$B$1:$H$1,0))+INDEX(Scenarios!$B$2:$B$3,MATCH(Inputs!$B$3,Scenarios!$A$2:$A$3,0))))^(C$3/4)*(1+Inputs!$B$9)))) -> 715577.11 | D10: =IF(D$3<=Warehouses!$G$6,0,IF(D4<=Warehouses!$F$6,Warehouses!$D$6*Warehouses!$E$6/4*(1+(INDEX(CPI!$B$2:$H$5,MATCH(Warehouses!$B$6,CPI!$A$2:$A$5,0),MATCH(D5,CPI!$B$1:$H$1,0))+INDEX(Scenarios!$B$2:$B$3,MATCH(Inputs!$B$3,Scenarios!$A$2:$A$3,0))))^(D$3/4),IF(D4<=EOMONTH(Warehouses!$F$6,3*(Inputs!$B$8+INDEX(Scenarios!$C$2:$C$3,MATCH(Inputs!$B$3,Scenarios!$A$2:$A$3,0)))),0,Warehouses!$D$6*Warehouses!$E$6/4*(1+(INDEX(CPI!$B$2:$H$5,MATCH(Warehouses!$B$6,CPI!$A$2:$A$5,0),MATCH(D5,CPI!$B$1:$H$1,0))+INDEX(Scenarios!$B$2:$B$3,MATCH(Inputs!$B$3,Scenarios!$A$2:$A$3,0))))^(D$3/4)*(1+Inputs!$B$9)))) -> 720183.69 | E10: =IF(E$3<=Warehouses!$G$6,0,IF(E4<=Warehouses!$F$6,Warehouses!$D$6*Warehouses!$E$6/4*(1+(INDEX(CPI!$B$2:$H$5,MATCH(Warehouses!$B$6,CPI!$A$2:$A$5,0),MATCH(E5,CPI!$B$1:$H$1,0))+INDEX(Scenarios!$B$2:$B$3,MATCH(Inputs!$B$3,Scenarios!$A$2:$A$3,0))))^(E$3/4),IF(E4<=EOMONTH(Warehouses!$F$6,3*(Inputs!$B$8+INDEX(Scenarios!$C$2:$C$3,MATCH(Inputs!$B$3,Scenarios!$A$2:$A$3,0)))),0,Warehouses!$D$6*Warehouses!$E$6/4*(1+(INDEX(CPI!$B$2:$H$5,MATCH(Warehouses!$B$6,CPI!$A$2:$A$5,0),MATCH(E5,CPI!$B$1:$H$1,0))+INDEX(Scenarios!$B$2:$B$3,MATCH(Inputs!$B$3,Scenarios!$A$2:$A$3,0))))^(E$3/4)*(1+Inputs!$B$9)))) -> 724819.92 | F10: =IF(F$3<=Warehouses!$G$6,0,IF(F4<=Warehouses!$F$6,Warehouses!$D$6*Warehouses!$E$6/4*(1+(INDEX(CPI!$B$2:$H$5,MATCH(Warehouses!$B$6,CPI!$A$2:$A$5,0),MATCH(F5,CPI!$B$1:$H$1,0))+INDEX(Scenarios!$B$2:$B$3,MATCH(Inputs!$B$3,Scenarios!$A$2:$A$3,0))))^(F$3/4),IF(F4<=EOMONTH(Warehouses!$F$6,3*(Inputs!$B$8+INDEX(Scenarios!$C$2:$C$3,MATCH(Inputs!$B$3,Scenarios!$A$2:$A$3,0)))),0,Warehouses!$D$6*Warehouses!$E$6/4*(1+(INDEX(CPI!$B$2:$H$5,MATCH(Warehouses!$B$6,CPI!$A$2:$A$5,0),MATCH(F5,CPI!$B$1:$H$1,0))+INDEX(Scenarios!$B$2:$B$3,MATCH(Inputs!$B$3,Scenarios!$A$2:$A$3,0))))^(F$3/4)*(1+Inputs!$B$9)))) -> 729486 | G10: =IF(G$3<=Warehouses!$G$6,0,IF(G4<=Warehouses!$F$6,Warehouses!$D$6*Warehouses!$E$6/4*(1+(INDEX(CPI!$B$2:$H$5,MATCH(Warehouses!$B$6,CPI!$A$2:$A$5,0),MATCH(G5,CPI!$B$1:$H$1,0))+INDEX(Scenarios!$B$2:$B$3,MATCH(Inputs!$B$3,Scenarios!$A$2:$A$3,0))))^(G$3/4),IF(G4<=EOMONTH(Warehouses!$F$6,3*(Inputs!$B$8+INDEX(Scenarios!$C$2:$C$3,MATCH(Inputs!$B$3,Scenarios!$A$2:$A$3,0)))),0,Warehouses!$D$6*Warehouses!$E$6/4*(1+(INDEX(CPI!$B$2:$H$5,MATCH(Warehouses!$B$6,CPI!$A$2:$A$5,0),MATCH(G5,CPI!$B$1:$H$1,0))+INDEX(Scenarios!$B$2:$B$3,MATCH(Inputs!$B$3,Scenarios!$A$2:$A$3,0))))^(G$3/4)*(1+Inputs!$B$9)))) -> 732393.61 | H10: =IF(H$3<=Warehouses!$G$6,0,IF(H4<=Warehouses!$F$6,Warehouses!$D$6*Warehouses!$E$6/4*(1+(INDEX(CPI!$B$2:$H$5,MATCH(Warehouses!$B$6,CPI!$A$2:$A$5,0),MATCH(H5,CPI!$B$1:$H$1,0))+INDEX(Scenarios!$B$2:$B$3,MATCH(Inputs!$B$3,Scenarios!$A$2:$A$3,0))))^(H$3/4),IF(H4<=EOMONTH(Warehouses!$F$6,3*(Inputs!$B$8+INDEX(Scenarios!$C$2:$C$3,MATCH(Inputs!$B$3,Scenarios!$A$2:$A$3,0)))),0,Warehouses!$D$6*Warehouses!$E$6/4*(1+(INDEX(CPI!$B$2:$H$5,MATCH(Warehouses!$B$6,CPI!$A$2:$A$5,0),MATCH(H5,CPI!$B$1:$H$1,0))+INDEX(Scenarios!$B$2:$B$3,MATCH(Inputs!$B$3,Scenarios!$A$2:$A$3,0))))^(H$3/4)*(1+Inputs!$B$9)))) -> 736748.97 | I10: =IF(I$3<=Warehouses!$G$6,0,IF(I4<=Warehouses!$F$6,Warehouses!$D$6*Warehouses!$E$6/4*(1+(INDEX(CPI!$B$2:$H$5,MATCH(Warehouses!$B$6,CPI!$A$2:$A$5,0),MATCH(I5,CPI!$B$1:$H$1,0))+INDEX(Scenarios!$B$2:$B$3,MATCH(Inputs!$B$3,Scenarios!$A$2:$A$3,0))))^(I$3/4),IF(I4<=EOMONTH(Warehouses!$F$6,3*(Inputs!$B$8+INDEX(Scenarios!$C$2:$C$3,MATCH(Inputs!$B$3,Scenarios!$A$2:$A$3,0)))),0,Warehouses!$D$6*Warehouses!$E$6/4*(1+(INDEX(CPI!$B$2:$H$5,MATCH(Warehouses!$B$6,CPI!$A$2:$A$5,0),MATCH(I5,CPI!$B$1:$H$1,0))+INDEX(Scenarios!$B$2:$B$3,MATCH(Inputs!$B$3,Scenarios!$A$2:$A$3,0))))^(I$3/4)*(1+Inputs!$B$9)))) -> 741130.22 | J10: =IF(J$3<=Warehouses!$G$6,0,IF(J4<=Warehouses!$F$6,Warehouses!$D$6*Warehouses!$E$6/4*(1+(INDEX(CPI!$B$2:$H$5,MATCH(Warehouses!$B$6,CPI!$A$2:$A$5,0),MATCH(J5,CPI!$B$1:$H$1,0))+INDEX(Scenarios!$B$2:$B$3,MATCH(Inputs!$B$3,Scenarios!$A$2:$A$3,0))))^(J$3/4),IF(J4<=EOMONTH(Warehouses!$F$6,3*(Inputs!$B$8+INDEX(Scenarios!$C$2:$C$3,MATCH(Inputs!$B$3,Scenarios!$A$2:$A$3,0)))),0,Warehouses!$D$6*Warehouses!$E$6/4*(1+(INDEX(CPI!$B$2:$H$5,MATCH(Warehouses!$B$6,CPI!$A$2:$A$5,0),MATCH(J5,CPI!$B$1:$H$1,0))+INDEX(Scenarios!$B$2:$B$3,MATCH(Inputs!$B$3,Scenarios!$A$2:$A$3,0))))^(J$3/4)*(1+Inputs!$B$9)))) -> 745537.54 | ... AD10: =IF(AD$3<=Warehouses!$G$6,0,IF(AD4<=Warehouses!$F$6,Warehouses!$D$6*Warehouses!$E$6/4*(1+(INDEX(CPI!$B$2:$H$5,MATCH(Warehouses!$B$6,CPI!$A$2:$A$5,0),MATCH(AD5,CPI!$B$1:$H$1,0))+INDEX(Scenarios!$B$2:$B$3,MATCH(Inputs!$B$3,Scenarios!$A$2:$A$3,0))))^(AD$3/4),IF(AD4<=EOMONTH(Warehouses!$F$6,3*(Inputs!$B$8+INDEX(Scenarios!$C$2:$C$3,MATCH(Inputs!$B$3,Scenarios!$A$2:$A$3,0)))),0,Warehouses!$D$6*Warehouses!$E$6/4*(1+(INDEX(CPI!$B$2:$H$5,MATCH(Warehouses!$B$6,CPI!$A$2:$A$5,0),MATCH(AD5,CPI!$B$1:$H$1,0))+INDEX(Scenarios!$B$2:$B$3,MATCH(Inputs!$B$3,Scenarios!$A$2:$A$3,0))))^(AD$3/4)*(1+Inputs!$B$9)))) -> 882052.75
A11: Rent 6 | B11: =0 -> 0 | C11: =IF(C$3<=Warehouses!$G$7,0,IF(C4<=Warehouses!$F$7,Warehouses!$D$7*Warehouses!$E$7/4*(1+(INDEX(CPI!$B$2:$H$5,MATCH(Warehouses!$B$7,CPI!$A$2:$A$5,0),MATCH(C5,CPI!$B$1:$H$1,0))+INDEX(Scenarios!$B$2:$B$3,MATCH(Inputs!$B$3,Scenarios!$A$2:$A$3,0))))^(C$3/4),IF(C4<=EOMONTH(Warehouses!$F$7,3*(Inputs!$B$8+INDEX(Scenarios!$C$2:$C$3,MATCH(Inputs!$B$3,Scenarios!$A$2:$A$3,0)))),0,Warehouses!$D$7*Warehouses!$E$7/4*(1+(INDEX(CPI!$B$2:$H$5,MATCH(Warehouses!$B$7,CPI!$A$2:$A$5,0),MATCH(C5,CPI!$B$1:$H$1,0))+INDEX(Scenarios!$B$2:$B$3,MATCH(Inputs!$B$3,Scenarios!$A$2:$A$3,0))))^(C$3/4)*(1+Inputs!$B$9)))) -> 0 | D11: =IF(D$3<=Warehouses!$G$7,0,IF(D4<=Warehouses!$F$7,Warehouses!$D$7*Warehouses!$E$7/4*(1+(INDEX(CPI!$B$2:$H$5,MATCH(Warehouses!$B$7,CPI!$A$2:$A$5,0),MATCH(D5,CPI!$B$1:$H$1,0))+INDEX(Scenarios!$B$2:$B$3,MATCH(Inputs!$B$3,Scenarios!$A$2:$A$3,0))))^(D$3/4),IF(D4<=EOMONTH(Warehouses!$F$7,3*(Inputs!$B$8+INDEX(Scenarios!$C$2:$C$3,MATCH(Inputs!$B$3,Scenarios!$A$2:$A$3,0)))),0,Warehouses!$D$7*Warehouses!$E$7/4*(1+(INDEX(CPI!$B$2:$H$5,MATCH(Warehouses!$B$7,CPI!$A$2:$A$5,0),MATCH(D5,CPI!$B$1:$H$1,0))+INDEX(Scenarios!$B$2:$B$3,MATCH(Inputs!$B$3,Scenarios!$A$2:$A$3,0))))^(D$3/4)*(1+Inputs!$B$9)))) -> 869290.55 | E11: =IF(E$3<=Warehouses!$G$7,0,IF(E4<=Warehouses!$F$7,Warehouses!$D$7*Warehouses!$E$7/4*(1+(INDEX(CPI!$B$2:$H$5,MATCH(Warehouses!$B$7,CPI!$A$2:$A$5,0),MATCH(E5,CPI!$B$1:$H$1,0))+INDEX(Scenarios!$B$2:$B$3,MATCH(Inputs!$B$3,Scenarios!$A$2:$A$3,0))))^(E$3/4),IF(E4<=EOMONTH(Warehouses!$F$7,3*(Inputs!$B$8+INDEX(Scenarios!$C$2:$C$3,MATCH(Inputs!$B$3,Scenarios!$A$2:$A$3,0)))),0,Warehouses!$D$7*Warehouses!$E$7/4*(1+(INDEX(CPI!$B$2:$H$5,MATCH(Warehouses!$B$7,CPI!$A$2:$A$5,0),MATCH(E5,CPI!$B$1:$H$1,0))+INDEX(Scenarios!$B$2:$B$3,MATCH(Inputs!$B$3,Scenarios!$A$2:$A$3,0))))^(E$3/4)*(1+Inputs!$B$9)))) -> 878066.97 | F11: =IF(F$3<=Warehouses!$G$7,0,IF(F4<=Warehouses!$F$7,Warehouses!$D$7*Warehouses!$E$7/4*(1+(INDEX(CPI!$B$2:$H$5,MATCH(Warehouses!$B$7,CPI!$A$2:$A$5,0),MATCH(F5,CPI!$B$1:$H$1,0))+INDEX(Scenarios!$B$2:$B$3,MATCH(Inputs!$B$3,Scenarios!$A$2:$A$3,0))))^(F$3/4),IF(F4<=EOMONTH(Warehouses!$F$7,3*(Inputs!$B$8+INDEX(Scenarios!$C$2:$C$3,MATCH(Inputs!$B$3,Scenarios!$A$2:$A$3,0)))),0,Warehouses!$D$7*Warehouses!$E$7/4*(1+(INDEX(CPI!$B$2:$H$5,MATCH(Warehouses!$B$7,CPI!$A$2:$A$5,0),MATCH(F5,CPI!$B$1:$H$1,0))+INDEX(Scenarios!$B$2:$B$3,MATCH(Inputs!$B$3,Scenarios!$A$2:$A$3,0))))^(F$3/4)*(1+Inputs!$B$9)))) -> 886932 | G11: =IF(G$3<=Warehouses!$G$7,0,IF(G4<=Warehouses!$F$7,Warehouses!$D$7*Warehouses!$E$7/4*(1+(INDEX(CPI!$B$2:$H$5,MATCH(Warehouses!$B$7,CPI!$A$2:$A$5,0),MATCH(G5,CPI!$B$1:$H$1,0))+INDEX(Scenarios!$B$2:$B$3,MATCH(Inputs!$B$3,Scenarios!$A$2:$A$3,0))))^(G$3/4),IF(G4<=EOMONTH(Warehouses!$F$7,3*(Inputs!$B$8+INDEX(Scenarios!$C$2:$C$3,MATCH(Inputs!$B$3,Scenarios!$A$2:$A$3,0)))),0,Warehouses!$D$7*Warehouses!$E$7/4*(1+(INDEX(CPI!$B$2:$H$5,MATCH(Warehouses!$B$7,CPI!$A$2:$A$5,0),MATCH(G5,CPI!$B$1:$H$1,0))+INDEX(Scenarios!$B$2:$B$3,MATCH(Inputs!$B$3,Scenarios!$A$2:$A$3,0))))^(G$3/4)*(1+Inputs!$B$9)))) -> 889436.67 | H11: =IF(H$3<=Warehouses!$G$7,0,IF(H4<=Warehouses!$F$7,Warehouses!$D$7*Warehouses!$E$7/4*(1+(INDEX(CPI!$B$2:$H$5,MATCH(Warehouses!$B$7,CPI!$A$2:$A$5,0),MATCH(H5,CPI!$B$1:$H$1,0))+INDEX(Scenarios!$B$2:$B$3,MATCH(Inputs!$B$3,Scenarios!$A$2:$A$3,0))))^(H$3/4),IF(H4<=EOMONTH(Warehouses!$F$7,3*(Inputs!$B$8+INDEX(Scenarios!$C$2:$C$3,MATCH(Inputs!$B$3,Scenarios!$A$2:$A$3,0)))),0,Warehouses!$D$7*Warehouses!$E$7/4*(1+(INDEX(CPI!$B$2:$H$5,MATCH(Warehouses!$B$7,CPI!$A$2:$A$5,0),MATCH(H5,CPI!$B$1:$H$1,0))+INDEX(Scenarios!$B$2:$B$3,MATCH(Inputs!$B$3,Scenarios!$A$2:$A$3,0))))^(H$3/4)*(1+Inputs!$B$9)))) -> 897119.13 | I11: =IF(I$3<=Warehouses!$G$7,0,IF(I4<=Warehouses!$F$7,Warehouses!$D$7*Warehouses!$E$7/4*(1+(INDEX(CPI!$B$2:$H$5,MATCH(Warehouses!$B$7,CPI!$A$2:$A$5,0),MATCH(I5,CPI!$B$1:$H$1,0))+INDEX(Scenarios!$B$2:$B$3,MATCH(Inputs!$B$3,Scenarios!$A$2:$A$3,0))))^(I$3/4),IF(I4<=EOMONTH(Warehouses!$F$7,3*(Inputs!$B$8+INDEX(Scenarios!$C$2:$C$3,MATCH(Inputs!$B$3,Scenarios!$A$2:$A$3,0)))),0,Warehouses!$D$7*Warehouses!$E$7/4*(1+(INDEX(CPI!$B$2:$H$5,MATCH(Warehouses!$B$7,CPI!$A$2:$A$5,0),MATCH(I5,CPI!$B$1:$H$1,0))+INDEX(Scenarios!$B$2:$B$3,MATCH(Inputs!$B$3,Scenarios!$A$2:$A$3,0))))^(I$3/4)*(1+Inputs!$B$9)))) -> 904867.95 | J11: =IF(J$3<=Warehouses!$G$7,0,IF(J4<=Warehouses!$F$7,Warehouses!$D$7*Warehouses!$E$7/4*(1+(INDEX(CPI!$B$2:$H$5,MATCH(Warehouses!$B$7,CPI!$A$2:$A$5,0),MATCH(J5,CPI!$B$1:$H$1,0))+INDEX(Scenarios!$B$2:$B$3,MATCH(Inputs!$B$3,Scenarios!$A$2:$A$3,0))))^(J$3/4),IF(J4<=EOMONTH(Warehouses!$F$7,3*(Inputs!$B$8+INDEX(Scenarios!$C$2:$C$3,MATCH(Inputs!$B$3,Scenarios!$A$2:$A$3,0)))),0,Warehouses!$D$7*Warehouses!$E$7/4*(1+(INDEX(CPI!$B$2:$H$5,MATCH(Warehouses!$B$7,CPI!$A$2:$A$5,0),MATCH(J5,CPI!$B$1:$H$1,0))+INDEX(Scenarios!$B$2:$B$3,MATCH(Inputs!$B$3,Scenarios!$A$2:$A$3,0))))^(J$3/4)*(1+Inputs!$B$9)))) -> 912683.7 | ... AD11: =IF(AD$3<=Warehouses!$G$7,0,IF(AD4<=Warehouses!$F$7,Warehouses!$D$7*Warehouses!$E$7/4*(1+(INDEX(CPI!$B$2:$H$5,MATCH(Warehouses!$B$7,CPI!$A$2:$A$5,0),MATCH(AD5,CPI!$B$1:$H$1,0))+INDEX(Scenarios!$B$2:$B$3,MATCH(Inputs!$B$3,Scenarios!$A$2:$A$3,0))))^(AD$3/4),IF(AD4<=EOMONTH(Warehouses!$F$7,3*(Inputs!$B$8+INDEX(Scenarios!$C$2:$C$3,MATCH(Inputs!$B$3,Scenarios!$A$2:$A$3,0)))),0,Warehouses!$D$7*Warehouses!$E$7/4*(1+(INDEX(CPI!$B$2:$H$5,MATCH(Warehouses!$B$7,CPI!$A$2:$A$5,0),MATCH(AD5,CPI!$B$1:$H$1,0))+INDEX(Scenarios!$B$2:$B$3,MATCH(Inputs!$B$3,Scenarios!$A$2:$A$3,0))))^(AD$3/4)*(1+Inputs!$B$9)))) -> 1093781.1
A12: Rent 7 | B12: =0 -> 0 | C12: =IF(C$3<=Warehouses!$G$8,0,IF(C4<=Warehouses!$F$8,Warehouses!$D$8*Warehouses!$E$8/4*(1+(INDEX(CPI!$B$2:$H$5,MATCH(Warehouses!$B$8,CPI!$A$2:$A$5,0),MATCH(C5,CPI!$B$1:$H$1,0))+INDEX(Scenarios!$B$2:$B$3,MATCH(Inputs!$B$3,Scenarios!$A$2:$A$3,0))))^(C$3/4),IF(C4<=EOMONTH(Warehouses!$F$8,3*(Inputs!$B$8+INDEX(Scenarios!$C$2:$C$3,MATCH(Inputs!$B$3,Scenarios!$A$2:$A$3,0)))),0,Warehouses!$D$8*Warehouses!$E$8/4*(1+(INDEX(CPI!$B$2:$H$5,MATCH(Warehouses!$B$8,CPI!$A$2:$A$5,0),MATCH(C5,CPI!$B$1:$H$1,0))+INDEX(Scenarios!$B$2:$B$3,MATCH(Inputs!$B$3,Scenarios!$A$2:$A$3,0))))^(C$3/4)*(1+Inputs!$B$9)))) -> 604037.45 | D12: =IF(D$3<=Warehouses!$G$8,0,IF(D4<=Warehouses!$F$8,Warehouses!$D$8*Warehouses!$E$8/4*(1+(INDEX(CPI!$B$2:$H$5,MATCH(Warehouses!$B$8,CPI!$A$2:$A$5,0),MATCH(D5,CPI!$B$1:$H$1,0))+INDEX(Scenarios!$B$2:$B$3,MATCH(Inputs!$B$3,Scenarios!$A$2:$A$3,0))))^(D$3/4),IF(D4<=EOMONTH(Warehouses!$F$8,3*(Inputs!$B$8+INDEX(Scenarios!$C$2:$C$3,MATCH(Inputs!$B$3,Scenarios!$A$2:$A$3,0)))),0,Warehouses!$D$8*Warehouses!$E$8/4*(1+(INDEX(CPI!$B$2:$H$5,MATCH(Warehouses!$B$8,CPI!$A$2:$A$5,0),MATCH(D5,CPI!$B$1:$H$1,0))+INDEX(Scenarios!$B$2:$B$3,MATCH(Inputs!$B$3,Scenarios!$A$2:$A$3,0))))^(D$3/4)*(1+Inputs!$B$9)))) -> 610135.86 | E12: =IF(E$3<=Warehouses!$G$8,0,IF(E4<=Warehouses!$F$8,Warehouses!$D$8*Warehouses!$E$8/4*(1+(INDEX(CPI!$B$2:$H$5,MATCH(Warehouses!$B$8,CPI!$A$2:$A$5,0),MATCH(E5,CPI!$B$1:$H$1,0))+INDEX(Scenarios!$B$2:$B$3,MATCH(Inputs!$B$3,Scenarios!$A$2:$A$3,0))))^(E$3/4),IF(E4<=EOMONTH(Warehouses!$F$8,3*(Inputs!$B$8+INDEX(Scenarios!$C$2:$C$3,MATCH(Inputs!$B$3,Scenarios!$A$2:$A$3,0)))),0,Warehouses!$D$8*Warehouses!$E$8/4*(1+(INDEX(CPI!$B$2:$H$5,MATCH(Warehouses!$B$8,CPI!$A$2:$A$5,0),MATCH(E5,CPI!$B$1:$H$1,0))+INDEX(Scenarios!$B$2:$B$3,MATCH(Inputs!$B$3,Scenarios!$A$2:$A$3,0))))^(E$3/4)*(1+Inputs!$B$9)))) -> 616295.83 | F12: =IF(F$3<=Warehouses!$G$8,0,IF(F4<=Warehouses!$F$8,Warehouses!$D$8*Warehouses!$E$8/4*(1+(INDEX(CPI!$B$2:$H$5,MATCH(Warehouses!$B$8,CPI!$A$2:$A$5,0),MATCH(F5,CPI!$B$1:$H$1,0))+INDEX(Scenarios!$B$2:$B$3,MATCH(Inputs!$B$3,Scenarios!$A$2:$A$3,0))))^(F$3/4),IF(F4<=EOMONTH(Warehouses!$F$8,3*(Inputs!$B$8+INDEX(Scenarios!$C$2:$C$3,MATCH(Inputs!$B$3,Scenarios!$A$2:$A$3,0)))),0,Warehouses!$D$8*Warehouses!$E$8/4*(1+(INDEX(CPI!$B$2:$H$5,MATCH(Warehouses!$B$8,CPI!$A$2:$A$5,0),MATCH(F5,CPI!$B$1:$H$1,0))+INDEX(Scenarios!$B$2:$B$3,MATCH(Inputs!$B$3,Scenarios!$A$2:$A$3,0))))^(F$3/4)*(1+Inputs!$B$9)))) -> 622518 | G12: =IF(G$3<=Warehouses!$G$8,0,IF(G4<=Warehouses!$F$8,Warehouses!$D$8*Warehouses!$E$8/4*(1+(INDEX(CPI!$B$2:$H$5,MATCH(Warehouses!$B$8,CPI!$A$2:$A$5,0),MATCH(G5,CPI!$B$1:$H$1,0))+INDEX(Scenarios!$B$2:$B$3,MATCH(Inputs!$B$3,Scenarios!$A$2:$A$3,0))))^(G$3/4),IF(G4<=EOMONTH(Warehouses!$F$8,3*(Inputs!$B$8+INDEX(Scenarios!$C$2:$C$3,MATCH(Inputs!$B$3,Scenarios!$A$2:$A$3,0)))),0,Warehouses!$D$8*Warehouses!$E$8/4*(1+(INDEX(CPI!$B$2:$H$5,MATCH(Warehouses!$B$8,CPI!$A$2:$A$5,0),MATCH(G5,CPI!$B$1:$H$1,0))+INDEX(Scenarios!$B$2:$B$3,MATCH(Inputs!$B$3,Scenarios!$A$2:$A$3,0))))^(G$3/4)*(1+Inputs!$B$9)))) -> 0 | H12: =IF(H$3<=Warehouses!$G$8,0,IF(H4<=Warehouses!$F$8,Warehouses!$D$8*Warehouses!$E$8/4*(1+(INDEX(CPI!$B$2:$H$5,MATCH(Warehouses!$B$8,CPI!$A$2:$A$5,0),MATCH(H5,CPI!$B$1:$H$1,0))+INDEX(Scenarios!$B$2:$B$3,MATCH(Inputs!$B$3,Scenarios!$A$2:$A$3,0))))^(H$3/4),IF(H4<=EOMONTH(Warehouses!$F$8,3*(Inputs!$B$8+INDEX(Scenarios!$C$2:$C$3,MATCH(Inputs!$B$3,Scenarios!$A$2:$A$3,0)))),0,Warehouses!$D$8*Warehouses!$E$8/4*(1+(INDEX(CPI!$B$2:$H$5,MATCH(Warehouses!$B$8,CPI!$A$2:$A$5,0),MATCH(H5,CPI!$B$1:$H$1,0))+INDEX(Scenarios!$B$2:$B$3,MATCH(Inputs!$B$3,Scenarios!$A$2:$A$3,0))))^(H$3/4)*(1+Inputs!$B$9)))) -> 0 | I12: =IF(I$3<=Warehouses!$G$8,0,IF(I4<=Warehouses!$F$8,Warehouses!$D$8*Warehouses!$E$8/4*(1+(INDEX(CPI!$B$2:$H$5,MATCH(Warehouses!$B$8,CPI!$A$2:$A$5,0),MATCH(I5,CPI!$B$1:$H$1,0))+INDEX(Scenarios!$B$2:$B$3,MATCH(Inputs!$B$3,Scenarios!$A$2:$A$3,0))))^(I$3/4),IF(I4<=EOMONTH(Warehouses!$F$8,3*(Inputs!$B$8+INDEX(Scenarios!$C$2:$C$3,MATCH(Inputs!$B$3,Scenarios!$A$2:$A$3,0)))),0,Warehouses!$D$8*Warehouses!$E$8/4*(1+(INDEX(CPI!$B$2:$H$5,MATCH(Warehouses!$B$8,CPI!$A$2:$A$5,0),MATCH(I5,CPI!$B$1:$H$1,0))+INDEX(Scenarios!$B$2:$B$3,MATCH(Inputs!$B$3,Scenarios!$A$2:$A$3,0))))^(I$3/4)*(1+Inputs!$B$9)))) -> 685915.4 | J12: =IF(J$3<=Warehouses!$G$8,0,IF(J4<=Warehouses!$F$8,Warehouses!$D$8*Warehouses!$E$8/4*(1+(INDEX(CPI!$B$2:$H$5,MATCH(Warehouses!$B$8,CPI!$A$2:$A$5,0),MATCH(J5,CPI!$B$1:$H$1,0))+INDEX(Scenarios!$B$2:$B$3,MATCH(Inputs!$B$3,Scenarios!$A$2:$A$3,0))))^(J$3/4),IF(J4<=EOMONTH(Warehouses!$F$8,3*(Inputs!$B$8+INDEX(Scenarios!$C$2:$C$3,MATCH(Inputs!$B$3,Scenarios!$A$2:$A$3,0)))),0,Warehouses!$D$8*Warehouses!$E$8/4*(1+(INDEX(CPI!$B$2:$H$5,MATCH(Warehouses!$B$8,CPI!$A$2:$A$5,0),MATCH(J5,CPI!$B$1:$H$1,0))+INDEX(Scenarios!$B$2:$B$3,MATCH(Inputs!$B$3,Scenarios!$A$2:$A$3,0))))^(J$3/4)*(1+Inputs!$B$9)))) -> 691839.95 | ... AD12: =IF(AD$3<=Warehouses!$G$8,0,IF(AD4<=Warehouses!$F$8,Warehouses!$D$8*Warehouses!$E$8/4*(1+(INDEX(CPI!$B$2:$H$5,MATCH(Warehouses!$B$8,CPI!$A$2:$A$5,0),MATCH(AD5,CPI!$B$1:$H$1,0))+INDEX(Scenarios!$B$2:$B$3,MATCH(Inputs!$B$3,Scenarios!$A$2:$A$3,0))))^(AD$3/4),IF(AD4<=EOMONTH(Warehouses!$F$8,3*(Inputs!$B$8+INDEX(Scenarios!$C$2:$C$3,MATCH(Inputs!$B$3,Scenarios!$A$2:$A$3,0)))),0,Warehouses!$D$8*Warehouses!$E$8/4*(1+(INDEX(CPI!$B$2:$H$5,MATCH(Warehouses!$B$8,CPI!$A$2:$A$5,0),MATCH(AD5,CPI!$B$1:$H$1,0))+INDEX(Scenarios!$B$2:$B$3,MATCH(Inputs!$B$3,Scenarios!$A$2:$A$3,0))))^(AD$3/4)*(1+Inputs!$B$9)))) -> 767700.81
A13: Rent 8 | B13: =0 -> 0 | C13: =IF(C$3<=Warehouses!$G$9,0,IF(C4<=Warehouses!$F$9,Warehouses!$D$9*Warehouses!$E$9/4*(1+(INDEX(CPI!$B$2:$H$5,MATCH(Warehouses!$B$9,CPI!$A$2:$A$5,0),MATCH(C5,CPI!$B$1:$H$1,0))+INDEX(Scenarios!$B$2:$B$3,MATCH(Inputs!$B$3,Scenarios!$A$2:$A$3,0))))^(C$3/4),IF(C4<=EOMONTH(Warehouses!$F$9,3*(Inputs!$B$8+INDEX(Scenarios!$C$2:$C$3,MATCH(Inputs!$B$3,Scenarios!$A$2:$A$3,0)))),0,Warehouses!$D$9*Warehouses!$E$9/4*(1+(INDEX(CPI!$B$2:$H$5,MATCH(Warehouses!$B$9,CPI!$A$2:$A$5,0),MATCH(C5,CPI!$B$1:$H$1,0))+INDEX(Scenarios!$B$2:$B$3,MATCH(Inputs!$B$3,Scenarios!$A$2:$A$3,0))))^(C$3/4)*(1+Inputs!$B$9)))) -> 0 | D13: =IF(D$3<=Warehouses!$G$9,0,IF(D4<=Warehouses!$F$9,Warehouses!$D$9*Warehouses!$E$9/4*(1+(INDEX(CPI!$B$2:$H$5,MATCH(Warehouses!$B$9,CPI!$A$2:$A$5,0),MATCH(D5,CPI!$B$1:$H$1,0))+INDEX(Scenarios!$B$2:$B$3,MATCH(Inputs!$B$3,Scenarios!$A$2:$A$3,0))))^(D$3/4),IF(D4<=EOMONTH(Warehouses!$F$9,3*(Inputs!$B$8+INDEX(Scenarios!$C$2:$C$3,MATCH(Inputs!$B$3,Scenarios!$A$2:$A$3,0)))),0,Warehouses!$D$9*Warehouses!$E$9/4*(1+(INDEX(CPI!$B$2:$H$5,MATCH(Warehouses!$B$9,CPI!$A$2:$A$5,0),MATCH(D5,CPI!$B$1:$H$1,0))+INDEX(Scenarios!$B$2:$B$3,MATCH(Inputs!$B$3,Scenarios!$A$2:$A$3,0))))^(D$3/4)*(1+Inputs!$B$9)))) -> 545026.31 | E13: =IF(E$3<=Warehouses!$G$9,0,IF(E4<=Warehouses!$F$9,Warehouses!$D$9*Warehouses!$E$9/4*(1+(INDEX(CPI!$B$2:$H$5,MATCH(Warehouses!$B$9,CPI!$A$2:$A$5,0),MATCH(E5,CPI!$B$1:$H$1,0))+INDEX(Scenarios!$B$2:$B$3,MATCH(Inputs!$B$3,Scenarios!$A$2:$A$3,0))))^(E$3/4),IF(E4<=EOMONTH(Warehouses!$F$9,3*(Inputs!$B$8+INDEX(Scenarios!$C$2:$C$3,MATCH(Inputs!$B$3,Scenarios!$A$2:$A$3,0)))),0,Warehouses!$D$9*Warehouses!$E$9/4*(1+(INDEX(CPI!$B$2:$H$5,MATCH(Warehouses!$B$9,CPI!$A$2:$A$5,0),MATCH(E5,CPI!$B$1:$H$1,0))+INDEX(Scenarios!$B$2:$B$3,MATCH(Inputs!$B$3,Scenarios!$A$2:$A$3,0))))^(E$3/4)*(1+Inputs!$B$9)))) -> 549468.18 | F13: =IF(F$3<=Warehouses!$G$9,0,IF(F4<=Warehouses!$F$9,Warehouses!$D$9*Warehouses!$E$9/4*(1+(INDEX(CPI!$B$2:$H$5,MATCH(Warehouses!$B$9,CPI!$A$2:$A$5,0),MATCH(F5,CPI!$B$1:$H$1,0))+INDEX(Scenarios!$B$2:$B$3,MATCH(Inputs!$B$3,Scenarios!$A$2:$A$3,0))))^(F$3/4),IF(F4<=EOMONTH(Warehouses!$F$9,3*(Inputs!$B$8+INDEX(Scenarios!$C$2:$C$3,MATCH(Inputs!$B$3,Scenarios!$A$2:$A$3,0)))),0,Warehouses!$D$9*Warehouses!$E$9/4*(1+(INDEX(CPI!$B$2:$H$5,MATCH(Warehouses!$B$9,CPI!$A$2:$A$5,0),MATCH(F5,CPI!$B$1:$H$1,0))+INDEX(Scenarios!$B$2:$B$3,MATCH(Inputs!$B$3,Scenarios!$A$2:$A$3,0))))^(F$3/4)*(1+Inputs!$B$9)))) -> 553946.25 | G13: =IF(G$3<=Warehouses!$G$9,0,IF(G4<=Warehouses!$F$9,Warehouses!$D$9*Warehouses!$E$9/4*(1+(INDEX(CPI!$B$2:$H$5,MATCH(Warehouses!$B$9,CPI!$A$2:$A$5,0),MATCH(G5,CPI!$B$1:$H$1,0))+INDEX(Scenarios!$B$2:$B$3,MATCH(Inputs!$B$3,Scenarios!$A$2:$A$3,0))))^(G$3/4),IF(G4<=EOMONTH(Warehouses!$F$9,3*(Inputs!$B$8+INDEX(Scenarios!$C$2:$C$3,MATCH(Inputs!$B$3,Scenarios!$A$2:$A$3,0)))),0,Warehouses!$D$9*Warehouses!$E$9/4*(1+(INDEX(CPI!$B$2:$H$5,MATCH(Warehouses!$B$9,CPI!$A$2:$A$5,0),MATCH(G5,CPI!$B$1:$H$1,0))+INDEX(Scenarios!$B$2:$B$3,MATCH(Inputs!$B$3,Scenarios!$A$2:$A$3,0))))^(G$3/4)*(1+Inputs!$B$9)))) -> 555759.02 | H13: =IF(H$3<=Warehouses!$G$9,0,IF(H4<=Warehouses!$F$9,Warehouses!$D$9*Warehouses!$E$9/4*(1+(INDEX(CPI!$B$2:$H$5,MATCH(Warehouses!$B$9,CPI!$A$2:$A$5,0),MATCH(H5,CPI!$B$1:$H$1,0))+INDEX(Scenarios!$B$2:$B$3,MATCH(Inputs!$B$3,Scenarios!$A$2:$A$3,0))))^(H$3/4),IF(H4<=EOMONTH(Warehouses!$F$9,3*(Inputs!$B$8+INDEX(Scenarios!$C$2:$C$3,MATCH(Inputs!$B$3,Scenarios!$A$2:$A$3,0)))),0,Warehouses!$D$9*Warehouses!$E$9/4*(1+(INDEX(CPI!$B$2:$H$5,MATCH(Warehouses!$B$9,CPI!$A$2:$A$5,0),MATCH(H5,CPI!$B$1:$H$1,0))+INDEX(Scenarios!$B$2:$B$3,MATCH(Inputs!$B$3,Scenarios!$A$2:$A$3,0))))^(H$3/4)*(1+Inputs!$B$9)))) -> 559745.19 | I13: =IF(I$3<=Warehouses!$G$9,0,IF(I4<=Warehouses!$F$9,Warehouses!$D$9*Warehouses!$E$9/4*(1+(INDEX(CPI!$B$2:$H$5,MATCH(Warehouses!$B$9,CPI!$A$2:$A$5,0),MATCH(I5,CPI!$B$1:$H$1,0))+INDEX(Scenarios!$B$2:$B$3,MATCH(Inputs!$B$3,Scenarios!$A$2:$A$3,0))))^(I$3/4),IF(I4<=EOMONTH(Warehouses!$F$9,3*(Inputs!$B$8+INDEX(Scenarios!$C$2:$C$3,MATCH(Inputs!$B$3,Scenarios!$A$2:$A$3,0)))),0,Warehouses!$D$9*Warehouses!$E$9/4*(1+(INDEX(CPI!$B$2:$H$5,MATCH(Warehouses!$B$9,CPI!$A$2:$A$5,0),MATCH(I5,CPI!$B$1:$H$1,0))+INDEX(Scenarios!$B$2:$B$3,MATCH(Inputs!$B$3,Scenarios!$A$2:$A$3,0))))^(I$3/4)*(1+Inputs!$B$9)))) -> 563759.94 | J13: =IF(J$3<=Warehouses!$G$9,0,IF(J4<=Warehouses!$F$9,Warehouses!$D$9*Warehouses!$E$9/4*(1+(INDEX(CPI!$B$2:$H$5,MATCH(Warehouses!$B$9,CPI!$A$2:$A$5,0),MATCH(J5,CPI!$B$1:$H$1,0))+INDEX(Scenarios!$B$2:$B$3,MATCH(Inputs!$B$3,Scenarios!$A$2:$A$3,0))))^(J$3/4),IF(J4<=EOMONTH(Warehouses!$F$9,3*(Inputs!$B$8+INDEX(Scenarios!$C$2:$C$3,MATCH(Inputs!$B$3,Scenarios!$A$2:$A$3,0)))),0,Warehouses!$D$9*Warehouses!$E$9/4*(1+(INDEX(CPI!$B$2:$H$5,MATCH(Warehouses!$B$9,CPI!$A$2:$A$5,0),MATCH(J5,CPI!$B$1:$H$1,0))+INDEX(Scenarios!$B$2:$B$3,MATCH(Inputs!$B$3,Scenarios!$A$2:$A$3,0))))^(J$3/4)*(1+Inputs!$B$9)))) -> 567803.49 | ... AD13: =IF(AD$3<=Warehouses!$G$9,0,IF(AD4<=Warehouses!$F$9,Warehouses!$D$9*Warehouses!$E$9/4*(1+(INDEX(CPI!$B$2:$H$5,MATCH(Warehouses!$B$9,CPI!$A$2:$A$5,0),MATCH(AD5,CPI!$B$1:$H$1,0))+INDEX(Scenarios!$B$2:$B$3,MATCH(Inputs!$B$3,Scenarios!$A$2:$A$3,0))))^(AD$3/4),IF(AD4<=EOMONTH(Warehouses!$F$9,3*(Inputs!$B$8+INDEX(Scenarios!$C$2:$C$3,MATCH(Inputs!$B$3,Scenarios!$A$2:$A$3,0)))),0,Warehouses!$D$9*Warehouses!$E$9/4*(1+(INDEX(CPI!$B$2:$H$5,MATCH(Warehouses!$B$9,CPI!$A$2:$A$5,0),MATCH(AD5,CPI!$B$1:$H$1,0))+INDEX(Scenarios!$B$2:$B$3,MATCH(Inputs!$B$3,Scenarios!$A$2:$A$3,0))))^(AD$3/4)*(1+Inputs!$B$9)))) -> 674446.23
A14: Gross rent | B14: =B6+B7+B8+B9+B10+B11+B12+B13 -> 0 | C14: =C6+C7+C8+C9+C10+C11+C12+C13 -> 3655035.6 | D14: =D6+D7+D8+D9+D10+D11+D12+D13 -> 5838871.5 | E14: =E6+E7+E8+E9+E10+E11+E12+E13 -> 6907358.5 | F14: =F6+F7+F8+F9+F10+F11+F12+F13 -> 6955176.8 | G14: =G6+G7+G8+G9+G10+G11+G12+G13 -> 6357224 | H14: =H6+H7+H8+H9+H10+H11+H12+H13 -> 6395786.2 | I14: =I6+I7+I8+I9+I10+I11+I12+I13 -> 7120506.6 | ... AD14: =AD6+AD7+AD8+AD9+AD10+AD11+AD12+AD13 -> 8465592.9
A15: Costs | B15: =B14*Inputs!$B$7 -> 0 | C15: =C14*Inputs!$B$7 -> 164476.6 | D15: =D14*Inputs!$B$7 -> 262749.22 | E15: =E14*Inputs!$B$7 -> 310831.13 | F15: =F14*Inputs!$B$7 -> 312982.95 | G15: =G14*Inputs!$B$7 -> 286075.08 | H15: =H14*Inputs!$B$7 -> 287810.38 | I15: =I14*Inputs!$B$7 -> 320422.8 | ... AD15: =AD14*Inputs!$B$7 -> 380951.68
A16: NOI | B16: =B14-B15 -> 0 | C16: =C14-C15 -> 3490559 | D16: =D14-D15 -> 5576122.3 | E16: =E14-E15 -> 6596527.3 | F16: =F14-F15 -> 6642193.8 | G16: =G14-G15 -> 6071148.9 | H16: =H14-H15 -> 6107975.8 | I16: =I14-I15 -> 6800083.8 | ... AD16: =AD14-AD15 -> 8084641.2
A17: Cash flow | B17: =-Inputs!$B$5 -> -318000000 | C17: =C16+IF(C$3=28,SUM(B16:C16)/(Inputs!$B$6+INDEX(Scenarios!$D$2:$D$3,MATCH(Inputs!$B$3,Scenarios!$A$2:$A$3,0))),0) -> 3490559 | D17: =D16+IF(D$3=28,SUM(B16:D16)/(Inputs!$B$6+INDEX(Scenarios!$D$2:$D$3,MATCH(Inputs!$B$3,Scenarios!$A$2:$A$3,0))),0) -> 5576122.3 | E17: =E16+IF(E$3=28,SUM(B16:E16)/(Inputs!$B$6+INDEX(Scenarios!$D$2:$D$3,MATCH(Inputs!$B$3,Scenarios!$A$2:$A$3,0))),0) -> 6596527.3 | F17: =F16+IF(F$3=28,SUM(C16:F16)/(Inputs!$B$6+INDEX(Scenarios!$D$2:$D$3,MATCH(Inputs!$B$3,Scenarios!$A$2:$A$3,0))),0) -> 6642193.8 | G17: =G16+IF(G$3=28,SUM(D16:G16)/(Inputs!$B$6+INDEX(Scenarios!$D$2:$D$3,MATCH(Inputs!$B$3,Scenarios!$A$2:$A$3,0))),0) -> 6071148.9 | H17: =H16+IF(H$3=28,SUM(E16:H16)/(Inputs!$B$6+INDEX(Scenarios!$D$2:$D$3,MATCH(Inputs!$B$3,Scenarios!$A$2:$A$3,0))),0) -> 6107975.8 | I17: =I16+IF(I$3=28,SUM(F16:I16)/(Inputs!$B$6+INDEX(Scenarios!$D$2:$D$3,MATCH(Inputs!$B$3,Scenarios!$A$2:$A$3,0))),0) -> 6800083.8 | J17: =J16+IF(J$3=28,SUM(G16:J16)/(Inputs!$B$6+INDEX(Scenarios!$D$2:$D$3,MATCH(Inputs!$B$3,Scenarios!$A$2:$A$3,0))),0) -> 6843033.9 | K17: =K16+IF(K$3=28,SUM(H16:K16)/(Inputs!$B$6+INDEX(Scenarios!$D$2:$D$3,MATCH(Inputs!$B$3,Scenarios!$A$2:$A$3,0))),0) -> 6118035.9 | L17: =L16+IF(L$3=28,SUM(I16:L16)/(Inputs!$B$6+INDEX(Scenarios!$D$2:$D$3,MATCH(Inputs!$B$3,Scenarios!$A$2:$A$3,0))),0) -> 6154182.7 | ... AD17: =AD16+IF(AD$3=28,SUM(AA16:AD16)/(Inputs!$B$6+INDEX(Scenarios!$D$2:$D$3,MATCH(Inputs!$B$3,Scenarios!$A$2:$A$3,0))),0) -> 5.3580333e+08

Sheet Returns
A3: Unlevered IRR | B3: =XIRR('Cash Flow'!$B$17:$AD$17,'Cash Flow'!$B$4:$AD$4) -> 0.14539644
A4: Net initial yield | B4: =SUM('Cash Flow'!$C$16:$F$16)/Inputs!$B$5 -> 0.070142775
A5: Area in the North (sqm) | B5: =SUMPRODUCT((Warehouses!$C$2:$C$9="North")*Warehouses!$D$2:$D$9) -> 103000
A6: Rent from the East a year (EUR) | B6: =SUMPRODUCT((Warehouses!$C$2:$C$9="East")*Warehouses!$D$2:$D$9*Warehouses!$E$2:$E$9) -> 7945000
A7: WAULT (years) | B7: =SUMPRODUCT(Warehouses!$D$2:$D$9*Warehouses!$E$2:$E$9,(Warehouses!$F$2:$F$9-Inputs!$B$4)/365.25)/SUMPRODUCT(Warehouses!$D$2:$D$9,Warehouses!$E$2:$E$9) -> 3.9836465
A8: Net profit (EUR) | B8: =SUM('Cash Flow'!$B$17:$AD$17) -> 3.9348563e+08
