Workbook

Sheet Assumptions
A1: CEDAR HOLLOW APARTMENTS – VALUE-ADD MULTIFAMILY ($000s)
A3: Units | B3: 286
A4: Average rent per unit a month ($) | B4: 1840
A5: Renovation premium per unit a month ($) | B5: 165
A6: Units renovated a year | B6: 72
A7: Renovation cost per unit ($000s) | B7: 14.5
A8: Rent growth | B8: 0.03
A9: Vacancy and credit loss | B9: 0.06
A10: Operating expenses a unit a year ($) | B10: 6400
A11: Expense growth | B11: 0.028
A12: Purchase price ($000s) | B12: 58500
A13: Loan ($000s) | B13: 38000
A14: Loan rate | B14: 0.0585
... A21: GP promote above the hurdle | B21: 0.5

Sheet Cash Flow
A3: Year | B3: 0 | C3: 1 | D3: 2 | E3: 3 | F3: 4 | G3: 5
A4: Renovated units | B4: =0 -> 0 | C4: =MIN(Assumptions!$B$3,C$3*Assumptions!$B$6) -> 72 | D4: =MIN(Assumptions!$B$3,D$3*Assumptions!$B$6) -> 144 | E4: =MIN(Assumptions!$B$3,E$3*Assumptions!$B$6) -> 216 | F4: =MIN(Assumptions!$B$3,F$3*Assumptions!$B$6) -> 286 | G4: =MIN(Assumptions!$B$3,G$3*Assumptions!$B$6) -> 286
A5: Gross potential rent | B5: =0 -> 0 | C5: =(Assumptions!$B$3*Assumptions!$B$4+C4*Assumptions!$B$5)*12*(1+Assumptions!$B$8)^(C$3-1)/1000 -> 6457.44 | D5: =(Assumptions!$B$3*Assumptions!$B$4+D4*Assumptions!$B$5)*12*(1+Assumptions!$B$8)^(D$3-1)/1000 -> 6798 | E5: =(Assumptions!$B$3*Assumptions!$B$4+E4*Assumptions!$B$5)*12*(1+Assumptions!$B$8)^(E$3-1)/1000 -> 7153.1819 | F5: =(Assumptions!$B$3*Assumptions!$B$4+F4*Assumptions!$B$5)*12*(1+Assumptions!$B$8)^(F$3-1)/1000 -> 7519.2293 | G5: =(Assumptions!$B$3*Assumptions!$B$4+G4*Assumptions!$B$5)*12*(1+Assumptions!$B$8)^(G$3-1)/1000 -> 7744.8062
A6: Effective rent | B6: =B5*(1-Assumptions!$B$9) -> 0 | C6: =C5*(1-Assumptions!$B$9) -> 6069.9936 | D6: =D5*(1-Assumptions!$B$9) -> 6390.12 | E6: =E5*(1-Assumptions!$B$9) -> 6723.991 | F6: =F5*(1-Assumptions!$B$9) -> 7068.0756 | G6: =G5*(1-Assumptions!$B$9) -> 7280.1178
A7: Operating expenses | B7: =0 -> 0 | C7: =Assumptions!$B$3*Assumptions!$B$10*(1+Assumptions!$B$11)^(C$3-1)/1000 -> 1830.4 | D7: =Assumptions!$B$3*Assumptions!$B$10*(1+Assumptions!$B$11)^(D$3-1)/1000 -> 1881.6512 | E7: =Assumptions!$B$3*Assumptions!$B$10*(1+Assumptions!$B$11)^(E$3-1)/1000 -> 1934.3374 | F7: =Assumptions!$B$3*Assumptions!$B$10*(1+Assumptions!$B$11)^(F$3-1)/1000 -> 1988.4989 | G7: =Assumptions!$B$3*Assumptions!$B$10*(1+Assumptions!$B$11)^(G$3-1)/1000 -> 2044.1769
A8: NOI | B8: =B6-B7 -> 0 | C8: =C6-C7 -> 4239.5936 | D8: =D6-D7 -> 4508.4688 | E8: =E6-E7 -> 4789.6536 | F8: =F6-F7 -> 5079.5767 | G8: =G6-G7 -> 5235.941
A9: Renovation capex | B9: =0 -> 0 | C9: =(C4-B4)*Assumptions!$B$7 -> 1044 | D9: =(D4-C4)*Assumptions!$B$7 -> 1044 | E9: =(E4-D4)*Assumptions!$B$7 -> 1044 | F9: =(F4-E4)*Assumptions!$B$7 -> 1015 | G9: =(G4-F4)*Assumptions!$B$7 -> 0
A10: Debt service | B10: =0 -> 0 | C10: =Assumptions!$B$13*Assumptions!$B$14 -> 2223 | D10: =Assumptions!$B$13*Assumptions!$B$14 -> 2223 | E10: =Assumptions!$B$13*Assumptions!$B$14 -> 2223 | F10: =Assumptions!$B$13*Assumptions!$B$14 -> 2223 | G10: =Assumptions!$B$13*Assumptions!$B$14 -> 2223
A11: Sale proceeds | B11: =IF(B$3=5,(B8*(1+Assumptions!$B$8)/Assumptions!$B$15)*(1-Assumptions!$B$16)-Assumptions!$B$13,0) -> 0 | C11: =IF(C$3=5,(C8*(1+Assumptions!$B$8)/Assumptions!$B$15)*(1-Assumptions!$B$16)-Assumptions!$B$13,0) -> 0 | D11: =IF(D$3=5,(D8*(1+Assumptions!$B$8)/Assumptions!$B$15)*(1-Assumptions!$B$16)-Assumptions!$B$13,0) -> 0 | E11: =IF(E$3=5,(E8*(1+Assumptions!$B$8)/Assumptions!$B$15)*(1-Assumptions!$B$16)-Assumptions!$B$13,0) -> 0 | F11: =IF(F$3=5,(F8*(1+Assumptions!$B$8)/Assumptions!$B$15)*(1-Assumptions!$B$16)-Assumptions!$B$13,0) -> 0 | G11: =IF(G$3=5,(G8*(1+Assumptions!$B$8)/Assumptions!$B$15)*(1-Assumptions!$B$16)-Assumptions!$B$13,0) -> 54384.764
A12: Project cash flow | B12: =-(Assumptions!$B$12-Assumptions!$B$13) -> -20500 | C12: =C8-C9-C10+C11 -> 972.5936 | D12: =D8-D9-D10+D11 -> 1241.4688 | E12: =E8-E9-E10+E11 -> 1522.6536 | F12: =F8-F9-F10+F11 -> 1841.5767 | G12: =G8-G9-G10+G11 -> 57397.705
A13: LP pref balance | B13: =-B12*Assumptions!$B$17 -> 18450 | C13: =B13*(1+Assumptions!$B$18)-B14 -> 19926 | D13: =C13*(1+Assumptions!$B$18)-C14 -> 20644.746 | E13: =D13*(1+Assumptions!$B$18)-D14 -> 21179.004 | F13: =E13*(1+Assumptions!$B$18)-E14 -> 21502.936 | G13: =F13*(1+Assumptions!$B$18)-F14 -> 21565.751
A14: LP to pref | B14: =0 -> 0 | C14: =MIN(C13*(1+Assumptions!$B$18),MAX(0,C12)*Assumptions!$B$17) -> 875.33424 | D14: =MIN(D13*(1+Assumptions!$B$18),MAX(0,D12)*Assumptions!$B$17) -> 1117.3219 | E14: =MIN(E13*(1+Assumptions!$B$18),MAX(0,E12)*Assumptions!$B$17) -> 1370.3882 | F14: =MIN(F13*(1+Assumptions!$B$18),MAX(0,F12)*Assumptions!$B$17) -> 1657.419 | G14: =MIN(G13*(1+Assumptions!$B$18),MAX(0,G12)*Assumptions!$B$17) -> 23291.012
A15: LP 8% hurdle met | B15: =0 -> 0 | C15: =IF(C14>=C13*(1+Assumptions!$B$18)-0.001,1,0) -> 0 | D15: =IF(D14>=D13*(1+Assumptions!$B$18)-0.001,1,0) -> 0 | E15: =IF(E14>=E13*(1+Assumptions!$B$18)-0.001,1,0) -> 0 | F15: =IF(F14>=F13*(1+Assumptions!$B$18)-0.001,1,0) -> 0 | G15: =IF(G14>=G13*(1+Assumptions!$B$18)-0.001,1,0) -> 1
A16: LP 15% balance | B16: =-B12*Assumptions!$B$17 -> 18450 | C16: =MAX(0,B16*(1+Assumptions!$B$19)-B14-B17*(1-Assumptions!$B$20)) -> 21217.5 | D16: =MAX(0,C16*(1+Assumptions!$B$19)-C14-C17*(1-Assumptions!$B$20)) -> 23524.791 | E16: =MAX(0,D16*(1+Assumptions!$B$19)-D14-D17*(1-Assumptions!$B$20)) -> 25936.187 | F16: =MAX(0,E16*(1+Assumptions!$B$19)-E14-E17*(1-Assumptions!$B$20)) -> 28456.227 | G16: =MAX(0,F16*(1+Assumptions!$B$19)-F14-F17*(1-Assumptions!$B$20)) -> 31067.242
A17: Split 1 cash | B17: =0 -> 0 | C17: =MIN(MAX(0,C12-C14/Assumptions!$B$17),MAX(0,C16*(1+Assumptions!$B$19)-C14)/(1-Assumptions!$B$20)) -> 0 | D17: =MIN(MAX(0,D12-D14/Assumptions!$B$17),MAX(0,D16*(1+Assumptions!$B$19)-D14)/(1-Assumptions!$B$20)) -> 0 | E17: =MIN(MAX(0,E12-E14/Assumptions!$B$17),MAX(0,E16*(1+Assumptions!$B$19)-E14)/(1-Assumptions!$B$20)) -> 0 | F17: =MIN(MAX(0,F12-F14/Assumptions!$B$17),MAX(0,F16*(1+Assumptions!$B$19)-F14)/(1-Assumptions!$B$20)) -> 0 | G17: =MIN(MAX(0,G12-G14/Assumptions!$B$17),MAX(0,G16*(1+Assumptions!$B$19)-G14)/(1-Assumptions!$B$20)) -> 17766.168
A18: Split 2 cash | B18: =0 -> 0 | C18: =MAX(0,C12-C14/Assumptions!$B$17)-C17 -> 0 | D18: =MAX(0,D12-D14/Assumptions!$B$17)-D17 -> 0 | E18: =MAX(0,E12-E14/Assumptions!$B$17)-E17 -> 0 | F18: =MAX(0,F12-F14/Assumptions!$B$17)-F17 -> 0 | G18: =MAX(0,G12-G14/Assumptions!$B$17)-G17 -> 13752.636
A19: LP cash flow | B19: =B12*Assumptions!$B$17 -> -18450 | C19: =C14+C17*(1-Assumptions!$B$20)+C18*(1-Assumptions!$B$21) -> 875.33424 | D19: =D14+D17*(1-Assumptions!$B$20)+D18*(1-Assumptions!$B$21) -> 1117.3219 | E19: =E14+E17*(1-Assumptions!$B$20)+E18*(1-Assumptions!$B$21) -> 1370.3882 | F19: =F14+F17*(1-Assumptions!$B$20)+F18*(1-Assumptions!$B$21) -> 1657.419 | G19: =G14+G17*(1-Assumptions!$B$20)+G18*(1-Assumptions!$B$21) -> 42603.647
A20: GP cash flow | B20: =B12*(1-Assumptions!$B$17) -> -2050 | C20: =C12-C19 -> 97.25936 | D20: =D12-D19 -> 124.14688 | E20: =E12-E19 -> 152.26536 | F20: =F12-F19 -> 184.15767 | G20: =G12-G19 -> 14794.058

Sheet Returns
A3: Project IRR | B3: =IRR('Cash Flow'!$B$12:$G$12) -> 0.268119
A4: LP net IRR | B4: =IRR('Cash Flow'!$B$19:$G$19) -> 0.22405892
A5: GP IRR | B5: =IRR('Cash Flow'!$B$20:$G$20) -> 0.51510419
A6: LP equity multiple | B6: =SUM('Cash Flow'!$C$19:$G$19)/-'Cash Flow'!$B$19 -> 2.5812526
A7: GP promote ($000s) | B7: =SUM('Cash Flow'!$B$20:$G$20)-SUM('Cash Flow'!$B$12:$G$12)*(1-Assumptions!$B$17) -> 9054.2877
A8: Exit value ($000s) | B8: ='Cash Flow'!$G$11+Assumptions!$B$13 -> 92384.764
A9: Net profit ($000s) | B9: =SUM('Cash Flow'!$B$12:$G$12) -> 42475.997
A10: Year-1 debt yield | B10: ='Cash Flow'!C8/Assumptions!$B$13 -> 0.11156825
