Workbook

Sheet Inputs
A1: SHINAGAWA BAY HOTEL – BUSINESS HOTEL, MONTHLY (JPY)
A3: Model start | B3: 46387
A4: Rooms | B4: 412
A5: ADR, year 1 (¥) | B5: 18500
A6: ADR growth a year | B6: 0.025
A7: Stabilised occupancy | B7: 0.84
A8: Ramp-up (months) | B8: 18
A9: F&B and other revenue share | B9: 0.12
A10: Departmental costs share of revenue | B10: 0.31
A11: Undistributed costs a month (¥) | B11: 62000000
A12: Base management fee | B12: 0.025
A13: Incentive fee over the owner priority | B13: 0.08
A14: Owner priority a year (¥) | B14: 1450000000
... A19: Exit cap rate | B19: 0.042

Sheet Seasonality
A1: Month | B1: Occupancy factor
A2: 1 | B2: 0.86
A3: 2 | B3: 0.92
A4: 3 | B4: 1.04
A5: 4 | B5: 1.08
A6: 5 | B6: 1.02
A7: 6 | B7: 0.97
A8: 7 | B8: 1.03
A9: 8 | B9: 1.09
A10: 9 | B10: 1
A11: 10 | B11: 1.06
A12: 11 | B12: 1.03
A13: 12 | B13: 0.9

Sheet Cash Flow
A3: Month | B3: 0 | C3: 1 | D3: 2 | E3: 3 | F3: 4 | G3: 5 | H3: 6 | I3: 7 | J3: 8 | K3: 9 | L3: 10 | M3: 11 | N3: 12 | O3: 13 | P3: 14 | Q3: 15 | R3: 16 | S3: 17 | T3: 18 | U3: 19 | V3: 20 | W3: 21 | X3: 22 | Y3: 23 | Z3: 24 | AA3: 25 | AB3: 26 | AC3: 27 | AD3: 28 | AE3: 29 | AF3: 30 | AG3: 31 | AH3: 32 | AI3: 33 | AJ3: 34 | AK3: 35 | AL3: 36 | AM3: 37 | AN3: 38 | AO3: 39 | AP3: 40 | AQ3: 41 | AR3: 42 | AS3: 43 | AT3: 44 | AU3: 45 | AV3: 46 | AW3: 47 | AX3: 48 | AY3: 49 | AZ3: 50 | BA3: 51 | BB3: 52 | BC3: 53 | BD3: 54 | BE3: 55 | BF3: 56 | BG3: 57 | BH3: 58 | BI3: 59 | BJ3: 60 | BK3: 61 | BL3: 62 | BM3: 63 | BN3: 64 | BO3: 65 | BP3: 66 | BQ3: 67 | BR3: 68 | BS3: 69 | BT3: 70 | BU3: 71 | BV3: 72 | BW3: 73 | BX3: 74 | BY3: 75 | BZ3: 76 | CA3: 77 | CB3: 78 | CC3: 79 | CD3: 80 | CE3: 81 | CF3: 82 | CG3: 83 | CH3: 84 | CI3: 85 | CJ3: 86 | CK3: 87 | CL3: 88 | CM3: 89 | CN3: 90 | CO3: 91 | CP3: 92 | CQ3: 93 | CR3: 94 | CS3: 95 | CT3: 96 | CU3: 97 | CV3: 98 | CW3: 99 | CX3: 100 | CY3: 101 | CZ3: 102 | DA3: 103 | DB3: 104 | DC3: 105 | DD3: 106 | DE3: 107 | DF3: 108 | DG3: 109 | DH3: 110 | DI3: 111 | DJ3: 112 | DK3: 113 | DL3: 114 | DM3: 115 | DN3: 116 | DO3: 117 | DP3: 118 | DQ3: 119 | DR3: 120
A4: Date | B4: =EOMONTH(Inputs!$B$3,B$3) -> 46387 | C4: =EOMONTH(Inputs!$B$3,C$3) -> 46418 | D4: =EOMONTH(Inputs!$B$3,D$3) -> 46446 | E4: =EOMONTH(Inputs!$B$3,E$3) -> 46477 | F4: =EOMONTH(Inputs!$B$3,F$3) -> 46507 | G4: =EOMONTH(Inputs!$B$3,G$3) -> 46538 | H4: =EOMONTH(Inputs!$B$3,H$3) -> 46568 | I4: =EOMONTH(Inputs!$B$3,I$3) -> 46599 | ... DR4: =EOMONTH(Inputs!$B$3,DR$3) -> 50040
A5: Occupancy | B5: =0 -> 0 | C5: =Inputs!$B$7*MIN(1,0.55+0.45*C$3/Inputs!$B$8)*CHOOSE(MONTH(C4),Seasonality!$B$2,Seasonality!$B$3,Seasonality!$B$4,Seasonality!$B$5,Seasonality!$B$6,Seasonality!$B$7,Seasonality!$B$8,Seasonality!$B$9,Seasonality!$B$10,Seasonality!$B$11,Seasonality!$B$12,Seasonality!$B$13) -> 0.41538 | D5: =Inputs!$B$7*MIN(1,0.55+0.45*D$3/Inputs!$B$8)*CHOOSE(MONTH(D4),Seasonality!$B$2,Seasonality!$B$3,Seasonality!$B$4,Seasonality!$B$5,Seasonality!$B$6,Seasonality!$B$7,Seasonality!$B$8,Seasonality!$B$9,Seasonality!$B$10,Seasonality!$B$11,Seasonality!$B$12,Seasonality!$B$13) -> 0.46368 | E5: =Inputs!$B$7*MIN(1,0.55+0.45*E$3/Inputs!$B$8)*CHOOSE(MONTH(E4),Seasonality!$B$2,Seasonality!$B$3,Seasonality!$B$4,Seasonality!$B$5,Seasonality!$B$6,Seasonality!$B$7,Seasonality!$B$8,Seasonality!$B$9,Seasonality!$B$10,Seasonality!$B$11,Seasonality!$B$12,Seasonality!$B$13) -> 0.546 | F5: =Inputs!$B$7*MIN(1,0.55+0.45*F$3/Inputs!$B$8)*CHOOSE(MONTH(F4),Seasonality!$B$2,Seasonality!$B$3,Seasonality!$B$4,Seasonality!$B$5,Seasonality!$B$6,Seasonality!$B$7,Seasonality!$B$8,Seasonality!$B$9,Seasonality!$B$10,Seasonality!$B$11,Seasonality!$B$12,Seasonality!$B$13) -> 0.58968 | G5: =Inputs!$B$7*MIN(1,0.55+0.45*G$3/Inputs!$B$8)*CHOOSE(MONTH(G4),Seasonality!$B$2,Seasonality!$B$3,Seasonality!$B$4,Seasonality!$B$5,Seasonality!$B$6,Seasonality!$B$7,Seasonality!$B$8,Seasonality!$B$9,Seasonality!$B$10,Seasonality!$B$11,Seasonality!$B$12,Seasonality!$B$13) -> 0.57834 | H5: =Inputs!$B$7*MIN(1,0.55+0.45*H$3/Inputs!$B$8)*CHOOSE(MONTH(H4),Seasonality!$B$2,Seasonality!$B$3,Seasonality!$B$4,Seasonality!$B$5,Seasonality!$B$6,Seasonality!$B$7,Seasonality!$B$8,Seasonality!$B$9,Seasonality!$B$10,Seasonality!$B$11,Seasonality!$B$12,Seasonality!$B$13) -> 0.57036 | I5: =Inputs!$B$7*MIN(1,0.55+0.45*I$3/Inputs!$B$8)*CHOOSE(MONTH(I4),Seasonality!$B$2,Seasonality!$B$3,Seasonality!$B$4,Seasonality!$B$5,Seasonality!$B$6,Seasonality!$B$7,Seasonality!$B$8,Seasonality!$B$9,Seasonality!$B$10,Seasonality!$B$11,Seasonality!$B$12,Seasonality!$B$13) -> 0.62727 | J5: =Inputs!$B$7*MIN(1,0.55+0.45*J$3/Inputs!$B$8)*CHOOSE(MONTH(J4),Seasonality!$B$2,Seasonality!$B$3,Seasonality!$B$4,Seasonality!$B$5,Seasonality!$B$6,Seasonality!$B$7,Seasonality!$B$8,Seasonality!$B$9,Seasonality!$B$10,Seasonality!$B$11,Seasonality!$B$12,Seasonality!$B$13) -> 0.6867 | ... DR5: =Inputs!$B$7*MIN(1,0.55+0.45*DR$3/Inputs!$B$8)*CHOOSE(MONTH(DR4),Seasonality!$B$2,Seasonality!$B$3,Seasonality!$B$4,Seasonality!$B$5,Seasonality!$B$6,Seasonality!$B$7,Seasonality!$B$8,Seasonality!$B$9,Seasonality!$B$10,Seasonality!$B$11,Seasonality!$B$12,Seasonality!$B$13) -> 0.756
A6: ADR | B6: =ROUND(Inputs!$B$5*(1+Inputs!$B$6)^INT((B$3-1)/12),-1) -> 18050 | C6: =ROUND(Inputs!$B$5*(1+Inputs!$B$6)^INT((C$3-1)/12),-1) -> 18500 | D6: =ROUND(Inputs!$B$5*(1+Inputs!$B$6)^INT((D$3-1)/12),-1) -> 18500 | E6: =ROUND(Inputs!$B$5*(1+Inputs!$B$6)^INT((E$3-1)/12),-1) -> 18500 | F6: =ROUND(Inputs!$B$5*(1+Inputs!$B$6)^INT((F$3-1)/12),-1) -> 18500 | G6: =ROUND(Inputs!$B$5*(1+Inputs!$B$6)^INT((G$3-1)/12),-1) -> 18500 | H6: =ROUND(Inputs!$B$5*(1+Inputs!$B$6)^INT((H$3-1)/12),-1) -> 18500 | I6: =ROUND(Inputs!$B$5*(1+Inputs!$B$6)^INT((I$3-1)/12),-1) -> 18500 | ... DR6: =ROUND(Inputs!$B$5*(1+Inputs!$B$6)^INT((DR$3-1)/12),-1) -> 23100
A7: Rooms revenue | B7: =0 -> 0 | C7: =Inputs!$B$4*DAY(C4)*C5*C6 -> 98146817 | D7: =Inputs!$B$4*DAY(D4)*D5*D6 -> 98956731 | E7: =Inputs!$B$4*DAY(E4)*E5*E6 -> 129009972 | F7: =Inputs!$B$4*DAY(F4)*F5*F6 -> 1.3483623e+08 | G7: =Inputs!$B$4*DAY(G4)*G5*G6 -> 1.3665133e+08 | H7: =Inputs!$B$4*DAY(H4)*H5*H6 -> 1.3041852e+08 | I7: =Inputs!$B$4*DAY(I4)*I5*I6 -> 1.4821261e+08 | J7: =Inputs!$B$4*DAY(J4)*J5*J6 -> 1.6225485e+08 | ... DR7: =Inputs!$B$4*DAY(DR4)*DR5*DR6 -> 2.230451e+08
A8: Total revenue | B8: =B7/(1-Inputs!$B$9) -> 0 | C8: =C7/(1-Inputs!$B$9) -> 1.1153047e+08 | D8: =D7/(1-Inputs!$B$9) -> 1.1245083e+08 | E8: =E7/(1-Inputs!$B$9) -> 1.4660224e+08 | F8: =F7/(1-Inputs!$B$9) -> 1.5322299e+08 | G8: =G7/(1-Inputs!$B$9) -> 1.552856e+08 | H8: =H7/(1-Inputs!$B$9) -> 1.4820286e+08 | I8: =I7/(1-Inputs!$B$9) -> 1.6842342e+08 | ... DR8: =DR7/(1-Inputs!$B$9) -> 253460340
A9: Departmental costs | B9: =B8*Inputs!$B$10 -> 0 | C9: =C8*Inputs!$B$10 -> 34574447 | D9: =D8*Inputs!$B$10 -> 34859757 | E9: =E8*Inputs!$B$10 -> 45446695 | F9: =F8*Inputs!$B$10 -> 47499126 | G9: =G8*Inputs!$B$10 -> 48138537 | H9: =H8*Inputs!$B$10 -> 45942887 | I9: =I8*Inputs!$B$10 -> 52211260 | ... DR9: =DR8*Inputs!$B$10 -> 78572705
A10: Undistributed costs | B10: =0 -> 0 | C10: =Inputs!$B$11*(1+Inputs!$B$6)^INT((C$3-1)/12) -> 62000000 | D10: =Inputs!$B$11*(1+Inputs!$B$6)^INT((D$3-1)/12) -> 62000000 | E10: =Inputs!$B$11*(1+Inputs!$B$6)^INT((E$3-1)/12) -> 62000000 | F10: =Inputs!$B$11*(1+Inputs!$B$6)^INT((F$3-1)/12) -> 62000000 | G10: =Inputs!$B$11*(1+Inputs!$B$6)^INT((G$3-1)/12) -> 62000000 | H10: =Inputs!$B$11*(1+Inputs!$B$6)^INT((H$3-1)/12) -> 62000000 | I10: =Inputs!$B$11*(1+Inputs!$B$6)^INT((I$3-1)/12) -> 62000000 | J10: =Inputs!$B$11*(1+Inputs!$B$6)^INT((J$3-1)/12) -> 62000000 | ... DR10: =Inputs!$B$11*(1+Inputs!$B$6)^INT((DR$3-1)/12) -> 77429504
A11: GOP | B11: =B8-B9-B10 -> 0 | C11: =C8-C9-C10 -> 14956027 | D11: =D8-D9-D10 -> 15591073 | E11: =E8-E9-E10 -> 39155546 | F11: =F8-F9-F10 -> 43723861 | G11: =G8-G9-G10 -> 45147067 | H11: =H8-H9-H10 -> 40259974 | I11: =I8-I9-I10 -> 54212160 | ... DR11: =DR8-DR9-DR10 -> 97458130
A12: Base fee | B12: =B8*Inputs!$B$12 -> 0 | C12: =C8*Inputs!$B$12 -> 2788261.9 | D12: =D8*Inputs!$B$12 -> 2811270.8 | E12: =E8*Inputs!$B$12 -> 3665056 | F12: =F8*Inputs!$B$12 -> 3830574.7 | G12: =G8*Inputs!$B$12 -> 3882140.1 | H12: =H8*Inputs!$B$12 -> 3705071.5 | I12: =I8*Inputs!$B$12 -> 4210585.5 | ... DR12: =DR8*Inputs!$B$12 -> 6336508.5
A13: Incentive fee | B13: =MAX(0,B11-B12-Inputs!$B$14/12)*Inputs!$B$13 -> 0 | C13: =MAX(0,C11-C12-Inputs!$B$14/12)*Inputs!$B$13 -> 0 | D13: =MAX(0,D11-D12-Inputs!$B$14/12)*Inputs!$B$13 -> 0 | E13: =MAX(0,E11-E12-Inputs!$B$14/12)*Inputs!$B$13 -> 0 | F13: =MAX(0,F11-F12-Inputs!$B$14/12)*Inputs!$B$13 -> 0 | G13: =MAX(0,G11-G12-Inputs!$B$14/12)*Inputs!$B$13 -> 0 | H13: =MAX(0,H11-H12-Inputs!$B$14/12)*Inputs!$B$13 -> 0 | I13: =MAX(0,I11-I12-Inputs!$B$14/12)*Inputs!$B$13 -> 0 | ... DR13: =MAX(0,DR11-DR12-Inputs!$B$14/12)*Inputs!$B$13 -> 0
A14: FF&E reserve | B14: =B8*Inputs!$B$15 -> 0 | C14: =C8*Inputs!$B$15 -> 4461219 | D14: =D8*Inputs!$B$15 -> 4498033.2 | E14: =E8*Inputs!$B$15 -> 5864089.6 | F14: =F8*Inputs!$B$15 -> 6128919.5 | G14: =G8*Inputs!$B$15 -> 6211424.2 | H14: =H8*Inputs!$B$15 -> 5928114.4 | I14: =I8*Inputs!$B$15 -> 6736936.8 | ... DR14: =DR8*Inputs!$B$15 -> 10138414
A15: NOI | B15: =B11-B12-B13-B14 -> 0 | C15: =C11-C12-C13-C14 -> 7706546.3 | D15: =D11-D12-D13-D14 -> 8281769.1 | E15: =E11-E12-E13-E14 -> 29626401 | F15: =F11-F12-F13-F14 -> 33764367 | G15: =G11-G12-G13-G14 -> 35053503 | H15: =H11-H12-H13-H14 -> 30626788 | I15: =I11-I12-I13-I14 -> 43264638 | ... DR15: =DR11-DR12-DR13-DR14 -> 80983208
A16: Interest | B16: =0 -> 0 | C16: =Inputs!$B$16*Inputs!$B$17*Inputs!$B$18/12 -> 13303125 | D16: =Inputs!$B$16*Inputs!$B$17*Inputs!$B$18/12 -> 13303125 | E16: =Inputs!$B$16*Inputs!$B$17*Inputs!$B$18/12 -> 13303125 | F16: =Inputs!$B$16*Inputs!$B$17*Inputs!$B$18/12 -> 13303125 | G16: =Inputs!$B$16*Inputs!$B$17*Inputs!$B$18/12 -> 13303125 | H16: =Inputs!$B$16*Inputs!$B$17*Inputs!$B$18/12 -> 13303125 | I16: =Inputs!$B$16*Inputs!$B$17*Inputs!$B$18/12 -> 13303125 | J16: =Inputs!$B$16*Inputs!$B$17*Inputs!$B$18/12 -> 13303125 | ... DR16: =Inputs!$B$16*Inputs!$B$17*Inputs!$B$18/12 -> 13303125
A17: Equity cash flow | B17: =-Inputs!$B$16*(1-Inputs!$B$17) -> -9675000000 | C17: =C15-C16+IF(C$3=120,SUM(B15:C15)/Inputs!$B$19-Inputs!$B$16*Inputs!$B$17,0) -> -5596578.7 | D17: =D15-D16+IF(D$3=120,SUM(B15:D15)/Inputs!$B$19-Inputs!$B$16*Inputs!$B$17,0) -> -5021355.9 | E17: =E15-E16+IF(E$3=120,SUM(B15:E15)/Inputs!$B$19-Inputs!$B$16*Inputs!$B$17,0) -> 16323276 | F17: =F15-F16+IF(F$3=120,SUM(B15:F15)/Inputs!$B$19-Inputs!$B$16*Inputs!$B$17,0) -> 20461242 | G17: =G15-G16+IF(G$3=120,SUM(B15:G15)/Inputs!$B$19-Inputs!$B$16*Inputs!$B$17,0) -> 21750378 | H17: =H15-H16+IF(H$3=120,SUM(B15:H15)/Inputs!$B$19-Inputs!$B$16*Inputs!$B$17,0) -> 17323663 | I17: =I15-I16+IF(I$3=120,SUM(B15:I15)/Inputs!$B$19-Inputs!$B$16*Inputs!$B$17,0) -> 29961513 | J17: =J15-J16+IF(J$3=120,SUM(B15:J15)/Inputs!$B$19-Inputs!$B$16*Inputs!$B$17,0) -> 39934694 | K17: =K15-K16+IF(K$3=120,SUM(B15:K15)/Inputs!$B$19-Inputs!$B$16*Inputs!$B$17,0) -> 30419645 | L17: =L15-L16+IF(L$3=120,SUM(B15:L15)/Inputs!$B$19-Inputs!$B$16*Inputs!$B$17,0) -> 44234087 | M17: =M15-M16+IF(M$3=120,SUM(B15:M15)/Inputs!$B$19-Inputs!$B$16*Inputs!$B$17,0) -> 40616777 | N17: =N15-N16+IF(N$3=120,SUM(C15:N15)/Inputs!$B$19-Inputs!$B$16*Inputs!$B$17,0) -> 32534100 | O17: =O15-O16+IF(O$3=120,SUM(D15:O15)/Inputs!$B$19-Inputs!$B$16*Inputs!$B$17,0) -> 31859599 | P17: =P15-P16+IF(P$3=120,SUM(E15:P15)/Inputs!$B$19-Inputs!$B$16*Inputs!$B$17,0) -> 35049562 | Q17: =Q15-Q16+IF(Q$3=120,SUM(F15:Q15)/Inputs!$B$19-Inputs!$B$16*Inputs!$B$17,0) -> 62125799 | R17: =R15-R16+IF(R$3=120,SUM(G15:R15)/Inputs!$B$19-Inputs!$B$16*Inputs!$B$17,0) -> 66590349 | S17: =S15-S16+IF(S$3=120,SUM(H15:S15)/Inputs!$B$19-Inputs!$B$16*Inputs!$B$17,0) -> 66821033 | T17: =T15-T16+IF(T$3=120,SUM(I15:T15)/Inputs!$B$19-Inputs!$B$16*Inputs!$B$17,0) -> 58761076 | ... DR17: =DR15-DR16+IF(DR$3=120,SUM(DG15:DR15)/Inputs!$B$19-Inputs!$B$16*Inputs!$B$17,0) -> 1.5597739e+10

Sheet Returns
A3: Levered IRR | B3: =(1+IRR('Cash Flow'!$B$17:$DR$17,0.005))^12-1 -> 0.11777075
A4: Stabilised RevPAR, year 3 (¥) | B4: =SUM('Cash Flow'!$Z$7:$AK$7)/(Inputs!$B$4*365) -> 16305.938
A5: Average occupancy | B5: =AVERAGE('Cash Flow'!$C$5:$DR$5) -> 0.813477
A6: GOP margin | B6: =SUM('Cash Flow'!$B$11:$DR$11)/SUM('Cash Flow'!$B$8:$DR$8) -> 0.40204389
A7: Incentive fees paid (¥) | B7: =SUM('Cash Flow'!$B$13:$DR$13) -> 714828.77
A8: Exit value (¥) | B8: =SUM('Cash Flow'!$DG$15:$DR$15)/Inputs!$B$19 -> 2.7355059e+10
A9: Net profit (¥) | B9: =SUM('Cash Flow'!$B$17:$DR$17) -> 1.4014204e+10
