Workbook

Sheet المدخلات
A1: مشروع النخيل السكني – AL NAKHEEL RESIDENTIAL, RIYADH (SAR)
A3: تاريخ البدء / Start date | B3: 46387
A4: عدد الوحدات / Units | B4: 640
A5: سعر البيع للوحدة / Sale price per unit (SAR) | B5: 1150000
A6: حصة البيع / Share of units sold | B6: 0.6
A7: الإيجار السنوي للوحدة / Rent per unit a year (SAR) | B7: 62000
A8: تكلفة البناء / Build cost (SAR) | B8: 420000000
A9: الأرض / Land (SAR) | B9: 165000000
A10: سايبور / SAIBOR | B10: 0.0545
A11: الهامش (نقطة أساس) / Margin (bps) | B11: 275
A12: نسبة التمويل / Loan to cost | B12: 0.5
A13: تاريخ التخارج / Exit date | B13: 48579
A14: عائد التخارج / Exit yield | B14: 0.07

Sheet التدفقات النقدية
A3: Year | B3: 0 | C3: 1 | D3: 2 | E3: 3 | F3: 4 | G3: 5 | H3: 6 | I3: 7 | J3: 8 | K3: 9 | L3: 10
A4: Date | B4: =EDATE(المدخلات!$B$3,12*B$3) -> 46387 | C4: =EDATE(المدخلات!$B$3,12*C$3) -> 46752 | D4: =EDATE(المدخلات!$B$3,12*D$3) -> 47118 | E4: =EDATE(المدخلات!$B$3,12*E$3) -> 47483 | F4: =EDATE(المدخلات!$B$3,12*F$3) -> 47848 | G4: =EDATE(المدخلات!$B$3,12*G$3) -> 48213 | H4: =EDATE(المدخلات!$B$3,12*H$3) -> 48579 | I4: =EDATE(المدخلات!$B$3,12*I$3) -> 48944 | ... L4: =EDATE(المدخلات!$B$3,12*L$3) -> 50040
A5: Build | B5: =IF(AND(B$3>=1,B$3<=3),المدخلات!$B$8/3,0) -> 0 | C5: =IF(AND(C$3>=1,C$3<=3),المدخلات!$B$8/3,0) -> 140000000 | D5: =IF(AND(D$3>=1,D$3<=3),المدخلات!$B$8/3,0) -> 140000000 | E5: =IF(AND(E$3>=1,E$3<=3),المدخلات!$B$8/3,0) -> 140000000 | F5: =IF(AND(F$3>=1,F$3<=3),المدخلات!$B$8/3,0) -> 0 | G5: =IF(AND(G$3>=1,G$3<=3),المدخلات!$B$8/3,0) -> 0 | H5: =IF(AND(H$3>=1,H$3<=3),المدخلات!$B$8/3,0) -> 0 | I5: =IF(AND(I$3>=1,I$3<=3),المدخلات!$B$8/3,0) -> 0 | ... L5: =IF(AND(L$3>=1,L$3<=3),المدخلات!$B$8/3,0) -> 0
A6: Land | B6: =IF(B$3=0,المدخلات!$B$9,0) -> 165000000 | C6: =IF(C$3=0,المدخلات!$B$9,0) -> 0 | D6: =IF(D$3=0,المدخلات!$B$9,0) -> 0 | E6: =IF(E$3=0,المدخلات!$B$9,0) -> 0 | F6: =IF(F$3=0,المدخلات!$B$9,0) -> 0 | G6: =IF(G$3=0,المدخلات!$B$9,0) -> 0 | H6: =IF(H$3=0,المدخلات!$B$9,0) -> 0 | I6: =IF(I$3=0,المدخلات!$B$9,0) -> 0 | ... L6: =IF(L$3=0,المدخلات!$B$9,0) -> 0
A7: Sales | B7: =IF(AND(B$3>=2,B$3<=4),المدخلات!$B$4*المدخلات!$B$6*المدخلات!$B$5/3,0) -> 0 | C7: =IF(AND(C$3>=2,C$3<=4),المدخلات!$B$4*المدخلات!$B$6*المدخلات!$B$5/3,0) -> 0 | D7: =IF(AND(D$3>=2,D$3<=4),المدخلات!$B$4*المدخلات!$B$6*المدخلات!$B$5/3,0) -> 147200000 | E7: =IF(AND(E$3>=2,E$3<=4),المدخلات!$B$4*المدخلات!$B$6*المدخلات!$B$5/3,0) -> 147200000 | F7: =IF(AND(F$3>=2,F$3<=4),المدخلات!$B$4*المدخلات!$B$6*المدخلات!$B$5/3,0) -> 147200000 | G7: =IF(AND(G$3>=2,G$3<=4),المدخلات!$B$4*المدخلات!$B$6*المدخلات!$B$5/3,0) -> 0 | H7: =IF(AND(H$3>=2,H$3<=4),المدخلات!$B$4*المدخلات!$B$6*المدخلات!$B$5/3,0) -> 0 | I7: =IF(AND(I$3>=2,I$3<=4),المدخلات!$B$4*المدخلات!$B$6*المدخلات!$B$5/3,0) -> 0 | ... L7: =IF(AND(L$3>=2,L$3<=4),المدخلات!$B$4*المدخلات!$B$6*المدخلات!$B$5/3,0) -> 0
A8: Rent | B8: =IF(AND(B$3>=4,B4<=المدخلات!$B$13),المدخلات!$B$4*(1-المدخلات!$B$6)*المدخلات!$B$7*1.025^(B$3-4),0) -> 0 | C8: =IF(AND(C$3>=4,C4<=المدخلات!$B$13),المدخلات!$B$4*(1-المدخلات!$B$6)*المدخلات!$B$7*1.025^(C$3-4),0) -> 0 | D8: =IF(AND(D$3>=4,D4<=المدخلات!$B$13),المدخلات!$B$4*(1-المدخلات!$B$6)*المدخلات!$B$7*1.025^(D$3-4),0) -> 0 | E8: =IF(AND(E$3>=4,E4<=المدخلات!$B$13),المدخلات!$B$4*(1-المدخلات!$B$6)*المدخلات!$B$7*1.025^(E$3-4),0) -> 0 | F8: =IF(AND(F$3>=4,F4<=المدخلات!$B$13),المدخلات!$B$4*(1-المدخلات!$B$6)*المدخلات!$B$7*1.025^(F$3-4),0) -> 15872000 | G8: =IF(AND(G$3>=4,G4<=المدخلات!$B$13),المدخلات!$B$4*(1-المدخلات!$B$6)*المدخلات!$B$7*1.025^(G$3-4),0) -> 16268800 | H8: =IF(AND(H$3>=4,H4<=المدخلات!$B$13),المدخلات!$B$4*(1-المدخلات!$B$6)*المدخلات!$B$7*1.025^(H$3-4),0) -> 16675520 | I8: =IF(AND(I$3>=4,I4<=المدخلات!$B$13),المدخلات!$B$4*(1-المدخلات!$B$6)*المدخلات!$B$7*1.025^(I$3-4),0) -> 0 | ... L8: =IF(AND(L$3>=4,L4<=المدخلات!$B$13),المدخلات!$B$4*(1-المدخلات!$B$6)*المدخلات!$B$7*1.025^(L$3-4),0) -> 0
A9: Debt | B9: =(المدخلات!$B$8+المدخلات!$B$9)*المدخلات!$B$12 -> 292500000 | C9: =(المدخلات!$B$8+المدخلات!$B$9)*المدخلات!$B$12 -> 292500000 | D9: =(المدخلات!$B$8+المدخلات!$B$9)*المدخلات!$B$12 -> 292500000 | E9: =(المدخلات!$B$8+المدخلات!$B$9)*المدخلات!$B$12 -> 292500000 | F9: =(المدخلات!$B$8+المدخلات!$B$9)*المدخلات!$B$12 -> 292500000 | G9: =(المدخلات!$B$8+المدخلات!$B$9)*المدخلات!$B$12 -> 292500000 | H9: =(المدخلات!$B$8+المدخلات!$B$9)*المدخلات!$B$12 -> 292500000 | I9: =(المدخلات!$B$8+المدخلات!$B$9)*المدخلات!$B$12 -> 292500000 | ... L9: =(المدخلات!$B$8+المدخلات!$B$9)*المدخلات!$B$12 -> 292500000
A10: Interest | B10: =0 -> 0 | C10: =IF(C$3<=4,C9*(المدخلات!$B$10+المدخلات!$B$11/10000),0) -> 23985000 | D10: =IF(D$3<=4,D9*(المدخلات!$B$10+المدخلات!$B$11/10000),0) -> 23985000 | E10: =IF(E$3<=4,E9*(المدخلات!$B$10+المدخلات!$B$11/10000),0) -> 23985000 | F10: =IF(F$3<=4,F9*(المدخلات!$B$10+المدخلات!$B$11/10000),0) -> 23985000 | G10: =IF(G$3<=4,G9*(المدخلات!$B$10+المدخلات!$B$11/10000),0) -> 0 | H10: =IF(H$3<=4,H9*(المدخلات!$B$10+المدخلات!$B$11/10000),0) -> 0 | I10: =IF(I$3<=4,I9*(المدخلات!$B$10+المدخلات!$B$11/10000),0) -> 0 | J10: =IF(J$3<=4,J9*(المدخلات!$B$10+المدخلات!$B$11/10000),0) -> 0 | ... L10: =IF(L$3<=4,L9*(المدخلات!$B$10+المدخلات!$B$11/10000),0) -> 0
A11: Exit | B11: =IF(B$3=MATCH(المدخلات!$B$13,$B$4:$L$4,0)-1,B8*1.025/المدخلات!$B$14,0) -> 0 | C11: =IF(C$3=MATCH(المدخلات!$B$13,$B$4:$L$4,0)-1,C8*1.025/المدخلات!$B$14,0) -> 0 | D11: =IF(D$3=MATCH(المدخلات!$B$13,$B$4:$L$4,0)-1,D8*1.025/المدخلات!$B$14,0) -> 0 | E11: =IF(E$3=MATCH(المدخلات!$B$13,$B$4:$L$4,0)-1,E8*1.025/المدخلات!$B$14,0) -> 0 | F11: =IF(F$3=MATCH(المدخلات!$B$13,$B$4:$L$4,0)-1,F8*1.025/المدخلات!$B$14,0) -> 0 | G11: =IF(G$3=MATCH(المدخلات!$B$13,$B$4:$L$4,0)-1,G8*1.025/المدخلات!$B$14,0) -> 0 | H11: =IF(H$3=MATCH(المدخلات!$B$13,$B$4:$L$4,0)-1,H8*1.025/المدخلات!$B$14,0) -> 2.4417726e+08 | I11: =IF(I$3=MATCH(المدخلات!$B$13,$B$4:$L$4,0)-1,I8*1.025/المدخلات!$B$14,0) -> 0 | ... L11: =IF(L$3=MATCH(المدخلات!$B$13,$B$4:$L$4,0)-1,L8*1.025/المدخلات!$B$14,0) -> 0
A12: Cash flow | B12: =-B5-B6+B7+B8-B10+B11+IF(B$3=0,B9,0)-IF(B$3=4,B9,0) -> 127500000 | C12: =-C5-C6+C7+C8-C10+C11+IF(C$3=0,C9,0)-IF(C$3=4,C9,0) -> -163985000 | D12: =-D5-D6+D7+D8-D10+D11+IF(D$3=0,D9,0)-IF(D$3=4,D9,0) -> -16785000 | E12: =-E5-E6+E7+E8-E10+E11+IF(E$3=0,E9,0)-IF(E$3=4,E9,0) -> -16785000 | F12: =-F5-F6+F7+F8-F10+F11+IF(F$3=0,F9,0)-IF(F$3=4,F9,0) -> -153413000 | G12: =-G5-G6+G7+G8-G10+G11+IF(G$3=0,G9,0)-IF(G$3=4,G9,0) -> 16268800 | H12: =-H5-H6+H7+H8-H10+H11+IF(H$3=0,H9,0)-IF(H$3=4,H9,0) -> 2.6085278e+08 | I12: =-I5-I6+I7+I8-I10+I11+IF(I$3=0,I9,0)-IF(I$3=4,I9,0) -> 0 | ... L12: =-L5-L6+L7+L8-L10+L11+IF(L$3=0,L9,0)-IF(L$3=4,L9,0) -> 0

Sheet النتائج
A3: العائد الداخلي / Levered IRR | B3: =IRR('التدفقات النقدية'!$B$12:$L$12) -> 0.11837199
A4: صافي الربح / Net profit (SAR) | B4: =SUM('التدفقات النقدية'!$B$12:$L$12) -> 53653577
A5: تكلفة التمويل / Finance rate | B5: =المدخلات!$B$10+المدخلات!$B$11/10000 -> 0.082
A6: سنة التخارج / Exit year | B6: =MATCH(المدخلات!$B$13,'التدفقات النقدية'!$B$4:$L$4,0)-1 -> 6
A7: قيمة التخارج / Exit value (SAR) | B7: =SUM('التدفقات النقدية'!$B$11:$L$11) -> 2.4417726e+08
