Workbook

Sheet Inputs
A1: CREEK VISTA TOWER – DEVELOPMENT WITH A CIRCUIT BREAKER (AED)
A3: Circuit breaker (1 = interest on, 0 = off) | B3: 1
A4: Land (AED) | B4: 95000000
A5: Build cost (AED) | B5: 310000000
A6: Build (quarters) | B6: 10
A7: Loan to cost | B7: 0.6
A8: Interest rate | B8: 0.071
A9: Sales (AED) | B9: 560000000
A10: Sales period (quarters) | B10: 6

Sheet Cash Flow
A3: Quarter | B3: 0 | C3: 1 | D3: 2 | E3: 3 | F3: 4 | G3: 5 | H3: 6 | I3: 7 | J3: 8 | K3: 9 | L3: 10 | M3: 11 | N3: 12 | O3: 13 | P3: 14 | Q3: 15 | R3: 16 | S3: 17 | T3: 18
A4: Build | B4: =IF(AND(B$3>=1,B$3<=Inputs!$B$6),Inputs!$B$5/Inputs!$B$6,0) -> 0 | C4: =IF(AND(C$3>=1,C$3<=Inputs!$B$6),Inputs!$B$5/Inputs!$B$6,0) -> 31000000 | D4: =IF(AND(D$3>=1,D$3<=Inputs!$B$6),Inputs!$B$5/Inputs!$B$6,0) -> 31000000 | E4: =IF(AND(E$3>=1,E$3<=Inputs!$B$6),Inputs!$B$5/Inputs!$B$6,0) -> 31000000 | F4: =IF(AND(F$3>=1,F$3<=Inputs!$B$6),Inputs!$B$5/Inputs!$B$6,0) -> 31000000 | G4: =IF(AND(G$3>=1,G$3<=Inputs!$B$6),Inputs!$B$5/Inputs!$B$6,0) -> 31000000 | H4: =IF(AND(H$3>=1,H$3<=Inputs!$B$6),Inputs!$B$5/Inputs!$B$6,0) -> 31000000 | I4: =IF(AND(I$3>=1,I$3<=Inputs!$B$6),Inputs!$B$5/Inputs!$B$6,0) -> 31000000 | ... T4: =IF(AND(T$3>=1,T$3<=Inputs!$B$6),Inputs!$B$5/Inputs!$B$6,0) -> 0
A5: Land | B5: =IF(B$3=0,Inputs!$B$4,0) -> 95000000 | C5: =IF(C$3=0,Inputs!$B$4,0) -> 0 | D5: =IF(D$3=0,Inputs!$B$4,0) -> 0 | E5: =IF(E$3=0,Inputs!$B$4,0) -> 0 | F5: =IF(F$3=0,Inputs!$B$4,0) -> 0 | G5: =IF(G$3=0,Inputs!$B$4,0) -> 0 | H5: =IF(H$3=0,Inputs!$B$4,0) -> 0 | I5: =IF(I$3=0,Inputs!$B$4,0) -> 0 | ... T5: =IF(T$3=0,Inputs!$B$4,0) -> 0
A6: Interest | B6: =0 -> 0 | C6: =IF(Inputs!$B$3=1,IFERROR((B9+C8/2)*Inputs!$B$8/4,0),0) -> 1183125.1 | D6: =IF(Inputs!$B$3=1,IFERROR((C9+D8/2)*Inputs!$B$8/4,0),0) -> 1527710.3 | E6: =IF(Inputs!$B$3=1,IFERROR((D9+E8/2)*Inputs!$B$8/4,0),0) -> 1875985 | F6: =IF(Inputs!$B$3=1,IFERROR((E9+F8/2)*Inputs!$B$8/4,0),0) -> 2227988.7 | G6: =IF(Inputs!$B$3=1,IFERROR((F9+G8/2)*Inputs!$B$8/4,0),0) -> 2583761.2 | H6: =IF(Inputs!$B$3=1,IFERROR((G9+H8/2)*Inputs!$B$8/4,0),0) -> 2943343.1 | I6: =IF(Inputs!$B$3=1,IFERROR((H9+I8/2)*Inputs!$B$8/4,0),0) -> 3306775 | J6: =IF(Inputs!$B$3=1,IFERROR((I9+J8/2)*Inputs!$B$8/4,0),0) -> 3674098.1 | ... T6: =IF(Inputs!$B$3=1,IFERROR((S9+T8/2)*Inputs!$B$8/4,0),0) -> 0
A7: Total cost | B7: =B4+B5+B6 -> 95000000 | C7: =C4+C5+C6 -> 32183125 | D7: =D4+D5+D6 -> 32527710 | E7: =E4+E5+E6 -> 32875985 | F7: =F4+F5+F6 -> 33227989 | G7: =G4+G5+G6 -> 33583761 | H7: =H4+H5+H6 -> 33943343 | I7: =I4+I5+I6 -> 34306775 | ... T7: =T4+T5+T6 -> 0
A8: Loan drawn | B8: =IF(B$3<=Inputs!$B$6,B7*Inputs!$B$7,0) -> 57000000 | C8: =IF(C$3<=Inputs!$B$6,C7*Inputs!$B$7,0) -> 19309875 | D8: =IF(D$3<=Inputs!$B$6,D7*Inputs!$B$7,0) -> 19516626 | E8: =IF(E$3<=Inputs!$B$6,E7*Inputs!$B$7,0) -> 19725591 | F8: =IF(F$3<=Inputs!$B$6,F7*Inputs!$B$7,0) -> 19936793 | G8: =IF(G$3<=Inputs!$B$6,G7*Inputs!$B$7,0) -> 20150257 | H8: =IF(H$3<=Inputs!$B$6,H7*Inputs!$B$7,0) -> 20366006 | I8: =IF(I$3<=Inputs!$B$6,I7*Inputs!$B$7,0) -> 20584065 | ... T8: =IF(T$3<=Inputs!$B$6,T7*Inputs!$B$7,0) -> 0
A9: Loan balance | B9: =0+B8-B11 -> 57000000 | C9: =B9+C8-C11 -> 76309875 | D9: =C9+D8-D11 -> 95826501 | E9: =D9+E8-E11 -> 1.1555209e+08 | F9: =E9+F8-F11 -> 1.3548889e+08 | G9: =F9+G8-G11 -> 1.5563914e+08 | H9: =G9+H8-H11 -> 1.7600515e+08 | I9: =H9+I8-I11 -> 1.9658921e+08 | J9: =I9+J8-J11 -> 2.1739367e+08 | ... T9: =S9+T8-T11 -> 0
A10: Sales | B10: =IF(AND(B$3>Inputs!$B$6,B$3<=Inputs!$B$6+Inputs!$B$10),Inputs!$B$9/Inputs!$B$10,0) -> 0 | C10: =IF(AND(C$3>Inputs!$B$6,C$3<=Inputs!$B$6+Inputs!$B$10),Inputs!$B$9/Inputs!$B$10,0) -> 0 | D10: =IF(AND(D$3>Inputs!$B$6,D$3<=Inputs!$B$6+Inputs!$B$10),Inputs!$B$9/Inputs!$B$10,0) -> 0 | E10: =IF(AND(E$3>Inputs!$B$6,E$3<=Inputs!$B$6+Inputs!$B$10),Inputs!$B$9/Inputs!$B$10,0) -> 0 | F10: =IF(AND(F$3>Inputs!$B$6,F$3<=Inputs!$B$6+Inputs!$B$10),Inputs!$B$9/Inputs!$B$10,0) -> 0 | G10: =IF(AND(G$3>Inputs!$B$6,G$3<=Inputs!$B$6+Inputs!$B$10),Inputs!$B$9/Inputs!$B$10,0) -> 0 | H10: =IF(AND(H$3>Inputs!$B$6,H$3<=Inputs!$B$6+Inputs!$B$10),Inputs!$B$9/Inputs!$B$10,0) -> 0 | I10: =IF(AND(I$3>Inputs!$B$6,I$3<=Inputs!$B$6+Inputs!$B$10),Inputs!$B$9/Inputs!$B$10,0) -> 0 | ... T10: =IF(AND(T$3>Inputs!$B$6,T$3<=Inputs!$B$6+Inputs!$B$10),Inputs!$B$9/Inputs!$B$10,0) -> 0
A11: Repayment | B11: =MIN(0+B8,B10) -> 0 | C11: =MIN(B9+C8,C10) -> 0 | D11: =MIN(C9+D8,D10) -> 0 | E11: =MIN(D9+E8,E10) -> 0 | F11: =MIN(E9+F8,F10) -> 0 | G11: =MIN(F9+G8,G10) -> 0 | H11: =MIN(G9+H8,H10) -> 0 | I11: =MIN(H9+I8,I10) -> 0 | J11: =MIN(I9+J8,J10) -> 0 | ... T11: =MIN(S9+T8,T10) -> 0
A12: Equity cash flow | B12: =B10-B11-(B7-B8) -> -38000000 | C12: =C10-C11-(C7-C8) -> -12873250 | D12: =D10-D11-(D7-D8) -> -13011084 | E12: =E10-E11-(E7-E8) -> -13150394 | F12: =F10-F11-(F7-F8) -> -13291195 | G12: =G10-G11-(G7-G8) -> -13433504 | H12: =H10-H11-(H7-H8) -> -13577337 | I12: =I10-I11-(I7-I8) -> -13722710 | ... T12: =T10-T11-(T7-T8) -> 0

Sheet Returns
A3: Levered IRR | B3: =(1+IRR('Cash Flow'!$B$12:$T$12,0.03))^4-1 -> 0.21136268
A4: Peak debt (AED) | B4: =MAX('Cash Flow'!$B$9:$T$9) -> 2.5967324e+08
A5: Interest capitalised (AED) | B5: =SUM('Cash Flow'!$B$6:$T$6) -> 36646326
A6: Total cost (AED) | B6: =SUM('Cash Flow'!$B$7:$T$7) -> 4.4164633e+08
A7: Net profit (AED) | B7: =SUM('Cash Flow'!$B$12:$T$12) -> 1.1835367e+08
A8: Profit on cost | B8: =B7/B6 -> 0.26798292
