Workbook

Sheet Inputs
A1: HARBORVIEW SELF STORAGE – LEASE-UP, MONTHLY (USD)
A3: Scenario sheet | B3: Base
A4: Units | B4: 820
A5: Rentable sq ft | B5: 71500
A6: Purchase price (USD) | B6: 14800000
A7: Exit cap rate | B7: 0.0575
A8: Operating cost share of revenue | B8: 0.36

Sheet Base
A1: Base case
A3: Street rate per sq ft a month (USD) | B3: 1.62
A4: Stabilised occupancy | B4: 0.91
A5: Lease-up speed | B5: 0.22
A6: Existing-customer rate increase | B6: 0.08

Sheet Downside
A1: Downside case
A3: Street rate per sq ft a month (USD) | B3: 1.48
A4: Stabilised occupancy | B4: 0.85
A5: Lease-up speed | B5: 0.15
A6: Existing-customer rate increase | B6: 0.05

Sheet Cash Flow
A3: Month | B3: 0 | C3: 1 | D3: 2 | E3: 3 | F3: 4 | G3: 5 | H3: 6 | I3: 7 | J3: 8 | K3: 9 | L3: 10 | M3: 11 | N3: 12 | O3: 13 | P3: 14 | Q3: 15 | R3: 16 | S3: 17 | T3: 18 | U3: 19 | V3: 20 | W3: 21 | X3: 22 | Y3: 23 | Z3: 24 | AA3: 25 | AB3: 26 | AC3: 27 | AD3: 28 | AE3: 29 | AF3: 30 | AG3: 31 | AH3: 32 | AI3: 33 | AJ3: 34 | AK3: 35 | AL3: 36 | AM3: 37 | AN3: 38 | AO3: 39 | AP3: 40 | AQ3: 41 | AR3: 42 | AS3: 43 | AT3: 44 | AU3: 45 | AV3: 46 | AW3: 47 | AX3: 48 | AY3: 49 | AZ3: 50 | BA3: 51 | BB3: 52 | BC3: 53 | BD3: 54 | BE3: 55 | BF3: 56 | BG3: 57 | BH3: 58 | BI3: 59 | BJ3: 60 | BK3: 61 | BL3: 62 | BM3: 63 | BN3: 64 | BO3: 65 | BP3: 66 | BQ3: 67 | BR3: 68 | BS3: 69 | BT3: 70 | BU3: 71 | BV3: 72 | BW3: 73 | BX3: 74 | BY3: 75 | BZ3: 76 | CA3: 77 | CB3: 78 | CC3: 79 | CD3: 80 | CE3: 81 | CF3: 82 | CG3: 83 | CH3: 84 | CI3: 85 | CJ3: 86 | CK3: 87 | CL3: 88 | CM3: 89 | CN3: 90 | CO3: 91 | CP3: 92 | CQ3: 93 | CR3: 94 | CS3: 95 | CT3: 96 | CU3: 97 | CV3: 98 | CW3: 99 | CX3: 100 | CY3: 101 | CZ3: 102 | DA3: 103 | DB3: 104 | DC3: 105 | DD3: 106 | DE3: 107 | DF3: 108 | DG3: 109 | DH3: 110 | DI3: 111 | DJ3: 112 | DK3: 113 | DL3: 114 | DM3: 115 | DN3: 116 | DO3: 117 | DP3: 118 | DQ3: 119 | DR3: 120
A4: Occupancy | B4: =0 -> 0 | C4: =INDIRECT(Inputs!$B$3&"!B4")/(1+EXP(-INDIRECT(Inputs!$B$3&"!B5")*(C$3-18))) -> 0.021114674 | D4: =INDIRECT(Inputs!$B$3&"!B4")/(1+EXP(-INDIRECT(Inputs!$B$3&"!B5")*(D$3-18))) -> 0.026161131 | E4: =INDIRECT(Inputs!$B$3&"!B4")/(1+EXP(-INDIRECT(Inputs!$B$3&"!B5")*(E$3-18))) -> 0.032369782 | F4: =INDIRECT(Inputs!$B$3&"!B4")/(1+EXP(-INDIRECT(Inputs!$B$3&"!B5")*(F$3-18))) -> 0.039985232 | G4: =INDIRECT(Inputs!$B$3&"!B4")/(1+EXP(-INDIRECT(Inputs!$B$3&"!B5")*(G$3-18))) -> 0.049291697 | H4: =INDIRECT(Inputs!$B$3&"!B4")/(1+EXP(-INDIRECT(Inputs!$B$3&"!B5")*(H$3-18))) -> 0.060613312 | I4: =INDIRECT(Inputs!$B$3&"!B4")/(1+EXP(-INDIRECT(Inputs!$B$3&"!B5")*(I$3-18))) -> 0.074310832 | J4: =INDIRECT(Inputs!$B$3&"!B4")/(1+EXP(-INDIRECT(Inputs!$B$3&"!B5")*(J$3-18))) -> 0.090772945 | ... DR4: =INDIRECT(Inputs!$B$3&"!B4")/(1+EXP(-INDIRECT(Inputs!$B$3&"!B5")*(DR$3-18))) -> 0.91
A5: Street rate | B5: =INDIRECT(Inputs!$B$3&"!B3")*(1+0.03)^INT(B$3/12) -> 1.62 | C5: =INDIRECT(Inputs!$B$3&"!B3")*(1+0.03)^INT(C$3/12) -> 1.62 | D5: =INDIRECT(Inputs!$B$3&"!B3")*(1+0.03)^INT(D$3/12) -> 1.62 | E5: =INDIRECT(Inputs!$B$3&"!B3")*(1+0.03)^INT(E$3/12) -> 1.62 | F5: =INDIRECT(Inputs!$B$3&"!B3")*(1+0.03)^INT(F$3/12) -> 1.62 | G5: =INDIRECT(Inputs!$B$3&"!B3")*(1+0.03)^INT(G$3/12) -> 1.62 | H5: =INDIRECT(Inputs!$B$3&"!B3")*(1+0.03)^INT(H$3/12) -> 1.62 | I5: =INDIRECT(Inputs!$B$3&"!B3")*(1+0.03)^INT(I$3/12) -> 1.62 | ... DR5: =INDIRECT(Inputs!$B$3&"!B3")*(1+0.03)^INT(DR$3/12) -> 2.1771445
A6: In-place rate | B6: =B5 -> 1.62 | C6: =MAX(C5,B6*IF(MOD(C$3,12)=0,1+INDIRECT(Inputs!$B$3&"!B6"),1)) -> 1.62 | D6: =MAX(D5,C6*IF(MOD(D$3,12)=0,1+INDIRECT(Inputs!$B$3&"!B6"),1)) -> 1.62 | E6: =MAX(E5,D6*IF(MOD(E$3,12)=0,1+INDIRECT(Inputs!$B$3&"!B6"),1)) -> 1.62 | F6: =MAX(F5,E6*IF(MOD(F$3,12)=0,1+INDIRECT(Inputs!$B$3&"!B6"),1)) -> 1.62 | G6: =MAX(G5,F6*IF(MOD(G$3,12)=0,1+INDIRECT(Inputs!$B$3&"!B6"),1)) -> 1.62 | H6: =MAX(H5,G6*IF(MOD(H$3,12)=0,1+INDIRECT(Inputs!$B$3&"!B6"),1)) -> 1.62 | I6: =MAX(I5,H6*IF(MOD(I$3,12)=0,1+INDIRECT(Inputs!$B$3&"!B6"),1)) -> 1.62 | J6: =MAX(J5,I6*IF(MOD(J$3,12)=0,1+INDIRECT(Inputs!$B$3&"!B6"),1)) -> 1.62 | ... DR6: =MAX(DR5,DQ6*IF(MOD(DR$3,12)=0,1+INDIRECT(Inputs!$B$3&"!B6"),1)) -> 3.4974585
A7: Revenue | B7: =Inputs!$B$5*B4*B6 -> 0 | C7: =Inputs!$B$5*C4*C6 -> 2445.7127 | D7: =Inputs!$B$5*D4*D6 -> 3030.2438 | E7: =Inputs!$B$5*E4*E6 -> 3749.3919 | F7: =Inputs!$B$5*F4*F6 -> 4631.4894 | G7: =Inputs!$B$5*G4*G6 -> 5709.4573 | H7: =Inputs!$B$5*H4*H6 -> 7020.84 | I7: =Inputs!$B$5*I4*I6 -> 8607.4237 | ... DR7: =Inputs!$B$5*DR4*DR6 -> 227562.14
A8: Operating costs | B8: =B7*Inputs!$B$8+IF(B$3>0,Inputs!$B$4*2.5,0) -> 0 | C8: =C7*Inputs!$B$8+IF(C$3>0,Inputs!$B$4*2.5,0) -> 2930.4566 | D8: =D7*Inputs!$B$8+IF(D$3>0,Inputs!$B$4*2.5,0) -> 3140.8878 | E8: =E7*Inputs!$B$8+IF(E$3>0,Inputs!$B$4*2.5,0) -> 3399.7811 | F8: =F7*Inputs!$B$8+IF(F$3>0,Inputs!$B$4*2.5,0) -> 3717.3362 | G8: =G7*Inputs!$B$8+IF(G$3>0,Inputs!$B$4*2.5,0) -> 4105.4046 | H8: =H7*Inputs!$B$8+IF(H$3>0,Inputs!$B$4*2.5,0) -> 4577.5024 | I8: =I7*Inputs!$B$8+IF(I$3>0,Inputs!$B$4*2.5,0) -> 5148.6725 | ... DR8: =DR7*Inputs!$B$8+IF(DR$3>0,Inputs!$B$4*2.5,0) -> 83972.369
A9: NOI | B9: =B7-B8 -> 0 | C9: =C7-C8 -> -484.7439 | D9: =D7-D8 -> -110.64394 | E9: =E7-E8 -> 349.6108 | F9: =F7-F8 -> 914.15323 | G9: =G7-G8 -> 1604.0527 | H9: =H7-H8 -> 2443.3376 | I9: =I7-I8 -> 3458.7512 | ... DR9: =DR7-DR8 -> 143589.77
A10: Cash flow | B10: =-Inputs!$B$6 -> -14800000 | C10: =C9+IF(C$3=120,SUM(B9:C9)/Inputs!$B$7,0) -> -484.7439 | D10: =D9+IF(D$3=120,SUM(B9:D9)/Inputs!$B$7,0) -> -110.64394 | E10: =E9+IF(E$3=120,SUM(B9:E9)/Inputs!$B$7,0) -> 349.6108 | F10: =F9+IF(F$3=120,SUM(B9:F9)/Inputs!$B$7,0) -> 914.15323 | G10: =G9+IF(G$3=120,SUM(B9:G9)/Inputs!$B$7,0) -> 1604.0527 | H10: =H9+IF(H$3=120,SUM(B9:H9)/Inputs!$B$7,0) -> 2443.3376 | I10: =I9+IF(I$3=120,SUM(B9:I9)/Inputs!$B$7,0) -> 3458.7512 | J10: =J9+IF(J$3=120,SUM(B9:J9)/Inputs!$B$7,0) -> 4679.1073 | K10: =K9+IF(K$3=120,SUM(B9:K9)/Inputs!$B$7,0) -> 6134.095 | L10: =L9+IF(L$3=120,SUM(B9:L9)/Inputs!$B$7,0) -> 7852.3871 | M10: =M9+IF(M$3=120,SUM(B9:M9)/Inputs!$B$7,0) -> 9858.9623 | N10: =N9+IF(N$3=120,SUM(C9:N9)/Inputs!$B$7,0) -> 13309.408 | O10: =O9+IF(O$3=120,SUM(D9:O9)/Inputs!$B$7,0) -> 16145.086 | P10: =P9+IF(P$3=120,SUM(E9:P9)/Inputs!$B$7,0) -> 19309.802 | Q10: =Q9+IF(Q$3=120,SUM(F9:Q9)/Inputs!$B$7,0) -> 22774.974 | R10: =R9+IF(R$3=120,SUM(G9:R9)/Inputs!$B$7,0) -> 26490.736 | S10: =S9+IF(S$3=120,SUM(H9:S9)/Inputs!$B$7,0) -> 30387.068 | T10: =T9+IF(T$3=120,SUM(I9:T9)/Inputs!$B$7,0) -> 34378.072 | ... DR10: =DR9+IF(DR$3=120,SUM(DG9:DR9)/Inputs!$B$7,0) -> 28046334

Sheet Returns
A3: Unlevered IRR | B3: =(1+IRR('Cash Flow'!$B$10:$DR$10,0.01))^12-1 -> 0.11513108
A4: Stabilised NOI, year 5 (USD) | B4: =SUM('Cash Flow'!$AY$9:$BJ$9) -> 1083603.7
A5: Occupancy at month 24 | B5: ='Cash Flow'!$AA$4 -> 0.7493529
A6: Months to 85% occupancy | B6: =IFERROR(MATCH(TRUE(),INDEX('Cash Flow'!$B$4:$DR$4>=0.85,0),0)-1,"not reached") -> 31
A7: Net profit (USD) | B7: =SUM('Cash Flow'!$B$10:$DR$10) -> 23427106
