Workbook

Sheet Assumptions
A1: BIRCHWOOD GRANGE – SENIOR LIVING (GBP)
A3: Beds | B3: 120
A4: Weekly fee, residential (£) | B4: 1250
A5: Weekly fee, nursing (£) | B5: 1480
A6: Weekly fee, dementia (£) | B6: 1560
A7: Occupancy | B7: 0.92
A8: Residents per carer | B8: 4.5
A9: Carer cost a year (£) | B9: 31500
A10: Other costs share of fees | B10: 0.28
A11: Purchase price (£) | B11: 38500000
A12: Exit yield | B12: 0.0625
A13: Fee review a year | B13: 0.035

Sheet Cash Flow
A3: Year | B3: 0 | C3: 1 | D3: 2 | E3: 3 | F3: 4 | G3: 5 | H3: 6 | I3: 7 | J3: 8
A4: Residents | B4: =0 -> 0 | C4: =ROUNDDOWN(Beds*Occupancy,0) -> 110 | D4: =ROUNDDOWN(Beds*Occupancy,0) -> 110 | E4: =ROUNDDOWN(Beds*Occupancy,0) -> 110 | F4: =ROUNDDOWN(Beds*Occupancy,0) -> 110 | G4: =ROUNDDOWN(Beds*Occupancy,0) -> 110 | H4: =ROUNDDOWN(Beds*Occupancy,0) -> 110 | I4: =ROUNDDOWN(Beds*Occupancy,0) -> 110 | J4: =ROUNDDOWN(Beds*Occupancy,0) -> 110
A5: Blended weekly fee | B5: =0 -> 0 | C5: =FLOOR(SUMPRODUCT({0.45,0.35,0.2},CHOOSE({1,2,3},Fee_Residential,Fee_Nursing,Fee_Dementia))*(1+Review)^(C$3-1),5) -> 1390 | D5: =FLOOR(SUMPRODUCT({0.45,0.35,0.2},CHOOSE({1,2,3},Fee_Residential,Fee_Nursing,Fee_Dementia))*(1+Review)^(D$3-1),5) -> 1440 | E5: =FLOOR(SUMPRODUCT({0.45,0.35,0.2},CHOOSE({1,2,3},Fee_Residential,Fee_Nursing,Fee_Dementia))*(1+Review)^(E$3-1),5) -> 1490 | F5: =FLOOR(SUMPRODUCT({0.45,0.35,0.2},CHOOSE({1,2,3},Fee_Residential,Fee_Nursing,Fee_Dementia))*(1+Review)^(F$3-1),5) -> 1540 | G5: =FLOOR(SUMPRODUCT({0.45,0.35,0.2},CHOOSE({1,2,3},Fee_Residential,Fee_Nursing,Fee_Dementia))*(1+Review)^(G$3-1),5) -> 1595 | H5: =FLOOR(SUMPRODUCT({0.45,0.35,0.2},CHOOSE({1,2,3},Fee_Residential,Fee_Nursing,Fee_Dementia))*(1+Review)^(H$3-1),5) -> 1650 | I5: =FLOOR(SUMPRODUCT({0.45,0.35,0.2},CHOOSE({1,2,3},Fee_Residential,Fee_Nursing,Fee_Dementia))*(1+Review)^(I$3-1),5) -> 1710 | J5: =FLOOR(SUMPRODUCT({0.45,0.35,0.2},CHOOSE({1,2,3},Fee_Residential,Fee_Nursing,Fee_Dementia))*(1+Review)^(J$3-1),5) -> 1770
A6: Fees | B6: =B4*B5*52 -> 0 | C6: =C4*C5*52 -> 7950800 | D6: =D4*D5*52 -> 8236800 | E6: =E4*E5*52 -> 8522800 | F6: =F4*F5*52 -> 8808800 | G6: =G4*G5*52 -> 9123400 | H6: =H4*H5*52 -> 9438000 | I6: =I4*I5*52 -> 9781200 | J6: =J4*J5*52 -> 10124400
A7: Carers | B7: =0 -> 0 | C7: =CEILING(C4/Staff_Ratio,1)*4.2 -> 105 | D7: =CEILING(D4/Staff_Ratio,1)*4.2 -> 105 | E7: =CEILING(E4/Staff_Ratio,1)*4.2 -> 105 | F7: =CEILING(F4/Staff_Ratio,1)*4.2 -> 105 | G7: =CEILING(G4/Staff_Ratio,1)*4.2 -> 105 | H7: =CEILING(H4/Staff_Ratio,1)*4.2 -> 105 | I7: =CEILING(I4/Staff_Ratio,1)*4.2 -> 105 | J7: =CEILING(J4/Staff_Ratio,1)*4.2 -> 105
A8: Staff costs | B8: =ROUNDUP(B7,0)*Carer_Cost*(1+Review)^MAX(0,B$3-1) -> 0 | C8: =ROUNDUP(C7,0)*Carer_Cost*(1+Review)^MAX(0,C$3-1) -> 3307500 | D8: =ROUNDUP(D7,0)*Carer_Cost*(1+Review)^MAX(0,D$3-1) -> 3423262.5 | E8: =ROUNDUP(E7,0)*Carer_Cost*(1+Review)^MAX(0,E$3-1) -> 3543076.7 | F8: =ROUNDUP(F7,0)*Carer_Cost*(1+Review)^MAX(0,F$3-1) -> 3667084.4 | G8: =ROUNDUP(G7,0)*Carer_Cost*(1+Review)^MAX(0,G$3-1) -> 3795432.3 | H8: =ROUNDUP(H7,0)*Carer_Cost*(1+Review)^MAX(0,H$3-1) -> 3928272.5 | I8: =ROUNDUP(I7,0)*Carer_Cost*(1+Review)^MAX(0,I$3-1) -> 4065762 | J8: =ROUNDUP(J7,0)*Carer_Cost*(1+Review)^MAX(0,J$3-1) -> 4208063.7
A9: Other costs | B9: =B6*Other_Costs -> 0 | C9: =C6*Other_Costs -> 2226224 | D9: =D6*Other_Costs -> 2306304 | E9: =E6*Other_Costs -> 2386384 | F9: =F6*Other_Costs -> 2466464 | G9: =G6*Other_Costs -> 2554552 | H9: =H6*Other_Costs -> 2642640 | I9: =I6*Other_Costs -> 2738736 | J9: =J6*Other_Costs -> 2834832
A10: EBITDAR | B10: =B6-B8-B9 -> 0 | C10: =C6-C8-C9 -> 2417076 | D10: =D6-D8-D9 -> 2507233.5 | E10: =E6-E8-E9 -> 2593339.3 | F10: =F6-F8-F9 -> 2675251.6 | G10: =G6-G8-G9 -> 2773415.7 | H10: =H6-H8-H9 -> 2867087.5 | I10: =I6-I8-I9 -> 2976702 | J10: =J6-J8-J9 -> 3081504.3
A11: Cash flow | B11: =-Price -> -38500000 | C11: =C10+IF(C$3=8,C10*(1+Review)/Exit_Yield,0) -> 2417076 | D11: =D10+IF(D$3=8,D10*(1+Review)/Exit_Yield,0) -> 2507233.5 | E11: =E10+IF(E$3=8,E10*(1+Review)/Exit_Yield,0) -> 2593339.3 | F11: =F10+IF(F$3=8,F10*(1+Review)/Exit_Yield,0) -> 2675251.6 | G11: =G10+IF(G$3=8,G10*(1+Review)/Exit_Yield,0) -> 2773415.7 | H11: =H10+IF(H$3=8,H10*(1+Review)/Exit_Yield,0) -> 2867087.5 | I11: =I10+IF(I$3=8,I10*(1+Review)/Exit_Yield,0) -> 2976702 | J11: =J10+IF(J$3=8,J10*(1+Review)/Exit_Yield,0) -> 54111216

Sheet Returns
A3: Unlevered IRR | B3: =IRR('Cash Flow'!$B$11:$J$11) -> 0.098499318
A4: EBITDAR margin, year 1 | B4: ='Cash Flow'!C10/'Cash Flow'!C6 -> 0.30400413
A5: Carers on the rota | B5: ='Cash Flow'!C7 -> 105
A6: Blended weekly fee, year 1 (£) | B6: ='Cash Flow'!C5 -> 1390
A7: Net profit (£) | B7: =SUM('Cash Flow'!$B$11:$J$11) -> 34421322
