Workbook

Sheet Inputs
A1: TOUR LUMIÈRE – PARIS OFFICE IN A USD FUND (EUR / USD)
A3: Purchase price (EUR) | B3: 212000000
A4: Rent a year (EUR) | B4: 11800000
A5: Indexation | B5: 0.021
A6: Void at lease break (months) | B6: 9
A7: Lease break in year | B7: 4
A8: Exit yield | B8: 0.0475
A9: EURUSD today | B9: 1.085
A10: EURUSD at exit | B10: 1.12
A11: Hedge cost a year | B11: 0.0115
A12: LTV | B12: 0.45
A13: Loan rate | B13: 0.039

Sheet Cash Flow
A3: Year | B3: 0 | C3: 1 | D3: 2 | E3: 3 | F3: 4 | G3: 5 | H3: 6 | I3: 7
A4: Rent | B4: =0 -> 0 | C4: =Inputs!$B$4*(1+Inputs!$B$5)^(C$3-1)*IF(C$3=Inputs!$B$7+1,1-Inputs!$B$6/12,1) -> 11800000 | D4: =Inputs!$B$4*(1+Inputs!$B$5)^(D$3-1)*IF(D$3=Inputs!$B$7+1,1-Inputs!$B$6/12,1) -> 12047800 | E4: =Inputs!$B$4*(1+Inputs!$B$5)^(E$3-1)*IF(E$3=Inputs!$B$7+1,1-Inputs!$B$6/12,1) -> 12300804 | F4: =Inputs!$B$4*(1+Inputs!$B$5)^(F$3-1)*IF(F$3=Inputs!$B$7+1,1-Inputs!$B$6/12,1) -> 12559121 | G4: =Inputs!$B$4*(1+Inputs!$B$5)^(G$3-1)*IF(G$3=Inputs!$B$7+1,1-Inputs!$B$6/12,1) -> 3205715.6 | H4: =Inputs!$B$4*(1+Inputs!$B$5)^(H$3-1)*IF(H$3=Inputs!$B$7+1,1-Inputs!$B$6/12,1) -> 13092142 | I4: =Inputs!$B$4*(1+Inputs!$B$5)^(I$3-1)*IF(I$3=Inputs!$B$7+1,1-Inputs!$B$6/12,1) -> 13367077
A5: Interest | B5: =0 -> 0 | C5: =Inputs!$B$3*Inputs!$B$12*Inputs!$B$13 -> 3720600 | D5: =Inputs!$B$3*Inputs!$B$12*Inputs!$B$13 -> 3720600 | E5: =Inputs!$B$3*Inputs!$B$12*Inputs!$B$13 -> 3720600 | F5: =Inputs!$B$3*Inputs!$B$12*Inputs!$B$13 -> 3720600 | G5: =Inputs!$B$3*Inputs!$B$12*Inputs!$B$13 -> 3720600 | H5: =Inputs!$B$3*Inputs!$B$12*Inputs!$B$13 -> 3720600 | I5: =Inputs!$B$3*Inputs!$B$12*Inputs!$B$13 -> 3720600
A6: Exit | B6: =IF(B$3=7,B4*(1+Inputs!$B$5)/Inputs!$B$8,0) -> 0 | C6: =IF(C$3=7,C4*(1+Inputs!$B$5)/Inputs!$B$8,0) -> 0 | D6: =IF(D$3=7,D4*(1+Inputs!$B$5)/Inputs!$B$8,0) -> 0 | E6: =IF(E$3=7,E4*(1+Inputs!$B$5)/Inputs!$B$8,0) -> 0 | F6: =IF(F$3=7,F4*(1+Inputs!$B$5)/Inputs!$B$8,0) -> 0 | G6: =IF(G$3=7,G4*(1+Inputs!$B$5)/Inputs!$B$8,0) -> 0 | H6: =IF(H$3=7,H4*(1+Inputs!$B$5)/Inputs!$B$8,0) -> 0 | I6: =IF(I$3=7,I4*(1+Inputs!$B$5)/Inputs!$B$8,0) -> 2.8732181e+08
A7: Loan | B7: =IF(B$3=0,Inputs!$B$3*Inputs!$B$12,IF(B$3=7,-Inputs!$B$3*Inputs!$B$12,0)) -> 95400000 | C7: =IF(C$3=0,Inputs!$B$3*Inputs!$B$12,IF(C$3=7,-Inputs!$B$3*Inputs!$B$12,0)) -> 0 | D7: =IF(D$3=0,Inputs!$B$3*Inputs!$B$12,IF(D$3=7,-Inputs!$B$3*Inputs!$B$12,0)) -> 0 | E7: =IF(E$3=0,Inputs!$B$3*Inputs!$B$12,IF(E$3=7,-Inputs!$B$3*Inputs!$B$12,0)) -> 0 | F7: =IF(F$3=0,Inputs!$B$3*Inputs!$B$12,IF(F$3=7,-Inputs!$B$3*Inputs!$B$12,0)) -> 0 | G7: =IF(G$3=0,Inputs!$B$3*Inputs!$B$12,IF(G$3=7,-Inputs!$B$3*Inputs!$B$12,0)) -> 0 | H7: =IF(H$3=0,Inputs!$B$3*Inputs!$B$12,IF(H$3=7,-Inputs!$B$3*Inputs!$B$12,0)) -> 0 | I7: =IF(I$3=0,Inputs!$B$3*Inputs!$B$12,IF(I$3=7,-Inputs!$B$3*Inputs!$B$12,0)) -> -95400000
A8: Cash flow (EUR) | B8: =-Inputs!$B$3+B7 -> -116600000 | C8: =C4-C5+C6+C7 -> 8079400 | D8: =D4-D5+D6+D7 -> 8327200 | E8: =E4-E5+E6+E7 -> 8580203.8 | F8: =F4-F5+F6+F7 -> 8838520.7 | G8: =G4-G5+G6+G7 -> -514884.45 | H8: =H4-H5+H6+H7 -> 9371542.3 | I8: =I4-I5+I6+I7 -> 2.0156829e+08
A9: FX rate | B9: =Inputs!$B$9+(Inputs!$B$10-Inputs!$B$9)*B$3/7 -> 1.085 | C9: =Inputs!$B$9+(Inputs!$B$10-Inputs!$B$9)*C$3/7 -> 1.09 | D9: =Inputs!$B$9+(Inputs!$B$10-Inputs!$B$9)*D$3/7 -> 1.095 | E9: =Inputs!$B$9+(Inputs!$B$10-Inputs!$B$9)*E$3/7 -> 1.1 | F9: =Inputs!$B$9+(Inputs!$B$10-Inputs!$B$9)*F$3/7 -> 1.105 | G9: =Inputs!$B$9+(Inputs!$B$10-Inputs!$B$9)*G$3/7 -> 1.11 | H9: =Inputs!$B$9+(Inputs!$B$10-Inputs!$B$9)*H$3/7 -> 1.115 | I9: =Inputs!$B$9+(Inputs!$B$10-Inputs!$B$9)*I$3/7 -> 1.12
A10: Hedge cost (USD) | B10: =0 -> 0 | C10: =Inputs!$B$3*(1-Inputs!$B$12)*Inputs!$B$11*C9 -> 1461581 | D10: =Inputs!$B$3*(1-Inputs!$B$12)*Inputs!$B$11*D9 -> 1468285.5 | E10: =Inputs!$B$3*(1-Inputs!$B$12)*Inputs!$B$11*E9 -> 1474990 | F10: =Inputs!$B$3*(1-Inputs!$B$12)*Inputs!$B$11*F9 -> 1481694.5 | G10: =Inputs!$B$3*(1-Inputs!$B$12)*Inputs!$B$11*G9 -> 1488399 | H10: =Inputs!$B$3*(1-Inputs!$B$12)*Inputs!$B$11*H9 -> 1495103.5 | I10: =Inputs!$B$3*(1-Inputs!$B$12)*Inputs!$B$11*I9 -> 1501808
A11: Cash flow (USD) | B11: =B8*B9-B10 -> -126511000 | C11: =C8*C9-C10 -> 7344965 | D11: =D8*D9-D10 -> 7649998.5 | E11: =E8*E9-E10 -> 7963234.2 | F11: =F8*F9-F10 -> 8284870.9 | G11: =G8*G9-G10 -> -2059920.7 | H11: =H8*H9-H10 -> 8954166.2 | I11: =I8*I9-I10 -> 2.2425467e+08

Sheet Returns
A3: Levered IRR (EUR) | B3: =IRR('Cash Flow'!$B$8:$I$8) -> 0.12728571
A4: Levered IRR (USD) | B4: =IRR('Cash Flow'!$B$11:$I$11) -> 0.12270721
A5: Net profit (EUR) | B5: =SUM('Cash Flow'!$B$8:$I$8) -> 1.2765027e+08
A6: Net profit (USD) | B6: =SUM('Cash Flow'!$B$11:$I$11) -> 1.3588099e+08
A7: FX gain or loss (USD) | B7: =B6-B5*Inputs!$B$9 -> -2619554.8
A8: Hedge cost over the hold (USD) | B8: =SUM('Cash Flow'!$B$10:$I$10) -> 10371862
