Workbook

Sheet Inputs
A1: NORDIC CORE PROPERTY FUND – OPEN-ENDED, QUARTERLY (EUR)
A3: Property value (EUR) | B3: 1800000000
A4: Cash (EUR) | B4: 90000000
A5: Debt (EUR) | B5: 420000000
A6: NOI yield on value | B6: 0.048
A7: Capital growth a year | B7: 0.01
A8: Subscriptions a quarter (EUR) | B8: 20000000
A9: Redemption requests a quarter (EUR) | B9: 160000000
A10: Gate (share of NAV a quarter) | B10: 0.1
A11: Dilution levy on redemptions | B11: 0.01
A12: Management fee a year (of NAV) | B12: 0.0065
A13: Units in issue | B13: 13000000
A14: Minimum cash (share of NAV) | B14: 0.03

Sheet NAV
A3: Quarter | B3: 0 | C3: 1 | D3: 2 | E3: 3 | F3: 4 | G3: 5 | H3: 6 | I3: 7 | J3: 8 | K3: 9 | L3: 10 | M3: 11 | N3: 12
A4: Property value | B4: =Inputs!$B$3 -> 1800000000 | C4: =B4*(1+Inputs!$B$7)^(1/4)-C10 -> 1.7440645e+09 | D4: =C4*(1+Inputs!$B$7)^(1/4)-D10 -> 1.6547207e+09 | E4: =D4*(1+Inputs!$B$7)^(1/4)-E10 -> 1.5730967e+09 | F4: =E4*(1+Inputs!$B$7)^(1/4)-F10 -> 1.4985423e+09 | G4: =F4*(1+Inputs!$B$7)^(1/4)-G10 -> 1.430445e+09 | H4: =G4*(1+Inputs!$B$7)^(1/4)-H10 -> 1.3682457e+09 | I4: =H4*(1+Inputs!$B$7)^(1/4)-I10 -> 1.3114334e+09 | J4: =I4*(1+Inputs!$B$7)^(1/4)-J10 -> 1.2595417e+09 | ... N4: =M4*(1+Inputs!$B$7)^(1/4)-N10 -> 1.0931914e+09
A5: Income | B5: =0 -> 0 | C5: =B4*Inputs!$B$6/4 -> 21600000 | D5: =C4*Inputs!$B$6/4 -> 20928774 | E5: =D4*Inputs!$B$6/4 -> 19856648 | F5: =E4*Inputs!$B$6/4 -> 18877161 | G5: =F4*Inputs!$B$6/4 -> 17982507 | H5: =G4*Inputs!$B$6/4 -> 17165340 | I5: =H4*Inputs!$B$6/4 -> 16418948 | J5: =I4*Inputs!$B$6/4 -> 15737201 | ... N5: =M4*Inputs!$B$6/4 -> 13551712
A6: Fee | B6: =0 -> 0 | C6: =B12*Inputs!$B$12/4 -> 2388750 | D6: =C12*Inputs!$B$12/4 -> 2223267.3 | E6: =D12*Inputs!$B$12/4 -> 2073119.1 | F6: =E12*Inputs!$B$12/4 -> 1935975.8 | G6: =F12*Inputs!$B$12/4 -> 1810710.5 | H6: =G12*Inputs!$B$12/4 -> 1696294.5 | I6: =H12*Inputs!$B$12/4 -> 1591788 | J6: =I12*Inputs!$B$12/4 -> 1496332.9 | ... N6: =M12*Inputs!$B$12/4 -> 1190330.7
A7: Requests | B7: =0 -> 0 | C7: =Inputs!$B$9+B9 -> 160000000 | D7: =Inputs!$B$9+C9 -> 173000000 | E7: =Inputs!$B$9+D9 -> 1.9618355e+08 | F7: =Inputs!$B$9+E9 -> 2.2860699e+08 | G7: =Inputs!$B$9+F9 -> 2.6947002e+08 | H7: =Inputs!$B$9+G9 -> 3.1804168e+08 | I7: =Inputs!$B$9+H9 -> 3.7365433e+08 | J7: =Inputs!$B$9+I9 -> 4.3569815e+08 | ... N7: =Inputs!$B$9+M9 -> 7.3774389e+08
A8: Paid out | B8: =0 -> 0 | C8: =MIN(C7,B12*Inputs!$B$10)*(1-Inputs!$B$11) -> 145530000 | D8: =MIN(D7,C12*Inputs!$B$10)*(1-Inputs!$B$11) -> 1.3544828e+08 | E8: =MIN(E7,D12*Inputs!$B$10)*(1-Inputs!$B$11) -> 1.2630079e+08 | F8: =MIN(F7,E12*Inputs!$B$10)*(1-Inputs!$B$11) -> 1.179456e+08 | G8: =MIN(G7,F12*Inputs!$B$10)*(1-Inputs!$B$11) -> 1.1031405e+08 | H8: =MIN(H7,G12*Inputs!$B$10)*(1-Inputs!$B$11) -> 1.0334348e+08 | I8: =MIN(I7,H12*Inputs!$B$10)*(1-Inputs!$B$11) -> 96976624 | J8: =MIN(J7,I12*Inputs!$B$10)*(1-Inputs!$B$11) -> 91161205 | ... N8: =MIN(N7,M12*Inputs!$B$10)*(1-Inputs!$B$11) -> 72518610
A9: Queue | B9: =0 -> 0 | C9: =C7-C8/(1-Inputs!$B$11) -> 13000000 | D9: =D7-D8/(1-Inputs!$B$11) -> 36183553 | E9: =E7-E8/(1-Inputs!$B$11) -> 68606993 | F9: =F7-F8/(1-Inputs!$B$11) -> 1.0947002e+08 | G9: =G7-G8/(1-Inputs!$B$11) -> 1.5804168e+08 | H9: =H7-H8/(1-Inputs!$B$11) -> 2.1365433e+08 | I9: =I7-I8/(1-Inputs!$B$11) -> 2.7569815e+08 | J9: =J7-J8/(1-Inputs!$B$11) -> 3.4361612e+08 | ... N9: =N7-N8/(1-Inputs!$B$11) -> 6.6449276e+08
A10: Property sold | B10: =0 -> 0 | C10: =MAX(0,B12*Inputs!$B$14-(B11+C5-C6+Inputs!$B$8-C8)) -> 60418750 | D10: =MAX(0,C12*Inputs!$B$14-(C11+D5-D6+Inputs!$B$8-D8)) -> 93687711 | E10: =MAX(0,D12*Inputs!$B$14-(D11+E5-E6+Inputs!$B$8-E8)) -> 85745300 | F10: =MAX(0,E12*Inputs!$B$14-(E11+F5-F6+Inputs!$B$8-F8)) -> 78472540 | G10: =MAX(0,F12*Inputs!$B$14-(F11+G5-G6+Inputs!$B$8-G8)) -> 71829667 | H10: =MAX(0,G12*Inputs!$B$14-(G11+H5-H6+Inputs!$B$8-H8)) -> 65762136 | I10: =MAX(0,H12*Inputs!$B$14-(H11+I5-I6+Inputs!$B$8-I8)) -> 60220114 | J10: =MAX(0,I12*Inputs!$B$14-(I11+J5-J6+Inputs!$B$8-J8)) -> 55158089 | ... N10: =MAX(0,M12*Inputs!$B$14-(M11+N5-N6+Inputs!$B$8-N8)) -> 38930661
A11: Cash | B11: =Inputs!$B$4 -> 90000000 | C11: =B11+C5-C6+Inputs!$B$8-C8+C10 -> 44100000 | D11: =C11+D5-D6+Inputs!$B$8-D8+D10 -> 41044934 | E11: =D11+E5-E6+Inputs!$B$8-E8+E10 -> 38272968 | F11: =E11+F5-F6+Inputs!$B$8-F8+F10 -> 35741091 | G11: =F11+G5-G6+Inputs!$B$8-G8+G10 -> 33428501 | H11: =G11+H5-H6+Inputs!$B$8-H8+H10 -> 31316205 | I11: =H11+I5-I6+Inputs!$B$8-I8+I10 -> 29386856 | J11: =I11+J5-J6+Inputs!$B$8-J8+J10 -> 27624608 | ... N11: =M11+N5-N6+Inputs!$B$8-N8+N10 -> 21975336
A12: NAV | B12: =Inputs!$B$3+Inputs!$B$4-Inputs!$B$5 -> 1470000000 | C12: =C4+C11-Inputs!$B$5 -> 1.3681645e+09 | D12: =D4+D11-Inputs!$B$5 -> 1.2757656e+09 | E12: =E4+E11-Inputs!$B$5 -> 1.1913697e+09 | F12: =F4+F11-Inputs!$B$5 -> 1.1142834e+09 | G12: =G4+G11-Inputs!$B$5 -> 1.0438735e+09 | H12: =H4+H11-Inputs!$B$5 -> 9.7956186e+08 | I12: =I4+I11-Inputs!$B$5 -> 9.2082025e+08 | J12: =J4+J11-Inputs!$B$5 -> 8.6716628e+08 | ... N12: =N4+N11-Inputs!$B$5 -> 6.9516673e+08
A13: Units | B13: =Inputs!$B$13 -> 13000000 | C13: =B13+Inputs!$B$8/B14-C8/(1-Inputs!$B$11)/B14 -> 11876871 | D13: =C13+Inputs!$B$8/C14-D8/(1-Inputs!$B$11)/C14 -> 10862801 | E13: =D13+Inputs!$B$8/D14-E8/(1-Inputs!$B$11)/D14 -> 9946815.8 | F13: =E13+Inputs!$B$8/E14-F8/(1-Inputs!$B$11)/E14 -> 9119115.4 | G13: =F13+Inputs!$B$8/F14-G8/(1-Inputs!$B$11)/F14 -> 8370880.6 | H13: =G13+Inputs!$B$8/G14-H8/(1-Inputs!$B$11)/G14 -> 7694173.7 | I13: =H13+Inputs!$B$8/H14-I8/(1-Inputs!$B$11)/H14 -> 7081850.5 | J13: =I13+Inputs!$B$8/I14-J8/(1-Inputs!$B$11)/I14 -> 6527481.6 | ... N13: =M13+Inputs!$B$8/M14-N8/(1-Inputs!$B$11)/M14 -> 4782175.9
A14: NAV per unit | B14: =(Inputs!$B$3+Inputs!$B$4-Inputs!$B$5)/Inputs!$B$13 -> 113.07692 | C14: =C12/C13 -> 115.1957 | D14: =D12/D13 -> 117.44352 | E14: =E12/E13 -> 119.77398 | F14: =F12/F13 -> 122.19205 | G14: =G12/G13 -> 124.70295 | H14: =H12/H13 -> 127.31216 | I14: =I12/I13 -> 130.02537 | J14: =J12/J13 -> 132.84852 | ... N14: =N12/N13 -> 145.3662

Sheet Returns
A3: Total return a year (NAV per unit) | B3: =(NAV!N14/NAV!B14)^(4/12)-1 -> 0.087334454
A4: Redemption queue at the end (EUR) | B4: =NAV!N9 -> 6.6449276e+08
A5: Quarters gated | B5: =COUNTIF(NAV!$B$9:$N$9,">0") -> 12
A6: Property sold to pay redemptions (EUR) | B6: =SUM(NAV!$B$10:$N$10) -> 7.4952475e+08
A7: Loan to value at the end | B7: =Inputs!$B$5/NAV!N4 -> 0.38419622
A8: NAV at the end (EUR) | B8: =NAV!N12 -> 6.9516673e+08
