Workbook

Sheet Terms
A1: MERIDIAN REAL ESTATE FUND III – CLOSED-ENDED (EUR)
A3: Commitments (EUR) | B3: 400000000
A4: Management fee on commitments, years 1–4 | B4: 0.015
A5: Management fee on invested capital after year 4 | B5: 0.01
A6: Preferred return | B6: 0.08
A7: Carried interest | B7: 0.2
A8: GP catch-up | B8: 1
A9: Gross exit multiple on deals | B9: 1.75

Sheet Deals
A1: Deal | B1: Equity (EUR) | C1: Invest year | D1: Exit year | E1: Yield to equity
A2: Madrid offices | B2: 62000000 | C2: 1 | D2: 5 | E2: 0.045
A3: Lyon logistics | B3: 48000000 | C3: 1 | D3: 6 | E3: 0.055
A4: Milan resi | B4: 71000000 | C4: 2 | D4: 6 | E4: 0.04
A5: Berlin student | B5: 39000000 | C5: 2 | D5: 7 | E5: 0.05
A6: Warsaw retail | B6: 44000000 | C6: 3 | D6: 7 | E6: 0.065
A7: Lisbon hotel | B7: 56000000 | C7: 3 | D7: 8 | E7: 0.03

Sheet Fund
A3: Year | B3: 0 | C3: 1 | D3: 2 | E3: 3 | F3: 4 | G3: 5 | H3: 6 | I3: 7 | J3: 8 | K3: 9 | L3: 10
A4: Invested | B4: =SUMIF(Deals!$C$2:$C$7,B$3,Deals!$B$2:$B$7) -> 0 | C4: =SUMIF(Deals!$C$2:$C$7,C$3,Deals!$B$2:$B$7) -> 110000000 | D4: =SUMIF(Deals!$C$2:$C$7,D$3,Deals!$B$2:$B$7) -> 110000000 | E4: =SUMIF(Deals!$C$2:$C$7,E$3,Deals!$B$2:$B$7) -> 100000000 | F4: =SUMIF(Deals!$C$2:$C$7,F$3,Deals!$B$2:$B$7) -> 0 | G4: =SUMIF(Deals!$C$2:$C$7,G$3,Deals!$B$2:$B$7) -> 0 | H4: =SUMIF(Deals!$C$2:$C$7,H$3,Deals!$B$2:$B$7) -> 0 | I4: =SUMIF(Deals!$C$2:$C$7,I$3,Deals!$B$2:$B$7) -> 0 | ... L4: =SUMIF(Deals!$C$2:$C$7,L$3,Deals!$B$2:$B$7) -> 0
A5: Income | B5: =SUMPRODUCT((Deals!$C$2:$C$7<B$3)*(Deals!$D$2:$D$7>=B$3)*Deals!$B$2:$B$7*Deals!$E$2:$E$7) -> 0 | C5: =SUMPRODUCT((Deals!$C$2:$C$7<C$3)*(Deals!$D$2:$D$7>=C$3)*Deals!$B$2:$B$7*Deals!$E$2:$E$7) -> 0 | D5: =SUMPRODUCT((Deals!$C$2:$C$7<D$3)*(Deals!$D$2:$D$7>=D$3)*Deals!$B$2:$B$7*Deals!$E$2:$E$7) -> 5430000 | E5: =SUMPRODUCT((Deals!$C$2:$C$7<E$3)*(Deals!$D$2:$D$7>=E$3)*Deals!$B$2:$B$7*Deals!$E$2:$E$7) -> 10220000 | F5: =SUMPRODUCT((Deals!$C$2:$C$7<F$3)*(Deals!$D$2:$D$7>=F$3)*Deals!$B$2:$B$7*Deals!$E$2:$E$7) -> 14760000 | G5: =SUMPRODUCT((Deals!$C$2:$C$7<G$3)*(Deals!$D$2:$D$7>=G$3)*Deals!$B$2:$B$7*Deals!$E$2:$E$7) -> 14760000 | H5: =SUMPRODUCT((Deals!$C$2:$C$7<H$3)*(Deals!$D$2:$D$7>=H$3)*Deals!$B$2:$B$7*Deals!$E$2:$E$7) -> 11970000 | I5: =SUMPRODUCT((Deals!$C$2:$C$7<I$3)*(Deals!$D$2:$D$7>=I$3)*Deals!$B$2:$B$7*Deals!$E$2:$E$7) -> 6490000 | ... L5: =SUMPRODUCT((Deals!$C$2:$C$7<L$3)*(Deals!$D$2:$D$7>=L$3)*Deals!$B$2:$B$7*Deals!$E$2:$E$7) -> 0
A6: Exit proceeds | B6: =SUMIF(Deals!$D$2:$D$7,B$3,Deals!$B$2:$B$7)*Terms!$B$9 -> 0 | C6: =SUMIF(Deals!$D$2:$D$7,C$3,Deals!$B$2:$B$7)*Terms!$B$9 -> 0 | D6: =SUMIF(Deals!$D$2:$D$7,D$3,Deals!$B$2:$B$7)*Terms!$B$9 -> 0 | E6: =SUMIF(Deals!$D$2:$D$7,E$3,Deals!$B$2:$B$7)*Terms!$B$9 -> 0 | F6: =SUMIF(Deals!$D$2:$D$7,F$3,Deals!$B$2:$B$7)*Terms!$B$9 -> 0 | G6: =SUMIF(Deals!$D$2:$D$7,G$3,Deals!$B$2:$B$7)*Terms!$B$9 -> 108500000 | H6: =SUMIF(Deals!$D$2:$D$7,H$3,Deals!$B$2:$B$7)*Terms!$B$9 -> 208250000 | I6: =SUMIF(Deals!$D$2:$D$7,I$3,Deals!$B$2:$B$7)*Terms!$B$9 -> 145250000 | ... L6: =SUMIF(Deals!$D$2:$D$7,L$3,Deals!$B$2:$B$7)*Terms!$B$9 -> 0
A7: Management fee | B7: =IF(B$3=0,0,IF(B$3<=4,Terms!$B$3*Terms!$B$4,SUMPRODUCT((Deals!$C$2:$C$7<B$3)*(Deals!$D$2:$D$7>=B$3)*Deals!$B$2:$B$7)*Terms!$B$5)) -> 0 | C7: =IF(C$3=0,0,IF(C$3<=4,Terms!$B$3*Terms!$B$4,SUMPRODUCT((Deals!$C$2:$C$7<C$3)*(Deals!$D$2:$D$7>=C$3)*Deals!$B$2:$B$7)*Terms!$B$5)) -> 6000000 | D7: =IF(D$3=0,0,IF(D$3<=4,Terms!$B$3*Terms!$B$4,SUMPRODUCT((Deals!$C$2:$C$7<D$3)*(Deals!$D$2:$D$7>=D$3)*Deals!$B$2:$B$7)*Terms!$B$5)) -> 6000000 | E7: =IF(E$3=0,0,IF(E$3<=4,Terms!$B$3*Terms!$B$4,SUMPRODUCT((Deals!$C$2:$C$7<E$3)*(Deals!$D$2:$D$7>=E$3)*Deals!$B$2:$B$7)*Terms!$B$5)) -> 6000000 | F7: =IF(F$3=0,0,IF(F$3<=4,Terms!$B$3*Terms!$B$4,SUMPRODUCT((Deals!$C$2:$C$7<F$3)*(Deals!$D$2:$D$7>=F$3)*Deals!$B$2:$B$7)*Terms!$B$5)) -> 6000000 | G7: =IF(G$3=0,0,IF(G$3<=4,Terms!$B$3*Terms!$B$4,SUMPRODUCT((Deals!$C$2:$C$7<G$3)*(Deals!$D$2:$D$7>=G$3)*Deals!$B$2:$B$7)*Terms!$B$5)) -> 3200000 | H7: =IF(H$3=0,0,IF(H$3<=4,Terms!$B$3*Terms!$B$4,SUMPRODUCT((Deals!$C$2:$C$7<H$3)*(Deals!$D$2:$D$7>=H$3)*Deals!$B$2:$B$7)*Terms!$B$5)) -> 2580000 | I7: =IF(I$3=0,0,IF(I$3<=4,Terms!$B$3*Terms!$B$4,SUMPRODUCT((Deals!$C$2:$C$7<I$3)*(Deals!$D$2:$D$7>=I$3)*Deals!$B$2:$B$7)*Terms!$B$5)) -> 1390000 | ... L7: =IF(L$3=0,0,IF(L$3<=4,Terms!$B$3*Terms!$B$4,SUMPRODUCT((Deals!$C$2:$C$7<L$3)*(Deals!$D$2:$D$7>=L$3)*Deals!$B$2:$B$7)*Terms!$B$5)) -> 0
A8: Capital called | B8: =B4+B7 -> 0 | C8: =C4+C7 -> 116000000 | D8: =D4+D7 -> 116000000 | E8: =E4+E7 -> 106000000 | F8: =F4+F7 -> 6000000 | G8: =G4+G7 -> 3200000 | H8: =H4+H7 -> 2580000 | I8: =I4+I7 -> 1390000 | ... L8: =L4+L7 -> 0
A9: Distributions | B9: =B5+B6 -> 0 | C9: =C5+C6 -> 0 | D9: =D5+D6 -> 5430000 | E9: =E5+E6 -> 10220000 | F9: =F5+F6 -> 14760000 | G9: =G5+G6 -> 123260000 | H9: =H5+H6 -> 220220000 | I9: =I5+I6 -> 151740000 | ... L9: =L5+L6 -> 0
A10: Net cash to LPs | B10: =B9-B8-IF(B$3=10,Waterfall!$B$9-Waterfall!$B$11,0) -> 0 | C10: =C9-C8-IF(C$3=10,Waterfall!$B$9-Waterfall!$B$11,0) -> -116000000 | D10: =D9-D8-IF(D$3=10,Waterfall!$B$9-Waterfall!$B$11,0) -> -110570000 | E10: =E9-E8-IF(E$3=10,Waterfall!$B$9-Waterfall!$B$11,0) -> -95780000 | F10: =F9-F8-IF(F$3=10,Waterfall!$B$9-Waterfall!$B$11,0) -> 8760000 | G10: =G9-G8-IF(G$3=10,Waterfall!$B$9-Waterfall!$B$11,0) -> 120060000 | H10: =H9-H8-IF(H$3=10,Waterfall!$B$9-Waterfall!$B$11,0) -> 217640000 | I10: =I9-I8-IF(I$3=10,Waterfall!$B$9-Waterfall!$B$11,0) -> 150350000 | ... L10: =L9-L8-IF(L$3=10,Waterfall!$B$9-Waterfall!$B$11,0) -> -54716000
A11: Cumulative called | B11: =SUM($B$8:B8) -> 0 | C11: =SUM($B$8:C8) -> 116000000 | D11: =SUM($B$8:D8) -> 232000000 | E11: =SUM($B$8:E8) -> 338000000 | F11: =SUM($B$8:F8) -> 344000000 | G11: =SUM($B$8:G8) -> 347200000 | H11: =SUM($B$8:H8) -> 349780000 | I11: =SUM($B$8:I8) -> 351170000 | ... L11: =SUM($B$8:L8) -> 351730000
A12: Cumulative distributed | B12: =SUM($B$9:B9) -> 0 | C12: =SUM($B$9:C9) -> 0 | D12: =SUM($B$9:D9) -> 5430000 | E12: =SUM($B$9:E9) -> 15650000 | F12: =SUM($B$9:F9) -> 30410000 | G12: =SUM($B$9:G9) -> 153670000 | H12: =SUM($B$9:H9) -> 373890000 | I12: =SUM($B$9:I9) -> 525630000 | ... L12: =SUM($B$9:L9) -> 625310000
A13: Unrealised value | B13: =SUMPRODUCT((Deals!$C$2:$C$7<=B$3)*(Deals!$D$2:$D$7>B$3)*Deals!$B$2:$B$7)*(1+(Terms!$B$9-1)*0.5) -> 0 | C13: =SUMPRODUCT((Deals!$C$2:$C$7<=C$3)*(Deals!$D$2:$D$7>C$3)*Deals!$B$2:$B$7)*(1+(Terms!$B$9-1)*0.5) -> 151250000 | D13: =SUMPRODUCT((Deals!$C$2:$C$7<=D$3)*(Deals!$D$2:$D$7>D$3)*Deals!$B$2:$B$7)*(1+(Terms!$B$9-1)*0.5) -> 302500000 | E13: =SUMPRODUCT((Deals!$C$2:$C$7<=E$3)*(Deals!$D$2:$D$7>E$3)*Deals!$B$2:$B$7)*(1+(Terms!$B$9-1)*0.5) -> 440000000 | F13: =SUMPRODUCT((Deals!$C$2:$C$7<=F$3)*(Deals!$D$2:$D$7>F$3)*Deals!$B$2:$B$7)*(1+(Terms!$B$9-1)*0.5) -> 440000000 | G13: =SUMPRODUCT((Deals!$C$2:$C$7<=G$3)*(Deals!$D$2:$D$7>G$3)*Deals!$B$2:$B$7)*(1+(Terms!$B$9-1)*0.5) -> 354750000 | H13: =SUMPRODUCT((Deals!$C$2:$C$7<=H$3)*(Deals!$D$2:$D$7>H$3)*Deals!$B$2:$B$7)*(1+(Terms!$B$9-1)*0.5) -> 191125000 | I13: =SUMPRODUCT((Deals!$C$2:$C$7<=I$3)*(Deals!$D$2:$D$7>I$3)*Deals!$B$2:$B$7)*(1+(Terms!$B$9-1)*0.5) -> 77000000 | ... L13: =SUMPRODUCT((Deals!$C$2:$C$7<=L$3)*(Deals!$D$2:$D$7>L$3)*Deals!$B$2:$B$7)*(1+(Terms!$B$9-1)*0.5) -> 0
A14: DPI | B14: =IF(B11>0,B12/B11,0) -> 0 | C14: =IF(C11>0,C12/C11,0) -> 0 | D14: =IF(D11>0,D12/D11,0) -> 0.023405172 | E14: =IF(E11>0,E12/E11,0) -> 0.046301775 | F14: =IF(F11>0,F12/F11,0) -> 0.088401163 | G14: =IF(G11>0,G12/G11,0) -> 0.44259793 | H14: =IF(H11>0,H12/H11,0) -> 1.068929 | I14: =IF(I11>0,I12/I11,0) -> 1.4967964 | ... L14: =IF(L11>0,L12/L11,0) -> 1.7778125
A15: RVPI | B15: =IF(B11>0,B13/B11,0) -> 0 | C15: =IF(C11>0,C13/C11,0) -> 1.3038793 | D15: =IF(D11>0,D13/D11,0) -> 1.3038793 | E15: =IF(E11>0,E13/E11,0) -> 1.3017751 | F15: =IF(F11>0,F13/F11,0) -> 1.2790698 | G15: =IF(G11>0,G13/G11,0) -> 1.0217454 | H15: =IF(H11>0,H13/H11,0) -> 0.54641489 | I15: =IF(I11>0,I13/I11,0) -> 0.21926702 | ... L15: =IF(L11>0,L13/L11,0) -> 0
A16: TVPI | B16: =B14+B15 -> 0 | C16: =C14+C15 -> 1.3038793 | D16: =D14+D15 -> 1.3272845 | E16: =E14+E15 -> 1.3480769 | F16: =F14+F15 -> 1.3674709 | G16: =G14+G15 -> 1.4643433 | H16: =H14+H15 -> 1.6153439 | I16: =I14+I15 -> 1.7160634 | ... L16: =L14+L15 -> 1.7778125

Sheet Waterfall
A3: Total called | B3: =SUM(Fund!$B$8:$L$8) -> 351730000
A4: Total distributed | B4: =SUM(Fund!$B$9:$L$9) -> 625310000
A5: Profit | B5: =B4-B3 -> 273580000
A6: Preferred return | B6: =B3*((1+Terms!$B$6)^5-1) -> 1.6507676e+08
A7: GP catch-up | B7: =MIN(MAX(0,B5-B6),B6*Terms!$B$7/(1-Terms!$B$7)*Terms!$B$8) -> 41269191
A8: Split above | B8: =MAX(0,B5-B6-B7) -> 67234044
A9: Carried interest | B9: =B7+B8*Terms!$B$7 -> 54716000
A10: Carry if it were a fifth of profit | B10: =B5*Terms!$B$7 -> 54716000
A11: Clawback | B11: =MAX(0,B9-B10) -> 0
A12: Net to LPs | B12: =B4-B9+B11 -> 570594000

Sheet Returns
A3: Net IRR to LPs | B3: =IRR(Fund!$B$10:$L$10) -> 0.13479865
A4: TVPI at year 10 | B4: =Fund!L16 -> 1.7778125
A5: DPI at year 5 | B5: =Fund!G14 -> 0.44259793
A6: RVPI at year 5 | B6: =Fund!G15 -> 1.0217454
A7: Carried interest (EUR) | B7: =Waterfall!B9 -> 54716000
A8: Clawback (EUR) | B8: =Waterfall!B11 -> 0
A9: Peak capital called (EUR) | B9: =MAX(Fund!$B$11:$L$11) -> 351730000
