Workbook

Sheet Inputs
A1: WADI HANIFA LAND BANK (SAR)
A3: Land cost (SAR) | B3: 240000000
A4: Plots | B4: 400
A5: Sale price per plot (SAR) | B5: 1150000
A6: Infrastructure (SAR) | B6: 95000000
A7: First year of sales | B7: 2
A8: Last year of sales | B8: 6
A9: Discount rate | B9: 0.1

Sheet Cash Flow
A1: Year | B1: Plots sold | C1: Sales | D1: Costs | E1: Cash flow
A2: 0 | B2: =IF(AND(A2>=Inputs!$B$7,A2<=Inputs!$B$8),Inputs!$B$4/(Inputs!$B$8-Inputs!$B$7+1),0) -> 0 | C2: =B2*Inputs!$B$5*1.03^A2 -> 0 | D2: =IF(A2=0,Inputs!$B$3,0)+IF(AND(A2>=1,A2<=3),Inputs!$B$6/3,0) -> 240000000 | E2: =C2-D2 -> -240000000
A3: 1 | B3: =IF(AND(A3>=Inputs!$B$7,A3<=Inputs!$B$8),Inputs!$B$4/(Inputs!$B$8-Inputs!$B$7+1),0) -> 0 | C3: =B3*Inputs!$B$5*1.03^A3 -> 0 | D3: =IF(A3=0,Inputs!$B$3,0)+IF(AND(A3>=1,A3<=3),Inputs!$B$6/3,0) -> 31666667 | E3: =C3-D3 -> -31666667
A4: 2 | B4: =IF(AND(A4>=Inputs!$B$7,A4<=Inputs!$B$8),Inputs!$B$4/(Inputs!$B$8-Inputs!$B$7+1),0) -> 80 | C4: =B4*Inputs!$B$5*1.03^A4 -> 97602800 | D4: =IF(A4=0,Inputs!$B$3,0)+IF(AND(A4>=1,A4<=3),Inputs!$B$6/3,0) -> 31666667 | E4: =C4-D4 -> 65936133
A5: 3 | B5: =IF(AND(A5>=Inputs!$B$7,A5<=Inputs!$B$8),Inputs!$B$4/(Inputs!$B$8-Inputs!$B$7+1),0) -> 80 | C5: =B5*Inputs!$B$5*1.03^A5 -> 100530884 | D5: =IF(A5=0,Inputs!$B$3,0)+IF(AND(A5>=1,A5<=3),Inputs!$B$6/3,0) -> 31666667 | E5: =C5-D5 -> 68864217
A6: 4 | B6: =IF(AND(A6>=Inputs!$B$7,A6<=Inputs!$B$8),Inputs!$B$4/(Inputs!$B$8-Inputs!$B$7+1),0) -> 80 | C6: =B6*Inputs!$B$5*1.03^A6 -> 1.0354681e+08 | D6: =IF(A6=0,Inputs!$B$3,0)+IF(AND(A6>=1,A6<=3),Inputs!$B$6/3,0) -> 0 | E6: =C6-D6 -> 1.0354681e+08
A7: 5 | B7: =IF(AND(A7>=Inputs!$B$7,A7<=Inputs!$B$8),Inputs!$B$4/(Inputs!$B$8-Inputs!$B$7+1),0) -> 80 | C7: =B7*Inputs!$B$5*1.03^A7 -> 1.0665321e+08 | D7: =IF(A7=0,Inputs!$B$3,0)+IF(AND(A7>=1,A7<=3),Inputs!$B$6/3,0) -> 0 | E7: =C7-D7 -> 1.0665321e+08
A8: 6 | B8: =IF(AND(A8>=Inputs!$B$7,A8<=Inputs!$B$8),Inputs!$B$4/(Inputs!$B$8-Inputs!$B$7+1),0) -> 80 | C8: =B8*Inputs!$B$5*1.03^A8 -> 1.0985281e+08 | D8: =IF(A8=0,Inputs!$B$3,0)+IF(AND(A8>=1,A8<=3),Inputs!$B$6/3,0) -> 0 | E8: =C8-D8 -> 1.0985281e+08
A9: 7 | B9: =IF(AND(A9>=Inputs!$B$7,A9<=Inputs!$B$8),Inputs!$B$4/(Inputs!$B$8-Inputs!$B$7+1),0) -> 0 | C9: =B9*Inputs!$B$5*1.03^A9 -> 0 | D9: =IF(A9=0,Inputs!$B$3,0)+IF(AND(A9>=1,A9<=3),Inputs!$B$6/3,0) -> 0 | E9: =C9-D9 -> 0
A10: 8 | B10: =IF(AND(A10>=Inputs!$B$7,A10<=Inputs!$B$8),Inputs!$B$4/(Inputs!$B$8-Inputs!$B$7+1),0) -> 0 | C10: =B10*Inputs!$B$5*1.03^A10 -> 0 | D10: =IF(A10=0,Inputs!$B$3,0)+IF(AND(A10>=1,A10<=3),Inputs!$B$6/3,0) -> 0 | E10: =C10-D10 -> 0

Sheet Returns
A3: IRR | B3: =IRR('Cash Flow'!E2:E10) -> 0.13584556
A4: NPV at the discount rate (SAR) | B4: =NPV(Inputs!$B$9,'Cash Flow'!E3:E10)+'Cash Flow'!E2 -> 36399667
A5: Sales in the selling window (SAR) | B5: =SUM(INDIRECT("'Cash Flow'!C"&(Inputs!$B$7+2)&":C"&(Inputs!$B$8+2))) -> 5.1818652e+08
A6: Net profit (SAR) | B6: =SUM('Cash Flow'!E2:E10) -> 1.8318652e+08

Sheet Sensitivity
A1: Net profit (SAR m): land cost (rows) × sale price per plot (columns)
B2: 1000000 | C2: 1150000 | D2: 1300000
A3: 200000000 | B3: =(SUMPRODUCT('Cash Flow'!$B$2:$B$10,1.03^'Cash Flow'!$A$2:$A$10)*B$2-$A3-Inputs!$B$6)/1000000 -> 155.59697 | C3: =(SUMPRODUCT('Cash Flow'!$B$2:$B$10,1.03^'Cash Flow'!$A$2:$A$10)*C$2-$A3-Inputs!$B$6)/1000000 -> 223.18652 | D3: =(SUMPRODUCT('Cash Flow'!$B$2:$B$10,1.03^'Cash Flow'!$A$2:$A$10)*D$2-$A3-Inputs!$B$6)/1000000 -> 290.77607
A4: 240000000 | B4: =(SUMPRODUCT('Cash Flow'!$B$2:$B$10,1.03^'Cash Flow'!$A$2:$A$10)*B$2-$A4-Inputs!$B$6)/1000000 -> 115.59697 | C4: =(SUMPRODUCT('Cash Flow'!$B$2:$B$10,1.03^'Cash Flow'!$A$2:$A$10)*C$2-$A4-Inputs!$B$6)/1000000 -> 183.18652 | D4: =(SUMPRODUCT('Cash Flow'!$B$2:$B$10,1.03^'Cash Flow'!$A$2:$A$10)*D$2-$A4-Inputs!$B$6)/1000000 -> 250.77607
A5: 280000000 | B5: =(SUMPRODUCT('Cash Flow'!$B$2:$B$10,1.03^'Cash Flow'!$A$2:$A$10)*B$2-$A5-Inputs!$B$6)/1000000 -> 75.596974 | C5: =(SUMPRODUCT('Cash Flow'!$B$2:$B$10,1.03^'Cash Flow'!$A$2:$A$10)*C$2-$A5-Inputs!$B$6)/1000000 -> 143.18652 | D5: =(SUMPRODUCT('Cash Flow'!$B$2:$B$10,1.03^'Cash Flow'!$A$2:$A$10)*D$2-$A5-Inputs!$B$6)/1000000 -> 210.77607
