Workbook

Sheet Inputs
A1: SEEFELD BÜROHAUS – OFFICE, ZURICH (kCHF)
A3: Purchase price (kCHF) | B3: 68500
A4: Rent a year (kCHF) | B4: 2950
A5: CPI indexation | B5: 0.009
A6: SARON | B6: -0.0025
A7: Loan margin | B7: 0.0095
A8: LTV | B8: 0.55
A9: Exit yield | B9: 0.0385
A10: Operating costs (kCHF a year) | B10: 410

Sheet Cash Flow
A3: Year | B3: 0 | C3: 1 | D3: 2 | E3: 3 | F3: 4 | G3: 5 | H3: 6 | I3: 7 | J3: 8 | K3: 9 | L3: 10
A4: Rent | B4: =0 -> 0 | C4: =Inputs!$B$4*(1+Inputs!$B$5)^(C$3-1) -> 2950 | D4: =Inputs!$B$4*(1+Inputs!$B$5)^(D$3-1) -> 2976.55 | E4: =Inputs!$B$4*(1+Inputs!$B$5)^(E$3-1) -> 3003.3389 | F4: =Inputs!$B$4*(1+Inputs!$B$5)^(F$3-1) -> 3030.369 | G4: =Inputs!$B$4*(1+Inputs!$B$5)^(G$3-1) -> 3057.6423 | H4: =Inputs!$B$4*(1+Inputs!$B$5)^(H$3-1) -> 3085.1611 | I4: =Inputs!$B$4*(1+Inputs!$B$5)^(I$3-1) -> 3112.9276 | J4: =Inputs!$B$4*(1+Inputs!$B$5)^(J$3-1) -> 3140.9439 | ... L4: =Inputs!$B$4*(1+Inputs!$B$5)^(L$3-1) -> 3197.7353
A5: Costs | B5: =0 -> 0 | C5: =Inputs!$B$10*(1.01)^(C$3-1) -> 410 | D5: =Inputs!$B$10*(1.01)^(D$3-1) -> 414.1 | E5: =Inputs!$B$10*(1.01)^(E$3-1) -> 418.241 | F5: =Inputs!$B$10*(1.01)^(F$3-1) -> 422.42341 | G5: =Inputs!$B$10*(1.01)^(G$3-1) -> 426.64764 | H5: =Inputs!$B$10*(1.01)^(H$3-1) -> 430.91412 | I5: =Inputs!$B$10*(1.01)^(I$3-1) -> 435.22326 | J5: =Inputs!$B$10*(1.01)^(J$3-1) -> 439.57549 | ... L5: =Inputs!$B$10*(1.01)^(L$3-1) -> 448.41096
A6: Interest | B6: =0 -> 0 | C6: =Inputs!$B$3*Inputs!$B$8*(MAX(0,Inputs!$B$6)+Inputs!$B$7) -> 357.9125 | D6: =Inputs!$B$3*Inputs!$B$8*(MAX(0,Inputs!$B$6)+Inputs!$B$7) -> 357.9125 | E6: =Inputs!$B$3*Inputs!$B$8*(MAX(0,Inputs!$B$6)+Inputs!$B$7) -> 357.9125 | F6: =Inputs!$B$3*Inputs!$B$8*(MAX(0,Inputs!$B$6)+Inputs!$B$7) -> 357.9125 | G6: =Inputs!$B$3*Inputs!$B$8*(MAX(0,Inputs!$B$6)+Inputs!$B$7) -> 357.9125 | H6: =Inputs!$B$3*Inputs!$B$8*(MAX(0,Inputs!$B$6)+Inputs!$B$7) -> 357.9125 | I6: =Inputs!$B$3*Inputs!$B$8*(MAX(0,Inputs!$B$6)+Inputs!$B$7) -> 357.9125 | J6: =Inputs!$B$3*Inputs!$B$8*(MAX(0,Inputs!$B$6)+Inputs!$B$7) -> 357.9125 | ... L6: =Inputs!$B$3*Inputs!$B$8*(MAX(0,Inputs!$B$6)+Inputs!$B$7) -> 357.9125
A7: Loan | B7: =IF(B$3=0,Inputs!$B$3*Inputs!$B$8,IF(B$3=10,-Inputs!$B$3*Inputs!$B$8,0)) -> 37675 | C7: =IF(C$3=0,Inputs!$B$3*Inputs!$B$8,IF(C$3=10,-Inputs!$B$3*Inputs!$B$8,0)) -> 0 | D7: =IF(D$3=0,Inputs!$B$3*Inputs!$B$8,IF(D$3=10,-Inputs!$B$3*Inputs!$B$8,0)) -> 0 | E7: =IF(E$3=0,Inputs!$B$3*Inputs!$B$8,IF(E$3=10,-Inputs!$B$3*Inputs!$B$8,0)) -> 0 | F7: =IF(F$3=0,Inputs!$B$3*Inputs!$B$8,IF(F$3=10,-Inputs!$B$3*Inputs!$B$8,0)) -> 0 | G7: =IF(G$3=0,Inputs!$B$3*Inputs!$B$8,IF(G$3=10,-Inputs!$B$3*Inputs!$B$8,0)) -> 0 | H7: =IF(H$3=0,Inputs!$B$3*Inputs!$B$8,IF(H$3=10,-Inputs!$B$3*Inputs!$B$8,0)) -> 0 | I7: =IF(I$3=0,Inputs!$B$3*Inputs!$B$8,IF(I$3=10,-Inputs!$B$3*Inputs!$B$8,0)) -> 0 | ... L7: =IF(L$3=0,Inputs!$B$3*Inputs!$B$8,IF(L$3=10,-Inputs!$B$3*Inputs!$B$8,0)) -> -37675
A8: Exit | B8: =IF(B$3=10,B4*(1+Inputs!$B$5)/Inputs!$B$9,0) -> 0 | C8: =IF(C$3=10,C4*(1+Inputs!$B$5)/Inputs!$B$9,0) -> 0 | D8: =IF(D$3=10,D4*(1+Inputs!$B$5)/Inputs!$B$9,0) -> 0 | E8: =IF(E$3=10,E4*(1+Inputs!$B$5)/Inputs!$B$9,0) -> 0 | F8: =IF(F$3=10,F4*(1+Inputs!$B$5)/Inputs!$B$9,0) -> 0 | G8: =IF(G$3=10,G4*(1+Inputs!$B$5)/Inputs!$B$9,0) -> 0 | H8: =IF(H$3=10,H4*(1+Inputs!$B$5)/Inputs!$B$9,0) -> 0 | I8: =IF(I$3=10,I4*(1+Inputs!$B$5)/Inputs!$B$9,0) -> 0 | ... L8: =IF(L$3=10,L4*(1+Inputs!$B$5)/Inputs!$B$9,0) -> 83805.582
A9: Cash flow | B9: =-Inputs!$B$3+B7 -> -30825 | C9: =C4-C5-C6+C7+C8 -> 2182.0875 | D9: =D4-D5-D6+D7+D8 -> 2204.5375 | E9: =E4-E5-E6+E7+E8 -> 2227.1854 | F9: =F4-F5-F6+F7+F8 -> 2250.0331 | G9: =G4-G5-G6+G7+G8 -> 2273.0822 | H9: =H4-H5-H6+H7+H8 -> 2296.3345 | I9: =I4-I5-I6+I7+I8 -> 2319.7918 | J9: =J4-J5-J6+J7+J8 -> 2343.4559 | ... L9: =L4-L5-L6+L7+L8 -> 48521.994

Sheet Returns
A3: Levered IRR | B3: =IRR('Cash Flow'!$B$9:$L$9) -> 0.10408919
A4: All-in loan rate | B4: =MAX(0,Inputs!$B$6)+Inputs!$B$7 -> 0.0095
A5: Exit value (kCHF) | B5: =SUM('Cash Flow'!$B$8:$L$8) -> 83805.582
A6: Net profit (kCHF) | B6: =SUM('Cash Flow'!$B$9:$L$9) -> 38160.831
A7: Cash-on-cash, year 1 | B7: =('Cash Flow'!C4-'Cash Flow'!C5-'Cash Flow'!C6)/-'Cash Flow'!B9 -> 0.070789538
