Workbook

Sheet Inputs
A1: CEDAR CROSSING RETAIL PARK (USD)
A3: Valuation date | B3: 46387
A4: Purchase price (USD) | B4: 38000000
A5: Discount rate | B5: 0.075
A6: Exit cap rate | B6: 0.0675
A7: Market rent growth | B7: 0.025
A8: Fit-out start | B8: 46419
A9: Fit-out end | B9: 46535
A10: Non-recoverable costs (USD a year) | B10: 650000

Sheet Rent Roll
A1: Tenant | B1: Type | C1: Area (sq ft) | D1: Rent (USD/sq ft) | E1: Lease end | F1: Grade | H1: Years left | I1: Credit haircut | J1: Step-up
A2: Anchor grocer | B2: Anchor | C2: 62000 | D2: 14.5 | E2: 49705 | F2: A | H2: =DATEDIF(Inputs!$B$3,E2,"y") -> 9 | I2: =_xlfn.SWITCH(F2,"A",0,"B",0.02,"C",0.05,0.1) -> 0 | J2: =_xlfn.IFS(B2="Anchor",0.01,B2="Big box",0.015,B2="Pad",0.025,TRUE(),0.02) -> 0.01
A3: Home store | B3: Big box | C3: 38000 | D3: 16 | E3: 48029 | F3: B | H3: =DATEDIF(Inputs!$B$3,E3,"y") -> 4 | I3: =_xlfn.SWITCH(F3,"A",0,"B",0.02,"C",0.05,0.1) -> 0.02 | J3: =_xlfn.IFS(B3="Anchor",0.01,B3="Big box",0.015,B3="Pad",0.025,TRUE(),0.02) -> 0.015
A4: Pharmacy | B4: Shop | C4: 12000 | D4: 28 | E4: 47483 | F4: A | H4: =DATEDIF(Inputs!$B$3,E4,"y") -> 3 | I4: =_xlfn.SWITCH(F4,"A",0,"B",0.02,"C",0.05,0.1) -> 0 | J4: =_xlfn.IFS(B4="Anchor",0.01,B4="Big box",0.015,B4="Pad",0.025,TRUE(),0.02) -> 0.02
A5: Pet store | B5: Shop | C5: 9000 | D5: 24.5 | E5: 47756 | F5: C | H5: =DATEDIF(Inputs!$B$3,E5,"y") -> 3 | I5: =_xlfn.SWITCH(F5,"A",0,"B",0.02,"C",0.05,0.1) -> 0.05 | J5: =_xlfn.IFS(B5="Anchor",0.01,B5="Big box",0.015,B5="Pad",0.025,TRUE(),0.02) -> 0.02
A6: Restaurant pad | B6: Pad | C6: 6500 | D6: 42 | E6: 48669 | F6: B | H6: =DATEDIF(Inputs!$B$3,E6,"y") -> 6 | I6: =_xlfn.SWITCH(F6,"A",0,"B",0.02,"C",0.05,0.1) -> 0.02 | J6: =_xlfn.IFS(B6="Anchor",0.01,B6="Big box",0.015,B6="Pad",0.025,TRUE(),0.02) -> 0.025
A7: Gym | B7: Big box | C7: 24000 | D7: 15.5 | E7: 46996 | F7: C | H7: =DATEDIF(Inputs!$B$3,E7,"y") -> 1 | I7: =_xlfn.SWITCH(F7,"A",0,"B",0.02,"C",0.05,0.1) -> 0.05 | J7: =_xlfn.IFS(B7="Anchor",0.01,B7="Big box",0.015,B7="Pad",0.025,TRUE(),0.02) -> 0.015

Sheet Cash Flow
A3: Year | B3: 0 | C3: 1 | D3: 2 | E3: 3 | F3: 4 | G3: 5 | H3: 6 | I3: 7 | J3: 8 | K3: 9 | L3: 10
A4: Date | B4: =EDATE(Inputs!$B$3,12*B$3+IF(B$3>0,MOD(B$3,3),0)) -> 46387 | C4: =EDATE(Inputs!$B$3,12*C$3+IF(C$3>0,MOD(C$3,3),0)) -> 46783 | D4: =EDATE(Inputs!$B$3,12*D$3+IF(D$3>0,MOD(D$3,3),0)) -> 47177 | E4: =EDATE(Inputs!$B$3,12*E$3+IF(E$3>0,MOD(E$3,3),0)) -> 47483 | F4: =EDATE(Inputs!$B$3,12*F$3+IF(F$3>0,MOD(F$3,3),0)) -> 47879 | G4: =EDATE(Inputs!$B$3,12*G$3+IF(G$3>0,MOD(G$3,3),0)) -> 48273 | H4: =EDATE(Inputs!$B$3,12*H$3+IF(H$3>0,MOD(H$3,3),0)) -> 48579 | I4: =EDATE(Inputs!$B$3,12*I$3+IF(I$3>0,MOD(I$3,3),0)) -> 48975 | ... L4: =EDATE(Inputs!$B$3,12*L$3+IF(L$3>0,MOD(L$3,3),0)) -> 50071
A5: Rent | B5: =0 -> 0 | C5: =IF(C4<='Rent Roll'!$E$2,'Rent Roll'!$C$2*'Rent Roll'!$D$2*(1+'Rent Roll'!$J$2)^(C$3-1)*(1-'Rent Roll'!$I$2),'Rent Roll'!$C$2*'Rent Roll'!$D$2*(1+Inputs!$B$7)^C$3*0.9)+IF(C4<='Rent Roll'!$E$3,'Rent Roll'!$C$3*'Rent Roll'!$D$3*(1+'Rent Roll'!$J$3)^(C$3-1)*(1-'Rent Roll'!$I$3),'Rent Roll'!$C$3*'Rent Roll'!$D$3*(1+Inputs!$B$7)^C$3*0.9)+IF(C4<='Rent Roll'!$E$4,'Rent Roll'!$C$4*'Rent Roll'!$D$4*(1+'Rent Roll'!$J$4)^(C$3-1)*(1-'Rent Roll'!$I$4),'Rent Roll'!$C$4*'Rent Roll'!$D$4*(1+Inputs!$B$7)^C$3*0.9)+IF(C4<='Rent Roll'!$E$5,'Rent Roll'!$C$5*'Rent Roll'!$D$5*(1+'Rent Roll'!$J$5)^(C$3-1)*(1-'Rent Roll'!$I$5),'Rent Roll'!$C$5*'Rent Roll'!$D$5*(1+Inputs!$B$7)^C$3*0.9)+IF(C4<='Rent Roll'!$E$6,'Rent Roll'!$C$6*'Rent Roll'!$D$6*(1+'Rent Roll'!$J$6)^(C$3-1)*(1-'Rent Roll'!$I$6),'Rent Roll'!$C$6*'Rent Roll'!$D$6*(1+Inputs!$B$7)^C$3*0.9)+IF(C4<='Rent Roll'!$E$7,'Rent Roll'!$C$7*'Rent Roll'!$D$7*(1+'Rent Roll'!$J$7)^(C$3-1)*(1-'Rent Roll'!$I$7),'Rent Roll'!$C$7*'Rent Roll'!$D$7*(1+Inputs!$B$7)^C$3*0.9) -> 2661255 | D5: =IF(D4<='Rent Roll'!$E$2,'Rent Roll'!$C$2*'Rent Roll'!$D$2*(1+'Rent Roll'!$J$2)^(D$3-1)*(1-'Rent Roll'!$I$2),'Rent Roll'!$C$2*'Rent Roll'!$D$2*(1+Inputs!$B$7)^D$3*0.9)+IF(D4<='Rent Roll'!$E$3,'Rent Roll'!$C$3*'Rent Roll'!$D$3*(1+'Rent Roll'!$J$3)^(D$3-1)*(1-'Rent Roll'!$I$3),'Rent Roll'!$C$3*'Rent Roll'!$D$3*(1+Inputs!$B$7)^D$3*0.9)+IF(D4<='Rent Roll'!$E$4,'Rent Roll'!$C$4*'Rent Roll'!$D$4*(1+'Rent Roll'!$J$4)^(D$3-1)*(1-'Rent Roll'!$I$4),'Rent Roll'!$C$4*'Rent Roll'!$D$4*(1+Inputs!$B$7)^D$3*0.9)+IF(D4<='Rent Roll'!$E$5,'Rent Roll'!$C$5*'Rent Roll'!$D$5*(1+'Rent Roll'!$J$5)^(D$3-1)*(1-'Rent Roll'!$I$5),'Rent Roll'!$C$5*'Rent Roll'!$D$5*(1+Inputs!$B$7)^D$3*0.9)+IF(D4<='Rent Roll'!$E$6,'Rent Roll'!$C$6*'Rent Roll'!$D$6*(1+'Rent Roll'!$J$6)^(D$3-1)*(1-'Rent Roll'!$I$6),'Rent Roll'!$C$6*'Rent Roll'!$D$6*(1+Inputs!$B$7)^D$3*0.9)+IF(D4<='Rent Roll'!$E$7,'Rent Roll'!$C$7*'Rent Roll'!$D$7*(1+'Rent Roll'!$J$7)^(D$3-1)*(1-'Rent Roll'!$I$7),'Rent Roll'!$C$7*'Rent Roll'!$D$7*(1+Inputs!$B$7)^D$3*0.9) -> 2695129.9 | E5: =IF(E4<='Rent Roll'!$E$2,'Rent Roll'!$C$2*'Rent Roll'!$D$2*(1+'Rent Roll'!$J$2)^(E$3-1)*(1-'Rent Roll'!$I$2),'Rent Roll'!$C$2*'Rent Roll'!$D$2*(1+Inputs!$B$7)^E$3*0.9)+IF(E4<='Rent Roll'!$E$3,'Rent Roll'!$C$3*'Rent Roll'!$D$3*(1+'Rent Roll'!$J$3)^(E$3-1)*(1-'Rent Roll'!$I$3),'Rent Roll'!$C$3*'Rent Roll'!$D$3*(1+Inputs!$B$7)^E$3*0.9)+IF(E4<='Rent Roll'!$E$4,'Rent Roll'!$C$4*'Rent Roll'!$D$4*(1+'Rent Roll'!$J$4)^(E$3-1)*(1-'Rent Roll'!$I$4),'Rent Roll'!$C$4*'Rent Roll'!$D$4*(1+Inputs!$B$7)^E$3*0.9)+IF(E4<='Rent Roll'!$E$5,'Rent Roll'!$C$5*'Rent Roll'!$D$5*(1+'Rent Roll'!$J$5)^(E$3-1)*(1-'Rent Roll'!$I$5),'Rent Roll'!$C$5*'Rent Roll'!$D$5*(1+Inputs!$B$7)^E$3*0.9)+IF(E4<='Rent Roll'!$E$6,'Rent Roll'!$C$6*'Rent Roll'!$D$6*(1+'Rent Roll'!$J$6)^(E$3-1)*(1-'Rent Roll'!$I$6),'Rent Roll'!$C$6*'Rent Roll'!$D$6*(1+Inputs!$B$7)^E$3*0.9)+IF(E4<='Rent Roll'!$E$7,'Rent Roll'!$C$7*'Rent Roll'!$D$7*(1+'Rent Roll'!$J$7)^(E$3-1)*(1-'Rent Roll'!$I$7),'Rent Roll'!$C$7*'Rent Roll'!$D$7*(1+Inputs!$B$7)^E$3*0.9) -> 2740058.5 | F5: =IF(F4<='Rent Roll'!$E$2,'Rent Roll'!$C$2*'Rent Roll'!$D$2*(1+'Rent Roll'!$J$2)^(F$3-1)*(1-'Rent Roll'!$I$2),'Rent Roll'!$C$2*'Rent Roll'!$D$2*(1+Inputs!$B$7)^F$3*0.9)+IF(F4<='Rent Roll'!$E$3,'Rent Roll'!$C$3*'Rent Roll'!$D$3*(1+'Rent Roll'!$J$3)^(F$3-1)*(1-'Rent Roll'!$I$3),'Rent Roll'!$C$3*'Rent Roll'!$D$3*(1+Inputs!$B$7)^F$3*0.9)+IF(F4<='Rent Roll'!$E$4,'Rent Roll'!$C$4*'Rent Roll'!$D$4*(1+'Rent Roll'!$J$4)^(F$3-1)*(1-'Rent Roll'!$I$4),'Rent Roll'!$C$4*'Rent Roll'!$D$4*(1+Inputs!$B$7)^F$3*0.9)+IF(F4<='Rent Roll'!$E$5,'Rent Roll'!$C$5*'Rent Roll'!$D$5*(1+'Rent Roll'!$J$5)^(F$3-1)*(1-'Rent Roll'!$I$5),'Rent Roll'!$C$5*'Rent Roll'!$D$5*(1+Inputs!$B$7)^F$3*0.9)+IF(F4<='Rent Roll'!$E$6,'Rent Roll'!$C$6*'Rent Roll'!$D$6*(1+'Rent Roll'!$J$6)^(F$3-1)*(1-'Rent Roll'!$I$6),'Rent Roll'!$C$6*'Rent Roll'!$D$6*(1+Inputs!$B$7)^F$3*0.9)+IF(F4<='Rent Roll'!$E$7,'Rent Roll'!$C$7*'Rent Roll'!$D$7*(1+'Rent Roll'!$J$7)^(F$3-1)*(1-'Rent Roll'!$I$7),'Rent Roll'!$C$7*'Rent Roll'!$D$7*(1+Inputs!$B$7)^F$3*0.9) -> 2759810.2 | G5: =IF(G4<='Rent Roll'!$E$2,'Rent Roll'!$C$2*'Rent Roll'!$D$2*(1+'Rent Roll'!$J$2)^(G$3-1)*(1-'Rent Roll'!$I$2),'Rent Roll'!$C$2*'Rent Roll'!$D$2*(1+Inputs!$B$7)^G$3*0.9)+IF(G4<='Rent Roll'!$E$3,'Rent Roll'!$C$3*'Rent Roll'!$D$3*(1+'Rent Roll'!$J$3)^(G$3-1)*(1-'Rent Roll'!$I$3),'Rent Roll'!$C$3*'Rent Roll'!$D$3*(1+Inputs!$B$7)^G$3*0.9)+IF(G4<='Rent Roll'!$E$4,'Rent Roll'!$C$4*'Rent Roll'!$D$4*(1+'Rent Roll'!$J$4)^(G$3-1)*(1-'Rent Roll'!$I$4),'Rent Roll'!$C$4*'Rent Roll'!$D$4*(1+Inputs!$B$7)^G$3*0.9)+IF(G4<='Rent Roll'!$E$5,'Rent Roll'!$C$5*'Rent Roll'!$D$5*(1+'Rent Roll'!$J$5)^(G$3-1)*(1-'Rent Roll'!$I$5),'Rent Roll'!$C$5*'Rent Roll'!$D$5*(1+Inputs!$B$7)^G$3*0.9)+IF(G4<='Rent Roll'!$E$6,'Rent Roll'!$C$6*'Rent Roll'!$D$6*(1+'Rent Roll'!$J$6)^(G$3-1)*(1-'Rent Roll'!$I$6),'Rent Roll'!$C$6*'Rent Roll'!$D$6*(1+Inputs!$B$7)^G$3*0.9)+IF(G4<='Rent Roll'!$E$7,'Rent Roll'!$C$7*'Rent Roll'!$D$7*(1+'Rent Roll'!$J$7)^(G$3-1)*(1-'Rent Roll'!$I$7),'Rent Roll'!$C$7*'Rent Roll'!$D$7*(1+Inputs!$B$7)^G$3*0.9) -> 2795385 | H5: =IF(H4<='Rent Roll'!$E$2,'Rent Roll'!$C$2*'Rent Roll'!$D$2*(1+'Rent Roll'!$J$2)^(H$3-1)*(1-'Rent Roll'!$I$2),'Rent Roll'!$C$2*'Rent Roll'!$D$2*(1+Inputs!$B$7)^H$3*0.9)+IF(H4<='Rent Roll'!$E$3,'Rent Roll'!$C$3*'Rent Roll'!$D$3*(1+'Rent Roll'!$J$3)^(H$3-1)*(1-'Rent Roll'!$I$3),'Rent Roll'!$C$3*'Rent Roll'!$D$3*(1+Inputs!$B$7)^H$3*0.9)+IF(H4<='Rent Roll'!$E$4,'Rent Roll'!$C$4*'Rent Roll'!$D$4*(1+'Rent Roll'!$J$4)^(H$3-1)*(1-'Rent Roll'!$I$4),'Rent Roll'!$C$4*'Rent Roll'!$D$4*(1+Inputs!$B$7)^H$3*0.9)+IF(H4<='Rent Roll'!$E$5,'Rent Roll'!$C$5*'Rent Roll'!$D$5*(1+'Rent Roll'!$J$5)^(H$3-1)*(1-'Rent Roll'!$I$5),'Rent Roll'!$C$5*'Rent Roll'!$D$5*(1+Inputs!$B$7)^H$3*0.9)+IF(H4<='Rent Roll'!$E$6,'Rent Roll'!$C$6*'Rent Roll'!$D$6*(1+'Rent Roll'!$J$6)^(H$3-1)*(1-'Rent Roll'!$I$6),'Rent Roll'!$C$6*'Rent Roll'!$D$6*(1+Inputs!$B$7)^H$3*0.9)+IF(H4<='Rent Roll'!$E$7,'Rent Roll'!$C$7*'Rent Roll'!$D$7*(1+'Rent Roll'!$J$7)^(H$3-1)*(1-'Rent Roll'!$I$7),'Rent Roll'!$C$7*'Rent Roll'!$D$7*(1+Inputs!$B$7)^H$3*0.9) -> 2851237 | I5: =IF(I4<='Rent Roll'!$E$2,'Rent Roll'!$C$2*'Rent Roll'!$D$2*(1+'Rent Roll'!$J$2)^(I$3-1)*(1-'Rent Roll'!$I$2),'Rent Roll'!$C$2*'Rent Roll'!$D$2*(1+Inputs!$B$7)^I$3*0.9)+IF(I4<='Rent Roll'!$E$3,'Rent Roll'!$C$3*'Rent Roll'!$D$3*(1+'Rent Roll'!$J$3)^(I$3-1)*(1-'Rent Roll'!$I$3),'Rent Roll'!$C$3*'Rent Roll'!$D$3*(1+Inputs!$B$7)^I$3*0.9)+IF(I4<='Rent Roll'!$E$4,'Rent Roll'!$C$4*'Rent Roll'!$D$4*(1+'Rent Roll'!$J$4)^(I$3-1)*(1-'Rent Roll'!$I$4),'Rent Roll'!$C$4*'Rent Roll'!$D$4*(1+Inputs!$B$7)^I$3*0.9)+IF(I4<='Rent Roll'!$E$5,'Rent Roll'!$C$5*'Rent Roll'!$D$5*(1+'Rent Roll'!$J$5)^(I$3-1)*(1-'Rent Roll'!$I$5),'Rent Roll'!$C$5*'Rent Roll'!$D$5*(1+Inputs!$B$7)^I$3*0.9)+IF(I4<='Rent Roll'!$E$6,'Rent Roll'!$C$6*'Rent Roll'!$D$6*(1+'Rent Roll'!$J$6)^(I$3-1)*(1-'Rent Roll'!$I$6),'Rent Roll'!$C$6*'Rent Roll'!$D$6*(1+Inputs!$B$7)^I$3*0.9)+IF(I4<='Rent Roll'!$E$7,'Rent Roll'!$C$7*'Rent Roll'!$D$7*(1+'Rent Roll'!$J$7)^(I$3-1)*(1-'Rent Roll'!$I$7),'Rent Roll'!$C$7*'Rent Roll'!$D$7*(1+Inputs!$B$7)^I$3*0.9) -> 2890140.8 | J5: =IF(J4<='Rent Roll'!$E$2,'Rent Roll'!$C$2*'Rent Roll'!$D$2*(1+'Rent Roll'!$J$2)^(J$3-1)*(1-'Rent Roll'!$I$2),'Rent Roll'!$C$2*'Rent Roll'!$D$2*(1+Inputs!$B$7)^J$3*0.9)+IF(J4<='Rent Roll'!$E$3,'Rent Roll'!$C$3*'Rent Roll'!$D$3*(1+'Rent Roll'!$J$3)^(J$3-1)*(1-'Rent Roll'!$I$3),'Rent Roll'!$C$3*'Rent Roll'!$D$3*(1+Inputs!$B$7)^J$3*0.9)+IF(J4<='Rent Roll'!$E$4,'Rent Roll'!$C$4*'Rent Roll'!$D$4*(1+'Rent Roll'!$J$4)^(J$3-1)*(1-'Rent Roll'!$I$4),'Rent Roll'!$C$4*'Rent Roll'!$D$4*(1+Inputs!$B$7)^J$3*0.9)+IF(J4<='Rent Roll'!$E$5,'Rent Roll'!$C$5*'Rent Roll'!$D$5*(1+'Rent Roll'!$J$5)^(J$3-1)*(1-'Rent Roll'!$I$5),'Rent Roll'!$C$5*'Rent Roll'!$D$5*(1+Inputs!$B$7)^J$3*0.9)+IF(J4<='Rent Roll'!$E$6,'Rent Roll'!$C$6*'Rent Roll'!$D$6*(1+'Rent Roll'!$J$6)^(J$3-1)*(1-'Rent Roll'!$I$6),'Rent Roll'!$C$6*'Rent Roll'!$D$6*(1+Inputs!$B$7)^J$3*0.9)+IF(J4<='Rent Roll'!$E$7,'Rent Roll'!$C$7*'Rent Roll'!$D$7*(1+'Rent Roll'!$J$7)^(J$3-1)*(1-'Rent Roll'!$I$7),'Rent Roll'!$C$7*'Rent Roll'!$D$7*(1+Inputs!$B$7)^J$3*0.9) -> 2948079.7 | ... L5: =IF(L4<='Rent Roll'!$E$2,'Rent Roll'!$C$2*'Rent Roll'!$D$2*(1+'Rent Roll'!$J$2)^(L$3-1)*(1-'Rent Roll'!$I$2),'Rent Roll'!$C$2*'Rent Roll'!$D$2*(1+Inputs!$B$7)^L$3*0.9)+IF(L4<='Rent Roll'!$E$3,'Rent Roll'!$C$3*'Rent Roll'!$D$3*(1+'Rent Roll'!$J$3)^(L$3-1)*(1-'Rent Roll'!$I$3),'Rent Roll'!$C$3*'Rent Roll'!$D$3*(1+Inputs!$B$7)^L$3*0.9)+IF(L4<='Rent Roll'!$E$4,'Rent Roll'!$C$4*'Rent Roll'!$D$4*(1+'Rent Roll'!$J$4)^(L$3-1)*(1-'Rent Roll'!$I$4),'Rent Roll'!$C$4*'Rent Roll'!$D$4*(1+Inputs!$B$7)^L$3*0.9)+IF(L4<='Rent Roll'!$E$5,'Rent Roll'!$C$5*'Rent Roll'!$D$5*(1+'Rent Roll'!$J$5)^(L$3-1)*(1-'Rent Roll'!$I$5),'Rent Roll'!$C$5*'Rent Roll'!$D$5*(1+Inputs!$B$7)^L$3*0.9)+IF(L4<='Rent Roll'!$E$6,'Rent Roll'!$C$6*'Rent Roll'!$D$6*(1+'Rent Roll'!$J$6)^(L$3-1)*(1-'Rent Roll'!$I$6),'Rent Roll'!$C$6*'Rent Roll'!$D$6*(1+Inputs!$B$7)^L$3*0.9)+IF(L4<='Rent Roll'!$E$7,'Rent Roll'!$C$7*'Rent Roll'!$D$7*(1+'Rent Roll'!$J$7)^(L$3-1)*(1-'Rent Roll'!$I$7),'Rent Roll'!$C$7*'Rent Roll'!$D$7*(1+Inputs!$B$7)^L$3*0.9) -> 3120398.1
A6: Costs | B6: =0 -> 0 | C6: =Inputs!$B$10*(1.03)^(C$3-1) -> 650000 | D6: =Inputs!$B$10*(1.03)^(D$3-1) -> 669500 | E6: =Inputs!$B$10*(1.03)^(E$3-1) -> 689585 | F6: =Inputs!$B$10*(1.03)^(F$3-1) -> 710272.55 | G6: =Inputs!$B$10*(1.03)^(G$3-1) -> 731580.73 | H6: =Inputs!$B$10*(1.03)^(H$3-1) -> 753528.15 | I6: =Inputs!$B$10*(1.03)^(I$3-1) -> 776133.99 | J6: =Inputs!$B$10*(1.03)^(J$3-1) -> 799418.01 | ... L6: =Inputs!$B$10*(1.03)^(L$3-1) -> 848102.57
A7: Exit | B7: =IF(B$3=10,B5*1.025/Inputs!$B$6,0) -> 0 | C7: =IF(C$3=10,C5*1.025/Inputs!$B$6,0) -> 0 | D7: =IF(D$3=10,D5*1.025/Inputs!$B$6,0) -> 0 | E7: =IF(E$3=10,E5*1.025/Inputs!$B$6,0) -> 0 | F7: =IF(F$3=10,F5*1.025/Inputs!$B$6,0) -> 0 | G7: =IF(G$3=10,G5*1.025/Inputs!$B$6,0) -> 0 | H7: =IF(H$3=10,H5*1.025/Inputs!$B$6,0) -> 0 | I7: =IF(I$3=10,I5*1.025/Inputs!$B$6,0) -> 0 | ... L7: =IF(L$3=10,L5*1.025/Inputs!$B$6,0) -> 47383823
A8: Cash flow | B8: =-Inputs!$B$4-NETWORKDAYS(Inputs!$B$8,Inputs!$B$9)*4500 -> -38382500 | C8: =C5-C6+C7 -> 2011255 | D8: =D5-D6+D7 -> 2025629.9 | E8: =E5-E6+E7 -> 2050473.5 | F8: =F5-F6+F7 -> 2049537.6 | G8: =G5-G6+G7 -> 2063804.2 | H8: =H5-H6+H7 -> 2097708.9 | I8: =I5-I6+I7 -> 2114006.8 | J8: =J5-J6+J7 -> 2148661.7 | ... L8: =L5-L6+L7 -> 49656118

Sheet Returns
A3: Unlevered IRR | B3: =XIRR('Cash Flow'!$B$8:$L$8,'Cash Flow'!$B$4:$L$4) -> 0.070449461
A4: NPV at the discount rate (USD) | B4: =XNPV(Inputs!$B$5,'Cash Flow'!$B$8:$L$8,'Cash Flow'!$B$4:$L$4) -> -1310746.3
A5: Highest rent (USD/sq ft) | B5: =_xlfn.MAXIFS('Rent Roll'!D2:D7,'Rent Roll'!B2:B7,"<>Anchor") -> 42
A6: Lowest big-box rent (USD/sq ft) | B6: =_xlfn.MINIFS('Rent Roll'!D2:D7,'Rent Roll'!B2:B7,"Big box") -> 15.5
A7: Fit-out working days | B7: =NETWORKDAYS(Inputs!$B$8,Inputs!$B$9) -> 85
A8: WALE (years) | B8: =SUMPRODUCT('Rent Roll'!C2:C7,'Rent Roll'!H2:H7)/SUM('Rent Roll'!C2:C7) -> 5.5181518
A9: Net profit (USD) | B9: =SUM('Cash Flow'!$B$8:$L$8) -> 30018619
