Workbook

Sheet Inputs
A1: RIVERSIDE GREENS, PUNE – BUILD TO SELL (₹ crore)
A3: Apartments | B3: 820
A4: Saleable area per apartment (sq ft) | B4: 1150
A5: Sale rate (₹ per sq ft) | B5: 8200
A6: Construction cost (₹ crore) | B6: 412
A7: Land (₹ crore) | B7: 165
A8: GST on sales | B8: 0.05
A9: Sales period (quarters) | B9: 10
A10: Discount rate | B10: 0.14

Sheet Cash Flow
A3: Quarter | B3: 0 | C3: 1 | D3: 2 | E3: 3 | F3: 4 | G3: 5 | H3: 6 | I3: 7 | J3: 8 | K3: 9 | L3: 10 | M3: 11 | N3: 12 | O3: 13 | P3: 14
A4: Sales (₹ crore) | B4: =IF(AND(B$3>=2,B$3<2+Inputs!$B$9),Inputs!$B$3*Inputs!$B$4*Inputs!$B$5*1.01^B$3/Inputs!$B$9/10000000,0) -> 0 | C4: =IF(AND(C$3>=2,C$3<2+Inputs!$B$9),Inputs!$B$3*Inputs!$B$4*Inputs!$B$5*1.01^C$3/Inputs!$B$9/10000000,0) -> 0 | D4: =IF(AND(D$3>=2,D$3<2+Inputs!$B$9),Inputs!$B$3*Inputs!$B$4*Inputs!$B$5*1.01^D$3/Inputs!$B$9/10000000,0) -> 78.880253 | E4: =IF(AND(E$3>=2,E$3<2+Inputs!$B$9),Inputs!$B$3*Inputs!$B$4*Inputs!$B$5*1.01^E$3/Inputs!$B$9/10000000,0) -> 79.669055 | F4: =IF(AND(F$3>=2,F$3<2+Inputs!$B$9),Inputs!$B$3*Inputs!$B$4*Inputs!$B$5*1.01^F$3/Inputs!$B$9/10000000,0) -> 80.465746 | G4: =IF(AND(G$3>=2,G$3<2+Inputs!$B$9),Inputs!$B$3*Inputs!$B$4*Inputs!$B$5*1.01^G$3/Inputs!$B$9/10000000,0) -> 81.270403 | H4: =IF(AND(H$3>=2,H$3<2+Inputs!$B$9),Inputs!$B$3*Inputs!$B$4*Inputs!$B$5*1.01^H$3/Inputs!$B$9/10000000,0) -> 82.083107 | I4: =IF(AND(I$3>=2,I$3<2+Inputs!$B$9),Inputs!$B$3*Inputs!$B$4*Inputs!$B$5*1.01^I$3/Inputs!$B$9/10000000,0) -> 82.903938 | ... P4: =IF(AND(P$3>=2,P$3<2+Inputs!$B$9),Inputs!$B$3*Inputs!$B$4*Inputs!$B$5*1.01^P$3/Inputs!$B$9/10000000,0) -> 0
A5: GST (₹ crore) | B5: =B4*Inputs!$B$8/(1+Inputs!$B$8) -> 0 | C5: =C4*Inputs!$B$8/(1+Inputs!$B$8) -> 0 | D5: =D4*Inputs!$B$8/(1+Inputs!$B$8) -> 3.7562025 | E5: =E4*Inputs!$B$8/(1+Inputs!$B$8) -> 3.7937645 | F5: =F4*Inputs!$B$8/(1+Inputs!$B$8) -> 3.8317022 | G5: =G4*Inputs!$B$8/(1+Inputs!$B$8) -> 3.8700192 | H5: =H4*Inputs!$B$8/(1+Inputs!$B$8) -> 3.9087194 | I5: =I4*Inputs!$B$8/(1+Inputs!$B$8) -> 3.9478066 | ... P5: =P4*Inputs!$B$8/(1+Inputs!$B$8) -> 0
A6: Construction (₹ crore) | B6: =IF(AND(B$3>=1,B$3<=10),Inputs!$B$6/10,0) -> 0 | C6: =IF(AND(C$3>=1,C$3<=10),Inputs!$B$6/10,0) -> 41.2 | D6: =IF(AND(D$3>=1,D$3<=10),Inputs!$B$6/10,0) -> 41.2 | E6: =IF(AND(E$3>=1,E$3<=10),Inputs!$B$6/10,0) -> 41.2 | F6: =IF(AND(F$3>=1,F$3<=10),Inputs!$B$6/10,0) -> 41.2 | G6: =IF(AND(G$3>=1,G$3<=10),Inputs!$B$6/10,0) -> 41.2 | H6: =IF(AND(H$3>=1,H$3<=10),Inputs!$B$6/10,0) -> 41.2 | I6: =IF(AND(I$3>=1,I$3<=10),Inputs!$B$6/10,0) -> 41.2 | ... P6: =IF(AND(P$3>=1,P$3<=10),Inputs!$B$6/10,0) -> 0
A7: Land (₹ crore) | B7: =IF(B$3=0,Inputs!$B$7,0) -> 165 | C7: =IF(C$3=0,Inputs!$B$7,0) -> 0 | D7: =IF(D$3=0,Inputs!$B$7,0) -> 0 | E7: =IF(E$3=0,Inputs!$B$7,0) -> 0 | F7: =IF(F$3=0,Inputs!$B$7,0) -> 0 | G7: =IF(G$3=0,Inputs!$B$7,0) -> 0 | H7: =IF(H$3=0,Inputs!$B$7,0) -> 0 | I7: =IF(I$3=0,Inputs!$B$7,0) -> 0 | ... P7: =IF(P$3=0,Inputs!$B$7,0) -> 0
A8: Cash flow (₹ crore) | B8: =B4-B5-B6-B7 -> -165 | C8: =C4-C5-C6-C7 -> -41.2 | D8: =D4-D5-D6-D7 -> 33.92405 | E8: =E4-E5-E6-E7 -> 34.675291 | F8: =F4-F5-F6-F7 -> 35.434044 | G8: =G4-G5-G6-G7 -> 36.200384 | H8: =H4-H5-H6-H7 -> 36.974388 | I8: =I4-I5-I6-I7 -> 37.756132 | ... P8: =P4-P5-P6-P7 -> 0

Sheet Returns
A3: Project IRR | B3: =(1+IRR('Cash Flow'!$B$8:$P$8))^4-1 -> 0.54758434
A4: Revenue (₹ crore) | B4: =SUM('Cash Flow'!$B$4:$P$4) -> 825.26197
A5: Net profit (₹ crore) | B5: =SUM('Cash Flow'!$B$8:$P$8) -> 208.96378
A6: Profit margin | B6: =B5/B4 -> 0.25320903
A7: Revenue per apartment (₹) | B7: =B4*10000000/Inputs!$B$3 -> 10064170
