Workbook

Sheet Inputs
A1: AL MANAZIL REIT – LISTED SAUDI REIT (SAR)
A3: Units in issue | B3: 150000000
A4: Unit price on the exchange (SAR) | B4: 9.2
A5: Fund manager fee a year (of NAV) | B5: 0.0075
A6: Distribution of net income | B6: 0.9
A7: Murabaha rate | B7: 0.062
A8: Murabaha facility (SAR) | B8: 520000000
A9: Maintenance capex share of NOI | B9: 0.06
A10: Zakat rate | B10: 0.025
A11: Rent growth a year | B11: 0.02
A12: Valuation cap rate | B12: 0.075

Sheet Properties
A1: Property | B1: Sector | C1: NOI a year (SAR) | D1: Occupancy
A2: Olaya Towers | B2: Office | C2: 61000000 | D2: 0.93
A3: Jeddah Logistics Park | B3: Logistics | C3: 38500000 | D3: 1
A4: Al Khobar Mall | B4: Retail | C4: 47200000 | D4: 0.88
A5: Riyadh Hotel Apartments | B5: Hospitality | C5: 22800000 | D5: 0.79
A6: Dammam Schools | B6: Education | C6: 18400000 | D6: 1

Sheet Projection
A3: Year | B3: 0 | C3: 1 | D3: 2 | E3: 3 | F3: 4 | G3: 5
A4: NOI | B4: =0 -> 0 | C4: =SUMPRODUCT(Properties!$C$2:$C$6,Properties!$D$2:$D$6/MAX(Properties!$D$2:$D$6))*(1+Inputs!$B$11)^(C$3-1) -> 173178000 | D4: =SUMPRODUCT(Properties!$C$2:$C$6,Properties!$D$2:$D$6/MAX(Properties!$D$2:$D$6))*(1+Inputs!$B$11)^(D$3-1) -> 176641560 | E4: =SUMPRODUCT(Properties!$C$2:$C$6,Properties!$D$2:$D$6/MAX(Properties!$D$2:$D$6))*(1+Inputs!$B$11)^(E$3-1) -> 1.8017439e+08 | F4: =SUMPRODUCT(Properties!$C$2:$C$6,Properties!$D$2:$D$6/MAX(Properties!$D$2:$D$6))*(1+Inputs!$B$11)^(F$3-1) -> 1.8377788e+08 | G4: =SUMPRODUCT(Properties!$C$2:$C$6,Properties!$D$2:$D$6/MAX(Properties!$D$2:$D$6))*(1+Inputs!$B$11)^(G$3-1) -> 1.8745344e+08
A5: Fund manager fee | B5: =0 -> 0 | C5: =B16*Inputs!$B$5 -> 13417800 | D5: =C16*Inputs!$B$5 -> 13764156 | E5: =D16*Inputs!$B$5 -> 14117439 | F5: =E16*Inputs!$B$5 -> 14477788 | G5: =F16*Inputs!$B$5 -> 14845344
A6: Finance cost | B6: =0 -> 0 | C6: =Inputs!$B$8*Inputs!$B$7 -> 32240000 | D6: =Inputs!$B$8*Inputs!$B$7 -> 32240000 | E6: =Inputs!$B$8*Inputs!$B$7 -> 32240000 | F6: =Inputs!$B$8*Inputs!$B$7 -> 32240000 | G6: =Inputs!$B$8*Inputs!$B$7 -> 32240000
A7: Depreciation | B7: =0 -> 0 | C7: =C15*0.012 -> 28262650 | D7: =D15*0.012 -> 28827903 | E7: =E15*0.012 -> 29404461 | F7: =F15*0.012 -> 29992550 | G7: =G15*0.012 -> 30592401
A8: Net income | B8: =B4-B5-B6-B7 -> 0 | C8: =C4-C5-C6-C7 -> 99257550 | D8: =D4-D5-D6-D7 -> 1.018095e+08 | E8: =E4-E5-E6-E7 -> 1.0441249e+08 | F8: =F4-F5-F6-F7 -> 1.0706754e+08 | G8: =G4-G5-G6-G7 -> 1.0977569e+08
A9: FFO | B9: =B8+B7 -> 0 | C9: =C8+C7 -> 127520200 | D9: =D8+D7 -> 130637404 | E9: =E8+E7 -> 1.3381695e+08 | F9: =F8+F7 -> 1.3706009e+08 | G9: =G8+G7 -> 1.4036809e+08
A10: Maintenance capex | B10: =B4*Inputs!$B$9 -> 0 | C10: =C4*Inputs!$B$9 -> 10390680 | D10: =D4*Inputs!$B$9 -> 10598494 | E10: =E4*Inputs!$B$9 -> 10810463 | F10: =F4*Inputs!$B$9 -> 11026673 | G10: =G4*Inputs!$B$9 -> 11247206
A11: AFFO | B11: =B9-B10 -> 0 | C11: =C9-C10 -> 117129520 | D11: =D9-D10 -> 1.2003891e+08 | E11: =E9-E10 -> 1.2300649e+08 | F11: =F9-F10 -> 1.2603342e+08 | G11: =G9-G10 -> 1.2912089e+08
A12: Zakat | B12: =MAX(0,B8)*Inputs!$B$10 -> 0 | C12: =MAX(0,C8)*Inputs!$B$10 -> 2481438.8 | D12: =MAX(0,D8)*Inputs!$B$10 -> 2545237.5 | E12: =MAX(0,E8)*Inputs!$B$10 -> 2610312.3 | F12: =MAX(0,F8)*Inputs!$B$10 -> 2676688.5 | G12: =MAX(0,G8)*Inputs!$B$10 -> 2744392.3
A13: Distribution | B13: =MAX(0,B8-B12)*Inputs!$B$6 -> 0 | C13: =MAX(0,C8-C12)*Inputs!$B$6 -> 87098500 | D13: =MAX(0,D8-D12)*Inputs!$B$6 -> 89337837 | E13: =MAX(0,E8-E12)*Inputs!$B$6 -> 91621961 | F13: =MAX(0,F8-F12)*Inputs!$B$6 -> 93951767 | G13: =MAX(0,G8-G12)*Inputs!$B$6 -> 96328170
A14: Distribution per unit | B14: =B13/Inputs!$B$3 -> 0 | C14: =C13/Inputs!$B$3 -> 0.58065667 | D14: =D13/Inputs!$B$3 -> 0.59558558 | E14: =E13/Inputs!$B$3 -> 0.61081307 | F14: =F13/Inputs!$B$3 -> 0.62634512 | G14: =G13/Inputs!$B$3 -> 0.6421878
A15: Property value | B15: =SUMPRODUCT(Properties!$C$2:$C$6,Properties!$D$2:$D$6/MAX(Properties!$D$2:$D$6))*(1+Inputs!$B$11)^B$3/Inputs!$B$12 -> 2309040000 | C15: =SUMPRODUCT(Properties!$C$2:$C$6,Properties!$D$2:$D$6/MAX(Properties!$D$2:$D$6))*(1+Inputs!$B$11)^C$3/Inputs!$B$12 -> 2355220800 | D15: =SUMPRODUCT(Properties!$C$2:$C$6,Properties!$D$2:$D$6/MAX(Properties!$D$2:$D$6))*(1+Inputs!$B$11)^D$3/Inputs!$B$12 -> 2402325216 | E15: =SUMPRODUCT(Properties!$C$2:$C$6,Properties!$D$2:$D$6/MAX(Properties!$D$2:$D$6))*(1+Inputs!$B$11)^E$3/Inputs!$B$12 -> 2.4503717e+09 | F15: =SUMPRODUCT(Properties!$C$2:$C$6,Properties!$D$2:$D$6/MAX(Properties!$D$2:$D$6))*(1+Inputs!$B$11)^F$3/Inputs!$B$12 -> 2.4993792e+09 | G15: =SUMPRODUCT(Properties!$C$2:$C$6,Properties!$D$2:$D$6/MAX(Properties!$D$2:$D$6))*(1+Inputs!$B$11)^G$3/Inputs!$B$12 -> 2.5493667e+09
A16: NAV | B16: =B15-Inputs!$B$8 -> 1789040000 | C16: =C15-Inputs!$B$8 -> 1835220800 | D16: =D15-Inputs!$B$8 -> 1882325216 | E16: =E15-Inputs!$B$8 -> 1.9303717e+09 | F16: =F15-Inputs!$B$8 -> 1.9793792e+09 | G16: =G15-Inputs!$B$8 -> 2.0293667e+09
A17: NAV per unit | B17: =B16/Inputs!$B$3 -> 11.926933 | C17: =C16/Inputs!$B$3 -> 12.234805 | D17: =D16/Inputs!$B$3 -> 12.548835 | E17: =E16/Inputs!$B$3 -> 12.869145 | F17: =F16/Inputs!$B$3 -> 13.195861 | G17: =G16/Inputs!$B$3 -> 13.529112

Sheet Returns
A3: Dividend yield on the unit price | B3: =Projection!C14/Inputs!$B$4 -> 0.063114855
A4: FFO per unit, year 1 (SAR) | B4: =Projection!C9/Inputs!$B$3 -> 0.85013467
A5: AFFO payout ratio | B5: =Projection!C13/Projection!C11 -> 0.74360845
A6: NAV per unit (SAR) | B6: =Projection!B17 -> 11.926933
A7: Premium or discount to NAV | B7: =Inputs!$B$4/Projection!B17-1 -> -0.22863659
A8: Gearing (debt to property value) | B8: =Inputs!$B$8/Projection!B15 -> 0.22520182
A9: Total return to unitholders a year | B9: =((Projection!G17+SUM(Projection!C14:G14))/Inputs!$B$4)^(1/5)-1 -> 0.12508143
