Workbook

Sheet Inputs
A1: HAFENCITY JV – RESIDENTIAL DEVELOPMENT (EUR)
A3: Development cost (EUR) | B3: 148000000
A4: Sales (EUR) | B4: 196000000
A5: Operating partner equity share | B5: 0.1
A6: Preferred return | B6: 0.06
A7: Catch-up to the operating partner | B7: 0.5
A8: Promote above the catch-up | B8: 0.25
A9: Years to sell out | B9: 4

Sheet Cash Flow
A3: Year | B3: 0 | C3: 1 | D3: 2 | E3: 3 | F3: 4
A4: Project cash flow | B4: =-Inputs!$B$3 -> -148000000 | C4: =Inputs!$B$4/Inputs!$B$9 -> 49000000 | D4: =Inputs!$B$4/Inputs!$B$9 -> 49000000 | E4: =Inputs!$B$4/Inputs!$B$9 -> 49000000 | F4: =Inputs!$B$4/Inputs!$B$9 -> 49000000
A5: Capital partner | B5: =B4*(1-Inputs!$B$5) -> -133200000 | C5: =0 -> 0 | D5: =0 -> 0 | E5: =0 -> 0 | F5: =0 -> 0
A6: Operating partner | B6: =B4*Inputs!$B$5 -> -14800000 | C6: =0 -> 0 | D6: =0 -> 0 | E6: =0 -> 0 | F6: =0 -> 0

Sheet Waterfall
A3: Distributable | B3: =SUMIF('Cash Flow'!C4:F4,">0") -> 196000000
A4: Equity in | B4: =Inputs!$B$3 -> 148000000
A5: Pref to all | B5: =MIN(B3,B4*((1+Inputs!$B$6)^Inputs!$B$9-1)) -> 38846590
A6: Return of equity | B6: =MIN(B3-B5,B4) -> 148000000
A7: Catch-up | B7: =MIN(B3-B5-B6,B5*Inputs!$B$7/(1-Inputs!$B$7)*Inputs!$B$8/Inputs!$B$7) -> 9153409.9
A8: Remaining | B8: =B3-B5-B6-B7 -> 0
A9: Operating partner total | B9: =(B5+B6)*Inputs!$B$5+B7+B8*Inputs!$B$8+B8*(1-Inputs!$B$8)*Inputs!$B$5 -> 27838069
A10: Capital partner total | B10: =B3-B9 -> 1.6816193e+08

Sheet Dashboard
A1: HAFENCITY JV – DASHBOARD
A3: Returns
A4: =Waterfall!B10/(Inputs!B3*(1-Inputs!B5)) -> 1.262477 | B4: Capital partner multiple
A5: =Waterfall!B9/(Inputs!B3*Inputs!B5) -> 1.8809506 | B5: Operating partner multiple
A6: =Waterfall!B3-Inputs!B3 -> 48000000 | B6: Net profit (EUR)
A7: =(Waterfall!B3/Inputs!B3)^(1/Inputs!B9)-1 -> 0.072750162 | B7: Project return a year
A8: =Waterfall!B7+Waterfall!B8*Inputs!B8 -> 9153409.9 | B8: Promote paid (EUR)
