Workbook

Sheet Inputs
A1: HARBOUR LENDING FUND II – REAL ESTATE DEBT (USD m)
A3: LP equity (USD m) | B3: 450
A4: Fund leverage (debt to equity) | B4: 0.5
A5: Cost of fund leverage | B5: 0.058
A6: Management fee on equity | B6: 0.0075
A7: Incentive fee hurdle (net return a year) | B7: 0.06
A8: Incentive fee above the hurdle | B8: 0.15
A9: Defaulted loan recovery | B9: 0.8
A10: Fund expenses a year (USD m) | B10: 2.2

Sheet Loans
A1: Loan | B1: Amount (USD m) | C1: Coupon | D1: LTV | E1: Maturity (year) | F1: Defaults in year
A2: Chicago office | B2: 120 | C2: 0.085 | D2: 0.62 | E2: 3 | F2: 0
A3: Austin multifamily | B3: 95 | C3: 0.078 | D3: 0.68 | E3: 4 | F3: 0
A4: Miami hotel | B4: 80 | C4: 0.098 | D4: 0.6 | E4: 3 | F4: 2
A5: Denver industrial | B5: 110 | C5: 0.072 | D5: 0.55 | E5: 5 | F5: 0
A6: Phoenix BTR | B6: 70 | C6: 0.081 | D6: 0.7 | E6: 4 | F6: 0
A7: Seattle life science | B7: 90 | C7: 0.093 | D7: 0.58 | E7: 5 | F7: 0
A8: Atlanta retail | B8: 60 | C8: 0.105 | D8: 0.64 | E8: 2 | F8: 0
A9: Dallas student | B9: 75 | C9: 0.079 | D9: 0.66 | E9: 4 | F9: 0

Sheet Fund
A3: Year | B3: 0 | C3: 1 | D3: 2 | E3: 3 | F3: 4 | G3: 5
A4: Loans outstanding | B4: =SUMPRODUCT((Loans!$E$2:$E$9>B$3)*((Loans!$F$2:$F$9=0)+(Loans!$F$2:$F$9>B$3)>0)*Loans!$B$2:$B$9) -> 700 | C4: =SUMPRODUCT((Loans!$E$2:$E$9>C$3)*((Loans!$F$2:$F$9=0)+(Loans!$F$2:$F$9>C$3)>0)*Loans!$B$2:$B$9) -> 700 | D4: =SUMPRODUCT((Loans!$E$2:$E$9>D$3)*((Loans!$F$2:$F$9=0)+(Loans!$F$2:$F$9>D$3)>0)*Loans!$B$2:$B$9) -> 560 | E4: =SUMPRODUCT((Loans!$E$2:$E$9>E$3)*((Loans!$F$2:$F$9=0)+(Loans!$F$2:$F$9>E$3)>0)*Loans!$B$2:$B$9) -> 440 | F4: =SUMPRODUCT((Loans!$E$2:$E$9>F$3)*((Loans!$F$2:$F$9=0)+(Loans!$F$2:$F$9>F$3)>0)*Loans!$B$2:$B$9) -> 200 | G4: =SUMPRODUCT((Loans!$E$2:$E$9>G$3)*((Loans!$F$2:$F$9=0)+(Loans!$F$2:$F$9>G$3)>0)*Loans!$B$2:$B$9) -> 0
A5: Interest income | B5: =0 -> 0 | C5: =SUMPRODUCT((Loans!$E$2:$E$9>=C$3)*((Loans!$F$2:$F$9=0)+(Loans!$F$2:$F$9>C$3)>0)*Loans!$B$2:$B$9*Loans!$C$2:$C$9) -> 59.635 | D5: =SUMPRODUCT((Loans!$E$2:$E$9>=D$3)*((Loans!$F$2:$F$9=0)+(Loans!$F$2:$F$9>D$3)>0)*Loans!$B$2:$B$9*Loans!$C$2:$C$9) -> 51.795 | E5: =SUMPRODUCT((Loans!$E$2:$E$9>=E$3)*((Loans!$F$2:$F$9=0)+(Loans!$F$2:$F$9>E$3)>0)*Loans!$B$2:$B$9*Loans!$C$2:$C$9) -> 45.495 | F5: =SUMPRODUCT((Loans!$E$2:$E$9>=F$3)*((Loans!$F$2:$F$9=0)+(Loans!$F$2:$F$9>F$3)>0)*Loans!$B$2:$B$9*Loans!$C$2:$C$9) -> 35.295 | G5: =SUMPRODUCT((Loans!$E$2:$E$9>=G$3)*((Loans!$F$2:$F$9=0)+(Loans!$F$2:$F$9>G$3)>0)*Loans!$B$2:$B$9*Loans!$C$2:$C$9) -> 16.29
A6: Default loss | B6: =0 -> 0 | C6: =SUMPRODUCT((Loans!$F$2:$F$9=C$3)*Loans!$B$2:$B$9)*(1-Inputs!$B$9) -> 0 | D6: =SUMPRODUCT((Loans!$F$2:$F$9=D$3)*Loans!$B$2:$B$9)*(1-Inputs!$B$9) -> 16 | E6: =SUMPRODUCT((Loans!$F$2:$F$9=E$3)*Loans!$B$2:$B$9)*(1-Inputs!$B$9) -> 0 | F6: =SUMPRODUCT((Loans!$F$2:$F$9=F$3)*Loans!$B$2:$B$9)*(1-Inputs!$B$9) -> 0 | G6: =SUMPRODUCT((Loans!$F$2:$F$9=G$3)*Loans!$B$2:$B$9)*(1-Inputs!$B$9) -> 0
A7: Principal back | B7: =0 -> 0 | C7: =SUMPRODUCT((Loans!$E$2:$E$9=C$3)*(Loans!$F$2:$F$9=0)*Loans!$B$2:$B$9)+SUMPRODUCT((Loans!$F$2:$F$9=C$3)*Loans!$B$2:$B$9)*Inputs!$B$9 -> 0 | D7: =SUMPRODUCT((Loans!$E$2:$E$9=D$3)*(Loans!$F$2:$F$9=0)*Loans!$B$2:$B$9)+SUMPRODUCT((Loans!$F$2:$F$9=D$3)*Loans!$B$2:$B$9)*Inputs!$B$9 -> 124 | E7: =SUMPRODUCT((Loans!$E$2:$E$9=E$3)*(Loans!$F$2:$F$9=0)*Loans!$B$2:$B$9)+SUMPRODUCT((Loans!$F$2:$F$9=E$3)*Loans!$B$2:$B$9)*Inputs!$B$9 -> 120 | F7: =SUMPRODUCT((Loans!$E$2:$E$9=F$3)*(Loans!$F$2:$F$9=0)*Loans!$B$2:$B$9)+SUMPRODUCT((Loans!$F$2:$F$9=F$3)*Loans!$B$2:$B$9)*Inputs!$B$9 -> 240 | G7: =SUMPRODUCT((Loans!$E$2:$E$9=G$3)*(Loans!$F$2:$F$9=0)*Loans!$B$2:$B$9)+SUMPRODUCT((Loans!$F$2:$F$9=G$3)*Loans!$B$2:$B$9)*Inputs!$B$9 -> 200
A8: Leverage cost | B8: =0 -> 0 | C8: =MIN(Inputs!$B$3*Inputs!$B$4,B4*Inputs!$B$4/(1+Inputs!$B$4))*Inputs!$B$5 -> 13.05 | D8: =MIN(Inputs!$B$3*Inputs!$B$4,C4*Inputs!$B$4/(1+Inputs!$B$4))*Inputs!$B$5 -> 13.05 | E8: =MIN(Inputs!$B$3*Inputs!$B$4,D4*Inputs!$B$4/(1+Inputs!$B$4))*Inputs!$B$5 -> 10.826667 | F8: =MIN(Inputs!$B$3*Inputs!$B$4,E4*Inputs!$B$4/(1+Inputs!$B$4))*Inputs!$B$5 -> 8.5066667 | G8: =MIN(Inputs!$B$3*Inputs!$B$4,F4*Inputs!$B$4/(1+Inputs!$B$4))*Inputs!$B$5 -> 3.8666667
A9: Management fee | B9: =0 -> 0 | C9: =Inputs!$B$3*Inputs!$B$6 -> 3.375 | D9: =Inputs!$B$3*Inputs!$B$6 -> 3.375 | E9: =Inputs!$B$3*Inputs!$B$6 -> 3.375 | F9: =Inputs!$B$3*Inputs!$B$6 -> 3.375 | G9: =Inputs!$B$3*Inputs!$B$6 -> 3.375
A10: Expenses | B10: =0 -> 0 | C10: =Inputs!$B$10 -> 2.2 | D10: =Inputs!$B$10 -> 2.2 | E10: =Inputs!$B$10 -> 2.2 | F10: =Inputs!$B$10 -> 2.2 | G10: =Inputs!$B$10 -> 2.2
A11: Net income before incentive | B11: =B5-B6-B8-B9-B10 -> 0 | C11: =C5-C6-C8-C9-C10 -> 41.01 | D11: =D5-D6-D8-D9-D10 -> 17.17 | E11: =E5-E6-E8-E9-E10 -> 29.093333 | F11: =F5-F6-F8-F9-F10 -> 21.213333 | G11: =G5-G6-G8-G9-G10 -> 6.8483333
A12: Incentive fee | B12: =0 -> 0 | C12: =MAX(0,C11-Inputs!$B$3*Inputs!$B$7)*Inputs!$B$8 -> 2.1015 | D12: =MAX(0,D11-Inputs!$B$3*Inputs!$B$7)*Inputs!$B$8 -> 0 | E12: =MAX(0,E11-Inputs!$B$3*Inputs!$B$7)*Inputs!$B$8 -> 0.314 | F12: =MAX(0,F11-Inputs!$B$3*Inputs!$B$7)*Inputs!$B$8 -> 0 | G12: =MAX(0,G11-Inputs!$B$3*Inputs!$B$7)*Inputs!$B$8 -> 0
A13: Net to LPs | B13: =-Inputs!$B$3 -> -450 | C13: =C11-C12+C7*Inputs!$B$3/SUM(Loans!$B$2:$B$9) -> 38.9085 | D13: =D11-D12+D7*Inputs!$B$3/SUM(Loans!$B$2:$B$9) -> 96.884286 | E13: =E11-E12+E7*Inputs!$B$3/SUM(Loans!$B$2:$B$9) -> 105.92219 | F13: =F11-F12+F7*Inputs!$B$3/SUM(Loans!$B$2:$B$9) -> 175.49905 | G13: =G11-G12+G7*Inputs!$B$3/SUM(Loans!$B$2:$B$9) -> 135.41976

Sheet Returns
A3: Net IRR to LPs | B3: =IRR(Fund!$B$13:$G$13) -> 0.061432974
A4: Weighted average coupon | B4: =SUMPRODUCT(Loans!B2:B9,Loans!C2:C9)/SUM(Loans!B2:B9) -> 0.085192857
A5: Weighted average LTV | B5: =SUMPRODUCT(Loans!B2:B9,Loans!D2:D9)/SUM(Loans!B2:B9) -> 0.62371429
A6: Credit losses (USD m) | B6: =SUM(Fund!$B$6:$G$6) -> 16
A7: Incentive fees (USD m) | B7: =SUM(Fund!$B$12:$G$12) -> 2.4155
A8: Net income to LPs (USD m) | B8: =SUM(Fund!$B$13:$G$13) -> 102.63379
