Workbook

Sheet Terms
A1: AL DIRIYAH GATE REAL ESTATE FUND – PRIVATE FUND, CMA (SAR)
A3: Units subscribed | B3: 45000000
A4: Subscription price per unit (SAR) | B4: 10
A5: Management fee (of NAV) | B5: 0.015
A6: Fund board fees a year (SAR) | B6: 600000
A7: Custodian fee (of NAV) | B7: 0.0005
A8: Zakat | B8: 0.025
A9: Subscription fee | B9: 0.02
A10: Exit costs | B10: 0.02

Sheet Projects
A1: Project | B1: Cost (SAR) | C1: Build years | D1: Sale value (SAR) | E1: Sale year
A2: Villas phase 1 | B2: 185000000 | C2: 2 | D2: 305000000 | E2: 3
A3: Retail strip | B3: 140000000 | C3: 2 | D3: 236000000 | E3: 4

Sheet Fund
A3: Year | B3: 0 | C3: 1 | D3: 2 | E3: 3 | F3: 4
A4: Spend | B4: =0 -> 0 | C4: =IF(C$3<=Projects!$C$2,Projects!$B$2/Projects!$C$2,0)+IF(C$3<=Projects!$C$3,Projects!$B$3/Projects!$C$3,0) -> 162500000 | D4: =IF(D$3<=Projects!$C$2,Projects!$B$2/Projects!$C$2,0)+IF(D$3<=Projects!$C$3,Projects!$B$3/Projects!$C$3,0) -> 162500000 | E4: =IF(E$3<=Projects!$C$2,Projects!$B$2/Projects!$C$2,0)+IF(E$3<=Projects!$C$3,Projects!$B$3/Projects!$C$3,0) -> 0 | F4: =IF(F$3<=Projects!$C$2,Projects!$B$2/Projects!$C$2,0)+IF(F$3<=Projects!$C$3,Projects!$B$3/Projects!$C$3,0) -> 0
A5: Sales | B5: =0 -> 0 | C5: =IF(C$3=Projects!$E$2,Projects!$D$2*(1-Terms!$B$10),0)+IF(C$3=Projects!$E$3,Projects!$D$3*(1-Terms!$B$10),0) -> 0 | D5: =IF(D$3=Projects!$E$2,Projects!$D$2*(1-Terms!$B$10),0)+IF(D$3=Projects!$E$3,Projects!$D$3*(1-Terms!$B$10),0) -> 0 | E5: =IF(E$3=Projects!$E$2,Projects!$D$2*(1-Terms!$B$10),0)+IF(E$3=Projects!$E$3,Projects!$D$3*(1-Terms!$B$10),0) -> 298900000 | F5: =IF(F$3=Projects!$E$2,Projects!$D$2*(1-Terms!$B$10),0)+IF(F$3=Projects!$E$3,Projects!$D$3*(1-Terms!$B$10),0) -> 231280000
A6: Fees | B6: =0 -> 0 | C6: =B11*(Terms!$B$5+Terms!$B$7)+Terms!$B$6 -> 7435500 | D6: =C11*(Terms!$B$5+Terms!$B$7)+Terms!$B$6 -> 7149362.2 | E6: =D11*(Terms!$B$5+Terms!$B$7)+Terms!$B$6 -> 6874813.1 | F6: =E11*(Terms!$B$5+Terms!$B$7)+Terms!$B$6 -> 8376833.1
A7: Zakat | B7: =0 -> 0 | C7: =MAX(0,B11)*Terms!$B$8 -> 11025000 | D7: =MAX(0,C11)*Terms!$B$8 -> 10563488 | E7: =MAX(0,D11)*Terms!$B$8 -> 10120666 | F7: =MAX(0,E11)*Terms!$B$8 -> 12543279
A8: Net cash | B8: =Terms!$B$3*Terms!$B$4*(1-Terms!$B$9) -> 441000000 | C8: =C5-C4-C6-C7 -> -180960500 | D8: =D5-D4-D6-D7 -> -1.8021285e+08 | E8: =E5-E4-E6-E7 -> 2.8190452e+08 | F8: =F5-F4-F6-F7 -> 2.1035989e+08
A9: Property at cost | B9: =0 -> 0 | C9: =B9+C4-IF(C$3=Projects!$E$2,Projects!$B$2,0)-IF(C$3=Projects!$E$3,Projects!$B$3,0) -> 162500000 | D9: =C9+D4-IF(D$3=Projects!$E$2,Projects!$B$2,0)-IF(D$3=Projects!$E$3,Projects!$B$3,0) -> 325000000 | E9: =D9+E4-IF(E$3=Projects!$E$2,Projects!$B$2,0)-IF(E$3=Projects!$E$3,Projects!$B$3,0) -> 140000000 | F9: =E9+F4-IF(F$3=Projects!$E$2,Projects!$B$2,0)-IF(F$3=Projects!$E$3,Projects!$B$3,0) -> 0
A10: Cash | B10: =B8 -> 441000000 | C10: =B10+C8 -> 260039500 | D10: =C10+D8 -> 79826650 | E10: =D10+E8 -> 3.6173117e+08 | F10: =E10+F8 -> 5.7209106e+08
A11: NAV | B11: =B10+B9 -> 441000000 | C11: =C10+C9 -> 422539500 | D11: =D10+D9 -> 4.0482665e+08 | E11: =E10+E9 -> 5.0173117e+08 | F11: =F10+F9 -> 5.7209106e+08
A12: NAV per unit | B12: =B11/Terms!$B$3 -> 9.8 | C12: =C11/Terms!$B$3 -> 9.3897667 | D12: =D11/Terms!$B$3 -> 8.9961478 | E12: =E11/Terms!$B$3 -> 11.149582 | F12: =F11/Terms!$B$3 -> 12.713135

Sheet Returns
A3: NAV per unit at the end (SAR) | B3: =Fund!F12 -> 12.713135
A4: Return per unit a year | B4: =(B3/Terms!$B$4)^(1/4)-1 -> 0.061849976
A5: Fees paid over the life (SAR) | B5: =SUM(Fund!$B$6:$F$6) -> 29836508
A6: Zakat paid (SAR) | B6: =SUM(Fund!$B$7:$F$7) -> 44252433
A7: Cash short at any year end (SAR) | B7: =-MIN(0,MIN(Fund!$B$10:$F$10)) -> 0
