Workbook

Sheet Inputs
A2: Quarterly rent | B2: 250000
A3: Quarterly rent growth | B3: 0.005
A4: Exit cap rate | B4: 0.06
A5: Loan | B5: 6000000
A6: Interest rate | B6: 0.05
A7: Equity | B7: 4000000

Sheet CF
A3: Quarter ending | B3: 46022 | C3: 46112 | D3: =EOMONTH(C3,3) -> 46203 | E3: =EOMONTH(D3,3) -> 46295 | F3: =EOMONTH(E3,3) -> 46387 | G3: =EOMONTH(F3,3) -> 46477 | H3: =EOMONTH(G3,3) -> 46568 | I3: =EOMONTH(H3,3) -> 46660 | J3: =EOMONTH(I3,3) -> 46752 | K3: =EOMONTH(J3,3) -> 46843 | ... V3: =EOMONTH(U3,3) -> 47848
A4: Quarter | C4: 1 | D4: 2 | E4: 3 | F4: 4 | G4: 5 | H4: 6 | I4: 7 | J4: 8 | K4: 9 | L4: 10 | M4: 11 | N4: 12 | O4: 13 | P4: 14 | Q4: 15 | R4: 16 | S4: 17 | T4: 18 | U4: 19 | V4: 20
A6: Rent | C6: =Inputs!$B$2*(1+Inputs!$B$3)^(C4-1) -> 250000 | D6: =Inputs!$B$2*(1+Inputs!$B$3)^(D4-1) -> 251250 | E6: =Inputs!$B$2*(1+Inputs!$B$3)^(E4-1) -> 252506.25 | F6: =Inputs!$B$2*(1+Inputs!$B$3)^(F4-1) -> 253768.78 | G6: =Inputs!$B$2*(1+Inputs!$B$3)^(G4-1) -> 255037.63 | H6: =Inputs!$B$2*(1+Inputs!$B$3)^(H4-1) -> 256312.81 | I6: =Inputs!$B$2*(1+Inputs!$B$3)^(I4-1) -> 257594.38 | J6: =Inputs!$B$2*(1+Inputs!$B$3)^(J4-1) -> 258882.35 | ... V6: =Inputs!$B$2*(1+Inputs!$B$3)^(V4-1) -> 274849.65
A7: Interest | C7: =-Inputs!$B$5*Inputs!$B$6/4 -> -75000 | D7: =-Inputs!$B$5*Inputs!$B$6/4 -> -75000 | E7: =-Inputs!$B$5*Inputs!$B$6/4 -> -75000 | F7: =-Inputs!$B$5*Inputs!$B$6/4 -> -75000 | G7: =-Inputs!$B$5*Inputs!$B$6/4 -> -75000 | H7: =-Inputs!$B$5*Inputs!$B$6/4 -> -75000 | I7: =-Inputs!$B$5*Inputs!$B$6/4 -> -75000 | J7: =-Inputs!$B$5*Inputs!$B$6/4 -> -75000 | ... V7: =-Inputs!$B$5*Inputs!$B$6/4 -> -75000
A8: Sale proceeds | V8: =V6*4/Inputs!$B$4 -> 18323310
A10: Loan repayment | C10: 0 | D10: 0 | E10: 0 | F10: 0 | G10: 0 | H10: 0 | I10: 0 | J10: 0 | K10: 0 | L10: 0 | M10: 0 | N10: 0 | O10: 0 | P10: 0 | Q10: 0 | R10: 0 | S10: 0 | T10: 0 | U10: 0 | V10: =-Inputs!$B$5 -> -6000000
A11: Net cash flow to equity | B11: =-Inputs!B7 -> -4000000 | C11: =SUM(C6:C10) -> 175000 | D11: =SUM(D6:D10) -> 176250 | E11: =SUM(E6:E10) -> 177506.25 | F11: =SUM(F6:F10) -> 178768.78 | G11: =SUM(G6:G10) -> 180037.63 | H11: =SUM(H6:H10) -> 181312.81 | I11: =SUM(I6:I10) -> 182594.38 | J11: =SUM(J6:J10) -> 183882.35 | ... V11: =SUM(V6:V10) -> 12523159
A12: Cumulative cash | C12: =SUM($C11:C11) -> 175000 | D12: =SUM($C11:D11) -> 351250 | E12: =SUM($C11:E11) -> 528756.25 | F12: =SUM($C11:F11) -> 707525.03 | G12: =SUM($C11:G11) -> 887562.66 | H12: =SUM($C11:H11) -> 1068875.5 | I12: =SUM($C11:I11) -> 1251469.8 | J12: =SUM($C11:J11) -> 1435352.2 | ... V12: =SUM($C11:V11) -> 16068089

Sheet Summary
A2: Levered IRR | B2: =XIRR(CF!B11:V11,CF!B3:V3) -> 0.39948847
A3: Net profit | B3: =SUM(CF!B11:V11) -> 12068089
A4: Exit year rent (trailing four quarters) | B4: =SUM(CF!S6:V6) -> 1091221.3
