Workbook

Sheet Inputs
A1: OAKWOOD RETAIL PARK (USD)
A2: Year 1 rent | B2: 1000000
A3: Rent growth | B3: 0.03
A4: Operating costs (share of rent) | B4: 0.3
A5: Purchase price | B5: 12000000
A6: Exit cap rate | B6: 0.065
A7: Hold period (years) | B7: 10
A8: Discount rate | B8: 0.08

Sheet Cash Flow
A1: OAKWOOD RETAIL PARK – ANNUAL CASH FLOW (USD)
A4: Year | C4: 0 | D4: =C4+1 -> 1 | E4: =D4+1 -> 2 | F4: =E4+1 -> 3 | G4: =F4+1 -> 4 | H4: =G4+1 -> 5 | I4: =H4+1 -> 6 | J4: =I4+1 -> 7 | K4: =J4+1 -> 8 | ... M4: =L4+1 -> 10 | N4: Total
A5: Calendar year | C5: 2025 | D5: 2026 | E5: 2027 | F5: 2028 | G5: 2029 | H5: 2030 | I5: 2031 | J5: 2032 | K5: 2033 | L5: 2034 | M5: 2035
A7: Rent | D7: =IF(AND(D$4>=1,D$4<=Inputs!$B$7),Inputs!$B$2*(1+Inputs!$B$3)^(D$4-1),0) -> 1000000 | E7: =IF(AND(E$4>=1,E$4<=Inputs!$B$7),Inputs!$B$2*(1+Inputs!$B$3)^(E$4-1),0) -> 1030000 | F7: =IF(AND(F$4>=1,F$4<=Inputs!$B$7),Inputs!$B$2*(1+Inputs!$B$3)^(F$4-1),0) -> 1060900 | G7: =IF(AND(G$4>=1,G$4<=Inputs!$B$7),Inputs!$B$2*(1+Inputs!$B$3)^(G$4-1),0) -> 1092727 | H7: =IF(AND(H$4>=1,H$4<=Inputs!$B$7),Inputs!$B$2*(1+Inputs!$B$3)^(H$4-1),0) -> 1125508.8 | I7: =IF(AND(I$4>=1,I$4<=Inputs!$B$7),Inputs!$B$2*(1+Inputs!$B$3)^(I$4-1),0) -> 1159274.1 | J7: =IF(AND(J$4>=1,J$4<=Inputs!$B$7),Inputs!$B$2*(1+Inputs!$B$3)^(J$4-1),0) -> 1194052.3 | K7: =IF(AND(K$4>=1,K$4<=Inputs!$B$7),Inputs!$B$2*(1+Inputs!$B$3)^(K$4-1),0) -> 1229873.9 | ... M7: =IF(AND(M$4>=1,M$4<=Inputs!$B$7),Inputs!$B$2*(1+Inputs!$B$3)^(M$4-1),0) -> 1304773.2 | N7: =SUM(C7:M7) -> 11463879
A8: Operating costs | D8: =-D7*Inputs!$B$4 -> -300000 | E8: =-E7*Inputs!$B$4 -> -309000 | F8: =-F7*Inputs!$B$4 -> -318270 | G8: =-G7*Inputs!$B$4 -> -327818.1 | H8: =-H7*Inputs!$B$4 -> -337652.64 | I8: =-I7*Inputs!$B$4 -> -347782.22 | J8: =-J7*Inputs!$B$4 -> -358215.69 | K8: =-K7*Inputs!$B$4 -> -368962.16 | ... M8: =-M7*Inputs!$B$4 -> -391431.96 | N8: =SUM(C8:M8) -> -3439163.8
A9: Net operating income | D9: =D7+D8 -> 700000 | E9: =E7+E8 -> 721000 | F9: =F7+F8 -> 742630 | G9: =G7+G8 -> 764908.9 | H9: =H7+H8 -> 787856.17 | I9: =I7+I8 -> 811491.85 | J9: =J7+J8 -> 835836.61 | K9: =K7+K8 -> 860911.71 | ... M9: =M7+M8 -> 913341.23 | N9: =SUM(C9:M9) -> 8024715.5
A10: Capital expenditure | D10: -100000 | E10: -100000 | F10: -100000 | G10: -100000 | H10: -100000 | I10: -100000 | J10: -100000 | K10: -100000 | L10: -100000 | M10: -100000 | N10: =SUM(C10:M10) -> -1000000
A11: Sale proceeds | D11: =IF(D$4=Inputs!$B$7,D9*(1+Inputs!$B$3)/Inputs!$B$6,0) -> 0 | E11: =IF(E$4=Inputs!$B$7,E9*(1+Inputs!$B$3)/Inputs!$B$6,0) -> 0 | F11: =IF(F$4=Inputs!$B$7,F9*(1+Inputs!$B$3)/Inputs!$B$6,0) -> 0 | G11: =IF(G$4=Inputs!$B$7,G9*(1+Inputs!$B$3)/Inputs!$B$6,0) -> 0 | H11: =IF(H$4=Inputs!$B$7,H9*(1+Inputs!$B$3)/Inputs!$B$6,0) -> 0 | I11: =IF(I$4=Inputs!$B$7,I9*(1+Inputs!$B$3)/Inputs!$B$6,0) -> 0 | J11: =IF(J$4=Inputs!$B$7,J9*(1+Inputs!$B$3)/Inputs!$B$6,0) -> 0 | K11: =IF(K$4=Inputs!$B$7,K9*(1+Inputs!$B$3)/Inputs!$B$6,0) -> 0 | ... M11: =IF(M$4=Inputs!$B$7,M9*(1+Inputs!$B$3)/Inputs!$B$6,0) -> 14472946 | N11: =SUM(C11:M11) -> 14472946
A12: Purchase | C12: =-Inputs!B5 -> -12000000 | N12: =SUM(C12:M12) -> -12000000
A13: Net cash flow | C13: =SUM(C9:C12) -> -12000000 | D13: =SUM(D9:D12) -> 600000 | E13: =SUM(E9:E12) -> 621000 | F13: =SUM(F9:F12) -> 642630 | G13: =SUM(G9:G12) -> 664908.9 | H13: =SUM(H9:H12) -> 687856.17 | I13: =SUM(I9:I12) -> 711491.85 | J13: =SUM(J9:J12) -> 735836.61 | ... M13: =SUM(M9:M12) -> 15286287 | N13: =SUM(C13:M13) -> 9497661.1

Sheet Summary
A2: Unlevered IRR | B2: =IRR('Cash Flow'!C13:M13) -> 0.072179882
A3: NPV at the discount rate | B3: =NPV(Inputs!B8,'Cash Flow'!D13:M13)+'Cash Flow'!C13 -> -682140.39
A4: Equity multiple | B4: =SUMIF('Cash Flow'!C13:M13,">0")/-SUMIF('Cash Flow'!C13:M13,"<0") -> 1.7914718
A5: Exit value | B5: ='Cash Flow'!M11 -> 14472946
A6: Total net operating income | B6: ='Cash Flow'!N9 -> 8024715.5
A7: Net profit | B7: ='Cash Flow'!N13 -> 9497661.1
