Workbook

Sheet Inputs
A1: AL WAHA BUSINESS PARK (SAR)
A2: Land cost | B2: 50000000
A3: Construction cost (total, phased on Cash Flow) | B3: 200000000
A4: Stabilised rent | B4: 33000000
A5: Rent growth | B5: 0.03
A6: Operating costs (share of rent) | B6: 0.2
A7: Exit cap rate | B7: 0.07
A8: Hold period (years) | B8: 10
A9: Loan to cost | B9: 0.55
A10: Interest rate | B10: 0.065
A11: Minimum DSCR covenant | B11: 1.25
A12: Maximum LTV covenant | B12: 0.6
A13: LP share of equity | B13: 0.9
... A17: Selling costs | B17: 0.02

Sheet Cash Flow
A1: AL WAHA BUSINESS PARK – CASH FLOW (SAR)
A3: Year | C3: 2026 | D3: 2027 | E3: 2028 | F3: 2029 | G3: 2030 | H3: 2031 | I3: 2032 | J3: 2033 | K3: 2034 | L3: 2035 | M3: Total
A4: Period | C4: 1 | D4: =C4+1 -> 2 | E4: =D4+1 -> 3 | F4: =E4+1 -> 4 | G4: =F4+1 -> 5 | H4: =G4+1 -> 6 | I4: =H4+1 -> 7 | J4: =I4+1 -> 8 | K4: =J4+1 -> 9 | L4: =K4+1 -> 10
A6: Land | C6: =IF(C$4=1,-Inputs!$B$2,0) -> -50000000 | D6: =IF(D$4=1,-Inputs!$B$2,0) -> 0 | E6: =IF(E$4=1,-Inputs!$B$2,0) -> 0 | F6: =IF(F$4=1,-Inputs!$B$2,0) -> 0 | G6: =IF(G$4=1,-Inputs!$B$2,0) -> 0 | H6: =IF(H$4=1,-Inputs!$B$2,0) -> 0 | I6: =IF(I$4=1,-Inputs!$B$2,0) -> 0 | J6: =IF(J$4=1,-Inputs!$B$2,0) -> 0 | ... L6: =IF(L$4=1,-Inputs!$B$2,0) -> 0 | M6: =SUM(C6:L6) -> -50000000
A7: Construction cost | C7: -60000000 | D7: -95000000 | E7: -50000000 | F7: 0 | G7: 0 | H7: 0 | I7: 0 | J7: 0 | K7: 0 | L7: 0 | M7: =SUM(C7:L7) -> -205000000
A8: Occupancy | C8: 0 | D8: 0 | E8: 0 | F8: 0.4 | G8: 0.75 | H8: 0.95 | I8: 0.95 | J8: 0.95 | K8: 0.95 | L8: 0.95
A9: Rent | C9: =IF(C$4<=Inputs!$B$8,Inputs!$B$4*C8*(1+Inputs!$B$5)^MAX(0,C$4-4),0) -> 0 | D9: =IF(D$4<=Inputs!$B$8,Inputs!$B$4*D8*(1+Inputs!$B$5)^MAX(0,D$4-4),0) -> 0 | E9: =IF(E$4<=Inputs!$B$8,Inputs!$B$4*E8*(1+Inputs!$B$5)^MAX(0,E$4-4),0) -> 0 | F9: =IF(F$4<=Inputs!$B$8,Inputs!$B$4*F8*(1+Inputs!$B$5)^MAX(0,F$4-4),0) -> 13200000 | G9: =IF(G$4<=Inputs!$B$8,Inputs!$B$4*G8*(1+Inputs!$B$5)^MAX(0,G$4-4),0) -> 25492500 | H9: =IF(H$4<=Inputs!$B$8,Inputs!$B$4*H8*(1+Inputs!$B$5)^MAX(0,H$4-4),0) -> 33259215 | I9: =IF(I$4<=Inputs!$B$8,Inputs!$B$4*I8*(1+Inputs!$B$5)^MAX(0,I$4-4),0) -> 34256991 | J9: =IF(J$4<=Inputs!$B$8,Inputs!$B$4*J8*(1+Inputs!$B$5)^MAX(0,J$4-4),0) -> 35284701 | ... L9: =IF(L$4<=Inputs!$B$8,Inputs!$B$4*L8*(1+Inputs!$B$5)^MAX(0,L$4-4),0) -> 37433539 | M9: =SUM(C9:L9) -> 2.1527019e+08
A10: Operating costs | C10: =-C9*Inputs!$B$6 -> 0 | D10: =-D9*Inputs!$B$6 -> 0 | E10: =-E9*Inputs!$B$6 -> 0 | F10: =-F9*Inputs!$B$6 -> -2640000 | G10: =-G9*Inputs!$B$6 -> -5098500 | H10: =-H9*Inputs!$B$6 -> -6651843 | I10: =-I9*Inputs!$B$6 -> -6851398.3 | J10: =-J9*Inputs!$B$6 -> -7056940.2 | ... L10: =-L9*Inputs!$B$6 -> -7486707.9 | M10: =SUM(C10:L10) -> -43054038
A11: Net operating income | C11: =C9+C10 -> 0 | D11: =D9+D10 -> 0 | E11: =E9+E10 -> 0 | F11: =F9+F10 -> 10560000 | G11: =G9+G10 -> 20394000 | H11: =H9+H10 -> 26607372 | I11: =I9+I10 -> 27405593 | J11: =J9+J10 -> 28227761 | ... L11: =L9+L10 -> 29946832 | M11: =SUM(C11:L11) -> 1.7221615e+08
A12: Sale proceeds | C12: =IF(C$4=Inputs!$B$8,C11*(1+Inputs!$B$5)/Inputs!$B$7*(1-Inputs!$B$17),0) -> 0 | D12: =IF(D$4=Inputs!$B$8,D11*(1+Inputs!$B$5)/Inputs!$B$7*(1-Inputs!$B$17),0) -> 0 | E12: =IF(E$4=Inputs!$B$8,E11*(1+Inputs!$B$5)/Inputs!$B$7*(1-Inputs!$B$17),0) -> 0 | F12: =IF(F$4=Inputs!$B$8,F11*(1+Inputs!$B$5)/Inputs!$B$7*(1-Inputs!$B$17),0) -> 0 | G12: =IF(G$4=Inputs!$B$8,G11*(1+Inputs!$B$5)/Inputs!$B$7*(1-Inputs!$B$17),0) -> 0 | H12: =IF(H$4=Inputs!$B$8,H11*(1+Inputs!$B$5)/Inputs!$B$7*(1-Inputs!$B$17),0) -> 0 | I12: =IF(I$4=Inputs!$B$8,I11*(1+Inputs!$B$5)/Inputs!$B$7*(1-Inputs!$B$17),0) -> 0 | J12: =IF(J$4=Inputs!$B$8,J11*(1+Inputs!$B$5)/Inputs!$B$7*(1-Inputs!$B$17),0) -> 0 | ... L12: =IF(L$4=Inputs!$B$8,L11*(1+Inputs!$B$5)/Inputs!$B$7*(1-Inputs!$B$17),0) -> 4.3183331e+08 | M12: =SUM(C12:L12) -> 4.3183331e+08
A13: Unlevered cash flow | C13: =C6+C7+C11+C12 -> -110000000 | D13: =D6+D7+D11+D12 -> -95000000 | E13: =E6+E7+E11+E12 -> -50000000 | F13: =F6+F7+F11+F12 -> 10560000 | G13: =G6+G7+G11+G12 -> 20394000 | H13: =H6+H7+H11+H12 -> 26607372 | I13: =I6+I7+I11+I12 -> 27405593 | J13: =J6+J7+J11+J12 -> 28227761 | ... L13: =L6+L7+L11+L12 -> 4.6178014e+08 | M13: =SUM(C13:L13) -> 3.4904946e+08
A14: Loan drawdown | C14: =-(C6+C7)*Inputs!$B$9 -> 60500000 | D14: =-(D6+D7)*Inputs!$B$9 -> 52250000 | E14: =-(E6+E7)*Inputs!$B$9 -> 27500000 | F14: =-(F6+F7)*Inputs!$B$9 -> 0 | G14: =-(G6+G7)*Inputs!$B$9 -> 0 | H14: =-(H6+H7)*Inputs!$B$9 -> 0 | I14: =-(I6+I7)*Inputs!$B$9 -> 0 | J14: =-(J6+J7)*Inputs!$B$9 -> 0 | ... L14: =-(L6+L7)*Inputs!$B$9 -> 0 | M14: =SUM(C14:L14) -> 140250000
A15: Opening debt | C15: =0 -> 0 | D15: =C19 -> 60500000 | E15: =D19 -> 112750000 | F15: =E19 -> 140250000 | G15: =F19 -> 140250000 | H15: =G19 -> 140250000 | I15: =H19 -> 140250000 | J15: =I19 -> 140250000 | K15: =J19 -> 140250000 | L15: =K19 -> 140250000
A16: Interest | C16: =-C15*Inputs!$B$10 -> 0 | D16: =-D15*Inputs!$B$10 -> -3932500 | E16: =-E15*Inputs!$B$10 -> -7328750 | F16: =-F15*Inputs!$B$10 -> -9116250 | G16: =-G15*Inputs!$B$10 -> -9116250 | H16: =-H15*Inputs!$B$10 -> -9116250 | I16: =-I15*Inputs!$B$10 -> -9116250 | J16: =-J15*Inputs!$B$10 -> -9116250 | ... L16: =-L15*Inputs!$B$10 -> -9116250 | M16: =SUM(C16:L16) -> -75075000
A17: Loan repayment | C17: =IF(C$4=Inputs!$B$8,-(C15+C14),0) -> 0 | D17: =IF(D$4=Inputs!$B$8,-(D15+D14),0) -> 0 | E17: =IF(E$4=Inputs!$B$8,-(E15+E14),0) -> 0 | F17: =IF(F$4=Inputs!$B$8,-(F15+F14),0) -> 0 | G17: =IF(G$4=Inputs!$B$8,-(G15+G14),0) -> 0 | H17: =IF(H$4=Inputs!$B$8,-(H15+H14),0) -> 0 | I17: =IF(I$4=Inputs!$B$8,-(I15+I14),0) -> 0 | J17: =IF(J$4=Inputs!$B$8,-(J15+J14),0) -> 0 | ... L17: =IF(L$4=Inputs!$B$8,-(L15+L14),0) -> -140250000 | M17: =SUM(C17:L17) -> -140250000
A18: Levered cash flow to equity | C18: =C13+C14+C16+C17 -> -49500000 | D18: =D13+D14+D16+D17 -> -46682500 | E18: =E13+E14+E16+E17 -> -29828750 | F18: =F13+F14+F16+F17 -> 1443750 | G18: =G13+G14+G16+G17 -> 11277750 | H18: =H13+H14+H16+H17 -> 17491122 | I18: =I13+I14+I16+I17 -> 18289343 | J18: =J13+J14+J16+J17 -> 19111511 | ... L18: =L13+L14+L16+L17 -> 3.1241389e+08 | M18: =SUM(C18:L18) -> 2.7397446e+08
A19: Closing debt | C19: =C15+C14+C17 -> 60500000 | D19: =D15+D14+D17 -> 112750000 | E19: =E15+E14+E17 -> 140250000 | F19: =F15+F14+F17 -> 140250000 | G19: =G15+G14+G17 -> 140250000 | H19: =H15+H14+H17 -> 140250000 | I19: =I15+I14+I17 -> 140250000 | J19: =J15+J14+J17 -> 140250000 | ... L19: =L15+L14+L17 -> 0
A20: DSCR | C20: =IF(AND(C11>0,C16<0),C11/-C16,"") | D20: =IF(AND(D11>0,D16<0),D11/-D16,"") | E20: =IF(AND(E11>0,E16<0),E11/-E16,"") | F20: =IF(AND(F11>0,F16<0),F11/-F16,"") -> 1.158371 | G20: =IF(AND(G11>0,G16<0),G11/-G16,"") -> 2.2371041 | H20: =IF(AND(H11>0,H16<0),H11/-H16,"") -> 2.9186751 | I20: =IF(AND(I11>0,I16<0),I11/-I16,"") -> 3.0062354 | J20: =IF(AND(J11>0,J16<0),J11/-J16,"") -> 3.0964224 | ... L20: =IF(AND(L11>0,L16<0),L11/-L16,"") -> 3.2849946
A21: Property value | C21: =IF(C11>0,C11/Inputs!$B$7,"") | D21: =IF(D11>0,D11/Inputs!$B$7,"") | E21: =IF(E11>0,E11/Inputs!$B$7,"") | F21: =IF(F11>0,F11/Inputs!$B$7,"") -> 1.5085714e+08 | G21: =IF(G11>0,G11/Inputs!$B$7,"") -> 2.9134286e+08 | H21: =IF(H11>0,H11/Inputs!$B$7,"") -> 3.8010531e+08 | I21: =IF(I11>0,I11/Inputs!$B$7,"") -> 3.9150847e+08 | J21: =IF(J11>0,J11/Inputs!$B$7,"") -> 4.0325373e+08 | ... L21: =IF(L11>0,L11/Inputs!$B$7,"") -> 4.2781188e+08
A22: LTV | C22: =IF(AND(ISNUMBER(C21),C19>0),C19/C21,"") | D22: =IF(AND(ISNUMBER(D21),D19>0),D19/D21,"") | E22: =IF(AND(ISNUMBER(E21),E19>0),E19/E21,"") | F22: =IF(AND(ISNUMBER(F21),F19>0),F19/F21,"") -> 0.9296875 | G22: =IF(AND(ISNUMBER(G21),G19>0),G19/G21,"") -> 0.48139159 | H22: =IF(AND(ISNUMBER(H21),H19>0),H19/H21,"") -> 0.36897669 | I22: =IF(AND(ISNUMBER(I21),I19>0),I19/I21,"") -> 0.35822979 | J22: =IF(AND(ISNUMBER(J21),J19>0),J19/J21,"") -> 0.34779592 | ... L22: =IF(AND(ISNUMBER(L21),L19>0),L19/L21,"")
A23: Cumulative equity cash flow | C23: =SUM($C18:C18) -> -49500000 | D23: =SUM($C18:D18) -> -96182500 | E23: =SUM($C18:E18) -> -126011250 | F23: =SUM($C18:F18) -> -124567500 | G23: =SUM($C18:G18) -> -113289750 | H23: =SUM($C18:H18) -> -95798628 | I23: =SUM($C18:I18) -> -77509285 | J23: =SUM($C18:J18) -> -58397774 | ... L23: =SUM($C18:L18) -> 2.7397446e+08

Sheet Returns
A2: Unlevered IRR | B2: =IRR('Cash Flow'!C13:L13) -> 0.12378164
A3: Levered IRR | B3: =IRR('Cash Flow'!C18:L18) -> 0.16844934
A4: Equity multiple | B4: =SUMIF('Cash Flow'!C18:L18,">0")/-SUMIF('Cash Flow'!C18:L18,"<0") -> 3.1742064
A5: Net profit | B5: =SUM('Cash Flow'!C18:L18) -> 2.7397446e+08
A6: Peak equity | B6: =-MIN('Cash Flow'!C23:L23) -> 126011250
A7: Minimum DSCR | B7: =MIN('Cash Flow'!C20:L20) -> 1.158371
A8: Maximum LTV | B8: =MAX('Cash Flow'!C22:L22) -> 0.9296875
A9: NPV at the discount rate | B9: =NPV(Inputs!B16,'Cash Flow'!C18:L18) -> 71796799
A10: Total development cost | B10: =-('Cash Flow'!M6+'Cash Flow'!M7) -> 255000000
A11: Profit on cost | B11: =B5/B10 -> 1.0744097
