Workbook

Sheet Summary
B1: Deal Summary · Al Rimal Riverside Fund (illustrative)
B3: SAR '000 unless stated. All figures link to the calculation tabs.
B5: Project | E5: Partner returns
B6: Gross development value | C6: =Assumptions!C18*(1+Assumptions!F10) -> 1800000 | E6: Fund gross IRR (levered, pre-promote) | F6: =Returns!C6 -> 0.1444434
B7: Total development budget | C7: =-SUM('Cash Flow'!$E$6:$AB$6,'Cash Flow'!$E$7:$AB$7) -> 1200000 | E7: LP net IRR (after all fees & promote) | F7: =Returns!C7 -> 0.13099204
B8: Project profit (unlevered) | C8: =Returns!C8 -> 600000 | E8: Sponsor total profit incl. promote | F8: =Returns!C9 -> 63783.296
B9: Profit on cost | C9: =Returns!C10 -> 0.5 | E9: Peak facility balance | F9: =Returns!C11 -> 360000
B10: Project unlevered IRR | C10: =Returns!C5 -> 0.15161204

Sheet Assumptions
B2: Al Rimal Riverside Fund (illustrative) · assumptions
B3: SAR '000 unless stated
B5: Model start date (first day of Q1) | C5: 46388 | D5: date
B6: Fund term | C6: 24 | D6: quarters
B7: Active scenario (1 = Base, 2 = Upside, 3 = Downside) | C7: 1 | D7: selector
C9: Base | D9: Upside | E9: Downside | F9: Live
B10: Sales price adjustment vs base | C10: 0 | D10: 0.05 | E10: -0.1 | F10: =CHOOSE(Scenario,C10,D10,E10) -> 0
B11: Hard cost overrun on all packages | C11: 0 | D11: -0.02 | E11: 0.08 | F11: =CHOOSE(Scenario,C11,D11,E11) -> 0
B12: 3M SAIBOR (average over term) | C12: 0.05 | D12: 0.045 | E12: 0.06 | F12: =CHOOSE(Scenario,C12,D12,E12) -> 0.05
B14: Land | C14: 300000
B15: Hard cost (total, excl. overrun) | C15: 900000
B16: Construction start (quarter) | C16: 2
B17: Construction duration (quarters) | C17: 10
B18: Gross sales value (base) | C18: 1800000
B19: Sales start (quarter) | C19: 13
B20: Facility size as % of hard cost (LTC) | C20: 0.4
B21: Margin over SAIBOR | C21: 0.02
B22: Management fee (a year, on commitments) | C22: 0.015
B23: LP commitments | C23: 800000
B24: Preferred return (a year) | C24: 0.05
B25: Promote above the preferred return | C25: 0.3
B26: Bulk sale discount at fund term | C26: 0.1

Sheet Cash Flow
B1: Al Rimal Riverside Fund · quarterly cash flow (SAR '000)
B3: Quarter | E3: 1 | F3: 2 | G3: 3 | H3: 4 | I3: 5 | J3: 6 | K3: 7 | L3: 8 | M3: 9 | N3: 10 | O3: 11 | P3: 12 | Q3: 13 | R3: 14 | S3: 15 | T3: 16 | U3: 17 | V3: 18 | W3: 19 | X3: 20 | Y3: 21 | Z3: 22 | AA3: 23 | AB3: 24
B4: Quarter end | E4: =EOMONTH(Model_Start,3*E3-1) -> 46477 | F4: =EOMONTH(Model_Start,3*F3-1) -> 46568 | G4: =EOMONTH(Model_Start,3*G3-1) -> 46660 | H4: =EOMONTH(Model_Start,3*H3-1) -> 46752 | I4: =EOMONTH(Model_Start,3*I3-1) -> 46843 | J4: =EOMONTH(Model_Start,3*J3-1) -> 46934 | K4: =EOMONTH(Model_Start,3*K3-1) -> 47026 | L4: =EOMONTH(Model_Start,3*L3-1) -> 47118 | ... AB4: =EOMONTH(Model_Start,3*AB3-1) -> 48579
B6: Land | E6: =IF(E$3=1,-Assumptions!$C$14,0) -> -300000 | F6: =IF(F$3=1,-Assumptions!$C$14,0) -> 0 | G6: =IF(G$3=1,-Assumptions!$C$14,0) -> 0 | H6: =IF(H$3=1,-Assumptions!$C$14,0) -> 0 | I6: =IF(I$3=1,-Assumptions!$C$14,0) -> 0 | J6: =IF(J$3=1,-Assumptions!$C$14,0) -> 0 | K6: =IF(K$3=1,-Assumptions!$C$14,0) -> 0 | L6: =IF(L$3=1,-Assumptions!$C$14,0) -> 0 | ... AB6: =IF(AB$3=1,-Assumptions!$C$14,0) -> 0
B7: Hard cost | E7: =IF(AND(E$3>=Assumptions!$C$16,E$3<Assumptions!$C$16+Assumptions!$C$17,E$3<=Fund_Term),-Assumptions!$C$15*(1+Assumptions!$F$11)/Assumptions!$C$17,0) -> 0 | F7: =IF(AND(F$3>=Assumptions!$C$16,F$3<Assumptions!$C$16+Assumptions!$C$17,F$3<=Fund_Term),-Assumptions!$C$15*(1+Assumptions!$F$11)/Assumptions!$C$17,0) -> -90000 | G7: =IF(AND(G$3>=Assumptions!$C$16,G$3<Assumptions!$C$16+Assumptions!$C$17,G$3<=Fund_Term),-Assumptions!$C$15*(1+Assumptions!$F$11)/Assumptions!$C$17,0) -> -90000 | H7: =IF(AND(H$3>=Assumptions!$C$16,H$3<Assumptions!$C$16+Assumptions!$C$17,H$3<=Fund_Term),-Assumptions!$C$15*(1+Assumptions!$F$11)/Assumptions!$C$17,0) -> -90000 | I7: =IF(AND(I$3>=Assumptions!$C$16,I$3<Assumptions!$C$16+Assumptions!$C$17,I$3<=Fund_Term),-Assumptions!$C$15*(1+Assumptions!$F$11)/Assumptions!$C$17,0) -> -90000 | J7: =IF(AND(J$3>=Assumptions!$C$16,J$3<Assumptions!$C$16+Assumptions!$C$17,J$3<=Fund_Term),-Assumptions!$C$15*(1+Assumptions!$F$11)/Assumptions!$C$17,0) -> -90000 | K7: =IF(AND(K$3>=Assumptions!$C$16,K$3<Assumptions!$C$16+Assumptions!$C$17,K$3<=Fund_Term),-Assumptions!$C$15*(1+Assumptions!$F$11)/Assumptions!$C$17,0) -> -90000 | L7: =IF(AND(L$3>=Assumptions!$C$16,L$3<Assumptions!$C$16+Assumptions!$C$17,L$3<=Fund_Term),-Assumptions!$C$15*(1+Assumptions!$F$11)/Assumptions!$C$17,0) -> -90000 | ... AB7: =IF(AND(AB$3>=Assumptions!$C$16,AB$3<Assumptions!$C$16+Assumptions!$C$17,AB$3<=Fund_Term),-Assumptions!$C$15*(1+Assumptions!$F$11)/Assumptions!$C$17,0) -> 0
B8: Sales receipts | E8: =IF(E$3>Fund_Term,0,IF(AND(E$3>=Assumptions!$C$19,E$3<Assumptions!$C$19+8),Assumptions!$C$18*(1+Assumptions!$F$10)/8,0)+IF(E$3=Fund_Term,Assumptions!$C$18*(1+Assumptions!$F$10)*MAX(0,Assumptions!$C$19+8-Fund_Term-1)/8*(1-Assumptions!$C$26),0)) -> 0 | F8: =IF(F$3>Fund_Term,0,IF(AND(F$3>=Assumptions!$C$19,F$3<Assumptions!$C$19+8),Assumptions!$C$18*(1+Assumptions!$F$10)/8,0)+IF(F$3=Fund_Term,Assumptions!$C$18*(1+Assumptions!$F$10)*MAX(0,Assumptions!$C$19+8-Fund_Term-1)/8*(1-Assumptions!$C$26),0)) -> 0 | G8: =IF(G$3>Fund_Term,0,IF(AND(G$3>=Assumptions!$C$19,G$3<Assumptions!$C$19+8),Assumptions!$C$18*(1+Assumptions!$F$10)/8,0)+IF(G$3=Fund_Term,Assumptions!$C$18*(1+Assumptions!$F$10)*MAX(0,Assumptions!$C$19+8-Fund_Term-1)/8*(1-Assumptions!$C$26),0)) -> 0 | H8: =IF(H$3>Fund_Term,0,IF(AND(H$3>=Assumptions!$C$19,H$3<Assumptions!$C$19+8),Assumptions!$C$18*(1+Assumptions!$F$10)/8,0)+IF(H$3=Fund_Term,Assumptions!$C$18*(1+Assumptions!$F$10)*MAX(0,Assumptions!$C$19+8-Fund_Term-1)/8*(1-Assumptions!$C$26),0)) -> 0 | I8: =IF(I$3>Fund_Term,0,IF(AND(I$3>=Assumptions!$C$19,I$3<Assumptions!$C$19+8),Assumptions!$C$18*(1+Assumptions!$F$10)/8,0)+IF(I$3=Fund_Term,Assumptions!$C$18*(1+Assumptions!$F$10)*MAX(0,Assumptions!$C$19+8-Fund_Term-1)/8*(1-Assumptions!$C$26),0)) -> 0 | J8: =IF(J$3>Fund_Term,0,IF(AND(J$3>=Assumptions!$C$19,J$3<Assumptions!$C$19+8),Assumptions!$C$18*(1+Assumptions!$F$10)/8,0)+IF(J$3=Fund_Term,Assumptions!$C$18*(1+Assumptions!$F$10)*MAX(0,Assumptions!$C$19+8-Fund_Term-1)/8*(1-Assumptions!$C$26),0)) -> 0 | K8: =IF(K$3>Fund_Term,0,IF(AND(K$3>=Assumptions!$C$19,K$3<Assumptions!$C$19+8),Assumptions!$C$18*(1+Assumptions!$F$10)/8,0)+IF(K$3=Fund_Term,Assumptions!$C$18*(1+Assumptions!$F$10)*MAX(0,Assumptions!$C$19+8-Fund_Term-1)/8*(1-Assumptions!$C$26),0)) -> 0 | L8: =IF(L$3>Fund_Term,0,IF(AND(L$3>=Assumptions!$C$19,L$3<Assumptions!$C$19+8),Assumptions!$C$18*(1+Assumptions!$F$10)/8,0)+IF(L$3=Fund_Term,Assumptions!$C$18*(1+Assumptions!$F$10)*MAX(0,Assumptions!$C$19+8-Fund_Term-1)/8*(1-Assumptions!$C$26),0)) -> 0 | ... AB8: =IF(AB$3>Fund_Term,0,IF(AND(AB$3>=Assumptions!$C$19,AB$3<Assumptions!$C$19+8),Assumptions!$C$18*(1+Assumptions!$F$10)/8,0)+IF(AB$3=Fund_Term,Assumptions!$C$18*(1+Assumptions!$F$10)*MAX(0,Assumptions!$C$19+8-Fund_Term-1)/8*(1-Assumptions!$C$26),0)) -> 0
B9: Project cash flow (unlevered) | E9: =SUM(E6:E8) -> -300000 | F9: =SUM(F6:F8) -> -90000 | G9: =SUM(G6:G8) -> -90000 | H9: =SUM(H6:H8) -> -90000 | I9: =SUM(I6:I8) -> -90000 | J9: =SUM(J6:J8) -> -90000 | K9: =SUM(K6:K8) -> -90000 | L9: =SUM(L6:L8) -> -90000 | ... AB9: =SUM(AB6:AB8) -> 0
B10: Opening facility balance | E10: =0 -> 0 | F10: =E14 -> 0 | G10: =F14 -> 36000 | H10: =G14 -> 72000 | I10: =H14 -> 108000 | J10: =I14 -> 144000 | K10: =J14 -> 180000 | L10: =K14 -> 216000 | M10: =L14 -> 252000 | ... AB10: =AA14 -> 0
B11: Facility drawdown | E11: =-E7*Assumptions!$C$20 -> 0 | F11: =-F7*Assumptions!$C$20 -> 36000 | G11: =-G7*Assumptions!$C$20 -> 36000 | H11: =-H7*Assumptions!$C$20 -> 36000 | I11: =-I7*Assumptions!$C$20 -> 36000 | J11: =-J7*Assumptions!$C$20 -> 36000 | K11: =-K7*Assumptions!$C$20 -> 36000 | L11: =-L7*Assumptions!$C$20 -> 36000 | ... AB11: =-AB7*Assumptions!$C$20 -> 0
B12: Interest paid | E12: =-E10*(Assumptions!$F$12+Assumptions!$C$21)/4 -> 0 | F12: =-F10*(Assumptions!$F$12+Assumptions!$C$21)/4 -> 0 | G12: =-G10*(Assumptions!$F$12+Assumptions!$C$21)/4 -> -630 | H12: =-H10*(Assumptions!$F$12+Assumptions!$C$21)/4 -> -1260 | I12: =-I10*(Assumptions!$F$12+Assumptions!$C$21)/4 -> -1890 | J12: =-J10*(Assumptions!$F$12+Assumptions!$C$21)/4 -> -2520 | K12: =-K10*(Assumptions!$F$12+Assumptions!$C$21)/4 -> -3150 | L12: =-L10*(Assumptions!$F$12+Assumptions!$C$21)/4 -> -3780 | ... AB12: =-AB10*(Assumptions!$F$12+Assumptions!$C$21)/4 -> 0
B13: Facility repayment | E13: =IF(E$3=Fund_Term,-(E10+E11),-MIN(E10+E11,MAX(0,E8))) -> 0 | F13: =IF(F$3=Fund_Term,-(F10+F11),-MIN(F10+F11,MAX(0,F8))) -> 0 | G13: =IF(G$3=Fund_Term,-(G10+G11),-MIN(G10+G11,MAX(0,G8))) -> 0 | H13: =IF(H$3=Fund_Term,-(H10+H11),-MIN(H10+H11,MAX(0,H8))) -> 0 | I13: =IF(I$3=Fund_Term,-(I10+I11),-MIN(I10+I11,MAX(0,I8))) -> 0 | J13: =IF(J$3=Fund_Term,-(J10+J11),-MIN(J10+J11,MAX(0,J8))) -> 0 | K13: =IF(K$3=Fund_Term,-(K10+K11),-MIN(K10+K11,MAX(0,K8))) -> 0 | L13: =IF(L$3=Fund_Term,-(L10+L11),-MIN(L10+L11,MAX(0,L8))) -> 0 | ... AB13: =IF(AB$3=Fund_Term,-(AB10+AB11),-MIN(AB10+AB11,MAX(0,AB8))) -> 0
B14: Closing facility balance | E14: =E10+E11+E13 -> 0 | F14: =F10+F11+F13 -> 36000 | G14: =G10+G11+G13 -> 72000 | H14: =H10+H11+H13 -> 108000 | I14: =I10+I11+I13 -> 144000 | J14: =J10+J11+J13 -> 180000 | K14: =K10+K11+K13 -> 216000 | L14: =L10+L11+L13 -> 252000 | ... AB14: =AB10+AB11+AB13 -> 0
B15: Fund management fee | E15: =IF(E$3<=Fund_Term,-Assumptions!$C$23*Assumptions!$C$22/4,0) -> -3000 | F15: =IF(F$3<=Fund_Term,-Assumptions!$C$23*Assumptions!$C$22/4,0) -> -3000 | G15: =IF(G$3<=Fund_Term,-Assumptions!$C$23*Assumptions!$C$22/4,0) -> -3000 | H15: =IF(H$3<=Fund_Term,-Assumptions!$C$23*Assumptions!$C$22/4,0) -> -3000 | I15: =IF(I$3<=Fund_Term,-Assumptions!$C$23*Assumptions!$C$22/4,0) -> -3000 | J15: =IF(J$3<=Fund_Term,-Assumptions!$C$23*Assumptions!$C$22/4,0) -> -3000 | K15: =IF(K$3<=Fund_Term,-Assumptions!$C$23*Assumptions!$C$22/4,0) -> -3000 | L15: =IF(L$3<=Fund_Term,-Assumptions!$C$23*Assumptions!$C$22/4,0) -> -3000 | ... AB15: =IF(AB$3<=Fund_Term,-Assumptions!$C$23*Assumptions!$C$22/4,0) -> -3000
B16: Fund gross cash flow (levered, pre-promote) | E16: =E9+E11+E12+E13+E15 -> -303000 | F16: =F9+F11+F12+F13+F15 -> -57000 | G16: =G9+G11+G12+G13+G15 -> -57630 | H16: =H9+H11+H12+H13+H15 -> -58260 | I16: =I9+I11+I12+I13+I15 -> -58890 | J16: =J9+J11+J12+J13+J15 -> -59520 | K16: =K9+K11+K12+K13+K15 -> -60150 | L16: =L9+L11+L12+L13+L15 -> -60780 | ... AB16: =AB9+AB11+AB12+AB13+AB15 -> -3000
B17: Promote paid to the sponsor | E17: =IF(E$3=Fund_Term,-Assumptions!$C$25*MAX(0,SUM($E16:$AB16)-Assumptions!$C$23*((1+Assumptions!$C$24)^(Fund_Term/4)-1)),0) -> 0 | F17: =IF(F$3=Fund_Term,-Assumptions!$C$25*MAX(0,SUM($E16:$AB16)-Assumptions!$C$23*((1+Assumptions!$C$24)^(Fund_Term/4)-1)),0) -> 0 | G17: =IF(G$3=Fund_Term,-Assumptions!$C$25*MAX(0,SUM($E16:$AB16)-Assumptions!$C$23*((1+Assumptions!$C$24)^(Fund_Term/4)-1)),0) -> 0 | H17: =IF(H$3=Fund_Term,-Assumptions!$C$25*MAX(0,SUM($E16:$AB16)-Assumptions!$C$23*((1+Assumptions!$C$24)^(Fund_Term/4)-1)),0) -> 0 | I17: =IF(I$3=Fund_Term,-Assumptions!$C$25*MAX(0,SUM($E16:$AB16)-Assumptions!$C$23*((1+Assumptions!$C$24)^(Fund_Term/4)-1)),0) -> 0 | J17: =IF(J$3=Fund_Term,-Assumptions!$C$25*MAX(0,SUM($E16:$AB16)-Assumptions!$C$23*((1+Assumptions!$C$24)^(Fund_Term/4)-1)),0) -> 0 | K17: =IF(K$3=Fund_Term,-Assumptions!$C$25*MAX(0,SUM($E16:$AB16)-Assumptions!$C$23*((1+Assumptions!$C$24)^(Fund_Term/4)-1)),0) -> 0 | L17: =IF(L$3=Fund_Term,-Assumptions!$C$25*MAX(0,SUM($E16:$AB16)-Assumptions!$C$23*((1+Assumptions!$C$24)^(Fund_Term/4)-1)),0) -> 0 | ... AB17: =IF(AB$3=Fund_Term,-Assumptions!$C$25*MAX(0,SUM($E16:$AB16)-Assumptions!$C$23*((1+Assumptions!$C$24)^(Fund_Term/4)-1)),0) -> -63783.296
B18: LP net cash flow | E18: =E16+E17 -> -303000 | F18: =F16+F17 -> -57000 | G18: =G16+G17 -> -57630 | H18: =H16+H17 -> -58260 | I18: =I16+I17 -> -58890 | J18: =J16+J17 -> -59520 | K18: =K16+K17 -> -60150 | L18: =L16+L17 -> -60780 | ... AB18: =AB16+AB17 -> -66783.296
B19: Sponsor cash flow (promote) | E19: =-E17 -> 0 | F19: =-F17 -> 0 | G19: =-G17 -> 0 | H19: =-H17 -> 0 | I19: =-I17 -> 0 | J19: =-J17 -> 0 | K19: =-K17 -> 0 | L19: =-L17 -> 0 | ... AB19: =-AB17 -> 63783.296

Sheet Returns
B2: Returns (SAR '000 unless stated)
B5: Project unlevered IRR | C5: =IFERROR((1+IRR('Cash Flow'!$E$9:$AB$9))^4-1,0) -> 0.15161204
B6: Fund gross IRR (levered, pre-promote) | C6: =IFERROR((1+IRR('Cash Flow'!$E$16:$AB$16))^4-1,0) -> 0.1444434
B7: LP net IRR (after all fees & promote) | C7: =IFERROR((1+IRR('Cash Flow'!$E$18:$AB$18))^4-1,0) -> 0.13099204
B8: Project profit (unlevered) | C8: =SUM('Cash Flow'!$E$9:$AB$9) -> 600000
B9: Sponsor total profit (promote) | C9: =SUM('Cash Flow'!$E$19:$AB$19) -> 63783.296
B10: Profit on cost | C10: =C8/-SUM('Cash Flow'!$E$6:$AB$6,'Cash Flow'!$E$7:$AB$7) -> 0.5
B11: Peak facility balance | C11: =MAX('Cash Flow'!$E$14:$AB$14) -> 360000
