Workbook

Sheet Summary
B5: Summary
B7: General Info | E7: Returns
B8: Project Name | C8: The Willows Condos and Retail | F8: Project Costs | G8: Total Profit | H8: Equity Multiple | I8: IRR
E9: Unlevered Project Level | F9: =-SUMIF(CF!$B$10:$O$10,"<0") -> 36000000 | G9: =SUM(CF!$B$10:$O$10) -> 16000000 | H9: =(F9+G9)/F9 -> 1.4444444 | I9: =XIRR(CF!$B$10:$O$10,CF!$B$3:$O$3) -> 0.21496752
E10: Levered Project Level | F10: =-SUMIF(CF!$B$14:$O$14,"<0") -> 15164062 | G10: =SUM(CF!$B$14:$O$14) -> 13353438 | H10: =(F10+G10)/F10 -> 1.8805976 | I10: =XIRR(CF!$B$14:$O$14,CF!$B$3:$O$3) -> 0.35198958
E11: Partnership Returns
E12: LP | F12: =-SUMIF(CF!$B$17:$O$17,"<0") -> 13647656 | G12: =SUM(CF!$B$17:$O$17) -> 9614475 | H12: =(F12+G12)/F12 -> 1.7044781 | I12: =XIRR(CF!$B$17:$O$17,CF!$B$3:$O$3) -> 0.29439642
E13: GP | F13: =-SUMIF(CF!$B$18:$O$18,"<0") -> 1516406.2 | G13: =SUM(CF!$B$18:$O$18) -> 3738962.5 | H13: =(F13+G13)/F13 -> 3.4656734 | I13: =XIRR(CF!$B$18:$O$18,CF!$B$3:$O$3) -> 0.74491578

Sheet Inputs
A1: THE WILLOWS CONDOS AND RETAIL (USD)
A2: Land and acquisition | B2: 6000000
A3: Construction cost | B3: 30000000
A4: Condo sales (total) | B4: 38000000
A5: Retail exit value | B5: 14000000
A6: Loan to cost | B6: 0.65
A7: Interest rate (a year) | B7: 0.075
A8: LP share | B8: 0.9

Sheet CF
A3: Quarter ending | B3: 46112 | C3: 46203 | D3: 46295 | E3: 46387 | F3: 46477 | G3: 46568 | H3: 46660 | I3: 46752 | J3: 46843 | K3: 46934 | L3: 47026 | M3: 47118 | N3: 47208 | O3: 47299
A4: Quarter | B4: 0 | C4: 1 | D4: 2 | E4: 3 | F4: 4 | G4: 5 | H4: 6 | I4: 7 | J4: 8 | K4: 9 | L4: 10 | M4: 11 | N4: 12 | O4: 13
A6: Acquisition | B6: =IF(B$4=0,-Inputs!$B$2,0) -> -6000000 | C6: =IF(C$4=0,-Inputs!$B$2,0) -> 0 | D6: =IF(D$4=0,-Inputs!$B$2,0) -> 0 | E6: =IF(E$4=0,-Inputs!$B$2,0) -> 0 | F6: =IF(F$4=0,-Inputs!$B$2,0) -> 0 | G6: =IF(G$4=0,-Inputs!$B$2,0) -> 0 | H6: =IF(H$4=0,-Inputs!$B$2,0) -> 0 | I6: =IF(I$4=0,-Inputs!$B$2,0) -> 0 | ... O6: =IF(O$4=0,-Inputs!$B$2,0) -> 0
A7: Construction | B7: =IF(AND(B$4>=1,B$4<=8),-Inputs!$B$3/8,0) -> 0 | C7: =IF(AND(C$4>=1,C$4<=8),-Inputs!$B$3/8,0) -> -3750000 | D7: =IF(AND(D$4>=1,D$4<=8),-Inputs!$B$3/8,0) -> -3750000 | E7: =IF(AND(E$4>=1,E$4<=8),-Inputs!$B$3/8,0) -> -3750000 | F7: =IF(AND(F$4>=1,F$4<=8),-Inputs!$B$3/8,0) -> -3750000 | G7: =IF(AND(G$4>=1,G$4<=8),-Inputs!$B$3/8,0) -> -3750000 | H7: =IF(AND(H$4>=1,H$4<=8),-Inputs!$B$3/8,0) -> -3750000 | I7: =IF(AND(I$4>=1,I$4<=8),-Inputs!$B$3/8,0) -> -3750000 | ... O7: =IF(AND(O$4>=1,O$4<=8),-Inputs!$B$3/8,0) -> 0
A8: Condo sales | B8: =IF(AND(B$4>=9,B$4<=12),Inputs!$B$4/4,0) -> 0 | C8: =IF(AND(C$4>=9,C$4<=12),Inputs!$B$4/4,0) -> 0 | D8: =IF(AND(D$4>=9,D$4<=12),Inputs!$B$4/4,0) -> 0 | E8: =IF(AND(E$4>=9,E$4<=12),Inputs!$B$4/4,0) -> 0 | F8: =IF(AND(F$4>=9,F$4<=12),Inputs!$B$4/4,0) -> 0 | G8: =IF(AND(G$4>=9,G$4<=12),Inputs!$B$4/4,0) -> 0 | H8: =IF(AND(H$4>=9,H$4<=12),Inputs!$B$4/4,0) -> 0 | I8: =IF(AND(I$4>=9,I$4<=12),Inputs!$B$4/4,0) -> 0 | ... O8: =IF(AND(O$4>=9,O$4<=12),Inputs!$B$4/4,0) -> 0
A9: Retail sale | B9: =IF(B$4=13,Inputs!$B$5,0) -> 0 | C9: =IF(C$4=13,Inputs!$B$5,0) -> 0 | D9: =IF(D$4=13,Inputs!$B$5,0) -> 0 | E9: =IF(E$4=13,Inputs!$B$5,0) -> 0 | F9: =IF(F$4=13,Inputs!$B$5,0) -> 0 | G9: =IF(G$4=13,Inputs!$B$5,0) -> 0 | H9: =IF(H$4=13,Inputs!$B$5,0) -> 0 | I9: =IF(I$4=13,Inputs!$B$5,0) -> 0 | ... O9: =IF(O$4=13,Inputs!$B$5,0) -> 14000000
A10: Unlevered cash flow | B10: =SUM(B6:B9) -> -6000000 | C10: =SUM(C6:C9) -> -3750000 | D10: =SUM(D6:D9) -> -3750000 | E10: =SUM(E6:E9) -> -3750000 | F10: =SUM(F6:F9) -> -3750000 | G10: =SUM(G6:G9) -> -3750000 | H10: =SUM(H6:H9) -> -3750000 | I10: =SUM(I6:I9) -> -3750000 | ... O10: =SUM(O6:O9) -> 14000000
A11: Loan draw | B11: =-(B6+B7)*Inputs!$B$6 -> 3900000 | C11: =-(C6+C7)*Inputs!$B$6 -> 2437500 | D11: =-(D6+D7)*Inputs!$B$6 -> 2437500 | E11: =-(E6+E7)*Inputs!$B$6 -> 2437500 | F11: =-(F6+F7)*Inputs!$B$6 -> 2437500 | G11: =-(G6+G7)*Inputs!$B$6 -> 2437500 | H11: =-(H6+H7)*Inputs!$B$6 -> 2437500 | I11: =-(I6+I7)*Inputs!$B$6 -> 2437500 | ... O11: =-(O6+O7)*Inputs!$B$6 -> 0
A12: Interest | B12: =0 -> 0 | C12: =-B15*Inputs!$B$7/4 -> -73125 | D12: =-C15*Inputs!$B$7/4 -> -118828.12 | E12: =-D15*Inputs!$B$7/4 -> -164531.25 | F12: =-E15*Inputs!$B$7/4 -> -210234.38 | G12: =-F15*Inputs!$B$7/4 -> -255937.5 | H12: =-G15*Inputs!$B$7/4 -> -301640.62 | I12: =-H15*Inputs!$B$7/4 -> -347343.75 | J12: =-I15*Inputs!$B$7/4 -> -393046.88 | ... O12: =-N15*Inputs!$B$7/4 -> 0
A13: Repayment | B13: =0 -> 0 | C13: =-MIN(B15+C11,MAX(0,C8+C9)) -> 0 | D13: =-MIN(C15+D11,MAX(0,D8+D9)) -> 0 | E13: =-MIN(D15+E11,MAX(0,E8+E9)) -> 0 | F13: =-MIN(E15+F11,MAX(0,F8+F9)) -> 0 | G13: =-MIN(F15+G11,MAX(0,G8+G9)) -> 0 | H13: =-MIN(G15+H11,MAX(0,H8+H9)) -> 0 | I13: =-MIN(H15+I11,MAX(0,I8+I9)) -> 0 | J13: =-MIN(I15+J11,MAX(0,J8+J9)) -> 0 | ... O13: =-MIN(N15+O11,MAX(0,O8+O9)) -> 0
A14: Levered cash flow | B14: =B10+B11+B12+B13 -> -2100000 | C14: =C10+C11+C12+C13 -> -1385625 | D14: =D10+D11+D12+D13 -> -1431328.1 | E14: =E10+E11+E12+E13 -> -1477031.2 | F14: =F10+F11+F12+F13 -> -1522734.4 | G14: =G10+G11+G12+G13 -> -1568437.5 | H14: =H10+H11+H12+H13 -> -1614140.6 | I14: =I10+I11+I12+I13 -> -1659843.8 | ... O14: =O10+O11+O12+O13 -> 14000000
A15: Loan balance | B15: =B11+B13 -> 3900000 | C15: =B15+C11+C13 -> 6337500 | D15: =C15+D11+D13 -> 8775000 | E15: =D15+E11+E13 -> 11212500 | F15: =E15+F11+F13 -> 13650000 | G15: =F15+G11+G13 -> 16087500 | H15: =G15+H11+H13 -> 18525000 | I15: =H15+I11+I13 -> 20962500 | J15: =I15+J11+J13 -> 23400000 | ... O15: =N15+O11+O13 -> 0
A17: LP cash flow | B17: =B14*Inputs!$B$8-IF(B$4=13,0.2*MAX(0,SUM($B$14:$O$14))*Inputs!$B$8,0) -> -1890000 | C17: =C14*Inputs!$B$8-IF(C$4=13,0.2*MAX(0,SUM($B$14:$O$14))*Inputs!$B$8,0) -> -1247062.5 | D17: =D14*Inputs!$B$8-IF(D$4=13,0.2*MAX(0,SUM($B$14:$O$14))*Inputs!$B$8,0) -> -1288195.3 | E17: =E14*Inputs!$B$8-IF(E$4=13,0.2*MAX(0,SUM($B$14:$O$14))*Inputs!$B$8,0) -> -1329328.1 | F17: =F14*Inputs!$B$8-IF(F$4=13,0.2*MAX(0,SUM($B$14:$O$14))*Inputs!$B$8,0) -> -1370460.9 | G17: =G14*Inputs!$B$8-IF(G$4=13,0.2*MAX(0,SUM($B$14:$O$14))*Inputs!$B$8,0) -> -1411593.8 | H17: =H14*Inputs!$B$8-IF(H$4=13,0.2*MAX(0,SUM($B$14:$O$14))*Inputs!$B$8,0) -> -1452726.6 | I17: =I14*Inputs!$B$8-IF(I$4=13,0.2*MAX(0,SUM($B$14:$O$14))*Inputs!$B$8,0) -> -1493859.4 | ... O17: =O14*Inputs!$B$8-IF(O$4=13,0.2*MAX(0,SUM($B$14:$O$14))*Inputs!$B$8,0) -> 10196381
A18: GP cash flow | B18: =B14*(1-Inputs!$B$8)+IF(B$4=13,0.2*MAX(0,SUM($B$14:$O$14))*Inputs!$B$8,0) -> -210000 | C18: =C14*(1-Inputs!$B$8)+IF(C$4=13,0.2*MAX(0,SUM($B$14:$O$14))*Inputs!$B$8,0) -> -138562.5 | D18: =D14*(1-Inputs!$B$8)+IF(D$4=13,0.2*MAX(0,SUM($B$14:$O$14))*Inputs!$B$8,0) -> -143132.81 | E18: =E14*(1-Inputs!$B$8)+IF(E$4=13,0.2*MAX(0,SUM($B$14:$O$14))*Inputs!$B$8,0) -> -147703.12 | F18: =F14*(1-Inputs!$B$8)+IF(F$4=13,0.2*MAX(0,SUM($B$14:$O$14))*Inputs!$B$8,0) -> -152273.44 | G18: =G14*(1-Inputs!$B$8)+IF(G$4=13,0.2*MAX(0,SUM($B$14:$O$14))*Inputs!$B$8,0) -> -156843.75 | H18: =H14*(1-Inputs!$B$8)+IF(H$4=13,0.2*MAX(0,SUM($B$14:$O$14))*Inputs!$B$8,0) -> -161414.06 | I18: =I14*(1-Inputs!$B$8)+IF(I$4=13,0.2*MAX(0,SUM($B$14:$O$14))*Inputs!$B$8,0) -> -165984.38 | ... O18: =O14*(1-Inputs!$B$8)+IF(O$4=13,0.2*MAX(0,SUM($B$14:$O$14))*Inputs!$B$8,0) -> 3803618.8
