Workbook

Sheet Summary
B2: KEY RETURN METRICS
N20: PARTNERSHIP RETURNS | Q20: ROI | R20: EMx | S20: IRR
N21: [Limited Partner Name] | Q21: =SUM(Underwriting!$B$17:$AS$17)/-SUMIF(Underwriting!$B$17:$AS$17,"<0") -> 2.4013678 | R21: =Q21+1 -> 3.4013678 | S21: =XIRR(Underwriting!$B$17:$AS$17,Underwriting!$B$4:$AS$4) -> 0.5489864
N22: [General Partner Name] | Q22: =SUM(Underwriting!$B$18:$AS$18)/-SUMIF(Underwriting!$B$18:$AS$18,"<0") -> 8.4047874 | R22: =Q22+1 -> 9.4047874 | S22: =XIRR(Underwriting!$B$18:$AS$18,Underwriting!$B$4:$AS$4) -> 1.1479957
N24: PROPERTY RETURNS | Q24: ROI | R24: EMx | S24: IRR
N25: Unlevered | Q25: =SUM(Underwriting!$B$10:$AS$10)/-SUMIF(Underwriting!$B$10:$AS$10,"<0") -> 1.4338462 | R25: =Q25+1 -> 2.4338462 | S25: =XIRR(Underwriting!$B$10:$AS$10,Underwriting!$B$4:$AS$4) -> 0.367004
N26: Levered | Q26: =SUM(Underwriting!$B$14:$AS$14)/-SUMIF(Underwriting!$B$14:$AS$14,"<0") -> 3.0017098 | R26: =Q26+1 -> 4.0017098 | S26: =XIRR(Underwriting!$B$14:$AS$14,Underwriting!$B$4:$AS$4) -> 0.63387978
B30: Net Profit | C30: =SUM(Underwriting!$B$14:$AS$14) -> 19649192
B31: Total Uses | C31: =-SUM(Underwriting!$B$6:$AS$6,Underwriting!$B$7:$AS$7) -> 15000000

Sheet Inputs
A1: HARBOUR VIEW RETAIL (USD)
A2: Land | B2: 3000000
A3: Hard costs (total) | B3: 12000000
A4: Construction months | B4: 18
A5: Stabilised NOI (a year) | B5: 2100000
A6: Exit cap rate | B6: 0.065
A7: Hold (months after completion) | B7: 24
A8: Loan to cost | B8: 0.6
A9: Interest rate (a year) | B9: 0.07
A10: LP share of equity | B10: 0.9
A11: Preferred return | B11: 0.08
A12: GP promote above the pref | B12: 0.2

Sheet Underwriting
A3: Month | B3: 0 | C3: 1 | D3: 2 | E3: 3 | F3: 4 | G3: 5 | H3: 6 | I3: 7 | J3: 8 | K3: 9 | L3: 10 | M3: 11 | N3: 12 | O3: 13 | P3: 14 | Q3: 15 | R3: 16 | S3: 17 | T3: 18 | U3: 19 | V3: 20 | W3: 21 | X3: 22 | Y3: 23 | Z3: 24 | AA3: 25 | AB3: 26 | AC3: 27 | AD3: 28 | AE3: 29 | AF3: 30 | AG3: 31 | AH3: 32 | AI3: 33 | AJ3: 34 | AK3: 35 | AL3: 36 | AM3: 37 | AN3: 38 | AO3: 39 | AP3: 40 | AQ3: 41 | AR3: 42 | AS3: 43
A4: Month ending | B4: 46053 | C4: 46081 | D4: 46112 | E4: 46142 | F4: 46173 | G4: 46203 | H4: 46234 | I4: 46265 | J4: 46295 | K4: 46326 | L4: 46356 | M4: 46387 | N4: 46418 | O4: 46446 | P4: 46477 | Q4: 46507 | R4: 46538 | S4: 46568 | T4: 46599 | U4: 46630 | V4: 46660 | W4: 46691 | X4: 46721 | Y4: 46752 | Z4: 46783 | AA4: 46812 | AB4: 46843 | AC4: 46873 | AD4: 46904 | AE4: 46934 | AF4: 46965 | AG4: 46996 | AH4: 47026 | AI4: 47057 | AJ4: 47087 | AK4: 47118 | AL4: 47149 | AM4: 47177 | AN4: 47208 | AO4: 47238 | AP4: 47269 | AQ4: 47299 | AR4: 47330 | AS4: 47361
A6: Land | B6: =IF(B$3=0,-Inputs!$B$2,0) -> -3000000 | C6: =IF(C$3=0,-Inputs!$B$2,0) -> 0 | D6: =IF(D$3=0,-Inputs!$B$2,0) -> 0 | E6: =IF(E$3=0,-Inputs!$B$2,0) -> 0 | F6: =IF(F$3=0,-Inputs!$B$2,0) -> 0 | G6: =IF(G$3=0,-Inputs!$B$2,0) -> 0 | H6: =IF(H$3=0,-Inputs!$B$2,0) -> 0 | I6: =IF(I$3=0,-Inputs!$B$2,0) -> 0 | ... AS6: =IF(AS$3=0,-Inputs!$B$2,0) -> 0
A7: Hard costs | B7: =IF(AND(B$3>=1,B$3<=Inputs!$B$4),-Inputs!$B$3/Inputs!$B$4,0) -> 0 | C7: =IF(AND(C$3>=1,C$3<=Inputs!$B$4),-Inputs!$B$3/Inputs!$B$4,0) -> -666666.67 | D7: =IF(AND(D$3>=1,D$3<=Inputs!$B$4),-Inputs!$B$3/Inputs!$B$4,0) -> -666666.67 | E7: =IF(AND(E$3>=1,E$3<=Inputs!$B$4),-Inputs!$B$3/Inputs!$B$4,0) -> -666666.67 | F7: =IF(AND(F$3>=1,F$3<=Inputs!$B$4),-Inputs!$B$3/Inputs!$B$4,0) -> -666666.67 | G7: =IF(AND(G$3>=1,G$3<=Inputs!$B$4),-Inputs!$B$3/Inputs!$B$4,0) -> -666666.67 | H7: =IF(AND(H$3>=1,H$3<=Inputs!$B$4),-Inputs!$B$3/Inputs!$B$4,0) -> -666666.67 | I7: =IF(AND(I$3>=1,I$3<=Inputs!$B$4),-Inputs!$B$3/Inputs!$B$4,0) -> -666666.67 | ... AS7: =IF(AND(AS$3>=1,AS$3<=Inputs!$B$4),-Inputs!$B$3/Inputs!$B$4,0) -> 0
A8: NOI | B8: =IF(AND(B$3>Inputs!$B$4,B$3<=Inputs!$B$4+Inputs!$B$7),Inputs!$B$5/12,0) -> 0 | C8: =IF(AND(C$3>Inputs!$B$4,C$3<=Inputs!$B$4+Inputs!$B$7),Inputs!$B$5/12,0) -> 0 | D8: =IF(AND(D$3>Inputs!$B$4,D$3<=Inputs!$B$4+Inputs!$B$7),Inputs!$B$5/12,0) -> 0 | E8: =IF(AND(E$3>Inputs!$B$4,E$3<=Inputs!$B$4+Inputs!$B$7),Inputs!$B$5/12,0) -> 0 | F8: =IF(AND(F$3>Inputs!$B$4,F$3<=Inputs!$B$4+Inputs!$B$7),Inputs!$B$5/12,0) -> 0 | G8: =IF(AND(G$3>Inputs!$B$4,G$3<=Inputs!$B$4+Inputs!$B$7),Inputs!$B$5/12,0) -> 0 | H8: =IF(AND(H$3>Inputs!$B$4,H$3<=Inputs!$B$4+Inputs!$B$7),Inputs!$B$5/12,0) -> 0 | I8: =IF(AND(I$3>Inputs!$B$4,I$3<=Inputs!$B$4+Inputs!$B$7),Inputs!$B$5/12,0) -> 0 | ... AS8: =IF(AND(AS$3>Inputs!$B$4,AS$3<=Inputs!$B$4+Inputs!$B$7),Inputs!$B$5/12,0) -> 0
A9: Sale proceeds | B9: =IF(B$3=Inputs!$B$4+Inputs!$B$7+1,Inputs!$B$5/Inputs!$B$6,0) -> 0 | C9: =IF(C$3=Inputs!$B$4+Inputs!$B$7+1,Inputs!$B$5/Inputs!$B$6,0) -> 0 | D9: =IF(D$3=Inputs!$B$4+Inputs!$B$7+1,Inputs!$B$5/Inputs!$B$6,0) -> 0 | E9: =IF(E$3=Inputs!$B$4+Inputs!$B$7+1,Inputs!$B$5/Inputs!$B$6,0) -> 0 | F9: =IF(F$3=Inputs!$B$4+Inputs!$B$7+1,Inputs!$B$5/Inputs!$B$6,0) -> 0 | G9: =IF(G$3=Inputs!$B$4+Inputs!$B$7+1,Inputs!$B$5/Inputs!$B$6,0) -> 0 | H9: =IF(H$3=Inputs!$B$4+Inputs!$B$7+1,Inputs!$B$5/Inputs!$B$6,0) -> 0 | I9: =IF(I$3=Inputs!$B$4+Inputs!$B$7+1,Inputs!$B$5/Inputs!$B$6,0) -> 0 | ... AS9: =IF(AS$3=Inputs!$B$4+Inputs!$B$7+1,Inputs!$B$5/Inputs!$B$6,0) -> 32307692
A10: Unlevered cash flow | B10: =SUM(B6:B9) -> -3000000 | C10: =SUM(C6:C9) -> -666666.67 | D10: =SUM(D6:D9) -> -666666.67 | E10: =SUM(E6:E9) -> -666666.67 | F10: =SUM(F6:F9) -> -666666.67 | G10: =SUM(G6:G9) -> -666666.67 | H10: =SUM(H6:H9) -> -666666.67 | I10: =SUM(I6:I9) -> -666666.67 | ... AS10: =SUM(AS6:AS9) -> 32307692
A11: Loan draw | B11: =-(B6+B7)*Inputs!$B$8 -> 1800000 | C11: =-(C6+C7)*Inputs!$B$8 -> 400000 | D11: =-(D6+D7)*Inputs!$B$8 -> 400000 | E11: =-(E6+E7)*Inputs!$B$8 -> 400000 | F11: =-(F6+F7)*Inputs!$B$8 -> 400000 | G11: =-(G6+G7)*Inputs!$B$8 -> 400000 | H11: =-(H6+H7)*Inputs!$B$8 -> 400000 | I11: =-(I6+I7)*Inputs!$B$8 -> 400000 | ... AS11: =-(AS6+AS7)*Inputs!$B$8 -> 0
A12: Interest | B12: =0 -> 0 | C12: =-B15*Inputs!$B$9/12 -> -10500 | D12: =-C15*Inputs!$B$9/12 -> -12833.333 | E12: =-D15*Inputs!$B$9/12 -> -15166.667 | F12: =-E15*Inputs!$B$9/12 -> -17500 | G12: =-F15*Inputs!$B$9/12 -> -19833.333 | H12: =-G15*Inputs!$B$9/12 -> -22166.667 | I12: =-H15*Inputs!$B$9/12 -> -24500 | J12: =-I15*Inputs!$B$9/12 -> -26833.333 | ... AS12: =-AR15*Inputs!$B$9/12 -> -52500
A13: Loan repayment | B13: =0 -> 0 | C13: =IF(C$3=Inputs!$B$4+Inputs!$B$7+1,-(B15+C11),0) -> 0 | D13: =IF(D$3=Inputs!$B$4+Inputs!$B$7+1,-(C15+D11),0) -> 0 | E13: =IF(E$3=Inputs!$B$4+Inputs!$B$7+1,-(D15+E11),0) -> 0 | F13: =IF(F$3=Inputs!$B$4+Inputs!$B$7+1,-(E15+F11),0) -> 0 | G13: =IF(G$3=Inputs!$B$4+Inputs!$B$7+1,-(F15+G11),0) -> 0 | H13: =IF(H$3=Inputs!$B$4+Inputs!$B$7+1,-(G15+H11),0) -> 0 | I13: =IF(I$3=Inputs!$B$4+Inputs!$B$7+1,-(H15+I11),0) -> 0 | J13: =IF(J$3=Inputs!$B$4+Inputs!$B$7+1,-(I15+J11),0) -> 0 | ... AS13: =IF(AS$3=Inputs!$B$4+Inputs!$B$7+1,-(AR15+AS11),0) -> -9000000
A14: Levered cash flow | B14: =B10+B11+B12+B13 -> -1200000 | C14: =C10+C11+C12+C13 -> -277166.67 | D14: =D10+D11+D12+D13 -> -279500 | E14: =E10+E11+E12+E13 -> -281833.33 | F14: =F10+F11+F12+F13 -> -284166.67 | G14: =G10+G11+G12+G13 -> -286500 | H14: =H10+H11+H12+H13 -> -288833.33 | I14: =I10+I11+I12+I13 -> -291166.67 | ... AS14: =AS10+AS11+AS12+AS13 -> 23255192
A15: Loan balance | B15: =B11+B13 -> 1800000 | C15: =B15+C11+C13 -> 2200000 | D15: =C15+D11+D13 -> 2600000 | E15: =D15+E11+E13 -> 3000000 | F15: =E15+F11+F13 -> 3400000 | G15: =F15+G11+G13 -> 3800000 | H15: =G15+H11+H13 -> 4200000 | I15: =H15+I11+I13 -> 4600000 | J15: =I15+J11+J13 -> 5000000 | ... AS15: =AR15+AS11+AS13 -> 0
A17: LP share of levered cash flow | B17: =B14*Inputs!$B$10-IF(B$3=Inputs!$B$4+Inputs!$B$7+1,Inputs!$B$12*MAX(0,SUM($B$14:$AS$14))*Inputs!$B$10,0) -> -1080000 | C17: =C14*Inputs!$B$10-IF(C$3=Inputs!$B$4+Inputs!$B$7+1,Inputs!$B$12*MAX(0,SUM($B$14:$AS$14))*Inputs!$B$10,0) -> -249450 | D17: =D14*Inputs!$B$10-IF(D$3=Inputs!$B$4+Inputs!$B$7+1,Inputs!$B$12*MAX(0,SUM($B$14:$AS$14))*Inputs!$B$10,0) -> -251550 | E17: =E14*Inputs!$B$10-IF(E$3=Inputs!$B$4+Inputs!$B$7+1,Inputs!$B$12*MAX(0,SUM($B$14:$AS$14))*Inputs!$B$10,0) -> -253650 | F17: =F14*Inputs!$B$10-IF(F$3=Inputs!$B$4+Inputs!$B$7+1,Inputs!$B$12*MAX(0,SUM($B$14:$AS$14))*Inputs!$B$10,0) -> -255750 | G17: =G14*Inputs!$B$10-IF(G$3=Inputs!$B$4+Inputs!$B$7+1,Inputs!$B$12*MAX(0,SUM($B$14:$AS$14))*Inputs!$B$10,0) -> -257850 | H17: =H14*Inputs!$B$10-IF(H$3=Inputs!$B$4+Inputs!$B$7+1,Inputs!$B$12*MAX(0,SUM($B$14:$AS$14))*Inputs!$B$10,0) -> -259950 | I17: =I14*Inputs!$B$10-IF(I$3=Inputs!$B$4+Inputs!$B$7+1,Inputs!$B$12*MAX(0,SUM($B$14:$AS$14))*Inputs!$B$10,0) -> -262050 | ... AS17: =AS14*Inputs!$B$10-IF(AS$3=Inputs!$B$4+Inputs!$B$7+1,Inputs!$B$12*MAX(0,SUM($B$14:$AS$14))*Inputs!$B$10,0) -> 17392818
A18: GP share of levered cash flow | B18: =B14*(1-Inputs!$B$10)+IF(B$3=Inputs!$B$4+Inputs!$B$7+1,Inputs!$B$12*MAX(0,SUM($B$14:$AS$14))*Inputs!$B$10,0) -> -120000 | C18: =C14*(1-Inputs!$B$10)+IF(C$3=Inputs!$B$4+Inputs!$B$7+1,Inputs!$B$12*MAX(0,SUM($B$14:$AS$14))*Inputs!$B$10,0) -> -27716.667 | D18: =D14*(1-Inputs!$B$10)+IF(D$3=Inputs!$B$4+Inputs!$B$7+1,Inputs!$B$12*MAX(0,SUM($B$14:$AS$14))*Inputs!$B$10,0) -> -27950 | E18: =E14*(1-Inputs!$B$10)+IF(E$3=Inputs!$B$4+Inputs!$B$7+1,Inputs!$B$12*MAX(0,SUM($B$14:$AS$14))*Inputs!$B$10,0) -> -28183.333 | F18: =F14*(1-Inputs!$B$10)+IF(F$3=Inputs!$B$4+Inputs!$B$7+1,Inputs!$B$12*MAX(0,SUM($B$14:$AS$14))*Inputs!$B$10,0) -> -28416.667 | G18: =G14*(1-Inputs!$B$10)+IF(G$3=Inputs!$B$4+Inputs!$B$7+1,Inputs!$B$12*MAX(0,SUM($B$14:$AS$14))*Inputs!$B$10,0) -> -28650 | H18: =H14*(1-Inputs!$B$10)+IF(H$3=Inputs!$B$4+Inputs!$B$7+1,Inputs!$B$12*MAX(0,SUM($B$14:$AS$14))*Inputs!$B$10,0) -> -28883.333 | I18: =I14*(1-Inputs!$B$10)+IF(I$3=Inputs!$B$4+Inputs!$B$7+1,Inputs!$B$12*MAX(0,SUM($B$14:$AS$14))*Inputs!$B$10,0) -> -29116.667 | ... AS18: =AS14*(1-Inputs!$B$10)+IF(AS$3=Inputs!$B$4+Inputs!$B$7+1,Inputs!$B$12*MAX(0,SUM($B$14:$AS$14))*Inputs!$B$10,0) -> 5862373.8
