Workbook

Sheet Fund Summary
B2: AURORA REAL ESTATE FUND I · FUND SUMMARY
B3: All amounts in EUR
B5: Fund returns
B6: Gross IRR | C6: =IRR('Fund Cash Flow'!D9:N9) -> 0.12065819
B7: Net IRR | C7: =IRR(Waterfall!D27:N27) -> 0.083000294
B8: TVPI | C8: =SUM(Waterfall!D24:N24)*(1-Assumptions!C5)/SUM(Waterfall!D6:N6)/(1-Assumptions!C5) -> 1.5274657
B9: DPI | C9: =C8 -> 1.5274657
B11: Fund economics
B12: Total capital called | C12: =SUM('Fund Cash Flow'!D15:N15) -> 132820000
B13: Total distributions | C13: =SUM(Waterfall!D24:N24) -> 202878000
B14: Gross profit (assets) | C14: =SUM('Fund Cash Flow'!D9:N9) -> 104660000
B15: Carried interest (GP) | C15: =SUM(Waterfall!D25:N25) -> 17602000
B16: Management fees | C16: =-SUM('Fund Cash Flow'!D11:N11) -> 13500000

Sheet Assumptions
B2: AURORA REAL ESTATE FUND I · ASSUMPTIONS (EUR)
B4: Total commitments | C4: 150000000
B5: GP commitment (share of total) | C5: 0.02
B6: Management fee (investment period, on commitments) | C6: 0.015
B7: Management fee (after, on invested capital) | C7: 0.0125
B8: Investment period (years) | C8: 4
B9: Fund expenses (a year) | C9: 350000
B10: Preferred return | C10: 0.08
B11: GP catch-up | C11: 1
B12: Carried interest | C12: 0.2
B14: Assets | C14: Equity in | D14: Year in | E14: Net income yield | F14: Exit multiple of cost | G14: Year out
B15: Rhine Logistics | C15: 42000000 | D15: 1 | E15: 0.055 | F15: 1.55 | G15: 6
B16: Porto Residences | C16: 38000000 | D16: 2 | E16: 0.045 | F16: 1.7 | G16: 8
B17: Milan Offices | C17: 51000000 | D17: 3 | E17: 0.05 | F17: 1.35 | G17: 9

Sheet Fund Cash Flow
B2: FUND CASH FLOW (EUR)
B4: Year | D4: 0 | E4: 1 | F4: 2 | G4: 3 | H4: 4 | I4: 5 | J4: 6 | K4: 7 | L4: 8 | M4: 9 | N4: 10
B6: Acquisitions | D6: =IF(D$4=Assumptions!$D$15,-Assumptions!$C$15,0)+IF(D$4=Assumptions!$D$16,-Assumptions!$C$16,0)+IF(D$4=Assumptions!$D$17,-Assumptions!$C$17,0) -> 0 | E6: =IF(E$4=Assumptions!$D$15,-Assumptions!$C$15,0)+IF(E$4=Assumptions!$D$16,-Assumptions!$C$16,0)+IF(E$4=Assumptions!$D$17,-Assumptions!$C$17,0) -> -42000000 | F6: =IF(F$4=Assumptions!$D$15,-Assumptions!$C$15,0)+IF(F$4=Assumptions!$D$16,-Assumptions!$C$16,0)+IF(F$4=Assumptions!$D$17,-Assumptions!$C$17,0) -> -38000000 | G6: =IF(G$4=Assumptions!$D$15,-Assumptions!$C$15,0)+IF(G$4=Assumptions!$D$16,-Assumptions!$C$16,0)+IF(G$4=Assumptions!$D$17,-Assumptions!$C$17,0) -> -51000000 | H6: =IF(H$4=Assumptions!$D$15,-Assumptions!$C$15,0)+IF(H$4=Assumptions!$D$16,-Assumptions!$C$16,0)+IF(H$4=Assumptions!$D$17,-Assumptions!$C$17,0) -> 0 | I6: =IF(I$4=Assumptions!$D$15,-Assumptions!$C$15,0)+IF(I$4=Assumptions!$D$16,-Assumptions!$C$16,0)+IF(I$4=Assumptions!$D$17,-Assumptions!$C$17,0) -> 0 | J6: =IF(J$4=Assumptions!$D$15,-Assumptions!$C$15,0)+IF(J$4=Assumptions!$D$16,-Assumptions!$C$16,0)+IF(J$4=Assumptions!$D$17,-Assumptions!$C$17,0) -> 0 | K6: =IF(K$4=Assumptions!$D$15,-Assumptions!$C$15,0)+IF(K$4=Assumptions!$D$16,-Assumptions!$C$16,0)+IF(K$4=Assumptions!$D$17,-Assumptions!$C$17,0) -> 0 | ... N6: =IF(N$4=Assumptions!$D$15,-Assumptions!$C$15,0)+IF(N$4=Assumptions!$D$16,-Assumptions!$C$16,0)+IF(N$4=Assumptions!$D$17,-Assumptions!$C$17,0) -> 0
B7: Net income | D7: =IF(AND(D$4>Assumptions!$D$15,D$4<=Assumptions!$G$15),Assumptions!$C$15*Assumptions!$E$15,0)+IF(AND(D$4>Assumptions!$D$16,D$4<=Assumptions!$G$16),Assumptions!$C$16*Assumptions!$E$16,0)+IF(AND(D$4>Assumptions!$D$17,D$4<=Assumptions!$G$17),Assumptions!$C$17*Assumptions!$E$17,0) -> 0 | E7: =IF(AND(E$4>Assumptions!$D$15,E$4<=Assumptions!$G$15),Assumptions!$C$15*Assumptions!$E$15,0)+IF(AND(E$4>Assumptions!$D$16,E$4<=Assumptions!$G$16),Assumptions!$C$16*Assumptions!$E$16,0)+IF(AND(E$4>Assumptions!$D$17,E$4<=Assumptions!$G$17),Assumptions!$C$17*Assumptions!$E$17,0) -> 0 | F7: =IF(AND(F$4>Assumptions!$D$15,F$4<=Assumptions!$G$15),Assumptions!$C$15*Assumptions!$E$15,0)+IF(AND(F$4>Assumptions!$D$16,F$4<=Assumptions!$G$16),Assumptions!$C$16*Assumptions!$E$16,0)+IF(AND(F$4>Assumptions!$D$17,F$4<=Assumptions!$G$17),Assumptions!$C$17*Assumptions!$E$17,0) -> 2310000 | G7: =IF(AND(G$4>Assumptions!$D$15,G$4<=Assumptions!$G$15),Assumptions!$C$15*Assumptions!$E$15,0)+IF(AND(G$4>Assumptions!$D$16,G$4<=Assumptions!$G$16),Assumptions!$C$16*Assumptions!$E$16,0)+IF(AND(G$4>Assumptions!$D$17,G$4<=Assumptions!$G$17),Assumptions!$C$17*Assumptions!$E$17,0) -> 4020000 | H7: =IF(AND(H$4>Assumptions!$D$15,H$4<=Assumptions!$G$15),Assumptions!$C$15*Assumptions!$E$15,0)+IF(AND(H$4>Assumptions!$D$16,H$4<=Assumptions!$G$16),Assumptions!$C$16*Assumptions!$E$16,0)+IF(AND(H$4>Assumptions!$D$17,H$4<=Assumptions!$G$17),Assumptions!$C$17*Assumptions!$E$17,0) -> 6570000 | I7: =IF(AND(I$4>Assumptions!$D$15,I$4<=Assumptions!$G$15),Assumptions!$C$15*Assumptions!$E$15,0)+IF(AND(I$4>Assumptions!$D$16,I$4<=Assumptions!$G$16),Assumptions!$C$16*Assumptions!$E$16,0)+IF(AND(I$4>Assumptions!$D$17,I$4<=Assumptions!$G$17),Assumptions!$C$17*Assumptions!$E$17,0) -> 6570000 | J7: =IF(AND(J$4>Assumptions!$D$15,J$4<=Assumptions!$G$15),Assumptions!$C$15*Assumptions!$E$15,0)+IF(AND(J$4>Assumptions!$D$16,J$4<=Assumptions!$G$16),Assumptions!$C$16*Assumptions!$E$16,0)+IF(AND(J$4>Assumptions!$D$17,J$4<=Assumptions!$G$17),Assumptions!$C$17*Assumptions!$E$17,0) -> 6570000 | K7: =IF(AND(K$4>Assumptions!$D$15,K$4<=Assumptions!$G$15),Assumptions!$C$15*Assumptions!$E$15,0)+IF(AND(K$4>Assumptions!$D$16,K$4<=Assumptions!$G$16),Assumptions!$C$16*Assumptions!$E$16,0)+IF(AND(K$4>Assumptions!$D$17,K$4<=Assumptions!$G$17),Assumptions!$C$17*Assumptions!$E$17,0) -> 4260000 | ... N7: =IF(AND(N$4>Assumptions!$D$15,N$4<=Assumptions!$G$15),Assumptions!$C$15*Assumptions!$E$15,0)+IF(AND(N$4>Assumptions!$D$16,N$4<=Assumptions!$G$16),Assumptions!$C$16*Assumptions!$E$16,0)+IF(AND(N$4>Assumptions!$D$17,N$4<=Assumptions!$G$17),Assumptions!$C$17*Assumptions!$E$17,0) -> 0
B8: Sale proceeds | D8: =IF(D$4=Assumptions!$G$15,Assumptions!$C$15*Assumptions!$F$15,0)+IF(D$4=Assumptions!$G$16,Assumptions!$C$16*Assumptions!$F$16,0)+IF(D$4=Assumptions!$G$17,Assumptions!$C$17*Assumptions!$F$17,0) -> 0 | E8: =IF(E$4=Assumptions!$G$15,Assumptions!$C$15*Assumptions!$F$15,0)+IF(E$4=Assumptions!$G$16,Assumptions!$C$16*Assumptions!$F$16,0)+IF(E$4=Assumptions!$G$17,Assumptions!$C$17*Assumptions!$F$17,0) -> 0 | F8: =IF(F$4=Assumptions!$G$15,Assumptions!$C$15*Assumptions!$F$15,0)+IF(F$4=Assumptions!$G$16,Assumptions!$C$16*Assumptions!$F$16,0)+IF(F$4=Assumptions!$G$17,Assumptions!$C$17*Assumptions!$F$17,0) -> 0 | G8: =IF(G$4=Assumptions!$G$15,Assumptions!$C$15*Assumptions!$F$15,0)+IF(G$4=Assumptions!$G$16,Assumptions!$C$16*Assumptions!$F$16,0)+IF(G$4=Assumptions!$G$17,Assumptions!$C$17*Assumptions!$F$17,0) -> 0 | H8: =IF(H$4=Assumptions!$G$15,Assumptions!$C$15*Assumptions!$F$15,0)+IF(H$4=Assumptions!$G$16,Assumptions!$C$16*Assumptions!$F$16,0)+IF(H$4=Assumptions!$G$17,Assumptions!$C$17*Assumptions!$F$17,0) -> 0 | I8: =IF(I$4=Assumptions!$G$15,Assumptions!$C$15*Assumptions!$F$15,0)+IF(I$4=Assumptions!$G$16,Assumptions!$C$16*Assumptions!$F$16,0)+IF(I$4=Assumptions!$G$17,Assumptions!$C$17*Assumptions!$F$17,0) -> 0 | J8: =IF(J$4=Assumptions!$G$15,Assumptions!$C$15*Assumptions!$F$15,0)+IF(J$4=Assumptions!$G$16,Assumptions!$C$16*Assumptions!$F$16,0)+IF(J$4=Assumptions!$G$17,Assumptions!$C$17*Assumptions!$F$17,0) -> 65100000 | K8: =IF(K$4=Assumptions!$G$15,Assumptions!$C$15*Assumptions!$F$15,0)+IF(K$4=Assumptions!$G$16,Assumptions!$C$16*Assumptions!$F$16,0)+IF(K$4=Assumptions!$G$17,Assumptions!$C$17*Assumptions!$F$17,0) -> 0 | ... N8: =IF(N$4=Assumptions!$G$15,Assumptions!$C$15*Assumptions!$F$15,0)+IF(N$4=Assumptions!$G$16,Assumptions!$C$16*Assumptions!$F$16,0)+IF(N$4=Assumptions!$G$17,Assumptions!$C$17*Assumptions!$F$17,0) -> 0
B9: Gross asset cash flow | D9: =SUM(D6:D8) -> 0 | E9: =SUM(E6:E8) -> -42000000 | F9: =SUM(F6:F8) -> -35690000 | G9: =SUM(G6:G8) -> -46980000 | H9: =SUM(H6:H8) -> 6570000 | I9: =SUM(I6:I8) -> 6570000 | J9: =SUM(J6:J8) -> 71670000 | K9: =SUM(K6:K8) -> 4260000 | ... N9: =SUM(N6:N8) -> 0
B11: Management fee | D11: =0 -> 0 | E11: =-IF(E$4<=Assumptions!$C$8,Assumptions!$C$4*Assumptions!$C$6,(IF(AND(E$4>=Assumptions!$D$15,E$4<Assumptions!$G$15),Assumptions!$C$15,0)+IF(AND(E$4>=Assumptions!$D$16,E$4<Assumptions!$G$16),Assumptions!$C$16,0)+IF(AND(E$4>=Assumptions!$D$17,E$4<Assumptions!$G$17),Assumptions!$C$17,0))*Assumptions!$C$7) -> -2250000 | F11: =-IF(F$4<=Assumptions!$C$8,Assumptions!$C$4*Assumptions!$C$6,(IF(AND(F$4>=Assumptions!$D$15,F$4<Assumptions!$G$15),Assumptions!$C$15,0)+IF(AND(F$4>=Assumptions!$D$16,F$4<Assumptions!$G$16),Assumptions!$C$16,0)+IF(AND(F$4>=Assumptions!$D$17,F$4<Assumptions!$G$17),Assumptions!$C$17,0))*Assumptions!$C$7) -> -2250000 | G11: =-IF(G$4<=Assumptions!$C$8,Assumptions!$C$4*Assumptions!$C$6,(IF(AND(G$4>=Assumptions!$D$15,G$4<Assumptions!$G$15),Assumptions!$C$15,0)+IF(AND(G$4>=Assumptions!$D$16,G$4<Assumptions!$G$16),Assumptions!$C$16,0)+IF(AND(G$4>=Assumptions!$D$17,G$4<Assumptions!$G$17),Assumptions!$C$17,0))*Assumptions!$C$7) -> -2250000 | H11: =-IF(H$4<=Assumptions!$C$8,Assumptions!$C$4*Assumptions!$C$6,(IF(AND(H$4>=Assumptions!$D$15,H$4<Assumptions!$G$15),Assumptions!$C$15,0)+IF(AND(H$4>=Assumptions!$D$16,H$4<Assumptions!$G$16),Assumptions!$C$16,0)+IF(AND(H$4>=Assumptions!$D$17,H$4<Assumptions!$G$17),Assumptions!$C$17,0))*Assumptions!$C$7) -> -2250000 | I11: =-IF(I$4<=Assumptions!$C$8,Assumptions!$C$4*Assumptions!$C$6,(IF(AND(I$4>=Assumptions!$D$15,I$4<Assumptions!$G$15),Assumptions!$C$15,0)+IF(AND(I$4>=Assumptions!$D$16,I$4<Assumptions!$G$16),Assumptions!$C$16,0)+IF(AND(I$4>=Assumptions!$D$17,I$4<Assumptions!$G$17),Assumptions!$C$17,0))*Assumptions!$C$7) -> -1637500 | J11: =-IF(J$4<=Assumptions!$C$8,Assumptions!$C$4*Assumptions!$C$6,(IF(AND(J$4>=Assumptions!$D$15,J$4<Assumptions!$G$15),Assumptions!$C$15,0)+IF(AND(J$4>=Assumptions!$D$16,J$4<Assumptions!$G$16),Assumptions!$C$16,0)+IF(AND(J$4>=Assumptions!$D$17,J$4<Assumptions!$G$17),Assumptions!$C$17,0))*Assumptions!$C$7) -> -1112500 | K11: =-IF(K$4<=Assumptions!$C$8,Assumptions!$C$4*Assumptions!$C$6,(IF(AND(K$4>=Assumptions!$D$15,K$4<Assumptions!$G$15),Assumptions!$C$15,0)+IF(AND(K$4>=Assumptions!$D$16,K$4<Assumptions!$G$16),Assumptions!$C$16,0)+IF(AND(K$4>=Assumptions!$D$17,K$4<Assumptions!$G$17),Assumptions!$C$17,0))*Assumptions!$C$7) -> -1112500 | L11: =-IF(L$4<=Assumptions!$C$8,Assumptions!$C$4*Assumptions!$C$6,(IF(AND(L$4>=Assumptions!$D$15,L$4<Assumptions!$G$15),Assumptions!$C$15,0)+IF(AND(L$4>=Assumptions!$D$16,L$4<Assumptions!$G$16),Assumptions!$C$16,0)+IF(AND(L$4>=Assumptions!$D$17,L$4<Assumptions!$G$17),Assumptions!$C$17,0))*Assumptions!$C$7) -> -637500 | ... N11: =-IF(N$4<=Assumptions!$C$8,Assumptions!$C$4*Assumptions!$C$6,(IF(AND(N$4>=Assumptions!$D$15,N$4<Assumptions!$G$15),Assumptions!$C$15,0)+IF(AND(N$4>=Assumptions!$D$16,N$4<Assumptions!$G$16),Assumptions!$C$16,0)+IF(AND(N$4>=Assumptions!$D$17,N$4<Assumptions!$G$17),Assumptions!$C$17,0))*Assumptions!$C$7) -> 0
B12: Fund expenses | D12: =0 -> 0 | E12: =-Assumptions!$C$9 -> -350000 | F12: =-Assumptions!$C$9 -> -350000 | G12: =-Assumptions!$C$9 -> -350000 | H12: =-Assumptions!$C$9 -> -350000 | I12: =-Assumptions!$C$9 -> -350000 | J12: =-Assumptions!$C$9 -> -350000 | K12: =-Assumptions!$C$9 -> -350000 | L12: =-Assumptions!$C$9 -> -350000 | ... N12: =-Assumptions!$C$9 -> -350000
B13: Fund cash flow before carry | D13: =D9+D11+D12 -> 0 | E13: =E9+E11+E12 -> -44600000 | F13: =F9+F11+F12 -> -38290000 | G13: =G9+G11+G12 -> -49580000 | H13: =H9+H11+H12 -> 3970000 | I13: =I9+I11+I12 -> 4582500 | J13: =J9+J11+J12 -> 70207500 | K13: =K9+K11+K12 -> 2797500 | ... N13: =N9+N11+N12 -> -350000
B15: Capital called | D15: =-MIN(0,D13) -> 0 | E15: =-MIN(0,E13) -> 44600000 | F15: =-MIN(0,F13) -> 38290000 | G15: =-MIN(0,G13) -> 49580000 | H15: =-MIN(0,H13) -> 0 | I15: =-MIN(0,I13) -> 0 | J15: =-MIN(0,J13) -> 0 | K15: =-MIN(0,K13) -> 0 | ... N15: =-MIN(0,N13) -> 350000
B16: Distributable cash | D16: =MAX(0,D13) -> 0 | E16: =MAX(0,E13) -> 0 | F16: =MAX(0,F13) -> 0 | G16: =MAX(0,G13) -> 0 | H16: =MAX(0,H13) -> 3970000 | I16: =MAX(0,I13) -> 4582500 | J16: =MAX(0,J13) -> 70207500 | K16: =MAX(0,K13) -> 2797500 | ... N16: =MAX(0,N13) -> 0

Sheet Waterfall
B2: DISTRIBUTION WATERFALL (EUR)
B4: Year | D4: 0 | E4: 1 | F4: 2 | G4: 3 | H4: 4 | I4: 5 | J4: 6 | K4: 7 | L4: 8 | M4: 9 | N4: 10
B6: Contributions (all partners) | D6: ='Fund Cash Flow'!D15 -> 0 | E6: ='Fund Cash Flow'!E15 -> 44600000 | F6: ='Fund Cash Flow'!F15 -> 38290000 | G6: ='Fund Cash Flow'!G15 -> 49580000 | H6: ='Fund Cash Flow'!H15 -> 0 | I6: ='Fund Cash Flow'!I15 -> 0 | J6: ='Fund Cash Flow'!J15 -> 0 | K6: ='Fund Cash Flow'!K15 -> 0 | ... N6: ='Fund Cash Flow'!N15 -> 350000
B7: Distributable cash | D7: ='Fund Cash Flow'!D16 -> 0 | E7: ='Fund Cash Flow'!E16 -> 0 | F7: ='Fund Cash Flow'!F16 -> 0 | G7: ='Fund Cash Flow'!G16 -> 0 | H7: ='Fund Cash Flow'!H16 -> 3970000 | I7: ='Fund Cash Flow'!I16 -> 4582500 | J7: ='Fund Cash Flow'!J16 -> 70207500 | K7: ='Fund Cash Flow'!K16 -> 2797500 | ... N7: ='Fund Cash Flow'!N16 -> 0
B9: Unreturned capital, opening | D9: =0 -> 0 | E9: =D11 -> 0 | F9: =E11 -> 44600000 | G9: =F11 -> 82890000 | H9: =G11 -> 132470000 | I9: =H11 -> 128500000 | J9: =I11 -> 123917500 | K9: =J11 -> 53710000 | L9: =K11 -> 50912500 | ... N9: =M11 -> 0
B10: 1. Return of capital | D10: =MIN(D7,D9+D6) -> 0 | E10: =MIN(E7,E9+E6) -> 0 | F10: =MIN(F7,F9+F6) -> 0 | G10: =MIN(G7,G9+G6) -> 0 | H10: =MIN(H7,H9+H6) -> 3970000 | I10: =MIN(I7,I9+I6) -> 4582500 | J10: =MIN(J7,J9+J6) -> 70207500 | K10: =MIN(K7,K9+K6) -> 2797500 | ... N10: =MIN(N7,N9+N6) -> 0
B11: Unreturned capital, closing | D11: =D9+D6-D10 -> 0 | E11: =E9+E6-E10 -> 44600000 | F11: =F9+F6-F10 -> 82890000 | G11: =G9+G6-G10 -> 132470000 | H11: =H9+H6-H10 -> 128500000 | I11: =I9+I6-I10 -> 123917500 | J11: =J9+J6-J10 -> 53710000 | K11: =K9+K6-K10 -> 50912500 | ... N11: =N9+N6-N10 -> 350000
B13: Preferred return accrued, opening | D13: =0 -> 0 | E13: =D16 -> 0 | F13: =E16 -> 0 | G13: =F16 -> 3568000 | H13: =G16 -> 10484640 | I13: =H16 -> 21921011 | J13: =I16 -> 33954692 | K13: =J16 -> 46584467 | L13: =K16 -> 54608025 | ... N13: =M16 -> 0
B14: Preferred return for the year | D14: =(D9+D13)*Assumptions!$C$10 -> 0 | E14: =(E9+E13)*Assumptions!$C$10 -> 0 | F14: =(F9+F13)*Assumptions!$C$10 -> 3568000 | G14: =(G9+G13)*Assumptions!$C$10 -> 6916640 | H14: =(H9+H13)*Assumptions!$C$10 -> 11436371 | I14: =(I9+I13)*Assumptions!$C$10 -> 12033681 | J14: =(J9+J13)*Assumptions!$C$10 -> 12629775 | K14: =(K9+K13)*Assumptions!$C$10 -> 8023557.4 | ... N14: =(N9+N13)*Assumptions!$C$10 -> 0
B15: 2. Preferred return paid | D15: =MIN(D7-D10,D13+D14) -> 0 | E15: =MIN(E7-E10,E13+E14) -> 0 | F15: =MIN(F7-F10,F13+F14) -> 0 | G15: =MIN(G7-G10,G13+G14) -> 0 | H15: =MIN(H7-H10,H13+H14) -> 0 | I15: =MIN(I7-I10,I13+I14) -> 0 | J15: =MIN(J7-J10,J13+J14) -> 0 | K15: =MIN(K7-K10,K13+K14) -> 0 | ... N15: =MIN(N7-N10,N13+N14) -> 0
B16: Preferred return accrued, closing | D16: =D13+D14-D15 -> 0 | E16: =E13+E14-E15 -> 0 | F16: =F13+F14-F15 -> 3568000 | G16: =G13+G14-G15 -> 10484640 | H16: =H13+H14-H15 -> 21921011 | I16: =I13+I14-I15 -> 33954692 | J16: =J13+J14-J15 -> 46584467 | K16: =K13+K14-K15 -> 54608025 | ... N16: =N13+N14-N15 -> 0
B18: 3. GP catch-up | D18: =MIN(D7-D10-D15,MAX(0,Assumptions!$C$12/(1-Assumptions!$C$12)*SUM($D$15:D15)-0)*Assumptions!$C$11) -> 0 | E18: =MIN(E7-E10-E15,MAX(0,Assumptions!$C$12/(1-Assumptions!$C$12)*SUM($D$15:E15)-SUM($D$18:D18))*Assumptions!$C$11) -> 0 | F18: =MIN(F7-F10-F15,MAX(0,Assumptions!$C$12/(1-Assumptions!$C$12)*SUM($D$15:F15)-SUM($D$18:E18))*Assumptions!$C$11) -> 0 | G18: =MIN(G7-G10-G15,MAX(0,Assumptions!$C$12/(1-Assumptions!$C$12)*SUM($D$15:G15)-SUM($D$18:F18))*Assumptions!$C$11) -> 0 | H18: =MIN(H7-H10-H15,MAX(0,Assumptions!$C$12/(1-Assumptions!$C$12)*SUM($D$15:H15)-SUM($D$18:G18))*Assumptions!$C$11) -> 0 | I18: =MIN(I7-I10-I15,MAX(0,Assumptions!$C$12/(1-Assumptions!$C$12)*SUM($D$15:I15)-SUM($D$18:H18))*Assumptions!$C$11) -> 0 | J18: =MIN(J7-J10-J15,MAX(0,Assumptions!$C$12/(1-Assumptions!$C$12)*SUM($D$15:J15)-SUM($D$18:I18))*Assumptions!$C$11) -> 0 | K18: =MIN(K7-K10-K15,MAX(0,Assumptions!$C$12/(1-Assumptions!$C$12)*SUM($D$15:K15)-SUM($D$18:J18))*Assumptions!$C$11) -> 0 | L18: =MIN(L7-L10-L15,MAX(0,Assumptions!$C$12/(1-Assumptions!$C$12)*SUM($D$15:L15)-SUM($D$18:K18))*Assumptions!$C$11) -> 0 | ... N18: =MIN(N7-N10-N15,MAX(0,Assumptions!$C$12/(1-Assumptions!$C$12)*SUM($D$15:N15)-SUM($D$18:M18))*Assumptions!$C$11) -> 0
B19: Cumulative LP profit distributed | D19: =SUM($D$15:D15)+SUM($D$21:D21) -> 0 | E19: =SUM($D$15:E15)+SUM($D$21:E21) -> 0 | F19: =SUM($D$15:F15)+SUM($D$21:F21) -> 0 | G19: =SUM($D$15:G15)+SUM($D$21:G21) -> 0 | H19: =SUM($D$15:H15)+SUM($D$21:H21) -> 0 | I19: =SUM($D$15:I15)+SUM($D$21:I21) -> 0 | J19: =SUM($D$15:J15)+SUM($D$21:J21) -> 0 | K19: =SUM($D$15:K15)+SUM($D$21:K21) -> 0 | ... N19: =SUM($D$15:N15)+SUM($D$21:N21) -> 70408000
B20: Cumulative GP catch-up | D20: =SUM($D$18:D18) -> 0 | E20: =SUM($D$18:E18) -> 0 | F20: =SUM($D$18:F18) -> 0 | G20: =SUM($D$18:G18) -> 0 | H20: =SUM($D$18:H18) -> 0 | I20: =SUM($D$18:I18) -> 0 | J20: =SUM($D$18:J18) -> 0 | K20: =SUM($D$18:K18) -> 0 | ... N20: =SUM($D$18:N18) -> 16684210
B21: 4. Split: to LPs | D21: =(D7-D10-D15-D18)*(1-Assumptions!$C$12) -> 0 | E21: =(E7-E10-E15-E18)*(1-Assumptions!$C$12) -> 0 | F21: =(F7-F10-F15-F18)*(1-Assumptions!$C$12) -> 0 | G21: =(G7-G10-G15-G18)*(1-Assumptions!$C$12) -> 0 | H21: =(H7-H10-H15-H18)*(1-Assumptions!$C$12) -> 0 | I21: =(I7-I10-I15-I18)*(1-Assumptions!$C$12) -> 0 | J21: =(J7-J10-J15-J18)*(1-Assumptions!$C$12) -> 0 | K21: =(K7-K10-K15-K18)*(1-Assumptions!$C$12) -> 0 | ... N21: =(N7-N10-N15-N18)*(1-Assumptions!$C$12) -> 0
B22: 4. Split: to GP | D22: =(D7-D10-D15-D18)*Assumptions!$C$12 -> 0 | E22: =(E7-E10-E15-E18)*Assumptions!$C$12 -> 0 | F22: =(F7-F10-F15-F18)*Assumptions!$C$12 -> 0 | G22: =(G7-G10-G15-G18)*Assumptions!$C$12 -> 0 | H22: =(H7-H10-H15-H18)*Assumptions!$C$12 -> 0 | I22: =(I7-I10-I15-I18)*Assumptions!$C$12 -> 0 | J22: =(J7-J10-J15-J18)*Assumptions!$C$12 -> 0 | K22: =(K7-K10-K15-K18)*Assumptions!$C$12 -> 0 | ... N22: =(N7-N10-N15-N18)*Assumptions!$C$12 -> 0
B24: Total to all partners (pro rata to commitments) | D24: =D10+D15+D21 -> 0 | E24: =E10+E15+E21 -> 0 | F24: =F10+F15+F21 -> 0 | G24: =G10+G15+G21 -> 0 | H24: =H10+H15+H21 -> 3970000 | I24: =I10+I15+I21 -> 4582500 | J24: =J10+J15+J21 -> 70207500 | K24: =K10+K15+K21 -> 2797500 | ... N24: =N10+N15+N21 -> 0
B25: Carried interest to GP | D25: =D18+D22 -> 0 | E25: =E18+E22 -> 0 | F25: =F18+F22 -> 0 | G25: =G18+G22 -> 0 | H25: =H18+H22 -> 0 | I25: =I18+I22 -> 0 | J25: =J18+J22 -> 0 | K25: =K18+K22 -> 0 | ... N25: =N18+N22 -> 0
B27: LP net cash flow | D27: =(-D6+D24)*(1-Assumptions!$C$5) -> 0 | E27: =(-E6+E24)*(1-Assumptions!$C$5) -> -43708000 | F27: =(-F6+F24)*(1-Assumptions!$C$5) -> -37524200 | G27: =(-G6+G24)*(1-Assumptions!$C$5) -> -48588400 | H27: =(-H6+H24)*(1-Assumptions!$C$5) -> 3890600 | I27: =(-I6+I24)*(1-Assumptions!$C$5) -> 4490850 | J27: =(-J6+J24)*(1-Assumptions!$C$5) -> 68803350 | K27: =(-K6+K24)*(1-Assumptions!$C$5) -> 2741550 | ... N27: =(-N6+N24)*(1-Assumptions!$C$5) -> -343000
B28: GP carry cash flow | D28: =D25 -> 0 | E28: =E25 -> 0 | F28: =F25 -> 0 | G28: =G25 -> 0 | H28: =H25 -> 0 | I28: =I25 -> 0 | J28: =J25 -> 0 | K28: =K25 -> 0 | ... N28: =N25 -> 0
