Workbook

Sheet Results
B2: NAKHEEL GARDENS · RESULTS (SAR '000)
B5: Gross development value | C5: =SUM('Quarterly CF'!C7:S7) -> 348000
B6: Total development cost | C6: =-SUM('Quarterly CF'!C19:S19) -> 260600
B7: Developer profit | C7: =C5-C6+SUM('Quarterly CF'!C26:S27) -> 79464.767
B8: Profit on cost | C8: =C7/C6 -> 0.30493003
B10: Project IRR (unlevered) | C10: =(1+IRR('Quarterly CF'!C21:S21))^4-1 -> 0.35654275
B11: Equity IRR | C11: =(1+IRR('Quarterly CF'!C31:S31))^4-1 -> 0.35962871
B12: Peak Murabaha balance | C12: =MAX('Quarterly CF'!C29:S29) -> 60680.472
B13: Equity multiple | C13: =SUMIF('Quarterly CF'!C31:S31,">0")/-SUMIF('Quarterly CF'!C31:S31,"<0") -> 2.2723503

Sheet Inputs
B2: NAKHEEL GARDENS · INPUTS (SAR '000)
B4: Units | C4: 240
B5: Average unit price | C5: 1450
B6: Land cost | C6: 62000
B7: Construction cost | C7: 168000
B8: Construction start (quarter) | C8: 1
B9: Construction length (quarters) | C9: 10
B10: Soft costs (% of construction) | C10: 0.12
B11: Sales and marketing (% of sales) | C11: 0.03
B12: Deposit at sale | C12: 0.1
B13: Paid at handover | C13: 0.3
B14: Escrow release lag (quarters) | C14: 1
B15: SAIBOR | C15: 0.055
... B18: Equity (share of land and first costs) | C18: 1
B20: Sales curve (share of units sold, by quarter from launch)
B21: Quarter | C21: 0 | D21: 1 | E21: 2 | F21: 3 | G21: 4 | H21: 5 | I21: 6 | J21: 7 | K21: 8 | L21: 9 | M21: 10 | N21: 11 | O21: 12 | P21: 13 | Q21: 14 | R21: 15 | S21: 16
B22: Share sold | C22: 0 | D22: 0.15 | E22: 0.15 | F22: 0.12 | G22: 0.1 | H22: 0.1 | I22: 0.08 | J22: 0.08 | K22: 0.07 | L22: 0.06 | M22: 0.05 | N22: 0.04 | O22: 0 | P22: 0 | Q22: 0 | R22: 0 | S22: 0

Sheet Quarterly CF
B2: QUARTERLY CASH FLOW (SAR '000)
B3: Quarter ending | C3: 46112 | D3: 46203 | E3: 46295 | F3: 46387 | G3: 46477 | H3: 46568 | I3: 46660 | J3: 46752 | K3: 46843 | L3: 46934 | M3: 47026 | N3: 47118 | O3: 47208 | P3: 47299 | Q3: 47391 | R3: 47483 | S3: 47573
B4: Quarter | C4: 0 | D4: 1 | E4: 2 | F4: 3 | G4: 4 | H4: 5 | I4: 6 | J4: 7 | K4: 8 | L4: 9 | M4: 10 | N4: 11 | O4: 12 | P4: 13 | Q4: 14 | R4: 15 | S4: 16
B6: Units sold | C6: =Inputs!$C$4*Inputs!C22 -> 0 | D6: =Inputs!$C$4*Inputs!D22 -> 36 | E6: =Inputs!$C$4*Inputs!E22 -> 36 | F6: =Inputs!$C$4*Inputs!F22 -> 28.8 | G6: =Inputs!$C$4*Inputs!G22 -> 24 | H6: =Inputs!$C$4*Inputs!H22 -> 24 | I6: =Inputs!$C$4*Inputs!I22 -> 19.2 | J6: =Inputs!$C$4*Inputs!J22 -> 19.2 | ... S6: =Inputs!$C$4*Inputs!S22 -> 0
B7: Sales contracted | C7: =C6*Inputs!$C$5 -> 0 | D7: =D6*Inputs!$C$5 -> 52200 | E7: =E6*Inputs!$C$5 -> 52200 | F7: =F6*Inputs!$C$5 -> 41760 | G7: =G6*Inputs!$C$5 -> 34800 | H7: =H6*Inputs!$C$5 -> 34800 | I7: =I6*Inputs!$C$5 -> 27840 | J7: =J6*Inputs!$C$5 -> 27840 | ... S7: =S6*Inputs!$C$5 -> 0
B8: Construction progress | C8: =IF(AND(C$4>=Inputs!$C$8,C$4<Inputs!$C$8+ROUND(Inputs!$C$9,0)),1/ROUND(Inputs!$C$9,0),0) -> 0 | D8: =IF(AND(D$4>=Inputs!$C$8,D$4<Inputs!$C$8+ROUND(Inputs!$C$9,0)),1/ROUND(Inputs!$C$9,0),0) -> 0.1 | E8: =IF(AND(E$4>=Inputs!$C$8,E$4<Inputs!$C$8+ROUND(Inputs!$C$9,0)),1/ROUND(Inputs!$C$9,0),0) -> 0.1 | F8: =IF(AND(F$4>=Inputs!$C$8,F$4<Inputs!$C$8+ROUND(Inputs!$C$9,0)),1/ROUND(Inputs!$C$9,0),0) -> 0.1 | G8: =IF(AND(G$4>=Inputs!$C$8,G$4<Inputs!$C$8+ROUND(Inputs!$C$9,0)),1/ROUND(Inputs!$C$9,0),0) -> 0.1 | H8: =IF(AND(H$4>=Inputs!$C$8,H$4<Inputs!$C$8+ROUND(Inputs!$C$9,0)),1/ROUND(Inputs!$C$9,0),0) -> 0.1 | I8: =IF(AND(I$4>=Inputs!$C$8,I$4<Inputs!$C$8+ROUND(Inputs!$C$9,0)),1/ROUND(Inputs!$C$9,0),0) -> 0.1 | J8: =IF(AND(J$4>=Inputs!$C$8,J$4<Inputs!$C$8+ROUND(Inputs!$C$9,0)),1/ROUND(Inputs!$C$9,0),0) -> 0.1 | ... S8: =IF(AND(S$4>=Inputs!$C$8,S$4<Inputs!$C$8+ROUND(Inputs!$C$9,0)),1/ROUND(Inputs!$C$9,0),0) -> 0
B9: Cumulative progress | C9: =SUM($C$8:C8) -> 0 | D9: =SUM($C$8:D8) -> 0.1 | E9: =SUM($C$8:E8) -> 0.2 | F9: =SUM($C$8:F8) -> 0.3 | G9: =SUM($C$8:G8) -> 0.4 | H9: =SUM($C$8:H8) -> 0.5 | I9: =SUM($C$8:I8) -> 0.6 | J9: =SUM($C$8:J8) -> 0.7 | ... S9: =SUM($C$8:S8) -> 1
B11: Buyer payments into escrow | C11: =IF(C$4<Inputs!$C$8+ROUND(Inputs!$C$9,0),C7*(Inputs!$C$12+(1-Inputs!$C$12-Inputs!$C$13)*C9)+0*(1-Inputs!$C$12-Inputs!$C$13)*C8,0)+IF(C$4=Inputs!$C$8+ROUND(Inputs!$C$9,0),0*Inputs!$C$13+C7,0)+IF(C$4>Inputs!$C$8+ROUND(Inputs!$C$9,0),C7,0) -> 0 | D11: =IF(D$4<Inputs!$C$8+ROUND(Inputs!$C$9,0),D7*(Inputs!$C$12+(1-Inputs!$C$12-Inputs!$C$13)*D9)+SUM($C$7:C7)*(1-Inputs!$C$12-Inputs!$C$13)*D8,0)+IF(D$4=Inputs!$C$8+ROUND(Inputs!$C$9,0),SUM($C$7:C7)*Inputs!$C$13+D7,0)+IF(D$4>Inputs!$C$8+ROUND(Inputs!$C$9,0),D7,0) -> 8352 | E11: =IF(E$4<Inputs!$C$8+ROUND(Inputs!$C$9,0),E7*(Inputs!$C$12+(1-Inputs!$C$12-Inputs!$C$13)*E9)+SUM($C$7:D7)*(1-Inputs!$C$12-Inputs!$C$13)*E8,0)+IF(E$4=Inputs!$C$8+ROUND(Inputs!$C$9,0),SUM($C$7:D7)*Inputs!$C$13+E7,0)+IF(E$4>Inputs!$C$8+ROUND(Inputs!$C$9,0),E7,0) -> 14616 | F11: =IF(F$4<Inputs!$C$8+ROUND(Inputs!$C$9,0),F7*(Inputs!$C$12+(1-Inputs!$C$12-Inputs!$C$13)*F9)+SUM($C$7:E7)*(1-Inputs!$C$12-Inputs!$C$13)*F8,0)+IF(F$4=Inputs!$C$8+ROUND(Inputs!$C$9,0),SUM($C$7:E7)*Inputs!$C$13+F7,0)+IF(F$4>Inputs!$C$8+ROUND(Inputs!$C$9,0),F7,0) -> 17956.8 | G11: =IF(G$4<Inputs!$C$8+ROUND(Inputs!$C$9,0),G7*(Inputs!$C$12+(1-Inputs!$C$12-Inputs!$C$13)*G9)+SUM($C$7:F7)*(1-Inputs!$C$12-Inputs!$C$13)*G8,0)+IF(G$4=Inputs!$C$8+ROUND(Inputs!$C$9,0),SUM($C$7:F7)*Inputs!$C$13+G7,0)+IF(G$4>Inputs!$C$8+ROUND(Inputs!$C$9,0),G7,0) -> 20601.6 | H11: =IF(H$4<Inputs!$C$8+ROUND(Inputs!$C$9,0),H7*(Inputs!$C$12+(1-Inputs!$C$12-Inputs!$C$13)*H9)+SUM($C$7:G7)*(1-Inputs!$C$12-Inputs!$C$13)*H8,0)+IF(H$4=Inputs!$C$8+ROUND(Inputs!$C$9,0),SUM($C$7:G7)*Inputs!$C$13+H7,0)+IF(H$4>Inputs!$C$8+ROUND(Inputs!$C$9,0),H7,0) -> 24777.6 | I11: =IF(I$4<Inputs!$C$8+ROUND(Inputs!$C$9,0),I7*(Inputs!$C$12+(1-Inputs!$C$12-Inputs!$C$13)*I9)+SUM($C$7:H7)*(1-Inputs!$C$12-Inputs!$C$13)*I8,0)+IF(I$4=Inputs!$C$8+ROUND(Inputs!$C$9,0),SUM($C$7:H7)*Inputs!$C$13+I7,0)+IF(I$4>Inputs!$C$8+ROUND(Inputs!$C$9,0),I7,0) -> 25752 | J11: =IF(J$4<Inputs!$C$8+ROUND(Inputs!$C$9,0),J7*(Inputs!$C$12+(1-Inputs!$C$12-Inputs!$C$13)*J9)+SUM($C$7:I7)*(1-Inputs!$C$12-Inputs!$C$13)*J8,0)+IF(J$4=Inputs!$C$8+ROUND(Inputs!$C$9,0),SUM($C$7:I7)*Inputs!$C$13+J7,0)+IF(J$4>Inputs!$C$8+ROUND(Inputs!$C$9,0),J7,0) -> 29092.8 | K11: =IF(K$4<Inputs!$C$8+ROUND(Inputs!$C$9,0),K7*(Inputs!$C$12+(1-Inputs!$C$12-Inputs!$C$13)*K9)+SUM($C$7:J7)*(1-Inputs!$C$12-Inputs!$C$13)*K8,0)+IF(K$4=Inputs!$C$8+ROUND(Inputs!$C$9,0),SUM($C$7:J7)*Inputs!$C$13+K7,0)+IF(K$4>Inputs!$C$8+ROUND(Inputs!$C$9,0),K7,0) -> 30415.2 | ... S11: =IF(S$4<Inputs!$C$8+ROUND(Inputs!$C$9,0),S7*(Inputs!$C$12+(1-Inputs!$C$12-Inputs!$C$13)*S9)+SUM($C$7:R7)*(1-Inputs!$C$12-Inputs!$C$13)*S8,0)+IF(S$4=Inputs!$C$8+ROUND(Inputs!$C$9,0),SUM($C$7:R7)*Inputs!$C$13+S7,0)+IF(S$4>Inputs!$C$8+ROUND(Inputs!$C$9,0),S7,0) -> 0
B12: Escrow balance | C12: =0+C11-C13 -> 0 | D12: =C12+D11-D13 -> 7516.8 | E12: =D12+E11-E13 -> 18374.4 | F12: =E12+F11-F13 -> 28647.36 | G12: =F12+G11-G13 -> 36915.84 | H12: =G12+H11-H13 -> 43152 | I12: =H12+I11-I13 -> 44822.4 | J12: =I12+J11-J13 -> 42344.64 | K12: =J12+K11-K13 -> 34312.8 | ... S12: =R12+S11-S13 -> 0
B13: Escrow release | C13: =0 -> 0 | D13: =IF(D$4>=Inputs!$C$8+ROUND(Inputs!$C$9,0),C12+D11,MIN(C12+D11,MAX(0,D9*SUM($C$11:D11)-SUM($C$13:C13)))) -> 835.2 | E13: =IF(E$4>=Inputs!$C$8+ROUND(Inputs!$C$9,0),D12+E11,MIN(D12+E11,MAX(0,E9*SUM($C$11:E11)-SUM($C$13:D13)))) -> 3758.4 | F13: =IF(F$4>=Inputs!$C$8+ROUND(Inputs!$C$9,0),E12+F11,MIN(E12+F11,MAX(0,F9*SUM($C$11:F11)-SUM($C$13:E13)))) -> 7683.84 | G13: =IF(G$4>=Inputs!$C$8+ROUND(Inputs!$C$9,0),F12+G11,MIN(F12+G11,MAX(0,G9*SUM($C$11:G11)-SUM($C$13:F13)))) -> 12333.12 | H13: =IF(H$4>=Inputs!$C$8+ROUND(Inputs!$C$9,0),G12+H11,MIN(G12+H11,MAX(0,H9*SUM($C$11:H11)-SUM($C$13:G13)))) -> 18541.44 | I13: =IF(I$4>=Inputs!$C$8+ROUND(Inputs!$C$9,0),H12+I11,MIN(H12+I11,MAX(0,I9*SUM($C$11:I11)-SUM($C$13:H13)))) -> 24081.6 | J13: =IF(J$4>=Inputs!$C$8+ROUND(Inputs!$C$9,0),I12+J11,MIN(I12+J11,MAX(0,J9*SUM($C$11:J11)-SUM($C$13:I13)))) -> 31570.56 | K13: =IF(K$4>=Inputs!$C$8+ROUND(Inputs!$C$9,0),J12+K11,MIN(J12+K11,MAX(0,K9*SUM($C$11:K11)-SUM($C$13:J13)))) -> 38447.04 | ... S13: =IF(S$4>=Inputs!$C$8+ROUND(Inputs!$C$9,0),R12+S11,MIN(R12+S11,MAX(0,S9*SUM($C$11:S11)-SUM($C$13:R13)))) -> 0
B15: Land | C15: =IF(C$4=0,-Inputs!$C$6,0) -> -62000 | D15: =IF(D$4=0,-Inputs!$C$6,0) -> 0 | E15: =IF(E$4=0,-Inputs!$C$6,0) -> 0 | F15: =IF(F$4=0,-Inputs!$C$6,0) -> 0 | G15: =IF(G$4=0,-Inputs!$C$6,0) -> 0 | H15: =IF(H$4=0,-Inputs!$C$6,0) -> 0 | I15: =IF(I$4=0,-Inputs!$C$6,0) -> 0 | J15: =IF(J$4=0,-Inputs!$C$6,0) -> 0 | ... S15: =IF(S$4=0,-Inputs!$C$6,0) -> 0
B16: Construction | C16: =-Inputs!$C$7*C8 -> 0 | D16: =-Inputs!$C$7*D8 -> -16800 | E16: =-Inputs!$C$7*E8 -> -16800 | F16: =-Inputs!$C$7*F8 -> -16800 | G16: =-Inputs!$C$7*G8 -> -16800 | H16: =-Inputs!$C$7*H8 -> -16800 | I16: =-Inputs!$C$7*I8 -> -16800 | J16: =-Inputs!$C$7*J8 -> -16800 | ... S16: =-Inputs!$C$7*S8 -> 0
B17: Soft costs | C17: =C16*Inputs!$C$10 -> 0 | D17: =D16*Inputs!$C$10 -> -2016 | E17: =E16*Inputs!$C$10 -> -2016 | F17: =F16*Inputs!$C$10 -> -2016 | G17: =G16*Inputs!$C$10 -> -2016 | H17: =H16*Inputs!$C$10 -> -2016 | I17: =I16*Inputs!$C$10 -> -2016 | J17: =J16*Inputs!$C$10 -> -2016 | ... S17: =S16*Inputs!$C$10 -> 0
B18: Sales and marketing | C18: =-C7*Inputs!$C$11 -> 0 | D18: =-D7*Inputs!$C$11 -> -1566 | E18: =-E7*Inputs!$C$11 -> -1566 | F18: =-F7*Inputs!$C$11 -> -1252.8 | G18: =-G7*Inputs!$C$11 -> -1044 | H18: =-H7*Inputs!$C$11 -> -1044 | I18: =-I7*Inputs!$C$11 -> -835.2 | J18: =-J7*Inputs!$C$11 -> -835.2 | ... S18: =-S7*Inputs!$C$11 -> 0
B19: Total costs | C19: =SUM(C15:C18) -> -62000 | D19: =SUM(D15:D18) -> -20382 | E19: =SUM(E15:E18) -> -20382 | F19: =SUM(F15:F18) -> -20068.8 | G19: =SUM(G15:G18) -> -19860 | H19: =SUM(H15:H18) -> -19860 | I19: =SUM(I15:I18) -> -19651.2 | J19: =SUM(J15:J18) -> -19651.2 | ... S19: =SUM(S15:S18) -> 0
B21: Project cash flow (unlevered) | C21: =C11+C19 -> -62000 | D21: =D11+D19 -> -12030 | E21: =E11+E19 -> -5766 | F21: =F11+F19 -> -2112 | G21: =G11+G19 -> 741.6 | H21: =H11+H19 -> 4917.6 | I21: =I11+I19 -> 6100.8 | J21: =J11+J19 -> 9441.6 | ... S21: =S11+S19 -> 0
B23: Funding need after escrow | C23: =-MIN(0,C13+C19) -> 62000 | D23: =-MIN(0,D13+D19) -> 19546.8 | E23: =-MIN(0,E13+E19) -> 16623.6 | F23: =-MIN(0,F13+F19) -> 12384.96 | G23: =-MIN(0,G13+G19) -> 7526.88 | H23: =-MIN(0,H13+H19) -> 1318.56 | I23: =-MIN(0,I13+I19) -> 0 | J23: =-MIN(0,J13+J19) -> 0 | ... S23: =-MIN(0,S13+S19) -> 0
B24: Equity | C24: =IF(C$4=0,C23,0) -> 62000 | D24: =IF(D$4=0,D23,0) -> 0 | E24: =IF(E$4=0,E23,0) -> 0 | F24: =IF(F$4=0,F23,0) -> 0 | G24: =IF(G$4=0,G23,0) -> 0 | H24: =IF(H$4=0,H23,0) -> 0 | I24: =IF(I$4=0,I23,0) -> 0 | J24: =IF(J$4=0,J23,0) -> 0 | ... S24: =IF(S$4=0,S23,0) -> 0
B25: Murabaha draw | C25: =IF(C$4=0,0,C23-C26) -> 0 | D25: =IF(D$4=0,0,D23-D26) -> 19546.8 | E25: =IF(E$4=0,0,E23-E26) -> 17014.536 | F25: =IF(F$4=0,0,F23-F26) -> 13116.187 | G25: =IF(G$4=0,0,G23-G26) -> 8520.4305 | H25: =IF(H$4=0,0,H23-H26) -> 2482.5191 | I25: =IF(I$4=0,0,I23-I26) -> 1213.6094 | J25: =IF(J$4=0,0,J23-J26) -> 1173.7279 | ... S25: =IF(S$4=0,0,S23-S26) -> 0
B26: Murabaha profit | C26: =0 -> 0 | D26: =-C29*(Inputs!$C$15+Inputs!$C$16)/4 -> 0 | E26: =-D29*(Inputs!$C$15+Inputs!$C$16)/4 -> -390.936 | F26: =-E29*(Inputs!$C$15+Inputs!$C$16)/4 -> -731.22672 | G26: =-F29*(Inputs!$C$15+Inputs!$C$16)/4 -> -993.55045 | H26: =-G29*(Inputs!$C$15+Inputs!$C$16)/4 -> -1163.9591 | I26: =-H29*(Inputs!$C$15+Inputs!$C$16)/4 -> -1213.6094 | J26: =-I29*(Inputs!$C$15+Inputs!$C$16)/4 -> -1173.7279 | K26: =-J29*(Inputs!$C$15+Inputs!$C$16)/4 -> -982.46584 | ... S26: =-R29*(Inputs!$C$15+Inputs!$C$16)/4 -> 0
B27: Murabaha fee | C27: =-C25*Inputs!$C$17 -> 0 | D27: =-D25*Inputs!$C$17 -> -146.601 | E27: =-E25*Inputs!$C$17 -> -127.60902 | F27: =-F25*Inputs!$C$17 -> -98.3714 | G27: =-G25*Inputs!$C$17 -> -63.903228 | H27: =-H25*Inputs!$C$17 -> -18.618893 | I27: =-I25*Inputs!$C$17 -> -9.1020708 | J27: =-J25*Inputs!$C$17 -> -8.802959 | ... S27: =-S25*Inputs!$C$17 -> 0
B28: Murabaha repayment | C28: =MIN(0+C25,MAX(0,C13+C19+C26+C27)) -> 0 | D28: =MIN(C29+D25,MAX(0,D13+D19+D26+D27)) -> 0 | E28: =MIN(D29+E25,MAX(0,E13+E19+E26+E27)) -> 0 | F28: =MIN(E29+F25,MAX(0,F13+F19+F26+F27)) -> 0 | G28: =MIN(F29+G25,MAX(0,G13+G19+G26+G27)) -> 0 | H28: =MIN(G29+H25,MAX(0,H13+H19+H26+H27)) -> 0 | I28: =MIN(H29+I25,MAX(0,I13+I19+I26+I27)) -> 3207.6885 | J28: =MIN(I29+J25,MAX(0,J13+J19+J26+J27)) -> 10736.829 | K28: =MIN(J29+K25,MAX(0,K13+K19+K26+K27)) -> 17910.406 | ... S28: =MIN(R29+S25,MAX(0,S13+S19+S26+S27)) -> 0
B29: Murabaha balance | C29: =0+C25-C28 -> 0 | D29: =C29+D25-D28 -> 19546.8 | E29: =D29+E25-E28 -> 36561.336 | F29: =E29+F25-F28 -> 49677.523 | G29: =F29+G25-G28 -> 58197.953 | H29: =G29+H25-H28 -> 60680.472 | I29: =H29+I25-I28 -> 58686.393 | J29: =I29+J25-J28 -> 49123.292 | K29: =J29+K25-K28 -> 32195.352 | ... S29: =R29+S25-S28 -> 0
B31: Equity cash flow | C31: =C13+C19+C25+C26+C27-C28+IF(C$4=16,C12,0) -> -62000 | D31: =D13+D19+D25+D26+D27-D28+IF(D$4=16,D12,0) -> -146.601 | E31: =E13+E19+E25+E26+E27-E28+IF(E$4=16,E12,0) -> -127.60902 | F31: =F13+F19+F25+F26+F27-F28+IF(F$4=16,F12,0) -> -98.3714 | G31: =G13+G19+G25+G26+G27-G28+IF(G$4=16,G12,0) -> -63.903228 | H31: =H13+H19+H25+H26+H27-H28+IF(H$4=16,H12,0) -> -18.618893 | I31: =I13+I19+I25+I26+I27-I28+IF(I$4=16,I12,0) -> 1213.6094 | J31: =J13+J19+J25+J26+J27-J28+IF(J$4=16,J12,0) -> 1173.7279 | ... S31: =S13+S19+S25+S26+S27-S28+IF(S$4=16,S12,0) -> 0
