Workbook

Sheet Returns
B2: MARINA BAY HOTEL · RETURNS (AED)
C5: IRR | D5: MOIC | E5: Profit
B6: Unleveraged | C6: =IRR('Cash Flow'!C11:O11) -> 0.071229761 | D6: =SUMIF('Cash Flow'!C11:O11,">0")/-SUMIF('Cash Flow'!C11:O11,"<0") -> 1.684544 | E6: =SUM('Cash Flow'!C11:O11) -> 3.4980196e+08
B7: Leveraged | C7: =IRR('Cash Flow'!C18:O18) -> 0.075987598 | D7: =SUMIF('Cash Flow'!C18:O18,">0")/-SUMIF('Cash Flow'!C18:O18,"<0") -> 1.8398542 | E7: =SUM('Cash Flow'!C18:O18) -> 2.1586101e+08
B9: Stabilised RevPAR (year 5) | C9: =Operations!H9 -> 612.35148
B10: Yield on cost (year 5 EBITDA) | C10: =Operations!H20/-SUM('Cash Flow'!C6:O8) -> 0.071259517
B11: Total development cost | C11: =-SUM('Cash Flow'!C6:O8) -> 511000000

Sheet Assumptions
B2: MARINA BAY HOTEL · ASSUMPTIONS (AED)
B4: Keys | C4: 320
B5: Land | C5: 95000000
B6: Construction cost per key | C6: 1150000
B7: Pre-opening and FF&E (total) | C7: 48000000
B8: Opening year | C8: 3
B9: Stabilised ADR | C9: 780
B10: Stabilised occupancy | C10: 0.74
B11: ADR growth (a year) | C11: 0.03
B12: F&B revenue (% of rooms) | C12: 0.42
B13: Other revenue (% of rooms) | C13: 0.06
B14: Departmental costs (% of revenue) | C14: 0.38
B15: Undistributed costs (% of revenue) | C15: 0.17
... B24: Amortisation (years after opening) | C24: 20
B26: Ramp-up (share of stabilised occupancy and ADR, by operating year)
B27: Operating year | C27: 1 | D27: 2 | E27: 3
B28: Occupancy ramp | C28: 0.7 | D28: 0.86 | E28: 1
B29: ADR ramp | C29: 0.88 | D29: 0.95 | E29: 1

Sheet Operations
B2: OPERATIONS (AED)
B4: Year | C4: 0 | D4: 1 | E4: 2 | F4: 3 | G4: 4 | H4: 5 | I4: 6 | J4: 7 | K4: 8 | L4: 9 | M4: 10 | N4: 11 | O4: 12
B5: Operating year | C5: =MAX(0,C4-ROUND(Assumptions!$C$8,0)+1) -> 0 | D5: =MAX(0,D4-ROUND(Assumptions!$C$8,0)+1) -> 0 | E5: =MAX(0,E4-ROUND(Assumptions!$C$8,0)+1) -> 0 | F5: =MAX(0,F4-ROUND(Assumptions!$C$8,0)+1) -> 1 | G5: =MAX(0,G4-ROUND(Assumptions!$C$8,0)+1) -> 2 | H5: =MAX(0,H4-ROUND(Assumptions!$C$8,0)+1) -> 3 | I5: =MAX(0,I4-ROUND(Assumptions!$C$8,0)+1) -> 4 | J5: =MAX(0,J4-ROUND(Assumptions!$C$8,0)+1) -> 5 | ... O5: =MAX(0,O4-ROUND(Assumptions!$C$8,0)+1) -> 10
B7: Occupancy | C7: =Assumptions!$C$10*IF(C5=0,0,IF(C5>=3,1,INDEX(Assumptions!$C$28:$E$28,1,C5))) -> 0 | D7: =Assumptions!$C$10*IF(D5=0,0,IF(D5>=3,1,INDEX(Assumptions!$C$28:$E$28,1,D5))) -> 0 | E7: =Assumptions!$C$10*IF(E5=0,0,IF(E5>=3,1,INDEX(Assumptions!$C$28:$E$28,1,E5))) -> 0 | F7: =Assumptions!$C$10*IF(F5=0,0,IF(F5>=3,1,INDEX(Assumptions!$C$28:$E$28,1,F5))) -> 0.518 | G7: =Assumptions!$C$10*IF(G5=0,0,IF(G5>=3,1,INDEX(Assumptions!$C$28:$E$28,1,G5))) -> 0.6364 | H7: =Assumptions!$C$10*IF(H5=0,0,IF(H5>=3,1,INDEX(Assumptions!$C$28:$E$28,1,H5))) -> 0.74 | I7: =Assumptions!$C$10*IF(I5=0,0,IF(I5>=3,1,INDEX(Assumptions!$C$28:$E$28,1,I5))) -> 0.74 | J7: =Assumptions!$C$10*IF(J5=0,0,IF(J5>=3,1,INDEX(Assumptions!$C$28:$E$28,1,J5))) -> 0.74 | ... O7: =Assumptions!$C$10*IF(O5=0,0,IF(O5>=3,1,INDEX(Assumptions!$C$28:$E$28,1,O5))) -> 0.74
B8: ADR | C8: =IF(C5=0,0,Assumptions!$C$9*IF(C5=0,0,IF(C5>=3,1,INDEX(Assumptions!$C$29:$E$29,1,C5)))*(1+Assumptions!$C$11)^(C4-ROUND(Assumptions!$C$8,0))) -> 0 | D8: =IF(D5=0,0,Assumptions!$C$9*IF(D5=0,0,IF(D5>=3,1,INDEX(Assumptions!$C$29:$E$29,1,D5)))*(1+Assumptions!$C$11)^(D4-ROUND(Assumptions!$C$8,0))) -> 0 | E8: =IF(E5=0,0,Assumptions!$C$9*IF(E5=0,0,IF(E5>=3,1,INDEX(Assumptions!$C$29:$E$29,1,E5)))*(1+Assumptions!$C$11)^(E4-ROUND(Assumptions!$C$8,0))) -> 0 | F8: =IF(F5=0,0,Assumptions!$C$9*IF(F5=0,0,IF(F5>=3,1,INDEX(Assumptions!$C$29:$E$29,1,F5)))*(1+Assumptions!$C$11)^(F4-ROUND(Assumptions!$C$8,0))) -> 686.4 | G8: =IF(G5=0,0,Assumptions!$C$9*IF(G5=0,0,IF(G5>=3,1,INDEX(Assumptions!$C$29:$E$29,1,G5)))*(1+Assumptions!$C$11)^(G4-ROUND(Assumptions!$C$8,0))) -> 763.23 | H8: =IF(H5=0,0,Assumptions!$C$9*IF(H5=0,0,IF(H5>=3,1,INDEX(Assumptions!$C$29:$E$29,1,H5)))*(1+Assumptions!$C$11)^(H4-ROUND(Assumptions!$C$8,0))) -> 827.502 | I8: =IF(I5=0,0,Assumptions!$C$9*IF(I5=0,0,IF(I5>=3,1,INDEX(Assumptions!$C$29:$E$29,1,I5)))*(1+Assumptions!$C$11)^(I4-ROUND(Assumptions!$C$8,0))) -> 852.32706 | J8: =IF(J5=0,0,Assumptions!$C$9*IF(J5=0,0,IF(J5>=3,1,INDEX(Assumptions!$C$29:$E$29,1,J5)))*(1+Assumptions!$C$11)^(J4-ROUND(Assumptions!$C$8,0))) -> 877.89687 | ... O8: =IF(O5=0,0,Assumptions!$C$9*IF(O5=0,0,IF(O5>=3,1,INDEX(Assumptions!$C$29:$E$29,1,O5)))*(1+Assumptions!$C$11)^(O4-ROUND(Assumptions!$C$8,0))) -> 1017.7231
B9: RevPAR | C9: =C7*C8 -> 0 | D9: =D7*D8 -> 0 | E9: =E7*E8 -> 0 | F9: =F7*F8 -> 355.5552 | G9: =G7*G8 -> 485.71957 | H9: =H7*H8 -> 612.35148 | I9: =I7*I8 -> 630.72202 | J9: =J7*J8 -> 649.64369 | ... O9: =O7*O8 -> 753.11508
B10: Rooms revenue | C10: =C9*Assumptions!$C$4*365 -> 0 | D10: =D9*Assumptions!$C$4*365 -> 0 | E10: =E9*Assumptions!$C$4*365 -> 0 | F10: =F9*Assumptions!$C$4*365 -> 41528847 | G10: =G9*Assumptions!$C$4*365 -> 56732046 | H10: =H9*Assumptions!$C$4*365 -> 71522653 | I10: =I9*Assumptions!$C$4*365 -> 73668332 | J10: =J9*Assumptions!$C$4*365 -> 75878382 | ... O10: =O9*Assumptions!$C$4*365 -> 87963842
B11: F&B revenue | C11: =C10*Assumptions!$C$12 -> 0 | D11: =D10*Assumptions!$C$12 -> 0 | E11: =E10*Assumptions!$C$12 -> 0 | F11: =F10*Assumptions!$C$12 -> 17442116 | G11: =G10*Assumptions!$C$12 -> 23827459 | H11: =H10*Assumptions!$C$12 -> 30039514 | I11: =I10*Assumptions!$C$12 -> 30940700 | J11: =J10*Assumptions!$C$12 -> 31868921 | ... O11: =O10*Assumptions!$C$12 -> 36944813
B12: Other revenue | C12: =C10*Assumptions!$C$13 -> 0 | D12: =D10*Assumptions!$C$13 -> 0 | E12: =E10*Assumptions!$C$13 -> 0 | F12: =F10*Assumptions!$C$13 -> 2491730.8 | G12: =G10*Assumptions!$C$13 -> 3403922.8 | H12: =H10*Assumptions!$C$13 -> 4291359.2 | I12: =I10*Assumptions!$C$13 -> 4420099.9 | J12: =J10*Assumptions!$C$13 -> 4552702.9 | ... O12: =O10*Assumptions!$C$13 -> 5277830.5
B13: Total revenue | C13: =SUM(C10:C12) -> 0 | D13: =SUM(D10:D12) -> 0 | E13: =SUM(E10:E12) -> 0 | F13: =SUM(F10:F12) -> 61462694 | G13: =SUM(G10:G12) -> 83963428 | H13: =SUM(H10:H12) -> 1.0585353e+08 | I13: =SUM(I10:I12) -> 1.0902913e+08 | J13: =SUM(J10:J12) -> 1.1230001e+08 | ... O13: =SUM(O10:O12) -> 1.3018649e+08
B14: Departmental costs | C14: =-C13*Assumptions!$C$14 -> 0 | D14: =-D13*Assumptions!$C$14 -> 0 | E14: =-E13*Assumptions!$C$14 -> 0 | F14: =-F13*Assumptions!$C$14 -> -23355824 | G14: =-G13*Assumptions!$C$14 -> -31906103 | H14: =-H13*Assumptions!$C$14 -> -40224340 | I14: =-I13*Assumptions!$C$14 -> -41431070 | J14: =-J13*Assumptions!$C$14 -> -42674002 | ... O14: =-O13*Assumptions!$C$14 -> -49470864
B15: Undistributed costs | C15: =-C13*Assumptions!$C$15 -> 0 | D15: =-D13*Assumptions!$C$15 -> 0 | E15: =-E13*Assumptions!$C$15 -> 0 | F15: =-F13*Assumptions!$C$15 -> -10448658 | G15: =-G13*Assumptions!$C$15 -> -14273783 | H15: =-H13*Assumptions!$C$15 -> -17995099 | I15: =-I13*Assumptions!$C$15 -> -18534952 | J15: =-J13*Assumptions!$C$15 -> -19091001 | ... O15: =-O13*Assumptions!$C$15 -> -22131703
B16: GOP | C16: =SUM(C13:C15) -> 0 | D16: =SUM(D13:D15) -> 0 | E16: =SUM(E13:E15) -> 0 | F16: =SUM(F13:F15) -> 27658212 | G16: =SUM(G13:G15) -> 37783543 | H16: =SUM(H13:H15) -> 47634087 | I16: =SUM(I13:I15) -> 49063109 | J16: =SUM(J13:J15) -> 50535003 | ... O16: =SUM(O13:O15) -> 58583918
B17: Base management fee | C17: =-C13*Assumptions!$C$16 -> 0 | D17: =-D13*Assumptions!$C$16 -> 0 | E17: =-E13*Assumptions!$C$16 -> 0 | F17: =-F13*Assumptions!$C$16 -> -1843880.8 | G17: =-G13*Assumptions!$C$16 -> -2518902.8 | H17: =-H13*Assumptions!$C$16 -> -3175605.8 | I17: =-I13*Assumptions!$C$16 -> -3270874 | J17: =-J13*Assumptions!$C$16 -> -3369000.2 | ... O17: =-O13*Assumptions!$C$16 -> -3905594.6
B18: Incentive fee | C18: =-MAX(0,C16)*Assumptions!$C$17 -> 0 | D18: =-MAX(0,D16)*Assumptions!$C$17 -> 0 | E18: =-MAX(0,E16)*Assumptions!$C$17 -> 0 | F18: =-MAX(0,F16)*Assumptions!$C$17 -> -2212657 | G18: =-MAX(0,G16)*Assumptions!$C$17 -> -3022683.4 | H18: =-MAX(0,H16)*Assumptions!$C$17 -> -3810726.9 | I18: =-MAX(0,I16)*Assumptions!$C$17 -> -3925048.8 | J18: =-MAX(0,J16)*Assumptions!$C$17 -> -4042800.2 | ... O18: =-MAX(0,O16)*Assumptions!$C$17 -> -4686713.5
B19: FF&E reserve | C19: =-C13*Assumptions!$C$18 -> 0 | D19: =-D13*Assumptions!$C$18 -> 0 | E19: =-E13*Assumptions!$C$18 -> 0 | F19: =-F13*Assumptions!$C$18 -> -2458507.8 | G19: =-G13*Assumptions!$C$18 -> -3358537.1 | H19: =-H13*Assumptions!$C$18 -> -4234141 | I19: =-I13*Assumptions!$C$18 -> -4361165.3 | J19: =-J13*Assumptions!$C$18 -> -4492000.2 | ... O19: =-O13*Assumptions!$C$18 -> -5207459.4
B20: EBITDA | C20: =SUM(C16:C19) -> 0 | D20: =SUM(D16:D19) -> 0 | E20: =SUM(E16:E19) -> 0 | F20: =SUM(F16:F19) -> 21143167 | G20: =SUM(G16:G19) -> 28883419 | H20: =SUM(H16:H19) -> 36413613 | I20: =SUM(I16:I19) -> 37506021 | J20: =SUM(J16:J19) -> 38631202 | ... O20: =SUM(O16:O19) -> 44784151

Sheet Cash Flow
B2: CASH FLOW (AED)
B4: Year | C4: 0 | D4: 1 | E4: 2 | F4: 3 | G4: 4 | H4: 5 | I4: 6 | J4: 7 | K4: 8 | L4: 9 | M4: 10 | N4: 11 | O4: 12
B6: Land | C6: =IF(C$4=0,-Assumptions!$C$5,0) -> -95000000 | D6: =IF(D$4=0,-Assumptions!$C$5,0) -> 0 | E6: =IF(E$4=0,-Assumptions!$C$5,0) -> 0 | F6: =IF(F$4=0,-Assumptions!$C$5,0) -> 0 | G6: =IF(G$4=0,-Assumptions!$C$5,0) -> 0 | H6: =IF(H$4=0,-Assumptions!$C$5,0) -> 0 | I6: =IF(I$4=0,-Assumptions!$C$5,0) -> 0 | J6: =IF(J$4=0,-Assumptions!$C$5,0) -> 0 | ... O6: =IF(O$4=0,-Assumptions!$C$5,0) -> 0
B7: Construction | C7: =IF(AND(C$4>=1,C$4<ROUND(Assumptions!$C$8,0)),-Assumptions!$C$4*Assumptions!$C$6/(ROUND(Assumptions!$C$8,0)-1),0) -> 0 | D7: =IF(AND(D$4>=1,D$4<ROUND(Assumptions!$C$8,0)),-Assumptions!$C$4*Assumptions!$C$6/(ROUND(Assumptions!$C$8,0)-1),0) -> -184000000 | E7: =IF(AND(E$4>=1,E$4<ROUND(Assumptions!$C$8,0)),-Assumptions!$C$4*Assumptions!$C$6/(ROUND(Assumptions!$C$8,0)-1),0) -> -184000000 | F7: =IF(AND(F$4>=1,F$4<ROUND(Assumptions!$C$8,0)),-Assumptions!$C$4*Assumptions!$C$6/(ROUND(Assumptions!$C$8,0)-1),0) -> 0 | G7: =IF(AND(G$4>=1,G$4<ROUND(Assumptions!$C$8,0)),-Assumptions!$C$4*Assumptions!$C$6/(ROUND(Assumptions!$C$8,0)-1),0) -> 0 | H7: =IF(AND(H$4>=1,H$4<ROUND(Assumptions!$C$8,0)),-Assumptions!$C$4*Assumptions!$C$6/(ROUND(Assumptions!$C$8,0)-1),0) -> 0 | I7: =IF(AND(I$4>=1,I$4<ROUND(Assumptions!$C$8,0)),-Assumptions!$C$4*Assumptions!$C$6/(ROUND(Assumptions!$C$8,0)-1),0) -> 0 | J7: =IF(AND(J$4>=1,J$4<ROUND(Assumptions!$C$8,0)),-Assumptions!$C$4*Assumptions!$C$6/(ROUND(Assumptions!$C$8,0)-1),0) -> 0 | ... O7: =IF(AND(O$4>=1,O$4<ROUND(Assumptions!$C$8,0)),-Assumptions!$C$4*Assumptions!$C$6/(ROUND(Assumptions!$C$8,0)-1),0) -> 0
B8: Pre-opening and FF&E | C8: =IF(C$4=ROUND(Assumptions!$C$8,0)-1,-Assumptions!$C$7,0) -> 0 | D8: =IF(D$4=ROUND(Assumptions!$C$8,0)-1,-Assumptions!$C$7,0) -> 0 | E8: =IF(E$4=ROUND(Assumptions!$C$8,0)-1,-Assumptions!$C$7,0) -> -48000000 | F8: =IF(F$4=ROUND(Assumptions!$C$8,0)-1,-Assumptions!$C$7,0) -> 0 | G8: =IF(G$4=ROUND(Assumptions!$C$8,0)-1,-Assumptions!$C$7,0) -> 0 | H8: =IF(H$4=ROUND(Assumptions!$C$8,0)-1,-Assumptions!$C$7,0) -> 0 | I8: =IF(I$4=ROUND(Assumptions!$C$8,0)-1,-Assumptions!$C$7,0) -> 0 | J8: =IF(J$4=ROUND(Assumptions!$C$8,0)-1,-Assumptions!$C$7,0) -> 0 | ... O8: =IF(O$4=ROUND(Assumptions!$C$8,0)-1,-Assumptions!$C$7,0) -> 0
B9: EBITDA | C9: =IF(C$4<=ROUND(Assumptions!$C$19,0),Operations!C20,0) -> 0 | D9: =IF(D$4<=ROUND(Assumptions!$C$19,0),Operations!D20,0) -> 0 | E9: =IF(E$4<=ROUND(Assumptions!$C$19,0),Operations!E20,0) -> 0 | F9: =IF(F$4<=ROUND(Assumptions!$C$19,0),Operations!F20,0) -> 21143167 | G9: =IF(G$4<=ROUND(Assumptions!$C$19,0),Operations!G20,0) -> 28883419 | H9: =IF(H$4<=ROUND(Assumptions!$C$19,0),Operations!H20,0) -> 36413613 | I9: =IF(I$4<=ROUND(Assumptions!$C$19,0),Operations!I20,0) -> 37506021 | J9: =IF(J$4<=ROUND(Assumptions!$C$19,0),Operations!J20,0) -> 38631202 | ... O9: =IF(O$4<=ROUND(Assumptions!$C$19,0),Operations!O20,0) -> 0
B10: Sale (net) | C10: =IF(C$4=ROUND(Assumptions!$C$19,0),Operations!D20*Assumptions!$C$20*(1-Assumptions!$C$21),0) -> 0 | D10: =IF(D$4=ROUND(Assumptions!$C$19,0),Operations!E20*Assumptions!$C$20*(1-Assumptions!$C$21),0) -> 0 | E10: =IF(E$4=ROUND(Assumptions!$C$19,0),Operations!F20*Assumptions!$C$20*(1-Assumptions!$C$21),0) -> 0 | F10: =IF(F$4=ROUND(Assumptions!$C$19,0),Operations!G20*Assumptions!$C$20*(1-Assumptions!$C$21),0) -> 0 | G10: =IF(G$4=ROUND(Assumptions!$C$19,0),Operations!H20*Assumptions!$C$20*(1-Assumptions!$C$21),0) -> 0 | H10: =IF(H$4=ROUND(Assumptions!$C$19,0),Operations!I20*Assumptions!$C$20*(1-Assumptions!$C$21),0) -> 0 | I10: =IF(I$4=ROUND(Assumptions!$C$19,0),Operations!J20*Assumptions!$C$20*(1-Assumptions!$C$21),0) -> 0 | J10: =IF(J$4=ROUND(Assumptions!$C$19,0),Operations!K20*Assumptions!$C$20*(1-Assumptions!$C$21),0) -> 0 | ... N10: =IF(N$4=ROUND(Assumptions!$C$19,0),Operations!O20*Assumptions!$C$20*(1-Assumptions!$C$21),0) -> 0 | O10: =0 -> 0
B11: Unleveraged cash flow | C11: =SUM(C6:C10) -> -95000000 | D11: =SUM(D6:D10) -> -184000000 | E11: =SUM(E6:E10) -> -232000000 | F11: =SUM(F6:F10) -> 21143167 | G11: =SUM(G6:G10) -> 28883419 | H11: =SUM(H6:H10) -> 36413613 | I11: =SUM(I6:I10) -> 37506021 | J11: =SUM(J6:J10) -> 38631202 | ... O11: =SUM(O6:O10) -> 0
B13: Loan draw | C13: =-SUM(C6:C8)*Assumptions!$C$22 -> 52250000 | D13: =-SUM(D6:D8)*Assumptions!$C$22 -> 101200000 | E13: =-SUM(E6:E8)*Assumptions!$C$22 -> 127600000 | F13: =-SUM(F6:F8)*Assumptions!$C$22 -> 0 | G13: =-SUM(G6:G8)*Assumptions!$C$22 -> 0 | H13: =-SUM(H6:H8)*Assumptions!$C$22 -> 0 | I13: =-SUM(I6:I8)*Assumptions!$C$22 -> 0 | J13: =-SUM(J6:J8)*Assumptions!$C$22 -> 0 | ... O13: =-SUM(O6:O8)*Assumptions!$C$22 -> 0
B14: Interest | C14: =0 -> 0 | D14: =-C16*Assumptions!$C$23 -> -3396250 | E14: =-D16*Assumptions!$C$23 -> -9974250 | F14: =-E16*Assumptions!$C$23 -> -18268250 | G14: =-F16*Assumptions!$C$23 -> -17354838 | H14: =-G16*Assumptions!$C$23 -> -16441425 | I14: =-H16*Assumptions!$C$23 -> -15528012 | J14: =-I16*Assumptions!$C$23 -> -14614600 | K14: =-J16*Assumptions!$C$23 -> -13701188 | ... O14: =-N16*Assumptions!$C$23 -> 0
B15: Repayment | C15: =0 -> 0 | D15: =-IF(D$4=ROUND(Assumptions!$C$19,0),C16,IF(D$4>ROUND(Assumptions!$C$19,0),0,IF(AND(D$4>=ROUND(Assumptions!$C$8,0),D$4<ROUND(Assumptions!$C$19,0)),C16/MAX(1,Assumptions!$C$24-(D$4-ROUND(Assumptions!$C$8,0))),0))) -> 0 | E15: =-IF(E$4=ROUND(Assumptions!$C$19,0),D16,IF(E$4>ROUND(Assumptions!$C$19,0),0,IF(AND(E$4>=ROUND(Assumptions!$C$8,0),E$4<ROUND(Assumptions!$C$19,0)),D16/MAX(1,Assumptions!$C$24-(E$4-ROUND(Assumptions!$C$8,0))),0))) -> 0 | F15: =-IF(F$4=ROUND(Assumptions!$C$19,0),E16,IF(F$4>ROUND(Assumptions!$C$19,0),0,IF(AND(F$4>=ROUND(Assumptions!$C$8,0),F$4<ROUND(Assumptions!$C$19,0)),E16/MAX(1,Assumptions!$C$24-(F$4-ROUND(Assumptions!$C$8,0))),0))) -> -14052500 | G15: =-IF(G$4=ROUND(Assumptions!$C$19,0),F16,IF(G$4>ROUND(Assumptions!$C$19,0),0,IF(AND(G$4>=ROUND(Assumptions!$C$8,0),G$4<ROUND(Assumptions!$C$19,0)),F16/MAX(1,Assumptions!$C$24-(G$4-ROUND(Assumptions!$C$8,0))),0))) -> -14052500 | H15: =-IF(H$4=ROUND(Assumptions!$C$19,0),G16,IF(H$4>ROUND(Assumptions!$C$19,0),0,IF(AND(H$4>=ROUND(Assumptions!$C$8,0),H$4<ROUND(Assumptions!$C$19,0)),G16/MAX(1,Assumptions!$C$24-(H$4-ROUND(Assumptions!$C$8,0))),0))) -> -14052500 | I15: =-IF(I$4=ROUND(Assumptions!$C$19,0),H16,IF(I$4>ROUND(Assumptions!$C$19,0),0,IF(AND(I$4>=ROUND(Assumptions!$C$8,0),I$4<ROUND(Assumptions!$C$19,0)),H16/MAX(1,Assumptions!$C$24-(I$4-ROUND(Assumptions!$C$8,0))),0))) -> -14052500 | J15: =-IF(J$4=ROUND(Assumptions!$C$19,0),I16,IF(J$4>ROUND(Assumptions!$C$19,0),0,IF(AND(J$4>=ROUND(Assumptions!$C$8,0),J$4<ROUND(Assumptions!$C$19,0)),I16/MAX(1,Assumptions!$C$24-(J$4-ROUND(Assumptions!$C$8,0))),0))) -> -14052500 | K15: =-IF(K$4=ROUND(Assumptions!$C$19,0),J16,IF(K$4>ROUND(Assumptions!$C$19,0),0,IF(AND(K$4>=ROUND(Assumptions!$C$8,0),K$4<ROUND(Assumptions!$C$19,0)),J16/MAX(1,Assumptions!$C$24-(K$4-ROUND(Assumptions!$C$8,0))),0))) -> -14052500 | ... O15: =-IF(O$4=ROUND(Assumptions!$C$19,0),N16,IF(O$4>ROUND(Assumptions!$C$19,0),0,IF(AND(O$4>=ROUND(Assumptions!$C$8,0),O$4<ROUND(Assumptions!$C$19,0)),N16/MAX(1,Assumptions!$C$24-(O$4-ROUND(Assumptions!$C$8,0))),0))) -> 0
B16: Loan balance | C16: =C13 -> 52250000 | D16: =C16+D13+D15 -> 153450000 | E16: =D16+E13+E15 -> 281050000 | F16: =E16+F13+F15 -> 266997500 | G16: =F16+G13+G15 -> 252945000 | H16: =G16+H13+H15 -> 238892500 | I16: =H16+I13+I15 -> 224840000 | J16: =I16+J13+J15 -> 210787500 | K16: =J16+K13+K15 -> 196735000 | ... O16: =N16+O13+O15 -> 0
B18: Leveraged cash flow | C18: =C11+C13+C14+C15 -> -42750000 | D18: =D11+D13+D14+D15 -> -86196250 | E18: =E11+E13+E14+E15 -> -114374250 | F18: =F11+F13+F14+F15 -> -11177583 | G18: =G11+G13+G14+G15 -> -2523918.2 | H18: =H11+H13+H14+H15 -> 5919688 | I18: =I11+I13+I14+I15 -> 7925508.9 | J18: =J11+J13+J14+J15 -> 9964102.1 | ... O18: =O11+O13+O14+O15 -> 0
