Workbook

Sheet Summary
B2: ST MARY AXE HOUSE · SUMMARY (GBP)
B5: Net initial yield | C5: ='Cash Flow'!E8/(Assumptions!C4*(1+Assumptions!C5)) -> 0.05302681
B6: IRR (ungeared) | C6: =IRR('Cash Flow'!D12:O12) -> 0.083121766
B7: IRR (geared) | C7: =IRR('Cash Flow'!D17:O17) -> 0.099394256
B8: Equity multiple | C8: =SUMIF('Cash Flow'!D17:O17,">0")/-SUMIF('Cash Flow'!D17:O17,"<0") -> 2.3079597
B9: WAULT (years) | C9: =SUMPRODUCT('Rent Roll'!C5:C10,'Rent Roll'!D5:D10,'Rent Roll'!E5:E10)/SUMPRODUCT('Rent Roll'!C5:C10,'Rent Roll'!D5:D10) -> 5.0583892
B10: Geared profit | C10: =SUM('Cash Flow'!D17:O17) -> 1.1241914e+08

Sheet Assumptions
B2: ST MARY AXE HOUSE · ASSUMPTIONS (GBP)
B4: Purchase price | C4: 150000000
B5: Purchase costs (SDLT and fees) | C5: 0.068
B6: Market rent (per sq ft a year) | C6: 72.5
B7: Market rent growth | C7: 0.025
B8: Non-recoverable costs (% of rent) | C8: 0.035
B9: Exit cap rate | C9: 0.0525
B10: Selling costs | C10: 0.015
B11: Hold (years) | C11: 10
B12: Loan to value | C12: 0.5
B13: Interest rate | C13: 0.058
B14: Arrangement fee | C14: 0.01

Sheet Rent Roll
B2: RENT ROLL
B4: Tenant | C4: Area (sq ft) | D4: Rent (per sq ft) | E4: Lease expiry (year) | F4: Renewal probability | G4: Downtime (months) | H4: TI (per sq ft) | I4: LC (months of rent)
B5: Harcourt Legal LLP | C5: 32000 | D5: 64 | E5: 3 | F5: 0.65 | G5: 9 | H5: 45 | I5: 2
B6: Northgate Capital | C6: 21500 | D6: 70 | E6: 5 | F6: 0.7 | G6: 6 | H6: 40 | I6: 2
B7: Ferro Digital | C7: 18000 | D7: 58.5 | E7: 2 | F7: 0.5 | G7: 12 | H7: 50 | I7: 2.5
B8: Albion Insurance | C8: 40000 | D8: 66 | E8: 8 | F8: 0.75 | G8: 9 | H8: 45 | I8: 2
B9: Quill & Co | C9: 9500 | D9: 74 | E9: 6 | F9: 0.6 | G9: 6 | H9: 35 | I9: 1.5
B10: Tessera Labs | C10: 14000 | D10: 61 | E10: 4 | F10: 0.55 | G10: 9 | H10: 50 | I10: 2
B11: Total | C11: =SUM(C5:C10) -> 135000

Sheet Tenant CF
B2: TENANT CASH FLOW (GBP)
B4: Year | D4: 0 | E4: 1 | F4: 2 | G4: 3 | H4: 4 | I4: 5 | J4: 6 | K4: 7 | L4: 8 | M4: 9 | N4: 10 | O4: 11
B6: ='Rent Roll'!B5 -> Harcourt Legal LLP | C6: Rent | D6: 0 | E6: =IF(E$4<='Rent Roll'!$E$5,'Rent Roll'!$C$5*'Rent Roll'!$D$5,'Rent Roll'!$C$5*Assumptions!$C$6*(1+Assumptions!$C$7)^(E$4-1)*('Rent Roll'!$F$5+(1-'Rent Roll'!$F$5)*IF(E$4='Rent Roll'!$E$5+1,MAX(0,12-ROUND('Rent Roll'!$G$5,0))/12,1))) -> 2048000 | F6: =IF(F$4<='Rent Roll'!$E$5,'Rent Roll'!$C$5*'Rent Roll'!$D$5,'Rent Roll'!$C$5*Assumptions!$C$6*(1+Assumptions!$C$7)^(F$4-1)*('Rent Roll'!$F$5+(1-'Rent Roll'!$F$5)*IF(F$4='Rent Roll'!$E$5+1,MAX(0,12-ROUND('Rent Roll'!$G$5,0))/12,1))) -> 2048000 | G6: =IF(G$4<='Rent Roll'!$E$5,'Rent Roll'!$C$5*'Rent Roll'!$D$5,'Rent Roll'!$C$5*Assumptions!$C$6*(1+Assumptions!$C$7)^(G$4-1)*('Rent Roll'!$F$5+(1-'Rent Roll'!$F$5)*IF(G$4='Rent Roll'!$E$5+1,MAX(0,12-ROUND('Rent Roll'!$G$5,0))/12,1))) -> 2048000 | H6: =IF(H$4<='Rent Roll'!$E$5,'Rent Roll'!$C$5*'Rent Roll'!$D$5,'Rent Roll'!$C$5*Assumptions!$C$6*(1+Assumptions!$C$7)^(H$4-1)*('Rent Roll'!$F$5+(1-'Rent Roll'!$F$5)*IF(H$4='Rent Roll'!$E$5+1,MAX(0,12-ROUND('Rent Roll'!$G$5,0))/12,1))) -> 1842559.9 | I6: =IF(I$4<='Rent Roll'!$E$5,'Rent Roll'!$C$5*'Rent Roll'!$D$5,'Rent Roll'!$C$5*Assumptions!$C$6*(1+Assumptions!$C$7)^(I$4-1)*('Rent Roll'!$F$5+(1-'Rent Roll'!$F$5)*IF(I$4='Rent Roll'!$E$5+1,MAX(0,12-ROUND('Rent Roll'!$G$5,0))/12,1))) -> 2560845.9 | J6: =IF(J$4<='Rent Roll'!$E$5,'Rent Roll'!$C$5*'Rent Roll'!$D$5,'Rent Roll'!$C$5*Assumptions!$C$6*(1+Assumptions!$C$7)^(J$4-1)*('Rent Roll'!$F$5+(1-'Rent Roll'!$F$5)*IF(J$4='Rent Roll'!$E$5+1,MAX(0,12-ROUND('Rent Roll'!$G$5,0))/12,1))) -> 2624867.1 | K6: =IF(K$4<='Rent Roll'!$E$5,'Rent Roll'!$C$5*'Rent Roll'!$D$5,'Rent Roll'!$C$5*Assumptions!$C$6*(1+Assumptions!$C$7)^(K$4-1)*('Rent Roll'!$F$5+(1-'Rent Roll'!$F$5)*IF(K$4='Rent Roll'!$E$5+1,MAX(0,12-ROUND('Rent Roll'!$G$5,0))/12,1))) -> 2690488.7 | L6: =IF(L$4<='Rent Roll'!$E$5,'Rent Roll'!$C$5*'Rent Roll'!$D$5,'Rent Roll'!$C$5*Assumptions!$C$6*(1+Assumptions!$C$7)^(L$4-1)*('Rent Roll'!$F$5+(1-'Rent Roll'!$F$5)*IF(L$4='Rent Roll'!$E$5+1,MAX(0,12-ROUND('Rent Roll'!$G$5,0))/12,1))) -> 2757750.9 | ... O6: =IF(O$4<='Rent Roll'!$E$5,'Rent Roll'!$C$5*'Rent Roll'!$D$5,'Rent Roll'!$C$5*Assumptions!$C$6*(1+Assumptions!$C$7)^(O$4-1)*('Rent Roll'!$F$5+(1-'Rent Roll'!$F$5)*IF(O$4='Rent Roll'!$E$5+1,MAX(0,12-ROUND('Rent Roll'!$G$5,0))/12,1))) -> 2969796.1
C7: TI | D7: 0 | E7: =IF(E$4='Rent Roll'!$E$5+1,-'Rent Roll'!$C$5*'Rent Roll'!$H$5*(1-'Rent Roll'!$F$5*0.5),0) -> 0 | F7: =IF(F$4='Rent Roll'!$E$5+1,-'Rent Roll'!$C$5*'Rent Roll'!$H$5*(1-'Rent Roll'!$F$5*0.5),0) -> 0 | G7: =IF(G$4='Rent Roll'!$E$5+1,-'Rent Roll'!$C$5*'Rent Roll'!$H$5*(1-'Rent Roll'!$F$5*0.5),0) -> 0 | H7: =IF(H$4='Rent Roll'!$E$5+1,-'Rent Roll'!$C$5*'Rent Roll'!$H$5*(1-'Rent Roll'!$F$5*0.5),0) -> -972000 | I7: =IF(I$4='Rent Roll'!$E$5+1,-'Rent Roll'!$C$5*'Rent Roll'!$H$5*(1-'Rent Roll'!$F$5*0.5),0) -> 0 | J7: =IF(J$4='Rent Roll'!$E$5+1,-'Rent Roll'!$C$5*'Rent Roll'!$H$5*(1-'Rent Roll'!$F$5*0.5),0) -> 0 | K7: =IF(K$4='Rent Roll'!$E$5+1,-'Rent Roll'!$C$5*'Rent Roll'!$H$5*(1-'Rent Roll'!$F$5*0.5),0) -> 0 | L7: =IF(L$4='Rent Roll'!$E$5+1,-'Rent Roll'!$C$5*'Rent Roll'!$H$5*(1-'Rent Roll'!$F$5*0.5),0) -> 0 | ... O7: =IF(O$4='Rent Roll'!$E$5+1,-'Rent Roll'!$C$5*'Rent Roll'!$H$5*(1-'Rent Roll'!$F$5*0.5),0) -> 0
C8: Leasing commission | D8: 0 | E8: =IF(E$4='Rent Roll'!$E$5+1,-'Rent Roll'!$C$5*Assumptions!$C$6*(1+Assumptions!$C$7)^(E$4-1)/12*'Rent Roll'!$I$5,0) -> 0 | F8: =IF(F$4='Rent Roll'!$E$5+1,-'Rent Roll'!$C$5*Assumptions!$C$6*(1+Assumptions!$C$7)^(F$4-1)/12*'Rent Roll'!$I$5,0) -> 0 | G8: =IF(G$4='Rent Roll'!$E$5+1,-'Rent Roll'!$C$5*Assumptions!$C$6*(1+Assumptions!$C$7)^(G$4-1)/12*'Rent Roll'!$I$5,0) -> 0 | H8: =IF(H$4='Rent Roll'!$E$5+1,-'Rent Roll'!$C$5*Assumptions!$C$6*(1+Assumptions!$C$7)^(H$4-1)/12*'Rent Roll'!$I$5,0) -> -416397.71 | I8: =IF(I$4='Rent Roll'!$E$5+1,-'Rent Roll'!$C$5*Assumptions!$C$6*(1+Assumptions!$C$7)^(I$4-1)/12*'Rent Roll'!$I$5,0) -> 0 | J8: =IF(J$4='Rent Roll'!$E$5+1,-'Rent Roll'!$C$5*Assumptions!$C$6*(1+Assumptions!$C$7)^(J$4-1)/12*'Rent Roll'!$I$5,0) -> 0 | K8: =IF(K$4='Rent Roll'!$E$5+1,-'Rent Roll'!$C$5*Assumptions!$C$6*(1+Assumptions!$C$7)^(K$4-1)/12*'Rent Roll'!$I$5,0) -> 0 | L8: =IF(L$4='Rent Roll'!$E$5+1,-'Rent Roll'!$C$5*Assumptions!$C$6*(1+Assumptions!$C$7)^(L$4-1)/12*'Rent Roll'!$I$5,0) -> 0 | ... O8: =IF(O$4='Rent Roll'!$E$5+1,-'Rent Roll'!$C$5*Assumptions!$C$6*(1+Assumptions!$C$7)^(O$4-1)/12*'Rent Roll'!$I$5,0) -> 0
B10: ='Rent Roll'!B6 -> Northgate Capital | C10: Rent | D10: 0 | E10: =IF(E$4<='Rent Roll'!$E$6,'Rent Roll'!$C$6*'Rent Roll'!$D$6,'Rent Roll'!$C$6*Assumptions!$C$6*(1+Assumptions!$C$7)^(E$4-1)*('Rent Roll'!$F$6+(1-'Rent Roll'!$F$6)*IF(E$4='Rent Roll'!$E$6+1,MAX(0,12-ROUND('Rent Roll'!$G$6,0))/12,1))) -> 1505000 | F10: =IF(F$4<='Rent Roll'!$E$6,'Rent Roll'!$C$6*'Rent Roll'!$D$6,'Rent Roll'!$C$6*Assumptions!$C$6*(1+Assumptions!$C$7)^(F$4-1)*('Rent Roll'!$F$6+(1-'Rent Roll'!$F$6)*IF(F$4='Rent Roll'!$E$6+1,MAX(0,12-ROUND('Rent Roll'!$G$6,0))/12,1))) -> 1505000 | G10: =IF(G$4<='Rent Roll'!$E$6,'Rent Roll'!$C$6*'Rent Roll'!$D$6,'Rent Roll'!$C$6*Assumptions!$C$6*(1+Assumptions!$C$7)^(G$4-1)*('Rent Roll'!$F$6+(1-'Rent Roll'!$F$6)*IF(G$4='Rent Roll'!$E$6+1,MAX(0,12-ROUND('Rent Roll'!$G$6,0))/12,1))) -> 1505000 | H10: =IF(H$4<='Rent Roll'!$E$6,'Rent Roll'!$C$6*'Rent Roll'!$D$6,'Rent Roll'!$C$6*Assumptions!$C$6*(1+Assumptions!$C$7)^(H$4-1)*('Rent Roll'!$F$6+(1-'Rent Roll'!$F$6)*IF(H$4='Rent Roll'!$E$6+1,MAX(0,12-ROUND('Rent Roll'!$G$6,0))/12,1))) -> 1505000 | I10: =IF(I$4<='Rent Roll'!$E$6,'Rent Roll'!$C$6*'Rent Roll'!$D$6,'Rent Roll'!$C$6*Assumptions!$C$6*(1+Assumptions!$C$7)^(I$4-1)*('Rent Roll'!$F$6+(1-'Rent Roll'!$F$6)*IF(I$4='Rent Roll'!$E$6+1,MAX(0,12-ROUND('Rent Roll'!$G$6,0))/12,1))) -> 1505000 | J10: =IF(J$4<='Rent Roll'!$E$6,'Rent Roll'!$C$6*'Rent Roll'!$D$6,'Rent Roll'!$C$6*Assumptions!$C$6*(1+Assumptions!$C$7)^(J$4-1)*('Rent Roll'!$F$6+(1-'Rent Roll'!$F$6)*IF(J$4='Rent Roll'!$E$6+1,MAX(0,12-ROUND('Rent Roll'!$G$6,0))/12,1))) -> 1499045.2 | K10: =IF(K$4<='Rent Roll'!$E$6,'Rent Roll'!$C$6*'Rent Roll'!$D$6,'Rent Roll'!$C$6*Assumptions!$C$6*(1+Assumptions!$C$7)^(K$4-1)*('Rent Roll'!$F$6+(1-'Rent Roll'!$F$6)*IF(K$4='Rent Roll'!$E$6+1,MAX(0,12-ROUND('Rent Roll'!$G$6,0))/12,1))) -> 1807672.1 | L10: =IF(L$4<='Rent Roll'!$E$6,'Rent Roll'!$C$6*'Rent Roll'!$D$6,'Rent Roll'!$C$6*Assumptions!$C$6*(1+Assumptions!$C$7)^(L$4-1)*('Rent Roll'!$F$6+(1-'Rent Roll'!$F$6)*IF(L$4='Rent Roll'!$E$6+1,MAX(0,12-ROUND('Rent Roll'!$G$6,0))/12,1))) -> 1852863.9 | ... O10: =IF(O$4<='Rent Roll'!$E$6,'Rent Roll'!$C$6*'Rent Roll'!$D$6,'Rent Roll'!$C$6*Assumptions!$C$6*(1+Assumptions!$C$7)^(O$4-1)*('Rent Roll'!$F$6+(1-'Rent Roll'!$F$6)*IF(O$4='Rent Roll'!$E$6+1,MAX(0,12-ROUND('Rent Roll'!$G$6,0))/12,1))) -> 1995331.8
C11: TI | D11: 0 | E11: =IF(E$4='Rent Roll'!$E$6+1,-'Rent Roll'!$C$6*'Rent Roll'!$H$6*(1-'Rent Roll'!$F$6*0.5),0) -> 0 | F11: =IF(F$4='Rent Roll'!$E$6+1,-'Rent Roll'!$C$6*'Rent Roll'!$H$6*(1-'Rent Roll'!$F$6*0.5),0) -> 0 | G11: =IF(G$4='Rent Roll'!$E$6+1,-'Rent Roll'!$C$6*'Rent Roll'!$H$6*(1-'Rent Roll'!$F$6*0.5),0) -> 0 | H11: =IF(H$4='Rent Roll'!$E$6+1,-'Rent Roll'!$C$6*'Rent Roll'!$H$6*(1-'Rent Roll'!$F$6*0.5),0) -> 0 | I11: =IF(I$4='Rent Roll'!$E$6+1,-'Rent Roll'!$C$6*'Rent Roll'!$H$6*(1-'Rent Roll'!$F$6*0.5),0) -> 0 | J11: =IF(J$4='Rent Roll'!$E$6+1,-'Rent Roll'!$C$6*'Rent Roll'!$H$6*(1-'Rent Roll'!$F$6*0.5),0) -> -559000 | K11: =IF(K$4='Rent Roll'!$E$6+1,-'Rent Roll'!$C$6*'Rent Roll'!$H$6*(1-'Rent Roll'!$F$6*0.5),0) -> 0 | L11: =IF(L$4='Rent Roll'!$E$6+1,-'Rent Roll'!$C$6*'Rent Roll'!$H$6*(1-'Rent Roll'!$F$6*0.5),0) -> 0 | ... O11: =IF(O$4='Rent Roll'!$E$6+1,-'Rent Roll'!$C$6*'Rent Roll'!$H$6*(1-'Rent Roll'!$F$6*0.5),0) -> 0
C12: Leasing commission | D12: 0 | E12: =IF(E$4='Rent Roll'!$E$6+1,-'Rent Roll'!$C$6*Assumptions!$C$6*(1+Assumptions!$C$7)^(E$4-1)/12*'Rent Roll'!$I$6,0) -> 0 | F12: =IF(F$4='Rent Roll'!$E$6+1,-'Rent Roll'!$C$6*Assumptions!$C$6*(1+Assumptions!$C$7)^(F$4-1)/12*'Rent Roll'!$I$6,0) -> 0 | G12: =IF(G$4='Rent Roll'!$E$6+1,-'Rent Roll'!$C$6*Assumptions!$C$6*(1+Assumptions!$C$7)^(G$4-1)/12*'Rent Roll'!$I$6,0) -> 0 | H12: =IF(H$4='Rent Roll'!$E$6+1,-'Rent Roll'!$C$6*Assumptions!$C$6*(1+Assumptions!$C$7)^(H$4-1)/12*'Rent Roll'!$I$6,0) -> 0 | I12: =IF(I$4='Rent Roll'!$E$6+1,-'Rent Roll'!$C$6*Assumptions!$C$6*(1+Assumptions!$C$7)^(I$4-1)/12*'Rent Roll'!$I$6,0) -> 0 | J12: =IF(J$4='Rent Roll'!$E$6+1,-'Rent Roll'!$C$6*Assumptions!$C$6*(1+Assumptions!$C$7)^(J$4-1)/12*'Rent Roll'!$I$6,0) -> -293930.43 | K12: =IF(K$4='Rent Roll'!$E$6+1,-'Rent Roll'!$C$6*Assumptions!$C$6*(1+Assumptions!$C$7)^(K$4-1)/12*'Rent Roll'!$I$6,0) -> 0 | L12: =IF(L$4='Rent Roll'!$E$6+1,-'Rent Roll'!$C$6*Assumptions!$C$6*(1+Assumptions!$C$7)^(L$4-1)/12*'Rent Roll'!$I$6,0) -> 0 | ... O12: =IF(O$4='Rent Roll'!$E$6+1,-'Rent Roll'!$C$6*Assumptions!$C$6*(1+Assumptions!$C$7)^(O$4-1)/12*'Rent Roll'!$I$6,0) -> 0
B14: ='Rent Roll'!B7 -> Ferro Digital | C14: Rent | D14: 0 | E14: =IF(E$4<='Rent Roll'!$E$7,'Rent Roll'!$C$7*'Rent Roll'!$D$7,'Rent Roll'!$C$7*Assumptions!$C$6*(1+Assumptions!$C$7)^(E$4-1)*('Rent Roll'!$F$7+(1-'Rent Roll'!$F$7)*IF(E$4='Rent Roll'!$E$7+1,MAX(0,12-ROUND('Rent Roll'!$G$7,0))/12,1))) -> 1053000 | F14: =IF(F$4<='Rent Roll'!$E$7,'Rent Roll'!$C$7*'Rent Roll'!$D$7,'Rent Roll'!$C$7*Assumptions!$C$6*(1+Assumptions!$C$7)^(F$4-1)*('Rent Roll'!$F$7+(1-'Rent Roll'!$F$7)*IF(F$4='Rent Roll'!$E$7+1,MAX(0,12-ROUND('Rent Roll'!$G$7,0))/12,1))) -> 1053000 | G14: =IF(G$4<='Rent Roll'!$E$7,'Rent Roll'!$C$7*'Rent Roll'!$D$7,'Rent Roll'!$C$7*Assumptions!$C$6*(1+Assumptions!$C$7)^(G$4-1)*('Rent Roll'!$F$7+(1-'Rent Roll'!$F$7)*IF(G$4='Rent Roll'!$E$7+1,MAX(0,12-ROUND('Rent Roll'!$G$7,0))/12,1))) -> 685532.81 | H14: =IF(H$4<='Rent Roll'!$E$7,'Rent Roll'!$C$7*'Rent Roll'!$D$7,'Rent Roll'!$C$7*Assumptions!$C$6*(1+Assumptions!$C$7)^(H$4-1)*('Rent Roll'!$F$7+(1-'Rent Roll'!$F$7)*IF(H$4='Rent Roll'!$E$7+1,MAX(0,12-ROUND('Rent Roll'!$G$7,0))/12,1))) -> 1405342.3 | I14: =IF(I$4<='Rent Roll'!$E$7,'Rent Roll'!$C$7*'Rent Roll'!$D$7,'Rent Roll'!$C$7*Assumptions!$C$6*(1+Assumptions!$C$7)^(I$4-1)*('Rent Roll'!$F$7+(1-'Rent Roll'!$F$7)*IF(I$4='Rent Roll'!$E$7+1,MAX(0,12-ROUND('Rent Roll'!$G$7,0))/12,1))) -> 1440475.8 | J14: =IF(J$4<='Rent Roll'!$E$7,'Rent Roll'!$C$7*'Rent Roll'!$D$7,'Rent Roll'!$C$7*Assumptions!$C$6*(1+Assumptions!$C$7)^(J$4-1)*('Rent Roll'!$F$7+(1-'Rent Roll'!$F$7)*IF(J$4='Rent Roll'!$E$7+1,MAX(0,12-ROUND('Rent Roll'!$G$7,0))/12,1))) -> 1476487.7 | K14: =IF(K$4<='Rent Roll'!$E$7,'Rent Roll'!$C$7*'Rent Roll'!$D$7,'Rent Roll'!$C$7*Assumptions!$C$6*(1+Assumptions!$C$7)^(K$4-1)*('Rent Roll'!$F$7+(1-'Rent Roll'!$F$7)*IF(K$4='Rent Roll'!$E$7+1,MAX(0,12-ROUND('Rent Roll'!$G$7,0))/12,1))) -> 1513399.9 | L14: =IF(L$4<='Rent Roll'!$E$7,'Rent Roll'!$C$7*'Rent Roll'!$D$7,'Rent Roll'!$C$7*Assumptions!$C$6*(1+Assumptions!$C$7)^(L$4-1)*('Rent Roll'!$F$7+(1-'Rent Roll'!$F$7)*IF(L$4='Rent Roll'!$E$7+1,MAX(0,12-ROUND('Rent Roll'!$G$7,0))/12,1))) -> 1551234.9 | ... O14: =IF(O$4<='Rent Roll'!$E$7,'Rent Roll'!$C$7*'Rent Roll'!$D$7,'Rent Roll'!$C$7*Assumptions!$C$6*(1+Assumptions!$C$7)^(O$4-1)*('Rent Roll'!$F$7+(1-'Rent Roll'!$F$7)*IF(O$4='Rent Roll'!$E$7+1,MAX(0,12-ROUND('Rent Roll'!$G$7,0))/12,1))) -> 1670510.3
C15: TI | D15: 0 | E15: =IF(E$4='Rent Roll'!$E$7+1,-'Rent Roll'!$C$7*'Rent Roll'!$H$7*(1-'Rent Roll'!$F$7*0.5),0) -> 0 | F15: =IF(F$4='Rent Roll'!$E$7+1,-'Rent Roll'!$C$7*'Rent Roll'!$H$7*(1-'Rent Roll'!$F$7*0.5),0) -> 0 | G15: =IF(G$4='Rent Roll'!$E$7+1,-'Rent Roll'!$C$7*'Rent Roll'!$H$7*(1-'Rent Roll'!$F$7*0.5),0) -> -675000 | H15: =IF(H$4='Rent Roll'!$E$7+1,-'Rent Roll'!$C$7*'Rent Roll'!$H$7*(1-'Rent Roll'!$F$7*0.5),0) -> 0 | I15: =IF(I$4='Rent Roll'!$E$7+1,-'Rent Roll'!$C$7*'Rent Roll'!$H$7*(1-'Rent Roll'!$F$7*0.5),0) -> 0 | J15: =IF(J$4='Rent Roll'!$E$7+1,-'Rent Roll'!$C$7*'Rent Roll'!$H$7*(1-'Rent Roll'!$F$7*0.5),0) -> 0 | K15: =IF(K$4='Rent Roll'!$E$7+1,-'Rent Roll'!$C$7*'Rent Roll'!$H$7*(1-'Rent Roll'!$F$7*0.5),0) -> 0 | L15: =IF(L$4='Rent Roll'!$E$7+1,-'Rent Roll'!$C$7*'Rent Roll'!$H$7*(1-'Rent Roll'!$F$7*0.5),0) -> 0 | ... O15: =IF(O$4='Rent Roll'!$E$7+1,-'Rent Roll'!$C$7*'Rent Roll'!$H$7*(1-'Rent Roll'!$F$7*0.5),0) -> 0
C16: Leasing commission | D16: 0 | E16: =IF(E$4='Rent Roll'!$E$7+1,-'Rent Roll'!$C$7*Assumptions!$C$6*(1+Assumptions!$C$7)^(E$4-1)/12*'Rent Roll'!$I$7,0) -> 0 | F16: =IF(F$4='Rent Roll'!$E$7+1,-'Rent Roll'!$C$7*Assumptions!$C$6*(1+Assumptions!$C$7)^(F$4-1)/12*'Rent Roll'!$I$7,0) -> 0 | G16: =IF(G$4='Rent Roll'!$E$7+1,-'Rent Roll'!$C$7*Assumptions!$C$6*(1+Assumptions!$C$7)^(G$4-1)/12*'Rent Roll'!$I$7,0) -> -285638.67 | H16: =IF(H$4='Rent Roll'!$E$7+1,-'Rent Roll'!$C$7*Assumptions!$C$6*(1+Assumptions!$C$7)^(H$4-1)/12*'Rent Roll'!$I$7,0) -> 0 | I16: =IF(I$4='Rent Roll'!$E$7+1,-'Rent Roll'!$C$7*Assumptions!$C$6*(1+Assumptions!$C$7)^(I$4-1)/12*'Rent Roll'!$I$7,0) -> 0 | J16: =IF(J$4='Rent Roll'!$E$7+1,-'Rent Roll'!$C$7*Assumptions!$C$6*(1+Assumptions!$C$7)^(J$4-1)/12*'Rent Roll'!$I$7,0) -> 0 | K16: =IF(K$4='Rent Roll'!$E$7+1,-'Rent Roll'!$C$7*Assumptions!$C$6*(1+Assumptions!$C$7)^(K$4-1)/12*'Rent Roll'!$I$7,0) -> 0 | L16: =IF(L$4='Rent Roll'!$E$7+1,-'Rent Roll'!$C$7*Assumptions!$C$6*(1+Assumptions!$C$7)^(L$4-1)/12*'Rent Roll'!$I$7,0) -> 0 | ... O16: =IF(O$4='Rent Roll'!$E$7+1,-'Rent Roll'!$C$7*Assumptions!$C$6*(1+Assumptions!$C$7)^(O$4-1)/12*'Rent Roll'!$I$7,0) -> 0
B18: ='Rent Roll'!B8 -> Albion Insurance | C18: Rent | D18: 0 | E18: =IF(E$4<='Rent Roll'!$E$8,'Rent Roll'!$C$8*'Rent Roll'!$D$8,'Rent Roll'!$C$8*Assumptions!$C$6*(1+Assumptions!$C$7)^(E$4-1)*('Rent Roll'!$F$8+(1-'Rent Roll'!$F$8)*IF(E$4='Rent Roll'!$E$8+1,MAX(0,12-ROUND('Rent Roll'!$G$8,0))/12,1))) -> 2640000 | F18: =IF(F$4<='Rent Roll'!$E$8,'Rent Roll'!$C$8*'Rent Roll'!$D$8,'Rent Roll'!$C$8*Assumptions!$C$6*(1+Assumptions!$C$7)^(F$4-1)*('Rent Roll'!$F$8+(1-'Rent Roll'!$F$8)*IF(F$4='Rent Roll'!$E$8+1,MAX(0,12-ROUND('Rent Roll'!$G$8,0))/12,1))) -> 2640000 | G18: =IF(G$4<='Rent Roll'!$E$8,'Rent Roll'!$C$8*'Rent Roll'!$D$8,'Rent Roll'!$C$8*Assumptions!$C$6*(1+Assumptions!$C$7)^(G$4-1)*('Rent Roll'!$F$8+(1-'Rent Roll'!$F$8)*IF(G$4='Rent Roll'!$E$8+1,MAX(0,12-ROUND('Rent Roll'!$G$8,0))/12,1))) -> 2640000 | H18: =IF(H$4<='Rent Roll'!$E$8,'Rent Roll'!$C$8*'Rent Roll'!$D$8,'Rent Roll'!$C$8*Assumptions!$C$6*(1+Assumptions!$C$7)^(H$4-1)*('Rent Roll'!$F$8+(1-'Rent Roll'!$F$8)*IF(H$4='Rent Roll'!$E$8+1,MAX(0,12-ROUND('Rent Roll'!$G$8,0))/12,1))) -> 2640000 | I18: =IF(I$4<='Rent Roll'!$E$8,'Rent Roll'!$C$8*'Rent Roll'!$D$8,'Rent Roll'!$C$8*Assumptions!$C$6*(1+Assumptions!$C$7)^(I$4-1)*('Rent Roll'!$F$8+(1-'Rent Roll'!$F$8)*IF(I$4='Rent Roll'!$E$8+1,MAX(0,12-ROUND('Rent Roll'!$G$8,0))/12,1))) -> 2640000 | J18: =IF(J$4<='Rent Roll'!$E$8,'Rent Roll'!$C$8*'Rent Roll'!$D$8,'Rent Roll'!$C$8*Assumptions!$C$6*(1+Assumptions!$C$7)^(J$4-1)*('Rent Roll'!$F$8+(1-'Rent Roll'!$F$8)*IF(J$4='Rent Roll'!$E$8+1,MAX(0,12-ROUND('Rent Roll'!$G$8,0))/12,1))) -> 2640000 | K18: =IF(K$4<='Rent Roll'!$E$8,'Rent Roll'!$C$8*'Rent Roll'!$D$8,'Rent Roll'!$C$8*Assumptions!$C$6*(1+Assumptions!$C$7)^(K$4-1)*('Rent Roll'!$F$8+(1-'Rent Roll'!$F$8)*IF(K$4='Rent Roll'!$E$8+1,MAX(0,12-ROUND('Rent Roll'!$G$8,0))/12,1))) -> 2640000 | L18: =IF(L$4<='Rent Roll'!$E$8,'Rent Roll'!$C$8*'Rent Roll'!$D$8,'Rent Roll'!$C$8*Assumptions!$C$6*(1+Assumptions!$C$7)^(L$4-1)*('Rent Roll'!$F$8+(1-'Rent Roll'!$F$8)*IF(L$4='Rent Roll'!$E$8+1,MAX(0,12-ROUND('Rent Roll'!$G$8,0))/12,1))) -> 2640000 | ... O18: =IF(O$4<='Rent Roll'!$E$8,'Rent Roll'!$C$8*'Rent Roll'!$D$8,'Rent Roll'!$C$8*Assumptions!$C$6*(1+Assumptions!$C$7)^(O$4-1)*('Rent Roll'!$F$8+(1-'Rent Roll'!$F$8)*IF(O$4='Rent Roll'!$E$8+1,MAX(0,12-ROUND('Rent Roll'!$G$8,0))/12,1))) -> 3712245.2
C19: TI | D19: 0 | E19: =IF(E$4='Rent Roll'!$E$8+1,-'Rent Roll'!$C$8*'Rent Roll'!$H$8*(1-'Rent Roll'!$F$8*0.5),0) -> 0 | F19: =IF(F$4='Rent Roll'!$E$8+1,-'Rent Roll'!$C$8*'Rent Roll'!$H$8*(1-'Rent Roll'!$F$8*0.5),0) -> 0 | G19: =IF(G$4='Rent Roll'!$E$8+1,-'Rent Roll'!$C$8*'Rent Roll'!$H$8*(1-'Rent Roll'!$F$8*0.5),0) -> 0 | H19: =IF(H$4='Rent Roll'!$E$8+1,-'Rent Roll'!$C$8*'Rent Roll'!$H$8*(1-'Rent Roll'!$F$8*0.5),0) -> 0 | I19: =IF(I$4='Rent Roll'!$E$8+1,-'Rent Roll'!$C$8*'Rent Roll'!$H$8*(1-'Rent Roll'!$F$8*0.5),0) -> 0 | J19: =IF(J$4='Rent Roll'!$E$8+1,-'Rent Roll'!$C$8*'Rent Roll'!$H$8*(1-'Rent Roll'!$F$8*0.5),0) -> 0 | K19: =IF(K$4='Rent Roll'!$E$8+1,-'Rent Roll'!$C$8*'Rent Roll'!$H$8*(1-'Rent Roll'!$F$8*0.5),0) -> 0 | L19: =IF(L$4='Rent Roll'!$E$8+1,-'Rent Roll'!$C$8*'Rent Roll'!$H$8*(1-'Rent Roll'!$F$8*0.5),0) -> 0 | ... O19: =IF(O$4='Rent Roll'!$E$8+1,-'Rent Roll'!$C$8*'Rent Roll'!$H$8*(1-'Rent Roll'!$F$8*0.5),0) -> 0
C20: Leasing commission | D20: 0 | E20: =IF(E$4='Rent Roll'!$E$8+1,-'Rent Roll'!$C$8*Assumptions!$C$6*(1+Assumptions!$C$7)^(E$4-1)/12*'Rent Roll'!$I$8,0) -> 0 | F20: =IF(F$4='Rent Roll'!$E$8+1,-'Rent Roll'!$C$8*Assumptions!$C$6*(1+Assumptions!$C$7)^(F$4-1)/12*'Rent Roll'!$I$8,0) -> 0 | G20: =IF(G$4='Rent Roll'!$E$8+1,-'Rent Roll'!$C$8*Assumptions!$C$6*(1+Assumptions!$C$7)^(G$4-1)/12*'Rent Roll'!$I$8,0) -> 0 | H20: =IF(H$4='Rent Roll'!$E$8+1,-'Rent Roll'!$C$8*Assumptions!$C$6*(1+Assumptions!$C$7)^(H$4-1)/12*'Rent Roll'!$I$8,0) -> 0 | I20: =IF(I$4='Rent Roll'!$E$8+1,-'Rent Roll'!$C$8*Assumptions!$C$6*(1+Assumptions!$C$7)^(I$4-1)/12*'Rent Roll'!$I$8,0) -> 0 | J20: =IF(J$4='Rent Roll'!$E$8+1,-'Rent Roll'!$C$8*Assumptions!$C$6*(1+Assumptions!$C$7)^(J$4-1)/12*'Rent Roll'!$I$8,0) -> 0 | K20: =IF(K$4='Rent Roll'!$E$8+1,-'Rent Roll'!$C$8*Assumptions!$C$6*(1+Assumptions!$C$7)^(K$4-1)/12*'Rent Roll'!$I$8,0) -> 0 | L20: =IF(L$4='Rent Roll'!$E$8+1,-'Rent Roll'!$C$8*Assumptions!$C$6*(1+Assumptions!$C$7)^(L$4-1)/12*'Rent Roll'!$I$8,0) -> 0 | ... O20: =IF(O$4='Rent Roll'!$E$8+1,-'Rent Roll'!$C$8*Assumptions!$C$6*(1+Assumptions!$C$7)^(O$4-1)/12*'Rent Roll'!$I$8,0) -> 0
B22: ='Rent Roll'!B9 -> Quill & Co | C22: Rent | D22: 0 | E22: =IF(E$4<='Rent Roll'!$E$9,'Rent Roll'!$C$9*'Rent Roll'!$D$9,'Rent Roll'!$C$9*Assumptions!$C$6*(1+Assumptions!$C$7)^(E$4-1)*('Rent Roll'!$F$9+(1-'Rent Roll'!$F$9)*IF(E$4='Rent Roll'!$E$9+1,MAX(0,12-ROUND('Rent Roll'!$G$9,0))/12,1))) -> 703000 | F22: =IF(F$4<='Rent Roll'!$E$9,'Rent Roll'!$C$9*'Rent Roll'!$D$9,'Rent Roll'!$C$9*Assumptions!$C$6*(1+Assumptions!$C$7)^(F$4-1)*('Rent Roll'!$F$9+(1-'Rent Roll'!$F$9)*IF(F$4='Rent Roll'!$E$9+1,MAX(0,12-ROUND('Rent Roll'!$G$9,0))/12,1))) -> 703000 | G22: =IF(G$4<='Rent Roll'!$E$9,'Rent Roll'!$C$9*'Rent Roll'!$D$9,'Rent Roll'!$C$9*Assumptions!$C$6*(1+Assumptions!$C$7)^(G$4-1)*('Rent Roll'!$F$9+(1-'Rent Roll'!$F$9)*IF(G$4='Rent Roll'!$E$9+1,MAX(0,12-ROUND('Rent Roll'!$G$9,0))/12,1))) -> 703000 | H22: =IF(H$4<='Rent Roll'!$E$9,'Rent Roll'!$C$9*'Rent Roll'!$D$9,'Rent Roll'!$C$9*Assumptions!$C$6*(1+Assumptions!$C$7)^(H$4-1)*('Rent Roll'!$F$9+(1-'Rent Roll'!$F$9)*IF(H$4='Rent Roll'!$E$9+1,MAX(0,12-ROUND('Rent Roll'!$G$9,0))/12,1))) -> 703000 | I22: =IF(I$4<='Rent Roll'!$E$9,'Rent Roll'!$C$9*'Rent Roll'!$D$9,'Rent Roll'!$C$9*Assumptions!$C$6*(1+Assumptions!$C$7)^(I$4-1)*('Rent Roll'!$F$9+(1-'Rent Roll'!$F$9)*IF(I$4='Rent Roll'!$E$9+1,MAX(0,12-ROUND('Rent Roll'!$G$9,0))/12,1))) -> 703000 | J22: =IF(J$4<='Rent Roll'!$E$9,'Rent Roll'!$C$9*'Rent Roll'!$D$9,'Rent Roll'!$C$9*Assumptions!$C$6*(1+Assumptions!$C$7)^(J$4-1)*('Rent Roll'!$F$9+(1-'Rent Roll'!$F$9)*IF(J$4='Rent Roll'!$E$9+1,MAX(0,12-ROUND('Rent Roll'!$G$9,0))/12,1))) -> 703000 | K22: =IF(K$4<='Rent Roll'!$E$9,'Rent Roll'!$C$9*'Rent Roll'!$D$9,'Rent Roll'!$C$9*Assumptions!$C$6*(1+Assumptions!$C$7)^(K$4-1)*('Rent Roll'!$F$9+(1-'Rent Roll'!$F$9)*IF(K$4='Rent Roll'!$E$9+1,MAX(0,12-ROUND('Rent Roll'!$G$9,0))/12,1))) -> 638991.07 | L22: =IF(L$4<='Rent Roll'!$E$9,'Rent Roll'!$C$9*'Rent Roll'!$D$9,'Rent Roll'!$C$9*Assumptions!$C$6*(1+Assumptions!$C$7)^(L$4-1)*('Rent Roll'!$F$9+(1-'Rent Roll'!$F$9)*IF(L$4='Rent Roll'!$E$9+1,MAX(0,12-ROUND('Rent Roll'!$G$9,0))/12,1))) -> 818707.31 | ... O22: =IF(O$4<='Rent Roll'!$E$9,'Rent Roll'!$C$9*'Rent Roll'!$D$9,'Rent Roll'!$C$9*Assumptions!$C$6*(1+Assumptions!$C$7)^(O$4-1)*('Rent Roll'!$F$9+(1-'Rent Roll'!$F$9)*IF(O$4='Rent Roll'!$E$9+1,MAX(0,12-ROUND('Rent Roll'!$G$9,0))/12,1))) -> 881658.23
C23: TI | D23: 0 | E23: =IF(E$4='Rent Roll'!$E$9+1,-'Rent Roll'!$C$9*'Rent Roll'!$H$9*(1-'Rent Roll'!$F$9*0.5),0) -> 0 | F23: =IF(F$4='Rent Roll'!$E$9+1,-'Rent Roll'!$C$9*'Rent Roll'!$H$9*(1-'Rent Roll'!$F$9*0.5),0) -> 0 | G23: =IF(G$4='Rent Roll'!$E$9+1,-'Rent Roll'!$C$9*'Rent Roll'!$H$9*(1-'Rent Roll'!$F$9*0.5),0) -> 0 | H23: =IF(H$4='Rent Roll'!$E$9+1,-'Rent Roll'!$C$9*'Rent Roll'!$H$9*(1-'Rent Roll'!$F$9*0.5),0) -> 0 | I23: =IF(I$4='Rent Roll'!$E$9+1,-'Rent Roll'!$C$9*'Rent Roll'!$H$9*(1-'Rent Roll'!$F$9*0.5),0) -> 0 | J23: =IF(J$4='Rent Roll'!$E$9+1,-'Rent Roll'!$C$9*'Rent Roll'!$H$9*(1-'Rent Roll'!$F$9*0.5),0) -> 0 | K23: =IF(K$4='Rent Roll'!$E$9+1,-'Rent Roll'!$C$9*'Rent Roll'!$H$9*(1-'Rent Roll'!$F$9*0.5),0) -> -232750 | L23: =IF(L$4='Rent Roll'!$E$9+1,-'Rent Roll'!$C$9*'Rent Roll'!$H$9*(1-'Rent Roll'!$F$9*0.5),0) -> 0 | ... O23: =IF(O$4='Rent Roll'!$E$9+1,-'Rent Roll'!$C$9*'Rent Roll'!$H$9*(1-'Rent Roll'!$F$9*0.5),0) -> 0
C24: Leasing commission | D24: 0 | E24: =IF(E$4='Rent Roll'!$E$9+1,-'Rent Roll'!$C$9*Assumptions!$C$6*(1+Assumptions!$C$7)^(E$4-1)/12*'Rent Roll'!$I$9,0) -> 0 | F24: =IF(F$4='Rent Roll'!$E$9+1,-'Rent Roll'!$C$9*Assumptions!$C$6*(1+Assumptions!$C$7)^(F$4-1)/12*'Rent Roll'!$I$9,0) -> 0 | G24: =IF(G$4='Rent Roll'!$E$9+1,-'Rent Roll'!$C$9*Assumptions!$C$6*(1+Assumptions!$C$7)^(G$4-1)/12*'Rent Roll'!$I$9,0) -> 0 | H24: =IF(H$4='Rent Roll'!$E$9+1,-'Rent Roll'!$C$9*Assumptions!$C$6*(1+Assumptions!$C$7)^(H$4-1)/12*'Rent Roll'!$I$9,0) -> 0 | I24: =IF(I$4='Rent Roll'!$E$9+1,-'Rent Roll'!$C$9*Assumptions!$C$6*(1+Assumptions!$C$7)^(I$4-1)/12*'Rent Roll'!$I$9,0) -> 0 | J24: =IF(J$4='Rent Roll'!$E$9+1,-'Rent Roll'!$C$9*Assumptions!$C$6*(1+Assumptions!$C$7)^(J$4-1)/12*'Rent Roll'!$I$9,0) -> 0 | K24: =IF(K$4='Rent Roll'!$E$9+1,-'Rent Roll'!$C$9*Assumptions!$C$6*(1+Assumptions!$C$7)^(K$4-1)/12*'Rent Roll'!$I$9,0) -> -99842.355 | L24: =IF(L$4='Rent Roll'!$E$9+1,-'Rent Roll'!$C$9*Assumptions!$C$6*(1+Assumptions!$C$7)^(L$4-1)/12*'Rent Roll'!$I$9,0) -> 0 | ... O24: =IF(O$4='Rent Roll'!$E$9+1,-'Rent Roll'!$C$9*Assumptions!$C$6*(1+Assumptions!$C$7)^(O$4-1)/12*'Rent Roll'!$I$9,0) -> 0
B26: ='Rent Roll'!B10 -> Tessera Labs | C26: Rent | D26: 0 | E26: =IF(E$4<='Rent Roll'!$E$10,'Rent Roll'!$C$10*'Rent Roll'!$D$10,'Rent Roll'!$C$10*Assumptions!$C$6*(1+Assumptions!$C$7)^(E$4-1)*('Rent Roll'!$F$10+(1-'Rent Roll'!$F$10)*IF(E$4='Rent Roll'!$E$10+1,MAX(0,12-ROUND('Rent Roll'!$G$10,0))/12,1))) -> 854000 | F26: =IF(F$4<='Rent Roll'!$E$10,'Rent Roll'!$C$10*'Rent Roll'!$D$10,'Rent Roll'!$C$10*Assumptions!$C$6*(1+Assumptions!$C$7)^(F$4-1)*('Rent Roll'!$F$10+(1-'Rent Roll'!$F$10)*IF(F$4='Rent Roll'!$E$10+1,MAX(0,12-ROUND('Rent Roll'!$G$10,0))/12,1))) -> 854000 | G26: =IF(G$4<='Rent Roll'!$E$10,'Rent Roll'!$C$10*'Rent Roll'!$D$10,'Rent Roll'!$C$10*Assumptions!$C$6*(1+Assumptions!$C$7)^(G$4-1)*('Rent Roll'!$F$10+(1-'Rent Roll'!$F$10)*IF(G$4='Rent Roll'!$E$10+1,MAX(0,12-ROUND('Rent Roll'!$G$10,0))/12,1))) -> 854000 | H26: =IF(H$4<='Rent Roll'!$E$10,'Rent Roll'!$C$10*'Rent Roll'!$D$10,'Rent Roll'!$C$10*Assumptions!$C$6*(1+Assumptions!$C$7)^(H$4-1)*('Rent Roll'!$F$10+(1-'Rent Roll'!$F$10)*IF(H$4='Rent Roll'!$E$10+1,MAX(0,12-ROUND('Rent Roll'!$G$10,0))/12,1))) -> 854000 | I26: =IF(I$4<='Rent Roll'!$E$10,'Rent Roll'!$C$10*'Rent Roll'!$D$10,'Rent Roll'!$C$10*Assumptions!$C$6*(1+Assumptions!$C$7)^(I$4-1)*('Rent Roll'!$F$10+(1-'Rent Roll'!$F$10)*IF(I$4='Rent Roll'!$E$10+1,MAX(0,12-ROUND('Rent Roll'!$G$10,0))/12,1))) -> 742245.18 | J26: =IF(J$4<='Rent Roll'!$E$10,'Rent Roll'!$C$10*'Rent Roll'!$D$10,'Rent Roll'!$C$10*Assumptions!$C$6*(1+Assumptions!$C$7)^(J$4-1)*('Rent Roll'!$F$10+(1-'Rent Roll'!$F$10)*IF(J$4='Rent Roll'!$E$10+1,MAX(0,12-ROUND('Rent Roll'!$G$10,0))/12,1))) -> 1148379.3 | K26: =IF(K$4<='Rent Roll'!$E$10,'Rent Roll'!$C$10*'Rent Roll'!$D$10,'Rent Roll'!$C$10*Assumptions!$C$6*(1+Assumptions!$C$7)^(K$4-1)*('Rent Roll'!$F$10+(1-'Rent Roll'!$F$10)*IF(K$4='Rent Roll'!$E$10+1,MAX(0,12-ROUND('Rent Roll'!$G$10,0))/12,1))) -> 1177088.8 | L26: =IF(L$4<='Rent Roll'!$E$10,'Rent Roll'!$C$10*'Rent Roll'!$D$10,'Rent Roll'!$C$10*Assumptions!$C$6*(1+Assumptions!$C$7)^(L$4-1)*('Rent Roll'!$F$10+(1-'Rent Roll'!$F$10)*IF(L$4='Rent Roll'!$E$10+1,MAX(0,12-ROUND('Rent Roll'!$G$10,0))/12,1))) -> 1206516 | ... O26: =IF(O$4<='Rent Roll'!$E$10,'Rent Roll'!$C$10*'Rent Roll'!$D$10,'Rent Roll'!$C$10*Assumptions!$C$6*(1+Assumptions!$C$7)^(O$4-1)*('Rent Roll'!$F$10+(1-'Rent Roll'!$F$10)*IF(O$4='Rent Roll'!$E$10+1,MAX(0,12-ROUND('Rent Roll'!$G$10,0))/12,1))) -> 1299285.8
C27: TI | D27: 0 | E27: =IF(E$4='Rent Roll'!$E$10+1,-'Rent Roll'!$C$10*'Rent Roll'!$H$10*(1-'Rent Roll'!$F$10*0.5),0) -> 0 | F27: =IF(F$4='Rent Roll'!$E$10+1,-'Rent Roll'!$C$10*'Rent Roll'!$H$10*(1-'Rent Roll'!$F$10*0.5),0) -> 0 | G27: =IF(G$4='Rent Roll'!$E$10+1,-'Rent Roll'!$C$10*'Rent Roll'!$H$10*(1-'Rent Roll'!$F$10*0.5),0) -> 0 | H27: =IF(H$4='Rent Roll'!$E$10+1,-'Rent Roll'!$C$10*'Rent Roll'!$H$10*(1-'Rent Roll'!$F$10*0.5),0) -> 0 | I27: =IF(I$4='Rent Roll'!$E$10+1,-'Rent Roll'!$C$10*'Rent Roll'!$H$10*(1-'Rent Roll'!$F$10*0.5),0) -> -507500 | J27: =IF(J$4='Rent Roll'!$E$10+1,-'Rent Roll'!$C$10*'Rent Roll'!$H$10*(1-'Rent Roll'!$F$10*0.5),0) -> 0 | K27: =IF(K$4='Rent Roll'!$E$10+1,-'Rent Roll'!$C$10*'Rent Roll'!$H$10*(1-'Rent Roll'!$F$10*0.5),0) -> 0 | L27: =IF(L$4='Rent Roll'!$E$10+1,-'Rent Roll'!$C$10*'Rent Roll'!$H$10*(1-'Rent Roll'!$F$10*0.5),0) -> 0 | ... O27: =IF(O$4='Rent Roll'!$E$10+1,-'Rent Roll'!$C$10*'Rent Roll'!$H$10*(1-'Rent Roll'!$F$10*0.5),0) -> 0
C28: Leasing commission | D28: 0 | E28: =IF(E$4='Rent Roll'!$E$10+1,-'Rent Roll'!$C$10*Assumptions!$C$6*(1+Assumptions!$C$7)^(E$4-1)/12*'Rent Roll'!$I$10,0) -> 0 | F28: =IF(F$4='Rent Roll'!$E$10+1,-'Rent Roll'!$C$10*Assumptions!$C$6*(1+Assumptions!$C$7)^(F$4-1)/12*'Rent Roll'!$I$10,0) -> 0 | G28: =IF(G$4='Rent Roll'!$E$10+1,-'Rent Roll'!$C$10*Assumptions!$C$6*(1+Assumptions!$C$7)^(G$4-1)/12*'Rent Roll'!$I$10,0) -> 0 | H28: =IF(H$4='Rent Roll'!$E$10+1,-'Rent Roll'!$C$10*Assumptions!$C$6*(1+Assumptions!$C$7)^(H$4-1)/12*'Rent Roll'!$I$10,0) -> 0 | I28: =IF(I$4='Rent Roll'!$E$10+1,-'Rent Roll'!$C$10*Assumptions!$C$6*(1+Assumptions!$C$7)^(I$4-1)/12*'Rent Roll'!$I$10,0) -> -186728.35 | J28: =IF(J$4='Rent Roll'!$E$10+1,-'Rent Roll'!$C$10*Assumptions!$C$6*(1+Assumptions!$C$7)^(J$4-1)/12*'Rent Roll'!$I$10,0) -> 0 | K28: =IF(K$4='Rent Roll'!$E$10+1,-'Rent Roll'!$C$10*Assumptions!$C$6*(1+Assumptions!$C$7)^(K$4-1)/12*'Rent Roll'!$I$10,0) -> 0 | L28: =IF(L$4='Rent Roll'!$E$10+1,-'Rent Roll'!$C$10*Assumptions!$C$6*(1+Assumptions!$C$7)^(L$4-1)/12*'Rent Roll'!$I$10,0) -> 0 | ... O28: =IF(O$4='Rent Roll'!$E$10+1,-'Rent Roll'!$C$10*Assumptions!$C$6*(1+Assumptions!$C$7)^(O$4-1)/12*'Rent Roll'!$I$10,0) -> 0

Sheet Cash Flow
B2: CASH FLOW (GBP)
B4: Year | D4: 0 | E4: 1 | F4: 2 | G4: 3 | H4: 4 | I4: 5 | J4: 6 | K4: 7 | L4: 8 | M4: 9 | N4: 10 | O4: 11
B6: Gross rent | D6: ='Tenant CF'!D6+'Tenant CF'!D10+'Tenant CF'!D14+'Tenant CF'!D18+'Tenant CF'!D22+'Tenant CF'!D26 -> 0 | E6: ='Tenant CF'!E6+'Tenant CF'!E10+'Tenant CF'!E14+'Tenant CF'!E18+'Tenant CF'!E22+'Tenant CF'!E26 -> 8803000 | F6: ='Tenant CF'!F6+'Tenant CF'!F10+'Tenant CF'!F14+'Tenant CF'!F18+'Tenant CF'!F22+'Tenant CF'!F26 -> 8803000 | G6: ='Tenant CF'!G6+'Tenant CF'!G10+'Tenant CF'!G14+'Tenant CF'!G18+'Tenant CF'!G22+'Tenant CF'!G26 -> 8435532.8 | H6: ='Tenant CF'!H6+'Tenant CF'!H10+'Tenant CF'!H14+'Tenant CF'!H18+'Tenant CF'!H22+'Tenant CF'!H26 -> 8949902.1 | I6: ='Tenant CF'!I6+'Tenant CF'!I10+'Tenant CF'!I14+'Tenant CF'!I18+'Tenant CF'!I22+'Tenant CF'!I26 -> 9591566.9 | J6: ='Tenant CF'!J6+'Tenant CF'!J10+'Tenant CF'!J14+'Tenant CF'!J18+'Tenant CF'!J22+'Tenant CF'!J26 -> 10091779 | K6: ='Tenant CF'!K6+'Tenant CF'!K10+'Tenant CF'!K14+'Tenant CF'!K18+'Tenant CF'!K22+'Tenant CF'!K26 -> 10467641 | ... O6: ='Tenant CF'!O6+'Tenant CF'!O10+'Tenant CF'!O14+'Tenant CF'!O18+'Tenant CF'!O22+'Tenant CF'!O26 -> 12528827
B7: Non-recoverable costs | D7: =-D6*Assumptions!$C$8 -> 0 | E7: =-E6*Assumptions!$C$8 -> -308105 | F7: =-F6*Assumptions!$C$8 -> -308105 | G7: =-G6*Assumptions!$C$8 -> -295243.65 | H7: =-H6*Assumptions!$C$8 -> -313246.57 | I7: =-I6*Assumptions!$C$8 -> -335704.84 | J7: =-J6*Assumptions!$C$8 -> -353212.27 | K7: =-K6*Assumptions!$C$8 -> -366367.42 | ... O7: =-O6*Assumptions!$C$8 -> -438508.96
B8: Net operating income | D8: =D6+D7 -> 0 | E8: =E6+E7 -> 8494895 | F8: =F6+F7 -> 8494895 | G8: =G6+G7 -> 8140289.2 | H8: =H6+H7 -> 8636655.6 | I8: =I6+I7 -> 9255862.1 | J8: =J6+J7 -> 9738567 | K8: =K6+K7 -> 10101273 | ... O8: =O6+O7 -> 12090319
B9: TI and leasing costs | D9: ='Tenant CF'!D7+'Tenant CF'!D11+'Tenant CF'!D15+'Tenant CF'!D19+'Tenant CF'!D23+'Tenant CF'!D27+'Tenant CF'!D8+'Tenant CF'!D12+'Tenant CF'!D16+'Tenant CF'!D20+'Tenant CF'!D24+'Tenant CF'!D28 -> 0 | E9: ='Tenant CF'!E7+'Tenant CF'!E11+'Tenant CF'!E15+'Tenant CF'!E19+'Tenant CF'!E23+'Tenant CF'!E27+'Tenant CF'!E8+'Tenant CF'!E12+'Tenant CF'!E16+'Tenant CF'!E20+'Tenant CF'!E24+'Tenant CF'!E28 -> 0 | F9: ='Tenant CF'!F7+'Tenant CF'!F11+'Tenant CF'!F15+'Tenant CF'!F19+'Tenant CF'!F23+'Tenant CF'!F27+'Tenant CF'!F8+'Tenant CF'!F12+'Tenant CF'!F16+'Tenant CF'!F20+'Tenant CF'!F24+'Tenant CF'!F28 -> 0 | G9: ='Tenant CF'!G7+'Tenant CF'!G11+'Tenant CF'!G15+'Tenant CF'!G19+'Tenant CF'!G23+'Tenant CF'!G27+'Tenant CF'!G8+'Tenant CF'!G12+'Tenant CF'!G16+'Tenant CF'!G20+'Tenant CF'!G24+'Tenant CF'!G28 -> -960638.67 | H9: ='Tenant CF'!H7+'Tenant CF'!H11+'Tenant CF'!H15+'Tenant CF'!H19+'Tenant CF'!H23+'Tenant CF'!H27+'Tenant CF'!H8+'Tenant CF'!H12+'Tenant CF'!H16+'Tenant CF'!H20+'Tenant CF'!H24+'Tenant CF'!H28 -> -1388397.7 | I9: ='Tenant CF'!I7+'Tenant CF'!I11+'Tenant CF'!I15+'Tenant CF'!I19+'Tenant CF'!I23+'Tenant CF'!I27+'Tenant CF'!I8+'Tenant CF'!I12+'Tenant CF'!I16+'Tenant CF'!I20+'Tenant CF'!I24+'Tenant CF'!I28 -> -694228.35 | J9: ='Tenant CF'!J7+'Tenant CF'!J11+'Tenant CF'!J15+'Tenant CF'!J19+'Tenant CF'!J23+'Tenant CF'!J27+'Tenant CF'!J8+'Tenant CF'!J12+'Tenant CF'!J16+'Tenant CF'!J20+'Tenant CF'!J24+'Tenant CF'!J28 -> -852930.43 | K9: ='Tenant CF'!K7+'Tenant CF'!K11+'Tenant CF'!K15+'Tenant CF'!K19+'Tenant CF'!K23+'Tenant CF'!K27+'Tenant CF'!K8+'Tenant CF'!K12+'Tenant CF'!K16+'Tenant CF'!K20+'Tenant CF'!K24+'Tenant CF'!K28 -> -332592.36 | ... O9: ='Tenant CF'!O7+'Tenant CF'!O11+'Tenant CF'!O15+'Tenant CF'!O19+'Tenant CF'!O23+'Tenant CF'!O27+'Tenant CF'!O8+'Tenant CF'!O12+'Tenant CF'!O16+'Tenant CF'!O20+'Tenant CF'!O24+'Tenant CF'!O28 -> 0
B10: Purchase | D10: =IF(D$4=0,-Assumptions!$C$4*(1+Assumptions!$C$5),0) -> -160200000 | E10: =IF(E$4=0,-Assumptions!$C$4*(1+Assumptions!$C$5),0) -> 0 | F10: =IF(F$4=0,-Assumptions!$C$4*(1+Assumptions!$C$5),0) -> 0 | G10: =IF(G$4=0,-Assumptions!$C$4*(1+Assumptions!$C$5),0) -> 0 | H10: =IF(H$4=0,-Assumptions!$C$4*(1+Assumptions!$C$5),0) -> 0 | I10: =IF(I$4=0,-Assumptions!$C$4*(1+Assumptions!$C$5),0) -> 0 | J10: =IF(J$4=0,-Assumptions!$C$4*(1+Assumptions!$C$5),0) -> 0 | K10: =IF(K$4=0,-Assumptions!$C$4*(1+Assumptions!$C$5),0) -> 0 | ... O10: =IF(O$4=0,-Assumptions!$C$4*(1+Assumptions!$C$5),0) -> 0
B11: Sale (net) | D11: =IF(D$4=ROUND(Assumptions!$C$11,0),E8/Assumptions!$C$9*(1-Assumptions!$C$10),0) -> 0 | E11: =IF(E$4=ROUND(Assumptions!$C$11,0),F8/Assumptions!$C$9*(1-Assumptions!$C$10),0) -> 0 | F11: =IF(F$4=ROUND(Assumptions!$C$11,0),G8/Assumptions!$C$9*(1-Assumptions!$C$10),0) -> 0 | G11: =IF(G$4=ROUND(Assumptions!$C$11,0),H8/Assumptions!$C$9*(1-Assumptions!$C$10),0) -> 0 | H11: =IF(H$4=ROUND(Assumptions!$C$11,0),I8/Assumptions!$C$9*(1-Assumptions!$C$10),0) -> 0 | I11: =IF(I$4=ROUND(Assumptions!$C$11,0),J8/Assumptions!$C$9*(1-Assumptions!$C$10),0) -> 0 | J11: =IF(J$4=ROUND(Assumptions!$C$11,0),K8/Assumptions!$C$9*(1-Assumptions!$C$10),0) -> 0 | K11: =IF(K$4=ROUND(Assumptions!$C$11,0),L8/Assumptions!$C$9*(1-Assumptions!$C$10),0) -> 0 | ... N11: =IF(N$4=ROUND(Assumptions!$C$11,0),O8/Assumptions!$C$9*(1-Assumptions!$C$10),0) -> 2.268374e+08 | O11: =0 -> 0
B12: Ungeared cash flow | D12: =IF(D$4>ROUND(Assumptions!$C$11,0),0,SUM(D8:D11)) -> -160200000 | E12: =IF(E$4>ROUND(Assumptions!$C$11,0),0,SUM(E8:E11)) -> 8494895 | F12: =IF(F$4>ROUND(Assumptions!$C$11,0),0,SUM(F8:F11)) -> 8494895 | G12: =IF(G$4>ROUND(Assumptions!$C$11,0),0,SUM(G8:G11)) -> 7179650.5 | H12: =IF(H$4>ROUND(Assumptions!$C$11,0),0,SUM(H8:H11)) -> 7248257.8 | I12: =IF(I$4>ROUND(Assumptions!$C$11,0),0,SUM(I8:I11)) -> 8561633.7 | J12: =IF(J$4>ROUND(Assumptions!$C$11,0),0,SUM(J8:J11)) -> 8885636.6 | K12: =IF(K$4>ROUND(Assumptions!$C$11,0),0,SUM(K8:K11)) -> 9768680.9 | ... O12: =IF(O$4>ROUND(Assumptions!$C$11,0),0,SUM(O8:O11)) -> 0
B14: Loan | D14: =IF(D$4=0,Assumptions!$C$4*Assumptions!$C$12*(1-Assumptions!$C$14),0) -> 74250000 | E14: =IF(E$4=0,Assumptions!$C$4*Assumptions!$C$12*(1-Assumptions!$C$14),0) -> 0 | F14: =IF(F$4=0,Assumptions!$C$4*Assumptions!$C$12*(1-Assumptions!$C$14),0) -> 0 | G14: =IF(G$4=0,Assumptions!$C$4*Assumptions!$C$12*(1-Assumptions!$C$14),0) -> 0 | H14: =IF(H$4=0,Assumptions!$C$4*Assumptions!$C$12*(1-Assumptions!$C$14),0) -> 0 | I14: =IF(I$4=0,Assumptions!$C$4*Assumptions!$C$12*(1-Assumptions!$C$14),0) -> 0 | J14: =IF(J$4=0,Assumptions!$C$4*Assumptions!$C$12*(1-Assumptions!$C$14),0) -> 0 | K14: =IF(K$4=0,Assumptions!$C$4*Assumptions!$C$12*(1-Assumptions!$C$14),0) -> 0 | ... O14: =IF(O$4=0,Assumptions!$C$4*Assumptions!$C$12*(1-Assumptions!$C$14),0) -> 0
B15: Interest | D15: =IF(AND(D$4>=1,D$4<=ROUND(Assumptions!$C$11,0)),-Assumptions!$C$4*Assumptions!$C$12*Assumptions!$C$13,0) -> 0 | E15: =IF(AND(E$4>=1,E$4<=ROUND(Assumptions!$C$11,0)),-Assumptions!$C$4*Assumptions!$C$12*Assumptions!$C$13,0) -> -4350000 | F15: =IF(AND(F$4>=1,F$4<=ROUND(Assumptions!$C$11,0)),-Assumptions!$C$4*Assumptions!$C$12*Assumptions!$C$13,0) -> -4350000 | G15: =IF(AND(G$4>=1,G$4<=ROUND(Assumptions!$C$11,0)),-Assumptions!$C$4*Assumptions!$C$12*Assumptions!$C$13,0) -> -4350000 | H15: =IF(AND(H$4>=1,H$4<=ROUND(Assumptions!$C$11,0)),-Assumptions!$C$4*Assumptions!$C$12*Assumptions!$C$13,0) -> -4350000 | I15: =IF(AND(I$4>=1,I$4<=ROUND(Assumptions!$C$11,0)),-Assumptions!$C$4*Assumptions!$C$12*Assumptions!$C$13,0) -> -4350000 | J15: =IF(AND(J$4>=1,J$4<=ROUND(Assumptions!$C$11,0)),-Assumptions!$C$4*Assumptions!$C$12*Assumptions!$C$13,0) -> -4350000 | K15: =IF(AND(K$4>=1,K$4<=ROUND(Assumptions!$C$11,0)),-Assumptions!$C$4*Assumptions!$C$12*Assumptions!$C$13,0) -> -4350000 | ... O15: =IF(AND(O$4>=1,O$4<=ROUND(Assumptions!$C$11,0)),-Assumptions!$C$4*Assumptions!$C$12*Assumptions!$C$13,0) -> 0
B16: Repayment | D16: =IF(D$4=ROUND(Assumptions!$C$11,0),-Assumptions!$C$4*Assumptions!$C$12,0) -> 0 | E16: =IF(E$4=ROUND(Assumptions!$C$11,0),-Assumptions!$C$4*Assumptions!$C$12,0) -> 0 | F16: =IF(F$4=ROUND(Assumptions!$C$11,0),-Assumptions!$C$4*Assumptions!$C$12,0) -> 0 | G16: =IF(G$4=ROUND(Assumptions!$C$11,0),-Assumptions!$C$4*Assumptions!$C$12,0) -> 0 | H16: =IF(H$4=ROUND(Assumptions!$C$11,0),-Assumptions!$C$4*Assumptions!$C$12,0) -> 0 | I16: =IF(I$4=ROUND(Assumptions!$C$11,0),-Assumptions!$C$4*Assumptions!$C$12,0) -> 0 | J16: =IF(J$4=ROUND(Assumptions!$C$11,0),-Assumptions!$C$4*Assumptions!$C$12,0) -> 0 | K16: =IF(K$4=ROUND(Assumptions!$C$11,0),-Assumptions!$C$4*Assumptions!$C$12,0) -> 0 | ... O16: =IF(O$4=ROUND(Assumptions!$C$11,0),-Assumptions!$C$4*Assumptions!$C$12,0) -> 0
B17: Geared cash flow | D17: =D12+D14+D15+D16 -> -85950000 | E17: =E12+E14+E15+E16 -> 4144895 | F17: =F12+F14+F15+F16 -> 4144895 | G17: =G12+G14+G15+G16 -> 2829650.5 | H17: =H12+H14+H15+H16 -> 2898257.8 | I17: =I12+I14+I15+I16 -> 4211633.7 | J17: =J12+J14+J15+J16 -> 4535636.6 | K17: =K12+K14+K15+K16 -> 5418680.9 | ... O17: =O12+O14+O15+O16 -> 0
