Workbook

Sheet Inputs
A1: SAHAB OFFICES – SHAPES (SAR)
A2: GFA | B2: 50000
A3: NLA | B3: 40000
A4: Years | B4: 10
A5: Rent per sqm | B5: 1200
A6: Exit yield | B6: 0.07
A7: Cost per sqm GFA | B7: 4000

Sheet Cash Flow
A1: Period | B1: 1 | C1: 2 | D1: 3 | E1: 4 | F1: 5 | G1: 6 | H1: 7 | I1: 8 | J1: 9 | K1: 10 | L1: 11 | M1: 12
A2: Occupancy | B2: 0 | C2: 0 | D2: 0 | E2: 0 | F2: 0 | G2: 0 | H2: 0 | I2: 0 | J2: 0 | K2: 0.6 | L2: 0.9 | M2: 0.95
A3: Rent | B3: =Inputs!$B$3*Inputs!$B$5*B2 | C3: =Inputs!$B$3*Inputs!$B$5*C2 | D3: =Inputs!$B$3*Inputs!$B$5*D2 | E3: =Inputs!$B$3*Inputs!$B$5*E2 | F3: =Inputs!$B$3*Inputs!$B$5*F2 | G3: =Inputs!$B$3*Inputs!$B$5*G2 | H3: =Inputs!$B$3*Inputs!$B$5*H2 | I3: =Inputs!$B$3*Inputs!$B$5*I2 | ... M3: =Inputs!$B$3*Inputs!$B$5*M2
A4: Cost | B4: =-Inputs!$B$2*Inputs!$B$7/3 | C4: =-Inputs!$B$2*Inputs!$B$7/3 | D4: =-Inputs!$B$2*Inputs!$B$7/3 | E4: 0 | F4: 0 | G4: 0 | H4: 0 | I4: 0 | J4: 0 | K4: 0 | L4: 0 | M4: 0
A5: Exit | B5: =IF(B1=12,B3/Inputs!$B$6,0) | C5: =IF(C1=12,C3/Inputs!$B$6,0) | D5: =IF(D1=12,D3/Inputs!$B$6,0) | E5: =IF(E1=12,E3/Inputs!$B$6,0) | F5: =IF(F1=12,F3/Inputs!$B$6,0) | G5: =IF(G1=12,G3/Inputs!$B$6,0) | H5: =IF(H1=12,H3/Inputs!$B$6,0) | I5: =IF(I1=12,I3/Inputs!$B$6,0) | ... M5: =IF(M1=12,M3/Inputs!$B$6,0)
A6: Net cash flow | B6: =B3+B4+B5 | C6: =C3+C4+C5 | D6: =D3+D4+D5 | E6: =E3+E4+E5 | F6: =F3+F4+F5 | G6: =G3+G4+G5 | H6: =H3+H4+H5 | I6: =I3+I4+I5 | ... M6: =M3+M4+M5
A7: Fee to partner | B7: -100000 | C7: -100000 | D7: -100000 | E7: -100000 | F7: -100000 | G7: -100000 | H7: -100000 | I7: -100000 | J7: -100000 | K7: -100000 | L7: -100000 | M7: -100000

Sheet Returns
A1: Unlevered IRR | B1: =IRR('Cash Flow'!B6:M6)
A2: Levered IRR | B2: =IRR('Cash Flow'!B7:M7)
A3: Net profit | B3: =SUM('Cash Flow'!B6:M6)
