Workbook

Sheet Inputs
A1: LONG LEASE – 50 YEARS MONTHLY (USD)
A2: Price | B2: 100000000
A3: Rent a month | B3: 600000
A4: Rent growth a year | B4: 0.02
A5: Exit yield | B5: 0.05

Sheet Hidden
A1: Management fee share | B1: 0.03

Sheet Cash Flow
A1: Month | B1: 0 | C1: 1 | D1: 2 | E1: 3 | F1: 4 | G1: 5 | H1: 6 | I1: 7 | J1: 8 | K1: 9 | L1: 10 | M1: 11 | N1: 12 | O1: 13 | P1: 14 | Q1: 15 | R1: 16 | S1: 17 | T1: 18 | U1: 19 | V1: 20 | W1: 21 | X1: 22 | Y1: 23 | Z1: 24 | AA1: 25 | AB1: 26 | AC1: 27 | AD1: 28 | AE1: 29 | AF1: 30 | AG1: 31 | AH1: 32 | AI1: 33 | AJ1: 34 | AK1: 35 | AL1: 36 | AM1: 37 | AN1: 38 | AO1: 39 | AP1: 40 | AQ1: 41 | AR1: 42 | AS1: 43 | AT1: 44 | AU1: 45 | AV1: 46 | AW1: 47 | AX1: 48 | AY1: 49 | AZ1: 50 | BA1: 51 | BB1: 52 | BC1: 53 | BD1: 54 | BE1: 55 | BF1: 56 | BG1: 57 | BH1: 58 | BI1: 59 | BJ1: 60 | BK1: 61 | BL1: 62 | BM1: 63 | BN1: 64 | BO1: 65 | BP1: 66 | BQ1: 67 | BR1: 68 | BS1: 69 | BT1: 70 | BU1: 71 | BV1: 72 | BW1: 73 | BX1: 74 | BY1: 75 | BZ1: 76 | CA1: 77 | CB1: 78 | CC1: 79 | CD1: 80 | CE1: 81 | CF1: 82 | CG1: 83 | CH1: 84 | CI1: 85 | CJ1: 86 | CK1: 87 | CL1: 88 | CM1: 89 | CN1: 90 | CO1: 91 | CP1: 92 | CQ1: 93 | CR1: 94 | CS1: 95 | CT1: 96 | CU1: 97 | CV1: 98 | CW1: 99 | CX1: 100 | CY1: 101 | CZ1: 102 | DA1: 103 | DB1: 104 | DC1: 105 | DD1: 106 | DE1: 107 | DF1: 108 | DG1: 109 | DH1: 110 | DI1: 111 | DJ1: 112 | DK1: 113 | DL1: 114 | DM1: 115 | DN1: 116 | DO1: 117 | DP1: 118 | DQ1: 119 | DR1: 120 | DS1: 121 | DT1: 122 | DU1: 123 | DV1: 124 | DW1: 125 | DX1: 126 | DY1: 127 | DZ1: 128 | EA1: 129 | EB1: 130 | EC1: 131 | ED1: 132 | EE1: 133 | EF1: 134 | EG1: 135 | EH1: 136 | EI1: 137 | EJ1: 138 | EK1: 139 | EL1: 140 | EM1: 141 | EN1: 142 | EO1: 143 | EP1: 144 | EQ1: 145 | ER1: 146 | ES1: 147 | ET1: 148 | EU1: 149 | EV1: 150 | EW1: 151 | EX1: 152 | EY1: 153 | EZ1: 154 | FA1: 155 | FB1: 156 | FC1: 157 | FD1: 158 | FE1: 159 | FF1: 160 | FG1: 161 | FH1: 162 | FI1: 163 | FJ1: 164 | FK1: 165 | FL1: 166 | FM1: 167 | FN1: 168 | FO1: 169 | FP1: 170 | FQ1: 171 | FR1: 172 | FS1: 173 | FT1: 174 | FU1: 175 | FV1: 176 | FW1: 177 | FX1: 178 | FY1: 179 | FZ1: 180 | GA1: 181 | GB1: 182 | GC1: 183 | GD1: 184 | GE1: 185 | GF1: 186 | GG1: 187 | GH1: 188 | GI1: 189 | GJ1: 190 | GK1: 191 | GL1: 192 | GM1: 193 | GN1: 194 | GO1: 195 | GP1: 196 | GQ1: 197 | GR1: 198 | GS1: 199 | GT1: 200 | GU1: 201 | GV1: 202 | GW1: 203 | GX1: 204 | GY1: 205 | GZ1: 206 | HA1: 207 | HB1: 208 | HC1: 209 | HD1: 210 | HE1: 211 | HF1: 212 | HG1: 213 | HH1: 214 | HI1: 215 | HJ1: 216 | HK1: 217 | HL1: 218 | HM1: 219 | HN1: 220 | HO1: 221 | HP1: 222 | HQ1: 223 | HR1: 224 | HS1: 225 | HT1: 226 | HU1: 227 | HV1: 228 | HW1: 229 | HX1: 230 | HY1: 231 | HZ1: 232 | IA1: 233 | IB1: 234 | IC1: 235 | ID1: 236 | IE1: 237 | IF1: 238 | IG1: 239 | IH1: 240 | II1: 241 | IJ1: 242 | IK1: 243 | IL1: 244 | IM1: 245 | IN1: 246 | IO1: 247 | IP1: 248 | IQ1: 249 | IR1: 250 | IS1: 251 | IT1: 252 | IU1: 253 | IV1: 254 | IW1: 255 | IX1: 256 | IY1: 257 | IZ1: 258 | JA1: 259 | JB1: 260 | JC1: 261 | JD1: 262 | JE1: 263 | JF1: 264 | JG1: 265 | JH1: 266 | JI1: 267 | JJ1: 268 | JK1: 269 | JL1: 270 | JM1: 271 | JN1: 272 | JO1: 273 | JP1: 274 | JQ1: 275 | JR1: 276 | JS1: 277 | JT1: 278 | JU1: 279 | JV1: 280 | JW1: 281 | JX1: 282 | JY1: 283 | JZ1: 284 | KA1: 285 | KB1: 286 | KC1: 287 | KD1: 288 | KE1: 289 | KF1: 290 | KG1: 291 | KH1: 292 | KI1: 293 | KJ1: 294 | KK1: 295 | KL1: 296 | KM1: 297 | KN1: 298 | KO1: 299 | KP1: 300 | KQ1: 301 | KR1: 302 | KS1: 303 | KT1: 304 | KU1: 305 | KV1: 306 | KW1: 307 | KX1: 308 | KY1: 309 | KZ1: 310 | LA1: 311 | LB1: 312 | LC1: 313 | LD1: 314 | LE1: 315 | LF1: 316 | LG1: 317 | LH1: 318 | LI1: 319 | LJ1: 320 | LK1: 321 | LL1: 322 | LM1: 323 | LN1: 324 | LO1: 325 | LP1: 326 | LQ1: 327 | LR1: 328 | LS1: 329 | LT1: 330 | LU1: 331 | LV1: 332 | LW1: 333 | LX1: 334 | LY1: 335 | LZ1: 336 | MA1: 337 | MB1: 338 | MC1: 339 | MD1: 340 | ME1: 341 | MF1: 342 | MG1: 343 | MH1: 344 | MI1: 345 | MJ1: 346 | MK1: 347 | ML1: 348 | MM1: 349 | MN1: 350 | MO1: 351 | MP1: 352 | MQ1: 353 | MR1: 354 | MS1: 355 | MT1: 356 | MU1: 357 | MV1: 358 | MW1: 359 | MX1: 360 | MY1: 361 | MZ1: 362 | NA1: 363 | NB1: 364 | NC1: 365 | ND1: 366 | NE1: 367 | NF1: 368 | NG1: 369 | NH1: 370 | NI1: 371 | NJ1: 372 | NK1: 373 | NL1: 374 | NM1: 375 | NN1: 376 | NO1: 377 | NP1: 378 | NQ1: 379 | NR1: 380 | NS1: 381 | NT1: 382 | NU1: 383 | NV1: 384 | NW1: 385 | NX1: 386 | NY1: 387 | NZ1: 388 | OA1: 389 | OB1: 390 | OC1: 391 | OD1: 392 | OE1: 393 | OF1: 394 | OG1: 395 | OH1: 396 | OI1: 397 | OJ1: 398 | OK1: 399 | OL1: 400 | OM1: 401 | ON1: 402 | OO1: 403 | OP1: 404 | OQ1: 405 | OR1: 406 | OS1: 407 | OT1: 408 | OU1: 409 | OV1: 410 | OW1: 411 | OX1: 412 | OY1: 413 | OZ1: 414 | PA1: 415 | PB1: 416 | PC1: 417 | PD1: 418 | PE1: 419 | PF1: 420 | PG1: 421 | PH1: 422 | PI1: 423 | PJ1: 424 | PK1: 425 | PL1: 426 | PM1: 427 | PN1: 428 | PO1: 429 | PP1: 430 | PQ1: 431 | PR1: 432 | PS1: 433 | PT1: 434 | PU1: 435 | PV1: 436 | PW1: 437 | PX1: 438 | PY1: 439 | PZ1: 440 | QA1: 441 | QB1: 442 | QC1: 443 | QD1: 444 | QE1: 445 | QF1: 446 | QG1: 447 | QH1: 448 | QI1: 449 | QJ1: 450 | QK1: 451 | QL1: 452 | QM1: 453 | QN1: 454 | QO1: 455 | QP1: 456 | QQ1: 457 | QR1: 458 | QS1: 459 | QT1: 460 | QU1: 461 | QV1: 462 | QW1: 463 | QX1: 464 | QY1: 465 | QZ1: 466 | RA1: 467 | RB1: 468 | RC1: 469 | RD1: 470 | RE1: 471 | RF1: 472 | RG1: 473 | RH1: 474 | RI1: 475 | RJ1: 476 | RK1: 477 | RL1: 478 | RM1: 479 | RN1: 480 | RO1: 481 | RP1: 482 | RQ1: 483 | RR1: 484 | RS1: 485 | RT1: 486 | RU1: 487 | RV1: 488 | RW1: 489 | RX1: 490 | RY1: 491 | RZ1: 492 | SA1: 493 | SB1: 494 | SC1: 495 | SD1: 496 | SE1: 497 | SF1: 498 | SG1: 499 | SH1: 500 | SI1: 501 | SJ1: 502 | SK1: 503 | SL1: 504 | SM1: 505 | SN1: 506 | SO1: 507 | SP1: 508 | SQ1: 509 | SR1: 510 | SS1: 511 | ST1: 512 | SU1: 513 | SV1: 514 | SW1: 515 | SX1: 516 | SY1: 517 | SZ1: 518 | TA1: 519 | TB1: 520 | TC1: 521 | TD1: 522 | TE1: 523 | TF1: 524 | TG1: 525 | TH1: 526 | TI1: 527 | TJ1: 528 | TK1: 529 | TL1: 530 | TM1: 531 | TN1: 532 | TO1: 533 | TP1: 534 | TQ1: 535 | TR1: 536 | TS1: 537 | TT1: 538 | TU1: 539 | TV1: 540 | TW1: 541 | TX1: 542 | TY1: 543 | TZ1: 544 | UA1: 545 | UB1: 546 | UC1: 547 | UD1: 548 | UE1: 549 | UF1: 550 | UG1: 551 | UH1: 552 | UI1: 553 | UJ1: 554 | UK1: 555 | UL1: 556 | UM1: 557 | UN1: 558 | UO1: 559 | UP1: 560 | UQ1: 561 | UR1: 562 | US1: 563 | UT1: 564 | UU1: 565 | UV1: 566 | UW1: 567 | UX1: 568 | UY1: 569 | UZ1: 570 | VA1: 571 | VB1: 572 | VC1: 573 | VD1: 574 | VE1: 575 | VF1: 576 | VG1: 577 | VH1: 578 | VI1: 579 | VJ1: 580 | VK1: 581 | VL1: 582 | VM1: 583 | VN1: 584 | VO1: 585 | VP1: 586 | VQ1: 587 | VR1: 588 | VS1: 589 | VT1: 590 | VU1: 591 | VV1: 592 | VW1: 593 | VX1: 594 | VY1: 595 | VZ1: 596 | WA1: 597 | WB1: 598 | WC1: 599 | WD1: 600
A2: Date | B2: =EDATE(DATE(2027,1,31),B1) | C2: =EDATE(DATE(2027,1,31),C1) | D2: =EDATE(DATE(2027,1,31),D1) | E2: =EDATE(DATE(2027,1,31),E1) | F2: =EDATE(DATE(2027,1,31),F1) | G2: =EDATE(DATE(2027,1,31),G1) | H2: =EDATE(DATE(2027,1,31),H1) | I2: =EDATE(DATE(2027,1,31),I1) | ... WD2: =EDATE(DATE(2027,1,31),WD1)
A3: Net cash flow | B3: =-Inputs!B2 | C3: =Inputs!B3*(1+Inputs!B4)^INT((C1-1)/12)*(1-Hidden!B1) | D3: =Inputs!B3*(1+Inputs!B4)^INT((D1-1)/12)*(1-Hidden!B1) | E3: =Inputs!B3*(1+Inputs!B4)^INT((E1-1)/12)*(1-Hidden!B1) | F3: =Inputs!B3*(1+Inputs!B4)^INT((F1-1)/12)*(1-Hidden!B1) | G3: =Inputs!B3*(1+Inputs!B4)^INT((G1-1)/12)*(1-Hidden!B1) | H3: =Inputs!B3*(1+Inputs!B4)^INT((H1-1)/12)*(1-Hidden!B1) | I3: =Inputs!B3*(1+Inputs!B4)^INT((I1-1)/12)*(1-Hidden!B1) | J3: =Inputs!B3*(1+Inputs!B4)^INT((J1-1)/12)*(1-Hidden!B1) | K3: =Inputs!B3*(1+Inputs!B4)^INT((K1-1)/12)*(1-Hidden!B1) | L3: =Inputs!B3*(1+Inputs!B4)^INT((L1-1)/12)*(1-Hidden!B1) | M3: =Inputs!B3*(1+Inputs!B4)^INT((M1-1)/12)*(1-Hidden!B1) | N3: =Inputs!B3*(1+Inputs!B4)^INT((N1-1)/12)*(1-Hidden!B1) | O3: =Inputs!B3*(1+Inputs!B4)^INT((O1-1)/12)*(1-Hidden!B1) | P3: =Inputs!B3*(1+Inputs!B4)^INT((P1-1)/12)*(1-Hidden!B1) | Q3: =Inputs!B3*(1+Inputs!B4)^INT((Q1-1)/12)*(1-Hidden!B1) | R3: =Inputs!B3*(1+Inputs!B4)^INT((R1-1)/12)*(1-Hidden!B1) | S3: =Inputs!B3*(1+Inputs!B4)^INT((S1-1)/12)*(1-Hidden!B1) | T3: =Inputs!B3*(1+Inputs!B4)^INT((T1-1)/12)*(1-Hidden!B1) | U3: =Inputs!B3*(1+Inputs!B4)^INT((U1-1)/12)*(1-Hidden!B1) | V3: =Inputs!B3*(1+Inputs!B4)^INT((V1-1)/12)*(1-Hidden!B1) | W3: =Inputs!B3*(1+Inputs!B4)^INT((W1-1)/12)*(1-Hidden!B1) | X3: =Inputs!B3*(1+Inputs!B4)^INT((X1-1)/12)*(1-Hidden!B1) | Y3: =Inputs!B3*(1+Inputs!B4)^INT((Y1-1)/12)*(1-Hidden!B1) | Z3: =Inputs!B3*(1+Inputs!B4)^INT((Z1-1)/12)*(1-Hidden!B1) | AA3: =Inputs!B3*(1+Inputs!B4)^INT((AA1-1)/12)*(1-Hidden!B1) | AB3: =Inputs!B3*(1+Inputs!B4)^INT((AB1-1)/12)*(1-Hidden!B1) | AC3: =Inputs!B3*(1+Inputs!B4)^INT((AC1-1)/12)*(1-Hidden!B1) | AD3: =Inputs!B3*(1+Inputs!B4)^INT((AD1-1)/12)*(1-Hidden!B1) | AE3: =Inputs!B3*(1+Inputs!B4)^INT((AE1-1)/12)*(1-Hidden!B1) | AF3: =Inputs!B3*(1+Inputs!B4)^INT((AF1-1)/12)*(1-Hidden!B1) | AG3: =Inputs!B3*(1+Inputs!B4)^INT((AG1-1)/12)*(1-Hidden!B1) | AH3: =Inputs!B3*(1+Inputs!B4)^INT((AH1-1)/12)*(1-Hidden!B1) | AI3: =Inputs!B3*(1+Inputs!B4)^INT((AI1-1)/12)*(1-Hidden!B1) | AJ3: =Inputs!B3*(1+Inputs!B4)^INT((AJ1-1)/12)*(1-Hidden!B1) | AK3: =Inputs!B3*(1+Inputs!B4)^INT((AK1-1)/12)*(1-Hidden!B1) | AL3: =Inputs!B3*(1+Inputs!B4)^INT((AL1-1)/12)*(1-Hidden!B1) | AM3: =Inputs!B3*(1+Inputs!B4)^INT((AM1-1)/12)*(1-Hidden!B1) | AN3: =Inputs!B3*(1+Inputs!B4)^INT((AN1-1)/12)*(1-Hidden!B1) | AO3: =Inputs!B3*(1+Inputs!B4)^INT((AO1-1)/12)*(1-Hidden!B1) | AP3: =Inputs!B3*(1+Inputs!B4)^INT((AP1-1)/12)*(1-Hidden!B1) | AQ3: =Inputs!B3*(1+Inputs!B4)^INT((AQ1-1)/12)*(1-Hidden!B1) | AR3: =Inputs!B3*(1+Inputs!B4)^INT((AR1-1)/12)*(1-Hidden!B1) | AS3: =Inputs!B3*(1+Inputs!B4)^INT((AS1-1)/12)*(1-Hidden!B1) | AT3: =Inputs!B3*(1+Inputs!B4)^INT((AT1-1)/12)*(1-Hidden!B1) | AU3: =Inputs!B3*(1+Inputs!B4)^INT((AU1-1)/12)*(1-Hidden!B1) | AV3: =Inputs!B3*(1+Inputs!B4)^INT((AV1-1)/12)*(1-Hidden!B1) | AW3: =Inputs!B3*(1+Inputs!B4)^INT((AW1-1)/12)*(1-Hidden!B1) | AX3: =Inputs!B3*(1+Inputs!B4)^INT((AX1-1)/12)*(1-Hidden!B1) | AY3: =Inputs!B3*(1+Inputs!B4)^INT((AY1-1)/12)*(1-Hidden!B1) | AZ3: =Inputs!B3*(1+Inputs!B4)^INT((AZ1-1)/12)*(1-Hidden!B1) | BA3: =Inputs!B3*(1+Inputs!B4)^INT((BA1-1)/12)*(1-Hidden!B1) | BB3: =Inputs!B3*(1+Inputs!B4)^INT((BB1-1)/12)*(1-Hidden!B1) | BC3: =Inputs!B3*(1+Inputs!B4)^INT((BC1-1)/12)*(1-Hidden!B1) | BD3: =Inputs!B3*(1+Inputs!B4)^INT((BD1-1)/12)*(1-Hidden!B1) | BE3: =Inputs!B3*(1+Inputs!B4)^INT((BE1-1)/12)*(1-Hidden!B1) | BF3: =Inputs!B3*(1+Inputs!B4)^INT((BF1-1)/12)*(1-Hidden!B1) | BG3: =Inputs!B3*(1+Inputs!B4)^INT((BG1-1)/12)*(1-Hidden!B1) | BH3: =Inputs!B3*(1+Inputs!B4)^INT((BH1-1)/12)*(1-Hidden!B1) | BI3: =Inputs!B3*(1+Inputs!B4)^INT((BI1-1)/12)*(1-Hidden!B1) | BJ3: =Inputs!B3*(1+Inputs!B4)^INT((BJ1-1)/12)*(1-Hidden!B1) | BK3: =Inputs!B3*(1+Inputs!B4)^INT((BK1-1)/12)*(1-Hidden!B1) | BL3: =Inputs!B3*(1+Inputs!B4)^INT((BL1-1)/12)*(1-Hidden!B1) | BM3: =Inputs!B3*(1+Inputs!B4)^INT((BM1-1)/12)*(1-Hidden!B1) | BN3: =Inputs!B3*(1+Inputs!B4)^INT((BN1-1)/12)*(1-Hidden!B1) | BO3: =Inputs!B3*(1+Inputs!B4)^INT((BO1-1)/12)*(1-Hidden!B1) | BP3: =Inputs!B3*(1+Inputs!B4)^INT((BP1-1)/12)*(1-Hidden!B1) | BQ3: =Inputs!B3*(1+Inputs!B4)^INT((BQ1-1)/12)*(1-Hidden!B1) | BR3: =Inputs!B3*(1+Inputs!B4)^INT((BR1-1)/12)*(1-Hidden!B1) | BS3: =Inputs!B3*(1+Inputs!B4)^INT((BS1-1)/12)*(1-Hidden!B1) | BT3: =Inputs!B3*(1+Inputs!B4)^INT((BT1-1)/12)*(1-Hidden!B1) | BU3: =Inputs!B3*(1+Inputs!B4)^INT((BU1-1)/12)*(1-Hidden!B1) | BV3: =Inputs!B3*(1+Inputs!B4)^INT((BV1-1)/12)*(1-Hidden!B1) | BW3: =Inputs!B3*(1+Inputs!B4)^INT((BW1-1)/12)*(1-Hidden!B1) | BX3: =Inputs!B3*(1+Inputs!B4)^INT((BX1-1)/12)*(1-Hidden!B1) | BY3: =Inputs!B3*(1+Inputs!B4)^INT((BY1-1)/12)*(1-Hidden!B1) | BZ3: =Inputs!B3*(1+Inputs!B4)^INT((BZ1-1)/12)*(1-Hidden!B1) | CA3: =Inputs!B3*(1+Inputs!B4)^INT((CA1-1)/12)*(1-Hidden!B1) | CB3: =Inputs!B3*(1+Inputs!B4)^INT((CB1-1)/12)*(1-Hidden!B1) | CC3: =Inputs!B3*(1+Inputs!B4)^INT((CC1-1)/12)*(1-Hidden!B1) | CD3: =Inputs!B3*(1+Inputs!B4)^INT((CD1-1)/12)*(1-Hidden!B1) | CE3: =Inputs!B3*(1+Inputs!B4)^INT((CE1-1)/12)*(1-Hidden!B1) | CF3: =Inputs!B3*(1+Inputs!B4)^INT((CF1-1)/12)*(1-Hidden!B1) | CG3: =Inputs!B3*(1+Inputs!B4)^INT((CG1-1)/12)*(1-Hidden!B1) | CH3: =Inputs!B3*(1+Inputs!B4)^INT((CH1-1)/12)*(1-Hidden!B1) | CI3: =Inputs!B3*(1+Inputs!B4)^INT((CI1-1)/12)*(1-Hidden!B1) | CJ3: =Inputs!B3*(1+Inputs!B4)^INT((CJ1-1)/12)*(1-Hidden!B1) | CK3: =Inputs!B3*(1+Inputs!B4)^INT((CK1-1)/12)*(1-Hidden!B1) | CL3: =Inputs!B3*(1+Inputs!B4)^INT((CL1-1)/12)*(1-Hidden!B1) | CM3: =Inputs!B3*(1+Inputs!B4)^INT((CM1-1)/12)*(1-Hidden!B1) | CN3: =Inputs!B3*(1+Inputs!B4)^INT((CN1-1)/12)*(1-Hidden!B1) | CO3: =Inputs!B3*(1+Inputs!B4)^INT((CO1-1)/12)*(1-Hidden!B1) | CP3: =Inputs!B3*(1+Inputs!B4)^INT((CP1-1)/12)*(1-Hidden!B1) | CQ3: =Inputs!B3*(1+Inputs!B4)^INT((CQ1-1)/12)*(1-Hidden!B1) | CR3: =Inputs!B3*(1+Inputs!B4)^INT((CR1-1)/12)*(1-Hidden!B1) | CS3: =Inputs!B3*(1+Inputs!B4)^INT((CS1-1)/12)*(1-Hidden!B1) | CT3: =Inputs!B3*(1+Inputs!B4)^INT((CT1-1)/12)*(1-Hidden!B1) | CU3: =Inputs!B3*(1+Inputs!B4)^INT((CU1-1)/12)*(1-Hidden!B1) | CV3: =Inputs!B3*(1+Inputs!B4)^INT((CV1-1)/12)*(1-Hidden!B1) | CW3: =Inputs!B3*(1+Inputs!B4)^INT((CW1-1)/12)*(1-Hidden!B1) | CX3: =Inputs!B3*(1+Inputs!B4)^INT((CX1-1)/12)*(1-Hidden!B1) | CY3: =Inputs!B3*(1+Inputs!B4)^INT((CY1-1)/12)*(1-Hidden!B1) | CZ3: =Inputs!B3*(1+Inputs!B4)^INT((CZ1-1)/12)*(1-Hidden!B1) | DA3: =Inputs!B3*(1+Inputs!B4)^INT((DA1-1)/12)*(1-Hidden!B1) | DB3: =Inputs!B3*(1+Inputs!B4)^INT((DB1-1)/12)*(1-Hidden!B1) | DC3: =Inputs!B3*(1+Inputs!B4)^INT((DC1-1)/12)*(1-Hidden!B1) | DD3: =Inputs!B3*(1+Inputs!B4)^INT((DD1-1)/12)*(1-Hidden!B1) | DE3: =Inputs!B3*(1+Inputs!B4)^INT((DE1-1)/12)*(1-Hidden!B1) | DF3: =Inputs!B3*(1+Inputs!B4)^INT((DF1-1)/12)*(1-Hidden!B1) | DG3: =Inputs!B3*(1+Inputs!B4)^INT((DG1-1)/12)*(1-Hidden!B1) | DH3: =Inputs!B3*(1+Inputs!B4)^INT((DH1-1)/12)*(1-Hidden!B1) | DI3: =Inputs!B3*(1+Inputs!B4)^INT((DI1-1)/12)*(1-Hidden!B1) | DJ3: =Inputs!B3*(1+Inputs!B4)^INT((DJ1-1)/12)*(1-Hidden!B1) | DK3: =Inputs!B3*(1+Inputs!B4)^INT((DK1-1)/12)*(1-Hidden!B1) | DL3: =Inputs!B3*(1+Inputs!B4)^INT((DL1-1)/12)*(1-Hidden!B1) | DM3: =Inputs!B3*(1+Inputs!B4)^INT((DM1-1)/12)*(1-Hidden!B1) | DN3: =Inputs!B3*(1+Inputs!B4)^INT((DN1-1)/12)*(1-Hidden!B1) | DO3: =Inputs!B3*(1+Inputs!B4)^INT((DO1-1)/12)*(1-Hidden!B1) | DP3: =Inputs!B3*(1+Inputs!B4)^INT((DP1-1)/12)*(1-Hidden!B1) | DQ3: =Inputs!B3*(1+Inputs!B4)^INT((DQ1-1)/12)*(1-Hidden!B1) | DR3: =Inputs!B3*(1+Inputs!B4)^INT((DR1-1)/12)*(1-Hidden!B1) | DS3: =Inputs!B3*(1+Inputs!B4)^INT((DS1-1)/12)*(1-Hidden!B1) | DT3: =Inputs!B3*(1+Inputs!B4)^INT((DT1-1)/12)*(1-Hidden!B1) | DU3: =Inputs!B3*(1+Inputs!B4)^INT((DU1-1)/12)*(1-Hidden!B1) | DV3: =Inputs!B3*(1+Inputs!B4)^INT((DV1-1)/12)*(1-Hidden!B1) | DW3: =Inputs!B3*(1+Inputs!B4)^INT((DW1-1)/12)*(1-Hidden!B1) | DX3: =Inputs!B3*(1+Inputs!B4)^INT((DX1-1)/12)*(1-Hidden!B1) | DY3: =Inputs!B3*(1+Inputs!B4)^INT((DY1-1)/12)*(1-Hidden!B1) | DZ3: =Inputs!B3*(1+Inputs!B4)^INT((DZ1-1)/12)*(1-Hidden!B1) | EA3: =Inputs!B3*(1+Inputs!B4)^INT((EA1-1)/12)*(1-Hidden!B1) | EB3: =Inputs!B3*(1+Inputs!B4)^INT((EB1-1)/12)*(1-Hidden!B1) | EC3: =Inputs!B3*(1+Inputs!B4)^INT((EC1-1)/12)*(1-Hidden!B1) | ED3: =Inputs!B3*(1+Inputs!B4)^INT((ED1-1)/12)*(1-Hidden!B1) | EE3: =Inputs!B3*(1+Inputs!B4)^INT((EE1-1)/12)*(1-Hidden!B1) | EF3: =Inputs!B3*(1+Inputs!B4)^INT((EF1-1)/12)*(1-Hidden!B1) | EG3: =Inputs!B3*(1+Inputs!B4)^INT((EG1-1)/12)*(1-Hidden!B1) | EH3: =Inputs!B3*(1+Inputs!B4)^INT((EH1-1)/12)*(1-Hidden!B1) | EI3: =Inputs!B3*(1+Inputs!B4)^INT((EI1-1)/12)*(1-Hidden!B1) | EJ3: =Inputs!B3*(1+Inputs!B4)^INT((EJ1-1)/12)*(1-Hidden!B1) | EK3: =Inputs!B3*(1+Inputs!B4)^INT((EK1-1)/12)*(1-Hidden!B1) | EL3: =Inputs!B3*(1+Inputs!B4)^INT((EL1-1)/12)*(1-Hidden!B1) | EM3: =Inputs!B3*(1+Inputs!B4)^INT((EM1-1)/12)*(1-Hidden!B1) | EN3: =Inputs!B3*(1+Inputs!B4)^INT((EN1-1)/12)*(1-Hidden!B1) | EO3: =Inputs!B3*(1+Inputs!B4)^INT((EO1-1)/12)*(1-Hidden!B1) | EP3: =Inputs!B3*(1+Inputs!B4)^INT((EP1-1)/12)*(1-Hidden!B1) | EQ3: =Inputs!B3*(1+Inputs!B4)^INT((EQ1-1)/12)*(1-Hidden!B1) | ER3: =Inputs!B3*(1+Inputs!B4)^INT((ER1-1)/12)*(1-Hidden!B1) | ES3: =Inputs!B3*(1+Inputs!B4)^INT((ES1-1)/12)*(1-Hidden!B1) | ET3: =Inputs!B3*(1+Inputs!B4)^INT((ET1-1)/12)*(1-Hidden!B1) | EU3: =Inputs!B3*(1+Inputs!B4)^INT((EU1-1)/12)*(1-Hidden!B1) | EV3: =Inputs!B3*(1+Inputs!B4)^INT((EV1-1)/12)*(1-Hidden!B1) | EW3: =Inputs!B3*(1+Inputs!B4)^INT((EW1-1)/12)*(1-Hidden!B1) | EX3: =Inputs!B3*(1+Inputs!B4)^INT((EX1-1)/12)*(1-Hidden!B1) | EY3: =Inputs!B3*(1+Inputs!B4)^INT((EY1-1)/12)*(1-Hidden!B1) | EZ3: =Inputs!B3*(1+Inputs!B4)^INT((EZ1-1)/12)*(1-Hidden!B1) | FA3: =Inputs!B3*(1+Inputs!B4)^INT((FA1-1)/12)*(1-Hidden!B1) | FB3: =Inputs!B3*(1+Inputs!B4)^INT((FB1-1)/12)*(1-Hidden!B1) | FC3: =Inputs!B3*(1+Inputs!B4)^INT((FC1-1)/12)*(1-Hidden!B1) | FD3: =Inputs!B3*(1+Inputs!B4)^INT((FD1-1)/12)*(1-Hidden!B1) | FE3: =Inputs!B3*(1+Inputs!B4)^INT((FE1-1)/12)*(1-Hidden!B1) | FF3: =Inputs!B3*(1+Inputs!B4)^INT((FF1-1)/12)*(1-Hidden!B1) | FG3: =Inputs!B3*(1+Inputs!B4)^INT((FG1-1)/12)*(1-Hidden!B1) | FH3: =Inputs!B3*(1+Inputs!B4)^INT((FH1-1)/12)*(1-Hidden!B1) | FI3: =Inputs!B3*(1+Inputs!B4)^INT((FI1-1)/12)*(1-Hidden!B1) | FJ3: =Inputs!B3*(1+Inputs!B4)^INT((FJ1-1)/12)*(1-Hidden!B1) | FK3: =Inputs!B3*(1+Inputs!B4)^INT((FK1-1)/12)*(1-Hidden!B1) | FL3: =Inputs!B3*(1+Inputs!B4)^INT((FL1-1)/12)*(1-Hidden!B1) | FM3: =Inputs!B3*(1+Inputs!B4)^INT((FM1-1)/12)*(1-Hidden!B1) | FN3: =Inputs!B3*(1+Inputs!B4)^INT((FN1-1)/12)*(1-Hidden!B1) | FO3: =Inputs!B3*(1+Inputs!B4)^INT((FO1-1)/12)*(1-Hidden!B1) | FP3: =Inputs!B3*(1+Inputs!B4)^INT((FP1-1)/12)*(1-Hidden!B1) | FQ3: =Inputs!B3*(1+Inputs!B4)^INT((FQ1-1)/12)*(1-Hidden!B1) | FR3: =Inputs!B3*(1+Inputs!B4)^INT((FR1-1)/12)*(1-Hidden!B1) | FS3: =Inputs!B3*(1+Inputs!B4)^INT((FS1-1)/12)*(1-Hidden!B1) | FT3: =Inputs!B3*(1+Inputs!B4)^INT((FT1-1)/12)*(1-Hidden!B1) | FU3: =Inputs!B3*(1+Inputs!B4)^INT((FU1-1)/12)*(1-Hidden!B1) | FV3: =Inputs!B3*(1+Inputs!B4)^INT((FV1-1)/12)*(1-Hidden!B1) | FW3: =Inputs!B3*(1+Inputs!B4)^INT((FW1-1)/12)*(1-Hidden!B1) | FX3: =Inputs!B3*(1+Inputs!B4)^INT((FX1-1)/12)*(1-Hidden!B1) | FY3: =Inputs!B3*(1+Inputs!B4)^INT((FY1-1)/12)*(1-Hidden!B1) | FZ3: =Inputs!B3*(1+Inputs!B4)^INT((FZ1-1)/12)*(1-Hidden!B1) | GA3: =Inputs!B3*(1+Inputs!B4)^INT((GA1-1)/12)*(1-Hidden!B1) | GB3: =Inputs!B3*(1+Inputs!B4)^INT((GB1-1)/12)*(1-Hidden!B1) | GC3: =Inputs!B3*(1+Inputs!B4)^INT((GC1-1)/12)*(1-Hidden!B1) | GD3: =Inputs!B3*(1+Inputs!B4)^INT((GD1-1)/12)*(1-Hidden!B1) | GE3: =Inputs!B3*(1+Inputs!B4)^INT((GE1-1)/12)*(1-Hidden!B1) | GF3: =Inputs!B3*(1+Inputs!B4)^INT((GF1-1)/12)*(1-Hidden!B1) | GG3: =Inputs!B3*(1+Inputs!B4)^INT((GG1-1)/12)*(1-Hidden!B1) | GH3: =Inputs!B3*(1+Inputs!B4)^INT((GH1-1)/12)*(1-Hidden!B1) | GI3: =Inputs!B3*(1+Inputs!B4)^INT((GI1-1)/12)*(1-Hidden!B1) | GJ3: =Inputs!B3*(1+Inputs!B4)^INT((GJ1-1)/12)*(1-Hidden!B1) | GK3: =Inputs!B3*(1+Inputs!B4)^INT((GK1-1)/12)*(1-Hidden!B1) | GL3: =Inputs!B3*(1+Inputs!B4)^INT((GL1-1)/12)*(1-Hidden!B1) | GM3: =Inputs!B3*(1+Inputs!B4)^INT((GM1-1)/12)*(1-Hidden!B1) | GN3: =Inputs!B3*(1+Inputs!B4)^INT((GN1-1)/12)*(1-Hidden!B1) | GO3: =Inputs!B3*(1+Inputs!B4)^INT((GO1-1)/12)*(1-Hidden!B1) | GP3: =Inputs!B3*(1+Inputs!B4)^INT((GP1-1)/12)*(1-Hidden!B1) | GQ3: =Inputs!B3*(1+Inputs!B4)^INT((GQ1-1)/12)*(1-Hidden!B1) | GR3: =Inputs!B3*(1+Inputs!B4)^INT((GR1-1)/12)*(1-Hidden!B1) | GS3: =Inputs!B3*(1+Inputs!B4)^INT((GS1-1)/12)*(1-Hidden!B1) | GT3: =Inputs!B3*(1+Inputs!B4)^INT((GT1-1)/12)*(1-Hidden!B1) | GU3: =Inputs!B3*(1+Inputs!B4)^INT((GU1-1)/12)*(1-Hidden!B1) | GV3: =Inputs!B3*(1+Inputs!B4)^INT((GV1-1)/12)*(1-Hidden!B1) | GW3: =Inputs!B3*(1+Inputs!B4)^INT((GW1-1)/12)*(1-Hidden!B1) | GX3: =Inputs!B3*(1+Inputs!B4)^INT((GX1-1)/12)*(1-Hidden!B1) | GY3: =Inputs!B3*(1+Inputs!B4)^INT((GY1-1)/12)*(1-Hidden!B1) | GZ3: =Inputs!B3*(1+Inputs!B4)^INT((GZ1-1)/12)*(1-Hidden!B1) | HA3: =Inputs!B3*(1+Inputs!B4)^INT((HA1-1)/12)*(1-Hidden!B1) | HB3: =Inputs!B3*(1+Inputs!B4)^INT((HB1-1)/12)*(1-Hidden!B1) | HC3: =Inputs!B3*(1+Inputs!B4)^INT((HC1-1)/12)*(1-Hidden!B1) | HD3: =Inputs!B3*(1+Inputs!B4)^INT((HD1-1)/12)*(1-Hidden!B1) | HE3: =Inputs!B3*(1+Inputs!B4)^INT((HE1-1)/12)*(1-Hidden!B1) | HF3: =Inputs!B3*(1+Inputs!B4)^INT((HF1-1)/12)*(1-Hidden!B1) | HG3: =Inputs!B3*(1+Inputs!B4)^INT((HG1-1)/12)*(1-Hidden!B1) | HH3: =Inputs!B3*(1+Inputs!B4)^INT((HH1-1)/12)*(1-Hidden!B1) | HI3: =Inputs!B3*(1+Inputs!B4)^INT((HI1-1)/12)*(1-Hidden!B1) | HJ3: =Inputs!B3*(1+Inputs!B4)^INT((HJ1-1)/12)*(1-Hidden!B1) | HK3: =Inputs!B3*(1+Inputs!B4)^INT((HK1-1)/12)*(1-Hidden!B1) | HL3: =Inputs!B3*(1+Inputs!B4)^INT((HL1-1)/12)*(1-Hidden!B1) | HM3: =Inputs!B3*(1+Inputs!B4)^INT((HM1-1)/12)*(1-Hidden!B1) | HN3: =Inputs!B3*(1+Inputs!B4)^INT((HN1-1)/12)*(1-Hidden!B1) | HO3: =Inputs!B3*(1+Inputs!B4)^INT((HO1-1)/12)*(1-Hidden!B1) | HP3: =Inputs!B3*(1+Inputs!B4)^INT((HP1-1)/12)*(1-Hidden!B1) | HQ3: =Inputs!B3*(1+Inputs!B4)^INT((HQ1-1)/12)*(1-Hidden!B1) | HR3: =Inputs!B3*(1+Inputs!B4)^INT((HR1-1)/12)*(1-Hidden!B1) | HS3: =Inputs!B3*(1+Inputs!B4)^INT((HS1-1)/12)*(1-Hidden!B1) | HT3: =Inputs!B3*(1+Inputs!B4)^INT((HT1-1)/12)*(1-Hidden!B1) | HU3: =Inputs!B3*(1+Inputs!B4)^INT((HU1-1)/12)*(1-Hidden!B1) | HV3: =Inputs!B3*(1+Inputs!B4)^INT((HV1-1)/12)*(1-Hidden!B1) | HW3: =Inputs!B3*(1+Inputs!B4)^INT((HW1-1)/12)*(1-Hidden!B1) | HX3: =Inputs!B3*(1+Inputs!B4)^INT((HX1-1)/12)*(1-Hidden!B1) | HY3: =Inputs!B3*(1+Inputs!B4)^INT((HY1-1)/12)*(1-Hidden!B1) | HZ3: =Inputs!B3*(1+Inputs!B4)^INT((HZ1-1)/12)*(1-Hidden!B1) | IA3: =Inputs!B3*(1+Inputs!B4)^INT((IA1-1)/12)*(1-Hidden!B1) | IB3: =Inputs!B3*(1+Inputs!B4)^INT((IB1-1)/12)*(1-Hidden!B1) | IC3: =Inputs!B3*(1+Inputs!B4)^INT((IC1-1)/12)*(1-Hidden!B1) | ID3: =Inputs!B3*(1+Inputs!B4)^INT((ID1-1)/12)*(1-Hidden!B1) | IE3: =Inputs!B3*(1+Inputs!B4)^INT((IE1-1)/12)*(1-Hidden!B1) | IF3: =Inputs!B3*(1+Inputs!B4)^INT((IF1-1)/12)*(1-Hidden!B1) | IG3: =Inputs!B3*(1+Inputs!B4)^INT((IG1-1)/12)*(1-Hidden!B1) | IH3: =Inputs!B3*(1+Inputs!B4)^INT((IH1-1)/12)*(1-Hidden!B1) | II3: =Inputs!B3*(1+Inputs!B4)^INT((II1-1)/12)*(1-Hidden!B1) | IJ3: =Inputs!B3*(1+Inputs!B4)^INT((IJ1-1)/12)*(1-Hidden!B1) | IK3: =Inputs!B3*(1+Inputs!B4)^INT((IK1-1)/12)*(1-Hidden!B1) | IL3: =Inputs!B3*(1+Inputs!B4)^INT((IL1-1)/12)*(1-Hidden!B1) | IM3: =Inputs!B3*(1+Inputs!B4)^INT((IM1-1)/12)*(1-Hidden!B1) | IN3: =Inputs!B3*(1+Inputs!B4)^INT((IN1-1)/12)*(1-Hidden!B1) | IO3: =Inputs!B3*(1+Inputs!B4)^INT((IO1-1)/12)*(1-Hidden!B1) | IP3: =Inputs!B3*(1+Inputs!B4)^INT((IP1-1)/12)*(1-Hidden!B1) | IQ3: =Inputs!B3*(1+Inputs!B4)^INT((IQ1-1)/12)*(1-Hidden!B1) | IR3: =Inputs!B3*(1+Inputs!B4)^INT((IR1-1)/12)*(1-Hidden!B1) | IS3: =Inputs!B3*(1+Inputs!B4)^INT((IS1-1)/12)*(1-Hidden!B1) | IT3: =Inputs!B3*(1+Inputs!B4)^INT((IT1-1)/12)*(1-Hidden!B1) | IU3: =Inputs!B3*(1+Inputs!B4)^INT((IU1-1)/12)*(1-Hidden!B1) | IV3: =Inputs!B3*(1+Inputs!B4)^INT((IV1-1)/12)*(1-Hidden!B1) | IW3: =Inputs!B3*(1+Inputs!B4)^INT((IW1-1)/12)*(1-Hidden!B1) | IX3: =Inputs!B3*(1+Inputs!B4)^INT((IX1-1)/12)*(1-Hidden!B1) | IY3: =Inputs!B3*(1+Inputs!B4)^INT((IY1-1)/12)*(1-Hidden!B1) | IZ3: =Inputs!B3*(1+Inputs!B4)^INT((IZ1-1)/12)*(1-Hidden!B1) | JA3: =Inputs!B3*(1+Inputs!B4)^INT((JA1-1)/12)*(1-Hidden!B1) | JB3: =Inputs!B3*(1+Inputs!B4)^INT((JB1-1)/12)*(1-Hidden!B1) | JC3: =Inputs!B3*(1+Inputs!B4)^INT((JC1-1)/12)*(1-Hidden!B1) | JD3: =Inputs!B3*(1+Inputs!B4)^INT((JD1-1)/12)*(1-Hidden!B1) | JE3: =Inputs!B3*(1+Inputs!B4)^INT((JE1-1)/12)*(1-Hidden!B1) | JF3: =Inputs!B3*(1+Inputs!B4)^INT((JF1-1)/12)*(1-Hidden!B1) | JG3: =Inputs!B3*(1+Inputs!B4)^INT((JG1-1)/12)*(1-Hidden!B1) | JH3: =Inputs!B3*(1+Inputs!B4)^INT((JH1-1)/12)*(1-Hidden!B1) | JI3: =Inputs!B3*(1+Inputs!B4)^INT((JI1-1)/12)*(1-Hidden!B1) | JJ3: =Inputs!B3*(1+Inputs!B4)^INT((JJ1-1)/12)*(1-Hidden!B1) | JK3: =Inputs!B3*(1+Inputs!B4)^INT((JK1-1)/12)*(1-Hidden!B1) | JL3: =Inputs!B3*(1+Inputs!B4)^INT((JL1-1)/12)*(1-Hidden!B1) | JM3: =Inputs!B3*(1+Inputs!B4)^INT((JM1-1)/12)*(1-Hidden!B1) | JN3: =Inputs!B3*(1+Inputs!B4)^INT((JN1-1)/12)*(1-Hidden!B1) | JO3: =Inputs!B3*(1+Inputs!B4)^INT((JO1-1)/12)*(1-Hidden!B1) | JP3: =Inputs!B3*(1+Inputs!B4)^INT((JP1-1)/12)*(1-Hidden!B1) | JQ3: =Inputs!B3*(1+Inputs!B4)^INT((JQ1-1)/12)*(1-Hidden!B1) | JR3: =Inputs!B3*(1+Inputs!B4)^INT((JR1-1)/12)*(1-Hidden!B1) | JS3: =Inputs!B3*(1+Inputs!B4)^INT((JS1-1)/12)*(1-Hidden!B1) | JT3: =Inputs!B3*(1+Inputs!B4)^INT((JT1-1)/12)*(1-Hidden!B1) | JU3: =Inputs!B3*(1+Inputs!B4)^INT((JU1-1)/12)*(1-Hidden!B1) | JV3: =Inputs!B3*(1+Inputs!B4)^INT((JV1-1)/12)*(1-Hidden!B1) | JW3: =Inputs!B3*(1+Inputs!B4)^INT((JW1-1)/12)*(1-Hidden!B1) | JX3: =Inputs!B3*(1+Inputs!B4)^INT((JX1-1)/12)*(1-Hidden!B1) | JY3: =Inputs!B3*(1+Inputs!B4)^INT((JY1-1)/12)*(1-Hidden!B1) | JZ3: =Inputs!B3*(1+Inputs!B4)^INT((JZ1-1)/12)*(1-Hidden!B1) | KA3: =Inputs!B3*(1+Inputs!B4)^INT((KA1-1)/12)*(1-Hidden!B1) | KB3: =Inputs!B3*(1+Inputs!B4)^INT((KB1-1)/12)*(1-Hidden!B1) | KC3: =Inputs!B3*(1+Inputs!B4)^INT((KC1-1)/12)*(1-Hidden!B1) | KD3: =Inputs!B3*(1+Inputs!B4)^INT((KD1-1)/12)*(1-Hidden!B1) | KE3: =Inputs!B3*(1+Inputs!B4)^INT((KE1-1)/12)*(1-Hidden!B1) | KF3: =Inputs!B3*(1+Inputs!B4)^INT((KF1-1)/12)*(1-Hidden!B1) | KG3: =Inputs!B3*(1+Inputs!B4)^INT((KG1-1)/12)*(1-Hidden!B1) | KH3: =Inputs!B3*(1+Inputs!B4)^INT((KH1-1)/12)*(1-Hidden!B1) | KI3: =Inputs!B3*(1+Inputs!B4)^INT((KI1-1)/12)*(1-Hidden!B1) | KJ3: =Inputs!B3*(1+Inputs!B4)^INT((KJ1-1)/12)*(1-Hidden!B1) | KK3: =Inputs!B3*(1+Inputs!B4)^INT((KK1-1)/12)*(1-Hidden!B1) | KL3: =Inputs!B3*(1+Inputs!B4)^INT((KL1-1)/12)*(1-Hidden!B1) | KM3: =Inputs!B3*(1+Inputs!B4)^INT((KM1-1)/12)*(1-Hidden!B1) | KN3: =Inputs!B3*(1+Inputs!B4)^INT((KN1-1)/12)*(1-Hidden!B1) | KO3: =Inputs!B3*(1+Inputs!B4)^INT((KO1-1)/12)*(1-Hidden!B1) | KP3: =Inputs!B3*(1+Inputs!B4)^INT((KP1-1)/12)*(1-Hidden!B1) | KQ3: =Inputs!B3*(1+Inputs!B4)^INT((KQ1-1)/12)*(1-Hidden!B1) | KR3: =Inputs!B3*(1+Inputs!B4)^INT((KR1-1)/12)*(1-Hidden!B1) | KS3: =Inputs!B3*(1+Inputs!B4)^INT((KS1-1)/12)*(1-Hidden!B1) | KT3: =Inputs!B3*(1+Inputs!B4)^INT((KT1-1)/12)*(1-Hidden!B1) | KU3: =Inputs!B3*(1+Inputs!B4)^INT((KU1-1)/12)*(1-Hidden!B1) | KV3: =Inputs!B3*(1+Inputs!B4)^INT((KV1-1)/12)*(1-Hidden!B1) | KW3: =Inputs!B3*(1+Inputs!B4)^INT((KW1-1)/12)*(1-Hidden!B1) | KX3: =Inputs!B3*(1+Inputs!B4)^INT((KX1-1)/12)*(1-Hidden!B1) | KY3: =Inputs!B3*(1+Inputs!B4)^INT((KY1-1)/12)*(1-Hidden!B1) | KZ3: =Inputs!B3*(1+Inputs!B4)^INT((KZ1-1)/12)*(1-Hidden!B1) | LA3: =Inputs!B3*(1+Inputs!B4)^INT((LA1-1)/12)*(1-Hidden!B1) | LB3: =Inputs!B3*(1+Inputs!B4)^INT((LB1-1)/12)*(1-Hidden!B1) | LC3: =Inputs!B3*(1+Inputs!B4)^INT((LC1-1)/12)*(1-Hidden!B1) | LD3: =Inputs!B3*(1+Inputs!B4)^INT((LD1-1)/12)*(1-Hidden!B1) | LE3: =Inputs!B3*(1+Inputs!B4)^INT((LE1-1)/12)*(1-Hidden!B1) | LF3: =Inputs!B3*(1+Inputs!B4)^INT((LF1-1)/12)*(1-Hidden!B1) | LG3: =Inputs!B3*(1+Inputs!B4)^INT((LG1-1)/12)*(1-Hidden!B1) | LH3: =Inputs!B3*(1+Inputs!B4)^INT((LH1-1)/12)*(1-Hidden!B1) | LI3: =Inputs!B3*(1+Inputs!B4)^INT((LI1-1)/12)*(1-Hidden!B1) | LJ3: =Inputs!B3*(1+Inputs!B4)^INT((LJ1-1)/12)*(1-Hidden!B1) | LK3: =Inputs!B3*(1+Inputs!B4)^INT((LK1-1)/12)*(1-Hidden!B1) | LL3: =Inputs!B3*(1+Inputs!B4)^INT((LL1-1)/12)*(1-Hidden!B1) | LM3: =Inputs!B3*(1+Inputs!B4)^INT((LM1-1)/12)*(1-Hidden!B1) | LN3: =Inputs!B3*(1+Inputs!B4)^INT((LN1-1)/12)*(1-Hidden!B1) | LO3: =Inputs!B3*(1+Inputs!B4)^INT((LO1-1)/12)*(1-Hidden!B1) | LP3: =Inputs!B3*(1+Inputs!B4)^INT((LP1-1)/12)*(1-Hidden!B1) | LQ3: =Inputs!B3*(1+Inputs!B4)^INT((LQ1-1)/12)*(1-Hidden!B1) | LR3: =Inputs!B3*(1+Inputs!B4)^INT((LR1-1)/12)*(1-Hidden!B1) | LS3: =Inputs!B3*(1+Inputs!B4)^INT((LS1-1)/12)*(1-Hidden!B1) | LT3: =Inputs!B3*(1+Inputs!B4)^INT((LT1-1)/12)*(1-Hidden!B1) | LU3: =Inputs!B3*(1+Inputs!B4)^INT((LU1-1)/12)*(1-Hidden!B1) | LV3: =Inputs!B3*(1+Inputs!B4)^INT((LV1-1)/12)*(1-Hidden!B1) | LW3: =Inputs!B3*(1+Inputs!B4)^INT((LW1-1)/12)*(1-Hidden!B1) | LX3: =Inputs!B3*(1+Inputs!B4)^INT((LX1-1)/12)*(1-Hidden!B1) | LY3: =Inputs!B3*(1+Inputs!B4)^INT((LY1-1)/12)*(1-Hidden!B1) | LZ3: =Inputs!B3*(1+Inputs!B4)^INT((LZ1-1)/12)*(1-Hidden!B1) | MA3: =Inputs!B3*(1+Inputs!B4)^INT((MA1-1)/12)*(1-Hidden!B1) | MB3: =Inputs!B3*(1+Inputs!B4)^INT((MB1-1)/12)*(1-Hidden!B1) | MC3: =Inputs!B3*(1+Inputs!B4)^INT((MC1-1)/12)*(1-Hidden!B1) | MD3: =Inputs!B3*(1+Inputs!B4)^INT((MD1-1)/12)*(1-Hidden!B1) | ME3: =Inputs!B3*(1+Inputs!B4)^INT((ME1-1)/12)*(1-Hidden!B1) | MF3: =Inputs!B3*(1+Inputs!B4)^INT((MF1-1)/12)*(1-Hidden!B1) | MG3: =Inputs!B3*(1+Inputs!B4)^INT((MG1-1)/12)*(1-Hidden!B1) | MH3: =Inputs!B3*(1+Inputs!B4)^INT((MH1-1)/12)*(1-Hidden!B1) | MI3: =Inputs!B3*(1+Inputs!B4)^INT((MI1-1)/12)*(1-Hidden!B1) | MJ3: =Inputs!B3*(1+Inputs!B4)^INT((MJ1-1)/12)*(1-Hidden!B1) | MK3: =Inputs!B3*(1+Inputs!B4)^INT((MK1-1)/12)*(1-Hidden!B1) | ML3: =Inputs!B3*(1+Inputs!B4)^INT((ML1-1)/12)*(1-Hidden!B1) | MM3: =Inputs!B3*(1+Inputs!B4)^INT((MM1-1)/12)*(1-Hidden!B1) | MN3: =Inputs!B3*(1+Inputs!B4)^INT((MN1-1)/12)*(1-Hidden!B1) | MO3: =Inputs!B3*(1+Inputs!B4)^INT((MO1-1)/12)*(1-Hidden!B1) | MP3: =Inputs!B3*(1+Inputs!B4)^INT((MP1-1)/12)*(1-Hidden!B1) | MQ3: =Inputs!B3*(1+Inputs!B4)^INT((MQ1-1)/12)*(1-Hidden!B1) | MR3: =Inputs!B3*(1+Inputs!B4)^INT((MR1-1)/12)*(1-Hidden!B1) | MS3: =Inputs!B3*(1+Inputs!B4)^INT((MS1-1)/12)*(1-Hidden!B1) | MT3: =Inputs!B3*(1+Inputs!B4)^INT((MT1-1)/12)*(1-Hidden!B1) | MU3: =Inputs!B3*(1+Inputs!B4)^INT((MU1-1)/12)*(1-Hidden!B1) | MV3: =Inputs!B3*(1+Inputs!B4)^INT((MV1-1)/12)*(1-Hidden!B1) | MW3: =Inputs!B3*(1+Inputs!B4)^INT((MW1-1)/12)*(1-Hidden!B1) | MX3: =Inputs!B3*(1+Inputs!B4)^INT((MX1-1)/12)*(1-Hidden!B1) | MY3: =Inputs!B3*(1+Inputs!B4)^INT((MY1-1)/12)*(1-Hidden!B1) | MZ3: =Inputs!B3*(1+Inputs!B4)^INT((MZ1-1)/12)*(1-Hidden!B1) | NA3: =Inputs!B3*(1+Inputs!B4)^INT((NA1-1)/12)*(1-Hidden!B1) | NB3: =Inputs!B3*(1+Inputs!B4)^INT((NB1-1)/12)*(1-Hidden!B1) | NC3: =Inputs!B3*(1+Inputs!B4)^INT((NC1-1)/12)*(1-Hidden!B1) | ND3: =Inputs!B3*(1+Inputs!B4)^INT((ND1-1)/12)*(1-Hidden!B1) | NE3: =Inputs!B3*(1+Inputs!B4)^INT((NE1-1)/12)*(1-Hidden!B1) | NF3: =Inputs!B3*(1+Inputs!B4)^INT((NF1-1)/12)*(1-Hidden!B1) | NG3: =Inputs!B3*(1+Inputs!B4)^INT((NG1-1)/12)*(1-Hidden!B1) | NH3: =Inputs!B3*(1+Inputs!B4)^INT((NH1-1)/12)*(1-Hidden!B1) | NI3: =Inputs!B3*(1+Inputs!B4)^INT((NI1-1)/12)*(1-Hidden!B1) | NJ3: =Inputs!B3*(1+Inputs!B4)^INT((NJ1-1)/12)*(1-Hidden!B1) | NK3: =Inputs!B3*(1+Inputs!B4)^INT((NK1-1)/12)*(1-Hidden!B1) | NL3: =Inputs!B3*(1+Inputs!B4)^INT((NL1-1)/12)*(1-Hidden!B1) | NM3: =Inputs!B3*(1+Inputs!B4)^INT((NM1-1)/12)*(1-Hidden!B1) | NN3: =Inputs!B3*(1+Inputs!B4)^INT((NN1-1)/12)*(1-Hidden!B1) | NO3: =Inputs!B3*(1+Inputs!B4)^INT((NO1-1)/12)*(1-Hidden!B1) | NP3: =Inputs!B3*(1+Inputs!B4)^INT((NP1-1)/12)*(1-Hidden!B1) | NQ3: =Inputs!B3*(1+Inputs!B4)^INT((NQ1-1)/12)*(1-Hidden!B1) | NR3: =Inputs!B3*(1+Inputs!B4)^INT((NR1-1)/12)*(1-Hidden!B1) | NS3: =Inputs!B3*(1+Inputs!B4)^INT((NS1-1)/12)*(1-Hidden!B1) | NT3: =Inputs!B3*(1+Inputs!B4)^INT((NT1-1)/12)*(1-Hidden!B1) | NU3: =Inputs!B3*(1+Inputs!B4)^INT((NU1-1)/12)*(1-Hidden!B1) | NV3: =Inputs!B3*(1+Inputs!B4)^INT((NV1-1)/12)*(1-Hidden!B1) | NW3: =Inputs!B3*(1+Inputs!B4)^INT((NW1-1)/12)*(1-Hidden!B1) | NX3: =Inputs!B3*(1+Inputs!B4)^INT((NX1-1)/12)*(1-Hidden!B1) | NY3: =Inputs!B3*(1+Inputs!B4)^INT((NY1-1)/12)*(1-Hidden!B1) | NZ3: =Inputs!B3*(1+Inputs!B4)^INT((NZ1-1)/12)*(1-Hidden!B1) | OA3: =Inputs!B3*(1+Inputs!B4)^INT((OA1-1)/12)*(1-Hidden!B1) | OB3: =Inputs!B3*(1+Inputs!B4)^INT((OB1-1)/12)*(1-Hidden!B1) | OC3: =Inputs!B3*(1+Inputs!B4)^INT((OC1-1)/12)*(1-Hidden!B1) | OD3: =Inputs!B3*(1+Inputs!B4)^INT((OD1-1)/12)*(1-Hidden!B1) | OE3: =Inputs!B3*(1+Inputs!B4)^INT((OE1-1)/12)*(1-Hidden!B1) | OF3: =Inputs!B3*(1+Inputs!B4)^INT((OF1-1)/12)*(1-Hidden!B1) | OG3: =Inputs!B3*(1+Inputs!B4)^INT((OG1-1)/12)*(1-Hidden!B1) | OH3: =Inputs!B3*(1+Inputs!B4)^INT((OH1-1)/12)*(1-Hidden!B1) | OI3: =Inputs!B3*(1+Inputs!B4)^INT((OI1-1)/12)*(1-Hidden!B1) | OJ3: =Inputs!B3*(1+Inputs!B4)^INT((OJ1-1)/12)*(1-Hidden!B1) | OK3: =Inputs!B3*(1+Inputs!B4)^INT((OK1-1)/12)*(1-Hidden!B1) | OL3: =Inputs!B3*(1+Inputs!B4)^INT((OL1-1)/12)*(1-Hidden!B1) | OM3: =Inputs!B3*(1+Inputs!B4)^INT((OM1-1)/12)*(1-Hidden!B1) | ON3: =Inputs!B3*(1+Inputs!B4)^INT((ON1-1)/12)*(1-Hidden!B1) | OO3: =Inputs!B3*(1+Inputs!B4)^INT((OO1-1)/12)*(1-Hidden!B1) | OP3: =Inputs!B3*(1+Inputs!B4)^INT((OP1-1)/12)*(1-Hidden!B1) | OQ3: =Inputs!B3*(1+Inputs!B4)^INT((OQ1-1)/12)*(1-Hidden!B1) | OR3: =Inputs!B3*(1+Inputs!B4)^INT((OR1-1)/12)*(1-Hidden!B1) | OS3: =Inputs!B3*(1+Inputs!B4)^INT((OS1-1)/12)*(1-Hidden!B1) | OT3: =Inputs!B3*(1+Inputs!B4)^INT((OT1-1)/12)*(1-Hidden!B1) | OU3: =Inputs!B3*(1+Inputs!B4)^INT((OU1-1)/12)*(1-Hidden!B1) | OV3: =Inputs!B3*(1+Inputs!B4)^INT((OV1-1)/12)*(1-Hidden!B1) | OW3: =Inputs!B3*(1+Inputs!B4)^INT((OW1-1)/12)*(1-Hidden!B1) | OX3: =Inputs!B3*(1+Inputs!B4)^INT((OX1-1)/12)*(1-Hidden!B1) | OY3: =Inputs!B3*(1+Inputs!B4)^INT((OY1-1)/12)*(1-Hidden!B1) | OZ3: =Inputs!B3*(1+Inputs!B4)^INT((OZ1-1)/12)*(1-Hidden!B1) | PA3: =Inputs!B3*(1+Inputs!B4)^INT((PA1-1)/12)*(1-Hidden!B1) | PB3: =Inputs!B3*(1+Inputs!B4)^INT((PB1-1)/12)*(1-Hidden!B1) | PC3: =Inputs!B3*(1+Inputs!B4)^INT((PC1-1)/12)*(1-Hidden!B1) | PD3: =Inputs!B3*(1+Inputs!B4)^INT((PD1-1)/12)*(1-Hidden!B1) | PE3: =Inputs!B3*(1+Inputs!B4)^INT((PE1-1)/12)*(1-Hidden!B1) | PF3: =Inputs!B3*(1+Inputs!B4)^INT((PF1-1)/12)*(1-Hidden!B1) | PG3: =Inputs!B3*(1+Inputs!B4)^INT((PG1-1)/12)*(1-Hidden!B1) | PH3: =Inputs!B3*(1+Inputs!B4)^INT((PH1-1)/12)*(1-Hidden!B1) | PI3: =Inputs!B3*(1+Inputs!B4)^INT((PI1-1)/12)*(1-Hidden!B1) | PJ3: =Inputs!B3*(1+Inputs!B4)^INT((PJ1-1)/12)*(1-Hidden!B1) | PK3: =Inputs!B3*(1+Inputs!B4)^INT((PK1-1)/12)*(1-Hidden!B1) | PL3: =Inputs!B3*(1+Inputs!B4)^INT((PL1-1)/12)*(1-Hidden!B1) | PM3: =Inputs!B3*(1+Inputs!B4)^INT((PM1-1)/12)*(1-Hidden!B1) | PN3: =Inputs!B3*(1+Inputs!B4)^INT((PN1-1)/12)*(1-Hidden!B1) | PO3: =Inputs!B3*(1+Inputs!B4)^INT((PO1-1)/12)*(1-Hidden!B1) | PP3: =Inputs!B3*(1+Inputs!B4)^INT((PP1-1)/12)*(1-Hidden!B1) | PQ3: =Inputs!B3*(1+Inputs!B4)^INT((PQ1-1)/12)*(1-Hidden!B1) | PR3: =Inputs!B3*(1+Inputs!B4)^INT((PR1-1)/12)*(1-Hidden!B1) | PS3: =Inputs!B3*(1+Inputs!B4)^INT((PS1-1)/12)*(1-Hidden!B1) | PT3: =Inputs!B3*(1+Inputs!B4)^INT((PT1-1)/12)*(1-Hidden!B1) | PU3: =Inputs!B3*(1+Inputs!B4)^INT((PU1-1)/12)*(1-Hidden!B1) | PV3: =Inputs!B3*(1+Inputs!B4)^INT((PV1-1)/12)*(1-Hidden!B1) | PW3: =Inputs!B3*(1+Inputs!B4)^INT((PW1-1)/12)*(1-Hidden!B1) | PX3: =Inputs!B3*(1+Inputs!B4)^INT((PX1-1)/12)*(1-Hidden!B1) | PY3: =Inputs!B3*(1+Inputs!B4)^INT((PY1-1)/12)*(1-Hidden!B1) | PZ3: =Inputs!B3*(1+Inputs!B4)^INT((PZ1-1)/12)*(1-Hidden!B1) | QA3: =Inputs!B3*(1+Inputs!B4)^INT((QA1-1)/12)*(1-Hidden!B1) | QB3: =Inputs!B3*(1+Inputs!B4)^INT((QB1-1)/12)*(1-Hidden!B1) | QC3: =Inputs!B3*(1+Inputs!B4)^INT((QC1-1)/12)*(1-Hidden!B1) | QD3: =Inputs!B3*(1+Inputs!B4)^INT((QD1-1)/12)*(1-Hidden!B1) | QE3: =Inputs!B3*(1+Inputs!B4)^INT((QE1-1)/12)*(1-Hidden!B1) | QF3: =Inputs!B3*(1+Inputs!B4)^INT((QF1-1)/12)*(1-Hidden!B1) | QG3: =Inputs!B3*(1+Inputs!B4)^INT((QG1-1)/12)*(1-Hidden!B1) | QH3: =Inputs!B3*(1+Inputs!B4)^INT((QH1-1)/12)*(1-Hidden!B1) | QI3: =Inputs!B3*(1+Inputs!B4)^INT((QI1-1)/12)*(1-Hidden!B1) | QJ3: =Inputs!B3*(1+Inputs!B4)^INT((QJ1-1)/12)*(1-Hidden!B1) | QK3: =Inputs!B3*(1+Inputs!B4)^INT((QK1-1)/12)*(1-Hidden!B1) | QL3: =Inputs!B3*(1+Inputs!B4)^INT((QL1-1)/12)*(1-Hidden!B1) | QM3: =Inputs!B3*(1+Inputs!B4)^INT((QM1-1)/12)*(1-Hidden!B1) | QN3: =Inputs!B3*(1+Inputs!B4)^INT((QN1-1)/12)*(1-Hidden!B1) | QO3: =Inputs!B3*(1+Inputs!B4)^INT((QO1-1)/12)*(1-Hidden!B1) | QP3: =Inputs!B3*(1+Inputs!B4)^INT((QP1-1)/12)*(1-Hidden!B1) | QQ3: =Inputs!B3*(1+Inputs!B4)^INT((QQ1-1)/12)*(1-Hidden!B1) | QR3: =Inputs!B3*(1+Inputs!B4)^INT((QR1-1)/12)*(1-Hidden!B1) | QS3: =Inputs!B3*(1+Inputs!B4)^INT((QS1-1)/12)*(1-Hidden!B1) | QT3: =Inputs!B3*(1+Inputs!B4)^INT((QT1-1)/12)*(1-Hidden!B1) | QU3: =Inputs!B3*(1+Inputs!B4)^INT((QU1-1)/12)*(1-Hidden!B1) | QV3: =Inputs!B3*(1+Inputs!B4)^INT((QV1-1)/12)*(1-Hidden!B1) | QW3: =Inputs!B3*(1+Inputs!B4)^INT((QW1-1)/12)*(1-Hidden!B1) | QX3: =Inputs!B3*(1+Inputs!B4)^INT((QX1-1)/12)*(1-Hidden!B1) | QY3: =Inputs!B3*(1+Inputs!B4)^INT((QY1-1)/12)*(1-Hidden!B1) | QZ3: =Inputs!B3*(1+Inputs!B4)^INT((QZ1-1)/12)*(1-Hidden!B1) | RA3: =Inputs!B3*(1+Inputs!B4)^INT((RA1-1)/12)*(1-Hidden!B1) | RB3: =Inputs!B3*(1+Inputs!B4)^INT((RB1-1)/12)*(1-Hidden!B1) | RC3: =Inputs!B3*(1+Inputs!B4)^INT((RC1-1)/12)*(1-Hidden!B1) | RD3: =Inputs!B3*(1+Inputs!B4)^INT((RD1-1)/12)*(1-Hidden!B1) | RE3: =Inputs!B3*(1+Inputs!B4)^INT((RE1-1)/12)*(1-Hidden!B1) | RF3: =Inputs!B3*(1+Inputs!B4)^INT((RF1-1)/12)*(1-Hidden!B1) | RG3: =Inputs!B3*(1+Inputs!B4)^INT((RG1-1)/12)*(1-Hidden!B1) | RH3: =Inputs!B3*(1+Inputs!B4)^INT((RH1-1)/12)*(1-Hidden!B1) | RI3: =Inputs!B3*(1+Inputs!B4)^INT((RI1-1)/12)*(1-Hidden!B1) | RJ3: =Inputs!B3*(1+Inputs!B4)^INT((RJ1-1)/12)*(1-Hidden!B1) | RK3: =Inputs!B3*(1+Inputs!B4)^INT((RK1-1)/12)*(1-Hidden!B1) | RL3: =Inputs!B3*(1+Inputs!B4)^INT((RL1-1)/12)*(1-Hidden!B1) | RM3: =Inputs!B3*(1+Inputs!B4)^INT((RM1-1)/12)*(1-Hidden!B1) | RN3: =Inputs!B3*(1+Inputs!B4)^INT((RN1-1)/12)*(1-Hidden!B1) | RO3: =Inputs!B3*(1+Inputs!B4)^INT((RO1-1)/12)*(1-Hidden!B1) | RP3: =Inputs!B3*(1+Inputs!B4)^INT((RP1-1)/12)*(1-Hidden!B1) | RQ3: =Inputs!B3*(1+Inputs!B4)^INT((RQ1-1)/12)*(1-Hidden!B1) | RR3: =Inputs!B3*(1+Inputs!B4)^INT((RR1-1)/12)*(1-Hidden!B1) | RS3: =Inputs!B3*(1+Inputs!B4)^INT((RS1-1)/12)*(1-Hidden!B1) | RT3: =Inputs!B3*(1+Inputs!B4)^INT((RT1-1)/12)*(1-Hidden!B1) | RU3: =Inputs!B3*(1+Inputs!B4)^INT((RU1-1)/12)*(1-Hidden!B1) | RV3: =Inputs!B3*(1+Inputs!B4)^INT((RV1-1)/12)*(1-Hidden!B1) | RW3: =Inputs!B3*(1+Inputs!B4)^INT((RW1-1)/12)*(1-Hidden!B1) | RX3: =Inputs!B3*(1+Inputs!B4)^INT((RX1-1)/12)*(1-Hidden!B1) | RY3: =Inputs!B3*(1+Inputs!B4)^INT((RY1-1)/12)*(1-Hidden!B1) | RZ3: =Inputs!B3*(1+Inputs!B4)^INT((RZ1-1)/12)*(1-Hidden!B1) | SA3: =Inputs!B3*(1+Inputs!B4)^INT((SA1-1)/12)*(1-Hidden!B1) | SB3: =Inputs!B3*(1+Inputs!B4)^INT((SB1-1)/12)*(1-Hidden!B1) | SC3: =Inputs!B3*(1+Inputs!B4)^INT((SC1-1)/12)*(1-Hidden!B1) | SD3: =Inputs!B3*(1+Inputs!B4)^INT((SD1-1)/12)*(1-Hidden!B1) | SE3: =Inputs!B3*(1+Inputs!B4)^INT((SE1-1)/12)*(1-Hidden!B1) | SF3: =Inputs!B3*(1+Inputs!B4)^INT((SF1-1)/12)*(1-Hidden!B1) | SG3: =Inputs!B3*(1+Inputs!B4)^INT((SG1-1)/12)*(1-Hidden!B1) | SH3: =Inputs!B3*(1+Inputs!B4)^INT((SH1-1)/12)*(1-Hidden!B1) | SI3: =Inputs!B3*(1+Inputs!B4)^INT((SI1-1)/12)*(1-Hidden!B1) | SJ3: =Inputs!B3*(1+Inputs!B4)^INT((SJ1-1)/12)*(1-Hidden!B1) | SK3: =Inputs!B3*(1+Inputs!B4)^INT((SK1-1)/12)*(1-Hidden!B1) | SL3: =Inputs!B3*(1+Inputs!B4)^INT((SL1-1)/12)*(1-Hidden!B1) | SM3: =Inputs!B3*(1+Inputs!B4)^INT((SM1-1)/12)*(1-Hidden!B1) | SN3: =Inputs!B3*(1+Inputs!B4)^INT((SN1-1)/12)*(1-Hidden!B1) | SO3: =Inputs!B3*(1+Inputs!B4)^INT((SO1-1)/12)*(1-Hidden!B1) | SP3: =Inputs!B3*(1+Inputs!B4)^INT((SP1-1)/12)*(1-Hidden!B1) | SQ3: =Inputs!B3*(1+Inputs!B4)^INT((SQ1-1)/12)*(1-Hidden!B1) | SR3: =Inputs!B3*(1+Inputs!B4)^INT((SR1-1)/12)*(1-Hidden!B1) | SS3: =Inputs!B3*(1+Inputs!B4)^INT((SS1-1)/12)*(1-Hidden!B1) | ST3: =Inputs!B3*(1+Inputs!B4)^INT((ST1-1)/12)*(1-Hidden!B1) | SU3: =Inputs!B3*(1+Inputs!B4)^INT((SU1-1)/12)*(1-Hidden!B1) | SV3: =Inputs!B3*(1+Inputs!B4)^INT((SV1-1)/12)*(1-Hidden!B1) | SW3: =Inputs!B3*(1+Inputs!B4)^INT((SW1-1)/12)*(1-Hidden!B1) | SX3: =Inputs!B3*(1+Inputs!B4)^INT((SX1-1)/12)*(1-Hidden!B1) | SY3: =Inputs!B3*(1+Inputs!B4)^INT((SY1-1)/12)*(1-Hidden!B1) | SZ3: =Inputs!B3*(1+Inputs!B4)^INT((SZ1-1)/12)*(1-Hidden!B1) | TA3: =Inputs!B3*(1+Inputs!B4)^INT((TA1-1)/12)*(1-Hidden!B1) | TB3: =Inputs!B3*(1+Inputs!B4)^INT((TB1-1)/12)*(1-Hidden!B1) | TC3: =Inputs!B3*(1+Inputs!B4)^INT((TC1-1)/12)*(1-Hidden!B1) | TD3: =Inputs!B3*(1+Inputs!B4)^INT((TD1-1)/12)*(1-Hidden!B1) | TE3: =Inputs!B3*(1+Inputs!B4)^INT((TE1-1)/12)*(1-Hidden!B1) | TF3: =Inputs!B3*(1+Inputs!B4)^INT((TF1-1)/12)*(1-Hidden!B1) | TG3: =Inputs!B3*(1+Inputs!B4)^INT((TG1-1)/12)*(1-Hidden!B1) | TH3: =Inputs!B3*(1+Inputs!B4)^INT((TH1-1)/12)*(1-Hidden!B1) | TI3: =Inputs!B3*(1+Inputs!B4)^INT((TI1-1)/12)*(1-Hidden!B1) | TJ3: =Inputs!B3*(1+Inputs!B4)^INT((TJ1-1)/12)*(1-Hidden!B1) | TK3: =Inputs!B3*(1+Inputs!B4)^INT((TK1-1)/12)*(1-Hidden!B1) | TL3: =Inputs!B3*(1+Inputs!B4)^INT((TL1-1)/12)*(1-Hidden!B1) | TM3: =Inputs!B3*(1+Inputs!B4)^INT((TM1-1)/12)*(1-Hidden!B1) | TN3: =Inputs!B3*(1+Inputs!B4)^INT((TN1-1)/12)*(1-Hidden!B1) | TO3: =Inputs!B3*(1+Inputs!B4)^INT((TO1-1)/12)*(1-Hidden!B1) | TP3: =Inputs!B3*(1+Inputs!B4)^INT((TP1-1)/12)*(1-Hidden!B1) | TQ3: =Inputs!B3*(1+Inputs!B4)^INT((TQ1-1)/12)*(1-Hidden!B1) | TR3: =Inputs!B3*(1+Inputs!B4)^INT((TR1-1)/12)*(1-Hidden!B1) | TS3: =Inputs!B3*(1+Inputs!B4)^INT((TS1-1)/12)*(1-Hidden!B1) | TT3: =Inputs!B3*(1+Inputs!B4)^INT((TT1-1)/12)*(1-Hidden!B1) | TU3: =Inputs!B3*(1+Inputs!B4)^INT((TU1-1)/12)*(1-Hidden!B1) | TV3: =Inputs!B3*(1+Inputs!B4)^INT((TV1-1)/12)*(1-Hidden!B1) | TW3: =Inputs!B3*(1+Inputs!B4)^INT((TW1-1)/12)*(1-Hidden!B1) | TX3: =Inputs!B3*(1+Inputs!B4)^INT((TX1-1)/12)*(1-Hidden!B1) | TY3: =Inputs!B3*(1+Inputs!B4)^INT((TY1-1)/12)*(1-Hidden!B1) | TZ3: =Inputs!B3*(1+Inputs!B4)^INT((TZ1-1)/12)*(1-Hidden!B1) | UA3: =Inputs!B3*(1+Inputs!B4)^INT((UA1-1)/12)*(1-Hidden!B1) | UB3: =Inputs!B3*(1+Inputs!B4)^INT((UB1-1)/12)*(1-Hidden!B1) | UC3: =Inputs!B3*(1+Inputs!B4)^INT((UC1-1)/12)*(1-Hidden!B1) | UD3: =Inputs!B3*(1+Inputs!B4)^INT((UD1-1)/12)*(1-Hidden!B1) | UE3: =Inputs!B3*(1+Inputs!B4)^INT((UE1-1)/12)*(1-Hidden!B1) | UF3: =Inputs!B3*(1+Inputs!B4)^INT((UF1-1)/12)*(1-Hidden!B1) | UG3: =Inputs!B3*(1+Inputs!B4)^INT((UG1-1)/12)*(1-Hidden!B1) | UH3: =Inputs!B3*(1+Inputs!B4)^INT((UH1-1)/12)*(1-Hidden!B1) | UI3: =Inputs!B3*(1+Inputs!B4)^INT((UI1-1)/12)*(1-Hidden!B1) | UJ3: =Inputs!B3*(1+Inputs!B4)^INT((UJ1-1)/12)*(1-Hidden!B1) | UK3: =Inputs!B3*(1+Inputs!B4)^INT((UK1-1)/12)*(1-Hidden!B1) | UL3: =Inputs!B3*(1+Inputs!B4)^INT((UL1-1)/12)*(1-Hidden!B1) | UM3: =Inputs!B3*(1+Inputs!B4)^INT((UM1-1)/12)*(1-Hidden!B1) | UN3: =Inputs!B3*(1+Inputs!B4)^INT((UN1-1)/12)*(1-Hidden!B1) | UO3: =Inputs!B3*(1+Inputs!B4)^INT((UO1-1)/12)*(1-Hidden!B1) | UP3: =Inputs!B3*(1+Inputs!B4)^INT((UP1-1)/12)*(1-Hidden!B1) | UQ3: =Inputs!B3*(1+Inputs!B4)^INT((UQ1-1)/12)*(1-Hidden!B1) | UR3: =Inputs!B3*(1+Inputs!B4)^INT((UR1-1)/12)*(1-Hidden!B1) | US3: =Inputs!B3*(1+Inputs!B4)^INT((US1-1)/12)*(1-Hidden!B1) | UT3: =Inputs!B3*(1+Inputs!B4)^INT((UT1-1)/12)*(1-Hidden!B1) | UU3: =Inputs!B3*(1+Inputs!B4)^INT((UU1-1)/12)*(1-Hidden!B1) | UV3: =Inputs!B3*(1+Inputs!B4)^INT((UV1-1)/12)*(1-Hidden!B1) | UW3: =Inputs!B3*(1+Inputs!B4)^INT((UW1-1)/12)*(1-Hidden!B1) | UX3: =Inputs!B3*(1+Inputs!B4)^INT((UX1-1)/12)*(1-Hidden!B1) | UY3: =Inputs!B3*(1+Inputs!B4)^INT((UY1-1)/12)*(1-Hidden!B1) | UZ3: =Inputs!B3*(1+Inputs!B4)^INT((UZ1-1)/12)*(1-Hidden!B1) | VA3: =Inputs!B3*(1+Inputs!B4)^INT((VA1-1)/12)*(1-Hidden!B1) | VB3: =Inputs!B3*(1+Inputs!B4)^INT((VB1-1)/12)*(1-Hidden!B1) | VC3: =Inputs!B3*(1+Inputs!B4)^INT((VC1-1)/12)*(1-Hidden!B1) | VD3: =Inputs!B3*(1+Inputs!B4)^INT((VD1-1)/12)*(1-Hidden!B1) | VE3: =Inputs!B3*(1+Inputs!B4)^INT((VE1-1)/12)*(1-Hidden!B1) | VF3: =Inputs!B3*(1+Inputs!B4)^INT((VF1-1)/12)*(1-Hidden!B1) | VG3: =Inputs!B3*(1+Inputs!B4)^INT((VG1-1)/12)*(1-Hidden!B1) | VH3: =Inputs!B3*(1+Inputs!B4)^INT((VH1-1)/12)*(1-Hidden!B1) | VI3: =Inputs!B3*(1+Inputs!B4)^INT((VI1-1)/12)*(1-Hidden!B1) | VJ3: =Inputs!B3*(1+Inputs!B4)^INT((VJ1-1)/12)*(1-Hidden!B1) | VK3: =Inputs!B3*(1+Inputs!B4)^INT((VK1-1)/12)*(1-Hidden!B1) | VL3: =Inputs!B3*(1+Inputs!B4)^INT((VL1-1)/12)*(1-Hidden!B1) | VM3: =Inputs!B3*(1+Inputs!B4)^INT((VM1-1)/12)*(1-Hidden!B1) | VN3: =Inputs!B3*(1+Inputs!B4)^INT((VN1-1)/12)*(1-Hidden!B1) | VO3: =Inputs!B3*(1+Inputs!B4)^INT((VO1-1)/12)*(1-Hidden!B1) | VP3: =Inputs!B3*(1+Inputs!B4)^INT((VP1-1)/12)*(1-Hidden!B1) | VQ3: =Inputs!B3*(1+Inputs!B4)^INT((VQ1-1)/12)*(1-Hidden!B1) | VR3: =Inputs!B3*(1+Inputs!B4)^INT((VR1-1)/12)*(1-Hidden!B1) | VS3: =Inputs!B3*(1+Inputs!B4)^INT((VS1-1)/12)*(1-Hidden!B1) | VT3: =Inputs!B3*(1+Inputs!B4)^INT((VT1-1)/12)*(1-Hidden!B1) | VU3: =Inputs!B3*(1+Inputs!B4)^INT((VU1-1)/12)*(1-Hidden!B1) | VV3: =Inputs!B3*(1+Inputs!B4)^INT((VV1-1)/12)*(1-Hidden!B1) | VW3: =Inputs!B3*(1+Inputs!B4)^INT((VW1-1)/12)*(1-Hidden!B1) | VX3: =Inputs!B3*(1+Inputs!B4)^INT((VX1-1)/12)*(1-Hidden!B1) | VY3: =Inputs!B3*(1+Inputs!B4)^INT((VY1-1)/12)*(1-Hidden!B1) | VZ3: =Inputs!B3*(1+Inputs!B4)^INT((VZ1-1)/12)*(1-Hidden!B1) | WA3: =Inputs!B3*(1+Inputs!B4)^INT((WA1-1)/12)*(1-Hidden!B1) | WB3: =Inputs!B3*(1+Inputs!B4)^INT((WB1-1)/12)*(1-Hidden!B1) | WC3: =Inputs!B3*(1+Inputs!B4)^INT((WC1-1)/12)*(1-Hidden!B1) | WD3: =Inputs!B3*(1+Inputs!B4)^INT((WD1-1)/12)*(1-Hidden!B1)+Inputs!B3*12*(1+Inputs!B4)^50/Inputs!B5

Sheet Returns
A1: Unlevered IRR | B1: =XIRR('Cash Flow'!B3:WD3,'Cash Flow'!B2:WD2)
A2: Net profit | B2: =SUM('Cash Flow'!B3:WD3)
