Workbook

Sheet Dashboard
B2: AL RAWDAH RESIDENCES (BTR) · DASHBOARD (SAR)
B5: Unlevered IRR | C5: =(1+IRR(CF!C16:AI16))^4-1 -> 0.13851777
B6: Levered IRR | C6: =(1+IRR(CF!C27:AI27))^4-1 -> 0.23355931
B7: Yield on cost (stabilised) | C7: =INDEX(CF!C10:AI10,1,ROUND(Assumptions!C14,0)+ROUND(Assumptions!C15,0)+ROUND(Assumptions!C16,0)+1)*4/-SUM(CF!C12:AI14) -> 0.091089497
B8: Equity multiple | C8: =SUMIF(CF!C27:AI27,">0")/-SUMIF(CF!C27:AI27,"<0") -> 2.755709
B9: Total development cost | C9: =-SUM(CF!C12:AI14) -> 284336750
B10: Levered profit | C10: =SUM(CF!C27:AI27) -> 2.2109557e+08

Sheet Assumptions
B2: AL RAWDAH RESIDENCES (BTR) · ASSUMPTIONS (SAR)
B4: Unit mix | C4: Units | D4: Size (sqm) | E4: Rent (a month)
B5: Studio | C5: 60 | D5: 42 | E5: 4200
B6: 1-bed | C6: 140 | D6: 68 | E6: 6100
B7: 2-bed | C7: 110 | D7: 105 | E7: 8600
B8: 3-bed | C8: 40 | D8: 150 | E8: 11800
B9: Total | C9: =SUM(C5:C8) -> 350 | E9: =SUMPRODUCT(C5:C8,E5:E8) -> 2524000
B11: Land | C11: 38000000
B12: Construction cost per sqm | C12: 7500
B13: Soft costs (% of construction) | C13: 0.11
B14: Construction start (quarter) | C14: 1
B15: Construction length (quarters) | C15: 6
B16: Lease-up (quarters to stabilise) | C16: 4
B17: Stabilised occupancy | C17: 0.94
B18: Rent growth (a year) | C18: 0.03
B19: Operating costs per unit (a year) | C19: 9500
B20: Exit quarter | C20: 28
B21: Exit cap rate | C21: 0.065
B22: Selling costs | C22: 0.015
... B27: Refinance cap rate | C27: 0.065

Sheet CF
B2: QUARTERLY CASH FLOW (SAR)
B3: Quarter ending | C3: 46112 | D3: 46203 | E3: 46295 | F3: 46387 | G3: 46477 | H3: 46568 | I3: 46660 | J3: 46752 | K3: 46843 | L3: 46934 | M3: 47026 | N3: 47118 | O3: 47208 | P3: 47299 | Q3: 47391 | R3: 47483 | S3: 47573 | T3: 47664 | U3: 47756 | V3: 47848 | W3: 47938 | X3: 48029 | Y3: 48121 | Z3: 48213 | AA3: 48304 | AB3: 48395 | AC3: 48487 | AD3: 48579 | AE3: 48669 | AF3: 48760 | AG3: 48852 | AH3: 48944 | AI3: 49034
B4: Quarter | C4: 0 | D4: 1 | E4: 2 | F4: 3 | G4: 4 | H4: 5 | I4: 6 | J4: 7 | K4: 8 | L4: 9 | M4: 10 | N4: 11 | O4: 12 | P4: 13 | Q4: 14 | R4: 15 | S4: 16 | T4: 17 | U4: 18 | V4: 19 | W4: 20 | X4: 21 | Y4: 22 | Z4: 23 | AA4: 24 | AB4: 25 | AC4: 26 | AD4: 27 | AE4: 28 | AF4: 29 | AG4: 30 | AH4: 31 | AI4: 32
B6: Construction progress | C6: =IF(AND(C$4>=ROUND(Assumptions!$C$14,0),C$4<(ROUND(Assumptions!$C$14,0)+ROUND(Assumptions!$C$15,0))),1/ROUND(Assumptions!$C$15,0),0) -> 0 | D6: =IF(AND(D$4>=ROUND(Assumptions!$C$14,0),D$4<(ROUND(Assumptions!$C$14,0)+ROUND(Assumptions!$C$15,0))),1/ROUND(Assumptions!$C$15,0),0) -> 0.16666667 | E6: =IF(AND(E$4>=ROUND(Assumptions!$C$14,0),E$4<(ROUND(Assumptions!$C$14,0)+ROUND(Assumptions!$C$15,0))),1/ROUND(Assumptions!$C$15,0),0) -> 0.16666667 | F6: =IF(AND(F$4>=ROUND(Assumptions!$C$14,0),F$4<(ROUND(Assumptions!$C$14,0)+ROUND(Assumptions!$C$15,0))),1/ROUND(Assumptions!$C$15,0),0) -> 0.16666667 | G6: =IF(AND(G$4>=ROUND(Assumptions!$C$14,0),G$4<(ROUND(Assumptions!$C$14,0)+ROUND(Assumptions!$C$15,0))),1/ROUND(Assumptions!$C$15,0),0) -> 0.16666667 | H6: =IF(AND(H$4>=ROUND(Assumptions!$C$14,0),H$4<(ROUND(Assumptions!$C$14,0)+ROUND(Assumptions!$C$15,0))),1/ROUND(Assumptions!$C$15,0),0) -> 0.16666667 | I6: =IF(AND(I$4>=ROUND(Assumptions!$C$14,0),I$4<(ROUND(Assumptions!$C$14,0)+ROUND(Assumptions!$C$15,0))),1/ROUND(Assumptions!$C$15,0),0) -> 0.16666667 | J6: =IF(AND(J$4>=ROUND(Assumptions!$C$14,0),J$4<(ROUND(Assumptions!$C$14,0)+ROUND(Assumptions!$C$15,0))),1/ROUND(Assumptions!$C$15,0),0) -> 0 | ... AI6: =IF(AND(AI$4>=ROUND(Assumptions!$C$14,0),AI$4<(ROUND(Assumptions!$C$14,0)+ROUND(Assumptions!$C$15,0))),1/ROUND(Assumptions!$C$15,0),0) -> 0
B7: Occupancy | C7: =IF(C$4<(ROUND(Assumptions!$C$14,0)+ROUND(Assumptions!$C$15,0)),0,Assumptions!$C$17*MIN(1,(C$4-(ROUND(Assumptions!$C$14,0)+ROUND(Assumptions!$C$15,0))+1)/ROUND(Assumptions!$C$16,0))) -> 0 | D7: =IF(D$4<(ROUND(Assumptions!$C$14,0)+ROUND(Assumptions!$C$15,0)),0,Assumptions!$C$17*MIN(1,(D$4-(ROUND(Assumptions!$C$14,0)+ROUND(Assumptions!$C$15,0))+1)/ROUND(Assumptions!$C$16,0))) -> 0 | E7: =IF(E$4<(ROUND(Assumptions!$C$14,0)+ROUND(Assumptions!$C$15,0)),0,Assumptions!$C$17*MIN(1,(E$4-(ROUND(Assumptions!$C$14,0)+ROUND(Assumptions!$C$15,0))+1)/ROUND(Assumptions!$C$16,0))) -> 0 | F7: =IF(F$4<(ROUND(Assumptions!$C$14,0)+ROUND(Assumptions!$C$15,0)),0,Assumptions!$C$17*MIN(1,(F$4-(ROUND(Assumptions!$C$14,0)+ROUND(Assumptions!$C$15,0))+1)/ROUND(Assumptions!$C$16,0))) -> 0 | G7: =IF(G$4<(ROUND(Assumptions!$C$14,0)+ROUND(Assumptions!$C$15,0)),0,Assumptions!$C$17*MIN(1,(G$4-(ROUND(Assumptions!$C$14,0)+ROUND(Assumptions!$C$15,0))+1)/ROUND(Assumptions!$C$16,0))) -> 0 | H7: =IF(H$4<(ROUND(Assumptions!$C$14,0)+ROUND(Assumptions!$C$15,0)),0,Assumptions!$C$17*MIN(1,(H$4-(ROUND(Assumptions!$C$14,0)+ROUND(Assumptions!$C$15,0))+1)/ROUND(Assumptions!$C$16,0))) -> 0 | I7: =IF(I$4<(ROUND(Assumptions!$C$14,0)+ROUND(Assumptions!$C$15,0)),0,Assumptions!$C$17*MIN(1,(I$4-(ROUND(Assumptions!$C$14,0)+ROUND(Assumptions!$C$15,0))+1)/ROUND(Assumptions!$C$16,0))) -> 0 | J7: =IF(J$4<(ROUND(Assumptions!$C$14,0)+ROUND(Assumptions!$C$15,0)),0,Assumptions!$C$17*MIN(1,(J$4-(ROUND(Assumptions!$C$14,0)+ROUND(Assumptions!$C$15,0))+1)/ROUND(Assumptions!$C$16,0))) -> 0.235 | ... AI7: =IF(AI$4<(ROUND(Assumptions!$C$14,0)+ROUND(Assumptions!$C$15,0)),0,Assumptions!$C$17*MIN(1,(AI$4-(ROUND(Assumptions!$C$14,0)+ROUND(Assumptions!$C$15,0))+1)/ROUND(Assumptions!$C$16,0))) -> 0.94
B8: Rent | C8: =Assumptions!$E$9*3*C7*(1+Assumptions!$C$18)^(MAX(0,C$4-(ROUND(Assumptions!$C$14,0)+ROUND(Assumptions!$C$15,0)))/4) -> 0 | D8: =Assumptions!$E$9*3*D7*(1+Assumptions!$C$18)^(MAX(0,D$4-(ROUND(Assumptions!$C$14,0)+ROUND(Assumptions!$C$15,0)))/4) -> 0 | E8: =Assumptions!$E$9*3*E7*(1+Assumptions!$C$18)^(MAX(0,E$4-(ROUND(Assumptions!$C$14,0)+ROUND(Assumptions!$C$15,0)))/4) -> 0 | F8: =Assumptions!$E$9*3*F7*(1+Assumptions!$C$18)^(MAX(0,F$4-(ROUND(Assumptions!$C$14,0)+ROUND(Assumptions!$C$15,0)))/4) -> 0 | G8: =Assumptions!$E$9*3*G7*(1+Assumptions!$C$18)^(MAX(0,G$4-(ROUND(Assumptions!$C$14,0)+ROUND(Assumptions!$C$15,0)))/4) -> 0 | H8: =Assumptions!$E$9*3*H7*(1+Assumptions!$C$18)^(MAX(0,H$4-(ROUND(Assumptions!$C$14,0)+ROUND(Assumptions!$C$15,0)))/4) -> 0 | I8: =Assumptions!$E$9*3*I7*(1+Assumptions!$C$18)^(MAX(0,I$4-(ROUND(Assumptions!$C$14,0)+ROUND(Assumptions!$C$15,0)))/4) -> 0 | J8: =Assumptions!$E$9*3*J7*(1+Assumptions!$C$18)^(MAX(0,J$4-(ROUND(Assumptions!$C$14,0)+ROUND(Assumptions!$C$15,0)))/4) -> 1779420 | ... AI8: =Assumptions!$E$9*3*AI7*(1+Assumptions!$C$18)^(MAX(0,AI$4-(ROUND(Assumptions!$C$14,0)+ROUND(Assumptions!$C$15,0)))/4) -> 8561919
B9: Operating costs | C9: =IF(C$4<(ROUND(Assumptions!$C$14,0)+ROUND(Assumptions!$C$15,0)),0,-Assumptions!$C$9*Assumptions!$C$19/4*(1+Assumptions!$C$18)^(MAX(0,C$4-(ROUND(Assumptions!$C$14,0)+ROUND(Assumptions!$C$15,0)))/4)) -> 0 | D9: =IF(D$4<(ROUND(Assumptions!$C$14,0)+ROUND(Assumptions!$C$15,0)),0,-Assumptions!$C$9*Assumptions!$C$19/4*(1+Assumptions!$C$18)^(MAX(0,D$4-(ROUND(Assumptions!$C$14,0)+ROUND(Assumptions!$C$15,0)))/4)) -> 0 | E9: =IF(E$4<(ROUND(Assumptions!$C$14,0)+ROUND(Assumptions!$C$15,0)),0,-Assumptions!$C$9*Assumptions!$C$19/4*(1+Assumptions!$C$18)^(MAX(0,E$4-(ROUND(Assumptions!$C$14,0)+ROUND(Assumptions!$C$15,0)))/4)) -> 0 | F9: =IF(F$4<(ROUND(Assumptions!$C$14,0)+ROUND(Assumptions!$C$15,0)),0,-Assumptions!$C$9*Assumptions!$C$19/4*(1+Assumptions!$C$18)^(MAX(0,F$4-(ROUND(Assumptions!$C$14,0)+ROUND(Assumptions!$C$15,0)))/4)) -> 0 | G9: =IF(G$4<(ROUND(Assumptions!$C$14,0)+ROUND(Assumptions!$C$15,0)),0,-Assumptions!$C$9*Assumptions!$C$19/4*(1+Assumptions!$C$18)^(MAX(0,G$4-(ROUND(Assumptions!$C$14,0)+ROUND(Assumptions!$C$15,0)))/4)) -> 0 | H9: =IF(H$4<(ROUND(Assumptions!$C$14,0)+ROUND(Assumptions!$C$15,0)),0,-Assumptions!$C$9*Assumptions!$C$19/4*(1+Assumptions!$C$18)^(MAX(0,H$4-(ROUND(Assumptions!$C$14,0)+ROUND(Assumptions!$C$15,0)))/4)) -> 0 | I9: =IF(I$4<(ROUND(Assumptions!$C$14,0)+ROUND(Assumptions!$C$15,0)),0,-Assumptions!$C$9*Assumptions!$C$19/4*(1+Assumptions!$C$18)^(MAX(0,I$4-(ROUND(Assumptions!$C$14,0)+ROUND(Assumptions!$C$15,0)))/4)) -> 0 | J9: =IF(J$4<(ROUND(Assumptions!$C$14,0)+ROUND(Assumptions!$C$15,0)),0,-Assumptions!$C$9*Assumptions!$C$19/4*(1+Assumptions!$C$18)^(MAX(0,J$4-(ROUND(Assumptions!$C$14,0)+ROUND(Assumptions!$C$15,0)))/4)) -> -831250 | ... AI9: =IF(AI$4<(ROUND(Assumptions!$C$14,0)+ROUND(Assumptions!$C$15,0)),0,-Assumptions!$C$9*Assumptions!$C$19/4*(1+Assumptions!$C$18)^(MAX(0,AI$4-(ROUND(Assumptions!$C$14,0)+ROUND(Assumptions!$C$15,0)))/4)) -> -999917.83
B10: NOI | C10: =C8+C9 -> 0 | D10: =D8+D9 -> 0 | E10: =E8+E9 -> 0 | F10: =F8+F9 -> 0 | G10: =G8+G9 -> 0 | H10: =H8+H9 -> 0 | I10: =I8+I9 -> 0 | J10: =J8+J9 -> 948170 | ... AI10: =AI8+AI9 -> 7562001.1
B12: Land | C12: =IF(C$4=0,-Assumptions!$C$11,0) -> -38000000 | D12: =IF(D$4=0,-Assumptions!$C$11,0) -> 0 | E12: =IF(E$4=0,-Assumptions!$C$11,0) -> 0 | F12: =IF(F$4=0,-Assumptions!$C$11,0) -> 0 | G12: =IF(G$4=0,-Assumptions!$C$11,0) -> 0 | H12: =IF(H$4=0,-Assumptions!$C$11,0) -> 0 | I12: =IF(I$4=0,-Assumptions!$C$11,0) -> 0 | J12: =IF(J$4=0,-Assumptions!$C$11,0) -> 0 | ... AI12: =IF(AI$4=0,-Assumptions!$C$11,0) -> 0
B13: Construction | C13: =-(SUMPRODUCT(Assumptions!$C$5:$C$8,Assumptions!$D$5:$D$8)*Assumptions!$C$12)*C6 -> 0 | D13: =-(SUMPRODUCT(Assumptions!$C$5:$C$8,Assumptions!$D$5:$D$8)*Assumptions!$C$12)*D6 -> -36987500 | E13: =-(SUMPRODUCT(Assumptions!$C$5:$C$8,Assumptions!$D$5:$D$8)*Assumptions!$C$12)*E6 -> -36987500 | F13: =-(SUMPRODUCT(Assumptions!$C$5:$C$8,Assumptions!$D$5:$D$8)*Assumptions!$C$12)*F6 -> -36987500 | G13: =-(SUMPRODUCT(Assumptions!$C$5:$C$8,Assumptions!$D$5:$D$8)*Assumptions!$C$12)*G6 -> -36987500 | H13: =-(SUMPRODUCT(Assumptions!$C$5:$C$8,Assumptions!$D$5:$D$8)*Assumptions!$C$12)*H6 -> -36987500 | I13: =-(SUMPRODUCT(Assumptions!$C$5:$C$8,Assumptions!$D$5:$D$8)*Assumptions!$C$12)*I6 -> -36987500 | J13: =-(SUMPRODUCT(Assumptions!$C$5:$C$8,Assumptions!$D$5:$D$8)*Assumptions!$C$12)*J6 -> 0 | ... AI13: =-(SUMPRODUCT(Assumptions!$C$5:$C$8,Assumptions!$D$5:$D$8)*Assumptions!$C$12)*AI6 -> 0
B14: Soft costs | C14: =C13*Assumptions!$C$13 -> 0 | D14: =D13*Assumptions!$C$13 -> -4068625 | E14: =E13*Assumptions!$C$13 -> -4068625 | F14: =F13*Assumptions!$C$13 -> -4068625 | G14: =G13*Assumptions!$C$13 -> -4068625 | H14: =H13*Assumptions!$C$13 -> -4068625 | I14: =I13*Assumptions!$C$13 -> -4068625 | J14: =J13*Assumptions!$C$13 -> 0 | ... AI14: =AI13*Assumptions!$C$13 -> 0
B15: Sale (net) | C15: =IF(C$4=ROUND(Assumptions!$C$20,0),D10*4/Assumptions!$C$21*(1-Assumptions!$C$22),0) -> 0 | D15: =IF(D$4=ROUND(Assumptions!$C$20,0),E10*4/Assumptions!$C$21*(1-Assumptions!$C$22),0) -> 0 | E15: =IF(E$4=ROUND(Assumptions!$C$20,0),F10*4/Assumptions!$C$21*(1-Assumptions!$C$22),0) -> 0 | F15: =IF(F$4=ROUND(Assumptions!$C$20,0),G10*4/Assumptions!$C$21*(1-Assumptions!$C$22),0) -> 0 | G15: =IF(G$4=ROUND(Assumptions!$C$20,0),H10*4/Assumptions!$C$21*(1-Assumptions!$C$22),0) -> 0 | H15: =IF(H$4=ROUND(Assumptions!$C$20,0),I10*4/Assumptions!$C$21*(1-Assumptions!$C$22),0) -> 0 | I15: =IF(I$4=ROUND(Assumptions!$C$20,0),J10*4/Assumptions!$C$21*(1-Assumptions!$C$22),0) -> 0 | J15: =IF(J$4=ROUND(Assumptions!$C$20,0),K10*4/Assumptions!$C$21*(1-Assumptions!$C$22),0) -> 0 | ... AH15: =IF(AH$4=ROUND(Assumptions!$C$20,0),AI10*4/Assumptions!$C$21*(1-Assumptions!$C$22),0) -> 0 | AI15: =0 -> 0
B16: Unlevered cash flow | C16: =IF(C$4>ROUND(Assumptions!$C$20,0),0,C10+C12+C13+C14+C15) -> -38000000 | D16: =IF(D$4>ROUND(Assumptions!$C$20,0),0,D10+D12+D13+D14+D15) -> -41056125 | E16: =IF(E$4>ROUND(Assumptions!$C$20,0),0,E10+E12+E13+E14+E15) -> -41056125 | F16: =IF(F$4>ROUND(Assumptions!$C$20,0),0,F10+F12+F13+F14+F15) -> -41056125 | G16: =IF(G$4>ROUND(Assumptions!$C$20,0),0,G10+G12+G13+G14+G15) -> -41056125 | H16: =IF(H$4>ROUND(Assumptions!$C$20,0),0,H10+H12+H13+H14+H15) -> -41056125 | I16: =IF(I$4>ROUND(Assumptions!$C$20,0),0,I10+I12+I13+I14+I15) -> -41056125 | J16: =IF(J$4>ROUND(Assumptions!$C$20,0),0,J10+J12+J13+J14+J15) -> 948170 | ... AI16: =IF(AI$4>ROUND(Assumptions!$C$20,0),0,AI10+AI12+AI13+AI14+AI15) -> 0
B18: Construction loan draw | C18: =-(C12+C13+C14)*Assumptions!$C$23 -> 22800000 | D18: =-(D12+D13+D14)*Assumptions!$C$23 -> 24633675 | E18: =-(E12+E13+E14)*Assumptions!$C$23 -> 24633675 | F18: =-(F12+F13+F14)*Assumptions!$C$23 -> 24633675 | G18: =-(G12+G13+G14)*Assumptions!$C$23 -> 24633675 | H18: =-(H12+H13+H14)*Assumptions!$C$23 -> 24633675 | I18: =-(I12+I13+I14)*Assumptions!$C$23 -> 24633675 | J18: =-(J12+J13+J14)*Assumptions!$C$23 -> 0 | ... AI18: =-(AI12+AI13+AI14)*Assumptions!$C$23 -> 0
B19: Construction loan interest | C19: =-0*Assumptions!$C$24/4 -> 0 | D19: =-C21*Assumptions!$C$24/4 -> -427500 | E19: =-D21*Assumptions!$C$24/4 -> -889381.41 | F19: =-E21*Assumptions!$C$24/4 -> -1351262.8 | G19: =-F21*Assumptions!$C$24/4 -> -1813144.2 | H19: =-G21*Assumptions!$C$24/4 -> -2275025.6 | I19: =-H21*Assumptions!$C$24/4 -> -2736907 | J19: =-I21*Assumptions!$C$24/4 -> -3198788.4 | K19: =-J21*Assumptions!$C$24/4 -> -3198788.4 | ... AI19: =-AH21*Assumptions!$C$24/4 -> 0
B20: Construction loan repayment | C20: =-IF(C$4=((ROUND(Assumptions!$C$14,0)+ROUND(Assumptions!$C$15,0))+ROUND(Assumptions!$C$16,0)),0+C18,0) -> 0 | D20: =-IF(D$4=((ROUND(Assumptions!$C$14,0)+ROUND(Assumptions!$C$15,0))+ROUND(Assumptions!$C$16,0)),C21+D18,0) -> 0 | E20: =-IF(E$4=((ROUND(Assumptions!$C$14,0)+ROUND(Assumptions!$C$15,0))+ROUND(Assumptions!$C$16,0)),D21+E18,0) -> 0 | F20: =-IF(F$4=((ROUND(Assumptions!$C$14,0)+ROUND(Assumptions!$C$15,0))+ROUND(Assumptions!$C$16,0)),E21+F18,0) -> 0 | G20: =-IF(G$4=((ROUND(Assumptions!$C$14,0)+ROUND(Assumptions!$C$15,0))+ROUND(Assumptions!$C$16,0)),F21+G18,0) -> 0 | H20: =-IF(H$4=((ROUND(Assumptions!$C$14,0)+ROUND(Assumptions!$C$15,0))+ROUND(Assumptions!$C$16,0)),G21+H18,0) -> 0 | I20: =-IF(I$4=((ROUND(Assumptions!$C$14,0)+ROUND(Assumptions!$C$15,0))+ROUND(Assumptions!$C$16,0)),H21+I18,0) -> 0 | J20: =-IF(J$4=((ROUND(Assumptions!$C$14,0)+ROUND(Assumptions!$C$15,0))+ROUND(Assumptions!$C$16,0)),I21+J18,0) -> 0 | K20: =-IF(K$4=((ROUND(Assumptions!$C$14,0)+ROUND(Assumptions!$C$15,0))+ROUND(Assumptions!$C$16,0)),J21+K18,0) -> 0 | ... AI20: =-IF(AI$4=((ROUND(Assumptions!$C$14,0)+ROUND(Assumptions!$C$15,0))+ROUND(Assumptions!$C$16,0)),AH21+AI18,0) -> 0
B21: Construction loan balance | C21: =0+C18+C20 -> 22800000 | D21: =C21+D18+D20 -> 47433675 | E21: =D21+E18+E20 -> 72067350 | F21: =E21+F18+F20 -> 96701025 | G21: =F21+G18+G20 -> 121334700 | H21: =G21+H18+H20 -> 145968375 | I21: =H21+I18+I20 -> 170602050 | J21: =I21+J18+J20 -> 170602050 | K21: =J21+K18+K20 -> 170602050 | ... AI21: =AH21+AI18+AI20 -> 0
B22: Investment loan draw | C22: =IF(C$4=((ROUND(Assumptions!$C$14,0)+ROUND(Assumptions!$C$15,0))+ROUND(Assumptions!$C$16,0)),D10*4/Assumptions!$C$27*Assumptions!$C$25,0) -> 0 | D22: =IF(D$4=((ROUND(Assumptions!$C$14,0)+ROUND(Assumptions!$C$15,0))+ROUND(Assumptions!$C$16,0)),E10*4/Assumptions!$C$27*Assumptions!$C$25,0) -> 0 | E22: =IF(E$4=((ROUND(Assumptions!$C$14,0)+ROUND(Assumptions!$C$15,0))+ROUND(Assumptions!$C$16,0)),F10*4/Assumptions!$C$27*Assumptions!$C$25,0) -> 0 | F22: =IF(F$4=((ROUND(Assumptions!$C$14,0)+ROUND(Assumptions!$C$15,0))+ROUND(Assumptions!$C$16,0)),G10*4/Assumptions!$C$27*Assumptions!$C$25,0) -> 0 | G22: =IF(G$4=((ROUND(Assumptions!$C$14,0)+ROUND(Assumptions!$C$15,0))+ROUND(Assumptions!$C$16,0)),H10*4/Assumptions!$C$27*Assumptions!$C$25,0) -> 0 | H22: =IF(H$4=((ROUND(Assumptions!$C$14,0)+ROUND(Assumptions!$C$15,0))+ROUND(Assumptions!$C$16,0)),I10*4/Assumptions!$C$27*Assumptions!$C$25,0) -> 0 | I22: =IF(I$4=((ROUND(Assumptions!$C$14,0)+ROUND(Assumptions!$C$15,0))+ROUND(Assumptions!$C$16,0)),J10*4/Assumptions!$C$27*Assumptions!$C$25,0) -> 0 | J22: =IF(J$4=((ROUND(Assumptions!$C$14,0)+ROUND(Assumptions!$C$15,0))+ROUND(Assumptions!$C$16,0)),K10*4/Assumptions!$C$27*Assumptions!$C$25,0) -> 0 | ... AH22: =IF(AH$4=((ROUND(Assumptions!$C$14,0)+ROUND(Assumptions!$C$15,0))+ROUND(Assumptions!$C$16,0)),AI10*4/Assumptions!$C$27*Assumptions!$C$25,0) -> 0 | AI22: =0 -> 0
B23: Investment loan interest | C23: =-0*Assumptions!$C$26/4 -> 0 | D23: =-C25*Assumptions!$C$26/4 -> 0 | E23: =-D25*Assumptions!$C$26/4 -> 0 | F23: =-E25*Assumptions!$C$26/4 -> 0 | G23: =-F25*Assumptions!$C$26/4 -> 0 | H23: =-G25*Assumptions!$C$26/4 -> 0 | I23: =-H25*Assumptions!$C$26/4 -> 0 | J23: =-I25*Assumptions!$C$26/4 -> 0 | K23: =-J25*Assumptions!$C$26/4 -> 0 | ... AI23: =-AH25*Assumptions!$C$26/4 -> 0
B24: Investment loan repayment | C24: =-IF(C$4=ROUND(Assumptions!$C$20,0),0+C22,0) -> 0 | D24: =-IF(D$4=ROUND(Assumptions!$C$20,0),C25+D22,0) -> 0 | E24: =-IF(E$4=ROUND(Assumptions!$C$20,0),D25+E22,0) -> 0 | F24: =-IF(F$4=ROUND(Assumptions!$C$20,0),E25+F22,0) -> 0 | G24: =-IF(G$4=ROUND(Assumptions!$C$20,0),F25+G22,0) -> 0 | H24: =-IF(H$4=ROUND(Assumptions!$C$20,0),G25+H22,0) -> 0 | I24: =-IF(I$4=ROUND(Assumptions!$C$20,0),H25+I22,0) -> 0 | J24: =-IF(J$4=ROUND(Assumptions!$C$20,0),I25+J22,0) -> 0 | K24: =-IF(K$4=ROUND(Assumptions!$C$20,0),J25+K22,0) -> 0 | ... AI24: =-IF(AI$4=ROUND(Assumptions!$C$20,0),AH25+AI22,0) -> 0
B25: Investment loan balance | C25: =0+C22+C24 -> 0 | D25: =C25+D22+D24 -> 0 | E25: =D25+E22+E24 -> 0 | F25: =E25+F22+F24 -> 0 | G25: =F25+G22+G24 -> 0 | H25: =G25+H22+H24 -> 0 | I25: =H25+I22+I24 -> 0 | J25: =I25+J22+J24 -> 0 | K25: =J25+K22+K24 -> 0 | ... AI25: =AH25+AI22+AI24 -> 0
B27: Levered cash flow | C27: =IF(C$4>ROUND(Assumptions!$C$20,0),0,C16+C18+C19+C20+C22+C23+C24) -> -15200000 | D27: =IF(D$4>ROUND(Assumptions!$C$20,0),0,D16+D18+D19+D20+D22+D23+D24) -> -16849950 | E27: =IF(E$4>ROUND(Assumptions!$C$20,0),0,E16+E18+E19+E20+E22+E23+E24) -> -17311831 | F27: =IF(F$4>ROUND(Assumptions!$C$20,0),0,F16+F18+F19+F20+F22+F23+F24) -> -17773713 | G27: =IF(G$4>ROUND(Assumptions!$C$20,0),0,G16+G18+G19+G20+G22+G23+G24) -> -18235594 | H27: =IF(H$4>ROUND(Assumptions!$C$20,0),0,H16+H18+H19+H20+H22+H23+H24) -> -18697476 | I27: =IF(I$4>ROUND(Assumptions!$C$20,0),0,I16+I18+I19+I20+I22+I23+I24) -> -19159357 | J27: =IF(J$4>ROUND(Assumptions!$C$20,0),0,J16+J18+J19+J20+J22+J23+J24) -> -2250618.4 | ... AI27: =IF(AI$4>ROUND(Assumptions!$C$20,0),0,AI16+AI18+AI19+AI20+AI22+AI23+AI24) -> 0
