Workbook

Sheet Fund Report
B2: AL NOOR INCOME FUND · FUND REPORT (SAR)
B5: NAV per unit (year 1) | C5: =NAV!D15 -> 11.822086
B6: NAV per unit (start) | C6: =NAV!C15 -> 11.415925
B7: Distribution yield | C7: =-NAV!D11/NAV!D14/NAV!C15 -> 0.056257024
B8: Income return | C8: =NAV!D10/NAV!C13 -> 0.066158132
B9: Total return (a year) | C9: =(NAV!D15-NAV!C15-NAV!D11/NAV!D14)/NAV!C15 -> 0.091835415
B10: Gearing (LTV) | C10: =Portfolio!C11/NAV!D6 -> 0.31516168
B11: Gross asset value | C11: =NAV!D6 -> 2.0624335e+09
B12: NAV | C12: =NAV!D13 -> 1.5014966e+09

Sheet Portfolio
B2: AL NOOR INCOME FUND · PORTFOLIO (SAR)
B4: Asset | C4: NOI year 1 | D4: Cap rate | E4: NOI growth
B5: Riyadh logistics park | C5: 42000000 | D5: 0.0675 | E5: 0.025
B6: Jeddah retail centre | C6: 36500000 | D6: 0.075 | E6: 0.015
B7: Khobar offices | C7: 21000000 | D7: 0.08 | E7: 0.01
B8: Riyadh residential compound | C8: 28500000 | D8: 0.07 | E8: 0.03
B9: Dammam warehouses | C9: 17500000 | D9: 0.0725 | E9: 0.02
B11: Fund debt | C11: 650000000
B12: Debt cost | C12: 0.058
B13: Fund costs (% of GAV) | C13: 0.0085
B14: Payout (% of net income) | C14: 0.9
B15: Units in issue (start) | C15: 120000000
B16: Net subscriptions (SAR a year) | C16: 80000000

Sheet NAV
B2: NAV BRIDGE (SAR)
B4: Year | C4: 0 | D4: 1 | E4: 2 | F4: 3 | G4: 4 | H4: 5
B6: Gross asset value | C6: =Portfolio!$C$5*(1+Portfolio!$E$5)^C$4/Portfolio!$D$5+Portfolio!$C$6*(1+Portfolio!$E$6)^C$4/Portfolio!$D$6+Portfolio!$C$7*(1+Portfolio!$E$7)^C$4/Portfolio!$D$7+Portfolio!$C$8*(1+Portfolio!$E$8)^C$4/Portfolio!$D$8+Portfolio!$C$9*(1+Portfolio!$E$9)^C$4/Portfolio!$D$9 -> 2.0199111e+09 | D6: =Portfolio!$C$5*(1+Portfolio!$E$5)^D$4/Portfolio!$D$5+Portfolio!$C$6*(1+Portfolio!$E$6)^D$4/Portfolio!$D$6+Portfolio!$C$7*(1+Portfolio!$E$7)^D$4/Portfolio!$D$7+Portfolio!$C$8*(1+Portfolio!$E$8)^D$4/Portfolio!$D$8+Portfolio!$C$9*(1+Portfolio!$E$9)^D$4/Portfolio!$D$9 -> 2.0624335e+09 | E6: =Portfolio!$C$5*(1+Portfolio!$E$5)^E$4/Portfolio!$D$5+Portfolio!$C$6*(1+Portfolio!$E$6)^E$4/Portfolio!$D$6+Portfolio!$C$7*(1+Portfolio!$E$7)^E$4/Portfolio!$D$7+Portfolio!$C$8*(1+Portfolio!$E$8)^E$4/Portfolio!$D$8+Portfolio!$C$9*(1+Portfolio!$E$9)^E$4/Portfolio!$D$9 -> 2.1059435e+09 | F6: =Portfolio!$C$5*(1+Portfolio!$E$5)^F$4/Portfolio!$D$5+Portfolio!$C$6*(1+Portfolio!$E$6)^F$4/Portfolio!$D$6+Portfolio!$C$7*(1+Portfolio!$E$7)^F$4/Portfolio!$D$7+Portfolio!$C$8*(1+Portfolio!$E$8)^F$4/Portfolio!$D$8+Portfolio!$C$9*(1+Portfolio!$E$9)^F$4/Portfolio!$D$9 -> 2.1504657e+09 | G6: =Portfolio!$C$5*(1+Portfolio!$E$5)^G$4/Portfolio!$D$5+Portfolio!$C$6*(1+Portfolio!$E$6)^G$4/Portfolio!$D$6+Portfolio!$C$7*(1+Portfolio!$E$7)^G$4/Portfolio!$D$7+Portfolio!$C$8*(1+Portfolio!$E$8)^G$4/Portfolio!$D$8+Portfolio!$C$9*(1+Portfolio!$E$9)^G$4/Portfolio!$D$9 -> 2.1960253e+09 | H6: =Portfolio!$C$5*(1+Portfolio!$E$5)^H$4/Portfolio!$D$5+Portfolio!$C$6*(1+Portfolio!$E$6)^H$4/Portfolio!$D$6+Portfolio!$C$7*(1+Portfolio!$E$7)^H$4/Portfolio!$D$7+Portfolio!$C$8*(1+Portfolio!$E$8)^H$4/Portfolio!$D$8+Portfolio!$C$9*(1+Portfolio!$E$9)^H$4/Portfolio!$D$9 -> 2.2426481e+09
B7: Net operating income | C7: =0 -> 0 | D7: =Portfolio!$C$5*(1+Portfolio!$E$5)^(D$4-1)+Portfolio!$C$6*(1+Portfolio!$E$6)^(D$4-1)+Portfolio!$C$7*(1+Portfolio!$E$7)^(D$4-1)+Portfolio!$C$8*(1+Portfolio!$E$8)^(D$4-1)+Portfolio!$C$9*(1+Portfolio!$E$9)^(D$4-1) -> 145500000 | E7: =Portfolio!$C$5*(1+Portfolio!$E$5)^(E$4-1)+Portfolio!$C$6*(1+Portfolio!$E$6)^(E$4-1)+Portfolio!$C$7*(1+Portfolio!$E$7)^(E$4-1)+Portfolio!$C$8*(1+Portfolio!$E$8)^(E$4-1)+Portfolio!$C$9*(1+Portfolio!$E$9)^(E$4-1) -> 148512500 | F7: =Portfolio!$C$5*(1+Portfolio!$E$5)^(F$4-1)+Portfolio!$C$6*(1+Portfolio!$E$6)^(F$4-1)+Portfolio!$C$7*(1+Portfolio!$E$7)^(F$4-1)+Portfolio!$C$8*(1+Portfolio!$E$8)^(F$4-1)+Portfolio!$C$9*(1+Portfolio!$E$9)^(F$4-1) -> 1.5159421e+08 | G7: =Portfolio!$C$5*(1+Portfolio!$E$5)^(G$4-1)+Portfolio!$C$6*(1+Portfolio!$E$6)^(G$4-1)+Portfolio!$C$7*(1+Portfolio!$E$7)^(G$4-1)+Portfolio!$C$8*(1+Portfolio!$E$8)^(G$4-1)+Portfolio!$C$9*(1+Portfolio!$E$9)^(G$4-1) -> 1.5474685e+08 | H7: =Portfolio!$C$5*(1+Portfolio!$E$5)^(H$4-1)+Portfolio!$C$6*(1+Portfolio!$E$6)^(H$4-1)+Portfolio!$C$7*(1+Portfolio!$E$7)^(H$4-1)+Portfolio!$C$8*(1+Portfolio!$E$8)^(H$4-1)+Portfolio!$C$9*(1+Portfolio!$E$9)^(H$4-1) -> 1.5797216e+08
B8: Debt cost | C8: =0 -> 0 | D8: =-Portfolio!$C$11*Portfolio!$C$12 -> -37700000 | E8: =-Portfolio!$C$11*Portfolio!$C$12 -> -37700000 | F8: =-Portfolio!$C$11*Portfolio!$C$12 -> -37700000 | G8: =-Portfolio!$C$11*Portfolio!$C$12 -> -37700000 | H8: =-Portfolio!$C$11*Portfolio!$C$12 -> -37700000
B9: Fund costs | C9: =0 -> 0 | D9: =-C6*Portfolio!$C$13 -> -17169244 | E9: =-D6*Portfolio!$C$13 -> -17530685 | F9: =-E6*Portfolio!$C$13 -> -17900520 | G9: =-F6*Portfolio!$C$13 -> -18278959 | H9: =-G6*Portfolio!$C$13 -> -18666215
B10: Net income | C10: =SUM(C7:C9) -> 0 | D10: =SUM(D7:D9) -> 90630756 | E10: =SUM(E7:E9) -> 93281815 | F10: =SUM(F7:F9) -> 95993692 | G10: =SUM(G7:G9) -> 98767889 | H10: =SUM(H7:H9) -> 1.0160594e+08
B11: Distributions | C11: =-C10*Portfolio!$C$14 -> 0 | D11: =-D10*Portfolio!$C$14 -> -81567680 | E11: =-E10*Portfolio!$C$14 -> -83953634 | F11: =-F10*Portfolio!$C$14 -> -86394323 | G11: =-G10*Portfolio!$C$14 -> -88891100 | H11: =-H10*Portfolio!$C$14 -> -91445349
B12: Net subscriptions | C12: =0 -> 0 | D12: =Portfolio!$C$16 -> 80000000 | E12: =Portfolio!$C$16 -> 80000000 | F12: =Portfolio!$C$16 -> 80000000 | G12: =Portfolio!$C$16 -> 80000000 | H12: =Portfolio!$C$16 -> 80000000
B13: NAV | C13: =C6-Portfolio!$C$11+C16 -> 1.3699111e+09 | D13: =D6-Portfolio!$C$11+D16 -> 1.5014966e+09 | E13: =E6-Portfolio!$C$11+E16 -> 1.6343348e+09 | F13: =F6-Portfolio!$C$11+F16 -> 1.7684564e+09 | G13: =G6-Portfolio!$C$11+G16 -> 1.9038927e+09 | H13: =H6-Portfolio!$C$11+H16 -> 2.0406761e+09
B14: Units in issue | C14: =Portfolio!$C$15 -> 120000000 | D14: =C14+D12/C15 -> 1.2700775e+08 | E14: =D14+E12/D15 -> 1.3377475e+08 | F14: =E14+F12/E15 -> 1.4032297e+08 | G14: =F14+G12/F15 -> 1.4667078e+08 | H14: =G14+H12/G15 -> 1.5283377e+08
B15: NAV per unit | C15: =C13/C14 -> 11.415925 | D15: =D13/D14 -> 11.822086 | E15: =E13/E14 -> 12.217065 | F15: =F13/F14 -> 12.602758 | G15: =G13/G14 -> 12.980722 | H15: =H13/H14 -> 13.352259
B16: Cash | C16: =C10+C11+C12 -> 0 | D16: =C16+D10+D11+D12 -> 89063076 | E16: =D16+E10+E11+E12 -> 1.7839126e+08 | F16: =E16+F10+F11+F12 -> 2.6799063e+08 | G16: =F16+G10+G11+G12 -> 3.5786742e+08 | H16: =G16+H10+H11+H12 -> 4.4802801e+08
