Workbook

Sheet Underwriting
B2: DATA CENTER DEVELOPMENT | UNDERWRITING
B3: All amounts in USD | H3: KEY METRICS
I4: EQUITY MULTIPLE | J4: IRR | K4: NET PROFIT
H5: Unlevered | I5: =SUMIF($S$104:$CY$104,">0")/-SUMIF($S$104:$CY$104,"<0") -> 1.960866 | J5: =XIRR(OFFSET($S$104,0,0,1,Sale_Month+1),OFFSET($S$51,0,0,1,Sale_Month+1)) -> 0.1541769 | K5: =SUM($S$104:$CY$104) -> 4.1251575e+08
B6: TIMING | H6: Levered | I6: =SUMIF($S$112:$CY$112,">0")/-SUMIF($S$112:$CY$112,"<0") -> 2.6037985 | J6: =XIRR(OFFSET($S$112,0,0,1,Sale_Month+1),OFFSET($S$51,0,0,1,Sale_Month+1)) -> 0.2507876 | K6: =SUM($S$112:$CY$112) -> 3.125069e+08
B7: Analysis Start | E7: 46388
B8: Sale Month | E8: 72 | H8: YIELD ON COST
B9: Stabilization (1st month) | E9: =MAX(F29+G29,F30+G30,F31+G31,F32+G32) -> 40 | H9: Untrended | J9: =Stabilized_NOI_Untrended/Project_Cost_Total -> 0.092109212
B10: Total IT Load (kW) | E10: =SUM(C29:C32) -> 24000 | H10: Trended | J10: =Stabilized_NOI/Project_Cost_Total -> 0.094514003
B11: Land Area (SF) | E11: 420000 | H11: At Sale | J11: =Exit_NOI/Project_Cost_Total -> 0.10264949
B12: Gross Building Area (SF) | E12: 185000 | H12: Development Spread (bps) | J12: =(J10-Exit_Cap)*10000 -> 320.14003
B14: USES | C14: Per kW | D14: Per GSF | E14: Total | F14: Start Month | G14: End Month | H14: Method
B15: Land Acquisition | E15: =E11*42 -> 17640000 | F15: 0 | G15: 0 | H15: Straight-Line
B16: Shell & Core | D16: 410 | E16: =D16*E12 -> 75850000 | F16: 1 | G16: 16 | H16: S-Curve
B17: Power & Cooling (MEP) | C17: 9800 | E17: =C17*IT_Load -> 235200000 | F17: 4 | G17: 20 | H17: S-Curve
B18: Fit-Out & IT Infrastructure | C18: 1400 | E18: =C18*IT_Load -> 33600000 | F18: 12 | G18: 22 | H18: Straight-Line
B19: Soft Costs | E19: =0.11*SUM(E16:E18) -> 37911500 | F19: 1 | G19: 22 | H19: Straight-Line
B20: Developer Fee | E20: =0.03*SUM(E16:E18) -> 10339500 | F20: 1 | G20: 22 | H20: Straight-Line
B21: Contingency | E21: =0.05*SUM(E16:E18) -> 17232500 | F21: 4 | G21: 22 | H21: S-Curve
B22: Total Project Cost | E22: =SUM(E15:E21) -> 427773500
B24: FINANCING
B25: Construction Loan to Cost | E25: 0.6 | F25: Rate | G25: 0.075
B26: Permanent Loan LTV | E26: 0.5 | F26: Rate | G26: 0.0625
B28: TENANT | C28: IT Load (kW) | D28: Rent / kW / Month | E28: Growth (% /Yr.) | F28: Lease Start Month | G28: Ramp-Up (months)
B29: Hyperscaler A | C29: 12000 | D29: 128 | E29: 0.025 | F29: 20 | G29: 12
B30: Hyperscaler B | C30: 8000 | D30: 134 | E30: 0.025 | F30: 24 | G30: 9
B31: Enterprise Colocation | C31: 2500 | D31: 195 | E31: 0.03 | F31: 22 | G31: 18
B32: Cloud On-Ramp | C32: 1500 | D32: 170 | E32: 0.03 | F32: 26 | G32: 6
B33: Total | C33: =SUM(C29:C32) -> 24000
B35: OPERATING EXPENSES | C35: Year 1 | D35: Basis
B36: Utilities | C36: 1150 | D36: per leased kW / yr
B37: Maintenance | C37: 2600000 | D37: fixed / yr
B38: Staffing | C38: 3300000 | D38: fixed / yr
B39: Insurance | C39: 950000 | D39: fixed / yr
B40: G&A | C40: 650000 | D40: fixed / yr
B41: Property Taxes | C41: 1900000 | D41: fixed / yr
B42: Management Fee | C42: 0.02 | D42: % of rent
B43: Expense Growth (% /Yr.) | C43: 0.03
B44: Expense Recovery % | C44: 1
B45: Opex Start Month | C45: =MIN(F29:F32) -> 20
B47: REVERSION
B48: Exit Cap Rate | C48: 0.0625
B49: Selling Costs | C49: 0.02
B50: Month | C50: 0.025 | S50: 0 | T50: 1 | U50: 2 | V50: 3 | W50: 4 | X50: 5 | Y50: 6 | Z50: 7 | AA50: 8 | AB50: 9 | AC50: 10 | AD50: 11 | AE50: 12 | AF50: 13 | AG50: 14 | AH50: 15 | AI50: 16 | AJ50: 17 | AK50: 18 | AL50: 19 | AM50: 20 | AN50: 21 | AO50: 22 | AP50: 23 | AQ50: 24 | AR50: 25 | AS50: 26 | AT50: 27 | AU50: 28 | AV50: 29 | AW50: 30 | AX50: 31 | AY50: 32 | AZ50: 33 | BA50: 34 | BB50: 35 | BC50: 36 | BD50: 37 | BE50: 38 | BF50: 39 | BG50: 40 | BH50: 41 | BI50: 42 | BJ50: 43 | BK50: 44 | BL50: 45 | BM50: 46 | BN50: 47 | BO50: 48 | BP50: 49 | BQ50: 50 | BR50: 51 | BS50: 52 | BT50: 53 | BU50: 54 | BV50: 55 | BW50: 56 | BX50: 57 | BY50: 58 | BZ50: 59 | CA50: 60 | CB50: 61 | CC50: 62 | CD50: 63 | CE50: 64 | CF50: 65 | CG50: 66 | CH50: 67 | CI50: 68 | CJ50: 69 | CK50: 70 | CL50: 71 | CM50: 72 | CN50: 73 | CO50: 74 | CP50: 75 | CQ50: 76 | CR50: 77 | CS50: 78 | CT50: 79 | CU50: 80 | CV50: 81 | CW50: 82 | CX50: 83 | CY50: 84
B51: Month Ending | S51: =EOMONTH(Timing_Start,S50-1) -> 46387 | T51: =EOMONTH(Timing_Start,T50-1) -> 46418 | U51: =EOMONTH(Timing_Start,U50-1) -> 46446 | V51: =EOMONTH(Timing_Start,V50-1) -> 46477 | W51: =EOMONTH(Timing_Start,W50-1) -> 46507 | X51: =EOMONTH(Timing_Start,X50-1) -> 46538 | Y51: =EOMONTH(Timing_Start,Y50-1) -> 46568 | Z51: =EOMONTH(Timing_Start,Z50-1) -> 46599 | ... CY51: =EOMONTH(Timing_Start,CY50-1) -> 48944
B52: Year | S52: =ROUNDUP(S50/12,0) -> 0 | T52: =ROUNDUP(T50/12,0) -> 1 | U52: =ROUNDUP(U50/12,0) -> 1 | V52: =ROUNDUP(V50/12,0) -> 1 | W52: =ROUNDUP(W50/12,0) -> 1 | X52: =ROUNDUP(X50/12,0) -> 1 | Y52: =ROUNDUP(Y50/12,0) -> 1 | Z52: =ROUNDUP(Z50/12,0) -> 1 | ... CY52: =ROUNDUP(CY50/12,0) -> 7
D53: Exit NOI (forward) | E53: =SUMPRODUCT(($S$50:$CY$50>Sale_Month-12)*($S$50:$CY$50<=Sale_Month)*$S$83:$CY$83)*(1+C50) -> 43910731
B54: Land Acquisition | D54: Permanent Loan | E54: =E26*E55/C48 -> 323444688 | S54: =IF(AND(S$50>=$F$15,S$50<=$G$15),$E$15*IF($H$15="S-Curve",(COS(PI()*(S$50-$F$15)/($G$15-$F$15+1))-COS(PI()*((S$50-$F$15)+1)/($G$15-$F$15+1)))/2,1/($G$15-$F$15+1)),0) -> 17640000 | T54: =IF(AND(T$50>=$F$15,T$50<=$G$15),$E$15*IF($H$15="S-Curve",(COS(PI()*(T$50-$F$15)/($G$15-$F$15+1))-COS(PI()*((T$50-$F$15)+1)/($G$15-$F$15+1)))/2,1/($G$15-$F$15+1)),0) -> 0 | U54: =IF(AND(U$50>=$F$15,U$50<=$G$15),$E$15*IF($H$15="S-Curve",(COS(PI()*(U$50-$F$15)/($G$15-$F$15+1))-COS(PI()*((U$50-$F$15)+1)/($G$15-$F$15+1)))/2,1/($G$15-$F$15+1)),0) -> 0 | V54: =IF(AND(V$50>=$F$15,V$50<=$G$15),$E$15*IF($H$15="S-Curve",(COS(PI()*(V$50-$F$15)/($G$15-$F$15+1))-COS(PI()*((V$50-$F$15)+1)/($G$15-$F$15+1)))/2,1/($G$15-$F$15+1)),0) -> 0 | W54: =IF(AND(W$50>=$F$15,W$50<=$G$15),$E$15*IF($H$15="S-Curve",(COS(PI()*(W$50-$F$15)/($G$15-$F$15+1))-COS(PI()*((W$50-$F$15)+1)/($G$15-$F$15+1)))/2,1/($G$15-$F$15+1)),0) -> 0 | X54: =IF(AND(X$50>=$F$15,X$50<=$G$15),$E$15*IF($H$15="S-Curve",(COS(PI()*(X$50-$F$15)/($G$15-$F$15+1))-COS(PI()*((X$50-$F$15)+1)/($G$15-$F$15+1)))/2,1/($G$15-$F$15+1)),0) -> 0 | Y54: =IF(AND(Y$50>=$F$15,Y$50<=$G$15),$E$15*IF($H$15="S-Curve",(COS(PI()*(Y$50-$F$15)/($G$15-$F$15+1))-COS(PI()*((Y$50-$F$15)+1)/($G$15-$F$15+1)))/2,1/($G$15-$F$15+1)),0) -> 0 | Z54: =IF(AND(Z$50>=$F$15,Z$50<=$G$15),$E$15*IF($H$15="S-Curve",(COS(PI()*(Z$50-$F$15)/($G$15-$F$15+1))-COS(PI()*((Z$50-$F$15)+1)/($G$15-$F$15+1)))/2,1/($G$15-$F$15+1)),0) -> 0 | ... CY54: =IF(AND(CY$50>=$F$15,CY$50<=$G$15),$E$15*IF($H$15="S-Curve",(COS(PI()*(CY$50-$F$15)/($G$15-$F$15+1))-COS(PI()*((CY$50-$F$15)+1)/($G$15-$F$15+1)))/2,1/($G$15-$F$15+1)),0) -> 0
B55: Shell & Core | D55: Stabilized NOI (annualised) | E55: =12*SUMPRODUCT(($S$50:$CY$50=Stabilization_1st_Month)*$S$83:$CY$83) -> 40430586 | S55: =IF(AND(S$50>=$F$16,S$50<=$G$16),$E$16*IF($H$16="S-Curve",(COS(PI()*(S$50-$F$16)/($G$16-$F$16+1))-COS(PI()*((S$50-$F$16)+1)/($G$16-$F$16+1)))/2,1/($G$16-$F$16+1)),0) -> 0 | T55: =IF(AND(T$50>=$F$16,T$50<=$G$16),$E$16*IF($H$16="S-Curve",(COS(PI()*(T$50-$F$16)/($G$16-$F$16+1))-COS(PI()*((T$50-$F$16)+1)/($G$16-$F$16+1)))/2,1/($G$16-$F$16+1)),0) -> 728718.24 | U55: =IF(AND(U$50>=$F$16,U$50<=$G$16),$E$16*IF($H$16="S-Curve",(COS(PI()*(U$50-$F$16)/($G$16-$F$16+1))-COS(PI()*((U$50-$F$16)+1)/($G$16-$F$16+1)))/2,1/($G$16-$F$16+1)),0) -> 2158150.5 | V55: =IF(AND(V$50>=$F$16,V$50<=$G$16),$E$16*IF($H$16="S-Curve",(COS(PI()*(V$50-$F$16)/($G$16-$F$16+1))-COS(PI()*((V$50-$F$16)+1)/($G$16-$F$16+1)))/2,1/($G$16-$F$16+1)),0) -> 3504646.2 | W55: =IF(AND(W$50>=$F$16,W$50<=$G$16),$E$16*IF($H$16="S-Curve",(COS(PI()*(W$50-$F$16)/($G$16-$F$16+1))-COS(PI()*((W$50-$F$16)+1)/($G$16-$F$16+1)))/2,1/($G$16-$F$16+1)),0) -> 4716460.4 | X55: =IF(AND(X$50>=$F$16,X$50<=$G$16),$E$16*IF($H$16="S-Curve",(COS(PI()*(X$50-$F$16)/($G$16-$F$16+1))-COS(PI()*((X$50-$F$16)+1)/($G$16-$F$16+1)))/2,1/($G$16-$F$16+1)),0) -> 5747023.6 | Y55: =IF(AND(Y$50>=$F$16,Y$50<=$G$16),$E$16*IF($H$16="S-Curve",(COS(PI()*(Y$50-$F$16)/($G$16-$F$16+1))-COS(PI()*((Y$50-$F$16)+1)/($G$16-$F$16+1)))/2,1/($G$16-$F$16+1)),0) -> 6556731.9 | Z55: =IF(AND(Z$50>=$F$16,Z$50<=$G$16),$E$16*IF($H$16="S-Curve",(COS(PI()*(Z$50-$F$16)/($G$16-$F$16+1))-COS(PI()*((Z$50-$F$16)+1)/($G$16-$F$16+1)))/2,1/($G$16-$F$16+1)),0) -> 7114468.7 | ... CY55: =IF(AND(CY$50>=$F$16,CY$50<=$G$16),$E$16*IF($H$16="S-Curve",(COS(PI()*(CY$50-$F$16)/($G$16-$F$16+1))-COS(PI()*((CY$50-$F$16)+1)/($G$16-$F$16+1)))/2,1/($G$16-$F$16+1)),0) -> 0
B56: Power & Cooling (MEP) | D56: Stabilized NOI (untrended) | E56: =SUMPRODUCT(C29:C32,D29:D32)*12*(1-C42)-SUM(C37:C41)-C36*IT_Load+C44*(SUM(C37:C41)+C36*IT_Load) -> 39401880 | S56: =IF(AND(S$50>=$F$17,S$50<=$G$17),$E$17*IF($H$17="S-Curve",(COS(PI()*(S$50-$F$17)/($G$17-$F$17+1))-COS(PI()*((S$50-$F$17)+1)/($G$17-$F$17+1)))/2,1/($G$17-$F$17+1)),0) -> 0 | T56: =IF(AND(T$50>=$F$17,T$50<=$G$17),$E$17*IF($H$17="S-Curve",(COS(PI()*(T$50-$F$17)/($G$17-$F$17+1))-COS(PI()*((T$50-$F$17)+1)/($G$17-$F$17+1)))/2,1/($G$17-$F$17+1)),0) -> 0 | U56: =IF(AND(U$50>=$F$17,U$50<=$G$17),$E$17*IF($H$17="S-Curve",(COS(PI()*(U$50-$F$17)/($G$17-$F$17+1))-COS(PI()*((U$50-$F$17)+1)/($G$17-$F$17+1)))/2,1/($G$17-$F$17+1)),0) -> 0 | V56: =IF(AND(V$50>=$F$17,V$50<=$G$17),$E$17*IF($H$17="S-Curve",(COS(PI()*(V$50-$F$17)/($G$17-$F$17+1))-COS(PI()*((V$50-$F$17)+1)/($G$17-$F$17+1)))/2,1/($G$17-$F$17+1)),0) -> 0 | W56: =IF(AND(W$50>=$F$17,W$50<=$G$17),$E$17*IF($H$17="S-Curve",(COS(PI()*(W$50-$F$17)/($G$17-$F$17+1))-COS(PI()*((W$50-$F$17)+1)/($G$17-$F$17+1)))/2,1/($G$17-$F$17+1)),0) -> 2002363.5 | X56: =IF(AND(X$50>=$F$17,X$50<=$G$17),$E$17*IF($H$17="S-Curve",(COS(PI()*(X$50-$F$17)/($G$17-$F$17+1))-COS(PI()*((X$50-$F$17)+1)/($G$17-$F$17+1)))/2,1/($G$17-$F$17+1)),0) -> 5938902.3 | Y56: =IF(AND(Y$50>=$F$17,Y$50<=$G$17),$E$17*IF($H$17="S-Curve",(COS(PI()*(Y$50-$F$17)/($G$17-$F$17+1))-COS(PI()*((Y$50-$F$17)+1)/($G$17-$F$17+1)))/2,1/($G$17-$F$17+1)),0) -> 9673199 | Z56: =IF(AND(Z$50>=$F$17,Z$50<=$G$17),$E$17*IF($H$17="S-Curve",(COS(PI()*(Z$50-$F$17)/($G$17-$F$17+1))-COS(PI()*((Z$50-$F$17)+1)/($G$17-$F$17+1)))/2,1/($G$17-$F$17+1)),0) -> 13078086 | ... CY56: =IF(AND(CY$50>=$F$17,CY$50<=$G$17),$E$17*IF($H$17="S-Curve",(COS(PI()*(CY$50-$F$17)/($G$17-$F$17+1))-COS(PI()*((CY$50-$F$17)+1)/($G$17-$F$17+1)))/2,1/($G$17-$F$17+1)),0) -> 0
B57: Fit-Out & IT Infrastructure | S57: =IF(AND(S$50>=$F$18,S$50<=$G$18),$E$18*IF($H$18="S-Curve",(COS(PI()*(S$50-$F$18)/($G$18-$F$18+1))-COS(PI()*((S$50-$F$18)+1)/($G$18-$F$18+1)))/2,1/($G$18-$F$18+1)),0) -> 0 | T57: =IF(AND(T$50>=$F$18,T$50<=$G$18),$E$18*IF($H$18="S-Curve",(COS(PI()*(T$50-$F$18)/($G$18-$F$18+1))-COS(PI()*((T$50-$F$18)+1)/($G$18-$F$18+1)))/2,1/($G$18-$F$18+1)),0) -> 0 | U57: =IF(AND(U$50>=$F$18,U$50<=$G$18),$E$18*IF($H$18="S-Curve",(COS(PI()*(U$50-$F$18)/($G$18-$F$18+1))-COS(PI()*((U$50-$F$18)+1)/($G$18-$F$18+1)))/2,1/($G$18-$F$18+1)),0) -> 0 | V57: =IF(AND(V$50>=$F$18,V$50<=$G$18),$E$18*IF($H$18="S-Curve",(COS(PI()*(V$50-$F$18)/($G$18-$F$18+1))-COS(PI()*((V$50-$F$18)+1)/($G$18-$F$18+1)))/2,1/($G$18-$F$18+1)),0) -> 0 | W57: =IF(AND(W$50>=$F$18,W$50<=$G$18),$E$18*IF($H$18="S-Curve",(COS(PI()*(W$50-$F$18)/($G$18-$F$18+1))-COS(PI()*((W$50-$F$18)+1)/($G$18-$F$18+1)))/2,1/($G$18-$F$18+1)),0) -> 0 | X57: =IF(AND(X$50>=$F$18,X$50<=$G$18),$E$18*IF($H$18="S-Curve",(COS(PI()*(X$50-$F$18)/($G$18-$F$18+1))-COS(PI()*((X$50-$F$18)+1)/($G$18-$F$18+1)))/2,1/($G$18-$F$18+1)),0) -> 0 | Y57: =IF(AND(Y$50>=$F$18,Y$50<=$G$18),$E$18*IF($H$18="S-Curve",(COS(PI()*(Y$50-$F$18)/($G$18-$F$18+1))-COS(PI()*((Y$50-$F$18)+1)/($G$18-$F$18+1)))/2,1/($G$18-$F$18+1)),0) -> 0 | Z57: =IF(AND(Z$50>=$F$18,Z$50<=$G$18),$E$18*IF($H$18="S-Curve",(COS(PI()*(Z$50-$F$18)/($G$18-$F$18+1))-COS(PI()*((Z$50-$F$18)+1)/($G$18-$F$18+1)))/2,1/($G$18-$F$18+1)),0) -> 0 | ... CY57: =IF(AND(CY$50>=$F$18,CY$50<=$G$18),$E$18*IF($H$18="S-Curve",(COS(PI()*(CY$50-$F$18)/($G$18-$F$18+1))-COS(PI()*((CY$50-$F$18)+1)/($G$18-$F$18+1)))/2,1/($G$18-$F$18+1)),0) -> 0
B58: Soft Costs | S58: =IF(AND(S$50>=$F$19,S$50<=$G$19),$E$19*IF($H$19="S-Curve",(COS(PI()*(S$50-$F$19)/($G$19-$F$19+1))-COS(PI()*((S$50-$F$19)+1)/($G$19-$F$19+1)))/2,1/($G$19-$F$19+1)),0) -> 0 | T58: =IF(AND(T$50>=$F$19,T$50<=$G$19),$E$19*IF($H$19="S-Curve",(COS(PI()*(T$50-$F$19)/($G$19-$F$19+1))-COS(PI()*((T$50-$F$19)+1)/($G$19-$F$19+1)))/2,1/($G$19-$F$19+1)),0) -> 1723250 | U58: =IF(AND(U$50>=$F$19,U$50<=$G$19),$E$19*IF($H$19="S-Curve",(COS(PI()*(U$50-$F$19)/($G$19-$F$19+1))-COS(PI()*((U$50-$F$19)+1)/($G$19-$F$19+1)))/2,1/($G$19-$F$19+1)),0) -> 1723250 | V58: =IF(AND(V$50>=$F$19,V$50<=$G$19),$E$19*IF($H$19="S-Curve",(COS(PI()*(V$50-$F$19)/($G$19-$F$19+1))-COS(PI()*((V$50-$F$19)+1)/($G$19-$F$19+1)))/2,1/($G$19-$F$19+1)),0) -> 1723250 | W58: =IF(AND(W$50>=$F$19,W$50<=$G$19),$E$19*IF($H$19="S-Curve",(COS(PI()*(W$50-$F$19)/($G$19-$F$19+1))-COS(PI()*((W$50-$F$19)+1)/($G$19-$F$19+1)))/2,1/($G$19-$F$19+1)),0) -> 1723250 | X58: =IF(AND(X$50>=$F$19,X$50<=$G$19),$E$19*IF($H$19="S-Curve",(COS(PI()*(X$50-$F$19)/($G$19-$F$19+1))-COS(PI()*((X$50-$F$19)+1)/($G$19-$F$19+1)))/2,1/($G$19-$F$19+1)),0) -> 1723250 | Y58: =IF(AND(Y$50>=$F$19,Y$50<=$G$19),$E$19*IF($H$19="S-Curve",(COS(PI()*(Y$50-$F$19)/($G$19-$F$19+1))-COS(PI()*((Y$50-$F$19)+1)/($G$19-$F$19+1)))/2,1/($G$19-$F$19+1)),0) -> 1723250 | Z58: =IF(AND(Z$50>=$F$19,Z$50<=$G$19),$E$19*IF($H$19="S-Curve",(COS(PI()*(Z$50-$F$19)/($G$19-$F$19+1))-COS(PI()*((Z$50-$F$19)+1)/($G$19-$F$19+1)))/2,1/($G$19-$F$19+1)),0) -> 1723250 | ... CY58: =IF(AND(CY$50>=$F$19,CY$50<=$G$19),$E$19*IF($H$19="S-Curve",(COS(PI()*(CY$50-$F$19)/($G$19-$F$19+1))-COS(PI()*((CY$50-$F$19)+1)/($G$19-$F$19+1)))/2,1/($G$19-$F$19+1)),0) -> 0
B59: Developer Fee | S59: =IF(AND(S$50>=$F$20,S$50<=$G$20),$E$20*IF($H$20="S-Curve",(COS(PI()*(S$50-$F$20)/($G$20-$F$20+1))-COS(PI()*((S$50-$F$20)+1)/($G$20-$F$20+1)))/2,1/($G$20-$F$20+1)),0) -> 0 | T59: =IF(AND(T$50>=$F$20,T$50<=$G$20),$E$20*IF($H$20="S-Curve",(COS(PI()*(T$50-$F$20)/($G$20-$F$20+1))-COS(PI()*((T$50-$F$20)+1)/($G$20-$F$20+1)))/2,1/($G$20-$F$20+1)),0) -> 469977.27 | U59: =IF(AND(U$50>=$F$20,U$50<=$G$20),$E$20*IF($H$20="S-Curve",(COS(PI()*(U$50-$F$20)/($G$20-$F$20+1))-COS(PI()*((U$50-$F$20)+1)/($G$20-$F$20+1)))/2,1/($G$20-$F$20+1)),0) -> 469977.27 | V59: =IF(AND(V$50>=$F$20,V$50<=$G$20),$E$20*IF($H$20="S-Curve",(COS(PI()*(V$50-$F$20)/($G$20-$F$20+1))-COS(PI()*((V$50-$F$20)+1)/($G$20-$F$20+1)))/2,1/($G$20-$F$20+1)),0) -> 469977.27 | W59: =IF(AND(W$50>=$F$20,W$50<=$G$20),$E$20*IF($H$20="S-Curve",(COS(PI()*(W$50-$F$20)/($G$20-$F$20+1))-COS(PI()*((W$50-$F$20)+1)/($G$20-$F$20+1)))/2,1/($G$20-$F$20+1)),0) -> 469977.27 | X59: =IF(AND(X$50>=$F$20,X$50<=$G$20),$E$20*IF($H$20="S-Curve",(COS(PI()*(X$50-$F$20)/($G$20-$F$20+1))-COS(PI()*((X$50-$F$20)+1)/($G$20-$F$20+1)))/2,1/($G$20-$F$20+1)),0) -> 469977.27 | Y59: =IF(AND(Y$50>=$F$20,Y$50<=$G$20),$E$20*IF($H$20="S-Curve",(COS(PI()*(Y$50-$F$20)/($G$20-$F$20+1))-COS(PI()*((Y$50-$F$20)+1)/($G$20-$F$20+1)))/2,1/($G$20-$F$20+1)),0) -> 469977.27 | Z59: =IF(AND(Z$50>=$F$20,Z$50<=$G$20),$E$20*IF($H$20="S-Curve",(COS(PI()*(Z$50-$F$20)/($G$20-$F$20+1))-COS(PI()*((Z$50-$F$20)+1)/($G$20-$F$20+1)))/2,1/($G$20-$F$20+1)),0) -> 469977.27 | ... CY59: =IF(AND(CY$50>=$F$20,CY$50<=$G$20),$E$20*IF($H$20="S-Curve",(COS(PI()*(CY$50-$F$20)/($G$20-$F$20+1))-COS(PI()*((CY$50-$F$20)+1)/($G$20-$F$20+1)))/2,1/($G$20-$F$20+1)),0) -> 0
B60: Contingency | S60: =IF(AND(S$50>=$F$21,S$50<=$G$21),$E$21*IF($H$21="S-Curve",(COS(PI()*(S$50-$F$21)/($G$21-$F$21+1))-COS(PI()*((S$50-$F$21)+1)/($G$21-$F$21+1)))/2,1/($G$21-$F$21+1)),0) -> 0 | T60: =IF(AND(T$50>=$F$21,T$50<=$G$21),$E$21*IF($H$21="S-Curve",(COS(PI()*(T$50-$F$21)/($G$21-$F$21+1))-COS(PI()*((T$50-$F$21)+1)/($G$21-$F$21+1)))/2,1/($G$21-$F$21+1)),0) -> 0 | U60: =IF(AND(U$50>=$F$21,U$50<=$G$21),$E$21*IF($H$21="S-Curve",(COS(PI()*(U$50-$F$21)/($G$21-$F$21+1))-COS(PI()*((U$50-$F$21)+1)/($G$21-$F$21+1)))/2,1/($G$21-$F$21+1)),0) -> 0 | V60: =IF(AND(V$50>=$F$21,V$50<=$G$21),$E$21*IF($H$21="S-Curve",(COS(PI()*(V$50-$F$21)/($G$21-$F$21+1))-COS(PI()*((V$50-$F$21)+1)/($G$21-$F$21+1)))/2,1/($G$21-$F$21+1)),0) -> 0 | W60: =IF(AND(W$50>=$F$21,W$50<=$G$21),$E$21*IF($H$21="S-Curve",(COS(PI()*(W$50-$F$21)/($G$21-$F$21+1))-COS(PI()*((W$50-$F$21)+1)/($G$21-$F$21+1)))/2,1/($G$21-$F$21+1)),0) -> 117514.42 | X60: =IF(AND(X$50>=$F$21,X$50<=$G$21),$E$21*IF($H$21="S-Curve",(COS(PI()*(X$50-$F$21)/($G$21-$F$21+1))-COS(PI()*((X$50-$F$21)+1)/($G$21-$F$21+1)))/2,1/($G$21-$F$21+1)),0) -> 349337.77 | Y60: =IF(AND(Y$50>=$F$21,Y$50<=$G$21),$E$21*IF($H$21="S-Curve",(COS(PI()*(Y$50-$F$21)/($G$21-$F$21+1))-COS(PI()*((Y$50-$F$21)+1)/($G$21-$F$21+1)))/2,1/($G$21-$F$21+1)),0) -> 571632.1 | Z60: =IF(AND(Z$50>=$F$21,Z$50<=$G$21),$E$21*IF($H$21="S-Curve",(COS(PI()*(Z$50-$F$21)/($G$21-$F$21+1))-COS(PI()*((Z$50-$F$21)+1)/($G$21-$F$21+1)))/2,1/($G$21-$F$21+1)),0) -> 778333.79 | ... CY60: =IF(AND(CY$50>=$F$21,CY$50<=$G$21),$E$21*IF($H$21="S-Curve",(COS(PI()*(CY$50-$F$21)/($G$21-$F$21+1))-COS(PI()*((CY$50-$F$21)+1)/($G$21-$F$21+1)))/2,1/($G$21-$F$21+1)),0) -> 0
B61: Total Development Cost | S61: =SUM(S54:S60) -> 17640000 | T61: =SUM(T54:T60) -> 2921945.5 | U61: =SUM(U54:U60) -> 4351377.8 | V61: =SUM(V54:V60) -> 5697873.5 | W61: =SUM(W54:W60) -> 9029565.5 | X61: =SUM(X54:X60) -> 14228491 | Y61: =SUM(Y54:Y60) -> 18994790 | Z61: =SUM(Z54:Z60) -> 23164116 | ... CY61: =SUM(CY54:CY60) -> 0
B63: Leased IT Load (kW) | S63: =$C$29*MAX(0,MIN(1,(S$50-$F$29+1)/$G$29))+$C$30*MAX(0,MIN(1,(S$50-$F$30+1)/$G$30))+$C$31*MAX(0,MIN(1,(S$50-$F$31+1)/$G$31))+$C$32*MAX(0,MIN(1,(S$50-$F$32+1)/$G$32)) -> 0 | T63: =$C$29*MAX(0,MIN(1,(T$50-$F$29+1)/$G$29))+$C$30*MAX(0,MIN(1,(T$50-$F$30+1)/$G$30))+$C$31*MAX(0,MIN(1,(T$50-$F$31+1)/$G$31))+$C$32*MAX(0,MIN(1,(T$50-$F$32+1)/$G$32)) -> 0 | U63: =$C$29*MAX(0,MIN(1,(U$50-$F$29+1)/$G$29))+$C$30*MAX(0,MIN(1,(U$50-$F$30+1)/$G$30))+$C$31*MAX(0,MIN(1,(U$50-$F$31+1)/$G$31))+$C$32*MAX(0,MIN(1,(U$50-$F$32+1)/$G$32)) -> 0 | V63: =$C$29*MAX(0,MIN(1,(V$50-$F$29+1)/$G$29))+$C$30*MAX(0,MIN(1,(V$50-$F$30+1)/$G$30))+$C$31*MAX(0,MIN(1,(V$50-$F$31+1)/$G$31))+$C$32*MAX(0,MIN(1,(V$50-$F$32+1)/$G$32)) -> 0 | W63: =$C$29*MAX(0,MIN(1,(W$50-$F$29+1)/$G$29))+$C$30*MAX(0,MIN(1,(W$50-$F$30+1)/$G$30))+$C$31*MAX(0,MIN(1,(W$50-$F$31+1)/$G$31))+$C$32*MAX(0,MIN(1,(W$50-$F$32+1)/$G$32)) -> 0 | X63: =$C$29*MAX(0,MIN(1,(X$50-$F$29+1)/$G$29))+$C$30*MAX(0,MIN(1,(X$50-$F$30+1)/$G$30))+$C$31*MAX(0,MIN(1,(X$50-$F$31+1)/$G$31))+$C$32*MAX(0,MIN(1,(X$50-$F$32+1)/$G$32)) -> 0 | Y63: =$C$29*MAX(0,MIN(1,(Y$50-$F$29+1)/$G$29))+$C$30*MAX(0,MIN(1,(Y$50-$F$30+1)/$G$30))+$C$31*MAX(0,MIN(1,(Y$50-$F$31+1)/$G$31))+$C$32*MAX(0,MIN(1,(Y$50-$F$32+1)/$G$32)) -> 0 | Z63: =$C$29*MAX(0,MIN(1,(Z$50-$F$29+1)/$G$29))+$C$30*MAX(0,MIN(1,(Z$50-$F$30+1)/$G$30))+$C$31*MAX(0,MIN(1,(Z$50-$F$31+1)/$G$31))+$C$32*MAX(0,MIN(1,(Z$50-$F$32+1)/$G$32)) -> 0 | ... CY63: =$C$29*MAX(0,MIN(1,(CY$50-$F$29+1)/$G$29))+$C$30*MAX(0,MIN(1,(CY$50-$F$30+1)/$G$30))+$C$31*MAX(0,MIN(1,(CY$50-$F$31+1)/$G$31))+$C$32*MAX(0,MIN(1,(CY$50-$F$32+1)/$G$32)) -> 24000
B64: Rent - Hyperscaler A | S64: =(S$50<=Sale_Month)*$C$29*MAX(0,MIN(1,(S$50-$F$29+1)/$G$29))*$D$29*(1+$E$29)^MAX(0,ROUNDUP((S$50-$F$29+1)/12,0)-1) -> 0 | T64: =(T$50<=Sale_Month)*$C$29*MAX(0,MIN(1,(T$50-$F$29+1)/$G$29))*$D$29*(1+$E$29)^MAX(0,ROUNDUP((T$50-$F$29+1)/12,0)-1) -> 0 | U64: =(U$50<=Sale_Month)*$C$29*MAX(0,MIN(1,(U$50-$F$29+1)/$G$29))*$D$29*(1+$E$29)^MAX(0,ROUNDUP((U$50-$F$29+1)/12,0)-1) -> 0 | V64: =(V$50<=Sale_Month)*$C$29*MAX(0,MIN(1,(V$50-$F$29+1)/$G$29))*$D$29*(1+$E$29)^MAX(0,ROUNDUP((V$50-$F$29+1)/12,0)-1) -> 0 | W64: =(W$50<=Sale_Month)*$C$29*MAX(0,MIN(1,(W$50-$F$29+1)/$G$29))*$D$29*(1+$E$29)^MAX(0,ROUNDUP((W$50-$F$29+1)/12,0)-1) -> 0 | X64: =(X$50<=Sale_Month)*$C$29*MAX(0,MIN(1,(X$50-$F$29+1)/$G$29))*$D$29*(1+$E$29)^MAX(0,ROUNDUP((X$50-$F$29+1)/12,0)-1) -> 0 | Y64: =(Y$50<=Sale_Month)*$C$29*MAX(0,MIN(1,(Y$50-$F$29+1)/$G$29))*$D$29*(1+$E$29)^MAX(0,ROUNDUP((Y$50-$F$29+1)/12,0)-1) -> 0 | Z64: =(Z$50<=Sale_Month)*$C$29*MAX(0,MIN(1,(Z$50-$F$29+1)/$G$29))*$D$29*(1+$E$29)^MAX(0,ROUNDUP((Z$50-$F$29+1)/12,0)-1) -> 0 | ... CY64: =(CY$50<=Sale_Month)*$C$29*MAX(0,MIN(1,(CY$50-$F$29+1)/$G$29))*$D$29*(1+$E$29)^MAX(0,ROUNDUP((CY$50-$F$29+1)/12,0)-1) -> 0
B65: Rent - Hyperscaler B | S65: =(S$50<=Sale_Month)*$C$30*MAX(0,MIN(1,(S$50-$F$30+1)/$G$30))*$D$30*(1+$E$30)^MAX(0,ROUNDUP((S$50-$F$30+1)/12,0)-1) -> 0 | T65: =(T$50<=Sale_Month)*$C$30*MAX(0,MIN(1,(T$50-$F$30+1)/$G$30))*$D$30*(1+$E$30)^MAX(0,ROUNDUP((T$50-$F$30+1)/12,0)-1) -> 0 | U65: =(U$50<=Sale_Month)*$C$30*MAX(0,MIN(1,(U$50-$F$30+1)/$G$30))*$D$30*(1+$E$30)^MAX(0,ROUNDUP((U$50-$F$30+1)/12,0)-1) -> 0 | V65: =(V$50<=Sale_Month)*$C$30*MAX(0,MIN(1,(V$50-$F$30+1)/$G$30))*$D$30*(1+$E$30)^MAX(0,ROUNDUP((V$50-$F$30+1)/12,0)-1) -> 0 | W65: =(W$50<=Sale_Month)*$C$30*MAX(0,MIN(1,(W$50-$F$30+1)/$G$30))*$D$30*(1+$E$30)^MAX(0,ROUNDUP((W$50-$F$30+1)/12,0)-1) -> 0 | X65: =(X$50<=Sale_Month)*$C$30*MAX(0,MIN(1,(X$50-$F$30+1)/$G$30))*$D$30*(1+$E$30)^MAX(0,ROUNDUP((X$50-$F$30+1)/12,0)-1) -> 0 | Y65: =(Y$50<=Sale_Month)*$C$30*MAX(0,MIN(1,(Y$50-$F$30+1)/$G$30))*$D$30*(1+$E$30)^MAX(0,ROUNDUP((Y$50-$F$30+1)/12,0)-1) -> 0 | Z65: =(Z$50<=Sale_Month)*$C$30*MAX(0,MIN(1,(Z$50-$F$30+1)/$G$30))*$D$30*(1+$E$30)^MAX(0,ROUNDUP((Z$50-$F$30+1)/12,0)-1) -> 0 | ... CY65: =(CY$50<=Sale_Month)*$C$30*MAX(0,MIN(1,(CY$50-$F$30+1)/$G$30))*$D$30*(1+$E$30)^MAX(0,ROUNDUP((CY$50-$F$30+1)/12,0)-1) -> 0
B66: Rent - Enterprise Colocation | S66: =(S$50<=Sale_Month)*$C$31*MAX(0,MIN(1,(S$50-$F$31+1)/$G$31))*$D$31*(1+$E$31)^MAX(0,ROUNDUP((S$50-$F$31+1)/12,0)-1) -> 0 | T66: =(T$50<=Sale_Month)*$C$31*MAX(0,MIN(1,(T$50-$F$31+1)/$G$31))*$D$31*(1+$E$31)^MAX(0,ROUNDUP((T$50-$F$31+1)/12,0)-1) -> 0 | U66: =(U$50<=Sale_Month)*$C$31*MAX(0,MIN(1,(U$50-$F$31+1)/$G$31))*$D$31*(1+$E$31)^MAX(0,ROUNDUP((U$50-$F$31+1)/12,0)-1) -> 0 | V66: =(V$50<=Sale_Month)*$C$31*MAX(0,MIN(1,(V$50-$F$31+1)/$G$31))*$D$31*(1+$E$31)^MAX(0,ROUNDUP((V$50-$F$31+1)/12,0)-1) -> 0 | W66: =(W$50<=Sale_Month)*$C$31*MAX(0,MIN(1,(W$50-$F$31+1)/$G$31))*$D$31*(1+$E$31)^MAX(0,ROUNDUP((W$50-$F$31+1)/12,0)-1) -> 0 | X66: =(X$50<=Sale_Month)*$C$31*MAX(0,MIN(1,(X$50-$F$31+1)/$G$31))*$D$31*(1+$E$31)^MAX(0,ROUNDUP((X$50-$F$31+1)/12,0)-1) -> 0 | Y66: =(Y$50<=Sale_Month)*$C$31*MAX(0,MIN(1,(Y$50-$F$31+1)/$G$31))*$D$31*(1+$E$31)^MAX(0,ROUNDUP((Y$50-$F$31+1)/12,0)-1) -> 0 | Z66: =(Z$50<=Sale_Month)*$C$31*MAX(0,MIN(1,(Z$50-$F$31+1)/$G$31))*$D$31*(1+$E$31)^MAX(0,ROUNDUP((Z$50-$F$31+1)/12,0)-1) -> 0 | ... CY66: =(CY$50<=Sale_Month)*$C$31*MAX(0,MIN(1,(CY$50-$F$31+1)/$G$31))*$D$31*(1+$E$31)^MAX(0,ROUNDUP((CY$50-$F$31+1)/12,0)-1) -> 0
B67: Rent - Cloud On-Ramp | S67: =(S$50<=Sale_Month)*$C$32*MAX(0,MIN(1,(S$50-$F$32+1)/$G$32))*$D$32*(1+$E$32)^MAX(0,ROUNDUP((S$50-$F$32+1)/12,0)-1) -> 0 | T67: =(T$50<=Sale_Month)*$C$32*MAX(0,MIN(1,(T$50-$F$32+1)/$G$32))*$D$32*(1+$E$32)^MAX(0,ROUNDUP((T$50-$F$32+1)/12,0)-1) -> 0 | U67: =(U$50<=Sale_Month)*$C$32*MAX(0,MIN(1,(U$50-$F$32+1)/$G$32))*$D$32*(1+$E$32)^MAX(0,ROUNDUP((U$50-$F$32+1)/12,0)-1) -> 0 | V67: =(V$50<=Sale_Month)*$C$32*MAX(0,MIN(1,(V$50-$F$32+1)/$G$32))*$D$32*(1+$E$32)^MAX(0,ROUNDUP((V$50-$F$32+1)/12,0)-1) -> 0 | W67: =(W$50<=Sale_Month)*$C$32*MAX(0,MIN(1,(W$50-$F$32+1)/$G$32))*$D$32*(1+$E$32)^MAX(0,ROUNDUP((W$50-$F$32+1)/12,0)-1) -> 0 | X67: =(X$50<=Sale_Month)*$C$32*MAX(0,MIN(1,(X$50-$F$32+1)/$G$32))*$D$32*(1+$E$32)^MAX(0,ROUNDUP((X$50-$F$32+1)/12,0)-1) -> 0 | Y67: =(Y$50<=Sale_Month)*$C$32*MAX(0,MIN(1,(Y$50-$F$32+1)/$G$32))*$D$32*(1+$E$32)^MAX(0,ROUNDUP((Y$50-$F$32+1)/12,0)-1) -> 0 | Z67: =(Z$50<=Sale_Month)*$C$32*MAX(0,MIN(1,(Z$50-$F$32+1)/$G$32))*$D$32*(1+$E$32)^MAX(0,ROUNDUP((Z$50-$F$32+1)/12,0)-1) -> 0 | ... CY67: =(CY$50<=Sale_Month)*$C$32*MAX(0,MIN(1,(CY$50-$F$32+1)/$G$32))*$D$32*(1+$E$32)^MAX(0,ROUNDUP((CY$50-$F$32+1)/12,0)-1) -> 0
B68: Total Rental Revenue | S68: =SUM(S64:S67) -> 0 | T68: =SUM(T64:T67) -> 0 | U68: =SUM(U64:U67) -> 0 | V68: =SUM(V64:V67) -> 0 | W68: =SUM(W64:W67) -> 0 | X68: =SUM(X64:X67) -> 0 | Y68: =SUM(Y64:Y67) -> 0 | Z68: =SUM(Z64:Z67) -> 0 | ... CY68: =SUM(CY64:CY67) -> 0
B70: Recovery - Hyperscaler A | S70: =(S$50<=Sale_Month)*$C$29/IT_Load*MAX(0,MIN(1,(S$50-$F$29+1)/$G$29))*$C$44*(SUM(S77:S81)+$C$36/12*IT_Load*(1+$C$43)^(S$52-1)) -> 0 | T70: =(T$50<=Sale_Month)*$C$29/IT_Load*MAX(0,MIN(1,(T$50-$F$29+1)/$G$29))*$C$44*(SUM(T77:T81)+$C$36/12*IT_Load*(1+$C$43)^(T$52-1)) -> 0 | U70: =(U$50<=Sale_Month)*$C$29/IT_Load*MAX(0,MIN(1,(U$50-$F$29+1)/$G$29))*$C$44*(SUM(U77:U81)+$C$36/12*IT_Load*(1+$C$43)^(U$52-1)) -> 0 | V70: =(V$50<=Sale_Month)*$C$29/IT_Load*MAX(0,MIN(1,(V$50-$F$29+1)/$G$29))*$C$44*(SUM(V77:V81)+$C$36/12*IT_Load*(1+$C$43)^(V$52-1)) -> 0 | W70: =(W$50<=Sale_Month)*$C$29/IT_Load*MAX(0,MIN(1,(W$50-$F$29+1)/$G$29))*$C$44*(SUM(W77:W81)+$C$36/12*IT_Load*(1+$C$43)^(W$52-1)) -> 0 | X70: =(X$50<=Sale_Month)*$C$29/IT_Load*MAX(0,MIN(1,(X$50-$F$29+1)/$G$29))*$C$44*(SUM(X77:X81)+$C$36/12*IT_Load*(1+$C$43)^(X$52-1)) -> 0 | Y70: =(Y$50<=Sale_Month)*$C$29/IT_Load*MAX(0,MIN(1,(Y$50-$F$29+1)/$G$29))*$C$44*(SUM(Y77:Y81)+$C$36/12*IT_Load*(1+$C$43)^(Y$52-1)) -> 0 | Z70: =(Z$50<=Sale_Month)*$C$29/IT_Load*MAX(0,MIN(1,(Z$50-$F$29+1)/$G$29))*$C$44*(SUM(Z77:Z81)+$C$36/12*IT_Load*(1+$C$43)^(Z$52-1)) -> 0 | ... CY70: =(CY$50<=Sale_Month)*$C$29/IT_Load*MAX(0,MIN(1,(CY$50-$F$29+1)/$G$29))*$C$44*(SUM(CY77:CY81)+$C$36/12*IT_Load*(1+$C$43)^(CY$52-1)) -> 0
B71: Recovery - Hyperscaler B | S71: =(S$50<=Sale_Month)*$C$30/IT_Load*MAX(0,MIN(1,(S$50-$F$30+1)/$G$30))*$C$44*(SUM(S77:S81)+$C$36/12*IT_Load*(1+$C$43)^(S$52-1)) -> 0 | T71: =(T$50<=Sale_Month)*$C$30/IT_Load*MAX(0,MIN(1,(T$50-$F$30+1)/$G$30))*$C$44*(SUM(T77:T81)+$C$36/12*IT_Load*(1+$C$43)^(T$52-1)) -> 0 | U71: =(U$50<=Sale_Month)*$C$30/IT_Load*MAX(0,MIN(1,(U$50-$F$30+1)/$G$30))*$C$44*(SUM(U77:U81)+$C$36/12*IT_Load*(1+$C$43)^(U$52-1)) -> 0 | V71: =(V$50<=Sale_Month)*$C$30/IT_Load*MAX(0,MIN(1,(V$50-$F$30+1)/$G$30))*$C$44*(SUM(V77:V81)+$C$36/12*IT_Load*(1+$C$43)^(V$52-1)) -> 0 | W71: =(W$50<=Sale_Month)*$C$30/IT_Load*MAX(0,MIN(1,(W$50-$F$30+1)/$G$30))*$C$44*(SUM(W77:W81)+$C$36/12*IT_Load*(1+$C$43)^(W$52-1)) -> 0 | X71: =(X$50<=Sale_Month)*$C$30/IT_Load*MAX(0,MIN(1,(X$50-$F$30+1)/$G$30))*$C$44*(SUM(X77:X81)+$C$36/12*IT_Load*(1+$C$43)^(X$52-1)) -> 0 | Y71: =(Y$50<=Sale_Month)*$C$30/IT_Load*MAX(0,MIN(1,(Y$50-$F$30+1)/$G$30))*$C$44*(SUM(Y77:Y81)+$C$36/12*IT_Load*(1+$C$43)^(Y$52-1)) -> 0 | Z71: =(Z$50<=Sale_Month)*$C$30/IT_Load*MAX(0,MIN(1,(Z$50-$F$30+1)/$G$30))*$C$44*(SUM(Z77:Z81)+$C$36/12*IT_Load*(1+$C$43)^(Z$52-1)) -> 0 | ... CY71: =(CY$50<=Sale_Month)*$C$30/IT_Load*MAX(0,MIN(1,(CY$50-$F$30+1)/$G$30))*$C$44*(SUM(CY77:CY81)+$C$36/12*IT_Load*(1+$C$43)^(CY$52-1)) -> 0
B72: Recovery - Enterprise Colocation | S72: =(S$50<=Sale_Month)*$C$31/IT_Load*MAX(0,MIN(1,(S$50-$F$31+1)/$G$31))*$C$44*(SUM(S77:S81)+$C$36/12*IT_Load*(1+$C$43)^(S$52-1)) -> 0 | T72: =(T$50<=Sale_Month)*$C$31/IT_Load*MAX(0,MIN(1,(T$50-$F$31+1)/$G$31))*$C$44*(SUM(T77:T81)+$C$36/12*IT_Load*(1+$C$43)^(T$52-1)) -> 0 | U72: =(U$50<=Sale_Month)*$C$31/IT_Load*MAX(0,MIN(1,(U$50-$F$31+1)/$G$31))*$C$44*(SUM(U77:U81)+$C$36/12*IT_Load*(1+$C$43)^(U$52-1)) -> 0 | V72: =(V$50<=Sale_Month)*$C$31/IT_Load*MAX(0,MIN(1,(V$50-$F$31+1)/$G$31))*$C$44*(SUM(V77:V81)+$C$36/12*IT_Load*(1+$C$43)^(V$52-1)) -> 0 | W72: =(W$50<=Sale_Month)*$C$31/IT_Load*MAX(0,MIN(1,(W$50-$F$31+1)/$G$31))*$C$44*(SUM(W77:W81)+$C$36/12*IT_Load*(1+$C$43)^(W$52-1)) -> 0 | X72: =(X$50<=Sale_Month)*$C$31/IT_Load*MAX(0,MIN(1,(X$50-$F$31+1)/$G$31))*$C$44*(SUM(X77:X81)+$C$36/12*IT_Load*(1+$C$43)^(X$52-1)) -> 0 | Y72: =(Y$50<=Sale_Month)*$C$31/IT_Load*MAX(0,MIN(1,(Y$50-$F$31+1)/$G$31))*$C$44*(SUM(Y77:Y81)+$C$36/12*IT_Load*(1+$C$43)^(Y$52-1)) -> 0 | Z72: =(Z$50<=Sale_Month)*$C$31/IT_Load*MAX(0,MIN(1,(Z$50-$F$31+1)/$G$31))*$C$44*(SUM(Z77:Z81)+$C$36/12*IT_Load*(1+$C$43)^(Z$52-1)) -> 0 | ... CY72: =(CY$50<=Sale_Month)*$C$31/IT_Load*MAX(0,MIN(1,(CY$50-$F$31+1)/$G$31))*$C$44*(SUM(CY77:CY81)+$C$36/12*IT_Load*(1+$C$43)^(CY$52-1)) -> 0
B73: Recovery - Cloud On-Ramp | S73: =(S$50<=Sale_Month)*$C$32/IT_Load*MAX(0,MIN(1,(S$50-$F$32+1)/$G$32))*$C$44*(SUM(S77:S81)+$C$36/12*IT_Load*(1+$C$43)^(S$52-1)) -> 0 | T73: =(T$50<=Sale_Month)*$C$32/IT_Load*MAX(0,MIN(1,(T$50-$F$32+1)/$G$32))*$C$44*(SUM(T77:T81)+$C$36/12*IT_Load*(1+$C$43)^(T$52-1)) -> 0 | U73: =(U$50<=Sale_Month)*$C$32/IT_Load*MAX(0,MIN(1,(U$50-$F$32+1)/$G$32))*$C$44*(SUM(U77:U81)+$C$36/12*IT_Load*(1+$C$43)^(U$52-1)) -> 0 | V73: =(V$50<=Sale_Month)*$C$32/IT_Load*MAX(0,MIN(1,(V$50-$F$32+1)/$G$32))*$C$44*(SUM(V77:V81)+$C$36/12*IT_Load*(1+$C$43)^(V$52-1)) -> 0 | W73: =(W$50<=Sale_Month)*$C$32/IT_Load*MAX(0,MIN(1,(W$50-$F$32+1)/$G$32))*$C$44*(SUM(W77:W81)+$C$36/12*IT_Load*(1+$C$43)^(W$52-1)) -> 0 | X73: =(X$50<=Sale_Month)*$C$32/IT_Load*MAX(0,MIN(1,(X$50-$F$32+1)/$G$32))*$C$44*(SUM(X77:X81)+$C$36/12*IT_Load*(1+$C$43)^(X$52-1)) -> 0 | Y73: =(Y$50<=Sale_Month)*$C$32/IT_Load*MAX(0,MIN(1,(Y$50-$F$32+1)/$G$32))*$C$44*(SUM(Y77:Y81)+$C$36/12*IT_Load*(1+$C$43)^(Y$52-1)) -> 0 | Z73: =(Z$50<=Sale_Month)*$C$32/IT_Load*MAX(0,MIN(1,(Z$50-$F$32+1)/$G$32))*$C$44*(SUM(Z77:Z81)+$C$36/12*IT_Load*(1+$C$43)^(Z$52-1)) -> 0 | ... CY73: =(CY$50<=Sale_Month)*$C$32/IT_Load*MAX(0,MIN(1,(CY$50-$F$32+1)/$G$32))*$C$44*(SUM(CY77:CY81)+$C$36/12*IT_Load*(1+$C$43)^(CY$52-1)) -> 0
B74: Total Recovery Income | S74: =SUM(S70:S73) -> 0 | T74: =SUM(T70:T73) -> 0 | U74: =SUM(U70:U73) -> 0 | V74: =SUM(V70:V73) -> 0 | W74: =SUM(W70:W73) -> 0 | X74: =SUM(X70:X73) -> 0 | Y74: =SUM(Y70:Y73) -> 0 | Z74: =SUM(Z70:Z73) -> 0 | ... CY74: =SUM(CY70:CY73) -> 0
B75: Effective Gross Revenue | S75: =S68+S74 -> 0 | T75: =T68+T74 -> 0 | U75: =U68+U74 -> 0 | V75: =V68+V74 -> 0 | W75: =W68+W74 -> 0 | X75: =X68+X74 -> 0 | Y75: =Y68+Y74 -> 0 | Z75: =Z68+Z74 -> 0 | ... CY75: =CY68+CY74 -> 0
B76: Utilities | S76: =(S$50<=Sale_Month)*$C$36/12*S63*(1+$C$43)^(S$52-1) -> 0 | T76: =(T$50<=Sale_Month)*$C$36/12*T63*(1+$C$43)^(T$52-1) -> 0 | U76: =(U$50<=Sale_Month)*$C$36/12*U63*(1+$C$43)^(U$52-1) -> 0 | V76: =(V$50<=Sale_Month)*$C$36/12*V63*(1+$C$43)^(V$52-1) -> 0 | W76: =(W$50<=Sale_Month)*$C$36/12*W63*(1+$C$43)^(W$52-1) -> 0 | X76: =(X$50<=Sale_Month)*$C$36/12*X63*(1+$C$43)^(X$52-1) -> 0 | Y76: =(Y$50<=Sale_Month)*$C$36/12*Y63*(1+$C$43)^(Y$52-1) -> 0 | Z76: =(Z$50<=Sale_Month)*$C$36/12*Z63*(1+$C$43)^(Z$52-1) -> 0 | ... CY76: =(CY$50<=Sale_Month)*$C$36/12*CY63*(1+$C$43)^(CY$52-1) -> 0
B77: Maintenance | S77: =(S$50<=Sale_Month)*(S$50>=$C$45)*$C$37/12*(1+$C$43)^(S$52-1) -> 0 | T77: =(T$50<=Sale_Month)*(T$50>=$C$45)*$C$37/12*(1+$C$43)^(T$52-1) -> 0 | U77: =(U$50<=Sale_Month)*(U$50>=$C$45)*$C$37/12*(1+$C$43)^(U$52-1) -> 0 | V77: =(V$50<=Sale_Month)*(V$50>=$C$45)*$C$37/12*(1+$C$43)^(V$52-1) -> 0 | W77: =(W$50<=Sale_Month)*(W$50>=$C$45)*$C$37/12*(1+$C$43)^(W$52-1) -> 0 | X77: =(X$50<=Sale_Month)*(X$50>=$C$45)*$C$37/12*(1+$C$43)^(X$52-1) -> 0 | Y77: =(Y$50<=Sale_Month)*(Y$50>=$C$45)*$C$37/12*(1+$C$43)^(Y$52-1) -> 0 | Z77: =(Z$50<=Sale_Month)*(Z$50>=$C$45)*$C$37/12*(1+$C$43)^(Z$52-1) -> 0 | ... CY77: =(CY$50<=Sale_Month)*(CY$50>=$C$45)*$C$37/12*(1+$C$43)^(CY$52-1) -> 0
B78: Staffing | S78: =(S$50<=Sale_Month)*(S$50>=$C$45)*$C$38/12*(1+$C$43)^(S$52-1) -> 0 | T78: =(T$50<=Sale_Month)*(T$50>=$C$45)*$C$38/12*(1+$C$43)^(T$52-1) -> 0 | U78: =(U$50<=Sale_Month)*(U$50>=$C$45)*$C$38/12*(1+$C$43)^(U$52-1) -> 0 | V78: =(V$50<=Sale_Month)*(V$50>=$C$45)*$C$38/12*(1+$C$43)^(V$52-1) -> 0 | W78: =(W$50<=Sale_Month)*(W$50>=$C$45)*$C$38/12*(1+$C$43)^(W$52-1) -> 0 | X78: =(X$50<=Sale_Month)*(X$50>=$C$45)*$C$38/12*(1+$C$43)^(X$52-1) -> 0 | Y78: =(Y$50<=Sale_Month)*(Y$50>=$C$45)*$C$38/12*(1+$C$43)^(Y$52-1) -> 0 | Z78: =(Z$50<=Sale_Month)*(Z$50>=$C$45)*$C$38/12*(1+$C$43)^(Z$52-1) -> 0 | ... CY78: =(CY$50<=Sale_Month)*(CY$50>=$C$45)*$C$38/12*(1+$C$43)^(CY$52-1) -> 0
B79: Insurance | S79: =(S$50<=Sale_Month)*(S$50>=$C$45)*$C$39/12*(1+$C$43)^(S$52-1) -> 0 | T79: =(T$50<=Sale_Month)*(T$50>=$C$45)*$C$39/12*(1+$C$43)^(T$52-1) -> 0 | U79: =(U$50<=Sale_Month)*(U$50>=$C$45)*$C$39/12*(1+$C$43)^(U$52-1) -> 0 | V79: =(V$50<=Sale_Month)*(V$50>=$C$45)*$C$39/12*(1+$C$43)^(V$52-1) -> 0 | W79: =(W$50<=Sale_Month)*(W$50>=$C$45)*$C$39/12*(1+$C$43)^(W$52-1) -> 0 | X79: =(X$50<=Sale_Month)*(X$50>=$C$45)*$C$39/12*(1+$C$43)^(X$52-1) -> 0 | Y79: =(Y$50<=Sale_Month)*(Y$50>=$C$45)*$C$39/12*(1+$C$43)^(Y$52-1) -> 0 | Z79: =(Z$50<=Sale_Month)*(Z$50>=$C$45)*$C$39/12*(1+$C$43)^(Z$52-1) -> 0 | ... CY79: =(CY$50<=Sale_Month)*(CY$50>=$C$45)*$C$39/12*(1+$C$43)^(CY$52-1) -> 0
B80: G&A | S80: =(S$50<=Sale_Month)*(S$50>=$C$45)*$C$40/12*(1+$C$43)^(S$52-1) -> 0 | T80: =(T$50<=Sale_Month)*(T$50>=$C$45)*$C$40/12*(1+$C$43)^(T$52-1) -> 0 | U80: =(U$50<=Sale_Month)*(U$50>=$C$45)*$C$40/12*(1+$C$43)^(U$52-1) -> 0 | V80: =(V$50<=Sale_Month)*(V$50>=$C$45)*$C$40/12*(1+$C$43)^(V$52-1) -> 0 | W80: =(W$50<=Sale_Month)*(W$50>=$C$45)*$C$40/12*(1+$C$43)^(W$52-1) -> 0 | X80: =(X$50<=Sale_Month)*(X$50>=$C$45)*$C$40/12*(1+$C$43)^(X$52-1) -> 0 | Y80: =(Y$50<=Sale_Month)*(Y$50>=$C$45)*$C$40/12*(1+$C$43)^(Y$52-1) -> 0 | Z80: =(Z$50<=Sale_Month)*(Z$50>=$C$45)*$C$40/12*(1+$C$43)^(Z$52-1) -> 0 | ... CY80: =(CY$50<=Sale_Month)*(CY$50>=$C$45)*$C$40/12*(1+$C$43)^(CY$52-1) -> 0
B81: Property Taxes | S81: =(S$50<=Sale_Month)*(S$50>=$C$45)*$C$41/12*(1+$C$43)^(S$52-1) -> 0 | T81: =(T$50<=Sale_Month)*(T$50>=$C$45)*$C$41/12*(1+$C$43)^(T$52-1) -> 0 | U81: =(U$50<=Sale_Month)*(U$50>=$C$45)*$C$41/12*(1+$C$43)^(U$52-1) -> 0 | V81: =(V$50<=Sale_Month)*(V$50>=$C$45)*$C$41/12*(1+$C$43)^(V$52-1) -> 0 | W81: =(W$50<=Sale_Month)*(W$50>=$C$45)*$C$41/12*(1+$C$43)^(W$52-1) -> 0 | X81: =(X$50<=Sale_Month)*(X$50>=$C$45)*$C$41/12*(1+$C$43)^(X$52-1) -> 0 | Y81: =(Y$50<=Sale_Month)*(Y$50>=$C$45)*$C$41/12*(1+$C$43)^(Y$52-1) -> 0 | Z81: =(Z$50<=Sale_Month)*(Z$50>=$C$45)*$C$41/12*(1+$C$43)^(Z$52-1) -> 0 | ... CY81: =(CY$50<=Sale_Month)*(CY$50>=$C$45)*$C$41/12*(1+$C$43)^(CY$52-1) -> 0
B82: Management Fee | S82: =$C$42*S68 -> 0 | T82: =$C$42*T68 -> 0 | U82: =$C$42*U68 -> 0 | V82: =$C$42*V68 -> 0 | W82: =$C$42*W68 -> 0 | X82: =$C$42*X68 -> 0 | Y82: =$C$42*Y68 -> 0 | Z82: =$C$42*Z68 -> 0 | ... CY82: =$C$42*CY68 -> 0
B83: Net Operating Income | S83: =S75-S84 -> 0 | T83: =T75-T84 -> 0 | U83: =U75-U84 -> 0 | V83: =V75-V84 -> 0 | W83: =W75-W84 -> 0 | X83: =X75-X84 -> 0 | Y83: =Y75-Y84 -> 0 | Z83: =Z75-Z84 -> 0 | ... CY83: =CY75-CY84 -> 0
B84: Total Operating Expenses | S84: =SUM(S76:S82) -> 0 | T84: =SUM(T76:T82) -> 0 | U84: =SUM(U76:U82) -> 0 | V84: =SUM(V76:V82) -> 0 | W84: =SUM(W76:W82) -> 0 | X84: =SUM(X76:X82) -> 0 | Y84: =SUM(Y76:Y82) -> 0 | Z84: =SUM(Z76:Z82) -> 0 | ... CY84: =SUM(CY76:CY82) -> 0
B86: Gross Sale Price | S86: =(S$50=Sale_Month)*Exit_NOI/Exit_Cap -> 0 | T86: =(T$50=Sale_Month)*Exit_NOI/Exit_Cap -> 0 | U86: =(U$50=Sale_Month)*Exit_NOI/Exit_Cap -> 0 | V86: =(V$50=Sale_Month)*Exit_NOI/Exit_Cap -> 0 | W86: =(W$50=Sale_Month)*Exit_NOI/Exit_Cap -> 0 | X86: =(X$50=Sale_Month)*Exit_NOI/Exit_Cap -> 0 | Y86: =(Y$50=Sale_Month)*Exit_NOI/Exit_Cap -> 0 | Z86: =(Z$50=Sale_Month)*Exit_NOI/Exit_Cap -> 0 | ... CY86: =(CY$50=Sale_Month)*Exit_NOI/Exit_Cap -> 0
B87: Selling Costs | S87: =-S86*$C$49 -> 0 | T87: =-T86*$C$49 -> 0 | U87: =-U86*$C$49 -> 0 | V87: =-V86*$C$49 -> 0 | W87: =-W86*$C$49 -> 0 | X87: =-X86*$C$49 -> 0 | Y87: =-Y86*$C$49 -> 0 | Z87: =-Z86*$C$49 -> 0 | ... CY87: =-CY86*$C$49 -> 0
B88: Net Sale Proceeds | S88: =S86+S87 -> 0 | T88: =T86+T87 -> 0 | U88: =U86+U87 -> 0 | V88: =V86+V87 -> 0 | W88: =W86+W87 -> 0 | X88: =X86+X87 -> 0 | Y88: =Y86+Y87 -> 0 | Z88: =Z86+Z87 -> 0 | ... CY88: =CY86+CY87 -> 0
B90: Construction Loan Draw | S90: =S61*$E$25 -> 10584000 | T90: =T61*$E$25 -> 1753167.3 | U90: =U61*$E$25 -> 2610826.7 | V90: =V61*$E$25 -> 3418724.1 | W90: =W61*$E$25 -> 5417739.3 | X90: =X61*$E$25 -> 8537094.6 | Y90: =Y61*$E$25 -> 11396874 | Z90: =Z61*$E$25 -> 13898470 | ... CY90: =CY61*$E$25 -> 0
B91: Construction Loan Interest | S91: =0 -> 0 | T91: =IF(T$50<=Stabilization_1st_Month,S93*$G$25/12,0) -> 66150 | U91: =IF(U$50<=Stabilization_1st_Month,T93*$G$25/12,0) -> 77107.296 | V91: =IF(V$50<=Stabilization_1st_Month,U93*$G$25/12,0) -> 93424.962 | W91: =IF(W$50<=Stabilization_1st_Month,V93*$G$25/12,0) -> 114791.99 | X91: =IF(X$50<=Stabilization_1st_Month,W93*$G$25/12,0) -> 148652.86 | Y91: =IF(Y$50<=Stabilization_1st_Month,X93*$G$25/12,0) -> 202009.7 | Z91: =IF(Z$50<=Stabilization_1st_Month,Y93*$G$25/12,0) -> 273240.16 | AA91: =IF(AA$50<=Stabilization_1st_Month,Z93*$G$25/12,0) -> 360105.6 | ... CY91: =IF(CY$50<=Stabilization_1st_Month,CX93*$G$25/12,0) -> 0
B92: Construction Loan Repayment | S92: =IF(S$50=Stabilization_1st_Month,0+S90,0) -> 0 | T92: =IF(T$50=Stabilization_1st_Month,S93+T90,0) -> 0 | U92: =IF(U$50=Stabilization_1st_Month,T93+U90,0) -> 0 | V92: =IF(V$50=Stabilization_1st_Month,U93+V90,0) -> 0 | W92: =IF(W$50=Stabilization_1st_Month,V93+W90,0) -> 0 | X92: =IF(X$50=Stabilization_1st_Month,W93+X90,0) -> 0 | Y92: =IF(Y$50=Stabilization_1st_Month,X93+Y90,0) -> 0 | Z92: =IF(Z$50=Stabilization_1st_Month,Y93+Z90,0) -> 0 | AA92: =IF(AA$50=Stabilization_1st_Month,Z93+AA90,0) -> 0 | ... CY92: =IF(CY$50=Stabilization_1st_Month,CX93+CY90,0) -> 0
B93: Construction Loan Balance | S93: =0+S90-S92 -> 10584000 | T93: =S93+T90-T92 -> 12337167 | U93: =T93+U90-U92 -> 14947994 | V93: =U93+V90-V92 -> 18366718 | W93: =V93+W90-W92 -> 23784457 | X93: =W93+X90-X92 -> 32321552 | Y93: =X93+Y90-Y92 -> 43718426 | Z93: =Y93+Z90-Z92 -> 57616896 | AA93: =Z93+AA90-AA92 -> 73572965 | ... CY93: =CX93+CY90-CY92 -> 0
B95: Permanent Loan Proceeds | S95: =(S$50=Stabilization_1st_Month)*Perm_Debt -> 0 | T95: =(T$50=Stabilization_1st_Month)*Perm_Debt -> 0 | U95: =(U$50=Stabilization_1st_Month)*Perm_Debt -> 0 | V95: =(V$50=Stabilization_1st_Month)*Perm_Debt -> 0 | W95: =(W$50=Stabilization_1st_Month)*Perm_Debt -> 0 | X95: =(X$50=Stabilization_1st_Month)*Perm_Debt -> 0 | Y95: =(Y$50=Stabilization_1st_Month)*Perm_Debt -> 0 | Z95: =(Z$50=Stabilization_1st_Month)*Perm_Debt -> 0 | ... CY95: =(CY$50=Stabilization_1st_Month)*Perm_Debt -> 0
B96: Permanent Loan Interest | S96: =AND(S$50>Stabilization_1st_Month,(S$50<=Sale_Month))*Perm_Debt*$G$26/12 -> 0 | T96: =AND(T$50>Stabilization_1st_Month,(T$50<=Sale_Month))*Perm_Debt*$G$26/12 -> 0 | U96: =AND(U$50>Stabilization_1st_Month,(U$50<=Sale_Month))*Perm_Debt*$G$26/12 -> 0 | V96: =AND(V$50>Stabilization_1st_Month,(V$50<=Sale_Month))*Perm_Debt*$G$26/12 -> 0 | W96: =AND(W$50>Stabilization_1st_Month,(W$50<=Sale_Month))*Perm_Debt*$G$26/12 -> 0 | X96: =AND(X$50>Stabilization_1st_Month,(X$50<=Sale_Month))*Perm_Debt*$G$26/12 -> 0 | Y96: =AND(Y$50>Stabilization_1st_Month,(Y$50<=Sale_Month))*Perm_Debt*$G$26/12 -> 0 | Z96: =AND(Z$50>Stabilization_1st_Month,(Z$50<=Sale_Month))*Perm_Debt*$G$26/12 -> 0 | ... CY96: =AND(CY$50>Stabilization_1st_Month,(CY$50<=Sale_Month))*Perm_Debt*$G$26/12 -> 0
B97: Permanent Loan Repayment | S97: =(S$50=Sale_Month)*Perm_Debt -> 0 | T97: =(T$50=Sale_Month)*Perm_Debt -> 0 | U97: =(U$50=Sale_Month)*Perm_Debt -> 0 | V97: =(V$50=Sale_Month)*Perm_Debt -> 0 | W97: =(W$50=Sale_Month)*Perm_Debt -> 0 | X97: =(X$50=Sale_Month)*Perm_Debt -> 0 | Y97: =(Y$50=Sale_Month)*Perm_Debt -> 0 | Z97: =(Z$50=Sale_Month)*Perm_Debt -> 0 | ... CY97: =(CY$50=Sale_Month)*Perm_Debt -> 0
B104: Unlevered Cash Flow | S104: =(S$50<=Sale_Month)*(-S61+S83+S88) -> -17640000 | T104: =(T$50<=Sale_Month)*(-T61+T83+T88) -> -2921945.5 | U104: =(U$50<=Sale_Month)*(-U61+U83+U88) -> -4351377.8 | V104: =(V$50<=Sale_Month)*(-V61+V83+V88) -> -5697873.5 | W104: =(W$50<=Sale_Month)*(-W61+W83+W88) -> -9029565.5 | X104: =(X$50<=Sale_Month)*(-X61+X83+X88) -> -14228491 | Y104: =(Y$50<=Sale_Month)*(-Y61+Y83+Y88) -> -18994790 | Z104: =(Z$50<=Sale_Month)*(-Z61+Z83+Z88) -> -23164116 | ... CY104: =(CY$50<=Sale_Month)*(-CY61+CY83+CY88) -> 0
B112: Levered Cash Flow | S112: =(S$50<=Sale_Month)*(S104+S90-S91-S92+S95-S96-S97) -> -7056000 | T112: =(T$50<=Sale_Month)*(T104+T90-T91-T92+T95-T96-T97) -> -1234928.2 | U112: =(U$50<=Sale_Month)*(U104+U90-U91-U92+U95-U96-U97) -> -1817658.4 | V112: =(V$50<=Sale_Month)*(V104+V90-V91-V92+V95-V96-V97) -> -2372574.4 | W112: =(W$50<=Sale_Month)*(W104+W90-W91-W92+W95-W96-W97) -> -3726618.2 | X112: =(X$50<=Sale_Month)*(X104+X90-X91-X92+X95-X96-X97) -> -5840049.3 | Y112: =(Y$50<=Sale_Month)*(Y104+Y90-Y91-Y92+Y95-Y96-Y97) -> -7799925.8 | Z112: =(Z$50<=Sale_Month)*(Z104+Z90-Z91-Z92+Z95-Z96-Z97) -> -9538886.7 | ... CY112: =(CY$50<=Sale_Month)*(CY104+CY90-CY91-CY92+CY95-CY96-CY97) -> 0

Sheet Annual CF
B2: DATA CENTER DEVELOPMENT | ANNUAL CASH FLOW
B4: Year | C4: 0 | D4: 1 | E4: 2 | F4: 3 | G4: 4 | H4: 5 | I4: 6 | J4: 7
B5: Total Development Cost | C5: =SUMIF(Underwriting!$S$52:$CY$52,C$4,Underwriting!$S$61:$CY$61) -> 17640000 | D5: =SUMIF(Underwriting!$S$52:$CY$52,D$4,Underwriting!$S$61:$CY$61) -> 2.3047078e+08 | E5: =SUMIF(Underwriting!$S$52:$CY$52,E$4,Underwriting!$S$61:$CY$61) -> 1.7966272e+08 | F5: =SUMIF(Underwriting!$S$52:$CY$52,F$4,Underwriting!$S$61:$CY$61) -> 0 | G5: =SUMIF(Underwriting!$S$52:$CY$52,G$4,Underwriting!$S$61:$CY$61) -> 0 | H5: =SUMIF(Underwriting!$S$52:$CY$52,H$4,Underwriting!$S$61:$CY$61) -> 0 | I5: =SUMIF(Underwriting!$S$52:$CY$52,I$4,Underwriting!$S$61:$CY$61) -> 0 | J5: =SUMIF(Underwriting!$S$52:$CY$52,J$4,Underwriting!$S$61:$CY$61) -> 0
B6: Total Rental Revenue | C6: =SUMIF(Underwriting!$S$52:$CY$52,C$4,Underwriting!$S$68:$CY$68) -> 0 | D6: =SUMIF(Underwriting!$S$52:$CY$52,D$4,Underwriting!$S$68:$CY$68) -> 0 | E6: =SUMIF(Underwriting!$S$52:$CY$52,E$4,Underwriting!$S$68:$CY$68) -> 2201611.1 | F6: =SUMIF(Underwriting!$S$52:$CY$52,F$4,Underwriting!$S$68:$CY$68) -> 30780814 | G6: =SUMIF(Underwriting!$S$52:$CY$52,G$4,Underwriting!$S$68:$CY$68) -> 41433824 | H6: =SUMIF(Underwriting!$S$52:$CY$52,H$4,Underwriting!$S$68:$CY$68) -> 42601523 | I6: =SUMIF(Underwriting!$S$52:$CY$52,I$4,Underwriting!$S$68:$CY$68) -> 43714018 | J6: =SUMIF(Underwriting!$S$52:$CY$52,J$4,Underwriting!$S$68:$CY$68) -> 0
B7: Total Recovery Income | C7: =SUMIF(Underwriting!$S$52:$CY$52,C$4,Underwriting!$S$74:$CY$74) -> 0 | D7: =SUMIF(Underwriting!$S$52:$CY$52,D$4,Underwriting!$S$74:$CY$74) -> 0 | E7: =SUMIF(Underwriting!$S$52:$CY$52,E$4,Underwriting!$S$74:$CY$74) -> 2212791.3 | F7: =SUMIF(Underwriting!$S$52:$CY$52,F$4,Underwriting!$S$74:$CY$74) -> 30352402 | G7: =SUMIF(Underwriting!$S$52:$CY$52,G$4,Underwriting!$S$74:$CY$74) -> 40372405 | H7: =SUMIF(Underwriting!$S$52:$CY$52,H$4,Underwriting!$S$74:$CY$74) -> 41643826 | I7: =SUMIF(Underwriting!$S$52:$CY$52,I$4,Underwriting!$S$74:$CY$74) -> 42893141 | J7: =SUMIF(Underwriting!$S$52:$CY$52,J$4,Underwriting!$S$74:$CY$74) -> 0
B8: Total Operating Expenses | C8: =SUMIF(Underwriting!$S$52:$CY$52,C$4,Underwriting!$S$84:$CY$84) -> 0 | D8: =SUMIF(Underwriting!$S$52:$CY$52,D$4,Underwriting!$S$84:$CY$84) -> 0 | E8: =SUMIF(Underwriting!$S$52:$CY$52,E$4,Underwriting!$S$84:$CY$84) -> 5728821.6 | F8: =SUMIF(Underwriting!$S$52:$CY$52,F$4,Underwriting!$S$84:$CY$84) -> 33229328 | G8: =SUMIF(Underwriting!$S$52:$CY$52,G$4,Underwriting!$S$84:$CY$84) -> 41215942 | H8: =SUMIF(Underwriting!$S$52:$CY$52,H$4,Underwriting!$S$84:$CY$84) -> 42495856 | I8: =SUMIF(Underwriting!$S$52:$CY$52,I$4,Underwriting!$S$84:$CY$84) -> 43767421 | J8: =SUMIF(Underwriting!$S$52:$CY$52,J$4,Underwriting!$S$84:$CY$84) -> 0
B9: Net Operating Income | C9: =SUMIF(Underwriting!$S$52:$CY$52,C$4,Underwriting!$S$83:$CY$83) -> 0 | D9: =SUMIF(Underwriting!$S$52:$CY$52,D$4,Underwriting!$S$83:$CY$83) -> 0 | E9: =SUMIF(Underwriting!$S$52:$CY$52,E$4,Underwriting!$S$83:$CY$83) -> -1314419.2 | F9: =SUMIF(Underwriting!$S$52:$CY$52,F$4,Underwriting!$S$83:$CY$83) -> 27903888 | G9: =SUMIF(Underwriting!$S$52:$CY$52,G$4,Underwriting!$S$83:$CY$83) -> 40590287 | H9: =SUMIF(Underwriting!$S$52:$CY$52,H$4,Underwriting!$S$83:$CY$83) -> 41749493 | I9: =SUMIF(Underwriting!$S$52:$CY$52,I$4,Underwriting!$S$83:$CY$83) -> 42839737 | J9: =SUMIF(Underwriting!$S$52:$CY$52,J$4,Underwriting!$S$83:$CY$83) -> 0
B10: Net Sale Proceeds | C10: =SUMIF(Underwriting!$S$52:$CY$52,C$4,Underwriting!$S$88:$CY$88) -> 0 | D10: =SUMIF(Underwriting!$S$52:$CY$52,D$4,Underwriting!$S$88:$CY$88) -> 0 | E10: =SUMIF(Underwriting!$S$52:$CY$52,E$4,Underwriting!$S$88:$CY$88) -> 0 | F10: =SUMIF(Underwriting!$S$52:$CY$52,F$4,Underwriting!$S$88:$CY$88) -> 0 | G10: =SUMIF(Underwriting!$S$52:$CY$52,G$4,Underwriting!$S$88:$CY$88) -> 0 | H10: =SUMIF(Underwriting!$S$52:$CY$52,H$4,Underwriting!$S$88:$CY$88) -> 0 | I10: =SUMIF(Underwriting!$S$52:$CY$52,I$4,Underwriting!$S$88:$CY$88) -> 6.8852026e+08 | J10: =SUMIF(Underwriting!$S$52:$CY$52,J$4,Underwriting!$S$88:$CY$88) -> 0
B11: Unlevered Cash Flow | C11: =SUMIF(Underwriting!$S$52:$CY$52,C$4,Underwriting!$S$104:$CY$104) -> -17640000 | D11: =SUMIF(Underwriting!$S$52:$CY$52,D$4,Underwriting!$S$104:$CY$104) -> -2.3047078e+08 | E11: =SUMIF(Underwriting!$S$52:$CY$52,E$4,Underwriting!$S$104:$CY$104) -> -1.8097714e+08 | F11: =SUMIF(Underwriting!$S$52:$CY$52,F$4,Underwriting!$S$104:$CY$104) -> 27903888 | G11: =SUMIF(Underwriting!$S$52:$CY$52,G$4,Underwriting!$S$104:$CY$104) -> 40590287 | H11: =SUMIF(Underwriting!$S$52:$CY$52,H$4,Underwriting!$S$104:$CY$104) -> 41749493 | I11: =SUMIF(Underwriting!$S$52:$CY$52,I$4,Underwriting!$S$104:$CY$104) -> 7.3136e+08 | J11: =SUMIF(Underwriting!$S$52:$CY$52,J$4,Underwriting!$S$104:$CY$104) -> 0
B12: Levered Cash Flow | C12: =SUMIF(Underwriting!$S$52:$CY$52,C$4,Underwriting!$S$112:$CY$112) -> -7056000 | D12: =SUMIF(Underwriting!$S$52:$CY$52,D$4,Underwriting!$S$112:$CY$112) -> -96040057 | E12: =SUMIF(Underwriting!$S$52:$CY$52,E$4,Underwriting!$S$112:$CY$112) -> -89762750 | F12: =SUMIF(Underwriting!$S$52:$CY$52,F$4,Underwriting!$S$112:$CY$112) -> 8654080.9 | G12: =SUMIF(Underwriting!$S$52:$CY$52,G$4,Underwriting!$S$112:$CY$112) -> 87477410 | H12: =SUMIF(Underwriting!$S$52:$CY$52,H$4,Underwriting!$S$112:$CY$112) -> 21534200 | I12: =SUMIF(Underwriting!$S$52:$CY$52,I$4,Underwriting!$S$112:$CY$112) -> 3.8770002e+08 | J12: =SUMIF(Underwriting!$S$52:$CY$52,J$4,Underwriting!$S$112:$CY$112) -> 0
