Workbook

Sheet Deal Summary
A1: NET LEASE ACQUISITION | DEAL SUMMARY
A3: Tenant | B3: Drive-thru restaurant (corporate guarantee)
A4: Location | B4: Dubai, Al Barsha
A6: Going-in cap rate | B6: ='Lease CF'!E7/Assumptions!B3 -> 0.070059859
A7: Year-1 cash-on-cash | B7: ='Lease CF'!L7/-'Lease CF'!L6 -> 0.080846727
A9: Unleveraged IRR | B9: =IRR('Lease CF'!K6:K22) -> 0.065716273
A10: Leveraged IRR | B10: =IRR('Lease CF'!L6:L22) -> 0.074187475
A11: Equity multiple | B11: =SUM('Lease CF'!L7:L22)/-'Lease CF'!L6 -> 1.7447194
A12: Net profit (leveraged) | B12: =SUM('Lease CF'!L6:L22) -> 4494381.4

Sheet Assumptions
A1: ASSUMPTIONS (AED)
A3: Purchase price | B3: 14200000
A4: Closing costs (% of price) | B4: 0.025
A5: Year-1 base rent | B5: 1010000
A6: Rent step every 5 lease years | B6: 0.1
A7: Lease years remaining | B7: 8
A8: Vacancy before re-letting (years) | B8: 1
A9: Market rent at re-letting (% of last rent) | B9: 0.95
A10: Market rent growth a year | B10: 0.02
A11: Non-recoverable costs (% of rent) | B11: 0.015
A12: Hold period (years) | B12: 10
A13: Exit cap rate | B13: 0.0725
A14: Selling costs | B14: 0.015
... A20: Lease years elapsed at purchase | B20: 7
A22: Loan amount | B22: =B3*B16 -> 8520000
A23: Annual debt service (amortising) | B23: =PMT(B17,B19,-B22) -> 663328.41

Sheet Lease CF
A1: LEASE CASH FLOW (AED)
A5: Year | B5: Lease year | C5: Base rent | D5: Non-recoverable costs | E5: Net operating income | F5: Interest | G5: Principal | H5: Debt service | I5: Sale proceeds | J5: Loan payoff | K5: Unleveraged cash flow | L5: Leveraged cash flow
A6: 0 | B6: =Assumptions!$B$20+A6 -> 7 | C6: 0 | D6: 0 | E6: 0 | F6: 0 | G6: 0 | H6: 0 | I6: 0 | J6: 0 | K6: =-Assumptions!B3*(1+Assumptions!B4) -> -14555000 | L6: =K6+Assumptions!B22 -> -6035000
A7: 1 | B7: =Assumptions!$B$20+A7 -> 8 | C7: =IF(A7<=Assumptions!$B$7,Assumptions!$B$5*(1+Assumptions!$B$6)^(INT((B7-1)/5)-INT(Assumptions!$B$20/5)),IF(A7<=Assumptions!$B$7+Assumptions!$B$8,0,Assumptions!$B$5*(1+Assumptions!$B$6)^(INT((Assumptions!$B$20+Assumptions!$B$7-1)/5)-INT(Assumptions!$B$20/5))*Assumptions!$B$9*(1+Assumptions!$B$10)^(A7-Assumptions!$B$7-Assumptions!$B$8-1))) -> 1010000 | D7: =-C7*Assumptions!$B$11 -> -15150 | E7: =C7+D7 -> 994850 | F7: =IF(A7<=Assumptions!$B$18,Assumptions!$B$22*Assumptions!$B$17,-CUMIPMT(Assumptions!$B$17,Assumptions!$B$19,Assumptions!$B$22,A7-Assumptions!$B$18,A7-Assumptions!$B$18,0)) -> 506940 | G7: =IF(A7<=Assumptions!$B$18,0,-CUMPRINC(Assumptions!$B$17,Assumptions!$B$19,Assumptions!$B$22,A7-Assumptions!$B$18,A7-Assumptions!$B$18,0)) -> 0 | H7: =F7+G7 -> 506940 | I7: =IF(A7=Assumptions!$B$12,E8/Assumptions!$B$13*(1-Assumptions!$B$14),0) -> 0 | J7: =IF(A7=Assumptions!$B$12,Assumptions!$B$22+IF(A7<=Assumptions!$B$18,0,CUMPRINC(Assumptions!$B$17,Assumptions!$B$19,Assumptions!$B$22,1,A7-Assumptions!$B$18,0)),0) -> 0 | K7: =(A7<=Assumptions!$B$12)*(E7+I7) -> 994850 | L7: =(A7<=Assumptions!$B$12)*(E7-H7+I7-J7) -> 487910
A8: 2 | B8: =Assumptions!$B$20+A8 -> 9 | C8: =IF(A8<=Assumptions!$B$7,Assumptions!$B$5*(1+Assumptions!$B$6)^(INT((B8-1)/5)-INT(Assumptions!$B$20/5)),IF(A8<=Assumptions!$B$7+Assumptions!$B$8,0,Assumptions!$B$5*(1+Assumptions!$B$6)^(INT((Assumptions!$B$20+Assumptions!$B$7-1)/5)-INT(Assumptions!$B$20/5))*Assumptions!$B$9*(1+Assumptions!$B$10)^(A8-Assumptions!$B$7-Assumptions!$B$8-1))) -> 1010000 | D8: =-C8*Assumptions!$B$11 -> -15150 | E8: =C8+D8 -> 994850 | F8: =IF(A8<=Assumptions!$B$18,Assumptions!$B$22*Assumptions!$B$17,-CUMIPMT(Assumptions!$B$17,Assumptions!$B$19,Assumptions!$B$22,A8-Assumptions!$B$18,A8-Assumptions!$B$18,0)) -> 506940 | G8: =IF(A8<=Assumptions!$B$18,0,-CUMPRINC(Assumptions!$B$17,Assumptions!$B$19,Assumptions!$B$22,A8-Assumptions!$B$18,A8-Assumptions!$B$18,0)) -> 0 | H8: =F8+G8 -> 506940 | I8: =IF(A8=Assumptions!$B$12,E9/Assumptions!$B$13*(1-Assumptions!$B$14),0) -> 0 | J8: =IF(A8=Assumptions!$B$12,Assumptions!$B$22+IF(A8<=Assumptions!$B$18,0,CUMPRINC(Assumptions!$B$17,Assumptions!$B$19,Assumptions!$B$22,1,A8-Assumptions!$B$18,0)),0) -> 0 | K8: =(A8<=Assumptions!$B$12)*(E8+I8) -> 994850 | L8: =(A8<=Assumptions!$B$12)*(E8-H8+I8-J8) -> 487910
A9: 3 | B9: =Assumptions!$B$20+A9 -> 10 | C9: =IF(A9<=Assumptions!$B$7,Assumptions!$B$5*(1+Assumptions!$B$6)^(INT((B9-1)/5)-INT(Assumptions!$B$20/5)),IF(A9<=Assumptions!$B$7+Assumptions!$B$8,0,Assumptions!$B$5*(1+Assumptions!$B$6)^(INT((Assumptions!$B$20+Assumptions!$B$7-1)/5)-INT(Assumptions!$B$20/5))*Assumptions!$B$9*(1+Assumptions!$B$10)^(A9-Assumptions!$B$7-Assumptions!$B$8-1))) -> 1010000 | D9: =-C9*Assumptions!$B$11 -> -15150 | E9: =C9+D9 -> 994850 | F9: =IF(A9<=Assumptions!$B$18,Assumptions!$B$22*Assumptions!$B$17,-CUMIPMT(Assumptions!$B$17,Assumptions!$B$19,Assumptions!$B$22,A9-Assumptions!$B$18,A9-Assumptions!$B$18,0)) -> 506940 | G9: =IF(A9<=Assumptions!$B$18,0,-CUMPRINC(Assumptions!$B$17,Assumptions!$B$19,Assumptions!$B$22,A9-Assumptions!$B$18,A9-Assumptions!$B$18,0)) -> 0 | H9: =F9+G9 -> 506940 | I9: =IF(A9=Assumptions!$B$12,E10/Assumptions!$B$13*(1-Assumptions!$B$14),0) -> 0 | J9: =IF(A9=Assumptions!$B$12,Assumptions!$B$22+IF(A9<=Assumptions!$B$18,0,CUMPRINC(Assumptions!$B$17,Assumptions!$B$19,Assumptions!$B$22,1,A9-Assumptions!$B$18,0)),0) -> 0 | K9: =(A9<=Assumptions!$B$12)*(E9+I9) -> 994850 | L9: =(A9<=Assumptions!$B$12)*(E9-H9+I9-J9) -> 487910
A10: 4 | B10: =Assumptions!$B$20+A10 -> 11 | C10: =IF(A10<=Assumptions!$B$7,Assumptions!$B$5*(1+Assumptions!$B$6)^(INT((B10-1)/5)-INT(Assumptions!$B$20/5)),IF(A10<=Assumptions!$B$7+Assumptions!$B$8,0,Assumptions!$B$5*(1+Assumptions!$B$6)^(INT((Assumptions!$B$20+Assumptions!$B$7-1)/5)-INT(Assumptions!$B$20/5))*Assumptions!$B$9*(1+Assumptions!$B$10)^(A10-Assumptions!$B$7-Assumptions!$B$8-1))) -> 1111000 | D10: =-C10*Assumptions!$B$11 -> -16665 | E10: =C10+D10 -> 1094335 | F10: =IF(A10<=Assumptions!$B$18,Assumptions!$B$22*Assumptions!$B$17,-CUMIPMT(Assumptions!$B$17,Assumptions!$B$19,Assumptions!$B$22,A10-Assumptions!$B$18,A10-Assumptions!$B$18,0)) -> 506940 | G10: =IF(A10<=Assumptions!$B$18,0,-CUMPRINC(Assumptions!$B$17,Assumptions!$B$19,Assumptions!$B$22,A10-Assumptions!$B$18,A10-Assumptions!$B$18,0)) -> 156388.41 | H10: =F10+G10 -> 663328.41 | I10: =IF(A10=Assumptions!$B$12,E11/Assumptions!$B$13*(1-Assumptions!$B$14),0) -> 0 | J10: =IF(A10=Assumptions!$B$12,Assumptions!$B$22+IF(A10<=Assumptions!$B$18,0,CUMPRINC(Assumptions!$B$17,Assumptions!$B$19,Assumptions!$B$22,1,A10-Assumptions!$B$18,0)),0) -> 0 | K10: =(A10<=Assumptions!$B$12)*(E10+I10) -> 1094335 | L10: =(A10<=Assumptions!$B$12)*(E10-H10+I10-J10) -> 431006.59
A11: 5 | B11: =Assumptions!$B$20+A11 -> 12 | C11: =IF(A11<=Assumptions!$B$7,Assumptions!$B$5*(1+Assumptions!$B$6)^(INT((B11-1)/5)-INT(Assumptions!$B$20/5)),IF(A11<=Assumptions!$B$7+Assumptions!$B$8,0,Assumptions!$B$5*(1+Assumptions!$B$6)^(INT((Assumptions!$B$20+Assumptions!$B$7-1)/5)-INT(Assumptions!$B$20/5))*Assumptions!$B$9*(1+Assumptions!$B$10)^(A11-Assumptions!$B$7-Assumptions!$B$8-1))) -> 1111000 | D11: =-C11*Assumptions!$B$11 -> -16665 | E11: =C11+D11 -> 1094335 | F11: =IF(A11<=Assumptions!$B$18,Assumptions!$B$22*Assumptions!$B$17,-CUMIPMT(Assumptions!$B$17,Assumptions!$B$19,Assumptions!$B$22,A11-Assumptions!$B$18,A11-Assumptions!$B$18,0)) -> 497634.89 | G11: =IF(A11<=Assumptions!$B$18,0,-CUMPRINC(Assumptions!$B$17,Assumptions!$B$19,Assumptions!$B$22,A11-Assumptions!$B$18,A11-Assumptions!$B$18,0)) -> 165693.52 | H11: =F11+G11 -> 663328.41 | I11: =IF(A11=Assumptions!$B$12,E12/Assumptions!$B$13*(1-Assumptions!$B$14),0) -> 0 | J11: =IF(A11=Assumptions!$B$12,Assumptions!$B$22+IF(A11<=Assumptions!$B$18,0,CUMPRINC(Assumptions!$B$17,Assumptions!$B$19,Assumptions!$B$22,1,A11-Assumptions!$B$18,0)),0) -> 0 | K11: =(A11<=Assumptions!$B$12)*(E11+I11) -> 1094335 | L11: =(A11<=Assumptions!$B$12)*(E11-H11+I11-J11) -> 431006.59
A12: 6 | B12: =Assumptions!$B$20+A12 -> 13 | C12: =IF(A12<=Assumptions!$B$7,Assumptions!$B$5*(1+Assumptions!$B$6)^(INT((B12-1)/5)-INT(Assumptions!$B$20/5)),IF(A12<=Assumptions!$B$7+Assumptions!$B$8,0,Assumptions!$B$5*(1+Assumptions!$B$6)^(INT((Assumptions!$B$20+Assumptions!$B$7-1)/5)-INT(Assumptions!$B$20/5))*Assumptions!$B$9*(1+Assumptions!$B$10)^(A12-Assumptions!$B$7-Assumptions!$B$8-1))) -> 1111000 | D12: =-C12*Assumptions!$B$11 -> -16665 | E12: =C12+D12 -> 1094335 | F12: =IF(A12<=Assumptions!$B$18,Assumptions!$B$22*Assumptions!$B$17,-CUMIPMT(Assumptions!$B$17,Assumptions!$B$19,Assumptions!$B$22,A12-Assumptions!$B$18,A12-Assumptions!$B$18,0)) -> 487776.12 | G12: =IF(A12<=Assumptions!$B$18,0,-CUMPRINC(Assumptions!$B$17,Assumptions!$B$19,Assumptions!$B$22,A12-Assumptions!$B$18,A12-Assumptions!$B$18,0)) -> 175552.29 | H12: =F12+G12 -> 663328.41 | I12: =IF(A12=Assumptions!$B$12,E13/Assumptions!$B$13*(1-Assumptions!$B$14),0) -> 0 | J12: =IF(A12=Assumptions!$B$12,Assumptions!$B$22+IF(A12<=Assumptions!$B$18,0,CUMPRINC(Assumptions!$B$17,Assumptions!$B$19,Assumptions!$B$22,1,A12-Assumptions!$B$18,0)),0) -> 0 | K12: =(A12<=Assumptions!$B$12)*(E12+I12) -> 1094335 | L12: =(A12<=Assumptions!$B$12)*(E12-H12+I12-J12) -> 431006.59
A13: 7 | B13: =Assumptions!$B$20+A13 -> 14 | C13: =IF(A13<=Assumptions!$B$7,Assumptions!$B$5*(1+Assumptions!$B$6)^(INT((B13-1)/5)-INT(Assumptions!$B$20/5)),IF(A13<=Assumptions!$B$7+Assumptions!$B$8,0,Assumptions!$B$5*(1+Assumptions!$B$6)^(INT((Assumptions!$B$20+Assumptions!$B$7-1)/5)-INT(Assumptions!$B$20/5))*Assumptions!$B$9*(1+Assumptions!$B$10)^(A13-Assumptions!$B$7-Assumptions!$B$8-1))) -> 1111000 | D13: =-C13*Assumptions!$B$11 -> -16665 | E13: =C13+D13 -> 1094335 | F13: =IF(A13<=Assumptions!$B$18,Assumptions!$B$22*Assumptions!$B$17,-CUMIPMT(Assumptions!$B$17,Assumptions!$B$19,Assumptions!$B$22,A13-Assumptions!$B$18,A13-Assumptions!$B$18,0)) -> 477330.76 | G13: =IF(A13<=Assumptions!$B$18,0,-CUMPRINC(Assumptions!$B$17,Assumptions!$B$19,Assumptions!$B$22,A13-Assumptions!$B$18,A13-Assumptions!$B$18,0)) -> 185997.65 | H13: =F13+G13 -> 663328.41 | I13: =IF(A13=Assumptions!$B$12,E14/Assumptions!$B$13*(1-Assumptions!$B$14),0) -> 0 | J13: =IF(A13=Assumptions!$B$12,Assumptions!$B$22+IF(A13<=Assumptions!$B$18,0,CUMPRINC(Assumptions!$B$17,Assumptions!$B$19,Assumptions!$B$22,1,A13-Assumptions!$B$18,0)),0) -> 0 | K13: =(A13<=Assumptions!$B$12)*(E13+I13) -> 1094335 | L13: =(A13<=Assumptions!$B$12)*(E13-H13+I13-J13) -> 431006.59
A14: 8 | B14: =Assumptions!$B$20+A14 -> 15 | C14: =IF(A14<=Assumptions!$B$7,Assumptions!$B$5*(1+Assumptions!$B$6)^(INT((B14-1)/5)-INT(Assumptions!$B$20/5)),IF(A14<=Assumptions!$B$7+Assumptions!$B$8,0,Assumptions!$B$5*(1+Assumptions!$B$6)^(INT((Assumptions!$B$20+Assumptions!$B$7-1)/5)-INT(Assumptions!$B$20/5))*Assumptions!$B$9*(1+Assumptions!$B$10)^(A14-Assumptions!$B$7-Assumptions!$B$8-1))) -> 1111000 | D14: =-C14*Assumptions!$B$11 -> -16665 | E14: =C14+D14 -> 1094335 | F14: =IF(A14<=Assumptions!$B$18,Assumptions!$B$22*Assumptions!$B$17,-CUMIPMT(Assumptions!$B$17,Assumptions!$B$19,Assumptions!$B$22,A14-Assumptions!$B$18,A14-Assumptions!$B$18,0)) -> 466263.9 | G14: =IF(A14<=Assumptions!$B$18,0,-CUMPRINC(Assumptions!$B$17,Assumptions!$B$19,Assumptions!$B$22,A14-Assumptions!$B$18,A14-Assumptions!$B$18,0)) -> 197064.51 | H14: =F14+G14 -> 663328.41 | I14: =IF(A14=Assumptions!$B$12,E15/Assumptions!$B$13*(1-Assumptions!$B$14),0) -> 0 | J14: =IF(A14=Assumptions!$B$12,Assumptions!$B$22+IF(A14<=Assumptions!$B$18,0,CUMPRINC(Assumptions!$B$17,Assumptions!$B$19,Assumptions!$B$22,1,A14-Assumptions!$B$18,0)),0) -> 0 | K14: =(A14<=Assumptions!$B$12)*(E14+I14) -> 1094335 | L14: =(A14<=Assumptions!$B$12)*(E14-H14+I14-J14) -> 431006.59
A15: 9 | B15: =Assumptions!$B$20+A15 -> 16 | C15: =IF(A15<=Assumptions!$B$7,Assumptions!$B$5*(1+Assumptions!$B$6)^(INT((B15-1)/5)-INT(Assumptions!$B$20/5)),IF(A15<=Assumptions!$B$7+Assumptions!$B$8,0,Assumptions!$B$5*(1+Assumptions!$B$6)^(INT((Assumptions!$B$20+Assumptions!$B$7-1)/5)-INT(Assumptions!$B$20/5))*Assumptions!$B$9*(1+Assumptions!$B$10)^(A15-Assumptions!$B$7-Assumptions!$B$8-1))) -> 0 | D15: =-C15*Assumptions!$B$11 -> 0 | E15: =C15+D15 -> 0 | F15: =IF(A15<=Assumptions!$B$18,Assumptions!$B$22*Assumptions!$B$17,-CUMIPMT(Assumptions!$B$17,Assumptions!$B$19,Assumptions!$B$22,A15-Assumptions!$B$18,A15-Assumptions!$B$18,0)) -> 454538.56 | G15: =IF(A15<=Assumptions!$B$18,0,-CUMPRINC(Assumptions!$B$17,Assumptions!$B$19,Assumptions!$B$22,A15-Assumptions!$B$18,A15-Assumptions!$B$18,0)) -> 208789.85 | H15: =F15+G15 -> 663328.41 | I15: =IF(A15=Assumptions!$B$12,E16/Assumptions!$B$13*(1-Assumptions!$B$14),0) -> 0 | J15: =IF(A15=Assumptions!$B$12,Assumptions!$B$22+IF(A15<=Assumptions!$B$18,0,CUMPRINC(Assumptions!$B$17,Assumptions!$B$19,Assumptions!$B$22,1,A15-Assumptions!$B$18,0)),0) -> 0 | K15: =(A15<=Assumptions!$B$12)*(E15+I15) -> 0 | L15: =(A15<=Assumptions!$B$12)*(E15-H15+I15-J15) -> -663328.41
A16: 10 | B16: =Assumptions!$B$20+A16 -> 17 | C16: =IF(A16<=Assumptions!$B$7,Assumptions!$B$5*(1+Assumptions!$B$6)^(INT((B16-1)/5)-INT(Assumptions!$B$20/5)),IF(A16<=Assumptions!$B$7+Assumptions!$B$8,0,Assumptions!$B$5*(1+Assumptions!$B$6)^(INT((Assumptions!$B$20+Assumptions!$B$7-1)/5)-INT(Assumptions!$B$20/5))*Assumptions!$B$9*(1+Assumptions!$B$10)^(A16-Assumptions!$B$7-Assumptions!$B$8-1))) -> 1055450 | D16: =-C16*Assumptions!$B$11 -> -15831.75 | E16: =C16+D16 -> 1039618.2 | F16: =IF(A16<=Assumptions!$B$18,Assumptions!$B$22*Assumptions!$B$17,-CUMIPMT(Assumptions!$B$17,Assumptions!$B$19,Assumptions!$B$22,A16-Assumptions!$B$18,A16-Assumptions!$B$18,0)) -> 442115.57 | G16: =IF(A16<=Assumptions!$B$18,0,-CUMPRINC(Assumptions!$B$17,Assumptions!$B$19,Assumptions!$B$22,A16-Assumptions!$B$18,A16-Assumptions!$B$18,0)) -> 221212.84 | H16: =F16+G16 -> 663328.41 | I16: =IF(A16=Assumptions!$B$12,E17/Assumptions!$B$13*(1-Assumptions!$B$14),0) -> 14406958 | J16: =IF(A16=Assumptions!$B$12,Assumptions!$B$22+IF(A16<=Assumptions!$B$18,0,CUMPRINC(Assumptions!$B$17,Assumptions!$B$19,Assumptions!$B$22,1,A16-Assumptions!$B$18,0)),0) -> 7209300.9 | K16: =(A16<=Assumptions!$B$12)*(E16+I16) -> 15446576 | L16: =(A16<=Assumptions!$B$12)*(E16-H16+I16-J16) -> 7573946.9
A17: 11 | B17: =Assumptions!$B$20+A17 -> 18 | C17: =IF(A17<=Assumptions!$B$7,Assumptions!$B$5*(1+Assumptions!$B$6)^(INT((B17-1)/5)-INT(Assumptions!$B$20/5)),IF(A17<=Assumptions!$B$7+Assumptions!$B$8,0,Assumptions!$B$5*(1+Assumptions!$B$6)^(INT((Assumptions!$B$20+Assumptions!$B$7-1)/5)-INT(Assumptions!$B$20/5))*Assumptions!$B$9*(1+Assumptions!$B$10)^(A17-Assumptions!$B$7-Assumptions!$B$8-1))) -> 1076559 | D17: =-C17*Assumptions!$B$11 -> -16148.385 | E17: =C17+D17 -> 1060410.6 | F17: =IF(A17<=Assumptions!$B$18,Assumptions!$B$22*Assumptions!$B$17,-CUMIPMT(Assumptions!$B$17,Assumptions!$B$19,Assumptions!$B$22,A17-Assumptions!$B$18,A17-Assumptions!$B$18,0)) -> 428953.4 | G17: =IF(A17<=Assumptions!$B$18,0,-CUMPRINC(Assumptions!$B$17,Assumptions!$B$19,Assumptions!$B$22,A17-Assumptions!$B$18,A17-Assumptions!$B$18,0)) -> 234375.01 | H17: =F17+G17 -> 663328.41 | I17: =IF(A17=Assumptions!$B$12,E18/Assumptions!$B$13*(1-Assumptions!$B$14),0) -> 0 | J17: =IF(A17=Assumptions!$B$12,Assumptions!$B$22+IF(A17<=Assumptions!$B$18,0,CUMPRINC(Assumptions!$B$17,Assumptions!$B$19,Assumptions!$B$22,1,A17-Assumptions!$B$18,0)),0) -> 0 | K17: =(A17<=Assumptions!$B$12)*(E17+I17) -> 0 | L17: =(A17<=Assumptions!$B$12)*(E17-H17+I17-J17) -> 0
A18: 12 | B18: =Assumptions!$B$20+A18 -> 19 | C18: =IF(A18<=Assumptions!$B$7,Assumptions!$B$5*(1+Assumptions!$B$6)^(INT((B18-1)/5)-INT(Assumptions!$B$20/5)),IF(A18<=Assumptions!$B$7+Assumptions!$B$8,0,Assumptions!$B$5*(1+Assumptions!$B$6)^(INT((Assumptions!$B$20+Assumptions!$B$7-1)/5)-INT(Assumptions!$B$20/5))*Assumptions!$B$9*(1+Assumptions!$B$10)^(A18-Assumptions!$B$7-Assumptions!$B$8-1))) -> 1098090.2 | D18: =-C18*Assumptions!$B$11 -> -16471.353 | E18: =C18+D18 -> 1081618.8 | F18: =IF(A18<=Assumptions!$B$18,Assumptions!$B$22*Assumptions!$B$17,-CUMIPMT(Assumptions!$B$17,Assumptions!$B$19,Assumptions!$B$22,A18-Assumptions!$B$18,A18-Assumptions!$B$18,0)) -> 415008.09 | G18: =IF(A18<=Assumptions!$B$18,0,-CUMPRINC(Assumptions!$B$17,Assumptions!$B$19,Assumptions!$B$22,A18-Assumptions!$B$18,A18-Assumptions!$B$18,0)) -> 248320.32 | H18: =F18+G18 -> 663328.41 | I18: =IF(A18=Assumptions!$B$12,E19/Assumptions!$B$13*(1-Assumptions!$B$14),0) -> 0 | J18: =IF(A18=Assumptions!$B$12,Assumptions!$B$22+IF(A18<=Assumptions!$B$18,0,CUMPRINC(Assumptions!$B$17,Assumptions!$B$19,Assumptions!$B$22,1,A18-Assumptions!$B$18,0)),0) -> 0 | K18: =(A18<=Assumptions!$B$12)*(E18+I18) -> 0 | L18: =(A18<=Assumptions!$B$12)*(E18-H18+I18-J18) -> 0
... A21: 15 | B21: =Assumptions!$B$20+A21 -> 22 | C21: =IF(A21<=Assumptions!$B$7,Assumptions!$B$5*(1+Assumptions!$B$6)^(INT((B21-1)/5)-INT(Assumptions!$B$20/5)),IF(A21<=Assumptions!$B$7+Assumptions!$B$8,0,Assumptions!$B$5*(1+Assumptions!$B$6)^(INT((Assumptions!$B$20+Assumptions!$B$7-1)/5)-INT(Assumptions!$B$20/5))*Assumptions!$B$9*(1+Assumptions!$B$10)^(A21-Assumptions!$B$7-Assumptions!$B$8-1))) -> 1165302.1 | D21: =-C21*Assumptions!$B$11 -> -17479.531 | E21: =C21+D21 -> 1147822.6 | F21: =IF(A21<=Assumptions!$B$18,Assumptions!$B$22*Assumptions!$B$17,-CUMIPMT(Assumptions!$B$17,Assumptions!$B$19,Assumptions!$B$22,A21-Assumptions!$B$18,A21-Assumptions!$B$18,0)) -> 367993.26 | G21: =IF(A21<=Assumptions!$B$18,0,-CUMPRINC(Assumptions!$B$17,Assumptions!$B$19,Assumptions!$B$22,A21-Assumptions!$B$18,A21-Assumptions!$B$18,0)) -> 295335.16 | H21: =F21+G21 -> 663328.41 | I21: =IF(A21=Assumptions!$B$12,E22/Assumptions!$B$13*(1-Assumptions!$B$14),0) -> 0 | J21: =IF(A21=Assumptions!$B$12,Assumptions!$B$22+IF(A21<=Assumptions!$B$18,0,CUMPRINC(Assumptions!$B$17,Assumptions!$B$19,Assumptions!$B$22,1,A21-Assumptions!$B$18,0)),0) -> 0 | K21: =(A21<=Assumptions!$B$12)*(E21+I21) -> 0 | L21: =(A21<=Assumptions!$B$12)*(E21-H21+I21-J21) -> 0
A22: 16 | B22: =Assumptions!$B$20+A22 -> 23 | C22: =IF(A22<=Assumptions!$B$7,Assumptions!$B$5*(1+Assumptions!$B$6)^(INT((B22-1)/5)-INT(Assumptions!$B$20/5)),IF(A22<=Assumptions!$B$7+Assumptions!$B$8,0,Assumptions!$B$5*(1+Assumptions!$B$6)^(INT((Assumptions!$B$20+Assumptions!$B$7-1)/5)-INT(Assumptions!$B$20/5))*Assumptions!$B$9*(1+Assumptions!$B$10)^(A22-Assumptions!$B$7-Assumptions!$B$8-1))) -> 1188608.1 | D22: =-C22*Assumptions!$B$11 -> -17829.122 | E22: =C22+D22 -> 1170779 | F22: =IF(A22<=Assumptions!$B$18,Assumptions!$B$22*Assumptions!$B$17,-CUMIPMT(Assumptions!$B$17,Assumptions!$B$19,Assumptions!$B$22,A22-Assumptions!$B$18,A22-Assumptions!$B$18,0)) -> 350420.82 | G22: =IF(A22<=Assumptions!$B$18,0,-CUMPRINC(Assumptions!$B$17,Assumptions!$B$19,Assumptions!$B$22,A22-Assumptions!$B$18,A22-Assumptions!$B$18,0)) -> 312907.6 | H22: =F22+G22 -> 663328.41 | I22: =IF(A22=Assumptions!$B$12,E22*(1+Assumptions!$B$10)/Assumptions!$B$13*(1-Assumptions!$B$14),0) -> 0 | J22: =IF(A22=Assumptions!$B$12,Assumptions!$B$22+IF(A22<=Assumptions!$B$18,0,CUMPRINC(Assumptions!$B$17,Assumptions!$B$19,Assumptions!$B$22,1,A22-Assumptions!$B$18,0)),0) -> 0 | K22: =(A22<=Assumptions!$B$12)*(E22+I22) -> 0 | L22: =(A22<=Assumptions!$B$12)*(E22-H22+I22-J22) -> 0
