Workbook

Sheet Returns
A1: HYPERSCALE CAMPUS | RETURNS
B3: Unlevered | C3: Levered
A4: IRR | B4: =(1+IRR(Campus!H41:AV41,0.03))^4-1 -> 0.13817692 | C4: =(1+IRR(Campus!H42:AV42,0.03))^4-1 -> 0.24341654
A5: Equity multiple | B5: =SUMIF(Campus!H41:AV41,">0")/-SUMIF(Campus!H41:AV41,"<0") -> 2.1658417 | C5: =SUMIF(Campus!H42:AV42,">0")/-SUMIF(Campus!H42:AV42,"<0") -> 3.2296383
A6: Profit | B6: =SUM(Campus!H41:AV41) -> 2.6530831e+09 | C6: =SUM(Campus!H42:AV42) -> 1.8324959e+09
A8: Total development cost | B8: =SUM(Campus!H26:AV26) -> 2423000000
A9: Peak Murabaha balance | B9: =MAX(Campus!H38:AV38) -> 2.236369e+09

Sheet Campus
A1: HYPERSCALE CAMPUS | INPUTS AND QUARTERLY CASH FLOW (SAR)
A3: PHASES | B3: IT load (MW) | C3: Start quarter | D3: Build (quarters) | E3: Capex per MW (SAR m) | F3: Pre-let at delivery
A4: Phase 1 | B4: 36 | C4: 1 | D4: 6 | E4: 38 | F4: 0.7
A5: Phase 2 | B5: 24 | C5: 7 | D5: 5 | E5: 40 | F5: 0.5
A8: Land (SAR) | B8: 95000000
A9: Rent per kW a month (SAR) | B9: 330
A10: Rent escalation a year | B10: 0.025
A11: Take-up of the rest (quarters) | B11: 4
A12: PUE | B12: 1.3
A13: Power tariff (SAR per MWh) | B13: 180
A14: Power margin kept | B14: 0.1
A15: Operating costs (% of rent) | B15: 0.12
A16: Murabaha share of cost | B16: 0.6
A17: Murabaha profit rate | B17: 0.068
A18: Exit quarter | B18: 32
A19: Exit cap rate | B19: 0.0725
A20: Disposal costs | B20: 0.01
A22: Quarter | H22: 0 | I22: 1 | J22: 2 | K22: 3 | L22: 4 | M22: 5 | N22: 6 | O22: 7 | P22: 8 | Q22: 9 | R22: 10 | S22: 11 | T22: 12 | U22: 13 | V22: 14 | W22: 15 | X22: 16 | Y22: 17 | Z22: 18 | AA22: 19 | AB22: 20 | AC22: 21 | AD22: 22 | AE22: 23 | AF22: 24 | AG22: 25 | AH22: 26 | AI22: 27 | AJ22: 28 | AK22: 29 | AL22: 30 | AM22: 31 | AN22: 32 | AO22: 33 | AP22: 34 | AQ22: 35 | AR22: 36 | AS22: 37 | AT22: 38 | AU22: 39 | AV22: 40
A23: Phase 1 capex | H23: =IF(AND(H$22>=$C$4,H$22<$C$4+$D$4),$B$4*$E$4*1000000/$D$4,0) -> 0 | I23: =IF(AND(I$22>=$C$4,I$22<$C$4+$D$4),$B$4*$E$4*1000000/$D$4,0) -> 228000000 | J23: =IF(AND(J$22>=$C$4,J$22<$C$4+$D$4),$B$4*$E$4*1000000/$D$4,0) -> 228000000 | K23: =IF(AND(K$22>=$C$4,K$22<$C$4+$D$4),$B$4*$E$4*1000000/$D$4,0) -> 228000000 | L23: =IF(AND(L$22>=$C$4,L$22<$C$4+$D$4),$B$4*$E$4*1000000/$D$4,0) -> 228000000 | M23: =IF(AND(M$22>=$C$4,M$22<$C$4+$D$4),$B$4*$E$4*1000000/$D$4,0) -> 228000000 | N23: =IF(AND(N$22>=$C$4,N$22<$C$4+$D$4),$B$4*$E$4*1000000/$D$4,0) -> 228000000 | O23: =IF(AND(O$22>=$C$4,O$22<$C$4+$D$4),$B$4*$E$4*1000000/$D$4,0) -> 0 | ... AV23: =IF(AND(AV$22>=$C$4,AV$22<$C$4+$D$4),$B$4*$E$4*1000000/$D$4,0) -> 0
A24: Phase 2 capex | H24: =IF(AND(H$22>=$C$5,H$22<$C$5+$D$5),$B$5*$E$5*1000000/$D$5,0) -> 0 | I24: =IF(AND(I$22>=$C$5,I$22<$C$5+$D$5),$B$5*$E$5*1000000/$D$5,0) -> 0 | J24: =IF(AND(J$22>=$C$5,J$22<$C$5+$D$5),$B$5*$E$5*1000000/$D$5,0) -> 0 | K24: =IF(AND(K$22>=$C$5,K$22<$C$5+$D$5),$B$5*$E$5*1000000/$D$5,0) -> 0 | L24: =IF(AND(L$22>=$C$5,L$22<$C$5+$D$5),$B$5*$E$5*1000000/$D$5,0) -> 0 | M24: =IF(AND(M$22>=$C$5,M$22<$C$5+$D$5),$B$5*$E$5*1000000/$D$5,0) -> 0 | N24: =IF(AND(N$22>=$C$5,N$22<$C$5+$D$5),$B$5*$E$5*1000000/$D$5,0) -> 0 | O24: =IF(AND(O$22>=$C$5,O$22<$C$5+$D$5),$B$5*$E$5*1000000/$D$5,0) -> 192000000 | ... AV24: =IF(AND(AV$22>=$C$5,AV$22<$C$5+$D$5),$B$5*$E$5*1000000/$D$5,0) -> 0
A25: Land | H25: =$B$8 -> 95000000 | I25: 0 | J25: 0 | K25: 0 | L25: 0 | M25: 0 | N25: 0 | O25: 0 | P25: 0 | Q25: 0 | R25: 0 | S25: 0 | T25: 0 | U25: 0 | V25: 0 | W25: 0 | X25: 0 | Y25: 0 | Z25: 0 | AA25: 0 | AB25: 0 | AC25: 0 | AD25: 0 | AE25: 0 | AF25: 0 | AG25: 0 | AH25: 0 | AI25: 0 | AJ25: 0 | AK25: 0 | AL25: 0 | AM25: 0 | AN25: 0 | AO25: 0 | AP25: 0 | AQ25: 0 | AR25: 0 | AS25: 0 | AT25: 0 | AU25: 0 | AV25: 0
A26: Total cost | H26: =SUM(H23:H25) -> 95000000 | I26: =SUM(I23:I25) -> 228000000 | J26: =SUM(J23:J25) -> 228000000 | K26: =SUM(K23:K25) -> 228000000 | L26: =SUM(L23:L25) -> 228000000 | M26: =SUM(M23:M25) -> 228000000 | N26: =SUM(N23:N25) -> 228000000 | O26: =SUM(O23:O25) -> 192000000 | ... AV26: =SUM(AV23:AV25) -> 0
A28: Phase 1 leased MW | H28: =IF((H$22-$C$4-$D$4+1)>=1,$B$4*MIN(1,$F$4+(1-$F$4)*((H$22-$C$4-$D$4+1)-1)/$B$11),0) -> 0 | I28: =IF((I$22-$C$4-$D$4+1)>=1,$B$4*MIN(1,$F$4+(1-$F$4)*((I$22-$C$4-$D$4+1)-1)/$B$11),0) -> 0 | J28: =IF((J$22-$C$4-$D$4+1)>=1,$B$4*MIN(1,$F$4+(1-$F$4)*((J$22-$C$4-$D$4+1)-1)/$B$11),0) -> 0 | K28: =IF((K$22-$C$4-$D$4+1)>=1,$B$4*MIN(1,$F$4+(1-$F$4)*((K$22-$C$4-$D$4+1)-1)/$B$11),0) -> 0 | L28: =IF((L$22-$C$4-$D$4+1)>=1,$B$4*MIN(1,$F$4+(1-$F$4)*((L$22-$C$4-$D$4+1)-1)/$B$11),0) -> 0 | M28: =IF((M$22-$C$4-$D$4+1)>=1,$B$4*MIN(1,$F$4+(1-$F$4)*((M$22-$C$4-$D$4+1)-1)/$B$11),0) -> 0 | N28: =IF((N$22-$C$4-$D$4+1)>=1,$B$4*MIN(1,$F$4+(1-$F$4)*((N$22-$C$4-$D$4+1)-1)/$B$11),0) -> 0 | O28: =IF((O$22-$C$4-$D$4+1)>=1,$B$4*MIN(1,$F$4+(1-$F$4)*((O$22-$C$4-$D$4+1)-1)/$B$11),0) -> 25.2 | ... AV28: =IF((AV$22-$C$4-$D$4+1)>=1,$B$4*MIN(1,$F$4+(1-$F$4)*((AV$22-$C$4-$D$4+1)-1)/$B$11),0) -> 36
A29: Phase 2 leased MW | H29: =IF((H$22-$C$5-$D$5+1)>=1,$B$5*MIN(1,$F$5+(1-$F$5)*((H$22-$C$5-$D$5+1)-1)/$B$11),0) -> 0 | I29: =IF((I$22-$C$5-$D$5+1)>=1,$B$5*MIN(1,$F$5+(1-$F$5)*((I$22-$C$5-$D$5+1)-1)/$B$11),0) -> 0 | J29: =IF((J$22-$C$5-$D$5+1)>=1,$B$5*MIN(1,$F$5+(1-$F$5)*((J$22-$C$5-$D$5+1)-1)/$B$11),0) -> 0 | K29: =IF((K$22-$C$5-$D$5+1)>=1,$B$5*MIN(1,$F$5+(1-$F$5)*((K$22-$C$5-$D$5+1)-1)/$B$11),0) -> 0 | L29: =IF((L$22-$C$5-$D$5+1)>=1,$B$5*MIN(1,$F$5+(1-$F$5)*((L$22-$C$5-$D$5+1)-1)/$B$11),0) -> 0 | M29: =IF((M$22-$C$5-$D$5+1)>=1,$B$5*MIN(1,$F$5+(1-$F$5)*((M$22-$C$5-$D$5+1)-1)/$B$11),0) -> 0 | N29: =IF((N$22-$C$5-$D$5+1)>=1,$B$5*MIN(1,$F$5+(1-$F$5)*((N$22-$C$5-$D$5+1)-1)/$B$11),0) -> 0 | O29: =IF((O$22-$C$5-$D$5+1)>=1,$B$5*MIN(1,$F$5+(1-$F$5)*((O$22-$C$5-$D$5+1)-1)/$B$11),0) -> 0 | ... AV29: =IF((AV$22-$C$5-$D$5+1)>=1,$B$5*MIN(1,$F$5+(1-$F$5)*((AV$22-$C$5-$D$5+1)-1)/$B$11),0) -> 24
A30: Rent | H30: =(H28+H29)*1000*$B$9*3*(1+$B$10)^INT(H$22/4) -> 0 | I30: =(I28+I29)*1000*$B$9*3*(1+$B$10)^INT(I$22/4) -> 0 | J30: =(J28+J29)*1000*$B$9*3*(1+$B$10)^INT(J$22/4) -> 0 | K30: =(K28+K29)*1000*$B$9*3*(1+$B$10)^INT(K$22/4) -> 0 | L30: =(L28+L29)*1000*$B$9*3*(1+$B$10)^INT(L$22/4) -> 0 | M30: =(M28+M29)*1000*$B$9*3*(1+$B$10)^INT(M$22/4) -> 0 | N30: =(N28+N29)*1000*$B$9*3*(1+$B$10)^INT(N$22/4) -> 0 | O30: =(O28+O29)*1000*$B$9*3*(1+$B$10)^INT(O$22/4) -> 25571700 | ... AV30: =(AV28+AV29)*1000*$B$9*3*(1+$B$10)^INT(AV$22/4) -> 76037022
A31: Power margin | H31: =(H28+H29)*$B$12*24*91.25*$B$13*$B$14 -> 0 | I31: =(I28+I29)*$B$12*24*91.25*$B$13*$B$14 -> 0 | J31: =(J28+J29)*$B$12*24*91.25*$B$13*$B$14 -> 0 | K31: =(K28+K29)*$B$12*24*91.25*$B$13*$B$14 -> 0 | L31: =(L28+L29)*$B$12*24*91.25*$B$13*$B$14 -> 0 | M31: =(M28+M29)*$B$12*24*91.25*$B$13*$B$14 -> 0 | N31: =(N28+N29)*$B$12*24*91.25*$B$13*$B$14 -> 0 | O31: =(O28+O29)*$B$12*24*91.25*$B$13*$B$14 -> 1291399.2 | ... AV31: =(AV28+AV29)*$B$12*24*91.25*$B$13*$B$14 -> 3074760
A32: Operating costs | H32: =-H30*$B$15 -> 0 | I32: =-I30*$B$15 -> 0 | J32: =-J30*$B$15 -> 0 | K32: =-K30*$B$15 -> 0 | L32: =-L30*$B$15 -> 0 | M32: =-M30*$B$15 -> 0 | N32: =-N30*$B$15 -> 0 | O32: =-O30*$B$15 -> -3068604 | ... AV32: =-AV30*$B$15 -> -9124442.6
A33: Net operating income | H33: =H30+H31+H32 -> 0 | I33: =I30+I31+I32 -> 0 | J33: =J30+J31+J32 -> 0 | K33: =K30+K31+K32 -> 0 | L33: =L30+L31+L32 -> 0 | M33: =M30+M31+M32 -> 0 | N33: =N30+N31+N32 -> 0 | O33: =O30+O31+O32 -> 23794495 | ... AV33: =AV30+AV31+AV32 -> 69987339
A35: Exit value | H35: =IF(H$22=$B$18,4*I33/$B$19*(1-$B$20),0) -> 0 | I35: =IF(I$22=$B$18,4*J33/$B$19*(1-$B$20),0) -> 0 | J35: =IF(J$22=$B$18,4*K33/$B$19*(1-$B$20),0) -> 0 | K35: =IF(K$22=$B$18,4*L33/$B$19*(1-$B$20),0) -> 0 | L35: =IF(L$22=$B$18,4*M33/$B$19*(1-$B$20),0) -> 0 | M35: =IF(M$22=$B$18,4*N33/$B$19*(1-$B$20),0) -> 0 | N35: =IF(N$22=$B$18,4*O33/$B$19*(1-$B$20),0) -> 0 | O35: =IF(O$22=$B$18,4*P33/$B$19*(1-$B$20),0) -> 0 | ... AU35: =IF(AU$22=$B$18,4*AV33/$B$19*(1-$B$20),0) -> 0 | AV35: =IF(AV$22=$B$18,4*AV33/$B$19*(1-$B$20),0) -> 0
A36: Murabaha drawn | H36: =H26*$B$16 -> 57000000 | I36: =I26*$B$16 -> 136800000 | J36: =J26*$B$16 -> 136800000 | K36: =K26*$B$16 -> 136800000 | L36: =L26*$B$16 -> 136800000 | M36: =M26*$B$16 -> 136800000 | N36: =N26*$B$16 -> 136800000 | O36: =O26*$B$16 -> 115200000 | ... AV36: =AV26*$B$16 -> 0
A37: Murabaha profit (capitalised) | H37: =0 -> 0 | I37: =IF(I$22<=$B$18,H38*$B$17/4,0) -> 969000 | J37: =IF(J$22<=$B$18,I38*$B$17/4,0) -> 3311073 | K37: =IF(K$22<=$B$18,J38*$B$17/4,0) -> 5692961.2 | L37: =IF(L$22<=$B$18,K38*$B$17/4,0) -> 8115341.6 | M37: =IF(M$22<=$B$18,L38*$B$17/4,0) -> 10578902 | N37: =IF(N$22<=$B$18,M38*$B$17/4,0) -> 13084344 | O37: =IF(O$22<=$B$18,N38*$B$17/4,0) -> 15632378 | P37: =IF(P$22<=$B$18,O38*$B$17/4,0) -> 17856528 | ... AV37: =IF(AV$22<=$B$18,AU38*$B$17/4,0) -> 0
A38: Murabaha balance | H38: =0+H36+H37-H39 -> 57000000 | I38: =H38+I36+I37-I39 -> 194769000 | J38: =I38+J36+J37-J39 -> 334880073 | K38: =J38+K36+K37-K39 -> 4.7737303e+08 | L38: =K38+L36+L37-L39 -> 6.2228838e+08 | M38: =L38+M36+M37-M39 -> 7.6966728e+08 | N38: =M38+N36+N37-N39 -> 9.1955162e+08 | O38: =N38+O36+O37-O39 -> 1.050384e+09 | P38: =O38+P36+P37-P39 -> 1.1834405e+09 | ... AV38: =AU38+AV36+AV37-AV39 -> 0
A39: Murabaha repaid | H39: =IF(H$22=$B$18,0+H36+H37,0) -> 0 | I39: =IF(I$22=$B$18,H38+I36+I37,0) -> 0 | J39: =IF(J$22=$B$18,I38+J36+J37,0) -> 0 | K39: =IF(K$22=$B$18,J38+K36+K37,0) -> 0 | L39: =IF(L$22=$B$18,K38+L36+L37,0) -> 0 | M39: =IF(M$22=$B$18,L38+M36+M37,0) -> 0 | N39: =IF(N$22=$B$18,M38+N36+N37,0) -> 0 | O39: =IF(O$22=$B$18,N38+O36+O37,0) -> 0 | P39: =IF(P$22=$B$18,O38+P36+P37,0) -> 0 | ... AV39: =IF(AV$22=$B$18,AU38+AV36+AV37,0) -> 0
A41: Unlevered cash flow | H41: =(H$22<=$B$18)*(-H26+H33+H35) -> -95000000 | I41: =(I$22<=$B$18)*(-I26+I33+I35) -> -228000000 | J41: =(J$22<=$B$18)*(-J26+J33+J35) -> -228000000 | K41: =(K$22<=$B$18)*(-K26+K33+K35) -> -228000000 | L41: =(L$22<=$B$18)*(-L26+L33+L35) -> -228000000 | M41: =(M$22<=$B$18)*(-M26+M33+M35) -> -228000000 | N41: =(N$22<=$B$18)*(-N26+N33+N35) -> -228000000 | O41: =(O$22<=$B$18)*(-O26+O33+O35) -> -1.682055e+08 | ... AV41: =(AV$22<=$B$18)*(-AV26+AV33+AV35) -> 0
A42: Levered cash flow | H42: =(H$22<=$B$18)*(H41+H36-H39) -> -38000000 | I42: =(I$22<=$B$18)*(I41+I36-I39) -> -91200000 | J42: =(J$22<=$B$18)*(J41+J36-J39) -> -91200000 | K42: =(K$22<=$B$18)*(K41+K36-K39) -> -91200000 | L42: =(L$22<=$B$18)*(L41+L36-L39) -> -91200000 | M42: =(M$22<=$B$18)*(M41+M36-M39) -> -91200000 | N42: =(N$22<=$B$18)*(N41+N36-N39) -> -91200000 | O42: =(O$22<=$B$18)*(O41+O36-O39) -> -53005505 | ... AV42: =(AV$22<=$B$18)*(AV41+AV36-AV39) -> 0
