Workbook

Sheet Summary
A1: BRANCH INVESTMENT | SUMMARY
A3: Tenant | B3: High-street bank (25-year lease, 17 years unexpired)
A5: Net initial yield | B5: =Inputs!B6/(Inputs!B4*(1+Inputs!B5)) -> 0.060138242
A6: Reversionary yield | B6: =CF!D6*(1+Inputs!B23)/(Inputs!B4*(1+Inputs!B5)) -> 0.068040901
A8: Property IRR | B8: =XIRR(CF!C17:BK17,CF!C4:BK4) -> 0.08268438
A9: Equity IRR | B9: =XIRR(CF!C18:BK18,CF!C4:BK4) -> 0.098739053
A10: Equity multiple | B10: =SUMIF(CF!C18:BK18,">0")/-SUMIF(CF!C18:BK18,"<0") -> 2.088354
A11: Profit on equity | B11: =SUM(CF!C18:BK18) -> 3727830.2

Sheet Inputs
A1: INPUTS (GBP)
A3: Valuation date | B3: 46381
A4: Purchase price | B4: 6150000
A5: SDLT and fees (% of price) | B5: 0.068
A6: Passing rent (a year) | B6: 395000
A7: Quarters to the next review | B7: 6
A8: Review cycle (quarters) | B8: 20
A9: CPI assumption a year | B9: 0.025
A10: Review collar floor a year | B10: 0.01
A11: Review collar cap a year | B11: 0.03
A12: Exit quarter | B12: 40
A13: Exit yield | B13: 0.0625
A14: Purchaser costs at exit | B14: 0.068
... A19: Arrangement fee | B19: 0.01
A21: Loan | B21: =B4*B16 -> 3075000
A22: All-in rate | B22: =B17+B18 -> 0.06
A23: Review uplift (each review) | B23: =MAX((1+B10)^(B8/4),MIN((1+B11)^(B8/4),(1+B9)^(B8/4)))-1 -> 0.13140821

Sheet CF
A3: Quarter | C3: 0 | D3: 1 | E3: 2 | F3: 3 | G3: 4 | H3: 5 | I3: 6 | J3: 7 | K3: 8 | L3: 9 | M3: 10 | N3: 11 | O3: 12 | P3: 13 | Q3: 14 | R3: 15 | S3: 16 | T3: 17 | U3: 18 | V3: 19 | W3: 20 | X3: 21 | Y3: 22 | Z3: 23 | AA3: 24 | AB3: 25 | AC3: 26 | AD3: 27 | AE3: 28 | AF3: 29 | AG3: 30 | AH3: 31 | AI3: 32 | AJ3: 33 | AK3: 34 | AL3: 35 | AM3: 36 | AN3: 37 | AO3: 38 | AP3: 39 | AQ3: 40 | AR3: 41 | AS3: 42 | AT3: 43 | AU3: 44 | AV3: 45 | AW3: 46 | AX3: 47 | AY3: 48 | AZ3: 49 | BA3: 50 | BB3: 51 | BC3: 52 | BD3: 53 | BE3: 54 | BF3: 55 | BG3: 56 | BH3: 57 | BI3: 58 | BJ3: 59 | BK3: 60
A4: Quarter date | C4: =EDATE(Inputs!$B$3,3*C3) -> 46381 | D4: =EDATE(Inputs!$B$3,3*D3) -> 46471 | E4: =EDATE(Inputs!$B$3,3*E3) -> 46563 | F4: =EDATE(Inputs!$B$3,3*F3) -> 46655 | G4: =EDATE(Inputs!$B$3,3*G3) -> 46746 | H4: =EDATE(Inputs!$B$3,3*H3) -> 46837 | I4: =EDATE(Inputs!$B$3,3*I3) -> 46929 | J4: =EDATE(Inputs!$B$3,3*J3) -> 47021 | ... BK4: =EDATE(Inputs!$B$3,3*BK3) -> 51860
A5: Reviews passed | C5: =IF(C3<Inputs!$B$7,0,INT((C3-Inputs!$B$7)/Inputs!$B$8)+1) -> 0 | D5: =IF(D3<Inputs!$B$7,0,INT((D3-Inputs!$B$7)/Inputs!$B$8)+1) -> 0 | E5: =IF(E3<Inputs!$B$7,0,INT((E3-Inputs!$B$7)/Inputs!$B$8)+1) -> 0 | F5: =IF(F3<Inputs!$B$7,0,INT((F3-Inputs!$B$7)/Inputs!$B$8)+1) -> 0 | G5: =IF(G3<Inputs!$B$7,0,INT((G3-Inputs!$B$7)/Inputs!$B$8)+1) -> 0 | H5: =IF(H3<Inputs!$B$7,0,INT((H3-Inputs!$B$7)/Inputs!$B$8)+1) -> 0 | I5: =IF(I3<Inputs!$B$7,0,INT((I3-Inputs!$B$7)/Inputs!$B$8)+1) -> 1 | J5: =IF(J3<Inputs!$B$7,0,INT((J3-Inputs!$B$7)/Inputs!$B$8)+1) -> 1 | ... BK5: =IF(BK3<Inputs!$B$7,0,INT((BK3-Inputs!$B$7)/Inputs!$B$8)+1) -> 3
A6: Rent (a year) | C6: =Inputs!$B$6*(1+Inputs!$B$23)^C5 -> 395000 | D6: =Inputs!$B$6*(1+Inputs!$B$23)^D5 -> 395000 | E6: =Inputs!$B$6*(1+Inputs!$B$23)^E5 -> 395000 | F6: =Inputs!$B$6*(1+Inputs!$B$23)^F5 -> 395000 | G6: =Inputs!$B$6*(1+Inputs!$B$23)^G5 -> 395000 | H6: =Inputs!$B$6*(1+Inputs!$B$23)^H5 -> 395000 | I6: =Inputs!$B$6*(1+Inputs!$B$23)^I5 -> 446906.24 | J6: =Inputs!$B$6*(1+Inputs!$B$23)^J5 -> 446906.24 | ... BK6: =Inputs!$B$6*(1+Inputs!$B$23)^BK5 -> 572077.78
A7: Rent received | C7: =IF(AND(C3>=0,C3<Inputs!$B$12),C6/4,0)*(C$3<=Inputs!$B$12) -> 98750 | D7: =IF(AND(D3>=0,D3<Inputs!$B$12),D6/4,0)*(D$3<=Inputs!$B$12) -> 98750 | E7: =IF(AND(E3>=0,E3<Inputs!$B$12),E6/4,0)*(E$3<=Inputs!$B$12) -> 98750 | F7: =IF(AND(F3>=0,F3<Inputs!$B$12),F6/4,0)*(F$3<=Inputs!$B$12) -> 98750 | G7: =IF(AND(G3>=0,G3<Inputs!$B$12),G6/4,0)*(G$3<=Inputs!$B$12) -> 98750 | H7: =IF(AND(H3>=0,H3<Inputs!$B$12),H6/4,0)*(H$3<=Inputs!$B$12) -> 98750 | I7: =IF(AND(I3>=0,I3<Inputs!$B$12),I6/4,0)*(I$3<=Inputs!$B$12) -> 111726.56 | J7: =IF(AND(J3>=0,J3<Inputs!$B$12),J6/4,0)*(J$3<=Inputs!$B$12) -> 111726.56 | ... BK7: =IF(AND(BK3>=0,BK3<Inputs!$B$12),BK6/4,0)*(BK$3<=Inputs!$B$12) -> 0
A9: Purchase | C9: =IF(C3=0,-Inputs!$B$4*(1+Inputs!$B$5),0) -> -6568200 | D9: =IF(D3=0,-Inputs!$B$4*(1+Inputs!$B$5),0) -> 0 | E9: =IF(E3=0,-Inputs!$B$4*(1+Inputs!$B$5),0) -> 0 | F9: =IF(F3=0,-Inputs!$B$4*(1+Inputs!$B$5),0) -> 0 | G9: =IF(G3=0,-Inputs!$B$4*(1+Inputs!$B$5),0) -> 0 | H9: =IF(H3=0,-Inputs!$B$4*(1+Inputs!$B$5),0) -> 0 | I9: =IF(I3=0,-Inputs!$B$4*(1+Inputs!$B$5),0) -> 0 | J9: =IF(J3=0,-Inputs!$B$4*(1+Inputs!$B$5),0) -> 0 | ... BK9: =IF(BK3=0,-Inputs!$B$4*(1+Inputs!$B$5),0) -> 0
A10: Exit value | C10: =IF(C3=Inputs!$B$12,C6/Inputs!$B$13/(1+Inputs!$B$14),0) -> 0 | D10: =IF(D3=Inputs!$B$12,D6/Inputs!$B$13/(1+Inputs!$B$14),0) -> 0 | E10: =IF(E3=Inputs!$B$12,E6/Inputs!$B$13/(1+Inputs!$B$14),0) -> 0 | F10: =IF(F3=Inputs!$B$12,F6/Inputs!$B$13/(1+Inputs!$B$14),0) -> 0 | G10: =IF(G3=Inputs!$B$12,G6/Inputs!$B$13/(1+Inputs!$B$14),0) -> 0 | H10: =IF(H3=Inputs!$B$12,H6/Inputs!$B$13/(1+Inputs!$B$14),0) -> 0 | I10: =IF(I3=Inputs!$B$12,I6/Inputs!$B$13/(1+Inputs!$B$14),0) -> 0 | J10: =IF(J3=Inputs!$B$12,J6/Inputs!$B$13/(1+Inputs!$B$14),0) -> 0 | ... BK10: =IF(BK3=Inputs!$B$12,BK6/Inputs!$B$13/(1+Inputs!$B$14),0) -> 0
A12: Loan drawn | C12: =IF(C3=0,Inputs!$B$21,0) -> 3075000 | D12: =IF(D3=0,Inputs!$B$21,0) -> 0 | E12: =IF(E3=0,Inputs!$B$21,0) -> 0 | F12: =IF(F3=0,Inputs!$B$21,0) -> 0 | G12: =IF(G3=0,Inputs!$B$21,0) -> 0 | H12: =IF(H3=0,Inputs!$B$21,0) -> 0 | I12: =IF(I3=0,Inputs!$B$21,0) -> 0 | J12: =IF(J3=0,Inputs!$B$21,0) -> 0 | ... BK12: =IF(BK3=0,Inputs!$B$21,0) -> 0
A13: Interest | C13: =IF(AND(C3>0,(C$3<=Inputs!$B$12)),-Inputs!$B$21*Inputs!$B$22/4,0) -> 0 | D13: =IF(AND(D3>0,(D$3<=Inputs!$B$12)),-Inputs!$B$21*Inputs!$B$22/4,0) -> -46125 | E13: =IF(AND(E3>0,(E$3<=Inputs!$B$12)),-Inputs!$B$21*Inputs!$B$22/4,0) -> -46125 | F13: =IF(AND(F3>0,(F$3<=Inputs!$B$12)),-Inputs!$B$21*Inputs!$B$22/4,0) -> -46125 | G13: =IF(AND(G3>0,(G$3<=Inputs!$B$12)),-Inputs!$B$21*Inputs!$B$22/4,0) -> -46125 | H13: =IF(AND(H3>0,(H$3<=Inputs!$B$12)),-Inputs!$B$21*Inputs!$B$22/4,0) -> -46125 | I13: =IF(AND(I3>0,(I$3<=Inputs!$B$12)),-Inputs!$B$21*Inputs!$B$22/4,0) -> -46125 | J13: =IF(AND(J3>0,(J$3<=Inputs!$B$12)),-Inputs!$B$21*Inputs!$B$22/4,0) -> -46125 | ... BK13: =IF(AND(BK3>0,(BK$3<=Inputs!$B$12)),-Inputs!$B$21*Inputs!$B$22/4,0) -> 0
A14: Arrangement fee | C14: =IF(C3=0,-Inputs!$B$21*Inputs!$B$19,0) -> -30750 | D14: =IF(D3=0,-Inputs!$B$21*Inputs!$B$19,0) -> 0 | E14: =IF(E3=0,-Inputs!$B$21*Inputs!$B$19,0) -> 0 | F14: =IF(F3=0,-Inputs!$B$21*Inputs!$B$19,0) -> 0 | G14: =IF(G3=0,-Inputs!$B$21*Inputs!$B$19,0) -> 0 | H14: =IF(H3=0,-Inputs!$B$21*Inputs!$B$19,0) -> 0 | I14: =IF(I3=0,-Inputs!$B$21*Inputs!$B$19,0) -> 0 | J14: =IF(J3=0,-Inputs!$B$21*Inputs!$B$19,0) -> 0 | ... BK14: =IF(BK3=0,-Inputs!$B$21*Inputs!$B$19,0) -> 0
A15: Loan repaid | C15: =IF(C3=Inputs!$B$12,-Inputs!$B$21,0) -> 0 | D15: =IF(D3=Inputs!$B$12,-Inputs!$B$21,0) -> 0 | E15: =IF(E3=Inputs!$B$12,-Inputs!$B$21,0) -> 0 | F15: =IF(F3=Inputs!$B$12,-Inputs!$B$21,0) -> 0 | G15: =IF(G3=Inputs!$B$12,-Inputs!$B$21,0) -> 0 | H15: =IF(H3=Inputs!$B$12,-Inputs!$B$21,0) -> 0 | I15: =IF(I3=Inputs!$B$12,-Inputs!$B$21,0) -> 0 | J15: =IF(J3=Inputs!$B$12,-Inputs!$B$21,0) -> 0 | ... BK15: =IF(BK3=Inputs!$B$12,-Inputs!$B$21,0) -> 0
A17: Property cash flow | C17: =(C$3<=Inputs!$B$12)*(C7+C9+C10) -> -6469450 | D17: =(D$3<=Inputs!$B$12)*(D7+D9+D10) -> 98750 | E17: =(E$3<=Inputs!$B$12)*(E7+E9+E10) -> 98750 | F17: =(F$3<=Inputs!$B$12)*(F7+F9+F10) -> 98750 | G17: =(G$3<=Inputs!$B$12)*(G7+G9+G10) -> 98750 | H17: =(H$3<=Inputs!$B$12)*(H7+H9+H10) -> 98750 | I17: =(I$3<=Inputs!$B$12)*(I7+I9+I10) -> 111726.56 | J17: =(J$3<=Inputs!$B$12)*(J7+J9+J10) -> 111726.56 | ... BK17: =(BK$3<=Inputs!$B$12)*(BK7+BK9+BK10) -> 0
A18: Equity cash flow | C18: =(C$3<=Inputs!$B$12)*(C17+C12+C13+C14+C15) -> -3425200 | D18: =(D$3<=Inputs!$B$12)*(D17+D12+D13+D14+D15) -> 52625 | E18: =(E$3<=Inputs!$B$12)*(E17+E12+E13+E14+E15) -> 52625 | F18: =(F$3<=Inputs!$B$12)*(F17+F12+F13+F14+F15) -> 52625 | G18: =(G$3<=Inputs!$B$12)*(G17+G12+G13+G14+G15) -> 52625 | H18: =(H$3<=Inputs!$B$12)*(H17+H12+H13+H14+H15) -> 52625 | I18: =(I$3<=Inputs!$B$12)*(I17+I12+I13+I14+I15) -> 65601.561 | J18: =(J$3<=Inputs!$B$12)*(J17+J12+J13+J14+J15) -> 65601.561 | ... BK18: =(BK$3<=Inputs!$B$12)*(BK17+BK12+BK13+BK14+BK15) -> 0
