Workbook

Sheet Summary
B2: =Underwriting!B2 -> RETAIL DEVELOPMENT MODEL
B4: INVESTMENT DESCRIPTION
B6: Net Rentable Area (SF) | F6: =Underwriting!E18 -> 83000
B11: Sale Month | F11: =Underwriting!I15 -> 96
N20: PARTNERSHIP RETURNS | Q20: ROI | R20: EMx | S20: IRR
N21: LP | Q21: =Underwriting!I229/-SUMIF(Underwriting!L229:DP229,"<0") -> 1.483388 | R21: =Underwriting!G229 -> 2.483388 | S21: =Underwriting!H229 -> 0.15801218
N22: GP | Q22: =Underwriting!I228/-SUMIF(Underwriting!L228:DP228,"<0") -> 3.893068 | R22: =Underwriting!G228 -> 4.893068 | S22: =Underwriting!H228 -> 0.27062634
N24: PROPERTY RETURNS | Q24: ROI | R24: EMx | S24: IRR
N25: Unlevered | Q25: =Underwriting!I211/Underwriting!I36 -> 1.1046745 | R25: =Underwriting!G211 -> 2.1017549 | S25: =Underwriting!H211 -> 0.11915338
N26: Levered | Q26: =Underwriting!I212/Underwriting!I232 -> 1.724356 | R26: =Underwriting!G212 -> 2.724356 | S26: =Underwriting!H212 -> 0.17326763
N27: DEVELOPMENT RETURNS
N28: Yield-on-Cost | S28: =Underwriting!H215 -> 0.076203211
N29: Market Cap Rate | S29: =Underwriting!H216 -> 0.0675
N30: Development Spread | S30: =Underwriting!H217 -> 87.032115
H31: USES | M31: Amount
H32: Total Project Cost | M32: =Underwriting!I36 -> 27387471

Sheet Underwriting
B2: RETAIL DEVELOPMENT MODEL
B3: Analysis Month | L3: 0 | M3: 1 | N3: 2 | O3: 3 | P3: 4 | Q3: 5 | R3: 6 | S3: 7 | T3: 8 | U3: 9 | V3: 10 | W3: 11 | X3: 12 | Y3: 13 | Z3: 14 | AA3: 15 | AB3: 16 | AC3: 17 | AD3: 18 | AE3: 19 | AF3: 20 | AG3: 21 | AH3: 22 | AI3: 23 | AJ3: 24 | AK3: 25 | AL3: 26 | AM3: 27 | AN3: 28 | AO3: 29 | AP3: 30 | AQ3: 31 | AR3: 32 | AS3: 33 | AT3: 34 | AU3: 35 | AV3: 36 | AW3: 37 | AX3: 38 | AY3: 39 | AZ3: 40 | BA3: 41 | BB3: 42 | BC3: 43 | BD3: 44 | BE3: 45 | BF3: 46 | BG3: 47 | BH3: 48 | BI3: 49 | BJ3: 50 | BK3: 51 | BL3: 52 | BM3: 53 | BN3: 54 | BO3: 55 | BP3: 56 | BQ3: 57 | BR3: 58 | BS3: 59 | BT3: 60 | BU3: 61 | BV3: 62 | BW3: 63 | BX3: 64 | BY3: 65 | BZ3: 66 | CA3: 67 | CB3: 68 | CC3: 69 | CD3: 70 | CE3: 71 | CF3: 72 | CG3: 73 | CH3: 74 | CI3: 75 | CJ3: 76 | CK3: 77 | CL3: 78 | CM3: 79 | CN3: 80 | CO3: 81 | CP3: 82 | CQ3: 83 | CR3: 84 | CS3: 85 | CT3: 86 | CU3: 87 | CV3: 88 | CW3: 89 | CX3: 90 | CY3: 91 | CZ3: 92 | DA3: 93 | DB3: 94 | DC3: 95 | DD3: 96 | DE3: 97 | DF3: 98 | DG3: 99 | DH3: 100 | DI3: 101 | DJ3: 102 | DK3: 103 | DL3: 104 | DM3: 105 | DN3: 106 | DO3: 107 | DP3: 108
B5: Levered IRR | C5: =H212 -> 0.17326763 | D5: Levered EMx: | E5: =G212 -> 2.724356 | H5: Development Spread (Untrended) | I5: =H217 -> 87.032115
B13: Analysis Begin Date | E13: 46447
F15: Sale Month | I15: 96
B17: Land Area (SF) | E17: 520000
B18: Net Rentable Area (SF) | E18: =E105 -> 83000
B24: Analysis Date | L24: =EOMONTH($E$13,L3-1) -> 46446 | M24: =EOMONTH($E$13,M3-1) -> 46477 | N24: =EOMONTH($E$13,N3-1) -> 46507 | O24: =EOMONTH($E$13,O3-1) -> 46538 | P24: =EOMONTH($E$13,P3-1) -> 46568 | Q24: =EOMONTH($E$13,Q3-1) -> 46599 | R24: =EOMONTH($E$13,R3-1) -> 46630 | S24: =EOMONTH($E$13,S3-1) -> 46660 | ... DP24: =EOMONTH($E$13,DP3-1) -> 49734
B25: USES | D25: START | E25: END | F25: METHOD | H25: /RENTABLE SF | I25: AMOUNT
B27: Land Purchase Price | D27: 0 | E27: 0 | F27: Straight-Line | H27: =I27/$E$18 -> 118.07229 | I27: 9800000
B28: Closing / Legal Costs | D28: 0 | E28: 0 | F28: Straight-Line | H28: =I28/$E$18 -> 1.1807229 | I28: =I27*0.01 -> 98000
B30: Site Work | D30: 2 | E30: 8 | F30: Straight-Line | H30: 14 | I30: =H30*E18 -> 1162000
B31: Building Shell | D31: 4 | E31: 16 | F31: S-Curve | H31: 118 | I31: =H31*E18 -> 9794000
B32: Tenant Improvements | D32: 12 | E32: 20 | F32: S-Curve | H32: 42 | I32: =H32*E18 -> 3486000
B33: Soft Costs | D33: 1 | E33: 20 | F33: Straight-Line | H33: =I33/$E$18 -> 15.66 | I33: =0.09*SUM(I30:I32) -> 1299780
B34: Developer Fee | D34: 1 | E34: 20 | F34: Straight-Line | H34: =I34/$E$18 -> 12.35652 | I34: =0.04*SUM(I27:I33) -> 1025591.2
B35: Contingency | D35: 4 | E35: 20 | F35: S-Curve | H35: =I35/$E$18 -> 8.7 | I35: =0.05*SUM(I30:I32) -> 722100
B36: Total Project Cost | I36: =SUM(I27:I35) -> 27387471
B40: Construction Loan to Cost | E40: 0.6
B41: Construction Loan Rate | E41: 0.0775
B42: Permanent Loan LTV | E42: 0.6
B43: Permanent Loan Rate | E43: 0.0625
B44: Permanent Loan Month | E44: 30
B91: RETAIL BASE RENTAL INCOME
B92: SUITE | C92: TENANT | D92: LEASE START | E92: SF | F92: RENT START | G92: RENT GROWTH % | H92: RENT/SF/YR | I92: ANNUAL RENT | K92: STEP
B93: Anchor-1 | C93: Greenfield Grocers | D93: 18 | E93: 52000 | F93: =D93+3 -> 21 | G93: 0.1 | H93: 21 | I93: =H93*E93 -> 1092000 | K93: Every 5 Years
B94: 101 | C94: Spec | D94: 20 | E94: 4200 | F94: =D94+3 -> 23 | G94: 0.03 | H94: 35 | I94: =H94*E94 -> 147000 | K94: Annual
B95: 102 | C95: Spec | D95: 22 | E95: 3600 | F95: =D95+3 -> 25 | G95: 0.03 | H95: 35 | I95: =H95*E95 -> 126000 | K95: Annual
B96: 103 | C96: Spec | D96: 24 | E96: 3600 | F96: =D96+3 -> 27 | G96: 0.03 | H96: 34 | I96: =H96*E96 -> 122400 | K96: Annual
B97: 104 | C97: Spec | D97: 26 | E97: 2800 | F97: =D97+3 -> 29 | G97: 0.03 | H97: 37 | I97: =H97*E97 -> 103600 | K97: Annual
B98: 201 | C98: Spec | D98: 22 | E98: 6000 | F98: =D98+3 -> 25 | G98: 0.03 | H98: 32 | I98: =H98*E98 -> 192000 | K98: Annual
B99: 202 | C99: Spec | D99: 28 | E99: 5200 | F99: =D99+3 -> 31 | G99: 0.03 | H99: 32 | I99: =H99*E99 -> 166400 | K99: Annual
B100: Outparcel-1 | C100: Burger Drive-Thru | D100: 16 | E100: 3200 | F100: =D100+3 -> 19 | G100: 0.1 | H100: 58 | I100: =H100*E100 -> 185600 | K100: Every 5 Years
B101: Outparcel-2 | C101: Corner Coffee | D101: 18 | E101: 2400 | F101: =D101+3 -> 21 | G101: 0.1 | H101: 64 | I101: =H101*E101 -> 153600 | K101: Every 5 Years
B105: TOTAL RENTAL INCOME | E105: =SUM(E93:E101) -> 83000 | H105: =I105/E105 -> 27.573494 | I105: =SUM(I93:I101) -> 2288600
B120: Operating Expenses / SF / Yr | E120: 7.4
B121: Expense Growth | E121: 0.03
B122: Recovery % | E122: 0.9
B123: General Vacancy | E123: 0.05
B124: Exit Cap Rate | E124: 0.07
B125: Selling Costs | E125: 0.02
B126: Market Cap Rate | E126: 0.0675
B130: LP Share of Equity | E130: 0.9
B131: Preferred Return (simple, a year) | E131: 0.08
B132: GP Promote above the Pref | E132: 0.2
B140: Rental Income | L140: =(L$3<=$I$15)*(((L$3>=$F$93)*$I$93/12*(1+$G$93)^IF($K$93="Annual",INT(MAX(0,L$3-$F$93)/12),5*INT(MAX(0,L$3-$F$93)/60)))+((L$3>=$F$94)*$I$94/12*(1+$G$94)^IF($K$94="Annual",INT(MAX(0,L$3-$F$94)/12),5*INT(MAX(0,L$3-$F$94)/60)))+((L$3>=$F$95)*$I$95/12*(1+$G$95)^IF($K$95="Annual",INT(MAX(0,L$3-$F$95)/12),5*INT(MAX(0,L$3-$F$95)/60)))+((L$3>=$F$96)*$I$96/12*(1+$G$96)^IF($K$96="Annual",INT(MAX(0,L$3-$F$96)/12),5*INT(MAX(0,L$3-$F$96)/60)))+((L$3>=$F$97)*$I$97/12*(1+$G$97)^IF($K$97="Annual",INT(MAX(0,L$3-$F$97)/12),5*INT(MAX(0,L$3-$F$97)/60)))+((L$3>=$F$98)*$I$98/12*(1+$G$98)^IF($K$98="Annual",INT(MAX(0,L$3-$F$98)/12),5*INT(MAX(0,L$3-$F$98)/60)))+((L$3>=$F$99)*$I$99/12*(1+$G$99)^IF($K$99="Annual",INT(MAX(0,L$3-$F$99)/12),5*INT(MAX(0,L$3-$F$99)/60)))+((L$3>=$F$100)*$I$100/12*(1+$G$100)^IF($K$100="Annual",INT(MAX(0,L$3-$F$100)/12),5*INT(MAX(0,L$3-$F$100)/60)))+((L$3>=$F$101)*$I$101/12*(1+$G$101)^IF($K$101="Annual",INT(MAX(0,L$3-$F$101)/12),5*INT(MAX(0,L$3-$F$101)/60)))) -> 0 | M140: =(M$3<=$I$15)*(((M$3>=$F$93)*$I$93/12*(1+$G$93)^IF($K$93="Annual",INT(MAX(0,M$3-$F$93)/12),5*INT(MAX(0,M$3-$F$93)/60)))+((M$3>=$F$94)*$I$94/12*(1+$G$94)^IF($K$94="Annual",INT(MAX(0,M$3-$F$94)/12),5*INT(MAX(0,M$3-$F$94)/60)))+((M$3>=$F$95)*$I$95/12*(1+$G$95)^IF($K$95="Annual",INT(MAX(0,M$3-$F$95)/12),5*INT(MAX(0,M$3-$F$95)/60)))+((M$3>=$F$96)*$I$96/12*(1+$G$96)^IF($K$96="Annual",INT(MAX(0,M$3-$F$96)/12),5*INT(MAX(0,M$3-$F$96)/60)))+((M$3>=$F$97)*$I$97/12*(1+$G$97)^IF($K$97="Annual",INT(MAX(0,M$3-$F$97)/12),5*INT(MAX(0,M$3-$F$97)/60)))+((M$3>=$F$98)*$I$98/12*(1+$G$98)^IF($K$98="Annual",INT(MAX(0,M$3-$F$98)/12),5*INT(MAX(0,M$3-$F$98)/60)))+((M$3>=$F$99)*$I$99/12*(1+$G$99)^IF($K$99="Annual",INT(MAX(0,M$3-$F$99)/12),5*INT(MAX(0,M$3-$F$99)/60)))+((M$3>=$F$100)*$I$100/12*(1+$G$100)^IF($K$100="Annual",INT(MAX(0,M$3-$F$100)/12),5*INT(MAX(0,M$3-$F$100)/60)))+((M$3>=$F$101)*$I$101/12*(1+$G$101)^IF($K$101="Annual",INT(MAX(0,M$3-$F$101)/12),5*INT(MAX(0,M$3-$F$101)/60)))) -> 0 | N140: =(N$3<=$I$15)*(((N$3>=$F$93)*$I$93/12*(1+$G$93)^IF($K$93="Annual",INT(MAX(0,N$3-$F$93)/12),5*INT(MAX(0,N$3-$F$93)/60)))+((N$3>=$F$94)*$I$94/12*(1+$G$94)^IF($K$94="Annual",INT(MAX(0,N$3-$F$94)/12),5*INT(MAX(0,N$3-$F$94)/60)))+((N$3>=$F$95)*$I$95/12*(1+$G$95)^IF($K$95="Annual",INT(MAX(0,N$3-$F$95)/12),5*INT(MAX(0,N$3-$F$95)/60)))+((N$3>=$F$96)*$I$96/12*(1+$G$96)^IF($K$96="Annual",INT(MAX(0,N$3-$F$96)/12),5*INT(MAX(0,N$3-$F$96)/60)))+((N$3>=$F$97)*$I$97/12*(1+$G$97)^IF($K$97="Annual",INT(MAX(0,N$3-$F$97)/12),5*INT(MAX(0,N$3-$F$97)/60)))+((N$3>=$F$98)*$I$98/12*(1+$G$98)^IF($K$98="Annual",INT(MAX(0,N$3-$F$98)/12),5*INT(MAX(0,N$3-$F$98)/60)))+((N$3>=$F$99)*$I$99/12*(1+$G$99)^IF($K$99="Annual",INT(MAX(0,N$3-$F$99)/12),5*INT(MAX(0,N$3-$F$99)/60)))+((N$3>=$F$100)*$I$100/12*(1+$G$100)^IF($K$100="Annual",INT(MAX(0,N$3-$F$100)/12),5*INT(MAX(0,N$3-$F$100)/60)))+((N$3>=$F$101)*$I$101/12*(1+$G$101)^IF($K$101="Annual",INT(MAX(0,N$3-$F$101)/12),5*INT(MAX(0,N$3-$F$101)/60)))) -> 0 | O140: =(O$3<=$I$15)*(((O$3>=$F$93)*$I$93/12*(1+$G$93)^IF($K$93="Annual",INT(MAX(0,O$3-$F$93)/12),5*INT(MAX(0,O$3-$F$93)/60)))+((O$3>=$F$94)*$I$94/12*(1+$G$94)^IF($K$94="Annual",INT(MAX(0,O$3-$F$94)/12),5*INT(MAX(0,O$3-$F$94)/60)))+((O$3>=$F$95)*$I$95/12*(1+$G$95)^IF($K$95="Annual",INT(MAX(0,O$3-$F$95)/12),5*INT(MAX(0,O$3-$F$95)/60)))+((O$3>=$F$96)*$I$96/12*(1+$G$96)^IF($K$96="Annual",INT(MAX(0,O$3-$F$96)/12),5*INT(MAX(0,O$3-$F$96)/60)))+((O$3>=$F$97)*$I$97/12*(1+$G$97)^IF($K$97="Annual",INT(MAX(0,O$3-$F$97)/12),5*INT(MAX(0,O$3-$F$97)/60)))+((O$3>=$F$98)*$I$98/12*(1+$G$98)^IF($K$98="Annual",INT(MAX(0,O$3-$F$98)/12),5*INT(MAX(0,O$3-$F$98)/60)))+((O$3>=$F$99)*$I$99/12*(1+$G$99)^IF($K$99="Annual",INT(MAX(0,O$3-$F$99)/12),5*INT(MAX(0,O$3-$F$99)/60)))+((O$3>=$F$100)*$I$100/12*(1+$G$100)^IF($K$100="Annual",INT(MAX(0,O$3-$F$100)/12),5*INT(MAX(0,O$3-$F$100)/60)))+((O$3>=$F$101)*$I$101/12*(1+$G$101)^IF($K$101="Annual",INT(MAX(0,O$3-$F$101)/12),5*INT(MAX(0,O$3-$F$101)/60)))) -> 0 | P140: =(P$3<=$I$15)*(((P$3>=$F$93)*$I$93/12*(1+$G$93)^IF($K$93="Annual",INT(MAX(0,P$3-$F$93)/12),5*INT(MAX(0,P$3-$F$93)/60)))+((P$3>=$F$94)*$I$94/12*(1+$G$94)^IF($K$94="Annual",INT(MAX(0,P$3-$F$94)/12),5*INT(MAX(0,P$3-$F$94)/60)))+((P$3>=$F$95)*$I$95/12*(1+$G$95)^IF($K$95="Annual",INT(MAX(0,P$3-$F$95)/12),5*INT(MAX(0,P$3-$F$95)/60)))+((P$3>=$F$96)*$I$96/12*(1+$G$96)^IF($K$96="Annual",INT(MAX(0,P$3-$F$96)/12),5*INT(MAX(0,P$3-$F$96)/60)))+((P$3>=$F$97)*$I$97/12*(1+$G$97)^IF($K$97="Annual",INT(MAX(0,P$3-$F$97)/12),5*INT(MAX(0,P$3-$F$97)/60)))+((P$3>=$F$98)*$I$98/12*(1+$G$98)^IF($K$98="Annual",INT(MAX(0,P$3-$F$98)/12),5*INT(MAX(0,P$3-$F$98)/60)))+((P$3>=$F$99)*$I$99/12*(1+$G$99)^IF($K$99="Annual",INT(MAX(0,P$3-$F$99)/12),5*INT(MAX(0,P$3-$F$99)/60)))+((P$3>=$F$100)*$I$100/12*(1+$G$100)^IF($K$100="Annual",INT(MAX(0,P$3-$F$100)/12),5*INT(MAX(0,P$3-$F$100)/60)))+((P$3>=$F$101)*$I$101/12*(1+$G$101)^IF($K$101="Annual",INT(MAX(0,P$3-$F$101)/12),5*INT(MAX(0,P$3-$F$101)/60)))) -> 0 | Q140: =(Q$3<=$I$15)*(((Q$3>=$F$93)*$I$93/12*(1+$G$93)^IF($K$93="Annual",INT(MAX(0,Q$3-$F$93)/12),5*INT(MAX(0,Q$3-$F$93)/60)))+((Q$3>=$F$94)*$I$94/12*(1+$G$94)^IF($K$94="Annual",INT(MAX(0,Q$3-$F$94)/12),5*INT(MAX(0,Q$3-$F$94)/60)))+((Q$3>=$F$95)*$I$95/12*(1+$G$95)^IF($K$95="Annual",INT(MAX(0,Q$3-$F$95)/12),5*INT(MAX(0,Q$3-$F$95)/60)))+((Q$3>=$F$96)*$I$96/12*(1+$G$96)^IF($K$96="Annual",INT(MAX(0,Q$3-$F$96)/12),5*INT(MAX(0,Q$3-$F$96)/60)))+((Q$3>=$F$97)*$I$97/12*(1+$G$97)^IF($K$97="Annual",INT(MAX(0,Q$3-$F$97)/12),5*INT(MAX(0,Q$3-$F$97)/60)))+((Q$3>=$F$98)*$I$98/12*(1+$G$98)^IF($K$98="Annual",INT(MAX(0,Q$3-$F$98)/12),5*INT(MAX(0,Q$3-$F$98)/60)))+((Q$3>=$F$99)*$I$99/12*(1+$G$99)^IF($K$99="Annual",INT(MAX(0,Q$3-$F$99)/12),5*INT(MAX(0,Q$3-$F$99)/60)))+((Q$3>=$F$100)*$I$100/12*(1+$G$100)^IF($K$100="Annual",INT(MAX(0,Q$3-$F$100)/12),5*INT(MAX(0,Q$3-$F$100)/60)))+((Q$3>=$F$101)*$I$101/12*(1+$G$101)^IF($K$101="Annual",INT(MAX(0,Q$3-$F$101)/12),5*INT(MAX(0,Q$3-$F$101)/60)))) -> 0 | R140: =(R$3<=$I$15)*(((R$3>=$F$93)*$I$93/12*(1+$G$93)^IF($K$93="Annual",INT(MAX(0,R$3-$F$93)/12),5*INT(MAX(0,R$3-$F$93)/60)))+((R$3>=$F$94)*$I$94/12*(1+$G$94)^IF($K$94="Annual",INT(MAX(0,R$3-$F$94)/12),5*INT(MAX(0,R$3-$F$94)/60)))+((R$3>=$F$95)*$I$95/12*(1+$G$95)^IF($K$95="Annual",INT(MAX(0,R$3-$F$95)/12),5*INT(MAX(0,R$3-$F$95)/60)))+((R$3>=$F$96)*$I$96/12*(1+$G$96)^IF($K$96="Annual",INT(MAX(0,R$3-$F$96)/12),5*INT(MAX(0,R$3-$F$96)/60)))+((R$3>=$F$97)*$I$97/12*(1+$G$97)^IF($K$97="Annual",INT(MAX(0,R$3-$F$97)/12),5*INT(MAX(0,R$3-$F$97)/60)))+((R$3>=$F$98)*$I$98/12*(1+$G$98)^IF($K$98="Annual",INT(MAX(0,R$3-$F$98)/12),5*INT(MAX(0,R$3-$F$98)/60)))+((R$3>=$F$99)*$I$99/12*(1+$G$99)^IF($K$99="Annual",INT(MAX(0,R$3-$F$99)/12),5*INT(MAX(0,R$3-$F$99)/60)))+((R$3>=$F$100)*$I$100/12*(1+$G$100)^IF($K$100="Annual",INT(MAX(0,R$3-$F$100)/12),5*INT(MAX(0,R$3-$F$100)/60)))+((R$3>=$F$101)*$I$101/12*(1+$G$101)^IF($K$101="Annual",INT(MAX(0,R$3-$F$101)/12),5*INT(MAX(0,R$3-$F$101)/60)))) -> 0 | S140: =(S$3<=$I$15)*(((S$3>=$F$93)*$I$93/12*(1+$G$93)^IF($K$93="Annual",INT(MAX(0,S$3-$F$93)/12),5*INT(MAX(0,S$3-$F$93)/60)))+((S$3>=$F$94)*$I$94/12*(1+$G$94)^IF($K$94="Annual",INT(MAX(0,S$3-$F$94)/12),5*INT(MAX(0,S$3-$F$94)/60)))+((S$3>=$F$95)*$I$95/12*(1+$G$95)^IF($K$95="Annual",INT(MAX(0,S$3-$F$95)/12),5*INT(MAX(0,S$3-$F$95)/60)))+((S$3>=$F$96)*$I$96/12*(1+$G$96)^IF($K$96="Annual",INT(MAX(0,S$3-$F$96)/12),5*INT(MAX(0,S$3-$F$96)/60)))+((S$3>=$F$97)*$I$97/12*(1+$G$97)^IF($K$97="Annual",INT(MAX(0,S$3-$F$97)/12),5*INT(MAX(0,S$3-$F$97)/60)))+((S$3>=$F$98)*$I$98/12*(1+$G$98)^IF($K$98="Annual",INT(MAX(0,S$3-$F$98)/12),5*INT(MAX(0,S$3-$F$98)/60)))+((S$3>=$F$99)*$I$99/12*(1+$G$99)^IF($K$99="Annual",INT(MAX(0,S$3-$F$99)/12),5*INT(MAX(0,S$3-$F$99)/60)))+((S$3>=$F$100)*$I$100/12*(1+$G$100)^IF($K$100="Annual",INT(MAX(0,S$3-$F$100)/12),5*INT(MAX(0,S$3-$F$100)/60)))+((S$3>=$F$101)*$I$101/12*(1+$G$101)^IF($K$101="Annual",INT(MAX(0,S$3-$F$101)/12),5*INT(MAX(0,S$3-$F$101)/60)))) -> 0 | ... DP140: =(DP$3<=$I$15)*(((DP$3>=$F$93)*$I$93/12*(1+$G$93)^IF($K$93="Annual",INT(MAX(0,DP$3-$F$93)/12),5*INT(MAX(0,DP$3-$F$93)/60)))+((DP$3>=$F$94)*$I$94/12*(1+$G$94)^IF($K$94="Annual",INT(MAX(0,DP$3-$F$94)/12),5*INT(MAX(0,DP$3-$F$94)/60)))+((DP$3>=$F$95)*$I$95/12*(1+$G$95)^IF($K$95="Annual",INT(MAX(0,DP$3-$F$95)/12),5*INT(MAX(0,DP$3-$F$95)/60)))+((DP$3>=$F$96)*$I$96/12*(1+$G$96)^IF($K$96="Annual",INT(MAX(0,DP$3-$F$96)/12),5*INT(MAX(0,DP$3-$F$96)/60)))+((DP$3>=$F$97)*$I$97/12*(1+$G$97)^IF($K$97="Annual",INT(MAX(0,DP$3-$F$97)/12),5*INT(MAX(0,DP$3-$F$97)/60)))+((DP$3>=$F$98)*$I$98/12*(1+$G$98)^IF($K$98="Annual",INT(MAX(0,DP$3-$F$98)/12),5*INT(MAX(0,DP$3-$F$98)/60)))+((DP$3>=$F$99)*$I$99/12*(1+$G$99)^IF($K$99="Annual",INT(MAX(0,DP$3-$F$99)/12),5*INT(MAX(0,DP$3-$F$99)/60)))+((DP$3>=$F$100)*$I$100/12*(1+$G$100)^IF($K$100="Annual",INT(MAX(0,DP$3-$F$100)/12),5*INT(MAX(0,DP$3-$F$100)/60)))+((DP$3>=$F$101)*$I$101/12*(1+$G$101)^IF($K$101="Annual",INT(MAX(0,DP$3-$F$101)/12),5*INT(MAX(0,DP$3-$F$101)/60)))) -> 0
B141: Recovery Income | L141: =L144*$E$122*((L$3>=$F$93)*$E$93+(L$3>=$F$94)*$E$94+(L$3>=$F$95)*$E$95+(L$3>=$F$96)*$E$96+(L$3>=$F$97)*$E$97+(L$3>=$F$98)*$E$98+(L$3>=$F$99)*$E$99+(L$3>=$F$100)*$E$100+(L$3>=$F$101)*$E$101)/$E$105 -> 0 | M141: =M144*$E$122*((M$3>=$F$93)*$E$93+(M$3>=$F$94)*$E$94+(M$3>=$F$95)*$E$95+(M$3>=$F$96)*$E$96+(M$3>=$F$97)*$E$97+(M$3>=$F$98)*$E$98+(M$3>=$F$99)*$E$99+(M$3>=$F$100)*$E$100+(M$3>=$F$101)*$E$101)/$E$105 -> 0 | N141: =N144*$E$122*((N$3>=$F$93)*$E$93+(N$3>=$F$94)*$E$94+(N$3>=$F$95)*$E$95+(N$3>=$F$96)*$E$96+(N$3>=$F$97)*$E$97+(N$3>=$F$98)*$E$98+(N$3>=$F$99)*$E$99+(N$3>=$F$100)*$E$100+(N$3>=$F$101)*$E$101)/$E$105 -> 0 | O141: =O144*$E$122*((O$3>=$F$93)*$E$93+(O$3>=$F$94)*$E$94+(O$3>=$F$95)*$E$95+(O$3>=$F$96)*$E$96+(O$3>=$F$97)*$E$97+(O$3>=$F$98)*$E$98+(O$3>=$F$99)*$E$99+(O$3>=$F$100)*$E$100+(O$3>=$F$101)*$E$101)/$E$105 -> 0 | P141: =P144*$E$122*((P$3>=$F$93)*$E$93+(P$3>=$F$94)*$E$94+(P$3>=$F$95)*$E$95+(P$3>=$F$96)*$E$96+(P$3>=$F$97)*$E$97+(P$3>=$F$98)*$E$98+(P$3>=$F$99)*$E$99+(P$3>=$F$100)*$E$100+(P$3>=$F$101)*$E$101)/$E$105 -> 0 | Q141: =Q144*$E$122*((Q$3>=$F$93)*$E$93+(Q$3>=$F$94)*$E$94+(Q$3>=$F$95)*$E$95+(Q$3>=$F$96)*$E$96+(Q$3>=$F$97)*$E$97+(Q$3>=$F$98)*$E$98+(Q$3>=$F$99)*$E$99+(Q$3>=$F$100)*$E$100+(Q$3>=$F$101)*$E$101)/$E$105 -> 0 | R141: =R144*$E$122*((R$3>=$F$93)*$E$93+(R$3>=$F$94)*$E$94+(R$3>=$F$95)*$E$95+(R$3>=$F$96)*$E$96+(R$3>=$F$97)*$E$97+(R$3>=$F$98)*$E$98+(R$3>=$F$99)*$E$99+(R$3>=$F$100)*$E$100+(R$3>=$F$101)*$E$101)/$E$105 -> 0 | S141: =S144*$E$122*((S$3>=$F$93)*$E$93+(S$3>=$F$94)*$E$94+(S$3>=$F$95)*$E$95+(S$3>=$F$96)*$E$96+(S$3>=$F$97)*$E$97+(S$3>=$F$98)*$E$98+(S$3>=$F$99)*$E$99+(S$3>=$F$100)*$E$100+(S$3>=$F$101)*$E$101)/$E$105 -> 0 | ... DP141: =DP144*$E$122*((DP$3>=$F$93)*$E$93+(DP$3>=$F$94)*$E$94+(DP$3>=$F$95)*$E$95+(DP$3>=$F$96)*$E$96+(DP$3>=$F$97)*$E$97+(DP$3>=$F$98)*$E$98+(DP$3>=$F$99)*$E$99+(DP$3>=$F$100)*$E$100+(DP$3>=$F$101)*$E$101)/$E$105 -> 0
B142: General Vacancy | L142: =-$E$123*(L140+L141) -> 0 | M142: =-$E$123*(M140+M141) -> 0 | N142: =-$E$123*(N140+N141) -> 0 | O142: =-$E$123*(O140+O141) -> 0 | P142: =-$E$123*(P140+P141) -> 0 | Q142: =-$E$123*(Q140+Q141) -> 0 | R142: =-$E$123*(R140+R141) -> 0 | S142: =-$E$123*(S140+S141) -> 0 | ... DP142: =-$E$123*(DP140+DP141) -> 0
B143: Effective Gross Revenue | L143: =SUM(L140:L142) -> 0 | M143: =SUM(M140:M142) -> 0 | N143: =SUM(N140:N142) -> 0 | O143: =SUM(O140:O142) -> 0 | P143: =SUM(P140:P142) -> 0 | Q143: =SUM(Q140:Q142) -> 0 | R143: =SUM(R140:R142) -> 0 | S143: =SUM(S140:S142) -> 0 | ... DP143: =SUM(DP140:DP142) -> 0
B144: Operating Expenses | L144: =(L$3<=$I$15)*(L$3>=MIN($F$93:$F$101))*$E$120*$E$105/12*(1+$E$121)^INT(L$3/12) -> 0 | M144: =(M$3<=$I$15)*(M$3>=MIN($F$93:$F$101))*$E$120*$E$105/12*(1+$E$121)^INT(M$3/12) -> 0 | N144: =(N$3<=$I$15)*(N$3>=MIN($F$93:$F$101))*$E$120*$E$105/12*(1+$E$121)^INT(N$3/12) -> 0 | O144: =(O$3<=$I$15)*(O$3>=MIN($F$93:$F$101))*$E$120*$E$105/12*(1+$E$121)^INT(O$3/12) -> 0 | P144: =(P$3<=$I$15)*(P$3>=MIN($F$93:$F$101))*$E$120*$E$105/12*(1+$E$121)^INT(P$3/12) -> 0 | Q144: =(Q$3<=$I$15)*(Q$3>=MIN($F$93:$F$101))*$E$120*$E$105/12*(1+$E$121)^INT(Q$3/12) -> 0 | R144: =(R$3<=$I$15)*(R$3>=MIN($F$93:$F$101))*$E$120*$E$105/12*(1+$E$121)^INT(R$3/12) -> 0 | S144: =(S$3<=$I$15)*(S$3>=MIN($F$93:$F$101))*$E$120*$E$105/12*(1+$E$121)^INT(S$3/12) -> 0 | ... DP144: =(DP$3<=$I$15)*(DP$3>=MIN($F$93:$F$101))*$E$120*$E$105/12*(1+$E$121)^INT(DP$3/12) -> 0
B145: Net Operating Income | L145: =L143-L144 -> 0 | M145: =M143-M144 -> 0 | N145: =N143-N144 -> 0 | O145: =O143-O144 -> 0 | P145: =P143-P144 -> 0 | Q145: =Q143-Q144 -> 0 | R145: =R143-R144 -> 0 | S145: =S143-S144 -> 0 | ... DP145: =DP143-DP144 -> 0
B150: Development Cost | L150: =IF(AND(L$3>=$D$27,L$3<=$E$27),$I$27*IF($F$27="S-Curve",(COS(PI()*(L$3-$D$27)/($E$27-$D$27+1))-COS(PI()*(L$3-$D$27+1)/($E$27-$D$27+1)))/2,1/($E$27-$D$27+1)),0)+IF(AND(L$3>=$D$28,L$3<=$E$28),$I$28*IF($F$28="S-Curve",(COS(PI()*(L$3-$D$28)/($E$28-$D$28+1))-COS(PI()*(L$3-$D$28+1)/($E$28-$D$28+1)))/2,1/($E$28-$D$28+1)),0)+IF(AND(L$3>=$D$30,L$3<=$E$30),$I$30*IF($F$30="S-Curve",(COS(PI()*(L$3-$D$30)/($E$30-$D$30+1))-COS(PI()*(L$3-$D$30+1)/($E$30-$D$30+1)))/2,1/($E$30-$D$30+1)),0)+IF(AND(L$3>=$D$31,L$3<=$E$31),$I$31*IF($F$31="S-Curve",(COS(PI()*(L$3-$D$31)/($E$31-$D$31+1))-COS(PI()*(L$3-$D$31+1)/($E$31-$D$31+1)))/2,1/($E$31-$D$31+1)),0)+IF(AND(L$3>=$D$32,L$3<=$E$32),$I$32*IF($F$32="S-Curve",(COS(PI()*(L$3-$D$32)/($E$32-$D$32+1))-COS(PI()*(L$3-$D$32+1)/($E$32-$D$32+1)))/2,1/($E$32-$D$32+1)),0)+IF(AND(L$3>=$D$33,L$3<=$E$33),$I$33*IF($F$33="S-Curve",(COS(PI()*(L$3-$D$33)/($E$33-$D$33+1))-COS(PI()*(L$3-$D$33+1)/($E$33-$D$33+1)))/2,1/($E$33-$D$33+1)),0)+IF(AND(L$3>=$D$34,L$3<=$E$34),$I$34*IF($F$34="S-Curve",(COS(PI()*(L$3-$D$34)/($E$34-$D$34+1))-COS(PI()*(L$3-$D$34+1)/($E$34-$D$34+1)))/2,1/($E$34-$D$34+1)),0)+IF(AND(L$3>=$D$35,L$3<=$E$35),$I$35*IF($F$35="S-Curve",(COS(PI()*(L$3-$D$35)/($E$35-$D$35+1))-COS(PI()*(L$3-$D$35+1)/($E$35-$D$35+1)))/2,1/($E$35-$D$35+1)),0) -> 9898000 | M150: =IF(AND(M$3>=$D$27,M$3<=$E$27),$I$27*IF($F$27="S-Curve",(COS(PI()*(M$3-$D$27)/($E$27-$D$27+1))-COS(PI()*(M$3-$D$27+1)/($E$27-$D$27+1)))/2,1/($E$27-$D$27+1)),0)+IF(AND(M$3>=$D$28,M$3<=$E$28),$I$28*IF($F$28="S-Curve",(COS(PI()*(M$3-$D$28)/($E$28-$D$28+1))-COS(PI()*(M$3-$D$28+1)/($E$28-$D$28+1)))/2,1/($E$28-$D$28+1)),0)+IF(AND(M$3>=$D$30,M$3<=$E$30),$I$30*IF($F$30="S-Curve",(COS(PI()*(M$3-$D$30)/($E$30-$D$30+1))-COS(PI()*(M$3-$D$30+1)/($E$30-$D$30+1)))/2,1/($E$30-$D$30+1)),0)+IF(AND(M$3>=$D$31,M$3<=$E$31),$I$31*IF($F$31="S-Curve",(COS(PI()*(M$3-$D$31)/($E$31-$D$31+1))-COS(PI()*(M$3-$D$31+1)/($E$31-$D$31+1)))/2,1/($E$31-$D$31+1)),0)+IF(AND(M$3>=$D$32,M$3<=$E$32),$I$32*IF($F$32="S-Curve",(COS(PI()*(M$3-$D$32)/($E$32-$D$32+1))-COS(PI()*(M$3-$D$32+1)/($E$32-$D$32+1)))/2,1/($E$32-$D$32+1)),0)+IF(AND(M$3>=$D$33,M$3<=$E$33),$I$33*IF($F$33="S-Curve",(COS(PI()*(M$3-$D$33)/($E$33-$D$33+1))-COS(PI()*(M$3-$D$33+1)/($E$33-$D$33+1)))/2,1/($E$33-$D$33+1)),0)+IF(AND(M$3>=$D$34,M$3<=$E$34),$I$34*IF($F$34="S-Curve",(COS(PI()*(M$3-$D$34)/($E$34-$D$34+1))-COS(PI()*(M$3-$D$34+1)/($E$34-$D$34+1)))/2,1/($E$34-$D$34+1)),0)+IF(AND(M$3>=$D$35,M$3<=$E$35),$I$35*IF($F$35="S-Curve",(COS(PI()*(M$3-$D$35)/($E$35-$D$35+1))-COS(PI()*(M$3-$D$35+1)/($E$35-$D$35+1)))/2,1/($E$35-$D$35+1)),0) -> 116268.56 | N150: =IF(AND(N$3>=$D$27,N$3<=$E$27),$I$27*IF($F$27="S-Curve",(COS(PI()*(N$3-$D$27)/($E$27-$D$27+1))-COS(PI()*(N$3-$D$27+1)/($E$27-$D$27+1)))/2,1/($E$27-$D$27+1)),0)+IF(AND(N$3>=$D$28,N$3<=$E$28),$I$28*IF($F$28="S-Curve",(COS(PI()*(N$3-$D$28)/($E$28-$D$28+1))-COS(PI()*(N$3-$D$28+1)/($E$28-$D$28+1)))/2,1/($E$28-$D$28+1)),0)+IF(AND(N$3>=$D$30,N$3<=$E$30),$I$30*IF($F$30="S-Curve",(COS(PI()*(N$3-$D$30)/($E$30-$D$30+1))-COS(PI()*(N$3-$D$30+1)/($E$30-$D$30+1)))/2,1/($E$30-$D$30+1)),0)+IF(AND(N$3>=$D$31,N$3<=$E$31),$I$31*IF($F$31="S-Curve",(COS(PI()*(N$3-$D$31)/($E$31-$D$31+1))-COS(PI()*(N$3-$D$31+1)/($E$31-$D$31+1)))/2,1/($E$31-$D$31+1)),0)+IF(AND(N$3>=$D$32,N$3<=$E$32),$I$32*IF($F$32="S-Curve",(COS(PI()*(N$3-$D$32)/($E$32-$D$32+1))-COS(PI()*(N$3-$D$32+1)/($E$32-$D$32+1)))/2,1/($E$32-$D$32+1)),0)+IF(AND(N$3>=$D$33,N$3<=$E$33),$I$33*IF($F$33="S-Curve",(COS(PI()*(N$3-$D$33)/($E$33-$D$33+1))-COS(PI()*(N$3-$D$33+1)/($E$33-$D$33+1)))/2,1/($E$33-$D$33+1)),0)+IF(AND(N$3>=$D$34,N$3<=$E$34),$I$34*IF($F$34="S-Curve",(COS(PI()*(N$3-$D$34)/($E$34-$D$34+1))-COS(PI()*(N$3-$D$34+1)/($E$34-$D$34+1)))/2,1/($E$34-$D$34+1)),0)+IF(AND(N$3>=$D$35,N$3<=$E$35),$I$35*IF($F$35="S-Curve",(COS(PI()*(N$3-$D$35)/($E$35-$D$35+1))-COS(PI()*(N$3-$D$35+1)/($E$35-$D$35+1)))/2,1/($E$35-$D$35+1)),0) -> 282268.56 | O150: =IF(AND(O$3>=$D$27,O$3<=$E$27),$I$27*IF($F$27="S-Curve",(COS(PI()*(O$3-$D$27)/($E$27-$D$27+1))-COS(PI()*(O$3-$D$27+1)/($E$27-$D$27+1)))/2,1/($E$27-$D$27+1)),0)+IF(AND(O$3>=$D$28,O$3<=$E$28),$I$28*IF($F$28="S-Curve",(COS(PI()*(O$3-$D$28)/($E$28-$D$28+1))-COS(PI()*(O$3-$D$28+1)/($E$28-$D$28+1)))/2,1/($E$28-$D$28+1)),0)+IF(AND(O$3>=$D$30,O$3<=$E$30),$I$30*IF($F$30="S-Curve",(COS(PI()*(O$3-$D$30)/($E$30-$D$30+1))-COS(PI()*(O$3-$D$30+1)/($E$30-$D$30+1)))/2,1/($E$30-$D$30+1)),0)+IF(AND(O$3>=$D$31,O$3<=$E$31),$I$31*IF($F$31="S-Curve",(COS(PI()*(O$3-$D$31)/($E$31-$D$31+1))-COS(PI()*(O$3-$D$31+1)/($E$31-$D$31+1)))/2,1/($E$31-$D$31+1)),0)+IF(AND(O$3>=$D$32,O$3<=$E$32),$I$32*IF($F$32="S-Curve",(COS(PI()*(O$3-$D$32)/($E$32-$D$32+1))-COS(PI()*(O$3-$D$32+1)/($E$32-$D$32+1)))/2,1/($E$32-$D$32+1)),0)+IF(AND(O$3>=$D$33,O$3<=$E$33),$I$33*IF($F$33="S-Curve",(COS(PI()*(O$3-$D$33)/($E$33-$D$33+1))-COS(PI()*(O$3-$D$33+1)/($E$33-$D$33+1)))/2,1/($E$33-$D$33+1)),0)+IF(AND(O$3>=$D$34,O$3<=$E$34),$I$34*IF($F$34="S-Curve",(COS(PI()*(O$3-$D$34)/($E$34-$D$34+1))-COS(PI()*(O$3-$D$34+1)/($E$34-$D$34+1)))/2,1/($E$34-$D$34+1)),0)+IF(AND(O$3>=$D$35,O$3<=$E$35),$I$35*IF($F$35="S-Curve",(COS(PI()*(O$3-$D$35)/($E$35-$D$35+1))-COS(PI()*(O$3-$D$35+1)/($E$35-$D$35+1)))/2,1/($E$35-$D$35+1)),0) -> 282268.56 | P150: =IF(AND(P$3>=$D$27,P$3<=$E$27),$I$27*IF($F$27="S-Curve",(COS(PI()*(P$3-$D$27)/($E$27-$D$27+1))-COS(PI()*(P$3-$D$27+1)/($E$27-$D$27+1)))/2,1/($E$27-$D$27+1)),0)+IF(AND(P$3>=$D$28,P$3<=$E$28),$I$28*IF($F$28="S-Curve",(COS(PI()*(P$3-$D$28)/($E$28-$D$28+1))-COS(PI()*(P$3-$D$28+1)/($E$28-$D$28+1)))/2,1/($E$28-$D$28+1)),0)+IF(AND(P$3>=$D$30,P$3<=$E$30),$I$30*IF($F$30="S-Curve",(COS(PI()*(P$3-$D$30)/($E$30-$D$30+1))-COS(PI()*(P$3-$D$30+1)/($E$30-$D$30+1)))/2,1/($E$30-$D$30+1)),0)+IF(AND(P$3>=$D$31,P$3<=$E$31),$I$31*IF($F$31="S-Curve",(COS(PI()*(P$3-$D$31)/($E$31-$D$31+1))-COS(PI()*(P$3-$D$31+1)/($E$31-$D$31+1)))/2,1/($E$31-$D$31+1)),0)+IF(AND(P$3>=$D$32,P$3<=$E$32),$I$32*IF($F$32="S-Curve",(COS(PI()*(P$3-$D$32)/($E$32-$D$32+1))-COS(PI()*(P$3-$D$32+1)/($E$32-$D$32+1)))/2,1/($E$32-$D$32+1)),0)+IF(AND(P$3>=$D$33,P$3<=$E$33),$I$33*IF($F$33="S-Curve",(COS(PI()*(P$3-$D$33)/($E$33-$D$33+1))-COS(PI()*(P$3-$D$33+1)/($E$33-$D$33+1)))/2,1/($E$33-$D$33+1)),0)+IF(AND(P$3>=$D$34,P$3<=$E$34),$I$34*IF($F$34="S-Curve",(COS(PI()*(P$3-$D$34)/($E$34-$D$34+1))-COS(PI()*(P$3-$D$34+1)/($E$34-$D$34+1)))/2,1/($E$34-$D$34+1)),0)+IF(AND(P$3>=$D$35,P$3<=$E$35),$I$35*IF($F$35="S-Curve",(COS(PI()*(P$3-$D$35)/($E$35-$D$35+1))-COS(PI()*(P$3-$D$35+1)/($E$35-$D$35+1)))/2,1/($E$35-$D$35+1)),0) -> 430714.04 | Q150: =IF(AND(Q$3>=$D$27,Q$3<=$E$27),$I$27*IF($F$27="S-Curve",(COS(PI()*(Q$3-$D$27)/($E$27-$D$27+1))-COS(PI()*(Q$3-$D$27+1)/($E$27-$D$27+1)))/2,1/($E$27-$D$27+1)),0)+IF(AND(Q$3>=$D$28,Q$3<=$E$28),$I$28*IF($F$28="S-Curve",(COS(PI()*(Q$3-$D$28)/($E$28-$D$28+1))-COS(PI()*(Q$3-$D$28+1)/($E$28-$D$28+1)))/2,1/($E$28-$D$28+1)),0)+IF(AND(Q$3>=$D$30,Q$3<=$E$30),$I$30*IF($F$30="S-Curve",(COS(PI()*(Q$3-$D$30)/($E$30-$D$30+1))-COS(PI()*(Q$3-$D$30+1)/($E$30-$D$30+1)))/2,1/($E$30-$D$30+1)),0)+IF(AND(Q$3>=$D$31,Q$3<=$E$31),$I$31*IF($F$31="S-Curve",(COS(PI()*(Q$3-$D$31)/($E$31-$D$31+1))-COS(PI()*(Q$3-$D$31+1)/($E$31-$D$31+1)))/2,1/($E$31-$D$31+1)),0)+IF(AND(Q$3>=$D$32,Q$3<=$E$32),$I$32*IF($F$32="S-Curve",(COS(PI()*(Q$3-$D$32)/($E$32-$D$32+1))-COS(PI()*(Q$3-$D$32+1)/($E$32-$D$32+1)))/2,1/($E$32-$D$32+1)),0)+IF(AND(Q$3>=$D$33,Q$3<=$E$33),$I$33*IF($F$33="S-Curve",(COS(PI()*(Q$3-$D$33)/($E$33-$D$33+1))-COS(PI()*(Q$3-$D$33+1)/($E$33-$D$33+1)))/2,1/($E$33-$D$33+1)),0)+IF(AND(Q$3>=$D$34,Q$3<=$E$34),$I$34*IF($F$34="S-Curve",(COS(PI()*(Q$3-$D$34)/($E$34-$D$34+1))-COS(PI()*(Q$3-$D$34+1)/($E$34-$D$34+1)))/2,1/($E$34-$D$34+1)),0)+IF(AND(Q$3>=$D$35,Q$3<=$E$35),$I$35*IF($F$35="S-Curve",(COS(PI()*(Q$3-$D$35)/($E$35-$D$35+1))-COS(PI()*(Q$3-$D$35+1)/($E$35-$D$35+1)))/2,1/($E$35-$D$35+1)),0) -> 719125.82 | R150: =IF(AND(R$3>=$D$27,R$3<=$E$27),$I$27*IF($F$27="S-Curve",(COS(PI()*(R$3-$D$27)/($E$27-$D$27+1))-COS(PI()*(R$3-$D$27+1)/($E$27-$D$27+1)))/2,1/($E$27-$D$27+1)),0)+IF(AND(R$3>=$D$28,R$3<=$E$28),$I$28*IF($F$28="S-Curve",(COS(PI()*(R$3-$D$28)/($E$28-$D$28+1))-COS(PI()*(R$3-$D$28+1)/($E$28-$D$28+1)))/2,1/($E$28-$D$28+1)),0)+IF(AND(R$3>=$D$30,R$3<=$E$30),$I$30*IF($F$30="S-Curve",(COS(PI()*(R$3-$D$30)/($E$30-$D$30+1))-COS(PI()*(R$3-$D$30+1)/($E$30-$D$30+1)))/2,1/($E$30-$D$30+1)),0)+IF(AND(R$3>=$D$31,R$3<=$E$31),$I$31*IF($F$31="S-Curve",(COS(PI()*(R$3-$D$31)/($E$31-$D$31+1))-COS(PI()*(R$3-$D$31+1)/($E$31-$D$31+1)))/2,1/($E$31-$D$31+1)),0)+IF(AND(R$3>=$D$32,R$3<=$E$32),$I$32*IF($F$32="S-Curve",(COS(PI()*(R$3-$D$32)/($E$32-$D$32+1))-COS(PI()*(R$3-$D$32+1)/($E$32-$D$32+1)))/2,1/($E$32-$D$32+1)),0)+IF(AND(R$3>=$D$33,R$3<=$E$33),$I$33*IF($F$33="S-Curve",(COS(PI()*(R$3-$D$33)/($E$33-$D$33+1))-COS(PI()*(R$3-$D$33+1)/($E$33-$D$33+1)))/2,1/($E$33-$D$33+1)),0)+IF(AND(R$3>=$D$34,R$3<=$E$34),$I$34*IF($F$34="S-Curve",(COS(PI()*(R$3-$D$34)/($E$34-$D$34+1))-COS(PI()*(R$3-$D$34+1)/($E$34-$D$34+1)))/2,1/($E$34-$D$34+1)),0)+IF(AND(R$3>=$D$35,R$3<=$E$35),$I$35*IF($F$35="S-Curve",(COS(PI()*(R$3-$D$35)/($E$35-$D$35+1))-COS(PI()*(R$3-$D$35+1)/($E$35-$D$35+1)))/2,1/($E$35-$D$35+1)),0) -> 982587.79 | S150: =IF(AND(S$3>=$D$27,S$3<=$E$27),$I$27*IF($F$27="S-Curve",(COS(PI()*(S$3-$D$27)/($E$27-$D$27+1))-COS(PI()*(S$3-$D$27+1)/($E$27-$D$27+1)))/2,1/($E$27-$D$27+1)),0)+IF(AND(S$3>=$D$28,S$3<=$E$28),$I$28*IF($F$28="S-Curve",(COS(PI()*(S$3-$D$28)/($E$28-$D$28+1))-COS(PI()*(S$3-$D$28+1)/($E$28-$D$28+1)))/2,1/($E$28-$D$28+1)),0)+IF(AND(S$3>=$D$30,S$3<=$E$30),$I$30*IF($F$30="S-Curve",(COS(PI()*(S$3-$D$30)/($E$30-$D$30+1))-COS(PI()*(S$3-$D$30+1)/($E$30-$D$30+1)))/2,1/($E$30-$D$30+1)),0)+IF(AND(S$3>=$D$31,S$3<=$E$31),$I$31*IF($F$31="S-Curve",(COS(PI()*(S$3-$D$31)/($E$31-$D$31+1))-COS(PI()*(S$3-$D$31+1)/($E$31-$D$31+1)))/2,1/($E$31-$D$31+1)),0)+IF(AND(S$3>=$D$32,S$3<=$E$32),$I$32*IF($F$32="S-Curve",(COS(PI()*(S$3-$D$32)/($E$32-$D$32+1))-COS(PI()*(S$3-$D$32+1)/($E$32-$D$32+1)))/2,1/($E$32-$D$32+1)),0)+IF(AND(S$3>=$D$33,S$3<=$E$33),$I$33*IF($F$33="S-Curve",(COS(PI()*(S$3-$D$33)/($E$33-$D$33+1))-COS(PI()*(S$3-$D$33+1)/($E$33-$D$33+1)))/2,1/($E$33-$D$33+1)),0)+IF(AND(S$3>=$D$34,S$3<=$E$34),$I$34*IF($F$34="S-Curve",(COS(PI()*(S$3-$D$34)/($E$34-$D$34+1))-COS(PI()*(S$3-$D$34+1)/($E$34-$D$34+1)))/2,1/($E$34-$D$34+1)),0)+IF(AND(S$3>=$D$35,S$3<=$E$35),$I$35*IF($F$35="S-Curve",(COS(PI()*(S$3-$D$35)/($E$35-$D$35+1))-COS(PI()*(S$3-$D$35+1)/($E$35-$D$35+1)))/2,1/($E$35-$D$35+1)),0) -> 1206064.4 | ... DP150: =IF(AND(DP$3>=$D$27,DP$3<=$E$27),$I$27*IF($F$27="S-Curve",(COS(PI()*(DP$3-$D$27)/($E$27-$D$27+1))-COS(PI()*(DP$3-$D$27+1)/($E$27-$D$27+1)))/2,1/($E$27-$D$27+1)),0)+IF(AND(DP$3>=$D$28,DP$3<=$E$28),$I$28*IF($F$28="S-Curve",(COS(PI()*(DP$3-$D$28)/($E$28-$D$28+1))-COS(PI()*(DP$3-$D$28+1)/($E$28-$D$28+1)))/2,1/($E$28-$D$28+1)),0)+IF(AND(DP$3>=$D$30,DP$3<=$E$30),$I$30*IF($F$30="S-Curve",(COS(PI()*(DP$3-$D$30)/($E$30-$D$30+1))-COS(PI()*(DP$3-$D$30+1)/($E$30-$D$30+1)))/2,1/($E$30-$D$30+1)),0)+IF(AND(DP$3>=$D$31,DP$3<=$E$31),$I$31*IF($F$31="S-Curve",(COS(PI()*(DP$3-$D$31)/($E$31-$D$31+1))-COS(PI()*(DP$3-$D$31+1)/($E$31-$D$31+1)))/2,1/($E$31-$D$31+1)),0)+IF(AND(DP$3>=$D$32,DP$3<=$E$32),$I$32*IF($F$32="S-Curve",(COS(PI()*(DP$3-$D$32)/($E$32-$D$32+1))-COS(PI()*(DP$3-$D$32+1)/($E$32-$D$32+1)))/2,1/($E$32-$D$32+1)),0)+IF(AND(DP$3>=$D$33,DP$3<=$E$33),$I$33*IF($F$33="S-Curve",(COS(PI()*(DP$3-$D$33)/($E$33-$D$33+1))-COS(PI()*(DP$3-$D$33+1)/($E$33-$D$33+1)))/2,1/($E$33-$D$33+1)),0)+IF(AND(DP$3>=$D$34,DP$3<=$E$34),$I$34*IF($F$34="S-Curve",(COS(PI()*(DP$3-$D$34)/($E$34-$D$34+1))-COS(PI()*(DP$3-$D$34+1)/($E$34-$D$34+1)))/2,1/($E$34-$D$34+1)),0)+IF(AND(DP$3>=$D$35,DP$3<=$E$35),$I$35*IF($F$35="S-Curve",(COS(PI()*(DP$3-$D$35)/($E$35-$D$35+1))-COS(PI()*(DP$3-$D$35+1)/($E$35-$D$35+1)))/2,1/($E$35-$D$35+1)),0) -> 0
B151: Construction Loan Draw | L151: =L150*$E$40 -> 5938800 | M151: =M150*$E$40 -> 69761.136 | N151: =N150*$E$40 -> 169361.14 | O151: =O150*$E$40 -> 169361.14 | P151: =P150*$E$40 -> 258428.43 | Q151: =Q150*$E$40 -> 431475.49 | R151: =R150*$E$40 -> 589552.67 | S151: =S150*$E$40 -> 723638.61 | ... DP151: =DP150*$E$40 -> 0
B152: Construction Interest | L152: =0 -> 0 | M152: =IF(M$3<=$E$44,L153*$E$41/12,0) -> 38354.75 | N152: =IF(N$3<=$E$44,M153*$E$41/12,0) -> 38805.291 | O152: =IF(O$3<=$E$44,N153*$E$41/12,0) -> 39899.081 | P152: =IF(P$3<=$E$44,O153*$E$41/12,0) -> 40992.872 | Q152: =IF(Q$3<=$E$44,P153*$E$41/12,0) -> 42661.889 | R152: =IF(R$3<=$E$44,Q153*$E$41/12,0) -> 45448.501 | S152: =IF(S$3<=$E$44,R153*$E$41/12,0) -> 49256.029 | T152: =IF(T$3<=$E$44,S153*$E$41/12,0) -> 53929.529 | ... DP152: =IF(DP$3<=$E$44,DO153*$E$41/12,0) -> 0
B153: Construction Loan Balance | L153: =0+L151-L154 -> 5938800 | M153: =L153+M151-M154 -> 6008561.1 | N153: =M153+N151-N154 -> 6177922.3 | O153: =N153+O151-O154 -> 6347283.4 | P153: =O153+P151-P154 -> 6605711.8 | Q153: =P153+Q151-Q154 -> 7037187.3 | R153: =Q153+R151-R154 -> 7626740 | S153: =R153+S151-S154 -> 8350378.6 | T153: =S153+T151-T154 -> 9176470.3 | ... DP153: =DO153+DP151-DP154 -> 0
B154: Construction Loan Payoff | L154: =IF(L$3=$E$44,0+L151,0) -> 0 | M154: =IF(M$3=$E$44,L153+M151,0) -> 0 | N154: =IF(N$3=$E$44,M153+N151,0) -> 0 | O154: =IF(O$3=$E$44,N153+O151,0) -> 0 | P154: =IF(P$3=$E$44,O153+P151,0) -> 0 | Q154: =IF(Q$3=$E$44,P153+Q151,0) -> 0 | R154: =IF(R$3=$E$44,Q153+R151,0) -> 0 | S154: =IF(S$3=$E$44,R153+S151,0) -> 0 | T154: =IF(T$3=$E$44,S153+T151,0) -> 0 | ... DP154: =IF(DP$3=$E$44,DO153+DP151,0) -> 0
B155: Permanent Loan Funding | L155: =IF(L$3=$E$44,$E$42*12*SUMPRODUCT(($L$3:$DP$3>$E$44)*($L$3:$DP$3<=$E$44+12)*$L$145:$DP$145)/12/$E$126,0) -> 0 | M155: =IF(M$3=$E$44,$E$42*12*SUMPRODUCT(($L$3:$DP$3>$E$44)*($L$3:$DP$3<=$E$44+12)*$L$145:$DP$145)/12/$E$126,0) -> 0 | N155: =IF(N$3=$E$44,$E$42*12*SUMPRODUCT(($L$3:$DP$3>$E$44)*($L$3:$DP$3<=$E$44+12)*$L$145:$DP$145)/12/$E$126,0) -> 0 | O155: =IF(O$3=$E$44,$E$42*12*SUMPRODUCT(($L$3:$DP$3>$E$44)*($L$3:$DP$3<=$E$44+12)*$L$145:$DP$145)/12/$E$126,0) -> 0 | P155: =IF(P$3=$E$44,$E$42*12*SUMPRODUCT(($L$3:$DP$3>$E$44)*($L$3:$DP$3<=$E$44+12)*$L$145:$DP$145)/12/$E$126,0) -> 0 | Q155: =IF(Q$3=$E$44,$E$42*12*SUMPRODUCT(($L$3:$DP$3>$E$44)*($L$3:$DP$3<=$E$44+12)*$L$145:$DP$145)/12/$E$126,0) -> 0 | R155: =IF(R$3=$E$44,$E$42*12*SUMPRODUCT(($L$3:$DP$3>$E$44)*($L$3:$DP$3<=$E$44+12)*$L$145:$DP$145)/12/$E$126,0) -> 0 | S155: =IF(S$3=$E$44,$E$42*12*SUMPRODUCT(($L$3:$DP$3>$E$44)*($L$3:$DP$3<=$E$44+12)*$L$145:$DP$145)/12/$E$126,0) -> 0 | ... DP155: =IF(DP$3=$E$44,$E$42*12*SUMPRODUCT(($L$3:$DP$3>$E$44)*($L$3:$DP$3<=$E$44+12)*$L$145:$DP$145)/12/$E$126,0) -> 0
B156: Permanent Loan Debt Service | L156: =IF(AND(L$3>$E$44,(L$3<=$I$15)),SUM($L$155:$DP$155)*$E$43/12,0) -> 0 | M156: =IF(AND(M$3>$E$44,(M$3<=$I$15)),SUM($L$155:$DP$155)*$E$43/12,0) -> 0 | N156: =IF(AND(N$3>$E$44,(N$3<=$I$15)),SUM($L$155:$DP$155)*$E$43/12,0) -> 0 | O156: =IF(AND(O$3>$E$44,(O$3<=$I$15)),SUM($L$155:$DP$155)*$E$43/12,0) -> 0 | P156: =IF(AND(P$3>$E$44,(P$3<=$I$15)),SUM($L$155:$DP$155)*$E$43/12,0) -> 0 | Q156: =IF(AND(Q$3>$E$44,(Q$3<=$I$15)),SUM($L$155:$DP$155)*$E$43/12,0) -> 0 | R156: =IF(AND(R$3>$E$44,(R$3<=$I$15)),SUM($L$155:$DP$155)*$E$43/12,0) -> 0 | S156: =IF(AND(S$3>$E$44,(S$3<=$I$15)),SUM($L$155:$DP$155)*$E$43/12,0) -> 0 | ... DP156: =IF(AND(DP$3>$E$44,(DP$3<=$I$15)),SUM($L$155:$DP$155)*$E$43/12,0) -> 0
B157: Permanent Loan Payoff | L157: =IF(L$3=$I$15,SUM($L$155:$DP$155),0) -> 0 | M157: =IF(M$3=$I$15,SUM($L$155:$DP$155),0) -> 0 | N157: =IF(N$3=$I$15,SUM($L$155:$DP$155),0) -> 0 | O157: =IF(O$3=$I$15,SUM($L$155:$DP$155),0) -> 0 | P157: =IF(P$3=$I$15,SUM($L$155:$DP$155),0) -> 0 | Q157: =IF(Q$3=$I$15,SUM($L$155:$DP$155),0) -> 0 | R157: =IF(R$3=$I$15,SUM($L$155:$DP$155),0) -> 0 | S157: =IF(S$3=$I$15,SUM($L$155:$DP$155),0) -> 0 | ... DP157: =IF(DP$3=$I$15,SUM($L$155:$DP$155),0) -> 0
B160: Gross Sale Price | L160: =IF(L$3=$I$15,SUMPRODUCT(($L$3:$DP$3>$I$15-12)*($L$3:$DP$3<=$I$15)*$L$145:$DP$145)*(1+$E$121)/$E$124,0) -> 0 | M160: =IF(M$3=$I$15,SUMPRODUCT(($L$3:$DP$3>$I$15-12)*($L$3:$DP$3<=$I$15)*$L$145:$DP$145)*(1+$E$121)/$E$124,0) -> 0 | N160: =IF(N$3=$I$15,SUMPRODUCT(($L$3:$DP$3>$I$15-12)*($L$3:$DP$3<=$I$15)*$L$145:$DP$145)*(1+$E$121)/$E$124,0) -> 0 | O160: =IF(O$3=$I$15,SUMPRODUCT(($L$3:$DP$3>$I$15-12)*($L$3:$DP$3<=$I$15)*$L$145:$DP$145)*(1+$E$121)/$E$124,0) -> 0 | P160: =IF(P$3=$I$15,SUMPRODUCT(($L$3:$DP$3>$I$15-12)*($L$3:$DP$3<=$I$15)*$L$145:$DP$145)*(1+$E$121)/$E$124,0) -> 0 | Q160: =IF(Q$3=$I$15,SUMPRODUCT(($L$3:$DP$3>$I$15-12)*($L$3:$DP$3<=$I$15)*$L$145:$DP$145)*(1+$E$121)/$E$124,0) -> 0 | R160: =IF(R$3=$I$15,SUMPRODUCT(($L$3:$DP$3>$I$15-12)*($L$3:$DP$3<=$I$15)*$L$145:$DP$145)*(1+$E$121)/$E$124,0) -> 0 | S160: =IF(S$3=$I$15,SUMPRODUCT(($L$3:$DP$3>$I$15-12)*($L$3:$DP$3<=$I$15)*$L$145:$DP$145)*(1+$E$121)/$E$124,0) -> 0 | ... DP160: =IF(DP$3=$I$15,SUMPRODUCT(($L$3:$DP$3>$I$15-12)*($L$3:$DP$3<=$I$15)*$L$145:$DP$145)*(1+$E$121)/$E$124,0) -> 0
B161: Selling Costs | L161: =-L160*$E$125 -> 0 | M161: =-M160*$E$125 -> 0 | N161: =-N160*$E$125 -> 0 | O161: =-O160*$E$125 -> 0 | P161: =-P160*$E$125 -> 0 | Q161: =-Q160*$E$125 -> 0 | R161: =-R160*$E$125 -> 0 | S161: =-S160*$E$125 -> 0 | ... DP161: =-DP160*$E$125 -> 0
G210: EMx | H210: IRR | I210: Profit
B211: Net Unlevered Cash Flow | G211: =SUMIF($L$211:$DP$211,">0")/-SUMIF($L$211:$DP$211,"<0") -> 2.1017549 | H211: =XIRR(OFFSET($L$211,0,0,1,$I$15+1),OFFSET($L$24,0,0,1,$I$15+1)) -> 0.11915338 | I211: =SUM($L$211:$DP$211) -> 30254242 | L211: =(L$3<=$I$15)*(-L150+L145+L160+L161) -> -9898000 | M211: =(M$3<=$I$15)*(-M150+M145+M160+M161) -> -116268.56 | N211: =(N$3<=$I$15)*(-N150+N145+N160+N161) -> -282268.56 | O211: =(O$3<=$I$15)*(-O150+O145+O160+O161) -> -282268.56 | P211: =(P$3<=$I$15)*(-P150+P145+P160+P161) -> -430714.04 | Q211: =(Q$3<=$I$15)*(-Q150+Q145+Q160+Q161) -> -719125.82 | R211: =(R$3<=$I$15)*(-R150+R145+R160+R161) -> -982587.79 | S211: =(S$3<=$I$15)*(-S150+S145+S160+S161) -> -1206064.4 | ... DP211: =(DP$3<=$I$15)*(-DP150+DP145+DP160+DP161) -> 0
B212: Net Levered Cash Flow | G212: =SUMIF($L$212:$DP$212,">0")/-SUMIF($L$212:$DP$212,"<0") -> 2.724356 | H212: =XIRR(OFFSET($L$212,0,0,1,$I$15+1),OFFSET($L$24,0,0,1,$I$15+1)) -> 0.17326763 | I212: =SUM($L$212:$DP$212) -> 21439817 | L212: =(L$3<=$I$15)*(L211+L151-L152-L154+L155-L156-L157) -> -3959200 | M212: =(M$3<=$I$15)*(M211+M151-M152-M154+M155-M156-M157) -> -84862.174 | N212: =(N$3<=$I$15)*(N211+N151-N152-N154+N155-N156-N157) -> -151712.71 | O212: =(O$3<=$I$15)*(O211+O151-O152-O154+O155-O156-O157) -> -152806.51 | P212: =(P$3<=$I$15)*(P211+P151-P152-P154+P155-P156-P157) -> -213278.49 | Q212: =(Q$3<=$I$15)*(Q211+Q151-Q152-Q154+Q155-Q156-Q157) -> -330312.22 | R212: =(R$3<=$I$15)*(R211+R151-R152-R154+R155-R156-R157) -> -438483.62 | S212: =(S$3<=$I$15)*(S211+S151-S152-S154+S155-S156-S157) -> -531681.77 | ... DP212: =(DP$3<=$I$15)*(DP211+DP151-DP152-DP154+DP155-DP156-DP157) -> 0
B215: Yield-on-Cost | H215: =SUMPRODUCT(($L$3:$DP$3>$E$44)*($L$3:$DP$3<=$E$44+12)*$L$145:$DP$145)/I36 -> 0.076203211
B216: Market Cap Rate | H216: =E126 -> 0.0675
B217: Development Spread | H217: =(H215-H216)*10000 -> 87.032115
B228: GP | G228: =SUMIF($L$228:$DP$228,">0")/-SUMIF($L$228:$DP$228,"<0") -> 4.893068 | H228: =XIRR(OFFSET($L$228,0,0,1,$I$15+1),OFFSET($L$24,0,0,1,$I$15+1)) -> 0.27062634 | I228: =SUM($L$228:$DP$228) -> 4840454.5 | L228: =L212*(1-$E$130)+IF(L$3=$I$15,$I$233,0) -> -395920 | M228: =M212*(1-$E$130)+IF(M$3=$I$15,$I$233,0) -> -8486.2174 | N228: =N212*(1-$E$130)+IF(N$3=$I$15,$I$233,0) -> -15171.271 | O228: =O212*(1-$E$130)+IF(O$3=$I$15,$I$233,0) -> -15280.651 | P228: =P212*(1-$E$130)+IF(P$3=$I$15,$I$233,0) -> -21327.849 | Q228: =Q212*(1-$E$130)+IF(Q$3=$I$15,$I$233,0) -> -33031.222 | R228: =R212*(1-$E$130)+IF(R$3=$I$15,$I$233,0) -> -43848.362 | S228: =S212*(1-$E$130)+IF(S$3=$I$15,$I$233,0) -> -53168.177 | ... DP228: =DP212*(1-$E$130)+IF(DP$3=$I$15,$I$233,0) -> 0
B229: LP | G229: =SUMIF($L$229:$DP$229,">0")/-SUMIF($L$229:$DP$229,"<0") -> 2.483388 | H229: =XIRR(OFFSET($L$229,0,0,1,$I$15+1),OFFSET($L$24,0,0,1,$I$15+1)) -> 0.15801218 | I229: =SUM($L$229:$DP$229) -> 16599363 | L229: =L212*$E$130-IF(L$3=$I$15,$I$233,0) -> -3563280 | M229: =M212*$E$130-IF(M$3=$I$15,$I$233,0) -> -76375.957 | N229: =N212*$E$130-IF(N$3=$I$15,$I$233,0) -> -136541.44 | O229: =O212*$E$130-IF(O$3=$I$15,$I$233,0) -> -137525.85 | P229: =P212*$E$130-IF(P$3=$I$15,$I$233,0) -> -191950.64 | Q229: =Q212*$E$130-IF(Q$3=$I$15,$I$233,0) -> -297281 | R229: =R212*$E$130-IF(R$3=$I$15,$I$233,0) -> -394635.25 | S229: =S212*$E$130-IF(S$3=$I$15,$I$233,0) -> -478513.59 | ... DP229: =DP212*$E$130-IF(DP$3=$I$15,$I$233,0) -> 0
B232: Equity Contributed | I232: =-SUMIF($L$212:$DP$212,"<0") -> 12433521
B233: GP Promote at Sale | I233: =MAX(0,$E$132*($I$212-$E$131*$I$232*$I$15/12)) -> 2696472.7
