Workbook

Sheet Summary
B2: [INVESTMENT NAME]
B3: [City], [State]
G20: PRO FORMA | J20: STABILIZED (UNTRENDED)
G21: Effective Gross Revenue | J21: =U!C30*0.9 -> #VALUE!
L24: PROPERTY RETURNS | N24: ROI | O24: EMx | P24: IRR
L25: Unlevered | N25: =U!I12/U!I20 -> 0.65352113 | O25: =U!G12 -> 1.56 | P25: =U!H12 -> 0.1849
L26: Levered | N26: =U!I13/U!I21 -> 0.99090909 | O26: =U!G13 -> 1.99 | P26: =U!H13 -> 0.2533
G31: USES | I31: % | J31: /Buildable SF | K31: Amount
G32: Land Costs | I32: =K32/K36 -> 0.18181818 | J32: =K32/37500 -> 42.666667 | K32: =U!I3 -> 1600000
G33: Hard Costs | I33: =K33/K36 -> 0.81818182 | J33: =K33/37500 -> 192 | K33: =U!I4 -> 7200000
G36: Total Uses | I36: =SUM(I32:I33) -> 1 | J36: =K36/37500 -> 234.66667 | K36: =SUM(K32:K33) -> 8800000

Sheet U
B1: USES | D1: START | E1: END | F1: METHOD | H1: /RENTABLE SF | I1: AMOUNT
B2: Land Costs
B3: Land Costs | D3: 0 | E3: 0 | F3: Straight-Line | H3: =I3/37500 -> 42.666667 | I3: 1600000
B4: Construction Costs | D4: 1 | E4: 18 | F4: S-Curve | H4: =I4/37500 -> 192 | I4: 7200000
B5: Marketing | D5: 1 | E5: 18 | F5: Straight-Line | H5: =I5/37500 -> 2 | I5: 75000
G11: EQUITY MULTIPLE | H11: IRR | I11: NET PROFIT
B12: Net Unlevered Cash Flow | G12: 1.56 | H12: 0.1849 | I12: 5800000
B13: Net Levered Cash Flow | G13: 1.99 | H13: 0.2533 | I13: 4360000
F15: Analysis Year | G15: 0 | H15: 1 | I15: 2 | J15: 3 | K15: 4
B16: TOTAL PROJECT COST BEFORE FINANCING | G16: =I3 -> 1600000 | H16: =I4*0.8 -> 5760000 | I16: =I4*0.2 -> 1440000 | J16: 0 | K16: 0
I20: =I3+I4+I5 -> 8875000
I21: 4400000
B29: SUITE | C29: TENANT | E29: SF | G29: RENT GROWTH % | H29: RENT/SF/YR | I29: ANNUAL RENT
B30: 100-1 | C30: Acme Ltd | E30: 25000 | G30: 0.02 | H30: 34 | I30: =E30*H30 -> 850000
B31: 100-2 | C31: Beta LLP | E31: 12500 | G31: 0.02 | H31: 32 | I31: =E31*H31 -> 400000

Sheet Waterfall
B15: Tier 1 (Pref + Return of Capital) | C15: Equity Multiple | D15: IRR | E15: 0.1
B16: Tier 2 (Promote) | C16: 1.5 | D16: 0.1 | F16: 0.15
B30: LP Equity Multiple | D30: 4.64
