Workbook

Sheet Returns
B2: RIVERSIDE GARDENS · returns
B4: Gross development value | D4: =(Assumptions!$D$7*Assumptions!$D$9) -> 86700000
B5: Total development cost | D5: =-SUM(CashFlow!D5:AQ7)+SUM(CashFlow!D12:AQ12) -> 68003070
B6: Net profit | D6: =D4-D5 -> 18696930
B7: Profit on cost | D7: =D6/D5 -> 0.27494245
B8: Unlevered IRR | D8: =(1+IRR(CashFlow!D9:AQ9,0.02))^12-1 -> 0.17642051
B9: Levered IRR | D9: =(1+IRR(CashFlow!D15:AQ15,0.02))^12-1 -> 0.2513185
B10: Peak debt | D10: =MAX(CashFlow!D13:AQ13) -> 44694843
B11: NPV at discount rate | D11: =NPV(Assumptions!$D$20/12,CashFlow!D9:AQ9) -> 7656286.2
B12: Equity multiple | D12: =SUMIF(CashFlow!D15:AQ15,">0")/-SUMIF(CashFlow!D15:AQ15,"<0") -> 1.8394061

Sheet Assumptions
B2: RIVERSIDE GARDENS · residential scheme
B4: Site
B5: Site area (sqm) | D5: 6500
B6: Gross internal area (sqm) | D6: 12000
B7: Net sales area (sqm) | D7: 10200
B8: Revenue
B9: Sales price (£/sqm) | D9: 8500
B10: Sales period (months) | D10: 12
B11: Costs
B12: Land cost | D12: 25000000
B13: Build cost (£/sqm GIA) | D13: 2800
B14: Professional fees | D14: 0.1
B15: Contingency | D15: 0.05
B16: Build period (months) | D16: 24
B17: Funding
B18: Loan to cost | D18: 0.65
B19: Interest rate | D19: 0.075
B20: Discount rate | D20: 0.1
B22: Marketing budget | D22: 500000

Sheet CashFlow
B2: Monthly cash flow (£)
B4: Month | D4: 1 | E4: 2 | F4: 3 | G4: 4 | H4: 5 | I4: 6 | J4: 7 | K4: 8 | L4: 9 | M4: 10 | N4: 11 | O4: 12 | P4: 13 | Q4: 14 | R4: 15 | S4: 16 | T4: 17 | U4: 18 | V4: 19 | W4: 20 | X4: 21 | Y4: 22 | Z4: 23 | AA4: 24 | AB4: 25 | AC4: 26 | AD4: 27 | AE4: 28 | AF4: 29 | AG4: 30 | AH4: 31 | AI4: 32 | AJ4: 33 | AK4: 34 | AL4: 35 | AM4: 36 | AN4: 37 | AO4: 38 | AP4: 39 | AQ4: 40
B5: Land | D5: =IF(D4=1,-Assumptions!$D$12,0) -> -25000000 | E5: =IF(E4=1,-Assumptions!$D$12,0) -> 0 | F5: =IF(F4=1,-Assumptions!$D$12,0) -> 0 | G5: =IF(G4=1,-Assumptions!$D$12,0) -> 0 | H5: =IF(H4=1,-Assumptions!$D$12,0) -> 0 | I5: =IF(I4=1,-Assumptions!$D$12,0) -> 0 | J5: =IF(J4=1,-Assumptions!$D$12,0) -> 0 | K5: =IF(K4=1,-Assumptions!$D$12,0) -> 0 | ... AQ5: =IF(AQ4=1,-Assumptions!$D$12,0) -> 0
B6: Build | D6: =IF(D4<=Assumptions!$D$16,-(Assumptions!$D$6*Assumptions!$D$13)/Assumptions!$D$16,0) -> -1400000 | E6: =IF(E4<=Assumptions!$D$16,-(Assumptions!$D$6*Assumptions!$D$13)/Assumptions!$D$16,0) -> -1400000 | F6: =IF(F4<=Assumptions!$D$16,-(Assumptions!$D$6*Assumptions!$D$13)/Assumptions!$D$16,0) -> -1400000 | G6: =IF(G4<=Assumptions!$D$16,-(Assumptions!$D$6*Assumptions!$D$13)/Assumptions!$D$16,0) -> -1400000 | H6: =IF(H4<=Assumptions!$D$16,-(Assumptions!$D$6*Assumptions!$D$13)/Assumptions!$D$16,0) -> -1400000 | I6: =IF(I4<=Assumptions!$D$16,-(Assumptions!$D$6*Assumptions!$D$13)/Assumptions!$D$16,0) -> -1400000 | J6: =IF(J4<=Assumptions!$D$16,-(Assumptions!$D$6*Assumptions!$D$13)/Assumptions!$D$16,0) -> -1400000 | K6: =IF(K4<=Assumptions!$D$16,-(Assumptions!$D$6*Assumptions!$D$13)/Assumptions!$D$16,0) -> -1400000 | L6: =IF(L4<=Assumptions!$D$16,-(Assumptions!$D$6*Assumptions!$D$13)/Assumptions!$D$16,0) -> -1400000 | M6: -1400000 | N6: =IF(N4<=Assumptions!$D$16,-(Assumptions!$D$6*Assumptions!$D$13)/Assumptions!$D$16,0) -> -1400000 | O6: =IF(O4<=Assumptions!$D$16,-(Assumptions!$D$6*Assumptions!$D$13)/Assumptions!$D$16,0) -> -1400000 | P6: =IF(P4<=Assumptions!$D$16,-(Assumptions!$D$6*Assumptions!$D$13)/Assumptions!$D$16,0) -> -1400000 | Q6: =IF(Q4<=Assumptions!$D$16,-(Assumptions!$D$6*Assumptions!$D$13)/Assumptions!$D$16,0) -> -1400000 | R6: =IF(R4<=Assumptions!$D$16,-(Assumptions!$D$6*Assumptions!$D$13)/Assumptions!$D$16,0) -> -1400000 | S6: =IF(S4<=Assumptions!$D$16,-(Assumptions!$D$6*Assumptions!$D$13)/Assumptions!$D$16,0) -> -1400000 | T6: =IF(T4<=Assumptions!$D$16,-(Assumptions!$D$6*Assumptions!$D$13)/Assumptions!$D$16,0) -> -1400000 | U6: =IF(U4<=Assumptions!$D$16,-(Assumptions!$D$6*Assumptions!$D$13)/Assumptions!$D$16,0) -> -1400000 | ... AQ6: =IF(AQ4<=Assumptions!$D$16,-(Assumptions!$D$6*Assumptions!$D$13)/Assumptions!$D$16,0) -> 0
B7: Fees & contingency | D7: =D6*(Assumptions!$D$14+Assumptions!$D$15) -> -210000 | E7: =E6*(Assumptions!$D$14+Assumptions!$D$15) -> -210000 | F7: =F6*(Assumptions!$D$14+Assumptions!$D$15) -> -210000 | G7: =G6*(Assumptions!$D$14+Assumptions!$D$15) -> -210000 | H7: =H6*(Assumptions!$D$14+Assumptions!$D$15) -> -210000 | I7: =I6*(Assumptions!$D$14+Assumptions!$D$15) -> -210000 | J7: =J6*(Assumptions!$D$14+Assumptions!$D$15) -> -210000 | K7: =K6*(Assumptions!$D$14+Assumptions!$D$15) -> -210000 | ... AQ7: =AQ6*(Assumptions!$D$14+Assumptions!$D$15) -> 0
B8: Sales revenue | D8: =IF(AND(D4>Assumptions!$D$16,D4<=Assumptions!$D$16+Assumptions!$D$10),(Assumptions!$D$7*Assumptions!$D$9)/Assumptions!$D$10,0) -> 0 | E8: =IF(AND(E4>Assumptions!$D$16,E4<=Assumptions!$D$16+Assumptions!$D$10),(Assumptions!$D$7*Assumptions!$D$9)/Assumptions!$D$10,0) -> 0 | F8: =IF(AND(F4>Assumptions!$D$16,F4<=Assumptions!$D$16+Assumptions!$D$10),(Assumptions!$D$7*Assumptions!$D$9)/Assumptions!$D$10,0) -> 0 | G8: =IF(AND(G4>Assumptions!$D$16,G4<=Assumptions!$D$16+Assumptions!$D$10),(Assumptions!$D$7*Assumptions!$D$9)/Assumptions!$D$10,0) -> 0 | H8: =IF(AND(H4>Assumptions!$D$16,H4<=Assumptions!$D$16+Assumptions!$D$10),(Assumptions!$D$7*Assumptions!$D$9)/Assumptions!$D$10,0) -> 0 | I8: =IF(AND(I4>Assumptions!$D$16,I4<=Assumptions!$D$16+Assumptions!$D$10),(Assumptions!$D$7*Assumptions!$D$9)/Assumptions!$D$10,0) -> 0 | J8: =IF(AND(J4>Assumptions!$D$16,J4<=Assumptions!$D$16+Assumptions!$D$10),(Assumptions!$D$7*Assumptions!$D$9)/Assumptions!$D$10,0) -> 0 | K8: =IF(AND(K4>Assumptions!$D$16,K4<=Assumptions!$D$16+Assumptions!$D$10),(Assumptions!$D$7*Assumptions!$D$9)/Assumptions!$D$10,0) -> 0 | ... AQ8: =IF(AND(AQ4>Assumptions!$D$16,AQ4<=Assumptions!$D$16+Assumptions!$D$10),(Assumptions!$D$7*Assumptions!$D$9)/Assumptions!$D$10,0) -> 0
B9: Net cash flow (unlevered) | D9: =SUM(D5:D8) -> -26610000 | E9: =SUM(E5:E8) -> -1610000 | F9: =SUM(F5:F8) -> -1610000 | G9: =SUM(G5:G8) -> -1610000 | H9: =SUM(H5:H8) -> -1610000 | I9: =SUM(I5:I8) -> -1610000 | J9: =SUM(J5:J8) -> -1610000 | K9: =SUM(K5:K8) -> -1610000 | ... O9: =SUM(O5:O8) -> -1610000 | P9: =SUM(P5:P7) -> -1610000 | Q9: =SUM(Q5:Q8) -> -1610000 | R9: =SUM(R5:R8) -> -1610000 | S9: =SUM(S5:S8) -> -1610000 | T9: =SUM(T5:T8) -> -1610000 | U9: =SUM(U5:U8) -> -1610000 | V9: =SUM(V5:V8) -> -1610000 | W9: =SUM(W5:W8) -> -1610000 | X9: =SUM(X5:X8) -> -1610000 | ... AQ9: =SUM(AQ5:AQ8) -> 0
B10: Cumulative cost | D10: =-SUM($D$5:D7) -> 26610000 | E10: =-SUM($D$5:E7) -> 28220000 | F10: =-SUM($D$5:F7) -> 29830000 | G10: =-SUM($D$5:G7) -> 31440000 | H10: =-SUM($D$5:H7) -> 33050000 | I10: =-SUM($D$5:I7) -> 34660000 | J10: =-SUM($D$5:J7) -> 36270000 | K10: =-SUM($D$5:K7) -> 37880000 | ... AQ10: =-SUM($D$5:AQ7) -> 63640000
B11: Debt draw | D11: =MAX(0,MIN(-(D5+D6+D7),D10-(1-Assumptions!$D$18)*(-SUM($D$5:$AQ$7)))) -> 4336000 | E11: =MAX(0,MIN(-(E5+E6+E7),E10-(1-Assumptions!$D$18)*(-SUM($D$5:$AQ$7)))) -> 1610000 | F11: =MAX(0,MIN(-(F5+F6+F7),F10-(1-Assumptions!$D$18)*(-SUM($D$5:$AQ$7)))) -> 1610000 | G11: =MAX(0,MIN(-(G5+G6+G7),G10-(1-Assumptions!$D$18)*(-SUM($D$5:$AQ$7)))) -> 1610000 | H11: =MAX(0,MIN(-(H5+H6+H7),H10-(1-Assumptions!$D$18)*(-SUM($D$5:$AQ$7)))) -> 1610000 | I11: =MAX(0,MIN(-(I5+I6+I7),I10-(1-Assumptions!$D$18)*(-SUM($D$5:$AQ$7)))) -> 1610000 | J11: =MAX(0,MIN(-(J5+J6+J7),J10-(1-Assumptions!$D$18)*(-SUM($D$5:$AQ$7)))) -> 1610000 | K11: =MAX(0,MIN(-(K5+K6+K7),K10-(1-Assumptions!$D$18)*(-SUM($D$5:$AQ$7)))) -> 1610000 | ... AQ11: =MAX(0,MIN(-(AQ5+AQ6+AQ7),AQ10-(1-Assumptions!$D$18)*(-SUM($D$5:$AQ$7)))) -> 0
B12: Interest | D12: =0*Assumptions!$D$19/12 -> 0 | E12: =D13*Assumptions!$D$19/12 -> 27100 | F12: =E13*Assumptions!$D$19/12 -> 37331.875 | G12: =F13*Assumptions!$D$19/12 -> 47627.699 | H12: =G13*Assumptions!$D$19/12 -> 57987.872 | I12: =H13*Assumptions!$D$19/12 -> 68412.797 | J12: =I13*Assumptions!$D$19/12 -> 78902.877 | K12: =J13*Assumptions!$D$19/12 -> 89458.519 | L12: =K13*Assumptions!$D$19/12 -> 100080.14 | ... AQ12: =AP13*Assumptions!$D$19/12 -> 0
B13: Debt balance | D13: =0+D11+D12-D14 -> 4336000 | E13: =D13+E11+E12-E14 -> 5973100 | F13: =E13+F11+F12-F14 -> 7620431.9 | G13: =F13+G11+G12-G14 -> 9278059.6 | H13: =G13+H11+H12-H14 -> 10946047 | I13: =H13+I11+I12-I14 -> 12624460 | J13: =I13+J11+J12-J14 -> 14313363 | K13: =J13+K11+K12-K14 -> 16012822 | L13: =K13+L11+L12-L14 -> 17722902 | ... AQ13: =AP13+AQ11+AQ12-AQ14 -> 0
B14: Debt repayment | D14: =IF(D8>0,MIN(D8,0+D11+D12),0) -> 0 | E14: =IF(E8>0,MIN(E8,D13+E11+E12),0) -> 0 | F14: =IF(F8>0,MIN(F8,E13+F11+F12),0) -> 0 | G14: =IF(G8>0,MIN(G8,F13+G11+G12),0) -> 0 | H14: =IF(H8>0,MIN(H8,G13+H11+H12),0) -> 0 | I14: =IF(I8>0,MIN(I8,H13+I11+I12),0) -> 0 | J14: =IF(J8>0,MIN(J8,I13+J11+J12),0) -> 0 | K14: =IF(K8>0,MIN(K8,J13+K11+K12),0) -> 0 | L14: =IF(L8>0,MIN(L8,K13+L11+L12),0) -> 0 | ... AQ14: =IF(AQ8>0,MIN(AQ8,AP13+AQ11+AQ12),0) -> 0
B15: Net cash flow to equity | D15: =D9+D11-D14 -> -22274000 | E15: =E9+E11-E14 -> 0 | F15: =F9+F11-F14 -> 0 | G15: =G9+G11-G14 -> 0 | H15: =H9+H11-H14 -> 0 | I15: =I9+I11-I14 -> 0 | J15: =J9+J11-J14 -> 0 | K15: =K9+K11-K14 -> 0 | ... AQ15: =AQ9+AQ11-AQ14 -> 0

Sheet Checks
B2: Checks and dates
B4: Analysis date | D4: =TODAY() -> 46310
B5: Completion date | D5: =EDATE(D4,Assumptions!D16) -> 47041
B6: Average monthly sales after build | D6: =AVERAGEIFS(CashFlow!D8:AQ8,CashFlow!D4:AQ4,">"&Assumptions!D16) -> 5418750
B7: Scheme | D7: =_xlfn.CONCAT("Scheme: ",Returns!B2) -> Scheme: RIVERSIDE GARDENS · returns
B8: Debt balance at month 30 | D8: =LOOKUP(30,CashFlow!D4:AQ4,CashFlow!D13:AQ13) -> 2364292.8
B9: Rank of levered IRR | D9: =RANK(Returns!D9,Returns!D7:D9) -> 2
B10: Debt trend at month 41 | D10: =FORECAST(41,CashFlow!D13:AQ13,CashFlow!D4:AQ4) -> 10223373
B11: Strength | D11: =_xlfn.IFS(Returns!D7>0.2,"strong",Returns!D7>0.1,"ok",TRUE(),"weak") -> strong
B12: Sales after build | D12: =SUMPRODUCT((CashFlow!D4:AQ4>Assumptions!D16)*CashFlow!D8:AQ8) -> 86700000
B13: Days to completion | D13: =D5-D4 -> 731
B15: Cost per unit sold | D15: =Returns!D5/0 -> #DIV/0!
