Workbook

Sheet Inputs
A1: RIVERSIDE LOGISTICS PARK (SAR)
A2: Scenario (1 = Base, 2 = Downside) | B2: 1
A3: Rent per sqm · Base | B3: 150
A4: Rent per sqm · Downside | B4: 120
A5: Lettable area (sqm) | B5: 400000
A6: Rent growth | B6: 0.03
A7: Operating costs (share of rent) | B7: 0.15
A8: Construction cost | B8: 600000000
A9: Exit yield | B9: 0.07
A10: Exit year | B10: 8
A11: Interest rate | B11: 0.06
A12: Loan to cost | B12: 0.55
A13: Debt cap | B13: 340000000
A14: Minimum DSCR covenant | B14: 1.3
A15: Professional fees | B15: =B8*0.08 -> 48000000

Sheet Cash Flow
A1: RIVERSIDE LOGISTICS PARK - CASH FLOW (SAR)
A3: Year | C3: 2027 | D3: 2028 | E3: 2029 | F3: 2030 | G3: 2031 | H3: 2032 | I3: 2033 | J3: 2034 | K3: 2035 | L3: 2036 | M3: Total
A4: Period | C4: 1 | D4: =C4+1 -> 2 | E4: =D4+1 -> 3 | F4: =E4+1 -> 4 | G4: =F4+1 -> 5 | H4: =G4+1 -> 6 | I4: =H4+1 -> 7 | J4: =I4+1 -> 8 | K4: =J4+1 -> 9 | L4: =K4+1 -> 10
A6: Construction cost | C6: =IF(C$4<=2,-(Inputs!$B$8+Inputs!$B$15)/2,0) -> -324000000 | D6: =IF(D$4<=2,-(Inputs!$B$8+Inputs!$B$15)/2,0) -> -324000000 | E6: =IF(E$4<=2,-(Inputs!$B$8+Inputs!$B$15)/2,0) -> 0 | F6: =IF(F$4<=2,-(Inputs!$B$8+Inputs!$B$15)/2,0) -> 0 | G6: =IF(G$4<=2,-(Inputs!$B$8+Inputs!$B$15)/2,0) -> 0 | H6: =IF(H$4<=2,-(Inputs!$B$8+Inputs!$B$15)/2,0) -> 0 | I6: =IF(I$4<=2,-(Inputs!$B$8+Inputs!$B$15)/2,0) -> 0 | J6: =IF(J$4<=2,-(Inputs!$B$8+Inputs!$B$15)/2,0) -> 0 | ... L6: =IF(L$4<=2,-(Inputs!$B$8+Inputs!$B$15)/2,0) -> 0 | M6: =SUM(C6:L6) -> -648000000
A7: Occupancy | C7: 0 | D7: 0 | E7: 0.6 | F7: 0.85 | G7: 0.95 | H7: 0.95 | I7: 0.95 | J7: 0.95 | K7: 0.95 | L7: 0.95
A8: Rent | C8: =IF(C$4<=Inputs!$B$10,Inputs!$B$5*CHOOSE(Inputs!$B$2,Inputs!$B$3,Inputs!$B$4)*C7*(1+Inputs!$B$6)^MAX(0,C$4-3),0) -> 0 | D8: =IF(D$4<=Inputs!$B$10,Inputs!$B$5*CHOOSE(Inputs!$B$2,Inputs!$B$3,Inputs!$B$4)*D7*(1+Inputs!$B$6)^MAX(0,D$4-3),0) -> 0 | E8: =IF(E$4<=Inputs!$B$10,Inputs!$B$5*CHOOSE(Inputs!$B$2,Inputs!$B$3,Inputs!$B$4)*E7*(1+Inputs!$B$6)^MAX(0,E$4-3),0) -> 36000000 | F8: =IF(F$4<=Inputs!$B$10,Inputs!$B$5*CHOOSE(Inputs!$B$2,Inputs!$B$3,Inputs!$B$4)*F7*(1+Inputs!$B$6)^MAX(0,F$4-3),0) -> 52530000 | G8: =IF(G$4<=Inputs!$B$10,Inputs!$B$5*CHOOSE(Inputs!$B$2,Inputs!$B$3,Inputs!$B$4)*G7*(1+Inputs!$B$6)^MAX(0,G$4-3),0) -> 60471300 | H8: =IF(H$4<=Inputs!$B$10,Inputs!$B$5*CHOOSE(Inputs!$B$2,Inputs!$B$3,Inputs!$B$4)*H7*(1+Inputs!$B$6)^MAX(0,H$4-3),0) -> 62285439 | I8: =IF(I$4<=Inputs!$B$10,Inputs!$B$5*CHOOSE(Inputs!$B$2,Inputs!$B$3,Inputs!$B$4)*I7*(1+Inputs!$B$6)^MAX(0,I$4-3),0) -> 64154002 | J8: =IF(J$4<=Inputs!$B$10,Inputs!$B$5*CHOOSE(Inputs!$B$2,Inputs!$B$3,Inputs!$B$4)*J7*(1+Inputs!$B$6)^MAX(0,J$4-3),0) -> 66078622 | ... L8: =IF(L$4<=Inputs!$B$10,Inputs!$B$5*CHOOSE(Inputs!$B$2,Inputs!$B$3,Inputs!$B$4)*L7*(1+Inputs!$B$6)^MAX(0,L$4-3),0) -> 0 | M8: =SUM(C8:L8) -> 3.4151936e+08
A9: Operating costs | C9: =-C8*Inputs!$B$7 -> 0 | D9: =-D8*Inputs!$B$7 -> 0 | E9: =-E8*Inputs!$B$7 -> -5400000 | F9: =-F8*Inputs!$B$7 -> -7879500 | G9: =-G8*Inputs!$B$7 -> -9070695 | H9: =-H8*Inputs!$B$7 -> -9342815.8 | I9: =-I8*Inputs!$B$7 -> -9623100.3 | J9: =-J8*Inputs!$B$7 -> -9911793.3 | ... L9: =-L8*Inputs!$B$7 -> 0 | M9: =SUM(C9:L9) -> -51227905
A10: Net operating income | C10: =C8+C9 -> 0 | D10: =D8+D9 -> 0 | E10: =E8+E9 -> 30600000 | F10: =F8+F9 -> 44650500 | G10: =G8+G9 -> 51400605 | H10: =H8+H9 -> 52942623 | I10: =I8+I9 -> 54530902 | J10: =J8+J9 -> 56166829 | ... L10: =L8+L9 -> 0 | M10: =SUM(C10:L10) -> 2.9029146e+08
A11: Sale proceeds | C11: =IF(C$4=Inputs!$B$10,C10*(1+Inputs!$B$6)/Inputs!$B$9*0.98,0) -> 0 | D11: =IF(D$4=Inputs!$B$10,D10*(1+Inputs!$B$6)/Inputs!$B$9*0.98,0) -> 0 | E11: =IF(E$4=Inputs!$B$10,E10*(1+Inputs!$B$6)/Inputs!$B$9*0.98,0) -> 0 | F11: =IF(F$4=Inputs!$B$10,F10*(1+Inputs!$B$6)/Inputs!$B$9*0.98,0) -> 0 | G11: =IF(G$4=Inputs!$B$10,G10*(1+Inputs!$B$6)/Inputs!$B$9*0.98,0) -> 0 | H11: =IF(H$4=Inputs!$B$10,H10*(1+Inputs!$B$6)/Inputs!$B$9*0.98,0) -> 0 | I11: =IF(I$4=Inputs!$B$10,I10*(1+Inputs!$B$6)/Inputs!$B$9*0.98,0) -> 0 | J11: =IF(J$4=Inputs!$B$10,J10*(1+Inputs!$B$6)/Inputs!$B$9*0.98,0) -> 8.0992567e+08 | ... L11: =IF(L$4=Inputs!$B$10,L10*(1+Inputs!$B$6)/Inputs!$B$9*0.98,0) -> 0 | M11: =SUM(C11:L11) -> 8.0992567e+08
A12: Unlevered cash flow | C12: =C6+C10+C11 -> -324000000 | D12: =D6+D10+D11 -> -324000000 | E12: =E6+E10+E11 -> 30600000 | F12: =F6+F10+F11 -> 44650500 | G12: =G6+G10+G11 -> 51400605 | H12: =H6+H10+H11 -> 52942623 | I12: =I6+I10+I11 -> 54530902 | J12: =J6+J10+J11 -> 8.660925e+08 | ... L12: =L6+L10+L11 -> 0 | M12: =SUM(C12:L12) -> 4.5221713e+08
A13: Debt drawn | C13: =IF(C$4<=2,MIN(Inputs!$B$12*(Inputs!$B$8+Inputs!$B$15),Inputs!$B$13)/2,0) -> 170000000 | D13: =IF(D$4<=2,MIN(Inputs!$B$12*(Inputs!$B$8+Inputs!$B$15),Inputs!$B$13)/2,0) -> 170000000 | E13: =IF(E$4<=2,MIN(Inputs!$B$12*(Inputs!$B$8+Inputs!$B$15),Inputs!$B$13)/2,0) -> 0 | F13: =IF(F$4<=2,MIN(Inputs!$B$12*(Inputs!$B$8+Inputs!$B$15),Inputs!$B$13)/2,0) -> 0 | G13: =IF(G$4<=2,MIN(Inputs!$B$12*(Inputs!$B$8+Inputs!$B$15),Inputs!$B$13)/2,0) -> 0 | H13: =IF(H$4<=2,MIN(Inputs!$B$12*(Inputs!$B$8+Inputs!$B$15),Inputs!$B$13)/2,0) -> 0 | I13: =IF(I$4<=2,MIN(Inputs!$B$12*(Inputs!$B$8+Inputs!$B$15),Inputs!$B$13)/2,0) -> 0 | J13: =IF(J$4<=2,MIN(Inputs!$B$12*(Inputs!$B$8+Inputs!$B$15),Inputs!$B$13)/2,0) -> 0 | ... L13: =IF(L$4<=2,MIN(Inputs!$B$12*(Inputs!$B$8+Inputs!$B$15),Inputs!$B$13)/2,0) -> 0 | M13: =SUM(C13:L13) -> 340000000
A14: Opening debt | C14: =0 -> 0 | D14: =C17 -> 170000000 | E14: =D17 -> 340000000 | F14: =E17 -> 340000000 | G14: =F17 -> 340000000 | H14: =G17 -> 340000000 | I14: =H17 -> 340000000 | J14: =I17 -> 340000000 | K14: =J17 -> 0 | L14: =K17 -> 0
A15: Interest | C15: =-C14*Inputs!$B$11 -> 0 | D15: =-D14*Inputs!$B$11 -> -10200000 | E15: =-E14*Inputs!$B$11 -> -20400000 | F15: =-F14*Inputs!$B$11 -> -20400000 | G15: =-G14*Inputs!$B$11 -> -20400000 | H15: =-H14*Inputs!$B$11 -> -20400000 | I15: =-I14*Inputs!$B$11 -> -20400000 | J15: =-J14*Inputs!$B$11 -> -20400000 | ... L15: =-L14*Inputs!$B$11 -> 0 | M15: =SUM(C15:L15) -> -132600000
A16: Loan repayment | C16: =IF(C$4=Inputs!$B$10,-(C14+C13),0) -> 0 | D16: =IF(D$4=Inputs!$B$10,-(D14+D13),0) -> 0 | E16: =IF(E$4=Inputs!$B$10,-(E14+E13),0) -> 0 | F16: =IF(F$4=Inputs!$B$10,-(F14+F13),0) -> 0 | G16: =IF(G$4=Inputs!$B$10,-(G14+G13),0) -> 0 | H16: =IF(H$4=Inputs!$B$10,-(H14+H13),0) -> 0 | I16: =IF(I$4=Inputs!$B$10,-(I14+I13),0) -> 0 | J16: =IF(J$4=Inputs!$B$10,-(J14+J13),0) -> -340000000 | ... L16: =IF(L$4=Inputs!$B$10,-(L14+L13),0) -> 0 | M16: =SUM(C16:L16) -> -340000000
A17: Closing debt | C17: =C14+C13+C16 -> 170000000 | D17: =D14+D13+D16 -> 340000000 | E17: =E14+E13+E16 -> 340000000 | F17: =F14+F13+F16 -> 340000000 | G17: =G14+G13+G16 -> 340000000 | H17: =H14+H13+H16 -> 340000000 | I17: =I14+I13+I16 -> 340000000 | J17: =J14+J13+J16 -> 0 | ... L17: =L14+L13+L16 -> 0
A18: DSCR | C18: =IF(AND(C10>0,C15<0),C10/-C15,"") | D18: =IF(AND(D10>0,D15<0),D10/-D15,"") | E18: =IF(AND(E10>0,E15<0),E10/-E15,"") -> 1.5 | F18: =IF(AND(F10>0,F15<0),F10/-F15,"") -> 2.18875 | G18: =IF(AND(G10>0,G15<0),G10/-G15,"") -> 2.5196375 | H18: =IF(AND(H10>0,H15<0),H10/-H15,"") -> 2.5952266 | I18: =IF(AND(I10>0,I15<0),I10/-I15,"") -> 2.6730834 | J18: =IF(AND(J10>0,J15<0),J10/-J15,"") -> 2.7532759 | ... L18: =IF(AND(L10>0,L15<0),L10/-L15,"")
A19: Cash trapped | C19: =IF(AND(ISNUMBER(C18),C$4<Inputs!$B$10),IF(C18<Inputs!$B$14,MAX(0,C10+C15),0),0) -> 0 | D19: =IF(AND(ISNUMBER(D18),D$4<Inputs!$B$10),IF(D18<Inputs!$B$14,MAX(0,D10+D15),0),0) -> 0 | E19: =IF(AND(ISNUMBER(E18),E$4<Inputs!$B$10),IF(E18<Inputs!$B$14,MAX(0,E10+E15),0),0) -> 0 | F19: =IF(AND(ISNUMBER(F18),F$4<Inputs!$B$10),IF(F18<Inputs!$B$14,MAX(0,F10+F15),0),0) -> 0 | G19: =IF(AND(ISNUMBER(G18),G$4<Inputs!$B$10),IF(G18<Inputs!$B$14,MAX(0,G10+G15),0),0) -> 0 | H19: =IF(AND(ISNUMBER(H18),H$4<Inputs!$B$10),IF(H18<Inputs!$B$14,MAX(0,H10+H15),0),0) -> 0 | I19: =IF(AND(ISNUMBER(I18),I$4<Inputs!$B$10),IF(I18<Inputs!$B$14,MAX(0,I10+I15),0),0) -> 0 | J19: =IF(AND(ISNUMBER(J18),J$4<Inputs!$B$10),IF(J18<Inputs!$B$14,MAX(0,J10+J15),0),0) -> 0 | ... L19: =IF(AND(ISNUMBER(L18),L$4<Inputs!$B$10),IF(L18<Inputs!$B$14,MAX(0,L10+L15),0),0) -> 0 | M19: =SUM(C19:L19) -> 0
A20: Cash released | C20: =IF(C$4=Inputs!$B$10,SUM($C19:C19),0) -> 0 | D20: =IF(D$4=Inputs!$B$10,SUM($C19:D19),0) -> 0 | E20: =IF(E$4=Inputs!$B$10,SUM($C19:E19),0) -> 0 | F20: =IF(F$4=Inputs!$B$10,SUM($C19:F19),0) -> 0 | G20: =IF(G$4=Inputs!$B$10,SUM($C19:G19),0) -> 0 | H20: =IF(H$4=Inputs!$B$10,SUM($C19:H19),0) -> 0 | I20: =IF(I$4=Inputs!$B$10,SUM($C19:I19),0) -> 0 | J20: =IF(J$4=Inputs!$B$10,SUM($C19:J19),0) -> 0 | ... L20: =IF(L$4=Inputs!$B$10,SUM($C19:L19),0) -> 0 | M20: =SUM(C20:L20) -> 0
A21: Levered cash flow to equity | C21: =C12+C13+C15+C16-C19+C20 -> -154000000 | D21: =D12+D13+D15+D16-D19+D20 -> -164200000 | E21: =E12+E13+E15+E16-E19+E20 -> 10200000 | F21: =F12+F13+F15+F16-F19+F20 -> 24250500 | G21: =G12+G13+G15+G16-G19+G20 -> 31000605 | H21: =H12+H13+H15+H16-H19+H20 -> 32542623 | I21: =I12+I13+I15+I16-I19+I20 -> 34130902 | J21: =J12+J13+J15+J16-J19+J20 -> 5.056925e+08 | ... L21: =L12+L13+L15+L16-L19+L20 -> 0 | M21: =SUM(C21:L21) -> 3.1961713e+08
A22: Cumulative equity cash flow | C22: =SUM($C21:C21) -> -154000000 | D22: =SUM($C21:D21) -> -318200000 | E22: =SUM($C21:E21) -> -308000000 | F22: =SUM($C21:F21) -> -283749500 | G22: =SUM($C21:G21) -> -252748895 | H22: =SUM($C21:H21) -> -2.2020627e+08 | I22: =SUM($C21:I21) -> -1.8607537e+08 | J22: =SUM($C21:J21) -> 3.1961713e+08 | ... L22: =SUM($C21:L21) -> 3.1961713e+08

Sheet Returns
A1: RETURNS
A2: Unlevered IRR | B2: =IRR('Cash Flow'!C12:L12) -> 0.094846972
A3: Levered IRR | B3: =IFERROR(IRR('Cash Flow'!C21:L21),0) -> 0.12571923
A4: Equity multiple | B4: =SUMIF('Cash Flow'!C21:L21,">0")/-SUMIF('Cash Flow'!C21:L21,"<0") -> 2.0044536
A5: Net profit | B5: =SUM('Cash Flow'!C21:L21) -> 3.1961713e+08
A6: Peak debt | B6: =MAX('Cash Flow'!C17:L17) -> 340000000
A7: Minimum DSCR | B7: =MIN('Cash Flow'!C18:L18) -> 1.5
A8: Total development cost | B8: =-'Cash Flow'!M6 -> 648000000
A9: Profit on cost | B9: =B5/B8 -> 0.49323631
A10: Cash trapped (total) | B10: ='Cash Flow'!M19 -> 0
