Workbook

Sheet Inputs
A1: AL WAHA MIXED-USE · inputs
A3: General
A4: Project start date | B4: date | C4: 46023
A5: Land | B5: SAR | C5: 60000000
A6: Build period | B6: years | C6: 2
A7: Hold after completion | B7: years | C7: 5
A8: Phase 1 · Residential
A9: Residential GLA | B9: sqm | C9: 24000
A10: Residential rent | B10: SAR/sqm/yr | C10: 1100
A11: Construction cost | B11: SAR/sqm | C11: 4200
A12: Phase 2 · Retail
A13: Retail GLA | B13: sqm | C13: 9000
A14: Retail rent | B14: SAR/sqm/yr | C14: 1800
A15: Construction cost | B15: SAR/sqm | C15: 5000
A16: Operations
A17: Vacancy | B17: % | C17: 5
A18: Operating costs | B18: % of rent | C18: 20
A19: Rent growth | B19: % p.a. | C19: 3
A20: Exit yield | B20: % | C20: 7.5
A21: Funding
A22: Debt (loan to cost) | B22: % | C22: 50
A23: Interest rate | B23: % | C23: 6.5

Sheet CashFlow
A1: Annual cash flow (SAR)
A3: Year | B3: 0 | C3: 1 | D3: 2 | E3: 3 | F3: 4 | G3: 5 | H3: 6 | I3: 7 | J3: 8 | K3: 9
A4: Date | B4: =EDATE(Inputs!$C$4,12*B3) -> 46023 | C4: =EDATE(Inputs!$C$4,12*C3) -> 46388 | D4: =EDATE(Inputs!$C$4,12*D3) -> 46753 | E4: =EDATE(Inputs!$C$4,12*E3) -> 47119 | F4: =EDATE(Inputs!$C$4,12*F3) -> 47484 | G4: =EDATE(Inputs!$C$4,12*G3) -> 47849 | H4: =EDATE(Inputs!$C$4,12*H3) -> 48214 | I4: =EDATE(Inputs!$C$4,12*I3) -> 48580 | ... K4: =EDATE(Inputs!$C$4,12*K3) -> 49310
A5: Land | B5: =IF(B3=0,-Inputs!$C$5,0) -> -60000000 | C5: =IF(C3=0,-Inputs!$C$5,0) -> 0 | D5: =IF(D3=0,-Inputs!$C$5,0) -> 0 | E5: =IF(E3=0,-Inputs!$C$5,0) -> 0 | F5: =IF(F3=0,-Inputs!$C$5,0) -> 0 | G5: =IF(G3=0,-Inputs!$C$5,0) -> 0 | H5: =IF(H3=0,-Inputs!$C$5,0) -> 0 | I5: =IF(I3=0,-Inputs!$C$5,0) -> 0 | ... K5: =IF(K3=0,-Inputs!$C$5,0) -> 0
A6: Construction | B6: =IF(B3<Inputs!$C$6,-(Inputs!$C$9*Inputs!$C$11+Inputs!$C$13*Inputs!$C$15)/Inputs!$C$6,0) -> -72900000 | C6: =IF(C3<Inputs!$C$6,-(Inputs!$C$9*Inputs!$C$11+Inputs!$C$13*Inputs!$C$15)/Inputs!$C$6,0) -> -72900000 | D6: =IF(D3<Inputs!$C$6,-(Inputs!$C$9*Inputs!$C$11+Inputs!$C$13*Inputs!$C$15)/Inputs!$C$6,0) -> 0 | E6: =IF(E3<Inputs!$C$6,-(Inputs!$C$9*Inputs!$C$11+Inputs!$C$13*Inputs!$C$15)/Inputs!$C$6,0) -> 0 | F6: =IF(F3<Inputs!$C$6,-(Inputs!$C$9*Inputs!$C$11+Inputs!$C$13*Inputs!$C$15)/Inputs!$C$6,0) -> 0 | G6: =IF(G3<Inputs!$C$6,-(Inputs!$C$9*Inputs!$C$11+Inputs!$C$13*Inputs!$C$15)/Inputs!$C$6,0) -> 0 | H6: =IF(H3<Inputs!$C$6,-(Inputs!$C$9*Inputs!$C$11+Inputs!$C$13*Inputs!$C$15)/Inputs!$C$6,0) -> 0 | I6: =IF(I3<Inputs!$C$6,-(Inputs!$C$9*Inputs!$C$11+Inputs!$C$13*Inputs!$C$15)/Inputs!$C$6,0) -> 0 | ... K6: =IF(K3<Inputs!$C$6,-(Inputs!$C$9*Inputs!$C$11+Inputs!$C$13*Inputs!$C$15)/Inputs!$C$6,0) -> 0
A7: Rent (net) | B7: =IF(AND(B3>=Inputs!$C$6,B3<Inputs!$C$6+Inputs!$C$7),(Inputs!$C$9*Inputs!$C$10+Inputs!$C$13*Inputs!$C$14)*(1-Inputs!$C$17/100)*(1-Inputs!$C$18/100)*(1+Inputs!$C$19/100)^(B3-Inputs!$C$6),0) -> 0 | C7: =IF(AND(C3>=Inputs!$C$6,C3<Inputs!$C$6+Inputs!$C$7),(Inputs!$C$9*Inputs!$C$10+Inputs!$C$13*Inputs!$C$14)*(1-Inputs!$C$17/100)*(1-Inputs!$C$18/100)*(1+Inputs!$C$19/100)^(C3-Inputs!$C$6),0) -> 0 | D7: =IF(AND(D3>=Inputs!$C$6,D3<Inputs!$C$6+Inputs!$C$7),(Inputs!$C$9*Inputs!$C$10+Inputs!$C$13*Inputs!$C$14)*(1-Inputs!$C$17/100)*(1-Inputs!$C$18/100)*(1+Inputs!$C$19/100)^(D3-Inputs!$C$6),0) -> 32376000 | E7: =IF(AND(E3>=Inputs!$C$6,E3<Inputs!$C$6+Inputs!$C$7),(Inputs!$C$9*Inputs!$C$10+Inputs!$C$13*Inputs!$C$14)*(1-Inputs!$C$17/100)*(1-Inputs!$C$18/100)*(1+Inputs!$C$19/100)^(E3-Inputs!$C$6),0) -> 33347280 | F7: =IF(AND(F3>=Inputs!$C$6,F3<Inputs!$C$6+Inputs!$C$7),(Inputs!$C$9*Inputs!$C$10+Inputs!$C$13*Inputs!$C$14)*(1-Inputs!$C$17/100)*(1-Inputs!$C$18/100)*(1+Inputs!$C$19/100)^(F3-Inputs!$C$6),0) -> 34347698 | G7: =IF(AND(G3>=Inputs!$C$6,G3<Inputs!$C$6+Inputs!$C$7),(Inputs!$C$9*Inputs!$C$10+Inputs!$C$13*Inputs!$C$14)*(1-Inputs!$C$17/100)*(1-Inputs!$C$18/100)*(1+Inputs!$C$19/100)^(G3-Inputs!$C$6),0) -> 35378129 | H7: =IF(AND(H3>=Inputs!$C$6,H3<Inputs!$C$6+Inputs!$C$7),(Inputs!$C$9*Inputs!$C$10+Inputs!$C$13*Inputs!$C$14)*(1-Inputs!$C$17/100)*(1-Inputs!$C$18/100)*(1+Inputs!$C$19/100)^(H3-Inputs!$C$6),0) -> 36439473 | I7: =IF(AND(I3>=Inputs!$C$6,I3<Inputs!$C$6+Inputs!$C$7),(Inputs!$C$9*Inputs!$C$10+Inputs!$C$13*Inputs!$C$14)*(1-Inputs!$C$17/100)*(1-Inputs!$C$18/100)*(1+Inputs!$C$19/100)^(I3-Inputs!$C$6),0) -> 0 | ... K7: =IF(AND(K3>=Inputs!$C$6,K3<Inputs!$C$6+Inputs!$C$7),(Inputs!$C$9*Inputs!$C$10+Inputs!$C$13*Inputs!$C$14)*(1-Inputs!$C$17/100)*(1-Inputs!$C$18/100)*(1+Inputs!$C$19/100)^(K3-Inputs!$C$6),0) -> 0
A8: Exit value | B8: =IF(B3=Inputs!$C$6+Inputs!$C$7-1,(Inputs!$C$9*Inputs!$C$10+Inputs!$C$13*Inputs!$C$14)*(1-Inputs!$C$17/100)*(1-Inputs!$C$18/100)*(1+Inputs!$C$19/100)^(B3-Inputs!$C$6+1)/(Inputs!$C$20/100),0) -> 0 | C8: =IF(C3=Inputs!$C$6+Inputs!$C$7-1,(Inputs!$C$9*Inputs!$C$10+Inputs!$C$13*Inputs!$C$14)*(1-Inputs!$C$17/100)*(1-Inputs!$C$18/100)*(1+Inputs!$C$19/100)^(C3-Inputs!$C$6+1)/(Inputs!$C$20/100),0) -> 0 | D8: =IF(D3=Inputs!$C$6+Inputs!$C$7-1,(Inputs!$C$9*Inputs!$C$10+Inputs!$C$13*Inputs!$C$14)*(1-Inputs!$C$17/100)*(1-Inputs!$C$18/100)*(1+Inputs!$C$19/100)^(D3-Inputs!$C$6+1)/(Inputs!$C$20/100),0) -> 0 | E8: =IF(E3=Inputs!$C$6+Inputs!$C$7-1,(Inputs!$C$9*Inputs!$C$10+Inputs!$C$13*Inputs!$C$14)*(1-Inputs!$C$17/100)*(1-Inputs!$C$18/100)*(1+Inputs!$C$19/100)^(E3-Inputs!$C$6+1)/(Inputs!$C$20/100),0) -> 0 | F8: =IF(F3=Inputs!$C$6+Inputs!$C$7-1,(Inputs!$C$9*Inputs!$C$10+Inputs!$C$13*Inputs!$C$14)*(1-Inputs!$C$17/100)*(1-Inputs!$C$18/100)*(1+Inputs!$C$19/100)^(F3-Inputs!$C$6+1)/(Inputs!$C$20/100),0) -> 0 | G8: =IF(G3=Inputs!$C$6+Inputs!$C$7-1,(Inputs!$C$9*Inputs!$C$10+Inputs!$C$13*Inputs!$C$14)*(1-Inputs!$C$17/100)*(1-Inputs!$C$18/100)*(1+Inputs!$C$19/100)^(G3-Inputs!$C$6+1)/(Inputs!$C$20/100),0) -> 0 | H8: =IF(H3=Inputs!$C$6+Inputs!$C$7-1,(Inputs!$C$9*Inputs!$C$10+Inputs!$C$13*Inputs!$C$14)*(1-Inputs!$C$17/100)*(1-Inputs!$C$18/100)*(1+Inputs!$C$19/100)^(H3-Inputs!$C$6+1)/(Inputs!$C$20/100),0) -> 5.0043543e+08 | I8: =IF(I3=Inputs!$C$6+Inputs!$C$7-1,(Inputs!$C$9*Inputs!$C$10+Inputs!$C$13*Inputs!$C$14)*(1-Inputs!$C$17/100)*(1-Inputs!$C$18/100)*(1+Inputs!$C$19/100)^(I3-Inputs!$C$6+1)/(Inputs!$C$20/100),0) -> 0 | ... K8: =IF(K3=Inputs!$C$6+Inputs!$C$7-1,(Inputs!$C$9*Inputs!$C$10+Inputs!$C$13*Inputs!$C$14)*(1-Inputs!$C$17/100)*(1-Inputs!$C$18/100)*(1+Inputs!$C$19/100)^(K3-Inputs!$C$6+1)/(Inputs!$C$20/100),0) -> 0
A9: Unlevered cash flow | B9: =SUM(B5:B8) -> -132900000 | C9: =SUM(C5:C8) -> -72900000 | D9: =SUM(D5:D8) -> 32376000 | E9: =SUM(E5:E8) -> 33347280 | F9: =SUM(F5:F8) -> 34347698 | G9: =SUM(G5:G8) -> 35378129 | H9: =SUM(H5:H8) -> 5.3687491e+08 | I9: =SUM(I5:I8) -> 0 | ... K9: =SUM(K5:K8) -> 0
A10: Debt draw | B10: =IF(B3<Inputs!$C$6,-B6*Inputs!$C$22/100,0) -> 36450000 | C10: =IF(C3<Inputs!$C$6,-C6*Inputs!$C$22/100,0) -> 36450000 | D10: =IF(D3<Inputs!$C$6,-D6*Inputs!$C$22/100,0) -> 0 | E10: =IF(E3<Inputs!$C$6,-E6*Inputs!$C$22/100,0) -> 0 | F10: =IF(F3<Inputs!$C$6,-F6*Inputs!$C$22/100,0) -> 0 | G10: =IF(G3<Inputs!$C$6,-G6*Inputs!$C$22/100,0) -> 0 | H10: =IF(H3<Inputs!$C$6,-H6*Inputs!$C$22/100,0) -> 0 | I10: =IF(I3<Inputs!$C$6,-I6*Inputs!$C$22/100,0) -> 0 | ... K10: =IF(K3<Inputs!$C$6,-K6*Inputs!$C$22/100,0) -> 0
A11: Interest | B11: =-(0)*Inputs!$C$23/100 -> 0 | C11: =-(SUM($B$10:B10)-SUM($B$12:B12))*Inputs!$C$23/100 -> -2369250 | D11: =-(SUM($B$10:C10)-SUM($B$12:C12))*Inputs!$C$23/100 -> -4738500 | E11: =-(SUM($B$10:D10)-SUM($B$12:D12))*Inputs!$C$23/100 -> -4738500 | F11: =-(SUM($B$10:E10)-SUM($B$12:E12))*Inputs!$C$23/100 -> -4738500 | G11: =-(SUM($B$10:F10)-SUM($B$12:F12))*Inputs!$C$23/100 -> -4738500 | H11: =-(SUM($B$10:G10)-SUM($B$12:G12))*Inputs!$C$23/100 -> -4738500 | I11: =-(SUM($B$10:H10)-SUM($B$12:H12))*Inputs!$C$23/100 -> 0 | J11: =-(SUM($B$10:I10)-SUM($B$12:I12))*Inputs!$C$23/100 -> 0 | K11: =-(SUM($B$10:J10)-SUM($B$12:J12))*Inputs!$C$23/100 -> 0
A12: Debt repayment | B12: =IF(B3=Inputs!$C$6+Inputs!$C$7-1,SUM($B$10:B10)-0,0) -> 0 | C12: =IF(C3=Inputs!$C$6+Inputs!$C$7-1,SUM($B$10:C10)-SUM($B$12:B12),0) -> 0 | D12: =IF(D3=Inputs!$C$6+Inputs!$C$7-1,SUM($B$10:D10)-SUM($B$12:C12),0) -> 0 | E12: =IF(E3=Inputs!$C$6+Inputs!$C$7-1,SUM($B$10:E10)-SUM($B$12:D12),0) -> 0 | F12: =IF(F3=Inputs!$C$6+Inputs!$C$7-1,SUM($B$10:F10)-SUM($B$12:E12),0) -> 0 | G12: =IF(G3=Inputs!$C$6+Inputs!$C$7-1,SUM($B$10:G10)-SUM($B$12:F12),0) -> 0 | H12: =IF(H3=Inputs!$C$6+Inputs!$C$7-1,SUM($B$10:H10)-SUM($B$12:G12),0) -> 72900000 | I12: =IF(I3=Inputs!$C$6+Inputs!$C$7-1,SUM($B$10:I10)-SUM($B$12:H12),0) -> 0 | J12: =IF(J3=Inputs!$C$6+Inputs!$C$7-1,SUM($B$10:J10)-SUM($B$12:I12),0) -> 0 | K12: =IF(K3=Inputs!$C$6+Inputs!$C$7-1,SUM($B$10:K10)-SUM($B$12:J12),0) -> 0
A13: Levered cash flow | B13: =B9+B10+B11-B12 -> -96450000 | C13: =C9+C10+C11-C12 -> -38819250 | D13: =D9+D10+D11-D12 -> 27637500 | E13: =E9+E10+E11-E12 -> 28608780 | F13: =F9+F10+F11-F12 -> 29609198 | G13: =G9+G10+G11-G12 -> 30639629 | H13: =H9+H10+H11-H12 -> 4.5923641e+08 | I13: =I9+I10+I11-I12 -> 0 | ... K13: =K9+K10+K11-K12 -> 0

Sheet Results
A1: AL WAHA MIXED-USE
A3: Total development cost | B3: =-SUM(CashFlow!B5:K6) -> 205800000
A4: Net profit | B4: =SUM(CashFlow!B13:K13) -> 4.4046226e+08
A5: Profit on cost | B5: =B4/B3 -> 2.1402442
A6: Project IRR (unlevered) | B6: =XIRR(CashFlow!B9:K9,CashFlow!B4:K4) -> 0.26694786
A7: Equity IRR (levered) | B7: =XIRR(CashFlow!B13:K13,CashFlow!B4:K4) -> 0.33408226
A8: Peak debt | B8: =SUM(CashFlow!B10:K10) -> 72900000
