Workbook

Sheet README
A1: Al Narjis market data (DUMMY)
A2: Synthetic data for the Bohio agent demo. Not real transactions, leases, plots, regulations or emails.
A4: Sheet | B4: Contents
A5: Benchmarks | B5: Comparable-sales and retail-rent percentiles for the chosen scope and period, and where the model sits. Edit the blue cells.
A6: Regulation check | B6: Checks a scheme against the zoning rules of a plot (FAR, coverage, setbacks, height, parking). Edit the blue cells.
A7: Transactions | B7: 160 dummy residential sales, Oct 2024 to Sep 2026. Price/sqm and scope columns are formulas.
A8: Rentals | B8: 110 dummy leases (retail and residential). Rent/sqm and scope columns are formulas.
A9: Zoning rules | B9: Dummy zoning classes with FAR, coverage, setbacks, height and parking ratios.
A10: Plots | B10: Dummy plots and their zoning class. NRJ-0417 is the demo site.
A11: Outlook emails | B11: Dummy emails the agent reads for context on assumption changes, with the change it extracts.
A13: Legend
A14: Blue text | B14: Input you can change
A15: Black text | B15: Formula
A16: Green text | B16: Formula pulling from another sheet
A17: Yellow fill | B17: Key input
A19: Districts / scope rings | B19: 1 = Al Narjis · 2 = adjacent (Al Yasmin, Al Arid, Al Malqa) · 3 = wider north Riyadh (Hittin, Al Sahafa)
A20: As-of date | B20: 2026-09-29
A21: Generator | B21: data/generate_dummy_data.py (seeded, reproducible)

Sheet Benchmarks
A1: Market benchmarks (DUMMY data)
A2: Change the blue inputs; percentiles and the model position recalculate.
B4: Inputs
B5: Comp scope | C5: Al Narjis + adjacent | D5: Al Narjis / Al Narjis + adjacent / North Riyadh
B6: As-of date | C6: 46294
B7: Period (months) | C7: 12
B8: Property type | C8: All | D8: All / Apartment / Townhouse / Duplex
B9: Scope ring (derived) | C9: =MATCH(C5,{"Al Narjis","Al Narjis + adjacent","North Riyadh"},0) -> 2
B11: Model assumptions (from EstateMaster)
B12: Residential sale price (SAR/sqm) | C12: 13500 | D12: Base case in the demo model
B13: Retail rent (SAR/sqm/yr) | C13: 2400
B15: Benchmark | C15: Comps (n) | D15: P10 | E15: P25 | F15: Median | G15: P75 | H15: P90
B16: Residential sale price (SAR/sqm) | C16: =COUNT(Transactions!$M$5:$M$164) -> 57 | D16: =IFERROR(PERCENTILE(Transactions!$M$5:$M$164,0.1),0) -> 11121.583 | E16: =IFERROR(PERCENTILE(Transactions!$M$5:$M$164,0.25),0) -> 11778.261 | F16: =IFERROR(PERCENTILE(Transactions!$M$5:$M$164,0.5),0) -> 12255.474 | G16: =IFERROR(PERCENTILE(Transactions!$M$5:$M$164,0.75),0) -> 12625.85 | H16: =IFERROR(PERCENTILE(Transactions!$M$5:$M$164,0.9),0) -> 13123.835
B17: Retail rent (SAR/sqm/yr) | C17: =COUNT(Rentals!$M$5:$M$114) -> 23 | D17: =IFERROR(PERCENTILE(Rentals!$M$5:$M$114,0.1),0) -> 2071.8248 | E17: =IFERROR(PERCENTILE(Rentals!$M$5:$M$114,0.25),0) -> 2116.4659 | F17: =IFERROR(PERCENTILE(Rentals!$M$5:$M$114,0.5),0) -> 2272.5352 | G17: =IFERROR(PERCENTILE(Rentals!$M$5:$M$114,0.75),0) -> 2404.5846 | H17: =IFERROR(PERCENTILE(Rentals!$M$5:$M$114,0.9),0) -> 2521.87
B19: Model position | C19: Model value | D19: Percentile | E19: Status | F19: Gap to median
B20: =B16 -> Residential sale price (SAR/sqm) | C20: =C12 -> 13500 | D20: =IF(C16>0,COUNTIF(Transactions!$M$5:$M$164,"<"&C20)/C16,0) -> 0.96491228 | E20: =IF(OR(D20>=0.9,D20<=0.1),"Outside range",IF(OR(D20>0.75,D20<0.25),"Stretched","In range")) -> Outside range | F20: =IF(F16>0,C20/F16-1,0) -> 0.10154854
B21: =B17 -> Retail rent (SAR/sqm/yr) | C21: =C13 -> 2400 | D21: =IF(C17>0,COUNTIF(Rentals!$M$5:$M$114,"<"&C21)/C17,0) -> 0.73913043 | E21: =IF(OR(D21>=0.9,D21<=0.1),"Outside range",IF(OR(D21>0.75,D21<0.25),"Stretched","In range")) -> In range | F21: =IF(F17>0,C21/F17-1,0) -> 0.056089247
B23: Status rule: percentile 25–75 in range; 10–25 or 75–90 stretched; outside 10–90 outside range (same rule as the demo).

Sheet Regulation check
A1: Regulation check (DUMMY rules)
A2: Pick a plot and enter the scheme; each rule is checked against the zoning class.
B4: Plot
B5: Plot ID | C5: NRJ-0417
B6: District | C6: =INDEX(Plots!$B$5:$B$12,MATCH($C$5,Plots!$A$5:$A$12,0)) -> Al Narjis
B7: Zone code | C7: =INDEX(Plots!$C$5:$C$12,MATCH($C$5,Plots!$A$5:$A$12,0)) -> C-MU1
B8: Plot area (sqm) | C8: =INDEX(Plots!$D$5:$D$12,MATCH($C$5,Plots!$A$5:$A$12,0)) -> 20000
B9: Frontage x depth (m) | C9: =INDEX(Plots!$E$5:$E$12,MATCH($C$5,Plots!$A$5:$A$12,0))&" x "&INDEX(Plots!$F$5:$F$12,MATCH($C$5,Plots!$A$5:$A$12,0)) -> 200 x 100
B10: Zone description | C10: =INDEX('Zoning rules'!$B$5:$B$9,MATCH($C$7,'Zoning rules'!$A$5:$A$9,0)) -> Mixed-use, commercial corridor
B12: Scheme (from EstateMaster)
B13: GFA (sqm) | C13: 62000
B14: Building footprint (sqm) | C14: 11400
B15: Floors (tallest block) | C15: 11
B16: Front setback provided (m) | C16: 14
B17: Side setback provided (m) | C17: 25
B18: Rear setback provided (m) | C18: 10
B19: Residential NSA (sqm) | C19: 30000
B20: Average unit size (sqm) | C20: 140
B21: Retail GLA (sqm) | C21: 12000
B22: Parking spaces provided | C22: 620
B24: Rule | C24: Limit | D24: Scheme | E24: Status | F24: Headroom
B25: FAR | C25: =INDEX('Zoning rules'!$C$5:$C$9,MATCH($C$7,'Zoning rules'!$A$5:$A$9,0)) -> 3 | D25: =C13/C8 -> 3.1 | E25: =IF(D25<=C25+0.0001,"Compliant","Breach") -> Breach | F25: =C25*C8-C13 -> -2000
B26: Site coverage | C26: =INDEX('Zoning rules'!$D$5:$D$9,MATCH($C$7,'Zoning rules'!$A$5:$A$9,0)) -> 0.6 | D26: =C14/C8 -> 0.57 | E26: =IF(D26<=C26,"Compliant","Breach") -> Compliant | F26: =C26*C8-C14 -> 600
B27: Front setback (m) | C27: =INDEX('Zoning rules'!$E$5:$E$9,MATCH($C$7,'Zoning rules'!$A$5:$A$9,0)) -> 6 | D27: =C16 -> 14 | E27: =IF(D27>=C27,"Compliant","Breach") -> Compliant | F27: =D27-C27 -> 8
B28: Side setback (m) | C28: =INDEX('Zoning rules'!$F$5:$F$9,MATCH($C$7,'Zoning rules'!$A$5:$A$9,0)) -> 3 | D28: =C17 -> 25 | E28: =IF(D28>=C28,"Compliant","Breach") -> Compliant | F28: =D28-C28 -> 22
B29: Rear setback (m) | C29: =INDEX('Zoning rules'!$G$5:$G$9,MATCH($C$7,'Zoning rules'!$A$5:$A$9,0)) -> 3 | D29: =C18 -> 10 | E29: =IF(D29>=C29,"Compliant","Breach") -> Compliant | F29: =D29-C29 -> 7
B30: Max floors | C30: =INDEX('Zoning rules'!$H$5:$H$9,MATCH($C$7,'Zoning rules'!$A$5:$A$9,0)) -> 12 | D30: =C15 -> 11 | E30: =IF(D30<=C30,"Compliant","Breach") -> Compliant | F30: =C30-D30 -> 1
B31: Parking spaces required | C31: =ROUNDUP(C19/C20*INDEX('Zoning rules'!$I$5:$I$9,MATCH($C$7,'Zoning rules'!$A$5:$A$9,0))+IF(INDEX('Zoning rules'!$J$5:$J$9,MATCH($C$7,'Zoning rules'!$A$5:$A$9,0))>0,C21/INDEX('Zoning rules'!$J$5:$J$9,MATCH($C$7,'Zoning rules'!$A$5:$A$9,0)),0),0) -> 562 | D31: =C22 -> 620 | E31: =IF(D31>=C31,"Compliant","Breach") -> Compliant | F31: =D31-C31 -> 58
B33: Negative headroom = breach. Parking: units = NSA / average unit size.

Sheet Transactions
A1: Residential sales (DUMMY)
A2: Synthetic records. Columns H, J, K are formulas.
A4: Record ID | B4: Date | C4: District | D4: Scope ring | E4: Property type | F4: Status | G4: Floor | H4: Unit size (sqm) | I4: Price (SAR) | J4: Price (SAR/sqm) | K4: Months before as-of | L4: In comp set | M4: Comp value (SAR/sqm)
A5: TX-24022 | B5: 46274 | C5: Al Narjis | D5: 1 | E5: Apartment | F5: Ready | G5: 8 | H5: 162 | I5: 1968000 | J5: =IF(H5>0,I5/H5,0) -> 12148.148 | K5: =(Benchmarks!$C$6-B5)/30.44 -> 0.65703022 | L5: =IF(AND(D5<=Benchmarks!$C$9,K5<=Benchmarks!$C$7,OR(Benchmarks!$C$8="All",Benchmarks!$C$8=E5)),1,0) -> 1 | M5: =IF(L5=1,J5,"") -> 12148.148
A6: TX-24145 | B6: 46271 | C6: Al Sahafa | D6: 3 | E6: Apartment | F6: Ready | G6: 4 | H6: 163 | I6: 1984000 | J6: =IF(H6>0,I6/H6,0) -> 12171.779 | K6: =(Benchmarks!$C$6-B6)/30.44 -> 0.75558476 | L6: =IF(AND(D6<=Benchmarks!$C$9,K6<=Benchmarks!$C$7,OR(Benchmarks!$C$8="All",Benchmarks!$C$8=E6)),1,0) -> 0 | M6: =IF(L6=1,J6,"")
A7: TX-24088 | B7: 46269 | C7: Al Arid | D7: 2 | E7: Apartment | F7: Ready | G7: 4 | H7: 122 | I7: 1388000 | J7: =IF(H7>0,I7/H7,0) -> 11377.049 | K7: =(Benchmarks!$C$6-B7)/30.44 -> 0.82128778 | L7: =IF(AND(D7<=Benchmarks!$C$9,K7<=Benchmarks!$C$7,OR(Benchmarks!$C$8="All",Benchmarks!$C$8=E7)),1,0) -> 1 | M7: =IF(L7=1,J7,"") -> 11377.049
A8: TX-24065 | B8: 46265 | C8: Al Sahafa | D8: 3 | E8: Apartment | F8: Ready | G8: 8 | H8: 105 | I8: 1241000 | J8: =IF(H8>0,I8/H8,0) -> 11819.048 | K8: =(Benchmarks!$C$6-B8)/30.44 -> 0.95269382 | L8: =IF(AND(D8<=Benchmarks!$C$9,K8<=Benchmarks!$C$7,OR(Benchmarks!$C$8="All",Benchmarks!$C$8=E8)),1,0) -> 0 | M8: =IF(L8=1,J8,"")
A9: TX-24071 | B9: 46257 | C9: Al Arid | D9: 2 | E9: Townhouse | F9: Ready | G9: 0 | H9: 236 | I9: 2845000 | J9: =IF(H9>0,I9/H9,0) -> 12055.085 | K9: =(Benchmarks!$C$6-B9)/30.44 -> 1.2155059 | L9: =IF(AND(D9<=Benchmarks!$C$9,K9<=Benchmarks!$C$7,OR(Benchmarks!$C$8="All",Benchmarks!$C$8=E9)),1,0) -> 1 | M9: =IF(L9=1,J9,"") -> 12055.085
A10: TX-24124 | B10: 46245 | C10: Al Arid | D10: 2 | E10: Apartment | F10: Ready | G10: 6 | H10: 106 | I10: 1258000 | J10: =IF(H10>0,I10/H10,0) -> 11867.925 | K10: =(Benchmarks!$C$6-B10)/30.44 -> 1.609724 | L10: =IF(AND(D10<=Benchmarks!$C$9,K10<=Benchmarks!$C$7,OR(Benchmarks!$C$8="All",Benchmarks!$C$8=E10)),1,0) -> 1 | M10: =IF(L10=1,J10,"") -> 11867.925
A11: TX-24032 | B11: 46231 | C11: Al Narjis | D11: 1 | E11: Townhouse | F11: Ready | G11: 0 | H11: 217 | I11: 2714000 | J11: =IF(H11>0,I11/H11,0) -> 12506.912 | K11: =(Benchmarks!$C$6-B11)/30.44 -> 2.0696452 | L11: =IF(AND(D11<=Benchmarks!$C$9,K11<=Benchmarks!$C$7,OR(Benchmarks!$C$8="All",Benchmarks!$C$8=E11)),1,0) -> 1 | M11: =IF(L11=1,J11,"") -> 12506.912
A12: TX-24118 | B12: 46231 | C12: Hittin | D12: 3 | E12: Apartment | F12: Ready | G12: 7 | H12: 99 | I12: 1326000 | J12: =IF(H12>0,I12/H12,0) -> 13393.939 | K12: =(Benchmarks!$C$6-B12)/30.44 -> 2.0696452 | L12: =IF(AND(D12<=Benchmarks!$C$9,K12<=Benchmarks!$C$7,OR(Benchmarks!$C$8="All",Benchmarks!$C$8=E12)),1,0) -> 0 | M12: =IF(L12=1,J12,"")
A13: TX-24135 | B13: 46230 | C13: Al Yasmin | D13: 2 | E13: Apartment | F13: Off-plan | G13: 7 | H13: 149 | I13: 1795000 | J13: =IF(H13>0,I13/H13,0) -> 12046.98 | K13: =(Benchmarks!$C$6-B13)/30.44 -> 2.1024967 | L13: =IF(AND(D13<=Benchmarks!$C$9,K13<=Benchmarks!$C$7,OR(Benchmarks!$C$8="All",Benchmarks!$C$8=E13)),1,0) -> 1 | M13: =IF(L13=1,J13,"") -> 12046.98
A14: TX-24011 | B14: 46228 | C14: Al Arid | D14: 2 | E14: Townhouse | F14: Off-plan | G14: 0 | H14: 257 | I14: 3022000 | J14: =IF(H14>0,I14/H14,0) -> 11758.755 | K14: =(Benchmarks!$C$6-B14)/30.44 -> 2.1681997 | L14: =IF(AND(D14<=Benchmarks!$C$9,K14<=Benchmarks!$C$7,OR(Benchmarks!$C$8="All",Benchmarks!$C$8=E14)),1,0) -> 1 | M14: =IF(L14=1,J14,"") -> 11758.755
A15: TX-24132 | B15: 46221 | C15: Hittin | D15: 3 | E15: Apartment | F15: Ready | G15: 2 | H15: 146 | I15: 2094000 | J15: =IF(H15>0,I15/H15,0) -> 14342.466 | K15: =(Benchmarks!$C$6-B15)/30.44 -> 2.3981603 | L15: =IF(AND(D15<=Benchmarks!$C$9,K15<=Benchmarks!$C$7,OR(Benchmarks!$C$8="All",Benchmarks!$C$8=E15)),1,0) -> 0 | M15: =IF(L15=1,J15,"")
A16: TX-24005 | B16: 46220 | C16: Al Narjis | D16: 1 | E16: Apartment | F16: Ready | G16: 5 | H16: 186 | I16: 2165000 | J16: =IF(H16>0,I16/H16,0) -> 11639.785 | K16: =(Benchmarks!$C$6-B16)/30.44 -> 2.4310118 | L16: =IF(AND(D16<=Benchmarks!$C$9,K16<=Benchmarks!$C$7,OR(Benchmarks!$C$8="All",Benchmarks!$C$8=E16)),1,0) -> 1 | M16: =IF(L16=1,J16,"") -> 11639.785
... A164: TX-24148 | B164: 45567 | C164: Al Malqa | D164: 2 | E164: Apartment | F164: Off-plan | G164: 5 | H164: 132 | I164: 1642000 | J164: =IF(H164>0,I164/H164,0) -> 12439.394 | K164: =(Benchmarks!$C$6-B164)/30.44 -> 23.883049 | L164: =IF(AND(D164<=Benchmarks!$C$9,K164<=Benchmarks!$C$7,OR(Benchmarks!$C$8="All",Benchmarks!$C$8=E164)),1,0) -> 0 | M164: =IF(L164=1,J164,"")

Sheet Rentals
A1: Leases (DUMMY)
A2: Synthetic records. Columns I, J, K, L are formulas. Only retail leases enter the rent benchmark.
A4: Record ID | B4: Start date | C4: District | D4: Scope ring | E4: Use | F4: Frontage | G4: Term (years) | H4: Unit size (sqm) | I4: Annual rent (SAR) | J4: Rent (SAR/sqm/yr) | K4: Months before as-of | L4: In comp set | M4: Comp value (SAR/sqm/yr)
A5: LS-51014 | B5: 46282 | C5: Al Narjis | D5: 1 | E5: Retail | F5: Internal | G5: 10 | H5: 320 | I5: 744900 | J5: =IF(H5>0,I5/H5,0) -> 2327.8125 | K5: =(Benchmarks!$C$6-B5)/30.44 -> 0.39421813 | L5: =IF(AND(E5="Retail",D5<=Benchmarks!$C$9,K5<=Benchmarks!$C$7),1,0) -> 1 | M5: =IF(L5=1,J5,"") -> 2327.8125
A6: LS-51025 | B6: 46276 | C6: Al Narjis | D6: 1 | E6: Residential | F6: - | G6: 1 | H6: 127 | I6: 77000 | J6: =IF(H6>0,I6/H6,0) -> 606.29921 | K6: =(Benchmarks!$C$6-B6)/30.44 -> 0.5913272 | L6: =IF(AND(E6="Retail",D6<=Benchmarks!$C$9,K6<=Benchmarks!$C$7),1,0) -> 0 | M6: =IF(L6=1,J6,"")
A7: LS-51044 | B7: 46250 | C7: Al Sahafa | D7: 3 | E7: Retail | F7: Main road | G7: 5 | H7: 242 | I7: 446600 | J7: =IF(H7>0,I7/H7,0) -> 1845.4545 | K7: =(Benchmarks!$C$6-B7)/30.44 -> 1.4454665 | L7: =IF(AND(E7="Retail",D7<=Benchmarks!$C$9,K7<=Benchmarks!$C$7),1,0) -> 0 | M7: =IF(L7=1,J7,"")
A8: LS-51019 | B8: 46243 | C8: Al Arid | D8: 2 | E8: Retail | F8: Main road | G8: 3 | H8: 198 | I8: 414900 | J8: =IF(H8>0,I8/H8,0) -> 2095.4545 | K8: =(Benchmarks!$C$6-B8)/30.44 -> 1.6754271 | L8: =IF(AND(E8="Retail",D8<=Benchmarks!$C$9,K8<=Benchmarks!$C$7),1,0) -> 1 | M8: =IF(L8=1,J8,"") -> 2095.4545
A9: LS-51041 | B9: 46241 | C9: Al Sahafa | D9: 3 | E9: Retail | F9: Main road | G9: 1 | H9: 157 | I9: 324900 | J9: =IF(H9>0,I9/H9,0) -> 2069.4268 | K9: =(Benchmarks!$C$6-B9)/30.44 -> 1.7411301 | L9: =IF(AND(E9="Retail",D9<=Benchmarks!$C$9,K9<=Benchmarks!$C$7),1,0) -> 0 | M9: =IF(L9=1,J9,"")
A10: LS-51051 | B10: 46240 | C10: Al Yasmin | D10: 2 | E10: Retail | F10: Internal | G10: 5 | H10: 214 | I10: 491400 | J10: =IF(H10>0,I10/H10,0) -> 2296.2617 | K10: =(Benchmarks!$C$6-B10)/30.44 -> 1.7739816 | L10: =IF(AND(E10="Retail",D10<=Benchmarks!$C$9,K10<=Benchmarks!$C$7),1,0) -> 1 | M10: =IF(L10=1,J10,"") -> 2296.2617
A11: LS-51086 | B11: 46222 | C11: Al Narjis | D11: 1 | E11: Residential | F11: - | G11: 1 | H11: 154 | I11: 91500 | J11: =IF(H11>0,I11/H11,0) -> 594.15584 | K11: =(Benchmarks!$C$6-B11)/30.44 -> 2.3653088 | L11: =IF(AND(E11="Retail",D11<=Benchmarks!$C$9,K11<=Benchmarks!$C$7),1,0) -> 0 | M11: =IF(L11=1,J11,"")
A12: LS-51024 | B12: 46219 | C12: Al Sahafa | D12: 3 | E12: Retail | F12: Main road | G12: 5 | H12: 306 | I12: 621100 | J12: =IF(H12>0,I12/H12,0) -> 2029.7386 | K12: =(Benchmarks!$C$6-B12)/30.44 -> 2.4638633 | L12: =IF(AND(E12="Retail",D12<=Benchmarks!$C$9,K12<=Benchmarks!$C$7),1,0) -> 0 | M12: =IF(L12=1,J12,"")
A13: LS-51049 | B13: 46217 | C13: Al Malqa | D13: 2 | E13: Retail | F13: Internal | G13: 5 | H13: 91 | I13: 228300 | J13: =IF(H13>0,I13/H13,0) -> 2508.7912 | K13: =(Benchmarks!$C$6-B13)/30.44 -> 2.5295664 | L13: =IF(AND(E13="Retail",D13<=Benchmarks!$C$9,K13<=Benchmarks!$C$7),1,0) -> 1 | M13: =IF(L13=1,J13,"") -> 2508.7912
A14: LS-51007 | B14: 46215 | C14: Al Narjis | D14: 1 | E14: Residential | F14: - | G14: 1 | H14: 170 | I14: 100600 | J14: =IF(H14>0,I14/H14,0) -> 591.76471 | K14: =(Benchmarks!$C$6-B14)/30.44 -> 2.5952694 | L14: =IF(AND(E14="Retail",D14<=Benchmarks!$C$9,K14<=Benchmarks!$C$7),1,0) -> 0 | M14: =IF(L14=1,J14,"")
A15: LS-51080 | B15: 46213 | C15: Al Yasmin | D15: 2 | E15: Retail | F15: Internal | G15: 5 | H15: 160 | I15: 330900 | J15: =IF(H15>0,I15/H15,0) -> 2068.125 | K15: =(Benchmarks!$C$6-B15)/30.44 -> 2.6609724 | L15: =IF(AND(E15="Retail",D15<=Benchmarks!$C$9,K15<=Benchmarks!$C$7),1,0) -> 1 | M15: =IF(L15=1,J15,"") -> 2068.125
A16: LS-51094 | B16: 46209 | C16: Al Yasmin | D16: 2 | E16: Retail | F16: Main road | G16: 3 | H16: 268 | I16: 606500 | J16: =IF(H16>0,I16/H16,0) -> 2263.0597 | K16: =(Benchmarks!$C$6-B16)/30.44 -> 2.7923784 | L16: =IF(AND(E16="Retail",D16<=Benchmarks!$C$9,K16<=Benchmarks!$C$7),1,0) -> 1 | M16: =IF(L16=1,J16,"") -> 2263.0597
... A114: LS-51047 | B114: 45572 | C114: Al Narjis | D114: 1 | E114: Retail | F114: Internal | G114: 5 | H114: 258 | I114: 535700 | J114: =IF(H114>0,I114/H114,0) -> 2076.3566 | K114: =(Benchmarks!$C$6-B114)/30.44 -> 23.718791 | L114: =IF(AND(E114="Retail",D114<=Benchmarks!$C$9,K114<=Benchmarks!$C$7),1,0) -> 0 | M114: =IF(L114=1,J114,"")

Sheet Zoning rules
A1: Zoning rules (DUMMY)
A2: Synthetic rules for the demo, not actual Riyadh regulations.
A4: Zone code | B4: Description | C4: Max FAR | D4: Max site coverage | E4: Front setback (m) | F4: Side setback (m) | G4: Rear setback (m) | H4: Max floors | I4: Parking per residential unit | J4: Retail sqm per parking space | K4: Permitted uses
A5: C-MU1 | B5: Mixed-use, commercial corridor | C5: 3 | D5: 0.6 | E5: 6 | F5: 3 | G5: 3 | H5: 12 | I5: 1.5 | J5: 50 | K5: Residential, retail, office
A6: C-MU2 | B6: Mixed-use, high density | C6: 4.5 | D6: 0.55 | E6: 8 | F6: 4 | G6: 4 | H6: 20 | I6: 1.5 | J6: 45 | K6: Residential, retail, office, hotel
A7: C-2 | B7: Commercial | C7: 2.4 | D7: 0.65 | E7: 6 | F7: 2 | G7: 3 | H7: 8 | I7: 1 | J7: 40 | K7: Retail, office
A8: R-3 | B8: Residential, medium density | C8: 1.8 | D8: 0.6 | E8: 5 | F8: 2 | G8: 2 | H8: 4 | I8: 1.5 | J8: 0 | K8: Residential
A9: R-2 | B9: Residential, villas | C9: 1.2 | D9: 0.6 | E9: 4 | F9: 2 | G9: 2 | H9: 3 | I9: 2 | J9: 0 | K9: Residential

Sheet Plots
A1: Plots (DUMMY)
A2: Synthetic plot register. NRJ-0417 is the demo site.
A4: Plot ID | B4: District | C4: Zone code | D4: Plot area (sqm) | E4: Frontage (m) | F4: Depth (m) | G4: Street width (m) | H4: Max GFA (sqm) | I4: Note
A5: NRJ-0417 | B5: Al Narjis | C5: C-MU1 | D5: 20000 | E5: 200 | F5: 100 | G5: 40 | H5: =D5*INDEX('Zoning rules'!$C$5:$C$9,MATCH(C5,'Zoning rules'!$A$5:$A$9,0)) -> 60000 | I5: Subject site (Al Narjis Mixed-Use)
A6: NRJ-0422 | B6: Al Narjis | C6: C-MU1 | D6: 12500 | E6: 125 | F6: 100 | G6: 40 | H6: =D6*INDEX('Zoning rules'!$C$5:$C$9,MATCH(C6,'Zoning rules'!$A$5:$A$9,0)) -> 37500
A7: NRJ-0510 | B7: Al Narjis | C7: R-3 | D7: 3600 | E7: 60 | F7: 60 | G7: 20 | H7: =D7*INDEX('Zoning rules'!$C$5:$C$9,MATCH(C7,'Zoning rules'!$A$5:$A$9,0)) -> 6480
A8: NRJ-0588 | B8: Al Narjis | C8: R-2 | D8: 900 | E8: 30 | F8: 30 | G8: 15 | H8: =D8*INDEX('Zoning rules'!$C$5:$C$9,MATCH(C8,'Zoning rules'!$A$5:$A$9,0)) -> 1080
A9: YSM-0231 | B9: Al Yasmin | C9: C-2 | D9: 8000 | E9: 100 | F9: 80 | G9: 30 | H9: =D9*INDEX('Zoning rules'!$C$5:$C$9,MATCH(C9,'Zoning rules'!$A$5:$A$9,0)) -> 19200
A10: MLQ-0109 | B10: Al Malqa | C10: C-MU2 | D10: 24000 | E10: 200 | F10: 120 | G10: 60 | H10: =D10*INDEX('Zoning rules'!$C$5:$C$9,MATCH(C10,'Zoning rules'!$A$5:$A$9,0)) -> 108000
A11: ARD-0340 | B11: Al Arid | C11: R-3 | D11: 4800 | E11: 80 | F11: 60 | G11: 20 | H11: =D11*INDEX('Zoning rules'!$C$5:$C$9,MATCH(C11,'Zoning rules'!$A$5:$A$9,0)) -> 8640
A12: HTN-0077 | B12: Hittin | C12: C-MU2 | D12: 16000 | E12: 160 | F12: 100 | G12: 40 | H12: =D12*INDEX('Zoning rules'!$C$5:$C$9,MATCH(C12,'Zoning rules'!$A$5:$A$9,0)) -> 72000

Sheet Outlook emails
A1: Outlook inbox sample (DUMMY)
A2: Synthetic emails. The agent extracts the proposed assumption change and cites the quote.
A4: Received | B4: From | C4: Address | D4: Subject | E4: Body | F4: Assumption | G4: Proposed change | H4: Quote used | I4: Confidence
A5: 2026-09-27 08:14 | B5: Omar H. · Project Manager | C5: omar.h@kinan.example | D5: Programme update: approvals slipping | E5: Municipality comments on the building permit came back on Thursday. Resubmission plus review adds roughly 3 months. Construction start moves from Jan to Apr 2027. Handover follows. | F5: Delay (months) | G5: 3 | H5: adds roughly 3 months | I5: 0.9
A6: 2026-09-25 16:02 | B6: Layla S. · Debt Advisory, Gulf Bank (dummy) | C6: l.s@bank.example | D6: Indicative term sheet: Al Narjis construction facility | E6: Please find the indicative terms: 50% loan-to-cost, pricing SAIBOR + 250 bps, which today is c. 9.0% all-in. Subject to credit approval. | F6: Interest rate (pp) | G6: 0.5 | H6: c. 9.0% all-in | I6: 0.85
A7: 2026-09-25 16:02 | B7: Layla S. · Debt Advisory, Gulf Bank (dummy) | C7: l.s@bank.example | D7: Indicative term sheet: Al Narjis construction facility | E7: (same email) | F7: Leverage LTC (pp) | G7: -5 | H7: 50% loan-to-cost | I7: 0.85
A8: 2026-09-22 11:40 | B8: Sara K. · Cost Consultant (QS) | C8: sara.k@qs.example | D8: Tender returns: podium and tower | E8: Three tenders received. The lowest compliant bid is 8% above the cost plan, driven by steel and MEP. We recommend carrying SAR 5,620/sqm GFA in the feasibility. | F8: Construction cost (%) | G8: 8 | H8: carrying SAR 5,620/sqm | I8: 0.95
A9: 2026-09-18 09:05 | B9: Faisal A. · Sales Director | C9: faisal.a@kinan.example | D9: Off-plan launch pricing | E9: Two competing launches in Al Narjis opened at 12,600 to 12,900 SAR/sqm. I suggest we launch at 12,800 and hold the premium for the top floors. | F9: Sale price (%) | G9: -5.2 | H9: launch at 12,800 | I9: 0.8
A10: 2026-09-15 14:30 | B10: Dana M. · Planning Consultant | C10: dana.m@planning.example | D10: Pre-application feedback, plot NRJ-0417 | E10: The authority confirmed FAR 3.0 with no bonus for the public plaza. The scheme must come down to 60,000 sqm GFA. Setbacks and height are fine. | F10: Buildable area (%) | G10: -3.3 | H10: come down to 60,000 sqm GFA | I10: 0.9
A11: 2026-09-10 17:20 | B11: Khalid R. · Leasing Agent | C11: khalid.r@leasing.example | D11: Anchor LOI for the podium | E11: Supermarket anchor has signed an LOI for 2,400 sqm at SAR 2,300/sqm/yr, 10-year term. Line shops should follow at similar levels. | F11: Retail rent (%) | G11: -4.2 | H11: SAR 2,300/sqm/yr | I11: 0.75
A12: 2026-09-09 10:00 | B12: HR · KINAN | C12: hr@kinan.example | D12: Team offsite logistics | E12: Buses leave at 7:30 from the head office. Please confirm dietary requirements by Sunday. | F12: - | G12: - | H12: No assumption content: ignored | I12: -
