Workbook

Sheet Assumptions
A1: AL BIDDA WATERFRONT — SCENARIO MODEL
A2: Project being contributed into Bohio RE Opportunity Fund III
A4: DRIVER | B4: Unit | C4: Bear | D4: Base | E4: Bull | F4: Stress | G4: Stretch | H4: Note
A5: Construction cost | B5: SAR/sqm | C5: 6100 | D5: 5800 | E5: 5600 | F5: 6500 | G5: 5450 | H5: QS estimate +/- tender outcome
A6: Programme | B6: months | C6: 34 | D6: 30 | E6: 28 | F6: 39 | G6: 26 | H6: Critical path; each month carries finance cost
A7: Residential price | B7: SAR/sqft | C7: 1360 | D7: 1450 | E7: 1520 | F7: 1270 | G7: 1570 | H7: Corniche comparables
A8: Sales absorption | B8: units/month | C8: 14 | D8: 22 | E8: 27 | F8: 11 | G8: 29 | H8: Drives sell-out and working capital
A9: Retail rent | B9: SAR/sqm/yr | C9: 1600 | D9: 1800 | E9: 1900 | F9: 1480 | G9: 1960 | H9: Ground-floor podium
A10: Stabilised occupancy | B10: % | C10: 90 | D10: 94 | E10: 97 | F10: 85 | G10: 98 | H10: Retail + serviced component
A11: Exit cap rate | B11: % | C11: 6.4 | D11: 6 | E11: 5.75 | F11: 6.9 | G11: 5.5 | H11: On stabilised NOI
A12: SAIBOR + margin | B12: % | C12: 7.4 | D12: 6.6 | E12: 6.1 | F12: 8 | G12: 5.9 | H12: All-in cost of debt
A13: Loan-to-cost | B13: % | C13: 50 | D13: 55 | E13: 60 | F13: 45 | G13: 60 | H13: Senior facility
A15: FIXED INPUTS
A16: Site area | B16: sqm | C16: 18500
A17: GFA | B17: sqm | C17: 96000
A18: Net sellable / leasable | B18: sqm | C18: 72000
A19: Residential share of NSA | B19: % | C19: 78
A20: Retail share of NSA | B20: % | C20: 22
A21: Land cost | B21: SAR M | C21: 210
A22: Soft costs | B22: % of hard cost | C22: 14
A23: Contingency | B23: % of hard cost | C23: 7
A24: Selling costs | B24: % of revenue | C24: 3.5
A25: Opex | B25: % of retail revenue | C25: 28

Sheet Scenarios
A1: SCENARIO ENGINE — OUTPUTS BY CASE
A2: All cases read their drivers from Assumptions. SAR M unless stated.
A4: Line | B4: Bear | C4: Base | D4: Bull | E4: Stress | F4: Stretch
A5: Construction cost (SAR/sqm) | B5: =Assumptions!C5 | C5: =Assumptions!D5 | D5: =Assumptions!E5 | E5: =Assumptions!F5 | F5: =Assumptions!G5
A6: Programme (months) | B6: =Assumptions!C6 | C6: =Assumptions!D6 | D6: =Assumptions!E6 | E6: =Assumptions!F6 | F6: =Assumptions!G6
A7: Resi price (SAR/sqft) | B7: =Assumptions!C7 | C7: =Assumptions!D7 | D7: =Assumptions!E7 | E7: =Assumptions!F7 | F7: =Assumptions!G7
A8: Absorption (units/mo) | B8: =Assumptions!C8 | C8: =Assumptions!D8 | D8: =Assumptions!E8 | E8: =Assumptions!F8 | F8: =Assumptions!G8
A9: Retail rent (SAR/sqm/yr) | B9: =Assumptions!C9 | C9: =Assumptions!D9 | D9: =Assumptions!E9 | E9: =Assumptions!F9 | F9: =Assumptions!G9
A10: Occupancy (%) | B10: =Assumptions!C10 | C10: =Assumptions!D10 | D10: =Assumptions!E10 | E10: =Assumptions!F10 | F10: =Assumptions!G10
A11: Exit cap (%) | B11: =Assumptions!C11 | C11: =Assumptions!D11 | D11: =Assumptions!E11 | E11: =Assumptions!F11 | F11: =Assumptions!G11
A12: Cost of debt (%) | B12: =Assumptions!C12 | C12: =Assumptions!D12 | D12: =Assumptions!E12 | E12: =Assumptions!F12 | F12: =Assumptions!G12
A13: LTC (%) | B13: =Assumptions!C13 | C13: =Assumptions!D13 | D13: =Assumptions!E13 | E13: =Assumptions!F13 | F13: =Assumptions!G13
A15: COST
A16: Hard cost | B16: =Assumptions!C17*B5/1000000 | C16: =Assumptions!C17*C5/1000000 | D16: =Assumptions!C17*D5/1000000 | E16: =Assumptions!C17*E5/1000000 | F16: =Assumptions!C17*F5/1000000
A17: Soft costs | B17: =B16*Assumptions!C22/100 | C17: =C16*Assumptions!C22/100 | D17: =D16*Assumptions!C22/100 | E17: =E16*Assumptions!C22/100 | F17: =F16*Assumptions!C22/100
A18: Contingency | B18: =B16*Assumptions!C23/100 | C18: =C16*Assumptions!C23/100 | D18: =D16*Assumptions!C23/100 | E18: =E16*Assumptions!C23/100 | F18: =F16*Assumptions!C23/100
A19: Land | B19: =Assumptions!C21 | C19: =Assumptions!C21 | D19: =Assumptions!C21 | E19: =Assumptions!C21 | F19: =Assumptions!C21
A20: Total development cost | B20: =SUM(B16:B19) | C20: =SUM(C16:C19) | D20: =SUM(D16:D19) | E20: =SUM(E16:E19) | F20: =SUM(F16:F19)
A22: REVENUE
A23: Residential sales | B23: =Assumptions!C18*Assumptions!C19/100*10.7639*B7/1000000 | C23: =Assumptions!C18*Assumptions!C19/100*10.7639*C7/1000000 | D23: =Assumptions!C18*Assumptions!C19/100*10.7639*D7/1000000 | E23: =Assumptions!C18*Assumptions!C19/100*10.7639*E7/1000000 | F23: =Assumptions!C18*Assumptions!C19/100*10.7639*F7/1000000
A24: Retail NOI (stabilised) | B24: =Assumptions!C18*Assumptions!C20/100*B9*B10/100*(1-Assumptions!C25/100)/1000000 | C24: =Assumptions!C18*Assumptions!C20/100*C9*C10/100*(1-Assumptions!C25/100)/1000000 | D24: =Assumptions!C18*Assumptions!C20/100*D9*D10/100*(1-Assumptions!C25/100)/1000000 | E24: =Assumptions!C18*Assumptions!C20/100*E9*E10/100*(1-Assumptions!C25/100)/1000000 | F24: =Assumptions!C18*Assumptions!C20/100*F9*F10/100*(1-Assumptions!C25/100)/1000000
A25: Retail exit value | B25: =B24/(B11/100) | C25: =C24/(C11/100) | D25: =D24/(D11/100) | E25: =E24/(E11/100) | F25: =F24/(F11/100)
A26: Selling costs | B26: =-B23*Assumptions!C24/100 | C26: =-C23*Assumptions!C24/100 | D26: =-D23*Assumptions!C24/100 | E26: =-E23*Assumptions!C24/100 | F26: =-F23*Assumptions!C24/100
A27: Total revenue | B27: =B23+B25+B26 | C27: =C23+C25+C26 | D27: =D23+D25+D26 | E27: =E23+E25+E26 | F27: =F23+F25+F26
A29: FINANCE
A30: Debt drawn | B30: =B20*B13/100 | C30: =C20*C13/100 | D30: =D20*D13/100 | E30: =E20*E13/100 | F30: =F20*F13/100
A31: Equity | B31: =B20-B30 | C31: =C20-C30 | D31: =D20-D30 | E31: =E20-E30 | F31: =F20-F30
A32: Finance cost | B32: =B30*B12/100*B6/12*0.6 | C32: =C30*C12/100*C6/12*0.6 | D32: =D30*D12/100*D6/12*0.6 | E32: =E30*E12/100*E6/12*0.6 | F32: =F30*F12/100*F6/12*0.6
A34: RETURNS
A35: Profit | B35: =B27-B20-B32 | C35: =C27-C20-C32 | D35: =D27-D20-D32 | E35: =E27-E20-E32 | F35: =F27-F20-F32
A36: ROI on cost (%) | B36: =B35/B20*100 | C36: =C35/C20*100 | D36: =D35/D20*100 | E36: =E35/E20*100 | F36: =F35/F20*100
A37: Equity multiple (x) | B37: =(B31+B35)/B31 | C37: =(C31+C35)/C31 | D37: =(D31+D35)/D31 | E37: =(E31+E35)/E31 | F37: =(F31+F35)/F31
A38: Yield on cost (%) | B38: =B24/(B20*Assumptions!C20/100)*100 | C38: =C24/(C20*Assumptions!C20/100)*100 | D38: =D24/(D20*Assumptions!C20/100)*100 | E38: =E24/(E20*Assumptions!C20/100)*100 | F38: =F24/(F20*Assumptions!C20/100)*100
A39: Project IRR (%) | B39: =((B31+B35)/B31)^(12/B6)*100-100 | C39: =((C31+C35)/C31)^(12/C6)*100-100 | D39: =((D31+D35)/D31)^(12/D6)*100-100 | E39: =((E31+E35)/E31)^(12/E6)*100-100 | F39: =((F31+F35)/F31)^(12/F6)*100-100
A40: Profit on revenue (%) | B40: =B35/B27*100 | C40: =C35/C27*100 | D40: =D35/D27*100 | E40: =E35/E27*100 | F40: =F35/F27*100

Sheet What must be true
A1: WHAT HAS TO BE TRUE FOR EACH CASE
A3: Case | B3: Has to be true | C3: Evidence to watch | D3: Owner
A4: Bear | B4: Tender clears at SAR 6,100/sqm (5% over QS) and absorption slows to 14/mo | C4: Tender returns; monthly reservations | D4: Development / Commercial
A5: Bear | B5: Exit cap widens to 6.40% on a softer rate outlook | C5: SAIBOR forward curve; comparable trades | D5: Investments
A6: Bear | B6: Resi pricing gives back to SAR 1,360/sqft | C6: Corniche comparables | D6: Commercial
A7: Base | B7: Tender lands at the QS estimate of SAR 5,800/sqm | C7: Tender returns vs QS | D7: Development
A8: Base | B8: Resi pricing holds at SAR 1,450/sqft with 22 units/mo | C8: Corniche comparables; reservation run-rate | D8: Commercial
A9: Base | B9: 30-month programme is held with no critical-path slip | C9: Monthly programme report; float | D9: Development
A10: Bull | B10: Value engineering takes cost to SAR 5,600/sqm | C10: VE register; contractor buy-in | D10: Development
A11: Bull | B11: Waterfront premium supports SAR 1,520/sqft at 27 units/mo | C11: Achieved prices on Tower B launch | D11: Commercial
A12: Bull | B12: Exit cap compresses to 5.75% on a REIT block bid for the podium | C12: REIT appetite; 2026 trades | D12: Investments
A13: Stress | B13: Bear cost +6.5% AND programme +5 months AND cap +50bps together | C13: All three simultaneously | D13: Investment Committee
A14: Stress | B14: Absorption falls to 11/mo and the lender cuts LTC to 45% | C14: Reservation run-rate; credit committee terms | D14: Investments / Finance
... A16: Stretch | B16: Cap compresses to 5.50% with the podium 98% let | C16: Letting schedule; REIT bid | D16: Investments
A18: READ-ACROSS
A19: Resi pricing is the largest single swing: every SAR 50/sqft on the 605k saleable sqft moves profit by ~SAR 29M net of selling costs.
A20: Construction cost is next: every SAR 100/sqm moves profit by ~SAR 11.6M once soft costs and contingency scale with it.
A21: Exit cap only bites the podium: 25bps of compression is worth ~SAR 14M of exit value.
A22: Programme drives finance cost only; a 3-month slip is not fatal alone but compounds with cost and cap in the stress case.
A23: Yield on cost is measured on the retail podium only (NOI over its pro-rata share of TDC); the residential is for sale, not held.
